Workbook
Name FCP: 'Bond Calculator'!$B$7

Sheet Bond Calculator
A1: Hedrick Brothers Construction
A3: Performance / Payment Bond | E3: Performance / Payment Bond
A4: General Construction | E4: Design Build
A5: 42888 | E5: 42053
B6: =IF(B13>500000,500000,B13) -> 500000 | C6: 0.0091 | D6: =B6*C6 -> 4550 | F6: 0 | G6: 0.01875 | H6: =SUM(F6*G6) -> 0
B7: =IF(B13<2500000,(B13-B6),IF(B13>B6,2000000,0)) -> 1720594.1 | C7: 0.00725 | D7: =B7*C7 -> 12474.307 | F7: 0 | G7: 0.015 | H7: =SUM(F7*G7) -> 0
B8: =IF(B13<5000000,MAX(0,B13-2500000),IF(B13>2500000,2500000)) -> 0 | C8: 0.0063 | D8: =B8*C8 -> 0 | F8: 0 | G8: 0.01125 | H8: =SUM(F8*G8) -> 0
B9: =IF(B13<7500000,MAX(0,B13-5000000),IF(B13>7500000,2500000,0)) -> 0 | C9: 0.00555 | D9: =B9*C9 -> 0 | F9: 0 | G9: 0.009 | H9: =SUM(F9*G9) -> 0
B10: =IF(B13<7500000,MAX(0,B13-7500000),IF(B13>7500000,(B13-7500000))) -> 0 | C10: 0.0051 | D10: =B10*C10 -> 0 | F10: 0 | G10: 0.00825 | H10: =SUM(F10*G10) -> 0
D11: =B11*C11 -> 0 | F11: 0 | G11: 0.0075 | H11: =SUM(F11*G11) -> 0
A12: Contract Value | B12: ='Cost Summary'!D76 -> 33148733 | C12: Total | D12: =SUM(D6:D11) -> 17024.307 | E12: Contract Value | F12: =SUM(F6+F7+F8+F9+F10+F11) -> 0 | G12: Total | H12: =SUM(H6:H11) -> 0
A13: Cost Summary | B13: 2220594.1 | D13: =SUM(D12/B12) -> 0.00051357338 | H13: =SUM(H12/F12) -> #DIV/0!
B14: =B12-B13 -> 30928139

Sheet Allowances
A7: ='Area Calculations'!B4 -> The Club at Ibis Conceptual Estimate | C7: ='Area Calculations'!B5 -> West Palm Beach, FL
A9: Allowances
A10: =TODAY() -> 46146
A12: NO. | B12: DESCRIPTION | C12: VALUE
A13: 1 | C13: 0
A14: =A13+1 -> 2 | C14: 0
A15: =A14+1 -> 3 | C15: 0
A16: =A15+1 -> 4 | C16: 0
A17: =A16+1 -> 5 | C17: 0
A18: =A17+1 -> 6 | C18: 0
A19: =A18+1 -> 7 | C19: 0
A20: =A19+1 -> 8 | C20: 0
A21: =A20+1 -> 9 | C21: 0
A22: =A21+1 -> 10 | C22: 0
A23: =A22+1 -> 11 | C23: 0
A24: =A23+1 -> 12 | C24: 0
A25: =A24+1 -> 13 | C25: 0
... A28: =A27+1 -> 16 | C28: 0
A29: =A28+1 -> 17
A30: =A29+1 -> 18
A31: =A30+1 -> 19 | B31: Total | C31: =SUM(C13:C30) -> 0
B33: *All ALLOWANCES IN BID TABS MUST BE LISTED HERE

Sheet Alternates
A7: ='Area Calculations'!B4 -> The Club at Ibis Conceptual Estimate | C7: ='Area Calculations'!B5 -> West Palm Beach, FL
A9: Alternates
A10: =TODAY() -> 46146
A12: NO. | B12: DESCRIPTION | C12: VALUE
A13: ALT. #1 | B13: Description | C13: 0
A14: ALT. #2 | B14: Description | C14: 0
A15: ALT. #3 | B15: Description | C15: 0
A16: ALT. #4 | B16: Description | C16: 0
A17: ALT. #5 | B17: Description | C17: 0
A18: ALT. #6 | B18: Description | C18: 0
A19: ALT. #7 | B19: Description | C19: 0
A20: ALT. #8 | B20: Description | C20: 0
A21: ALT. #9 | B21: Description | C21: 0
A22: ALT. #10 | B22: Description | C22: 0
A23: ALT. #11 | B23: Description | C23: 0
A24: ALT. #12 | B24: Description | C24: 0
... A27: ALT. #15 | B27: Description | C27: 0
B28: Total | C28: =SUM(C13:C27) -> 0

Sheet Labor Rates Calculator
A5: Hedrick Brothers Construction Co., Inc.
A6: Salaries and Burden Calculations
A7: As of 8/22/24
C8: MARK-UP | F8: 0.18
E9: Burdened Rate | F9: Mark-up | G9: Total | I9: ANNUAL BURDENED AMOUNT | J9: ANNUAL BURDENED AMOUNT (W/ M/U)
B10: 1 | C10: Proj Exec | E10: 157.66656 | F10: =E10*$F$8 -> 28.379981 | G10: =SUM(E10:F10) -> 186.04654 | I10: =E10*2080 -> 327946.45 | J10: =G10*2080 -> 386976.81
B11: 2 | C11: Sr PM | E11: 130.67475 | F11: =E11*$F$8 -> 23.521455 | G11: =SUM(E11:F11) -> 154.1962 | I11: =E11*2080 -> 271803.48 | J11: =G11*2080 -> 320728.11
B12: 3 | C12: PM 3 | E12: 120.34132 | F12: =E12*$F$8 -> 21.661438 | G12: =SUM(E12:F12) -> 142.00276 | I12: =E12*2080 -> 250309.95 | J12: =G12*2080 -> 295365.75
B13: 4 | C13: PM 2 | E13: 110.14476 | F13: =E13*$F$8 -> 19.826057 | G13: =SUM(E13:F13) -> 129.97082 | I13: =E13*2080 -> 229101.1 | J13: =G13*2080 -> 270339.3
B14: 5 | C14: PM 1 | E14: 94.265604 | F14: =E14*$F$8 -> 16.967809 | G14: =SUM(E14:F14) -> 111.23341 | I14: =E14*2080 -> 196072.46 | J14: =G14*2080 -> 231365.5
B15: 6 | C15: Proj Admin | E15: 66.505247 | F15: =E15*$F$8 -> 11.970944 | G15: =SUM(E15:F15) -> 78.476192 | I15: =E15*2080 -> 138330.91 | J15: =G15*2080 -> 163230.48
B16: 7 | C16: Proj Acct | E16: 85.81004 | F16: =E16*$F$8 -> 15.445807 | G16: =SUM(E16:F16) -> 101.25585 | I16: =E16*2080 -> 178484.88 | J16: =G16*2080 -> 210612.16
B17: 8 | C17: Asst PM | E17: 82.733564 | F17: =E17*$F$8 -> 14.892041 | G17: =SUM(E17:F17) -> 97.625605 | I17: =E17*2080 -> 172085.81 | J17: =G17*2080 -> 203061.26
B18: 9 | C18: Supt 3 | E18: 131.75199 | F18: =E18*$F$8 -> 23.715358 | G18: =SUM(E18:F18) -> 155.46735 | I18: =E18*2080 -> 274044.14 | J18: =G18*2080 -> 323372.08
B19: 10 | C19: Supt 2 | E19: 110.59223 | F19: =E19*$F$8 -> 19.906601 | G19: =SUM(E19:F19) -> 130.49883 | I19: =E19*2080 -> 230031.83 | J19: =G19*2080 -> 271437.56
B20: 11 | C20: Supt 1 | E20: 90.514804 | F20: =E20*$F$8 -> 16.292665 | G20: =SUM(E20:F20) -> 106.80747 | I20: =E20*2080 -> 188270.79 | J20: =G20*2080 -> 222159.54
B21: 12 | C21: Asst Supt | E21: 59.915466 | F21: =E21*$F$8 -> 10.784784 | G21: =SUM(E21:F21) -> 70.70025 | I21: =E21*2080 -> 124624.17 | J21: =G21*2080 -> 147056.52
... B26: 17 | C26: Safety | E26: 79.733968 | F26: =E26*$F$8 -> 14.352114 | G26: =SUM(E26:F26) -> 94.086082 | I26: =E26*2080 -> 165846.65 | J26: =G26*2080 -> 195699.05
C27: Labor | E27: 32.408056 | F27: =E27*$F$8 -> 5.83345 | G27: =SUM(E27:F27) -> 38.241506 | I27: =E27*2080 -> 67408.756 | J27: =G27*2080 -> 79542.332
C28: Apprentice | E28: 32.978211 | F28: =E28*$F$8 -> 5.9360779 | G28: =SUM(E28:F28) -> 38.914289 | I28: =E28*2080 -> 68594.678 | J28: =G28*2080 -> 80941.72
C29: Carpenter | E29: 45.013251 | F29: =E29*$F$8 -> 8.1023852 | G29: =SUM(E29:F29) -> 53.115636 | I29: =E29*2080 -> 93627.563 | J29: =G29*2080 -> 110480.52
C30: Driver | E30: 35.486876 | F30: =E30*$F$8 -> 6.3876377 | G30: =SUM(E30:F30) -> 41.874514 | I30: =E30*2080 -> 73812.702 | J30: =G30*2080 -> 87098.989
C31: Leadman | E31: 46.605242 | F31: =E31*$F$8 -> 8.3889436 | G31: =SUM(E31:F31) -> 54.994186 | I31: =E31*2080 -> 96938.904 | J31: =G31*2080 -> 114387.91
C32: Supt MEP | E32: 0 | F32: =E32*$F$8 -> 0 | G32: =SUM(E32:F32) -> 0 | I32: =E32*2080 -> 0 | J32: =G32*2080 -> 0
C33: Gen Supt | E33: 130.4108 | F33: =E33*$F$8 -> 23.473945 | G33: =SUM(E33:F33) -> 153.88475 | I33: =E33*2080 -> 271254.47 | J33: =G33*2080 -> 320080.28
C34: Cons Mgr | E34: 135.45804 | F34: =E34*$F$8 -> 24.382447 | G34: =SUM(E34:F34) -> 159.84048 | I34: =E34*2080 -> 281752.72 | J34: =G34*2080 -> 332468.2
C35: Proj Coor | E35: 0 | F35: =E35*$F$8 -> 0 | G35: =SUM(E35:F35) -> 0 | I35: =E35*2080 -> 0 | J35: =G35*2080 -> 0
C36: Mktg | E36: 85.41309 | F36: =E36*$F$8 -> 15.374356 | G36: =SUM(E36:F36) -> 100.78745 | I36: =E36*2080 -> 177659.23 | J36: =G36*2080 -> 209637.89
C37: Bus Dev | E37: 121.55329 | F37: =E37*$F$8 -> 21.879592 | G37: =SUM(E37:F37) -> 143.43288 | I37: =E37*2080 -> 252830.84 | J37: =G37*2080 -> 298340.39
C38: Chief, 3 & 2 | E38: 140.9198 | F38: =E38*$F$8 -> 25.365565 | G38: =SUM(E38:F38) -> 166.28537 | I38: =E38*2080 -> 293113.19 | J38: =G38*2080 -> 345873.56
... C40: Exec Asst | E40: 69.670191 | F40: =E40*$F$8 -> 12.540634 | G40: =SUM(E40:F40) -> 82.210826 | I40: =E40*2080 -> 144914 | J40: =G40*2080 -> 170998.52
D41: TOTAL | E41: =SUM(E10:E40) -> 2612.4097 | F41: =SUM(F10:F40) -> 470.23374 | G41: =SUM(G10:G40) -> 3082.6434 | I41: =SUM(I10:I40) -> 5433812.1 | J41: =SUM(J10:J40) -> 6411898.3
G42: =E41/G41 -> 0.84745763 | I42: =I41/J41 -> 0.84745763

Sheet Area Calculations
B2: PROJECT AREA CALCULATIONS
B4: The Club at Ibis Conceptual Estimate | I4: Gross (sf) | J4: =H35 -> 0 | K4: FORMULA OFF GCS
B5: West Palm Beach, FL | I5: AC (sf) | J5: =E35 -> 0
I6: Rentable (sf) | J6: =F35 -> 0
I7: Site (acres) | J7: 1 | K7: FORMULA OFF GCS
I8: Parking Spaces | J8: 1
B9: =NOW() -> 46146.222 | I9: Build Duration (months) | J9: 1 | K9: FORMULA OFF GCS
B10: Drawings Date
A13: I. | B13: Floor | C13: Building | D13: Room | E13: ACSF | F13: RSF | G13: Acres | H13: Gross SF | I13: GROSS%
C14: Racquet | I14: =H14/$J$4 -> #DIV/0!
I15: =H15/$J$4 -> #DIV/0!
C16: Spa Building | I16: =H16/$J$4 -> #DIV/0!
I17: =H17/$J$4 -> #DIV/0!
C18: New Fitness Building | I18: =H18/$J$4 -> #DIV/0!
I19: =H19/$J$4 -> #DIV/0!
I20: =H20/$J$4 -> #DIV/0!
I21: =H21/$J$4 -> #DIV/0!
I22: =H22/$J$4 -> #DIV/0!
I23: =H23/$J$4 -> #DIV/0!
I24: =H24/$J$4 -> #DIV/0!
I25: =H25/$J$4 -> #DIV/0!
I26: =H26/$J$4 -> #DIV/0!
I27: =H27/$J$4 -> #DIV/0!
I28: =H28/$J$4 -> #DIV/0!
I29: =H29/$J$4 -> #DIV/0!
I30: =H30/$J$4 -> #DIV/0!
... I34: =H34/$J$4 -> #DIV/0!
B35: TOTAL | E35: =SUM(E14:E34) -> 0 | F35: =SUM(F14:F34) -> 0 | G35: =SUM(G14:G34) -> 0 | H35: =SUM(H14:H34) -> 0 | I35: =SUM(I14:I34) -> #DIV/0!
A37: II. | C37: Units | E37: Site SF | H37: Site(acres) | J37: %
I40: =SUM(H41:H45) -> 0
J41: =H41/$J$7 -> 0
J42: =H42/$J$7 -> 0
J43: =H43/$J$7 -> 0
J44: =H44/$J$7 -> 0
J45: =H45/$J$7 -> 0
I46: =SUM(H47:H49) -> 0
J47: =H47/$J$7 -> 0
J48: =H48/$J$7 -> 0
J49: =H49/$J$7 -> 0
B51: TOTAL | E51: =SUM(E41:E49) -> 0 | H51: =SUM(H40:H50) -> 0 | J51: =SUM(J40:J50) -> 0
C53: Levels | H53: GSF | J53: %
J56: =H56/$J$4 -> #DIV/0!
J57: =H57/$J$4 -> #DIV/0!
J58: =H58/$J$4 -> #DIV/0!
B60: TOTAL GSF | H60: =SUM(H55:H59) -> 0 | J60: =SUM(J55:J59) -> #DIV/0!
M61: Design Team
M62: Architectural Drawings by
M63: Structural Drawings by
M64: MEP FA FP Drawings by
M65: Civil Drawings by
M66: Land scape Drawings by
M67: Kitchen Drawings by
M68: Storefront Designer by
M69: Geotech report by
M70: Specifications
A76: IV. | B76: SITE AREAS | I76: $ /UNIT | J76: %
B79: Site Perimeter | I79: LF
B80: Walk Gates
B81: Drive Gates
B82: Tire Grates / Truck Wash
A83: III. | B83: SITE AREAS | I83: $ /UNIT | J83: %
B84: Sidewalks
B85: Drives
B86: Asphalt Parking
B87: Fill CY
A88: III. | B88: Barking Spaces | C88: FLOOR BREAKDOWN | H88: QTY. | J88: %
J90: =H90/$J$8 -> 0
J91: =H91/$J$8 -> 0
B93: TOTAL Units | H93: =SUM(H90:H92) -> 0 | J93: =SUM(J90:J92) -> 0

Sheet Sub List
A5: ='Area Calculations'!$B$4 -> The Club at Ibis Conceptual Estimate
A7: Subcontractor List
A9: CSI | B9: CSI DESCRIPTION | C9: Sub 1 | D9: Sub 2 | E9: Sub 3
A10: 02A | B10: Demolition | C10: N&P | D10: Wildcat | E10: Rapid Removal
A11: 03A | B11: Concrete / CMU | C11: Victory | D11: De Celis | E11: Proshell
A12: 05A | B12: Structural Steel | C12: Suncor | D12: VMI | E12: Steel Fabricators
A13: 06F | B13: Millwork | C13: Borgzinner | D13: JC Wood | E13: Premier Architectural
A14: 07D | B14: Roofing | C14: Campany | D14: Crown | E14: Assurance
A15: 08C | B15: Glass and Glazing | C15: Performance | D15: A.Christian | E15: A.Crystal
A16: 09A | B16: Stucco | C16: Dorado | D16: Welch | E16: Lion
A17: 09B | B17: Drywall / Framing | C17: Dorado | D17: Everlast | E17: K&S
A18: 09E | B18: Tile | C18: Concolidated | D18: Jack Walsh | E18: O'Neil
A19: 09F | B19: Flooring: Carpet and Resilient Flooring | C19: Concolidated | D19: Jack Walsh | E19: O'Neil
A20: 09I | B20: Painting | C20: Dorado | D20: Phoenix | E20: Talbot
... A29: 31A | B29: Sitework | C29: American Engineering | D29: BiG D | E29: Princeland
A30: 32E | B30: Synthetic Fields | C30: Fast Dry | D30: Papico

Sheet Manpower
A1: IBIS
A2: STAFFING SCHEDULE
A3: YEAR | C3: 2026 | K3: 2027 | W3: 2028
A4: MONTHS | C4: MAY | D4: JUN | E4: JULY | F4: AUG | G4: SEPT | H4: OCT | I4: NOV | J4: DEC | K4: JAN | L4: FEB | M4: MAR | N4: APR | O4: MAY | P4: JUN | Q4: JULY | R4: AUG | S4: SEP | T4: OCT | U4: NOV | V4: DEC | W4: JAN | X4: FEB | Y4: MAR | Z4: APR | AA4: MAY | AB4: JUN | AD4: AUG | AF4: SEP
C5: 1 | D5: =C5+1 -> 2 | E5: =D5+1 -> 3 | F5: =E5+1 -> 4 | G5: =F5+1 -> 5 | H5: =G5+1 -> 6 | I5: =H5+1 -> 7 | J5: 8 | K5: 9 | L5: =K5+1 -> 10 | M5: =L5+1 -> 11 | N5: =M5+1 -> 12 | O5: =N5+1 -> 13 | P5: =O5+1 -> 14 | Q5: =P5+1 -> 15 | R5: =Q5+1 -> 16 | S5: =R5+1 -> 17 | ... V5: =U5+1 -> 20 | W5: 21 | X5: =W5+1 -> 22 | Y5: =X5+1 -> 23 | Z5: =Y5+1 -> 24 | AA5: =Z5+1 -> 25 | AB5: =AA5+1 -> 26 | AC5: 27 | AD5: 28 | AF5: =AD5+1 -> 29
A6: PHASE 1 - CLUBHOUSE PARCEL
A7: CLUBHOUSE
A8: RACQUET ADDITIONS
A9: PHASE 2 - NORTH & CLUBHOUSE PARCEL
A10: NORTH PARCEL - BOCCE, BASKETBALL, & SITE IMPROVEMENTS
A11: NORTH PARCEL - NEW 11,000SF SPA BUILDING
A12: NORTH PARCEL - EXPANSION & RENOVATION EXISTING POA
A13: CLUBHOUSE PARCEL - NEW FITNESS BUILDING/OUTDOOR TERRACE
A14: PHASE 3 - CLUBHOUSE PARCEL
A15: 19TH HOLE RESTAURANT
A16: RENOVATION OF EXISTING FITNESS BUILDING
A17: CLOSEOUT
A18: STAFFING | AE18: AVERAGE | AG18: Average
A19: PRESIDENT - LUX RESIDENTIAL | B19: N/A | AE19: =SUM(C19:AD19)/$AD$5 -> 0 | AG19: 0
A20: PROJECT EXECUTIVE | B20: Art | C20: 0.2 | D20: 0.2 | E20: 0.2 | F20: 0.2 | G20: 0.2 | H20: 0.2 | I20: 0.2 | J20: 0.2 | K20: 0.2 | L20: 0.2 | M20: 0.2 | N20: 0.2 | O20: 0.2 | P20: 0.2 | Q20: 0.2 | R20: 0.2 | S20: 0.2 | T20: 0.2 | U20: 0.2 | V20: 0.2 | W20: 0.2 | X20: 0.2 | Y20: 0.2 | Z20: 0.2 | AA20: 0.2 | AB20: 0.2 | AC20: 0.2 | AD20: 0.2 | AE20: =SUM(C20:AD20)/$AD$5 -> 0.2 | AF20: 0 | AG20: =(AF20) -> 0
A21: SENIOR PROJECT MANAGER | AE21: =SUM(C21:AD21)/$AD$5 -> 0 | AG21: =(AF21) -> 0
A22: PROJECT MANAGER | B22: Dave Rawdon | C22: 0.5 | D22: 0.5 | E22: 0.5 | F22: 0.5 | G22: 0.5 | H22: 0.5 | I22: 1 | J22: 1 | K22: 1 | L22: 1 | M22: 1 | N22: 1 | O22: 1 | P22: 1 | Q22: 1 | R22: 1 | S22: 1 | T22: 1 | U22: 1 | V22: 1 | W22: 1 | X22: 1 | Y22: 1 | Z22: 1 | AA22: 1 | AB22: 1 | AC22: 1 | AD22: 1 | AE22: =SUM(C22:AD22)/$AD$5 -> 0.89285714 | AF22: 1 | AG22: =(AF22) -> 1
A23: ASSISTANT PROJECT MANAGER | B23: TBD | AE23: =SUM(C23:AD23)/$AD$5 -> 0 | AG23: =(AF23) -> 0
A24: PROJECT ADMIN | B24: TBD | C24: 0.5 | D24: 0.5 | E24: 0.5 | F24: 0.5 | G24: 0.5 | H24: 0.5 | I24: 1 | J24: 1 | K24: 1 | L24: 1 | M24: 1 | N24: 1 | O24: 1 | P24: 1 | Q24: 1 | R24: 1 | S24: 1 | T24: 1 | U24: 1 | V24: 1 | W24: 1 | X24: 1 | Y24: 1 | Z24: 1 | AA24: 1 | AB24: 1 | AC24: 1 | AD24: 1 | AE24: =SUM(C24:AD24)/$AD$5 -> 0.89285714 | AF24: 1 | AG24: =(AF24) -> 1
A25: SUPERINTENDENT - LEVEL 2 | B25: Brad | C25: 1 | D25: 1 | E25: 1 | F25: 1 | G25: 1 | H25: 1 | I25: 1 | J25: 1 | K25: 1 | L25: 1 | M25: 1 | N25: 1 | O25: 1 | P25: 1 | Q25: 1 | R25: 1 | S25: 1 | T25: 1 | U25: 1 | V25: 1 | W25: 1 | X25: 1 | Y25: 1 | Z25: 1 | AA25: 1 | AB25: 1 | AC25: 1 | AD25: 1 | AE25: =SUM(C25:AD25)/$AD$5 -> 1 | AF25: 1 | AG25: =(AF25) -> 1
A26: SUPERINTENDENT - LEVEL 1 | B26: TBD | K26: 1 | L26: 1 | M26: 1 | N26: 1 | O26: 1 | P26: 1 | Q26: 1 | R26: 1 | S26: 1 | T26: 1 | U26: 1 | V26: 1 | W26: 1 | X26: 1 | AE26: =SUM(C26:AD26)/$AD$5 -> 0.5 | AG26: =(AF26) -> 0
A27: ASSISTANT SUPERINTENDENT | B27: TBD | C27: 1 | D27: 1 | E27: 1 | F27: 1 | G27: 1 | H27: 1 | I27: 1 | J27: 1 | K27: 1 | L27: 1 | M27: 1 | N27: 1 | O27: 1 | P27: 1 | Q27: 1 | R27: 1 | S27: 1 | T27: 1 | U27: 1 | V27: 1 | W27: 1 | X27: 1 | Y27: 1 | Z27: 1 | AA27: 1 | AB27: 1 | AC27: 1 | AD27: 1 | AE27: =SUM(C27:AD27)/$AD$5 -> 1 | AF27: 1 | AG27: =(AF27) -> 1
A28: ASSISTANT SUPERINTENDENT | B28: TBD | K28: 1 | L28: 1 | M28: 1 | N28: 1 | O28: 1 | P28: 1 | Q28: 1 | R28: 1 | S28: 1 | T28: 1 | U28: 1 | V28: 1 | W28: 1 | X28: 1 | AE28: =SUM(C28:AD28)/$AD$5 -> 0.5 | AG28: =(AF28) -> 0
A29: Quality Control | B29: TBD | C29: 0.2 | D29: 0.2 | E29: 0.2 | F29: 0.2 | G29: 0.2 | H29: 0.2 | I29: 0.2 | J29: 0.2 | K29: 0.2 | L29: 0.2 | M29: 0.2 | N29: 0.2 | O29: 0.2 | P29: 0.2 | Q29: 0.2 | R29: 0.2 | S29: 0.2 | T29: 0.2 | U29: 0.2 | V29: 0.2 | W29: 0.2 | X29: 0.2 | Y29: 0.2 | Z29: 0.2 | AA29: 0.2 | AB29: 0.2 | AC29: 0.2 | AD29: 0.2 | AE29: =SUM(C29:AD29)/$AD$5 -> 0.2 | AF29: 0 | AG29: =(AF29) -> 0
A30: General Super | B30: TBD | AE30: =SUM(C30:AD30)/$AD$5 -> 0 | AG30: =(AF30) -> 0
A31: Safety | B31: TBD | C31: 0.2 | D31: 0.2 | E31: 0.2 | F31: 0.2 | G31: 0.2 | H31: 0.2 | I31: 0.2 | J31: 0.2 | K31: 0.2 | L31: 0.2 | M31: 0.2 | N31: 0.2 | O31: 0.2 | P31: 0.2 | Q31: 0.2 | R31: 0.2 | S31: 0.2 | T31: 0.2 | U31: 0.2 | V31: 0.2 | W31: 0.2 | X31: 0.2 | Y31: 0.2 | Z31: 0.2 | AA31: 0.2 | AB31: 0.2 | AC31: 0.2 | AD31: 0.2 | AE31: =SUM(C31:AD31)/$AD$5 -> 0.2 | AF31: 0 | AG31: =(AF31) -> 0
A32: ACCOUNTING | B32: TBD | C32: 0.2 | D32: 0.2 | E32: 0.2 | F32: 0.2 | G32: 0.2 | H32: 0.2 | I32: 0.2 | J32: 0.2 | K32: 0.2 | L32: 0.2 | M32: 0.2 | N32: 0.2 | O32: 0.2 | P32: 0.2 | Q32: 0.2 | R32: 0.2 | S32: 0.2 | T32: 0.2 | U32: 0.2 | V32: 0.2 | W32: 0.2 | X32: 0.2 | Y32: 0.2 | Z32: 0.2 | AA32: 0.2 | AB32: 0.2 | AC32: 0.2 | AD32: 0.2 | AE32: =SUM(C32:AD32)/$AD$5 -> 0.2 | AF32: 0.2 | AG32: =(AF32) -> 0.2
A33: Scheduling Consultant w/ weekly updates | B33: TBD | AE33: =SUM(C33:AD33)/$AD$5 -> 0 | AG33: =(AF33) -> 0
A34: FOREMAN | B34: Job Cost | AE34: =SUM(C34:AD34)/$AD$5 -> 0 | AG34: =(AF34) -> 0
A35: CARPENTER | B35: Job Cost | AE35: =SUM(C35:AD35)/$AD$5 -> 0 | AG35: =(AF35) -> 0
A36: LABORER | B36: Job Cost | AE36: =SUM(C36:AD36)/$AD$5 -> 0 | AG36: =(AF36) -> 0
AE37: =SUM(C37:AD37)/$AD$5 -> 0 | AG37: =(AF37) -> 0

Sheet GCs & GRs
A1: Contract Reference | B1: General Condition Ref. | C1: ='Area Calculations'!B4 -> The Club at Ibis Conceptual Estimate
C3: Construction | F3: Activity | H3: Start | I3: Finish | J3: Days | K3: Weeks | L3: Months | M3: % Time | N3: Remarks | Q3: Demo to building pad
F4: Construction | H4: 46143 | I4: 46996 | J4: =SUM(I4-H4) -> 853 | K4: =SUM(J4/7) -> 121.85714 | L4: =SUM(J4/30) -> 28.433333 | Q4: Activity | S4: Start | T4: Finish | U4: Days | V4: Weeks | W4: Months | Z4: Per RFP Schedule
F5: Close Out | H5: 46997 | I5: 47026 | J5: =SUM(I5-H5) -> 29 | K5: =SUM(J5/7) -> 4.1428571 | L5: =SUM(J5/30) -> 0.96666667 | Q5: Construction | S5: 0 | T5: 0 | U5: =SUM(T5-S5) -> 0 | V5: =SUM(U5/7) -> 0 | W5: =SUM(U5/30) -> 0
F6: General Conditions | H6: General Req. - Field Office | J6: General Req. | L6: Total | Q6: Building
C7: Description | D7: Qty. | E7: U | F7: Unit | G7: Const. | H7: Unit | I7: General | J7: Unit | K7: General | O7: LABOR RATE FY 2025 *Updated 09.26.24 | P7: LABOR RATE (MIAMI/FT. LAUDERDALE) | Q7: Activity | S7: Start | T7: Finish | U7: Days | V7: Weeks | W7: Months | X7: LABOR RATE (MF CENTRAL FLORIDA)
F8: Cost | G8: Cond. | H8: Cost | I8: Req. | J8: Cost | K8: Req. | Q8: Construction | S8: 0 | T8: 0 | U8: =SUM(T8-S8) -> 0 | V8: =SUM(U8/7) -> 0 | W8: =SUM(U8/30) -> 0
C9: Field Labor - Construction | L9: =SUM(L10:L27) -> 2897709.5
C10: Project Executive | D10: =$K$4 -> 121.85714 | E10: wks | F10: =(O10*40)*M10 -> 1488.3724 | G10: =SUM(D10*F10) -> 181368.8 | L10: =SUM(G10+I10+K10) -> 181368.8 | M10: =Manpower!$AE$20 -> 0.2 | N10: Art | O10: ='Labor Rates Calculator'!G10 -> 186.04654 | P10: 253 | X10: 216
C11: Senior Project Manager | D11: =$K$4 -> 121.85714 | E11: wks | F11: =(O11*40)*M11 -> 0 | G11: =SUM(D11*F11) -> 0 | L11: =SUM(G11+I11+K11) -> 0 | M11: =Manpower!$AE$21 -> 0 | O11: ='Labor Rates Calculator'!G11 -> 154.1962 | P11: 195 | X11: 175
C12: Project Manager - Level 3 | D12: =$K$4 -> 121.85714 | E12: wks | F12: =(O12*40)*M12 -> 5071.5272 | G12: =SUM(D12*F12) -> 618001.82 | L12: =SUM(G12+I12+K12) -> 618001.82 | M12: =Manpower!AE22 -> 0.89285714 | N12: =N13 -> 0 | O12: ='Labor Rates Calculator'!G12 -> 142.00276
C13: Project Manager - Level 2 | D13: =$K$4 -> 121.85714 | E13: wks | F13: =(O13*40)*M13 -> 0 | G13: =SUM(D13*F13) -> 0 | L13: =SUM(G13+I13+K13) -> 0 | M13: 0 | O13: ='Labor Rates Calculator'!G13 -> 129.97082 | P13: 185 | X13: 155
C14: Project Manager - Level 1 | D14: =$K$4 -> 121.85714 | E14: wks | F14: =(O14*40)*M14 -> 0 | G14: =SUM(D14*F14) -> 0 | L14: =SUM(G14+I14+K14) -> 0 | M14: 0 | O14: ='Labor Rates Calculator'!G14 -> 111.23341 | P14: 163 | X14: 130
C15: Project Administator | D15: =$K$4 -> 121.85714 | E15: wks | F15: =(O15*40)*M15 -> 2802.7211 | G15: =SUM(D15*F15) -> 341531.59 | L15: =SUM(G15+I15+K15) -> 341531.59 | M15: =Manpower!$AE$24 -> 0.89285714 | N15: TBD | O15: ='Labor Rates Calculator'!G15 -> 78.476192 | P15: 95 | X15: 65
C16: Project Accountant | D16: =$K$4 -> 121.85714 | E16: wks | F16: =(O16*40)*M16 -> 0 | G16: =SUM(D16*F16) -> 0 | L16: =SUM(G16+I16+K16) -> 0 | M16: 0 | O16: ='Labor Rates Calculator'!G16 -> 101.25585 | P16: 81 | X16: 60
C17: Assistant Project Manager | D17: =$K$4 -> 121.85714 | E17: wks | F17: =(O17*40)*M17 -> 0 | G17: =SUM(D17*F17) -> 0 | L17: =SUM(G17+I17+K17) -> 0 | M17: 0 | O17: ='Labor Rates Calculator'!G17 -> 97.625605 | P17: 118 | X17: 95
C18: Superintendent - Level 3 | D18: =$K$4 -> 121.85714 | E18: wks | F18: =(O18*40)*M18 -> 0 | G18: =SUM(D18*F18) -> 0 | L18: =SUM(G18+I18+K18) -> 0 | M18: 0 | O18: ='Labor Rates Calculator'!G18 -> 155.46735 | P18: 183 | X18: 194
C19: Superintendent - Level 2 | D19: =$K$4 -> 121.85714 | E19: wks | F19: =(O19*40)*M19 -> 5219.9531 | G19: =SUM(D19*F19) -> 636088.57 | L19: =SUM(G19+I19+K19) -> 636088.57 | M19: =Manpower!$AE$25 -> 1 | N19: Brad Harrison | O19: ='Labor Rates Calculator'!G19 -> 130.49883 | P19: 161 | X19: 173
C20: Superintendent - Level 1 | D20: =$K$4 -> 121.85714 | E20: wks | F20: =(O20*40)*M20 -> 2136.1494 | G20: =SUM(D20*F20) -> 260305.06 | L20: =SUM(G20+I20+K20) -> 260305.06 | M20: =Manpower!$AE$26 -> 0.5 | N20: TBD for phase 2 only | O20: ='Labor Rates Calculator'!G20 -> 106.80747 | P20: 161 | X20: 173
C21: Superintendent - Level 1 | D21: =$K$4 -> 121.85714 | E21: wks | F21: =(O21*40)*M21 -> 0 | G21: =SUM(D21*F21) -> 0 | L21: =SUM(G21+I21+K21) -> 0 | M21: 0 | O21: ='Labor Rates Calculator'!G20 -> 106.80747 | P21: 121 | X21: 155
C22: Assistant Superintendent | D22: =$K$4 -> 121.85714 | E22: wks | F22: =(O22*40)*M22 -> 2828.01 | G22: =SUM(D22*F22) -> 344613.22 | L22: =SUM(G22+I22+K22) -> 344613.22 | M22: =Manpower!$AE$27 -> 1 | N22: TBD | O22: ='Labor Rates Calculator'!G21 -> 70.70025 | P22: 84 | X22: 95
C23: Assistant Superintendent | D23: =$K$4 -> 121.85714 | E23: wks | F23: =(O23*40)*M23 -> 1414.005 | G23: =SUM(D23*F23) -> 172306.61 | L23: =SUM(G23+I23+K23) -> 172306.61 | M23: =Manpower!$AE$28 -> 0.5 | N23: TBD for phase 2 only | O23: ='Labor Rates Calculator'!G21 -> 70.70025 | P23: 84 | X23: 95
C24: Quality Control Manager | D24: =$K$4 -> 121.85714 | E24: wks | F24: =(O24*40)*M24 -> 971.68174 | G24: =SUM(D24*F24) -> 118406.36 | L24: =SUM(G24+I24+K24) -> 118406.36 | M24: =Manpower!$AE$29 -> 0.2 | O24: ='Labor Rates Calculator'!G22 -> 121.46022
C25: Foreman | D25: =$K$4 -> 121.85714 | E25: wks | F25: =(O25*40)*M25 -> 0 | G25: =SUM(D25*F25) -> 0 | L25: =SUM(G25+I25+K25) -> 0 | M25: =Manpower!$AE$34 -> 0 | O25: ='Labor Rates Calculator'!G23 -> 49.003574 | P25: 65 | X25: 65
C26: Accounting | D26: =$K$4 -> 121.85714 | E26: wks | F26: =(O26*40)*M26 -> 1094.4532 | G26: =SUM(D26*F26) -> 133366.95 | L26: =SUM(G26+I26+K26) -> 133366.95 | M26: =Manpower!$AE$32 -> 0.2 | O26: ='Labor Rates Calculator'!G24 -> 136.80666 | P26: 80 | X26: 90
C27: Safety Supervisor/Inspector | D27: =K4 -> 121.85714 | E27: wks | F27: =(O27*40)*M27 -> 752.68866 | G27: =SUM(D27*F27) -> 91720.489 | L27: =SUM(G27+I27+K27) -> 91720.489 | M27: =Manpower!$AE$31 -> 0.2 | O27: ='Labor Rates Calculator'!G26 -> 94.086082 | P27: 96 | X27: 96
C28: Field Labor - Close Out | L28: =SUM(L29:L43) -> 93428.985
C29: Project Executive | D29: =$K$5 -> 4.1428571 | E29: wks | F29: =(40*O29)*M29 -> 0 | G29: =SUM(D29*F29) -> 0 | L29: =SUM(G29+I29+K29) -> 0 | M29: =Manpower!$AG$20 -> 0 | O29: =+O10 -> 186.04654 | P29: =+P10 -> 253 | X29: =+X10 -> 216
C30: Senior Project Manager | D30: =$K$5 -> 4.1428571 | E30: wks | F30: =(40*O30)*M30 -> 0 | G30: =SUM(D30*F30) -> 0 | L30: =SUM(G30+I30+K30) -> 0 | M30: =+M11 -> 0 | O30: =+O11 -> 154.1962 | P30: =+P11 -> 195 | X30: =+X11 -> 175
C31: Project Manager - Level 3 | D31: =$K$5 -> 4.1428571 | E31: wks | F31: =(40*O31)*M31 -> 5071.5272 | G31: =SUM(D31*F31) -> 21010.613 | L31: =SUM(G31+I31+K31) -> 21010.613 | M31: =+M12 -> 0.89285714 | O31: =O12 -> 142.00276
C32: Project Manager - Level 2 | D32: =$K$5 -> 4.1428571 | E32: wks | F32: =(40*O32)*M32 -> 5198.8326 | G32: =SUM(D32*F32) -> 21538.021 | L32: =SUM(G32+I32+K32) -> 21538.021 | M32: =Manpower!$AG$22 -> 1 | O32: =+O13 -> 129.97082 | P32: =+P13 -> 185 | X32: =+X13 -> 155
C33: Project Manager - Level 1 | D33: =$K$5 -> 4.1428571 | E33: wks | F33: =(40*O33)*M33 -> 0 | G33: =SUM(D33*F33) -> 0 | L33: =SUM(G33+I33+K33) -> 0 | M33: =+M14 -> 0 | O33: =+O14 -> 111.23341 | P33: =+P14 -> 163 | X33: =+X14 -> 130
C34: Project Administator | D34: =$K$5 -> 4.1428571 | E34: wks | F34: =(40*O34)*M34 -> 3139.0477 | G34: =SUM(D34*F34) -> 13004.626 | L34: =SUM(G34+I34+K34) -> 13004.626 | M34: =Manpower!$AG$24 -> 1 | O34: =+O15 -> 78.476192 | P34: =+P15 -> 95 | X34: =+X15 -> 65
C35: Project Coordinator | D35: =$K$5 -> 4.1428571 | E35: wks | F35: =(40*O35)*M35 -> 0 | G35: =SUM(D35*F35) -> 0 | L35: =SUM(G35+I35+K35) -> 0 | M35: =+M16 -> 0 | O35: =+O16 -> 101.25585 | P35: =+P16 -> 81 | X35: =+X16 -> 60
C36: Assistant Project Manager | D36: =$K$5 -> 4.1428571 | E36: wks | F36: =(40*O36)*M36 -> 0 | G36: =SUM(D36*F36) -> 0 | L36: =SUM(G36+I36+K36) -> 0 | M36: =+M17 -> 0 | O36: =+O17 -> 97.625605 | P36: =+P17 -> 118 | X36: =+X17 -> 95
C37: Superintendent - Level 3 | D37: =$K$5 -> 4.1428571 | E37: wks | F37: =(40*O37)*M37 -> 0 | G37: =SUM(D37*F37) -> 0 | L37: =SUM(G37+I37+K37) -> 0 | M37: =+M18 -> 0 | O37: =+O18 -> 155.46735 | P37: =+P18 -> 183 | X37: =+X18 -> 194
C38: Superintendent - Level 2 | D38: =$K$5 -> 4.1428571 | E38: wks | F38: =(40*O38)*M38 -> 5219.9531 | G38: =SUM(D38*F38) -> 21625.52 | L38: =SUM(G38+I38+K38) -> 21625.52 | M38: =Manpower!$AF$25 -> 1 | O38: =+O19 -> 130.49883 | P38: =+P19 -> 161 | X38: =+X19 -> 173
C39: Superintendent - Level 1 | D39: =$K$5 -> 4.1428571 | E39: wks | F39: =(40*O39)*M39 -> 0 | G39: =SUM(D39*F39) -> 0 | L39: =SUM(G39+I39+K39) -> 0 | M39: =+M21 -> 0 | O39: =+O21 -> 106.80747 | P39: =+P21 -> 121 | X39: =+X21 -> 155
C40: Assistant Superinterndent | D40: =$K$5 -> 4.1428571 | E40: wks | F40: =(40*O40)*M40 -> 2828.01 | G40: =SUM(D40*F40) -> 11716.041 | L40: =SUM(G40+I40+K40) -> 11716.041 | M40: =Manpower!$AF$27 -> 1 | O40: =+O22 -> 70.70025 | P40: =+P22 -> 84 | X40: =+X22 -> 95
C41: Foreman | D41: =$K$5 -> 4.1428571 | E41: wks | F41: =(40*O41)*M41 -> 0 | G41: =SUM(D41*F41) -> 0 | L41: =SUM(G41+I41+K41) -> 0 | M41: =+M25 -> 0 | O41: =+O25 -> 49.003574 | P41: =+P25 -> 65 | X41: =+X25 -> 65
C42: Accounting | D42: =$K$5 -> 4.1428571 | E42: wks | F42: =(40*O42)*M42 -> 1094.4532 | G42: =SUM(D42*F42) -> 4534.1634 | L42: =SUM(G42+I42+K42) -> 4534.1634 | M42: =Manpower!$AF$32 -> 0.2 | O42: =+O26 -> 136.80666 | P42: =+P26 -> 80 | X42: =+X26 -> 90
C43: Safety Supervisor/Inspector | D43: =$K$5 -> 4.1428571 | E43: wks | F43: =(40*O43)*M43 -> 0 | G43: =SUM(D43*F43) -> 0 | L43: =SUM(G43+I43+K43) -> 0 | M43: 0 | O43: =+O27 -> 94.086082 | P43: =+P27 -> 96 | X43: =+X27 -> 96
C44: Field Office - Contractor | L44: =SUM(L45:L64) -> 136938.5
C45: Field Office Set Up / Removal - Double Wide | D45: 0 | E45: ea | H45: 16000 | I45: =SUM(D45*H45) -> 0 | J45: ` | L45: =SUM(G45+I45+K45) -> 0
C46: Field Office - Double Wide | D46: 0 | E46: mos | H46: 3500 | I46: =SUM(D46*H46) -> 0 | L46: =SUM(G46+I46+K46) -> 0
C47: Field Office Set Up / Removal - Single Wide | D47: 1 | E47: ea | H47: 15958 | I47: =SUM(D47*H47) -> 15958 | L47: =SUM(G47+I47+K47) -> 15958 | N47: WILLSCOT 4/16/2024 (36x10 mobile office)
C48: Field Office - Single Wide | D48: =$L$4 -> 28.433333 | E48: mos | H48: 1732 | I48: =SUM(D48*H48) -> 49246.533 | L48: =SUM(G48+I48+K48) -> 49246.533 | N48: WILLSCOT 4/16/2024 (36x10 mobile office)
C49: Field Office Set Up / Removal - Connex | D49: 0 | E49: ea | H49: 1371 | I49: =SUM(D49*H49) -> 0 | L49: =SUM(G49+I49+K49) -> 0 | N49: WILLSCOT 20' COMBO W/10' OFFICE
C50: Field Office - Conex | D50: =$L$4 -> 28.433333 | E50: mos | H50: 573 | I50: =SUM(D50*H50) -> 16292.3 | L50: =SUM(G50+I50+K50) -> 16292.3 | N50: WILLSCOT 20' COMBO W/10' OFFICE
C51: Connect Telephone Lines | D51: 0 | E51: ea | H51: 2000 | I51: =SUM(D51*H51) -> 0 | L51: =SUM(G51+I51+K51) -> 0
C52: Telephone | D52: =$L$4 -> 28.433333 | E52: mos | H52: 250 | I52: =SUM(D52*H52) -> 7108.3333 | L52: =SUM(G52+I52+K52) -> 7108.3333
C53: Cellular Telephones | D53: =$L$4 -> 28.433333 | E53: mos | H53: 0 | I53: =SUM(D53*H53) -> 0 | L53: =SUM(G53+I53+K53) -> 0 | N53: In labor rates
C54: Furniture | D54: 2 | E54: ls | H54: 500 | I54: =SUM(D54*H54) -> 1000 | L54: =SUM(G54+I54+K54) -> 1000
C55: Office Supplies | D55: =$L$4 -> 28.433333 | E55: mos | H55: 100 | I55: =SUM(D55*H55) -> 2843.3333 | L55: =SUM(G55+I55+K55) -> 2843.3333
C56: Drinking Water | D56: =$L$4 -> 28.433333 | E56: mos | H56: 50 | I56: =SUM(D56*H56) -> 1421.6667 | L56: =SUM(G56+I56+K56) -> 1421.6667
C57: Janitor Supplies/Cleaning | D57: =$L$4 -> 28.433333 | E57: mos | H57: 250 | I57: =SUM(D57*H57) -> 7108.3333 | L57: =SUM(G57+I57+K57) -> 7108.3333
C58: Computers | D58: 0 | E58: ls | H58: 0 | I58: =SUM(D58*H58) -> 0 | L58: =SUM(G58+I58+K58) -> 0
C59: Printers | D59: 0 | E59: ls | H59: 500 | I59: =SUM(D59*H59) -> 0 | L59: =SUM(G59+I59+K59) -> 0
C60: Copy Machine | D60: 2 | E60: ls | H60: 500 | I60: =SUM(D60*H60) -> 1000 | L60: =SUM(G60+I60+K60) -> 1000
C61: Alarm System | D61: 0 | E61: mos | H61: 0 | I61: =SUM(D61*H61) -> 0 | L61: =SUM(G61+I61+K61) -> 0
C62: Installation Office Equip. | D62: 0 | E62: ls | H62: 250 | I62: =SUM(D62*H62) -> 0 | L62: =SUM(G62+I62+K62) -> 0
C63: Storage Trailers Set Up / Removal | D63: 1 | E63: ea | H63: 840 | I63: =SUM(D63*H63) -> 840 | L63: =SUM(G63+I63+K63) -> 840 | N63: willscot 40' trailer
C64: Storage Trailers | D64: =$L$4 -> 28.433333 | E64: mos | H64: 1200 | I64: =SUM(D64*H64) -> 34120 | L64: =SUM(G64+I64+K64) -> 34120 | N64: Rate - $1200 ea. per month
C65: Field Office - Owner | N65: =SUM(L66:L80) -> 0
C66: Field Office Set Up / Removal | D66: 1 | E66: ls | J66: 0 | K66: =SUM(D66*J66) -> 0 | L66: =SUM(G66+I66+K66) -> 0 | N66: assume not required
C67: Field Office | D67: =L4 -> 28.433333 | E67: mos | J67: 0 | K67: =SUM(D67*J67) -> 0 | L67: =SUM(G67+I67+K67) -> 0 | N67: assume not required
C68: Connect Telephone Lines | D68: 1 | E68: ls | J68: 0 | K68: =SUM(D68*J68) -> 0 | L68: =SUM(G68+I68+K68) -> 0 | N68: assume not required
C69: Telephone | D69: =L4 -> 28.433333 | E69: mos | J69: 0 | K69: =SUM(D69*J69) -> 0 | L69: =SUM(G69+I69+K69) -> 0 | N69: assume not required
C70: Cellular Telephones | D70: =L4+L5 -> 29.4 | E70: mos | J70: 0 | K70: =SUM(D70*J70) -> 0 | L70: =SUM(G70+I70+K70) -> 0 | N70: assume not required
C71: Furniture | D71: 1 | E71: ls | J71: 0 | K71: =SUM(D71*J71) -> 0 | L71: =SUM(G71+I71+K71) -> 0 | N71: assume not required
C72: Office Supplies | D72: =L4+L5 -> 29.4 | E72: mos | J72: 0 | K72: =SUM(D72*J72) -> 0 | L72: =SUM(G72+I72+K72) -> 0 | N72: assume not required
C73: Drinking Water | D73: =L4+L5 -> 29.4 | E73: mos | J73: 0 | K73: =SUM(D73*J73) -> 0 | L73: =SUM(G73+I73+K73) -> 0 | N73: assume not required
C74: Janitor Supplies | D74: =L4 -> 28.433333 | E74: mos | J74: 0 | K74: =SUM(D74*J74) -> 0 | L74: =SUM(G74+I74+K74) -> 0 | N74: assume not required
C75: Computers | D75: 1 | E75: ls | J75: 0 | K75: =SUM(D75*J75) -> 0 | L75: =SUM(G75+I75+K75) -> 0 | N75: assume not required
C76: Printers | D76: 1 | E76: ls | J76: 0 | K76: =SUM(D76*J76) -> 0 | L76: =SUM(G76+I76+K76) -> 0 | N76: assume not required
C77: Copy Machine | D77: =L4+L5 -> 29.4 | E77: mos | J77: 0 | K77: =SUM(D77*J77) -> 0 | L77: =SUM(G77+I77+K77) -> 0 | N77: assume not required
C78: Fax Machine | D78: 1 | E78: ls | J78: 0 | K78: =SUM(D78*J78) -> 0 | L78: =SUM(G78+I78+K78) -> 0 | N78: assume not required
C79: Alarm System | D79: =L4 -> 28.433333 | E79: mos | J79: 0 | K79: =SUM(D79*J79) -> 0 | L79: =SUM(G79+I79+K79) -> 0 | N79: assume not required
C80: Installation Office Equip. | D80: 1 | E80: ls | J80: 0 | K80: =SUM(D80*J80) -> 0 | L80: =SUM(G80+I80+K80) -> 0 | N80: assume not required
C81: Temporary Utilities | L81: =SUM(L82:L94) -> 84208.867
C82: Temp. Electrical Service | D82: 0 | E82: ls | J82: 0 | K82: =SUM(D82*J82) -> 0 | L82: =SUM(G82+I82+K82) -> 0 | N82: by elect sub
C83: Temp. Electrical - Const. Phase | D83: =$L$4 -> 28.433333 | E83: mos | J83: 0 | K83: =SUM(D83*J83) -> 0 | L83: =SUM(G83+I83+K83) -> 0 | N83: by owner
C84: Temp. Electrical - Operate Phase | D84: =L4 -> 28.433333 | E84: mos | J84: 0 | K84: =SUM(D84*J84) -> 0 | L84: =SUM(G84+I84+K84) -> 0 | N84: by owner
C85: Temp. Wiring & Lighting | D85: 0 | E85: sf | J85: 0 | K85: =SUM(D85*J85) -> 0 | L85: =SUM(G85+I85+K85) -> 0 | N85: by elect sub
C86: Temporary Water - Service | D86: 0 | E86: ls | J86: 0 | K86: =SUM(D86*J86) -> 0 | L86: =SUM(G86+I86+K86) -> 0 | N86: by owner
C87: Temporary Water | D87: =L4 -> 28.433333 | E87: mos | J87: 0 | K87: =SUM(D87*J87) -> 0 | L87: =SUM(G87+I87+K87) -> 0
C88: Temporary Toilets | D88: =$L$4 -> 28.433333 | E88: mos | J88: =407*4 -> 1628 | K88: =SUM(D88*J88) -> 46289.467 | L88: =SUM(G88+I88+K88) -> 46289.467 | N88: 04/15/2024 united site services
C89: Temporary Toilet Set Up / Removal | D89: 4 | E89: ea | J89: 93 | K89: =SUM(D89*J89) -> 372 | L89: =SUM(G89+I89+K89) -> 372 | N89: 04/15/2024 united site services
C90: Temporary Washing Station | D90: =$L$4 -> 28.433333 | E90: mos | J90: =407*2 -> 814 | K90: =SUM(D90*J90) -> 23144.733 | L90: =SUM(G90+I90+K90) -> 23144.733 | N90: 04/15/2024 united site services
C91: Temporary Washing Station Set Up / Removal | D91: 2 | E91: ea | J91: 93 | K91: =SUM(D91*J91) -> 186 | L91: =SUM(G91+I91+K91) -> 186 | N91: 04/15/2024 united site services
C92: Temporary Holding Tanks | D92: =L4 -> 28.433333 | E92: mos | J92: 500 | K92: =SUM(D92*J92) -> 14216.667 | L92: =SUM(G92+I92+K92) -> 14216.667
C93: Temporary Ventilation | D93: 0 | E93: ls | J93: 0 | K93: =SUM(D93*J93) -> 0 | L93: =SUM(G93+I93+K93) -> 0
C94: Temporary Cooling | D94: =L4 -> 28.433333 | E94: mos | J94: 0 | K94: =SUM(D94*J94) -> 0 | L94: =SUM(G94+I94+K94) -> 0
C95: Equipment | L95: =SUM(L96:L98) -> 113733.33
C96: Small Tools | D96: =$L$4 -> 28.433333 | E96: mos | J96: 1500 | K96: =SUM(D96*J96) -> 42650 | L96: =SUM(G96+I96+K96) -> 42650
C97: Equipment Rental | D97: =$L$4 -> 28.433333 | E97: mos | J97: 2500 | K97: =SUM(D97*J97) -> 71083.333 | L97: =SUM(G97+I97+K97) -> 71083.333
C98: Engineering Instruments | D98: 0 | E98: ls | J98: 1000 | K98: =SUM(D98*J98) -> 0 | L98: =SUM(G98+I98+K98) -> 0
C99: Security | L99: =SUM(L100:L117) -> 70553.333
B100: 15000 | C100: Temporary Fence - 6' Post Driven w/ windscreen | D100: 0 | E100: lf | J100: 8.3 | K100: =J100*D100 -> 0 | L100: =SUM(G100+I100+K100) -> 0 | N100: rent national 4/15/2024
C101: Temporary Fence - 8' Post Driven w/ windscreen | D101: 0 | E101: lf | J101: 9.8 | K101: =J101*D101 -> 0 | L101: =SUM(G101+I101+K101) -> 0 | N101: rent national 4/15/2024
...

Sheet IDS
G1: Hedrick Plug
F2: X | G2: Excluded
B3: BACK TO SUMMARY SHEET | F3: I | G3: Included | H3: Bidder 1 | J3: Bidder 2 | L3: Bidder 3 | N3: Bidder 4 | P3: Bidder5 | R3: Bidder6
A4: Project: | B4: ='Area Calculations'!B4 -> The Club at Ibis Conceptual Estimate | G4: Company | H4: HB Construction
A5: Trade: | B5: IDS Services | G5: Contact | H5: Butch Carmichael
A6: CSI Code: | G6: Phone | H6: 561-225-4868
A7: Date: | G7: Email | H7: <bcarmichael@hedrickbrothers.com>
A8: Adjusted Bid | G8: Adjusted Bid | H8: =I99 -> 50969 | J8: =K99 -> 0 | L8: =M99 -> 0 | N8: =O99 -> 0 | P8: =Q99 -> 0 | R8: =S99 -> 0
A9: BID DOCUMENTS: | C9: Plan/ Spec. Package | D9: QTY | E9: U/M | F9: Unit Cost | G9: Subtotal | H9: Yes/No | I9: Price | J9: Yes/No | K9: Price | L9: Yes/No | M9: Price | N9: Yes/No | O9: Price | P9: Yes/No | Q9: Price | R9: Yes/No | S9: Price
B10: Plans By Division
B11: ='[1]Area Calculations'!J54 -> #VALUE! | C11: P
B12: ='[1]Area Calculations'!J55 -> #VALUE! | C12: P
B13: ='[1]Area Calculations'!J56 -> #VALUE! | C13: P
B14: ='[1]Area Calculations'!J57 -> #VALUE! | C14: P
B15: ='[1]Area Calculations'!J58 -> #VALUE! | C15: P
B16: ='[1]Area Calculations'!J59 -> #VALUE! | C16: P
B17: ='[1]Area Calculations'!J60 -> #VALUE! | C17: P
B18: ='[1]Area Calculations'!J61 -> #VALUE! | C18: P
B19: ='[1]Area Calculations'!J62 -> #VALUE! | C19: P
B21: Survey
B22: OCIP Insurance per exhibit
B23: GENERAL INCLUSIONS
B24: INCLUDES ALL SALES TAX
B25: ALL HOISTING & RIGGING REQUIRED TO COMPLETE THIS SCOPE
B26: PROVIDE P&P BONDS
B27: FLORIDA STATE CONTRACTORS LIC.
B28: GENERAL LIABILITY AND WORKERS COMP. INSURANCE LIMITS
B29: STATE AND LOCAL TAXES
B30: SPECIFIC TRADE SCOPE OF WORK REQUIREMENTS
B31: BASE BID | I31: 50969
B33: Pre-construction Modeling/BIM Execution Plan Meetings
B34: BIM Execution Plan Meeting including writing of BEP
B35: Initial Jobsite Visit
B36: Model Architectural
B37: Model Structural
B38: Model Mechanical/HVAC
B39: Model Plumbing
B40: Model Electrical
B41: Model Fire Sprinkler
B42: Model Civil
B43: Model FF&E
B45: Pre-construction - Digital Scanning
... B93: Other:
F95: SUBTOTAL | I95: =SUM(I31:I94) -> 50969 | K95: =SUM(K31:K94) -> 0 | M95: =SUM(M31:M94) -> 0 | O95: =SUM(O31:O94) -> 0 | Q95: =SUM(Q31:Q94) -> 0 | S95: =SUM(S31:S94) -> 0
F96: BOND RATE | H96: 0 | J96: 0 | L96: 0 | N96: 0 | P96: 0 | R96: 0
F97: BOND AMOUNT | I97: =H96*I95 -> 0 | K97: =J96*K95 -> 0 | M97: =L96*M95 -> 0 | O97: =N96*O95 -> 0 | Q97: =P96*Q95 -> 0 | S97: =R96*S95 -> 0
F99: ADJUSTED TOTAL | I99: =SUM(I95:I97) -> 50969 | K99: =SUM(K95:K97) -> 0 | M99: =SUM(M95:M97) -> 0 | O99: =SUM(O95:O97) -> 0 | Q99: =SUM(Q95:Q97) -> 0 | S99: =SUM(S95:S97) -> 0
F100: Cost per SF | I100: =I99/'[1]Area Calculations'!$G$4 -> #DIV/0! | K100: =K99/'[1]Area Calculations'!$G$4 -> #VALUE! | M100: =M99/'[1]Area Calculations'!$G$4 -> #VALUE! | O100: =O99/'[1]Area Calculations'!$G$4 -> #VALUE! | Q100: =Q99/'[1]Area Calculations'!$G$4 -> #VALUE! | R100: =R99/'[1]Area Calculations'!$G$4 -> #VALUE! | S100: =S99/'[1]Cost Summary'!#REF! -> #REF!
F101: Cost per Unit | I101: =I99/'[1]Area Calculations'!$G$9 -> #DIV/0! | K101: =K99/'[1]Area Calculations'!$G$9 -> #VALUE! | M101: =M99/'[1]Area Calculations'!$G$9 -> #VALUE! | O101: =O99/'[1]Area Calculations'!$G$9 -> #VALUE! | Q101: =Q99/'[1]Area Calculations'!$G$9 -> #VALUE! | R101: =R99/'[1]Area Calculations'!$G$9 -> #VALUE! | S101: =S99/'[1]Cost Summary'!#REF! -> #REF!
A103: QUALIFICATIONS
A107: EXCLUSIONS/OWNER PROVIDED ITEMS:
A111: ALTERNATES:
A115: PROPOSED VE (Provide Clear Description):
A119: FULLY LOADED LABOR RATES
B120: Laborer
B121: Mechanic
B122: Superintendent
B123: Project Manager
A125: SCHEDULE
B126: Prepared shop drawings/submittals
B127: Mobilization
B128: Total duration to complete scope of work
A130: Winner
A131: Company | B131: =H4 -> HB Construction
A132: Contact | B132: =H5 -> Butch Carmichael
A133: Phone | B133: =H6 -> 561-225-4868
A134: Email | B134: =H7 -> <bcarmichael@hedrickbrothers.com>
A135: Base Bid | B135: =H8 -> 50969
B137: Need Prequalification
B138: Prequalified

Sheet Cost Summary (2)
A1: COST ESTIMATE (ROM)
A6: ='Area Calculations'!B4 -> The Club at Ibis Conceptual Estimate
A7: ='Area Calculations'!B5 -> West Palm Beach, FL | E7: Gross (sf) | F7: =J7+N7+R7+W7+Y7+AA7+AE7+AC7 -> 149933 | I7: Gross (sf) | J7: 663 | M7: Gross (sf) | N7: 11678 | Q7: Gross (sf) | R7: =5262+1663+4300 -> 11225 | W7: 91377 | Y7: 8946 | AA7: =5824+223 -> 6047 | AC7: =3436+1206 -> 4642 | AE7: =8101+7254 -> 15355
E8: Build Duration (months) | F8: ='GCs & GRs'!$L$4+'GCs & GRs'!$L$5 -> 29.4 | I8: Build Duration (months) | J8: 10 | M8: Build Duration (months) | N8: 14 | Q8: Build Duration (months) | R8: 12 | W8: 7 | Y8: 5 | AA8: 5 | AC8: 7 | AE8: 7
A9: =NOW() -> 46146.222 | E9: Acres | F9: =J9+N9+R9+W9+Y9+AA9+AE9+AC9 -> 9.77 | I9: Acres | J9: 3.49 | M9: Acres | N9: 2.14 | Q9: Acres | R9: 0.96 | W9: 1.57 | Y9: 0.25 | AA9: 0.17 | AC9: 0.88 | AE9: 0.31
A11: CSI | B11: CSI DESCRIPTION | D11: GRAND TOTAL | E11: $ /GSF | F11: % | H11: Phase 1B Racquet Courts | I11: $ /GSF | J11: % | L11: Phase 2 New Spa Building | M11: $ /GSF | N11: % | P11: Phase 2A New Fitness Build. + Pav. | Q11: $ /GSF | R11: % | T11: Verif | U11: Delta | W11: Phase 1A Interior Club House Renos | Y11: Phase 2 Bocce& Basketball | AA11: Phase 2 POA building | AC11: Phase 3 19th Hole Restaurant | AE11: Phase 3 Reno Existing Fitness Building | AG11: Prev. | AI11: Delta | AK11: Notes
A13: 01A | B13: Surveying | D13: ='Cost Summary'!D13*($D$85+1) -> 61417.558 | H13: ='Cost Summary'!H13*(1+$H$85) -> 16136.035 | L13: ='Cost Summary'!L13*(1+$L$85) -> 32960.02 | M13: =L13/$N$7 -> 2.8224028 | N13: =L13/$L$76 -> 0.0034984029 | P13: ='Cost Summary'!P13*(1+$P$85) -> 12321.503 | Q13: =P13/$R$7 -> 1.097684 | R13: =P13/$P$76 -> 0.001875447 | T13: =H13+L13+P13+W13+Y13+AA13+AC13+AE13 -> 61417.558 | U13: =D13-T13 -> 0 | AI13: =D13-AG13 -> 61417.558
A14: 01B | B14: Materials Testing | C14: By Owner
A15: 02A | B15: Demolition | D15: ='Cost Summary'!D15*($D$85+1) -> 40301.583 | H15: ='Cost Summary'!H15*(1+$H$85) -> 10267.919 | L15: ='Cost Summary'!L15*(1+$L$85) -> 0 | M15: =L15/$N$7 -> 0 | N15: =L15/$L$76 -> 0 | P15: ='Cost Summary'!P15*(1+$P$85) -> 30033.663 | Q15: =P15/$R$7 -> 2.6756048 | R15: =P15/$P$76 -> 0.004571402 | T15: =H15+L15+P15+W15+Y15+AA15+AC15+AE15 -> 40301.583 | U15: =D15-T15 -> 0 | AI15: =D15-AG15 -> 40301.583
A16: 03A | B16: Concrete / CMU | D16: ='Cost Summary'!D16*($D$85+1) -> 1796291.3 | H16: ='Cost Summary'!H16*(1+$H$85) -> 153115.21 | L16: ='Cost Summary'!L16*(1+$L$85) -> 803388.69 | M16: =L16/$N$7 -> 68.795058 | N16: =L16/$L$76 -> 0.085272317 | P16: ='Cost Summary'!P16*(1+$P$85) -> 839787.43 | Q16: =P16/$R$7 -> 74.814025 | R16: =P16/$P$76 -> 0.12782343 | T16: =H16+L16+P16+W16+Y16+AA16+AC16+AE16 -> 1796291.3 | U16: =D16-T16 -> 0 | AI16: =D16-AG16 -> 1796291.3
A17: 05A | B17: Structural Steel | D17: ='Cost Summary'!D17*($D$85+1) -> 640995.28 | H17: ='Cost Summary'!H17*(1+$H$85) -> 304649.16 | L17: ='Cost Summary'!L17*(1+$L$85) -> 296006.04 | M17: =L17/$N$7 -> 25.347323 | N17: =L17/$L$76 -> 0.031418317 | P17: ='Cost Summary'!P17*(1+$P$85) -> 40340.087 | Q17: =P17/$R$7 -> 3.5937717 | R17: =P17/$P$76 -> 0.0061401353 | T17: =H17+L17+P17+W17+Y17+AA17+AC17+AE17 -> 640995.28 | U17: =D17-T17 -> 0 | AI17: =D17-AG17 -> 640995.28
A18: 05C | B18: Misc. Metals | D18: ='Cost Summary'!D18*($D$85+1) -> 108734.7 | H18: ='Cost Summary'!H18*(1+$H$85) -> 1361.5261 | L18: ='Cost Summary'!L18*(1+$L$85) -> 93478.109 | M18: =L18/$N$7 -> 8.0046334 | N18: =L18/$L$76 -> 0.0099218411 | P18: ='Cost Summary'!P18*(1+$P$85) -> 13895.062 | Q18: =P18/$R$7 -> 1.2378674 | R18: =P18/$P$76 -> 0.0021149572 | T18: =H18+L18+P18+W18+Y18+AA18+AC18+AE18 -> 108734.7 | U18: =D18-T18 -> 0 | AI18: =D18-AG18 -> 108734.7
A19: 06A | B19: Rough Carpentry | D19: ='Cost Summary'!D19*($D$85+1) -> 357903.73 | H19: ='Cost Summary'!H19*(1+$H$85) -> 7413.3809 | L19: ='Cost Summary'!L19*(1+$L$85) -> 179577.92 | M19: =L19/$N$7 -> 15.377455 | N19: =L19/$L$76 -> 0.019060544 | P19: ='Cost Summary'!P19*(1+$P$85) -> 170912.43 | Q19: =P19/$R$7 -> 15.226051 | R19: =P19/$P$76 -> 0.026014456 | T19: =H19+L19+P19+W19+Y19+AA19+AC19+AE19 -> 357903.73 | U19: =D19-T19 -> 0 | AI19: =D19-AG19 -> 357903.73
A20: 06C | B20: Wood Trusses | D20: ='Cost Summary'!D20*($D$85+1) -> 42694.008 | H20: ='Cost Summary'!H20*(1+$H$85) -> 7360.0444 | L20: ='Cost Summary'!L20*(1+$L$85) -> 0 | M20: =L20/$N$7 -> 0 | N20: =L20/$L$76 -> 0 | P20: ='Cost Summary'!P20*(1+$P$85) -> 35333.963 | Q20: =P20/$R$7 -> 3.1477918 | R20: =P20/$P$76 -> 0.0053781568 | T20: =H20+L20+P20+W20+Y20+AA20+AC20+AE20 -> 42694.008 | U20: =D20-T20 -> 0 | AI20: =D20-AG20 -> 42694.008
A21: 06F | B21: Millwork | D21: ='Cost Summary'!D21*($D$85+1) -> 518139.73 | H21: ='Cost Summary'!H21*(1+$H$85) -> 15044.555 | L21: ='Cost Summary'!L21*(1+$L$85) -> 437483.18 | M21: =L21/$N$7 -> 37.462166 | N21: =L21/$L$76 -> 0.046434814 | P21: ='Cost Summary'!P21*(1+$P$85) -> 65612.003 | Q21: =P21/$R$7 -> 5.8451673 | R21: =P21/$P$76 -> 0.0099867552 | T21: =H21+L21+P21+W21+Y21+AA21+AC21+AE21 -> 518139.73 | U21: =D21-T21 -> 0 | AI21: =D21-AG21 -> 518139.73
A22: 07D | B22: Roofing | D22: ='Cost Summary'!D22*($D$85+1) -> 527810.06 | H22: ='Cost Summary'!H22*(1+$H$85) -> 23131.568 | L22: ='Cost Summary'!L22*(1+$L$85) -> 357364.66 | M22: =L22/$N$7 -> 30.601529 | N22: =L22/$L$76 -> 0.03793097 | P22: ='Cost Summary'!P22*(1+$P$85) -> 147313.84 | Q22: =P22/$R$7 -> 13.123727 | R22: =P22/$P$76 -> 0.022422532 | T22: =H22+L22+P22+W22+Y22+AA22+AC22+AE22 -> 527810.06 | U22: =D22-T22 -> 0 | AI22: =D22-AG22 -> 527810.06
A23: 07E | B23: Caulking & Waterproofing | D23: ='Cost Summary'!D23*($D$85+1) -> 91072.032 | H23: ='Cost Summary'!H23*(1+$H$85) -> 1701.9076 | L23: ='Cost Summary'!L23*(1+$L$85) -> 49030.038 | M23: =L23/$N$7 -> 4.1984961 | N23: =L23/$L$76 -> 0.0052040874 | P23: ='Cost Summary'!P23*(1+$P$85) -> 40340.087 | Q23: =P23/$R$7 -> 3.5937717 | R23: =P23/$P$76 -> 0.0061401353 | T23: =H23+L23+P23+W23+Y23+AA23+AC23+AE23 -> 91072.032 | U23: =D23-T23 -> 0 | AI23: =D23-AG23 -> 91072.032
A24: 07H | B24: Panelized Exterior Skin | D24: ='Cost Summary'!D24*($D$85+1) -> 232868.14 | H24: ='Cost Summary'!H24*(1+$H$85) -> 0 | L24: ='Cost Summary'!L24*(1+$L$85) -> 232868.14 | M24: =L24/$N$7 -> 19.940755 | N24: =L24/$L$76 -> 0.02471681 | P24: ='Cost Summary'!P24*(1+$P$85) -> 0 | Q24: =P24/$R$7 -> 0 | R24: =P24/$P$76 -> 0 | T24: =H24+L24+P24+W24+Y24+AA24+AC24+AE24 -> 232868.14 | U24: =D24-T24 -> 0 | AI24: =D24-AG24 -> 232868.14
A25: 08A | B25: Doors, Frames, & Hardware | D25: ='Cost Summary'!D25*($D$85+1) -> 170190.76 | H25: ='Cost Summary'!H25*(1+$H$85) -> 3593.7717 | L25: ='Cost Summary'!L25*(1+$L$85) -> 125268.61 | M25: =L25/$N$7 -> 10.726889 | N25: =L25/$L$76 -> 0.013296111 | P25: ='Cost Summary'!P25*(1+$P$85) -> 41328.374 | Q25: =P25/$R$7 -> 3.6818151 | R25: =P25/$P$76 -> 0.0062905618 | T25: =H25+L25+P25+W25+Y25+AA25+AC25+AE25 -> 170190.76 | U25: =D25-T25 -> 0 | AI25: =D25-AG25 -> 170190.76
A26: 08C | B26: Glass and Glazing | D26: ='Cost Summary'!D26*($D$85+1) -> 522770.57 | H26: ='Cost Summary'!H26*(1+$H$85) -> 0 | L26: ='Cost Summary'!L26*(1+$L$85) -> 147488.39 | M26: =L26/$N$7 -> 12.629593 | N26: =L26/$L$76 -> 0.015654536 | P26: ='Cost Summary'!P26*(1+$P$85) -> 375282.18 | Q26: =P26/$R$7 -> 33.432711 | R26: =P26/$P$76 -> 0.057121427 | T26: =H26+L26+P26+W26+Y26+AA26+AC26+AE26 -> 522770.57 | U26: =D26-T26 -> 0 | AI26: =D26-AG26 -> 522770.57
... A41: 13B | B41: Swimming Pools | D41: ='Cost Summary'!D41*($D$85+1) -> 452969.25 | H41: ='Cost Summary'!H41*(1+$H$85) -> 0 | L41: ='Cost Summary'!L41*(1+$L$85) -> 452969.25 | M41: =L41/$N$7 -> 38.788256 | N41: =L41/$L$76 -> 0.048078518 | P41: ='Cost Summary'!P41*(1+$P$85) -> 0 | Q41: =P41/$R$7 -> 0 | R41: =P41/$P$76 -> 0 | T41: =H41+L41+P41+W41+Y41+AA41+AC41+AE41 -> 452969.25 | U41: =D41-T41 -> 0 | AI41: =D41-AG41 -> 452969.25
A42: 13C | B42: Covered Structures | D42: ='Cost Summary'!D42*($D$85+1) -> 303073.03 | H42: ='Cost Summary'!H42*(1+$H$85) -> 303073.03 | L42: ='Cost Summary'!L42*(1+$L$85) -> 0 | M42: =L42/$N$7 -> 0 | N42: =L42/$L$76 -> 0 | P42: ='Cost Summary'!P42*(1+$P$85) -> 0 | T42: =H42+L42+P42+W42+Y42+AA42+AC42+AE42 -> 303073.03 | U42: =D42-T42 -> 0
A43: 14A | B43: Elevators | D43: ='Cost Summary'!D43*($D$85+1) -> 133482.95 | H43: ='Cost Summary'!H43*(1+$H$85) -> 0 | L43: ='Cost Summary'!L43*(1+$L$85) -> 0 | M43: =L43/$N$7 -> 0 | N43: =L43/$L$76 -> 0 | P43: ='Cost Summary'!P43*(1+$P$85) -> 133482.95 | Q43: =P43/$R$7 -> 11.891577 | R43: =P43/$P$76 -> 0.020317342 | T43: =H43+L43+P43+W43+Y43+AA43+AC43+AE43 -> 133482.95 | U43: =D43-T43 -> 0 | AI43: =D43-AG43 -> 133482.95
A44: 21A | B44: Fire Sprinkler | D44: ='Cost Summary'!D44*($D$85+1) -> 85711.968 | H44: ='Cost Summary'!H44*(1+$H$85) -> 3403.8152 | L44: ='Cost Summary'!L44*(1+$L$85) -> 41968.066 | M44: =L44/$N$7 -> 3.5937717 | N44: =L44/$L$76 -> 0.004454524 | P44: ='Cost Summary'!P44*(1+$P$85) -> 40340.087 | Q44: =P44/$R$7 -> 3.5937717 | R44: =P44/$P$76 -> 0.0061401353 | T44: =H44+L44+P44+W44+Y44+AA44+AC44+AE44 -> 85711.968 | U44: =D44-T44 -> 0 | AI44: =D44-AG44 -> 85711.968
A45: 22A | B45: Plumbing | D45: ='Cost Summary'!D45*($D$85+1) -> 545226.51 | H45: ='Cost Summary'!H45*(1+$H$85) -> 35937.717 | L45: ='Cost Summary'!L45*(1+$L$85) -> 338841.33 | M45: =L45/$N$7 -> 29.015356 | N45: =L45/$L$76 -> 0.03596489 | P45: ='Cost Summary'!P45*(1+$P$85) -> 170447.46 | Q45: =P45/$R$7 -> 15.184629 | R45: =P45/$P$76 -> 0.025943683 | T45: =H45+L45+P45+W45+Y45+AA45+AC45+AE45 -> 545226.51 | U45: =D45-T45 -> 0 | AI45: =D45-AG45 -> 545226.51
A46: 23A | B46: HVAC | D46: ='Cost Summary'!D46*($D$85+1) -> 1600768.6 | H46: ='Cost Summary'!H46*(1+$H$85) -> 43125.26 | L46: ='Cost Summary'!L46*(1+$L$85) -> 1117149.6 | M46: =L46/$N$7 -> 95.66275 | N46: =L46/$L$76 -> 0.11857515 | P46: ='Cost Summary'!P46*(1+$P$85) -> 440493.73 | Q46: =P46/$R$7 -> 39.242203 | R46: =P46/$P$76 -> 0.06704723 | T46: =H46+L46+P46+W46+Y46+AA46+AC46+AE46 -> 1600768.6 | U46: =D46-T46 -> 0 | AI46: =D46-AG46 -> 1600768.6
A47: 26A | B47: Electrical & Fire Alarm | D47: ='Cost Summary'!D47*($D$85+1) -> 1730944.9 | H47: ='Cost Summary'!H47*(1+$H$85) -> 285054.76 | L47: ='Cost Summary'!L47*(1+$L$85) -> 743018.2 | M47: =L47/$N$7 -> 63.625467 | N47: =L47/$L$76 -> 0.078864545 | P47: ='Cost Summary'!P47*(1+$P$85) -> 702871.92 | Q47: =P47/$R$7 -> 62.616652 | R47: =P47/$P$76 -> 0.10698362 | T47: =H47+L47+P47+W47+Y47+AA47+AC47+AE47 -> 1730944.9 | U47: =D47-T47 -> 0 | AI47: =D47-AG47 -> 1730944.9
A48: 28A | B48: Low Voltage - Conduits included in Electrical | D48: ='Cost Summary'!D48*($D$85+1) -> 245784.72 | H48: ='Cost Summary'!H48*(1+$H$85) -> 19189.714 | L48: ='Cost Summary'!L48*(1+$L$85) -> 98772.248 | M48: =L48/$N$7 -> 8.4579764 | N48: =L48/$L$76 -> 0.010483765 | P48: ='Cost Summary'!P48*(1+$P$85) -> 127822.76 | Q48: =P48/$R$7 -> 11.387328 | R48: =P48/$P$76 -> 0.019455809 | T48: =H48+L48+P48+W48+Y48+AA48+AC48+AE48 -> 245784.72 | U48: =D48-T48 -> 0 | AI48: =D48-AG48 -> 245784.72
A49: 31A | B49: Sitework | D49: ='Cost Summary'!D49*($D$85+1) -> 2138400.9 | H49: ='Cost Summary'!H49*(1+$H$85) -> 1168780.8 | L49: ='Cost Summary'!L49*(1+$L$85) -> 564735.55 | M49: =L49/$N$7 -> 48.358927 | N49: =L49/$L$76 -> 0.059941483 | P49: ='Cost Summary'!P49*(1+$P$85) -> 404884.59 | Q49: =P49/$R$7 -> 36.069896 | R49: =P49/$P$76 -> 0.061627188 | T49: =H49+L49+P49+W49+Y49+AA49+AC49+AE49 -> 2138400.9 | U49: =D49-T49 -> 0 | AI49: =D49-AG49 -> 2138400.9
A50: 32A | B50: Pavers | D50: ='Cost Summary'!D50*($D$85+1) -> 289576.88 | H50: ='Cost Summary'!H50*(1+$H$85) -> 173204.39 | L50: ='Cost Summary'!L50*(1+$L$85) -> 67702.551 | M50: =L50/$N$7 -> 5.797444 | N50: =L50/$L$76 -> 0.0071860029 | P50: ='Cost Summary'!P50*(1+$P$85) -> 48669.937 | Q50: =P50/$R$7 -> 4.3358518 | R50: =P50/$P$76 -> 0.0074080156 | T50: =H50+L50+P50+W50+Y50+AA50+AC50+AE50 -> 289576.88 | U50: =D50-T50 -> 0 | AI50: =D50-AG50 -> 289576.88
A51: 32B | B51: Site Furnishings | C51: By Owner | AI51: =D51-AG51 -> 0
A52: 32C | B52: Landscape and Irrigation | D52: ='Cost Summary'!D52*($D$85+1) -> 502614.64 | H52: ='Cost Summary'!H52*(1+$H$85) -> 189443.11 | L52: ='Cost Summary'!L52*(1+$L$85) -> 164800.1 | M52: =L52/$N$7 -> 14.112014 | N52: =L52/$L$76 -> 0.017492014 | P52: ='Cost Summary'!P52*(1+$P$85) -> 148371.43 | Q52: =P52/$R$7 -> 13.217945 | R52: =P52/$P$76 -> 0.022583508 | T52: =H52+L52+P52+W52+Y52+AA52+AC52+AE52 -> 502614.64 | U52: =D52-T52 -> 0 | AI52: =D52-AG52 -> 502614.64
A53: 32D | B53: Fencing | D53: ='Cost Summary'!D53*($D$85+1) -> 74006.027 | H53: ='Cost Summary'!H53*(1+$H$85) -> 74006.027 | L53: ='Cost Summary'!L53*(1+$L$85) -> 0 | M53: =L53/$N$7 -> 0 | N53: =L53/$L$76 -> 0 | P53: ='Cost Summary'!P53*(1+$P$85) -> 0 | Q53: =P53/$R$7 -> 0 | R53: =P53/$P$76 -> 0 | T53: =H53+L53+P53+W53+Y53+AA53+AC53+AE53 -> 74006.027 | U53: =D53-T53 -> 0 | AI53: =D53-AG53 -> 74006.027
A54: 32E | B54: Synthetic Fields | D54: ='Cost Summary'!D54*($D$85+1) -> 3029036.1 | H54: ='Cost Summary'!H54*(1+$H$85) -> 3029036.1 | L54: ='Cost Summary'!L54*(1+$L$85) -> 0 | M54: =L54/$N$7 -> 0 | N54: =L54/$L$76 -> 0 | P54: ='Cost Summary'!P54*(1+$P$85) -> 0 | Q54: =P54/$R$7 -> 0 | R54: =P54/$P$76 -> 0 | T54: =H54+L54+P54+W54+Y54+AA54+AC54+AE54 -> 3029036.1 | U54: =D54-T54 -> 0 | AI54: =D54-AG54 -> 3029036.1
B55: Phase 1 Interior Clubhouse Renovations | D55: ='Cost Summary'!D55*($D$85+1) -> 157481.43 | T55: =H55+L55+P55+W55+Y55+AA55+AC55+AE55 -> 157481.43 | U55: =D55-T55 -> 0 | W55: ='Cost Summary'!W55*(1+$W$85) -> 157481.43
B56: Phase 2 Bocce & Basketball | D56: ='Cost Summary'!D56*($D$85+1) -> 1653555 | T56: =H56+L56+P56+W56+Y56+AA56+AC56+AE56 -> 1653555 | U56: =D56-T56 -> 0 | X56: 14901.05 | Y56: ='Cost Summary'!Y56*(1+$Y$85) -> 1653555
B57: Phase 2 POA | D57: ='Cost Summary'!D57*($D$85+1) -> 1968517.9 | T57: =H57+L57+P57+W57+Y57+AA57+AC57+AE57 -> 1968517.9 | U57: =D57-T57 -> 0 | AA57: ='Cost Summary'!AA57*(1+$AA$85) -> 1968517.9
B58: Phase 3 19th Hole | D58: ='Cost Summary'!D58*($D$85+1) -> 1968517.9 | T58: =H58+L58+P58+W58+Y58+AA58+AC58+AE58 -> 1968517.9 | U58: =D58-T58 -> 0 | AC58: ='Cost Summary'!AC58*(1+$AC$85) -> 1968517.9
B59: Phase 3 Existing Fitness Building | D59: ='Cost Summary'!D59*($D$85+1) -> 1811036.4 | T59: =H59+L59+P59+W59+Y59+AA59+AC59+AE59 -> 1811036.4 | U59: =D59-T59 -> 0 | AE59: ='Cost Summary'!AE59*(1+$AE$85) -> 1811036.4
B60: SUB-TOTAL 1 (Cost of Work)Building | D60: =SUM(D13:D59) -> 26101552 | E60: =D60/F7 -> 174.0881 | F60: =D60/$D$76 -> 0.78740721 | H60: =SUM(H13:H54) -> 5950738.8 | L60: =SUM(L13:L54) -> 7418516 | M60: =SUM(M13:M59) -> 635.25569 | N60: =SUM(N13:N54) -> 0.78740721 | P60: =SUM(P13:P54) -> 5173188.2 | Q60: =SUM(Q13:Q54) -> 460.86309 | R60: =SUM(R13:R54) -> 0.78740721 | T60: =H60+L60+P60+W60+Y60+AA60+AC60+AE60 -> 26101552 | U60: =D60-T60 -> 0 | W60: =SUM(W13:W59) -> 157481.43 | Y60: =SUM(Y13:Y59) -> 1653555 | AA60: =SUM(AA13:AA59) -> 1968517.9 | AC60: =SUM(AC13:AC59) -> 1968517.9 | AE60: =SUM(AE13:AE59) -> 1811036.4 | AG60: =SUM(AG13:AG54) -> 0 | AI60: =D60-AG60 -> 26101552
C61: GC Contingency | D61: =$D$60*AL61 -> 652538.79 | E61: =D61/$F$7 -> 4.3522026 | F61: =D61/$D$76 -> 0.01968518 | H61: =$H$60*$AL$61 -> 148768.47 | L61: =$L$60*$AL$61 -> 185462.9 | M61: =L61/$N$7 -> 15.881392 | N61: =L61/$L$76 -> 0.01968518 | P61: =$P$60*$AL$61 -> 129329.71 | Q61: =P61/$R$7 -> 11.521577 | R61: =P61/$P$76 -> 0.01968518 | T61: =H61+L61+P61+W61+Y61+AA61+AC61+AE61 -> 652538.79 | U61: =D61-T61 -> 0 | W61: =W60*$AL$61 -> 3937.0357 | Y61: =Y60*$AL$61 -> 41338.875 | AA61: =AA60*$AL$61 -> 49212.947 | AC61: =AC60*$AL$61 -> 49212.947 | AE61: =AE60*$AL$61 -> 45275.911 | AI61: =D61-AG61 -> 652538.79 | AL61: ='Cost Summary'!AL61 -> 0.025
C62: Owner Contingency | D62: By owner | AL62: ='Cost Summary'!AL62 -> 0
C63: Escalation Contingency | D63: =$D$60*AL63 -> 652538.79 | E63: =D63/$F$7 -> 4.3522026 | F63: =D63/$D$76 -> 0.01968518 | H63: =$H$60*$AL$63 -> 148768.47 | L63: =$L$60*$AL$63 -> 185462.9 | M63: =L63/$N$7 -> 15.881392 | N63: =L63/$L$76 -> 0.01968518 | P63: =$P$60*$AL$63 -> 129329.71 | Q63: =P63/$R$7 -> 11.521577 | R63: =P63/$P$76 -> 0.01968518 | T63: =H63+L63+P63+W63+Y63+AA63+AC63+AE63 -> 652538.79 | U63: =D63-T63 -> 0 | W63: =W60*$AL$63 -> 3937.0357 | Y63: =Y60*$AL$63 -> 41338.875 | AA63: =AA60*$AL$63 -> 49212.947 | AC63: =AC60*$AL$63 -> 49212.947 | AE63: =AE60*$AL$63 -> 45275.911 | AI63: =D63-AG63 -> 652538.79 | AL63: ='Cost Summary'!AL63 -> 0.025
B64: SUB-TOTAL 2 (Contingency) | D64: =SUM(D60:D63) -> 27406629 | E64: =SUM(E60:E63) -> 182.79251 | F64: =SUM(F60:F63) -> 0.82677757 | H64: =SUM(H60:H63) -> 6248275.7 | L64: =SUM(L60:L63) -> 7789441.8 | M64: =SUM(M60:M63) -> 667.01848 | N64: =SUM(N60:N63) -> 0.82677757 | P64: =SUM(P60:P63) -> 5431847.6 | Q64: =SUM(Q60:Q63) -> 483.90625 | R64: =SUM(R60:R63) -> 0.82677757 | T64: =H64+L64+P64+W64+Y64+AA64+AC64+AE64 -> 27406629 | U64: =D64-T64 -> 0 | W64: =SUM(W60:W63) -> 165355.5 | Y64: =SUM(Y60:Y63) -> 1736232.8 | AA64: =SUM(AA60:AA63) -> 2066943.8 | AC64: =SUM(AC60:AC63) -> 2066943.8 | AE64: =SUM(AE60:AE63) -> 1901588.3 | AG64: =SUM(AG60:AG63) -> 0 | AI64: =SUM(AI60:AI63) -> 27406629
C65: General Conditions | D65: ='GCs & GRs'!L160 -> 2991138.4 | E65: =D65/$F$7 -> 19.949834 | F65: =D65/$D$76 -> 0.090233869 | H65: =H64/$D$64*$D$65 -> 681932.01 | L65: =L64/$D$64*$D$65 -> 850133.69 | M65: =L65/$N$7 -> 72.797884 | N65: =L65/$L$76 -> 0.090233869 | P65: =P64/$D$64*$D$65 -> 592827.68 | Q65: =P65/$R$7 -> 52.813156 | R65: =P65/$P$76 -> 0.090233869 | T65: =H65+L65+P65+W65+Y65+AA65+AC65+AE65 -> 2991138.4 | U65: =D65-T65 -> 0 | W65: =W64/$D$64*$D$65 -> 18046.772 | Y65: =Y64/$D$64*$D$65 -> 189491.11 | AA65: =AA64/$D$64*$D$65 -> 225584.65 | AC65: =AC64/$D$64*$D$65 -> 225584.65 | AE65: =AE64/$D$64*$D$65 -> 207537.88 | AI65: =D65-AG65 -> 2991138.4 | AL65: ='Cost Summary'!AL65 -> 0.090233869
C66: General Requirements | D66: ='GCs & GRs'!L161 -> 705899.49 | E66: =D66/$F$7 -> 4.7080996 | F66: =D66/$D$76 -> 0.021294916 | H66: =H64/$D$64*$D$66 -> 160933.86 | L66: =L64/$D$64*$D$66 -> 200628.94 | M66: =L66/$N$7 -> 17.180077 | N66: =L66/$L$76 -> 0.021294916 | P66: =P64/$D$64*$D$66 -> 139905.51 | Q66: =P66/$R$7 -> 12.463743 | R66: =P66/$P$76 -> 0.021294916 | T66: =H66+L66+P66+W66+Y66+AA66+AC66+AE66 -> 705899.49 | U66: =D66-T66 -> 0 | W66: =W64/$D$64*$D$66 -> 4258.9829 | Y66: =Y64/$D$64*$D$66 -> 44719.32 | AA66: =AA64/$D$64*$D$66 -> 53237.286 | AC66: =AC64/$D$64*$D$66 -> 53237.286 | AE66: =AE64/$D$64*$D$66 -> 48978.303 | AI66: =D66-AG66 -> 705899.49 | AL66: ='Cost Summary'!AL66 -> 0.021294916
C67: Innovation & Digital Services (IDS)
C68: Builders Risk Insurance & Deductibles | D68: By owner
C69: Subcontractor Default Insurance | AI69: =D69-AG69 -> 0 | AL69: ='Cost Summary'!AL69 -> 0.015
B70: Procore | AI70: =D70-AG70 -> 0 | AL70: ='Cost Summary'!AL70 -> 0.0025
C71: Warranty | AL71: ='Cost Summary'!AL71 -> 0.006
B72: General Liability Insurance | C72: General Liability Insurance | D72: ='Cost Summary'!D72 -> 466555.01 | E72: ='Cost Summary'!E72 -> 3.3055952 | F72: ='Cost Summary'!F72 -> 0.014074595 | H72: ='Cost Summary'!H72 -> 106367.12 | L72: ='Cost Summary'!L72 -> 132603.07 | M72: ='Cost Summary'!M72 -> 11.354947 | N72: ='Cost Summary'!N72 -> 0.014074595 | P72: ='Cost Summary'!P72 -> 92468.712 | Q72: ='Cost Summary'!Q72 -> 8.2377472 | R72: ='Cost Summary'!R72 -> 0.014074595 | W72: ='Cost Summary'!W72 -> 2814.9189 | Y72: ='Cost Summary'!Y72 -> 29556.648 | AA72: ='Cost Summary'!AA72 -> 35186.486 | AC72: ='Cost Summary'!AC72 -> 35186.486 | AE72: ='Cost Summary'!AE72 -> 32371.567 | AI72: =D72-AG72 -> 466555.01 | AL72: ='Cost Summary'!AL72 -> 0.015
B73: SUB-TOTAL 3 (Bonds, Insurances, & GC's) | D73: =SUM(D64:D72) -> 31570222 | E73: =SUM(E64:E72) -> 210.75604 | F73: =SUM(F64:F72) -> 0.95238095 | H73: =SUM(H64:H72) -> 7197508.7 | L73: =SUM(L64:L72) -> 8972807.5 | M73: =SUM(M64:M72) -> 768.35138 | N73: =SUM(N64:N72) -> 0.95238095 | P73: =SUM(P64:P72) -> 6257049.5 | Q73: =SUM(Q64:Q72) -> 557.42089 | R73: =SUM(R64:R72) -> 0.95238095 | T73: =H73+L73+P73+W73+Y73+AA73+AC73+AE73 -> 31570222 | U73: =D73-T73 -> 0 | W73: =SUM(W64:W72) -> 190476.17 | Y73: =SUM(Y64:Y72) -> 1999999.8 | AA73: =SUM(AA64:AA72) -> 2380952.2 | AC73: =SUM(AC64:AC72) -> 2380952.2 | AE73: =SUM(AE64:AE72) -> 2190476 | AG73: =SUM(AG64:AG72) -> 0 | AI73: =SUM(AI64:AI72) -> 31570222
C74: Overhead | D74: =D73*$AL$74 -> 947106.66 | E74: =D74/$F$7 -> 6.316866 | F74: =D74/$D$76 -> 0.028571429 | H74: =H73*$AL$74 -> 215925.26 | L74: =L73*$AL$74 -> 269184.22 | M74: =L74/$N$7 -> 23.050542 | N74: =L74/$L$76 -> 0.028571429 | P74: =P73*$AL$74 -> 187711.49 | Q74: =P74/$R$7 -> 16.722627 | R74: =P74/$P$76 -> 0.028571429 | T74: =H74+L74+P74+W74+Y74+AA74+AC74+AE74 -> 947106.66 | U74: =D74-T74 -> 0 | W74: =W73*$AL$74 -> 5714.2852 | Y74: =Y73*$AL$74 -> 59999.995 | AA74: =AA73*$AL$74 -> 71428.566 | AC74: =AC73*$AL$74 -> 71428.566 | AE74: =AE73*$AL$74 -> 65714.28 | AI74: =D74-AG74 -> 947106.66 | AL74: ='Cost Summary'!$AL$74 -> 0.03
C75: Contractor's Fee | D75: =D73*$AL$75 -> 631404.44 | E75: =D75/$F$7 -> 4.211244 | F75: =D75/$D$76 -> 0.019047619 | H75: =H73*$AL$75 -> 143950.17 | L75: =L73*$AL$75 -> 179456.15 | M75: =L75/$N$7 -> 15.367028 | N75: =L75/$L$76 -> 0.019047619 | P75: =P73*$AL$75 -> 125140.99 | Q75: =P75/$R$7 -> 11.148418 | R75: =P75/$P$76 -> 0.019047619 | T75: =H75+L75+P75+W75+Y75+AA75+AC75+AE75 -> 631404.44 | U75: =D75-T75 -> 0 | W75: =W73*$AL$75 -> 3809.5235 | Y75: =Y73*$AL$75 -> 39999.997 | AA75: =AA73*$AL$75 -> 47619.044 | AC75: =AC73*$AL$75 -> 47619.044 | AE75: =AE73*$AL$75 -> 43809.52 | AI75: =D75-AG75 -> 631404.44 | AL75: ='Cost Summary'!$AL$75 -> 0.02
B76: ESTIMATE TOTAL | D76: =SUM(D73:D75) -> 33148733 | E76: =SUM(E73:E74) -> 217.0729 | F76: =SUM(F73:F75) -> 1 | H76: =SUM(H73:H75) -> 7557384.2 | L76: =SUM(L73:L75) -> 9421447.8 | M76: =SUM(M73:M74) -> 791.40193 | N76: =SUM(N73:N75) -> 1 | P76: =SUM(P73:P75) -> 6569902 | Q76: =SUM(Q73:Q74) -> 574.14352 | R76: =SUM(R73:R75) -> 1 | T76: =H76+L76+P76+W76+Y76+AA76+AC76+AE76 -> 33148733 | U76: =D76-T76 -> 0 | W76: =SUM(W73:W75) -> 199999.98 | Y76: =SUM(Y73:Y75) -> 2099999.8 | AA76: =SUM(AA73:AA75) -> 2499999.8 | AC76: =SUM(AC73:AC75) -> 2499999.8 | AE76: =SUM(AE73:AE75) -> 2299999.8 | AG76: =SUM(AG73:AG74) -> 0 | AI76: =SUM(AI73:AI74) -> 32517329
B78: CONSTRUCTION CONCEPTUAL BUDGET RANGE | C78: CONSTRUCTION CONCEPTUAL BUDGET RANGE | D78: $31 - 35 Million
B79: From Original cost summary | D79: ='Cost Summary'!$D$76 -> 33148733 | H79: ='Cost Summary'!$H$76 -> 7557384.2 | L79: ='Cost Summary'!$L$76 -> 9421447.9 | P79: ='Cost Summary'!$P$76 -> 6569902 | T79: =H79+L79+P79+W79+Y79+AA79+AC79+AE79 -> 33148733 | U79: =D79-T79 -> 0 | W79: ='Cost Summary'!$W$76 -> 199999.98 | Y79: ='Cost Summary'!$Y$76 -> 2099999.8 | AA79: ='Cost Summary'!$AA$76 -> 2499999.8 | AC79: ='Cost Summary'!$AC$76 -> 2499999.8 | AE79: ='Cost Summary'!$AE$76 -> 2299999.8
B80: Delta | D80: =D76-D79 -> -0.11802612 | H80: =H76-H79 -> -0.02690808 | L80: =L76-L79 -> -0.033545082 | P80: =P76-P79 -> -0.023392145 | W80: =W76-W79 -> -0.00071210027 | Y80: =Y76-Y79 -> -0.0074770534 | AA80: =AA76-AA79 -> -0.0089012538 | AC80: =AC76-AC79 -> -0.0089012538 | AE80: =AE76-AE79 -> -0.0081891534
C82: Performance & Payment Bond | D82: =D76*$AL$82 -> 331487.33 | E82: =D82/$F$7 -> 2.2109031 | F82: =D82/$D$76 -> 0.01 | H82: =H76*$AL$82 -> 75573.842 | L82: =L76*$AL$82 -> 94214.478 | M82: =L82/$F$7 -> 0.6283772 | N82: =L82/$H$76 -> 0.012466546 | P82: =P76*$AL$82 -> 65699.02 | Q82: =P82/$R$7 -> 5.8529194 | R82: =P82/$H$76 -> 0.0086933545 | AL82: ='Cost Summary'!AL80 -> 0.01
D84: ='Cost Summary'!$D$82 -> 715116.76 | H84: ='Cost Summary'!$H$82 -> 163035.25 | L84: ='Cost Summary'!$L$82 -> 203248.65 | P84: ='Cost Summary'!$P$82 -> 141732.32 | W84: ='Cost Summary'!$W$82 -> 4314.5944 | Y84: ='Cost Summary'!$Y$82 -> 45303.241 | AA84: ='Cost Summary'!$AA$82 -> 53932.43 | AC84: ='Cost Summary'!$AC$82 -> 53932.43 | AE84: ='Cost Summary'!$AE$82 -> 49617.836
D85: ='Cost Summary'!$D$83+$D$86 -> 0.026791912 | H85: =$D$85 -> 0.026791912 | L85: =$D$85 -> 0.026791912 | P85: =$D$85 -> 0.026791912 | W85: ='Cost Summary'!$W$83+W86 -> 0.026791912 | Y85: ='Cost Summary'!$Y$83+Y86 -> 0.026791912 | AA85: ='Cost Summary'!$AA$83+AA86 -> 0.026791912 | AC85: ='Cost Summary'!$AC$83+AC86 -> 0.026791912 | AE85: ='Cost Summary'!$AE$83+AE86 -> 0.026791912
D86: -0.0013396 | W86: =$D$86 -> -0.0013396 | Y86: =$D$86 -> -0.0013396 | AA86: =$D$86 -> -0.0013396 | AC86: =$D$86 -> -0.0013396 | AE86: =$D$86 -> -0.0013396
D91: 2220594 | H91: 5300000 | L91: 10200000 | P91: 7600000 | W91: 200000 | Y91: 2100000 | AA91: 2500000 | AC91: 2500000 | AE91: 2300000
C92: GROSS MARGIN | M92: =L91/N7 -> 873.43723 | W92: 1.39571
C93: COST % | D93: COST $ | E93: BILLABLE | F93: MARGIN
B94: POTENTIAL BUYOUT SAVINGS | G94: 50/50 SPLIT OR LUMP SUM
B95: GENERAL CONDITIONS | D95: =D65*'Labor Rates Calculator'!I42 -> 2534863.1 | E95: =D65 -> 2991138.4 | F95: =E95-D95 -> 456275.36
B96: SDI | C96: 0.011 | D96: =C96*D64 -> 301472.92 | E96: =D60*1.5% -> 391523.27 | F96: =E96-D96 -> 90050.353
B97: GENERAL LIABILITY INSURANCE | C97: 0.011 | D97: =C97*D76 -> 364636.07 | E97: =D72 -> 466555.01 | F97: =E97-D97 -> 101918.94
B98: FEE | F98: =D74+D75 -> 1578511.1
E99: TOTAL | F99: =SUM(F94:F98) -> 2226755.8 | H99: =F99/D76 -> 0.067174686
B101: KEEP THIS TO ONE PAGE !!!!

Sheet Cost Summary
A1: COST ESTIMATE (ROM)
A6: ='Area Calculations'!B4 -> The Club at Ibis Conceptual Estimate
A7: ='Area Calculations'!B5 -> West Palm Beach, FL | E7: Gross (sf) | F7: =J7+N7+R7+W7+Y7+AA7+AE7+AC7 -> 141141 | I7: Gross (sf) | J7: 663 | M7: Gross (sf) | N7: 11678 | Q7: Gross (sf) | R7: =5262+1663+4300 -> 11225 | W7: 91377 | Y7: 0 | AA7: 6201 | AC7: =3436+1206 -> 4642 | AE7: =8101+7254 -> 15355
E8: Build Duration (months) | F8: ='GCs & GRs'!$L$4+'GCs & GRs'!$L$5 -> 29.4 | I8: Build Duration (months) | J8: 10 | M8: Build Duration (months) | N8: 14 | Q8: Build Duration (months) | R8: 12 | W8: 7 | Y8: 5 | AA8: 5 | AC8: 7 | AE8: 7
A9: =NOW() -> 46146.222 | E9: Acres | F9: =J9+N9+R9+W9+Y9+AA9+AE9+AC9 -> 9.77 | I9: Acres | J9: 3.49 | M9: Acres | N9: 2.14 | Q9: Acres | R9: 0.96 | W9: 1.57 | Y9: 0.25 | AA9: 0.17 | AC9: 0.88 | AE9: 0.31
A11: CSI | B11: CSI DESCRIPTION | D11: GRAND TOTAL | E11: $ /GSF | F11: % | H11: Phase 1B Racquet Courts | I11: $ /GSF | J11: % | L11: Phase 2 New Spa Building | M11: $ /GSF | N11: % | P11: Phase 2A New Fitness Build. + Pav. | Q11: $ /GSF | R11: % | T11: Verif | U11: Delta | W11: Phase 1A Interior Club House Renos | Y11: Phase 2 Bocce& Basketball | AA11: Phase 2 POA building | AC11: Phase 3 19th Hole Restaurant | AE11: Phase 3 Reno Existing Fitness Building | AG11: Prev. | AI11: Delta | AK11: Notes
A13: 01A | B13: Surveying | D13: ='01A Surveying'!B98 -> 59815 | H13: =SUM('01A Surveying'!$I$36:$I$39) -> 15715 | L13: =SUM('01A Surveying'!$I$42:$I$44) -> 32100 | M13: =L13/$N$7 -> 2.7487583 | N13: =L13/$L$76 -> 0.0034071196 | P13: =SUM('01A Surveying'!$I$47:$I$49) -> 12000 | Q13: =P13/$R$7 -> 1.0690423 | R13: =P13/$P$76 -> 0.0018265113 | T13: =H13+L13+P13+W13+Y13+AA13+AC13+AE13 -> 59815 | U13: =D13-T13 -> 0 | AI13: =D13-AG13 -> 59815
A14: 01B | B14: Materials Testing | C14: By Owner
A15: 02A | B15: Demolition | D15: ='02A Demolition'!B100 -> 39250 | H15: =SUM('02A Demolition'!$I$36:$I$41) -> 10000 | L15: =SUM('02A Demolition'!$I$44:$I$45) -> 0 | M15: =L15/$N$7 -> 0 | N15: =L15/$L$76 -> 0 | P15: =SUM('02A Demolition'!$I$48:$I$52) -> 29250 | Q15: =P15/$R$7 -> 2.6057906 | R15: =P15/$P$76 -> 0.0044521212 | T15: =H15+L15+P15+W15+Y15+AA15+AC15+AE15 -> 39250 | U15: =D15-T15 -> 0 | AI15: =D15-AG15 -> 39250
A16: 03A | B16: Concrete / CMU | D16: ='03A Concrete'!B110 -> 1749421 | H16: =SUM('03A Concrete'!$I$36:$I$45) -> 149120 | L16: =SUM('03A Concrete'!$I$48:$I$50) -> 782426 | M16: =L16/$N$7 -> 67 | N16: =L16/$L$76 -> 0.08304732 | P16: =SUM('03A Concrete'!$I$53:$I$57) -> 817875 | Q16: =P16/$R$7 -> 72.861915 | R16: =P16/$P$76 -> 0.12448816 | T16: =H16+L16+P16+W16+Y16+AA16+AC16+AE16 -> 1749421 | U16: =D16-T16 -> 0 | AI16: =D16-AG16 -> 1749421
A17: 05A | B17: Structural Steel | D17: ='05A Structural Steel'!$B$96 -> 624269.9 | H17: =SUM('05A Structural Steel'!$I$36:$I$37) -> 296700 | L17: =SUM('05A Structural Steel'!$I$41:$I$44) -> 288282.4 | M17: =L17/$N$7 -> 24.685939 | N17: =L17/$L$76 -> 0.030598524 | P17: =SUM('05A Structural Steel'!$I$47:$I$48) -> 39287.5 | Q17: =P17/$R$7 -> 3.5 | R17: =P17/$P$76 -> 0.0059799218 | T17: =H17+L17+P17+W17+Y17+AA17+AC17+AE17 -> 624269.9 | U17: =D17-T17 -> 0 | AI17: =D17-AG17 -> 624269.9
A18: 05C | B18: Misc. Metals | D18: ='05C Misc. Metals'!B99 -> 105897.5 | H18: =SUM('05C Misc. Metals'!$I$36:$I$37) -> 1326 | L18: =SUM('05C Misc. Metals'!$I$41:$I$44) -> 91039 | M18: =L18/$N$7 -> 7.7957698 | N18: =L18/$L$76 -> 0.0096629522 | P18: =SUM('05C Misc. Metals'!$I$47:$I$51) -> 13532.5 | Q18: =P18/$R$7 -> 1.2055679 | R18: =P18/$P$76 -> 0.002059772 | T18: =H18+L18+P18+W18+Y18+AA18+AC18+AE18 -> 105897.5 | U18: =D18-T18 -> 0 | AI18: =D18-AG18 -> 105897.5
A19: 06A | B19: Rough Carpentry | D19: ='06A Rough Carpentry'!B103 -> 348565.01 | H19: =SUM('06A Rough Carpentry'!$I$36:$I$40) -> 7219.9447 | L19: =SUM('06A Rough Carpentry'!$I$43:$I$47) -> 174892.23 | M19: =L19/$N$7 -> 14.976214 | N19: =L19/$L$76 -> 0.018563201 | P19: =SUM('06A Rough Carpentry'!$I$50:$I$55) -> 166452.84 | Q19: =P19/$R$7 -> 14.828761 | R19: =P19/$P$76 -> 0.025335665 | T19: =H19+L19+P19+W19+Y19+AA19+AC19+AE19 -> 348565.01 | U19: =D19-T19 -> 0 | AI19: =D19-AG19 -> 348565.01
A20: 06C | B20: Wood Trusses | D20: ='06C Wood Trusses'!$B$94 -> 41580 | H20: =SUM('06C Wood Trusses'!$I$36:$I$38) -> 7168 | L20: =SUM('06C Wood Trusses'!$I$41:$I$42) -> 0 | M20: =L20/$N$7 -> 0 | N20: =L20/$L$76 -> 0 | P20: =SUM('06C Wood Trusses'!$I$45:$I$47) -> 34412 | Q20: =P20/$R$7 -> 3.065657 | R20: =P20/$P$76 -> 0.0052378255 | T20: =H20+L20+P20+W20+Y20+AA20+AC20+AE20 -> 41580 | U20: =D20-T20 -> 0 | AI20: =D20-AG20 -> 41580
A21: 06F | B21: Millwork | D21: ='06F Millwork'!B118 -> 504620 | H21: =SUM('06F Millwork'!$I$36:$I$39) -> 14652 | L21: =SUM('06F Millwork'!$I$42:$I$63) -> 426068 | M21: =L21/$N$7 -> 36.484672 | N21: =L21/$L$76 -> 0.045223198 | P21: =SUM('06F Millwork'!$I$66:$I$71) -> 63900 | Q21: =P21/$R$7 -> 5.6926503 | R21: =P21/$P$76 -> 0.0097261725 | T21: =H21+L21+P21+W21+Y21+AA21+AC21+AE21 -> 504620 | U21: =D21-T21 -> 0 | AI21: =D21-AG21 -> 504620
A22: 07D | B22: Roofing | D22: ='07D Roofing'!B98 -> 514038 | H22: =SUM('07D Roofing'!$I$36:$I$38) -> 22528 | L22: =SUM('07D Roofing'!$I$41:$I$44) -> 348040 | M22: =L22/$N$7 -> 29.803048 | N22: =L22/$L$76 -> 0.036941244 | P22: =SUM('07D Roofing'!$I$47:$I$51) -> 143470 | Q22: =P22/$R$7 -> 12.781292 | R22: =P22/$P$76 -> 0.021837464 | T22: =H22+L22+P22+W22+Y22+AA22+AC22+AE22 -> 514038 | U22: =D22-T22 -> 0 | AI22: =D22-AG22 -> 514038
A23: 07E | B23: Caulking & Waterproofing | D23: ='07E Caulking & Waterproofing'!B118 -> 88695.705 | H23: =SUM('07E Caulking & Waterproofing'!$I$36:$I$38) -> 1657.5 | L23: =SUM('07E Caulking & Waterproofing'!$I$41:$I$44) -> 47750.705 | M23: =L23/$N$7 -> 4.0889455 | N23: =L23/$L$76 -> 0.005068298 | P23: =SUM('07E Caulking & Waterproofing'!$I$47:$I$49) -> 39287.5 | Q23: =P23/$R$7 -> 3.5 | R23: =P23/$P$76 -> 0.0059799218 | T23: =H23+L23+P23+W23+Y23+AA23+AC23+AE23 -> 88695.705 | U23: =D23-T23 -> 0 | AI23: =D23-AG23 -> 88695.705
A24: 07H | B24: Panelized Exterior Skin | D24: ='07H Panelized Exterior Skin'!$B$93 -> 226791.95 | H24: =SUM('07H Panelized Exterior Skin'!$I$36:$I$37) -> 0 | L24: =SUM('07H Panelized Exterior Skin'!$I$40:$I$42) -> 226791.95 | M24: =L24/$N$7 -> 19.420444 | N24: =L24/$L$76 -> 0.024071879 | P24: =SUM('07H Panelized Exterior Skin'!$I$45:$I$46) -> 0 | Q24: =P24/$R$7 -> 0 | R24: =P24/$P$76 -> 0 | T24: =H24+L24+P24+W24+Y24+AA24+AC24+AE24 -> 226791.95 | U24: =D24-T24 -> 0 | AI24: =D24-AG24 -> 226791.95
A25: 08A | B25: Doors, Frames, & Hardware | D25: ='08A Doors, Frames, & Hardware'!B95 -> 165750 | H25: =SUM('08A Doors, Frames, & Hardware'!$I$36:$I$38) -> 3500 | L25: =SUM('08A Doors, Frames, & Hardware'!$I$41:$I$43) -> 122000 | M25: =L25/$N$7 -> 10.446994 | N25: =L25/$L$76 -> 0.012949177 | P25: =SUM('08A Doors, Frames, & Hardware'!$I$46:$I$48) -> 40250 | Q25: =P25/$R$7 -> 3.5857461 | R25: =P25/$P$76 -> 0.0061264232 | T25: =H25+L25+P25+W25+Y25+AA25+AC25+AE25 -> 165750 | U25: =D25-T25 -> 0 | AI25: =D25-AG25 -> 165750
A26: 08C | B26: Glass and Glazing | D26: ='08C Glass and Glazing'!B95 -> 509130 | H26: =SUM('08C Glass and Glazing'!$I$36:$I$37) -> 0 | L26: =SUM('08C Glass and Glazing'!$I$40:$I$42) -> 143640 | M26: =L26/$N$7 -> 12.300051 | N26: =L26/$L$76 -> 0.015246064 | P26: =SUM('08C Glass and Glazing'!$I$45:$I$48) -> 365490 | Q26: =P26/$R$7 -> 32.560356 | R26: =P26/$P$76 -> 0.055630967 | T26: =H26+L26+P26+W26+Y26+AA26+AC26+AE26 -> 509130 | U26: =D26-T26 -> 0 | AI26: =D26-AG26 -> 509130
A27: 09A | B27: Stucco | D27: ='09A Stucco'!B97 -> 123408 | H27: =SUM('09A Stucco'!$I$36:$I$38) -> 9570 | L27: =SUM('09A Stucco'!$I$41:$I$43) -> 55848 | M27: =L27/$N$7 -> 4.7823257 | N27: =L27/$L$76 -> 0.0059277513 | P27: =SUM('09A Stucco'!$I$46:$I$50) -> 57990 | Q27: =P27/$R$7 -> 5.166147 | R27: =P27/$P$76 -> 0.0088266157 | T27: =H27+L27+P27+W27+Y27+AA27+AC27+AE27 -> 123408 | U27: =D27-T27 -> 0 | AI27: =D27-AG27 -> 123408
A28: 09B | B28: Drywall / Framing | D28: ='09B Drywall&Framing'!B95 -> 819230 | H28: =SUM('09B Drywall&Framing'!$I$36:$I$38) -> 19890 | L28: =SUM('09B Drywall&Framing'!$I$41:$I$43) -> 350340 | M28: =L28/$N$7 -> 30 | N28: =L28/$L$76 -> 0.037185367 | P28: =SUM('09B Drywall&Framing'!$I$46:$I$48) -> 449000 | Q28: =P28/$R$7 -> 40 | R28: =P28/$P$76 -> 0.068341963 | T28: =H28+L28+P28+W28+Y28+AA28+AC28+AE28 -> 819230 | U28: =D28-T28 -> 0 | AI28: =D28-AG28 -> 819230
A29: 09C | B29: Acoustical Ceilings | D29: ='09C Acoustical Ceilings'!B100 -> 32632 | H29: =SUM('09C Acoustical Ceilings'!$I$36:$I$37) -> 0 | L29: =SUM('09C Acoustical Ceilings'!$I$40:$I$48) -> 6376 | M29: =L29/$N$7 -> 0.5459839 | N29: =L29/$L$76 -> 0.00067675373 | P29: =SUM('09C Acoustical Ceilings'!$I$51:$I$53) -> 26256 | Q29: =P29/$R$7 -> 2.3390646 | R29: =P29/$P$76 -> 0.0039964066 | T29: =H29+L29+P29+W29+Y29+AA29+AC29+AE29 -> 32632 | U29: =D29-T29 -> 0 | AI29: =D29-AG29 -> 32632
A30: 09D | B30: Acoustical Treatment | D30: ='09D Acoustical Treatment'!$B$93 -> 25350 | H30: =SUM('09D Acoustical Treatment'!$I$35:$I$36) -> 0 | L30: =SUM('09D Acoustical Treatment'!$I$39:$I$40) -> 0 | M30: =L30/$N$7 -> 0 | N30: =L30/$L$76 -> 0 | P30: =SUM('09D Acoustical Treatment'!$I$43:$I$46) -> 25350 | Q30: =P30/$R$7 -> 2.2583519 | R30: =P30/$P$76 -> 0.003858505 | T30: =H30+L30+P30+W30+Y30+AA30+AC30+AE30 -> 25350 | U30: =D30-T30 -> 0 | AI30: =D30-AG30 -> 25350
A31: 09E | B31: Tile | D31: ='09E Tile & Stone'!B171 -> 449937.24 | H31: =SUM('09E Tile & Stone'!$I$41:$I$45) -> 34990.34 | L31: =SUM('09E Tile & Stone'!$I$48:$I$97) -> 316959.88 | M31: =L31/$N$7 -> 27.141624 | N31: =L31/$L$76 -> 0.033642375 | P31: =SUM('09E Tile & Stone'!$I$100:$I$124) -> 97987.02 | Q31: =P31/$R$7 -> 8.7293559 | R31: =P31/$P$76 -> 0.014914533 | T31: =H31+L31+P31+W31+Y31+AA31+AC31+AE31 -> 449937.24 | U31: =D31-T31 -> 0 | AI31: =D31-AG31 -> 449937.24
A32: 09F | B32: Flooring: Carpet and Resilient Flooring | D32: ='09F Carpet & Resilient'!B154 -> 53846.2 | H32: =SUM('09F Carpet & Resilient'!$I$40:$I$41) -> 0 | L32: =SUM('09F Carpet & Resilient'!$I$44:$I$65) -> 47876.58 | M32: =L32/$N$7 -> 4.0997243 | N32: =L32/$L$76 -> 0.0050816584 | P32: =SUM('09F Carpet & Resilient'!$I$68:$I$78) -> 5969.62 | Q32: =P32/$R$7 -> 0.5318147 | R32: =P32/$P$76 -> 0.00090863151 | T32: =H32+L32+P32+W32+Y32+AA32+AC32+AE32 -> 53846.2 | U32: =D32-T32 -> 0 | AI32: =D32-AG32 -> 53846.2
A33: 09G | B33: Sports Flooring | D33: ='09G Sports Flooring'!$B$103 -> 121912.25 | H33: =SUM('09G Sports Flooring'!$I$35:$I$36) -> 0 | L33: =SUM('09G Sports Flooring'!$I$39:$I$40) -> 0 | M33: =L33/$N$7 -> 0 | N33: =L33/$L$76 -> 0 | P33: =SUM('09G Sports Flooring'!$I$43:$I$47) -> 121912.25 | Q33: =P33/$R$7 -> 10.86078 | R33: =P33/$P$76 -> 0.018556175 | T33: =H33+L33+P33+W33+Y33+AA33+AC33+AE33 -> 121912.25 | U33: =D33-T33 -> 0 | AI33: =D33-AG33 -> 121912.25
A34: 09I | B34: Painting | D34: ='09I Painting'!B126 -> 227808.6 | H34: =SUM('09I Painting'!$I$41:$I$44) -> 2270.5 | L34: =SUM('09I Painting'!$I$47:$I$69) -> 121879.77 | M34: =L34/$N$7 -> 10.436699 | N34: =L34/$L$76 -> 0.012936416 | P34: =SUM('09I Painting'!$I$72:$I$78) -> 103658.33 | Q34: =P34/$R$7 -> 9.2345954 | R34: =P34/$P$76 -> 0.015777759 | T34: =H34+L34+P34+W34+Y34+AA34+AC34+AE34 -> 227808.6 | U34: =D34-T34 -> 0 | AI34: =D34-AG34 -> 227808.6
A35: 10A | B35: Signage | D35: ='10A Signage'!B95 -> 23403 | H35: =SUM('10A Signage'!$I$36:$I$38) -> 500 | L35: =SUM('10A Signage'!$I$41:$I$43) -> 11678 | M35: =L35/$N$7 -> 1 | N35: =L35/$L$76 -> 0.0012395122 | P35: =SUM('10A Signage'!$I$46:$I$48) -> 11225 | Q35: =P35/$R$7 -> 1 | R35: =P35/$P$76 -> 0.0017085491 | T35: =H35+L35+P35+W35+Y35+AA35+AC35+AE35 -> 23403 | U35: =D35-T35 -> 0 | AI35: =D35-AG35 -> 23403
A36: 10B | B36: Operable Partitions | D36: ='10B Operable Partitions'!$B$94 -> 190000 | H36: =SUM('10B Operable Partitions'!$I$36:$I$37) -> 0 | L36: =SUM('10B Operable Partitions'!$I$40:$I$41) -> 0 | M36: =L36/$N$7 -> 0 | N36: =L36/$L$76 -> 0 | P36: =SUM('10B Operable Partitions'!$I$44:$I$47) -> 190000 | Q36: =P36/$R$7 -> 16.926503 | R36: =P36/$P$76 -> 0.028919762 | T36: =H36+L36+P36+W36+Y36+AA36+AC36+AE36 -> 190000 | U36: =D36-T36 -> 0 | AI36: =D36-AG36 -> 190000
A37: 10C | B37: Toilet Partitions & Bathroom Accessories | D37: ='10C Toilet Partitions & Bath'!B102 -> 28590 | H37: =SUM('10C Toilet Partitions & Bath'!$I$36:$I$41) -> 12730 | L37: =SUM('10C Toilet Partitions & Bath'!$I$44:$I$48) -> 10820 | M37: =L37/$N$7 -> 0.92652852 | N37: =L37/$L$76 -> 0.0011484434 | P37: =SUM('10C Toilet Partitions & Bath'!$I$51:$I$55) -> 5040 | Q37: =P37/$R$7 -> 0.44899777 | R37: =P37/$P$76 -> 0.00076713473 | T37: =H37+L37+P37+W37+Y37+AA37+AC37+AE37 -> 28590 | U37: =D37-T37 -> 0 | AI37: =D37-AG37 -> 28590
A38: 10F | B38: Lockers | D38: ='10F Lockers'!B95 -> 104000 | H38: =SUM('10F Lockers'!$I$36:$I$37) -> 0 | L38: =SUM('10F Lockers'!$I$40:$I$43) -> 104000 | M38: =L38/$N$7 -> 8.9056345 | N38: =L38/$L$76 -> 0.011038643 | P38: =SUM('10F Lockers'!$I$46:$I$47) -> 0 | Q38: =P38/$R$7 -> 0 | R38: =P38/$P$76 -> 0 | T38: =H38+L38+P38+W38+Y38+AA38+AC38+AE38 -> 104000 | U38: =D38-T38 -> 0 | AI38: =D38-AG38 -> 104000
A39: 10I | B39: Fire Extinguishers& Cabinets | D39: ='10I Fire Extinguishers&Cabinet'!B95 -> 5180.6 | H39: =SUM('10I Fire Extinguishers&Cabinet'!$I$36:$I$38) -> 600 | L39: =SUM('10I Fire Extinguishers&Cabinet'!$I$41:$I$43) -> 2335.6 | M39: =L39/$N$7 -> 0.2 | N39: =L39/$L$76 -> 0.00024790245 | P39: =SUM('10I Fire Extinguishers&Cabinet'!$I$46:$I$48) -> 2245 | Q39: =P39/$R$7 -> 0.2 | R39: =P39/$P$76 -> 0.00034170981 | T39: =H39+L39+P39+W39+Y39+AA39+AC39+AE39 -> 5180.6 | U39: =D39-T39 -> 0 | AI39: =D39-AG39 -> 5180.6
A40: 12A | B40: Window Treatment | D40: ='12A Window Treatment'!B94 -> 34354.5 | H40: =SUM('12A Window Treatment'!$I$36:$I$37) -> 0 | L40: =SUM('12A Window Treatment'!$I$40:$I$42) -> 17517 | M40: =L40/$N$7 -> 1.5 | N40: =L40/$L$76 -> 0.0018592684 | P40: =SUM('12A Window Treatment'!$I$45:$I$47) -> 16837.5 | Q40: =P40/$R$7 -> 1.5 | R40: =P40/$P$76 -> 0.0025628236 | T40: =H40+L40+P40+W40+Y40+AA40+AC40+AE40 -> 34354.5 | U40: =D40-T40 -> 0 | AI40: =D40-AG40 -> 34354.5
A41: 13B | B41: Swimming Pools | D41: ='13B Swimming Pools'!$B$112 -> 441150 | H41: 0 | L41: =SUM('13B Swimming Pools'!$I$37:$I$42) -> 441150 | M41: =L41/$N$7 -> 37.77616 | N41: =L41/$L$76 -> 0.046824013 | P41: =SUM('13B Swimming Pools'!$I$45:$I$46) -> 0 | Q41: =P41/$R$7 -> 0 | R41: =P41/$P$76 -> 0 | T41: =H41+L41+P41+W41+Y41+AA41+AC41+AE41 -> 441150 | U41: =D41-T41 -> 0 | AI41: =D41-AG41 -> 441150
A42: 13C | B42: Covered Structures | C42: By Owner | D42: ='13C Awnings,Canopies,Shutters'!$B$97 -> 295165 | H42: =SUM('13C Awnings,Canopies,Shutters'!$I$36:$I$42) -> 295165 | L42: =SUM('13C Awnings,Canopies,Shutters'!$I$45:$I$46) -> 0 | M42: =L42/$N$7 -> 0 | N42: =L42/$L$76 -> 0 | P42: =SUM('13C Awnings,Canopies,Shutters'!$I$49:$I$50) -> 0 | T42: =H42+L42+P42+W42+Y42+AA42+AC42+AE42 -> 295165 | U42: =D42-T42 -> 0
A43: 14A | B43: Elevators | D43: ='14A Elevators'!$B$92 -> 130000 | H43: =SUM('14A Elevators'!$I$35:$I$36) -> 0 | L43: =SUM('14A Elevators'!$I$39:$I$40) -> 0 | M43: =L43/$N$7 -> 0 | N43: =L43/$L$76 -> 0 | P43: =SUM('14A Elevators'!$I$43:$I$45) -> 130000 | Q43: =P43/$R$7 -> 11.581292 | R43: =P43/$P$76 -> 0.019787205 | T43: =H43+L43+P43+W43+Y43+AA43+AC43+AE43 -> 130000 | U43: =D43-T43 -> 0 | AI43: =D43-AG43 -> 130000
A44: 21A | B44: Fire Sprinkler | D44: ='21A Fire Sprinkler'!B95 -> 83475.5 | H44: =SUM('21A Fire Sprinkler'!$I$36:$I$38) -> 3315 | L44: =SUM('21A Fire Sprinkler'!$I$41:$I$43) -> 40873 | M44: =L44/$N$7 -> 3.5 | N44: =L44/$L$76 -> 0.0043382929 | P44: =SUM('21A Fire Sprinkler'!$I$46:$I$48) -> 39287.5 | Q44: =P44/$R$7 -> 3.5 | R44: =P44/$P$76 -> 0.0059799218 | T44: =H44+L44+P44+W44+Y44+AA44+AC44+AE44 -> 83475.5 | U44: =D44-T44 -> 0 | AI44: =D44-AG44 -> 83475.5
A45: 22A | B45: Plumbing | D45: ='22A Plumbing '!B109 -> 531000 | H45: =SUM('22A Plumbing '!$I$46:$I$50) -> 35000 | L45: =SUM('22A Plumbing '!$I$53:$I$55) -> 330000 | M45: =L45/$N$7 -> 28.258263 | N45: =L45/$L$76 -> 0.035026464 | P45: =SUM('22A Plumbing '!$I$58:$I$61) -> 166000 | Q45: =P45/$R$7 -> 14.788419 | R45: =P45/$P$76 -> 0.025266739 | T45: =H45+L45+P45+W45+Y45+AA45+AC45+AE45 -> 531000 | U45: =D45-T45 -> 0 | AI45: =D45-AG45 -> 531000
A46: 23A | B46: HVAC | D46: ='23A HVAC'!B114 -> 1559000 | H46: =SUM('23A HVAC'!$I$45:$I$47) -> 42000 | L46: =SUM('23A HVAC'!$I$50:$I$57) -> 1088000 | M46: =L46/$N$7 -> 93.166638 | N46: =L46/$L$76 -> 0.11548119 | P46: =SUM('23A HVAC'!$I$60:$I$67) -> 429000 | Q46: =P46/$R$7 -> 38.218263 | R46: =P46/$P$76 -> 0.065297778 | T46: =H46+L46+P46+W46+Y46+AA46+AC46+AE46 -> 1559000 | U46: =D46-T46 -> 0 | AI46: =D46-AG46 -> 1559000
A47: 26A | B47: Electrical & Fire Alarm | D47: ='26A Electrical'!B126 -> 1685779.6 | H47: =SUM('26A Electrical'!$I$54:$I$63) -> 277616.87 | L47: =SUM('26A Electrical'!$I$66:$I$71) -> 723630.75 | M47: =L47/$N$7 -> 61.965298 | N47: =L47/$L$76 -> 0.076806746 | P47: =SUM('26A Electrical'!$I$74:$I$79) -> 684532 | Q47: =P47/$R$7 -> 60.982806 | R47: =P47/$P$76 -> 0.10419212 | T47: =H47+L47+P47+W47+Y47+AA47+AC47+AE47 -> 1685779.6 | U47: =D47-T47 -> 0 | AI47: =D47-AG47 -> 1685779.6
A48: 28A | B48: Low Voltage - Conduits included in Electrical | D48: ='28A Low Voltage'!$B$117 -> 239371.5 | H48: =SUM('28A Low Voltage'!$I$43:$I$50) -> 18689 | L48: =SUM('28A Low Voltage'!$I$53:$I$60) -> 96195 | M48: =L48/$N$7 -> 8.2372838 | N48: =L48/$L$76 -> 0.010210214 | P48: =SUM('28A Low Voltage'!$I$63:$I$70) -> 124487.5 | Q48: =P48/$R$7 -> 11.0902 | R48: =P48/$P$76 -> 0.018948152 | T48: =H48+L48+P48+W48+Y48+AA48+AC48+AE48 -> 239371.5 | U48: =D48-T48 -> 0 | AI48: =D48-AG48 -> 239371.5
A49: 31A | B49: Sitework | D49: ='31A Sitework'!B241 -> 2082604 | H49: =SUM('31A Sitework'!$I$43:$I$67) -> 1138284 | L49: =SUM('31A Sitework'!$I$70:$I$72) -> 550000 | M49: =L49/$N$7 -> 47.097106 | N49: =L49/$L$76 -> 0.058377439 | P49: =SUM('31A Sitework'!$I$75:$I$77) -> 394320 | Q49: =P49/$R$7 -> 35.128731 | R49: =P49/$P$76 -> 0.06001916 | T49: =H49+L49+P49+W49+Y49+AA49+AC49+AE49 -> 2082604 | U49: =D49-T49 -> 0 | AI49: =D49-AG49 -> 2082604
A50: 32A | B50: Pavers | D50: ='32A Pavers'!B98 -> 282021 | H50: =SUM('32A Pavers'!$I$36:$I$41) -> 168685 | L50: =SUM('32A Pavers'!$I$44:$I$46) -> 65936 | M50: =L50/$N$7 -> 5.6461723 | N50: =L50/$L$76 -> 0.0069984997 | P50: =SUM('32A Pavers'!$I$49:$I$51) -> 47400 | Q50: =P50/$R$7 -> 4.2227171 | R50: =P50/$P$76 -> 0.0072147195 | T50: =H50+L50+P50+W50+Y50+AA50+AC50+AE50 -> 282021 | U50: =D50-T50 -> 0 | AI50: =D50-AG50 -> 282021
A51: 32B | B51: Site Furnishings | C51: By Owner | R51: p | AI51: =D51-AG51 -> 0
A52: 32C | B52: Landscape and Irrigation | D52: ='32C Landscape and Irrigation'!B98 -> 489500 | H52: =SUM('32C Landscape and Irrigation'!$I$36:$I$39) -> 184500 | L52: =SUM('32C Landscape and Irrigation'!$I$42:$I$44) -> 160500 | M52: =L52/$N$7 -> 13.743792 | N52: =L52/$L$76 -> 0.017035598 | P52: =SUM('32C Landscape and Irrigation'!$I$47:$I$51) -> 144500 | Q52: =P52/$R$7 -> 12.873051 | R52: =P52/$P$76 -> 0.02199424 | T52: =H52+L52+P52+W52+Y52+AA52+AC52+AE52 -> 489500 | U52: =D52-T52 -> 0 | AI52: =D52-AG52 -> 489500
A53: 32D | B53: Fencing | D53: ='32D Fencing'!B96 -> 72075 | H53: =SUM('32D Fencing'!$I$36:$I$40) -> 72075 | L53: =SUM('32D Fencing'!$I$43:$I$44) -> 0 | M53: =L53/$N$7 -> 0 | N53: =L53/$L$76 -> 0 | P53: =SUM('32D Fencing'!$I$47:$I$48) -> 0 | Q53: =P53/$R$7 -> 0 | R53: =P53/$P$76 -> 0 | T53: =H53+L53+P53+W53+Y53+AA53+AC53+AE53 -> 72075 | U53: =D53-T53 -> 0 | AI53: =D53-AG53 -> 72075
A54: 32E | B54: Synthetic Fields | C54: By Owner | D54: ='32E Synthetic Fields'!$B$95 -> 2950000 | H54: =SUM('32E Synthetic Fields'!$I$36:$I$40) -> 2950000 | L54: =SUM('32E Synthetic Fields'!$I$43:$I$44) -> 0 | M54: =L54/$N$7 -> 0 | N54: =L54/$L$76 -> 0 | P54: =SUM('32E Synthetic Fields'!$I$47:$I$48) -> 0 | Q54: =P54/$R$7 -> 0 | R54: =P54/$P$76 -> 0 | T54: =H54+L54+P54+W54+Y54+AA54+AC54+AE54 -> 2950000 | U54: =D54-T54 -> 0 | AI54: =D54-AG54 -> 2950000
B55: Phase 1 Interior Clubhouse Renovations | D55: =W55 -> 153372.29 | T55: =H55+L55+P55+W55+Y55+AA55+AC55+AE55 -> 153372.29 | U55: =D55-T55 -> 0 | W55: =W85/$W$86 -> 153372.29
B56: Phase 2 Bocce & Basketball | D56: =Y56 -> 1610409.1 | T56: =H56+L56+P56+W56+Y56+AA56+AC56+AE56 -> 1610409.1 | U56: =D56-T56 -> 0 | X56: 14901.05 | Y56: =Y85/$W$86 -> 1610409.1
B57: Phase 2 POA | D57: =AA57 -> 1917153.7 | T57: =H57+L57+P57+W57+Y57+AA57+AC57+AE57 -> 1917153.7 | U57: =D57-T57 -> 0 | AA57: =AA85/$W$86 -> 1917153.7
B58: Phase 3 19th Hole | D58: =AC58 -> 1917153.7 | T58: =H58+L58+P58+W58+Y58+AA58+AC58+AE58 -> 1917153.7 | U58: =D58-T58 -> 0 | AC58: =AC85/$W$86 -> 1917153.7
B59: Phase 3 Existing Fitness Building | D59: =AE59 -> 1763781.4 | T59: =H59+L59+P59+W59+Y59+AA59+AC59+AE59 -> 1763781.4 | U59: =D59-T59 -> 0 | AE59: =AE85/W86 -> 1763781.4
B60: SUB-TOTAL 1 (Cost of Work)Building | D60: =SUM(D13:D59) -> 25420488 | E60: =D60/F7 -> 180.10704 | F60: =D60/$D$76 -> 0.76686152 | H60: =SUM(H13:H54) -> 5795467.2 | L60: =SUM(L13:L54) -> 7224945.9 | M60: =SUM(M13:M59) -> 618.68007 | N60: =SUM(N13:N54) -> 0.76686152 | P60: =SUM(P13:P54) -> 5038205.1 | Q60: =SUM(Q13:Q54) -> 448.83787 | R60: =SUM(R13:R54) -> 0.76686152 | T60: =H60+L60+P60+W60+Y60+AA60+AC60+AE60 -> 25420488 | U60: =D60-T60 -> 0 | W60: =SUM(W13:W59) -> 153372.29 | Y60: =SUM(Y13:Y59) -> 1610409.1 | AA60: =SUM(AA13:AA59) -> 1917153.7 | AC60: =SUM(AC13:AC59) -> 1917153.7 | AE60: =SUM(AE13:AE59) -> 1763781.4 | AG60: =SUM(AG13:AG54) -> 0 | AI60: =D60-AG60 -> 25420488
C61: GC Contingency | D61: =$D$60*AL61 -> 635512.2 | E61: =D61/$F$7 -> 4.5026761 | F61: =D61/$D$76 -> 0.019171538 | H61: =$H$60*$AL$61 -> 144886.68 | L61: =$L$60*$AL$61 -> 180623.65 | M61: =L61/$N$7 -> 15.467002 | N61: =L61/$L$76 -> 0.019171538 | P61: =$P$60*$AL$61 -> 125955.13 | Q61: =P61/$R$7 -> 11.220947 | R61: =P61/$P$76 -> 0.019171538 | T61: =H61+L61+P61+W61+Y61+AA61+AC61+AE61 -> 635512.2 | U61: =D61-T61 -> 0 | W61: =W60*$AL$61 -> 3834.3073 | Y61: =Y60*$AL$61 -> 40260.227 | AA61: =AA60*$AL$61 -> 47928.841 | AC61: =AC60*$AL$61 -> 47928.841 | AE61: =AE60*$AL$61 -> 44094.534 | AI61: =D61-AG61 -> 635512.2 | AL61: 0.025
C62: Owner Contingency | D62: By owner | AL62: 0
C63: Escalation Contingency | D63: =$D$60*AL63 -> 635512.2 | E63: =D63/$F$7 -> 4.5026761 | F63: =D63/$D$76 -> 0.019171538 | H63: =$H$60*$AL$63 -> 144886.68 | L63: =$L$60*$AL$63 -> 180623.65 | M63: =L63/$N$7 -> 15.467002 | N63: =L63/$L$76 -> 0.019171538 | P63: =$P$60*$AL$63 -> 125955.13 | Q63: =P63/$R$7 -> 11.220947 | R63: =P63/$P$76 -> 0.019171538 | T63: =H63+L63+P63+W63+Y63+AA63+AC63+AE63 -> 635512.2 | U63: =D63-T63 -> 0 | W63: =W60*$AL$63 -> 3834.3073 | Y63: =Y60*$AL$63 -> 40260.227 | AA63: =AA60*$AL$63 -> 47928.841 | AC63: =AC60*$AL$63 -> 47928.841 | AE63: =AE60*$AL$63 -> 44094.534 | AI63: =D63-AG63 -> 635512.2 | AL63: 0.025
B64: SUB-TOTAL 2 (Contingency) | D64: =SUM(D60:D63) -> 26691513 | E64: =SUM(E60:E63) -> 189.11239 | F64: =SUM(F60:F63) -> 0.8052046 | H64: =SUM(H60:H63) -> 6085240.5 | L64: =SUM(L60:L63) -> 7586193.2 | M64: =SUM(M60:M63) -> 649.61407 | N64: =SUM(N60:N63) -> 0.8052046 | P64: =SUM(P60:P63) -> 5290115.3 | Q64: =SUM(Q60:Q63) -> 471.27976 | R64: =SUM(R60:R63) -> 0.8052046 | T64: =H64+L64+P64+W64+Y64+AA64+AC64+AE64 -> 26691513 | U64: =D64-T64 -> 0 | W64: =SUM(W60:W63) -> 161040.91 | Y64: =SUM(Y60:Y63) -> 1690929.5 | AA64: =SUM(AA60:AA63) -> 2013011.3 | AC64: =SUM(AC60:AC63) -> 2013011.3 | AE64: =SUM(AE60:AE63) -> 1851970.4 | AG64: =SUM(AG60:AG63) -> 0 | AI64: =SUM(AI60:AI63) -> 26691513
C65: General Conditions | D65: ='GCs & GRs'!L160 -> 2991138.4 | E65: =D65/$F$7 -> 21.192555 | F65: =D65/$D$76 -> 0.090233869 | H65: =H64/$D$64*$D$65 -> 681932.01 | L65: =L64/$D$64*$D$65 -> 850133.69 | M65: =L65/$N$7 -> 72.797884 | N65: =L65/$L$76 -> 0.090233869 | P65: =P64/$D$64*$D$65 -> 592827.68 | Q65: =P65/$R$7 -> 52.813156 | R65: =P65/$P$76 -> 0.090233869 | T65: =H65+L65+P65+W65+Y65+AA65+AC65+AE65 -> 2991138.4 | U65: =D65-T65 -> 0 | W65: =W64/$D$64*$D$65 -> 18046.772 | Y65: =Y64/$D$64*$D$65 -> 189491.11 | AA65: =AA64/$D$64*$D$65 -> 225584.65 | AC65: =AC64/$D$64*$D$65 -> 225584.65 | AE65: =AE64/$D$64*$D$65 -> 207537.88 | AI65: =D65-AG65 -> 2991138.4 | AL65: =D65/D76 -> 0.090233869
C66: General Requirements | D66: ='GCs & GRs'!L161 -> 705899.49 | E66: =D66/$F$7 -> 5.001378 | F66: =D66/$D$76 -> 0.021294916 | H66: =H64/$D$64*$D$66 -> 160933.86 | L66: =L64/$D$64*$D$66 -> 200628.94 | M66: =L66/$N$7 -> 17.180077 | N66: =L66/$L$76 -> 0.021294916 | P66: =P64/$D$64*$D$66 -> 139905.51 | Q66: =P66/$R$7 -> 12.463743 | R66: =P66/$P$76 -> 0.021294916 | T66: =H66+L66+P66+W66+Y66+AA66+AC66+AE66 -> 705899.49 | U66: =D66-T66 -> 0 | W66: =W64/$D$64*$D$66 -> 4258.9829 | Y66: =Y64/$D$64*$D$66 -> 44719.32 | AA66: =AA64/$D$64*$D$66 -> 53237.286 | AC66: =AC64/$D$64*$D$66 -> 53237.286 | AE66: =AE64/$D$64*$D$66 -> 48978.303 | AI66: =D66-AG66 -> 705899.49 | AL66: =D66/D76 -> 0.021294916
C67: Innovation & Digital Services (IDS) | D67: =IDS!$B$135 -> 50969 | E67: =D67/$F$7 -> 0.36112115 | F67: =D67/$D$76 -> 0.0015375851 | H67: =H64/$D$64*$D$67 -> 11620.122 | L67: =L64/$D$64*$D$67 -> 14486.278 | M67: =L67/$N$7 -> 1.240476 | N67: =L67/$L$76 -> 0.0015375851 | P67: =P64/$D$64*$D$67 -> 10101.784 | Q67: =P67/$R$7 -> 0.89993619 | R67: =P67/$P$76 -> 0.0015375851 | T67: =H67+L67+P67+W67+Y67+AA67+AC67+AE67 -> 50969 | U67: =D67-T67 -> 0 | W67: =W64/$D$64*$D$67 -> 307.51701 | Y67: =Y64/$D$64*$D$67 -> 3228.9286 | AA67: =AA64/$D$64*$D$67 -> 3843.9626 | AC67: =AC64/$D$64*$D$67 -> 3843.9626 | AE67: =AE64/$D$64*$D$67 -> 3536.4456
C68: Builders Risk Insurance & Deductibles | D68: By owner
C69: Subcontractor Default Insurance | D69: =D64*AL69 -> 400372.69 | E69: =D69/$F$7 -> 2.8366859 | F69: =D69/$D$76 -> 0.012078069 | H69: =H64*$AL$69 -> 91278.608 | L69: =L64*$AL$69 -> 113792.9 | M69: =L69/$N$7 -> 9.7442111 | N69: =L69/$L$76 -> 0.012078069 | P69: =P64*$AL$69 -> 79351.73 | Q69: =P69/$R$7 -> 7.0691964 | R69: =P69/$P$76 -> 0.012078069 | T69: =H69+L69+P69+W69+Y69+AA69+AC69+AE69 -> 400372.69 | U69: =D69-T69 -> 0 | W69: =W64*$AL$69 -> 2415.6136 | Y69: =Y64*$AL$69 -> 25363.943 | AA69: =AA64*$AL$69 -> 30195.17 | AC69: =AC64*$AL$69 -> 30195.17 | AE69: =AE64*$AL$69 -> 27779.556 | AI69: =D69-AG69 -> 400372.69 | AL69: 0.015
B70: Procore | D70: =(D72+D69+D66+D65+D64+D67)*$AL$70 -> 78266.118 | E70: =D70/$F$7 -> 0.55452433 | F70: =D70/$D$76 -> 0.0023610591 | H70: =(H72+H69+H66+H65+H64+H67)*$AL$70 -> 17843.431 | L70: =(L72+L69+L66+L65+L64+L67)*$AL$70 -> 22244.595 | M70: =L70/$N$7 -> 1.9048292 | N70: =L70/$L$76 -> 0.0023610591 | P70: =(P72+P69+P66+P65+P64+P67)*$AL$70 -> 15511.927 | Q70: =P70/$R$7 -> 1.3819088 | R70: =P70/$P$76 -> 0.0023610591 | T70: =H70+L70+P70+W70+Y70+AA70+AC70+AE70 -> 78266.118 | U70: =D70-T70 -> 0 | W70: =(W72+W69+W66+W65+W64+W67)*$AL$70 -> 472.21178 | Y70: =(Y72+Y69+Y66+Y65+Y64+Y67)*$AL$70 -> 4958.2237 | AA70: =(AA72+AA69+AA66+AA65+AA64+AA67)*$AL$70 -> 5902.6472 | AC70: =(AC72+AC69+AC66+AC65+AC64+AC67)*$AL$70 -> 5902.6472 | AE70: =(AE72+AE69+AE66+AE65+AE64+AE67)*$AL$70 -> 5430.4355 | AI70: =D70-AG70 -> 78266.118 | AL70: 0.0025
C71: Warranty | D71: =$AL$71*(D67+D70+D69+D66+D65+D64) -> 185508.95 | E71: =D71/$F$7 -> 1.314352 | F71: =D71/$D$76 -> 0.0055962606 | H71: =$AL$71*(H67+H70+H69+H66+H65+H64) -> 42293.091 | L71: =$AL$71*(L67+L70+L69+L66+L65+L64) -> 52724.877 | M71: =L71/$N$7 -> 4.5148893 | N71: =L71/$L$76 -> 0.0055962606 | P71: =$AL$71*(P67+P70+P69+P66+P65+P64) -> 36766.884 | Q71: =P71/$R$7 -> 3.2754462 | R71: =P71/$P$76 -> 0.0055962606 | T71: =H71+L71+P71+W71+Y71+AA71+AC71+AE71 -> 185508.95 | U71: =D71-T71 -> 0 | W71: =$AL$71*(W67+W70+W69+W66+W65+W64) -> 1119.252 | Y71: =$AL$71*(Y67+Y70+Y69+Y66+Y65+Y64) -> 11752.146 | AA71: =$AL$71*(AA67+AA70+AA69+AA66+AA65+AA64) -> 13990.65 | AC71: =$AL$71*(AC67+AC70+AC69+AC66+AC65+AC64) -> 13990.65 | AE71: =$AL$71*(AE67+AE70+AE69+AE66+AE65+AE64) -> 12871.398 | AL71: 0.006
B72: General Liability Insurance | C72: General Liability Insurance | D72: =(D69+D66+D71+D65+D64+D67+D70)*$AL$72 -> 466555.01 | E72: =D72/$F$7 -> 3.3055952 | F72: =D72/$D$76 -> 0.014074595 | H72: =(H69+H66+H71+H65+H64+H67+H70)*$AL$72 -> 106367.12 | L72: =(L69+L66+L71+L65+L64+L67+L70)*$AL$72 -> 132603.07 | M72: =L72/$N$7 -> 11.354947 | N72: =L72/$L$76 -> 0.014074595 | P72: =(P69+P66+P71+P65+P64+P67+P70)*$AL$72 -> 92468.712 | Q72: =P72/$R$7 -> 8.2377472 | R72: =P72/$P$76 -> 0.014074595 | T72: =H72+L72+P72+W72+Y72+AA72+AC72+AE72 -> 466555.01 | U72: =D72-T72 -> 0 | W72: =(W69+W66+W71+W65+W64+W67+W70)*$AL$72 -> 2814.9189 | Y72: =(Y69+Y66+Y71+Y65+Y64+Y67+Y70)*$AL$72 -> 29556.648 | AA72: =(AA69+AA66+AA71+AA65+AA64+AA67+AA70)*$AL$72 -> 35186.486 | AC72: =(AC69+AC66+AC71+AC65+AC64+AC67+AC70)*$AL$72 -> 35186.486 | AE72: =(AE69+AE66+AE71+AE65+AE64+AE67+AE70)*$AL$72 -> 32371.567 | AI72: =D72-AG72 -> 466555.01 | AL72: 0.015
B73: SUB-TOTAL 3 (Bonds, Insurances, & GC's) | D73: =SUM(D64:D72) -> 31570222 | E73: =SUM(E64:E72) -> 223.67861 | F73: =SUM(F64:F72) -> 0.95238095 | H73: =SUM(H64:H72) -> 7197508.8 | L73: =SUM(L64:L72) -> 8972807.5 | M73: =SUM(M64:M72) -> 768.35139 | N73: =SUM(N64:N72) -> 0.95238095 | P73: =SUM(P64:P72) -> 6257049.5 | Q73: =SUM(Q64:Q72) -> 557.42089 | R73: =SUM(R64:R72) -> 0.95238095 | T73: =H73+L73+P73+W73+Y73+AA73+AC73+AE73 -> 31570222 | U73: =D73-T73 -> 0 | W73: =SUM(W64:W72) -> 190476.18 | Y73: =SUM(Y64:Y72) -> 1999999.8 | AA73: =SUM(AA64:AA72) -> 2380952.2 | AC73: =SUM(AC64:AC72) -> 2380952.2 | AE73: =SUM(AE64:AE72) -> 2190476 | AG73: =SUM(AG64:AG72) -> 0 | AI73: =SUM(AI64:AI72) -> 31333744
C74: GC Fee (OH) | D74: =D73*$AL$74 -> 947106.67 | E74: =D74/$F$7 -> 6.7103582 | F74: =D74/$D$76 -> 0.028571429 | H74: =H73*$AL$74 -> 215925.26 | L74: =L73*$AL$74 -> 269184.22 | M74: =L74/$N$7 -> 23.050542 | N74: =L74/$L$76 -> 0.028571429 | P74: =P73*$AL$74 -> 187711.49 | Q74: =P74/$R$7 -> 16.722627 | R74: =P74/$P$76 -> 0.028571429 | T74: =H74+L74+P74+W74+Y74+AA74+AC74+AE74 -> 947106.67 | U74: =D74-T74 -> 0 | W74: =W73*$AL$74 -> 5714.2853 | Y74: =Y73*$AL$74 -> 59999.995 | AA74: =AA73*$AL$74 -> 71428.566 | AC74: =AC73*$AL$74 -> 71428.566 | AE74: =AE73*$AL$74 -> 65714.281 | AI74: =D74-AG74 -> 947106.67 | AL74: 0.03
C75: GC Fee (P) | D75: =D73*$AL$75 -> 631404.44 | E75: =D75/$F$7 -> 4.4735721 | F75: =D75/$D$76 -> 0.019047619 | H75: =H73*$AL$75 -> 143950.18 | L75: =L73*$AL$75 -> 179456.15 | M75: =L75/$N$7 -> 15.367028 | N75: =L75/$L$76 -> 0.019047619 | P75: =P73*$AL$75 -> 125140.99 | Q75: =P75/$R$7 -> 11.148418 | R75: =P75/$P$76 -> 0.019047619 | T75: =H75+L75+P75+W75+Y75+AA75+AC75+AE75 -> 631404.44 | U75: =D75-T75 -> 0 | W75: =W73*$AL$75 -> 3809.5235 | Y75: =Y73*$AL$75 -> 39999.997 | AA75: =AA73*$AL$75 -> 47619.044 | AC75: =AC73*$AL$75 -> 47619.044 | AE75: =AE73*$AL$75 -> 43809.52 | AI75: =D75-AG75 -> 631404.44 | AL75: 0.02
B76: ESTIMATE TOTAL | D76: =SUM(D73:D75) -> 33148733 | E76: =SUM(E73:E74) -> 230.38896 | F76: =SUM(F73:F75) -> 1 | H76: =SUM(H73:H75) -> 7557384.2 | L76: =SUM(L73:L75) -> 9421447.9 | M76: =SUM(M73:M74) -> 791.40193 | N76: =SUM(N73:N75) -> 1 | P76: =SUM(P73:P75) -> 6569902 | Q76: =SUM(Q73:Q74) -> 574.14352 | R76: =SUM(R73:R75) -> 1 | T76: =H76+L76+P76+W76+Y76+AA76+AC76+AE76 -> 33148733 | U76: =D76-T76 -> 0 | W76: =SUM(W73:W75) -> 199999.98 | Y76: =SUM(Y73:Y75) -> 2099999.8 | AA76: =SUM(AA73:AA75) -> 2499999.8 | AC76: =SUM(AC73:AC75) -> 2499999.8 | AE76: =SUM(AE73:AE75) -> 2299999.8 | AG76: =SUM(AG73:AG74) -> 0 | AI76: =SUM(AI73:AI74) -> 32280851
C77: RFP Budget $34,000,000.00 | D77: =H85+L85+P85+W85+Y85+AA85+AC85+AE85 -> 32700000
B78: CONSTRUCTION CONCEPTUAL BUDGET RANGE | C78: CONSTRUCTION CONCEPTUAL BUDGET RANGE | D78: $31 - 35 Million
C80: Performance & Payment Bond | D80: =D76*$AL$80 -> 331487.33 | E80: =D80/$F$7 -> 2.3486254 | F80: =D80/$D$76 -> 0.01 | H80: =H76*$AL$80 -> 75573.842 | L80: =L76*$AL$80 -> 94214.479 | M80: =L80/$F$7 -> 0.66752027 | N80: =L80/$H$76 -> 0.012466546 | P80: =P76*$AL$80 -> 65699.02 | Q80: =P80/$R$7 -> 5.8529194 | R80: =P80/$H$76 -> 0.0086933545 | AL80: 0.01
C82: IDS, SDI, Procore, Warranty | D82: =D67+D69+D70+D71 -> 715116.76 | H82: =H67+H69+H70+H71 -> 163035.25 | L82: =L67+L69+L70+L71 -> 203248.65 | P82: =P67+P69+P70+P71 -> 141732.32 | W82: =W67+W69+W70+W71 -> 4314.5944 | Y82: =Y67+Y69+Y70+Y71 -> 45303.241 | AA82: =AA67+AA69+AA70+AA71 -> 53932.43 | AC82: =AC67+AC69+AC70+AC71 -> 53932.43 | AE82: =AE67+AE69+AE70+AE71 -> 49617.836
C83: % | D83: =D82/$D$60 -> 0.028131512 | H83: =H82/$H$60 -> 0.028131512 | L83: =L82/$L$60 -> 0.028131512 | P83: =P82/$P$60 -> 0.028131512 | W83: =W82/$W$60 -> 0.028131512 | Y83: =Y82/$Y$60 -> 0.028131512 | AA83: =AA82/$AA$60 -> 0.028131512 | AC83: =AC82/$AC$60 -> 0.028131512 | AE83: =AE82/$AE$60 -> 0.028131512
F85: Budgeted | H85: 5300000 | L85: 10200000 | P85: 7600000 | W85: 200000 | Y85: 2100000 | AA85: 2500000 | AC85: 2500000 | AE85: 2300000
L86: $/SF | M86: =L85/N7 -> 873.43723 | R86: =D76/D60 -> 1.3040164 | W86: 1.3040165
D87: 2220594
C88: GROSS MARGIN
C89: COST % | D89: COST $ | E89: BILLABLE | F89: MARGIN
B90: POTENTIAL BUYOUT SAVINGS | G90: 50/50 SPLIT OR LUMP SUM
B91: GENERAL CONDITIONS | D91: =D65*'Labor Rates Calculator'!I42 -> 2534863.1 | E91: =D65 -> 2991138.4 | F91: =E91-D91 -> 456275.36
B92: SDI | C92: 0.011 | D92: =C92*D64 -> 293606.64 | E92: =D69 -> 400372.69 | F92: =E92-D92 -> 106766.05
B93: GENERAL LIABILITY INSURANCE | C93: 0.011 | D93: =C93*D76 -> 364636.07 | E93: =D72 -> 466555.01 | F93: =E93-D93 -> 101918.94
B94: FEE | F94: =D74 -> 947106.67
E95: TOTAL | F95: =SUM(F90:F94) -> 1612067 | H95: =F95/D76 -> 0.048631331
B97: KEEP THIS TO ONE PAGE !!!!

Sheet 01A Surveying
G1: Hedrick Plug
F2: X | G2: Excluded
B3: BACK TO SUMMARY SHEET | F3: I | G3: Included | H3: Bidder 1 | J3: Bidder 2 | L3: Bidder 3 | N3: Bidder 4 | P3: Bidder5 | R3: Bidder6
A4: Project: | B4: ='Area Calculations'!B4 -> The Club at Ibis Conceptual Estimate | G4: Company
A5: Trade: | B5: Surveying | G5: Contact
A6: CSI Code: | B6: 01A | G6: Phone
A7: Date: | G7: Email
A8: Adjusted Bid | G8: Adjusted Bid | H8: =I62 -> 59815 | J8: =K62 -> 0 | L8: =M62 -> 0 | N8: =O62 -> 0 | P8: =Q62 -> 0 | R8: =S62 -> 0
A9: BID DOCUMENTS: | C9: Plan/ Spec. Package | D9: QTY | E9: U/M | F9: Unit Cost | G9: Subtotal | H9: Yes/No | I9: Price | J9: Yes/No | K9: Price | L9: Yes/No | M9: Price | N9: Yes/No | O9: Price | P9: Yes/No | Q9: Price | R9: Yes/No | S9: Price
B10: Plans By Division
B11: ='Area Calculations'!M62 -> Architectural Drawings by | C11: P
B12: ='Area Calculations'!M63 -> Structural Drawings by | C12: P
B13: ='Area Calculations'!M64 -> MEP FA FP Drawings by | C13: P
B14: ='Area Calculations'!M65 -> Civil Drawings by | C14: P
B15: ='Area Calculations'!M66 -> Land scape Drawings by | C15: P
B16: ='Area Calculations'!M67 -> Kitchen Drawings by | C16: P
B17: ='Area Calculations'!M68 -> Storefront Designer by | C17: P
B18: ='Area Calculations'!M69 -> Geotech report by | C18: P
B19: ='Area Calculations'!M70 -> Specifications | C19: P
B21: Surveying
B22: OCIP Insurance per exhibit
B23: GENERAL INCLUSIONS
B24: INCLUDES ALL SALES TAX
B25: ALL HOISTING & RIGGING REQUIRED TO COMPLETE THIS SCOPE
B26: PROVIDE P&P BONDS
B27: FLORIDA STATE CONTRACTORS LIC.
B28: GENERAL LIABILITY AND WORKERS COMP. INSURANCE LIMITS
B29: STATE AND LOCAL TAXES
B30: COMPASS
B31: SPECIFIC TRADE SCOPE OF WORK REQUIREMENTS
B32: BASE BID
... B36: Phase 1 Racquet Courts
B37: Restroom | C37: AE100 | D37: 1 | E37: LS | F37: 3500 | G37: =D37*F37 -> 3500 | I37: =G37 -> 3500
B38: Sitework | C38: AE100 | D38: ='Cost Summary'!J9 -> 3.49 | E38: AC | F38: 3500 | G38: =D38*F38 -> 12215 | I38: =G38 -> 12215
B40: Phase 2 Bocce & Basketball
B42: Phase 2 New Spa Building
B43: Area | C43: AE101 | D43: ='Cost Summary'!$N$9 -> 2.14 | E43: AC | F43: 15000 | G43: =D43*F43 -> 32100 | I43: =G43 -> 32100
B45: Phase 2 POA Building
B47: Phase 2 New Fitness Building
B48: Area | C48: AE101 | D48: ='Cost Summary'!$R$9 -> 0.96 | E48: AC | F48: 12500 | G48: =D48*F48 -> 12000 | I48: =G48 -> 12000
B50: Phase 3 19th Hole Restaurant
B52: Phase 3 Reno Existing Fitness Building
F58: SUBTOTAL | I58: =SUM(I32:I57) -> 59815 | K58: =SUM(K32:K57) -> 0 | M58: =SUM(M32:M57) -> 0 | O58: =SUM(O32:O57) -> 0 | Q58: =SUM(Q32:Q57) -> 0 | S58: =SUM(S32:S57) -> 0
F59: BOND RATE | H59: 0 | J59: 0 | L59: 0 | N59: 0 | P59: 0 | R59: 0
F60: BOND AMOUNT | I60: =H59*I58 -> 0 | K60: =J59*K58 -> 0 | M60: =L59*M58 -> 0 | O60: =N59*O58 -> 0 | Q60: =P59*Q58 -> 0 | S60: =R59*S58 -> 0
F62: ADJUSTED TOTAL | I62: =SUM(I58:I60) -> 59815 | K62: =SUM(K58:K60) -> 0 | M62: =SUM(M58:M60) -> 0 | O62: =SUM(O58:O60) -> 0 | Q62: =SUM(Q58:Q60) -> 0 | S62: =SUM(S58:S60) -> 0
F63: Cost per SF | I63: =I62/'Area Calculations'!$J$4 -> #DIV/0! | K63: =K62/'Area Calculations'!$J$4 -> #DIV/0! | M63: =M62/'Area Calculations'!$J$4 -> #DIV/0! | O63: =O62/'Area Calculations'!$J$4 -> #DIV/0! | Q63: =Q62/'Area Calculations'!$J$4 -> #DIV/0! | R63: =R62/'Area Calculations'!$J$4 -> #DIV/0! | S63: =S62/'Cost Summary'!#REF! -> #REF!
F64: Cost per Unit | I64: =I62/'Area Calculations'!#REF! -> #REF! | K64: =K62/'Area Calculations'!#REF! -> #REF! | M64: =M62/'Area Calculations'!#REF! -> #REF! | O64: =O62/'Area Calculations'!#REF! -> #REF! | Q64: =Q62/'Area Calculations'!#REF! -> #REF! | R64: =R62/'Area Calculations'!#REF! -> #REF! | S64: =S62/'Cost Summary'!#REF! -> #REF!
A66: QUALIFICATIONS
A70: EXCLUSIONS/OWNER PROVIDED ITEMS:
A74: ALTERNATES:
A78: PROPOSED VE (Provide Clear Description):
A82: FULLY LOADED LABOR RATES
B83: Laborer
B84: Mechanic
B85: Superintendent
B86: Project Manager
A88: SCHEDULE
B89: Prepared shop drawings/submittals
B90: Mobilization
B91: Total duration to complete scope of work
A93: Winner
A94: Company
A95: Contact
A96: Phone
A97: Email
A98: Base Bid | B98: =H8 -> 59815
B100: Need Prequalification
B101: Prequalified

Sheet 01B Material Testing
G1: Hedrick Plug
F2: X | G2: Excluded
B3: BACK TO SUMMARY SHEET | F3: I | G3: Included | H3: Bidder 1 | J3: Bidder 2 | L3: Bidder 3 | N3: Bidder 4 | P3: Bidder5 | R3: Bidder6
A4: Project: | B4: ='Area Calculations'!B4 -> The Club at Ibis Conceptual Estimate | G4: Company
A5: Trade: | B5: Material Testing | G5: Contact
A6: CSI Code: | B6: 01B | G6: Phone
A7: Date: | G7: Email
A8: Adjusted Bid | G8: Adjusted Bid | H8: =I70 -> 0 | J8: =K70 -> 0 | L8: =M70 -> 0 | N8: =O70 -> 0 | P8: =Q70 -> 0 | R8: =S70 -> 0
A9: BID DOCUMENTS: | C9: Plan/ Spec. Package | D9: QTY | E9: U/M | F9: Unit Cost | G9: Subtotal | H9: Yes/No | I9: Price | J9: Yes/No | K9: Price | L9: Yes/No | M9: Price | N9: Yes/No | O9: Price | P9: Yes/No | Q9: Price | R9: Yes/No | S9: Price
B10: Plans By Division
B11: ='Area Calculations'!M62 -> Architectural Drawings by | C11: P
B12: ='Area Calculations'!M63 -> Structural Drawings by | C12: P
B13: ='Area Calculations'!M64 -> MEP FA FP Drawings by | C13: P
B14: ='Area Calculations'!M65 -> Civil Drawings by | C14: P
B15: ='Area Calculations'!M66 -> Land scape Drawings by | C15: P
B16: ='Area Calculations'!M67 -> Kitchen Drawings by | C16: P
B17: ='Area Calculations'!M68 -> Storefront Designer by | C17: P
B18: ='Area Calculations'!M69 -> Geotech report by | C18: P
B19: ='Area Calculations'!M70 -> Specifications | C19: P
B21: Material Testing
B22: GENERAL INCLUSIONS
B23: INCLUDES ALL SALES TAX
B24: ALL HOISTING & RIGGING REQUIRED TO COMPLETE THIS SCOPE
B25: PROVIDE P&P BONDS
B26: FLORIDA STATE CONTRACTORS LIC.
B27: GENERAL LIABILITY AND WORKERS COMP. INSURANCE LIMITS
B28: STATE AND LOCAL TAXES
B29: COMPASS
B30: SPECIFIC TRADE SCOPE OF WORK REQUIREMENTS
B31: BASE BID
F66: SUBTOTAL | I66: =SUM(I22:I65) -> 0 | K66: =SUM(K22:K65) -> 0 | M66: =SUM(M22:M65) -> 0 | O66: =SUM(O22:O65) -> 0 | Q66: =SUM(Q22:Q65) -> 0 | S66: =SUM(S22:S65) -> 0
F67: BOND RATE | H67: 0 | J67: 0 | L67: 0 | N67: 0 | P67: 0 | R67: 0
F68: BOND AMOUNT | I68: =H67*I66 -> 0 | K68: =J67*K66 -> 0 | M68: =L67*M66 -> 0 | O68: =N67*O66 -> 0 | Q68: =P67*Q66 -> 0 | S68: =R67*S66 -> 0
F70: ADJUSTED TOTAL | I70: =SUM(I66:I68) -> 0 | K70: =SUM(K66:K68) -> 0 | M70: =SUM(M66:M68) -> 0 | O70: =SUM(O66:O68) -> 0 | Q70: =SUM(Q66:Q68) -> 0 | S70: =SUM(S66:S68) -> 0
F71: Cost per SF | I71: =I70/'Area Calculations'!$J$4 -> #DIV/0! | K71: =K70/'Area Calculations'!$J$4 -> #DIV/0! | M71: =M70/'Area Calculations'!$J$4 -> #DIV/0! | O71: =O70/'Area Calculations'!$J$4 -> #DIV/0! | Q71: =Q70/'Area Calculations'!$J$4 -> #DIV/0! | S71: =S70/'Area Calculations'!$J$4 -> #DIV/0!
F72: Cost per Unit | I72: =I70/'Area Calculations'!#REF! -> #REF! | K72: =K70/'Area Calculations'!#REF! -> #REF! | M72: =M70/'Area Calculations'!#REF! -> #REF! | O72: =O70/'Area Calculations'!#REF! -> #REF! | Q72: =Q70/'Area Calculations'!#REF! -> #REF! | S72: =S70/'Area Calculations'!#REF! -> #REF!
A74: QUALIFICATIONS
A78: EXCLUSIONS/OWNER PROVIDED ITEMS:
A82: ALTERNATES:
A86: PROPOSED VE (Provide Clear Description):
A90: FULLY LOADED LABOR RATES
B91: Laborer
B92: Mechanic
B93: Superintendent
B94: Project Manager
A96: SCHEDULE
B97: Prepared shop drawings/submittals
B98: Mobilization
B99: Total duration to complete scope of work
A101: Winner
A102: Company
A103: Contact
A104: Phone
A105: Email
A106: Base Bid
B108: Need Prequalification
B109: Prequalified

Sheet 01C Final Cleaning
G1: Hedrick Plug
F2: X | G2: Excluded
B3: BACK TO SUMMARY SHEET | F3: I | G3: Included | H3: Bidder 1 | J3: Bidder 2 | L3: Bidder 3 | N3: Bidder 4 | P3: Bidder5 | R3: Bidder6
A4: Project: | B4: ='Area Calculations'!B4 -> The Club at Ibis Conceptual Estimate | G4: Company
A5: Trade: | B5: Final Cleaning | G5: Contact
A6: CSI Code: | B6: 01C | G6: Phone
A7: Date: | G7: Email
A8: Adjusted Bid | G8: Adjusted Bid | H8: =I70 -> 0 | J8: =K70 -> 0 | L8: =M70 -> 0 | N8: =O70 -> 0 | P8: =Q70 -> 0 | R8: =S70 -> 0
A9: BID DOCUMENTS: | C9: Plan/ Spec. Package | D9: QTY | E9: U/M | F9: Unit Cost | G9: Subtotal | H9: Yes/No | I9: Price | J9: Yes/No | K9: Price | L9: Yes/No | M9: Price | N9: Yes/No | O9: Price | P9: Yes/No | Q9: Price | R9: Yes/No | S9: Price
B10: Plans By Division
B11: ='Area Calculations'!M62 -> Architectural Drawings by | C11: P
B12: ='Area Calculations'!M63 -> Structural Drawings by | C12: P
B13: ='Area Calculations'!M64 -> MEP FA FP Drawings by | C13: P
B14: ='Area Calculations'!M65 -> Civil Drawings by | C14: P
B15: ='Area Calculations'!M66 -> Land scape Drawings by | C15: P
B16: ='Area Calculations'!M67 -> Kitchen Drawings by | C16: P
B17: ='Area Calculations'!M68 -> Storefront Designer by | C17: P
B18: ='Area Calculations'!M69 -> Geotech report by | C18: P
B19: ='Area Calculations'!M70 -> Specifications | C19: P
B21: Final Cleaning
B22: GENERAL INCLUSIONS
B23: INCLUDES ALL SALES TAX
B24: ALL HOISTING & RIGGING REQUIRED TO COMPLETE THIS SCOPE
B25: PROVIDE P&P BONDS
B26: FLORIDA STATE CONTRACTORS LIC.
B27: GENERAL LIABILITY AND WORKERS COMP. INSURANCE LIMITS
B28: STATE AND LOCAL TAXES
B29: COMPASS
B30: SPECIFIC TRADE SCOPE OF WORK REQUIREMENTS
B31: BASE BID
H36: x
H37: i
F66: SUBTOTAL | I66: =SUM(I22:I65) -> 0 | K66: =SUM(K22:K65) -> 0 | M66: =SUM(M22:M65) -> 0 | O66: =SUM(O22:O65) -> 0 | Q66: =SUM(Q22:Q65) -> 0 | S66: =SUM(S22:S65) -> 0
F67: BOND RATE | H67: 0 | J67: 0 | L67: 0 | N67: 0 | P67: 0 | R67: 0
F68: BOND AMOUNT | I68: =H67*I66 -> 0 | K68: =J67*K66 -> 0 | M68: =L67*M66 -> 0 | O68: =N67*O66 -> 0 | Q68: =P67*Q66 -> 0 | S68: =R67*S66 -> 0
F70: ADJUSTED TOTAL | I70: =SUM(I66:I68) -> 0 | K70: =SUM(K66:K68) -> 0 | M70: =SUM(M66:M68) -> 0 | O70: =SUM(O66:O68) -> 0 | Q70: =SUM(Q66:Q68) -> 0 | S70: =SUM(S66:S68) -> 0
F71: Cost per SF | I71: =I70/'Area Calculations'!$J$4 -> #DIV/0! | K71: =K70/'Area Calculations'!$J$4 -> #DIV/0! | M71: =M70/'Area Calculations'!$J$4 -> #DIV/0! | O71: =O70/'Area Calculations'!$J$4 -> #DIV/0! | Q71: =Q70/'Area Calculations'!$J$4 -> #DIV/0! | S71: =S70/'Area Calculations'!$J$4 -> #DIV/0!
F72: Cost per Unit | I72: =I70/'Area Calculations'!#REF! -> #REF! | K72: =K70/'Area Calculations'!#REF! -> #REF! | M72: =M70/'Area Calculations'!#REF! -> #REF! | O72: =O70/'Area Calculations'!#REF! -> #REF! | Q72: =Q70/'Area Calculations'!#REF! -> #REF! | S72: =S70/'Area Calculations'!#REF! -> #REF!
A74: QUALIFICATIONS
A78: EXCLUSIONS/OWNER PROVIDED ITEMS:
A82: ALTERNATES:
A86: PROPOSED VE (Provide Clear Description):
A90: FULLY LOADED LABOR RATES
B91: Laborer
B92: Mechanic
B93: Superintendent
B94: Project Manager
A96: SCHEDULE
B97: Prepared shop drawings/submittals
B98: Mobilization
B99: Total duration to complete scope of work
A101: Winner
A102: Company
A103: Contact
A104: Phone
A105: Email
A106: Base Bid
B108: Need Prequalification
B109: Prequalified

Sheet 02A Demolition
G1: Hedrick Plug
F2: X | G2: Excluded
B3: BACK TO SUMMARY SHEET | F3: I | G3: Included | H3: Bidder 1 | J3: Bidder 2 | L3: Bidder 3 | N3: Bidder 4 | P3: Bidder5 | R3: Bidder6
A4: Project: | B4: ='Area Calculations'!B4 -> The Club at Ibis Conceptual Estimate | G4: Company
A5: Trade: | B5: Demolition | G5: Contact
A6: CSI Code: | B6: 02A | G6: Phone
A7: Date: | G7: Email
A8: Adjusted Bid | G8: Adjusted Bid | H8: =I64 -> 39250 | J8: =K64 -> 0 | L8: =M64 -> 0 | N8: =O64 -> 0 | P8: =Q64 -> 0 | R8: =S64 -> 0
A9: BID DOCUMENTS: | C9: Plan/ Spec. Package | D9: QTY | E9: U/M | F9: Unit Cost | G9: Subtotal | H9: Yes/No | I9: Price | J9: Yes/No | K9: Price | L9: Yes/No | M9: Price | N9: Yes/No | O9: Price | P9: Yes/No | Q9: Price | R9: Yes/No | S9: Price
B10: Plans By Division
B11: ='Area Calculations'!M62 -> Architectural Drawings by | C11: P
B12: ='Area Calculations'!M63 -> Structural Drawings by | C12: P
B13: ='Area Calculations'!M64 -> MEP FA FP Drawings by | C13: P
B14: ='Area Calculations'!M65 -> Civil Drawings by | C14: P
B15: ='Area Calculations'!M66 -> Land scape Drawings by | C15: P | H15: =sum(
B16: ='Area Calculations'!M67 -> Kitchen Drawings by | C16: P
B17: ='Area Calculations'!M68 -> Storefront Designer by | C17: P
B18: ='Area Calculations'!M69 -> Geotech report by | C18: P
B19: ='Area Calculations'!M70 -> Specifications | C19: P
B21: Demolition
B22: OCIP Insurance per exhibit
B23: GENERAL INCLUSIONS
B24: INCLUDES ALL SALES TAX
B25: ALL HOISTING & RIGGING REQUIRED TO COMPLETE THIS SCOPE
B26: PROVIDE P&P BONDS
B27: FLORIDA STATE CONTRACTORS LIC.
B28: GENERAL LIABILITY AND WORKERS COMP. INSURANCE LIMITS
B29: STATE AND LOCAL TAXES
B30: COMPASS
B31: SPECIFIC TRADE SCOPE OF WORK REQUIREMENTS
B32: BASE BID
... B36: Phase 1 Racquet Courts
B37: Tennis Canopies (193SF/EA) | C37: C1.1 | D37: 2 | E37: EA | F37: 2000 | G37: =D37*F37 -> 4000 | I37: =G37 -> 4000
B38: Shed (215SF) | C38: C1.1 | D38: 1 | E38: EA | F38: 2000 | G38: =D38*F38 -> 2000 | I38: =G38 -> 2000
B39: Bathroom Building (311SF) | C39: C1.1 | D39: 1 | E39: LS | F39: 2000 | G39: =D39*F39 -> 2000 | I39: =G39 -> 2000
A40: ADD | B40: Padle court canopy per RFI SD011 | D40: 1 | E40: EA | F40: 2000 | G40: =D40*F40 -> 2000 | I40: =G40 -> 2000
B42: Phase 2 Bocce & Basketball
B44: Phase 2 New Spa Building
B46: Phase 2 POA Building
B48: Phase 2 New Fitness Building
B49: Demo Create openings in existing exterior walls (1) First floor & (1) 2nd floor | C49: AD101,AD102 | D49: 25 | E49: LF | F49: 500 | G49: =D49*F49 -> 12500 | I49: =G49 -> 12500
B50: Demo Exterior wall finishes | C50: AD101, AD102 2/AD301 | D50: 335 | E50: SF | F50: 50 | G50: =D50*F50 -> 16750 | I50: =G50 -> 16750
B53: Phase 3 19th Hole Restaurant
B55: Phase 3 Reno Existing Fitness Building
F60: SUBTOTAL | I60: =SUM(I22:I59) -> 39250 | K60: =SUM(K22:K59) -> 0 | M60: =SUM(M22:M59) -> 0 | O60: =SUM(O22:O59) -> 0 | Q60: =SUM(Q22:Q59) -> 0 | S60: =SUM(S22:S59) -> 0
F61: BOND RATE | H61: 0 | J61: 0 | L61: 0 | N61: 0 | P61: 0 | R61: 0
F62: BOND AMOUNT | I62: =H61*I60 -> 0 | K62: =J61*K60 -> 0 | M62: =L61*M60 -> 0 | O62: =N61*O60 -> 0 | Q62: =P61*Q60 -> 0 | S62: =R61*S60 -> 0
F64: ADJUSTED TOTAL | I64: =SUM(I60:I62) -> 39250 | K64: =SUM(K60:K62) -> 0 | M64: =SUM(M60:M62) -> 0 | O64: =SUM(O60:O62) -> 0 | Q64: =SUM(Q60:Q62) -> 0 | S64: =SUM(S60:S62) -> 0
F65: Cost per SF | I65: =I64/'Area Calculations'!$J$4 -> #DIV/0! | K65: =K64/'Area Calculations'!$J$4 -> #DIV/0! | M65: =M64/'Area Calculations'!$J$4 -> #DIV/0! | O65: =O64/'Area Calculations'!$J$4 -> #DIV/0! | Q65: =Q64/'Area Calculations'!$J$4 -> #DIV/0! | S65: =S64/'Area Calculations'!$J$4 -> #DIV/0!
F66: Cost per Unit | I66: =I64/'Area Calculations'!#REF! -> #REF! | K66: =K64/'Area Calculations'!#REF! -> #REF! | M66: =M64/'Area Calculations'!#REF! -> #REF! | O66: =O64/'Area Calculations'!#REF! -> #REF! | Q66: =Q64/'Area Calculations'!#REF! -> #REF! | S66: =S64/'Area Calculations'!#REF! -> #REF!
A68: QUALIFICATIONS
A72: EXCLUSIONS/OWNER PROVIDED ITEMS:
A76: ALTERNATES:
A80: PROPOSED VE (Provide Clear Description):
A84: FULLY LOADED LABOR RATES
B85: Laborer
B86: Mechanic
B87: Superintendent
B88: Project Manager
A90: SCHEDULE
B91: Prepared shop drawings/submittals
B92: Mobilization
B93: Total duration to complete scope of work
A95: Winner
A96: Company
A97: Contact
A98: Phone
A99: Email
A100: Base Bid | B100: =H8 -> 39250
B102: Need Prequalification
B103: Prequalified

Sheet 02B Abatement
G1: Hedrick Plug
F2: X | G2: Excluded
B3: BACK TO SUMMARY SHEET | F3: I | G3: Included | H3: Bidder 1 | J3: Bidder 2 | L3: Bidder 3 | N3: Bidder 4 | P3: Bidder5 | R3: Bidder6
A4: Project: | B4: ='Area Calculations'!B4 -> The Club at Ibis Conceptual Estimate | G4: Company
A5: Trade: | B5: Abatement | G5: Contact
A6: CSI Code: | B6: 02B | G6: Phone
A7: Date: | G7: Email
A8: Adjusted Bid | G8: Adjusted Bid | H8: =I57 -> 0 | J8: =K57 -> 0 | L8: =M57 -> 0 | N8: =O57 -> 0 | P8: =Q57 -> 0 | R8: =S57 -> 0
A9: BID DOCUMENTS: | C9: Plan/ Spec. Package | D9: QTY | E9: U/M | F9: Unit Cost | G9: Subtotal | H9: Yes/No | I9: Price | J9: Yes/No | K9: Price | L9: Yes/No | M9: Price | N9: Yes/No | O9: Price | P9: Yes/No | Q9: Price | R9: Yes/No | S9: Price
B10: Plans By Division
B11: ='Area Calculations'!M62 -> Architectural Drawings by | C11: P
B12: ='Area Calculations'!M63 -> Structural Drawings by | C12: P
B13: ='Area Calculations'!M64 -> MEP FA FP Drawings by | C13: P
B14: ='Area Calculations'!M65 -> Civil Drawings by | C14: P
B15: ='Area Calculations'!M66 -> Land scape Drawings by | C15: P
B16: ='Area Calculations'!M67 -> Kitchen Drawings by | C16: P
B17: ='Area Calculations'!M68 -> Storefront Designer by | C17: P
B18: ='Area Calculations'!M69 -> Geotech report by | C18: P
B19: ='Area Calculations'!M70 -> Specifications | C19: P
B21: Abatement
B22: OCIP Insurance per exhibit
B23: GENERAL INCLUSIONS
B24: INCLUDES ALL SALES TAX
B25: ALL HOISTING & RIGGING REQUIRED TO COMPLETE THIS SCOPE
B26: PROVIDE P&P BONDS
B27: FLORIDA STATE CONTRACTORS LIC.
B28: GENERAL LIABILITY AND WORKERS COMP. INSURANCE LIMITS
B29: STATE AND LOCAL TAXES
B30: COMPASS
B31: SPECIFIC TRADE SCOPE OF WORK REQUIREMENTS
B32: BASE BID
H35: x
F53: SUBTOTAL | I53: =SUM(I22:I52) -> 0 | K53: =SUM(K22:K52) -> 0 | M53: =SUM(M22:M52) -> 0 | O53: =SUM(O22:O52) -> 0 | Q53: =SUM(Q22:Q52) -> 0 | S53: =SUM(S22:S52) -> 0
F54: BOND RATE | H54: 0 | J54: 0 | L54: 0 | N54: 0 | P54: 0 | R54: 0
F55: BOND AMOUNT | I55: =H54*I53 -> 0 | K55: =J54*K53 -> 0 | M55: =L54*M53 -> 0 | O55: =N54*O53 -> 0 | Q55: =P54*Q53 -> 0 | S55: =R54*S53 -> 0
F57: ADJUSTED TOTAL | I57: =SUM(I53:I55) -> 0 | K57: =SUM(K53:K55) -> 0 | M57: =SUM(M53:M55) -> 0 | O57: =SUM(O53:O55) -> 0 | Q57: =SUM(Q53:Q55) -> 0 | S57: =SUM(S53:S55) -> 0
F58: Cost per SF | I58: =I57/'Area Calculations'!$J$4 -> #DIV/0! | K58: =K57/'Area Calculations'!$J$4 -> #DIV/0! | M58: =M57/'Area Calculations'!$J$4 -> #DIV/0! | O58: =O57/'Area Calculations'!$J$4 -> #DIV/0! | Q58: =Q57/'Area Calculations'!$J$4 -> #DIV/0! | S58: =S57/'Area Calculations'!$J$4 -> #DIV/0!
F59: Cost per Unit | I59: =I57/'Area Calculations'!#REF! -> #REF! | K59: =K57/'Area Calculations'!#REF! -> #REF! | M59: =M57/'Area Calculations'!#REF! -> #REF! | O59: =O57/'Area Calculations'!#REF! -> #REF! | Q59: =Q57/'Area Calculations'!#REF! -> #REF! | S59: =S57/'Area Calculations'!#REF! -> #REF!
A61: QUALIFICATIONS
A65: EXCLUSIONS/OWNER PROVIDED ITEMS:
A69: ALTERNATES:
A73: PROPOSED VE (Provide Clear Description):
A77: FULLY LOADED LABOR RATES
B78: Laborer
B79: Mechanic
B80: Superintendent
B81: Project Manager
A83: SCHEDULE
B84: Prepared shop drawings/submittals
B85: Mobilization
B86: Total duration to complete scope of work
A88: Winner
A89: Company
A90: Contact
A91: Phone
A92: Email
A93: Base Bid
B95: Need Prequalification
B96: Prequalified

Sheet 03A Concrete
G1: Hedrick Plug
F2: X | G2: Excluded
B3: BACK TO SUMMARY SHEET | F3: I | G3: Included | H3: Bidder 1 | J3: Bidder2 | L3: Bidder 3 | N3: Bidder 4 | P3: Bidder 5 | R3: Bidder 6
A4: Project: | B4: ='Area Calculations'!B4 -> The Club at Ibis Conceptual Estimate | G4: Company
A5: Trade: | B5: Concrete | G5: Contact
A6: CSI Code: | B6: 03A | G6: Phone
A7: Date: | G7: Email
A8: Adjusted Bid | G8: Adjusted Bid | H8: =I68 -> 1749421 | J8: =K68 -> 0 | L8: =M68 -> 0 | N8: =O68 -> 0 | P8: =Q68 -> 0 | R8: =S68 -> 0
A9: BID DOCUMENTS: | C9: Plan/ Spec. Package | D9: QTY | E9: U/M | F9: Unit Cost | G9: Subtotal | H9: Yes/No | I9: Price | J9: Yes/No | K9: Price | L9: Yes/No | M9: Price | N9: Yes/No | O9: Price | P9: Yes/No | Q9: Price | R9: Yes/No | S9: Price
B10: Plans By Division
B11: ='Area Calculations'!M62 -> Architectural Drawings by | C11: P
B12: ='Area Calculations'!M63 -> Structural Drawings by | C12: P
B13: ='Area Calculations'!M64 -> MEP FA FP Drawings by | C13: P
B14: ='Area Calculations'!M65 -> Civil Drawings by | C14: P
B15: ='Area Calculations'!M66 -> Land scape Drawings by | C15: P
B16: ='Area Calculations'!M67 -> Kitchen Drawings by
B17: ='Area Calculations'!M68 -> Storefront Designer by
B18: ='Area Calculations'!M69 -> Geotech report by | C18: P
B19: ='Area Calculations'!M70 -> Specifications
B22: Concrete
B23: GENERAL INCLUSIONS
B24: INCLUDES ALL SALES TAX
B25: ALL HOISTING & RIGGING REQUIRED TO COMPLETE THIS SCOPE
B26: PROVIDE P&P BONDS
B27: FLORIDA STATE CONTRACTORS LIC.
B28: GENERAL LIABILITY AND WORKERS COMP. INSURANCE LIMITS
B29: STATE AND LOCAL TAXES
B30: COMPASS
B31: SPECIFIC TRADE SCOPE OF WORK REQUIREMENTS
B32: BASE BID
B34: Phase 1 Interior Club House Renovations
B36: Phase 1 Racquet Courts
B37: New Restroom Building | C37: C2.1 | D37: ='Cost Summary'!$J$7 -> 663 | E37: SF | F37: 60 | G37: =D37*F37 -> 39780 | I37: =G37 -> 39780
B38: Precast Lintels | C38: AE100 | D38: 2 | E38: EA | F38: 500 | G38: =D38*F38 -> 1000 | I38: =G38 -> 1000
A39: ADD | B39: Covered Pickleball courts | C39: C2.1 | D39: 11868 | E39: SF | F39: 5 | G39: =D39*F39 -> 59340 | I39: =G39 -> 59340
B40: 5 areas per RFI SD007
B41: Covered Seating area 22'x78' West of Tennis courts | C41: SP | D41: 8 | E41: EA | F41: 1750 | G41: =D41*F41 -> 14000 | I41: =G41 -> 14000
A42: ADD | B42: Covered Seating area 15'x30' West of Pickleball Courts per RFI SD007 | C42: SP | D42: 4 | E42: EA | F42: =F41 -> 1750 | G42: =D42*F42 -> 7000 | I42: =G42 -> 7000
A43: ADD | B43: Covered Seating area 35'x55' East of Pickleball Courts per RFI SD007 | C43: SP | D43: 8 | E43: EA | F43: =F41 -> 1750 | G43: =D43*F43 -> 14000 | I43: =G43 -> 14000
A44: ADD | B44: Padel Courts Seating area | C44: SP | D44: 8 | E44: EA | F44: =F41 -> 1750 | G44: =D44*F44 -> 14000 | I44: =G44 -> 14000
B46: Phase 2 Bocce & Basketball
B48: Phase 2 New Spa Building
B49: Area | C49: AE101 | D49: ='Cost Summary'!$N$7 -> 11678 | E49: SF | F49: 67 | G49: =D49*F49 -> 782426 | I49: =G49 -> 782426
B51: Phase 2 POA Building
B53: Phase 2 New Fitness Building
B54: Area (including Pavilion) | C54: AE101, AE102 | D54: ='Cost Summary'!$R$7 -> 11225 | E54: SF | F54: =F49 -> 67 | G54: =D54*F54 -> 752075 | I54: =G54 -> 752075
B55: Site steps to cart path (4 steps) | C55: AE101 | D55: 44 | E55: SF | F55: 200 | G55: =D55*F55 -> 8800 | I55: =G55 -> 8800
B56: Retaining wall 4' height | C56: SP | D56: 114 | E56: LF | F56: 500 | G56: =D56*F56 -> 57000 | I56: =G56 -> 57000
B58: Phase 3 19th Hole Restaurant
B60: Phase 3 Reno Existing Fitness Building
F64: SUBTOTAL | I64: =SUM(I25:I63) -> 1749421 | K64: =SUM(K25:K63) -> 0 | M64: =SUM(M25:M63) -> 0 | O64: =SUM(O25:O63) -> 0 | Q64: =SUM(Q25:Q63) -> 0 | S64: =SUM(S25:S63) -> 0
F65: BOND RATE | H65: 0 | J65: 0 | L65: 0 | N65: 0 | P65: 0 | R65: 0
F66: BOND AMOUNT | I66: =H65*I64 -> 0 | K66: =J65*K64 -> 0 | M66: =L65*M64 -> 0 | O66: =N65*O64 -> 0 | Q66: =P65*Q64 -> 0 | S66: =R65*S64 -> 0
F68: ADJUSTED TOTAL | I68: =SUM(I64:I67) -> 1749421 | K68: =SUM(K64:K67) -> 0 | M68: =SUM(M64:M66) -> 0 | O68: =SUM(O64:O66) -> 0 | Q68: =SUM(Q64:Q66) -> 0 | S68: =SUM(S64:S66) -> 0
F69: Cost per SF | I69: =I68/'Area Calculations'!$J$4 -> #DIV/0! | K69: =K68/'Area Calculations'!$J$4 -> #DIV/0! | M69: =M68/'Area Calculations'!$J$4 -> #DIV/0! | O69: =O68/'Area Calculations'!$J$4 -> #DIV/0! | Q69: =Q68/'Area Calculations'!$J$4 -> #DIV/0! | S69: =S68/'Area Calculations'!$J$4 -> #DIV/0!
F70: Cost per Unit | I70: =I68/'Area Calculations'!#REF! -> #REF! | K70: =K68/'Area Calculations'!#REF! -> #REF! | M70: =M68/'Area Calculations'!#REF! -> #REF! | O70: =O68/'Area Calculations'!#REF! -> #REF! | Q70: =Q68/'Area Calculations'!#REF! -> #REF! | S70: =S68/'Area Calculations'!#REF! -> #REF!
A72: QUALIFICATIONS
A76: EXCLUSIONS/OWNER PROVIDED ITEMS:
A80: ALTERNATES:
A84: PROPOSED VE (Provide Clear Description):
A88: UNIT RATES
A94: FULLY LOADED LABOR RATES
B95: Laborer
B96: Mechanic
B97: Superintendent
B98: Project Manager
A100: SCHEDULE
B101: Prepared shop drawings/submittals
B102: Mobilization
B103: Total duration to complete scope of work
A105: Winner
A106: Company
A107: Contact
A108: Phone
A109: Email
A110: Base Bid | B110: =H8 -> 1749421
B112: Need Prequalification
B113: Prequalified

Sheet 03B Precast Hollow Core
G1: Hedrick Plug
F2: X | G2: Excluded
B3: BACK TO SUMMARY SHEET | F3: I | G3: Included | H3: Bidder1 | J3: Bidder 2 | L3: Bidder 3 | N3: Bidder 4 | P3: Bidder 5 | R3: Bidder 6
A4: Project: | B4: ='Area Calculations'!B4 -> The Club at Ibis Conceptual Estimate | G4: Company
A5: Trade: | B5: Precast Hollow Core | G5: Contact
A6: CSI Code: | B6: 03B | G6: Phone
A7: Date: | G7: Email
A8: Adjusted Bid | G8: Adjusted Bid | H8: =I46 -> 0 | J8: =K46 -> 0 | L8: =M46 -> 0 | N8: =O46 -> 0 | P8: =Q46 -> 0 | R8: =S46 -> 0
A9: BID DOCUMENTS: | C9: Plan/ Spec. Package | D9: QTY | E9: U/M | F9: Unit Cost | G9: Subtotal | H9: Yes/No | I9: Price | J9: Yes/No | K9: Price | L9: Yes/No | M9: Price | N9: Yes/No | O9: Price | P9: Yes/No | Q9: Price | R9: Yes/No | S9: Price
B10: Plans By Division
B11: ='Area Calculations'!M62 -> Architectural Drawings by | C11: P
B12: ='Area Calculations'!M63 -> Structural Drawings by | C12: P
B13: ='Area Calculations'!M64 -> MEP FA FP Drawings by | C13: P
B14: ='Area Calculations'!M65 -> Civil Drawings by | C14: P
B15: ='Area Calculations'!M66 -> Land scape Drawings by | C15: P
B16: ='Area Calculations'!M67 -> Kitchen Drawings by
B17: ='Area Calculations'!M68 -> Storefront Designer by
B18: ='Area Calculations'!M69 -> Geotech report by | C18: P
B19: ='Area Calculations'!M70 -> Specifications
B21: Precast Hollow Core
B22: GENERAL INCLUSIONS
B23: INCLUDES ALL SALES TAX
B24: ALL HOISTING & RIGGING REQUIRED TO COMPLETE THIS SCOPE
B25: PROVIDE P&P BONDS
B26: FLORIDA STATE CONTRACTORS LIC.
B27: GENERAL LIABILITY AND WORKERS COMP. INSURANCE LIMITS
B28: STATE AND LOCAL TAXES
B29: COMPASS
B30: SPECIFIC TRADE SCOPE OF WORK REQUIREMENTS
B31: BASE BID
B32: Building SF
L34: i
F42: SUBTOTAL | I42: =SUM(I24:I41) -> 0 | K42: =SUM(K24:K41) -> 0 | M42: =SUM(M24:M41) -> 0 | O42: =SUM(O24:O41) -> 0 | Q42: =SUM(Q24:Q41) -> 0 | S42: =SUM(S24:S41) -> 0
F43: BOND RATE | H43: 0 | J43: 0 | L43: 0 | N43: 0 | P43: 0 | R43: 0
F44: BOND AMOUNT | I44: =H43*I42 -> 0 | K44: =J43*K42 -> 0 | M44: =L43*M42 -> 0 | O44: =N43*O42 -> 0 | Q44: =P43*Q42 -> 0 | S44: =R43*S42 -> 0
F46: ADJUSTED TOTAL | I46: =SUM(I42:I44) -> 0 | K46: =SUM(K42:K44) -> 0 | M46: =SUM(M42:M44) -> 0 | O46: =SUM(O42:O44) -> 0 | Q46: =SUM(Q42:Q44) -> 0 | S46: =SUM(S42:S44) -> 0
F47: Cost per SF | I47: =I46/'Area Calculations'!$J$4 -> #DIV/0! | K47: =K46/'Area Calculations'!$J$4 -> #DIV/0! | M47: =M46/'Area Calculations'!$J$4 -> #DIV/0! | O47: =O46/'Area Calculations'!$J$4 -> #DIV/0! | Q47: =Q46/'Area Calculations'!$J$4 -> #DIV/0! | S47: =S46/'Area Calculations'!$J$4 -> #DIV/0!
F48: Cost per Unit | I48: =I46/'Area Calculations'!#REF! -> #REF! | K48: =K46/'Area Calculations'!#REF! -> #REF! | M48: =M46/'Area Calculations'!#REF! -> #REF! | O48: =O46/'Area Calculations'!#REF! -> #REF! | Q48: =Q46/'Area Calculations'!#REF! -> #REF! | S48: =S46/'Area Calculations'!#REF! -> #REF!
A50: QUALIFICATIONS
A54: EXCLUSIONS/OWNER PROVIDED ITEMS:
A58: ALTERNATES:
A62: PROPOSED VE (Provide Clear Description):
A66: FULLY LOADED LABOR RATES
B67: Laborer
B68: Mechanic
B69: Superintendent
B70: Project Manager
A72: SCHEDULE
B73: Prepared shop drawings/submittals
B74: Mobilization
B75: Total duration to complete scope of work
A77: Winner
A78: Company
A79: Contact
A80: Phone
A81: Email
A82: Base Bid
B84: Need Prequalification
B85: Prequalified

Sheet 03C Architectural Precast
G1: Hedrick Plug
F2: X | G2: Excluded
B3: BACK TO SUMMARY SHEET | F3: I | G3: Included | H3: Bidder1 | J3: Bidder 2 | L3: Bidder 3 | N3: Bidder 4 | P3: Bidder 5 | R3: Bidder 6
A4: Project: | B4: ='Area Calculations'!B4 -> The Club at Ibis Conceptual Estimate | G4: Company
A5: Trade: | B5: Architectural Precast | G5: Contact
A6: CSI Code: | B6: 03C | G6: Phone
A7: Date: | G7: Email
A8: Adjusted Bid | G8: Adjusted Bid | H8: =I50 -> 0 | J8: =K50 -> 0 | L8: =M50 -> 0 | N8: =O50 -> 0 | P8: =Q50 -> 0 | R8: =S50 -> 0
A9: BID DOCUMENTS: | C9: Plan/ Spec. Package | D9: QTY | E9: U/M | F9: Unit Cost | G9: Subtotal | H9: Yes/No | I9: Price | J9: Yes/No | K9: Price | L9: Yes/No | M9: Price | N9: Yes/No | O9: Price | P9: Yes/No | Q9: Price | R9: Yes/No | S9: Price
B10: Plans By Division
B11: ='Area Calculations'!M62 -> Architectural Drawings by | C11: P
B12: ='Area Calculations'!M63 -> Structural Drawings by | C12: P
B13: ='Area Calculations'!M64 -> MEP FA FP Drawings by | C13: P
B14: ='Area Calculations'!M65 -> Civil Drawings by | C14: P
B15: ='Area Calculations'!M66 -> Land scape Drawings by | C15: P
B16: ='Area Calculations'!M67 -> Kitchen Drawings by
B17: ='Area Calculations'!M68 -> Storefront Designer by
B18: ='Area Calculations'!M69 -> Geotech report by | C18: P
B19: ='Area Calculations'!M70 -> Specifications
B21: Architectural Precast
B22: GENERAL INCLUSIONS
B23: INCLUDES ALL SALES TAX
B24: ALL HOISTING & RIGGING REQUIRED TO COMPLETE THIS SCOPE
B25: PROVIDE P&P BONDS
B26: FLORIDA STATE CONTRACTORS LIC.
B27: GENERAL LIABILITY AND WORKERS COMP. INSURANCE LIMITS
B28: STATE AND LOCAL TAXES
B29: COMPASS
B30: SPECIFIC TRADE SCOPE OF WORK REQUIREMENTS
B31: BASE BID
B32: Building SF
H38: i
F46: SUBTOTAL | I46: =SUM(I24:I45) -> 0 | K46: =SUM(K24:K45) -> 0 | M46: =SUM(M24:M45) -> 0 | O46: =SUM(O24:O45) -> 0 | Q46: =SUM(Q24:Q45) -> 0 | S46: =SUM(S24:S45) -> 0
F47: BOND RATE | H47: 0 | J47: 0 | L47: 0 | N47: 0 | P47: 0 | R47: 0
F48: BOND AMOUNT | I48: =H47*I46 -> 0 | K48: =J47*K46 -> 0 | M48: =L47*M46 -> 0 | O48: =N47*O46 -> 0 | Q48: =P47*Q46 -> 0 | S48: =R47*S46 -> 0
F50: ADJUSTED TOTAL | I50: =SUM(I46:I48) -> 0 | K50: =SUM(K46:K48) -> 0 | M50: =SUM(M46:M48) -> 0 | O50: =SUM(O46:O48) -> 0 | Q50: =SUM(Q46:Q48) -> 0 | S50: =SUM(S46:S48) -> 0
F51: Cost per SF | I51: =I50/'Area Calculations'!$J$4 -> #DIV/0! | K51: =K50/'Area Calculations'!$J$4 -> #DIV/0! | M51: =M50/'Area Calculations'!$J$4 -> #DIV/0! | O51: =O50/'Area Calculations'!$J$4 -> #DIV/0! | Q51: =Q50/'Area Calculations'!$J$4 -> #DIV/0! | S51: =S50/'Area Calculations'!$J$4 -> #DIV/0!
F52: Cost per Unit | I52: =I50/'Area Calculations'!#REF! -> #REF! | K52: =K50/'Area Calculations'!#REF! -> #REF! | M52: =M50/'Area Calculations'!#REF! -> #REF! | O52: =O50/'Area Calculations'!#REF! -> #REF! | Q52: =Q50/'Area Calculations'!#REF! -> #REF! | S52: =S50/'Area Calculations'!#REF! -> #REF!
A54: QUALIFICATIONS
A58: EXCLUSIONS/OWNER PROVIDED ITEMS:
A62: ALTERNATES:
A66: PROPOSED VE (Provide Clear Description):
A70: FULLY LOADED LABOR RATES
B71: Laborer
B72: Mechanic
B73: Superintendent
B74: Project Manager
A76: SCHEDULE
B77: Prepared shop drawings/submittals
B78: Mobilization
B79: Total duration to complete scope of work
A81: Winner
A82: Company
A83: Contact
A84: Phone
A85: Email
A86: Base Bid
B88: Need Prequalification
B89: Prequalified

Sheet 03C Concrete Tilt Up
G1: Hedrick Plug
F2: X | G2: Excluded
B3: BACK TO SUMMARY SHEET | F3: I | G3: Included | H3: Bidder1 | J3: Bidder 2 | L3: Bidder 3 | N3: Bidder 4 | P3: Bidder 5 | R3: Bidder 6
A4: Project: | B4: ='Area Calculations'!B4 -> The Club at Ibis Conceptual Estimate | G4: Company
A5: Trade: | B5: Concrete Tilt Up | G5: Contact
A6: CSI Code: | B6: 03C | G6: Phone
A7: Date: | G7: Email
A8: Adjusted Bid | G8: Adjusted Bid | H8: =I46 -> 0 | J8: =K46 -> 0 | L8: =M46 -> 0 | N8: =O46 -> 0 | P8: =Q46 -> 0 | R8: =S46 -> 0
A9: BID DOCUMENTS: | C9: Plan/ Spec. Package | D9: QTY | E9: U/M | F9: Unit Cost | G9: Subtotal | H9: Yes/No | I9: Price | J9: Yes/No | K9: Price | L9: Yes/No | M9: Price | N9: Yes/No | O9: Price | P9: Yes/No | Q9: Price | R9: Yes/No | S9: Price
B10: Plans By Division
B11: ='Area Calculations'!M62 -> Architectural Drawings by | C11: P
B12: ='Area Calculations'!M63 -> Structural Drawings by | C12: P
B13: ='Area Calculations'!M64 -> MEP FA FP Drawings by | C13: P
B14: ='Area Calculations'!M65 -> Civil Drawings by | C14: P
B15: ='Area Calculations'!M66 -> Land scape Drawings by | C15: P
B16: ='Area Calculations'!M67 -> Kitchen Drawings by
B17: ='Area Calculations'!M68 -> Storefront Designer by
B18: ='Area Calculations'!M69 -> Geotech report by | C18: P
B19: ='Area Calculations'!M70 -> Specifications
B21: Concrete Tilt Up
B22: GENERAL INCLUSIONS
B23: INCLUDES ALL SALES TAX
B24: ALL HOISTING & RIGGING REQUIRED TO COMPLETE THIS SCOPE
B25: PROVIDE P&P BONDS
B26: FLORIDA STATE CONTRACTORS LIC.
B27: GENERAL LIABILITY AND WORKERS COMP. INSURANCE LIMITS
B28: STATE AND LOCAL TAXES
B29: COMPASS
B30: SPECIFIC TRADE SCOPE OF WORK REQUIREMENTS
B31: BASE BID
B32: Building SF
L34: i
F42: SUBTOTAL | I42: =SUM(I24:I41) -> 0 | K42: =SUM(K24:K41) -> 0 | M42: =SUM(M24:M41) -> 0 | O42: =SUM(O24:O41) -> 0 | Q42: =SUM(Q24:Q41) -> 0 | S42: =SUM(S24:S41) -> 0
F43: BOND RATE | H43: 0 | J43: 0 | L43: 0 | N43: 0 | P43: 0 | R43: 0
F44: BOND AMOUNT | I44: =H43*I42 -> 0 | K44: =J43*K42 -> 0 | M44: =L43*M42 -> 0 | O44: =N43*O42 -> 0 | Q44: =P43*Q42 -> 0 | S44: =R43*S42 -> 0
F46: ADJUSTED TOTAL | I46: =SUM(I42:I44) -> 0 | K46: =SUM(K42:K44) -> 0 | M46: =SUM(M42:M44) -> 0 | O46: =SUM(O42:O44) -> 0 | Q46: =SUM(Q42:Q44) -> 0 | S46: =SUM(S42:S44) -> 0
F47: Cost per SF | I47: =I46/'Area Calculations'!$J$4 -> #DIV/0! | K47: =K46/'Area Calculations'!$J$4 -> #DIV/0! | M47: =M46/'Area Calculations'!$J$4 -> #DIV/0! | O47: =O46/'Area Calculations'!$J$4 -> #DIV/0! | Q47: =Q46/'Area Calculations'!$J$4 -> #DIV/0! | S47: =S46/'Area Calculations'!$J$4 -> #DIV/0!
F48: Cost per Unit | I48: =I46/'Area Calculations'!#REF! -> #REF! | K48: =K46/'Area Calculations'!#REF! -> #REF! | M48: =M46/'Area Calculations'!#REF! -> #REF! | O48: =O46/'Area Calculations'!#REF! -> #REF! | Q48: =Q46/'Area Calculations'!#REF! -> #REF! | S48: =S46/'Area Calculations'!#REF! -> #REF!
A50: QUALIFICATIONS
A54: EXCLUSIONS/OWNER PROVIDED ITEMS:
A58: ALTERNATES:
A62: PROPOSED VE (Provide Clear Description):
A66: FULLY LOADED LABOR RATES
B67: Laborer
B68: Mechanic
B69: Superintendent
B70: Project Manager
A72: SCHEDULE
B73: Prepared shop drawings/submittals
B74: Mobilization
B75: Total duration to complete scope of work
A77: Winner
A78: Company
A79: Contact
A80: Phone
A81: Email
A82: Base Bid
B84: Need Prequalification
B85: Prequalified

Sheet 03D Structural Precast
G1: Hedrick Plug
F2: X | G2: Excluded
B3: BACK TO SUMMARY SHEET | F3: I | G3: Included | H3: Bidder1 | J3: Bidder 2 | L3: Bidder 3 | N3: Bidder 4 | P3: Bidder 5 | R3: Bidder 6
A4: Project: | B4: ='Area Calculations'!B4 -> The Club at Ibis Conceptual Estimate | G4: Company
A5: Trade: | B5: Structural Precast | G5: Contact
A6: CSI Code: | B6: 03D | G6: Phone
A7: Date: | G7: Email
A8: Adjusted Bid | G8: Adjusted Bid | H8: =I96 -> 0 | J8: =K96 -> 0 | L8: =M96 -> 0 | N8: =O96 -> 0 | P8: =Q96 -> 0 | R8: =S96 -> 0
A9: BID DOCUMENTS: | C9: Plan/ Spec. Package | D9: QTY | E9: U/M | F9: Unit Cost | G9: Subtotal | H9: Yes/No | I9: Price | J9: Yes/No | K9: Price | L9: Yes/No | M9: Price | N9: Yes/No | O9: Price | P9: Yes/No | Q9: Price | R9: Yes/No | S9: Price
B10: Plans By Division
B11: ='Area Calculations'!M62 -> Architectural Drawings by | C11: P
B12: ='Area Calculations'!M63 -> Structural Drawings by | C12: P
B13: ='Area Calculations'!M64 -> MEP FA FP Drawings by | C13: P
B14: ='Area Calculations'!M65 -> Civil Drawings by | C14: P
B15: ='Area Calculations'!M66 -> Land scape Drawings by | C15: P
B16: ='Area Calculations'!M67 -> Kitchen Drawings by
B17: ='Area Calculations'!M68 -> Storefront Designer by
B18: ='Area Calculations'!M69 -> Geotech report by | C18: P
B19: ='Area Calculations'!M70 -> Specifications
B21: Structural Precast
B22: GENERAL INCLUSIONS
B23: INCLUDES ALL SALES TAX
B24: ALL HOISTING & RIGGING REQUIRED TO COMPLETE THIS SCOPE
B25: PROVIDE P&P BONDS
B26: FLORIDA STATE CONTRACTORS LIC.
B27: GENERAL LIABILITY AND WORKERS COMP. INSURANCE LIMITS
B28: STATE AND LOCAL TAXES
B29: COMPASS
B30: SPECIFIC TRADE SCOPE OF WORK REQUIREMENTS
B31: BASE BID
B32: Building SF
... B41: Dumpster Enclosure
B42: Monument Sign - | H42: i
B44: SLAB-ON-GRADE
B45: 5" Slab w/ WWF 6x6 w.2.9xw2.9
B46: a. Soil poisoning and pre-treat
B47: b. Fine grading building pad
B48: d. F&I rebar, as per plans
B49: e. F&I wire mesh, as per plans
B50: f. 4,000 PSI
B51: g. Sawcut constr. / control joints
B52: h. Finish slab to FF25/FL17
B53: i. Leave out strip, compact
B54: j. Patch slab after tilt operations
B55: k. Provide curing compound
... B85: Panel structural engineering
F92: SUBTOTAL | I92: =SUM(I24:I91) -> 0 | K92: =SUM(K24:K91) -> 0 | M92: =SUM(M24:M91) -> 0 | O92: =SUM(O24:O91) -> 0 | Q92: =SUM(Q24:Q91) -> 0 | S92: =SUM(S24:S91) -> 0
F93: BOND RATE | H93: 0 | J93: 0 | L93: 0 | N93: 0 | P93: 0 | R93: 0
F94: BOND AMOUNT | I94: =H93*I92 -> 0 | K94: =J93*K92 -> 0 | M94: =L93*M92 -> 0 | O94: =N93*O92 -> 0 | Q94: =P93*Q92 -> 0 | S94: =R93*S92 -> 0
F96: ADJUSTED TOTAL | I96: =SUM(I92:I94) -> 0 | K96: =SUM(K92:K94) -> 0 | M96: =SUM(M92:M94) -> 0 | O96: =SUM(O92:O94) -> 0 | Q96: =SUM(Q92:Q94) -> 0 | S96: =SUM(S92:S94) -> 0
F97: Cost per SF | I97: =I96/'Area Calculations'!$J$4 -> #DIV/0! | K97: =K96/'Area Calculations'!$J$4 -> #DIV/0! | M97: =M96/'Area Calculations'!$J$4 -> #DIV/0! | O97: =O96/'Area Calculations'!$J$4 -> #DIV/0! | Q97: =Q96/'Area Calculations'!$J$4 -> #DIV/0! | S97: =S96/'Area Calculations'!$J$4 -> #DIV/0!
F98: Cost per Unit | I98: =I96/'Area Calculations'!#REF! -> #REF! | K98: =K96/'Area Calculations'!#REF! -> #REF! | M98: =M96/'Area Calculations'!#REF! -> #REF! | O98: =O96/'Area Calculations'!#REF! -> #REF! | Q98: =Q96/'Area Calculations'!#REF! -> #REF! | S98: =S96/'Area Calculations'!#REF! -> #REF!
A100: QUALIFICATIONS
A104: EXCLUSIONS/OWNER PROVIDED ITEMS:
A108: ALTERNATES:
A112: PROPOSED VE (Provide Clear Description):
A116: FULLY LOADED LABOR RATES
B117: Laborer
B118: Mechanic
B119: Superintendent
B120: Project Manager
A122: SCHEDULE
B123: Prepared shop drawings/submittals
B124: Mobilization
B125: Total duration to complete scope of work
A127: Winner
A128: Company
A129: Contact
A130: Phone
A131: Email
A132: Base Bid
B134: Need Prequalification
B135: Prequalified

Sheet 03E Cranes and Hoisting
G1: Hedrick Plug
F2: X | G2: Excluded
B3: BACK TO SUMMARY SHEET | F3: I | G3: Included | H3: Bidder1 | J3: Bidder 2 | L3: Bidder 3 | N3: Bidder 4 | P3: Bidder 5 | R3: Bidder 6
A4: Project: | B4: ='Area Calculations'!B4 -> The Club at Ibis Conceptual Estimate | G4: Company
A5: Trade: | B5: Cranes and Hoisting | G5: Contact
A6: CSI Code: | B6: 03E | G6: Phone
A7: Date: | G7: Email
A8: Adjusted Bid | G8: Adjusted Bid | H8: =I96 -> 0 | J8: =K96 -> 0 | L8: =M96 -> 0 | N8: =O96 -> 0 | P8: =Q96 -> 0 | R8: =S96 -> 0
A9: BID DOCUMENTS: | C9: Plan/ Spec. Package | D9: QTY | E9: U/M | F9: Unit Cost | G9: Subtotal | H9: Yes/No | I9: Price | J9: Yes/No | K9: Price | L9: Yes/No | M9: Price | N9: Yes/No | O9: Price | P9: Yes/No | Q9: Price | R9: Yes/No | S9: Price
B10: Plans By Division
B11: ='Area Calculations'!M62 -> Architectural Drawings by | C11: P
B12: ='Area Calculations'!M63 -> Structural Drawings by | C12: P
B13: ='Area Calculations'!M64 -> MEP FA FP Drawings by | C13: P
B14: ='Area Calculations'!M65 -> Civil Drawings by | C14: P
B15: ='Area Calculations'!M66 -> Land scape Drawings by | C15: P
B16: ='Area Calculations'!M67 -> Kitchen Drawings by
B17: ='Area Calculations'!M68 -> Storefront Designer by
B18: ='Area Calculations'!M69 -> Geotech report by | C18: P
B19: ='Area Calculations'!M70 -> Specifications
B21: Cranes and Hoisting
B22: GENERAL INCLUSIONS
B23: INCLUDES ALL SALES TAX
B24: ALL HOISTING & RIGGING REQUIRED TO COMPLETE THIS SCOPE
B25: PROVIDE P&P BONDS
B26: FLORIDA STATE CONTRACTORS LIC.
B27: GENERAL LIABILITY AND WORKERS COMP. INSURANCE LIMITS
B28: STATE AND LOCAL TAXES
B29: COMPASS
B30: SPECIFIC TRADE SCOPE OF WORK REQUIREMENTS
B31: BASE BID
B32: Building SF
... B41: Dumpster Enclosure
B42: Monument Sign - | H42: i
B44: SLAB-ON-GRADE
B45: 5" Slab w/ WWF 6x6 w.2.9xw2.9
B46: a. Soil poisoning and pre-treat
B47: b. Fine grading building pad
B48: d. F&I rebar, as per plans
B49: e. F&I wire mesh, as per plans
B50: f. 4,000 PSI
B51: g. Sawcut constr. / control joints
B52: h. Finish slab to FF25/FL17
B53: i. Leave out strip, compact
B54: j. Patch slab after tilt operations
B55: k. Provide curing compound
... B85: Panel structural engineering
F92: SUBTOTAL | I92: =SUM(I24:I91) -> 0 | K92: =SUM(K24:K91) -> 0 | M92: =SUM(M24:M91) -> 0 | O92: =SUM(O24:O91) -> 0 | Q92: =SUM(Q24:Q91) -> 0 | S92: =SUM(S24:S91) -> 0
F93: BOND RATE | H93: 0 | J93: 0 | L93: 0 | N93: 0 | P93: 0 | R93: 0
F94: BOND AMOUNT | I94: =H93*I92 -> 0 | K94: =J93*K92 -> 0 | M94: =L93*M92 -> 0 | O94: =N93*O92 -> 0 | Q94: =P93*Q92 -> 0 | S94: =R93*S92 -> 0
F96: ADJUSTED TOTAL | I96: =SUM(I92:I94) -> 0 | K96: =SUM(K92:K94) -> 0 | M96: =SUM(M92:M94) -> 0 | O96: =SUM(O92:O94) -> 0 | Q96: =SUM(Q92:Q94) -> 0 | S96: =SUM(S92:S94) -> 0
F97: Cost per SF | I97: =I96/'Area Calculations'!$J$4 -> #DIV/0! | K97: =K96/'Area Calculations'!$J$4 -> #DIV/0! | M97: =M96/'Area Calculations'!$J$4 -> #DIV/0! | O97: =O96/'Area Calculations'!$J$4 -> #DIV/0! | Q97: =Q96/'Area Calculations'!$J$4 -> #DIV/0! | S97: =S96/'Area Calculations'!$J$4 -> #DIV/0!
F98: Cost per Unit | I98: =I96/'Area Calculations'!#REF! -> #REF! | K98: =K96/'Area Calculations'!#REF! -> #REF! | M98: =M96/'Area Calculations'!#REF! -> #REF! | O98: =O96/'Area Calculations'!#REF! -> #REF! | Q98: =Q96/'Area Calculations'!#REF! -> #REF! | S98: =S96/'Area Calculations'!#REF! -> #REF!
A100: QUALIFICATIONS
A104: EXCLUSIONS/OWNER PROVIDED ITEMS:
A108: ALTERNATES:
A112: PROPOSED VE (Provide Clear Description):
A116: FULLY LOADED LABOR RATES
B117: Laborer
B118: Mechanic
B119: Superintendent
B120: Project Manager
A122: SCHEDULE
B123: Prepared shop drawings/submittals
B124: Mobilization
B125: Total duration to complete scope of work
A127: Winner
A128: Company
A129: Contact
A130: Phone
A131: Email
A132: Base Bid
B134: Need Prequalification
B135: Prequalified

Sheet 03F Concrete Restoration
G1: Hedrick Plug
F2: X | G2: Excluded
B3: BACK TO SUMMARY SHEET | F3: I | G3: Included | H3: Bidder1 | J3: Bidder 2 | L3: Bidder 3 | N3: Bidder 4 | P3: Bidder 5 | R3: Bidder 6
A4: Project: | B4: ='Area Calculations'!B4 -> The Club at Ibis Conceptual Estimate | G4: Company
A5: Trade: | B5: Concrete Restoration | G5: Contact
A6: CSI Code: | B6: 03F | G6: Phone
A7: Date: | G7: Email
A8: Adjusted Bid | G8: Adjusted Bid | H8: =I96 -> 0 | J8: =K96 -> 0 | L8: =M96 -> 0 | N8: =O96 -> 0 | P8: =Q96 -> 0 | R8: =S96 -> 0
A9: BID DOCUMENTS: | C9: Plan/ Spec. Package | D9: QTY | E9: U/M | F9: Unit Cost | G9: Subtotal | H9: Yes/No | I9: Price | J9: Yes/No | K9: Price | L9: Yes/No | M9: Price | N9: Yes/No | O9: Price | P9: Yes/No | Q9: Price | R9: Yes/No | S9: Price
B10: Plans By Division
B11: ='Area Calculations'!M62 -> Architectural Drawings by | C11: P
B12: ='Area Calculations'!M63 -> Structural Drawings by | C12: P
B13: ='Area Calculations'!M64 -> MEP FA FP Drawings by | C13: P
B14: ='Area Calculations'!M65 -> Civil Drawings by | C14: P
B15: ='Area Calculations'!M66 -> Land scape Drawings by | C15: P
B16: ='Area Calculations'!M67 -> Kitchen Drawings by
B17: ='Area Calculations'!M68 -> Storefront Designer by
B18: ='Area Calculations'!M69 -> Geotech report by | C18: P
B19: ='Area Calculations'!M70 -> Specifications
B21: Concrete Restoration
B22: GENERAL INCLUSIONS
B23: INCLUDES ALL SALES TAX
B24: ALL HOISTING & RIGGING REQUIRED TO COMPLETE THIS SCOPE
B25: PROVIDE P&P BONDS
B26: FLORIDA STATE CONTRACTORS LIC.
B27: GENERAL LIABILITY AND WORKERS COMP. INSURANCE LIMITS
B28: STATE AND LOCAL TAXES
B29: COMPASS
B30: SPECIFIC TRADE SCOPE OF WORK REQUIREMENTS
B31: BASE BID
B32: Building SF
... B41: Dumpster Enclosure
B42: Monument Sign - | H42: i
B44: SLAB-ON-GRADE
B45: 5" Slab w/ WWF 6x6 w.2.9xw2.9
B46: a. Soil poisoning and pre-treat
B47: b. Fine grading building pad
B48: d. F&I rebar, as per plans
B49: e. F&I wire mesh, as per plans
B50: f. 4,000 PSI
B51: g. Sawcut constr. / control joints
B52: h. Finish slab to FF25/FL17
B53: i. Leave out strip, compact
B54: j. Patch slab after tilt operations
B55: k. Provide curing compound
... B85: Panel structural engineering
F92: SUBTOTAL | I92: =SUM(I24:I91) -> 0 | K92: =SUM(K24:K91) -> 0 | M92: =SUM(M24:M91) -> 0 | O92: =SUM(O24:O91) -> 0 | Q92: =SUM(Q24:Q91) -> 0 | S92: =SUM(S24:S91) -> 0
F93: BOND RATE | H93: 0 | J93: 0 | L93: 0 | N93: 0 | P93: 0 | R93: 0
F94: BOND AMOUNT | I94: =H93*I92 -> 0 | K94: =J93*K92 -> 0 | M94: =L93*M92 -> 0 | O94: =N93*O92 -> 0 | Q94: =P93*Q92 -> 0 | S94: =R93*S92 -> 0
F96: ADJUSTED TOTAL | I96: =SUM(I92:I94) -> 0 | K96: =SUM(K92:K94) -> 0 | M96: =SUM(M92:M94) -> 0 | O96: =SUM(O92:O94) -> 0 | Q96: =SUM(Q92:Q94) -> 0 | S96: =SUM(S92:S94) -> 0
F97: Cost per SF | I97: =I96/'Area Calculations'!$J$4 -> #DIV/0! | K97: =K96/'Area Calculations'!$J$4 -> #DIV/0! | M97: =M96/'Area Calculations'!$J$4 -> #DIV/0! | O97: =O96/'Area Calculations'!$J$4 -> #DIV/0! | Q97: =Q96/'Area Calculations'!$J$4 -> #DIV/0! | S97: =S96/'Area Calculations'!$J$4 -> #DIV/0!
F98: Cost per Unit | I98: =I96/'Area Calculations'!#REF! -> #REF! | K98: =K96/'Area Calculations'!#REF! -> #REF! | M98: =M96/'Area Calculations'!#REF! -> #REF! | O98: =O96/'Area Calculations'!#REF! -> #REF! | Q98: =Q96/'Area Calculations'!#REF! -> #REF! | S98: =S96/'Area Calculations'!#REF! -> #REF!
A100: QUALIFICATIONS
A104: EXCLUSIONS/OWNER PROVIDED ITEMS:
A108: ALTERNATES:
A112: PROPOSED VE (Provide Clear Description):
A116: FULLY LOADED LABOR RATES
B117: Laborer
B118: Mechanic
B119: Superintendent
B120: Project Manager
A122: SCHEDULE
B123: Prepared shop drawings/submittals
B124: Mobilization
B125: Total duration to complete scope of work
A127: Winner
A128: Company
A129: Contact
A130: Phone
A131: Email
A132: Base Bid
B134: Need Prequalification
B135: Prequalified

Sheet 04A Masonry
G1: Hedrick Plug
F2: X | G2: Excluded
B3: BACK TO SUMMARY SHEET | F3: I | G3: Included | H3: Bidder1 | J3: Bidder 2 | L3: Bidder 3 | N3: Bidder 4 | P3: Bidder 5 | R3: Bidder 6
A4: Project: | B4: ='Area Calculations'!B4 -> The Club at Ibis Conceptual Estimate | G4: Company
A5: Trade: | B5: Masonry | G5: Contact
A6: CSI Code: | B6: 04A | G6: Phone
A7: Date: | G7: Email
A8: Adjusted Bid | G8: Adjusted Bid | H8: =I86 -> 0 | J8: =K86 -> 0 | L8: =M86 -> 0 | N8: =O86 -> 0 | P8: =Q86 -> 0 | R8: =S86 -> 0
A9: BID DOCUMENTS: | C9: Plan/ Spec. Package | D9: QTY | E9: U/M | F9: Unit Cost | G9: Subtotal | H9: Yes/No | I9: Price | J9: Yes/No | K9: Price | L9: Yes/No | M9: Price | N9: Yes/No | O9: Price | P9: Yes/No | Q9: Price | R9: Yes/No | S9: Price
B10: Plans By Division
B11: ='Area Calculations'!M62 -> Architectural Drawings by | C11: P
B12: ='Area Calculations'!M63 -> Structural Drawings by | C12: P
B13: ='Area Calculations'!M64 -> MEP FA FP Drawings by | C13: P
B14: ='Area Calculations'!M65 -> Civil Drawings by | C14: P
B15: ='Area Calculations'!M66 -> Land scape Drawings by | C15: P
B16: ='Area Calculations'!M67 -> Kitchen Drawings by
B17: ='Area Calculations'!M68 -> Storefront Designer by
B18: ='Area Calculations'!M69 -> Geotech report by | C18: P
B19: ='Area Calculations'!M70 -> Specifications
B21: Masonry
B22: GENERAL INCLUSIONS
B23: INCLUDES ALL SALES TAX
B24: ALL HOISTING & RIGGING REQUIRED TO COMPLETE THIS SCOPE
B25: PROVIDE P&P BONDS
B26: FLORIDA STATE CONTRACTORS LIC.
B27: GENERAL LIABILITY AND WORKERS COMP. INSURANCE LIMITS
B28: STATE AND LOCAL TAXES
B29: COMPASS
B30: SPECIFIC TRADE SCOPE OF WORK REQUIREMENTS
B31: BASE BID
B32: Building SF
... B39: e. Horizontal Reinf.
B40: f. Lintels, ladder wire and accessories | H40: i
B41: g. Setting of Joist Embeds & door frames
B42: h. Above scope included for:
B43: 1)
B44: 2)
B45: 3)
F82: SUBTOTAL | I82: =SUM(I24:I81) -> 0 | K82: =SUM(K24:K81) -> 0 | M82: =SUM(M24:M81) -> 0 | O82: =SUM(O24:O81) -> 0 | Q82: =SUM(Q24:Q81) -> 0 | S82: =SUM(S24:S81) -> 0
F83: BOND RATE | H83: 0 | J83: 0 | L83: 0 | N83: 0 | P83: 0 | R83: 0
F84: BOND AMOUNT | I84: =H83*I82 -> 0 | K84: =J83*K82 -> 0 | M84: =L83*M82 -> 0 | O84: =N83*O82 -> 0 | Q84: =P83*Q82 -> 0 | S84: =R83*S82 -> 0
F86: ADJUSTED TOTAL | I86: =SUM(I82:I84) -> 0 | K86: =SUM(K82:K84) -> 0 | M86: =SUM(M82:M84) -> 0 | O86: =SUM(O82:O84) -> 0 | Q86: =SUM(Q82:Q84) -> 0 | S86: =SUM(S82:S84) -> 0
F87: Cost per SF | I87: =I86/'Area Calculations'!$J$4 -> #DIV/0! | K87: =K86/'Area Calculations'!$J$4 -> #DIV/0! | M87: =M86/'Area Calculations'!$J$4 -> #DIV/0! | O87: =O86/'Area Calculations'!$J$4 -> #DIV/0! | Q87: =Q86/'Area Calculations'!$J$4 -> #DIV/0! | S87: =S86/'Area Calculations'!$J$4 -> #DIV/0!
F88: Cost per Unit | I88: =I86/'Area Calculations'!#REF! -> #REF! | K88: =K86/'Area Calculations'!#REF! -> #REF! | M88: =M86/'Area Calculations'!#REF! -> #REF! | O88: =O86/'Area Calculations'!#REF! -> #REF! | Q88: =Q86/'Area Calculations'!#REF! -> #REF! | S88: =S86/'Area Calculations'!#REF! -> #REF!
A90: QUALIFICATIONS
A94: EXCLUSIONS/OWNER PROVIDED ITEMS:
A98: ALTERNATES:
A102: PROPOSED VE (Provide Clear Description):
A106: FULLY LOADED LABOR RATES
B107: Laborer
B108: Mechanic
B109: Superintendent
B110: Project Manager
A112: SCHEDULE
B113: Prepared shop drawings/submittals
B114: Mobilization
B115: Total duration to complete scope of work
A117: Winner
A118: Company
A119: Contact
A120: Phone
A121: Email
A122: Base Bid
B124: Need Prequalification
B125: Prequalified

Sheet 04B Stone Veneer
G1: Hedrick Plug
F2: X | G2: Excluded
B3: BACK TO SUMMARY SHEET | F3: I | G3: Included | H3: Bidder 1 | J3: Bidder2 | L3: Bidder 3 | N3: Bidder 4 | P3: Bidder5 | R3: Bidder6
A4: Project: | B4: ='Area Calculations'!B4 -> The Club at Ibis Conceptual Estimate | G4: Company
A5: Trade: | B5: Cast Stone, Stone Veneer | G5: Contact
A6: CSI Code: | B6: 04B | G6: Phone
A7: Date: | G7: Email
A8: Adjusted Bid | G8: Adjusted Bid | H8: =I56 -> 0 | J8: =K56 -> 0 | L8: =M56 -> 0 | N8: =O56 -> 0 | P8: =Q56 -> 0 | R8: =S56 -> 0
A9: BID DOCUMENTS: | C9: Plan/ Spec. Package | D9: QTY | E9: U/M | F9: Unit Cost | G9: Subtotal | H9: Yes/No | I9: Price | J9: Yes/No | K9: Price | L9: Yes/No | M9: Price | N9: Yes/No | O9: Price | P9: Yes/No | Q9: Price | R9: Yes/No | S9: Price
B10: Plans By Division
B11: ='Area Calculations'!M62 -> Architectural Drawings by | C11: P
B12: ='Area Calculations'!M63 -> Structural Drawings by | C12: P
B13: ='Area Calculations'!M64 -> MEP FA FP Drawings by | C13: P
B14: ='Area Calculations'!M65 -> Civil Drawings by | C14: P
B15: ='Area Calculations'!M66 -> Land scape Drawings by | C15: P
B16: ='Area Calculations'!M67 -> Kitchen Drawings by | C16: P
B17: ='Area Calculations'!M68 -> Storefront Designer by | C17: P
B18: ='Area Calculations'!M69 -> Geotech report by | C18: P
B19: ='Area Calculations'!M70 -> Specifications
B21: Cast Stone, Stone Veneer
B22: GENERAL INCLUSIONS
B23: INCLUDES ALL SALES TAX
B24: ALL HOISTING & RIGGING REQUIRED TO COMPLETE THIS SCOPE
B25: PROVIDE P&P BONDS
B26: FLORIDA STATE CONTRACTORS LIC.
B27: GENERAL LIABILITY AND WORKERS COMP. INSURANCE LIMITS
B28: STATE AND LOCAL TAXES
B29: COMPASS
B30: SPECIFIC TRADE SCOPE OF WORK REQUIREMENTS
B31: BASE BID
B33: Phase 1 Interior Club House Renovations
... B47: Phase 3 Reno Existing Fitness Building
F52: SUBTOTAL | I52: =SUM(I16:I51) -> 0 | K52: =SUM(K16:K51) -> 0 | M52: =SUM(M16:M51) -> 0 | O52: =SUM(O16:O51) -> 0 | Q52: =SUM(Q16:Q51) -> 0 | S52: =SUM(S16:S51) -> 0
F53: BOND RATE | H53: 0 | J53: 0 | L53: 0 | N53: 0 | P53: 0 | R53: 0
F54: BOND AMOUNT | I54: =H53*I52 -> 0 | K54: =J53*K52 -> 0 | M54: =L53*M52 -> 0 | O54: =N53*O52 -> 0 | Q54: =P53*Q52 -> 0 | S54: =R53*S52 -> 0
F56: ADJUSTED TOTAL | I56: =SUM(I52:I54) -> 0 | K56: =SUM(K52:K54) -> 0 | M56: =SUM(M52:M54) -> 0 | O56: =SUM(O52:O54) -> 0 | Q56: =SUM(Q52:Q54) -> 0 | S56: =SUM(S52:S54) -> 0
F57: Cost per SF | I57: =I56/'Area Calculations'!$J$4 -> #DIV/0! | K57: =K56/'Area Calculations'!$J$4 -> #DIV/0! | M57: =M56/'Area Calculations'!$J$4 -> #DIV/0! | O57: =O56/'Area Calculations'!$J$4 -> #DIV/0! | Q57: =Q56/'Area Calculations'!$J$4 -> #DIV/0! | S57: =S56/'Area Calculations'!$J$4 -> #DIV/0!
F58: Cost per Unit | I58: =I56/'Area Calculations'!#REF! -> #REF! | K58: =K56/'Area Calculations'!#REF! -> #REF! | M58: =M56/'Area Calculations'!#REF! -> #REF! | O58: =O56/'Area Calculations'!#REF! -> #REF! | Q58: =Q56/'Area Calculations'!#REF! -> #REF! | S58: =S56/'Area Calculations'!#REF! -> #REF!
A60: QUALIFICATIONS
A64: EXCLUSIONS/OWNER PROVIDED ITEMS:
A68: ALTERNATES:
A72: PROPOSED VE (Provide Clear Description):
A76: FULLY LOADED LABOR RATES
B77: Laborer
B78: Mechanic
B79: Superintendent
B80: Project Manager
A82: SCHEDULE
B83: Prepared shop drawings/submittals
B84: Mobilization
B85: Total duration to complete scope of work
A87: Winner
A88: Company
A89: Contact
A90: Phone
A91: Email
A92: Base Bid | B92: =H8 -> 0
B94: Need Prequalification
B95: Prequalified

Sheet 05A Structural Steel
G1: Hedrick Plug
F2: X | G2: Excluded
B3: BACK TO SUMMARY SHEET | F3: I | G3: Included | H3: Bidder 1 | J3: Bidder 2 | L3: Bidder 3 | N3: Bidder 4 | P3: Bidder5 | R3: Bidder6
A4: Project: | B4: ='Area Calculations'!B4 -> The Club at Ibis Conceptual Estimate | G4: Company
A5: Trade: | B5: Structural Steel | G5: Contact
A6: CSI Code: | B6: 05A | G6: Phone
A7: Date: | G7: Email
A8: Adjusted Bid | G8: Adjusted Bid | H8: =I60 -> 624269.9 | J8: =K60 -> 0 | L8: =M60 -> 0 | N8: =O60 -> 0 | P8: =Q60 -> 0 | R8: =S60 -> 0
A9: BID DOCUMENTS: | C9: Plan/ Spec. Package | D9: QTY | E9: U/M | F9: Unit Cost | G9: Subtotal | H9: Yes/No | I9: Price | J9: Yes/No | K9: Price | L9: Yes/No | M9: Price | N9: Yes/No | O9: Price | P9: Yes/No | Q9: Price | R9: Yes/No | S9: Price
B10: Plans By Division
B11: ='Area Calculations'!M62 -> Architectural Drawings by | C11: P
B12: ='Area Calculations'!M63 -> Structural Drawings by | C12: P
B13: ='Area Calculations'!M64 -> MEP FA FP Drawings by | C13: P
B14: ='Area Calculations'!M65 -> Civil Drawings by | C14: P
B15: ='Area Calculations'!M66 -> Land scape Drawings by | C15: P
B16: ='Area Calculations'!M67 -> Kitchen Drawings by | C16: P
B17: ='Area Calculations'!M68 -> Storefront Designer by | C17: P
B18: ='Area Calculations'!M69 -> Geotech report by | C18: P
B19: ='Area Calculations'!M70 -> Specifications | C19: P
B21: Structural Steel
B22: GENERAL INCLUSIONS
B23: INCLUDES ALL SALES TAX
B24: ALL HOISTING & RIGGING REQUIRED TO COMPLETE THIS SCOPE
B25: PROVIDE P&P BONDS
B26: FLORIDA STATE CONTRACTORS LIC.
B27: GENERAL LIABILITY AND WORKERS COMP. INSURANCE LIMITS
B28: STATE AND LOCAL TAXES
B29: COMPASS
B30: SPECIFIC TRADE SCOPE OF WORK REQUIREMENTS
B31: BASE BID
B32: Building SF
... B36: Phase 1 Racquet Courts
B37: (5) Covered Pickleball courts | C37: C2.1 | D37: 11868 | E37: SF | F37: 25 | G37: =D37*F37 -> 296700 | I37: =G37 -> 296700
B39: Phase 2 Bocce & Basketball
B41: Phase 2 New Spa Building
B42: Steel Columns | D42: ='Cost Summary'!$N$7 -> 11678 | E42: SF | F42: 3.5 | G42: =D42*F42 -> 40873 | I42: =G42 -> 40873
B43: Elevated roof Structure - Cold Form Metal Framing | C43: AE102 | D43: =6305-2181.51 -> 4123.49 | E43: SF | F43: 60 | G43: =D43*F43 -> 247409.4 | I43: =G43 -> 247409.4
B45: Phase 2 POA Building
B47: Phase 2 New Fitness Building
B48: Steel Columns | D48: ='Cost Summary'!$R$7 -> 11225 | E48: SF | F48: 3.5 | G48: =D48*F48 -> 39287.5 | I48: =G48 -> 39287.5
B50: Phase 3 19th Hole Restaurant
B52: Phase 3 Reno Existing Fitness Building
F56: SUBTOTAL | I56: =SUM(I23:I55) -> 624269.9 | K56: =SUM(K23:K55) -> 0 | M56: =SUM(M23:M55) -> 0 | O56: =SUM(O23:O55) -> 0 | Q56: =SUM(Q23:Q55) -> 0 | S56: =SUM(S23:S55) -> 0
F57: BOND RATE | H57: 0 | J57: 0 | L57: 0 | N57: 0 | P57: 0 | R57: 0
F58: BOND AMOUNT | I58: =H57*$I$56 -> 0 | K58: =J57*$I$56 -> 0 | M58: =L57*$I$56 -> 0 | O58: =N57*$I$56 -> 0 | Q58: =P57*$I$56 -> 0 | S58: =R57*$I$56 -> 0
F60: ADJUSTED TOTAL | I60: =SUM(I56:I58) -> 624269.9 | K60: =SUM(K56:K58) -> 0 | M60: =SUM(M56:M58) -> 0 | O60: =SUM(O56:O58) -> 0 | Q60: =SUM(Q56:Q58) -> 0 | S60: =SUM(S56:S58) -> 0
F61: Cost per SF | I61: =I60/'Area Calculations'!$J$4 -> #DIV/0! | K61: =K60/'Area Calculations'!$J$4 -> #DIV/0! | M61: =M60/'Area Calculations'!$J$4 -> #DIV/0! | O61: =O60/'Area Calculations'!$J$4 -> #DIV/0! | Q61: =Q60/'Area Calculations'!$J$4 -> #DIV/0! | S61: =S60/'Area Calculations'!$J$4 -> #DIV/0!
F62: Cost per Unit | I62: =I60/'Area Calculations'!#REF! -> #REF! | K62: =K60/'Area Calculations'!#REF! -> #REF! | M62: =M60/'Area Calculations'!#REF! -> #REF! | O62: =O60/'Area Calculations'!#REF! -> #REF! | Q62: =Q60/'Area Calculations'!#REF! -> #REF! | S62: =S60/'Area Calculations'!#REF! -> #REF!
A64: QUALIFICATIONS
A68: EXCLUSIONS/OWNER PROVIDED ITEMS:
A72: ALTERNATES:
A76: PROPOSED VE (Provide Clear Description):
A80: FULLY LOADED LABOR RATES
B81: Laborer
B82: Mechanic
B83: Superintendent
B84: Project Manager
A86: SCHEDULE
B87: Prepared shop drawings/submittals
B88: Mobilization
B89: Total duration to complete scope of work
A91: Winner
A92: Company
A93: Contact
A94: Phone
A95: Email
A96: Base Bid | B96: =H8 -> 624269.9
B98: Need Prequalification
B99: Prequalified

Sheet 05B Metal Trusses
G1: Hedrick Plug
F2: X | G2: Excluded
B3: BACK TO SUMMARY SHEET | F3: I | G3: Included | H3: Bidder 1 | J3: Bidder 2 | L3: Bidder 3 | N3: Bidder 4 | P3: Bidder 5 | R3: Bidder 6
A4: Project: | B4: ='Area Calculations'!B4 -> The Club at Ibis Conceptual Estimate | G4: Company
A5: Trade: | B5: Metal Trusses | G5: Contact
A6: CSI Code: | B6: 05B | G6: Phone
A7: Date: | G7: Email
A8: Adjusted Bid | G8: Adjusted Bid | H8: =I52 -> 0 | J8: =K52 -> 0 | L8: =M52 -> 0 | N8: =O52 -> 0 | P8: =Q52 -> 0 | R8: =S52 -> 0
A9: BID DOCUMENTS: | C9: Plan/ Spec. Package | D9: QTY | E9: U/M | F9: Unit Cost | G9: Subtotal | H9: Yes/No | I9: Price | J9: Yes/No | K9: Price | L9: Yes/No | M9: Price | N9: Yes/No | O9: Price | P9: Yes/No | Q9: Price | R9: Yes/No | S9: Price
B10: Plans By Division
B11: ='Area Calculations'!M62 -> Architectural Drawings by | C11: P
B12: ='Area Calculations'!M63 -> Structural Drawings by | C12: P
B13: ='Area Calculations'!M64 -> MEP FA FP Drawings by | C13: P
B14: ='Area Calculations'!M65 -> Civil Drawings by | C14: P
B15: ='Area Calculations'!M66 -> Land scape Drawings by | C15: P
B16: ='Area Calculations'!M67 -> Kitchen Drawings by | C16: P
B17: ='Area Calculations'!M68 -> Storefront Designer by | C17: P
B18: ='Area Calculations'!M69 -> Geotech report by | C18: P
B19: ='Area Calculations'!M70 -> Specifications | C19: P
B21: Metal Trusses
B22: GENERAL INCLUSIONS
B23: INCLUDES ALL SALES TAX
B24: ALL HOISTING & RIGGING REQUIRED TO COMPLETE THIS SCOPE
B25: PROVIDE P&P BONDS
B26: FLORIDA STATE CONTRACTORS LIC.
B27: GENERAL LIABILITY AND WORKERS COMP. INSURANCE LIMITS
B28: STATE AND LOCAL TAXES
B29: COMPASS
B30: SPECIFIC TRADE SCOPE OF WORK REQUIREMENTS
B31: BASE BID
B32: Building SF
B34: Structural Steel , incl.:
B35: a. Equipment, cranes, etc. | H35: i
B36: b. scheduled/detailed shop drawings.
B37: c. Steel Columns, W-Beams, Joists and Metal Decking as scheduled.
B38: d. Steel connections, angle iron, steel beam at elevator.
B39: e. Roof top equipment structural requirements.
B40: f. Above scope included for:
F48: SUBTOTAL | I48: =SUM(I23:I47) -> 0 | K48: =SUM(K23:K47) -> 0 | M48: =SUM(M23:M47) -> 0 | O48: =SUM(O23:O47) -> 0 | Q48: =SUM(Q23:Q47) -> 0 | S48: =SUM(S23:S47) -> 0
F49: BOND RATE | H49: 0 | J49: 0 | L49: 0 | N49: 0 | P49: 0 | R49: 0
F50: BOND AMOUNT | I50: =H49*$I$48 -> 0 | K50: =J49*$K$48 -> 0 | M50: =L49*$K$48 -> 0 | O50: =N49*$K$48 -> 0 | Q50: =P49*$K$48 -> 0 | S50: =R49*$K$48 -> 0
F52: ADJUSTED TOTAL | I52: =SUM(I48:I50) -> 0 | K52: =SUM(K48:K50) -> 0 | M52: =SUM(M48:M50) -> 0 | O52: =SUM(O48:O50) -> 0 | Q52: =SUM(Q48:Q50) -> 0 | S52: =SUM(S48:S50) -> 0
F53: Cost per SF | I53: =I52/'Area Calculations'!$J$4 -> #DIV/0! | K53: =K52/'Area Calculations'!$J$4 -> #DIV/0! | M53: =M52/'Area Calculations'!$J$4 -> #DIV/0! | O53: =O52/'Area Calculations'!$J$4 -> #DIV/0! | Q53: =Q52/'Area Calculations'!$J$4 -> #DIV/0! | S53: =S52/'Area Calculations'!$J$4 -> #DIV/0!
F54: Cost per Unit | I54: =I52/'Area Calculations'!#REF! -> #REF! | K54: =K52/'Area Calculations'!#REF! -> #REF! | M54: =M52/'Area Calculations'!#REF! -> #REF! | O54: =O52/'Area Calculations'!#REF! -> #REF! | Q54: =Q52/'Area Calculations'!#REF! -> #REF! | S54: =S52/'Area Calculations'!#REF! -> #REF!
A56: QUALIFICATIONS
A60: EXCLUSIONS/OWNER PROVIDED ITEMS:
A64: ALTERNATES:
A68: PROPOSED VE (Provide Clear Description):
A72: FULLY LOADED LABOR RATES
B73: Laborer
B74: Mechanic
B75: Superintendent
B76: Project Manager
A78: SCHEDULE
B79: Prepared shop drawings/submittals
B80: Mobilization
B81: Total duration to complete scope of work
A83: Winner
A84: Company
A85: Contact
A86: Phone
A87: Email
A88: Base Bid
B90: Need Prequalification
B91: Prequalified

Sheet 05C Misc. Metals
G1: Hedrick Plug
F2: X | G2: Excluded
B3: BACK TO SUMMARY SHEET | F3: I | G3: Included | H3: Bidder 1 | J3: Bidder 2 | L3: Bidder 3 | N3: Bidder 4 | P3: Bidder 5 | R3: Bidder 6
A4: Project: | B4: ='Area Calculations'!B4 -> The Club at Ibis Conceptual Estimate | G4: Company
A5: Trade: | B5: Misc. Metals | G5: Contact
A6: CSI Code: | B6: 05C | G6: Phone
A7: Date: | G7: Email
A8: Adjusted Bid | G8: Adjusted Bid | H8: =I63 -> 105897.5 | J8: =K63 -> 0 | L8: =M63 -> 0 | N8: =O63 -> 0 | P8: =Q63 -> 0 | R8: =S63 -> 0
A9: BID DOCUMENTS: | C9: Plan/ Spec. Package | D9: QTY | E9: U/M | F9: Unit Cost | G9: Subtotal | H9: Yes/No | I9: Price | J9: Yes/No | K9: Price | L9: Yes/No | M9: Price | N9: Yes/No | O9: Price | P9: Yes/No | Q9: Price | R9: Yes/No | S9: Price
B10: Plans By Division
B11: ='Area Calculations'!M62 -> Architectural Drawings by | C11: P
B12: ='Area Calculations'!M63 -> Structural Drawings by | C12: P
B13: ='Area Calculations'!M64 -> MEP FA FP Drawings by | C13: P
B14: ='Area Calculations'!M65 -> Civil Drawings by | C14: P
B15: ='Area Calculations'!M66 -> Land scape Drawings by | C15: P
B16: ='Area Calculations'!M67 -> Kitchen Drawings by | C16: P
B17: ='Area Calculations'!M68 -> Storefront Designer by | C17: P
B18: ='Area Calculations'!M69 -> Geotech report by | C18: P
B19: ='Area Calculations'!M70 -> Specifications | C19: P
B22: Misc. Metals
B23: GENERAL INCLUSIONS
B24: INCLUDES ALL SALES TAX
B25: ALL HOISTING & RIGGING REQUIRED TO COMPLETE THIS SCOPE
B26: PROVIDE P&P BONDS
B27: FLORIDA STATE CONTRACTORS LIC.
B28: GENERAL LIABILITY AND WORKERS COMP. INSURANCE LIMITS
B29: STATE AND LOCAL TAXES
B30: COMPASS
B31: SPECIFIC TRADE SCOPE OF WORK REQUIREMENTS
B32: BASE BID
B34: Phase 1 Interior Club House Renovations
B36: Phase 1 Racquet Courts
B37: Area | C37: AE100 | D37: ='Cost Summary'!$J$7 -> 663 | E37: SF | F37: 2 | G37: =D37*F37 -> 1326 | I37: =G37 -> 1326
B39: Phase 2 Bocce & Basketball
B41: Phase 2 New Spa Building
B42: Area | C42: AE101 | D42: ='Cost Summary'!$N$7 -> 11678 | E42: SF | F42: 0.5 | G42: =D42*F42 -> 5839 | I42: =G42 -> 5839
B43: Decortative Columns - Metal Artisan Panels | C43: AE301 | D43: 284 | E43: SF | F43: 300 | G43: =D43*F43 -> 85200 | I43: =G43 -> 85200
B45: Phase 2 POA Building
B47: Phase 2 New Fitness Building
B48: Area | C48: AE101 | D48: ='Cost Summary'!$R$7 -> 11225 | E48: SF | F48: 0.5 | G48: =D48*F48 -> 5612.5 | I48: =G48 -> 5612.5
B49: Stair S103 - Railings | C49: AE101 | D49: 70 | E49: LF | F49: 60 | G49: =D49*F49 -> 4200 | I49: =G49 -> 4200
B50: Stair S104 - Railings | C50: AE101 | D50: 62 | E50: LF | F50: 60 | G50: =D50*F50 -> 3720 | I50: =G50 -> 3720
B52: Phase 3 19th Hole Restaurant
B54: Phase 3 Reno Existing Fitness Building
F59: SUBTOTAL | I59: =SUM(I24:I58) -> 105897.5 | K59: =SUM(K24:K58) -> 0 | M59: =SUM(M23:M58) -> 0 | O59: =SUM(O23:O58) -> 0 | Q59: =SUM(Q24:Q58) -> 0 | S59: =SUM(S24:S58) -> 0
F60: BOND RATE | H60: 0 | J60: 0 | L60: 0.02 | N60: 0.02 | P60: 0.02 | R60: 0.02
F61: BOND AMOUNT | I61: =H60*$I$59 -> 0 | K61: =J60*$K$59 -> 0 | M61: =L60*$M$59 -> 0 | O61: =N60*$O$59 -> 0 | Q61: =P60*$Q$59 -> 0 | S61: =R60*S59 -> 0
F63: ADJUSTED TOTAL | I63: =SUM(I59:I62) -> 105897.5 | K63: =SUM(K59:K61) -> 0 | M63: =SUM(M59:M61) -> 0 | O63: =SUM(O59:O61) -> 0 | Q63: =SUM(Q59:Q61) -> 0 | S63: =SUM(S59:S61) -> 0
F64: Cost per SF | I64: =I63/'Area Calculations'!$J$4 -> #DIV/0! | K64: =K63/'Area Calculations'!$J$4 -> #DIV/0! | M64: =M63/'Area Calculations'!$J$4 -> #DIV/0! | O64: =O63/'Area Calculations'!$J$4 -> #DIV/0! | Q64: =Q63/'Area Calculations'!$J$4 -> #DIV/0! | S64: =S63/'Area Calculations'!$J$4 -> #DIV/0!
F65: Cost per Unit | I65: =I63/'Area Calculations'!#REF! -> #REF! | K65: =K63/'Area Calculations'!#REF! -> #REF! | M65: =M63/'Area Calculations'!#REF! -> #REF! | O65: =O63/'Area Calculations'!#REF! -> #REF! | Q65: =Q63/'Area Calculations'!#REF! -> #REF! | S65: =S63/'Area Calculations'!#REF! -> #REF!
A67: QUALIFICATIONS
A71: EXCLUSIONS/OWNER PROVIDED ITEMS:
A75: ALTERNATES:
A79: PROPOSED VE (Provide Clear Description):
A83: FULLY LOADED LABOR RATES
B84: Laborer
B85: Mechanic
B86: Superintendent
B87: Project Manager
A89: SCHEDULE
B90: Prepared shop drawings/submittals
B91: Mobilization
B92: Total duration to complete scope of work
A94: Winner
A95: Company
A96: Contact
A97: Phone
A98: Email
A99: Base Bid | B99: =H8 -> 105897.5
B101: Need Prequalification
B102: Prequalified

Sheet 05D Handrailings & Railings
G1: Hedrick Plug
F2: X | G2: Excluded
B3: BACK TO SUMMARY SHEET | F3: I | G3: Included | H3: Bidder 1 | J3: Bidder 2 | L3: Bidder 3 | N3: Bidder 4 | P3: Bidder 5 | R3: Bidder 6
A4: Project: | B4: ='Area Calculations'!B4 -> The Club at Ibis Conceptual Estimate | G4: Company
A5: Trade: | B5: Handrailings & Railings | G5: Contact
A6: CSI Code: | B6: 05D | G6: Phone
A7: Date: | G7: Email
A8: Adjusted Bid | G8: Adjusted Bid | H8: =I55 -> 0 | J8: =K55 -> 0 | L8: =M55 -> 0 | N8: =O55 -> 0 | P8: =Q55 -> 0 | R8: =S55 -> 0
A9: BID DOCUMENTS: | C9: Plan/ Spec. Package | D9: QTY | E9: U/M | F9: Unit Cost | G9: Subtotal | H9: Yes/No | I9: Price | J9: Yes/No | K9: Price | L9: Yes/No | M9: Price | N9: Yes/No | O9: Price | P9: Yes/No | Q9: Price | R9: Yes/No | S9: Price
B10: Plans By Division
B11: ='Area Calculations'!M62 -> Architectural Drawings by | C11: P
B12: ='Area Calculations'!M63 -> Structural Drawings by | C12: P
B13: ='Area Calculations'!M64 -> MEP FA FP Drawings by | C13: P
B14: ='Area Calculations'!M65 -> Civil Drawings by | C14: P
B15: ='Area Calculations'!M66 -> Land scape Drawings by | C15: P
B16: ='Area Calculations'!M67 -> Kitchen Drawings by | C16: P
B17: ='Area Calculations'!M68 -> Storefront Designer by | C17: P
B18: ='Area Calculations'!M69 -> Geotech report by | C18: P
B19: ='Area Calculations'!M70 -> Specifications | C19: P
B21: Handrailings & Railings
B22: GENERAL INCLUSIONS
B23: INCLUDES ALL SALES TAX
B24: ALL HOISTING & RIGGING REQUIRED TO COMPLETE THIS SCOPE
B25: PROVIDE P&P BONDS
B26: FLORIDA STATE CONTRACTORS LIC.
B27: GENERAL LIABILITY AND WORKERS COMP. INSURANCE LIMITS
B28: STATE AND LOCAL TAXES
B29: COMPASS
B30: SPECIFIC TRADE SCOPE OF WORK REQUIREMENTS
B31: BASE BID
H38: x
F51: SUBTOTAL | I51: =SUM(I23:I50) -> 0 | K51: =SUM(K23:K50) -> 0 | M51: =SUM(M22:M50) -> 0 | O51: =SUM(O22:O50) -> 0 | Q51: =SUM(Q23:Q50) -> 0 | S51: =SUM(S23:S50) -> 0
F52: BOND RATE | H52: 0 | J52: 0 | L52: 0.02 | N52: 0.02 | P52: 0.02 | R52: 0.02
F53: BOND AMOUNT | I53: =H52*$I$51 -> 0 | K53: =J52*$K$51 -> 0 | M53: =L52*$M$51 -> 0 | O53: =N52*$O$51 -> 0 | Q53: =P52*$Q$51 -> 0 | S53: =R52*S51 -> 0
F55: ADJUSTED TOTAL | I55: =SUM(I51:I54) -> 0 | K55: =SUM(K51:K53) -> 0 | M55: =SUM(M51:M53) -> 0 | O55: =SUM(O51:O53) -> 0 | Q55: =SUM(Q51:Q53) -> 0 | S55: =SUM(S51:S53) -> 0
F56: Cost per SF | I56: =I55/'Area Calculations'!$J$4 -> #DIV/0! | K56: =K55/'Area Calculations'!$J$4 -> #DIV/0! | M56: =M55/'Area Calculations'!$J$4 -> #DIV/0! | O56: =O55/'Area Calculations'!$J$4 -> #DIV/0! | Q56: =Q55/'Area Calculations'!$J$4 -> #DIV/0! | S56: =S55/'Area Calculations'!$J$4 -> #DIV/0!
F57: Cost per Unit | I57: =I55/'Area Calculations'!#REF! -> #REF! | K57: =K55/'Area Calculations'!#REF! -> #REF! | M57: =M55/'Area Calculations'!#REF! -> #REF! | O57: =O55/'Area Calculations'!#REF! -> #REF! | Q57: =Q55/'Area Calculations'!#REF! -> #REF! | S57: =S55/'Area Calculations'!#REF! -> #REF!
A59: QUALIFICATIONS
A63: EXCLUSIONS/OWNER PROVIDED ITEMS:
A67: ALTERNATES:
A71: PROPOSED VE (Provide Clear Description):
A75: FULLY LOADED LABOR RATES
B76: Laborer
B77: Mechanic
B78: Superintendent
B79: Project Manager
A81: SCHEDULE
B82: Prepared shop drawings/submittals
B83: Mobilization
B84: Total duration to complete scope of work
A86: Winner
A87: Company
A88: Contact
A89: Phone
A90: Email
A91: Base Bid
B93: Need Prequalification
B94: Prequalified

Sheet 05E Glass Railings
G1: Hedrick Plug
F2: X | G2: Excluded
B3: BACK TO SUMMARY SHEET | F3: I | G3: Included | H3: Bidder 1 | J3: Bidder 2 | L3: Bidder 3 | N3: Bidder 4 | P3: Bidder 5 | R3: Bidder 6
A4: Project: | B4: ='Area Calculations'!B4 -> The Club at Ibis Conceptual Estimate | G4: Company
A5: Trade: | B5: Glass Railings | G5: Contact
A6: CSI Code: | B6: 05E | G6: Phone
A7: Date: | G7: Email
A8: Adjusted Bid | G8: Adjusted Bid | H8: =I55 -> 0 | J8: =K55 -> 0 | L8: =M55 -> 0 | N8: =O55 -> 0 | P8: =Q55 -> 0 | R8: =S55 -> 0
A9: BID DOCUMENTS: | C9: Plan/ Spec. Package | D9: QTY | E9: U/M | F9: Unit Cost | G9: Subtotal | H9: Yes/No | I9: Price | J9: Yes/No | K9: Price | L9: Yes/No | M9: Price | N9: Yes/No | O9: Price | P9: Yes/No | Q9: Price | R9: Yes/No | S9: Price
B10: Plans By Division
B11: ='Area Calculations'!M62 -> Architectural Drawings by | C11: P
B12: ='Area Calculations'!M63 -> Structural Drawings by | C12: P
B13: ='Area Calculations'!M64 -> MEP FA FP Drawings by | C13: P
B14: ='Area Calculations'!M65 -> Civil Drawings by | C14: P
B15: ='Area Calculations'!M66 -> Land scape Drawings by | C15: P
B16: ='Area Calculations'!M67 -> Kitchen Drawings by | C16: P
B17: ='Area Calculations'!M68 -> Storefront Designer by | C17: P
B18: ='Area Calculations'!M69 -> Geotech report by | C18: P
B19: ='Area Calculations'!M70 -> Specifications | C19: P
B21: Glass Railings
B22: GENERAL INCLUSIONS
B23: INCLUDES ALL SALES TAX
B24: ALL HOISTING & RIGGING REQUIRED TO COMPLETE THIS SCOPE
B25: PROVIDE P&P BONDS
B26: FLORIDA STATE CONTRACTORS LIC.
B27: GENERAL LIABILITY AND WORKERS COMP. INSURANCE LIMITS
B28: STATE AND LOCAL TAXES
B29: COMPASS
B30: SPECIFIC TRADE SCOPE OF WORK REQUIREMENTS
B31: BASE BID
H38: x
F51: SUBTOTAL | I51: =SUM(I23:I50) -> 0 | K51: =SUM(K23:K50) -> 0 | M51: =SUM(M22:M50) -> 0 | O51: =SUM(O22:O50) -> 0 | Q51: =SUM(Q23:Q50) -> 0 | S51: =SUM(S23:S50) -> 0
F52: BOND RATE | H52: 0 | J52: 0 | L52: 0.02 | N52: 0.02 | P52: 0.02 | R52: 0.02
F53: BOND AMOUNT | I53: =H52*$I$51 -> 0 | K53: =J52*$K$51 -> 0 | M53: =L52*$M$51 -> 0 | O53: =N52*$O$51 -> 0 | Q53: =P52*$Q$51 -> 0 | S53: =R52*S51 -> 0
F55: ADJUSTED TOTAL | I55: =SUM(I51:I54) -> 0 | K55: =SUM(K51:K53) -> 0 | M55: =SUM(M51:M53) -> 0 | O55: =SUM(O51:O53) -> 0 | Q55: =SUM(Q51:Q53) -> 0 | S55: =SUM(S51:S53) -> 0
F56: Cost per SF | I56: =I55/'Area Calculations'!$J$4 -> #DIV/0! | K56: =K55/'Area Calculations'!$J$4 -> #DIV/0! | M56: =M55/'Area Calculations'!$J$4 -> #DIV/0! | O56: =O55/'Area Calculations'!$J$4 -> #DIV/0! | Q56: =Q55/'Area Calculations'!$J$4 -> #DIV/0! | S56: =S55/'Area Calculations'!$J$4 -> #DIV/0!
F57: Cost per Unit | I57: =I55/'Area Calculations'!#REF! -> #REF! | K57: =K55/'Area Calculations'!#REF! -> #REF! | M57: =M55/'Area Calculations'!#REF! -> #REF! | O57: =O55/'Area Calculations'!#REF! -> #REF! | Q57: =Q55/'Area Calculations'!#REF! -> #REF! | S57: =S55/'Area Calculations'!#REF! -> #REF!
A59: QUALIFICATIONS
A63: EXCLUSIONS/OWNER PROVIDED ITEMS:
A67: ALTERNATES:
A71: PROPOSED VE (Provide Clear Description):
A75: FULLY LOADED LABOR RATES
B76: Laborer
B77: Mechanic
B78: Superintendent
B79: Project Manager
A81: SCHEDULE
B82: Prepared shop drawings/submittals
B83: Mobilization
B84: Total duration to complete scope of work
A86: Winner
A87: Company
A88: Contact
A89: Phone
A90: Email
A91: Base Bid
B93: Need Prequalification
B94: Prequalified

Sheet 06A Rough Carpentry
G1: Hedrick Plug
F2: X | G2: Excluded
B3: BACK TO SUMMARY SHEET | F3: I | G3: Included | H3: Bidder 1 | J3: Bidder 2 | L3: Bidder 3 | N3: Bidder 4 | P3: Bidder 5 | R3: Bidder 6
A4: Project: | B4: ='Area Calculations'!B4 -> The Club at Ibis Conceptual Estimate | G4: Company
A5: Trade: | B5: Rough Carpentry | G5: Contact
A6: CSI Code: | B6: 06A | G6: Phone
A7: Date: | G7: Email
A8: Adjusted Bid | G8: Adjusted Bid | H8: =I67 -> 348565.01 | J8: =K67 -> 0 | L8: =M67 -> 0 | N8: =O67 -> 0 | P8: =Q67 -> 0 | R8: =S67 -> 0
A9: BID DOCUMENTS: | C9: Plan/ Spec. Package | D9: QTY | E9: U/M | F9: Unit Cost | G9: Subtotal | H9: Yes/No | I9: Price | J9: Yes/No | K9: Price | L9: Yes/No | M9: Price | N9: Yes/No | O9: Price | P9: Yes/No | Q9: Price | R9: Yes/No | S9: Price
B10: Plans By Division
B11: ='Area Calculations'!M62 -> Architectural Drawings by | C11: P
B12: ='Area Calculations'!M63 -> Structural Drawings by | C12: P
B13: ='Area Calculations'!M64 -> MEP FA FP Drawings by | C13: P
B14: ='Area Calculations'!M65 -> Civil Drawings by | C14: P
B15: ='Area Calculations'!M66 -> Land scape Drawings by | C15: P
B16: ='Area Calculations'!M67 -> Kitchen Drawings by | C16: P
B17: ='Area Calculations'!M68 -> Storefront Designer by | C17: P
B18: ='Area Calculations'!M69 -> Geotech report by | C18: P
B19: ='Area Calculations'!M70 -> Specifications | C19: P
B22: Rough Carpentry
B23: GENERAL INCLUSIONS
B24: INCLUDES ALL SALES TAX
B25: ALL HOISTING & RIGGING REQUIRED TO COMPLETE THIS SCOPE
B26: PROVIDE P&P BONDS
B27: FLORIDA STATE CONTRACTORS LIC.
B28: GENERAL LIABILITY AND WORKERS COMP. INSURANCE LIMITS
B29: STATE AND LOCAL TAXES
B30: COMPASS
B31: SPECIFIC TRADE SCOPE OF WORK REQUIREMENTS
B32: BASE BID
B34: Phase 1 Interior Club House Renovations
B36: Phase 1 Racquet Courts
B37: Misc. Rough Carpentry | C37: AE100 | D37: ='Cost Summary'!$J$7 -> 663 | E37: SF | F37: 2.5 | G37: =D37*F37 -> 1657.5 | I37: =G37 -> 1657.5
B38: Floor protection | C38: AE100 | D38: =D37 -> 663 | E38: SF | F38: 1.5 | G38: =D38*F38 -> 994.5 | I38: =G38 -> 994.5
B39: Trash Removal | D39: ='Cost Summary'!$J$8*4.3*0.05 -> 2.15 | F39: ='Labor Rates Calculator'!$G$29*40 -> 2124.6255 | G39: =D39*F39 -> 4567.9447 | I39: =G39 -> 4567.9447
B41: Phase 2 Bocce & Basketball
B43: Phase 2 New Spa Building
B44: Misc. Rough Carpentry | C44: AE101 | D44: ='Cost Summary'!$N$7 -> 11678 | E44: SF | F44: 8 | G44: =D44*F44 -> 93424 | I44: =G44 -> 93424
B45: Floor protection | C45: AE101 | D45: =D44 -> 11678 | E45: SF | F45: 1.5 | G45: =D45*F45 -> 17517 | I45: =G45 -> 17517
B46: Trash Removal | D46: ='Cost Summary'!$N$8*4.3*0.5 -> 30.1 | F46: ='Labor Rates Calculator'!$G$29*40 -> 2124.6255 | G46: =D46*F46 -> 63951.226 | I46: =G46 -> 63951.226
B48: Phase 2 POA Building
B50: Phase 2 New Fitness Building
B51: Misc. Rough Carpentry | C51: AE101 | D51: ='Cost Summary'!$R$7 -> 11225 | E51: SF | F51: 8 | G51: =D51*F51 -> 89800 | I51: =G51 -> 89800
B52: Floor protection | C52: AE101 | D52: =D51 -> 11225 | E52: SF | F52: 1.5 | G52: =D52*F52 -> 16837.5 | I52: =G52 -> 16837.5
B53: Trash Removal | D53: ='Cost Summary'!$R$8*4.3*0.5 -> 25.8 | F53: ='Labor Rates Calculator'!$G$29*40 -> 2124.6255 | G53: =D53*F53 -> 54815.337 | I53: =G53 -> 54815.337
B54: Temp protection at openings | D54: ='02A Demolition'!$D$49 -> 25 | E54: LF | F54: 200 | G54: =D54*F54 -> 5000 | I54: =G54 -> 5000
B56: Phase 3 19th Hole Restaurant
B58: Phase 3 Reno Existing Fitness Building
F63: SUBTOTAL | I63: =SUM(I24:I62) -> 348565.01 | K63: =SUM(K24:K62) -> 0 | M63: =SUM(M23:M62) -> 0 | O63: =SUM(O23:O62) -> 0 | Q63: =SUM(Q24:Q62) -> 0 | S63: =SUM(S24:S62) -> 0
F64: BOND RATE | H64: 0 | J64: 0 | L64: 0 | N64: 0 | P64: 0 | R64: 0
F65: BOND AMOUNT | I65: =H64*$I$63 -> 0 | K65: =J64*$K$63 -> 0 | M65: =L64*$M$63 -> 0 | O65: =N64*$O$63 -> 0 | Q65: =P64*$Q$63 -> 0 | S65: =R64*S63 -> 0
F67: ADJUSTED TOTAL | I67: =SUM(I63:I66) -> 348565.01 | K67: =SUM(K63:K65) -> 0 | M67: =SUM(M63:M65) -> 0 | O67: =SUM(O63:O65) -> 0 | Q67: =SUM(Q63:Q65) -> 0 | S67: =SUM(S63:S65) -> 0
F68: Cost per SF | I68: =I67/'Area Calculations'!$J$4 -> #DIV/0! | K68: =K67/'Area Calculations'!$J$4 -> #DIV/0! | M68: =M67/'Area Calculations'!$J$4 -> #DIV/0! | O68: =O67/'Area Calculations'!$J$4 -> #DIV/0! | Q68: =Q67/'Area Calculations'!$J$4 -> #DIV/0! | S68: =S67/'Area Calculations'!$J$4 -> #DIV/0!
F69: Cost per Unit | I69: =I67/'Area Calculations'!#REF! -> #REF! | K69: =K67/'Area Calculations'!#REF! -> #REF! | M69: =M67/'Area Calculations'!#REF! -> #REF! | O69: =O67/'Area Calculations'!#REF! -> #REF! | Q69: =Q67/'Area Calculations'!#REF! -> #REF! | S69: =S67/'Area Calculations'!#REF! -> #REF!
A71: QUALIFICATIONS
A75: EXCLUSIONS/OWNER PROVIDED ITEMS:
A79: ALTERNATES:
A83: PROPOSED VE (Provide Clear Description):
A87: FULLY LOADED LABOR RATES
B88: Laborer
B89: Mechanic
B90: Superintendent
B91: Project Manager
A93: SCHEDULE
B94: Prepared shop drawings/submittals
B95: Mobilization
B96: Total duration to complete scope of work
A98: Winner
A99: Company
A100: Contact
A101: Phone
A102: Email
A103: Base Bid | B103: =H8 -> 348565.01
B105: Need Prequalification
B106: Prequalified

Sheet 06C Wood Trusses
G1: Hedrick Plug
F2: X | G2: Excluded
B3: BACK TO SUMMARY SHEET | F3: I | G3: Included | H3: Bidder 1 | J3: Bidder 2 | L3: Bidder 3 | N3: Bidder 4 | P3: Bidder 5 | R3: Bidder 6
A4: Project: | B4: ='Area Calculations'!B4 -> The Club at Ibis Conceptual Estimate | G4: Company
A5: Trade: | B5: Wood Trusses | G5: Contact
A6: CSI Code: | B6: 06C | G6: Phone
A7: Date: | G7: Email
A8: Adjusted Bid | G8: Adjusted Bid | H8: =I58 -> 41580 | J8: =K58 -> 0 | L8: =M58 -> 0 | N8: =O58 -> 0 | P8: =Q58 -> 0 | R8: =S58 -> 0
A9: BID DOCUMENTS: | C9: Plan/ Spec. Package | D9: QTY | E9: U/M | F9: Unit Cost | G9: Subtotal | H9: Yes/No | I9: Price | J9: Yes/No | K9: Price | L9: Yes/No | M9: Price | N9: Yes/No | O9: Price | P9: Yes/No | Q9: Price | R9: Yes/No | S9: Price
B10: Plans By Division
B11: ='Area Calculations'!M62 -> Architectural Drawings by | C11: P
B12: ='Area Calculations'!M63 -> Structural Drawings by | C12: P
B13: ='Area Calculations'!M64 -> MEP FA FP Drawings by | C13: P
B14: ='Area Calculations'!M65 -> Civil Drawings by | C14: P
B15: ='Area Calculations'!M66 -> Land scape Drawings by | C15: P
B16: ='Area Calculations'!M67 -> Kitchen Drawings by | C16: P
B17: ='Area Calculations'!M68 -> Storefront Designer by | C17: P
B18: ='Area Calculations'!M69 -> Geotech report by | C18: P
B19: ='Area Calculations'!M70 -> Specifications | C19: P
B21: Wood Trusses
B22: GENERAL INCLUSIONS
B23: INCLUDES ALL SALES TAX
B24: ALL HOISTING & RIGGING REQUIRED TO COMPLETE THIS SCOPE
B25: PROVIDE P&P BONDS
B26: FLORIDA STATE CONTRACTORS LIC.
B27: GENERAL LIABILITY AND WORKERS COMP. INSURANCE LIMITS
B28: STATE AND LOCAL TAXES
B29: COMPASS
B30: SPECIFIC TRADE SCOPE OF WORK REQUIREMENTS
B31: BASE BID
B32: Building SF
... B36: Phase 1 Racquet Courts
B37: Trusses - Restrooms | C37: AE100 | D37: 1024 | E37: SF | F37: 7 | G37: =D37*F37 -> 7168 | I37: =G37 -> 7168
B39: Phase 2 Bocce & Basketball
B41: Phase 2 New Spa Building
B43: Phase 2 POA Building
B45: Phase 2 New Fitness Building
B46: Addition only | C46: AE103 | D46: 4916 | E46: SF | F46: =F37 -> 7 | G46: =D46*F46 -> 34412 | I46: =G46 -> 34412
B48: Phase 3 19th Hole Restaurant
B50: Phase 3 Reno Existing Fitness Building
F54: SUBTOTAL | I54: =SUM(I23:I53) -> 41580 | K54: =SUM(K23:K53) -> 0 | M54: =SUM(M22:M53) -> 0 | O54: =SUM(O22:O53) -> 0 | Q54: =SUM(Q23:Q53) -> 0 | S54: =SUM(S23:S53) -> 0
F55: BOND RATE | H55: 0 | J55: 0 | L55: 0 | N55: 0 | P55: 0 | R55: 0
F56: BOND AMOUNT | I56: =H55*$I$54 -> 0 | K56: =J55*$K$54 -> 0 | M56: =L55*$M$54 -> 0 | O56: =N55*$O$54 -> 0 | Q56: =P55*$Q$54 -> 0 | S56: =R55*S54 -> 0
F58: ADJUSTED TOTAL | I58: =SUM(I54:I56) -> 41580 | K58: =SUM(K54:K56) -> 0 | M58: =SUM(M54:M56) -> 0 | O58: =SUM(O54:O56) -> 0 | Q58: =SUM(Q54:Q56) -> 0 | S58: =SUM(S54:S56) -> 0
F59: Cost per SF | I59: =I58/'Area Calculations'!$J$4 -> #DIV/0! | K59: =K58/'Area Calculations'!$J$4 -> #DIV/0! | M59: =M58/'Area Calculations'!$J$4 -> #DIV/0! | O59: =O58/'Area Calculations'!$J$4 -> #DIV/0! | Q59: =Q58/'Area Calculations'!$J$4 -> #DIV/0! | S59: =S58/'Area Calculations'!$J$4 -> #DIV/0!
F60: Cost per Unit | I60: =I58/'Area Calculations'!#REF! -> #REF! | K60: =K58/'Area Calculations'!#REF! -> #REF! | M60: =M58/'Area Calculations'!#REF! -> #REF! | O60: =O58/'Area Calculations'!#REF! -> #REF! | Q60: =Q58/'Area Calculations'!#REF! -> #REF! | S60: =S58/'Area Calculations'!#REF! -> #REF!
A62: QUALIFICATIONS
A66: EXCLUSIONS/OWNER PROVIDED ITEMS:
A70: ALTERNATES:
A74: PROPOSED VE (Provide Clear Description):
A78: FULLY LOADED LABOR RATES
B79: Laborer
B80: Mechanic
B81: Superintendent
B82: Project Manager
A84: SCHEDULE
B85: Prepared shop drawings/submittals
B86: Mobilization
B87: Total duration to complete scope of work
A89: Winner
A90: Company
A91: Contact
A92: Phone
A93: Email
A94: Base Bid | B94: =H8 -> 41580
B96: Need Prequalification
B97: Prequalified

Sheet 06D Interior Finish Carpentry
G1: Hedrick Plug
F2: X | G2: Excluded
B3: BACK TO SUMMARY SHEET | F3: I | G3: Included | H3: Bidder 1 | J3: Bidder 2 | L3: Bidder 3 | N3: Bidder 4 | P3: Bidder 5 | R3: Bidder 6
A4: Project: | B4: ='Area Calculations'!B4 -> The Club at Ibis Conceptual Estimate | G4: Company
A5: Trade: | B5: Interior Finish Carpentry | G5: Contact
A6: CSI Code: | B6: 06D | G6: Phone
A7: Date: | G7: Email
A8: Adjusted Bid | G8: Adjusted Bid | H8: =I64 -> 0 | J8: =K64 -> 0 | L8: =M64 -> 0 | N8: =O64 -> 0 | P8: =Q64 -> 0 | R8: =S64 -> 0
A9: BID DOCUMENTS: | C9: Plan/ Spec. Package | D9: QTY | E9: U/M | F9: Unit Cost | G9: Subtotal | H9: Yes/No | I9: Price | J9: Yes/No | K9: Price | L9: Yes/No | M9: Price | N9: Yes/No | O9: Price | P9: Yes/No | Q9: Price | R9: Yes/No | S9: Price
B10: Plans By Division
B11: ='Area Calculations'!M62 -> Architectural Drawings by | C11: P
B12: ='Area Calculations'!M63 -> Structural Drawings by | C12: P
B13: ='Area Calculations'!M64 -> MEP FA FP Drawings by | C13: P
B14: ='Area Calculations'!M65 -> Civil Drawings by | C14: P
B15: ='Area Calculations'!M66 -> Land scape Drawings by | C15: P
B16: ='Area Calculations'!M67 -> Kitchen Drawings by | C16: P
B17: ='Area Calculations'!M68 -> Storefront Designer by | C17: P
B18: ='Area Calculations'!M69 -> Geotech report by | C18: P
B19: ='Area Calculations'!M70 -> Specifications | C19: P
B21: Interior Finish Carpentry
B22: GENERAL INCLUSIONS
B23: INCLUDES ALL SALES TAX
B24: ALL HOISTING & RIGGING REQUIRED TO COMPLETE THIS SCOPE
B25: PROVIDE P&P BONDS
B26: FLORIDA STATE CONTRACTORS LIC.
B27: GENERAL LIABILITY AND WORKERS COMP. INSURANCE LIMITS
B28: STATE AND LOCAL TAXES
B29: COMPASS
B30: SPECIFIC TRADE SCOPE OF WORK REQUIREMENTS
B31: BASE BID
B34: Install Doors:
... B36: a. single leaf
B37: b. 2 leaf | J37: i
B39: Exterior Doors:
B40: a. single leaf
B41: b. 2 leaf
B43: Base Molding:
B44: a. base (material)
B45: b. base (install) - Paint Grade $1.75 LF and Stain Grade $2.50 LF
B47: Chair Rail:
B48: a. chair rail (material)
B49: b. chair rail (install)
B51: Crown Molding:
B52: a. crown molding (material)
B53: b. crown molding (install)
B54: c. crown molding backing
F60: SUBTOTAL | I60: =SUM(I23:I59) -> 0 | K60: =SUM(K23:K59) -> 0 | M60: =SUM(M22:M59) -> 0 | O60: =SUM(O22:O59) -> 0 | Q60: =SUM(Q23:Q59) -> 0 | S60: =SUM(S23:S59) -> 0
F61: BOND RATE | H61: 0 | J61: 0 | L61: 0 | N61: 0 | P61: 0 | R61: 0
F62: BOND AMOUNT | I62: =H61*$I$60 -> 0 | K62: =J61*$K$60 -> 0 | M62: =L61*$M$60 -> 0 | O62: =N61*$O$60 -> 0 | Q62: =P61*$Q$60 -> 0 | S62: =R61*S60 -> 0
F64: ADJUSTED TOTAL | I64: =SUM(I60:I63) -> 0 | K64: =SUM(K60:K62) -> 0 | M64: =SUM(M60:M62) -> 0 | O64: =SUM(O60:O62) -> 0 | Q64: =SUM(Q60:Q62) -> 0 | S64: =SUM(S60:S62) -> 0
F65: Cost per SF | I65: =I64/'Area Calculations'!$J$4 -> #DIV/0! | K65: =K64/'Area Calculations'!$J$4 -> #DIV/0! | M65: =M64/'Area Calculations'!$J$4 -> #DIV/0! | O65: =O64/'Area Calculations'!$J$4 -> #DIV/0! | Q65: =Q64/'Area Calculations'!$J$4 -> #DIV/0! | S65: =S64/'Area Calculations'!$J$4 -> #DIV/0!
F66: Cost per Unit | I66: =I64/'Area Calculations'!#REF! -> #REF! | K66: =K64/'Area Calculations'!#REF! -> #REF! | M66: =M64/'Area Calculations'!#REF! -> #REF! | O66: =O64/'Area Calculations'!#REF! -> #REF! | Q66: =Q64/'Area Calculations'!#REF! -> #REF! | S66: =S64/'Area Calculations'!#REF! -> #REF!
A68: QUALIFICATIONS
A72: EXCLUSIONS/OWNER PROVIDED ITEMS:
A76: ALTERNATES:
A80: PROPOSED VE (Provide Clear Description):
A84: FULLY LOADED LABOR RATES
B85: Laborer
B86: Mechanic
B87: Superintendent
B88: Project Manager
A90: SCHEDULE
B91: Prepared shop drawings/submittals
B92: Mobilization
B93: Total duration to complete scope of work
A95: Winner
A96: Company
A97: Contact
A98: Phone
A99: Email
A100: Base Bid
B102: Need Prequalification
B103: Prequalified

Sheet 06E Heavy Timber Construction
G1: Hedrick Plug
F2: X | G2: Excluded
B3: BACK TO SUMMARY SHEET | F3: I | G3: Included | H3: Bidder 1 | J3: Bidder 2 | L3: Bidder 3 | N3: Bidder4 | P3: Bidder5 | R3: Bidder6
A4: Project: | B4: ='Area Calculations'!B4 -> The Club at Ibis Conceptual Estimate | G4: Company
A5: Trade: | B5: Heavy Timber Construction | G5: Contact
A6: CSI Code: | B6: 06E | G6: Phone
A7: Date: | G7: Email
A8: Adjusted Bid | G8: Adjusted Bid | H8: =I52 -> 0 | J8: =K52 -> 0 | L8: =M52 -> 0 | N8: =O52 -> 0 | P8: =Q52 -> 0 | R8: =S52 -> 0
A9: BID DOCUMENTS: | C9: Plan/ Spec. Package | D9: QTY | E9: U/M | F9: Unit Cost | G9: Subtotal | H9: Yes/No | I9: Price | J9: Yes/No | K9: Price | L9: Yes/No | M9: Price | N9: Yes/No | O9: Price | P9: Yes/No | Q9: Price | R9: Yes/No | S9: Price
B10: Plans By Division
B11: ='Area Calculations'!M62 -> Architectural Drawings by | C11: P
B12: ='Area Calculations'!M63 -> Structural Drawings by | C12: P
B13: ='Area Calculations'!M64 -> MEP FA FP Drawings by | C13: P
B14: ='Area Calculations'!M65 -> Civil Drawings by | C14: P
B15: ='Area Calculations'!M66 -> Land scape Drawings by | C15: P
B16: ='Area Calculations'!M67 -> Kitchen Drawings by | C16: P
B17: ='Area Calculations'!M68 -> Storefront Designer by | C17: P
B18: ='Area Calculations'!M69 -> Geotech report by | C18: P
B19: ='Area Calculations'!M70 -> Specifications | C19: P
B21: Heavy Timber Construction
A22: 3 | B22: This Subcontractor is responsible to supply and install a complete U.L. listed firestopping system for each penetration of their work through any fire rated assembly in order to maintain the fire rating of that work. Subcontractor to provide affidavit form their qualifier indicating all fire caulking is complete for the entire project. | C22: P
B23: GENERAL INCLUSIONS
B24: INCLUDES ALL SALES TAX
B25: ALL HOISTING & RIGGING REQUIRED TO COMPLETE THIS SCOPE
B26: PROVIDE P&P BONDS
B27: FLORIDA STATE CONTRACTORS LIC.
B28: GENERAL LIABILITY AND WORKERS COMP. INSURANCE LIMITS
B29: STATE AND LOCAL TAXES
B30: COMPASS
B31: SPECIFIC TRADE SCOPE OF WORK REQUIREMENTS
B32: BASE BID
H37: x
F48: SUBTOTAL | I48: =SUM(I24:I47) -> 0 | K48: =SUM(K24:K47) -> 0 | M48: =SUM(M24:M47) -> 0 | O48: =SUM(O24:O47) -> 0 | Q48: =SUM(Q24:Q47) -> 0 | S48: =SUM(S24:S47) -> 0
F49: BOND RATE | H49: 0 | J49: 0 | L49: 0 | N49: 0 | P49: 0 | R49: 0
F50: BOND AMOUNT | I50: =H49*I48 -> 0 | K50: =J49*K48 -> 0 | M50: =L49*M48 -> 0 | O50: =N49*O48 -> 0 | Q50: =P49*Q48 -> 0 | S50: =R49*S48 -> 0
F52: ADJUSTED TOTAL | I52: =SUM(I48:I51) -> 0 | K52: =SUM(K48:K51) -> 0 | M52: =SUM(M48:M51) -> 0 | O52: =SUM(O48:O51) -> 0 | Q52: =SUM(Q48:Q51) -> 0 | S52: =SUM(S48:S51) -> 0
F53: Cost per SF | I53: =I52/'Area Calculations'!$J$4 -> #DIV/0! | K53: =K52/'Area Calculations'!$J$4 -> #DIV/0! | M53: =M52/'Area Calculations'!$J$4 -> #DIV/0! | O53: =O52/'Area Calculations'!$J$4 -> #DIV/0! | Q53: =Q52/'Area Calculations'!$J$4 -> #DIV/0! | S53: =S52/'Area Calculations'!$J$4 -> #DIV/0!
F54: Cost per Unit | I54: =I52/'Area Calculations'!#REF! -> #REF! | K54: =K52/'Area Calculations'!#REF! -> #REF! | M54: =M52/'Area Calculations'!#REF! -> #REF! | O54: =O52/'Area Calculations'!#REF! -> #REF! | Q54: =Q52/'Area Calculations'!#REF! -> #REF! | S54: =S52/'Area Calculations'!#REF! -> #REF!
A56: QUALIFICATIONS
A60: EXCLUSIONS/OWNER PROVIDED ITEMS:
A64: ALTERNATES:
A68: PROPOSED VE (Provide Clear Description):
A72: FULLY LOADED LABOR RATES
B73: Laborer
B74: Mechanic
B75: Superintendent
B76: Project Manager
A78: SCHEDULE
B79: Prepared shop drawings/submittals
B80: Mobilization
B81: Total duration to complete scope of work
A83: Winner
A84: Company
A85: Contact
A86: Phone
A87: Email
A88: Base Bid
B90: Need Prequalification
B91: Prequalified

Sheet 06G Exterior Finish Carpent
G1: Hedrick Plug
F2: X | G2: Excluded
B3: BACK TO SUMMARY SHEET | F3: I | G3: Included | H3: Bidder 1 | J3: Bidder 2 | L3: Bidder 3 | N3: Bidder 4 | P3: Bidder 5 | R3: Bidder 6
A4: Project: | B4: ='Area Calculations'!B4 -> The Club at Ibis Conceptual Estimate | G4: Company
A5: Trade: | B5: Exterior Finish Carpentry | G5: Contact
A6: CSI Code: | B6: 06G | G6: Phone
A7: Date: | G7: Email
A8: Adjusted Bid | G8: Adjusted Bid | H8: =I64 -> 0 | J8: =K64 -> 0 | L8: =M64 -> 0 | N8: =O64 -> 0 | P8: =Q64 -> 0 | R8: =S64 -> 0
A9: BID DOCUMENTS: | C9: Plan/ Spec. Package | D9: QTY | E9: U/M | F9: Unit Cost | G9: Subtotal | H9: Yes/No | I9: Price | J9: Yes/No | K9: Price | L9: Yes/No | M9: Price | N9: Yes/No | O9: Price | P9: Yes/No | Q9: Price | R9: Yes/No | S9: Price
B10: Plans By Division
B11: ='Area Calculations'!M62 -> Architectural Drawings by | C11: P
B12: ='Area Calculations'!M63 -> Structural Drawings by | C12: P
B13: ='Area Calculations'!M64 -> MEP FA FP Drawings by | C13: P
B14: ='Area Calculations'!M65 -> Civil Drawings by | C14: P
B15: ='Area Calculations'!M66 -> Land scape Drawings by | C15: P
B16: ='Area Calculations'!M67 -> Kitchen Drawings by | C16: P
B17: ='Area Calculations'!M68 -> Storefront Designer by | C17: P
B18: ='Area Calculations'!M69 -> Geotech report by | C18: P
B19: ='Area Calculations'!M70 -> Specifications | C19: P
B21: Exterior Finish Carpentry
B22: GENERAL INCLUSIONS
B23: INCLUDES ALL SALES TAX
B24: ALL HOISTING & RIGGING REQUIRED TO COMPLETE THIS SCOPE
B25: PROVIDE P&P BONDS
B26: FLORIDA STATE CONTRACTORS LIC.
B27: GENERAL LIABILITY AND WORKERS COMP. INSURANCE LIMITS
B28: STATE AND LOCAL TAXES
B29: COMPASS
B30: SPECIFIC TRADE SCOPE OF WORK REQUIREMENTS
B31: BASE BID
B34: Install Doors:
... B36: a. single leaf
B37: b. 2 leaf | J37: i
B39: Exterior Doors:
B40: a. single leaf
B41: b. 2 leaf
B43: Base Molding:
B44: a. base (material)
B45: b. base (install) - Paint Grade $1.75 LF and Stain Grade $2.50 LF
B47: Chair Rail:
B48: a. chair rail (material)
B49: b. chair rail (install)
B51: Crown Molding:
B52: a. crown molding (material)
B53: b. crown molding (install)
B54: c. crown molding backing
F60: SUBTOTAL | I60: =SUM(I23:I59) -> 0 | K60: =SUM(K23:K59) -> 0 | M60: =SUM(M22:M59) -> 0 | O60: =SUM(O22:O59) -> 0 | Q60: =SUM(Q23:Q59) -> 0 | S60: =SUM(S23:S59) -> 0
F61: BOND RATE | H61: 0 | J61: 0 | L61: 0 | N61: 0 | P61: 0 | R61: 0
F62: BOND AMOUNT | I62: =H61*$I$60 -> 0 | K62: =J61*$K$60 -> 0 | M62: =L61*$M$60 -> 0 | O62: =N61*$O$60 -> 0 | Q62: =P61*$Q$60 -> 0 | S62: =R61*S60 -> 0
F64: ADJUSTED TOTAL | I64: =SUM(I60:I63) -> 0 | K64: =SUM(K60:K62) -> 0 | M64: =SUM(M60:M62) -> 0 | O64: =SUM(O60:O62) -> 0 | Q64: =SUM(Q60:Q62) -> 0 | S64: =SUM(S60:S62) -> 0
F65: Cost per SF | I65: =I64/'Area Calculations'!$J$4 -> #DIV/0! | K65: =K64/'Area Calculations'!$J$4 -> #DIV/0! | M65: =M64/'Area Calculations'!$J$4 -> #DIV/0! | O65: =O64/'Area Calculations'!$J$4 -> #DIV/0! | Q65: =Q64/'Area Calculations'!$J$4 -> #DIV/0! | S65: =S64/'Area Calculations'!$J$4 -> #DIV/0!
F66: Cost per Unit | I66: =I64/'Area Calculations'!#REF! -> #REF! | K66: =K64/'Area Calculations'!#REF! -> #REF! | M66: =M64/'Area Calculations'!#REF! -> #REF! | O66: =O64/'Area Calculations'!#REF! -> #REF! | Q66: =Q64/'Area Calculations'!#REF! -> #REF! | S66: =S64/'Area Calculations'!#REF! -> #REF!
A68: QUALIFICATIONS
A72: EXCLUSIONS/OWNER PROVIDED ITEMS:
A76: ALTERNATES:
A80: PROPOSED VE (Provide Clear Description):
A84: FULLY LOADED LABOR RATES
B85: Laborer
B86: Mechanic
B87: Superintendent
B88: Project Manager
A90: SCHEDULE
B91: Prepared shop drawings/submittals
B92: Mobilization
B93: Total duration to complete scope of work
A95: Winner
A96: Company
A97: Contact
A98: Phone
A99: Email
A100: Base Bid
B102: Need Prequalification
B103: Prequalified

Sheet 07B Sprayed Insulation
G1: Hedrick Plug
F2: X | G2: Excluded
B3: BACK TO SUMMARY SHEET | F3: I | G3: Included | H3: Bidder 1 | J3: Bidder 2 | L3: Bidder 3 | N3: Bidder 4 | P3: Bidder5 | R3: Bidder6
A4: Project: | B4: ='Area Calculations'!B4 -> The Club at Ibis Conceptual Estimate | G4: Company
A5: Trade: | B5: Sprayed Insulation | G5: Contact
A6: CSI Code: | B6: 07B | G6: Phone
A7: Date: | G7: Email
A8: Adjusted Bid | G8: Adjusted Bid | H8: =I58 -> 0 | J8: =K58 -> 0 | L8: =M58 -> 0 | N8: =O58 -> 0 | P8: =Q58 -> 0 | R8: =S58 -> 0
A9: BID DOCUMENTS: | C9: Plan/ Spec. Package | D9: QTY | E9: U/M | F9: Unit Cost | G9: Subtotal | H9: Yes/No | I9: Price | J9: Yes/No | K9: Price | L9: Yes/No | M9: Price | N9: Yes/No | O9: Price | P9: Yes/No | Q9: Price | R9: Yes/No | S9: Price
B10: Plans By Division
B11: ='Area Calculations'!M62 -> Architectural Drawings by | C11: P
B12: ='Area Calculations'!M63 -> Structural Drawings by | C12: P
B13: ='Area Calculations'!M64 -> MEP FA FP Drawings by | C13: P
B14: ='Area Calculations'!M65 -> Civil Drawings by | C14: P
B15: ='Area Calculations'!M66 -> Land scape Drawings by | C15: P
B16: ='Area Calculations'!M67 -> Kitchen Drawings by | C16: P
B17: ='Area Calculations'!M68 -> Storefront Designer by | C17: P
B18: ='Area Calculations'!M69 -> Geotech report by | C18: P
B19: ='Area Calculations'!M70 -> Specifications | C19: P
B20: ='Area Calculations'!M71 -> 0 | C20: P
B21: ='Area Calculations'!M72 -> 0 | C21: P
B22: ='Area Calculations'!M73 -> 0 | C22: P
B23: ='Area Calculations'!M74 -> 0 | C23: P
B25: Sprayed Insulation
B26: GENERAL INCLUSIONS
B27: INCLUDES ALL SALES TAX
B28: ALL HOISTING & RIGGING REQUIRED TO COMPLETE THIS SCOPE
B29: PROVIDE P&P BONDS
B30: FLORIDA STATE CONTRACTORS LIC.
B31: GENERAL LIABILITY AND WORKERS COMP. INSURANCE LIMITS
B32: STATE AND LOCAL TAXES
B33: SPECIFIC TRADE SCOPE OF WORK REQUIREMENTS
B34: BASE BID
B35: Building SF
H43: i
F54: SUBTOTAL | I54: =SUM(I26:I53) -> 0 | K54: =SUM(K26:K53) -> 0 | M54: =SUM(M26:M53) -> 0 | O54: =SUM(O26:O53) -> 0 | Q54: =SUM(Q26:Q53) -> 0 | S54: =SUM(S26:S53) -> 0
F55: BOND RATE | H55: 0 | J55: 0 | L55: 0 | N55: 0 | P55: 0 | R55: 0
F56: BOND AMOUNT | I56: =I54*H55 -> 0 | K56: =K54*J55 -> 0 | M56: =M54*L55 -> 0 | O56: =O54*N55 -> 0 | Q56: =Q54*P55 -> 0 | S56: =S54*R55 -> 0
F58: ADJUSTED TOTAL | I58: =SUM(I54:I56) -> 0 | K58: =SUM(K54:K56) -> 0 | M58: =SUM(M54:M56) -> 0 | O58: =SUM(O54:O56) -> 0 | Q58: =SUM(Q54:Q56) -> 0 | S58: =SUM(S54:S56) -> 0
F59: Cost per SF | I59: =I58/'Area Calculations'!$J$4 -> #DIV/0! | K59: =K58/'Area Calculations'!$J$4 -> #DIV/0! | M59: =M58/'Area Calculations'!$J$4 -> #DIV/0! | O59: =O58/'Area Calculations'!$J$4 -> #DIV/0! | Q59: =Q58/'Area Calculations'!$J$4 -> #DIV/0! | S59: =S58/'Area Calculations'!$J$4 -> #DIV/0!
F60: Cost per Unit | I60: =I58/'Area Calculations'!#REF! -> #REF! | K60: =K58/'Area Calculations'!#REF! -> #REF! | M60: =M58/'Area Calculations'!#REF! -> #REF! | O60: =O58/'Area Calculations'!#REF! -> #REF! | Q60: =Q58/'Area Calculations'!#REF! -> #REF! | S60: =S58/'Area Calculations'!#REF! -> #REF!
A62: QUALIFICATIONS
A66: EXCLUSIONS/OWNER PROVIDED ITEMS:
A70: ALTERNATES:
A74: PROPOSED VE (Provide Clear Description):
A78: FULLY LOADED LABOR RATES
B79: Laborer
B80: Mechanic
B81: Superintendent
B82: Project Manager
A84: SCHEDULE
B85: Prepared shop drawings/submittals
B86: Mobilization
B87: Total duration to complete scope of work
A89: Winner
A90: Company
A91: Contact
A92: Phone
A93: Email
A94: Base Bid
B96: Need Prequalification
B97: Prequalified

Sheet 07C Fireproofing&Firestopping
G1: Hedrick Plug
F2: X | G2: Excluded
B3: BACK TO SUMMARY SHEET | F3: I | G3: Included | H3: Bidder 1 | J3: Bidder 2 | L3: Bidder 3 | N3: Bidder 4 | P3: Bidder5 | R3: Bidder6
A4: Project: | B4: ='Area Calculations'!B4 -> The Club at Ibis Conceptual Estimate | G4: Company
A5: Trade: | B5: Fireproofing & Firestopping | G5: Contact
A6: CSI Code: | B6: 07C | G6: Phone
A7: Date: | G7: Email
A8: Adjusted Bid | G8: Adjusted Bid | H8: =I49 -> 0 | J8: =K49 -> 0 | L8: =M49 -> 0 | N8: =O49 -> 0 | P8: =Q49 -> 0 | R8: =S49 -> 0
A9: BID DOCUMENTS: | C9: Plan/ Spec. Package | D9: QTY | E9: U/M | F9: Unit Cost | G9: Subtotal | H9: Yes/No | I9: Price | J9: Yes/No | K9: Price | L9: Yes/No | M9: Price | N9: Yes/No | O9: Price | P9: Yes/No | Q9: Price | R9: Yes/No | S9: Price
B10: Plans By Division
B11: ='Area Calculations'!M62 -> Architectural Drawings by | C11: P
B12: ='Area Calculations'!M63 -> Structural Drawings by | C12: P
B13: ='Area Calculations'!M64 -> MEP FA FP Drawings by | C13: P
B14: ='Area Calculations'!M65 -> Civil Drawings by | C14: P
B15: ='Area Calculations'!M66 -> Land scape Drawings by | C15: P
B16: ='Area Calculations'!M67 -> Kitchen Drawings by | C16: P
B17: ='Area Calculations'!M68 -> Storefront Designer by | C17: P
B18: ='Area Calculations'!M69 -> Geotech report by | C18: P
B20: Fireproofing & Firestopping
B21: GENERAL INCLUSIONS
B22: INCLUDES ALL SALES TAX
B23: ALL HOISTING & RIGGING REQUIRED TO COMPLETE THIS SCOPE
B24: PROVIDE P&P BONDS
B25: FLORIDA STATE CONTRACTORS LIC.
B26: GENERAL LIABILITY AND WORKERS COMP. INSURANCE LIMITS
B27: STATE AND LOCAL TAXES
B28: COMPASS
B29: SPECIFIC TRADE SCOPE OF WORK REQUIREMENTS
B30: BASE BID
B31: Building SF
H35: i
B38: Penetartions for MEP FP
B39: Fire-rated head of walls and partitions
B44: Permits
F45: SUBTOTAL | I45: =SUM(I21:I44) -> 0 | K45: =SUM(K21:K44) -> 0 | M45: =SUM(M21:M44) -> 0 | O45: =SUM(O21:O44) -> 0 | Q45: =SUM(Q21:Q44) -> 0 | S45: =SUM(S21:S44) -> 0
F46: BOND RATE | H46: 0 | J46: 0 | L46: 0 | N46: 0 | P46: 0 | R46: 0
F47: BOND AMOUNT | I47: =I45*H46 -> 0 | K47: =K45*J46 -> 0 | M47: =M45*L46 -> 0 | O47: =O45*N46 -> 0 | Q47: =Q45*P46 -> 0 | S47: =S45*R46 -> 0
F48: Davis Bacon | H48: 0 | I48: =I45*H48 -> 0
F49: ADJUSTED TOTAL | I49: =SUM(I45:I48) -> 0 | K49: =SUM(K45:K47) -> 0 | M49: =SUM(M45:M47) -> 0 | O49: =SUM(O45:O47) -> 0 | Q49: =SUM(Q45:Q47) -> 0 | S49: =SUM(S45:S47) -> 0
F50: Cost per SF | I50: =I49/'Area Calculations'!$J$4 -> #DIV/0! | K50: =K49/'Area Calculations'!$J$4 -> #DIV/0! | M50: =M49/'Area Calculations'!$J$4 -> #DIV/0! | O50: =O49/'Area Calculations'!$J$4 -> #DIV/0! | Q50: =Q49/'Area Calculations'!$J$4 -> #DIV/0! | S50: =S49/'Area Calculations'!$J$4 -> #DIV/0!
F51: Cost per Unit | I51: =I49/'Area Calculations'!#REF! -> #REF! | K51: =K49/'Area Calculations'!#REF! -> #REF! | M51: =M49/'Area Calculations'!#REF! -> #REF! | O51: =O49/'Area Calculations'!#REF! -> #REF! | Q51: =Q49/'Area Calculations'!#REF! -> #REF! | S51: =S49/'Area Calculations'!#REF! -> #REF!
A53: QUALIFICATIONS
A57: EXCLUSIONS/OWNER PROVIDED ITEMS:
A61: ALTERNATES:
A65: PROPOSED VE (Provide Clear Description):
A69: FULLY LOADED LABOR RATES
B70: Laborer
B71: Mechanic
B72: Superintendent
B73: Project Manager
A75: SCHEDULE
B76: Prepared shop drawings/submittals
B77: Mobilization
B78: Total duration to complete scope of work
A80: Winner
A81: Company
A82: Contact
A83: Phone
A84: Email
A85: Base Bid
B87: Need Prequalification
B88: Prequalified

Sheet 06F Millwork
G1: Hedrick Plug
F2: X | G2: Excluded
B3: BACK TO SUMMARY SHEET | F3: I | G3: Included | H3: Bidder 1 | J3: Bidder 2 | L3: Bidder 3 | N3: Bidder4 | P3: Bidder5 | R3: Bidder6
A4: Project: | B4: ='Area Calculations'!B4 -> The Club at Ibis Conceptual Estimate | G4: Company
A5: Trade: | B5: Millwork | G5: Contact
A6: CSI Code: | B6: 06F | G6: Phone
A7: Date: | G7: Email
A8: Adjusted Bid | G8: Adjusted Bid | H8: =I82 -> 504620 | J8: =K82 -> 0 | L8: =M82 -> 0 | N8: =O82 -> 0 | P8: =Q82 -> 0 | R8: =S82 -> 0
A9: BID DOCUMENTS: | C9: Plan/ Spec. Package | D9: QTY | E9: U/M | F9: Unit Cost | G9: Subtotal | H9: Yes/No | I9: Price | J9: Yes/No | K9: Price | L9: Yes/No | M9: Price | N9: Yes/No | O9: Price | P9: Yes/No | Q9: Price | R9: Yes/No | S9: Price
B10: Plans By Division
B11: ='Area Calculations'!M62 -> Architectural Drawings by | C11: P
B12: ='Area Calculations'!M63 -> Structural Drawings by | C12: P
B13: ='Area Calculations'!M64 -> MEP FA FP Drawings by | C13: P
B14: ='Area Calculations'!M65 -> Civil Drawings by | C14: P
B15: ='Area Calculations'!M66 -> Land scape Drawings by | C15: P
B16: ='Area Calculations'!M67 -> Kitchen Drawings by | C16: P
B17: ='Area Calculations'!M68 -> Storefront Designer by | C17: P
B18: ='Area Calculations'!M69 -> Geotech report by | C18: P
B19: ='Area Calculations'!M70 -> Specifications | C19: P
B20: ='Area Calculations'!M71 -> 0 | C20: P
B22: Millwork
B23: GENERAL INCLUSIONS
B24: INCLUDES ALL SALES TAX
B25: ALL HOISTING & RIGGING REQUIRED TO COMPLETE THIS SCOPE
B26: PROVIDE P&P BONDS
B27: FLORIDA STATE CONTRACTORS LIC.
B28: GENERAL LIABILITY AND WORKERS COMP. INSURANCE LIMITS
B29: STATE AND LOCAL TAXES
B30: COMPASS
B31: SPECIFIC TRADE SCOPE OF WORK REQUIREMENTS
B32: BASE BID
B34: Phase 1 Interior Club House Renovations
B36: Phase 1 Racquet Courts
B37: Restroom Vanities | C37: AE100 | D37: 4 | E37: EA | F37: 3000 | G37: =D37*F37 -> 12000 | I37: =G37 -> 12000
B38: Base & trim | C38: AE100 | D38: ='Cost Summary'!$J$7 -> 663 | E38: SF | F38: 4 | G38: =D38*F38 -> 2652 | I38: =G38 -> 2652
B40: Phase 2 Bocce & Basketball
B42: Phase 2 New Spa Building
B43: Lobby 101 - Reception Desk - Polished stone slab allowance $65/SF | C43: AE101 | D43: 1 | E43: EA | F43: 60000 | G43: =D43*F43 -> 60000 | I43: =G43 -> 60000
B44: Lobby 101 - Retail Display Millwork - specialty material allowance $35/SY | C44: AE101 | D44: 2 | E44: EA | F44: 15000 | G44: =D44*F44 -> 30000 | I44: =G44 -> 30000
B45: Hair Salon 102 - Millwork Polished stone slab allowance $65/SF | C45: AE101 | D45: 27 | E45: LF | F45: 550 | G45: =D45*F45 -> 14850 | I45: =G45 -> 14850
B46: Retail 104 - Millwork stone slab allowance $65/SF | C46: AE101 | D46: 19 | E46: LF | F46: 750 | G46: =D46*F46 -> 14250 | I46: =G46 -> 14250
B47: Retail 104 - Specialty material allowance $50/SF | C47: AE101 | D47: =43 -> 43 | E47: SF | F47: 150 | G47: =D47*F47 -> 6450 | I47: =G47 -> 6450
B48: Treatment rooms 105A, 105B, 105C, 105D, 105E, & 105F - Polished stone slab allowance $65/SF | C48: AE101 | D48: =13*6 -> 78 | E48: LF | F48: =F46 -> 750 | G48: =D48*F48 -> 58500 | I48: =G48 -> 58500
B49: Treatment rooms 105A, 105B, 105C, 105D, 105E, & 105F - Specialty material allowance $50/SF | C49: AE101 | D49: =6*13 -> 78 | E49: LF | F49: =F46 -> 750 | G49: =D49*F49 -> 58500 | I49: =G49 -> 58500
B50: Unsiex Restroom 108 - Millwork - Polished stone slab allowance $65/SF | C50: AE101 | D50: 1 | E50: EA | F50: =F37 -> 3000 | G50: =D50*F50 -> 3000 | I50: =G50 -> 3000
B51: Employee Lounge 109 - PLAM and PLAM counter | C51: AE101 | D51: 11 | E51: LF | F51: 500 | G51: =D51*F51 -> 5500 | I51: =G51 -> 5500
B52: Steam Room 110A- Bench | C52: AE101 | D52: 12 | E52: LF | F52: 350 | G52: =D52*F52 -> 4200 | I52: =G52 -> 4200
B53: Steam Room 110B- Bench | C53: AE101 | D53: 12 | E53: LF | F53: =F52 -> 350 | G53: =D53*F53 -> 4200 | I53: =G53 -> 4200
B54: Office 113C - Shelving | C54: AE101 | D54: 8.5 | E54: LF | F54: 500 | G54: =D54*F54 -> 4250 | I54: =G54 -> 4250
