Workbook
Name FCP: 'Bond Calculator'!$B$7

Sheet AREA CALC's
B2: PROJECT AREA CALCULATIONS
E3: BU1 | F3: =E5/E4 -> 0.81350556 | G3: BU2 | H3: =G5/G4 -> 0.80223005 | I3: BU3 | J3: =I5/I4 -> 0.7880291 | K3: BU4 | L3: =K5/K4 -> #VALUE! | M3: Total
B4: Alton Hilltop Gardens | D4: Gross (sf) | E4: =M33 -> 236436 | F4: Gross (sf) | G4: =M56 -> 193538 | H4: Gross (sf) | I4: =M79 -> 84190.8 | J4: Gross (sf) | K4: Gross R (sf) | L4: =E4+G4+I4 -> 514164.8 | M4: Gross T (sf) | N4: =E4+G4+I4+N9+T4 -> 538483.8 | O4: FORMULA OFF GCS | Q4: EFF. | R4: =N5/N4 -> 0.76873028 | S4: Garage (sf) | T4: =M107 -> 9669 | V4: =N4-T4-N9 -> 514164.8
B5: Construction Design | D5: RSF | E5: =F33 -> 192342 | F5: RSF | G5: =F56 -> 155262 | H5: RSF | I5: =F79 -> 66344.8 | J5: RSF | K5: =F99+K99 -> 0 | M5: RSF | N5: =E5+G5+I5 -> 413948.8
D6: Units | E6: =D33 -> 177 | F6: Units | G6: =D56 -> 176 | H6: Units | I6: =D79 -> 79 | J6: Units | K6: =D99 -> 0 | M6: Units | N6: =E6+G6+I6 -> 432
D7: Bedrooms | E7: =H33 -> 348 | F7: Bedrooms | G7: =H56 -> 224 | H7: Bedrooms | I7: =H79 -> 84 | J7: Bedrooms | K7: =H99 -> 0 | M7: Site (acres) | N7: 17.64 | O7: FORMULA OFF GCS
D8: Bathrooms | E8: =G33 -> 318 | F8: Bathrooms | G8: =G56 -> 224 | H8: Bathrooms | I8: =G79 -> 84 | J8: Bathrooms | K8: =G99 -> 0 | M8: Parking Spaces
B9: =NOW() -> 46143.711 | M9: CH | N9: =M115 -> 14650 | O9: FORMULA OFF GCS
C10: 01 Bid set | M10: Duration (months) | N10: 20 | O10: FORMULA OFF GCS
B11: BU Type l | C11: Stories | D11: QTY.
C12: 5 | D12: 3
A13: l. | B13: Levels | C13: Units | D13: QTY. | E13: SF | F13: RSF | G13: Bathrooms | H13: Bedrooms | I13: BOH | J13: Corridors | K13: Balconies | L13: Stairs | M13: Gross SF | N13: %
C14: Building Type l | R14: St1 | T14: =D15+D38+D61 -> 28
B15: =$C$12 -> 5 | C15: St1 | D15: 0 | E15: 598 | F15: =D15*E15 -> 0 | G15: =D15*1 -> 0 | H15: =D15*1 -> 0 | M15: =F15 -> 0 | N15: =M15/$E$4 -> 0 | R15: A1 - 1 bed/1 bath | T15: =D16+D39+D62 -> 128
B16: =$C$12 -> 5 | C16: A1 - 1 bed/1 bath | D16: =12*$D$12 -> 36 | E16: 757 | F16: =D16*E16 -> 27252 | G16: =D16*1 -> 36 | H16: =D16*1 -> 36 | M16: =F16 -> 27252 | N16: =M16/$E$4 -> 0.11526164 | R16: A2 - 1 bed/1 bath | T16: =D17+D40+D63 -> 30
B17: =$C$12 -> 5 | C17: A2 - 1 bed/1 bath | D17: =0*$D$12 -> 0 | E17: 796 | F17: =D17*E17 -> 0 | G17: =D17*1 -> 0 | H17: =D17*1 -> 0 | M17: =F17 -> 0 | N17: =M17/$E$4 -> 0 | R17: B1- M - 1 bed/1 bath | T17: =D18+D41+D64 -> 12
B18: =$C$12 -> 5 | C18: B1- M - 1 bed/1 bath | D18: =0*$D$12 -> 0 | E18: 840 | F18: =D18*E18 -> 0 | G18: =D18*1 -> 0 | H18: =D18*1 -> 0 | M18: =F18 -> 0 | N18: =M18/$E$4 -> 0 | R18: B2- M - 1 bed/1 bath | T18: =D19+D42+D65 -> 5
B19: =$C$12 -> 5 | C19: B2- M - 1 bed/1 bath | D19: =0*$D$12 -> 0 | E19: 844 | F19: =D19*E19 -> 0 | G19: =D19*1 -> 0 | H19: =D19*1 -> 0 | M19: =F19 -> 0 | N19: =M19/$E$4 -> 0 | R19: A3(C2 MOD) - 1 bed/1 bath | T19: =D20+D43+D66 -> 2
B20: =$C$12 -> 5 | C20: A3(C2 MOD) - 1 bed/1 bath | D20: =0*$D$12 -> 0 | E20: 779 | F20: =D20*E20 -> 0 | G20: =D20*1 -> 0 | H20: =D20*1 -> 0 | M20: =F20 -> 0 | N20: =M20/$E$4 -> 0 | R20: B1 | T20: =D21+D44+D67 -> 18
B21: =$C$12 -> 5 | C21: B1 | D21: =0*$D$12 -> 0 | E21: 986 | F21: =D21*E21 -> 0 | G21: =D21*1 -> 0 | H21: =D21*1 -> 0 | M21: =F21 -> 0 | N21: =M21/$E$4 -> 0 | R21: B2 | T21: =D22+D45+D68 -> 9
B22: =$C$12 -> 5 | C22: B2 | D22: =0*$D$12 -> 0 | E22: 993 | F22: =D22*E22 -> 0 | G22: =D22*1 -> 0 | H22: =D22*1 -> 0 | M22: =F22 -> 0 | N22: =M22/$E$4 -> 0 | R22: B2.1 | T22: =D23+D46+D69 -> 6
B23: =$C$12 -> 5 | C23: B2.1 | D23: =0*$D$12 -> 0 | E23: 1014 | F23: =D23*E23 -> 0 | G23: =D23*1 -> 0 | H23: =D23*1 -> 0 | M23: =F23 -> 0 | N23: =M23/$E$4 -> 0 | R23: C1 - 2 bed/2 bath | T23: =D24+D47+D70 -> 44
B24: =$C$12 -> 5 | C24: C1 - 2 bed/2 bath | D24: =13*$D$12 -> 39 | E24: 1148 | F24: =D24*E24 -> 44772 | G24: =D24*2 -> 78 | H24: =D24*2 -> 78 | M24: =F24 -> 44772 | N24: =M24/$E$4 -> 0.18936203 | R24: C2 - 2 bed/2 bath | T24: =D25+D48+D71 -> 50
B25: =$C$12 -> 5 | C25: C2 - 2 bed/2 bath | D25: =14*$D$12 -> 42 | E25: 1054 | F25: =D25*E25 -> 44268 | G25: =D25*2 -> 84 | H25: =D25*2 -> 84 | M25: =F25 -> 44268 | N25: =M25/$E$4 -> 0.18723037 | R25: C3 2 bd /2 bath | T25: =D26+D49+D72 -> 70
B26: =$C$12 -> 5 | C26: C3 2 bd /2 bath | D26: =10*$D$12 -> 30 | E26: 1214 | F26: =D26*E26 -> 36420 | G26: =D26*2 -> 60 | H26: =D26*2 -> 60 | M26: =F26 -> 36420 | N26: =M26/$E$4 -> 0.15403746 | R26: D1 - 3 bed/2 bath | T26: =D27+D50+D73 -> 30
B27: =$C$12 -> 5 | C27: D1 - 3 bed/2 bath | D27: 30 | E27: 1321 | F27: =D27*E27 -> 39630 | G27: =D27*2 -> 60 | H27: =D27*3 -> 90 | M27: =F27 -> 39630 | N27: =M27/$E$4 -> 0.16761407 | T27: =SUM(T14:T26) -> 432
B28: =$C$12 -> 5 | C28: Corridors | J28: =7151*3 -> 21453 | M28: =J28 -> 21453 | N28: =M28/$E$4 -> 0.090734913
B29: =$C$12 -> 5 | C29: Balconies | K29: =3866*3 -> 11598 | M29: =K29 -> 11598 | N29: =M29/$E$4 -> 0.049053444
B30: =$C$12 -> 5 | C30: Amenity/ Maintenance | I30: =1682*3 -> 5046 | L30: 0 | M30: =I30 -> 5046 | N30: =M30/$E$4 -> 0.021341928
B31: =$C$12 -> 5 | C31: Stair Towers | L31: =1999*3 -> 5997 | M31: =L31 -> 5997 | N31: =M31/$E$4 -> 0.025364158
B33: TOTALs | D33: =SUM(D15:D27) -> 177 | F33: =SUM(F15:F27) -> 192342 | G33: =SUM(G15:G27) -> 318 | H33: =SUM(H15:H27) -> 348 | I33: =SUM(I30:I32) -> 5046 | J33: =SUM(J28:J32) -> 21453 | K33: =SUM(K14:K31) -> 11598 | L33: =SUM(L30:L32) -> 5997 | M33: =SUM(M15:M32) -> 236436 | N33: =SUM(N15:N31) -> 1 | O33: Av | P33: =F33/D33 -> 1086.678 | Q33: AV ALL | R33: =N5/432 -> 958.21481
B34: BU Type ll | C34: Stories | D34: QTY.
C35: 5 | D35: 2
A36: ll. | B36: Levels | C36: Units | D36: QTY. | E36: SF | F36: RSF | G36: Bathrooms | H36: Bedrooms | I36: BOH | J36: Corridors | K36: Balconies | L36: Stairs | M36: Gross SF | N36: %
C37: Building type ll
B38: =$C$35 -> 5 | C38: St1 | D38: =9*$D$35 -> 18 | E38: 598 | F38: =D38*E38 -> 10764 | G38: =D38*1 -> 18 | H38: =D38*1 -> 18 | M38: =F38 -> 10764 | N38: =M38/$G$4 -> 0.055616985
B39: =$C$35 -> 5 | C39: A1 - 1 bed/1 bath | D39: =34*$D$35 -> 68 | E39: 757 | F39: =D39*E39 -> 51476 | G39: =D39*1 -> 68 | H39: =D39*1 -> 68 | M39: =F39 -> 51476 | N39: =M39/$G$4 -> 0.26597361
B40: =$C$35 -> 5 | C40: A2 - 1 bed/1 bath | D40: =10*$D$35 -> 20 | E40: 796 | F40: =D40*E40 -> 15920 | G40: =D40*1 -> 20 | H40: =D40*1 -> 20 | M40: =F40 -> 15920 | N40: =M40/$G$4 -> 0.082257748
B41: =$C$35 -> 5 | C41: B1 M - 1 bed/1 bath | D41: =4*$D$35 -> 8 | E41: 840 | F41: =D41*E41 -> 6720 | G41: =D41*1 -> 8 | H41: =D41*1 -> 8 | M41: =F41 -> 6720 | N41: =M41/$G$4 -> 0.034721863
B42: =$C$35 -> 5 | C42: B2 M - 1 bed/1 bath | D42: =0*$D$35 -> 0 | E42: 844 | F42: =D42*E42 -> 0 | G42: =D42*1 -> 0 | H42: =D42*1 -> 0 | M42: =F42 -> 0 | N42: =M42/$G$4 -> 0
B43: =$C$35 -> 5 | C43: A3(C2 MOD) - 1 bed/1 bath | D43: =1*$D$35 -> 2 | E43: 779 | F43: =D43*E43 -> 1558 | G43: =D43*1 -> 2 | H43: =D43*1 -> 2 | M43: =F43 -> 1558 | N43: =M43/$G$4 -> 0.0080500987
B44: =$C$35 -> 5 | C44: B1 | D44: =6*$D$35 -> 12 | E44: 986 | F44: =D44*E44 -> 11832 | G44: =D44*1 -> 12 | H44: =D44*1 -> 12 | M44: =F44 -> 11832 | N44: =M44/$G$4 -> 0.061135281
B45: =$C$35 -> 5 | C45: B2 | D45: =0*$D$35 -> 0 | E45: 993 | F45: =D45*E45 -> 0 | G45: =D45*1 -> 0 | H45: =D45*1 -> 0 | M45: =F45 -> 0 | N45: =M45/$G$4 -> 0
B46: =$C$35 -> 5 | C46: B2.1 | D46: =0*$D$35 -> 0 | E46: 1014 | F46: =D46*E46 -> 0 | G46: =D46*1 -> 0 | H46: =D46*1 -> 0 | M46: =F46 -> 0 | N46: =M46/$G$4 -> 0
B47: =$C$35 -> 5 | C47: C1 - 2 bed/2 bath | D47: =0*$D$35 -> 0 | E47: 1148 | F47: =D47*E47 -> 0 | G47: =D47*2 -> 0 | H47: =D47*2 -> 0 | M47: =F47 -> 0 | N47: =M47/$G$4 -> 0
B48: =$C$35 -> 5 | C48: C2 - 2 bed/2 bath | D48: =4*$D$35 -> 8 | E48: 1054 | F48: =D48*E48 -> 8432 | G48: =D48*2 -> 16 | H48: =D48*2 -> 16 | M48: =F48 -> 8432 | N48: =M48/$G$4 -> 0.043567671
B49: =$C$35 -> 5 | C49: C3 2 bd /2 bath | D49: =20*$D$35 -> 40 | E49: 1214 | F49: =D49*E49 -> 48560 | G49: =D49*2 -> 80 | H49: =D49*2 -> 80 | M49: =F49 -> 48560 | N49: =M49/$G$4 -> 0.2509068
B50: =$C$35 -> 5 | C50: D1 - 3 bed/2 bath | D50: =0*$D$58 -> 0 | E50: 1321 | F50: =D50*E50 -> 0 | G50: =D50*2 -> 0 | H50: =D50*3 -> 0 | M50: =F50 -> 0 | N50: =M50/$G$4 -> 0
C51: Corridors | J51: =8703*2 -> 17406 | M51: =J51 -> 17406 | N51: =M51/$G$4 -> 0.089935827
C52: Balconies | K52: =5645*2 -> 11290 | M52: =K52 -> 11290 | N52: =M52/$G$4 -> 0.058334797
C53: Amenity/ Maintenance | I53: =(364+2372)*2 -> 5472 | L53: 0 | M53: =I53 -> 5472 | N53: =M53/$G$4 -> 0.028273517
C54: Stair Towers | L54: =2054*2 -> 4108 | M54: =L54 -> 4108 | N54: =M54/$G$4 -> 0.021225806
B56: TOTALs | D56: =SUM(D38:D50) -> 176 | F56: =SUM(F38:F50) -> 155262 | G56: =SUM(G38:G50) -> 224 | H56: =SUM(H38:H50) -> 224 | I56: =SUM(I53:I55) -> 5472 | J56: =SUM(J51:J55) -> 17406 | K56: =SUM(K37:K55) -> 11290 | L56: =SUM(L51:L55) -> 4108 | M56: =SUM(M38:M54) -> 193538 | N56: =SUM(N38:N54) -> 1 | O56: Av | P56: =F56/D56 -> 882.17045
B57: BU3 | C57: Stories | D57: QTY.
C58: 5 | D58: 1
A59: lll. | B59: Levels | C59: Units | D59: QTY. | E59: SF | F59: RSF | G59: Bathrooms | H59: Bed rooms | I59: BOH | J59: Corridors | K59: Balconies | L59: Stairs | M59: Gross SF | N59: %
C60: Building type lll
B61: =$C$58 -> 5 | C61: St1 | D61: =10*$D$58 -> 10 | E61: 598 | F61: =D61*E61 -> 5980 | G61: =D61*1 -> 10 | H61: =D61*1 -> 10 | M61: =F61 -> 5980 | N61: =M61/$I$4 -> 0.071029139
B62: =$C$58 -> 5 | C62: A1 - 1 bed/1 bath | D62: =24*$D$58 -> 24 | E62: 756.2 | F62: =D62*E62 -> 18148.8 | G62: =D62*1 -> 24 | H62: =D62*1 -> 24 | M62: =F62 -> 18148.8 | N62: =M62/$I$4 -> 0.2155675
B63: =$C$58 -> 5 | C63: A2 - 1 bed/1 bath | D63: =10*$D$58 -> 10 | E63: 796 | F63: =D63*E63 -> 7960 | G63: =D63*1 -> 10 | H63: =D63*1 -> 10 | M63: =F63 -> 7960 | N63: =M63/$I$4 -> 0.094547148
B64: =$C$58 -> 5 | C64: B1- M - 1 bed/1 bath | D64: =4*$D$58 -> 4 | E64: 839.75 | F64: =D64*E64 -> 3359 | G64: =D64*1 -> 4 | H64: =D64*1 -> 4 | M64: =F64 -> 3359 | N64: =M64/$I$4 -> 0.039897471
B65: =$C$58 -> 5 | C65: B2- M - 1 bed/1 bath | D65: 5 | E65: 844 | F65: =D65*E65 -> 4220 | G65: =D65*1 -> 5 | H65: =D65*1 -> 5 | M65: =F65 -> 4220 | N65: =M65/$I$4 -> 0.050124242 | Q65: balconies
B66: =$C$58 -> 5 | C66: A3(C2 MOD) - 1 bed/1 bath | D66: =0*$D$58 -> 0 | E66: 779 | F66: =D66*E66 -> 0 | G66: =D66*1 -> 0 | H66: =D66*1 -> 0 | M66: =F66 -> 0 | N66: =M66/$I$4 -> 0 | Q66: =K79+K56+K33 -> 28121
B67: =$C$58 -> 5 | C67: B1 | D67: =6*$D$58 -> 6 | E67: 986 | F67: =D67*E67 -> 5916 | G67: =D67*1 -> 6 | H67: =D67*1 -> 6 | M67: =F67 -> 5916 | N67: =M67/$I$4 -> 0.070268961 | Q67: Core
B68: =$C$58 -> 5 | C68: B2 | D68: 9 | E68: 993 | F68: =D68*E68 -> 8937 | G68: =D68*1 -> 9 | H68: =D68*1 -> 9 | M68: =F68 -> 8937 | N68: =M68/$I$4 -> 0.10615174 | Q68: =I33+J33+L33+I56+J56+L56+I79+J79+L79 -> 72095
B69: =$C$58 -> 5 | C69: B2.1 | D69: =6*$D$58 -> 6 | E69: 1014 | F69: =D69*E69 -> 6084 | G69: =D69*1 -> 6 | H69: =D69*1 -> 6 | M69: =F69 -> 6084 | N69: =M69/$I$4 -> 0.072264428
B70: =$C$58 -> 5 | C70: C1 - 2 bed/2 bath | D70: =5*$D$58 -> 5 | E70: 1148 | F70: =D70*E70 -> 5740 | G70: =D70*2 -> 10 | H70: =D70*2 -> 10 | M70: =F70 -> 5740 | N70: =M70/$I$4 -> 0.068178471
B71: =$C$58 -> 5 | C71: C2 - 2 bed/2 bath | D71: =0*$D$58 -> 0 | E71: 1054 | F71: =D71*E71 -> 0 | G71: =D71*2 -> 0 | H71: =D71*2 -> 0 | M71: =I71 -> 0 | N71: =M71/$I$4 -> 0
B72: =$C$58 -> 5 | C72: C3 2 bd /2 bath | D72: =0*$D$58 -> 0 | E72: 1214 | F72: =D72*E72 -> 0 | G72: =D72*2 -> 0 | H72: =D72*2 -> 0 | M72: =I72 -> 0 | N72: =M72/$I$4 -> 0
B73: =$C$58 -> 5 | C73: D1 - 3 bed/2 bath | D73: =0*$D$58 -> 0 | E73: 1321 | F73: =D73*E73 -> 0 | G73: =D73*2 -> 0 | H73: =D73*3 -> 0 | M73: =I73 -> 0 | N73: =M73/$I$4 -> 0
B74: =$C$58 -> 5 | C74: Corridors | J74: 8308 | M74: =J74 -> 8308 | N74: =M74/$I$4 -> 0.098680616
B75: =$C$58 -> 5 | C75: Balconies | D75: =F2 -> 0 | K75: 5233 | M75: =K75 -> 5233 | N75: =M75/$I$4 -> 0.062156435
B76: =$C$58 -> 5 | C76: Amenity/ Maintenance | I76: 2192 | L76: 0 | M76: =I76 -> 2192 | N76: =M76/$I$4 -> 0.026036099
B77: =$C$58 -> 5 | C77: Stair Towers | L77: 2113 | M77: =L77 -> 2113 | N77: =M77/$I$4 -> 0.025097754
B79: TOTALs | D79: =SUM(D61:D70) -> 79 | F79: =SUM(F61:F70) -> 66344.8 | G79: =SUM(G61:G73) -> 84 | H79: =SUM(H61:H73) -> 84 | I79: =SUM(I76:I78) -> 2192 | J79: =SUM(J74:J78) -> 8308 | K79: =SUM(K61:K78) -> 5233 | L79: =SUM(L76:L78) -> 2113 | M79: =SUM(M61:M77) -> 84190.8 | N79: =SUM(N61:N77) -> 1 | O79: Av | P79: =F79/D79 -> 839.80759
B80: BU4 | C80: Stories | D80: QTY.
C81: 0 | D81: 0
A82: lV. | B82: Levels | C82: Units | D82: QTY. | E82: SF | F82: RSF | G82: Bathrooms | H82: Bed rooms | I82: CH | J82: Corridors | K82: Balconies | L82: Maint. | M82: Gross SF | N82: %
C83: Building type 1
B84: =$C$81 -> 0 | C84: St1 | D84: =1*$C$81*$D$81 -> 0 | E84: 1 | F84: =D84*E84 -> 0 | G84: =D84*1 -> 0 | H84: =D84*1 -> 0 | M84: =F84 -> 0 | N84: =M84/$K$4 -> #VALUE!
B85: =$C$81 -> 0 | C85: A1 - 1 bed/1 bath | D85: =1*$C$81*$D$81 -> 0 | E85: 1 | F85: =D85*E85 -> 0 | G85: =D85*1 -> 0 | H85: =D85*1 -> 0 | M85: =F85 -> 0 | N85: =M85/$K$4 -> #VALUE!
B86: =$C$81 -> 0 | C86: A2 - 1 bed/1 bath | D86: =1*$C$81*$D$81 -> 0 | E86: 1 | F86: =D86*E86 -> 0 | G86: =D86*1 -> 0 | H86: =D86*1 -> 0 | M86: =F86 -> 0 | N86: =M86/$K$4 -> #VALUE!
B87: =$C$81 -> 0 | C87: A3 - 1 bed/1 bath | D87: =1*$C$81*$D$81 -> 0 | E87: 1 | F87: =D87*E87 -> 0 | G87: =D87*1 -> 0 | H87: =D87*1 -> 0 | M87: =F87 -> 0 | N87: =M87/$K$4 -> #VALUE!
B88: =$C$81 -> 0 | C88: B1 - 2 bed/2 bath | D88: =1*$C$81*$D$81 -> 0 | E88: 1 | F88: =D88*E88 -> 0 | G88: =D88*2 -> 0 | H88: =D88*2 -> 0 | M88: =F88 -> 0 | N88: =M88/$K$4 -> #VALUE!
B89: =$C$81 -> 0 | C89: B2 - 2 bed/2 bath | D89: =1*$C$81*$D$81 -> 0 | E89: 1 | F89: =D89*E89 -> 0 | G89: =D89*2 -> 0 | H89: =D89*2 -> 0 | M89: =F89 -> 0 | N89: =M89/$K$4 -> #VALUE!
B90: =$C$81 -> 0 | C90: B3 2 bd /2 bath | D90: =1*$C$81*$D$81 -> 0 | E90: 1 | F90: =D90*E90 -> 0 | G90: =D90*2 -> 0 | H90: =D90*2 -> 0 | M90: =F90 -> 0 | N90: =M90/$K$4 -> #VALUE!
B91: =$C$81 -> 0 | C91: B4 2 bd /2 bath | D91: =1*$C$81*$D$81 -> 0 | E91: 1 | F91: =D91*E91 -> 0 | G91: =D91*2 -> 0 | H91: =D91*2 -> 0 | M91: =F91 -> 0 | N91: =M91/$K$4 -> #VALUE!
B92: =$C$81 -> 0 | C92: C1 - 3 bed/2 bath | D92: =1*$C$81*$D$81 -> 0 | E92: 1 | F92: =D92*E92 -> 0 | G92: =D92*2 -> 0 | H92: =D92*3 -> 0 | M92: =F92 -> 0 | N92: =M92/$K$4 -> #VALUE!
B93: =$C$81 -> 0 | C93: C2 3 bd//2 bath | D93: =1*$C$81*$D$81 -> 0 | E93: 1 | F93: =D93*E93 -> 0 | G93: =D93*2 -> 0 | H93: =D93*3 -> 0 | M93: =F93 -> 0 | N93: =M93/$K$4 -> #VALUE!
B94: =$C$81 -> 0 | C94: Corridors | J94: =1*C81*D81 -> 0 | M94: =J94 -> 0 | N94: =M94/$K$4 -> #VALUE!
B95: =$C$81 -> 0 | C95: Balconies | K95: =1*D81*C81 -> 0 | M95: =K95 -> 0 | N95: =M95/$K$4 -> #VALUE!
B96: =$C$81 -> 0 | C96: Amenity/ Maintenance | L96: =1*C81*D81 -> 0 | M96: =L96 -> 0 | N96: =M96/$K$4 -> #VALUE!
B97: =$C$81 -> 0 | C97: Stair Towers | L97: =1*C81*D81 -> 0 | M97: =L97 -> 0 | N97: =M97/$K$4 -> #VALUE!
B99: TOTALs | D99: =SUM(D84:D93) -> 0 | F99: =SUM(F84:F93) -> 0 | G99: =SUM(G84:G93) -> 0 | H99: =SUM(H84:H93) -> 0 | K99: =SUM(K84:K98) -> 0 | L99: =SUM(L96:L98) -> 0 | M99: =SUM(M84:M97) -> 0 | N99: =SUM(N84:N97) -> #VALUE! | O99: Av | P99: =F99/D99 -> #DIV/0!
B100: Parking
A101: l. | B101: Levels | C101: Units | D101: QTY. | E101: SF | F101: Total | G101: Bathrooms | H101: Balconies | I101: Total AC SF | L101: Parking | M101: Gross SF | N101: %
C103: Typ1 Garages | D103: 1 | E103: 3409 | L103: 12 | M103: =D103*E103 -> 3409 | N103: =M103/$N$4 -> 0.0063307383
C104: Typ2 Garages | D104: 2 | E104: 3130 | L104: 24 | M104: =D104*E104 -> 6260 | N104: =M104/$N$4 -> 0.011625234
C105: Surface Parking | N105: =M105/$N$4 -> 0
F106: =D106*E106 -> 0 | I106: =F106 -> 0 | M106: =H106+I106 -> 0 | N106: =M106/$N$4 -> 0
...

Sheet Project Difference
B5: Item | C5: Multi Family | D5: Hilltop | E5: Dofference | F5: Notes
B6: Eartwork Import Fill to the required elevation | C6: 1600000 | D6: 2850000 | E6: =D6-C6 -> 1250000 | F6: Increase of 24,000 CY for import for pads and increase of 45,000 CY to balance the whole site
B7: LiFt station | C7: 275000 | D7: 875000 | E7: =D7-C7 -> 600000 | F7: Usr Muncibility lift Stataion ILO private one
B8: Landscaping (17.5 Acres) | C8: =17.5*75000 -> 1312500 | D8: 2700000 | E8: =D8-C8 -> 1387500 | F8: Usualy the price /Acre is around 65k-75k/ Acre Hilltop is 155k/Acre
B9: Facades decorative items | C9: 150000 | D9: 600000 | E9: =D9-C9 -> 450000 | F9: Adde decorative columns, brakets and Rafter tails
E10: =SUM(E6:E9) -> 3687500

Sheet Bond Calculator
A1: Hedrick Brothers Construction
A3: Performance / Payment Bond | E3: Performance / Payment Bond
A4: General Construction | E4: Design Build
A5: 42888 | E5: 42053
B6: =IF(B13>500000,500000,B13) -> 500000 | C6: 0.0091 | D6: =B6*C6 -> 4550 | F6: 0 | G6: 0.01875 | H6: =SUM(F6*G6) -> 0
B7: =IF(B13<2500000,(B13-B6),IF(B13>B6,2000000,0)) -> 1720594.1 | C7: 0.00725 | D7: =B7*C7 -> 12474.307 | F7: 0 | G7: 0.015 | H7: =SUM(F7*G7) -> 0
B8: =IF(B13<5000000,MAX(0,B13-2500000),IF(B13>2500000,2500000)) -> 0 | C8: 0.0063 | D8: =B8*C8 -> 0 | F8: 0 | G8: 0.01125 | H8: =SUM(F8*G8) -> 0
B9: =IF(B13<7500000,MAX(0,B13-5000000),IF(B13>7500000,2500000,0)) -> 0 | C9: 0.00555 | D9: =B9*C9 -> 0 | F9: 0 | G9: 0.009 | H9: =SUM(F9*G9) -> 0
B10: =IF(B13<7500000,MAX(0,B13-7500000),IF(B13>7500000,(B13-7500000))) -> 0 | C10: 0.0051 | D10: =B10*C10 -> 0 | F10: 0 | G10: 0.00825 | H10: =SUM(F10*G10) -> 0
D11: =B11*C11 -> 0 | F11: 0 | G11: 0.0075 | H11: =SUM(F11*G11) -> 0
A12: Contract Value | B12: ='Cost Summary'!#REF! -> #REF! | C12: Total | D12: =SUM(D6:D11) -> 17024.307 | E12: Contract Value | F12: =SUM(F6+F7+F8+F9+F10+F11) -> 0 | G12: Total | H12: =SUM(H6:H11) -> 0
A13: Cost Summary | B13: 2220594.1 | D13: =SUM(D12/B12) -> #REF! | H13: =SUM(H12/F12) -> #DIV/0!
B14: =B12-B13 -> #REF!

Sheet Allowances
A7: ='AREA CALC''s'!B4 -> Alton Hilltop Gardens | C7: ='AREA CALC''s'!B4 -> Alton Hilltop Gardens
A9: Allowances
A10: =TODAY() -> 46143
A12: NO. | B12: DESCRIPTION | C12: VALUE
A13: 1 | B13: Allowance for Luxer System | C13: 50000
A14: =A13+1 -> 2 | B14: Allowance for Elevator cab finishes | C14: 10000
A15: =A14+1 -> 3 | B15: Allowance for Clubhouse glass railing (MTL-1 and GL-1 as per ID) | C15: 46000
A16: =A15+1 -> 4 | B16: Allowance for Plumbing Fixtures
A17: =A16+1 -> 5 | B17: Allowance Electrical Fixtures | C17: ='32C Landscape and Irrigation'!I52 -> 0
A18: =A17+1 -> 6 | B18: Allowance for Electrical and Water Consumptions (Allowance) | C18: 25000
A19: =A18+1 -> 7 | B19: Allowance for unit entry wall tile | C19: ='09E Flooring'!S61 -> 93268
A20: =A19+1 -> 8 | B20: Allowance for 30 steel bollards | C20: 0
A21: =A20+1 -> 9 | B21: Allowance for clubhouse roller shades | C21: ='12A Window Treatment'!I47 -> 12000
A22: =A21+1 -> 10 | C22: 0
A23: =A22+1 -> 11 | B23: Total | C23: =SUM(C13:C22) -> 236268
B25: *All ALLOWANCES IN BID TABS MUST BE LISTED HERE

Sheet Alternates
A7: ='AREA CALC''s'!B4 -> Alton Hilltop Gardens
A9: Alternates | D9: Markup | E9: 1.125
A10: =TODAY() -> 46143
A12: NO. | B12: DESCRIPTION | C12: VALUE
A13: ALT. #1
A14: ALT. #2 | B14: Add for aluminum abrasive stair nosings | C14: ='05C Misc. Metals'!#REF!*E9 -> #REF!
A15: ALT. #3 | B15: Add Corrosion -Resistance Coating for the HVAC equipment | C15: =-'23A HVAC'!Q103*E9 -> 327375
A16: ALT. #4 | B16: Add for intumescent paint at steel columns ilo drywall wrap | C16: =(-'09B Drywall&Framing'!I57+'07C Fireproofing&Firestopping'!I63)*E9 -> 153664.88
A17: ALT. #5 | B17: Add Vibro replacement | C17: =380000*E9 -> 427500
A18: ALT. #6 | B18: Add for Solarban | C18: ='08C Glass and Glazing'!K140*E9 -> 279000
A19: ALT. #7 | B19: Add for original Caesarstone Calacatta Nuvo 3151 | C19: =E9*340315.37 -> 382854.79
B20: Total | C20: =SUM(C13:C19) -> #REF!

Sheet GCS&GRS HB
A1: Contract Reference | B1: General Condition Ref. | C1: Miami Vertice Riverside
C3: Construction | F3: Activity | H3: Start | I3: Finish | J3: Days | K3: Weeks | L3: Months | M3: % Time | N3: Remarks | Q3: Demo to building pad
F4: Construction | H4: 46049 | I4: 46671 | J4: =SUM(I4-H4) -> 622 | K4: =SUM(J4/7) -> 88.857143 | L4: =SUM(J4/30) -> 20.733333 | Q4: Activity | S4: Start | T4: Finish | U4: Days | V4: Weeks | W4: Months
F5: Close Out | H5: 46675 | I5: 46736 | J5: =SUM(I5-H5) -> 61 | K5: =SUM(J5/7) -> 8.7142857 | L5: =SUM(J5/30) -> 2.0333333 | Q5: Construction | S5: 0 | T5: 0 | U5: =SUM(T5-S5) -> 0 | V5: =SUM(U5/7) -> 0 | W5: =SUM(U5/30) -> 0
F6: General Conditions | H6: General Req. - Field Office | J6: General Req. | L6: Total | Q6: Building
C7: Description | D7: Qty. | E7: U | F7: Unit | G7: Const. | H7: Unit | I7: General | J7: Unit | K7: General | O7: LABOR RATE FY 2025 *Updated 09.26.24 | P7: LABOR RATE (MIAMI/FT. LAUDERDALE) | Q7: Activity | S7: Start | T7: Finish | U7: Days | V7: Weeks | W7: Months | X7: LABOR RATE (MF CENTRAL FLORIDA)
F8: Cost | G8: Cond. | H8: Cost | I8: Req. | J8: Cost | K8: Req. | Q8: Construction | S8: 0 | T8: 0 | U8: =SUM(T8-S8) -> 0 | V8: =SUM(U8/7) -> 0 | W8: =SUM(U8/30) -> 0
C9: Field Labor - Construction | L9: =SUM(L10:L27) -> 3833360.5
C10: Project Executive | D10: =$K$4 -> 88.857143 | E10: wks | F10: =(O10*40)*M10 -> 2809.6181 | G10: =SUM(D10*F10) -> 249654.64 | L10: =SUM(G10+I10+K10) -> 249654.64 | M10: 0.33 | O10: 212.84986 | P10: 253 | X10: 216
C11: Senior Project Manager | D11: =$K$4 -> 88.857143 | E11: wks | F11: =(O11*40)*M11 -> 0 | G11: =SUM(D11*F11) -> 0 | L11: =SUM(G11+I11+K11) -> 0 | M11: 0 | O11: 176.41091 | P11: 195 | X11: 175
C12: Project Manager - Level 3 | D12: =$K$4 -> 88.857143 | E12: wks | F12: =(O12*40)*M12 -> 6520 | G12: =SUM(D12*F12) -> 579348.57 | L12: =SUM(G12+I12+K12) -> 579348.57 | M12: 1 | O12: 163 | P12: 185 | X12: 155
C13: Project Manager - Level 2 | D13: =$K$4 -> 88.857143 | E13: wks | F13: =(O13*40)*M13 -> 0 | G13: =SUM(D13*F13) -> 0 | L13: =SUM(G13+I13+K13) -> 0 | M13: 0 | O13: 148.69542 | P13: 185 | X13: 155
C14: Project Manager - Level 1 | D14: =$K$4 -> 88.857143 | E14: wks | F14: =(O14*40)*M14 -> 2545.1713 | G14: =SUM(D14*F14) -> 226156.65 | L14: =SUM(G14+I14+K14) -> 226156.65 | M14: 0.5 | O14: 127.25857 | P14: 163 | X14: 130
C15: Project Administator | D15: =$K$4 -> 88.857143 | E15: wks | F15: =(O15*40)*M15 -> 3591.2833 | G15: =SUM(D15*F15) -> 319111.18 | L15: =SUM(G15+I15+K15) -> 319111.18 | M15: 1 | O15: 89.782084 | P15: 95 | X15: 65
C16: Project Accountant | D16: =$K$4 -> 88.857143 | E16: wks | F16: =(O16*40)*M16 -> 0 | G16: =SUM(D16*F16) -> 0 | L16: =SUM(G16+I16+K16) -> 0 | M16: 0 | O16: 115.84355 | P16: 81 | X16: 60
C17: Assistant Project Manager | D17: =$K$4 -> 88.857143 | E17: wks | F17: =(O17*40)*M17 -> 4467.6124 | G17: =SUM(D17*F17) -> 396979.28 | L17: =SUM(G17+I17+K17) -> 396979.28 | M17: 1 | O17: 111.69031 | P17: 118 | X17: 95
C18: General Superintendent | D18: =$K$4 -> 88.857143 | E18: wks | F18: =(O18*40)*M18 -> 563.37467 | G18: =SUM(D18*F18) -> 50059.864 | L18: =SUM(G18+I18+K18) -> 50059.864 | M18: 0.08 | O18: 176.05459
C19: Superintendent - Level 3 | D19: =$K$4 -> 88.857143 | E19: wks | F19: =(O19*40)*M19 -> 5335.9555 | G19: =SUM(D19*F19) -> 474137.76 | L19: =SUM(G19+I19+K19) -> 474137.76 | M19: 0.75 | O19: 177.86518 | P19: 183 | X19: 194
C20: Superintendent - Level 2 | D20: =$K$4 -> 88.857143 | E20: wks | F20: =(O20*40)*M20 -> 5971.9803 | G20: =SUM(D20*F20) -> 530653.1 | L20: =SUM(G20+I20+K20) -> 530653.1 | M20: 1 | O20: 149.29951 | P20: 161 | X20: 173
C21: Superintendent - Level 1 | D21: =$K$4 -> 88.857143 | E21: wks | F21: =(O21*40)*M21 -> 4887.7994 | G21: =SUM(D21*F21) -> 434315.89 | L21: =SUM(G21+I21+K21) -> 434315.89 | M21: 1 | O21: 122.19499 | P21: 121 | X21: 155
C22: Assistant Superinterndent | D22: =$K$4 -> 88.857143 | E22: wks | F22: =(O22*40)*M22 -> 2426.5764 | G22: =SUM(D22*F22) -> 215618.64 | L22: =SUM(G22+I22+K22) -> 215618.64 | M22: 0.75 | O22: 80.885879 | P22: 84 | X22: 95
C23: Quality Control Manager | D23: =$K$4 -> 88.857143 | E23: wks | F23: =(O23*40)*M23 -> 1111.6698 | G23: =SUM(D23*F23) -> 98779.801 | L23: =SUM(G23+I23+K23) -> 98779.801 | M23: 0.2 | O23: 138.95872
C24: Foreman | D24: =$K$4 -> 88.857143 | E24: wks | F24: =(O24*40)*M24 -> 0 | G24: =SUM(D24*F24) -> 0 | L24: =SUM(G24+I24+K24) -> 0 | M24: 0 | O24: 56.06341 | P24: 65 | X24: 65
C25: Accounting | D25: =$K$4 -> 88.857143 | E25: wks | F25: =(O25*40)*M25 -> 939.09653 | G25: =SUM(D25*F25) -> 83445.435 | L25: =SUM(G25+I25+K25) -> 83445.435 | M25: 0.15 | O25: 156.51609 | P25: 80 | X25: 90
C26: VDC Manager | D26: =$K$4 -> 88.857143 | E26: wks | F26: =(O26*40)*M26 -> 1109.4485 | G26: =SUM(D26*F26) -> 98582.425 | L26: =SUM(G26+I26+K26) -> 98582.425 | M26: 0.2 | O26: 138.68106 | P26: 101 | X26: 101
C27: Safety Supervisor/Inspector | D27: =K4 -> 88.857143 | E27: wks | F27: =(O27*40)*M27 -> 861.12686 | G27: =SUM(D27*F27) -> 76517.272 | L27: =SUM(G27+I27+K27) -> 76517.272 | M27: 0.2 | O27: 107.64086 | P27: 96 | X27: 96
C28: Field Labor - Close Out | L28: =SUM(L29:L43) -> 312545.3
C29: Project Executive | D29: =$K$5 -> 8.7142857 | E29: wks | F29: =(40*O29)*M29 -> 2128.4986 | G29: =SUM(D29*F29) -> 18548.345 | L29: =SUM(G29+I29+K29) -> 18548.345 | M29: 0.25 | O29: =+O10 -> 212.84986 | P29: =+P10 -> 253 | X29: =+X10 -> 216
C30: Senior Project Manager | D30: =$K$5 -> 8.7142857 | E30: wks | F30: =(40*O30)*M30 -> 7056.4365 | G30: =SUM(D30*F30) -> 61491.804 | L30: =SUM(G30+I30+K30) -> 61491.804 | M30: 1 | O30: =+O11 -> 176.41091 | P30: =+P11 -> 195 | X30: =+X11 -> 175
C31: Project Manager - Level 2 | D31: =$K$5 -> 8.7142857 | E31: wks | F31: =(40*O31)*M31 -> 0 | G31: =SUM(D31*F31) -> 0 | L31: =SUM(G31+I31+K31) -> 0 | M31: 0 | O31: =+O13 -> 148.69542 | P31: =+P13 -> 185 | X31: =+X13 -> 155
C32: Project Manager - Level 1 | D32: =$K$5 -> 8.7142857 | E32: wks | F32: =(40*O32)*M32 -> 0 | G32: =SUM(D32*F32) -> 0 | L32: =SUM(G32+I32+K32) -> 0 | M32: 0 | O32: =+O14 -> 127.25857 | P32: =+P14 -> 163 | X32: =+X14 -> 130
C33: Project Administator | D33: =$K$5 -> 8.7142857 | E33: wks | F33: =(40*O33)*M33 -> 3591.2833 | G33: =SUM(D33*F33) -> 31295.469 | L33: =SUM(G33+I33+K33) -> 31295.469 | M33: 1 | O33: =+O15 -> 89.782084 | P33: =+P15 -> 95 | X33: =+X15 -> 65
C34: Project Coordinator | D34: =$K$5 -> 8.7142857 | E34: wks | F34: =(40*O34)*M34 -> 0 | G34: =SUM(D34*F34) -> 0 | L34: =SUM(G34+I34+K34) -> 0 | M34: 0 | O34: =+O16 -> 115.84355 | P34: =+P16 -> 81 | X34: =+X16 -> 60
C35: Assistant Project Manager | D35: =$K$5 -> 8.7142857 | E35: wks | F35: =(40*O35)*M35 -> 4467.6124 | G35: =SUM(D35*F35) -> 38932.051 | L35: =SUM(G35+I35+K35) -> 38932.051 | M35: 1 | O35: =+O17 -> 111.69031 | P35: =+P17 -> 118 | X35: =+X17 -> 95
C36: Superintendent - Level 3 | D36: =$K$5 -> 8.7142857 | E36: wks | F36: =(40*O36)*M36 -> 5335.9555 | G36: =SUM(D36*F36) -> 46499.041 | L36: =SUM(G36+I36+K36) -> 46499.041 | M36: 0.75 | O36: =+O19 -> 177.86518 | P36: =+P19 -> 183 | X36: =+X19 -> 194
C37: Superintendent - Level 2 | D37: =$K$5 -> 8.7142857 | E37: wks | F37: =(40*O37)*M37 -> 5971.9803 | G37: =SUM(D37*F37) -> 52041.542 | L37: =SUM(G37+I37+K37) -> 52041.542 | M37: 1 | O37: =+O20 -> 149.29951 | P37: =+P20 -> 161 | X37: =+X20 -> 173
C38: Superintendent - Level 1 | D38: =$K$5 -> 8.7142857 | E38: wks | F38: =(40*O38)*M38 -> 4887.7994 | G38: =SUM(D38*F38) -> 42593.681 | L38: =SUM(G38+I38+K38) -> 42593.681 | M38: 1 | O38: =+O21 -> 122.19499 | P38: =+P21 -> 121 | X38: =+X21 -> 155
C39: Assistant Superinterndent | D39: =$K$5 -> 8.7142857 | E39: wks | F39: =(40*O39)*M39 -> 0 | G39: =SUM(D39*F39) -> 0 | L39: =SUM(G39+I39+K39) -> 0 | M39: 0 | O39: =+O22 -> 80.885879 | P39: =+P22 -> 84 | X39: =+X22 -> 95
C40: Foreman | D40: =$K$5 -> 8.7142857 | E40: wks | F40: =(40*O40)*M40 -> 0 | G40: =SUM(D40*F40) -> 0 | L40: =SUM(G40+I40+K40) -> 0 | M40: 0 | O40: =+O24 -> 56.06341 | P40: =+P24 -> 65 | X40: =+X24 -> 65
C41: Accounting | D41: =$K$5 -> 8.7142857 | E41: wks | F41: =(40*O41)*M41 -> 1565.1609 | G41: =SUM(D41*F41) -> 13639.259 | L41: =SUM(G41+I41+K41) -> 13639.259 | M41: 0.25 | O41: =+O25 -> 156.51609 | P41: =+P25 -> 80 | X41: =+X25 -> 90
C42: VDC Manager | D42: =$K$5 -> 8.7142857 | E42: wks | F42: =(40*O42)*M42 -> 0 | G42: =SUM(D42*F42) -> 0 | L42: =SUM(G42+I42+K42) -> 0 | M42: 0 | O42: =+O26 -> 138.68106 | P42: =+P26 -> 101 | X42: =+X26 -> 101
C43: Safety Supervisor/Inspector | D43: =$K$5 -> 8.7142857 | E43: wks | F43: =(40*O43)*M43 -> 861.12686 | G43: =SUM(D43*F43) -> 7504.1055 | L43: =SUM(G43+I43+K43) -> 7504.1055 | M43: 0.2 | O43: =+O27 -> 107.64086 | P43: =+P27 -> 96 | X43: =+X27 -> 96
C44: Field Office - Contractor | L44: =SUM(L45:L65) -> 326217.3
C45: Field Office Set Up / Removal - Double Wide | D45: 1 | E45: ea | H45: 15000 | I45: =SUM(D45*H45) -> 15000 | J45: ` | L45: =SUM(G45+I45+K45) -> 15000
C46: Field Office - Double Wide | D46: =L4 -> 20.733333 | E46: mos | H46: 3500 | I46: =SUM(D46*H46) -> 72566.667 | L46: =SUM(G46+I46+K46) -> 72566.667
C47: Field Office Set Up / Removal - Single Wide | D47: 1 | E47: ea | H47: 15238 | I47: =SUM(D47*H47) -> 15238 | L47: =SUM(G47+I47+K47) -> 15238 | N47: WILLSCOT 4/16/2024 (36x10 mobile office)
C48: Field Office - Single Wide | D48: 18 | E48: mos | H48: 1732 | I48: =SUM(D48*H48) -> 31176 | L48: =SUM(G48+I48+K48) -> 31176 | N48: WILLSCOT 4/16/2024 (36x10 mobile office)
C49: Field Office Set Up / Removal - Connex | E49: ea | H49: 1371 | I49: $ | L49: $ | N49: WILLSCOT 20' COMBO W/10' OFFICE
C50: Field Office - Conex | E50: mos | H50: 573 | I50: $ | L50: $ | N50: WILLSCOT 20' COMBO W/10' OFFICE
C51: Connect Telephone Lines | D51: 0 | E51: ea | H51: 2000 | I51: =SUM(D51*H51) -> 0 | L51: =SUM(G51+I51+K51) -> 0
C52: Telephone | D52: =$L$4 -> 20.733333 | E52: mos | H52: 250 | I52: =SUM(D52*H52) -> 5183.3333 | L52: =SUM(G52+I52+K52) -> 5183.3333
C53: Cellular Telephones | D53: =$L$4 -> 20.733333 | E53: mos | H53: 0 | I53: =SUM(D53*H53) -> 0 | L53: =SUM(G53+I53+K53) -> 0 | N53: In labor rates
C54: Furniture | D54: 0 | E54: ls | H54: 2000 | I54: =SUM(D54*H54) -> 0 | L54: =SUM(G54+I54+K54) -> 0
C55: Office Supplies | D55: =$L$4 -> 20.733333 | E55: mos | H55: 100 | I55: =SUM(D55*H55) -> 2073.3333 | L55: =SUM(G55+I55+K55) -> 2073.3333
C56: Drinking Water | D56: =$L$4 -> 20.733333 | E56: mos | H56: 50 | I56: =SUM(D56*H56) -> 1036.6667 | L56: =SUM(G56+I56+K56) -> 1036.6667
C57: Janitor Supplies/Cleaning | D57: =$L$4 -> 20.733333 | E57: mos | H57: 250 | I57: =SUM(D57*H57) -> 5183.3333 | L57: =SUM(G57+I57+K57) -> 5183.3333
C58: Software Charge | D58: 0.0015 | E58: % | H58: 95773314 | I58: =SUM(D58*H58) -> 143659.97 | L58: =SUM(G58+I58+K58) -> 143659.97 | N58: .25% of GMP Total
C59: Computers | D59: 0 | E59: ls | H59: 0 | I59: =SUM(D59*H59) -> 0 | L59: =SUM(G59+I59+K59) -> 0
C60: Printers | D60: 1 | E60: ls | H60: 4000 | I60: =SUM(D60*H60) -> 4000 | L60: =SUM(G60+I60+K60) -> 4000
C61: Copy Machine | D61: =L4 -> 20.733333 | E61: ls | H61: 1500 | I61: =SUM(D61*H61) -> 31100 | L61: =SUM(G61+I61+K61) -> 31100
C62: Alarm System | D62: =$L$4 -> 20.733333 | E62: mos | H62: 0 | I62: =SUM(D62*H62) -> 0 | L62: =SUM(G62+I62+K62) -> 0
C63: Installation Office Equip. | E63: ls | H63: 250 | I63: =SUM(D63*H63) -> 0 | L63: =SUM(G63+I63+K63) -> 0
C64: Storage Trailers Set Up / Removal | E64: ea | H64: 840 | I64: =SUM(D64*H64) -> 0 | L64: =SUM(G64+I64+K64) -> 0 | N64: willscot 40' trailer
C65: Storage Trailers | E65: mos | H65: 1200 | I65: =SUM(D65*H65) -> 0 | L65: =SUM(G65+I65+K65) -> 0 | N65: Rate - $1200 ea. per month
C66: Field Office - Owner | N66: =SUM(L67:L81) -> 0
C67: Field Office Set Up / Removal | D67: 1 | E67: ls | J67: 0 | K67: =SUM(D67*J67) -> 0 | L67: =SUM(G67+I67+K67) -> 0 | N67: assume not required
C68: Field Office | D68: =L4 -> 20.733333 | E68: mos | J68: 0 | K68: =SUM(D68*J68) -> 0 | L68: =SUM(G68+I68+K68) -> 0 | N68: assume not required
C69: Connect Telephone Lines | D69: 1 | E69: ls | J69: 0 | K69: =SUM(D69*J69) -> 0 | L69: =SUM(G69+I69+K69) -> 0 | N69: assume not required
C70: Telephone | D70: =L4 -> 20.733333 | E70: mos | J70: 0 | K70: =SUM(D70*J70) -> 0 | L70: =SUM(G70+I70+K70) -> 0 | N70: assume not required
C71: Cellular Telephones | D71: =L4+L5 -> 22.766667 | E71: mos | J71: 0 | K71: =SUM(D71*J71) -> 0 | L71: =SUM(G71+I71+K71) -> 0 | N71: assume not required
C72: Furniture | D72: 1 | E72: ls | J72: 0 | K72: =SUM(D72*J72) -> 0 | L72: =SUM(G72+I72+K72) -> 0 | N72: assume not required
C73: Office Supplies | D73: =L4+L5 -> 22.766667 | E73: mos | J73: 0 | K73: =SUM(D73*J73) -> 0 | L73: =SUM(G73+I73+K73) -> 0 | N73: assume not required
C74: Drinking Water | D74: =L4+L5 -> 22.766667 | E74: mos | J74: 0 | K74: =SUM(D74*J74) -> 0 | L74: =SUM(G74+I74+K74) -> 0 | N74: assume not required
C75: Janitor Supplies | D75: =L4 -> 20.733333 | E75: mos | J75: 0 | K75: =SUM(D75*J75) -> 0 | L75: =SUM(G75+I75+K75) -> 0 | N75: assume not required
C76: Computers | D76: 1 | E76: ls | J76: 0 | K76: =SUM(D76*J76) -> 0 | L76: =SUM(G76+I76+K76) -> 0 | N76: assume not required
C77: Printers | D77: 1 | E77: ls | J77: 0 | K77: =SUM(D77*J77) -> 0 | L77: =SUM(G77+I77+K77) -> 0 | N77: assume not required
C78: Copy Machine | D78: =L4+L5 -> 22.766667 | E78: mos | J78: 0 | K78: =SUM(D78*J78) -> 0 | L78: =SUM(G78+I78+K78) -> 0 | N78: assume not required
C79: Fax Machine | D79: 1 | E79: ls | J79: 0 | K79: =SUM(D79*J79) -> 0 | L79: =SUM(G79+I79+K79) -> 0 | N79: assume not required
C80: Alarm System | D80: =L4 -> 20.733333 | E80: mos | J80: 0 | K80: =SUM(D80*J80) -> 0 | L80: =SUM(G80+I80+K80) -> 0 | N80: assume not required
C81: Installation Office Equip. | D81: 1 | E81: ls | J81: 0 | K81: =SUM(D81*J81) -> 0 | L81: =SUM(G81+I81+K81) -> 0 | N81: assume not required
C82: Temporary Utilities | L82: =SUM(L83:L95) -> 0
C83: Temp. Electrical Service | D83: 0 | E83: ls | J83: 0 | K83: =SUM(D83*J83) -> 0 | L83: =SUM(G83+I83+K83) -> 0 | N83: by elect sub
C84: Temp. Electrical - Const. Phase | D84: 0 | E84: mos | J84: 0 | K84: =SUM(D84*J84) -> 0 | L84: =SUM(G84+I84+K84) -> 0 | N84: Allowance
C85: Temp. Electrical - Operate Phase | D85: 0 | E85: mos | J85: 0 | K85: =SUM(D85*J85) -> 0 | L85: =SUM(G85+I85+K85) -> 0 | N85: by owner
C86: Temp. Wiring & Lighting | D86: 0 | E86: sf | J86: 0 | K86: =SUM(D86*J86) -> 0 | L86: =SUM(G86+I86+K86) -> 0 | N86: by elect sub
C87: Temporary Water - Service | D87: 0 | E87: ls | J87: 0 | K87: =SUM(D87*J87) -> 0 | L87: =SUM(G87+I87+K87) -> 0 | N87: by owner
C88: Temporary Water | D88: 0 | E88: mos | J88: 0 | K88: =SUM(D88*J88) -> 0 | L88: =SUM(G88+I88+K88) -> 0
C89: Temporary Toilets | D89: 0 | E89: mos | J89: 2035 | K89: =SUM(D89*J89) -> 0 | L89: =SUM(G89+I89+K89) -> 0 | N89: 04/15/2024 united site services
C90: Temporary Toilet Set Up / Removal | D90: 0 | E90: ea | J90: 93 | K90: =SUM(D90*J90) -> 0 | L90: =SUM(G90+I90+K90) -> 0 | N90: 04/15/2024 united site services
C91: Temporary Washing Station | D91: 0 | E91: mos | J91: =407*1 -> 407 | K91: =SUM(D91*J91) -> 0 | L91: =SUM(G91+I91+K91) -> 0 | N91: 04/15/2024 united site services
C92: Temporary Washing Station Set Up / Removal | D92: 0 | E92: ea | J92: 93 | K92: =SUM(D92*J92) -> 0 | L92: =SUM(G92+I92+K92) -> 0 | N92: 04/15/2024 united site services
C93: Temporary Holding Tanks | D93: 0 | E93: mos | J93: 500 | K93: =SUM(D93*J93) -> 0 | L93: =SUM(G93+I93+K93) -> 0
C94: Temporary Ventilation | D94: 0 | E94: ls | J94: 0 | K94: =SUM(D94*J94) -> 0 | L94: =SUM(G94+I94+K94) -> 0
C95: Temporary Cooling | D95: 0 | E95: mos | J95: 0 | K95: =SUM(D95*J95) -> 0 | L95: =SUM(G95+I95+K95) -> 0
C96: Equipment | L96: =SUM(L97:L99) -> 82933.333
C97: Small Tools | D97: =$L$4 -> 20.733333 | E97: mos | J97: 1500 | K97: =SUM(D97*J97) -> 31100 | L97: =SUM(G97+I97+K97) -> 31100
C98: Equipment Rental | D98: =L4 -> 20.733333 | E98: mos | J98: 2500 | K98: =SUM(D98*J98) -> 51833.333 | L98: =SUM(G98+I98+K98) -> 51833.333
C99: Engineering Instruments | D99: 0 | E99: ls | J99: 1000 | K99: =SUM(D99*J99) -> 0 | L99: =SUM(G99+I99+K99) -> 0
C100: Security | L100: =SUM(L101:L118) -> 24513.333
B101: 15000 | C101: Temporary Fence - 6' Post Driven w/ windscreen | D101: 0 | E101: lf | J101: 8.3 | K101: =J101*D101 -> 0 | L101: =SUM(G101+I101+K101) -> 0 | N101: rent national 4/15/2024
...

Sheet GCs&GRs-1
A1: Contract Reference | B1: General Condition Ref. | C1: Miami Vertice Riverside
C3: Construction | F3: Activity | H3: Start | I3: Finish | J3: Days | K3: Weeks | L3: Months | M3: % Time | N3: Remarks | Q3: Demo to building pad
F4: Construction | H4: 46049 | I4: 46671 | J4: =SUM(I4-H4) -> 622 | K4: =SUM(J4/7) -> 88.857143 | L4: =SUM(J4/30) -> 20.733333 | Q4: Activity | S4: Start | T4: Finish | U4: Days | V4: Weeks | W4: Months
F5: Close Out | H5: 46675 | I5: 46736 | J5: =SUM(I5-H5) -> 61 | K5: =SUM(J5/7) -> 8.7142857 | L5: =SUM(J5/30) -> 2.0333333 | Q5: Construction | S5: 0 | T5: 0 | U5: =SUM(T5-S5) -> 0 | V5: =SUM(U5/7) -> 0 | W5: =SUM(U5/30) -> 0
F6: General Conditions | H6: General Req. - Field Office | J6: General Req. | L6: Total | Q6: Building
C7: Description | D7: Qty. | E7: U | F7: Unit | G7: Const. | H7: Unit | I7: General | J7: Unit | K7: General | O7: LABOR RATE FY 2025 *Updated 09.26.24 | P7: LABOR RATE (MIAMI/FT. LAUDERDALE) | Q7: Activity | S7: Start | T7: Finish | U7: Days | V7: Weeks | W7: Months | X7: LABOR RATE (MF CENTRAL FLORIDA)
F8: Cost | G8: Cond. | H8: Cost | I8: Req. | J8: Cost | K8: Req. | Q8: Construction | S8: 0 | T8: 0 | U8: =SUM(T8-S8) -> 0 | V8: =SUM(U8/7) -> 0 | W8: =SUM(U8/30) -> 0
C9: Field Labor - Construction | L9: =SUM(L10:L26) -> 3567861.4
C10: Project Executive | D10: =$K$4 -> 88.857143 | E10: wks | F10: =(O10*40)*M10 -> 4256.9972 | G10: =SUM(D10*F10) -> 378264.61 | L10: =SUM(G10+I10+K10) -> 378264.61 | M10: 0.5 | O10: 212.84986 | P10: 253 | X10: 216
C11: Senior Project Manager | D11: =$K$4 -> 88.857143 | E11: wks | F11: =(O11*40)*M11 -> 7056.4365 | G11: =SUM(D11*F11) -> 627014.78 | L11: =SUM(G11+I11+K11) -> 627014.78 | M11: 1 | O11: 176.41091 | P11: 195 | X11: 175
C12: Project Manager - Level 2 | D12: =$K$4 -> 88.857143 | E12: wks | F12: =(O12*40)*M12 -> 0 | G12: =SUM(D12*F12) -> 0 | L12: =SUM(G12+I12+K12) -> 0 | M12: 0 | O12: 148.69542 | P12: 185 | X12: 155
C13: Project Manager - Level 1 | D13: =$K$4 -> 88.857143 | E13: wks | F13: =(O13*40)*M13 -> 0 | G13: =SUM(D13*F13) -> 0 | L13: =SUM(G13+I13+K13) -> 0 | M13: 0 | O13: 127.25857 | P13: 163 | X13: 130
C14: Project Administator | D14: =$K$4 -> 88.857143 | E14: wks | F14: =(O14*40)*M14 -> 3591.2833 | G14: =SUM(D14*F14) -> 319111.18 | L14: =SUM(G14+I14+K14) -> 319111.18 | M14: 1 | O14: 89.782084 | P14: 95 | X14: 65
C15: Project Accountant | D15: =$K$4 -> 88.857143 | E15: wks | F15: =(O15*40)*M15 -> 0 | G15: =SUM(D15*F15) -> 0 | L15: =SUM(G15+I15+K15) -> 0 | M15: 0 | O15: 115.84355 | P15: 81 | X15: 60
C16: Assistant Project Manager | D16: =$K$4 -> 88.857143 | E16: wks | F16: =(O16*40)*M16 -> 4467.6124 | G16: =SUM(D16*F16) -> 396979.28 | L16: =SUM(G16+I16+K16) -> 396979.28 | M16: 1 | O16: 111.69031 | P16: 118 | X16: 95
C17: General Superintendent | D17: =$K$4 -> 88.857143 | E17: wks | F17: =(O17*40)*M17 -> 563.37467 | G17: =SUM(D17*F17) -> 50059.864 | L17: =SUM(G17+I17+K17) -> 50059.864 | M17: 0.08 | O17: 176.05459
C18: Superintendent - Level 3 | D18: =$K$4 -> 88.857143 | E18: wks | F18: =(O18*40)*M18 -> 5335.9555 | G18: =SUM(D18*F18) -> 474137.76 | L18: =SUM(G18+I18+K18) -> 474137.76 | M18: 0.75 | O18: 177.86518 | P18: 183 | X18: 194
C19: Superintendent - Level 2 | D19: =$K$4 -> 88.857143 | E19: wks | F19: =(O19*40)*M19 -> 5971.9803 | G19: =SUM(D19*F19) -> 530653.1 | L19: =SUM(G19+I19+K19) -> 530653.1 | M19: 1 | O19: 149.29951 | P19: 161 | X19: 173
C20: Superintendent - Level 1 | D20: =$K$4 -> 88.857143 | E20: wks | F20: =(O20*40)*M20 -> 4887.7994 | G20: =SUM(D20*F20) -> 434315.89 | L20: =SUM(G20+I20+K20) -> 434315.89 | M20: 1 | O20: 122.19499 | P20: 121 | X20: 155
C21: Assistant Superinterndent | D21: =$K$4 -> 88.857143 | E21: wks | F21: =(O21*40)*M21 -> 0 | G21: =SUM(D21*F21) -> 0 | L21: =SUM(G21+I21+K21) -> 0 | M21: 0 | O21: 80.885879 | P21: 84 | X21: 95
C22: Quality Control Manager | D22: =$K$4 -> 88.857143 | E22: wks | F22: =(O22*40)*M22 -> 1111.6698 | G22: =SUM(D22*F22) -> 98779.801 | L22: =SUM(G22+I22+K22) -> 98779.801 | M22: 0.2 | O22: 138.95872
C23: Foreman | D23: =$K$4 -> 88.857143 | E23: wks | F23: =(O23*40)*M23 -> 0 | G23: =SUM(D23*F23) -> 0 | L23: =SUM(G23+I23+K23) -> 0 | M23: 0 | O23: 56.06341 | P23: 65 | X23: 65
C24: Accounting | D24: =$K$4 -> 88.857143 | E24: wks | F24: =(O24*40)*M24 -> 939.09653 | G24: =SUM(D24*F24) -> 83445.435 | L24: =SUM(G24+I24+K24) -> 83445.435 | M24: 0.15 | O24: 156.51609 | P24: 80 | X24: 90
C25: VDC Manager | D25: =$K$4 -> 88.857143 | E25: wks | F25: =(O25*40)*M25 -> 1109.4485 | G25: =SUM(D25*F25) -> 98582.425 | L25: =SUM(G25+I25+K25) -> 98582.425 | M25: 0.2 | O25: 138.68106 | P25: 101 | X25: 101
C26: Safety Supervisor/Inspector | D26: =K4 -> 88.857143 | E26: wks | F26: =(O26*40)*M26 -> 861.12686 | G26: =SUM(D26*F26) -> 76517.272 | L26: =SUM(G26+I26+K26) -> 76517.272 | M26: 0.2 | O26: 107.64086 | P26: 96 | X26: 96
C27: Field Labor - Close Out | L27: =SUM(L28:L42) -> 312545.3
C28: Project Executive | D28: =$K$5 -> 8.7142857 | E28: wks | F28: =(40*O28)*M28 -> 2128.4986 | G28: =SUM(D28*F28) -> 18548.345 | L28: =SUM(G28+I28+K28) -> 18548.345 | M28: 0.25 | O28: =+O10 -> 212.84986 | P28: =+P10 -> 253 | X28: =+X10 -> 216
C29: Senior Project Manager | D29: =$K$5 -> 8.7142857 | E29: wks | F29: =(40*O29)*M29 -> 7056.4365 | G29: =SUM(D29*F29) -> 61491.804 | L29: =SUM(G29+I29+K29) -> 61491.804 | M29: 1 | O29: =+O11 -> 176.41091 | P29: =+P11 -> 195 | X29: =+X11 -> 175
C30: Project Manager - Level 2 | D30: =$K$5 -> 8.7142857 | E30: wks | F30: =(40*O30)*M30 -> 0 | G30: =SUM(D30*F30) -> 0 | L30: =SUM(G30+I30+K30) -> 0 | M30: 0 | O30: =+O12 -> 148.69542 | P30: =+P12 -> 185 | X30: =+X12 -> 155
C31: Project Manager - Level 1 | D31: =$K$5 -> 8.7142857 | E31: wks | F31: =(40*O31)*M31 -> 0 | G31: =SUM(D31*F31) -> 0 | L31: =SUM(G31+I31+K31) -> 0 | M31: 0 | O31: =+O13 -> 127.25857 | P31: =+P13 -> 163 | X31: =+X13 -> 130
C32: Project Administator | D32: =$K$5 -> 8.7142857 | E32: wks | F32: =(40*O32)*M32 -> 3591.2833 | G32: =SUM(D32*F32) -> 31295.469 | L32: =SUM(G32+I32+K32) -> 31295.469 | M32: 1 | O32: =+O14 -> 89.782084 | P32: =+P14 -> 95 | X32: =+X14 -> 65
C33: Project Coordinator | D33: =$K$5 -> 8.7142857 | E33: wks | F33: =(40*O33)*M33 -> 0 | G33: =SUM(D33*F33) -> 0 | L33: =SUM(G33+I33+K33) -> 0 | M33: 0 | O33: =+O15 -> 115.84355 | P33: =+P15 -> 81 | X33: =+X15 -> 60
C34: Assistant Project Manager | D34: =$K$5 -> 8.7142857 | E34: wks | F34: =(40*O34)*M34 -> 4467.6124 | G34: =SUM(D34*F34) -> 38932.051 | L34: =SUM(G34+I34+K34) -> 38932.051 | M34: 1 | O34: =+O16 -> 111.69031 | P34: =+P16 -> 118 | X34: =+X16 -> 95
C35: Superintendent - Level 3 | D35: =$K$5 -> 8.7142857 | E35: wks | F35: =(40*O35)*M35 -> 5335.9555 | G35: =SUM(D35*F35) -> 46499.041 | L35: =SUM(G35+I35+K35) -> 46499.041 | M35: 0.75 | O35: =+O18 -> 177.86518 | P35: =+P18 -> 183 | X35: =+X18 -> 194
C36: Superintendent - Level 2 | D36: =$K$5 -> 8.7142857 | E36: wks | F36: =(40*O36)*M36 -> 5971.9803 | G36: =SUM(D36*F36) -> 52041.542 | L36: =SUM(G36+I36+K36) -> 52041.542 | M36: 1 | O36: =+O19 -> 149.29951 | P36: =+P19 -> 161 | X36: =+X19 -> 173
C37: Superintendent - Level 1 | D37: =$K$5 -> 8.7142857 | E37: wks | F37: =(40*O37)*M37 -> 4887.7994 | G37: =SUM(D37*F37) -> 42593.681 | L37: =SUM(G37+I37+K37) -> 42593.681 | M37: 1 | O37: =+O20 -> 122.19499 | P37: =+P20 -> 121 | X37: =+X20 -> 155
C38: Assistant Superinterndent | D38: =$K$5 -> 8.7142857 | E38: wks | F38: =(40*O38)*M38 -> 0 | G38: =SUM(D38*F38) -> 0 | L38: =SUM(G38+I38+K38) -> 0 | M38: 0 | O38: =+O21 -> 80.885879 | P38: =+P21 -> 84 | X38: =+X21 -> 95
C39: Foreman | D39: =$K$5 -> 8.7142857 | E39: wks | F39: =(40*O39)*M39 -> 0 | G39: =SUM(D39*F39) -> 0 | L39: =SUM(G39+I39+K39) -> 0 | M39: 0 | O39: =+O23 -> 56.06341 | P39: =+P23 -> 65 | X39: =+X23 -> 65
C40: Accounting | D40: =$K$5 -> 8.7142857 | E40: wks | F40: =(40*O40)*M40 -> 1565.1609 | G40: =SUM(D40*F40) -> 13639.259 | L40: =SUM(G40+I40+K40) -> 13639.259 | M40: 0.25 | O40: =+O24 -> 156.51609 | P40: =+P24 -> 80 | X40: =+X24 -> 90
C41: VDC Manager | D41: =$K$5 -> 8.7142857 | E41: wks | F41: =(40*O41)*M41 -> 0 | G41: =SUM(D41*F41) -> 0 | L41: =SUM(G41+I41+K41) -> 0 | M41: 0 | O41: =+O25 -> 138.68106 | P41: =+P25 -> 101 | X41: =+X25 -> 101
C42: Safety Supervisor/Inspector | D42: =$K$5 -> 8.7142857 | E42: wks | F42: =(40*O42)*M42 -> 861.12686 | G42: =SUM(D42*F42) -> 7504.1055 | L42: =SUM(G42+I42+K42) -> 7504.1055 | M42: 0.2 | O42: =+O26 -> 107.64086 | P42: =+P26 -> 96 | X42: =+X26 -> 96
C43: Field Office - Contractor | L43: =SUM(L44:L64) -> 300300.64
C44: Field Office Set Up / Removal - Double Wide | D44: 1 | E44: ea | H44: 15000 | I44: =SUM(D44*H44) -> 15000 | J44: ` | L44: =SUM(G44+I44+K44) -> 15000
C45: Field Office - Double Wide | D45: =L4 -> 20.733333 | E45: mos | H45: 3500 | I45: =SUM(D45*H45) -> 72566.667 | L45: =SUM(G45+I45+K45) -> 72566.667
C46: Field Office Set Up / Removal - Single Wide | D46: 1 | E46: ea | H46: 15238 | I46: =SUM(D46*H46) -> 15238 | L46: =SUM(G46+I46+K46) -> 15238 | N46: WILLSCOT 4/16/2024 (36x10 mobile office)
C47: Field Office - Single Wide | D47: 18 | E47: mos | H47: 1732 | I47: =SUM(D47*H47) -> 31176 | L47: =SUM(G47+I47+K47) -> 31176 | N47: WILLSCOT 4/16/2024 (36x10 mobile office)
C48: Field Office Set Up / Removal - Connex | E48: ea | H48: 1371 | I48: $ | L48: $ | N48: WILLSCOT 20' COMBO W/10' OFFICE
C49: Field Office - Conex | E49: mos | H49: 573 | I49: $ | L49: $ | N49: WILLSCOT 20' COMBO W/10' OFFICE
C50: Connect Telephone Lines | D50: 0 | E50: ea | H50: 2000 | I50: =SUM(D50*H50) -> 0 | L50: =SUM(G50+I50+K50) -> 0
C51: Telephone | D51: =$L$4 -> 20.733333 | E51: mos | H51: 250 | I51: =SUM(D51*H51) -> 5183.3333 | L51: =SUM(G51+I51+K51) -> 5183.3333
C52: Cellular Telephones | D52: =$L$4 -> 20.733333 | E52: mos | H52: 0 | I52: =SUM(D52*H52) -> 0 | L52: =SUM(G52+I52+K52) -> 0 | N52: In labor rates
C53: Furniture | D53: 0 | E53: ls | H53: 2000 | I53: =SUM(D53*H53) -> 0 | L53: =SUM(G53+I53+K53) -> 0
C54: Office Supplies | D54: =$L$4 -> 20.733333 | E54: mos | H54: 100 | I54: =SUM(D54*H54) -> 2073.3333 | L54: =SUM(G54+I54+K54) -> 2073.3333
C55: Drinking Water | D55: =$L$4 -> 20.733333 | E55: mos | H55: 50 | I55: =SUM(D55*H55) -> 1036.6667 | L55: =SUM(G55+I55+K55) -> 1036.6667
C56: Janitor Supplies/Cleaning | D56: =$L$4 -> 20.733333 | E56: mos | H56: 250 | I56: =SUM(D56*H56) -> 5183.3333 | L56: =SUM(G56+I56+K56) -> 5183.3333
C57: Software Charge | D57: 0.0015 | E57: % | H57: 95773314 | I57: =SUM(D57*H57) -> 143659.97 | L57: =SUM(G57+I57+K57) -> 143659.97 | N57: .25% of GMP Total
C58: Computers | D58: 0 | E58: ls | H58: 0 | I58: =SUM(D58*H58) -> 0 | L58: =SUM(G58+I58+K58) -> 0
C59: Printers | D59: 1 | E59: ls | H59: 4000 | I59: =SUM(D59*H59) -> 4000 | L59: =SUM(G59+I59+K59) -> 4000
C60: Copy Machine | D60: =L4 -> 20.733333 | E60: ls | H60: 250 | I60: =SUM(D60*H60) -> 5183.3333 | L60: =SUM(G60+I60+K60) -> 5183.3333
C61: Alarm System | D61: =$L$4 -> 20.733333 | E61: mos | H61: 0 | I61: =SUM(D61*H61) -> 0 | L61: =SUM(G61+I61+K61) -> 0
C62: Installation Office Equip. | E62: ls | H62: 250 | I62: =SUM(D62*H62) -> 0 | L62: =SUM(G62+I62+K62) -> 0
C63: Storage Trailers Set Up / Removal | E63: ea | H63: 840 | I63: =SUM(D63*H63) -> 0 | L63: =SUM(G63+I63+K63) -> 0 | N63: willscot 40' trailer
C64: Storage Trailers | E64: mos | H64: 1200 | I64: =SUM(D64*H64) -> 0 | L64: =SUM(G64+I64+K64) -> 0 | N64: Rate - $1200 ea. per month
C65: Field Office - Owner | N65: =SUM(L66:L80) -> 0
C66: Field Office Set Up / Removal | D66: 1 | E66: ls | J66: 0 | K66: =SUM(D66*J66) -> 0 | L66: =SUM(G66+I66+K66) -> 0 | N66: assume not required
C67: Field Office | D67: =L4 -> 20.733333 | E67: mos | J67: 0 | K67: =SUM(D67*J67) -> 0 | L67: =SUM(G67+I67+K67) -> 0 | N67: assume not required
C68: Connect Telephone Lines | D68: 1 | E68: ls | J68: 0 | K68: =SUM(D68*J68) -> 0 | L68: =SUM(G68+I68+K68) -> 0 | N68: assume not required
C69: Telephone | D69: =L4 -> 20.733333 | E69: mos | J69: 0 | K69: =SUM(D69*J69) -> 0 | L69: =SUM(G69+I69+K69) -> 0 | N69: assume not required
C70: Cellular Telephones | D70: =L4+L5 -> 22.766667 | E70: mos | J70: 0 | K70: =SUM(D70*J70) -> 0 | L70: =SUM(G70+I70+K70) -> 0 | N70: assume not required
C71: Furniture | D71: 1 | E71: ls | J71: 0 | K71: =SUM(D71*J71) -> 0 | L71: =SUM(G71+I71+K71) -> 0 | N71: assume not required
C72: Office Supplies | D72: =L4+L5 -> 22.766667 | E72: mos | J72: 0 | K72: =SUM(D72*J72) -> 0 | L72: =SUM(G72+I72+K72) -> 0 | N72: assume not required
C73: Drinking Water | D73: =L4+L5 -> 22.766667 | E73: mos | J73: 0 | K73: =SUM(D73*J73) -> 0 | L73: =SUM(G73+I73+K73) -> 0 | N73: assume not required
C74: Janitor Supplies | D74: =L4 -> 20.733333 | E74: mos | J74: 0 | K74: =SUM(D74*J74) -> 0 | L74: =SUM(G74+I74+K74) -> 0 | N74: assume not required
C75: Computers | D75: 1 | E75: ls | J75: 0 | K75: =SUM(D75*J75) -> 0 | L75: =SUM(G75+I75+K75) -> 0 | N75: assume not required
C76: Printers | D76: 1 | E76: ls | J76: 0 | K76: =SUM(D76*J76) -> 0 | L76: =SUM(G76+I76+K76) -> 0 | N76: assume not required
C77: Copy Machine | D77: =L4+L5 -> 22.766667 | E77: mos | J77: 0 | K77: =SUM(D77*J77) -> 0 | L77: =SUM(G77+I77+K77) -> 0 | N77: assume not required
C78: Fax Machine | D78: 1 | E78: ls | J78: 0 | K78: =SUM(D78*J78) -> 0 | L78: =SUM(G78+I78+K78) -> 0 | N78: assume not required
C79: Alarm System | D79: =L4 -> 20.733333 | E79: mos | J79: 0 | K79: =SUM(D79*J79) -> 0 | L79: =SUM(G79+I79+K79) -> 0 | N79: assume not required
C80: Installation Office Equip. | D80: 1 | E80: ls | J80: 0 | K80: =SUM(D80*J80) -> 0 | L80: =SUM(G80+I80+K80) -> 0 | N80: assume not required
C81: Temporary Utilities | L81: =SUM(L82:L94) -> 0
C82: Temp. Electrical Service | D82: 0 | E82: ls | J82: 0 | K82: =SUM(D82*J82) -> 0 | L82: =SUM(G82+I82+K82) -> 0 | N82: by elect sub
C83: Temp. Electrical - Const. Phase | D83: 0 | E83: mos | J83: 0 | K83: =SUM(D83*J83) -> 0 | L83: =SUM(G83+I83+K83) -> 0 | N83: Allowance
C84: Temp. Electrical - Operate Phase | D84: 0 | E84: mos | J84: 0 | K84: =SUM(D84*J84) -> 0 | L84: =SUM(G84+I84+K84) -> 0 | N84: by owner
C85: Temp. Wiring & Lighting | D85: 0 | E85: sf | J85: 0 | K85: =SUM(D85*J85) -> 0 | L85: =SUM(G85+I85+K85) -> 0 | N85: by elect sub
C86: Temporary Water - Service | D86: 0 | E86: ls | J86: 0 | K86: =SUM(D86*J86) -> 0 | L86: =SUM(G86+I86+K86) -> 0 | N86: by owner
C87: Temporary Water | D87: 0 | E87: mos | J87: 0 | K87: =SUM(D87*J87) -> 0 | L87: =SUM(G87+I87+K87) -> 0
C88: Temporary Toilets | D88: 0 | E88: mos | J88: 2035 | K88: =SUM(D88*J88) -> 0 | L88: =SUM(G88+I88+K88) -> 0 | N88: 04/15/2024 united site services
C89: Temporary Toilet Set Up / Removal | D89: 0 | E89: ea | J89: 93 | K89: =SUM(D89*J89) -> 0 | L89: =SUM(G89+I89+K89) -> 0 | N89: 04/15/2024 united site services
C90: Temporary Washing Station | D90: 0 | E90: mos | J90: =407*1 -> 407 | K90: =SUM(D90*J90) -> 0 | L90: =SUM(G90+I90+K90) -> 0 | N90: 04/15/2024 united site services
C91: Temporary Washing Station Set Up / Removal | D91: 0 | E91: ea | J91: 93 | K91: =SUM(D91*J91) -> 0 | L91: =SUM(G91+I91+K91) -> 0 | N91: 04/15/2024 united site services
C92: Temporary Holding Tanks | D92: 0 | E92: mos | J92: 500 | K92: =SUM(D92*J92) -> 0 | L92: =SUM(G92+I92+K92) -> 0
C93: Temporary Ventilation | D93: 0 | E93: ls | J93: 0 | K93: =SUM(D93*J93) -> 0 | L93: =SUM(G93+I93+K93) -> 0
C94: Temporary Cooling | D94: 0 | E94: mos | J94: 0 | K94: =SUM(D94*J94) -> 0 | L94: =SUM(G94+I94+K94) -> 0
C95: Equipment | L95: =SUM(L96:L98) -> 82933.333
C96: Small Tools | D96: =$L$4 -> 20.733333 | E96: mos | J96: 1500 | K96: =SUM(D96*J96) -> 31100 | L96: =SUM(G96+I96+K96) -> 31100
C97: Equipment Rental | D97: =L4 -> 20.733333 | E97: mos | J97: 2500 | K97: =SUM(D97*J97) -> 51833.333 | L97: =SUM(G97+I97+K97) -> 51833.333
C98: Engineering Instruments | D98: 0 | E98: ls | J98: 1000 | K98: =SUM(D98*J98) -> 0 | L98: =SUM(G98+I98+K98) -> 0
C99: Security | L99: =SUM(L100:L117) -> 24513.333
B100: 15000 | C100: Temporary Fence - 6' Post Driven w/ windscreen | D100: 0 | E100: lf | J100: 8.3 | K100: =J100*D100 -> 0 | L100: =SUM(G100+I100+K100) -> 0 | N100: rent national 4/15/2024
C101: Temporary Fence - 8' Post Driven w/ windscreen | D101: 0 | E101: lf | J101: 9.8 | K101: =J101*D101 -> 0 | L101: =SUM(G101+I101+K101) -> 0 | N101: rent national 4/15/2024
...

Sheet GCs & GRs
A1: Contract Reference | B1: General Condition Ref. | C1: Alton Hilltop Gardens - Permit Set - General Conditions/Requirements Summary
C3: Construction | F3: Activity | H3: Start | I3: Finish | J3: Days | K3: Weeks | L3: Months | M3: % Time | N3: Remarks
F4: Construction | H4: 46049 | I4: 46674 | J4: =SUM(I4-H4) -> 625 | K4: =SUM(J4/7) -> 89.285714 | L4: =SUM(J4/30) -> 20.833333 | AA4: 46008 | AB4: 46630 | AC4: 622 | AD4: 88.86 | AE4: 20.73
F5: Close Out | H5: 46675 | I5: 46737 | J5: =SUM(I5-H5) -> 62 | K5: =SUM(J5/7) -> 8.8571429 | L5: =SUM(J5/30) -> 2.0666667 | AA5: 46566 | AB5: 46627 | AC5: 61 | AD5: 8.71 | AE5: 2.03
F6: General Conditions | H6: General Req. - Field Office | J6: General Req. | L6: Total
C7: Description | D7: Qty. | E7: U | F7: Unit | G7: Const. | H7: Unit | I7: General | J7: Unit | K7: General | O7: LABOR RATE FY 2025 *Updated 09.26.24
F8: Cost | G8: Cond. | H8: Cost | I8: Req. | J8: Cost | K8: Req.
C9: Field Labor - Construction | L9: 3567861
C10: Project Executive | D10: 88.9 | E10: wks | F10: =(O10*40)*M10 -> 4257 | G10: =SUM(D10*F10) -> 378447.3 | L10: 378265 | M10: 0.5 | O10: ='Labor Rates Calculator'!G10 -> 212.85
C11: Senior Project Manager | D11: 88.9 | E11: wks | F11: =(O11*40)*M11 -> 7056.4 | G11: =SUM(D11*F11) -> 627313.96 | L11: 627015 | M11: 1 | O11: ='Labor Rates Calculator'!G11 -> 176.41
C12: Project Manager - Level 2 | D12: 88.9 | E12: wks | F12: =(O12*40)*M12 -> 0 | G12: =SUM(D12*F12) -> 0 | L12: $ - | M12: 0 | O12: ='Labor Rates Calculator'!G12 -> 148.7
C13: Project Manager - Level 1 | D13: 88.9 | E13: wks | F13: =(O13*40)*M13 -> 0 | G13: =SUM(D13*F13) -> 0 | L13: $ - | M13: 0 | O13: ='Labor Rates Calculator'!G13 -> 127.26
C14: Project Administator | D14: 88.9 | E14: wks | F14: =(O14*40)*M14 -> 3591.2 | G14: =SUM(D14*F14) -> 319257.68 | L14: 319111 | M14: 1 | O14: ='Labor Rates Calculator'!G14 -> 89.78
C15: Project Accountant | D15: 88.9 | E15: wks | F15: =(O15*40)*M15 -> 0 | G15: =SUM(D15*F15) -> 0 | L15: $ - | M15: 0 | O15: ='Labor Rates Calculator'!G15 -> 115.84
C16: Assistant Project Manager | D16: 88.9 | E16: wks | F16: =(O16*40)*M16 -> 4467.6 | G16: =SUM(D16*F16) -> 397169.64 | L16: 396979 | M16: 1 | O16: ='Labor Rates Calculator'!G16 -> 111.69
C17: General Superintendent | D17: 88.9 | E17: wks | F17: =(O17*40)*M17 -> 563.36 | G17: =SUM(D17*F17) -> 50082.704 | L17: 50060 | M17: 0.08 | O17: ='Labor Rates Calculator'!G17 -> 176.05
C18: Superintendent - Level 3 | D18: 88.9 | E18: wks | F18: =(O18*40)*M18 -> 5336.1 | G18: =SUM(D18*F18) -> 474379.29 | L18: 474138 | M18: 0.75 | O18: ='Labor Rates Calculator'!G18 -> 177.87
C19: Superintendent - Level 2 | D19: 88.9 | E19: wks | F19: =(O19*40)*M19 -> 5972 | G19: =SUM(D19*F19) -> 530910.8 | L19: 530653 | M19: 1 | O19: ='Labor Rates Calculator'!G19 -> 149.3
C20: Superintendent - Level 1 | D20: 88.9 | E20: wks | F20: =(O20*40)*M20 -> 4887.6 | G20: =SUM(D20*F20) -> 434507.64 | L20: 434316 | M20: 1 | O20: ='Labor Rates Calculator'!G20 -> 122.19
C21: Assistant Superinterndent | D21: 88.9 | E21: wks | F21: =(O21*40)*M21 -> 0 | G21: =SUM(D21*F21) -> 0 | L21: $ - | M21: 0 | O21: ='Labor Rates Calculator'!G21 -> 80.89
C22: Quality Control Manager | D22: 88.9 | E22: wks | F22: =(O22*40)*M22 -> 1111.68 | G22: =SUM(D22*F22) -> 98828.352 | L22: 98780 | M22: 0.2 | O22: ='Labor Rates Calculator'!G22 -> 138.96
C23: Foreman | D23: 88.9 | E23: wks | F23: =(O23*40)*M23 -> 0 | G23: =SUM(D23*F23) -> 0 | L23: $ - | M23: 0 | O23: ='Labor Rates Calculator'!G23 -> 56.06
C24: Accounting | D24: 88.9 | E24: wks | F24: =(O24*40)*M24 -> 939.12 | G24: =SUM(D24*F24) -> 83487.768 | L24: 83445 | M24: 0.15 | O24: ='Labor Rates Calculator'!G24 -> 156.52
C25: VDC Manager | D25: 88.9 | E25: wks | F25: =(O25*40)*M25 -> 1109.44 | G25: =SUM(D25*F25) -> 98629.216 | L25: 98582 | M25: 0.2 | O25: ='Labor Rates Calculator'!G25 -> 138.68
C26: Safety Supervisor/Inspector | D26: 88.9 | E26: wks | F26: =(O26*40)*M26 -> 861.12 | G26: =SUM(D26*F26) -> 76553.568 | L26: 76517 | M26: 0.2 | O26: ='Labor Rates Calculator'!G26 -> 107.64
C27: Field Labor - Close Out | L27: 312545
C28: Project Executive | D28: 8.7 | E28: wks | F28: 1109 | G28: 18548 | L28: 18548 | M28: 0.25 | O28: 212.85
C29: Senior Project Manager | D29: 8.7 | E29: wks | F29: 7056 | G29: 61492 | L29: 61492 | M29: 1 | O29: 176.41
C30: Project Manager - Level 2 | D30: 8.7 | E30: wks | F30: $ - | G30: $ - | L30: $ - | M30: 0 | O30: 148.7
C31: Project Manager - Level 1 | D31: 8.7 | E31: wks | F31: $ - | G31: $ - | L31: $ - | M31: 0 | O31: 127.26
C32: Project Administator | D32: 8.7 | E32: wks | F32: 3591 | G32: 31295 | L32: 31295 | M32: 1 | O32: 89.78
C33: Project Coordinator | D33: 8.7 | E33: wks | F33: $ - | G33: $ - | L33: $ - | M33: 0 | O33: 115.84
C34: Assistant Project Manager | D34: 8.7 | E34: wks | F34: 4468 | G34: 38932 | L34: 38932 | M34: 1 | O34: 111.69
C35: Superintendent - Level 3 | D35: 8.7 | E35: wks | F35: 5336 | G35: 46499 | L35: 46499 | M35: 0.75 | O35: 177.87
C36: Superintendent - Level 2 | D36: 8.7 | E36: wks | F36: 5972 | G36: 52042 | L36: 52042 | M36: 1 | O36: 149.3
C37: Superintendent - Level 1 | D37: 8.7 | E37: wks | F37: 4888 | G37: 42594 | L37: 42594 | M37: 1 | O37: 122.19
C38: Assistant Superinterndent | D38: 8.7 | E38: wks | F38: $ - | G38: $ - | L38: $ - | M38: 0 | O38: 80.89
C39: Foreman | D39: 8.7 | E39: wks | F39: $ - | G39: $ - | L39: $ - | M39: 0 | O39: 56.06
C40: Accounting | D40: 8.7 | E40: wks | F40: 1565 | G40: 13639 | L40: 13639 | M40: 0.25 | O40: 156.52
C41: VDC Manager | D41: 8.7 | E41: wks | F41: $ - | G41: $ - | L41: $ - | M41: 0 | O41: 138.68
C42: Safety Supervisor/Inspector | D42: 8.7 | E42: wks | F42: 861 | G42: 7504 | L42: 7504 | M42: 0.2 | O42: 107.64
C43: Field Office - Contractor | L43: 326217
C44: Field Office Set Up / Removal - Double Wide | D44: 1 | E44: ea | H44: 15000 | I44: 15000 | J44: ` | L44: 15000
C45: Field Office - Double Wide | D45: 20.7 | E45: mos | H45: 3500 | I45: 72567 | L45: 72567
C46: Field Office Set Up / Removal - Single Wide | D46: 0 | E46: ea | H46: 15958 | I46: $ - | L46: $ - | N46: WILLSCOT 4/16/2024 (36x10 mobile office)
C47: Field Office - Single Wide | D47: 0 | E47: mos | H47: 1732 | I47: $ - | L47: $ - | N47: WILLSCOT 4/16/2024 (36x10 mobile office)
C48: Field Office Set Up / Removal - Connex | E48: ea | H48: 1371 | I48: $ | L48: $ | N48: WILLSCOT 20' COMBO W/10' OFFICE
C49: Field Office - Conex | E49: mos | H49: 573 | I49: $ | L49: $ | N49: WILLSCOT 20' COMBO W/10' OFFICE
C50: Connect Telephone Lines | D50: 0 | E50: ea | H50: 2000 | I50: $ - | L50: $ -
C51: Telephone | D51: 20.7 | E51: mos | H51: 250 | I51: 5183 | L51: 5183
C52: Cellular Telephones | D52: 20.7 | E52: mos | H52: $ - | I52: $ - | L52: $ - | N52: In labor rates
C53: Furniture | D53: 0 | E53: ls | H53: 2000 | I53: $ - | L53: $ -
C54: Office Supplies | D54: 20.7 | E54: mos | H54: 100 | I54: 2073 | L54: 2073
C55: Drinking Water | D55: 20.7 | E55: mos | H55: 50 | I55: 1037 | L55: 1037
C56: Janitor Supplies/Cleaning | D56: 20.7 | E56: mos | H56: 250 | I56: 5183 | L56: 5183
C57: Software Charge | D57: 0.0015 | E57: % | H57: 95773314 | I57: 143660 | L57: 143660 | N57: .25% of GMP Total
C58: Computers | D58: 0 | E58: ls | H58: $ - | I58: $ - | L58: $ -
C59: Printers | D59: 1 | E59: ls | H59: 4000 | I59: 4000 | L59: 4000
C60: Copy Machine | D60: 2 | E60: ls | H60: 2500 | I60: =D60*H60 -> 5000 | L60: =I60 -> 5000
C61: Alarm System | D61: 20.7 | E61: mos | H61: $ - | I61: $ - | L61: $ -
C62: Installation Office Equip. | E62: ls | H62: 250 | I62: $ - | L62: $ -
C63: Storage Trailers Set Up / Removal | D63: 2 | E63: ea | H63: 840 | I63: 1680 | L63: 1680 | N63: willscot 40' trailer
C64: Storage Trailers | D64: 20 | E64: mos | H64: 1200 | I64: 24000 | L64: 24000 | N64: Rate - $1200 ea. per month
C65: Temporary Utilities | L65: 95681
C66: Temp. Electrical Service | D66: 0 | E66: ls | J66: $ - | K66: $ - | L66: $ - | N66: by elect sub
C67: Temp. Electrical - Const. Phase | D67: 20.7 | E67: mos | J67: $ - | K67: $ - | L67: $ - | N67: Allowance
C68: Temp. Electrical - Operate Phase | D68: 20.7 | E68: mos | J68: $ - | K68: $ - | L68: $ - | N68: by owner
C69: Temp. Wiring & Lighting | D69: 0 | E69: sf | J69: $ - | K69: $ - | L69: $ - | N69: by elect sub
C70: Temporary Water - Service | D70: 0 | E70: ls | J70: $ - | K70: $ - | L70: $ - | N70: by owner
C71: Temporary Water | D71: 20.7 | E71: mos | J71: $ - | K71: $ - | L71: $ -
C72: Temporary Toilets | D72: 20.7 | E72: mos | J72: 4070 | K72: 84385 | L72: 84385 | N72: 04/15/2024 united site services
C73: Temporary Toilet Set Up / Removal | D73: 10 | E73: ea | J73: 93 | K73: 930 | L73: 930 | N73: 04/15/2024 united site services
C74: Temporary Washing Station | D74: 0 | E74: mos | J74: 407 | K74: $ - | L74: $ - | N74: 04/15/2024 united site services
C75: Temporary Washing Station Set Up / Removal | D75: 0 | E75: ea | J75: 93 | K75: $ - | L75: $ - | N75: 04/15/2024 united site services
C76: Temporary Holding Tanks | D76: 20.7 | E76: mos | J76: 500 | K76: 10367 | L76: 10367
C77: Temporary Ventilation | D77: 0 | E77: ls | J77: $ - | K77: $ - | L77: $ -
C78: Temporary Cooling | D78: 20.7 | E78: mos | J78: $ - | K78: $ - | L78: $ -
C79: Equipment | L79: 82933
C80: Small Tools | D80: 20.7 | E80: mos | J80: 1500 | K80: 31100 | L80: 31100
C81: Equipment Rental | D81: 20.7 | E81: mos | J81: 2500 | K81: 51833 | L81: 51833
C82: Engineering Instruments | D82: 0 | E82: ls | J82: 1000 | K82: $ - | L82: $ -
C83: Security | L83: 24513
B84: 15000 | C84: Temporary Fence - 6' Post Driven w/ windscreen | D84: 0 | E84: lf | J84: 8 | K84: $ - | L84: $ - | N84: rent national 4/15/2024
C85: Temporary Fence - 8' Post Driven w/ windscreen | D85: 0 | E85: lf | J85: 10 | K85: $ - | L85: $ - | N85: rent national 4/15/2024
C86: Temporary Fence - 6' Panels w/ windscreen | D86: 0 | E86: lf | J86: 6 | K86: $ - | L86: $ - | N86: rent national 4/15/2024
C87: Temporary Fence - 8' Panels w/ windscreen | D87: 0 | E87: lf | J87: 7 | K87: $ - | L87: $ - | N87: rent national 4/15/2024
C88: Temporary Fence - Gates 8'x24' | D88: 0 | E88: ea | J88: 800 | K88: $ - | L88: $ - | N88: rent national 4/15/2024
B89: 15000 | C89: Temporary Fence Maintain | D89: 20.7 | E89: mos | J89: 150 | K89: 3110 | L89: 3110
C90: Security Service | D90: 88.9 | E90: wks | J90: $ - | K90: $ - | L90: $ -
C91: Additional Safety Material/Modifications | D91: 1 | E91: ls | J91: 10000 | K91: 10000 | L91: 10000
B92: 15000 | C92: Protection Floor & Roof Openings | D92: 0 | E92: ls | J92: 2500 | K92: $ - | L92: $ -
C93: Protection Existing Floors & Walls | D93: 0 | E93: ls | J93: 1500 | K93: $ - | L93: $ -
C94: Protection Service Elevator | D94: 0 | E94: ls | J94: 500 | K94: $ - | L94: $ -
B95: 15000 | C95: Temporary Enclosures | D95: 0 | E95: ls | J95: 5000 | K95: $ - | L95: $ -
C96: Temporary Ladders | D96: 0 | E96: ls | J96: $ - | K96: $ - | L96: $ -
B97: 15000 | C97: Building Barricades | D97: 0 | E97: ls | J97: 5000 | K97: $ - | L97: $ -
B98: 15000 | C98: Site Barricades | D98: 0 | E98: ls | J98: 5000 | K98: $ - | L98: $ -
C99: Fire Protection | D99: 20.7 | E99: mos | J99: 500 | K99: 10367 | L99: 10367
C100: First Aid | D100: 20.7 | E100: mos | J100: 50 | K100: 1037 | L100: 1037
C101: Drug Testing | D101: 0 | E101: ea | J101: $ - | K101: $ - | L101: $ -
...

Sheet Labor Rates Calculator
A5: Hedrick Brothers Construction Co., Inc.
A6: Salaries and Burden Calculations
A7: As of 8/22/24
C8: MARK-UP | F8: 0.35
E9: Burdened Rate | F9: Mark-up | G9: Total
C10: Proj Exec | E10: 157.67 | F10: 55.18 | G10: 212.85
C11: Sr PM | E11: 130.67 | F11: 45.74 | G11: 176.41
C12: PM 2 | E12: 110.14 | F12: 38.55 | G12: 148.7
C13: PM 1 | E13: 94.27 | F13: 32.99 | G13: 127.26
C14: Proj Admin | E14: 66.51 | F14: 23.28 | G14: 89.78
C15: Proj Acct | E15: 85.81 | F15: 30.03 | G15: 115.84
C16: Asst PM | E16: 82.73 | F16: 28.96 | G16: 111.69
C17: Gen Supt | E17: 130.41 | F17: 45.64 | G17: 176.05
C18: Supt 3 | E18: 131.75 | F18: 46.11 | G18: 177.87
C19: Supt 2 | E19: 110.59 | F19: 38.71 | G19: 149.3
C20: Supt 1 | E20: 90.51 | F20: 31.68 | G20: 122.19
C21: Asst Supt | E21: 59.92 | F21: 20.97 | G21: 80.89
... C31: Leadman | E31: 46.61 | F31: 16.31 | G31: 62.92
C32: Supt MEP | E32: $ - | F32: $ - | G32: $ -
C33: PM 3 | E33: 120.34 | F33: 42.12 | G33: 162.46
C34: Cons Mgr | E34: 135.46 | F34: 47.41 | G34: 182.87
C35: Proj Coor | E35: $ - | F35: $ - | G35: $ -
C36: Mktg | E36: 85.41 | F36: 29.89 | G36: 115.31
C37: Bus Dev | E37: 121.55 | F37: 42.54 | G37: 164.1
C38: Chief, 3 & 2 | E38: 140.92 | F38: 49.32 | G38: 190.24
C39: Coord & Jrs | E39: 52.72 | F39: 18.45 | G39: 71.17
C40: Exec Asst | E40: 69.67 | F40: 24.38 | G40: 94.05
C42: Total | E42: =SUM(E10:E41) -> 2612.41 | F42: =SUM(F10:F41) -> 914.31 | G42: =SUM(G10:G41) -> 3526.76
G43: =E42/G42 -> 0.74073938

Sheet Cost Summary
A1: 26 | B1: COST ESTIMATE (ROM)
R3: Rev. 3 dated 03/19/26
B6: ='AREA CALC''s'!B4 -> Alton Hilltop Gardens | F6: Gross (sf) | G6: ='AREA CALC''s'!L4 -> 514164.8 | Q6: Gross (sf) | R6: ='AREA CALC''s'!N4 -> 538483.8 | S6: Site (acres) | T6: ='AREA CALC''s'!N7 -> 17.64
B7: GMP Estimate | F7: RSF | G7: ='AREA CALC''s'!N5 -> 413948.8 | Q7: RSF | R7: ='AREA CALC''s'!N5 -> 413948.8 | S7: CH | T7: ='AREA CALC''s'!N9 -> 14650
F8: Units | G8: ='AREA CALC''s'!N6 -> 432 | Q8: Units | R8: ='AREA CALC''s'!N6 -> 432 | S8: Duration | T8: 20
F10: Total Apartment Buildings | K10: Site | M10: Clubhouse | O10: Garage | Z10: B | AA10: (A-B)
B11: CSI | C11: CSI DESCRIPTION | F11: TOTAL | G11: $ /GSF | H11: $ /RSF | I11: $ /UNIT | K11: TOTAL | M11: TOTAL | O11: TOTAL | Q11: GRAND TOTAL | R11: $ /GSF | S11: $ /RSF | T11: $ /UNIT | U11: % | V11: No. of Proposals | W11: BO Price | X11: Savings | Y11: SUB | Z11: GMP R2 | AA11: Variance | AB11: Notes | AC11: No. of Proposals
B13: 00A | C13: Electrical and Water Consumptions (Allowance) | F13: 21000 | G13: =F13/$G$6 -> 0.040842936 | H13: =F13/$G$7 -> 0.050730912 | I13: =F13/$G$8 -> 48.611111 | M13: 4000 | Q13: =F13+K13+M13+O13 -> 25000 | R13: =Q13/$R$6 -> 0.046426652 | S13: =Q13/$G$7 -> 0.060393942 | T13: =Q13/$G$8 -> 57.87037 | U13: =Q13/$Q$89 -> 0.0002394545 | W13: =Q13 -> 25000 | X13: =W13-Q13 -> 0 | Z13: 25000 | AA13: =Q13-Z13 -> 0
B14: 01A | C14: Surveying | F14: ='01A Surveying'!C84 -> 66000 | G14: =F14/$G$6 -> 0.12836351 | H14: =F14/$G$7 -> 0.15944001 | I14: =F14/$G$8 -> 152.77778 | K14: ='01A Surveying'!F84 -> 30000 | M14: ='01A Surveying'!D84 -> 8000 | O14: ='01A Surveying'!E84 -> 6000 | Q14: =F14+K14+M14+O14 -> 110000 | R14: =Q14/$R$6 -> 0.20427727 | S14: =Q14/$G$7 -> 0.26573335 | T14: =Q14/$G$8 -> 254.62963 | U14: =Q14/$Q$89 -> 0.0010535998 | V14: 4 | W14: =Q14 -> 110000 | X14: =W14-Q14 -> 0 | Z14: 110000 | AA14: =Q14-Z14 -> 0 | AC14: 4
B15: 01B | C15: Materials Testing | F15: Excluded | Q15: Excluded | Z15: Excluded
B16: 01C | C16: Site Maintenance / Dumpster / Cleaning | F16: ='01C Final Cleaning'!B106 -> 898690 | G16: =F16/$G$6 -> 1.7478637 | H16: =F16/$G$7 -> 2.1710173 | I16: =F16/$G$8 -> 2080.3009 | Q16: =F16+K16+M16+O16 -> 898690 | R16: =Q16/$G$6 -> 1.7478637 | S16: =Q16/$G$7 -> 2.1710173 | T16: =Q16/$G$8 -> 2080.3009 | U16: =Q16/$Q$89 -> 0.0086078145 | W16: =Q16 -> 898690 | X16: =W16-Q16 -> 0 | Z16: 898690 | AA16: =Q16-Z16 -> 0
B17: 02A | C17: Demolition | F17: Excluded | Q17: Excluded | Z17: Excluded
B18: 03A | C18: Concrete (Tunnel Form) | F18: ='03A Concrete'!B175 -> 18970000 | G18: =F18/$G$6 -> 36.894785 | H18: =F18/$G$7 -> 45.826924 | I18: =F18/$G$8 -> 43912.037 | K18: ='03A Concrete'!F175 -> 120000 | M18: ='03A Concrete'!D175 -> 1040000 | O18: ='03A Concrete'!E175 -> 340000 | Q18: =F18+K18+M18+O18 -> 20470000 | R18: =Q18/$G$6 -> 39.812138 | S18: =Q18/$G$7 -> 49.45056 | T18: =Q18/$G$8 -> 47384.259 | U18: =Q18/$Q$89 -> 0.19606534 | V18: 3 | W18: 19780000 | X18: =W18-Q18 -> -690000 | Z18: 20470000 | AA18: =Q18-Z18 -> 0 | AC18: 3
B19: 03C | C19: Architectural Precast | F19: ='03A Concrete'!C176 -> 0 | G19: =F19/$G$6 -> 0 | H19: =F19/$G$7 -> 0 | I19: =F19/$G$8 -> 0 | K19: ='03C Architectural Precast'!B88 -> 368772 | M19: ='03A Concrete'!D176 -> 0 | O19: ='03A Concrete'!E176 -> 0 | Q19: =F19+K19+M19+O19 -> 368772 | R19: =Q19/$G$6 -> 0.71722529 | S19: =Q19/$G$7 -> 0.8908638 | T19: =Q19/$G$8 -> 853.63889 | U19: =Q19/$Q$89 -> 0.0035321645 | V19: 3 | Z19: 368772 | AA19: =Q19-Z19 -> 0 | AC19: 3
B20: 04A | C20: Masonry | F20: in Concrete | G20: in Concrete | H20: in Concrete | I20: in Concrete | K20: in Concrete | M20: in Concrete | O20: in Concrete | Q20: in Concrete | R20: in Concrete | S20: in Concrete | T20: in Concrete | Z20: in Concrete
B21: 04B | C21: Stone Veneer | F21: ='04B Stone Veneer'!B113 -> 101719 | K21: ='04B Stone Veneer'!E113 -> 9350 | M21: ='04B Stone Veneer'!C113 -> 13513 | Q21: =F21+K21+M21+O21 -> 124582 | R21: =Q21/$G$6 -> 0.24229975 | S21: =Q21/$G$7 -> 0.30095993 | T21: =Q21/$G$8 -> 288.38426 | U21: =Q21/$Q$89 -> 0.0011932688 | V21: 4 | Z21: 67260 | AA21: =Q21-Z21 -> 57322 | AB21: RFI CD #23, added precast trims | AC21: 4
B22: 05A | C22: Structural Steel | F22: in Concrete | G22: in Concrete | H22: in Concrete | I22: in Concrete | K22: in Concrete | M22: in Concrete | O22: in Concrete | Q22: in Concrete | R22: in Concrete | S22: in Concrete | T22: in Concrete | Z22: in Concrete
B23: 05C | C23: Misc. Metals | F23: ='05C Misc. Metals'!B113 -> 879361.55 | G23: =F23/$G$6 -> 1.7102718 | H23: =F23/$G$7 -> 2.1243244 | I23: =F23/$G$8 -> 2035.5591 | Q23: =F23+K23+M23+O23 -> 879361.55 | R23: =Q23/$G$6 -> 1.7102718 | S23: =Q23/$G$7 -> 2.1243244 | T23: =Q23/$G$8 -> 2035.5591 | U23: =Q23/$Q$89 -> 0.0084226831 | V23: 5 | Z23: 879361.55 | AA23: =Q23-Z23 -> 0 | AC23: 5
B24: 05E | C24: Glass Railings | G24: =F24/$G$6 -> 0 | H24: =F24/$G$7 -> 0 | I24: =F24/$G$8 -> 0 | M24: ='05E Glass Railings'!B91 -> 46000 | Q24: =F24+K24+M24+O24 -> 46000 | R24: =Q24/$G$6 -> 0.089465479 | S24: =Q24/$G$7 -> 0.11112485 | T24: =Q24/$G$8 -> 106.48148 | U24: =Q24/$Q$89 -> 0.00044059627 | V24: 4 | Z24: 46000 | AA24: =Q24-Z24 -> 0 | AC24: 4
B25: 05F | C25: Brackets & Rafter Tails | F25: ='05F Brackets & Rafter Tails'!B148 -> 493453 | Q25: =F25+K25+M25+O25 -> 493453 | R25: =Q25/$G$6 -> 0.95971758 | S25: =Q25/$G$7 -> 1.1920629 | T25: =Q25/$G$8 -> 1142.2523 | U25: =Q25/$Q$89 -> 0.0047263816 | V25: 4 | Z25: 493453 | AA25: =Q25-Z25 -> 0 | AC25: 4
B26: 05G | C26: Balcony Columns | F26: ='05G Balcony Columns'!B81 -> 0 | G26: =F26/$G$6 -> 0 | H26: =F26/$G$7 -> 0 | I26: =F26/$G$8 -> 0 | M26: 0 | Q26: =F26+K26+M26+O26 -> 0 | R26: =Q26/$G$6 -> 0 | S26: =Q26/$G$7 -> 0 | T26: =Q26/$G$8 -> 0 | U26: =Q26/$Q$89 -> 0 | Z26: 353486 | AA26: =Q26-Z26 -> -353486 | AB26: Moved to Drywall & Stucco
B27: 06A | C27: Rough Carpentry | F27: ='06A Rough Carpentry'!B115 -> 587134.4 | G27: =F27/$G$6 -> 1.1419187 | H27: =F27/$G$7 -> 1.4183744 | I27: =F27/$G$8 -> 1359.1074 | Q27: =F27+K27+M27+O27 -> 587134.4 | R27: =Q27/$G$6 -> 1.1419187 | S27: =Q27/$G$7 -> 1.4183744 | T27: =Q27/$G$8 -> 1359.1074 | U27: =Q27/$Q$89 -> 0.0056236789 | Z27: 462134.4 | AA27: =Q27-Z27 -> 125000 | AB27: Added grout for HMF
B28: 06C | C28: Wood Trusses | F28: ='06C Wood Trusses'!B107 -> 252757.98 | G28: =F28/$G$6 -> 0.49158943 | H28: =F28/$G$7 -> 0.61060204 | I28: =F28/$G$8 -> 585.08792 | Q28: =F28+K28+M28+O28 -> 252757.98 | R28: =Q28/$G$6 -> 0.49158943 | S28: =Q28/$G$7 -> 0.61060204 | T28: =Q28/$G$8 -> 585.08792 | U28: =Q28/$Q$89 -> 0.0024209614 | V28: 5 | Z28: 287972.58 | AA28: =Q28-Z28 -> -35214.6 | AB28: more competitive proposal | AC28: 5
B29: 06D | C29: Interior Finish Cabinetry | F29: ='06D Interior Finish Carpentry'!B98 -> 243815 | G29: =F29/$G$6 -> 0.47419621 | H29: =F29/$G$7 -> 0.58899796 | I29: =F29/$G$8 -> 564.38657 | Q29: =F29+K29+M29+O29 -> 243815 | R29: =Q29/$G$6 -> 0.47419621 | S29: =Q29/$G$7 -> 0.58899796 | T29: =Q29/$G$8 -> 564.38657 | U29: =Q29/$Q$89 -> 0.0023353039 | V29: 3 | Z29: 243815 | AA29: =Q29-Z29 -> 0 | AC29: 3
B30: 06F | C30: Millwork | F30: ='06F Millwork'!C190 -> 0 | G30: =F30/$G$6 -> 0 | H30: =F30/$G$7 -> 0 | I30: =F30/$G$8 -> 0 | M30: ='06F Millwork'!D190 -> 697916.55 | Q30: =F30+K30+M30+O30 -> 697916.55 | R30: =Q30/$G$6 -> 1.3573791 | S30: =Q30/$G$7 -> 1.6859973 | T30: =Q30/$G$8 -> 1615.5476 | U30: =Q30/$Q$89 -> 0.0066847702 | V30: 4 | Z30: 695928.88 | AA30: =Q30-Z30 -> 1987.6673 | AC30: 4
B31: 07B | C31: Building Insulation | F31: ='07B Building Insulation'!B123 -> 325845 | G31: =F31/$G$6 -> 0.6337365 | H31: =F31/$G$7 -> 0.78716257 | I31: =F31/$G$8 -> 754.27083 | M31: ='07B Building Insulation'!D123 -> 0 | Q31: =F31+K31+M31+O31 -> 325845 | R31: =Q31/$G$6 -> 0.6337365 | S31: =Q31/$G$7 -> 0.78716257 | T31: =Q31/$G$8 -> 754.27083 | U31: =Q31/$Q$89 -> 0.003121002 | V31: 6 | Z31: 325845 | AA31: =Q31-Z31 -> 0 | AC31: 6
B32: 07C | C32: Fireproofing & Firestopping | F32: ='07C Fireproofing&Firestopping'!B86 -> 227000 | G32: =F32/$G$6 -> 0.44149269 | H32: =F32/$G$7 -> 0.548377 | I32: =F32/$G$8 -> 525.46296 | Q32: =F32+K32+M32+O32 -> 227000 | R32: =Q32/$G$6 -> 0.44149269 | S32: =Q32/$G$7 -> 0.548377 | T32: =Q32/$G$8 -> 525.46296 | U32: =Q32/$Q$89 -> 0.0021742468 | V32: 4 | Z32: 227000 | AA32: =Q32-Z32 -> 0 | AC32: 4
B33: 07D | C33: Roofing | F33: ='07D Roofing'!B116 -> 2020840 | G33: =F33/$G$6 -> 3.9303352 | H33: =F33/$G$7 -> 4.8818598 | I33: =F33/$G$8 -> 4677.8704 | K33: ='07D Roofing'!E116 -> 0 | M33: ='07D Roofing'!C116 -> 96760 | O33: ='07D Roofing'!D116 -> 114310 | Q33: =F33+K33+M33+O33 -> 2231910 | R33: =Q33/$G$6 -> 4.3408456 | S33: =Q33/$G$7 -> 5.3917538 | T33: =Q33/$G$8 -> 5166.4583 | U33: =Q33/$Q$89 -> 0.021377635 | V33: 7 | Z33: 2231910 | AA33: =Q33-Z33 -> 0 | AC33: 7
B34: 07E | C34: Caulking & Waterproofing | F34: ='07E Caulking & Waterproofing'!B131 -> 893620.86 | G34: =F34/$G$6 -> 1.7380047 | H34: =F34/$G$7 -> 2.1587715 | I34: =F34/$G$8 -> 2068.5668 | Q34: =F34+K34+M34+O34 -> 893620.86 | R34: =Q34/$G$6 -> 1.7380047 | S34: =Q34/$G$7 -> 2.1587715 | T34: =Q34/$G$8 -> 2068.5668 | U34: =Q34/$Q$89 -> 0.0085592613 | V34: 4 | Z34: 800871.79 | AA34: =Q34-Z34 -> 92749.07 | AC34: 4
B35: 08A | C35: Doors, Frames, & Hardware | F35: ='08A Doors, Frames, & Hardware'!B150 -> 2337225 | G35: =F35/$G$6 -> 4.5456729 | H35: =F35/$G$7 -> 5.6461693 | I35: =F35/$G$8 -> 5410.2431 | Q35: =F35+K35+M35+O35 -> 2337225 | R35: =Q35/$G$6 -> 4.5456729 | S35: =Q35/$G$7 -> 5.6461693 | T35: =Q35/$G$8 -> 5410.2431 | U35: =Q35/$Q$89 -> 0.022386361 | V35: 3 | Z35: 2262225 | AA35: =Q35-Z35 -> 75000 | AB35: Panel entry door as per RFI | AC35: 3
B36: 08B | C36: Overhead Coiling Doors | F36: ='08B Overhead Coiling Doors'!B85 -> 66970 | G36: =F36/$G$6 -> 0.13025007 | H36: =F36/$G$7 -> 0.16178329 | I36: =F36/$G$8 -> 155.02315 | Q36: =F36+K36+M36+O36 -> 66970 | R36: =Q36/$G$6 -> 0.13025007 | S36: =Q36/$G$7 -> 0.16178329 | T36: =Q36/$G$8 -> 155.02315 | U36: =Q36/$Q$89 -> 0.00064145071 | V36: 7 | Z36: 66970 | AA36: =Q36-Z36 -> 0 | AC36: 7
B37: 08C | C37: Glass and Glazing | F37: ='08C Glass and Glazing'!B164 -> 3029956.3 | G37: =F37/$G$6 -> 5.8929671 | H37: =F37/$G$7 -> 7.3196402 | I37: =F37/$G$8 -> 7013.7877 | Q37: =F37+K37+M37+O37 -> 3029956.3 | R37: =Q37/$G$6 -> 5.8929671 | S37: =Q37/$G$7 -> 7.3196402 | T37: =Q37/$G$8 -> 7013.7877 | U37: =Q37/$Q$89 -> 0.029021466 | V37: 11 | Z37: 3029956.3 | AA37: =Q37-Z37 -> 0 | AC37: 11
B38: 08E | C38: Mirrors | F38: ='08E Mirrors'!B93 -> 229579.02 | G38: =F38/$G$6 -> 0.44650863 | H38: =F38/$G$7 -> 0.55460728 | I38: =F38/$G$8 -> 531.43291 | Q38: =F38+K38+M38+O38 -> 229579.02 | R38: =Q38/$G$6 -> 0.44650863 | S38: =Q38/$G$7 -> 0.55460728 | T38: =Q38/$G$8 -> 531.43291 | U38: =Q38/$Q$89 -> 0.0021989491 | V38: 3 | Z38: 230109.02 | AA38: =Q38-Z38 -> -530 | AC38: 3
B39: 09A | C39: Stucco | F39: ='09A Stucco'!B128 -> 3017500 | G39: =F39/$G$6 -> 5.8687409 | H39: =F39/$G$7 -> 7.2895489 | I39: =F39/$G$8 -> 6984.9537 | K39: ='09A Stucco'!E128 -> 17000 | M39: ='09A Stucco'!C128 -> 84500 | O39: ='09A Stucco'!D128 -> 25000 | Q39: =F39+K39+M39+O39 -> 3144000 | R39: =Q39/$G$6 -> 6.114771 | S39: =Q39/$G$7 -> 7.5951422 | T39: =Q39/$G$8 -> 7277.7778 | U39: =Q39/$Q$89 -> 0.030113797 | V39: 8 | Z39: 3000000 | AA39: =Q39-Z39 -> 144000 | AB39: Balcony columns, no net increase | AC39: 8
B40: 09B | C40: Drywall / Framing | F40: ='09B Drywall&Framing'!B113 -> 4941119 | G40: =F40/$G$6 -> 9.6099908 | H40: =F40/$G$7 -> 11.936546 | I40: =F40/$G$8 -> 11437.775 | K40: ='09B Drywall&Framing'!D113 -> 8756 | M40: ='09B Drywall&Framing'!C113 -> 150736 | O40: ='09B Drywall&Framing'!E113 -> 65340 | Q40: =F40+K40+M40+O40 -> 5165951 | R40: =Q40/$G$6 -> 10.047267 | S40: =Q40/$G$7 -> 12.479686 | T40: =Q40/$G$8 -> 11958.22 | U40: =Q40/$Q$89 -> 0.049480408 | V40: 5 | Z40: 4952465 | AA40: =Q40-Z40 -> 213486 | AB40: Balcony columns, no net increase | AC40: 5
B41: 09E | C41: Flooring | F41: ='09E Flooring'!B161 -> 2821318 | G41: =F41/$G$6 -> 5.4871862 | H41: =F41/$G$7 -> 6.8156207 | I41: =F41/$G$8 -> 6530.8287 | M41: ='09E Flooring'!C161 -> 334620 | Q41: =F41+K41+M41+O41 -> 3155938 | R41: =Q41/$G$6 -> 6.1379892 | S41: =Q41/$G$7 -> 7.6239815 | T41: =Q41/$G$8 -> 7305.412 | U41: =Q41/$Q$89 -> 0.030228142 | V41: 4 | Z41: 2582940 | AA41: =Q41-Z41 -> 572998 | AB41: Kast RFI for shower surround and kitchen backsplash material | AC41: 4
B42: 09I | C42: Painting | F42: ='09I Painting'!B117 -> 1553114.8 | G42: =F42/$G$6 -> 3.0206556 | H42: =F42/$G$7 -> 3.751949 | I42: =F42/$G$8 -> 3595.1732 | K42: ='09I Painting'!E117 -> 5742 | M42: ='09I Painting'!C117 -> 150834 | O42: ='09I Painting'!D117 -> 19952 | Q42: =F42+K42+M42+O42 -> 1729642.8 | R42: =Q42/$G$6 -> 3.3639853 | S42: =Q42/$G$7 -> 4.1783979 | T42: =Q42/$G$8 -> 4003.8028 | U42: =Q42/$Q$89 -> 0.01656683 | V42: 7 | W42: 1550000 | Y42: Talbot/CF | Z42: 1729642.8 | AA42: =Q42-Z42 -> 0 | AC42: 7
B43: 10A | C43: Signage | F43: ='10A Signage'!B92 -> 88080.3 | G43: =F43/$G$6 -> 0.17130753 | H43: =F43/$G$7 -> 0.21278066 | I43: =F43/$G$8 -> 203.88958 | M43: ='10C Toilet Partitions & Bath'!C94 -> 0 | Q43: =F43+K43+M43+O43 -> 88080.3 | R43: =Q43/$G$6 -> 0.17130753 | S43: =Q43/$G$7 -> 0.21278066 | T43: =Q43/$G$8 -> 203.88958 | U43: =Q43/$Q$89 -> 0.00084364896 | V43: 1 | Z43: 88080.3 | AA43: =Q43-Z43 -> 0 | AC43: 1
B44: 10C | C44: Bath Accessories / Signs / Fire Extinguishers | F44: ='10C Toilet Partitions & Bath'!B95 -> 352460 | G44: =F44/$G$6 -> 0.68550006 | H44: =F44/$G$7 -> 0.85145796 | I44: =F44/$G$8 -> 815.87963 | M44: ='10C Toilet Partitions & Bath'!C95 -> 0 | Q44: =F44+K44+M44+O44 -> 352460 | R44: =Q44/$G$6 -> 0.68550006 | S44: =Q44/$G$7 -> 0.85145796 | T44: =Q44/$G$8 -> 815.87963 | U44: =Q44/$Q$89 -> 0.0033759253 | V44: 3 | Z44: 307905 | AA44: =Q44-Z44 -> 44555 | AC44: 3
B45: 10D | C45: Shower enclosures | F45: ='10D Shower Enclosures'!B88 -> 254000 | G45: =F45/$G$6 -> 0.49400503 | H45: =F45/$G$7 -> 0.61360246 | I45: =F45/$G$8 -> 587.96296 | Q45: =F45+K45+M45+O45 -> 254000 | R45: =Q45/$G$6 -> 0.49400503 | S45: =Q45/$G$7 -> 0.61360246 | T45: =Q45/$G$8 -> 587.96296 | U45: =Q45/$Q$89 -> 0.0024328577 | V45: 4 | Z45: 282370 | AA45: =Q45-Z45 -> -28370 | AB45: more competitive proposal | AC45: 4
B46: 10J | C46: Postal Specialties | G46: =F46/$G$6 -> 0 | H46: =F46/$G$7 -> 0 | I46: =F46/$G$8 -> 0 | M46: ='10J Postal Specialties'!B100 -> 139907.36 | Q46: =F46+K46+M46+O46 -> 139907.36 | R46: =Q46/$G$6 -> 0.27210606 | S46: =Q46/$G$7 -> 0.33798228 | T46: =Q46/$G$8 -> 323.85963 | U46: =Q46/$Q$89 -> 0.0013400579 | V46: 2 | Z46: 139907.36 | AA46: =Q46-Z46 -> 0 | AC46: 2
B47: 10K | C47: MDF Shelving | F47: ='10K Metal Shelving'!B106 -> 356370 | G47: =F47/$G$6 -> 0.69310462 | H47: =F47/$G$7 -> 0.86090357 | I47: =F47/$G$8 -> 824.93056 | Q47: =F47+K47+M47+O47 -> 356370 | R47: =Q47/$G$6 -> 0.69310462 | S47: =Q47/$G$7 -> 0.86090357 | T47: =Q47/$G$8 -> 824.93056 | U47: =Q47/$Q$89 -> 0.003413376 | V47: 1 | Z47: 384350 | AA47: =Q47-Z47 -> -27980 | AB47: Removed shelf towers at W.I.C as per Kolter instruction | AC47: 1
B48: 11C | C48: Appliances | F48: ='11C Appliances'!B124 -> 1866841 | G48: =F48/$G$6 -> 3.6308223 | H48: =F48/$G$7 -> 4.5098355 | I48: =F48/$G$8 -> 4321.3912 | M48: ='11C Appliances'!C124 -> 21758 | Q48: =F48+K48+M48+O48 -> 1888599 | R48: =Q48/$G$6 -> 3.6731394 | S48: =Q48/$G$7 -> 4.5623976 | T48: =Q48/$G$8 -> 4371.7569 | U48: =Q48/$Q$89 -> 0.018089341 | V48: 3 | Z48: 1888599 | AA48: =Q48-Z48 -> 0 | AC48: 3
B49: 12A | C49: Window Treatment | F49: ='12A Window Treatment'!B89 -> 102000 | G49: =F49/$G$6 -> 0.19837997 | H49: =F49/$G$7 -> 0.24640729 | I49: =F49/$G$8 -> 236.11111 | M49: ='12A Window Treatment'!C89 -> 0 | Q49: =F49+K49+M49+O49 -> 102000 | R49: =Q49/$G$6 -> 0.19837997 | S49: =Q49/$G$7 -> 0.24640729 | T49: =Q49/$G$8 -> 236.11111 | U49: =Q49/$Q$89 -> 0.00097697435 | V49: 2 | Z49: 102000 | AA49: =Q49-Z49 -> 0 | AC49: 2
B50: 12B | C50: Residential Cabinets and Countertops | F50: ='12B Residential Cabinets & Tops'!B105 -> 2660474.9 | G50: =F50/$G$6 -> 5.1743621 | H50: =F50/$G$7 -> 6.4270626 | I50: =F50/$G$8 -> 6158.5066 | Q50: =F50+K50+M50+O50 -> 2660474.9 | R50: =Q50/$G$6 -> 5.1743621 | S50: =Q50/$G$7 -> 6.4270626 | T50: =Q50/$G$8 -> 6158.5066 | U50: =Q50/$Q$89 -> 0.025482507 | V50: 16 | Z50: 2660474.9 | AA50: =Q50-Z50 -> 0 | AC50: 10
B51: 13B | C51: Swimming Pool | F51: ='13B Swimming Pools'!B95 -> 365890 | G51: =F51/$G$6 -> 0.71162009 | H51: =F51/$G$7 -> 0.88390158 | I51: =F51/$G$8 -> 846.96759 | Q51: =F51+K51+M51+O51 -> 365890 | R51: =Q51/$G$6 -> 0.71162009 | S51: =Q51/$G$7 -> 0.88390158 | T51: =Q51/$G$8 -> 846.96759 | U51: =Q51/$Q$89 -> 0.0035045602 | V51: 6 | Z51: 365890 | AA51: =Q51-Z51 -> 0 | AC51: 6
B52: 13C | C52: Awnings, Canopies, Bahama Shutters | F52: ='13C Awnings,Canopies,Shutters'!B127 -> 1038214.3 | G52: =F52/$G$6 -> 2.0192249 | H52: =F52/$G$7 -> 2.5080743 | I52: =F52/$G$8 -> 2403.274 | Q52: =F52+K52+M52+O52 -> 1038214.3 | R52: =Q52/$G$6 -> 2.0192249 | S52: =Q52/$G$7 -> 2.5080743 | T52: =Q52/$G$8 -> 2403.274 | U52: =Q52/$Q$89 -> 0.0099442038 | V52: 5 | Z52: 1038214.3 | AA52: =Q52-Z52 -> 0 | AC52: 5
B53: 14A | C53: Elevators | F53: ='14A Elevators'!B117 -> 1384500 | G53: =F53/$G$6 -> 2.6927164 | H53: =F53/$G$7 -> 3.3446165 | I53: =F53/$G$8 -> 3204.8611 | M53: ='14A Elevators'!C117 -> 0 | Q53: =F53+K53+M53+O53 -> 1384500 | R53: =Q53/$G$6 -> 2.6927164 | S53: =Q53/$G$7 -> 3.3446165 | T53: =Q53/$G$8 -> 3204.8611 | U53: =Q53/$Q$89 -> 0.01326099 | V53: 3 | Z53: 1384500 | AA53: =Q53-Z53 -> 0 | AC53: 3
B54: 14B | C54: Chutes & Collectors | F54: ='14B Chutes&Collectors'!B120 -> 326932 | G54: =F54/$G$6 -> 0.63585061 | H54: =F54/$G$7 -> 0.7897885 | I54: =F54/$G$8 -> 756.78704 | Q54: =F54+K54+M54+O54 -> 326932 | R54: =Q54/$G$6 -> 0.63585061 | S54: =Q54/$G$7 -> 0.7897885 | T54: =Q54/$G$8 -> 756.78704 | U54: =Q54/$Q$89 -> 0.0031314135 | V54: 5 | Z54: 340802 | AA54: =Q54-Z54 -> -13870 | AC54: 5
B55: 21A | C55: Fire Sprinkler | F55: ='21A Fire Sprinkler'!B113 -> 1863500 | G55: =F55/$G$6 -> 3.6243243 | H55: =F55/$G$7 -> 4.5017645 | I55: =F55/$G$8 -> 4313.6574 | M55: ='21A Fire Sprinkler'!C113 -> 0 | Q55: =F55+K55+M55+O55 -> 1863500 | R55: =Q55/$G$6 -> 3.6243243 | S55: =Q55/$G$7 -> 4.5017645 | T55: =Q55/$G$8 -> 4313.6574 | U55: =Q55/$Q$89 -> 0.017848938 | V55: 9 | Z55: 1768500 | AA55: =Q55-Z55 -> 95000 | AC55: 9
B56: 22A | C56: Plumbing | F56: ='22A Plumbing '!B188-F57 -> 4653401 | G56: =F56/$G$6 -> 9.0504076 | H56: =F56/$G$7 -> 11.241489 | I56: =F56/$G$8 -> 10771.762 | M56: ='22A Plumbing '!C188 -> 265906 | O56: ='22A Plumbing '!D188 -> 14903 | Q56: =F56+K56+M56+O56 -> 4934210 | R56: =Q56/$G$6 -> 9.5965535 | S56: =Q56/$G$7 -> 11.919856 | T56: =Q56/$G$8 -> 11421.782 | U56: =Q56/$Q$89 -> 0.047260751 | V56: 3 | Z56: 5760010 | AA56: =Q56-Z56 -> -825800 | AC56: 3
B57: 22A | C57: Plumbing Fixtures | F57: =-'22A Plumbing '!U39 -> 825800 | G57: =F57/$G$6 -> 1.6060998 | H57: =F57/$G$7 -> 1.9949327 | I57: =F57/$G$8 -> 1911.5741 | Q57: =F57+K57+M57+O57 -> 825800 | R57: =Q57/$G$6 -> 1.6060998 | S57: =Q57/$G$7 -> 1.9949327 | T57: =Q57/$G$8 -> 1911.5741 | U57: =Q57/$Q$89 -> 0.0079096609 | V57: 3
B58: 22A | C58: Plumbing Units Submeters | F58: ='22A Plumbing '!AF8 -> 42768 | G58: =F58/$G$6 -> 0.083179556 | H58: =F58/$G$7 -> 0.10331713 | I58: =F58/$G$8 -> 99 | Q58: =F58+K58+M58+O58 -> 42768 | R58: =Q58/$G$6 -> 0.083179556 | S58: =Q58/$G$7 -> 0.10331713 | T58: =Q58/$G$8 -> 99 | U58: =Q58/$Q$89 -> 0.0004096396 | V58: 1
B59: 23A | C59: HVAC | F59: ='23A HVAC'!B121 -> 2776000 | G59: =F59/$G$6 -> 5.3990472 | H59: =F59/$G$7 -> 6.7061434 | I59: =F59/$G$8 -> 6425.9259 | K59: ='23A HVAC'!E121 -> 10000 | M59: ='23A HVAC'!C121 -> 180000 | O59: ='23A HVAC'!D121 -> 29000 | Q59: =F59+K59+M59+O59 -> 2995000 | R59: =Q59/$G$6 -> 5.8249806 | S59: =Q59/$G$7 -> 7.2351943 | T59: =Q59/$G$8 -> 6932.8704 | U59: =Q59/$Q$89 -> 0.028686649 | V59: 8 | Z59: 2995000 | AA59: =Q59-Z59 -> 0 | AC59: 8
B60: 26A | C60: Electrical | F60: ='26A Electrical'!B200 -> 9420000 | G60: =F60/$G$6 -> 18.320974 | H60: =F60/$G$7 -> 22.756438 | I60: =F60/$G$8 -> 21805.556 | K60: ='26A Electrical'!D200 -> 0 | Q60: =F60+K60+M60+O60 -> 9420000 | R60: =Q60/$G$6 -> 18.320974 | S60: =Q60/$G$7 -> 22.756438 | T60: =Q60/$G$8 -> 21805.556 | U60: =Q60/$Q$89 -> 0.090226454 | V60: 7 | Z60: 9390000 | AA60: =Q60-Z60 -> 30000 | AC60: 7
B61: 26B | C61: Light Fixtures | F61: Included | K61: ='26A Electrical'!C200 -> 0 | R61: =Q61/$G$6 -> 0 | S61: =Q61/$G$7 -> 0 | T61: =Q61/$G$8 -> 0 | U61: =Q61/$Q$89 -> 0 | AA61: =Q61-Z61 -> 0
B62: 26C | C62: Generators | F62: Excluded | Q62: Excluded | Z62: Excluded
B63: 27A | C63: Fire Alarm | F63: Included | R63: =Q63/$G$6 -> 0 | S63: =Q63/$G$7 -> 0 | T63: =Q63/$G$8 -> 0 | U63: =Q63/$Q$89 -> 0 | AA63: =Q63-Z63 -> 0
B64: 27B | C64: BDA System | F64: ='27B BDA'!B79 -> 242750 | G64: =F64/$G$6 -> 0.47212489 | H64: =F64/$G$7 -> 0.58642518 | I64: =F64/$G$8 -> 561.9213 | Q64: =F64+K64+M64+O64 -> 242750 | R64: =Q64/$G$6 -> 0.47212489 | S64: =Q64/$G$7 -> 0.58642518 | T64: =Q64/$G$8 -> 561.9213 | U64: =Q64/$Q$89 -> 0.0023251032 | V64: 2 | Z64: 242750 | AA64: =Q64-Z64 -> 0 | AC64: 2
B65: 28A | C65: Low Voltage | F65: ='28A Low Voltage'!B117 -> 995375 | G65: =F65/$G$6 -> 1.9359065 | H65: =F65/$G$7 -> 2.4045848 | I65: =F65/$G$8 -> 2304.1088 | Q65: =F65+K65+M65+O65 -> 995375 | R65: =Q65/$G$6 -> 1.9359065 | S65: =Q65/$G$7 -> 2.4045848 | T65: =Q65/$G$8 -> 2304.1088 | U65: =Q65/$Q$89 -> 0.0095338808 | V65: 3 | W65: ='28A Low Voltage'!M81 -> 846146 | X65: =Q65-W65 -> 149229 | Y65: Joy | Z65: 366524 | AA65: =Q65-Z65 -> 628851 | AC65: 3
B66: 28B | C66: Access Control | F66: Included in LV | Q66: 0 | R66: =Q66/$G$6 -> 0 | S66: =Q66/$G$7 -> 0 | T66: =Q66/$G$8 -> 0 | U66: =Q66/$Q$89 -> 0 | V66: 3 | Z66: 343200 | AA66: =Q66-Z66 -> -343200 | AB66: Moved to line above | AC66: 3
B67: 31A | C67: Sitework | G67: =F67/$G$6 -> 0 | H67: =F67/$G$7 -> 0 | I67: =F67/$G$8 -> 0 | K67: ='31A Sitework'!B244 -> 10941785 | Q67: =F67+K67+M67+O67 -> 10941785 | R67: =Q67/$G$6 -> 21.280696 | S67: =Q67/$G$7 -> 26.432701 | T67: =Q67/$G$8 -> 25328.206 | U67: =Q67/$Q$89 -> 0.10480238 | V67: 5 | Z67: 10376954 | AA67: =Q67-Z67 -> 564830.88 | AB67: Congress off site work and remove organic material as per Geotech report | AC67: 5
B68: 31D | C68: Soil Improvements | F68: Excluded | R68: =Q68/$G$6 -> 0 | S68: =Q68/$G$7 -> 0 | T68: =Q68/$G$8 -> 0 | U68: =Q68/$Q$89 -> 0 | V68: 2 | Z68: 0 | AA68: =Q68-Z68 -> 0 | AC68: 2
B69: 32A | C69: Pavers | F69: ='32A Pavers'!B134 -> 540250 | G69: =F69/$G$6 -> 1.0507332 | H69: =F69/$G$7 -> 1.3051131 | I69: =F69/$G$8 -> 1250.5787 | Q69: =F69+K69+M69+O69 -> 540250 | R69: =Q69/$G$6 -> 1.0507332 | S69: =Q69/$G$7 -> 1.3051131 | T69: =Q69/$G$8 -> 1250.5787 | U69: =Q69/$Q$89 -> 0.0051746117 | V69: 6 | Z69: 540250 | AA69: =Q69-Z69 -> 0 | AC69: 6
B70: 32B | C70: Site Furnishings | K70: ='32B Site Furnishings'!B102 -> 606146.1 | Q70: =F70+K70+M70+O70 -> 606146.1 | R70: =Q70/$G$6 -> 1.1788946 | S70: =Q70/$G$7 -> 1.4643021 | T70: =Q70/$G$8 -> 1403.116 | U70: =Q70/$Q$89 -> 0.0058057764 | V70: 1 | Z70: 581396.1 | AA70: =Q70-Z70 -> 24750 | AB70: Increased allowance to cover wood deck platform and BBQ grills as per Kast RFIs | AC70: 1
B71: 32C | C71: Landscape and Irrigation | G71: =F71/$G$6 -> 0 | H71: =F71/$G$7 -> 0 | I71: =F71/$G$8 -> 0 | K71: ='32C Landscape and Irrigation'!B103 -> 2789413 | Q71: =F71+K71+M71+O71 -> 2789413 | R71: =Q71/$G$6 -> 5.4251342 | S71: =Q71/$G$7 -> 6.738546 | T71: =Q71/$G$8 -> 6456.9746 | U71: =Q71/$Q$89 -> 0.0267175 | V71: 3 | Z71: 2789413 | AA71: =Q71-Z71 -> 0 | AC71: 3
B72: 32D | C72: Fencing | F72: 0 | G72: =F72/$G$6 -> 0 | H72: =F72/$G$7 -> 0 | I72: =F72/$G$8 -> 0 | K72: ='32D Fencing'!B108 -> 278850 | Q72: =F72+K72+M72+O72 -> 278850 | R72: =Q72/$G$6 -> 0.54233584 | S72: =Q72/$G$7 -> 0.67363403 | T72: =Q72/$G$8 -> 645.48611 | U72: =Q72/$Q$89 -> 0.0026708755 | V72: 4 | Z72: 531850 | AA72: =Q72-Z72 -> -253000 | AB72: Moved entry gates to LV contractor | AC72: 4
C73: SUB-TOTAL 1 (Cost of Work)Building | F73: =SUM(F13:F72) -> 74133625 | G73: =SUM(G13:G72) -> 143.02506 | H73: =SUM(H13:H72) -> 177.65108 | I73: =SUM(I13:I72) -> 170227.9 | K73: =SUM(K13:K72) -> 15185814 | M73: =SUM(M13:M72) -> 3234450.9 | O73: =SUM(O13:O72) -> 614505 | Q73: =SUM(Q13:Q72) -> 93168395 | R73: =SUM(R13:R72) -> 181.19151 | S73: =SUM(S13:S72) -> 225.07227 | T73: =SUM(T13:T72) -> 215667.58 | U73: =SUM(U13:U72) -> 0.89238365 | V73: 209 | W73: =SUM(W13:W72) -> 23209836 | X73: =SUM(X12:X72) -> -540771 | Z73: =SUM(Z13:Z72) -> 91510748 | AA73: =SUM(AA13:AA72) -> 789079.02 | AC73: =SUM(AC13:AC72) -> 209
D74: GC Contingency | F74: =F73*$AC$74 -> 741336.25 | G74: =G73*$AC$74 -> 1.4302506 | H74: =H73*$AC$74 -> 1.7765108 | I74: =I73*$AC$74 -> 1702.279 | K74: =K73*AC74 -> 151858.14 | M74: =M73*AC74 -> 32344.509 | O74: =O73*AC74 -> 6145.05 | Q74: =Q73*AC74 -> 931683.95 | R74: =Q74/G6 -> 1.8120337 | S74: =Q74/G7 -> 2.2507227 | T74: =Q74/G8 -> 2156.6758 | U74: =Q74/$Q$89 -> 0.0089238365 | Z74: 915107.48 | AA74: =Q74-Z74 -> 16576.47 | AC74: 0.01
D75: Owner Contingency | F75: By Owner | AC75: 0
D76: Escalation Contingency | AC76: 0
C77: SUB-TOTAL 2 (Contingency) | F77: =SUM(F73:F76) -> 74874962 | G77: =SUM(G73:G76) -> 144.45531 | H77: =SUM(H73:H76) -> 179.4276 | I77: =SUM(I73:I76) -> 171930.18 | K77: =SUM(K73:K76) -> 15337672 | M77: =SUM(M73:M76) -> 3266795.4 | O77: =SUM(O73:O76) -> 620650.05 | Q77: =SUM(Q73:Q76) -> 94100079 | R77: =SUM(R73:R76) -> 183.00355 | S77: =SUM(S73:S76) -> 227.32299 | T77: =SUM(T73:T76) -> 217824.26 | U77: =SUM(U73:U76) -> 0.90130749 | Z77: =SUM(Z73:Z76) -> 92425856 | AA77: =SUM(AA73:AA76) -> 805655.49
D78: General Conditions | F78: 3177583 | G78: =F78/$G$6 -> 6.1800866 | H78: =F78/$G$7 -> 7.6762706 | I78: =F78/$G$8 -> 7355.5162 | K78: 572314 | M78: 99839 | O78: =Q78-M78-K78-F78 -> 30670.699 | Q78: ='GCs&GRs-1'!L160 -> 3880406.7 | R78: =Q78/$G$6 -> 7.5470096 | S78: =Q78/$G$7 -> 9.3741224 | T78: =Q78/$G$8 -> 8982.4229 | U78: =Q78/$Q$89 -> 0.037167233 | Z78: 3880407 | AA78: =Q78-Z78 -> -0.30128976
D79: General Requirements | F79: 460259 | G79: =F79/$G$6 -> 0.89515852 | H79: =F79/$G$7 -> 1.1118742 | I79: =F79/$G$8 -> 1065.4144 | K79: 87040 | M79: 15170 | O79: =Q79-M79-K79-F79 -> 27132.451 | Q79: ='GCs&GRs-1'!L161 -> 589601.45 | R79: =Q79/$G$6 -> 1.1467169 | S79: =Q79/$G$7 -> 1.4243342 | T79: =Q79/$G$8 -> 1364.8182 | U79: =Q79/$Q$89 -> 0.0056473087 | Z79: 589601 | AA79: =Q79-Z79 -> 0.451
D80: Builders Risk Insurance & Deductibles | F80: By Owner | U80: =Q80/$Q$89 -> 0 | AA80: =Q80-Z80 -> 0
D81: Difference in OCIP Insurance Program (Allowance) | F81: =F101*AC81 -> 330115.6 | G81: =F81/$G$6 -> 0.6420424 | H81: =F81/$G$7 -> 0.7974793 | I81: =F81/$G$8 -> 764.15648 | K81: =K101*AC81 -> 66916.556 | M81: =M101*AC81 -> 14043.936 | O81: =Q81-M81-K81-F81 -> 2284.112 | Q81: =Q101*$AC$81 -> 413360.2 | R81: =Q81/$G$6 -> 0.80394497 | S81: =Q81/$G$7 -> 0.99857809 | T81: =Q81/$G$8 -> 956.85232 | U81: =Q81/$Q$89 -> 0.0039592384 | Z81: 1240080.6 | AA81: =Q81-Z81 -> -826720.41 | AC81: 0.004
D82: Subcontractor Default Insurance | F82: =F77*$AC$82 -> 935937.02 | G82: =F82/$G$6 -> 1.8203055 | H82: =F82/$G$7 -> 2.2609971 | I82: =F82/$G$8 -> 2166.5209 | K82: =K77*$AC$82 -> 191720.9 | M82: =M77*$AC$82 -> 40834.943 | O82: =O77*$AC$82 -> 7758.1256 | Q82: =Q77*$AC$82 -> 1176251 | R82: =Q82/$G$6 -> 2.2876926 | S82: =Q82/$G$7 -> 2.8415374 | T82: =Q82/$G$8 -> 2722.8032 | U82: =Q82/$Q$89 -> 0.011266344 | Z82: 1155323.2 | AA82: =Q82-Z82 -> 20927.794 | AC82: 0.0125
D83: Warranty | F83: =F73*$AC$83 -> 259467.69 | G83: =F83/$G$6 -> 0.50463915 | H83: =F83/$G$7 -> 0.62681107 | I83: =F83/$G$8 -> 600.61965 | K83: =K73*$AC$83 -> 53150.349 | M83: =M73*$AC$83 -> 11320.578 | O83: =O73*$AC$83 -> 2150.7675 | Q83: =Q73*$AC$83 -> 326089.38 | R83: =Q83/$G$6 -> 0.6342118 | S83: =Q83/$G$7 -> 0.78775294 | T83: =Q83/$G$8 -> 754.83654 | U83: =Q83/$Q$89 -> 0.0031233428 | Z83: 320287.62 | AA83: =Q83-Z83 -> 5801.7646 | AC83: 0.0035
D84: General Liability Insurance | F84: Excluded | U84: =Q84/$Q$89 -> 0 | AA84: =Q84-Z84 -> 0 | AC84: 0
D85: Difference in Coverage (DIC) | F85: Excluded | U85: =Q85/$Q$89 -> 0
C86: SUB-TOTAL 3 (Bonds, Insurances, & GC's) | F86: =SUM(F77:F85) -> 80038324 | G86: =SUM(G77:G85) -> 154.49755 | H86: =SUM(H77:H85) -> 191.90103 | I86: =SUM(I77:I85) -> 183882.41 | K86: =SUM(K77:K85) -> 16308814 | M86: =SUM(M77:M85) -> 3448003.9 | O86: =SUM(O77:O85) -> 690646.2 | Q86: =SUM(Q77:Q85) -> 1.0048579e+08 | R86: =SUM(R77:R85) -> 195.42312 | S86: =SUM(S77:S85) -> 242.74932 | T86: =SUM(T77:T85) -> 232605.99 | U86: =SUM(U77:U85) -> 0.96247095 | Z86: =SUM(Z77:Z84) -> 99611555 | AA86: =SUM(AA77:AA84) -> 5664.7873
D87: GC Fee (OH&P) | F87: =F86*AC87 -> 3201533 | G87: =G86*AC87 -> 6.1799019 | H87: =H86*AC87 -> 7.6760411 | I87: =I86*AC87 -> 7355.2963 | K87: =K86*$AC$87 -> 652352.56 | M87: =M86*$AC$87 -> 137920.16 | O87: =O86*$AC$87 -> 27625.848 | Q87: =Q86*$AC$87 -> 4019431.5 | R87: =Q87/R6 -> 7.4643499 | S87: =Q87/R7 -> 9.7099726 | T87: =Q87/R8 -> 9304.2396 | U87: =Q87/$Q$89 -> 0.038498838 | Z87: 3984462.2 | AA87: =Q87-Z87 -> 34969.311 | AC87: 0.04
D88: Credit Pre-Construction Fees | Q88: -101250 | R88: =Q88/R6 -> -0.18802794 | S88: =Q88/R7 -> -0.24459547 | T88: =Q88/G8 -> -234.375 | U88: =Q88/$Q$89 -> -0.00096979071 | Z88: -101250 | AA88: =Q88-Z88 -> 0
C89: ESTIMATE TOTAL | F89: =SUM(F86:F87) -> 83239857 | G89: =SUM(G86:G87) -> 160.67745 | H89: =SUM(H86:H87) -> 199.57707 | I89: =SUM(I86:I87) -> 191237.7 | K89: =SUM(K86:K87) -> 16961167 | M89: =SUM(M86:M87) -> 3585924 | O89: =SUM(O86:O87) -> 718272.05 | Q89: =SUM(Q86:Q88) -> 1.0440397e+08 | R89: =SUM(R86:R87) -> 202.88747 | S89: =SUM(S86:S87) -> 252.45929 | T89: =SUM(T86:T88) -> 241675.86 | U89: =SUM(U86:U88) -> 1 | Z89: =SUM(Z86:Z88) -> 1.0349477e+08 | AA89: =SUM(AA86:AA88) -> 40634.099
B90: 1 | C90: POTENTIAL VALUE ANALYSIS ITEMS SAVINGS GOALS | Q90: =-3045927 -> -3045927
B91: 2 | C91: Buyout 3% | Q91: =$Q$118*-3% -> -2746427.1
B92: 3 | C92: Buyout 4% | Q92: =$Q$118*-4% -> -3661902.8
B93: 4 | C93: Buyout 5% | Q93: =$Q$118*-5% -> -4577378.6
B94: 5 | C94: Buyout 6% | Q94: =$Q$118*-6% -> -5492854.3
C95: ESTIMATE TOTAL w/ VA Items | Q95: =Q89+Q90 -> 1.0135804e+08 | R95: =$Q$95/G6 -> 197.13143 | S95: =Q95/G7 -> 244.85647 | T95: =Q95/G8 -> 234625.1 | AC95: =AA95/Q95 -> 0
C96: ESTIMATE TOTAL w/ VA Items & 3% BO | Q96: =Q89+Q90+Q91 -> 98611616 | R96: =$Q$96/G6 -> 191.7899 | S96: =Q96/G7 -> 238.22177 | T96: =Q96/G8 -> 228267.63
C97: ESTIMATE TOTAL w/ VA Items & 4% BO | Q97: =Q89+Q90+Q92 -> 97696140 | R97: =$Q$97/G6 -> 190.00939 | S97: =Q97/G7 -> 236.0102 | T97: =Q97/G8 -> 226148.47
C98: ESTIMATE TOTAL w/ VA Items & 5% BO | Q98: =Q89+Q90+Q93 -> 96780664 | R98: =$Q$98/G6 -> 188.22888 | S98: =Q98/G7 -> 233.79863 | T98: =Q98/G8 -> 224029.32
C99: ESTIMATE TOTAL w/ VA Items & 6% BO | Q99: =Q89+Q90+Q94 -> 95865188 | R99: =$Q$99/G6 -> 186.44837 | S99: =Q99/G7 -> 231.58707 | T99: =Q99/G8 -> 221910.16
D100: Performance & Payment Bond | F100: =F89*$AC$100 -> 832398.57 | K100: =K89*$AC$100 -> 169611.67 | M100: =M89*$AC$100 -> 35859.24 | O100: =O89*$AC$100 -> 7182.7205 | Q100: =Q89*$AC$100 -> 1044039.7 | U100: =Q100/$Q$89 -> 0.01 | AC100: 0.01
F101: 82528900 | K101: 16729139 | M101: 3510984 | O101: 724943 | Q101: 103340051
F102: =F89/Q89*Q78 -> 3093795.2 | K102: =K89/Q89*Q78 -> 630399.64 | M102: =M89/Q89*Q78 -> 133278.88 | Q102: =F73+K73+M73+O73 -> 93168395 | Z102: 4079272 | AA102: =Q73-Z73 -> 1657647
F103: =F89/Q89*Q79 -> 470081.17 | K103: =K89/Q89*Q79 -> 95784.945 | M103: =M89/Q89*Q79 -> 20250.82 | Q103: =F77+K77+M77+O77 -> 94100079 | AA103: =Q77-Z77 -> 1674223.5
Q104: =F86+K86+M86+O86 -> 1.0048579e+08 | U104: =Q89-Z89 -> 909202.1 | AA104: =Q86-Z86 -> 874232.79
K105: =O81+M81+K81+F81 -> 413360.2 | Q105: =O89+M89+K89+F89 -> 1.0450522e+08 | S105: =Q89/432 -> 241675.86 | AA105: =Q89-Z89 -> 909202.1
...

Sheet IDS
G1: Hedrick Plug
F2: X | G2: Excluded
B3: BACK TO SUMMARY SHEET | F3: I | G3: Included | H3: Bidder 1 | J3: Bidder 2 | L3: Bidder 3 | N3: Bidder 4 | P3: Bidder5 | R3: Bidder6
A4: Project: | B4: 0 | G4: Company | H4: HB Construction
A5: Trade: | B5: IDS Services | G5: Contact | H5: Butch Carmichael
A6: CSI Code: | G6: Phone | H6: 561-225-4868
A7: Date: | G7: Email | H7: <bcarmichael@hedrickbrothers.com>
A8: Adjusted Bid | G8: Adjusted Bid | H8: =I99 -> 0 | J8: =K99 -> 0 | L8: =M99 -> 0 | N8: =O99 -> 0 | P8: =Q99 -> 0 | R8: =S99 -> 0
A9: BID DOCUMENTS: | C9: Plan/ Spec. Package | D9: QTY | E9: U/M | F9: Unit Cost | G9: Subtotal | H9: Yes/No | I9: Price | J9: Yes/No | K9: Price | L9: Yes/No | M9: Price | N9: Yes/No | O9: Price | P9: Yes/No | Q9: Price | R9: Yes/No | S9: Price
B10: Plans By Division
B11: 0 | C11: P
B12: 0 | C12: P
B13: 0 | C13: P
B14: 0 | C14: P
B15: 0 | C15: P
B16: 0 | C16: P
B17: 0 | C17: P
B18: 0 | C18: P
B19: 0 | C19: P
B21: Survey
B22: OCIP Insurance per exhibit
B23: GENERAL INCLUSIONS
B24: INCLUDES ALL SALES TAX
B25: ALL HOISTING & RIGGING REQUIRED TO COMPLETE THIS SCOPE
B26: PROVIDE P&P BONDS
B27: FLORIDA STATE CONTRACTORS LIC.
B28: GENERAL LIABILITY AND WORKERS COMP. INSURANCE LIMITS
B29: STATE AND LOCAL TAXES
B30: SPECIFIC TRADE SCOPE OF WORK REQUIREMENTS
B31: BASE BID | D31: 1 | E31: EA
B33: Pre-construction Modeling/BIM Execution Plan Meetings
B34: BIM Execution Plan Meeting including writing of BEP | H34: i
B35: Initial Jobsite Visit | H35: x
B36: Model Architectural | H36: i
B37: Model Structural | H37: i
B38: Model Mechanical/HVAC | H38: i
B39: Model Plumbing | H39: i
B40: Model Electrical | H40: x
B41: Model Fire Sprinkler | H41: x
B42: Model Civil | H42: x
B43: Model FF&E | H43: x
B45: Pre-construction - Digital Scanning
B46: Drone Mapping | H46: x
B47: Laser Scan of Existing Building after Demo | H47: x
B48: Photos of Existing Furniture to be Modeled | H48: x
B50: Pre-construction - BIM Coordination Meetings/ Clash Meetings
B51: Coordination/ Clash Meetings | H51: i
B52: Modification of Architectural Model | H52: i
B53: Modification of Structural Model | H53: i
B54: Modification of Mechanical/HVAC Model | H54: i
B55: Modification of Plumbing Model | H55: i
B56: Modification of Electrical Model | H56: x
B57: Modification of Fire Sprinkler Model | H57: x
B58: Modification of Civil Model | H58: x
B59: Modification of FF&E Model | H59: x
B61: Construction - BIM Coordination Meetings/ Clash Meetings
B62: Coordination/ Clash Meetings | H62: i
B63: Modification of Architectural Model | H63: i
B64: Modification of Structural Model | H64: i
B65: Modification of Mechanical/HVAC Model | H65: i
B66: Modification of Plumbing Model | H66: i
B67: Modification of Electrical Model | H67: x
B68: Modification of Fire Sprinkler Model | H68: x
B69: Modification of Civil Model | H69: x
B70: Modification of FF&E Model | H70: x
B72: As-Built Digital Scanning
B73: Pre-Drywall Laser Scan | H73: x
B74: Laser Scan to Verify Installation | H74: x
B76: Closeout Documents/ As-Builts
B77: Link RFIs to Model | H77: x
B78: Link Submittals to Model | H78: x
B79: Link O&M Documents to Model | H79: x
B80: Link Warranties & Guarantees to Model | H80: x
B82: Additional Services
B83: Additional Jobsite Visits | H83: x
B84: Interior Renderings | H84: x
B85: Exterior Renderings | H85: x
B86: 3D Fly Through | H86: x
B87: 4D Simulation | H87: x
B88: VR Presentations | H88: x
B89: Full Virtual Tour | H89: x
B90: Site Logistics | H90: x
B91: 5D Quantity Take-Off | H91: x
B92: Space Planning | H92: x
B93: Other: | H93: x
F95: SUBTOTAL | I95: =SUM(I31:I94) -> 0 | K95: =SUM(K31:K94) -> 0 | M95: =SUM(M31:M94) -> 0 | O95: =SUM(O31:O94) -> 0 | Q95: =SUM(Q31:Q94) -> 0 | S95: =SUM(S31:S94) -> 0
F96: BOND RATE | H96: 0 | J96: 0 | L96: 0 | N96: 0 | P96: 0 | R96: 0
F97: BOND AMOUNT | I97: =H96*I95 -> 0 | K97: =J96*K95 -> 0 | M97: =L96*M95 -> 0 | O97: =N96*O95 -> 0 | Q97: =P96*Q95 -> 0 | S97: =R96*S95 -> 0
F99: ADJUSTED TOTAL | I99: =SUM(I95:I97) -> 0 | K99: =SUM(K95:K97) -> 0 | M99: =SUM(M95:M97) -> 0 | O99: =SUM(O95:O97) -> 0 | Q99: =SUM(Q95:Q97) -> 0 | S99: =SUM(S95:S97) -> 0
F100: Cost per SF | I100: #DIV/0! | K100: #DIV/0! | M100: #DIV/0! | O100: #DIV/0! | Q100: #DIV/0! | R100: #DIV/0! | S100: #REF!
F101: Cost per Unit | I101: #DIV/0! | K101: #DIV/0! | M101: #DIV/0! | O101: #DIV/0! | Q101: #DIV/0! | R101: #DIV/0! | S101: #REF!
A103: QUALIFICATIONS
A107: EXCLUSIONS/OWNER PROVIDED ITEMS:
A111: ALTERNATES:
A115: PROPOSED VE (Provide Clear Description):
A119: FULLY LOADED LABOR RATES
B120: Laborer
B121: Mechanic
B122: Superintendent
B123: Project Manager
...

Sheet 01A Surveying
G1: Hedrick Plug
F2: X | G2: Excluded
B3: BACK TO SUMMARY SHEET | F3: I | G3: Included | H3: Bidder 1 | J3: Bidder 2 | L3: Bidder 3 | N3: Bidder 4 | P3: Bidder5 | R3: Bidder6
A4: Project: | B4: ='AREA CALC''s'!B4 -> Alton Hilltop Gardens | G4: Company | H4: HB | J4: Caulffield & Wheeler
A5: Trade: | B5: Surveying | G5: Contact | J5: Renee Watson
A6: CSI Code: | B6: 01A | G6: Phone | J6: 5613921991
A7: Date: | G7: Email | J7: estimates@cwiassoc.com
A8: Adjusted Bid | G8: Adjusted Bid | H8: =I48 -> 110000 | J8: =K48 -> 167700 | L8: =M48 -> 0 | N8: =O48 -> 0 | P8: =Q48 -> 0 | R8: =S48 -> 0
A9: BID DOCUMENTS: | C9: Plan/ Spec. Package | D9: QTY | E9: U/M | F9: Unit Cost | G9: Subtotal | H9: Yes/No | I9: Price | J9: Yes/No | K9: Price | L9: Yes/No | M9: Price | N9: Yes/No | O9: Price | P9: Yes/No | Q9: Price | R9: Yes/No | S9: Price
B10: Plans By Division
B11: =#REF! -> #REF! | C11: P
B12: =#REF! -> #REF! | C12: P
B13: =#REF! -> #REF! | C13: P
B14: =#REF! -> #REF! | C14: P
B15: =#REF! -> #REF! | C15: P
B16: =#REF! -> #REF! | C16: P
B17: =#REF! -> #REF! | C17: P
B18: =#REF! -> #REF! | C18: P
B19: =#REF! -> #REF! | C19: P
B21: Surveying
B22: OCIP Insurance per exhibit
B23: GENERAL INCLUSIONS
B24: INCLUDES ALL SALES TAX
B25: ALL HOISTING & RIGGING REQUIRED TO COMPLETE THIS SCOPE
B26: PROVIDE P&P BONDS
B27: FLORIDA STATE CONTRACTORS LIC.
B28: GENERAL LIABILITY AND WORKERS COMP. INSURANCE LIMITS
B29: STATE AND LOCAL TAXES
B30: COMPASS
B31: SPECIFIC TRADE SCOPE OF WORK REQUIREMENTS
B32: BASE BID | D32: 1 | E32: EA | K32: =27950*6 -> 167700
B35: Residential Building 1 | D35: 3 | E35: EA | F35: 10000 | G35: =D35*F35 -> 30000 | H35: i | I35: =G35 -> 30000
B36: Residential Building 2 | D36: 2 | E36: EA | F36: 12000 | G36: =D36*F36 -> 24000 | H36: i | I36: =G36 -> 24000
B37: Residential Building 3 | D37: 1 | E37: EA | F37: 12000 | G37: =D37*F37 -> 12000 | H37: i | I37: =G37 -> 12000
B39: Site | D39: 1 | E39: EA | F39: 30000 | G39: =D39*F39 -> 30000 | H39: i | I39: =G39 -> 30000
B40: Garage | D40: 3 | E40: EA | F40: 2000 | G40: =D40*F40 -> 6000 | H40: i | I40: =G40 -> 6000
B41: Clubhouse | D41: 1 | E41: EA | F41: 8000 | G41: =D41*F41 -> 8000 | H41: i | I41: =G41 -> 8000
F44: SUBTOTAL | G44: =SUM(G35:G43) -> 110000 | I44: =SUM(I32:I43) -> 110000 | K44: =SUM(K32:K43) -> 167700 | M44: =SUM(M32:M43) -> 0 | O44: =SUM(O32:O43) -> 0 | Q44: =SUM(Q32:Q43) -> 0 | S44: =SUM(S32:S43) -> 0
F45: BOND RATE | H45: 0 | J45: 0 | L45: 0 | N45: 0 | P45: 0 | R45: 0
F46: BOND AMOUNT | I46: =H45*I44 -> 0 | K46: =J45*K44 -> 0 | M46: =L45*M44 -> 0 | O46: =N45*O44 -> 0 | Q46: =P45*Q44 -> 0 | S46: =R45*S44 -> 0
F48: ADJUSTED TOTAL | I48: =SUM(I44:I46) -> 110000 | K48: =SUM(K44:K46) -> 167700 | M48: =SUM(M44:M46) -> 0 | O48: =SUM(O44:O46) -> 0 | Q48: =SUM(Q44:Q46) -> 0 | S48: =SUM(S44:S46) -> 0
F49: Cost per SF | I49: =I48/#REF! -> #REF! | K49: =K48/#REF! -> #REF! | M49: =M48/#REF! -> #REF! | O49: =O48/#REF! -> #REF! | Q49: =Q48/#REF! -> #REF! | R49: =R48/#REF! -> #REF! | S49: =S48/'Cost Summary'!#REF! -> #REF!
F50: Cost per Unit | I50: =I48/#REF! -> #REF! | K50: =K48/#REF! -> #REF! | M50: =M48/#REF! -> #REF! | O50: =O48/#REF! -> #REF! | Q50: =Q48/#REF! -> #REF! | R50: =R48/#REF! -> #REF! | S50: =S48/'Cost Summary'!#REF! -> #REF!
A52: QUALIFICATIONS
A56: EXCLUSIONS/OWNER PROVIDED ITEMS:
A60: ALTERNATES:
A64: PROPOSED VE (Provide Clear Description):
A68: FULLY LOADED LABOR RATES
B69: Laborer
B70: Mechanic
B71: Superintendent
B72: Project Manager
A74: SCHEDULE
B75: Prepared shop drawings/submittals
B76: Mobilization
B77: Total duration to complete scope of work
A79: Winner
A80: Company
A81: Contact
A82: Phone
A83: Email | C83: Buildings | D83: Clubhouse | E83: Garage | F83: Site
A84: Base Bid | B84: =H8 -> 110000 | C84: =B84-D84-E84-F84 -> 66000 | D84: =I41 -> 8000 | E84: =I40 -> 6000 | F84: =I39 -> 30000
B86: Need Prequalification
B87: Prequalified

Sheet 01B Material Testing
G1: Hedrick Plug
F2: X | G2: Excluded
B3: BACK TO SUMMARY SHEET | F3: I | G3: Included | H3: Bidder 1 | J3: Bidder 2 | L3: Bidder 3 | N3: Bidder 4 | P3: Bidder5 | R3: Bidder6
A4: Project: | B4: ='AREA CALC''s'!B4 -> Alton Hilltop Gardens | G4: Company
A5: Trade: | B5: Material Testing | G5: Contact
A6: CSI Code: | B6: 01B | G6: Phone
A7: Date: | G7: Email
A8: Adjusted Bid | G8: Adjusted Bid | H8: =I70 -> 0 | J8: =K70 -> 0 | L8: =M70 -> 0 | N8: =O70 -> 0 | P8: =Q70 -> 0 | R8: =S70 -> 0
A9: BID DOCUMENTS: | C9: Plan/ Spec. Package | D9: QTY | E9: U/M | F9: Unit Cost | G9: Subtotal | H9: Yes/No | I9: Price | J9: Yes/No | K9: Price | L9: Yes/No | M9: Price | N9: Yes/No | O9: Price | P9: Yes/No | Q9: Price | R9: Yes/No | S9: Price
B10: Plans By Division
B11: =#REF! -> #REF! | C11: P
B12: =#REF! -> #REF! | C12: P
B13: =#REF! -> #REF! | C13: P
B14: =#REF! -> #REF! | C14: P
B15: =#REF! -> #REF! | C15: P
B16: =#REF! -> #REF! | C16: P
B17: =#REF! -> #REF! | C17: P
B18: =#REF! -> #REF! | C18: P
B19: =#REF! -> #REF! | C19: P
B21: Material Testing
B22: GENERAL INCLUSIONS
B23: INCLUDES ALL SALES TAX
B24: ALL HOISTING & RIGGING REQUIRED TO COMPLETE THIS SCOPE
B25: PROVIDE P&P BONDS
B26: FLORIDA STATE CONTRACTORS LIC.
B27: GENERAL LIABILITY AND WORKERS COMP. INSURANCE LIMITS
B28: STATE AND LOCAL TAXES
B29: COMPASS
B30: SPECIFIC TRADE SCOPE OF WORK REQUIREMENTS
B31: BASE BID
H36: x
H37: i
F66: SUBTOTAL | I66: =SUM(I22:I65) -> 0 | K66: =SUM(K22:K65) -> 0 | M66: =SUM(M22:M65) -> 0 | O66: =SUM(O22:O65) -> 0 | Q66: =SUM(Q22:Q65) -> 0 | S66: =SUM(S22:S65) -> 0
F67: BOND RATE | H67: 0 | J67: 0 | L67: 0 | N67: 0 | P67: 0 | R67: 0
F68: BOND AMOUNT | I68: =H67*I66 -> 0 | K68: =J67*K66 -> 0 | M68: =L67*M66 -> 0 | O68: =N67*O66 -> 0 | Q68: =P67*Q66 -> 0 | S68: =R67*S66 -> 0
F70: ADJUSTED TOTAL | I70: =SUM(I66:I68) -> 0 | K70: =SUM(K66:K68) -> 0 | M70: =SUM(M66:M68) -> 0 | O70: =SUM(O66:O68) -> 0 | Q70: =SUM(Q66:Q68) -> 0 | S70: =SUM(S66:S68) -> 0
F71: Cost per SF | I71: =I70/#REF! -> #REF! | K71: =K70/#REF! -> #REF! | M71: =M70/#REF! -> #REF! | O71: =O70/#REF! -> #REF! | Q71: =Q70/#REF! -> #REF! | S71: =S70/#REF! -> #REF!
F72: Cost per Unit | I72: =I70/#REF! -> #REF! | K72: =K70/#REF! -> #REF! | M72: =M70/#REF! -> #REF! | O72: =O70/#REF! -> #REF! | Q72: =Q70/#REF! -> #REF! | S72: =S70/#REF! -> #REF!
A74: QUALIFICATIONS
A78: EXCLUSIONS/OWNER PROVIDED ITEMS:
A82: ALTERNATES:
A86: PROPOSED VE (Provide Clear Description):
A90: FULLY LOADED LABOR RATES
B91: Laborer
B92: Mechanic
B93: Superintendent
B94: Project Manager
A96: SCHEDULE
B97: Prepared shop drawings/submittals
B98: Mobilization
B99: Total duration to complete scope of work
A101: Winner
A102: Company
A103: Contact
A104: Phone
A105: Email
A106: Base Bid
B108: Need Prequalification
B109: Prequalified

Sheet 01C Final Cleaning
G1: Hedrick Plug
F2: X | G2: Excluded
B3: BACK TO SUMMARY SHEET | F3: I | G3: Included | H3: Bidder 1 | J3: Bidder 2 | L3: Bidder 3 | N3: Bidder 4 | P3: Bidder5 | R3: Bidder6
A4: Project: | B4: =#REF! -> #REF! | G4: Company
A5: Trade: | B5: Site Maintenance | G5: Contact
A6: CSI Code: | B6: 01C | G6: Phone
A7: Date: | G7: Email
A8: Adjusted Bid | G8: Adjusted Bid | H8: =I70 -> 0 | J8: =K70 -> 0 | L8: =M70 -> 0 | N8: =O70 -> 0 | P8: =Q70 -> 0 | R8: =S70 -> 0
A9: BID DOCUMENTS: | C9: Plan/ Spec. Package | D9: QTY | E9: U/M | F9: Unit Cost | G9: Subtotal | H9: Yes/No | I9: Price | J9: Yes/No | K9: Price | L9: Yes/No | M9: Price | N9: Yes/No | O9: Price | P9: Yes/No | Q9: Price | R9: Yes/No | S9: Price
B10: Plans By Division
B11: =#REF! -> #REF! | C11: P
B12: =#REF! -> #REF! | C12: P
B13: =#REF! -> #REF! | C13: P
B14: =#REF! -> #REF! | C14: P
B15: =#REF! -> #REF! | C15: P
B16: =#REF! -> #REF! | C16: P
B17: =#REF! -> #REF! | C17: P
B18: =#REF! -> #REF! | C18: P
B19: =#REF! -> #REF! | C19: P
B21: Final Cleaning
B22: GENERAL INCLUSIONS
B23: INCLUDES ALL SALES TAX
B24: ALL HOISTING & RIGGING REQUIRED TO COMPLETE THIS SCOPE
B25: PROVIDE P&P BONDS
B26: FLORIDA STATE CONTRACTORS LIC.
B27: GENERAL LIABILITY AND WORKERS COMP. INSURANCE LIMITS
B28: STATE AND LOCAL TAXES
B29: COMPASS
B30: SPECIFIC TRADE SCOPE OF WORK REQUIREMENTS
B31: BASE BID | G31: =SUM(G33:G47) -> 898690
B33: Construction fence | D33: 3600 | E33: LF | F33: 12 | G33: =D33*F33 -> 43200
B34: Construction gates | D34: 2 | E34: EA | F34: 6000 | G34: =D34*F34 -> 12000
B35: Maintenance during construction | D35: 1 | E35: LS | F35: 10000 | G35: =D35*F35 -> 10000
B36: Street Maintenance & Cleaning | D36: 1 | E36: LS | F36: 8000 | G36: =D36*F36 -> 8000 | H36: x
B37: Final Cleaning | D37: 412250 | E37: SF | F37: 0.5 | G37: =D37*F37 -> 206125 | H37: i
B38: Misc. Street Sweeping | D38: 1 | E38: LS | F38: 8000 | G38: =D38*F38 -> 8000
B39: Concrete Wash-out | D39: 1 | E39: LS | F39: 15000 | G39: =D39*F39 -> 15000
B40: Construction waste removal / recycle | D40: 1 | E40: LS | F40: 10000 | G40: =D40*F40 -> 10000
B41: Temp Fire Protection - Temp Holding Tanks (5) ea | D41: 16 | E41: Month | F41: 2500 | G41: =D41*F41 -> 40000
B42: Temp Fire Protection - Fill | D42: 5 | E42: ea | F42: 2000 | G42: =D42*F42 -> 10000
B43: Dumpster | D43: 16 | E43: Month | F43: 12665 | G43: =D43*F43 -> 202640
B44: Labors | D44: 16 | E44: Month | F44: 4850 | G44: =D44*F44 -> 77600
B45: Floor Protections | D45: 412250 | E45: LS | F45: 0.5 | G45: =D45*F45 -> 206125
B46: MOT | D46: 1 | E46: LS | F46: 40000 | G46: =D46*F46 -> 40000
B47: Safety rails, Penetration Covers & Maintenance of rails | D47: 1 | E47: LS | F47: 10000 | G47: =D47*F47 -> 10000
F66: SUBTOTAL | I66: =SUM(I22:I65) -> 0 | K66: =SUM(K22:K65) -> 0 | M66: =SUM(M22:M65) -> 0 | O66: =SUM(O22:O65) -> 0 | Q66: =SUM(Q22:Q65) -> 0 | S66: =SUM(S22:S65) -> 0
F67: BOND RATE | H67: 0 | J67: 0 | L67: 0 | N67: 0 | P67: 0 | R67: 0
F68: BOND AMOUNT | I68: =H67*I66 -> 0 | K68: =J67*K66 -> 0 | M68: =L67*M66 -> 0 | O68: =N67*O66 -> 0 | Q68: =P67*Q66 -> 0 | S68: =R67*S66 -> 0
F70: ADJUSTED TOTAL | I70: =SUM(I66:I68) -> 0 | K70: =SUM(K66:K68) -> 0 | M70: =SUM(M66:M68) -> 0 | O70: =SUM(O66:O68) -> 0 | Q70: =SUM(Q66:Q68) -> 0 | S70: =SUM(S66:S68) -> 0
F71: Cost per SF | I71: =I70/#REF! -> #REF! | K71: =K70/#REF! -> #REF! | M71: =M70/#REF! -> #REF! | O71: =O70/#REF! -> #REF! | Q71: =Q70/#REF! -> #REF! | S71: =S70/#REF! -> #REF!
F72: Cost per Unit | I72: =I70/#REF! -> #REF! | K72: =K70/#REF! -> #REF! | M72: =M70/#REF! -> #REF! | O72: =O70/#REF! -> #REF! | Q72: =Q70/#REF! -> #REF! | S72: =S70/#REF! -> #REF!
A74: QUALIFICATIONS
A78: EXCLUSIONS/OWNER PROVIDED ITEMS:
A82: ALTERNATES:
A86: PROPOSED VE (Provide Clear Description):
A90: FULLY LOADED LABOR RATES
B91: Laborer
B92: Mechanic
B93: Superintendent
B94: Project Manager
A96: SCHEDULE
B97: Prepared shop drawings/submittals
B98: Mobilization
B99: Total duration to complete scope of work
A101: Winner
A102: Company
A103: Contact
A104: Phone
A105: Email
A106: Base Bid | B106: =G31 -> 898690
B108: Need Prequalification
B109: Prequalified

Sheet 02A Demolition
G1: Hedrick Plug
F2: X | G2: Excluded
B3: BACK TO SUMMARY SHEET | F3: I | G3: Included | H3: Bidder 1 | J3: Bidder 2 | L3: Bidder 3 | N3: Bidder 4 | P3: Bidder5 | R3: Bidder6
A4: Project: | B4: =#REF! -> #REF! | G4: Company
A5: Trade: | B5: Demolition | G5: Contact
A6: CSI Code: | B6: 02A | G6: Phone
A7: Date: | G7: Email
A8: Adjusted Bid | G8: Adjusted Bid | H8: =I57 -> 0 | J8: =K57 -> 0 | L8: =M57 -> 0 | N8: =O57 -> 0 | P8: =Q57 -> 0 | R8: =S57 -> 0
A9: BID DOCUMENTS: | C9: Plan/ Spec. Package | D9: QTY | E9: U/M | F9: Unit Cost | G9: Subtotal | H9: Yes/No | I9: Price | J9: Yes/No | K9: Price | L9: Yes/No | M9: Price | N9: Yes/No | O9: Price | P9: Yes/No | Q9: Price | R9: Yes/No | S9: Price
B10: Plans By Division
B11: =#REF! -> #REF! | C11: P
B12: =#REF! -> #REF! | C12: P
B13: =#REF! -> #REF! | C13: P
B14: =#REF! -> #REF! | C14: P
B15: =#REF! -> #REF! | C15: P
B16: =#REF! -> #REF! | C16: P
B17: =#REF! -> #REF! | C17: P
B18: =#REF! -> #REF! | C18: P
B19: =#REF! -> #REF! | C19: P
B21: Demolition
B22: OCIP Insurance per exhibit
B23: GENERAL INCLUSIONS
B24: INCLUDES ALL SALES TAX
B25: ALL HOISTING & RIGGING REQUIRED TO COMPLETE THIS SCOPE
B26: PROVIDE P&P BONDS
B27: FLORIDA STATE CONTRACTORS LIC.
B28: GENERAL LIABILITY AND WORKERS COMP. INSURANCE LIMITS
B29: STATE AND LOCAL TAXES
B30: COMPASS
B31: SPECIFIC TRADE SCOPE OF WORK REQUIREMENTS
B32: BASE BID
H35: x
F53: SUBTOTAL | I53: =SUM(I22:I52) -> 0 | K53: =SUM(K22:K52) -> 0 | M53: =SUM(M22:M52) -> 0 | O53: =SUM(O22:O52) -> 0 | Q53: =SUM(Q22:Q52) -> 0 | S53: =SUM(S22:S52) -> 0
F54: BOND RATE | H54: 0 | J54: 0 | L54: 0 | N54: 0 | P54: 0 | R54: 0
F55: BOND AMOUNT | I55: =H54*I53 -> 0 | K55: =J54*K53 -> 0 | M55: =L54*M53 -> 0 | O55: =N54*O53 -> 0 | Q55: =P54*Q53 -> 0 | S55: =R54*S53 -> 0
F57: ADJUSTED TOTAL | I57: =SUM(I53:I55) -> 0 | K57: =SUM(K53:K55) -> 0 | M57: =SUM(M53:M55) -> 0 | O57: =SUM(O53:O55) -> 0 | Q57: =SUM(Q53:Q55) -> 0 | S57: =SUM(S53:S55) -> 0
F58: Cost per SF | I58: =I57/#REF! -> #REF! | K58: =K57/#REF! -> #REF! | M58: =M57/#REF! -> #REF! | O58: =O57/#REF! -> #REF! | Q58: =Q57/#REF! -> #REF! | S58: =S57/#REF! -> #REF!
F59: Cost per Unit | I59: =I57/#REF! -> #REF! | K59: =K57/#REF! -> #REF! | M59: =M57/#REF! -> #REF! | O59: =O57/#REF! -> #REF! | Q59: =Q57/#REF! -> #REF! | S59: =S57/#REF! -> #REF!
A61: QUALIFICATIONS
A65: EXCLUSIONS/OWNER PROVIDED ITEMS:
A69: ALTERNATES:
A73: PROPOSED VE (Provide Clear Description):
A77: FULLY LOADED LABOR RATES
B78: Laborer
B79: Mechanic
B80: Superintendent
B81: Project Manager
A83: SCHEDULE
B84: Prepared shop drawings/submittals
B85: Mobilization
B86: Total duration to complete scope of work
A88: Winner
A89: Company
A90: Contact
A91: Phone
A92: Email
A93: Base Bid
B95: Need Prequalification
B96: Prequalified

Sheet 02B Abatement
G1: Hedrick Plug
F2: X | G2: Excluded
B3: BACK TO SUMMARY SHEET | F3: I | G3: Included | H3: Bidder 1 | J3: Bidder 2 | L3: Bidder 3 | N3: Bidder 4 | P3: Bidder5 | R3: Bidder6
A4: Project: | B4: =#REF! -> #REF! | G4: Company
A5: Trade: | B5: Abatement | G5: Contact
A6: CSI Code: | B6: 02B | G6: Phone
A7: Date: | G7: Email
A8: Adjusted Bid | G8: Adjusted Bid | H8: =I57 -> 0 | J8: =K57 -> 0 | L8: =M57 -> 0 | N8: =O57 -> 0 | P8: =Q57 -> 0 | R8: =S57 -> 0
A9: BID DOCUMENTS: | C9: Plan/ Spec. Package | D9: QTY | E9: U/M | F9: Unit Cost | G9: Subtotal | H9: Yes/No | I9: Price | J9: Yes/No | K9: Price | L9: Yes/No | M9: Price | N9: Yes/No | O9: Price | P9: Yes/No | Q9: Price | R9: Yes/No | S9: Price
B10: Plans By Division
B11: =#REF! -> #REF! | C11: P
B12: =#REF! -> #REF! | C12: P
B13: =#REF! -> #REF! | C13: P
B14: =#REF! -> #REF! | C14: P
B15: =#REF! -> #REF! | C15: P
B16: =#REF! -> #REF! | C16: P
B17: =#REF! -> #REF! | C17: P
B18: =#REF! -> #REF! | C18: P
B19: =#REF! -> #REF! | C19: P
B21: Abatement
B22: OCIP Insurance per exhibit
B23: GENERAL INCLUSIONS
B24: INCLUDES ALL SALES TAX
B25: ALL HOISTING & RIGGING REQUIRED TO COMPLETE THIS SCOPE
B26: PROVIDE P&P BONDS
B27: FLORIDA STATE CONTRACTORS LIC.
B28: GENERAL LIABILITY AND WORKERS COMP. INSURANCE LIMITS
B29: STATE AND LOCAL TAXES
B30: COMPASS
B31: SPECIFIC TRADE SCOPE OF WORK REQUIREMENTS
B32: BASE BID
H35: x
F53: SUBTOTAL | I53: =SUM(I22:I52) -> 0 | K53: =SUM(K22:K52) -> 0 | M53: =SUM(M22:M52) -> 0 | O53: =SUM(O22:O52) -> 0 | Q53: =SUM(Q22:Q52) -> 0 | S53: =SUM(S22:S52) -> 0
F54: BOND RATE | H54: 0 | J54: 0 | L54: 0 | N54: 0 | P54: 0 | R54: 0
F55: BOND AMOUNT | I55: =H54*I53 -> 0 | K55: =J54*K53 -> 0 | M55: =L54*M53 -> 0 | O55: =N54*O53 -> 0 | Q55: =P54*Q53 -> 0 | S55: =R54*S53 -> 0
F57: ADJUSTED TOTAL | I57: =SUM(I53:I55) -> 0 | K57: =SUM(K53:K55) -> 0 | M57: =SUM(M53:M55) -> 0 | O57: =SUM(O53:O55) -> 0 | Q57: =SUM(Q53:Q55) -> 0 | S57: =SUM(S53:S55) -> 0
F58: Cost per SF | I58: =I57/#REF! -> #REF! | K58: =K57/#REF! -> #REF! | M58: =M57/#REF! -> #REF! | O58: =O57/#REF! -> #REF! | Q58: =Q57/#REF! -> #REF! | S58: =S57/#REF! -> #REF!
F59: Cost per Unit | I59: =I57/#REF! -> #REF! | K59: =K57/#REF! -> #REF! | M59: =M57/#REF! -> #REF! | O59: =O57/#REF! -> #REF! | Q59: =Q57/#REF! -> #REF! | S59: =S57/#REF! -> #REF!
A61: QUALIFICATIONS
A65: EXCLUSIONS/OWNER PROVIDED ITEMS:
A69: ALTERNATES:
A73: PROPOSED VE (Provide Clear Description):
A77: FULLY LOADED LABOR RATES
B78: Laborer
B79: Mechanic
B80: Superintendent
B81: Project Manager
A83: SCHEDULE
B84: Prepared shop drawings/submittals
B85: Mobilization
B86: Total duration to complete scope of work
A88: Winner
A89: Company
A90: Contact
A91: Phone
A92: Email
A93: Base Bid
B95: Need Prequalification
B96: Prequalified

Sheet 03A Concrete
G1: Hedrick Plug | K1: BO | O1: BO
F2: X | G2: Excluded
B3: BACK TO SUMMARY SHEET | F3: I | G3: Included | H3: Bidder 1 | J3: Bidder 1 | L3: Bidder 2 | N3: Bidder 2 | P3: Bidder2 | R3: Bidder 4 | T3: Bidder 5 | V3: Bidder 6
A4: Project: | B4: ='AREA CALC''s'!B4 -> Alton Hilltop Gardens | G4: Company | H4: Formcrete | J4: Formcrete | L4: Starlite | N4: StarliteR1 | P4: KD
A5: Trade: | B5: Concrete | G5: Contact | H5: Mujo | J5: Mujo | L5: Sean Williams | N5: Sean Williams | P5: Eduardo Garay
A6: CSI Code: | B6: 03A | G6: Phone | H6: 954-609-8102 | J6: 954-609-8102 | L6: 561-719-7607 | N6: 561-719-7607 | P6: 954-344-4515
A7: Date: | G7: Email | H7: maksu@formcrete.net | J7: maksu@formcrete.net | L7: <SeWilliams@starlitebuild.com> | N7: <SeWilliams@starlitebuild.com> | P7: egaray@kdconstruction.us
A8: Adjusted Bid | G8: Adjusted Bid | H8: =I133 -> 20470000 | J8: =K133 -> 19780000 | L8: =M133 -> 21013937 | N8: =O133 -> 20077932 | P8: =Q133 -> 22221824 | R8: =S133 -> 0 | T8: =U133 -> 0 | V8: =W133 -> 0
A9: BID DOCUMENTS: | C9: Plan/ Spec. Package | D9: QTY | E9: U/M | F9: Unit Cost | G9: Subtotal | H9: Yes/No | I9: Price | J9: Yes/No | K9: Price | L9: Yes/No | M9: Price | N9: Yes/No | O9: Price | P9: Yes/No | Q9: Price | R9: Yes/No | S9: Price | T9: Yes/No | U9: Price | V9: Yes/No | W9: Price
B10: Plans By Division
B11: =#REF! -> #REF! | C11: P
B12: =#REF! -> #REF! | C12: P
B13: =#REF! -> #REF! | C13: P
B14: =#REF! -> #REF! | C14: P
B15: =#REF! -> #REF! | C15: P
B16: =#REF! -> #REF!
B17: =#REF! -> #REF!
B18: =#REF! -> #REF! | C18: P
B19: =#REF! -> #REF!
B21: Concrete
B22: GENERAL INCLUSIONS
B23: INCLUDES ALL SALES TAX | H23: i | J23: i | L23: i | N23: i | P23: i
B24: ALL HOISTING & RIGGING REQUIRED TO COMPLETE THIS SCOPE | H24: i | J24: i | L24: i | N24: i | P24: i
B25: PROVIDE P&P BONDS | H25: x | I25: {1%} | J25: x | K25: {1%} | L25: x | M25: {1%} | N25: x | O25: {1%} | P25: x | Q25: {1%}
B26: FLORIDA STATE CONTRACTORS LIC. | H26: i | J26: i | L26: i | N26: i | P26: i
B27: GENERAL LIABILITY AND WORKERS COMP. INSURANCE LIMITS | H27: i | J27: i | L27: i | N27: i | P27: i
B28: STATE AND LOCAL TAXES | H28: i | J28: i | L28: i | N28: i | P28: i
B29: COMPASS PREQUALIFIED | H29: x | J29: x | L29: x | N29: x | P29: x
B30: PREQUALIFICATION SCORE
B31: SINGLE PROJECT LIMIT
B32: SPECIFIC TRADE SCOPE OF WORK REQUIREMENTS
B33: BASE BID | O33: 20250000
B35: Water table 7ft -
B36: Residential Buildings | D36: =238146+191025+83615 -> 512786 | E36: SF | F36: 40 | G36: =D36*F36 -> 20511440 | H36: i | I36: 18800000 | J36: i | K36: 18800000 | L36: i | M36: 19820188 | N36: i | P36: i | Q36: =3383974+3896814+3896814+3178716+3191517+3178716 -> 20726551
B37: Clubhouse | D37: 10558 | E37: SF | F37: 44 | G37: =D37*F37 -> 464552 | H37: i | I37: 915000 | J37: i | K37: 915000 | L37: i | M37: 573960 | N37: i | P37: i | Q37: 793623
B38: Garages | D38: 6539 | E38: SF | F38: 42 | G38: =D38*F38 -> 274638 | H38: i | I38: =340000 -> 340000 | J38: i | K38: =340000 -> 340000 | L38: i | M38: 421022 | N38: i | P38: i | Q38: =100188+94197+94199 -> 288584
B39: Maintenance Building | D39: 888 | E39: SF | F39: 42 | G39: =D39*F39 -> 37296 | H39: i | I39: 50000 | J39: i | K39: 50000 | L39: i | M39: 39960 | N39: i | P39: i | Q39: 46012
B40: Pool Pavilion | D40: 1532 | E40: SF | F40: 42 | G40: =D40*F40 -> 64344 | H40: i | I40: 125000 | J40: i | K40: 125000 | L40: i | M40: 126375 | N40: i | P40: i | Q40: 97554
B41: Precast litel aove windows | H41: i | I41: 90000 | J41: i | K41: 90000 | L41: P | M41: =I41 -> 90000 | N41: i | P41: P | Q41: 90000
B42: Site | H42: i | I42: 45000 | J42: i | K42: 45000 | L42: P | M42: =Q42 -> 45000 | N42: i | P42: P | Q42: =I42 -> 45000
B43: Monument sign | D43: 1 | E43: EA | F43: 7000 | G43: =D43*F43 -> 7000 | H43: i | J43: i | L43: P | M43: 10000 | N43: i | P43: P | Q43: 10000
B44: Main gates and fence columns (11) | C44: C3.01, C3.04 | D44: 11 | E44: EA | H44: i | J44: i | L44: P | M44: 2000 | N44: i | P44: P | Q44: 2000
B45: FPL Transformer concrete Pad (2) | C45: C3.01,3,4,56 | D45: 9 | E45: EA | H45: i | J45: i | L45: P | M45: 3000 | N45: i | P45: P | Q45: 3000
B46: Footings for sun shades and seating area | D46: 1 | E46: EA | F46: 11500 | G46: =D46*F46 -> 11500 | H46: i | I46: 25000 | J46: i | K46: 25000 | L46: P | M46: =I46 -> 25000 | N46: i | P46: P | Q46: =M46 -> 25000
B47: Site Trellis footings (4) footings | C47: C3.01 | D47: 4 | E47: EA | H47: i | J47: i | L47: P | M47: 2000 | N47: i | P47: P | Q47: 2000
B48: Pool cabana footings (5x4) 20 Footings | C48: C3.03, 5 | H48: i | J48: i | L48: P | M48: 5000 | N48: i | P48: P | Q48: 5000
B49: Sun shelter footings (4) footings | C49: C3.06 | H49: i | J49: i | L49: P | M49: 1000 | N49: i | P49: P | Q49: 1000
B50: Structure slab at building 5 | L50: P | M50: 10000 | N50: i
B51: Site Bollards | L51: P | M51: 5000 | N51: i
B52: Clubhouse platform | L52: P | M52: 30000 | N52: P | O52: 30000
B53: Compsite wood platform at pool area footings
B54: Residential Buildings | H54: i | J54: i | L54: i | N54: i | P54: i
B55: Concrete | H55: i | J55: i | L55: i | N55: i | P55: i
B56: Excavation for footings, layout and batter boards, formwork | H56: i | J56: i | L56: i | N56: i | P56: i
B57: Reinf., as scheduled/detailed | C57: S2.1.2 | H57: i | J57: i | L57: i | N57: i | P57: i
B58: CIP Footings 5000 PSI | C58: S1.0, S2.1.1 | H58: i | J58: i | L58: i | N58: i | P58: i
B59: Excavation for SOG, compaction, termite treatment and vapor barrier (15mil) | C59: S1.0 | H59: i | J59: i | L59: i | N59: i | P59: i
B60: 6" SOG 3000 PSI, WWF 6x6-W1.4xW1.4 | C60: S2.3.2 | H60: i | J60: i | L60: i | N60: i | P60: i
B61: 6" Tunnel Walls 5000PSI | C61: S4.1.1 | H61: i | J61: i | L61: i | N61: i | P61: i
B62: CIP Elevated slabs 6", 7" 5000 PSI | H62: i | J62: i | L62: i | N62: i | P62: i
B63: PL-1 Precast Lintels (assumed above windows and doors) | C63: 11/S2.1.2,S3.1.3 | H63: i | J63: i | L63: i | N63: i | P63: i
B64: Concrete beams as per schedule | C64: S3.3.1 | H64: i | J64: i | L64: i | N64: i | P64: i
B65: Concrete columns at Building Type II | H65: i | J65: i | L65: i | N65: i | P65: i
B66: Concert Curbs at Roof level | H66: i | J66: i | L66: x | N66: x | P66: x
B67: CIP Stairs w/ nosing | H67: i | J67: i | L67: i | N67: i | P67: i
B68: Concrete caps | C68: S3.1.3 | H68: i | J68: i | L68: i | N68: i | P68: i
B69: Control joints at slab, columns | C69: G/S3.1.4, F,G,H/S3.1.5 | H69: i | J69: i | L69: i | N69: i | P69: i
B70: Install and fill with grout all door frames in masonry walls
B71: Steel | H71: i | J71: i | L71: i | N71: i | P71: i
B72: Steel columns ST-1 4"X4"x1/4" w / head plates 12"x12"x3/4"
B73: Balcony steel columns | H73: i | J73: i | L73: i | N73: i | P73: i
B74: For fireproofing of structural steel members see architectural drawings | H74: x | J74: x | L74: x | N74: x | P74: x
B75: Masonry | H75: i | J75: i | L75: i | N75: i | P75: i
B76: Layout | H76: i | J76: i | L76: i | N76: i | P76: i
B77: 12" CMU walls at balconies and corridors | H77: i | J77: i | L77: i | N77: i | P77: i
B78: 8" CMU walls at balconies and corridors | H78: i | J78: i | L78: i | N78: i | P78: i
B79: Ladder wire/Rebars/Horizontal Reinf. | H79: i | J79: i | L79: i | N79: i | P79: i
B80: Filled cells with Grout 3000 PSI | H80: i | J80: i | L80: i | N80: i | P80: i
B81: Installation and grout door frames | H81: P | I81: 80000 | J81: P | K81: 80000 | L81: P | M81: 80000 | N81: P | O81: 80000 | P81: P | Q81: 80000
B82: Rough Carpentry | H82: i | J82: i | L82: i | N82: i | P82: i
B83: Installation of roof trusses | H83: i | J83: i | L83: i | M83: -282068 | N83: i | O83: -282068 | P83: i
B84: Furnish and install 5/8" CDX FR plywood sheathing | H84: i | J84: i | L84: i | N84: i | P84: i
B85: All require ply wood for soffits and facia | H85: i | J85: i
B86: Clubhouse | H86: i | J86: i | L86: i | N86: i | P86: i
B87: CIP Footings 5000 PSI | H87: i | J87: i | L87: i | N87: i | P87: i
B88: Excavation for SOG, compaction, termite treatment and vapor barrier (15mil) | H88: i | J88: i | L88: i | N88: i | P88: i
B89: 4" SOG 3000 PSI, WWF 6x6-W1.4xW1.4 | H89: i | J89: i | L89: i | N89: i | P89: i
B90: CIP Second floor slabs to be 8" 6000 PSI, reinforced w/ #5@12" O.C | C90: S2.CH.2 | H90: i | J90: i | L90: i | N90: i | P90: i
B91: CIP Stairs w/ nosing | H91: i | J91: i | L91: i | N91: i | P91: i
B92: Steel | H92: i | J92: i | L92: i | N92: i | P92: i
B93: Structural steel columns - no schedule or location provided | H93: i | J93: i | L93: i | N93: i | P93: i
B94: Masonry | H94: i | J94: i | L94: i | N94: i | P94: i
B95: Layout | H95: i | J95: i | L95: i | N95: i | P95: i
B96: 8" CMU walls at balconies and corridors | H96: i | J96: i | L96: i | N96: i | P96: i
B97: Ladder wire/Rebars/Horizontal Reinf. | H97: i | J97: i | L97: i | N97: i | P97: i
B98: Filled cells with Grout 3000 PSI | H98: i | J98: i | L98: i | N98: i | P98: i
B99: Rough Carpentry | H99: i | J99: i | L99: i | N99: i | P99: i
B100: Installation of roof trusses | H100: i | J100: i | L100: i | N100: i | P100: i
B101: Furnish and install 5/8" CDX FR plywood sheathing | H101: i | J101: i | L101: i | N101: i | P101: i
B103: Garages | H103: i | J103: i | L103: i | N103: i | P103: i
...

Sheet 03B Precast Hollow Core
G1: Hedrick Plug
F2: X | G2: Excluded
B3: BACK TO SUMMARY SHEET | F3: I | G3: Included | H3: Bidder1 | J3: Bidder 2 | L3: Bidder 3 | N3: Bidder 4 | P3: Bidder 5 | R3: Bidder 6
A4: Project: | B4: =#REF! -> #REF! | G4: Company
A5: Trade: | B5: Precast Hollow Core | G5: Contact
A6: CSI Code: | B6: 03B | G6: Phone
A7: Date: | G7: Email
A8: Adjusted Bid | G8: Adjusted Bid | H8: =I46 -> 0 | J8: =K46 -> 0 | L8: =M46 -> 0 | N8: =O46 -> 0 | P8: =Q46 -> 0 | R8: =S46 -> 0
A9: BID DOCUMENTS: | C9: Plan/ Spec. Package | D9: QTY | E9: U/M | F9: Unit Cost | G9: Subtotal | H9: Yes/No | I9: Price | J9: Yes/No | K9: Price | L9: Yes/No | M9: Price | N9: Yes/No | O9: Price | P9: Yes/No | Q9: Price | R9: Yes/No | S9: Price
B10: Plans By Division
B11: =#REF! -> #REF! | C11: P
B12: =#REF! -> #REF! | C12: P
B13: =#REF! -> #REF! | C13: P
B14: =#REF! -> #REF! | C14: P
B15: =#REF! -> #REF! | C15: P
B16: =#REF! -> #REF!
B17: =#REF! -> #REF!
B18: =#REF! -> #REF! | C18: P
B19: =#REF! -> #REF!
B21: Precast Hollow Core
B22: GENERAL INCLUSIONS
B23: INCLUDES ALL SALES TAX
B24: ALL HOISTING & RIGGING REQUIRED TO COMPLETE THIS SCOPE
B25: PROVIDE P&P BONDS
B26: FLORIDA STATE CONTRACTORS LIC.
B27: GENERAL LIABILITY AND WORKERS COMP. INSURANCE LIMITS
B28: STATE AND LOCAL TAXES
B29: COMPASS
B30: SPECIFIC TRADE SCOPE OF WORK REQUIREMENTS
B31: BASE BID
B32: Building SF
L34: i
F42: SUBTOTAL | I42: =SUM(I24:I41) -> 0 | K42: =SUM(K24:K41) -> 0 | M42: =SUM(M24:M41) -> 0 | O42: =SUM(O24:O41) -> 0 | Q42: =SUM(Q24:Q41) -> 0 | S42: =SUM(S24:S41) -> 0
F43: BOND RATE | H43: 0 | J43: 0 | L43: 0 | N43: 0 | P43: 0 | R43: 0
F44: BOND AMOUNT | I44: =H43*I42 -> 0 | K44: =J43*K42 -> 0 | M44: =L43*M42 -> 0 | O44: =N43*O42 -> 0 | Q44: =P43*Q42 -> 0 | S44: =R43*S42 -> 0
F46: ADJUSTED TOTAL | I46: =SUM(I42:I44) -> 0 | K46: =SUM(K42:K44) -> 0 | M46: =SUM(M42:M44) -> 0 | O46: =SUM(O42:O44) -> 0 | Q46: =SUM(Q42:Q44) -> 0 | S46: =SUM(S42:S44) -> 0
F47: Cost per SF | I47: =I46/#REF! -> #REF! | K47: =K46/#REF! -> #REF! | M47: =M46/#REF! -> #REF! | O47: =O46/#REF! -> #REF! | Q47: =Q46/#REF! -> #REF! | S47: =S46/#REF! -> #REF!
F48: Cost per Unit | I48: =I46/#REF! -> #REF! | K48: =K46/#REF! -> #REF! | M48: =M46/#REF! -> #REF! | O48: =O46/#REF! -> #REF! | Q48: =Q46/#REF! -> #REF! | S48: =S46/#REF! -> #REF!
A50: QUALIFICATIONS
A54: EXCLUSIONS/OWNER PROVIDED ITEMS:
A58: ALTERNATES:
A62: PROPOSED VE (Provide Clear Description):
A66: FULLY LOADED LABOR RATES
B67: Laborer
B68: Mechanic
B69: Superintendent
B70: Project Manager
A72: SCHEDULE
B73: Prepared shop drawings/submittals
B74: Mobilization
B75: Total duration to complete scope of work
A77: Winner
A78: Company
A79: Contact
A80: Phone
A81: Email
A82: Base Bid
B84: Need Prequalification
B85: Prequalified

Sheet 03C Concrete Tilt Up
G1: Hedrick Plug
F2: X | G2: Excluded
B3: BACK TO SUMMARY SHEET | F3: I | G3: Included | H3: Bidder1 | J3: Bidder 2 | L3: Bidder 3 | N3: Bidder 4 | P3: Bidder 5 | R3: Bidder 6
A4: Project: | B4: =#REF! -> #REF! | G4: Company
A5: Trade: | B5: Concrete Tilt Up | G5: Contact
A6: CSI Code: | B6: 03C | G6: Phone
A7: Date: | G7: Email
A8: Adjusted Bid | G8: Adjusted Bid | H8: =I46 -> 0 | J8: =K46 -> 0 | L8: =M46 -> 0 | N8: =O46 -> 0 | P8: =Q46 -> 0 | R8: =S46 -> 0
A9: BID DOCUMENTS: | C9: Plan/ Spec. Package | D9: QTY | E9: U/M | F9: Unit Cost | G9: Subtotal | H9: Yes/No | I9: Price | J9: Yes/No | K9: Price | L9: Yes/No | M9: Price | N9: Yes/No | O9: Price | P9: Yes/No | Q9: Price | R9: Yes/No | S9: Price
B10: Plans By Division
B11: =#REF! -> #REF! | C11: P
B12: =#REF! -> #REF! | C12: P
B13: =#REF! -> #REF! | C13: P
B14: =#REF! -> #REF! | C14: P
B15: =#REF! -> #REF! | C15: P
B16: =#REF! -> #REF!
B17: =#REF! -> #REF!
B18: =#REF! -> #REF! | C18: P
B19: =#REF! -> #REF!
B21: Concrete Tilt Up
B22: GENERAL INCLUSIONS
B23: INCLUDES ALL SALES TAX
B24: ALL HOISTING & RIGGING REQUIRED TO COMPLETE THIS SCOPE
B25: PROVIDE P&P BONDS
B26: FLORIDA STATE CONTRACTORS LIC.
B27: GENERAL LIABILITY AND WORKERS COMP. INSURANCE LIMITS
B28: STATE AND LOCAL TAXES
B29: COMPASS
B30: SPECIFIC TRADE SCOPE OF WORK REQUIREMENTS
B31: BASE BID
B32: Building SF
L34: i
F42: SUBTOTAL | I42: =SUM(I24:I41) -> 0 | K42: =SUM(K24:K41) -> 0 | M42: =SUM(M24:M41) -> 0 | O42: =SUM(O24:O41) -> 0 | Q42: =SUM(Q24:Q41) -> 0 | S42: =SUM(S24:S41) -> 0
F43: BOND RATE | H43: 0 | J43: 0 | L43: 0 | N43: 0 | P43: 0 | R43: 0
F44: BOND AMOUNT | I44: =H43*I42 -> 0 | K44: =J43*K42 -> 0 | M44: =L43*M42 -> 0 | O44: =N43*O42 -> 0 | Q44: =P43*Q42 -> 0 | S44: =R43*S42 -> 0
F46: ADJUSTED TOTAL | I46: =SUM(I42:I44) -> 0 | K46: =SUM(K42:K44) -> 0 | M46: =SUM(M42:M44) -> 0 | O46: =SUM(O42:O44) -> 0 | Q46: =SUM(Q42:Q44) -> 0 | S46: =SUM(S42:S44) -> 0
F47: Cost per SF | I47: =I46/#REF! -> #REF! | K47: =K46/#REF! -> #REF! | M47: =M46/#REF! -> #REF! | O47: =O46/#REF! -> #REF! | Q47: =Q46/#REF! -> #REF! | S47: =S46/#REF! -> #REF!
F48: Cost per Unit | I48: =I46/#REF! -> #REF! | K48: =K46/#REF! -> #REF! | M48: =M46/#REF! -> #REF! | O48: =O46/#REF! -> #REF! | Q48: =Q46/#REF! -> #REF! | S48: =S46/#REF! -> #REF!
A50: QUALIFICATIONS
A54: EXCLUSIONS/OWNER PROVIDED ITEMS:
A58: ALTERNATES:
A62: PROPOSED VE (Provide Clear Description):
A66: FULLY LOADED LABOR RATES
B67: Laborer
B68: Mechanic
B69: Superintendent
B70: Project Manager
A72: SCHEDULE
B73: Prepared shop drawings/submittals
B74: Mobilization
B75: Total duration to complete scope of work
A77: Winner
A78: Company
A79: Contact
A80: Phone
A81: Email
A82: Base Bid
B84: Need Prequalification
B85: Prequalified

Sheet 03D Structural Precast
G1: Hedrick Plug
F2: X | G2: Excluded
B3: BACK TO SUMMARY SHEET | F3: I | G3: Included | H3: Bidder1 | J3: Bidder 2 | L3: Bidder 3 | N3: Bidder 4 | P3: Bidder 5 | R3: Bidder 6
A4: Project: | B4: =#REF! -> #REF! | G4: Company
A5: Trade: | B5: Structural Precast | G5: Contact
A6: CSI Code: | B6: 03D | G6: Phone
A7: Date: | G7: Email
A8: Adjusted Bid | G8: Adjusted Bid | H8: =I96 -> 0 | J8: =K96 -> 0 | L8: =M96 -> 0 | N8: =O96 -> 0 | P8: =Q96 -> 0 | R8: =S96 -> 0
A9: BID DOCUMENTS: | C9: Plan/ Spec. Package | D9: QTY | E9: U/M | F9: Unit Cost | G9: Subtotal | H9: Yes/No | I9: Price | J9: Yes/No | K9: Price | L9: Yes/No | M9: Price | N9: Yes/No | O9: Price | P9: Yes/No | Q9: Price | R9: Yes/No | S9: Price
B10: Plans By Division
B11: =#REF! -> #REF! | C11: P
B12: =#REF! -> #REF! | C12: P
B13: =#REF! -> #REF! | C13: P
B14: =#REF! -> #REF! | C14: P
B15: =#REF! -> #REF! | C15: P
B16: =#REF! -> #REF!
B17: =#REF! -> #REF!
B18: =#REF! -> #REF! | C18: P
B19: =#REF! -> #REF!
B21: Structural Precast
B22: GENERAL INCLUSIONS
B23: INCLUDES ALL SALES TAX
B24: ALL HOISTING & RIGGING REQUIRED TO COMPLETE THIS SCOPE
B25: PROVIDE P&P BONDS
B26: FLORIDA STATE CONTRACTORS LIC.
B27: GENERAL LIABILITY AND WORKERS COMP. INSURANCE LIMITS
B28: STATE AND LOCAL TAXES
B29: COMPASS
B30: SPECIFIC TRADE SCOPE OF WORK REQUIREMENTS
B31: BASE BID
B32: Building SF
... B41: Dumpster Enclosure
B42: Monument Sign - | H42: i
B44: SLAB-ON-GRADE
B45: 5" Slab w/ WWF 6x6 w.2.9xw2.9
B46: a. Soil poisoning and pre-treat
B47: b. Fine grading building pad
B48: d. F&I rebar, as per plans
B49: e. F&I wire mesh, as per plans
B50: f. 4,000 PSI
B51: g. Sawcut constr. / control joints
B52: h. Finish slab to FF25/FL17
B53: i. Leave out strip, compact
B54: j. Patch slab after tilt operations
B55: k. Provide curing compound
... B85: Panel structural engineering
F92: SUBTOTAL | I92: =SUM(I24:I91) -> 0 | K92: =SUM(K24:K91) -> 0 | M92: =SUM(M24:M91) -> 0 | O92: =SUM(O24:O91) -> 0 | Q92: =SUM(Q24:Q91) -> 0 | S92: =SUM(S24:S91) -> 0
F93: BOND RATE | H93: 0 | J93: 0 | L93: 0 | N93: 0 | P93: 0 | R93: 0
F94: BOND AMOUNT | I94: =H93*I92 -> 0 | K94: =J93*K92 -> 0 | M94: =L93*M92 -> 0 | O94: =N93*O92 -> 0 | Q94: =P93*Q92 -> 0 | S94: =R93*S92 -> 0
F96: ADJUSTED TOTAL | I96: =SUM(I92:I94) -> 0 | K96: =SUM(K92:K94) -> 0 | M96: =SUM(M92:M94) -> 0 | O96: =SUM(O92:O94) -> 0 | Q96: =SUM(Q92:Q94) -> 0 | S96: =SUM(S92:S94) -> 0
F97: Cost per SF | I97: =I96/#REF! -> #REF! | K97: =K96/#REF! -> #REF! | M97: =M96/#REF! -> #REF! | O97: =O96/#REF! -> #REF! | Q97: =Q96/#REF! -> #REF! | S97: =S96/#REF! -> #REF!
F98: Cost per Unit | I98: =I96/#REF! -> #REF! | K98: =K96/#REF! -> #REF! | M98: =M96/#REF! -> #REF! | O98: =O96/#REF! -> #REF! | Q98: =Q96/#REF! -> #REF! | S98: =S96/#REF! -> #REF!
A100: QUALIFICATIONS
A104: EXCLUSIONS/OWNER PROVIDED ITEMS:
A108: ALTERNATES:
A112: PROPOSED VE (Provide Clear Description):
A116: FULLY LOADED LABOR RATES
B117: Laborer
B118: Mechanic
B119: Superintendent
B120: Project Manager
A122: SCHEDULE
B123: Prepared shop drawings/submittals
B124: Mobilization
B125: Total duration to complete scope of work
A127: Winner
A128: Company
A129: Contact
A130: Phone
A131: Email
A132: Base Bid
B134: Need Prequalification
B135: Prequalified

Sheet 03E Cranes and Hoisting
G1: Hedrick Plug
F2: X | G2: Excluded
B3: BACK TO SUMMARY SHEET | F3: I | G3: Included | H3: Bidder1 | J3: Bidder 2 | L3: Bidder 3 | N3: Bidder 4 | P3: Bidder 5 | R3: Bidder 6
A4: Project: | B4: =#REF! -> #REF! | G4: Company
A5: Trade: | B5: Cranes and Hoisting | G5: Contact
A6: CSI Code: | B6: 03E | G6: Phone
A7: Date: | G7: Email
A8: Adjusted Bid | G8: Adjusted Bid | H8: =I96 -> 0 | J8: =K96 -> 0 | L8: =M96 -> 0 | N8: =O96 -> 0 | P8: =Q96 -> 0 | R8: =S96 -> 0
A9: BID DOCUMENTS: | C9: Plan/ Spec. Package | D9: QTY | E9: U/M | F9: Unit Cost | G9: Subtotal | H9: Yes/No | I9: Price | J9: Yes/No | K9: Price | L9: Yes/No | M9: Price | N9: Yes/No | O9: Price | P9: Yes/No | Q9: Price | R9: Yes/No | S9: Price
B10: Plans By Division
B11: =#REF! -> #REF! | C11: P
B12: =#REF! -> #REF! | C12: P
B13: =#REF! -> #REF! | C13: P
B14: =#REF! -> #REF! | C14: P
B15: =#REF! -> #REF! | C15: P
B16: =#REF! -> #REF!
B17: =#REF! -> #REF!
B18: =#REF! -> #REF! | C18: P
B19: =#REF! -> #REF!
B21: Cranes and Hoisting
B22: GENERAL INCLUSIONS
B23: INCLUDES ALL SALES TAX
B24: ALL HOISTING & RIGGING REQUIRED TO COMPLETE THIS SCOPE
B25: PROVIDE P&P BONDS
B26: FLORIDA STATE CONTRACTORS LIC.
B27: GENERAL LIABILITY AND WORKERS COMP. INSURANCE LIMITS
B28: STATE AND LOCAL TAXES
B29: COMPASS
B30: SPECIFIC TRADE SCOPE OF WORK REQUIREMENTS
B31: BASE BID
B32: Building SF
... B41: Dumpster Enclosure
B42: Monument Sign - | H42: i
B44: SLAB-ON-GRADE
B45: 5" Slab w/ WWF 6x6 w.2.9xw2.9
B46: a. Soil poisoning and pre-treat
B47: b. Fine grading building pad
B48: d. F&I rebar, as per plans
B49: e. F&I wire mesh, as per plans
B50: f. 4,000 PSI
B51: g. Sawcut constr. / control joints
B52: h. Finish slab to FF25/FL17
B53: i. Leave out strip, compact
B54: j. Patch slab after tilt operations
B55: k. Provide curing compound
... B85: Panel structural engineering
F92: SUBTOTAL | I92: =SUM(I24:I91) -> 0 | K92: =SUM(K24:K91) -> 0 | M92: =SUM(M24:M91) -> 0 | O92: =SUM(O24:O91) -> 0 | Q92: =SUM(Q24:Q91) -> 0 | S92: =SUM(S24:S91) -> 0
F93: BOND RATE | H93: 0 | J93: 0 | L93: 0 | N93: 0 | P93: 0 | R93: 0
F94: BOND AMOUNT | I94: =H93*I92 -> 0 | K94: =J93*K92 -> 0 | M94: =L93*M92 -> 0 | O94: =N93*O92 -> 0 | Q94: =P93*Q92 -> 0 | S94: =R93*S92 -> 0
F96: ADJUSTED TOTAL | I96: =SUM(I92:I94) -> 0 | K96: =SUM(K92:K94) -> 0 | M96: =SUM(M92:M94) -> 0 | O96: =SUM(O92:O94) -> 0 | Q96: =SUM(Q92:Q94) -> 0 | S96: =SUM(S92:S94) -> 0
F97: Cost per SF | I97: =I96/#REF! -> #REF! | K97: =K96/#REF! -> #REF! | M97: =M96/#REF! -> #REF! | O97: =O96/#REF! -> #REF! | Q97: =Q96/#REF! -> #REF! | S97: =S96/#REF! -> #REF!
F98: Cost per Unit | I98: =I96/#REF! -> #REF! | K98: =K96/#REF! -> #REF! | M98: =M96/#REF! -> #REF! | O98: =O96/#REF! -> #REF! | Q98: =Q96/#REF! -> #REF! | S98: =S96/#REF! -> #REF!
A100: QUALIFICATIONS
A104: EXCLUSIONS/OWNER PROVIDED ITEMS:
A108: ALTERNATES:
A112: PROPOSED VE (Provide Clear Description):
A116: FULLY LOADED LABOR RATES
B117: Laborer
B118: Mechanic
B119: Superintendent
B120: Project Manager
A122: SCHEDULE
B123: Prepared shop drawings/submittals
B124: Mobilization
B125: Total duration to complete scope of work
A127: Winner
A128: Company
A129: Contact
A130: Phone
A131: Email
A132: Base Bid
B134: Need Prequalification
B135: Prequalified

Sheet 03F Concrete Restoration
G1: Hedrick Plug
F2: X | G2: Excluded
B3: BACK TO SUMMARY SHEET | F3: I | G3: Included | H3: Bidder1 | J3: Bidder 2 | L3: Bidder 3 | N3: Bidder 4 | P3: Bidder 5 | R3: Bidder 6
A4: Project: | B4: =#REF! -> #REF! | G4: Company
A5: Trade: | B5: Concrete Restoration | G5: Contact
A6: CSI Code: | B6: 03F | G6: Phone
A7: Date: | G7: Email
A8: Adjusted Bid | G8: Adjusted Bid | H8: =I96 -> 0 | J8: =K96 -> 0 | L8: =M96 -> 0 | N8: =O96 -> 0 | P8: =Q96 -> 0 | R8: =S96 -> 0
A9: BID DOCUMENTS: | C9: Plan/ Spec. Package | D9: QTY | E9: U/M | F9: Unit Cost | G9: Subtotal | H9: Yes/No | I9: Price | J9: Yes/No | K9: Price | L9: Yes/No | M9: Price | N9: Yes/No | O9: Price | P9: Yes/No | Q9: Price | R9: Yes/No | S9: Price
B10: Plans By Division
B11: =#REF! -> #REF! | C11: P
B12: =#REF! -> #REF! | C12: P
B13: =#REF! -> #REF! | C13: P
B14: =#REF! -> #REF! | C14: P
B15: =#REF! -> #REF! | C15: P
B16: =#REF! -> #REF!
B17: =#REF! -> #REF!
B18: =#REF! -> #REF! | C18: P
B19: =#REF! -> #REF!
B21: Concrete Restoration
B22: GENERAL INCLUSIONS
B23: INCLUDES ALL SALES TAX
B24: ALL HOISTING & RIGGING REQUIRED TO COMPLETE THIS SCOPE
B25: PROVIDE P&P BONDS
B26: FLORIDA STATE CONTRACTORS LIC.
B27: GENERAL LIABILITY AND WORKERS COMP. INSURANCE LIMITS
B28: STATE AND LOCAL TAXES
B29: COMPASS
B30: SPECIFIC TRADE SCOPE OF WORK REQUIREMENTS
B31: BASE BID
B32: Building SF
... B41: Dumpster Enclosure
B42: Monument Sign - | H42: i
B44: SLAB-ON-GRADE
B45: 5" Slab w/ WWF 6x6 w.2.9xw2.9
B46: a. Soil poisoning and pre-treat
B47: b. Fine grading building pad
B48: d. F&I rebar, as per plans
B49: e. F&I wire mesh, as per plans
B50: f. 4,000 PSI
B51: g. Sawcut constr. / control joints
B52: h. Finish slab to FF25/FL17
B53: i. Leave out strip, compact
B54: j. Patch slab after tilt operations
B55: k. Provide curing compound
... B85: Panel structural engineering
F92: SUBTOTAL | I92: =SUM(I24:I91) -> 0 | K92: =SUM(K24:K91) -> 0 | M92: =SUM(M24:M91) -> 0 | O92: =SUM(O24:O91) -> 0 | Q92: =SUM(Q24:Q91) -> 0 | S92: =SUM(S24:S91) -> 0
F93: BOND RATE | H93: 0 | J93: 0 | L93: 0 | N93: 0 | P93: 0 | R93: 0
F94: BOND AMOUNT | I94: =H93*I92 -> 0 | K94: =J93*K92 -> 0 | M94: =L93*M92 -> 0 | O94: =N93*O92 -> 0 | Q94: =P93*Q92 -> 0 | S94: =R93*S92 -> 0
F96: ADJUSTED TOTAL | I96: =SUM(I92:I94) -> 0 | K96: =SUM(K92:K94) -> 0 | M96: =SUM(M92:M94) -> 0 | O96: =SUM(O92:O94) -> 0 | Q96: =SUM(Q92:Q94) -> 0 | S96: =SUM(S92:S94) -> 0
F97: Cost per SF | I97: =I96/#REF! -> #REF! | K97: =K96/#REF! -> #REF! | M97: =M96/#REF! -> #REF! | O97: =O96/#REF! -> #REF! | Q97: =Q96/#REF! -> #REF! | S97: =S96/#REF! -> #REF!
F98: Cost per Unit | I98: =I96/#REF! -> #REF! | K98: =K96/#REF! -> #REF! | M98: =M96/#REF! -> #REF! | O98: =O96/#REF! -> #REF! | Q98: =Q96/#REF! -> #REF! | S98: =S96/#REF! -> #REF!
A100: QUALIFICATIONS
A104: EXCLUSIONS/OWNER PROVIDED ITEMS:
A108: ALTERNATES:
A112: PROPOSED VE (Provide Clear Description):
A116: FULLY LOADED LABOR RATES
B117: Laborer
B118: Mechanic
B119: Superintendent
B120: Project Manager
A122: SCHEDULE
B123: Prepared shop drawings/submittals
B124: Mobilization
B125: Total duration to complete scope of work
A127: Winner
A128: Company
A129: Contact
A130: Phone
A131: Email
A132: Base Bid
B134: Need Prequalification
B135: Prequalified

Sheet 04A Masonry
G1: Hedrick Plug
F2: X | G2: Excluded
B3: BACK TO SUMMARY SHEET | F3: I | G3: Included | H3: Bidder1 | J3: Bidder 2 | L3: Bidder 3 | N3: Bidder 4 | P3: Bidder 5 | R3: Bidder 6
A4: Project: | B4: ='AREA CALC''s'!B4 -> Alton Hilltop Gardens | G4: Company
A5: Trade: | B5: Masonry | G5: Contact
A6: CSI Code: | B6: 04A | G6: Phone
A7: Date: | G7: Email
A8: Adjusted Bid | G8: Adjusted Bid | H8: =I91 -> 0 | J8: =K91 -> 0 | L8: =M91 -> 0 | N8: =O91 -> 0 | P8: =Q91 -> 0 | R8: =S91 -> 0
A9: BID DOCUMENTS: | C9: Plan/ Spec. Package | D9: QTY | E9: U/M | F9: Unit Cost | G9: Subtotal | H9: Yes/No | I9: Price | J9: Yes/No | K9: Price | L9: Yes/No | M9: Price | N9: Yes/No | O9: Price | P9: Yes/No | Q9: Price | R9: Yes/No | S9: Price
B10: Plans By Division
B11: =#REF! -> #REF! | C11: P
B12: =#REF! -> #REF! | C12: P
B13: =#REF! -> #REF! | C13: P
B14: =#REF! -> #REF! | C14: P
B15: =#REF! -> #REF! | C15: P
B16: =#REF! -> #REF!
B17: =#REF! -> #REF!
B18: =#REF! -> #REF! | C18: P
B19: =#REF! -> #REF!
B21: Masonry
B22: GENERAL INCLUSIONS
B23: INCLUDES ALL SALES TAX
B24: ALL HOISTING & RIGGING REQUIRED TO COMPLETE THIS SCOPE
B25: PROVIDE P&P BONDS
B26: FLORIDA STATE CONTRACTORS LIC.
B27: GENERAL LIABILITY AND WORKERS COMP. INSURANCE LIMITS
B28: STATE AND LOCAL TAXES
B29: COMPASS
B30: SPECIFIC TRADE SCOPE OF WORK REQUIREMENTS
B31: BASE BID
B32: Building SF
... B39: e. Horizontal Reinf.
B40: f. Lintels, ladder wire and accessories | H40: i
B41: g. Setting of Joist Embeds & door frames
B42: h. Above scope included for:
B43: 1)
B44: 2)
B45: 3)
F87: SUBTOTAL | I87: =SUM(I24:I86) -> 0 | K87: =SUM(K24:K86) -> 0 | M87: =SUM(M24:M86) -> 0 | O87: =SUM(O24:O86) -> 0 | Q87: =SUM(Q24:Q86) -> 0 | S87: =SUM(S24:S86) -> 0
F88: BOND RATE | H88: 0 | J88: 0 | L88: 0 | N88: 0 | P88: 0 | R88: 0
F89: BOND AMOUNT | I89: =H88*I87 -> 0 | K89: =J88*K87 -> 0 | M89: =L88*M87 -> 0 | O89: =N88*O87 -> 0 | Q89: =P88*Q87 -> 0 | S89: =R88*S87 -> 0
F91: ADJUSTED TOTAL | I91: =SUM(I87:I89) -> 0 | K91: =SUM(K87:K89) -> 0 | M91: =SUM(M87:M89) -> 0 | O91: =SUM(O87:O89) -> 0 | Q91: =SUM(Q87:Q89) -> 0 | S91: =SUM(S87:S89) -> 0
F92: Cost per SF | I92: =I91/#REF! -> #REF! | K92: =K91/#REF! -> #REF! | M92: =M91/#REF! -> #REF! | O92: =O91/#REF! -> #REF! | Q92: =Q91/#REF! -> #REF! | S92: =S91/#REF! -> #REF!
F93: Cost per Unit | I93: =I91/#REF! -> #REF! | K93: =K91/#REF! -> #REF! | M93: =M91/#REF! -> #REF! | O93: =O91/#REF! -> #REF! | Q93: =Q91/#REF! -> #REF! | S93: =S91/#REF! -> #REF!
A95: QUALIFICATIONS
A99: EXCLUSIONS/OWNER PROVIDED ITEMS:
A103: ALTERNATES:
A107: PROPOSED VE (Provide Clear Description):
A111: FULLY LOADED LABOR RATES
B112: Laborer
B113: Mechanic
B114: Superintendent
B115: Project Manager
A117: SCHEDULE
B118: Prepared shop drawings/submittals
B119: Mobilization
B120: Total duration to complete scope of work
A122: Winner
A123: Company
A124: Contact
A125: Phone
A126: Email
A127: Base Bid
B129: Need Prequalification
B130: Prequalified

Sheet 03C Architectural Precast
G1: Hedrick Plug | N1: =N8-H8 -> -253772
F2: X | G2: Excluded | J2: offered the VE | L2: working on prefinished | N2: VE option stone finish
B3: BACK TO SUMMARY SHEET | F3: I | G3: Included | H3: Bidder 1 | J3: Bidder 2 | L3: Bidder 3 | N3: Bidder 3 | P3: Bidder 4 | R3: Bidder 5 | T3: Bidder 6
A4: Project: | B4: ='AREA CALC''s'!B4 -> Alton Hilltop Gardens | G4: Company | H4: Signature Privacy Walls | J4: Perma Cast | L4: Wall Way Corporation | N4: Wall Way Corporation | P4: American Eagle Fence LLC | R4: Cast Stone International
A5: Trade: | B5: Architectural Precast | G5: Contact | H5: Nick Solomon | J5: Chris Borkowski | L5: Mohammad Dadullah | N5: Mohammad Dadullah | P5: Jim Foster | R5: Patrick Barrera
A6: CSI Code: | B6: 03C | G6: Phone | H6: 727-458-0018 | J6: 941-415-2665 | L6: 305-888-8998 | N6: 305-888-8998 | P6: 850-502-8360 | R6: 561-227-8684
A7: Date: | G7: Email | H7: nick@signatureprivacywalls.com | J7: <chris@permacastwalls.com> | L7: <mdadullah@yahoo.com> | N7: <mdadullah@yahoo.com> | P7: jfoster@ameaglefence.com | R7: bids@caststoneinternational.com
A8: Adjusted Bid | G8: Adjusted Bid | H8: =I52 -> 368772 | J8: =K52 -> 409660 | L8: =M52 -> 419940 | N8: =O52 -> 115000 | P8: =Q52 -> 0 | R8: =S52 -> 0 | T8: =U52 -> 0
A9: BID DOCUMENTS: | C9: Plan/ Spec. Package | D9: QTY | E9: U/M | F9: Unit Cost | G9: Subtotal | H9: Yes/No | I9: Price | J9: Yes/No | K9: Price | L9: Yes/No | M9: Price | N9: Yes/No | O9: Price | P9: Yes/No | Q9: Price | R9: Yes/No | S9: Price | T9: Yes/No | U9: Price
B10: Plans By Division
B11: =#REF! -> #REF! | C11: P
B12: =#REF! -> #REF! | C12: P
B13: =#REF! -> #REF! | C13: P
B14: =#REF! -> #REF! | C14: P
B15: =#REF! -> #REF! | C15: P
B16: =#REF! -> #REF!
B17: =#REF! -> #REF!
B18: =#REF! -> #REF! | C18: P
B19: =#REF! -> #REF!
B21: Architectural Precast
B22: GENERAL INCLUSIONS
B23: INCLUDES ALL SALES TAX | H23: i | J23: i | L23: i | N23: i
B24: ALL HOISTING & RIGGING REQUIRED TO COMPLETE THIS SCOPE | H24: i | J24: i | L24: i | N24: i
B25: PROVIDE P&P BONDS | H25: x | J25: x | L25: x | N25: x
B26: FLORIDA STATE CONTRACTORS LIC. | H26: i | J26: i | L26: i | N26: i
B27: GENERAL LIABILITY AND WORKERS COMP. INSURANCE LIMITS | H27: i | J27: i | L27: i | N27: i
B28: STATE AND LOCAL TAXES | H28: i | J28: i | L28: i | N28: i
B29: COMPASS PREQUALIFIED | H29: x | I29: {Not in COMPASS} | J29: x | K29: {Not qualified} | L29: x | M29: {Not in COMPASS} | N29: x | O29: {Not in COMPASS}
B30: PREQUALIFICATION SCORE | H30: x | J30: x | K30: {4.0} | L30: x | N30: x
B31: SINGLE PROJECT LIMIT | H31: x | J31: x | L31: x | N31: x
B32: SPECIFIC TRADE SCOPE OF WORK REQUIREMENTS
B33: BASE BID | I33: =105811+1380+2961+280+900+5500 -> 116832 | K33: 157720 | M33: 168000 | O33: 115000
B34: Building SF
B36: Property 6' post and panel concrete wall (wall 4-1/2" wide) - 980 LF | C36: C3.02, HP 1 of 7 | D36: 980 | E36: LF | F36: 130 | G36: =F36*D36 -> 127400 | H36: i | I36: {20 ft O.C} | J36: i | K36: {20 ft O.C} | L36: i | M36: {8 ft O.C} | N36: i | O36: {5 ft O.C}
B37: 1' wide x 6' Posts for aluminum fence | C37: C3.02, HP 1 of 7 | D37: 14 | E37: EA | F37: 1300 | G37: =F37*D37 -> 18200 | H37: i | J37: i | L37: i | N37: x
B39: Stone veneer finish for wall only - Eldorado Marquee BOTH SIDES | D39: =980*6 -> 5880 | E39: SF | F39: 25 | G39: =F39*D39 -> 147000 | H39: i | I39: =125970*2 -> 251940 | J39: P | K39: =I39 -> 251940 | L39: P | M39: =I39 -> 251940 | N39: i | O39: stone finish
F48: SUBTOTAL | I48: =SUM(I24:I47) -> 368772 | K48: =SUM(K24:K47) -> 409660 | M48: =SUM(M24:M47) -> 419940 | O48: =SUM(O24:O47) -> 115000 | Q48: =SUM(Q24:Q47) -> 0 | S48: =SUM(S24:S47) -> 0 | U48: =SUM(U24:U47) -> 0
F49: BOND RATE | H49: 0 | J49: 0 | L49: 0 | N49: 0 | P49: 0 | R49: 0 | T49: 0
F50: BOND AMOUNT | I50: =H49*I48 -> 0 | K50: =J49*K48 -> 0 | M50: =L49*M48 -> 0 | O50: =N49*O48 -> 0 | Q50: =P49*Q48 -> 0 | S50: =R49*S48 -> 0 | U50: =T49*U48 -> 0
F52: ADJUSTED TOTAL | I52: =SUM(I48:I50) -> 368772 | K52: =SUM(K48:K50) -> 409660 | M52: =SUM(M48:M50) -> 419940 | O52: =SUM(O48:O50) -> 115000 | Q52: =SUM(Q48:Q50) -> 0 | S52: =SUM(S48:S50) -> 0 | U52: =SUM(U48:U50) -> 0
F53: Cost per SF | I53: =I52/#REF! -> #REF! | K53: =K52/#REF! -> #REF! | M53: =M52/#REF! -> #REF! | O53: =O52/#REF! -> #REF! | Q53: =Q52/#REF! -> #REF! | S53: =S52/#REF! -> #REF! | U53: =U52/#REF! -> #REF!
F54: Cost per Unit | I54: =I52/#REF! -> #REF! | K54: =K52/#REF! -> #REF! | M54: =M52/#REF! -> #REF! | O54: =O52/#REF! -> #REF! | Q54: =Q52/#REF! -> #REF! | S54: =S52/#REF! -> #REF! | U54: =U52/#REF! -> #REF!
A56: QUALIFICATIONS
A60: EXCLUSIONS/OWNER PROVIDED ITEMS:
A64: ALTERNATES:
B65: Add column base stone veneer
A68: PROPOSED VE (Provide Clear Description):
B69: Remove one side of stone veneer | H69: i | I69: =-125970 -> -125970
B70: Remove other side of stone veneer | H70: i | I70: =-125970 -> -125970
B71: Alternate wall prefinished | H71: x | J71: i | K71: 174340
A72: FULLY LOADED LABOR RATES
B73: Laborer
B74: Mechanic
B75: Superintendent
B76: Project Manager
A78: SCHEDULE
B79: Prepared shop drawings/submittals
B80: Mobilization
B81: Total duration to complete scope of work
A83: Winner
A84: Company | B84: =H4 -> Signature Privacy Walls
A85: Contact | B85: =H5 -> Nick Solomon
A86: Phone | B86: =H6 -> 727-458-0018
A87: Email | B87: =H7 -> nick@signatureprivacywalls.com | C87: Clubhouse | D87: Garage | E87: Site
A88: Base Bid | B88: =H8 -> 368772
B90: Need Prequalification
B91: Prequalified

Sheet 04B Stone Veneer
G1: Hedrick Plug | L1: pending scupper price | R1: pending scupper price | T1: pending scupper price
F2: X | G2: Excluded | H2: pre-Kast RFI | J2: dated 04.24.26 | N2: dated 04.13.26
B3: BACK TO SUMMARY SHEET | F3: I | G3: Included | H3: Bidder 1 | J3: Bidder 1 | L3: Bidder 2 | N3: Bidder 3 | P3: Bidder 4 | R3: Bidder 5 | T3: Bidder 4
A4: Project: | B4: ='AREA CALC''s'!B4 -> Alton Hilltop Gardens | G4: Company | H4: Titan Stone, LLC | J4: Cast Stone International | L4: Florida Stoneworks LLC | N4: Titan Stone R2 | P4: Liberty Casting Stone | R4: JS Plastering | T4: Marbon
A5: Trade: | B5: Cast Stone, Stone Veneer | G5: Contact | H5: Matthew Teston | J5: Patrick Barrera | L5: Steven Fritz | N5: Matthew Teston | R5: Manuel Castillo | T5: Paul Vassalotti
A6: CSI Code: | B6: 04B | G6: Phone | H6: (954) 662-2553 | J6: 561-625-0333 | L6: 941-217-4040 | N6: (954) 662-2553 | P6: 786-260-7895 | R6: 3217257751 | T6: 561-727-8377
A7: Date: | G7: Email | H7: <mteston@titanstone.com> | J7: bids@caststoneinternational.com | L7: steven.flstone@gmail.com | N7: <mteston@titanstone.com> | P7: wily@libertycastingstone.com | R7: manuel@jsplasteringinc.com | T7: Paul@marbon.com
A8: Adjusted Bid | G8: Adjusted Bid | H8: =I75 -> 67260 | J8: =K75 -> 124582 | L8: =M75 -> 134478.23 | N8: =O75 -> 145510 | P8: =Q75 -> 103406.08 | R8: =S75 -> 147763.09 | T8: =U75 -> 179621.39
A9: BID DOCUMENTS: | C9: Plan/ Spec. Package | D9: QTY | E9: U/M | F9: Unit Cost | G9: Subtotal | H9: Yes/No | I9: Price | J9: Yes/No | K9: Price | L9: Yes/No | M9: Price | N9: Yes/No | O9: Price | P9: Yes/No | Q9: Price
B10: Plans By Division
B11: =#REF! -> #REF! | C11: P
B12: =#REF! -> #REF! | C12: P
B13: =#REF! -> #REF! | C13: P
B14: =#REF! -> #REF! | C14: P
B15: =#REF! -> #REF! | C15: P
B16: =#REF! -> #REF! | C16: P
B17: =#REF! -> #REF! | C17: P
B18: =#REF! -> #REF! | C18: P
B19: =#REF! -> #REF!
B21: Cast Stone, Stone Veneer
B22: GENERAL INCLUSIONS
B23: INCLUDES ALL SALES TAX | H23: i | J23: i | L23: i | N23: i | P23: i | R23: i | T23: i
B24: ALL HOISTING & RIGGING REQUIRED TO COMPLETE THIS SCOPE | H24: i | J24: i | L24: i | N24: i | P24: i | R24: i | T24: i
B25: PROVIDE P&P BONDS | H25: x | I25: {2%} | J25: x | L25: x | N25: x | O25: {2%} | P25: x | R25: x | T25: x | U25: {2%}
B26: FLORIDA STATE CONTRACTORS LIC. | H26: i | J26: i | L26: i | N26: i | P26: i | R26: i | T26: i
B27: GENERAL LIABILITY AND WORKERS COMP. INSURANCE LIMITS | H27: i | J27: i | L27: i | N27: i | P27: i | R27: i | T27: i
B28: STATE AND LOCAL TAXES | H28: i | J28: i | L28: i | N28: i | P28: i | R28: i | T28: i
B29: COMPASS PREQUALIFIED | H29: x | I29: {Not Qualified} | J29: x | L29: x | N29: x | O29: {Not Qualified} | P29: x | R29: x | T29: x
B30: PREQUALIFICATION SCORE | H30: x | J30: x | L30: x | N30: x | P30: x | R30: x | T30: x
B31: SINGLE PROJECT LIMIT | H31: x | J31: x | L31: x | N31: x | P31: x | R31: x | T31: x
B32: SPECIFIC TRADE SCOPE OF WORK REQUIREMENTS
B33: BASE BID
B35: Stone Veneer, Incl.: | H35: i | J35: i | L35: i | N35: i | P35: i | R35: i | T35: i
B36: a. Stone specification - proposed El Dorado Stone Ashland height: 2.5", 7.75"-8", thickness: .688"-.813" | H36: i | J36: i | L36: i | N36: i | P36: i | R36: i | T36: i
B37: b. Labor costs for stocking and installation | H37: i | J37: i | L37: i | N37: i | P37: i | R37: i | T37: i
B38: c. Specified anchors and attachment hardware | H38: i | J38: i | L38: i | N38: i | P38: i | R38: i | T38: i
B39: d. Colored grout? | H39: i | J39: i | L39: i | N39: i | P39: i | R39: i | T39: i
B40: e. Scaffolding and equipment | H40: i | J40: i | K40: 17750 | L40: i | N40: i | P40: i | R40: i | T40: i
B41: f. Delivery costs | H41: i | J41: i | L41: i | N41: i | P41: i | R41: i | T41: i
B42: g. Sales tax included? | H42: i | J42: i | L42: i | N42: i | P42: i | R42: i | T42: i
B43: h. Above scope included for: | H43: i | J43: i | L43: i | N43: i | P43: i | R43: i | T43: i
B45: Supply and install Stone Veneer El Dorado Stone Ashland height: 2.5", 7.75"-8", thickness: .688"-.813" | H45: i | I45: =50600-7000 -> 43600 | J45: i | K45: 43958 | L45: i | M45: =11281.82+1529.64+11146.87+1510.08+11281.82+1529.64+4453.35+602.47+4453.35+602.47 -> 48391.51 | N45: i | O45: 64500 | P45: i | R45: i | T45: i | U45: =(15150+18180)*3+(6300+7560)*2+14400+17280 -> 159390
B46: Building 1 - entrance and wall return | C46: A4.1.2C | D46: 375 | E46: SF | F46: 35 | G46: =F46*D46 -> 13125 | H46: i | J46: i | L46: i | N46: i | P46: i | Q46: =14573.35 -> 14573.35 | R46: i | S46: 13206 | T46: i
B47: Building 2 - entrance and wall return | C47: A4.2.2C | D47: 380 | E47: SF | F47: 35 | G47: =F47*D47 -> 13300 | H47: i | J47: i | L47: i | N47: i | P47: i | Q47: 14221.97 | R47: i | S47: 13206 | T47: i
B48: Building 3- entrance and wall return | C48: A4.3.2C | D48: 380 | E48: SF | F48: 35 | G48: =F48*D48 -> 13300 | H48: i | J48: i | L48: i | N48: i | P48: i | Q48: 15521.41 | R48: i | S48: 13206 | T48: i
B49: Building 4 - entrance and wall return | C49: A4.4.1C | D49: 109 | E49: SF | F49: 35 | G49: =F49*D49 -> 3815 | H49: i | J49: i | L49: i | N49: i | P49: i | Q49: 7101.96 | R49: i | S49: 9324 | T49: i
B50: Building 5 - entrance and wall return | C50: A4.5.1 | D50: 0 | E50: SF | F50: 35 | G50: =F50*D50 -> 0 | H50: i | J50: i | L50: i | N50: i | P50: i | R50: i | T50: i
B51: Building 6 - entrance and wall return | C51: A4.6.1C | D51: 109 | E51: SF | F51: 35 | G51: =F51*D51 -> 3815 | H51: i | J51: i | L51: i | N51: i | P51: i | Q51: 7136.15 | R51: i | S51: 9324 | T51: i
B52: Clubhouse | C52: A4.CH.2 | D52: 390 | E52: SF | F52: 35 | G52: =F52*D52 -> 13650 | H52: i | I52: 14500 | J52: i | K52: 11377 | L52: i | M52: =11011.92+1490.52 -> 12502.44 | N52: i | O52: 18850 | P52: i | Q52: 15346.22 | R52: i | S52: 11393 | T52: i
B53: Stone Veneer Trim | H53: x | J53: i | L53: i | N53: i | P53: i | R53: x | T53: i
A55: KAST PRECON RFI | B55: Planters stone veneer - excluded, RFI response stone veneer OR stucco | H55: x | J55: x | L55: x | N55: x | P55: x | R55: x | T55: x
A56: KAST PRECON RFI | B56: Oolite benches | H56: x | J56: i | K56: 7250 | L56: i | M56: 5962 | N56: i | O56: 4100 | P56: i | Q56: 6771.39 | R56: P | S56: =$Q$56 -> 6771.39 | T56: P | U56: =$Q$56 -> 6771.39
A57: RFI CD-23 | B57: Precast trim around stone veneer entrances Buildings | H57: x | J57: i | K57: =2827+12662+11747 -> 27236 | L57: i | M57: 50274 | N57: i | O57: 35600 | P57: i | Q57: =3088.46+3190.19+3238.62+2408.9+1218.33+2408.9 -> 15553.4 | R57: P | S57: =M57 -> 50274 | T57: i
B58: Precast trim around stone veneer entrances Clubhouse | H58: x | J58: i | K58: =2136 -> 2136 | L58: i | M58: =2432.7+1350+1782+324+3510 -> 9398.7 | N58: i | O58: 8800 | P58: i | Q58: 3117.23 | R58: P | S58: =M58 -> 9398.7 | T58: i
B60: 6' post & panel concrete wall - Site (950 LF)- one side of wall - see Architectural Precast | C60: Sheet 7 of 10 | D60: =950*6 -> 5700 | E60: SF | F60: 35 | G60: =F60*D60 -> 199500 | H60: x | J60: x | L60: x | N60: x | P60: x | R60: x | T60: x
B61: Monument sign | D61: 1 | E61: EA | F61: 2500 | G61: =F61*D61 -> 2500 | H61: i | I61: 2160 | J61: i | K61: 2100 | L61: i | M61: =1592.41+215.17 -> 1807.58 | N61: i | O61: 2160 | P61: P | Q61: =S61 -> 2160 | R61: P | S61: =I61 -> 2160 | T61: i | U61: =1800+2160 -> 3960
B63: MVIS Water proofing - see Titan Stone email 2/24 with spec sheets and details | H63: i | I63: 7000 | J63: P | K63: =I63 -> 7000 | L63: i | N63: i | O63: 7000 | P63: i | R63: P | S63: =I63 -> 7000 | T63: P | U63: =I63 -> 7000
B64: Mortar - qualify color | H64: i | J64: i | L64: i | N64: i | P64: i | R64: i | T64: i
B65: Scratch coat | H65: i | J65: i | L65: i | N65: i | P65: i | R65: i | T65: i
B66: Equipment | H66: i | J66: i | L66: i | N66: i | P66: i | R66: i | T66: i
B67: Cleanup | H67: i | J67: i | L67: i | N67: i | P67: i | R67: i | T67: i
B69: Precast stone scuppers at Building 5 low roof | C69: 1,7/A8.5 | D69: 6 | E69: EA | H69: x | J69: i | K69: 5775 | L69: i | M69: 6142 | N69: i | O69: 4500 | P69: i | Q69: 1903 | R69: P | S69: 2500 | T69: P | U69: 2500
F71: SUBTOTAL | I71: =SUM(I16:I70) -> 67260 | K71: =SUM(K16:K70) -> 124582 | M71: =SUM(M16:M70) -> 134478.23 | O71: =SUM(O16:O70) -> 145510 | Q71: =SUM(Q16:Q70) -> 103406.08 | S71: =SUM(S16:S70) -> 147763.09 | U71: =SUM(U16:U70) -> 179621.39
F72: BOND RATE | H72: 0 | J72: 0 | L72: 0 | N72: 0 | P72: 0 | R72: 0 | T72: 0
F73: BOND AMOUNT | I73: =H72*I71 -> 0 | K73: =J72*K71 -> 0 | M73: =L72*M71 -> 0 | O73: =N72*O71 -> 0 | Q73: =P72*Q71 -> 0 | S73: =R72*S71 -> 0 | U73: =T72*U71 -> 0
F75: ADJUSTED TOTAL | I75: =SUM(I71:I73) -> 67260 | K75: =SUM(K71:K73) -> 124582 | M75: =SUM(M71:M73) -> 134478.23 | O75: =SUM(O71:O73) -> 145510 | Q75: =SUM(Q71:Q73) -> 103406.08 | S75: =SUM(S71:S73) -> 147763.09 | U75: =SUM(U71:U73) -> 179621.39
F76: Cost per SF | I76: =I75/#REF! -> #REF! | K76: =K75/#REF! -> #REF! | M76: =M75/#REF! -> #REF! | O76: =O75/#REF! -> #REF! | Q76: =Q75/#REF! -> #REF! | S76: =S75/#REF! -> #REF! | U76: =U75/#REF! -> #REF!
F77: Cost per Unit | I77: =I75/#REF! -> #REF! | K77: =K75/#REF! -> #REF! | M77: =M75/#REF! -> #REF! | O77: =O75/#REF! -> #REF! | Q77: =Q75/#REF! -> #REF! | S77: =S75/#REF! -> #REF! | U77: =U75/#REF! -> #REF!
A79: QUALIFICATIONS
B80: Exclude waterproofing at exterior wall applied stone veneer
A83: EXCLUSIONS/OWNER PROVIDED ITEMS:
A87: ALTERNATES:
B88: Deduct for stucco bands ilo precast bands at stone veneer (entrances) | J88: i | K88: =-K57-K58 -> -29372 | L88: i | M88: =-M57-M58 -> -59672.7 | N88: i | O88: =-O58-O57 -> -44400
B89: Add for one side of exterior precast wall | H89: i | I89: 151860 | J89: i | K89: 140244 | L89: i | M89: =243368.83/2 -> 121684.41 | N89: i | O89: 151860 | P89: i | Q89: 190910.43
B90: Add for stone veneer at base of gate columns (16 columns) | J90: i | K90: 6100 | L90: i | M90: =7395.26+1001.5 -> 8396.76 | N90: i | O90: 16400
B91: Air and water barrier for one side precast wall | L91: i | M91: =32967.4/2 -> 16483.7
B92: Pool planters stone veneer | L92: i | M92: =4642.28+629.85 -> 5272.13 | P92: i | Q92: 15394.25
A93: PROPOSED VE (Provide Clear Description):
A97: FULLY LOADED LABOR RATES
B98: Laborer
B99: Mechanic
B100: Superintendent
B101: Project Manager
A103: SCHEDULE
B104: Prepared shop drawings/submittals
B105: Mobilization
B106: Total duration to complete scope of work
A108: Winner
A109: Company | B109: =J4 -> Cast Stone International
A110: Contact | B110: =J5 -> Patrick Barrera
A111: Phone | B111: =J6 -> 561-625-0333
A112: Email | B112: =J7 -> bids@caststoneinternational.com | C112: Clubhouse | D112: Garage | E112: Site
A113: Base Bid | B113: =J8-C113-D113-E113 -> 101719 | C113: =K52+K58 -> 13513 | E113: =K61+K56 -> 9350
B115: Need Prequalification
B116: Prequalified

Sheet 05A Structural Steel
G1: Hedrick Plug
F2: X | G2: Excluded
B3: BACK TO SUMMARY SHEET | F3: I | G3: Included | H3: Bidder 1 | J3: Bidder 2 | L3: Bidder 3 | N3: Bidder 4 | P3: Bidder5 | R3: Bidder6
A4: Project: | B4: =#REF! -> #REF! | G4: Company
A5: Trade: | B5: Structural Steel | G5: Contact
A6: CSI Code: | B6: 05A | G6: Phone
A7: Date: | G7: Email
A8: Adjusted Bid | G8: Adjusted Bid | H8: =I56 -> 0 | J8: =K56 -> 0 | L8: =M56 -> 0 | N8: =O56 -> 0 | P8: =Q56 -> 0 | R8: =S56 -> 0
A9: BID DOCUMENTS: | C9: Plan/ Spec. Package | D9: QTY | E9: U/M | F9: Unit Cost | G9: Subtotal | H9: Yes/No | I9: Price | J9: Yes/No | K9: Price | L9: Yes/No | M9: Price | N9: Yes/No | O9: Price | P9: Yes/No | Q9: Price | R9: Yes/No | S9: Price
B10: Plans By Division
B11: =#REF! -> #REF! | C11: P
B12: =#REF! -> #REF! | C12: P
B13: =#REF! -> #REF! | C13: P
B14: =#REF! -> #REF! | C14: P
B15: =#REF! -> #REF! | C15: P
B16: =#REF! -> #REF! | C16: P
B17: =#REF! -> #REF! | C17: P
B18: =#REF! -> #REF! | C18: P
B19: =#REF! -> #REF! | C19: P
B21: Structural Steel
B22: GENERAL INCLUSIONS
B23: INCLUDES ALL SALES TAX
B24: ALL HOISTING & RIGGING REQUIRED TO COMPLETE THIS SCOPE
B25: PROVIDE P&P BONDS
B26: FLORIDA STATE CONTRACTORS LIC.
B27: GENERAL LIABILITY AND WORKERS COMP. INSURANCE LIMITS
B28: STATE AND LOCAL TAXES
B29: COMPASS
B30: SPECIFIC TRADE SCOPE OF WORK REQUIREMENTS
B31: BASE BID
B32: Building SF
... B40: f. Above scope included for:
H44: x
F52: SUBTOTAL | I52: =SUM(I23:I51) -> 0 | K52: =SUM(K23:K51) -> 0 | M52: =SUM(M23:M51) -> 0 | O52: =SUM(O23:O51) -> 0 | Q52: =SUM(Q23:Q51) -> 0 | S52: =SUM(S23:S51) -> 0
F53: BOND RATE | H53: 0 | J53: 0 | L53: 0 | N53: 0 | P53: 0 | R53: 0
F54: BOND AMOUNT | I54: =H53*$I$52 -> 0 | K54: =J53*$I$52 -> 0 | M54: =L53*$I$52 -> 0 | O54: =N53*$I$52 -> 0 | Q54: =P53*$I$52 -> 0 | S54: =R53*$I$52 -> 0
F56: ADJUSTED TOTAL | I56: =SUM(I52:I54) -> 0 | K56: =SUM(K52:K54) -> 0 | M56: =SUM(M52:M54) -> 0 | O56: =SUM(O52:O54) -> 0 | Q56: =SUM(Q52:Q54) -> 0 | S56: =SUM(S52:S54) -> 0
F57: Cost per SF | I57: =I56/#REF! -> #REF! | K57: =K56/#REF! -> #REF! | M57: =M56/#REF! -> #REF! | O57: =O56/#REF! -> #REF! | Q57: =Q56/#REF! -> #REF! | S57: =S56/#REF! -> #REF!
F58: Cost per Unit | I58: =I56/#REF! -> #REF! | K58: =K56/#REF! -> #REF! | M58: =M56/#REF! -> #REF! | O58: =O56/#REF! -> #REF! | Q58: =Q56/#REF! -> #REF! | S58: =S56/#REF! -> #REF!
A60: QUALIFICATIONS
A64: EXCLUSIONS/OWNER PROVIDED ITEMS:
A68: ALTERNATES:
A72: PROPOSED VE (Provide Clear Description):
A76: FULLY LOADED LABOR RATES
B77: Laborer
B78: Mechanic
B79: Superintendent
B80: Project Manager
A82: SCHEDULE
B83: Prepared shop drawings/submittals
B84: Mobilization
B85: Total duration to complete scope of work
A87: Winner
A88: Company
A89: Contact
A90: Phone
A91: Email
A92: Base Bid
B94: Need Prequalification
B95: Prequalified

Sheet 05B Metal Trusses
G1: Hedrick Plug
F2: X | G2: Excluded
B3: BACK TO SUMMARY SHEET | F3: I | G3: Included | H3: Bidder 1 | J3: Bidder 2 | L3: Bidder 3 | N3: Bidder 4 | P3: Bidder 5 | R3: Bidder 6
A4: Project: | B4: =#REF! -> #REF! | G4: Company
A5: Trade: | B5: Metal Trusses | G5: Contact
A6: CSI Code: | B6: 05B | G6: Phone
A7: Date: | G7: Email
A8: Adjusted Bid | G8: Adjusted Bid | H8: =I52 -> 0 | J8: =K52 -> 0 | L8: =M52 -> 0 | N8: =O52 -> 0 | P8: =Q52 -> 0 | R8: =S52 -> 0
A9: BID DOCUMENTS: | C9: Plan/ Spec. Package | D9: QTY | E9: U/M | F9: Unit Cost | G9: Subtotal | H9: Yes/No | I9: Price | J9: Yes/No | K9: Price | L9: Yes/No | M9: Price | N9: Yes/No | O9: Price | P9: Yes/No | Q9: Price | R9: Yes/No | S9: Price
B10: Plans By Division
B11: =#REF! -> #REF! | C11: P
B12: =#REF! -> #REF! | C12: P
B13: =#REF! -> #REF! | C13: P
B14: =#REF! -> #REF! | C14: P
B15: =#REF! -> #REF! | C15: P
B16: =#REF! -> #REF! | C16: P
B17: =#REF! -> #REF! | C17: P
B18: =#REF! -> #REF! | C18: P
B19: =#REF! -> #REF! | C19: P
B21: Metal Trusses
B22: GENERAL INCLUSIONS
B23: INCLUDES ALL SALES TAX
B24: ALL HOISTING & RIGGING REQUIRED TO COMPLETE THIS SCOPE
B25: PROVIDE P&P BONDS
B26: FLORIDA STATE CONTRACTORS LIC.
B27: GENERAL LIABILITY AND WORKERS COMP. INSURANCE LIMITS
B28: STATE AND LOCAL TAXES
B29: COMPASS
B30: SPECIFIC TRADE SCOPE OF WORK REQUIREMENTS
B31: BASE BID
B32: Building SF
B34: Structural Steel , incl.:
B35: a. Equipment, cranes, etc. | H35: i
B36: b. scheduled/detailed shop drawings.
B37: c. Steel Columns, W-Beams, Joists and Metal Decking as scheduled.
B38: d. Steel connections, angle iron, steel beam at elevator.
B39: e. Roof top equipment structural requirements.
B40: f. Above scope included for:
F48: SUBTOTAL | I48: =SUM(I23:I47) -> 0 | K48: =SUM(K23:K47) -> 0 | M48: =SUM(M23:M47) -> 0 | O48: =SUM(O23:O47) -> 0 | Q48: =SUM(Q23:Q47) -> 0 | S48: =SUM(S23:S47) -> 0
F49: BOND RATE | H49: 0 | J49: 0 | L49: 0 | N49: 0 | P49: 0 | R49: 0
F50: BOND AMOUNT | I50: =H49*$I$48 -> 0 | K50: =J49*$K$48 -> 0 | M50: =L49*$K$48 -> 0 | O50: =N49*$K$48 -> 0 | Q50: =P49*$K$48 -> 0 | S50: =R49*$K$48 -> 0
F52: ADJUSTED TOTAL | I52: =SUM(I48:I50) -> 0 | K52: =SUM(K48:K50) -> 0 | M52: =SUM(M48:M50) -> 0 | O52: =SUM(O48:O50) -> 0 | Q52: =SUM(Q48:Q50) -> 0 | S52: =SUM(S48:S50) -> 0
F53: Cost per SF | I53: =I52/#REF! -> #REF! | K53: =K52/#REF! -> #REF! | M53: =M52/#REF! -> #REF! | O53: =O52/#REF! -> #REF! | Q53: =Q52/#REF! -> #REF! | S53: =S52/#REF! -> #REF!
F54: Cost per Unit | I54: =I52/#REF! -> #REF! | K54: =K52/#REF! -> #REF! | M54: =M52/#REF! -> #REF! | O54: =O52/#REF! -> #REF! | Q54: =Q52/#REF! -> #REF! | S54: =S52/#REF! -> #REF!
A56: QUALIFICATIONS
A60: EXCLUSIONS/OWNER PROVIDED ITEMS:
A64: ALTERNATES:
A68: PROPOSED VE (Provide Clear Description):
A72: FULLY LOADED LABOR RATES
B73: Laborer
B74: Mechanic
B75: Superintendent
B76: Project Manager
A78: SCHEDULE
B79: Prepared shop drawings/submittals
B80: Mobilization
B81: Total duration to complete scope of work
A83: Winner
A84: Company
A85: Contact
A86: Phone
A87: Email
A88: Base Bid
B90: Need Prequalification
B91: Prequalified

Sheet 05C Misc. Metals
G1: Hedrick Plug | J1: BO
F2: X | G2: Excluded | J2: dated 04.27.26 | R2: 04.10.26 | T2: incomplete scope | V2: 110% higher
B3: BACK TO SUMMARY SHEET | F3: I | G3: Included | H3: Bidder 1 | J3: Bidder 1 | L3: Bidder 2 | N3: Bidder 3 | P3: Bidder 4 | R3: Bidder 4 | T3: Bidder 5 | V3: Bidder 6
A4: Project: | B4: ='AREA CALC''s'!B4 -> Alton Hilltop Gardens | G4: Company | H4: Pilar Welding | J4: Pilar Welding | L4: Greco Aluminum | N4: Coastal Metal | P4: All American Windows | R4: Bachiller Iron Works | T4: Complete Access | V4: JC Ornamental Works
A5: Trade: | B5: Misc. Metals | G5: Contact | H5: Sarai Campos | J5: Sarai Campos | L5: Chris Jones | N5: Laura Montes | P5: Vicente Fernandez | R5: David A. Rodriguez | T5: Chris Mauro
A6: CSI Code: | B6: 05C | G6: Phone | H6: 561-524-9246 | J6: 561-524-9246 | L6: 727-739-8873 | N6: 561-819-0308 | P6: 954-786-8525 | R6: 305-751-7765 ext 103 | T6: 407-408-4323
A7: Date: | G7: Email | H7: <sara@pilarwelding.com> | J7: <sara@pilarwelding.com> | L7: chris.jones@grecorailings.com | N7: lmontes@coastalmetal.biz | P7: vfernandez@aawimpact.com> | R7: drodriguez@biwiron.com | T7: chris@cacocf.com
A8: Adjusted Bid | G8: Misc Metals | H8: =I73 -> 879361.55 | J8: =K73 -> 813304.82 | L8: =M73 -> 998903 | N8: =O73 -> 1101307 | P8: =Q73 -> 151286.46 | R8: =S73 -> 1070750 | T8: =U73 -> 730889.16 | V8: =W73 -> 1937959.2
G9: Rafter Tails & Brackets | H9: ='05F Brackets & Rafter Tails'!L8 -> 412837.5 | J9: ='05F Brackets & Rafter Tails'!N8 -> 438146.25 | L9: cant price | N9: ='05F Brackets & Rafter Tails'!V8 -> 493453 | P9: included | R9: included below
G10: Awnings, Shutters,etc | H10: ='13C Awnings,Canopies,Shutters'!J8 -> 1038214.3 | J10: ='13C Awnings,Canopies,Shutters'!L8 -> 913200.57 | L10: cant price | N10: ='13C Awnings,Canopies,Shutters'!T8 -> 1153400.3 | P10: ='13C Awnings,Canopies,Shutters'!R8 -> 2125000 | R10: ='13C Awnings,Canopies,Shutters'!X8 -> 1955430
G11: Total | H11: =SUM(H8:I10) -> 2330413.4 | J11: =SUM(J8:K10) -> 2164651.6 | L11: =SUM(L8:M10) -> 998903 | N11: =SUM(N8:O10) -> 2748160.3 | P11: =SUM(P8:Q10) -> 2276286.5 | R11: =SUM(R8:S10) -> 3026180
A12: BID DOCUMENTS: | C12: Plan/ Spec. Package | D12: QTY | E12: U/M | F12: Unit Cost | G12: Subtotal | H12: Yes/No | I12: Price | J12: Yes/No | K12: Price | L12: Yes/No | M12: Price | N12: Yes/No | O12: Price | T12: Yes/No | U12: Price | V12: Yes/No | W12: Price
B13: Plans By Division
B14: =#REF! -> #REF! | C14: P
B15: =#REF! -> #REF! | C15: P
B16: =#REF! -> #REF! | C16: P
B17: =#REF! -> #REF! | C17: P
B18: =#REF! -> #REF! | C18: P
B19: =#REF! -> #REF! | C19: P
B20: =#REF! -> #REF! | C20: P
B21: =#REF! -> #REF! | C21: P
B22: =#REF! -> #REF! | C22: P
B24: Misc. Metals
B25: GENERAL INCLUSIONS
B26: INCLUDES ALL SALES TAX | H26: i | J26: i | L26: i | N26: i | P26: i | R26: i | T26: i | V26: i
B27: ALL HOISTING & RIGGING REQUIRED TO COMPLETE THIS SCOPE | H27: i | J27: i | L27: i | N27: i | P27: i | R27: i | T27: i | V27: i
B28: PROVIDE P&P BONDS | H28: x | J28: x | L28: x | M28: {0.7%} | N28: x | P28: x | R28: x | T28: x | V28: x
B29: FLORIDA STATE CONTRACTORS LIC. | H29: i | J29: i | L29: i | N29: i | P29: i | R29: i | T29: i | V29: i
B30: GENERAL LIABILITY AND WORKERS COMP. INSURANCE LIMITS | H30: i | J30: i | L30: i | N30: i | P30: i | R30: i | T30: i | V30: i
B31: STATE AND LOCAL TAXES | H31: i | J31: i | L31: i | N31: i | P31: i | R31: i | T31: i | V31: i
B32: COMPASS PREQUALIFIED | H32: x | I32: {Not Qualified} | J32: x | K32: {Not Qualified} | L32: x | M32: {Not Qualified} | N32: x | O32: {Denied} | P32: x | Q32: {Not Qualified} | R32: x | S32: {Not Qualified} | T32: i | U32: {Qualified} | V32: x
B33: PREQUALIFICATION SCORE | H33: x | I33: {6.0} | J33: x | K33: {6.0} | L33: x | M33: {4.0} | N33: x | P33: x | Q33: {2.4} | R33: x | S33: {2.4} | T33: i | U33: {6.0} | V33: x
B34: SINGLE PROJECT LIMIT | H34: x | J34: x | L34: x | N34: x | P34: x | R34: x | T34: i | U34: {2,000,000} | V34: x
B35: SPECIFIC TRADE SCOPE OF WORK REQUIREMENTS
B36: BASE BID | K36: 800245 | M36: =874903-12050 -> 862853 | U36: =415608+181850 -> 597458
B38: Acknowledgment of Addendum #1 | H38: i | J38: i | L38: i | N38: i | P38: i | R38: i | T38: i | V38: i
B39: Acknowledgment of Clarifications #1 thru #4 | H39: i | J39: i | L39: i | N39: i | P39: i | R39: i | T39: i | V39: i
B41: Residential Buildings | H41: i | I41: =101280+50220+3795+452880+16500 -> 624675 | J41: i | L41: i | N41: i | O41: =544028+213645 -> 757673 | P41: i | R41: i | S41: =155440+165335+150980+117805+118050+120400 -> 828010 | T41: i | V41: i | W41: =211660+7200+51600+56700+244400+7200+49200+58350+222110+7200+58350+148300+56700+51600+122650+56700+51600+148300+56700+51600 -> 1718120
B42: Building 1 thru 6 | H42: i | J42: i | L42: i | N42: i | P42: i | R42: i | T42: i | V42: i
B43: Stair Railings (Stair #1 and #2) | H43: i | J43: i | L43: i | N43: i | P43: i | R43: i | T43: i | V43: i
B44: Stair Wall mounted hand rail (Stair #1 and #2) | H44: i | J44: i | L44: i | N44: i | P44: i | R44: i | T44: i | V44: i
B45: Stair cane rail (Stair #1 and #2) | H45: i | J45: i | L45: i | N45: i | P45: i | R45: i | T45: i | V45: i
B46: Balcony Railings | H46: i | J46: i | L46: i | N46: i | P46: i | R46: i | T46: i | V46: i
B47: Decorative balcony railing @entrance | H47: i | J47: i | L47: i | N47: i | P47: i | R47: i | T47: i | V47: i
B48: Elevators (pit ladder, sump pit cover) | H48: i | I48: =76050 -> 76050 | J48: i | L48: P | M48: =I48 -> 76050 | N48: i | O48: =133782 -> 133782 | P48: P | Q48: =M48 -> 76050 | R48: i | S48: =41150+41150+41150+13920+13920+13920 -> 165210 | T48: P | U48: =Q48 -> 76050 | V48: P | W48: =I48 -> 76050
B49: Hoist Beams, Safety Beams - furnish only, install by Concrete | H49: i | I49: 43050 | J49: i | L49: P | M49: =I49 -> 43050 | N49: i | P49: =L49 -> P | Q49: =M49 -> 43050 | R49: i | T49: P | U49: =Q49 -> 43050 | V49: P | W49: =I49 -> 43050
B50: Separator Beams - by Concrete | H50: i | J50: i | L50: P | N50: i | P50: i | R50: i | T50: P | V50: P
B52: Clubhouse | H52: i | I52: =12750+1200+1260+2850+7110 -> 25170 | J52: i | L52: i | N52: i | O52: =13698+28290-18810-1295 -> 21883 | P52: i | R52: i | S52: =41335 -> 41335 | T52: x | V52: i | W52: =990+3200+14900+5800+20900 -> 45790
B53: Stair Railings (Stair #1) | C53: A7.CH.1 | D53: 26 | E53: LF | H53: i | J53: i | L53: i | N53: i | P53: i | R53: i | T53: x | V53: i
B54: Stair Wall mounted hand rail (Stair #1 and #2) | C54: A7.CH.2 | D54: =26+28*2 -> 82 | E54: LF | H54: i | J54: i | L54: i | N54: i | P54: i | R54: i | T54: x | V54: i
B55: Railing @entry steps | C55: A7.CH.2 | D55: 15 | E55: LF | H55: i | J55: i | L55: i | N55: i | P55: i | R55: i | T55: x | V55: i
B56: Decorative railing @ Stair #3 Includes balcony railing @ 2nd floor - in Glass railing | C56: A7.CH.3, ID7-01 | D56: 31 | E56: LF | H56: x | J56: x | L56: x | N56: x | P56: x | R56: x | T56: x | V56: x
B57: Decorative balcony railing @ cowork, maker's, fitness terrace | C57: A4.CH.2 | D57: 104 | E57: LF | H57: i | J57: i | L57: i | N57: i | P57: i | R57: i | T57: i | V57: i
B58: HSS and Beams for storefronts - in Concrete | H58: x | J58: x | L58: x | N58: x | P58: x | R58: x | T58: x | U58: cant price | V58: x
B59: Hoist Beams, Safety Beams - furnish only, install by Concrete | D59: 1 | E59: EA | H59: i | I59: =9350 -> 9350 | J59: i | L59: P | M59: =I59 -> 9350 | N59: i | O59: =12172 -> 12172 | P59: P | Q59: =M59 -> 9350 | R59: i | S59: 13920 | T59: x | V59: P | W59: =I59 -> 9350
B60: Separator Beams - furnish only, install by Concrete | D60: 1 | E60: EA | H60: i | J60: i | L60: P | N60: i | P60: i | R60: i | T60: x | U60: cant price | V60: P
B62: Bollards (allowance) - furnish only, concrete sub will install | D62: 30 | E62: EA | H62: i | I62: 7600 | J62: i | L62: P | M62: =I62 -> 7600 | N62: P | O62: =I62 -> 7600 | P62: P | Q62: =M62 -> 7600 | R62: i | T62: x | U62: cant price | V62: P | W62: =I62 -> 7600
B64: Engineering & Shop Drawings | H64: i | I64: 4000 | J64: i | L64: i | N64: i | P64: i | R64: i | T64: i | V64: i
B65: General Conditions | H65: i | I65: 80760 | J65: i | L65: i | N65: i | O65: 168197 | P65: i | R65: i | S65: 22275 | T65: i | V65: i
B66: Taxes | H66: i | J66: i | L66: i | N66: i | P66: i | R66: i | T66: i | V66: i
B68: Stair nosings | H68: x | J68: x | L68: x | N68: x | P68: x | R68: x | V68: x
F69: SUBTOTAL | I69: =SUM(I36:I68) -> 870655 | K69: =SUM(K36:K68) -> 800245 | M69: =SUM(M26:M68) -> 998903 | O69: =SUM(O25:O68) -> 1101307 | Q69: =SUM(Q36:Q68) -> 136050 | S69: =SUM(S36:S68) -> 1070750 | U69: =SUM(U25:U68) -> 716558 | W69: =SUM(W26:W68) -> 1899960
F70: BOND RATE | H70: 0.01 | J70: 0.015 | L70: 0 | N70: 0 | P70: 0.0175 | R70: 0 | T70: 0.02 | V70: 0.02
F71: BOND AMOUNT | I71: =H70*$I$69 -> 8706.55 | K71: =J70*$I$69 -> 13059.825 | M71: =L70*$M$69 -> 0 | O71: =N70*$O$69 -> 0 | Q71: =P70*$I$69 -> 15236.463 | S71: =R70*$I$69 -> 0 | U71: =T70*$U$69 -> 14331.16 | W71: =V70*W69 -> 37999.2
F73: ADJUSTED TOTAL | I73: =SUM(I69:I71) -> 879361.55 | K73: =SUM(K69:K71) -> 813304.82 | M73: =SUM(M69:M71) -> 998903 | O73: =SUM(O69:O71) -> 1101307 | Q73: =SUM(Q69:Q71) -> 151286.46 | S73: =SUM(S69:S71) -> 1070750 | U73: =SUM(U69:U71) -> 730889.16 | W73: =SUM(W69:W71) -> 1937959.2
F74: Cost per SF | I74: =I73/#REF! -> #REF! | K74: =K73/#REF! -> #REF! | M74: =M73/#REF! -> #REF! | O74: =O73/#REF! -> #REF! | Q74: =Q73/#REF! -> #REF! | S74: =S73/#REF! -> #REF! | U74: =U73/#REF! -> #REF! | W74: =W73/#REF! -> #REF!
F75: Cost per Unit | I75: =I73/#REF! -> #REF! | K75: =K73/#REF! -> #REF! | M75: =M73/#REF! -> #REF! | O75: =O73/#REF! -> #REF! | Q75: =Q73/#REF! -> #REF! | S75: =S73/#REF! -> #REF! | U75: =U73/#REF! -> #REF! | W75: =W73/#REF! -> #REF!
A77: QUALIFICATIONS
A81: EXCLUSIONS/OWNER PROVIDED ITEMS:
A85: ALTERNATES:
B86: Add for elevator metal install | K86: 19250 | Q86: 288900 | S86: 288900
A89: PROPOSED VE (Provide Clear Description):
B90: 2-line Hybrid Railing ilo 3-line
B91: 2-line ilo 3-line
B92: Square ends brackets, radius middle
B93: Angled ends for Rafter Tails ilo deco radius
B94: OCIP credit | P94: i | Q94: =-67570 -> -67570 | R94: i | S94: =-67570 -> -67570
A97: FULLY LOADED LABOR RATES
B98: Laborer
B99: Mechanic
B100: Superintendent
B101: Project Manager
A103: SCHEDULE
B104: Prepared shop drawings/submittals
B105: Mobilization
B106: Total duration to complete scope of work
A108: Winner
A109: Company | B109: =H4 -> Pilar Welding
A110: Contact | B110: =H5 -> Sarai Campos
A111: Phone | B111: =H6 -> 561-524-9246
A112: Email | B112: =H7 -> <sara@pilarwelding.com> | C112: Buildings | D112: Clubhouse | E112: Garage | F112: Site
A113: Base Bid | B113: =H8 -> 879361.55
B115: Need Prequalification
B116: Prequalified

Sheet Sheet1
C1: Brackets | D1: Rafter Tails
B2: Building I | C2: =94*3 -> 282 | D2: =48*3 -> 144
B3: Building II | C3: =167*2 -> 334 | D3: =48*2 -> 96
B4: Building III | C4: 145 | D4: 17
B5: Clubhouse | C5: 6 | D5: 71
B6: Garages | C6: 0 | D6: 90
D7: =81*2 -> 162
B8: Maintenance Bldg | C8: 0 | D8: 41
C9: =SUM(C2:C8) -> 767 | D9: =SUM(D2:D8) -> 621

Sheet 05D Handrailings & Railings
G1: Hedrick Plug
F2: X | G2: Excluded
B3: BACK TO SUMMARY SHEET | F3: I | G3: Included | H3: Bidder 1 | J3: Bidder 2 | L3: Bidder 3 | N3: Bidder 4 | P3: Bidder 5 | R3: Bidder 6
A4: Project: | B4: =#REF! -> #REF! | G4: Company
A5: Trade: | B5: Handrailings & Railings | G5: Contact
A6: CSI Code: | B6: 05D | G6: Phone
A7: Date: | G7: Email
A8: Adjusted Bid | G8: Adjusted Bid | H8: =I55 -> 0 | J8: =K55 -> 0 | L8: =M55 -> 0 | N8: =O55 -> 0 | P8: =Q55 -> 0 | R8: =S55 -> 0
A9: BID DOCUMENTS: | C9: Plan/ Spec. Package | D9: QTY | E9: U/M | F9: Unit Cost | G9: Subtotal | H9: Yes/No | I9: Price | J9: Yes/No | K9: Price | L9: Yes/No | M9: Price | N9: Yes/No | O9: Price | P9: Yes/No | Q9: Price | R9: Yes/No | S9: Price
B10: Plans By Division
B11: =#REF! -> #REF! | C11: P
B12: =#REF! -> #REF! | C12: P
B13: =#REF! -> #REF! | C13: P
B14: =#REF! -> #REF! | C14: P
B15: =#REF! -> #REF! | C15: P
B16: =#REF! -> #REF! | C16: P
B17: =#REF! -> #REF! | C17: P
B18: =#REF! -> #REF! | C18: P
B19: =#REF! -> #REF! | C19: P
B21: Handrailings & Railings
B22: GENERAL INCLUSIONS
B23: INCLUDES ALL SALES TAX
B24: ALL HOISTING & RIGGING REQUIRED TO COMPLETE THIS SCOPE
B25: PROVIDE P&P BONDS
B26: FLORIDA STATE CONTRACTORS LIC.
B27: GENERAL LIABILITY AND WORKERS COMP. INSURANCE LIMITS
B28: STATE AND LOCAL TAXES
B29: COMPASS
B30: SPECIFIC TRADE SCOPE OF WORK REQUIREMENTS
B31: BASE BID
F51: SUBTOTAL | I51: =SUM(I23:I50) -> 0 | K51: =SUM(K23:K50) -> 0 | M51: =SUM(M22:M50) -> 0 | O51: =SUM(O22:O50) -> 0 | Q51: =SUM(Q23:Q50) -> 0 | S51: =SUM(S23:S50) -> 0
F52: BOND RATE | H52: 0 | J52: 0 | L52: 0.02 | N52: 0.02 | P52: 0.02 | R52: 0.02
F53: BOND AMOUNT | I53: =H52*$I$51 -> 0 | K53: =J52*$K$51 -> 0 | M53: =L52*$M$51 -> 0 | O53: =N52*$O$51 -> 0 | Q53: =P52*$Q$51 -> 0 | S53: =R52*S51 -> 0
F55: ADJUSTED TOTAL | I55: =SUM(I51:I54) -> 0 | K55: =SUM(K51:K53) -> 0 | M55: =SUM(M51:M53) -> 0 | O55: =SUM(O51:O53) -> 0 | Q55: =SUM(Q51:Q53) -> 0 | S55: =SUM(S51:S53) -> 0
F56: Cost per SF | I56: =I55/#REF! -> #REF! | K56: =K55/#REF! -> #REF! | M56: =M55/#REF! -> #REF! | O56: =O55/#REF! -> #REF! | Q56: =Q55/#REF! -> #REF! | S56: =S55/#REF! -> #REF!
F57: Cost per Unit | I57: =I55/#REF! -> #REF! | K57: =K55/#REF! -> #REF! | M57: =M55/#REF! -> #REF! | O57: =O55/#REF! -> #REF! | Q57: =Q55/#REF! -> #REF! | S57: =S55/#REF! -> #REF!
A59: QUALIFICATIONS
A63: EXCLUSIONS/OWNER PROVIDED ITEMS:
A67: ALTERNATES:
A71: PROPOSED VE (Provide Clear Description):
A75: FULLY LOADED LABOR RATES
B76: Laborer
B77: Mechanic
B78: Superintendent
B79: Project Manager
A81: SCHEDULE
B82: Prepared shop drawings/submittals
B83: Mobilization
B84: Total duration to complete scope of work
A86: Winner
A87: Company
A88: Contact
A89: Phone
A90: Email
A91: Base Bid
B93: Need Prequalification
B94: Prequalified

Sheet 05E Glass Railings
G1: Hedrick Plug
F2: X | G2: Excluded | H2: Allowance | J2: VE | L2: VE | N2: VE
B3: BACK TO SUMMARY SHEET | F3: I | G3: Included | H3: Bidder 1 | J3: Bidder 2 | L3: Bidder 3 | N3: Bidder 4 | P3: Bidder 5 | R3: Bidder 6
A4: Project: | B4: ='AREA CALC''s'!B4 -> Alton Hilltop Gardens | G4: Company | H4: HB | J4: Pilar Welding | L4: Greco Aluminum | N4: Coastal Metal | P4: A Christian
A5: Trade: | B5: Glass Railings | G5: Contact | J5: Sarai Campos | L5: Chris Jones | N5: Laura Montes
A6: CSI Code: | B6: 05E | G6: Phone | J6: 561-524-9246 | L6: 727-739-8873 | N6: 561-819-0308
A7: Date: | G7: Email | J7: <sara@pilarwelding.com> | L7: chris.jones@grecorailings.com | N7: lmontes@coastalmetal.biz
A8: Adjusted Bid | G8: Adjusted Bid | H8: =I55 -> 46000 | J8: =K55 -> 21150 | L8: =M55 -> 12050 | N8: =O55 -> 20105 | P8: =Q55 -> 18790 | R8: =S55 -> 0
A9: BID DOCUMENTS: | C9: Plan/ Spec. Package | D9: QTY | E9: U/M | F9: Unit Cost | G9: Subtotal | H9: Yes/No | I9: Price | J9: Yes/No | K9: Price | L9: Yes/No | M9: Price | N9: Yes/No | O9: Price | P9: Yes/No | Q9: Price | R9: Yes/No | S9: Price
B10: Plans By Division
B11: =#REF! -> #REF! | C11: P
B12: =#REF! -> #REF! | C12: P
B13: =#REF! -> #REF! | C13: P
B14: =#REF! -> #REF! | C14: P
B15: =#REF! -> #REF! | C15: P
B16: =#REF! -> #REF! | C16: P
B17: =#REF! -> #REF! | C17: P
B18: =#REF! -> #REF! | C18: P
B19: =#REF! -> #REF! | C19: P
B21: Glass Railings
B22: GENERAL INCLUSIONS
B23: INCLUDES ALL SALES TAX
B24: ALL HOISTING & RIGGING REQUIRED TO COMPLETE THIS SCOPE
B25: PROVIDE P&P BONDS
B26: FLORIDA STATE CONTRACTORS LIC.
B27: GENERAL LIABILITY AND WORKERS COMP. INSURANCE LIMITS
B28: STATE AND LOCAL TAXES
B29: COMPASS
B30: SPECIFIC TRADE SCOPE OF WORK REQUIREMENTS
B31: BASE BID
B33: Decorative railing @ Stair #3 Includes balcony railing @ 2nd floor | C33: 1/ID7-01 | D33: 30 | E33: LF | F33: 1000 | G33: =D33*F33 -> 30000 | H33: i | I33: =G33 -> 30000 | J33: i | K33: 10800 | L33: i | M33: =12050 -> 12050 | N33: i | O33: =18810+1295 -> 20105 | P33: i | Q33: 18790
B34: Stair #3 glass balcony railing @ 2nd floor | D34: 16 | E34: LF | F34: 1000 | G34: =D34*F34 -> 16000 | H34: i | I34: =G34 -> 16000 | J34: i | K34: 10350 | L34: i | N34: i | P34: i
F51: SUBTOTAL | I51: =SUM(I23:I50) -> 46000 | K51: =SUM(K23:K50) -> 21150 | M51: =SUM(M22:M50) -> 12050 | O51: =SUM(O22:O50) -> 20105 | Q51: =SUM(Q23:Q50) -> 18790 | S51: =SUM(S23:S50) -> 0
F52: BOND RATE | H52: 0 | J52: 0 | L52: 0 | N52: 0 | P52: 0 | R52: 0.02
F53: BOND AMOUNT | I53: =H52*$I$51 -> 0 | K53: =J52*$I$51 -> 0 | M53: =L52*$M$51 -> 0 | O53: =N52*$O$51 -> 0 | Q53: =P52*$Q$51 -> 0 | S53: =R52*S51 -> 0
F55: ADJUSTED TOTAL | I55: =SUM(I51:I54) -> 46000 | K55: =SUM(K51:K54) -> 21150 | M55: =SUM(M51:M53) -> 12050 | O55: =SUM(O51:O53) -> 20105 | Q55: =SUM(Q51:Q53) -> 18790 | S55: =SUM(S51:S53) -> 0
F56: Cost per SF | I56: =I55/#REF! -> #REF! | K56: =K55/#REF! -> #REF! | M56: =M55/#REF! -> #REF! | O56: =O55/#REF! -> #REF! | Q56: =Q55/#REF! -> #REF! | S56: =S55/#REF! -> #REF!
F57: Cost per Unit | I57: =I55/#REF! -> #REF! | K57: =K55/#REF! -> #REF! | M57: =M55/#REF! -> #REF! | O57: =O55/#REF! -> #REF! | Q57: =Q55/#REF! -> #REF! | S57: =S55/#REF! -> #REF!
A59: QUALIFICATIONS
A63: EXCLUSIONS/OWNER PROVIDED ITEMS:
A67: ALTERNATES:
A71: PROPOSED VE (Provide Clear Description):
A75: FULLY LOADED LABOR RATES
B76: Laborer
B77: Mechanic
B78: Superintendent
B79: Project Manager
A81: SCHEDULE
B82: Prepared shop drawings/submittals
B83: Mobilization
B84: Total duration to complete scope of work
A86: Winner
A87: Company | B87: =H4 -> HB
A88: Contact | B88: =H5 -> 0
A89: Phone | B89: =H6 -> 0
A90: Email | B90: =H7 -> 0
A91: Base Bid | B91: =H8 -> 46000
B93: Need Prequalification
B94: Prequalified

Sheet Rafters & Brackets Clubhouse
G1: Hedrick Plug
F2: X | G2: Excluded
B3: BACK TO SUMMARY SHEET | F3: I | G3: Included | H3: Aluminum Rafter Tails & Brackets | J3: PVC Rafter Tails & Brackets
A4: Project: | B4: ='AREA CALC''s'!B4 -> Alton Hilltop Gardens | G4: Company | H4: Coastal
A5: Trade: | B5: Rough Carpentry | G5: Contact
A6: CSI Code: | B6: 06A | G6: Phone
A7: Date: | G7: Email
A8: Adjusted Bid | G8: Adjusted Bid | H8: =I61 -> 197000 | J8: =K61 -> 74050 | L8: 110000 | M8: saving
A9: BID DOCUMENTS: | C9: Plan/ Spec. Package | D9: QTY | E9: U/M | F9: Unit Cost | G9: Subtotal | H9: Yes/No | I9: Price | J9: Yes/No | K9: Price
B10: Plans By Division
B11: =#REF! -> #REF! | C11: P
B12: =#REF! -> #REF! | C12: P
B13: =#REF! -> #REF! | C13: P
B14: =#REF! -> #REF! | C14: P
B15: =#REF! -> #REF! | C15: P
B16: =#REF! -> #REF! | C16: P
B17: =#REF! -> #REF! | C17: P
B18: =#REF! -> #REF! | C18: P
B19: =#REF! -> #REF! | C19: P
B21: Rough Carpentry
B22: GENERAL INCLUSIONS
B23: INCLUDES ALL SALES TAX
B24: ALL HOISTING & RIGGING REQUIRED TO COMPLETE THIS SCOPE
B25: PROVIDE P&P BONDS
B26: FLORIDA STATE CONTRACTORS LIC.
B27: GENERAL LIABILITY AND WORKERS COMP. INSURANCE LIMITS
B28: STATE AND LOCAL TAXES
B29: COMPASS
B30: SPECIFIC TRADE SCOPE OF WORK REQUIREMENTS
B31: BASE BID
B32: Building SF
B34: Clubhouse | H34: i | J34: i
B35: BR2 - Aluminum Rafter tails (1'-10" x 6" , 111 ea) | D35: 111 | E35: EA | F35: 400 | G35: =F35*D35 -> 44400 | H35: i | I35: =G35 -> 44400 | J35: i | K35: =D35*70*2 -> 15540
B36: BR6 - Aluminum Brackets (2' x 6' , 5ea) | D36: 5 | E36: EA | F36: 1000 | G36: =F36*D36 -> 5000 | H36: i | I36: =G36 -> 5000 | J36: i | K36: =D36*460*2 -> 4600
B37: Installation | H37: i | J37: i
B38: Pool Pavilion | H38: i | J38: i
B39: BR2 - Aluminum Rafter tails (1'-10" x 6" , 58 ea) | D39: 58 | E39: EA | F39: 400 | G39: =F39*D39 -> 23200 | H39: i | I39: =G39 -> 23200 | J39: i | K39: =D39*70*2 -> 8120
B40: BR6 - Aluminum Brackets (2' x 6' , 8ea) | D40: 8 | E40: EA | F40: 1000 | G40: =F40*D40 -> 8000 | H40: i | I40: =G40 -> 8000 | J40: i | K40: =D40*460*2 -> 7360
B41: Installation | H41: i | J41: i
B42: Garage 1 | H42: i | J42: i
B43: BR2 - Aluminum Rafter tails (1'-10" x 6" , 86 ea) | D43: 86 | E43: EA | F43: 400 | G43: =F43*D43 -> 34400 | H43: i | I43: =G43 -> 34400 | J43: i | K43: =D43*70*2 -> 12040
B44: Installation | H44: i | J44: i
B45: Garage 2 | H45: i | J45: i
B46: BR2 - Aluminum Rafter tails (1'-10" x 6" , 86 ea) | D46: 86 | E46: EA | F46: 400 | G46: =F46*D46 -> 34400 | H46: i | I46: =G46 -> 34400 | J46: i | K46: =D46*70*2 -> 12040
B47: Installation | H47: i | J47: i
B48: Garage 3 | H48: i | J48: i
B49: BR2 - Aluminum Rafter tails (1'-10" x 6" , 86 ea) | D49: 86 | E49: EA | F49: 400 | G49: =F49*D49 -> 34400 | H49: i | I49: =G49 -> 34400 | J49: i | K49: =D49*70*2 -> 12040
B50: Installation | H50: i | J50: i
B51: Maintenance Building | H51: i | J51: i
B52: BR2 - Aluminum Rafter tails (1'-10" x 6" , 86 ea) | D52: 33 | E52: EA | F52: 400 | G52: =F52*D52 -> 13200 | H52: i | I52: =G52 -> 13200 | J52: i | K52: =D52*70 -> 2310
B53: Installation | H53: i | J53: i
F57: SUBTOTAL | G57: =SUM(G31:G56) -> 197000 | I57: =SUM(I23:I56) -> 197000 | K57: =SUM(K31:K56) -> 74050
F58: BOND RATE | H58: 0 | J58: 0
F59: BOND AMOUNT | I59: =H58*I57 -> 0 | K59: =J58*K57 -> 0
F61: ADJUSTED TOTAL | I61: =SUM(I57:I60) -> 197000 | K61: =SUM(K57:K60) -> 74050
F62: Cost per SF | I62: =I61/#REF! -> #REF! | K62: =K61/#REF! -> #REF!
F63: Cost per Unit | I63: =I61/#REF! -> #REF! | K63: =K61/#REF! -> #REF!
A65: QUALIFICATIONS
A69: EXCLUSIONS/OWNER PROVIDED ITEMS:
A73: ALTERNATES:
B74: 8x8 Aluminum columns with PC finish
B75: 8x8 Steel columns with Hardie Board wrap
B76: 8x8 PVC columns
A77: PROPOSED VE (Provide Clear Description):
A81: FULLY LOADED LABOR RATES
B82: Laborer
B83: Mechanic
B84: Superintendent
B85: Project Manager
A87: SCHEDULE
B88: Prepared shop drawings/submittals
B89: Mobilization
B90: Total duration to complete scope of work
A92: Winner
A93: Company
A94: Contact
A95: Phone
A96: Email
A97: Base Bid | B97: =#REF! -> #REF!
B99: Need Prequalification
B100: Prequalified

Sheet Rafter Tails & Brackets
G1: Hedrick Plug
F2: X | G2: Excluded
B3: BACK TO SUMMARY SHEET | F3: I | G3: Included | H3: Aluminum Rafter Tails & Brackets | J3: PVC Rafter Tails & Brackets | L3: Fiberglass Rafter Tails & Brackets
A4: Project: | B4: ='AREA CALC''s'!B4 -> Alton Hilltop Gardens | G4: Company
A5: Trade: | B5: Rough Carpentry | G5: Contact
A6: CSI Code: | B6: 06A | G6: Phone
A7: Date: | G7: Email
A8: Adjusted Bid | G8: Adjusted Bid | H8: =I50 -> 949500 | J8: =K50 -> 549500
A9: BID DOCUMENTS: | C9: Plan/ Spec. Package | D9: QTY | E9: U/M | F9: Unit Cost | G9: Subtotal | H9: Yes/No | I9: Price | J9: Yes/No | K9: Price | L9: Yes/No | M9: Price
B10: Plans By Division
B11: =#REF! -> #REF! | C11: P
B12: =#REF! -> #REF! | C12: P
B13: =#REF! -> #REF! | C13: P
B14: =#REF! -> #REF! | C14: P
B15: =#REF! -> #REF! | C15: P
B16: =#REF! -> #REF! | C16: P
B17: =#REF! -> #REF! | C17: P
B18: =#REF! -> #REF! | C18: P
B19: =#REF! -> #REF! | C19: P
B21: Rough Carpentry
B22: GENERAL INCLUSIONS
B23: INCLUDES ALL SALES TAX
B24: ALL HOISTING & RIGGING REQUIRED TO COMPLETE THIS SCOPE
B25: PROVIDE P&P BONDS
B26: FLORIDA STATE CONTRACTORS LIC.
B27: GENERAL LIABILITY AND WORKERS COMP. INSURANCE LIMITS
B28: STATE AND LOCAL TAXES
B29: COMPASS
B30: SPECIFIC TRADE SCOPE OF WORK REQUIREMENTS
B31: BASE BID
B32: Building SF
B34: Rafter Tails | D34: 814 | E34: EA | H34: i | J34: i | L34: i
B35: Brackets | D35: 327 | E35: EA | H35: i | J35: i | L35: i
B36: Bahama Shutters (740 ea) | D36: 6942 | E36: SF | H36: i | I36: =1099500-150000 -> 949500 | J36: i | K36: =I36-400000 -> 549500 | L36: i
H37: i | J37: i | L37: i
B38: Custom color add | H38: i | J38: i | L38: i
H39: i | J39: i | L39: i
F46: SUBTOTAL | G46: =SUM(G31:G41) -> 0 | I46: =SUM(I23:I45) -> 949500 | K46: =SUM(K23:K45) -> 549500 | M46: =SUM(M23:M45) -> 0
F47: BOND RATE | H47: 0 | J47: 0 | L47: 0
F48: BOND AMOUNT | I48: =H47*I46 -> 0 | K48: =J47*K46 -> 0 | M48: =L47*M46 -> 0
F50: ADJUSTED TOTAL | I50: =SUM(I46:I49) -> 949500 | K50: =SUM(K46:K49) -> 549500 | M50: =SUM(M46:M49) -> 0
F51: Cost per SF | I51: =I50/#REF! -> #REF! | K51: =K50/#REF! -> #REF! | M51: =M50/#REF! -> #REF!
F52: Cost per Unit | I52: =I50/#REF! -> #REF! | K52: =K50/#REF! -> #REF! | M52: =M50/#REF! -> #REF!
A54: QUALIFICATIONS
A58: EXCLUSIONS/OWNER PROVIDED ITEMS:
A62: ALTERNATES:
B63: 8x8 Aluminum columns with PC finish
B64: 8x8 Steel columns with Hardie Board wrap
B65: 8x8 PVC columns
A66: PROPOSED VE (Provide Clear Description):
A70: FULLY LOADED LABOR RATES
B71: Laborer
B72: Mechanic
B73: Superintendent
B74: Project Manager
A76: SCHEDULE
B77: Prepared shop drawings/submittals
B78: Mobilization
B79: Total duration to complete scope of work
A81: Winner
A82: Company
A83: Contact
A84: Phone
A85: Email
A86: Base Bid | B86: =#REF! -> #REF!
B88: Need Prequalification
B89: Prequalified

Sheet Shutters Analysis
G1: Hedrick Plug
F2: X | G2: Excluded | T2: https://www.architecturaldepot.com/ELSQEM.html
B3: BACK TO SUMMARY SHEET | F3: I | G3: Included | H3: Standard shutters | J3: Batten Shutters | T3: Aluminum prefinished
A4: Project: | B4: ='AREA CALC''s'!B4 -> Alton Hilltop Gardens | G4: Company
A5: Trade: | B5: Rough Carpentry | G5: Contact
A6: CSI Code: | B6: 06A | G6: Phone
A7: Date: | G7: Email
A8: Adjusted Bid | G8: Adjusted Bid | H8: =I50 -> 347100 | J8: =K50 -> 416520 | T8: =U50 -> 0
A9: BID DOCUMENTS: | C9: Plan/ Spec. Package | D9: QTY | E9: U/M | F9: Unit Cost | G9: Subtotal | H9: Yes/No | I9: Price | J9: Yes/No | K9: Price | T9: Yes/No | U9: Price
B10: Plans By Division
B11: =#REF! -> #REF! | C11: P
B12: =#REF! -> #REF! | C12: P
B13: =#REF! -> #REF! | C13: P
B14: =#REF! -> #REF! | C14: P
B15: =#REF! -> #REF! | C15: P
B16: =#REF! -> #REF! | C16: P
B17: =#REF! -> #REF! | C17: P
B18: =#REF! -> #REF! | C18: P
B19: =#REF! -> #REF! | C19: P
B21: Rough Carpentry
B22: GENERAL INCLUSIONS
B23: INCLUDES ALL SALES TAX
B24: ALL HOISTING & RIGGING REQUIRED TO COMPLETE THIS SCOPE
B25: PROVIDE P&P BONDS
B26: FLORIDA STATE CONTRACTORS LIC.
B27: GENERAL LIABILITY AND WORKERS COMP. INSURANCE LIMITS
B28: STATE AND LOCAL TAXES
B29: COMPASS
B30: SPECIFIC TRADE SCOPE OF WORK REQUIREMENTS
B31: BASE BID
B32: Building SF
B34: Rafter Tails | D34: 814 | E34: EA | H34: i | J34: i | T34: i
B35: Brackets | D35: 327 | E35: EA | H35: i | J35: i | T35: i
B36: Bahama Shutters (740 ea) | D36: 6942 | E36: SF | H36: i | I36: =D36*50 -> 347100 | J36: i | K36: =D36*60 -> 416520 | T36: i
H37: i | J37: i | T37: i
H38: i | J38: i | T38: i
H39: i | J39: i | T39: i
H40: i | J40: i | T40: i
H41: i | J41: i | T41: i
H42: i
H43: i
H44: i | J44: i | T44: i
F46: SUBTOTAL | G46: =SUM(G31:G41) -> 0 | I46: =SUM(I23:I45) -> 347100 | K46: =SUM(K23:K45) -> 416520 | M46: =SUM(M23:M45) -> 0 | O46: =SUM(O23:O45) -> 0 | Q46: =SUM(Q23:Q45) -> 0 | S46: =SUM(S23:S45) -> 0 | U46: =SUM(U23:U45) -> 0
F47: BOND RATE | H47: 0 | J47: 0 | L47: 0 | N47: 0 | P47: 0 | R47: 0 | T47: 0
F48: BOND AMOUNT | I48: =H47*$I$46 -> 0 | K48: =J47*$I$46 -> 0 | M48: =L47*$I$46 -> 0 | O48: =N47*$I$46 -> 0 | Q48: =P47*$I$46 -> 0 | S48: =R47*$I$46 -> 0 | U48: =T47*$I$46 -> 0
F50: ADJUSTED TOTAL | I50: =SUM(I46:I49) -> 347100 | K50: =SUM(K46:K49) -> 416520 | M50: =SUM(M46:M49) -> 0 | O50: =SUM(O46:O49) -> 0 | Q50: =SUM(Q46:Q49) -> 0 | S50: =SUM(S46:S49) -> 0 | U50: =SUM(U46:U49) -> 0
F51: Cost per SF | I51: =I50/#REF! -> #REF! | K51: =K50/#REF! -> #REF! | M51: =M50/#REF! -> #REF! | O51: =O50/#REF! -> #REF! | Q51: =Q50/#REF! -> #REF! | S51: =S50/#REF! -> #REF! | U51: =U50/#REF! -> #REF!
F52: Cost per Unit | I52: =I50/#REF! -> #REF! | K52: =K50/#REF! -> #REF! | M52: =M50/#REF! -> #REF! | O52: =O50/#REF! -> #REF! | Q52: =Q50/#REF! -> #REF! | S52: =S50/#REF! -> #REF! | U52: =U50/#REF! -> #REF!
A54: QUALIFICATIONS
A58: EXCLUSIONS/OWNER PROVIDED ITEMS:
A62: ALTERNATES:
B63: 8x8 Aluminum columns with PC finish
B64: 8x8 Steel columns with Hardie Board wrap
B65: 8x8 PVC columns
A66: PROPOSED VE (Provide Clear Description):
A70: FULLY LOADED LABOR RATES
B71: Laborer
B72: Mechanic
B73: Superintendent
B74: Project Manager
A76: SCHEDULE
B77: Prepared shop drawings/submittals
B78: Mobilization
B79: Total duration to complete scope of work
A81: Winner
A82: Company
A83: Contact
A84: Phone
A85: Email
A86: Base Bid | B86: =H8 -> 347100
B88: Need Prequalification
B89: Prequalified

Sheet 05F Brackets & Rafter Tails
G1: Hedrick Plug | J1: in louvers, awnings, shutters | N1: BO | R1: BO | X1: PROMISING | Z1: PROMISING | AB1: PROMISING | AO1: CH, Maint and G only
F2: X | G2: Excluded | H2: Aluminum | J2: dated 04.10.26 | N2: dated 04.27.26 | R2: dated 04.23.26 | T2: includes Misc Met | X2: VE Foam + EIFS | Z2: VE Foam + EIFS | AB2: VE Foam + EIFS | AD2: missing rafter tails & brackets | AF2: wont meet fire | AH2: wont meet fire | AJ2: wont meet fire | AS2: Aluminum | AU2: FOAM + EIFS | AW2: VE PVC | AY2: VE PVC | BA2: FRP
B3: BACK TO SUMMARY SHEET | F3: I | G3: Included | H3: Bidder 1 | J3: Bidder 1 | L3: Bidder 2 | N3: Bidder 2 | P3: Bidder 3 | R3: Bidder 3 | T3: Bidder 3 | V3: Bidder 4 | X3: Bidder 4 | Z3: Bidder 4 | AB3: Bidder 4 | AD3: Bidder 4 | AF3: Bidder 5 | AH3: Bidder 6 | AJ3: Bidder 7 | AO3: BACK TO SUMMARY SHEET
A4: Project: | B4: ='AREA CALC''s'!B4 -> Alton Hilltop Gardens | G4: Company | H4: Bachiller Iron Works | J4: Bachiller Iron Works R3 | L4: Pilar Welding | N4: Pilar Welding | P4: Awning Factory | R4: Awning Factory | T4: All American Windows | V4: Coastal Metal | X4: RB Plastering | Z4: Griffin Stucco | AB4: Stud Drywall | AD4: Complete Access | AF4: Shell Lumber | AH4: Holland | AJ4: Architectural Mall | AS4: Coastal Metal | AU4: Griffin Stucco | AW4: HB Elements | AY4: Decoro | BA4: Architectural Mall
A5: Trade: | B5: Misc. Metals | G5: Contact | H5: David A. Rodriguez | J5: David A. Rodriguez | L5: Sarai Campos | N5: Sarai Campos | P5: Estimating | R5: Estimating | T5: Vicente Fernandez | V5: Laura Montes | X5: Carlos Valencia | Z5: Rohit Puranik | AB5: Joe Colella | AD5: Chris Mauro | AF5: Duan Mercer | AH5: Sales (Holland) | AJ5: Jake Hed | AO5: Misc. Metals | AS5: Laura Montes | AU5: Rohit Puranik | AW5: Arseny | AY5: Samuel Boehne | BA5: Jake Hed
A6: CSI Code: | B6: 05C | G6: Phone | H6: 305-751-7765 | J6: 305-751-7765 | L6: 561-524-9246 | N6: 561-524-9246 | T6: 954-786-8525 | V6: 561-819-0308 | AD6: 407-408-4323 | AF6: 305-856-6401 | AJ6: 877-279-9993 | AO6: 05C | AS6: 561-819-0308
A7: Date: | G7: Email | H7: drodriguez@biwiron.com | J7: drodriguez@biwiron.com | L7: <sara@pilarwelding.com> | N7: <sara@pilarwelding.com> | P7: estimating5@theawningfactory.com | R7: estimating5@theawningfactory.com | T7: vfernandez@aawimpact.com> | V7: lmontes@coastalmetal.biz | AD7: chris@cacocf.com | AF7: <duan@shelllumber.com> | AH7: sales@hollandfiberglass.com | AJ7: <jake@architecturalmall.com> | AS7: lmontes@coastalmetal.biz
A8: Adjusted Bid | G8: Adjusted Bid | H8: =I108 -> 236630 | J8: included below | L8: =M108 -> 412837.5 | N8: =O108 -> 438146.25 | P8: =Q108 -> 480360 | R8: =S108 -> 427150 | T8: =U108 -> 0 | V8: =W108 -> 493453 | X8: =Y108 -> 71388 | Z8: =AA108 -> 66505 | AB8: =AC108 -> 148525 | AD8: =AE108 -> 0 | AF8: =AG108 -> 0 | AH8: =AI108 -> 0 | AJ8: =AK108 -> 0 | AS8: =AT67 -> 145587 | AU8: =AV67 -> 24760 | AW8: =AX67 -> 77675 | AY8: =AZ67 -> 31686.7 | BA8: =BB67 -> 163340
G9: Awnings, Shutters | J9: ='13C Awnings,Canopies,Shutters'!X8 -> 1955430 | L9: ='13C Awnings,Canopies,Shutters'!J8 -> 1038214.3 | N9: ='13C Awnings,Canopies,Shutters'!L8 -> 913200.57 | P9: ='13C Awnings,Canopies,Shutters'!T8 -> 1153400.3 | R9: ='13C Awnings,Canopies,Shutters'!P8 -> 982290 | T9: ='13C Awnings,Canopies,Shutters'!R8 -> 2125000 | V9: ='13C Awnings,Canopies,Shutters'!T8 -> 1153400.3
G10: Total | J10: =SUM(J8:K9) -> 1955430 | L10: =SUM(L8:M9) -> 1451051.9 | N10: =SUM(N8:O9) -> 1351346.8 | P10: =SUM(P8:Q9) -> 1633760.3 | R10: =SUM(R8:S9) -> 1409440 | T10: =SUM(T8:U9) -> 2125000 | V10: =SUM(V8:W9) -> 1646853.3
A11: BID DOCUMENTS: | C11: Plan/ Spec. Package | D11: QTY | E11: U/M | F11: Unit Cost | G11: Subtotal | L11: Yes/No | M11: Price | N11: Yes/No | O11: Price | P11: Yes/No | Q11: Price | R11: Yes/No | S11: Price | V11: Yes/No | W11: Price | AD11: Yes/No | AE11: Price | AF11: Yes/No | AG11: Price | AH11: Yes/No | AI11: Price | AJ11: Yes/No | AK11: Price
B12: Plans By Division | AO12: Plans By Division
B13: =#REF! -> #REF! | C13: P | AO13: =#REF! -> #REF!
B14: =#REF! -> #REF! | C14: P | AO14: =#REF! -> #REF!
B15: =#REF! -> #REF! | C15: P | AO15: =#REF! -> #REF!
B16: =#REF! -> #REF! | C16: P | AO16: =#REF! -> #REF!
B17: =#REF! -> #REF! | C17: P | AO17: =#REF! -> #REF!
B18: =#REF! -> #REF! | C18: P | AO18: =#REF! -> #REF!
B19: =#REF! -> #REF! | C19: P | AO19: =#REF! -> #REF!
B20: =#REF! -> #REF! | C20: P | AO20: =#REF! -> #REF!
B21: =#REF! -> #REF! | C21: P | AO21: =#REF! -> #REF!
B23: Misc. Metals | AO23: Misc. Metals
B24: GENERAL INCLUSIONS | AO24: GENERAL INCLUSIONS
B25: INCLUDES ALL SALES TAX | H25: i | J25: i | L25: i | N25: i | P25: i | R25: i | T25: i | V25: i | X25: i | Z25: i | AB25: i | AD25: i | AO25: INCLUDES ALL SALES TAX | AS25: i | AU25: i | AW25: i | AY25: i | BA25: i
