Workbook
Name FCP: 'Bond Calculator'!$B$7

Sheet Area Calculations
B2: PROJECT AREA CALCULATIONS
B4: ERAU Residential Hall & Garage Building | F4: Gross (sf) | G4: 578663
B5: Daytona Beach | F5: AC (sf)
F6: Site (acres) | G6: =H6/43560 -> 6.5699725 | H6: 286188
F7: Parking Spaces Surface | G7: 131
F8: Parking Spaces Garage | G8: 925
F9: No. of Units: | G9: =C30 -> 107
F10: No. of Beds: | G10: 423
F11: Build Duration (months)
B14: Floors | C14: Units | D14: AC SF | E14: Gross SF | F14: LSF | G14: GROSS%
G16: =E16/$G$4 -> 0
B17: 2nd | C17: 21 | G17: =E17/$G$4 -> 0
B18: 3rd | C18: 21 | G18: =E18/$G$4 -> 0
B19: 4th | C19: 21 | G19: =E19/$G$4 -> 0
B20: 5th | C20: 20 | G20: =E20/$G$4 -> 0
B21: 5th staff | C21: 1 | G21: =E21/$G$4 -> 0
B22: 5th guest | C22: 1 | G22: =E22/$G$4 -> 0
B23: 6th | C23: 20 | G23: =E23/$G$4 -> 0
B24: 6th staff | C24: 1 | G24: =E24/$G$4 -> 0
B25: 6th guest | C25: 1 | G25: =E25/$G$4 -> 0
G26: =E26/$G$4 -> 0
G27: =E27/$G$4 -> 0
B30: TOTAL | C30: =SUM(C16:C29) -> 107 | D30: =SUM(D16:D29) -> 0 | E30: =SUM(E16:E29) -> 0 | F30: =SUM(F16:F29) -> 0 | G30: =SUM(G16:G29) -> 0
A46: IV. | B46: SITE AREAS | F46: $ /UNIT | G46: %
B49: Site Perimeter | F49: LF
B50: Walk Gates
B51: Drive Gates
B52: Tire Grates / Truck Wash
A53: III. | B53: SITE AREAS | F53: $ /UNIT | G53: %
B54: Sidewalks
B55: Drives
B56: Asphalt Parking
B57: Fill CY
A58: III. | B58: Barking Spaces | C58: FLOOR BREAKDOWN | E58: QTY. | G58: %
G60: =E60/$G$7 -> 0
G61: =E61/$G$7 -> 0
B63: TOTAL Units | E63: =SUM(E60:E62) -> 0 | G63: =SUM(G60:G62) -> 0

Sheet Bond Calculator
A1: Hedrick Brothers Construction
A3: Performance / Payment Bond | E3: Performance / Payment Bond
A4: General Construction | E4: Design Build
B6: =IF(B13>500000,500000,B13) -> 500000 | C6: 0.0091 | D6: =B6*C6 -> 4550 | F6: 0 | G6: 0.01875 | H6: =SUM(F6*G6) -> 0
B7: =IF(B13<2500000,(B13-B6),IF(B13>B6,2000000,0)) -> 2000000 | C7: 0.00725 | D7: =B7*C7 -> 14500 | F7: 0 | G7: 0.015 | H7: =SUM(F7*G7) -> 0
B8: =IF(B13<5000000,MAX(0,B13-2500000),IF(B13>2500000,2500000)) -> 2500000 | C8: 0.0063 | D8: =B8*C8 -> 15750 | F8: 0 | G8: 0.01125 | H8: =SUM(F8*G8) -> 0
B9: =IF(B13<7500000,MAX(0,B13-5000000),IF(B13>7500000,2500000,0)) -> 2500000 | C9: 0.00555 | D9: =B9*C9 -> 13875 | F9: 0 | G9: 0.009 | H9: =SUM(F9*G9) -> 0
B10: =IF(B13<7500000,MAX(0,B13-7500000),IF(B13>7500000,(B13-7500000))) -> 92779112 | C10: 0.0051 | D10: =B10*C10 -> 473173.47 | F10: 0 | G10: 0.00825 | H10: =SUM(F10*G10) -> 0
D11: =B11*C11 -> 0 | F11: 0 | G11: 0.0075 | H11: =SUM(F11*G11) -> 0
A12: Contract Value | B12: ='Cost Summary'!C84 -> 1.0027911e+08 | C12: Total | D12: =SUM(D6:D11) -> 521848.47 | E12: Contract Value | F12: =SUM(F6+F7+F8+F9+F10+F11) -> 0 | G12: Total | H12: =SUM(H6:H11) -> 0
A13: Cost Summary | B13: ='Cost Summary'!C84 -> 1.0027911e+08 | D13: =SUM(D12/B12) -> 0.0052039598 | H13: =SUM(H12/F12) -> #DIV/0!
B14: =B12-B13 -> 0

Sheet Allowances
A3: ='Area Calculations'!B4 -> ERAU Residential Hall & Garage Building
A5: Allowances
A6: =TODAY() -> 46085
A8: NO. | B8: DESCRIPTION | C8: VALUE
A9: 1
A10: =A9+1 -> 2
A11: =A10+1 -> 3
A12: =A11+1 -> 4
A13: =A12+1 -> 5
A14: =A13+1 -> 6
A15: =A14+1 -> 7
A16: =A15+1 -> 8
A17: =A16+1 -> 9
A18: =A17+1 -> 10
A19: =A18+1 -> 11
A20: =A19+1 -> 12
A21: =A20+1 -> 13
... A26: =A25+1 -> 18
A27: =A26+1 -> 19 | B27: Total | C27: =SUM(C9:C26) -> 0

Sheet Alternate & VE
A3: ='Area Calculations'!B4 -> ERAU Residential Hall & Garage Building
A5: Alternate & Value Engineering Pricing
A6: =TODAY() -> 46085 | E6: Add markup | F6: 1.12
D7: 0.11067508
A8: NO. | B8: DESCRIPTION | C8: VALUE | D8: VALUE W/ MARK-UP
A9: 1 | B9: Provide a cost to ADD a performance and payment bond for the entirety of the project. | C9: ='Cost Summary'!C87 -> 1002791.1 | D9: =C9*(1+$D$7) -> 1113775.1
A10: =A9+1 -> 2 | B10: Provide cost to ADD epoxy paint in all student corridors from floor to five feet above, in lieu of base paint system | C10: ='09 90 Painting'!M67 -> 38975 | D10: =C10*(1+$D$7) -> 43288.561
A11: =A10+1 -> 3 | B11: Provide cost to DELETE the solid surface countertop from the residential unit kitchens, then provide plastic laminate countertops in lieu of. | C11: ='12 36 Solid Surface'!I70 -> -96475 | D11: =C11*(1+$D$7) -> -107152.38
A12: =A11+1 -> 4 | B12: Provide cost to delete the concealed anchors at the wall mounted railings, then provide costs exposed anchors in lieu of. | C12: ='05 52 Misc. Metals'!K76 -> -36060 | D12: =C12*(1+$D$7) -> -40050.943
A13: =A12+1 -> 5 | B13: Provide cost to delete the ESP coatings as noted on the drawings on the metal railings, then provide costs for primed and painted railings as noted in the specifications. | C13: ='09 90 Painting'!K66 -> -42400 | D13: =C13*(1+$D$7) -> -47092.623
A14: =A13+1 -> 6 | B14: Provide ADD costs for graphics on the precast panels at the exterior. | C14: =500000 -> 500000 | D14: =C14*(1+$D$7) -> 555337.54
A15: =A14+1 -> 7 | B15: Provide ADD costs for the exterior wing shaped sun screen (canopies) | C15: ='05 10 Steel'!I79 -> 403683.72 | D15: =C15*(1+$D$7) -> 448361.45
A16: =A15+1 -> 8 | B16: Provide ADD/DEDUCT costs per the allowance. (Base Bid per Interior Plans). | C16: =294000+4563708.31 -> 4857708.3 | D16: =C16*(1+$D$7) -> 5395335.6
A17: =A16+1 -> 9 | B17: Provide DEDUCT costs for under cabinetry lights in Units. | C17: -10550 | D17: =C17*(1+$D$7) -> -11717.622
A18: =A17+1 -> 10 | B18: ='ERUA Cost Summary'!B114 -> Assigned wallcoverings | C18: 175000 | D18: =C18*(1+$D$7) -> 194368.14
A19: =A18+1 -> 11 | B19: ='ERUA Cost Summary'!B115 -> Full Tile Kitchen Backsplashes | C19: 18500 | D19: =C19*(1+$D$7) -> 20547.489
A20: =A19+1 -> 12 | B20: ='ERUA Cost Summary'!B116 -> 30-Inch Trash Chutes | C20: 7608.87 | D20: =C20*(1+$D$7) -> 8450.9823
A21: =A20+1 -> 13 | B21: ='ERUA Cost Summary'!B117 -> Wallcoverings identified in Addendum 1 | C21: 303578 | D21: =C21*(1+$D$7) -> 337176.52
A22: =A21+1 -> 14 | B22: ='ERUA Cost Summary'!B118 -> Vinyl Flooring System with integral sound attenuation layer | C22: ='09 60 Flooring'!I59 -> -124910 | D22: =C22*(1+$D$7) -> -138734.42
A23: =A22+1 -> 15 | B23: ='ERUA Cost Summary'!B119 -> CPVC Piping in lieu of Copper up to 1 1/2" Deduct | C23: 0 | D23: =C23*(1+$D$7) -> 0 | E23: Base Bid
B24: ='ERUA Cost Summary'!B120 -> Copper Piping in lieu of CPVC up to 1 1/2" Add | C24: 300000 | D24: =C24*(1+$D$7) -> 333202.52 | F24: shades | G24: elec
A25: =A23+1 -> 16 | B25: ='ERUA Cost Summary'!B121 -> Motorized window shades for all public areas and lounges. | C25: =H25 -> 182132.36 | D25: =C25*(1+$D$7) -> 202289.87 | F25: 131382.36 | G25: =203*250 -> 50750 | H25: =F25+G25 -> 182132.36
A26: =A25+1 -> 17 | B26: ='ERUA Cost Summary'!B122 -> Automatic door operators - 24 Single doors / 4 Double doors | C26: =P32 -> 127000 | D26: =C26*(1+$D$7) -> 141055.74
A27: =A26+1 -> 18 | B27: Please provide a cost for only providing Rod & Shelves ( 2 each, stack) for the individual bedrooms, instead of the original closet millwork system as specified. | C27: ='12 34 Residential Casework'!AH39 -> -188100 | D27: =C27*(1+$D$7) -> -208917.98
B28: Total | C28: =SUM(C9:C27) -> 7418482.4 | D28: =SUM(D9:D27) -> 8239523.5 | M28: operator | N28: power | O28: pedistal
M29: installed
F30: 24 single door operators - HM door & frame | K30: +power | L30: 24 | M30: 3500 | N30: 500 | O30: 0 | P30: =L30*(M30+N30+O30) -> 96000
F31: 4 double door operators - storefront | K31: +power | L31: 4 | M31: 6000 | N31: 250 | O31: 1500 | P31: =L31*(M31+N31+O31) -> 31000
P32: =SUM(P30:P31) -> 127000
B35: Geopier - rammed aggregate | C35: ='31 32 Soil Stabilization'!N9-'31 32 Soil Stabilization'!H9 -> -682500 | D35: =C35*(1+$D$7) -> -758035.74
B36: Lighting fixture VE package | C36: -400000 | D36: =C36*(1+$D$7) -> -444270.03
B37: Light Fixture VE alternate to Sesco package - subject to architect and engineer approval | C37: -1000000 | D37: =C37*(1+$D$7) -> -1110675.1
B38: Aluminum feeders and secondaries 100amp and larger - subject to architect and engineer approval | C38: =-2137000 -> -2137000 | D38: =C38*(1+$D$7) -> -2373512.6

Sheet ERUA Cost Summary
A1: GC BID PROPOSAL SUMMARY
B3: EMBRY RIDDLE PHASE IV - RESIDENCE HALL AND GARAGE DAYTONA BEACH CAMPUS ADDENDUM NO 5 dated August 7, 2025 | C3: sq. ft. of project | E3: 578663
A5: Division | C5: PSF value | E5: Total
A6: 1 | B6: General Conditions, staffing and temp Facilities | C6: =+E6/$E$3 -> 7.6708747 | E6: ='Cost Summary'!E11+'Cost Summary'!E12 -> 4438851.4
A7: 1 | B7: Surveying | C7: =+E7/$E$3 -> 0.10350238 | E7: ='Cost Summary'!E13 -> 59893
A8: 1 | B8: Site Maintenance | C8: =+E8/$E$3 -> 3.0789029 | E8: ='Cost Summary'!E15 -> 1781647.2
A9: 1 | B9: Addition Building Width Allowance | C9: =+E9/$E$3 -> 0.86406077 | E9: 500000 | G9: 0 | H9: =E9-G9 -> 500000
A10: 2 | B10: Deep Foundations / Soils Improvements | C10: =+E10/$E$3 -> 2.2806724 | E10: ='Cost Summary'!E63 -> 1319740.7 | G10: 0 | H10: =E10-G10 -> 1319740.7 | J10: =SUM(E10:E13) -> 4699395.8 | K10: ='Cost Summary'!E62+'Cost Summary'!E63+'Cost Summary'!E64+'Cost Summary'!E65+'Cost Summary'!E66 -> 4699395.8 | L10: =J10-K10 -> 0
A11: 2 | B11: Site Work / Improvements | C11: =+E11/$E$3 -> 3.4730844 | E11: ='Cost Summary'!E62+'Cost Summary'!E63+'Cost Summary'!E64+'Cost Summary'!E65-N11-E10 -> 2009745.4 | G11: 3329486.1 | H11: =E11-G11 -> -1319740.7 | N11: =O11*1.1 -> 903601.79 | O11: =SUM(P11:U11) -> 821456.17 | P11: =P12 -> 149328 | Q11: =Q12 -> 86403.333 | R11: =R12 -> 1512 | S11: =S12 -> 22090.53 | T11: =T12 -> 183470 | U11: =P13 -> 378652.31
A12: 2 | B12: Parking Lot Pavement / Striping | C12: =+E12/$E$3 -> 0.84174079 | E12: =N12 -> 487084.25 | N12: =O12*1.1 -> 487084.25 | O12: =SUM(P12:U12) -> 442803.86 | P12: ='31 30 Site Work'!I68 -> 149328 | Q12: ='31 30 Site Work'!I74 -> 86403.333 | R12: ='31 30 Site Work'!I75 -> 1512 | S12: ='31 30 Site Work'!I132 -> 22090.53 | T12: =SUM('31 30 Site Work'!I142:I145) -> 183470
A13: 2 | B13: Landscaping (including sidewalk and curbs) | C13: =+E13/$E$3 -> 1.5256296 | E13: ='Cost Summary'!E66+N13 -> 882825.42 | N13: =O13*1.1 -> 416517.54 | O13: =SUM(P13:U13) -> 378652.31 | P13: =SUM('31 30 Site Work'!I78:I83) -> 378652.31
A14: 3 | B14: Concrete, Foundation/Slab on Grade | C14: =+E14/$E$3 -> 9.8222244 | E14: ='Cost Summary'!E16-E16 -> 5683757.8 | G14: 5757857.8 | H14: =E14-G14 -> -74100
A15: 3 | B15: Precast Concrete - Metromont | C15: =+E15/$E$3 -> 36.753267 | E15: ='Cost Summary'!E17-E9 -> 21267756 | G15: 21767756 | H15: =E15-G15 -> -500000
A16: 4 | B16: Masonry | C16: =+E16/$E$3 -> 0.12805381 | E16: ='03 30 CIP Concrete'!K76+'03 30 CIP Concrete'!K77 -> 74100 | H16: =E16-G16 -> 74100
A17: 5 | B17: Structural Steel | C17: =+E17/$E$3 -> 0.61037392 | E17: ='Cost Summary'!E19 -> 353200.8
A18: 5 | B18: Canopies and Shading Louvers | C18: =+E18/$E$3 -> 0 | E18: 0 | G18: 25450.99 | H18: =E18-G18 -> -25450.99
A19: 5 | B19: Decorative Metals | C19: =+E19/$E$3 -> 0 | E19: 0
A20: 5 | B20: Stairs, Railing Systems, Misc | C20: =+E20/$E$3 -> 0.58399691 | E20: ='Cost Summary'!E20 -> 337937.4
A21: 6 | B21: Interior Carpentry | C21: =+E21/$E$3 -> 0.57857915 | E21: ='Cost Summary'!E22 -> 334802.35 | G21: 1323589.8 | H21: =E21-G21 -> -988787.49 | J21: =E21 -> 334802.35 | K21: ='Cost Summary'!E22+'Cost Summary'!E47+'Cost Summary'!E48 -> 1684491.2 | L21: =J21-K21 -> -1349688.8 | O21: =SUM(P21:U21) -> 1684491.2 | P21: ='Cost Summary'!E22 -> 334802.35 | Q21: ='Cost Summary'!E47 -> 793220.85 | R21: ='Cost Summary'!E48 -> 556467.99
A22: 6 | B22: Rough Carpentry | C22: =+E22/$E$3 -> 0.85350368 | E22: ='Cost Summary'!C21 -> 493891
A23: 7 | B23: Thermal and Moisture Protection | C23: =+E23/$E$3 -> 1.5646229 | E23: ='Cost Summary'!E23+'Cost Summary'!E28+'Cost Summary'!E29 -> 905389.36 | J23: =E23 -> 905389.36 | K23: ='Cost Summary'!E23+'Cost Summary'!E29+'Cost Summary'!E28 -> 905389.36 | L23: =J23-K23 -> 0 | O23: =SUM(P23:U23) -> 905389.36 | P23: ='Cost Summary'!E23 -> 714322.61 | Q23: ='Cost Summary'!E28 -> 19366.75 | R23: ='Cost Summary'!E29 -> 171700
A24: 7 | B24: Exterior Metal Panels | C24: =+E24/$E$3 -> 2.2571616 | E24: ='Cost Summary'!E25 -> 1306135.9
A25: 7 | B25: Roofing and Trim | C25: =+E25/$E$3 -> 2.2803687 | E25: ='Cost Summary'!E26 -> 1319565
A26: 7 | B26: Fireproofing | C26: =+E26/$E$3 -> 0.15219912 | E26: ='Cost Summary'!E27 -> 88072
A27: 8 | B27: Doors / Frames | C27: =+E27/$E$3 -> 2.970493 | E27: ='Cost Summary'!E30-N27 -> 1718914.4 | J27: =E27+E28 -> 2093315.9 | K27: ='Cost Summary'!E30 -> 2093315.9 | L27: =J27-K27 -> 0 | N27: =O27*1.1 -> 374401.5 | O27: =SUM(P27:U27) -> 340365 | P27: ='08 10 DFH'!I155+'08 10 DFH'!I159 -> 340365
A28: 8 | B28: Door & Hardware Installation | C28: =+E28/$E$3 -> 0.6470113 | E28: =N27 -> 374401.5
A29: 8 | B29: Windows / Glazing | C29: =+E29/$E$3 -> 7.3420435 | E29: ='Cost Summary'!E33-N33 -> 4248568.9 | J29: =E29+E33 -> 5059090 | K29: ='Cost Summary'!E33 -> 5059090 | L29: =J29-K29 -> 0
A30: 8 | B30: Hangar Doors - OH Doors Trash Rooms | C30: =+E30/$E$3 -> 0.051454474 | E30: ='Cost Summary'!E32 -> 29774.8
A31: 8 | B31: Bi-parting Doors (5th Floor) | C31: =+E31/$E$3 -> 0.13567439 | E31: =S31 -> 78509.748 | J31: =E31+E32 -> 563645.85 | K31: ='Cost Summary'!E31 -> 563645.85 | L31: =J31-K31 -> 0 | N31: =O31*1.1 -> 0 | P31: ='08 32 Hangar Doors'!G40 -> 77732.424 | Q31: 0.01 | R31: =P31*Q31 -> 777.32424 | S31: =P31+R31 -> 78509.748
A32: 8 | B32: Overhead Hydraulic Doors (1st Floor) | C32: =+E32/$E$3 -> 0.83837414 | E32: =S32 -> 485136.1 | N32: =O32*1.1 -> 0 | P32: ='08 32 Hangar Doors'!G39 -> 480332.77 | Q32: 0.01 | R32: =P32*Q32 -> 4803.3277 | S32: =P32+R32 -> 485136.1
A33: 8 | B33: Curtainwall systems | C33: =+E33/$E$3 -> 1.4006789 | E33: =N33 -> 810521.05 | N33: =O33*1.1 -> 810521.05 | O33: =SUM(P33:U33) -> 736837.32 | P33: =SUM('08 50 Storefront & Windows'!G44:G47) -> 736837.32
A34: 9 | B34: Interior Framing and Gypsum Board | C34: =+E34/$E$3 -> 7.9741863 | E34: ='Cost Summary'!E34 -> 4614366.5
A35: 9 | B35: Acoustical Ceilings | C35: =+E35/$E$3 -> 0.53606206 | E35: ='Cost Summary'!E37 -> 310199.28
A36: 9 | B36: Painting | C36: =+E36/$E$3 -> 1.4731074 | E36: ='Cost Summary'!E41 -> 852432.73
A37: 9 | B37: Carpet, Vinyl Flooring, Tile - Labor | C37: =+E37/$E$3 -> 0.96635455 | E37: ='Cost Summary'!E35+'Cost Summary'!E38 -> 559193.62
A38: 9 | B38: Carpet Vinyl Floor Tile - Material | C38: =+E38/$E$3 -> 1.6956277 | E38: =SUM('ERUA Cost Summary'!E81:E84) -> 981197
A39: 9 | B39: Resinuous Flooring | C39: =+E39/$E$3 -> 0.19667664 | E39: ='Cost Summary'!E40 -> 113809.5
A40: 10 | B40: Specialties | C40: =+E40/$E$3 -> 0.10536298 | E40: ='Cost Summary'!E44 -> 60969.66
A41: 10 | B41: Toilet, Bath Accessories | C41: =+E41/$E$3 -> 0.52880766 | E41: ='Cost Summary'!E43 -> 306001.43
A42: 10 | B42: Interior Signage | C42: =+E42/$E$3 -> 0 | E42: 0
A43: 10 | B43: Exterior Signage | C43: =+E43/$E$3 -> 0 | E43: 0
A44: 10 | B44: Signage Allowance | C44: =+E44/$E$3 -> 0.034562431 | E44: ='Cost Summary'!C42 -> 20000
A45: 11 | B45: Appliances | C45: =+E45/$E$3 -> 0.91488256 | E45: ='Cost Summary'!E45 -> 529408.69
A46: 12 | B46: Cabinets and Countertops | C46: =+E46/$E$3 -> 2.3324264 | E46: ='Cost Summary'!E47+'Cost Summary'!E48 -> 1349688.8 | G46: 0 | H46: =E46-G46 -> 1349688.8
A47: 12 | B47: Window Treatments | C47: =+E47/$E$3 -> 0.28778201 | E47: ='Cost Summary'!E46 -> 166528.8
A48: 13 | B48: Pre-Engineered Canopies | C48: =+E48/$E$3 -> 0.043982404 | E48: ='Cost Summary'!E49 -> 25450.99 | G48: 0 | H48: =E48-G48 -> 25450.99
A49: 14 | B49: Elevators | C49: =+E49/$E$3 -> 1.9791122 | E49: ='Cost Summary'!E50 -> 1145239
A50: 14 | B50: Trash Chutes & Compactors | C50: =+E50/$E$3 -> 0.19974311 | E50: ='Cost Summary'!E51 -> 115583.95
A51: 15 | B51: Mechanical | C51: =+E51/$E$3 -> 0 | E51: 0
A52: 15 | B52: HVAC | C52: =+E52/$E$3 -> 17.986786 | E52: ='Cost Summary'!E55 -> 10408287
A53: 15 | B53: Plumbing Fixtures Package | C53: =+E53/$E$3 -> 1.4170597 | E53: ='Cost Summary'!E54 -> 820000
A54: 15 | B54: Plumbing Systems | C54: =+E54/$E$3 -> 5.8014524 | E54: ='Cost Summary'!E53 -> 3357085.9
A55: 15 | B55: Fire Protection | C55: =+E55/$E$3 -> 2.3132323 | E55: ='Cost Summary'!E52 -> 1338582
A56: 15 | B56: Lightning Protection | C56: =+E56/$E$3 -> 0.15708625 | E56: ='Cost Summary'!E57 -> 90900
A57: 16 | B57: Electrical | C57: =+E57/$E$3 -> 21.200135 | E57: ='Cost Summary'!E56 -> 12267734
A58: 16 | B58: Light Fixture Package | E58: inc Electrical
A59: 16 | B59: Fire Alarm Equipment | E59: inc Electrical
A60: 16 | B60: Head End (low voltage) | E60: inc Comns
A61: 16 | B61: Head End Equipment | E61: inc Comns
A62: 16 | B62: Communications | C62: =+E62/$E$3 -> 2.1204732 | E62: ='Cost Summary'!E58+'Cost Summary'!E59 -> 1227039.4
A63: 16 | B63: Access Control - Eaglecard / Video | C63: =+E63/$E$3 -> 1.5121064 | E63: ='Cost Summary'!E60 -> 875000
A64: 16 | B64: IT AV | E64: inc Comns
A65: 16 | B65: Electronic Safety and Security | E65: inc Access Cont
B66: SUBCONTRACTOR DISCOUNTS | C66: =+E66/$E$3 -> -1.056491 | E66: ='Cost Summary'!E67 -> -611352.25
C67: Sub-total | E67: =SUM(E6:E66) -> 92313568 | H67: =SUM(H6:H66) -> 360901.35
G68: 93676709 | H68: =E67 -> 92313568 | I68: =G68-H68 -> 1363140.9
B69: Additional Items (please include detailed description)
A70: 40 | B70: General Liability Insurance | E70: ='Cost Summary'!C81 -> 1482135.7
A71: 41 | B71: Application & Permit Fees | E71: 0
A72: 43 | B72: O&P | E72: ='Cost Summary'!C83 -> 3624546.2
A73: 44 | B73: Construction Contingency (GC recommendation only) | E73: ='Cost Summary'!C72 -> 0
A74: 45 | B74: Administration Fees | E74: ='Cost Summary'!C79+'Cost Summary'!C80 -> 738508.54
A75: 46 | B75: Additional Items - SDI | E75: ='Cost Summary'!C78 -> 1318120.7
A76: 47 | B76: Builders Risk | E76: ='Cost Summary'!C76 -> 802232.89
C77: Sub-total | E77: =SUM(E69:E76) -> 7965544.1
C78: TOTAL BASE BID | E78: =E67+E77 -> 1.0027911e+08
B79: ALLOWANCES "INCLUDED" IN ABOVE BID
A80: Allowance 1: | B80: Interior Signage | E80: 20000
A81: Allowance 2: | B81: LVT (LSC) | E81: =100027*4.75 -> 475128.25
A82: Allowance 3: | B82: Carpet Tile (CPT-2) | E82: =51810*4 -> 207240
A83: Allowance 4 | B83: Carpet Tile (CPT-1) UC | E83: =12385*4.75 -> 58828.75
A84: Allowance 5: | B84: Porcelain Tile UC | E84: =30000*8 -> 240000
A85: Allowance 6: | B85: Access Control | E85: 500000
A86: Allowance 7: | B86: Electrical Panels | E86: 10000
A87: Allowance 8: | B87: Electrical Service Coordination with FPL | E87: 20000
A88: Allowance 9: | B88: Exterior Gas Line | E88: 15000
A89: Allowance 10: | B89: Miscellaneous Mechanical Devices | E89: 100000
A90: Allowance 11: | B90: Addition Building Width | E90: 500000
A91: Allowance 12: | B91: Rerouting of Existing Site Fiber | E91: 250000
A92: Allowance 13: | B92: Door prep and wiring for electrical and data for electronic access control | E92: 375000
A93: Allowance 14: | B93: Bi-Directional Amplifier (BDA) system balance of design, material and installation. | E93: 247300
A94: Allowance 15: | B94: Garage Level 5 trench drains (not viable per Metromont) | E94: 85000
A96: Allowance 16: | B96: Other Contractor Proposed Allowances
A100: Unit Cost 1: | B100: Cost Allowance for Auto Single Doors | E100: see Add 7 response
C103: Sub-total | E103: =SUM(E80:E94) -> 3103497
B104: ALTERNATES
A105: Alternate 1: | B105: Performance and Payment Bond | E105: ='Alternate & VE'!D9 -> 1113775.1
A106: Alternate 2: | B106: Epoxy Paint in Corridors | E106: ='Alternate & VE'!D10 -> 43288.561
A107: Alternate 3: | B107: Solid Surface Countertop Deduct at Units | E107: ='Alternate & VE'!D11 -> -107152.38
A108: Alternate 4: | B108: Concealed Anchors at Stairs | E108: ='Alternate & VE'!D12 -> -40050.943
...

Sheet Cost Summary
A3: ='Area Calculations'!B4 -> ERAU Residential Hall & Garage Building
A4: ='Area Calculations'!B5 -> Daytona Beach | C4: Gross (sf) | F4: ='Area Calculations'!G4 -> 578663 | G4: Site (acres) | H4: ='Area Calculations'!G6 -> 6.5699725 | M4: Hank
A5: Hard Bid | C5: AC (sf) | F5: ='Area Calculations'!G5 -> 0 | G5: Parking Spcs | H5: ='Area Calculations'!G7 -> 131 | L5: surface | M5: Claudia
A6: =NOW() -> 46085.544 | C6: No. of Units: | F6: ='Area Calculations'!G9 -> 107 | G6: Parking Spcs | H6: ='Area Calculations'!G8 -> 925 | L6: garage | M6: Sam
C7: No. of Beds: | F7: ='Area Calculations'!G10 -> 423 | G7: Build Dur (mo) | H7: ='Area Calculations'!G11 -> 0 | M7: Hunter
E8: 0.01
A9: CSI | B9: CSI DESCRIPTION | C9: TOTAL | E9: =+ 1% -> 0.01 | F9: $ /SF | G9: $ /UNIT | H9: % | I9: Prev. | J9: Delta | K9: Notes
B11: General Conditions | C11: ='GCs & GRs'!L164 -> 3961757.1 | E11: =C11 -> 3961757.1 | F11: =C11/$F$4 -> 6.8463978 | G11: =C11/$F$6 -> 37025.767 | H11: =C11/$C$84 -> 0.039507301 | J11: =C11-I11 -> 3961757.1 | L11: =C11 -> 3961757.1 | M11: =C11/C84 -> 0.039507301 | P11: =E11-C11 -> 0
B12: General Requirements | C12: ='GCs & GRs'!L165 -> 477094.3 | E12: =C12 -> 477094.3 | F12: =C12/$F$4 -> 0.82447694 | G12: =C12/$F$6 -> 4458.8252 | H12: =C12/$C$84 -> 0.0047576638 | J12: =C12-I12 -> 477094.3 | L12: =C12 -> 477094.3 | M12: =C12/C84 -> 0.0047576638 | P12: =E12-C12 -> 0
A13: 02 21 00 | B13: Surveying | C13: ='02 21 Survey '!B94 -> 59300 | D13: =C13 -> 59300 | E13: =C13*(1+$E$8) -> 59893 | F13: =C13/$F$4 -> 0.10247761 | G13: =C13/$F$6 -> 554.20561 | H13: =C13/$C$84 -> 0.00059134947 | J13: =C13-I13 -> 59300 | L13: =C13 -> 59300 | P13: =E13-C13 -> 593
A14: 02 41 00 | B14: Demolition | C14: ='02 41 Demolition'!B91 -> 0 | F14: =C14/$F$4 -> 0 | G14: =C14/$F$6 -> 0 | H14: =C14/$C$84 -> 0 | L14: =C14 -> 0 | P14: =E14-C14 -> 0
A15: 02 50 10 | B15: Site Maintenance / Dumpster / Cleaning | C15: ='02 50 Site Maint'!B97 -> 1781647.2 | E15: =C15 -> 1781647.2 | F15: =C15/$F$4 -> 3.0789029 | G15: =C15/$F$6 -> 16650.909 | H15: =C15/$C$84 -> 0.017766883 | J15: =C15-I15 -> 1781647.2 | L15: =C15 -> 1781647.2 | P15: =E15-C15 -> 0
A16: 03 30 00 | B16: Concrete | C16: ='03 30 CIP Concrete'!$B$132 -> 5700849.3 | D16: =C16 -> 5700849.3 | E16: =C16*(1+$E$8) -> 5757857.8 | F16: =C16/$F$4 -> 9.8517606 | G16: =C16/$F$6 -> 53278.966 | H16: =C16/$C$84 -> 0.056849819 | J16: =C16-I16 -> 5700849.3 | L16: =C16 -> 5700849.3 | P16: =E16-C16 -> 57008.493
A17: 03 41 00 | B17: Precast Hollow Core | C17: ='03 41 Precast Hollow Core'!B124 -> 21767756 | E17: =C17 -> 21767756 | F17: =C17/$F$4 -> 37.617328 | G17: =C17/$F$6 -> 203436.97 | H17: =C17/$C$84 -> 0.21707169 | J17: =C17-I17 -> 21767756 | L17: =C17 -> 21767756 | P17: =E17-C17 -> 0
A18: 04 22 00 | B18: Concrete Unit Masonry | C18: ='04 22 Concrete Unit Masonry'!B92 -> 0 | F18: =C18/$F$4 -> 0 | G18: =C18/$F$6 -> 0 | H18: =C18/$C$84 -> 0 | J18: =C18-I18 -> 0 | L18: =C18 -> 0 | P18: =E18-C18 -> 0
A19: 05 10 00 | B19: Structural Steel | C19: ='05 10 Steel'!B102 -> 349703.77 | D19: =C19 -> 349703.77 | E19: =C19*(1+$E$8) -> 353200.8 | F19: =C19/$F$4 -> 0.60433061 | G19: =C19/$F$6 -> 3268.2595 | H19: =C19/$C$84 -> 0.0034873042 | J19: =C19-I19 -> 349703.77 | L19: =C19 -> 349703.77 | P19: =E19-C19 -> 3497.0377
A20: 05 52 00 | B20: Misc. Metals | C20: ='05 52 Misc. Metals'!B99 -> 334591.49 | D20: =C20 -> 334591.49 | E20: =C20*(1+$E$8) -> 337937.4 | F20: =C20/$F$4 -> 0.57821476 | G20: =C20/$F$6 -> 3127.0233 | H20: =C20/$C$84 -> 0.0033366021 | J20: =C20-I20 -> 334591.49 | L20: =C20 -> 334591.49 | P20: =E20-C20 -> 3345.9149
A21: 06 10 00 | B21: Rough Carpentry | C21: ='06 10 Rough Carpentry'!B91 -> 493891 | E21: =C21 -> 493891 | F21: =C21/$F$4 -> 0.85350368 | G21: =C21/$F$6 -> 4615.8037 | H21: =C21/$C$84 -> 0.0049251633 | J21: =C21-I21 -> 493891 | L21: =C21 -> 493891 | P21: =E21-C21 -> 0
A22: 06 21 00 | B22: Millwork | C22: ='06 21 Millwork'!B96 -> 331487.47 | D22: =C22 -> 331487.47 | E22: =C22*(1+$E$8) -> 334802.35 | F22: =C22/$F$4 -> 0.57285064 | G22: =C22/$F$6 -> 3098.0138 | H22: =C22/$C$84 -> 0.0033056483 | J22: =C22-I22 -> 331487.47 | L22: =C22 -> 331487.47 | P22: =E22-C22 -> 3314.8747
A23: 07 10 00 | B23: Waterproofing | C23: ='07 10 Waterproofing'!B96 -> 707250.11 | D23: =C23 -> 707250.11 | E23: =C23*(1+$E$8) -> 714322.61 | F23: =C23/$F$4 -> 1.2222142 | G23: =C23/$F$6 -> 6609.8141 | H23: =C23/$C$84 -> 0.0070528159 | J23: =C23-I23 -> 707250.11 | L23: =C23 -> 707250.11 | P23: =E23-C23 -> 7072.5011
A24: 07 21 00 | B24: Insulation - INC 09 29 50 | C24: ='07 21 Insulation'!B91 -> 0 | D24: =C24 -> 0 | E24: =C24*(1+$E$8) -> 0 | F24: =C24/$F$4 -> 0 | G24: =C24/$F$6 -> 0 | H24: =C24/$C$84 -> 0 | J24: =C24-I24 -> 0 | L24: =C24 -> 0 | P24: =E24-C24 -> 0
A25: 07 42 00 | B25: Metal Wall Panels | C25: ='07 42 Metal Panel'!B91 -> 1293203.9 | D25: =C25 -> 1293203.9 | E25: =C25*(1+$E$8) -> 1306135.9 | F25: =C25/$F$4 -> 2.2348134 | G25: =C25/$F$6 -> 12086.017 | H25: =C25/$C$84 -> 0.012896044 | J25: =C25-I25 -> 1293203.9 | L25: =C25 -> 1293203.9 | P25: =E25-C25 -> 12932.039
A26: 07 50 00 | B26: Roofing | C26: ='07 50 Roofing'!B94 -> 1306500 | D26: =C26 -> 1306500 | E26: =C26*(1+$E$8) -> 1319565 | F26: =C26/$F$4 -> 2.2577908 | G26: =C26/$F$6 -> 12210.28 | H26: =C26/$C$84 -> 0.013028636 | J26: =C26-I26 -> 1306500 | L26: =C26 -> 1306500 | P26: =E26-C26 -> 13065
A27: 07 81 00 | B27: Spray Fireproofing | C27: ='07 81 Spray Fireproofing'!B91 -> 87200 | D27: =C27 -> 87200 | E27: =C27*(1+$E$8) -> 88072 | F27: =C27/$F$4 -> 0.1506922 | G27: =C27/$F$6 -> 814.95327 | H27: =C27/$C$84 -> 0.00086957292 | J27: =C27-I27 -> 87200 | L27: =C27 -> 87200 | P27: =E27-C27 -> 872
A28: 07 84 00 | B28: Firestopping | C28: ='07 84 Firestopping'!B91 -> 19175 | D28: =C28 -> 19175 | E28: =C28*(1+$E$8) -> 19366.75 | F28: =C28/$F$4 -> 0.033136731 | G28: =C28/$F$6 -> 179.20561 | H28: =C28/$C$84 -> 0.00019121629 | J28: =C28-I28 -> 19175 | L28: =C28 -> 19175 | P28: =E28-C28 -> 191.75
A29: 07 92 00 | B29: Expansion Joints | C29: ='07 92 Exp Joint'!B91 -> 170000 | D29: =C29 -> 170000 | E29: =C29*(1+$E$8) -> 171700 | F29: =C29/$F$4 -> 0.29378066 | G29: =C29/$F$6 -> 1588.785 | H29: =C29/$C$84 -> 0.0016952683 | J29: =C29-I29 -> 170000 | L29: =C29 -> 170000 | P29: =E29-C29 -> 1700
A30: 08 10 70 | B30: Doors, Frames, & Hardware | C30: ='08 10 DFH'!B207 -> 2072590 | D30: =C30 -> 2072590 | E30: =C30*(1+$E$8) -> 2093315.9 | F30: =C30/$F$4 -> 3.5816874 | G30: =C30/$F$6 -> 19370 | H30: =C30/$C$84 -> 0.020668213 | J30: =C30-I30 -> 2072590 | L30: =C30 -> 2072590 | P30: =E30-C30 -> 20725.9
A31: 08 32 00 | B31: Hangar Doors | C31: ='08 32 Hangar Doors'!$B$92 -> 558065.19 | D31: =C31 -> 558065.19 | E31: =C31*(1+$E$8) -> 563645.85 | F31: =C31/$F$4 -> 0.96440449 | G31: =C31/$F$6 -> 5215.5626 | H31: =C31/$C$84 -> 0.005565119 | J31: =C31-I31 -> 558065.19 | L31: =C31 -> 558065.19 | M31: 0.01 | N31: =L31*M31 -> 5580.6519 | O31: =L31+N31 -> 563645.85 | P31: =E31-C31 -> 5580.6519 | Q31: =P31/L31 -> 0.01
A32: 08 33 00 | B32: Overhead Doors | C32: ='08 33 Overhead doors'!B94 -> 29480 | D32: =C32 -> 29480 | E32: =C32*(1+$E$8) -> 29774.8 | F32: =C32/$F$4 -> 0.050945023 | G32: =C32/$F$6 -> 275.51402 | H32: =C32/$C$84 -> 0.00029397947 | J32: =C32-I32 -> 29480 | L32: =C32 -> 29480 | P32: =E32-C32 -> 294.8
A33: 08 50 00 | B33: Storefront & Windows | C33: ='08 50 Storefront & Windows'!B161 -> 5009000 | D33: =C33 -> 5009000 | E33: =C33*(1+$E$8) -> 5059090 | F33: =C33/$F$4 -> 8.6561608 | G33: =C33/$F$6 -> 46813.084 | H33: =C33/$C$84 -> 0.049950582 | J33: =C33-I33 -> 5009000 | L33: =C33 -> 5009000 | P33: =E33-C33 -> 50090
A34: 09 29 50 | B34: Drywall & Framing | C34: ='09 29 Drywall & Frame'!B94 -> 4568679.8 | D34: =C34 -> 4568679.8 | E34: =C34*(1+$E$8) -> 4614366.5 | F34: =C34/$F$4 -> 7.8952339 | G34: =C34/$F$6 -> 42697.942 | H34: =C34/$C$84 -> 0.045559635 | J34: =C34-I34 -> 4568679.8 | L34: =C34 -> 4568679.8 | P34: =E34-C34 -> 45686.798
A35: 09 30 00 | B35: Tile | C35: ='09 30 Tile'!B78-C36 -> 219979.27 | D35: =C35 -> 219979.27 | E35: =C35*(1+$E$8) -> 222179.07 | F35: =C35/$F$4 -> 0.38015092 | G35: =C35/$F$6 -> 2055.8811 | H35: =C35/$C$84 -> 0.00219367 | J35: =C35-I35 -> 219979.27 | L35: =C35 -> 219979.27 | P35: =E35-C35 -> 2199.7927
B36: Tile mat allowance | C36: ='ERUA Cost Summary'!E84 -> 240000 | E36: =C36 -> 240000 | P36: =E36-C36 -> 0
A37: 09 51 00 | B37: Acoustical Ceilings | C37: ='09 51 ACT'!B77 -> 307128 | D37: =C37 -> 307128 | E37: =C37*(1+$E$8) -> 310199.28 | F37: =C37/$F$4 -> 0.53075452 | G37: =C37/$F$6 -> 2870.3551 | H37: =C37/$C$84 -> 0.0030627316 | J37: =C37-I37 -> 307128 | L37: =C37 -> 307128 | P37: =E37-C37 -> 3071.28
A38: 09 60 00 | B38: Flooring | C38: ='09 60 Flooring'!B81-C39 -> 333677.78 | D38: =C38 -> 333677.78 | E38: =C38*(1+$E$8) -> 337014.55 | F38: =C38/$F$4 -> 0.57663575 | G38: =C38/$F$6 -> 3118.4839 | H38: =C38/$C$84 -> 0.0033274903 | J38: =C38-I38 -> 333677.78 | L38: =C38 -> 333677.78 | P38: =E38-C38 -> 3336.7778
B39: Flooring Mat Allowance | C39: ='ERUA Cost Summary'!E81+'ERUA Cost Summary'!E82+'ERUA Cost Summary'!E83 -> 741197 | E39: =C39 -> 741197 | P39: =E39-C39 -> 0
A40: 09 96 00 | B40: Fluid-Applied Flooring | C40: ='09 96 Fluid Applied Flooring'!B74 -> 112682.67 | D40: =C40 -> 112682.67 | E40: =C40*(1+$E$8) -> 113809.5 | F40: =C40/$F$4 -> 0.19472935 | G40: =C40/$F$6 -> 1053.1091 | H40: =C40/$C$84 -> 0.0011236903 | J40: =C40-I40 -> 112682.67 | L40: =C40 -> 112682.67 | P40: =E40-C40 -> 1126.8267
A41: 09 90 00 | B41: Painting | C41: ='09 90 Painting'!B90 -> 843992.8 | D41: =C41 -> 843992.8 | E41: =C41*(1+$E$8) -> 852432.73 | F41: =C41/$F$4 -> 1.4585221 | G41: =C41/$F$6 -> 7887.7832 | H41: =C41/$C$84 -> 0.0084164367 | J41: =C41-I41 -> 843992.8 | L41: =C41 -> 843992.8 | P41: =E41-C41 -> 8439.928
A42: 10 14 00 | B42: Signage (Allowance) | C42: ='10 14 Signage'!B68 -> 20000 | E42: =C42 -> 20000 | F42: =C42/$F$4 -> 0.034562431 | G42: =C42/$F$6 -> 186.91589 | H42: =C42/$C$84 -> 0.00019944333 | J42: =C42-I42 -> 20000 | L42: =C42 -> 20000 | P42: =E42-C42 -> 0
A43: 10 20 00 | B43: Bath Accessories | C43: ='10 20 Toilet Partitions & Bath'!B88 -> 302971.71 | D43: =C43 -> 302971.71 | E43: =C43*(1+$E$8) -> 306001.43 | F43: =C43/$F$4 -> 0.52357194 | G43: =C43/$F$6 -> 2831.5113 | H43: =C43/$C$84 -> 0.0030212843 | J43: =C43-I43 -> 302971.71 | L43: =C43 -> 302971.71 | P43: =E43-C43 -> 3029.7171
A44: 10 44 00 | B44: Fire Extinguishers | C44: ='10 44 Fire Extinguishers'!B69 -> 60366 | D44: =C44 -> 60366 | E44: =C44*(1+$E$8) -> 60969.66 | F44: =C44/$F$4 -> 0.10431979 | G44: =C44/$F$6 -> 564.16822 | H44: =C44/$C$84 -> 0.0006019798 | J44: =C44-I44 -> 60366 | L44: =C44 -> 60366 | P44: =E44-C44 -> 603.66
A45: 11 30 00 | B45: Appliances | C45: ='11 30 Appliances'!B90 -> 524167.02 | D45: =C45 -> 524167.02 | E45: =C45*(1+$E$8) -> 529408.69 | F45: =C45/$F$4 -> 0.90582432 | G45: =C45/$F$6 -> 4898.7572 | H45: =C45/$C$84 -> 0.0052270808 | J45: =C45-I45 -> 524167.02 | L45: =C45 -> 524167.02 | P45: =E45-C45 -> 5241.6702
A46: 12 20 00 | B46: Window Treatment | C46: ='12 20 Window Treatment'!B72 -> 164880 | D46: =C46 -> 164880 | E46: =C46*(1+$E$8) -> 166528.8 | F46: =C46/$F$4 -> 0.28493268 | G46: =C46/$F$6 -> 1540.9346 | H46: =C46/$C$84 -> 0.0016442108 | J46: =C46-I46 -> 164880 | L46: =C46 -> 164880 | P46: =E46-C46 -> 1648.8
A47: 12 34 00 | B47: Residential Casework | C47: ='12 34 Residential Casework'!B102 -> 785367.18 | D47: =C47 -> 785367.18 | E47: =C47*(1+$E$8) -> 793220.85 | F47: =C47/$F$4 -> 1.3572099 | G47: =C47/$F$6 -> 7339.8802 | H47: =C47/$C$84 -> 0.0078318123 | J47: =C47-I47 -> 785367.18 | L47: =C47 -> 785367.18 | P47: =E47-C47 -> 7853.6718
A48: 12 36 00 | B48: Solid Surface / Countertops | C48: ='12 36 Solid Surface'!B93 -> 550958.41 | D48: =C48 -> 550958.41 | E48: =C48*(1+$E$8) -> 556467.99 | F48: =C48/$F$4 -> 0.9521231 | G48: =C48/$F$6 -> 5149.144 | H48: =C48/$C$84 -> 0.005494249 | J48: =C48-I48 -> 550958.41 | L48: =C48 -> 550958.41 | P48: =E48-C48 -> 5509.5841
A49: 13 30 00 | B49: Fabricated Engineered Structures | C49: ='13 30 Fab Eng Structures'!B92 -> 25199 | D49: =C49 -> 25199 | E49: =C49*(1+$E$8) -> 25450.99 | F49: =C49/$F$4 -> 0.043546935 | G49: =C49/$F$6 -> 235.50467 | H49: =C49/$C$84 -> 0.00025128862 | J49: =C49-I49 -> 25199 | L49: =C49 -> 25199 | P49: =E49-C49 -> 251.99
A50: 14 20 00 | B50: Elevators | C50: ='14 20 Elevators'!B121 -> 1133900 | D50: =C50 -> 1133900 | E50: =C50*(1+$E$8) -> 1145239 | F50: =C50/$F$4 -> 1.959517 | G50: =C50/$F$6 -> 10597.196 | H50: =C50/$C$84 -> 0.01130744 | J50: =C50-I50 -> 1133900 | L50: =C50 -> 1133900 | P50: =E50-C50 -> 11339
A51: 14 91 00 | B51: Trash Chute | C51: ='14 91 Trash Chutes'!B102 -> 114439.55 | D51: =C51 -> 114439.55 | E51: =C51*(1+$E$8) -> 115583.95 | F51: =C51/$F$4 -> 0.19776545 | G51: =C51/$F$6 -> 1069.5285 | H51: =C51/$C$84 -> 0.0011412102 | J51: =C51-I51 -> 114439.55 | L51: =C51 -> 114439.55 | P51: =E51-C51 -> 1144.3955
A52: 21 13 00 | B52: Fire Protection Systems | C52: ='21 13 Fire Protection'!B88 -> 1325328.7 | D52: =C52 -> 1325328.7 | E52: =C52*(1+$E$8) -> 1338582 | F52: =C52/$F$4 -> 2.290329 | G52: =C52/$F$6 -> 12386.249 | H52: =C52/$C$84 -> 0.013216398 | J52: =C52-I52 -> 1325328.7 | L52: =C52 -> 1325328.7 | P52: =E52-C52 -> 13253.287
A53: 22 00 00 | B53: Plumbing | C53: ='22 00 Plumbing '!B144-C54 -> 3323847.4 | D53: =C53 -> 3323847.4 | E53: =C53*(1+$E$8) -> 3357085.9 | F53: =C53/$F$4 -> 5.7440123 | G53: =C53/$F$6 -> 31063.994 | H53: =C53/$C$84 -> 0.03314596 | J53: =C53-I53 -> 3323847.4 | L53: =C53 -> 3323847.4 | P53: =E53-C53 -> 33238.474
B54: Plumbing fixtures | C54: 820000 | E54: =C54 -> 820000 | P54: =E54-C54 -> 0
A55: 23 00 00 | B55: HVAC | C55: ='23 00 HVAC'!B124 -> 10305235 | D55: =C55 -> 10305235 | E55: =C55*(1+$E$8) -> 10408287 | F55: =C55/$F$4 -> 17.808699 | G55: =C55/$F$6 -> 96310.607 | H55: =C55/$C$84 -> 0.10276552 | J55: =C55-I55 -> 10305235 | L55: =C55 -> 10305235 | P55: =E55-C55 -> 103052.35
A56: 26 00 00 | B56: Electrical | C56: ='26 00 Electrical'!B147 -> 12146271 | D56: =C56 -> 12146271 | E56: =C56*(1+$E$8) -> 12267734 | F56: =C56/$F$4 -> 20.990233 | G56: =C56/$F$6 -> 113516.55 | H56: =C56/$C$84 -> 0.12112464 | J56: =C56-I56 -> 12146271 | L56: =C56 -> 12146271 | P56: =E56-C56 -> 121462.71
A57: 26 41 00 | B57: Lightning Protection | C57: ='26 41 Lighting Protection'!B72 -> 90000 | D57: =C57 -> 90000 | E57: =C57*(1+$E$8) -> 90900 | F57: =C57/$F$4 -> 0.15553094 | G57: =C57/$F$6 -> 841.1215 | H57: =C57/$C$84 -> 0.00089749499 | J57: =C57-I57 -> 90000 | L57: =C57 -> 90000 | P57: =E57-C57 -> 900
A58: 27 00 00 | B58: Communications | C58: ='27 00 Communications'!B142 -> 960826.5 | D58: =C58 -> 960826.5 | E58: =C58*(1+$E$8) -> 970434.77 | F58: =C58/$F$4 -> 1.660425 | G58: =C58/$F$6 -> 8979.6869 | H58: =C58/$C$84 -> 0.0095815218 | J58: =C58-I58 -> 960826.5 | L58: =C58 -> 960826.5 | P58: =E58-C58 -> 9608.265
A59: 27 53 00 | B59: Bi-Directional Amplification (BDA) | C59: ='27 53 BDA'!B92 -> 254064 | D59: =C59 -> 254064 | E59: =C59*(1+$E$8) -> 256604.64 | F59: =C59/$F$4 -> 0.43905347 | G59: =C59/$F$6 -> 2374.4299 | H59: =C59/$C$84 -> 0.0025335685 | J59: =C59-I59 -> 254064 | L59: =C59 -> 254064 | P59: =E59-C59 -> 2540.64
A60: 28 10 00 | B60: Access Control (Allowance) | C60: ='27 00 Communications'!I142+'27 00 Communications'!I143 -> 875000 | E60: =C60 -> 875000 | F60: =C60/$F$4 -> 1.5121064 | G60: =C60/$F$6 -> 8177.5701 | H60: =C60/$C$84 -> 0.0087256457 | J60: =C60-I60 -> 875000 | L60: =C60 -> 875000 | P60: =E60-C60 -> 0
A61: 28 46 00 | B61: Fire Detection & Alarm | C61: Inc electrical | J61: 0
A62: 31 30 10 | B62: Sitework | C62: ='31 30 Site Work'!B192 -> 2548634 | D62: =C62 -> 2548634 | E62: =C62*(1+$E$8) -> 2574120.4 | F62: =C62/$F$4 -> 4.4043494 | G62: =C62/$F$6 -> 23819.01 | H62: =C62/$C$84 -> 0.025415403 | J62: =C62-I62 -> 2548634 | L62: =C62 -> 2548634 | P62: =E62-C62 -> 25486.34
A63: 31 32 00 | B63: Soil Stabilization | C63: ='31 32 Soil Stabilization'!B93 -> 1306674 | D63: =C63 -> 1306674 | E63: =C63*(1+$E$8) -> 1319740.7 | F63: =C63/$F$4 -> 2.2580914 | G63: =C63/$F$6 -> 12211.906 | H63: =C63/$C$84 -> 0.01303037 | J63: =C63-I63 -> 1306674 | L63: =C63 -> 1306674 | P63: =E63-C63 -> 13066.74
A64: 32 14 00 | B64: Brick Pavers | C64: ='32 14 Pavers'!B92 -> 126191.82 | D64: =C64 -> 126191.82 | E64: =C64*(1+$E$8) -> 127453.74 | F64: =C64/$F$4 -> 0.2180748 | G64: =C64/$F$6 -> 1179.3628 | H64: =C64/$C$84 -> 0.0012584058 | J64: =C64-I64 -> 126191.82 | L64: =C64 -> 126191.82 | P64: =E64-C64 -> 1261.9182
A65: 32 33 00 | B65: Site Furniture | C65: ='32 33 Site Furniture'!B99 -> 209676.36 | D65: =C65 -> 209676.36 | E65: =C65*(1+$E$8) -> 211773.12 | F65: =C65/$F$4 -> 0.36234623 | G65: =C65/$F$6 -> 1959.5921 | H65: =C65/$C$84 -> 0.0020909275 | J65: =C65-I65 -> 209676.36 | L65: =C65 -> 209676.36 | P65: =E65-C65 -> 2096.7636
A66: 32 80 00 | B66: Landscaping & Irrigation | C66: ='32 80 Landscape'!B138 -> 461690.97 | D66: =C66 -> 461690.97 | E66: =C66*(1+$E$8) -> 466307.88 | F66: =C66/$F$4 -> 0.79785811 | G66: =C66/$F$6 -> 4314.8689 | H66: =C66/$C$84 -> 0.0046040592 | J66: =C66-I66 -> 461690.97 | L66: =C66 -> 461690.97 | P66: =E66-C66 -> 4616.9097
B67: SUBCONTRACTOR DISCOUNTS | E67: =P67 -> -611352.25 | N67: =SUM(D11:D66) -> 61135225 | O67: =SUM(E11:E66)-E11-E12-E15-E17-E21-E36-E39-E42-E54-E60 -> 61746577 | P67: =N67-O67 -> -611352.25
J68: =C68-I68 -> 0
A69: 35 50 00 | B69: Marine - Construction & Equipment | F69: =C69/$F$4 -> 0 | G69: =C69/$F$6 -> 0 | H69: =C69/$C$84 -> 0 | J69: =C69-I69 -> 0
A70: 41 22 00 | B70: Crane and Hoist
B71: SUB-TOTAL 1 (Cost of Work)Building | C71: =SUM(C11:C69) -> 92313568 | E71: =SUM(E11:E69) -> 92313568 | F71: =SUM(F11:F69) -> 156.41638 | G71: =SUM(G11:G69) -> 845910.01 | H71: =SUM(H11:H69) -> 0.90260443 | I71: =SUM(I13:I69) -> 0 | J71: =C71-I71 -> 92313568 | Q71: Cost Summary | R71: =C71 -> 92313568
B72: GC Contingency | C72: =C71*L72 -> 0 | F72: =C72/$F$4 -> 0 | G72: =C72/$F$6 -> 0 | H72: =C72/$C$84 -> 0 | J72: =C72-I72 -> 0 | L72: 0 | Q72: ERAU Cost Summary | R72: ='ERUA Cost Summary'!E67 -> 92313568
B73: Escalation Contingency | C73: =C71*L73 -> 0 | H73: =C73/$C$84 -> 0 | J73: =C73-I73 -> 0 | L73: 0 | Q73: Delta | R73: =R72-R71 -> 0
B74: SUB-TOTAL 2 (Contingency) | C74: =SUM(C71:C73) -> 92313568 | F74: =SUM(F71:F73) -> 156.41638 | G74: =SUM(G71:G73) -> 845910.01 | H74: =SUM(H71:H73) -> 0.90260443 | I74: =SUM(I71:I73) -> 0 | J74: =SUM(J71:J73) -> 92313568
B75: Permits | C75: By owner | O75: /100 | P75: 0.8
B76: Builders Risk Insurance & Deductibles | C76: =L76*C84 -> 802232.89 | L76: 0.008 | N76: =C84 -> 1.0027911e+08 | O76: =N76/100 -> 1002791.1 | P76: =O76*P75 -> 802232.89
B77: Performance & Payment Bond - Alternate | C77: =C12*L77 -> 0 | F77: =C77/$F$4 -> 0 | G77: =C77/$F$6 -> 0 | H77: =C77/$C$84 -> 0 | L77: 0
B78: Subcontractor Default Insurance | C78: =(C74-C11-C12)*L78 -> 1318120.7 | F78: =C78/$F$4 -> 2.2778729 | G78: =C78/$F$6 -> 12318.885 | H78: =C78/$C$84 -> 0.01314452 | J78: =C78-I78 -> 1318120.7 | L78: 0.015
B79: Warranty | C79: =C74*L79 -> 507724.62 | F79: =C79/$F$4 -> 0.87740986 | G79: =C79/$F$6 -> 4745.0899 | H79: =C79/$C$84 -> 0.0050631145 | L79: 0.0055
B80: Procore | C80: =C74*L80 -> 230783.92 | F80: =C80/$F$4 -> 0.39882266 | G80: =C80/$F$6 -> 2156.8591 | H80: =C80/$C$84 -> 0.0023014157 | L80: 0.0025
B81: General Liability Insurance | C81: =(C78+C79+C80+C12+C11+C74)*L81 -> 1482135.7 | F81: =C81/$F$4 -> 2.5613107 | G81: =C81/$F$6 -> 13851.736 | H81: =C81/$C$84 -> 0.014780104 | J81: =C81-I81 -> 1482135.7 | L81: 0.015
B82: SUB-TOTAL 3 (Bonds, Insurances, & GC's) | C82: =SUM(C74:C81) -> 96654566 | F82: =SUM(F74:F81) -> 162.53179 | G82: =SUM(G74:G81) -> 878982.58 | H82: =SUM(H74:H81) -> 0.93789359 | I82: =SUM(I74:I81) -> 0 | J82: =SUM(J74:J81) -> 95113824
B83: GC Fee (OH&P) | C83: =C82*L83 -> 3624546.2 | F83: =C83/$F$4 -> 6.2636564 | G83: =C83/$F$6 -> 33874.264 | H83: =C83/$C$84 -> 0.036144578 | J83: =C83-I83 -> 3624546.2 | L83: 0.0375
B84: ESTIMATE TOTAL | C84: =SUM(C82:C83) -> 1.0027911e+08 | F84: =SUM(F82:F83) -> 168.79545 | G84: =SUM(G82:G83) -> 912856.84 | H84: =SUM(H82:H83) -> 0.97403816 | I84: =SUM(I82:I83) -> 0 | J84: =SUM(J82:J83) -> 98738370
B87: Performance & Payment Bond | C87: =C84*L87 -> 1002791.1 | F87: =C87/$F$4 -> 1.7329449 | G87: =C87/$F$6 -> 9371.8796 | H87: =C87/$C$84 -> 0.01 | L87: 0.01
B89: Cost Summary from above | C89: =C84 -> 1.0027911e+08
B90: ERAU Cost Summary | C90: ='ERUA Cost Summary'!E78 -> 1.0027911e+08 | F90: GROSS MARGIN
B91: Delta | C91: =C90-C89 -> 0 | F91: COST % | G91: COST | H91: BILLABLE | K91: BILLABLE | L91: MARGIN
E92: Missed Scope | L92: =-C71*M92 -> -923135.68 | M92: 0.01
B93: ESTIMATE TOTAL | C93: =C84 -> 1.0027911e+08 | E93: Additional Buyout | L93: =(E71-E56)*M93 -> 1600916.7 | M93: 0.02
B94: BM | C94: =99677000+777481 -> 100454481 | E94: Buyout/Electrician | M94: =L94/C84 -> 0
C95: =C93-C94 -> -175369.23 | E95: SDI | F95: 0.0075 | G95: =F95*(C74-C11-C12) -> 659060.37 | H95: =C78 -> 1318120.7 | L95: =H95-G95 -> 659060.37 | M95: =L95/$C$84 -> 0.0065722598
E96: GL | F96: 0.009 | G96: =C84*F96 -> 902512.01 | H96: =C81 -> 1482135.7 | L96: =H96-G96 -> 579623.72 | M96: =L96/$C$84 -> 0.0057801042
B97: ESTIMATE TOTAL | C97: 100334156 | E97: FEE | L97: =C83 -> 3624546.2 | M97: =L97/$C$84 -> 0.036144578
B98: BM | C98: =99677000+777481 -> 100454481 | L98: =SUM(L92:L97) -> 5541011.3 | M98: =L98/C84 -> 0.055255887
C99: =C97-C98 -> -120325
C102: =C84-35000000 -> 65279112
B103: KEEP THIS TO ONE PAGE !!!!
C104: =C102/F7 -> 154324.14

Sheet GCs & GRs
A1: Contract Reference | B1: General Condition Ref. | C1: TEST
C3: Construction | F3: Activity | H3: Start | I3: Finish | J3: Days | K3: Weeks | L3: Months | M3: % Time | N3: Remarks | Q3: 45915 | R3: 45932 | S3: 46629 | T3: 46628
F4: Construction | H4: 45931 | I4: =H4+J4 -> 46630 | J4: 699 | K4: =SUM(J4/7) -> 99.857143 | L4: =SUM(J4/30) -> 23.3 | Q4: 46612 | R4: =R3+Q5 -> 46629 | S4: 46588 | T4: =T3-S5 -> 46587
F5: Close Out | J5: =L5*30.42 -> 60.84 | K5: =L5*4.33 -> 8.66 | L5: 2 | Q5: =Q4-Q3 -> 697 | S5: =S3-S4 -> 41
F6: General Conditions | H6: General Req. - Field Office | J6: General Req. | L6: Total
C7: Description | D7: Qty. | E7: U | F7: Unit | G7: Const. | H7: Unit | I7: General | J7: Unit | K7: General | O7: CUSTOMIZED LABOR RATES
F8: Cost | G8: Cond. | H8: Cost | I8: Req. | J8: Cost | K8: Req.
C9: Field Labor - Construction | L9: =SUM(L10:L27) -> 3717618.1
A10: 1 | C10: Project Executive | D10: ='Staffing Schedule '!AE27 -> 56.29 | E10: wks | F10: =(O10*40)*M10 -> 6306.6625 | G10: =SUM(D10*F10) -> 355002.03 | L10: =SUM(G10+I10+K10) -> 355002.03 | M10: 1 | O10: ='Labor Rates'!G8 -> 157.66656
A11: =A10+1 -> 2 | C11: Senior Project Manager | D11: ='Staffing Schedule '!AE28 -> 99.59 | E11: wks | F11: =(O11*40)*M11 -> 5226.99 | G11: =SUM(D11*F11) -> 520555.93 | L11: =SUM(G11+I11+K11) -> 520555.93 | M11: 1 | O11: ='Labor Rates'!G9 -> 130.67475
A12: =A11+1 -> 3 | C12: Project Manager - Level 3 | D12: ='Staffing Schedule '!AE28 -> 99.59 | E12: wks | F12: =(O12*40)*M12 -> 0 | G12: =SUM(D12*F12) -> 0 | L12: =SUM(G12+I12+K12) -> 0 | M12: 0 | O12: ='Labor Rates'!G10 -> 120.34132
A13: =A12+1 -> 4 | C13: Project Manager - Level 2 | D13: =$K$4 -> 99.857143 | E13: wks | F13: =(O13*40)*M13 -> 0 | G13: =SUM(D13*F13) -> 0 | L13: =SUM(G13+I13+K13) -> 0 | M13: 0 | O13: ='Labor Rates'!G11 -> 110.14476
A14: =A13+1 -> 5 | C14: Project Manager - Level 1 | D14: =$K$4 -> 99.857143 | E14: wks | F14: =(O14*40)*M14 -> 3770.6242 | G14: =SUM(D14*F14) -> 376523.76 | L14: =SUM(G14+I14+K14) -> 376523.76 | M14: 1 | O14: ='Labor Rates'!G12 -> 94.265604
A15: =A14+1 -> 6 | C15: Project Administator | D15: ='Staffing Schedule '!AE31 -> 103.92 | E15: wks | F15: =(O15*40)*M15 -> 2660.2099 | G15: =SUM(D15*F15) -> 276449.01 | L15: =SUM(G15+I15+K15) -> 276449.01 | M15: 1 | O15: ='Labor Rates'!G13 -> 66.505247
A16: =A15+1 -> 7 | C16: Project Accountant | D16: ='Staffing Schedule '!AE30 -> 56.29 | E16: wks | F16: =(O16*40)*M16 -> 3432.4016 | G16: =SUM(D16*F16) -> 193209.89 | L16: =SUM(G16+I16+K16) -> 193209.89 | M16: 1 | O16: ='Labor Rates'!G14 -> 85.81004
A17: =A16+1 -> 8 | C17: Assistant Project Manager | D17: ='Staffing Schedule '!AE29 -> 103.92 | E17: wks | F17: =(O17*40)*M17 -> 3309.3425 | G17: =SUM(D17*F17) -> 343906.88 | L17: =SUM(G17+I17+K17) -> 343906.88 | M17: 1 | O17: ='Labor Rates'!G15 -> 82.733564
A18: =A17+1 -> 9 | C18: Superintendent - Level 3 | D18: ='Staffing Schedule '!AE23 -> 99.59 | E18: wks | F18: =(O18*40)*M18 -> 5270.0795 | G18: =SUM(D18*F18) -> 524847.22 | L18: =SUM(G18+I18+K18) -> 524847.22 | M18: 1 | O18: ='Labor Rates'!G16 -> 131.75199
A19: =A18+1 -> 10 | C19: Superintendent - Level 2 | D19: ='Staffing Schedule '!AE25 -> 82.27 | E19: wks | F19: =(O19*40)*M19 -> 4423.6891 | G19: =SUM(D19*F19) -> 363936.9 | L19: =SUM(G19+I19+K19) -> 363936.9 | M19: 1 | O19: ='Labor Rates'!G17 -> 110.59223
A20: =A19+1 -> 11 | C20: Superintendent - Level 1 | D20: 0 | E20: wks | F20: =(O20*40)*M20 -> 0 | G20: =SUM(D20*F20) -> 0 | L20: =SUM(G20+I20+K20) -> 0 | M20: 0 | O20: ='Labor Rates'!G18 -> 90.514804
A21: =A20+1 -> 12 | C21: Assistant Superinterndent #1 | D21: ='Staffing Schedule '!AE24 -> 103.92 | E21: wks | F21: =(O21*40)*M21 -> 2396.6186 | G21: =SUM(D21*F21) -> 249056.61 | L21: =SUM(G21+I21+K21) -> 249056.61 | M21: 1 | O21: ='Labor Rates'!G19 -> 59.915466
A22: =A21+1 -> 13 | C22: Assistant Superinterndent #2 | D22: ='Staffing Schedule '!AE26 -> 86.6 | E22: wks | F22: =(O22*40)*M22 -> 2396.6186 | G22: =SUM(D22*F22) -> 207547.17 | L22: =SUM(G22+I22+K22) -> 207547.17 | M22: 1 | O22: =O21 -> 59.915466
A23: =A22+1 -> 14 | C23: Quality Control Manager | D23: =$K$4 -> 99.857143 | E23: wks | F23: =(O23*40)*M23 -> 823.4591 | G23: =SUM(D23*F23) -> 82228.273 | L23: =SUM(G23+I23+K23) -> 82228.273 | M23: 0.2 | O23: ='Labor Rates'!G20 -> 102.93239
A24: =A23+1 -> 15 | C24: Foreman | D24: =$K$4 -> 99.857143 | E24: wks | F24: =(O24*40)*M24 -> 0 | G24: =SUM(D24*F24) -> 0 | L24: =SUM(G24+I24+K24) -> 0 | M24: 0 | O24: ='Labor Rates'!G21 -> 41.528452
A25: =A24+1 -> 16 | C25: Accounting | D25: =$K$4 -> 99.857143 | E25: wks | F25: =(O25*40)*M25 -> 695.62706 | G25: =SUM(D25*F25) -> 69463.331 | L25: =SUM(G25+I25+K25) -> 69463.331 | M25: 0.15 | O25: ='Labor Rates'!G22 -> 115.93784
A26: =A25+1 -> 17 | C26: VDC Manager | D26: 1 | E26: ls | F26: 91195 | G26: =SUM(D26*F26) -> 91195 | L26: =SUM(G26+I26+K26) -> 91195 | O26: ='Labor Rates'!G23 -> 102.72671
A27: =A26+1 -> 18 | C27: Safety Supervisor/Inspector | D27: =K4 -> 99.857143 | E27: wks | F27: =(O27*40)*M27 -> 637.87174 | G27: =SUM(D27*F27) -> 63696.05 | L27: =SUM(G27+I27+K27) -> 63696.05 | M27: 0.2 | O27: ='Labor Rates'!G24 -> 79.733968
C28: Field Labor - Close Out | L28: =SUM(L29:L45) -> 244139.02
A29: 1 | C29: Project Executive | D29: =$K$5 -> 8.66 | E29: wks | F29: =(40*O29)*M29 -> 315.33313 | G29: =SUM(D29*F29) -> 2730.7849 | L29: =SUM(G29+I29+K29) -> 2730.7849 | M29: 0.05 | O29: =O10 -> 157.66656
A30: =A29+1 -> 2 | C30: Senior Project Manager | D30: =$K$5 -> 8.66 | E30: wks | F30: =(40*O30)*M30 -> 5226.99 | G30: =SUM(D30*F30) -> 45265.733 | L30: =SUM(G30+I30+K30) -> 45265.733 | M30: =+M11 -> 1 | O30: =O11 -> 130.67475
A31: =A30+1 -> 3 | C31: Project Manager - Level 3 | D31: =$K$5 -> 8.66 | E31: wks | F31: =(40*O31)*M31 -> 0 | G31: =SUM(D31*F31) -> 0 | L31: =SUM(G31+I31+K31) -> 0 | M31: =+M12 -> 0 | O31: =O12 -> 120.34132
A32: =A31+1 -> 4 | C32: Project Manager - Level 2 | D32: =$K$5 -> 8.66 | E32: wks | F32: =(40*O32)*M32 -> 0 | G32: =SUM(D32*F32) -> 0 | L32: =SUM(G32+I32+K32) -> 0 | M32: =+M13 -> 0 | O32: =O13 -> 110.14476
A33: =A32+1 -> 5 | C33: Project Manager - Level 1 | D33: =$K$5 -> 8.66 | E33: wks | F33: =(40*O33)*M33 -> 3770.6242 | G33: =SUM(D33*F33) -> 32653.605 | L33: =SUM(G33+I33+K33) -> 32653.605 | M33: =+M14 -> 1 | O33: =O14 -> 94.265604
A34: =A33+1 -> 6 | C34: Project Administator | D34: =$K$5 -> 8.66 | E34: wks | F34: =(40*O34)*M34 -> 2660.2099 | G34: =SUM(D34*F34) -> 23037.418 | L34: =SUM(G34+I34+K34) -> 23037.418 | M34: =+M15 -> 1 | O34: =O15 -> 66.505247
A35: =A34+1 -> 7 | C35: Project Accountant | D35: =$K$5 -> 8.66 | E35: wks | F35: =(40*O35)*M35 -> 3432.4016 | G35: =SUM(D35*F35) -> 29724.598 | L35: =SUM(G35+I35+K35) -> 29724.598 | M35: =+M16 -> 1 | O35: =O16 -> 85.81004
A36: =A35+1 -> 8 | C36: Assistant Project Manager | D36: =$K$5 -> 8.66 | E36: wks | F36: =(40*O36)*M36 -> 0 | G36: =SUM(D36*F36) -> 0 | L36: =SUM(G36+I36+K36) -> 0 | M36: 0 | O36: =O17 -> 82.733564
A37: =A36+1 -> 9 | C37: Superintendent - Level 3 | D37: =$K$5 -> 8.66 | E37: wks | F37: =(40*O37)*M37 -> 5270.0795 | G37: =SUM(D37*F37) -> 45638.889 | L37: =SUM(G37+I37+K37) -> 45638.889 | M37: =+M18 -> 1 | O37: =O18 -> 131.75199
A38: =A37+1 -> 10 | C38: Superintendent - Level 2 | D38: =$K$5 -> 8.66 | E38: wks | F38: =(40*O38)*M38 -> 4423.6891 | G38: =SUM(D38*F38) -> 38309.148 | L38: =SUM(G38+I38+K38) -> 38309.148 | M38: =+M19 -> 1 | O38: =O19 -> 110.59223
A39: =A38+1 -> 11 | C39: Superintendent - Level 1 | D39: =$K$5 -> 8.66 | E39: wks | F39: =(40*O39)*M39 -> 0 | G39: =SUM(D39*F39) -> 0 | L39: =SUM(G39+I39+K39) -> 0 | M39: 0 | O39: =O20 -> 90.514804
A40: =A39+1 -> 12 | C40: Assistant Superinterndent | D40: =$K$5 -> 8.66 | E40: wks | F40: =(40*O40)*M40 -> 2396.6186 | G40: =SUM(D40*F40) -> 20754.717 | L40: =SUM(G40+I40+K40) -> 20754.717 | M40: 1 | O40: =O21 -> 59.915466
A41: =A40+1 -> 13 | C41: Quality Control Manager | D41: =$K$5 -> 8.66 | E41: wks | F41: =(40*O41)*M41 -> 0 | G41: =SUM(D41*F41) -> 0 | L41: =SUM(G41+I41+K41) -> 0 | M41: =+M24 -> 0 | O41: =O23 -> 102.93239
A42: =A41+1 -> 14 | C42: Foreman | D42: =$K$5 -> 8.66 | E42: wks | F42: =(40*O42)*M42 -> 0 | G42: =SUM(D42*F42) -> 0 | L42: =SUM(G42+I42+K42) -> 0 | M42: 0 | O42: =O24 -> 41.528452
A43: =A42+1 -> 15 | C43: Accounting | D43: =$K$5 -> 8.66 | E43: wks | F43: =(40*O43)*M43 -> 695.62706 | G43: =SUM(D43*F43) -> 6024.1303 | L43: =SUM(G43+I43+K43) -> 6024.1303 | M43: =+M25 -> 0.15 | O43: =O25 -> 115.93784
A44: =A43+1 -> 16 | C44: VDC Manager | D44: =$K$5 -> 8.66 | E44: wks | F44: =(40*O44)*M44 -> 0 | G44: =SUM(D44*F44) -> 0 | L44: =SUM(G44+I44+K44) -> 0 | M44: 0 | O44: =O26 -> 102.72671
A45: =A44+1 -> 17 | C45: Safety Supervisor/Inspector | D45: =$K$5 -> 8.66 | E45: wks | F45: =(40*O45)*M45 -> 0 | G45: =SUM(D45*F45) -> 0 | L45: =SUM(G45+I45+K45) -> 0 | M45: 0 | O45: =O27 -> 79.733968
C46: Field Office - Contractor | L46: =SUM(L47:L67) -> 171515
C47: Field Office Set Up / Removal - Double Wide | D47: 1 | E47: ea | H47: 16000 | I47: =SUM(D47*H47) -> 16000 | J47: ` | L47: =SUM(G47+I47+K47) -> 16000
C48: Field Office - Double Wide | D48: =$L$4 -> 23.3 | E48: mos | H48: 3500 | I48: =SUM(D48*H48) -> 81550 | L48: =SUM(G48+I48+K48) -> 81550
C49: Field Office Set Up / Removal - Single Wide | D49: 0 | E49: ea | H49: 15958 | I49: =SUM(D49*H49) -> 0 | L49: =SUM(G49+I49+K49) -> 0 | N49: WILLSCOT 4/16/2024 (36x10 mobile office)
C50: Field Office - Single Wide | D50: 0 | E50: mos | H50: 1732 | I50: =SUM(D50*H50) -> 0 | L50: =SUM(G50+I50+K50) -> 0 | N50: WILLSCOT 4/16/2024 (36x10 mobile office)
C51: Field Office Set Up / Removal - Connex | D51: 0 | E51: ea | H51: 1371 | I51: =SUM(D51*H51) -> 0 | L51: =SUM(G51+I51+K51) -> 0 | N51: WILLSCOT 20' COMBO W/10' OFFICE
C52: Field Office - Conex | D52: 0 | E52: mos | H52: 573 | I52: =SUM(D52*H52) -> 0 | L52: =SUM(G52+I52+K52) -> 0 | N52: WILLSCOT 20' COMBO W/10' OFFICE
C53: Connect Telephone Lines | D53: 1 | E53: ea | H53: 2000 | I53: =SUM(D53*H53) -> 2000 | L53: =SUM(G53+I53+K53) -> 2000
C54: Internet | D54: =$L$4 -> 23.3 | E54: mos | H54: 500 | I54: =SUM(D54*H54) -> 11650 | L54: =SUM(G54+I54+K54) -> 11650
C55: Cellular Telephones | D55: =$L$4 -> 23.3 | E55: mos | H55: 0 | I55: =SUM(D55*H55) -> 0 | L55: =SUM(G55+I55+K55) -> 0 | N55: In labor rates
C56: Furniture | D56: 1 | E56: ls | H56: 5000 | I56: =SUM(D56*H56) -> 5000 | L56: =SUM(G56+I56+K56) -> 5000
C57: Office Supplies | D57: =$L$4 -> 23.3 | E57: mos | H57: 500 | I57: =SUM(D57*H57) -> 11650 | L57: =SUM(G57+I57+K57) -> 11650
C58: Drinking Water | D58: =$L$4 -> 23.3 | E58: mos | H58: 200 | I58: =SUM(D58*H58) -> 4660 | L58: =SUM(G58+I58+K58) -> 4660
C59: Janitor Supplies/Cleaning | D59: =$L$4 -> 23.3 | E59: mos | H59: 250 | I59: =SUM(D59*H59) -> 5825 | L59: =SUM(G59+I59+K59) -> 5825
C60: Software Charge | D60: 0.0025 | E60: % | H60: 2.4931481e-91 | I60: =SUM(D60*H60) -> 6.2328703e-94 | L60: =SUM(G60+I60+K60) -> 6.2328703e-94 | N60: .25% of GMP Total
C61: Computers | D61: 1 | E61: ls | H61: 0 | I61: =SUM(D61*H61) -> 0 | L61: =SUM(G61+I61+K61) -> 0
C62: Printers | D62: 0 | E62: ls | H62: 500 | I62: =SUM(D62*H62) -> 0 | L62: =SUM(G62+I62+K62) -> 0
C63: Copy Machine | D63: 1 | E63: ls | H63: 7500 | I63: =SUM(D63*H63) -> 7500 | L63: =SUM(G63+I63+K63) -> 7500
C64: Alarm System | D64: =$L$4 -> 23.3 | E64: mos | H64: 0 | I64: =SUM(D64*H64) -> 0 | L64: =SUM(G64+I64+K64) -> 0
C65: Installation Office Equip. | D65: 0 | E65: ls | H65: 250 | I65: =SUM(D65*H65) -> 0 | L65: =SUM(G65+I65+K65) -> 0
C66: Storage Trailers Set Up / Removal | D66: 2 | E66: ea | H66: 840 | I66: =SUM(D66*H66) -> 1680 | L66: =SUM(G66+I66+K66) -> 1680 | N66: willscot 40' trailer
C67: Storage Trailers | D67: 20 | E67: mos | H67: 1200 | I67: =SUM(D67*H67) -> 24000 | L67: =SUM(G67+I67+K67) -> 24000 | N67: Rate - $1200 ea. per month
C68: Field Office - Owner | N68: =SUM(L69:L83) -> 0
C69: Field Office Set Up / Removal | D69: 1 | E69: ls | J69: 0 | K69: =SUM(D69*J69) -> 0 | L69: =SUM(G69+I69+K69) -> 0 | N69: assume not required
C70: Field Office | D70: =L4 -> 23.3 | E70: mos | J70: 0 | K70: =SUM(D70*J70) -> 0 | L70: =SUM(G70+I70+K70) -> 0 | N70: assume not required
C71: Connect Telephone Lines | D71: 1 | E71: ls | J71: 0 | K71: =SUM(D71*J71) -> 0 | L71: =SUM(G71+I71+K71) -> 0 | N71: assume not required
C72: Telephone | D72: =L4 -> 23.3 | E72: mos | J72: 0 | K72: =SUM(D72*J72) -> 0 | L72: =SUM(G72+I72+K72) -> 0 | N72: assume not required
C73: Cellular Telephones | D73: =L4+L5 -> 25.3 | E73: mos | J73: 0 | K73: =SUM(D73*J73) -> 0 | L73: =SUM(G73+I73+K73) -> 0 | N73: assume not required
C74: Furniture | D74: 1 | E74: ls | J74: 0 | K74: =SUM(D74*J74) -> 0 | L74: =SUM(G74+I74+K74) -> 0 | N74: assume not required
C75: Office Supplies | D75: =L4+L5 -> 25.3 | E75: mos | J75: 0 | K75: =SUM(D75*J75) -> 0 | L75: =SUM(G75+I75+K75) -> 0 | N75: assume not required
C76: Drinking Water | D76: =L4+L5 -> 25.3 | E76: mos | J76: 0 | K76: =SUM(D76*J76) -> 0 | L76: =SUM(G76+I76+K76) -> 0 | N76: assume not required
C77: Janitor Supplies | D77: =L4 -> 23.3 | E77: mos | J77: 0 | K77: =SUM(D77*J77) -> 0 | L77: =SUM(G77+I77+K77) -> 0 | N77: assume not required
C78: Computers | D78: 1 | E78: ls | J78: 0 | K78: =SUM(D78*J78) -> 0 | L78: =SUM(G78+I78+K78) -> 0 | N78: assume not required
C79: Printers | D79: 1 | E79: ls | J79: 0 | K79: =SUM(D79*J79) -> 0 | L79: =SUM(G79+I79+K79) -> 0 | N79: assume not required
C80: Copy Machine | D80: =L4+L5 -> 25.3 | E80: mos | J80: 0 | K80: =SUM(D80*J80) -> 0 | L80: =SUM(G80+I80+K80) -> 0 | N80: assume not required
C81: Fax Machine | D81: 1 | E81: ls | J81: 0 | K81: =SUM(D81*J81) -> 0 | L81: =SUM(G81+I81+K81) -> 0 | N81: assume not required
C82: Alarm System | D82: =L4 -> 23.3 | E82: mos | J82: 0 | K82: =SUM(D82*J82) -> 0 | L82: =SUM(G82+I82+K82) -> 0 | N82: assume not required
C83: Installation Office Equip. | D83: 1 | E83: ls | J83: 0 | K83: =SUM(D83*J83) -> 0 | L83: =SUM(G83+I83+K83) -> 0 | N83: assume not required
C84: Temporary Utilities | L84: =SUM(L85:L97) -> 136289.3
C85: Temp. Electrical Service | D85: 0 | E85: ls | J85: 0 | K85: =SUM(D85*J85) -> 0 | L85: =SUM(G85+I85+K85) -> 0 | N85: by elect sub
C86: Temp. Electrical - Const. Phase | D86: =$L$4 -> 23.3 | E86: mos | J86: 0 | K86: =SUM(D86*J86) -> 0 | L86: =SUM(G86+I86+K86) -> 0 | N86: by owner
C87: Temp. Electrical - Operate Phase | D87: =L4 -> 23.3 | E87: mos | J87: 0 | K87: =SUM(D87*J87) -> 0 | L87: =SUM(G87+I87+K87) -> 0 | N87: by owner
C88: Temp. Wiring & Lighting | D88: 0 | E88: sf | J88: 0 | K88: =SUM(D88*J88) -> 0 | L88: =SUM(G88+I88+K88) -> 0 | N88: by elect sub
C89: Temporary Water - Service | D89: 1 | E89: ls | J89: 150 | K89: =SUM(D89*J89) -> 150 | L89: =SUM(G89+I89+K89) -> 150 | N89: by owner
C90: Temporary Water | D90: =L4 -> 23.3 | E90: mos | J90: 0 | K90: =SUM(D90*J90) -> 0 | L90: =SUM(G90+I90+K90) -> 0
C91: Temporary Toilets | D91: =L4 -> 23.3 | E91: mos | J91: =407*D92 -> 4884 | K91: =SUM(D91*J91) -> 113797.2 | L91: =SUM(G91+I91+K91) -> 113797.2 | N91: 04/15/2024 united site services
C92: Temporary Toilet Set Up / Removal | D92: 12 | E92: ea | J92: 93 | K92: =SUM(D92*J92) -> 1116 | L92: =SUM(G92+I92+K92) -> 1116 | N92: 04/15/2024 united site services
C93: Temporary Washing Station | D93: =L4 -> 23.3 | E93: mos | J93: 407 | K93: =SUM(D93*J93) -> 9483.1 | L93: =SUM(G93+I93+K93) -> 9483.1 | N93: 04/15/2024 united site services
C94: Temporary Washing Station Set Up / Removal | D94: 1 | E94: ea | J94: 93 | K94: =SUM(D94*J94) -> 93 | L94: =SUM(G94+I94+K94) -> 93 | N94: 04/15/2024 united site services
C95: Temporary Holding Tanks | D95: =L4 -> 23.3 | E95: mos | J95: 500 | K95: =SUM(D95*J95) -> 11650 | L95: =SUM(G95+I95+K95) -> 11650
C96: Temporary Ventilation | D96: 0 | E96: ls | J96: 0 | K96: =SUM(D96*J96) -> 0 | L96: =SUM(G96+I96+K96) -> 0
C97: Temporary Cooling | D97: =L4 -> 23.3 | E97: mos | J97: 0 | K97: =SUM(D97*J97) -> 0 | L97: =SUM(G97+I97+K97) -> 0
C98: Equipment | L98: =SUM(L99:L101) -> 93200
C99: Small Tools | D99: =$L$4 -> 23.3 | E99: mos | J99: 1500 | K99: =SUM(D99*J99) -> 34950 | L99: =SUM(G99+I99+K99) -> 34950
C100: Equipment Rental | D100: =L4 -> 23.3 | E100: mos | J100: 2500 | K100: =SUM(D100*J100) -> 58250 | L100: =SUM(G100+I100+K100) -> 58250
C101: Engineering Instruments | D101: 0 | E101: ls | J101: 1000 | K101: =SUM(D101*J101) -> 0 | L101: =SUM(G101+I101+K101) -> 0
...

Sheet Labor Rates
A1: ='Area Calculations'!B4 -> ERAU Residential Hall & Garage Building
A3: Hedrick Brothers Construction Co., Inc.
A4: Salaries and Burden Calculations
C6: MARK-UP | F6: 0
E7: Burdened Rate | F7: Mark-up | G7: Total
B8: 1 | C8: Proj Exec | E8: 157.66656 | F8: =E8*$F$6 -> 0 | G8: =SUM(E8:F8) -> 157.66656
B9: 2 | C9: Sr PM | E9: 130.67475 | F9: =E9*$F$6 -> 0 | G9: =SUM(E9:F9) -> 130.67475
B10: 3 | C10: PM 3 | E10: 120.34132 | F10: =E10*$F$6 -> 0 | G10: =SUM(E10:F10) -> 120.34132
B11: 4 | C11: PM 2 | E11: 110.14476 | F11: =E11*$F$6 -> 0 | G11: =SUM(E11:F11) -> 110.14476
B12: 5 | C12: PM 1 | E12: 94.265604 | F12: =E12*$F$6 -> 0 | G12: =SUM(E12:F12) -> 94.265604
B13: 6 | C13: Proj Admin | E13: 66.505247 | F13: =E13*$F$6 -> 0 | G13: =SUM(E13:F13) -> 66.505247
B14: 7 | C14: Proj Acct | E14: 85.81004 | F14: =E14*$F$6 -> 0 | G14: =SUM(E14:F14) -> 85.81004
B15: 8 | C15: Asst PM | E15: 82.733564 | F15: =E15*$F$6 -> 0 | G15: =SUM(E15:F15) -> 82.733564
B16: 9 | C16: Supt 3 | E16: 131.75199 | F16: =E16*$F$6 -> 0 | G16: =SUM(E16:F16) -> 131.75199
B17: 10 | C17: Supt 2 | E17: 110.59223 | F17: =E17*$F$6 -> 0 | G17: =SUM(E17:F17) -> 110.59223
B18: 11 | C18: Supt 1 | E18: 90.514804 | F18: =E18*$F$6 -> 0 | G18: =SUM(E18:F18) -> 90.514804
B19: 12 | C19: Asst Supt | E19: 59.915466 | F19: =E19*$F$6 -> 0 | G19: =SUM(E19:F19) -> 59.915466
... B24: 17 | C24: Safety | E24: 79.733968 | F24: =E24*$F$6 -> 0 | G24: =SUM(E24:F24) -> 79.733968
C25: Labor | E25: 32.408056 | F25: =E25*$F$6 -> 0 | G25: =SUM(E25:F25) -> 32.408056
C26: Apprentice | E26: 32.978211 | F26: =E26*$F$6 -> 0 | G26: =SUM(E26:F26) -> 32.978211
C27: Carpenter | E27: 45.013251 | F27: =E27*$F$6 -> 0 | G27: =SUM(E27:F27) -> 45.013251
C28: Driver | E28: 35.486876 | F28: =E28*$F$6 -> 0 | G28: =SUM(E28:F28) -> 35.486876
C29: Leadman | E29: 46.605242 | F29: =E29*$F$6 -> 0 | G29: =SUM(E29:F29) -> 46.605242
C30: Supt MEP | E30: 0 | F30: =E30*$F$6 -> 0 | G30: =SUM(E30:F30) -> 0
C31: Gen Supt | E31: 130.4108 | F31: =E31*$F$6 -> 0 | G31: =SUM(E31:F31) -> 130.4108
C32: Cons Mgr | E32: 135.45804 | F32: =E32*$F$6 -> 0 | G32: =SUM(E32:F32) -> 135.45804
C33: Proj Coor | E33: 0 | F33: =E33*$F$6 -> 0 | G33: =SUM(E33:F33) -> 0
C34: Mktg | E34: 85.41309 | F34: =E34*$F$6 -> 0 | G34: =SUM(E34:F34) -> 85.41309
C35: Bus Dev | E35: 121.55329 | F35: =E35*$F$6 -> 0 | G35: =SUM(E35:F35) -> 121.55329
C36: Chief, 3 & 2 | E36: 140.9198 | F36: =E36*$F$6 -> 0 | G36: =SUM(E36:F36) -> 140.9198
... C38: Exec Asst | E38: 69.670191 | F38: =E38*$F$6 -> 0 | G38: =SUM(E38:F38) -> 69.670191

Sheet Staffing Schedule 
A1: Embry Riddle Aeronautical University
A2: STAFFING SCHEDULE
B3: PROJECT DURATION 24 Months
A4: YEAR | B4: 2025 | C4: thru | D4: 2027
A5: MONTHS | B5: Sept | C5: Oct | D5: Nov | E5: Dec | F5: Jan | G5: Feb | H5: Mar | I5: April | J5: May | K5: Jun | L5: July | M5: Aug | N5: Sept | O5: Oct | P5: Nov | Q5: Dec | R5: Jan | S5: Feb | T5: Mar | U5: April | V5: May | W5: Jun | X5: July | Y5: Aug
A6: 4 Story | B6: 1 | C6: 2 | D6: 3 | E6: 4 | F6: 5 | G6: 6 | H6: 7 | I6: 8 | J6: 9 | K6: 10 | L6: 11 | M6: 12 | N6: 13 | O6: 14 | P6: 15 | Q6: 16 | R6: 17 | S6: 18 | T6: 19 | U6: 20 | V6: 21 | W6: 22 | X6: 23 | Y6: 24 | AD6: Close Out Nov/ Dec | AE6: 45896
A7: INITIAL SITEWORK
A8: Infrastrure
A9: Foundation
A10: Erect Phase South A
A11: Erect Phase South B
A12: Erect Phase North A
A13: Erect Phase North B
A14: INTERIORS South A
A15: Building South Side A Envelope
A16: Interiors Phase South B
A17: Building Envelope Building South B
A18: INTERIORS North Side A
... A22: TCO/ Punch list
A23: LEAD SUPERINTENDENT | B23: 1 | C23: 1 | D23: 1 | E23: 1 | F23: 1 | G23: 1 | H23: 1 | I23: 1 | J23: 1 | K23: 1 | L23: 1 | M23: 1 | N23: 1 | O23: 1 | P23: 1 | Q23: 1 | R23: 1 | S23: 1 | T23: 1 | U23: 1 | V23: 1 | W23: 1 | X23: 1 | AD23: =SUM(B23:AC23) -> 23 | AE23: =AD23*4.33 -> 99.59
A24: ASSISTANT SUPERINTENDENT | B24: 1 | C24: 1 | D24: 1 | E24: 1 | F24: 1 | G24: 1 | H24: 1 | I24: 1 | J24: 1 | K24: 1 | L24: 1 | M24: 1 | N24: 1 | O24: 1 | P24: 1 | Q24: 1 | R24: 1 | S24: 1 | T24: 1 | U24: 1 | V24: 1 | W24: 1 | X24: 1 | Y24: 1 | AD24: =SUM(B24:AC24) -> 24 | AE24: =AD24*4.33 -> 103.92
A25: PROJECT SUPERINTENDENT | G25: 1 | H25: 1 | I25: 1 | J25: 1 | K25: 1 | L25: 1 | M25: 1 | N25: 1 | O25: 1 | P25: 1 | Q25: 1 | R25: 1 | S25: 1 | T25: 1 | U25: 1 | V25: 1 | W25: 1 | X25: 1 | Y25: 1 | AD25: =SUM(B25:AC25) -> 19 | AE25: =AD25*4.33 -> 82.27
A26: ASSISTANT SUPERINTENDENT | E26: 1 | F26: 1 | G26: 1 | H26: 1 | I26: 1 | J26: 1 | K26: 1 | L26: 1 | M26: 1 | N26: 1 | O26: 1 | P26: 1 | Q26: 1 | R26: 1 | S26: 1 | T26: 1 | U26: 1 | V26: 1 | W26: 1 | X26: 1 | AD26: =SUM(B26:AC26) -> 20 | AE26: =AD26*4.33 -> 86.6
A27: PROJECT EXECUTIVE | B27: 1 | C27: 1 | D27: 1 | E27: 1 | F27: 1 | G27: 1 | H27: 1 | I27: 1 | J27: 1 | K27: 1 | L27: 1 | M27: 1 | N27: 1 | AD27: =SUM(B27:AC27) -> 13 | AE27: =AD27*4.33 -> 56.29
A28: SENIOR PROJECT MANAGER | B28: 1 | C28: 1 | D28: 1 | E28: 1 | F28: 1 | G28: 1 | H28: 1 | I28: 1 | J28: 1 | K28: 1 | L28: 1 | M28: 1 | N28: 1 | O28: 1 | P28: 1 | Q28: 1 | R28: 1 | S28: 1 | T28: 1 | U28: 1 | V28: 1 | W28: 1 | X28: 1 | AD28: =SUM(B28:AC28) -> 23 | AE28: =AD28*4.33 -> 99.59
A29: APM | B29: 1 | C29: 1 | D29: 1 | E29: 1 | F29: 1 | G29: 1 | H29: 1 | I29: 1 | J29: 1 | K29: 1 | L29: 1 | M29: 1 | N29: 1 | O29: 1 | P29: 1 | Q29: 1 | R29: 1 | S29: 1 | T29: 1 | U29: 1 | V29: 1 | W29: 1 | X29: 1 | Y29: 1 | AD29: =SUM(B29:AC29) -> 24 | AE29: =AD29*4.33 -> 103.92
A30: PROJECT ACCOUNTANT | B30: 1 | C30: 1 | D30: 1 | E30: 1 | F30: 1 | G30: 1 | H30: 1 | I30: 1 | J30: 1 | K30: 1 | L30: 1 | M30: 1 | N30: 1 | AD30: =SUM(B30:AC30) -> 13 | AE30: =AD30*4.33 -> 56.29
A31: PA | B31: 1 | C31: 1 | D31: 1 | E31: 1 | F31: 1 | G31: 1 | H31: 1 | I31: 1 | J31: 1 | K31: 1 | L31: 1 | M31: 1 | N31: 1 | O31: 1 | P31: 1 | Q31: 1 | R31: 1 | S31: 1 | T31: 1 | U31: 1 | V31: 1 | W31: 1 | X31: 1 | Y31: 1 | AD31: =SUM(B31:AC31) -> 24 | AE31: =AD31*4.33 -> 103.92
A32: FOREMAN | B32: 1 | C32: 1 | D32: 1 | E32: 1 | F32: 1 | G32: 1 | H32: 1 | I32: 1 | J32: 1 | K32: 1 | L32: 1 | M32: 1 | N32: 1 | O32: 1 | P32: 1 | Q32: 1 | R32: 1 | S32: 1 | T32: 1 | U32: 1 | V32: 1 | W32: 1 | X32: 1 | Y32: 1 | AD32: =SUM(B32:AC32) -> 24 | AE32: =AD32*4.33 -> 103.92
A33: FOREMAN | AD33: =SUM(B33:AC33) -> 0 | AE33: =AD33*4.33 -> 0
A34: CARPENTER | B34: 1 | C34: 1 | D34: 1 | E34: 1 | F34: 1 | G34: 1 | H34: 1 | I34: 1 | J34: 1 | K34: 1 | L34: 1 | M34: 1 | N34: 1 | O34: 1 | P34: 1 | Q34: 1 | R34: 1 | S34: 1 | T34: 1 | U34: 1 | V34: 1 | W34: 1 | X34: 1 | Y34: 1 | AD34: =SUM(B34:AC34) -> 24 | AE34: =AD34*4.33 -> 103.92
A35: CARPETNER | E35: 1 | F35: 1 | G35: 1 | H35: 1 | I35: 1 | J35: 1 | K35: 1 | L35: 1 | M35: 1 | N35: 1 | O35: 1 | P35: 1 | Q35: 1 | R35: 1 | S35: 1 | T35: 1 | U35: 1 | V35: 1 | W35: 1 | AD35: =SUM(B35:AC35) -> 19 | AE35: =AD35*4.33 -> 82.27

Sheet 02 21 Survey 
G1: Hedrick Plug
F2: X | G2: Excluded
F3: I | G3: Included
B4: BACK TO SUMMARY SHEET | G4: Sub Add/Deduct | H4: Bidder 1 | J4: Bidder 2 | L4: Bidder 3 | N4: Bidder 4 | P4: Bidder 5 | R4: Bidder 6
A5: Project: | B5: ='Area Calculations'!B4 -> ERAU Residential Hall & Garage Building | G5: Company | H5: American Layout & Land Surveying | J5: Leading Edge Land Serv | L5: MacGillivray & Co | N5: Carnahan Proctor & Cross | P5: Pacifica Engineering Services | R5: RYANIK
A6: Trade: | B6: Survey | G6: Contact | H6: Lisa Rizzi | J6: Karol J. Hofius | L6: Arlene Wroblewski
A7: CSI Code: | B7: 02 21 00 | G7: Phone | H7: (732) 807-6250 | J7: (407) 351-6730 | L7: (631) 291-8886
A8: Date: | G8: Email | H8: estimating@americansurveyors.us | J8: khofius@leadingedgels.com | L8: bids@macgillivraysurveying.com
G9: Adjusted Bid | H9: =I58 -> 59300 | J9: =K58 -> 72365 | L9: =M58 -> 105919.77 | N9: =O58 -> 0 | P9: =Q58 -> 0 | R9: =S58 -> 0
C10: Plan/ Spec. Package | D10: QTY | E10: U/M | F10: Unit Cost | G10: Subtotal | H10: Yes/No | I10: Price | J10: Yes/No | K10: Price | L10: Yes/No | M10: Price | N10: Yes/No | O10: Price | P10: Yes/No | Q10: Price | R10: Yes/No | S10: Price
B11: GENERAL INCLUSIONS
B12: INCLUDES ALL SALES TAX | H12: i | J12: i | L12: i
B13: ALL HOISTING & RIGGING REQUIRED TO COMPLETE THIS SCOPE | H13: i | J13: i | L13: i
B14: PROVIDE P&P BONDS | H14: x | J14: x | L14: x
B15: FLORIDA STATE CONTRACTORS LIC. | H15: i | J15: i | L15: i
B16: GENERAL LIABILITY AND WORKERS COMP. INSURANCE LIMITS | H16: i | J16: i | L16: i
B17: STATE AND LOCAL TAXES | H17: i | J17: i | L17: i
B18: COMPASS | H18: x | J18: x | K18: {5.0} | L18: x
B19: SPECIFIC TRADE SCOPE OF WORK REQUIREMENTS
B20: BASE BID
B22: Verify and Set Horizontal & Vertical Control | H22: I | I22: 2100 | J22: I | K22: 1820 | L22: I | M22: 7416.75
B23: Builidng Layout | H23: I | I23: =750+2800+500 -> 4050 | J23: I | K23: 7270 | L23: I | M23: 45311.75
B24: Parking Garage Layout | H24: I | I24: 0 | J24: I | K24: 9190 | L24: I | M24: 0
B25: Foundations Surveys | H25: I | I25: 1500 | J25: I | K25: 5345 | L25: I | M25: 0
B27: Sitework | M27: 33039.1
B28: Site boundary | H28: I | I28: 845 | K28: 845 | L28: I
B29: Detention Basins | H29: I | I29: 2000 | K29: 2000 | L29: I
B30: Utilities | H30: I | I30: =10950+1050+2150+150 -> 14300 | K30: 14300 | L30: I
B31: Curb Layout | H31: I | I31: 3675 | K31: 3675 | L31: I
B32: Sidewalks | H32: I | I32: 4785 | K32: 4785 | L32: I
B33: Trash Enclosure | H33: I | I33: 350 | J33: I | K33: 910 | L33: I
B34: Transformer Pad | H34: I | I34: 600 | J34: I | L34: I
B35: Generator Enclosure | H35: I | I35: 350 | L35: I
B36: Site Lighting | H36: I | I36: 1350 | J36: I | K36: 2225 | L36: I
B38: Site As-builts | H38: I | I38: =3895+19500 -> 23395 | K38: 20000 | M38: 20152.17
F54: SUBTOTAL | I54: =SUM(I20:I53) -> 59300 | K54: =SUM(K20:K53) -> 72365 | M54: =SUM(M20:M53) -> 105919.77 | O54: =SUM(O20:O53) -> 0 | Q54: =SUM(Q20:Q53) -> 0 | S54: =SUM(S20:S53) -> 0
F55: BOND RATE | H55: 0 | J55: 0 | L55: 0 | N55: 0 | P55: 0 | R55: 0
F56: BOND AMOUNT | I56: =H55*I54 -> 0 | K56: =J55*K54 -> 0 | M56: =L55*M54 -> 0 | O56: =N55*O54 -> 0 | Q56: =P55*Q54 -> 0 | S56: =R55*S54 -> 0
F58: ADJUSTED TOTAL | I58: =SUM(I54:I56) -> 59300 | K58: =SUM(K54:K56) -> 72365 | M58: =SUM(M54:M56) -> 105919.77 | O58: =SUM(O54:O56) -> 0 | Q58: =SUM(Q54:Q56) -> 0 | S58: =SUM(S54:S56) -> 0
F59: Cost per SF | I59: =I58/'Area Calculations'!$G$4 -> 0.10247761 | K59: =K58/'Area Calculations'!$G$4 -> 0.12505552 | M59: =M58/'Area Calculations'!$G$4 -> 0.18304224 | O59: =O58/'Area Calculations'!$G$4 -> 0 | Q59: =Q58/'Area Calculations'!$G$4 -> 0 | R59: =R58/'Area Calculations'!$G$4 -> 0 | S59: =S58/'Cost Summary'!#REF! -> #REF!
F60: Cost per Unit | I60: =I58/'Area Calculations'!$G$9 -> 554.20561 | K60: =K58/'Area Calculations'!$G$9 -> 676.30841 | M60: =M58/'Area Calculations'!$G$9 -> 989.90439 | O60: =O58/'Area Calculations'!$G$9 -> 0 | Q60: =Q58/'Area Calculations'!$G$9 -> 0 | R60: =R58/'Area Calculations'!$G$9 -> 0 | S60: =S58/'Cost Summary'!#REF! -> #REF!
A62: QUALIFICATIONS
A66: EXCLUSIONS/OWNER PROVIDED ITEMS:
A70: ALTERNATES:
A74: PROPOSED VE (Provide Clear Description):
A78: FULLY LOADED LABOR RATES
B79: Laborer
B80: Mechanic
B81: Superintendent
B82: Project Manager
A84: SCHEDULE
B85: Prepared shop drawings/submittals
B86: Mobilization
B87: Total duration to complete scope of work
A89: Winner
A90: Company | B90: =H5 -> American Layout & Land Surveying
A91: Contact | B91: =H6 -> Lisa Rizzi
A92: Phone | B92: =H7 -> (732) 807-6250
A93: Email | B93: =H8 -> estimating@americansurveyors.us
A94: Base Bid | B94: =I58 -> 59300

Sheet 02 41 Demolition
G1: Hedrick Plug
F2: X | G2: Excluded
F3: I | G3: Included
B4: BACK TO SUMMARY SHEET | G4: Sub Add/Deduct | H4: Bidder 1 | J4: Bidder 2 | L4: Bidder 3 | N4: Bidder 4 | P4: Bidder5 | R4: Bidder6
A5: Project: | B5: ='Area Calculations'!B4 -> ERAU Residential Hall & Garage Building | G5: Company
A6: Trade: | B6: Demolition | G6: Contact
A7: CSI Code: | B7: 02 41 00 | G7: Phone
A8: Date: | G8: Email
G9: Adjusted Bid | H9: =I55 -> 0 | J9: =K55 -> 0 | L9: =M55 -> 0 | N9: =O55 -> 0 | P9: =Q55 -> 0 | R9: =S55 -> 0
C10: Plan/ Spec. Package | D10: QTY | E10: U/M | F10: Unit Cost | G10: Subtotal | H10: Yes/No | I10: Price | J10: Yes/No | K10: Price | L10: Yes/No | M10: Price | N10: Yes/No | O10: Price | P10: Yes/No | Q10: Price | R10: Yes/No | S10: Price
B11: GENERAL INCLUSIONS
B12: INCLUDES ALL SALES TAX
B13: ALL HOISTING & RIGGING REQUIRED TO COMPLETE THIS SCOPE
B14: PROVIDE P&P BONDS
B15: FLORIDA STATE CONTRACTORS LIC.
B16: GENERAL LIABILITY AND WORKERS COMP. INSURANCE LIMITS
B17: STATE AND LOCAL TAXES
B18: SPECIFIC TRADE SCOPE OF WORK REQUIREMENTS
B19: BASE BID
F51: SUBTOTAL | I51: =SUM(I11:I50) -> 0 | K51: =SUM(K11:K50) -> 0 | M51: =SUM(M11:M50) -> 0 | O51: =SUM(O11:O50) -> 0 | Q51: =SUM(Q11:Q50) -> 0 | S51: =SUM(S11:S50) -> 0
F52: BOND RATE | H52: 0 | J52: 0 | L52: 0 | N52: 0 | P52: 0 | R52: 0
F53: BOND AMOUNT | I53: =H52*I51 -> 0 | K53: =J52*K51 -> 0 | M53: =L52*M51 -> 0 | O53: =N52*O51 -> 0 | Q53: =P52*Q51 -> 0 | S53: =R52*S51 -> 0
F55: ADJUSTED TOTAL | I55: =SUM(I51:I53) -> 0 | K55: =SUM(K51:K53) -> 0 | M55: =SUM(M51:M53) -> 0 | O55: =SUM(O51:O53) -> 0 | Q55: =SUM(Q51:Q53) -> 0 | S55: =SUM(S51:S53) -> 0
F56: Cost per SF | I56: =I55/'Area Calculations'!$G$4 -> 0 | K56: =K55/'Area Calculations'!$G$4 -> 0 | M56: =M55/'Area Calculations'!$G$4 -> 0 | O56: =O55/'Area Calculations'!$G$4 -> 0 | Q56: =Q55/'Area Calculations'!$G$4 -> 0 | S56: =S55/'Area Calculations'!$G$4 -> 0
F57: Cost per Unit | I57: =I55/'Area Calculations'!$G$9 -> 0 | K57: =K55/'Area Calculations'!$G$9 -> 0 | M57: =M55/'Area Calculations'!$G$9 -> 0 | O57: =O55/'Area Calculations'!$G$9 -> 0 | Q57: =Q55/'Area Calculations'!$G$9 -> 0 | S57: =S55/'Area Calculations'!$G$9 -> 0
A59: QUALIFICATIONS
A63: EXCLUSIONS/OWNER PROVIDED ITEMS:
A67: ALTERNATES:
A71: PROPOSED VE (Provide Clear Description):
A75: FULLY LOADED LABOR RATES
B76: Laborer
B77: Mechanic
B78: Superintendent
B79: Project Manager
A81: SCHEDULE
B82: Prepared shop drawings/submittals
B83: Mobilization
B84: Total duration to complete scope of work
A86: Winner
A87: Company
A88: Contact
A89: Phone
A90: Email
A91: Base Bid

Sheet 02 50 Site Maint
G1: Hedrick Plug
F2: X | G2: Excluded
F3: I | G3: Included
B4: BACK TO SUMMARY SHEET | G4: Sub Add/Deduct | H4: Bidder 1 | J4: Bidder 2 | L4: Bidder 3 | N4: Bidder 4 | P4: Bidder5 | R4: Bidder6
A5: Project: | B5: ='Area Calculations'!B4 -> ERAU Residential Hall & Garage Building | G5: Company | J5: Oneliance | L5: Milclean USA
A6: Trade: | B6: Site Maintenance | G6: Contact | J6: Justin Dossie | L6: Karina Correa
A7: CSI Code: | B7: 02 10 | G7: Phone | J7: (757) 812-5650 | L7: (954) 681-3641
A8: Date: | G8: Email | J8: jdossie@oneliance.com | L8: karina@milcleanusa.com
A9: Base Bid | G9: Base Bid | H9: =I61 -> 1781647.2 | J9: =K61 -> 199490 | L9: =M61 -> 155983.11 | N9: =O61 -> 0 | P9: =Q61 -> 0 | R9: =S61 -> 0
C10: Plan/ Spec. Package | D10: QTY | E10: U/M | F10: Unit Cost | G10: Subtotal | H10: Yes/No | I10: Price | J10: Yes/No | K10: Price | L10: Yes/No | M10: Price | N10: Yes/No | O10: Price | P10: Yes/No | Q10: Price | R10: Yes/No | S10: Price
B11: GENERAL INCLUSIONS
B12: INCLUDES ALL SALES TAX
B13: ALL HOISTING & RIGGING REQUIRED TO COMPLETE THIS SCOPE
B14: PROVIDE P&P BONDS
B15: FLORIDA STATE CONTRACTORS LIC.
B16: GENERAL LIABILITY AND WORKERS COMP. INSURANCE LIMITS
B17: STATE AND LOCAL TAXES
B18: SPECIFIC TRADE SCOPE OF WORK REQUIREMENTS
B19: BASE BID
B22: Construction fence | D22: 2274 | E22: lf | F22: 12 | G22: =D22*F22 -> 27288 | I22: =G22 -> 27288
B23: Construction gates | D23: 2 | E23: ea | F23: 10000 | G23: =D23*F23 -> 20000 | I23: =G23 -> 20000
B24: Maintenance during construction | D24: 1 | E24: ls | F24: 3000 | G24: =D24*F24 -> 3000 | I24: =G24 -> 3000
B25: Street Maintenance & Cleaning | D25: 1 | E25: ls | F25: 50000 | G25: =D25*F25 -> 50000 | I25: =G25 -> 50000
B26: Final Cleaning - garage - pressure wash | D26: =54077+(51436*5) -> 311257 | E26: sf | F26: 0.15 | G26: =D26*F26 -> 46688.55 | I26: =G26 -> 46688.55 | K26: 46710 | M26: 9337.71
B27: Final Cleaning - building | D27: =578663-D26 -> 267406 | E27: sf | F27: 0.5 | G27: =D27*F27 -> 133703 | I27: =G27 -> 133703 | K27: 108780 | M27: =78673+10500+24396.81-M26 -> 104232.1
B28: Final Cleaning - building windows exterior | D28: ='08 50 Storefront & Windows'!AC66 -> 33930.643 | E28: sf | F28: 1.25 | G28: =D28*F28 -> 42413.304 | I28: =G28 -> 42413.304 | K28: 44000 | M28: =$G28 -> 42413.304
B29: Concrete Wash-out | E29: ls | F29: 10000 | G29: =D29*F29 -> 0 | I29: =G29 -> 0
B30: Construction waste removal / recycle | E30: ls | F30: 8000 | G30: =D30*F30 -> 0 | I30: =G30 -> 0
B31: Temp Parking | G31: =D31*F31 -> 0 | I31: =G31 -> 0
B32: Bus - buy 2 | D32: 2 | E32: ea | F32: 35000 | G32: =D32*F32 -> 70000 | I32: =G32 -> 70000
B33: Bus - drivers - 2 | D33: ='GCs & GRs'!K4 -> 99.857143 | E33: wks | F33: =2*8*5*35 -> 2800 | G33: =D33*F33 -> 279600 | I33: =G33 -> 279600
B34: Bus - fuel & maint | D34: ='GCs & GRs'!K4 -> 99.857143 | E34: wks | F34: =20/5*5*5*2 -> 200 | G34: =D34*F34 -> 19971.429 | I34: =G34 -> 19971.429
B35: Parking control | D35: ='GCs & GRs'!K4 -> 99.857143 | E35: wks | F35: =2*8*5*35 -> 2800 | G35: =D35*F35 -> 279600 | I35: =G35 -> 279600
B36: Dumpster | D36: ='GCs & GRs'!K4 -> 99.857143 | E36: wks | F36: =4*600 -> 2400 | G36: =D36*F36 -> 239657.14 | I36: =G36 -> 239657.14
B37: Trash Chute | D37: 8 | E37: mo | F37: =40000/8 -> 5000 | G37: =D37*F37 -> 40000
B38: Labor | D38: ='GCs & GRs'!K4 -> 99.857143 | E38: wks | F38: =2*8*55 -> 880 | G38: =D38*F38 -> 87874.286 | I38: =G38 -> 87874.286
B39: Floor Protection | D39: =D27 -> 267406 | E39: sf | F39: 0.25 | G39: =D39*F39 -> 66851.5 | I39: =G39 -> 66851.5
B40: MOT | D40: 1 | E40: ls | F40: 50000 | G40: =D40*F40 -> 50000 | I40: =G40 -> 50000
B41: Safety rails, Penetration Covers & Maintenance of rails | E41: ls | F41: 5000 | G41: =D41*F41 -> 0 | I41: =G41 -> 0
B42: Polution Coverage | D42: 1 | E42: ls | F42: 15000 | G42: =D42*F42 -> 15000 | I42: =G42 -> 15000
I43: =G43 -> 0
B44: Buck Hoist | D44: 14 | E44: mo | F44: 25000 | G44: =D44*F44 -> 350000 | I44: =G44 -> 350000
I45: =G45 -> 0
I46: =G46 -> 0
I47: =G47 -> 0
I48: =G48 -> 0
I49: =G49 -> 0
I50: =G50 -> 0
I51: =G51 -> 0
I52: =G52 -> 0
I53: =G53 -> 0
I54: =G54 -> 0
I55: =G55 -> 0
F57: SUBTOTAL | G57: Base Bid | I57: =SUM(I22:I56) -> 1781647.2 | K57: =SUM(K22:K56) -> 199490 | M57: =SUM(M22:M56) -> 155983.11 | O57: =SUM(O22:O56) -> 0 | Q57: =SUM(Q22:Q56) -> 0 | S57: =SUM(S22:S56) -> 0
F58: BOND RATE | H58: 0 | J58: 0 | L58: 0 | N58: 0 | P58: 0 | R58: 0
F59: BOND AMOUNT | I59: =H58*I57 -> 0 | K59: =J58*K57 -> 0 | M59: =L58*M57 -> 0 | O59: =N58*O57 -> 0 | Q59: =P58*Q57 -> 0 | S59: =R58*S57 -> 0
F61: ADJUSTED TOTAL | I61: =SUM(I57:I59) -> 1781647.2 | K61: =SUM(K57:K59) -> 199490 | M61: =SUM(M57:M59) -> 155983.11 | O61: =SUM(O57:O59) -> 0 | Q61: =SUM(Q57:Q59) -> 0 | S61: =SUM(S57:S59) -> 0
F62: Cost per SF | I62: =I61/'Area Calculations'!$G$4 -> 3.0789029 | K62: =K61/'Area Calculations'!$G$4 -> 0.34474297 | M62: =M61/'Area Calculations'!$G$4 -> 0.26955778 | O62: =O61/'Area Calculations'!$G$4 -> 0 | Q62: =Q61/'Area Calculations'!$G$4 -> 0 | S62: =S61/'Area Calculations'!$G$4 -> 0
F63: Cost per Unit | I63: =I61/'Area Calculations'!$G$9 -> 16650.909 | K63: =K61/'Area Calculations'!$G$9 -> 1864.3925 | M63: =M61/'Area Calculations'!$G$9 -> 1457.7861 | O63: =O61/'Area Calculations'!$G$9 -> 0 | Q63: =Q61/'Area Calculations'!$G$9 -> 0 | S63: =S61/'Area Calculations'!$G$9 -> 0
A65: QUALIFICATIONS
A69: EXCLUSIONS/OWNER PROVIDED ITEMS:
A73: ALTERNATES:
A77: PROPOSED VE (Provide Clear Description):
A81: FULLY LOADED LABOR RATES
B82: Laborer
B83: Mechanic
B84: Superintendent
B85: Project Manager
A87: SCHEDULE
B88: Prepared shop drawings/submittals
B89: Mobilization
B90: Total duration to complete scope of work
A92: Winner
A93: Company
A94: Contact
A95: Phone
A96: Email
A97: Base Bid | B97: =I61 -> 1781647.2

Sheet 03 30 CIP Concrete
G1: Hedrick Plug
F2: X | G2: Excluded
F3: I | G3: Included
B4: BACK TO SUMMARY SHEET | G4: Sub Add/Deduct | H4: Bidder 1 | J4: Bidder 7 | L4: Bidder2 | N4: Bidder 3 | P4: Bidder 5 | R4: Bidder 4 | T4: Bidder 6 | V4: Bidder 8 | X4: Bidder 9
A5: Project: | B5: ='Area Calculations'!B4 -> ERAU Residential Hall & Garage Building | G5: Company | H5: DeWitt Custom Concrete | J5: Don Kings Concrete | L5: 2000 Concrete | N5: Starlite | P5: Baker Concrete | R5: Legomatic Construction | T5: Core Concrete | V5: Genesis Concrete Struct | X5: Leo's Concrete Specilaties
A6: Trade: | B6: Concrete | G6: Contact | H6: Tim Streeter | J6: Dan Belanger | L6: Sebastian Lopez | N6: Sean Williams | P6: Allison Mickley | R6: Casey Isaac
A7: CSI Code: | B7: 03 30 00 | G7: Phone | H7: (786) 208.8458 | J7: (407) 977-9001 | L7: (239) 687.8581 | N7: (561) 719-7607 | P7: (407) 205-3776 | R7: (386) 216-6335
A8: Date: | G8: Email | H8: tim@dewittcc.com | J8: DBelanger@dkcfl.com | L8: slopez@2000concrete.com | N8: SeWilliams@starlitebuild.com | P8: MickleyA@BakerConcrete.com | R8: caseyisaac@legomaticconstruction.com
G9: Adjusted Bid | H9: =I96 -> 6808725.6 | J9: =K96 -> 5700849.3 | L9: =M96 -> 5882569.3 | N9: =O96 -> 6755331.3 | P9: =Q96 -> 6892046.3 | R9: =S96 -> 8202620.9 | T9: =U96 -> 0 | V9: =W96 -> 0 | X9: =Y96 -> 0
C10: Plan/ Spec. Package | D10: QTY | E10: U/M | F10: Unit Cost | G10: Subtotal | H10: Yes/No | I10: Price | J10: Yes/No | K10: Price | L10: Yes/No | M10: Price | N10: Yes/No | O10: Price | P10: Yes/No | Q10: Price | R10: Yes/No | S10: Price | T10: Yes/No | U10: Price | V10: Yes/No | W10: Price | X10: Yes/No | Y10: Price
B11: GENERAL INCLUSIONS
B12: INCLUDES ALL SALES TAX | H12: i
B13: ALL HOISTING & RIGGING REQUIRED TO COMPLETE THIS SCOPE | H13: i
B14: PROVIDE P&P BONDS | H14: x | I14: {2.0%}
B15: FLORIDA STATE CONTRACTORS LIC. | H15: i
B16: GENERAL LIABILITY AND WORKERS COMP. INSURANCE LIMITS | H16: i
B17: STATE AND LOCAL TAXES | H17: i
B18: COMPASS | H18: x | I18: {6.0}
B19: SPECIFIC TRADE SCOPE OF WORK REQUIREMENTS
B20: BASE BID | I20: =4845635 -> 4845635 | K20: =5459900-K66-K67 -> 3654100 | M20: =5448000-M66-M67 -> 4053489 | O20: =6133682-O66 -> 4514629 | Q20: 4828019 | S20: =8426760.93-S76-S79 -> 8335834.9
AG21: + 20" spoils
B22: Foundations | H22: I | J22: I | L22: I | N22: I | P22: I | R22: I | AG22: =20/12 -> 1.6666667
A23: =D23 -> 1504 | B23: Mat 36" | D23: 1504 | E23: cy | F23: 650 | G23: =D23*F23 -> 977600 | AC23: 13537 | AD23: SF | AG23: =$AG$22*AC23/27 -> 835.61728
A24: =D24 -> 1268 | B24: Mat 48" | D24: 1268 | E24: cy | F24: 650 | G24: =D24*F24 -> 824200 | AC24: 8558 | AD24: SF | AG24: =$AG$22*AC24/27 -> 528.2716
A25: =D25 -> 287 | B25: Mat 60" | D25: 287 | E25: cy | F25: 650 | G25: =D25*F25 -> 186550 | AC25: 1550 | AD25: SF | AG25: =$AG$22*AC25/27 -> 95.679012
A26: =D26 -> 48 | B26: Footing - F14.0 | D26: 48 | E26: cy | F26: 650 | G26: =D26*F26 -> 31200 | AA26: 7 | AB26: Footing - F14.0 | AC26: 2 | AD26: EA | AE26: 48 | AF26: CY | AG26: =14*14*AG22/27*2 -> 24.197531
A27: =D27 -> 49 | B27: Footing - F20.0 | D27: 49 | E27: cy | F27: 650 | G27: =D27*F27 -> 31850 | AA27: 8 | AB27: Footing - F20.0 | AC27: 2 | AD27: EA | AE27: 0 | AG27: =20*11*AG22/27*2 -> 27.160494
A28: =D28 -> 158 | B28: Footing - F43.0 | D28: 158 | E28: cy | F28: 650 | G28: =D28*F28 -> 102700 | AA28: 9 | AB28: Footing - F43.0 | AC28: 2 | AD28: EA | AE28: 0 | AG28: =43*11*AG22/27*2 -> 58.395062
A29: =D29 -> 31 | B29: Footing - CF2.5 | D29: 31 | E29: cy | F29: 650 | G29: =D29*F29 -> 20150 | AA29: 10 | AB29: Footing - CF2.5 | AC29: 133 | AD29: LF | AE29: 31 | AF29: CY | AG29: =2.5*133*2/27 -> 24.62963
A30: =D30 -> 17 | B30: Footing - CF4.0 | D30: 17 | E30: cy | F30: 650 | G30: =D30*F30 -> 11050 | AA30: 11 | AB30: Footing - CF4.0 | AC30: 46 | AD30: LF | AE30: 17 | AF30: CY | AG30: =4*46*AG22/27 -> 11.358025
A31: =D31 -> 580 | B31: Footing - CF7.0 | D31: 580 | E31: cy | F31: 650 | G31: =D31*F31 -> 377000 | AA31: 12 | AB31: Footing - CF7.0 | AC31: 895 | AD31: LF | AE31: 580 | AF31: CY | AG31: =7*895*AG22/27 -> 386.7284
A32: =D32 -> 316 | B32: Footing - CF10.0 | D32: 316 | E32: cy | F32: 650 | G32: =D32*F32 -> 205400 | AA32: 13 | AB32: Footing - CF10.0 | AC32: 342 | AD32: LF | AE32: 316 | AF32: CY | AG32: =10*242*AG22/27 -> 149.38272
A33: =D33 -> 651 | B33: Footing - CF16.0 | D33: 651 | E33: cy | F33: 650 | G33: =D33*F33 -> 423150 | AA33: 14 | AB33: Footing - CF16.0 | AC33: 366 | AD33: LF | AE33: 651 | AF33: CY | AG33: =16*366*AG22/27 -> 361.48148
A34: =D34 -> 8 | B34: Footing - CMU walls | D34: 8 | E34: cy | F34: 650 | G34: =D34*F34 -> 5200 | AF34: to top of footing | AG34: =SUM(AG23:AG33) -> 2502.9012 | AH34: cy
G35: =D35*F35 -> 0 | AF35: footings | AG35: =SUM(D23:D34) -> 4917 | AH35: cy
B36: Slabs on grade | G36: =D36*F36 -> 0 | H36: I | J36: I | L36: I | N36: I | P36: I | R36: I | AG36: =SUM(AG34:AG35) -> 7419.9012 | AH36: cy
A37: =D37*0.33/27 -> 506.59889 | B37: SOG - 4" | D37: 41449 | E37: sf | F37: 8 | G37: =D37*F37 -> 331592
A38: =D38*0.42/27 -> 928.07556 | B38: SOG - 5" | D38: 59662 | E38: sf | F38: 10 | G38: =D38*F38 -> 596620
G39: =D39*F39 -> 0
B40: CIP Walls | G40: =D40*F40 -> 0 | H40: I | J40: I | L40: I | N40: I | P40: I | R40: I
B41: foundation level CIP wall between grid lines A.21 & A.22, @ B.15 & B.24 | C41: 8/S301 | G41: =D41*F41 -> 0
A42: =D42 -> 42 | B42: 12" thick - elev -3-4" to 5'-11" | C42: =3.33+5.92 -> 9.25 | D42: 42 | E42: cy | F42: 1500 | G42: =D42*F42 -> 63000
B43: foundation level CIP wall between grid lines A.19 & A.27 @ B.15 & B.24 | C43: 9/S302 | G43: =D43*F43 -> 0
A44: =D44 -> 31 | B44: 12" thick - elev -3-4" to 2'-2" | C44: =3.33+2.17 -> 5.5 | D44: 31 | E44: cy | F44: 1500 | G44: =D44*F44 -> 46500
B45: foundation level CIP wall between grid lines B.06 & B.31 @ A.30 | G45: =D45*F45 -> 0
A46: =D46 -> 7 | B46: 10" thick - elev -2'-2" to 14'-4" | C46: =15.17-0.83 -> 14.34 | D46: 7 | E46: cy | F46: 1500 | G46: =D46*F46 -> 10500
B47: 12" thick - elevator pit walls | C47: 1/S303 | D47: 2 | E47: cy | F47: 1500 | G47: =D47*F47 -> 3000
G48: =D48*F48 -> 0
B49: CIP Columns | G49: =D49*F49 -> 0 | H49: I | J49: I | L49: I | N49: I | P49: I | R49: I
A50: =D50 -> 4.4280093 | B50: Grid line A.31 & B.08 - 2'-6" x 5'-2" (not sized on plan) - elev -3-4" to 5'-11"? | C50: =3.33+5.92 -> 9.25 | D50: =2.5*5.17*9.25/27 -> 4.4280093 | E50: cy | F50: 2000 | G50: =D50*F50 -> 8856.0185
A51: =D51 -> 4.4280093 | B51: Grid line A.31 & B.30 - 2'-6" x 5'-2" (not sized on plan) - elev -3-4" to 5'-11"? | C51: =3.33+5.92 -> 9.25 | D51: =2.5*5.17*9.25/27 -> 4.4280093 | E51: cy | F51: 2000 | G51: =D51*F51 -> 8856.0185
A52: =D52 -> 8.8560185 | B52: Grid line A.31 & B.15 - 5'-2" x 5'-0" (not sized on plan) - elev -3-4" to 5'-11"? | C52: =3.33+5.92 -> 9.25 | D52: =5*5.17*9.25/27 -> 8.8560185 | E52: cy | F52: 2000 | G52: =D52*F52 -> 17712.037
A53: =D53 -> 8.8560185 | B53: Grid line A.31 & B.24 - 5'-2" x 5'-0" (not sized on plan) - elev -3-4" to 5'-11"? | C53: =3.33+5.92 -> 9.25 | D53: =5*5.17*9.25/27 -> 8.8560185 | E53: cy | F53: 2000 | G53: =D53*F53 -> 17712.037
G54: =D54*F54 -> 0
B55: CIP Pier | G55: =D55*F55 -> 0 | H55: I | J55: I | L55: I | N55: I | P55: I | R55: I
A56: =D56 -> 42 | B56: P1 - continuious 18" thick | C56: 123 | D56: 42 | E56: cy | F56: 1500 | G56: =D56*F56 -> 63000
B57: P2 - - 3'-4" x 3'-4" - | F57: 1500 | G57: =D57*F57 -> 0
A58: =D58 -> 2.1412037 | B58: P3 - Grid A.22 & B.15, A.22 & B.24 - 2'-6" x 2'-6" - elev -3-4" to 5'-11" | C58: =3.33+5.92 -> 9.25 | D58: =2.5*2.5*9.25/27 -> 2.1412037 | E58: cy | F58: 1500 | G58: =D58*F58 -> 3211.8056
G59: =D59*F59 -> 0
A60: =D60 -> 151.79359 | B60: PT Beams - at Grid Lines A.31 & A.33 - second floor framing only | C60: 1, 2, 3, 4/S321 | D60: =169.75*5.17*4.67/27 -> 151.79359 | E60: cy | F60: 2500 | G60: =D60*F60 -> 379483.98 | H60: I | J60: I | L60: I | N60: I | P60: I | R60: I
A61: =SUM(A23:A60) -> 6654.1773 | G61: =D61*F61 -> 0
B62: Set CIP embeds | H62: I | J62: I | L62: I
B63: Set precast column & wall anchor bolts | G63: =D63*F63 -> 0 | H63: I | J63: I | L63: I | P63: I
B64: Vapor barrier - 15 mil | G64: =D64*F64 -> 0 | H64: I | J64: I | K64: 4600 | L64: I | N64: I | P64: I | R64: I
B65: Excavation of footings | G65: =D65*F65 -> 0 | H65: I | J65: I | L65: I | N65: I | R65: I
B66: Topping Slabs - Hollow Core - 3-1/2" | G66: =D66*F66 -> 0 | H66: I | I66: 927567 | J66: I | K66: 1374800 | L66: I | M66: =1023005+214061 -> 1237066 | N66: I | O66: 1619053 | P66: I | Q66: 1847378 | R66: I
B67: Wash Pours | G67: =D67*F67 -> 0 | H67: I | I67: 430000 | J67: I | K67: 431000 | L67: I | M67: 157445 | N67: I | O67: 450000 | P67: I | R67: I
B68: Adjustment | I68: 400000 | M68: 200000
G69: =D69*F69 -> 0 | AB69: Footing - CF10.0 | AC69: 854 | AD69: SF
B70: Backfill at footings | D70: =D71+D72 -> 889.38272 | G70: =D70*F70 -> 0 | H70: I | J70: i | K70: 20000 | M70: 17920 | N70: I | R70: I
B71: Backfill to bring grade over footings up to bottom of SOG - use footing spoils | D71: =AG90 -> 396.04938 | E71: cy | F71: 25 | G71: =D71*F71 -> 9901.2346 | H71: I | J71: i | L71: I | N71: I | R71: I | AB71: Footing - CF16.0 | AC71: 1098 | AD71: SF
B72: Backfill at garage entry ramp - use footing spoils | D72: =9.25*48*0.5*60/27 -> 493.33333 | E72: cy | F72: 25 | G72: =D72*F72 -> 12333.333 | H72: I | J72: i | L72: I | N72: I | R72: I | AB72: Footing - CF2.5 | AC72: 333 | AD72: SF
B73: Handle footing spoils - excess haul off - assume 20" to top of footings | D73: =AG36-D72-D71 -> 6530.5185 | E73: cy | F73: 18 | G73: =D73*F73 -> 117549.33 | I73: =$G73 -> 117549.33 | K73: =$G73 -> 117549.33 | M73: =$G73 -> 117549.33 | O73: =$G73 -> 117549.33 | Q73: =$G73 -> 117549.33 | S73: =ROUND($G73,0) -> 117549 | AB73: Footing - CF4.0 | AC73: 114 | AD73: SF
G74: =D74*F74 -> 0 | AB74: Footing - CF7.0 | AC74: 2239 | AD74: SF
B75: 8" CMU Walls | G75: =D75*F75 -> 0 | K75: Pyramid | M75: Pyramid | Q75: Pyramid | AB75: Footing - F14.0 | AC75: 392 | AD75: SF
B76: walls - S112, S114 - B.15 to B.24 / A.18 - to 10'-0" | D76: 1693 | E76: sf | F76: 16 | G76: =D76*F76 -> 27088 | H76: I | I76: 0 | K76: 70000 | M76: 70000 | N76: I | O76: 0 | Q76: 70000 | R76: I | S76: 65493 | AB76: Footing - F20.0 | AC76: 440 | AD76: SF
B77: walls - Addendum #5 added wall in trash room level 1 | G77: =D77*F77 -> 0 | I77: 4100 | K77: 4100 | M77: 4100 | O77: 4100 | Q77: 4100 | S77: 4100 | AB77: Footing - F43.0 | AC77: 946 | AD77: SF
G78: =D78*F78 -> 0
B79: Dumpster Enclosure | D79: 1 | E79: ls | F79: 25000 | G79: =D79*F79 -> 25000 | I79: =$G79 -> 25000 | J79: I | L79: I | M79: 0 | O79: =$G79 -> 25000 | R79: I | S79: 25433
G80: =D80*F80 -> 0
B81: Hardscape - sidewalks & stabilization | G81: =D81*F81 -> 0 | H81: X | J81: X | L81: X | N81: X | R81: X | S81: -370789
G82: =D82*F82 -> 0
B83: House keeping pads | D83: 1 | E83: ls | F83: 20000 | G83: =D83*F83 -> 20000 | I83: =$G83 -> 20000 | K83: =$G83 -> 20000 | M83: =$G83 -> 20000 | O83: =$G83 -> 20000 | Q83: =$G83 -> 20000 | S83: =$G83 -> 20000
G84: =D84*F84 -> 0
B85: Addendum #5 | G85: =D85*F85 -> 0 | H85: I | J85: I | N85: I
B86: Addendum #6 | G86: =D86*F86 -> 0 | J86: I
B87: Addendum #7 - extend foundations | G87: =D87*F87 -> 0 | I87: 5000 | J87: I | K87: 4700 | M87: 5000 | O87: 5000 | Q87: 5000 | S87: 5000
G88: =D88*F88 -> 0
G89: =D89*F89 -> 0
G90: =D90*F90 -> 0 | AC90: =SUM(AC69:AC84) -> 6416 | AD90: SF | AE90: =(24-4)/12 -> 1.6666667 | AF90: ft | AG90: =AC90*AE90/27 -> 396.04938 | AH90: cy
F92: SUBTOTAL | G92: =SUM(G20:G91) -> 4957965.8 | I92: =SUM(I20:I91) -> 6774851.3 | K92: =SUM(K20:K91) -> 5700849.3 | M92: =SUM(M20:M91) -> 5882569.3 | O92: =SUM(O20:O91) -> 6755331.3 | Q92: =SUM(Q20:Q91) -> 6892046.3 | S92: =SUM(S20:S91) -> 8202620.9 | U92: =SUM(U20:U91) -> 0 | W92: =SUM(W20:W91) -> 0 | Y92: =SUM(Y20:Y91) -> 0
F93: BOND RATE | H93: 0.005 | J93: 0 | L93: 0 | N93: 0 | P93: 0 | R93: 0 | T93: 0 | V93: 0 | X93: 0
F94: BOND AMOUNT | I94: =H93*I92 -> 33874.257 | K94: =J93*K92 -> 0 | M94: =L93*M92 -> 0 | O94: =N93*O92 -> 0 | Q94: =P93*Q92 -> 0 | S94: =R93*S92 -> 0 | U94: =T93*U92 -> 0 | W94: =V93*W92 -> 0 | Y94: =X93*Y92 -> 0
F96: ADJUSTED TOTAL | I96: =SUM(I92:I95) -> 6808725.6 | K96: =SUM(K92:K94) -> 5700849.3 | M96: =SUM(M92:M95) -> 5882569.3 | O96: =SUM(O92:O94) -> 6755331.3 | Q96: =SUM(Q92:Q94) -> 6892046.3 | S96: =SUM(S92:S94) -> 8202620.9 | U96: =SUM(U92:U94) -> 0 | W96: =SUM(W92:W94) -> 0 | Y96: =SUM(Y92:Y94) -> 0
F97: Cost per SF | I97: =I96/'Area Calculations'!$G$4 -> 11.766305 | K97: =K96/'Area Calculations'!$G$4 -> 9.8517606 | M97: =M96/'Area Calculations'!$G$4 -> 10.165795 | O97: =O96/'Area Calculations'!$G$4 -> 11.674034 | Q97: =Q96/'Area Calculations'!$G$4 -> 11.910294 | S97: =S96/'Area Calculations'!$G$4 -> 14.175126 | U97: =U96/'Area Calculations'!$G$4 -> 0 | W97: =W96/'Area Calculations'!$G$4 -> 0 | Y97: =Y96/'Area Calculations'!$G$4 -> 0
F98: Cost per Unit | I98: =I96/'Area Calculations'!$G$9 -> 63632.949 | K98: =K96/'Area Calculations'!$G$9 -> 53278.966 | M98: =M96/'Area Calculations'!$G$9 -> 54977.283 | O98: =O96/'Area Calculations'!$G$9 -> 63133.938 | Q98: =Q96/'Area Calculations'!$G$9 -> 64411.648 | S98: =S96/'Area Calculations'!$G$9 -> 76660.009 | U98: =U96/'Area Calculations'!$G$9 -> 0 | W98: =W96/'Area Calculations'!$G$9 -> 0 | Y98: =Y96/'Area Calculations'!$G$9 -> 0
A100: QUALIFICATIONS
A104: EXCLUSIONS/OWNER PROVIDED ITEMS:
A108: ALTERNATES:
A112: PROPOSED VE (Provide Clear Description):
...

Sheet 03 41 Precast Hollow Core
G1: Hedrick Plug
F2: X | G2: Excluded
F3: I | G3: Included
B4: BACK TO SUMMARY SHEET | G4: Sub Add/Deduct | H4: Bidder1 | J4: Bidder 2 | L4: Bidder 3 | N4: Bidder 4 | P4: Bidder 5 | R4: Bidder 6
A5: Project: | B5: ='Area Calculations'!B4 -> ERAU Residential Hall & Garage Building | G5: Company | H5: Metromont
A6: Trade: | B6: Precast Hollow Core | G6: Contact | H6: Eric Scherden
A7: CSI Code: | B7: 03 41 00 | G7: Phone | H7: 813-417-8796
A8: Date: | G8: Email | H8: escherden@metromont.com
G9: Adjusted Bid | H9: =I88 -> 21767756 | J9: =K88 -> 0 | L9: =M88 -> 0 | N9: =O88 -> 0 | P9: =Q88 -> 0 | R9: =S88 -> 0
C10: Plan/ Spec. Package | D10: QTY | E10: U/M | F10: Unit Cost | G10: Subtotal | H10: Yes/No | I10: Price | J10: Yes/No | K10: Price | L10: Yes/No | M10: Price | N10: Yes/No | O10: Price | P10: Yes/No | Q10: Price | R10: Yes/No | S10: Price
B11: GENERAL INCLUSIONS
B12: INCLUDES ALL SALES TAX | H12: i
B13: ALL HOISTING & RIGGING REQUIRED TO COMPLETE THIS SCOPE | H13: i
B14: PROVIDE P&P BONDS | H14: x | I14: {0.525%}
B15: FLORIDA STATE CONTRACTORS LIC. | H15: i
B16: GENERAL LIABILITY AND WORKERS COMP. INSURANCE LIMITS | H16: i
B17: STATE AND LOCAL TAXES | H17: i
B18: COMPASS | H18: x | I18: {4.0}
B19: SPECIFIC TRADE SCOPE OF WORK REQUIREMENTS
B20: BASE BID | I20: 20274020
B21: Residence Hall Dorms
B22: All precast columns CLA 24x24 | C22: E0.05, E1.01 | D22: 16 | H22: i
B23: Field topped double Tee FTA | C23: E0.05 | H23: i
B24: L Girders LGA 18x48 | C24: E0.05 | H24: i
B25: Factory topped Metrodeck 9" MDK for the roof | C25: E0.06, E2.06 | H25: i
B26: Factory topped Metrodeck 10" MDK Skimcoat for all floors | C26: E0.06, E2.01 | H26: i
B27: Horizontzl insulated wall panels WPB 11" and 12" with return | C27: E0.07 | H27: i
B28: Horizontzl soild wall panels WPB 8" | H28: i
B29: Vertical insulated wall panels WPB 11" with return | C29: E0.07 | H29: i
B30: Vertical insulated wall panels Non-Thermal WPB 11" | C30: E0.07 | H30: i
B31: Vertical solid wall panels Non-Insulated WPB 8" | C31: E0.07 | H31: i
B33: Parking Garage
B34: All precast columns CLA 96x16 | C34: E1.01 | D34: 4 | H34: i
B35: All precast columns CLA 24x33 | C35: E1.01 | D35: 4 | H35: i
B36: Facyory topped double Tee FTA DT | C36: E0.05, E2.02 | D36: 242000 | E36: SF | H36: i
B37: Flat slabs FS 8" | C37: E0.05 | H37: i
B38: Litewall vertical MWV 8" | C38: E0.05 | H38: i
B39: R beams RBA 8x30 | C39: E0.05 | H39: i
B40: Vertical shear walls SWA 12" | C40: E0.05 S113 | H40: i
B41: Spandrel SPA 8x43 | C41: E0.05 | H41: i
B42: T girders TGA 30x36 | C42: E0.05 | H42: i
B43: Horizontzl insulated wall panels WPA 8", 12" | C43: E0.07 | H43: i
B44: Horizontzl soild wall panels WPA 8" | H44: i
B45: Vertical solid wall panels Non-Insulated WPA 8" | C45: E0.07 | H45: i
B46: Fascia FCA 8x48 | H46: i
B48: Z Stairs, Landings, stringers, stair nose | H48: i
B49: Steel beam supporting Metrodeck at each levels 2,3,4,5,6,& Roof 4//EA (RFI1-13) | C49: E2.01A | D49: 24 | H49: i
B50: Diaphragm Steel (RFI1-14) | C50: S121, 124 | D50: 24 | H50: i
B51: Pre-cast Beam above the hanger doors (RFI1-39 Add#1) | C51: 2,3&4 A558
B55: Alternates
B56: Caulking at all precast-to-precast joints and pecast-to washpur joints Uerthan caulking at both sides with mineral wool filter at all fire rated joints at wall common with dormitory corridors, stair, and elevator shafts at Parking Garage | H56: i | I56: 414666
B57: Urethane caulking at exterior (1 layer) and interior (1Layer) Precast-to-precast wall panel, vertical joints and wall panel horizontal joints at Dorm Building | H57: i
B58: Barrier cabels at parking garage | H58: i | I58: 104830
B59: Cast -in-place Wash pours strips and topping slabs for Parking Garage | H59: x
B60: Cast -in-place Wash pours strips and 3-1/2" topping reinforced slabs over metrodeck floor areas at Dorm Building | C60: S121 | H60: i
B61: Field topping slabe 2" fpr all stair landings, flatslabs, including trash rooms, elevator lobbies/Vistibules, electrical rooms, and mechanical rooms at elevated floors | C61: RFI1-17 add#1 | H61: i
B62: Monumental wall graphics (Allowance) (see alternate
B63: Pre cast site dumpster enclosures walls | H63: i | I63: 26500
B64: Corrosion inhabitor and stainless steel connectors at the top level of garage | H64: i | I64: 43500
B65: Window opening chammfers and building corner extensions | H65: i | I65: 89590
B66: Signed and sealed bracing plan | H66: i | I66: 18900
B67: Fagman | H67: i | I67: =50375*2 -> 100750
B68: Crane Mats 6 months | H68: i | I68: =6*30500 -> 183000
B69: Building expansion allowance #11 | H69: i | I69: 500000
B70: General scope | H70: i
B71: BIM Model | H71: i
B72: All cranes and equipment for installation | H72: i
B73: Wood nailer for personnel door framing | H73: i
B74: Window framing wood nailer | H74: i
B75: Stair nosings | H75: i
B76: Provide all steel embeds for the Pre-Cast walls, Columns, and beams (installation by Cast-In Place Sub) | C76: S301 | H76: i
B77: Non-Shrink grout as required for all columns walls | C77: S302
B78: Fill all grout pocket after all connections | C78: S310
B79: Fill all keyway with CIP concrete for all slab-to slab or slab to wall connectins | C79: S310
B81: Addendum #7 - extending wings | I81: 12000
F84: SUBTOTAL | I84: =SUM(I13:I83) -> 21767756 | K84: =SUM(K13:K83) -> 0 | M84: =SUM(M13:M83) -> 0 | O84: =SUM(O13:O83) -> 0 | Q84: =SUM(Q13:Q83) -> 0 | S84: =SUM(S13:S83) -> 0
F85: BOND RATE | H85: 0 | J85: 0 | L85: 0 | N85: 0 | P85: 0 | R85: 0
F86: BOND AMOUNT | I86: =H85*I84 -> 0 | K86: =J85*K84 -> 0 | M86: =L85*M84 -> 0 | O86: =N85*O84 -> 0 | Q86: =P85*Q84 -> 0 | S86: =R85*S84 -> 0
F88: ADJUSTED TOTAL | I88: =SUM(I84:I86) -> 21767756 | K88: =SUM(K84:K86) -> 0 | M88: =SUM(M84:M86) -> 0 | O88: =SUM(O84:O86) -> 0 | Q88: =SUM(Q84:Q86) -> 0 | S88: =SUM(S84:S86) -> 0
F89: Cost per SF | I89: =I88/'Area Calculations'!$G$4 -> 37.617328 | K89: =K88/'Area Calculations'!$G$4 -> 0 | M89: =M88/'Area Calculations'!$G$4 -> 0 | O89: =O88/'Area Calculations'!$G$4 -> 0 | Q89: =Q88/'Area Calculations'!$G$4 -> 0 | S89: =S88/'Area Calculations'!$G$4 -> 0
F90: Cost per Unit | I90: =I88/'Area Calculations'!$G$9 -> 203436.97 | K90: =K88/'Area Calculations'!$G$9 -> 0 | M90: =M88/'Area Calculations'!$G$9 -> 0 | O90: =O88/'Area Calculations'!$G$9 -> 0 | Q90: =Q88/'Area Calculations'!$G$9 -> 0 | S90: =S88/'Area Calculations'!$G$9 -> 0
A92: QUALIFICATIONS
A96: EXCLUSIONS/OWNER PROVIDED ITEMS:
A100: ALTERNATES:
A104: PROPOSED VE (Provide Clear Description):
A108: FULLY LOADED LABOR RATES
B109: Laborer
B110: Mechanic
B111: Superintendent
B112: Project Manager
A114: SCHEDULE
B115: Prepared shop drawings/submittals
B116: Mobilization
B117: Total duration to complete scope of work
A119: Winner
A120: Company | B120: =H5 -> Metromont
A121: Contact | B121: =H6 -> Eric Scherden
A122: Phone | B122: =H7 -> 813-417-8796
A123: Email | B123: =H8 -> escherden@metromont.com
A124: Base Bid | B124: =H9 -> 21767756

Sheet 03 45 Architectural Precast
G1: Hedrick Plug
F2: X | G2: Excluded
F3: I | G3: Included
B4: BACK TO SUMMARY SHEET | G4: Sub Add/Deduct | H4: Bidder1 | J4: Bidder 2 | L4: Bidder 3 | N4: Bidder 4 | P4: Bidder 5 | R4: Bidder 6
A5: Project: | B5: ='Area Calculations'!B4 -> ERAU Residential Hall & Garage Building | G5: Company
A6: Trade: | B6: Architectural Precast | G6: Contact
A7: CSI Code: | B7: 03 45 00 | G7: Phone
A8: Date: | G8: Email
G9: Adjusted Bid | H9: =I56 -> 0 | J9: =K56 -> 0 | L9: =M56 -> 0 | N9: =O56 -> 0 | P9: =Q56 -> 0 | R9: =S56 -> 0
C10: Plan/ Spec. Package | D10: QTY | E10: U/M | F10: Unit Cost | G10: Subtotal | H10: Yes/No | I10: Price | J10: Yes/No | K10: Price | L10: Yes/No | M10: Price | N10: Yes/No | O10: Price | P10: Yes/No | Q10: Price | R10: Yes/No | S10: Price
B11: GENERAL INCLUSIONS
B12: INCLUDES ALL SALES TAX
B13: ALL HOISTING & RIGGING REQUIRED TO COMPLETE THIS SCOPE
B14: PROVIDE P&P BONDS
B15: FLORIDA STATE CONTRACTORS LIC.
B16: GENERAL LIABILITY AND WORKERS COMP. INSURANCE LIMITS
B17: STATE AND LOCAL TAXES
B18: SPECIFIC TRADE SCOPE OF WORK REQUIREMENTS
B19: BASE BID
F52: SUBTOTAL | I52: =SUM(I13:I51) -> 0 | K52: =SUM(K13:K51) -> 0 | M52: =SUM(M13:M51) -> 0 | O52: =SUM(O13:O51) -> 0 | Q52: =SUM(Q13:Q51) -> 0 | S52: =SUM(S13:S51) -> 0
F53: BOND RATE | H53: 0 | J53: 0 | L53: 0 | N53: 0 | P53: 0 | R53: 0
F54: BOND AMOUNT | I54: =H53*I52 -> 0 | K54: =J53*K52 -> 0 | M54: =L53*M52 -> 0 | O54: =N53*O52 -> 0 | Q54: =P53*Q52 -> 0 | S54: =R53*S52 -> 0
F56: ADJUSTED TOTAL | I56: =SUM(I52:I54) -> 0 | K56: =SUM(K52:K54) -> 0 | M56: =SUM(M52:M54) -> 0 | O56: =SUM(O52:O54) -> 0 | Q56: =SUM(Q52:Q54) -> 0 | S56: =SUM(S52:S54) -> 0
F57: Cost per SF | I57: =I56/'Area Calculations'!$G$4 -> 0 | K57: =K56/'Area Calculations'!$G$4 -> 0 | M57: =M56/'Area Calculations'!$G$4 -> 0 | O57: =O56/'Area Calculations'!$G$4 -> 0 | Q57: =Q56/'Area Calculations'!$G$4 -> 0 | S57: =S56/'Area Calculations'!$G$4 -> 0
F58: Cost per Unit | I58: =I56/'Area Calculations'!$G$9 -> 0 | K58: =K56/'Area Calculations'!$G$9 -> 0 | M58: =M56/'Area Calculations'!$G$9 -> 0 | O58: =O56/'Area Calculations'!$G$9 -> 0 | Q58: =Q56/'Area Calculations'!$G$9 -> 0 | S58: =S56/'Area Calculations'!$G$9 -> 0
A60: QUALIFICATIONS
A64: EXCLUSIONS/OWNER PROVIDED ITEMS:
A68: ALTERNATES:
A72: PROPOSED VE (Provide Clear Description):
A76: FULLY LOADED LABOR RATES
B77: Laborer
B78: Mechanic
B79: Superintendent
B80: Project Manager
A82: SCHEDULE
B83: Prepared shop drawings/submittals
B84: Mobilization
B85: Total duration to complete scope of work
A87: Winner
A88: Company
A89: Contact
A90: Phone
A91: Email
A92: Base Bid

Sheet 03 47 Tilt Wall Concrete
G1: Hedrick Plug
F2: X | G2: Excluded
F3: I | G3: Included
B4: BACK TO SUMMARY SHEET | G4: Sub Add/Deduct | H4: Bidder1 | J4: Bidder 2 | L4: Bidder 3 | N4: Bidder 4 | P4: Bidder 5 | R4: Bidder 6
A5: Project: | B5: ='Area Calculations'!B4 -> ERAU Residential Hall & Garage Building | G5: Company
A6: Trade: | B6: Tilt Wall Concrete | G6: Contact
A7: CSI Code: | B7: 03 47 00 | G7: Phone
A8: Date: | G8: Email
G9: Adjusted Bid | H9: =I55 -> 0 | J9: =K55 -> 0 | L9: =M55 -> 0 | N9: =O55 -> 0 | P9: =Q55 -> 0 | R9: =S55 -> 0
C10: Plan/ Spec. Package | D10: QTY | E10: U/M | F10: Unit Cost | G10: Subtotal | H10: Yes/No | I10: Price | J10: Yes/No | K10: Price | L10: Yes/No | M10: Price | N10: Yes/No | O10: Price | P10: Yes/No | Q10: Price | R10: Yes/No | S10: Price
B11: GENERAL INCLUSIONS
B12: INCLUDES ALL SALES TAX
B13: ALL HOISTING & RIGGING REQUIRED TO COMPLETE THIS SCOPE
B14: PROVIDE P&P BONDS
B15: FLORIDA STATE CONTRACTORS LIC.
B16: GENERAL LIABILITY AND WORKERS COMP. INSURANCE LIMITS
B17: STATE AND LOCAL TAXES
B18: SPECIFIC TRADE SCOPE OF WORK REQUIREMENTS
B19: BASE BID
F51: SUBTOTAL | I51: =SUM(I13:I50) -> 0 | K51: =SUM(K13:K50) -> 0 | M51: =SUM(M13:M50) -> 0 | O51: =SUM(O13:O50) -> 0 | Q51: =SUM(Q13:Q50) -> 0 | S51: =SUM(S13:S50) -> 0
F52: BOND RATE | H52: 0 | J52: 0 | L52: 0 | N52: 0 | P52: 0 | R52: 0
F53: BOND AMOUNT | I53: =H52*I51 -> 0 | K53: =J52*K51 -> 0 | M53: =L52*M51 -> 0 | O53: =N52*O51 -> 0 | Q53: =P52*Q51 -> 0 | S53: =R52*S51 -> 0
F55: ADJUSTED TOTAL | I55: =SUM(I51:I53) -> 0 | K55: =SUM(K51:K53) -> 0 | M55: =SUM(M51:M53) -> 0 | O55: =SUM(O51:O53) -> 0 | Q55: =SUM(Q51:Q53) -> 0 | S55: =SUM(S51:S53) -> 0
F56: Cost per SF | I56: =I55/'Area Calculations'!$G$4 -> 0 | K56: =K55/'Area Calculations'!$G$4 -> 0 | M56: =M55/'Area Calculations'!$G$4 -> 0 | O56: =O55/'Area Calculations'!$G$4 -> 0 | Q56: =Q55/'Area Calculations'!$G$4 -> 0 | S56: =S55/'Area Calculations'!$G$4 -> 0
F57: Cost per Unit | I57: =I55/'Area Calculations'!$G$9 -> 0 | K57: =K55/'Area Calculations'!$G$9 -> 0 | M57: =M55/'Area Calculations'!$G$9 -> 0 | O57: =O55/'Area Calculations'!$G$9 -> 0 | Q57: =Q55/'Area Calculations'!$G$9 -> 0 | S57: =S55/'Area Calculations'!$G$9 -> 0
A59: QUALIFICATIONS
A63: EXCLUSIONS/OWNER PROVIDED ITEMS:
A67: ALTERNATES:
A71: PROPOSED VE (Provide Clear Description):
A75: FULLY LOADED LABOR RATES
B76: Laborer
B77: Mechanic
B78: Superintendent
B79: Project Manager
A81: SCHEDULE
B82: Prepared shop drawings/submittals
B83: Mobilization
B84: Total duration to complete scope of work
A86: Winner
A87: Company
A88: Contact
A89: Phone
A90: Email
A91: Base Bid

Sheet 04 22 Concrete Unit Masonry
G1: Hedrick Plug
F2: X | G2: Excluded
F3: I | G3: Included
B4: BACK TO SUMMARY SHEET | G4: Sub Add/Deduct | H4: Bidder1 | J4: Bidder 2 | L4: Bidder 3 | N4: Bidder 4 | P4: Bidder 5 | R4: Bidder 6
A5: Project: | B5: ='Area Calculations'!B4 -> ERAU Residential Hall & Garage Building | G5: Company
A6: Trade: | B6: Concrete Unit Masonry | G6: Contact
A7: CSI Code: | B7: 04 22 00 | G7: Phone
A8: Date: | G8: Email
G9: Adjusted Bid | H9: =I56 -> 0 | J9: =K56 -> 0 | L9: =M56 -> 0 | N9: =O56 -> 0 | P9: =Q56 -> 0 | R9: =S56 -> 0
C10: Plan/ Spec. Package | D10: QTY | E10: U/M | F10: Unit Cost | G10: Subtotal | H10: Yes/No | I10: Price | J10: Yes/No | K10: Price | L10: Yes/No | M10: Price | N10: Yes/No | O10: Price | P10: Yes/No | Q10: Price | R10: Yes/No | S10: Price
B11: GENERAL INCLUSIONS
B12: INCLUDES ALL SALES TAX
B13: ALL HOISTING & RIGGING REQUIRED TO COMPLETE THIS SCOPE
B14: PROVIDE P&P BONDS
B15: FLORIDA STATE CONTRACTORS LIC.
B16: GENERAL LIABILITY AND WORKERS COMP. INSURANCE LIMITS
B17: STATE AND LOCAL TAXES
B18: COMPASS
B19: SPECIFIC TRADE SCOPE OF WORK REQUIREMENTS
B20: BASE BID
B22: 8" CMU Walls
B23: walls - S112, S114 - B.15 to B.24 / A.18
F52: SUBTOTAL | I52: =SUM(I13:I51) -> 0 | K52: =SUM(K13:K51) -> 0 | M52: =SUM(M13:M51) -> 0 | O52: =SUM(O13:O51) -> 0 | Q52: =SUM(Q13:Q51) -> 0 | S52: =SUM(S13:S51) -> 0
F53: BOND RATE | H53: 0 | J53: 0 | L53: 0 | N53: 0 | P53: 0 | R53: 0
F54: BOND AMOUNT | I54: =H53*I52 -> 0 | K54: =J53*K52 -> 0 | M54: =L53*M52 -> 0 | O54: =N53*O52 -> 0 | Q54: =P53*Q52 -> 0 | S54: =R53*S52 -> 0
F56: ADJUSTED TOTAL | I56: =SUM(I52:I54) -> 0 | K56: =SUM(K52:K54) -> 0 | M56: =SUM(M52:M54) -> 0 | O56: =SUM(O52:O54) -> 0 | Q56: =SUM(Q52:Q54) -> 0 | S56: =SUM(S52:S54) -> 0
F57: Cost per SF | I57: =I56/'Area Calculations'!$G$4 -> 0 | K57: =K56/'Area Calculations'!$G$4 -> 0 | M57: =M56/'Area Calculations'!$G$4 -> 0 | O57: =O56/'Area Calculations'!$G$4 -> 0 | Q57: =Q56/'Area Calculations'!$G$4 -> 0 | S57: =S56/'Area Calculations'!$G$4 -> 0
F58: Cost per Unit | I58: =I56/'Area Calculations'!$G$9 -> 0 | K58: =K56/'Area Calculations'!$G$9 -> 0 | M58: =M56/'Area Calculations'!$G$9 -> 0 | O58: =O56/'Area Calculations'!$G$9 -> 0 | Q58: =Q56/'Area Calculations'!$G$9 -> 0 | S58: =S56/'Area Calculations'!$G$9 -> 0
A60: QUALIFICATIONS
A64: EXCLUSIONS/OWNER PROVIDED ITEMS:
A68: ALTERNATES:
A72: PROPOSED VE (Provide Clear Description):
A76: FULLY LOADED LABOR RATES
B77: Laborer
B78: Mechanic
B79: Superintendent
B80: Project Manager
A82: SCHEDULE
B83: Prepared shop drawings/submittals
B84: Mobilization
B85: Total duration to complete scope of work
A87: Winner
A88: Company
A89: Contact
A90: Phone
A91: Email
A92: Base Bid

Sheet 05 10 Steel
G1: Hedrick Plug
F2: X | G2: Excluded
F3: I | G3: Included | P3: canopy VE option
B4: BACK TO SUMMARY SHEET | G4: Sub Add/Deduct | H4: Bidder 1 | J4: Bidder 2 | L4: Bidder 2 | N4: Bidder 3 | P4: Bidder 3 | R4: Bidder 5
A5: Project: | B5: ='Area Calculations'!B4 -> ERAU Residential Hall & Garage Building | G5: Company | H5: Pilar Welding | J5: Suncor | L5: Paradise Panel and Steel | N5: Rapid Accurate Design | P5: Coastal Metal
A6: Trade: | B6: Steel | G6: Contact | H6: Estimating | J6: Scott Kuiper | L6: Ralph Gainer | N6: Zach Thompson | P6: Laura Montes
A7: CSI Code: | B7: 05 10 00 | G7: Phone | H7: 561-524-9246 | J7: 305-359-1400 | L7: 305-597-5714 ext 206 | N7: 561-635-5907 | P7: 561-819-0308
A8: Date: | G8: Email | H8: estimating@pilarwelding.com | J8: scott.k@suncor.net | L8: rgainer@panelsandsteel.com | N8: zt@radaf.com | P8: lmontes@coastalmetal.biz
G9: Adjusted Bid | H9: =I66 -> 349703.77 | J9: =K66 -> 344087.55 | L9: =M66 -> 416407 | N9: =O66 -> 888072 | P9: =Q66 -> 39837 | R9: =S66 -> 0
C10: Plan/ Spec. Package | D10: QTY | E10: U/M | F10: Unit Cost | G10: Subtotal | H10: Yes/No | I10: Price | J10: Yes/No | K10: Price | L10: Yes/No | M10: Price | N10: Yes/No | O10: Price | P10: Yes/No | Q10: Price | R10: Yes/No | S10: Price
B11: GENERAL INCLUSIONS
B12: INCLUDES ALL SALES TAX | H12: i | J12: i | L12: i | N12: i | P12: i
B13: ALL HOISTING & RIGGING REQUIRED TO COMPLETE THIS SCOPE | H13: i | J13: i | L13: ? | N13: i | P13: i
B14: PROVIDE P&P BONDS | H14: x | I14: {3.0%} | J14: x | L14: x | N14: x | P14: x
B15: FLORIDA STATE CONTRACTORS LIC. | H15: i | J15: i | L15: i | N15: i | P15: i
B16: GENERAL LIABILITY AND WORKERS COMP. INSURANCE LIMITS | H16: i | J16: i | L16: i | N16: i | P16: i
B17: STATE AND LOCAL TAXES | H17: i | J17: i | L17: i | N17: i | P17: i
B18: COMPASS | H18: x | J18: i | L18: x | N18: x | P18: i | Q18: {4.0}
B19: SPECIFIC TRADE SCOPE OF WORK REQUIREMENTS
B20: BASE BID | O20: =51300+28800 -> 80100
B22: Acknowledgement of RFIs | H22: i | J22: i | L22: i | N22: i | P22: i
B23: Acknowledgement of addendums | H23: i | J23: i | L23: i | N23: i | P23: i
B24: Acknowledgement of specs manual | H24: i | J24: i | L24: i | N24: i | P24: i
B26: Steel Shade devices (6) - Excluded, see alternate | H26: x | J26: x | L26: x | N26: x | P26: i | Q26: {212610}
B27: Aluminum Powdercoating 10 year warranty as per Add #5 | H27: x | J27: x | L27: x | N27: x | P27: i | Q27: {alum powdercoated}
B28: Structural Steel as per details S500,S502,S503 | H28: x | J28: x | L28: x | N28: x | P28: i
B29: Steel Canopies devices (5) - AESS Cat 1 as per RFI #29 | H29: i | I29: =213511.43+62178.52 -> 275689.95 | J29: i | K29: 304250.55 | L29: i | M29: =224870+151700 -> 376570 | N29: i | O29: 774930 | P29: i
B30: RFI#200 Galvanized w/ white paint | H30: i | J30: i | L30: i | N30: i | P30: i | Q30: {alum powdercoated}
B31: Structural Steel as per details S500,S501,S502,S503 | H31: i | J31: i | L31: i | N31: i | P31: i
B32: Water scuppers | H32: i | J32: i | L32: i | N32: i | P32: i
B33: ACM paneling - in Metal Panel | H33: x | J33: x | L33: i | N33: i | O33: asked deduct | P33: x
B35: Precast T flange support at CIP slab edge - foundation level CIP wall between grid lines A.21 & A.22, B.15 & B.24 | H35: i | J35: P | L35: P | N35: P | P35: P
B36: GALV L8x8x1/2 x 12" @ 4'-0" w/ (132 LF of wall) | C36: 8/S301, S112,S114 | D36: 27 | E36: EA | F36: =27*1*3 -> 81 | G36: =F36*D36 -> 2187 | H36: i | I36: =93.45*D36 -> 2523.15 | J36: P | K36: =$G$36 -> 2187 | L36: P | M36: =$G$36 -> 2187 | N36: P | O36: =$G$36 -> 2187 | P36: P | Q36: =$G$36 -> 2187
B37: (2) 3/4" SS SCR ANCHORS w/ 6" EMBED @ 8" | D37: =2*D36 -> 54 | E37: EA | F37: 10 | G37: =F37*D37 -> 540 | H37: i | J37: P | K37: =$G$37 -> 540 | L37: P | M37: =$G$37 -> 540 | N37: P | O37: =$G$37 -> 540 | P37: P | Q37: =$G$37 -> 540
B39: Elevator Guide Rail bracing - confirm requirement with elev sub - Excluded | C39: 5 & 6/S311 | H39: x | J39: x | L39: x | N39: x | P39: x
B41: Plates & embed at PT Beams - 2nd Floor Framing only - Grid Lines A.31 & A.33 | H41: i | I41: =71.47*170 -> 12149.9 | J41: P | L41: P | N41: P | P41: P
B42: 3/4"x10"x72" PL | C42: 4/S321 | D42: 4 | E42: EA | F42: =26*6*3 -> 468 | G42: =F42*D42 -> 1872 | H42: i | J42: P | K42: =$G$42 -> 1872 | L42: P | M42: =$G$42 -> 1872 | N42: P | O42: =$G$42 -> 1872 | P42: P | Q42: =$G$42 -> 1872
B43: 3/4"x12"x36" PL | C43: 4/S321, S122, S124 | D43: 4 | E43: EA | F43: =30*3*3 -> 270 | G43: =F43*D43 -> 1080 | H43: i | J43: P | K43: =$G$43 -> 1080 | L43: P | M43: =$G$43 -> 1080 | N43: P | O43: =$G$43 -> 1080 | P43: P | Q43: =$G$43 -> 1080
B44: (10) 3/4" ⌀ x 8" LG HAS @ 8" EW ( at CIP columns) | D44: =10*D43 -> 40 | E44: EA | F44: 20 | G44: =F44*D44 -> 800 | H44: i | J44: P | K44: =$G$44 -> 800 | L44: P | M44: =$G$44 -> 800 | N44: P | O44: =$G$44 -> 800 | P44: P | Q44: =$G$44 -> 800
B45: GALV 1/2"x12"x1'-0" PL @ 4' OC (170 LF of PT beam) | C45: 1 & 2/S321 | D45: 43 | E45: EA | F45: =20*1*3 -> 60 | G45: =F45*D45 -> 2580 | H45: i | J45: P | K45: =$G$45 -> 2580 | L45: P | M45: =$G$45 -> 2580 | N45: P | O45: =$G$45 -> 2580 | P45: P | Q45: =$G$45 -> 2580
B46: (4)3/4" ⌀ x 8" LG HAS @ 8" EW | D46: =4*D45 -> 172 | E46: EA | F46: 20 | G46: =F46*D46 -> 3440 | H46: i | J46: P | K46: =$G$46 -> 3440 | L46: P | M46: =$G$46 -> 3440 | N46: P | O46: =$G$46 -> 3440 | P46: P | Q46: =$G$46 -> 3440
B47: L6x4x3/8 LLV CONT (170 LF of PT beam) | C47: 1& 2/S321 | D47: 170 | E47: LF | F47: =12*1*3 -> 36 | G47: =F47*D47 -> 6120 | H47: i | J47: P | K47: =$G$47 -> 6120 | L47: P | M47: =$G$47 -> 6120 | N47: P | O47: =$G$47 -> 6120 | P47: P | Q47: =$G$47 -> 6120
B48: L8x6x1/2x12" LLV @ 3' OC (170 LF of PT beam) | C48: 3/S321 | D48: 57 | E48: EA | F48: =23*1*3 -> 69 | G48: =F48*D48 -> 3933 | H48: i | J48: P | K48: =$G$48 -> 3933 | L48: P | M48: =$G$48 -> 3933 | N48: P | O48: =$G$48 -> 3933 | P48: P | Q48: =$G$48 -> 3933
B49: (2) 3/4" ADHESIVE ANCHORS w/ 6" EMBED @ 8" THRU VERT SLOT | D49: =2*D48 -> 114 | E49: EA | F49: 10 | G49: =F49*D49 -> 1140 | H49: i | J49: P | K49: =$G$49 -> 1140 | L49: P | M49: =$G$49 -> 1140 | N49: P | O49: =$G$49 -> 1140 | P49: P | Q49: =$G$49 -> 1140
B50: PL 1/2"x9"x0'-9" (170 LF of PT beam) | C50: 3/S321 | D50: 170 | E50: LF | F50: =15*1*3 -> 45 | G50: =F50*D50 -> 7650 | H50: i | J50: P | K50: =$G$50 -> 7650 | L50: P | M50: =$G$50 -> 7650 | N50: P | O50: =$G$50 -> 7650 | P50: P | Q50: =$G$50 -> 7650
B51: (4) 3/4"x6"LG HEADED STUDS @ 6" EW | D51: =340 -> 340 | E51: EA | F51: 5 | G51: =F51*D51 -> 1700 | H51: i | J51: P | K51: =$G$51 -> 1700 | L51: P | M51: =$G$51 -> 1700 | N51: P | O51: =$G$51 -> 1700 | P51: P | Q51: =$G$51 -> 1700
B52: Top of CMU wall to Double Tees - walls - S112, S114 - B.15 to B.24 / A.18 | C52: 3/S400 | H52: i | J52: P | L52: P | N52: P | P52: P
B53: 3/8" PL x5" WIDE @ 4'-0" (180 LF of CMU wall) | D53: 45 | E53: EA | F53: =6*4*3 -> 72 | G53: =F53*D53 -> 3240 | H53: i | I53: =212.91*D53 -> 9580.95 | J53: P | K53: =$G$53 -> 3240 | L53: P | M53: =$G$53 -> 3240 | N53: P | O53: =$G$53 -> 3240 | P53: P | Q53: =$G$53 -> 3240
B54: 3/8" ⌀SCREW ANCHORS W/ 2" EMBED | D54: 45 | E54: EA | F54: 5 | G54: =F54*D54 -> 225 | H54: i | J54: P | K54: =$G$54 -> 225 | L54: P | M54: =$G$54 -> 225 | N54: P | O54: =$G$54 -> 225 | P54: P | Q54: =$G$54 -> 225
B55: PL1/4"x5"x18" @ 4'-0" | D55: 45 | E55: EA | F55: =5*2*3 -> 30 | G55: =F55*D55 -> 1350 | H55: i | J55: P | K55: =$G$55 -> 1350 | L55: P | M55: =$G$55 -> 1350 | N55: P | O55: =$G$55 -> 1350 | P55: P | Q55: =$G$55 -> 1350
B56: L6x4x5/16x3", BS @ 4'-0" | D56: 45 | E56: EA | F56: =10*0.3*3 -> 9 | G56: =F56*D56 -> 405 | H56: i | J56: P | K56: =$G$56 -> 405 | L56: P | M56: =$G$56 -> 405 | N56: P | O56: =$G$56 -> 405 | P56: P | Q56: =$G$56 -> 405
B57: 6"x4"x1/4"x4" WIDE BENT PL @4' | D57: 45 | E57: EA | F57: =5*0.5*3 -> 7.5 | G57: =F57*D57 -> 337.5 | H57: i | J57: P | K57: =$G$57 -> 337.5 | L57: P | M57: =$G$57 -> 337.5 | N57: P | O57: =$G$57 -> 337.5 | P57: P | Q57: =$G$57 -> 337.5
B58: L6x6x3/8x4" @ 4'-0" BS | D58: 45 | E58: EA | F58: =15*0.5*3 -> 22.5 | G58: =F58*D58 -> 1012.5 | H58: i | J58: P | K58: =$G$58 -> 1012.5 | L58: P | M58: =$G$58 -> 1012.5 | N58: P | O58: =$G$58 -> 1012.5 | P58: P | Q58: =$G$58 -> 1012.5
B59: 3/8" ⌀ SCREW ANCHORS | D59: 45 | E59: EA | F59: 5 | G59: =F59*D59 -> 225 | H59: i | J59: P | K59: =$G$59 -> 225 | L59: P | M59: =$G$59 -> 225 | N59: P | O59: =$G$59 -> 225 | P59: P | Q59: =$G$59 -> 225
B60: General Conditions and Installation | H60: i | I60: =(66952.58+6626.4+6450+6998.44)/2 -> 43513.71 | J60: i | L60: i | N60: i
F62: SUBTOTAL | I62: =SUM(I12:I61) -> 343457.66 | K62: =SUM(K12:K61) -> 344087.55 | M62: =SUM(M12:M61) -> 416407 | O62: =SUM(O12:O51) -> 888072 | Q62: =SUM(Q12:Q61) -> 39837 | S62: =SUM(S12:S51) -> 0
F63: BOND RATE | H63: 0.015 | J63: 0 | L63: 0 | N63: 0 | P63: 0 | R63: 0
F64: BOND AMOUNT | I64: =H63*$M$62 -> 6246.105 | K64: =J63*$M$62 -> 0 | M64: =L63*$M$62 -> 0 | O64: =N63*$M$62 -> 0 | Q64: =P63*$M$62 -> 0 | S64: =R63*$M$62 -> 0
F66: ADJUSTED TOTAL | I66: =SUM(I62:I64) -> 349703.77 | K66: =SUM(K62:K64) -> 344087.55 | M66: =SUM(M62:M64) -> 416407 | O66: =SUM(O62:O64) -> 888072 | Q66: =SUM(Q62:Q64) -> 39837 | S66: =SUM(S62:S64) -> 0
F67: Cost per SF | I67: =I66/'Area Calculations'!$G$4 -> 0.60433061 | K67: =K66/'Area Calculations'!$G$4 -> 0.59462511 | M67: =M66/'Area Calculations'!$G$4 -> 0.71960191 | O67: =O66/'Area Calculations'!$G$4 -> 1.5346964 | Q67: =Q66/'Area Calculations'!$G$4 -> 0.068843178 | S67: =S66/'Area Calculations'!$G$4 -> 0
F68: Cost per Unit | I68: =I66/'Area Calculations'!$G$9 -> 3268.2595 | K68: =K66/'Area Calculations'!$G$9 -> 3215.7715 | M68: =M66/'Area Calculations'!$G$9 -> 3891.6542 | O68: =O66/'Area Calculations'!$G$9 -> 8299.7383 | Q68: =Q66/'Area Calculations'!$G$9 -> 372.30841 | S68: =S66/'Area Calculations'!$G$9 -> 0
A70: QUALIFICATIONS
A74: EXCLUSIONS/OWNER PROVIDED ITEMS:
A78: ALTERNATES:
B79: Wing Shaped canopies | H79: i | I79: 403683.72 | J79: i | K79: 930415 | L79: i | M79: 417300 | N79: i | O79: 1092168 | P79: i | Q79: 212610
A82: PROPOSED VE (Provide Clear Description):
A86: FULLY LOADED LABOR RATES
B87: Laborer
B88: Mechanic
B89: Superintendent
B90: Project Manager
A92: SCHEDULE
B93: Prepared shop drawings/submittals
B94: Mobilization
B95: Total duration to complete scope of work
A97: Winner
A98: Company | B98: =H5 -> Pilar Welding
A99: Contact | B99: =H6 -> Estimating
A100: Phone | B100: =H7 -> 561-524-9246
A101: Email | B101: =H8 -> estimating@pilarwelding.com
A102: Base Bid | B102: =H9 -> 349703.77

Sheet 05 52 Misc. Metals
G1: Hedrick Plug
F2: X | G2: Excluded
F3: I | G3: Included
B4: BACK TO SUMMARY SHEET | G4: Sub Add/Deduct | H4: Bidder 1 | J4: Bidder 2 | L4: Bidder 3 | N4: Bidder 4 | P4: Bidder 4 | R4: Bidder 5 | T4: Bidder 6 | V4: Bidder 7
A5: Project: | B5: ='Area Calculations'!B4 -> ERAU Residential Hall & Garage Building | G5: Company | H5: Pilar Welding | J5: Coastal Metal | L5: Paradise Panel and Steel | N5: Chancey Metals | P5: Unlimited Welding | R5: Pilar Welding | T5: Rapid Accurate Design | V5: Atlantic Central Enterprises, Inc
A6: Trade: | B6: Misc. Metals | G6: Contact | H6: Estimating | J6: Laura Montes | L6: Ralph Gainer | N6: Estimating | P6: Robert Rutherford | R6: Yailen Montes | T6: Zach Thompson | V6: Steve Traulsen
A7: CSI Code: | B7: 05 52 00 | G7: Phone | H7: 561-524-9246 | J7: (561) 819-0308 | L7: 305-597-5714 ext 206 | N7: 904-260-6880 | P7: 407-509-6877 | R7: 561-524-9246 | T7: 561-635-5907 | V7: 386-255-6227
A8: Date: | G8: Email | H8: estimating@pilarwelding.com | J8: <lmontes@coastalmetal.biz> | L8: rgainer@panelsandsteel.com | N8: Estimating@chanceymetals.com | P8: Robert.Rutherford@unlimitedwelding.com | R8: <estimating@pilarwelding.com> | T8: zt@radaf.com | V8: ace-st@cfl.rr.com
G9: Adjusted Bid | H9: =I63 -> 334591.49 | J9: =K63 -> 458856 | L9: =M63 -> 486855 | N9: =O63 -> 474707 | P9: =Q63 -> 760591 | R9: =S63 -> 0 | T9: =U63 -> 303840 | V9: =W63 -> 0
C10: Plan/ Spec. Package | D10: QTY | E10: U/M | F10: Unit Cost | G10: Subtotal | J10: Yes/No | K10: Price | L10: Yes/No | M10: Price | N10: Yes/No | O10: Price | P10: Yes/No | Q10: Price | R10: Yes/No | S10: Price | T10: Yes/No | U10: Price | V10: Yes/No | W10: Price
B11: GENERAL INCLUSIONS
B12: INCLUDES ALL SALES TAX | H12: i | J12: i | L12: i | N12: i | P12: i
B13: ALL HOISTING & RIGGING REQUIRED TO COMPLETE THIS SCOPE | H13: i | J13: i | L13: i | N13: i | P13: x
B14: PROVIDE P&P BONDS | H14: x | J14: x | L14: x | N14: x | P14: x
B15: FLORIDA STATE CONTRACTORS LIC. | H15: i | J15: i | L15: i | N15: i | P15: i
B16: GENERAL LIABILITY AND WORKERS COMP. INSURANCE LIMITS | H16: i | J16: i | L16: i | N16: i | P16: i
B17: STATE AND LOCAL TAXES | H17: i | J17: i | L17: i | N17: i | P17: i
B18: COMPASS | H18: x | J18: i | L18: x | N18: x | P18: x
B19: SPECIFIC TRADE SCOPE OF WORK REQUIREMENTS
B20: BASE BID | I20: =66891.78+19584+28864+18528+37080+53010+18620+2660 -> 245237.78 | Q20: 491751
B22: Acknowledgement of RFIs | H22: i | J22: i | L22: i | N22: i | P22: i
B23: Acknowledgement of addendums | H23: i | J23: i | L23: i | N23: i | P23: i
B24: Acknowledgement of specs manual | H24: i | J24: i | L24: i | N24: i | P24: i
B26: Stair guardrailings (Stairs A,B,C,D) | D26: =122*2+130*2 -> 504 | E26: LF | F26: 90 | G26: =F26*D26 -> 45360 | H26: i | J26: i | K26: 129210 | L26: i | M26: =30700+30700+27000+27000 -> 115400 | N26: i | O26: 77602 | P26: i
B27: Railing specs (1 1/2" dia guardrail, 1 1/2" dia posts, 3/4" dia. metal pickets) | H27: i | J27: i | L27: i | N27: P | O27: 25000 | P27: i
B28: ESP painting - see in Painting | H28: i | J28: x | L28: x | N28: x | P28: x
B29: Stair wall mounted handrailings | D29: =122*2+130*2 -> 504 | E29: LF | F29: 90 | G29: =F29*D29 -> 45360 | H29: i | J29: i | L29: i | N29: i | P29: i
B30: Railing specs (1 1/2" dia guardrail)) | H30: i | J30: i | L30: i | N30: i | P30: i
B31: ESP painting - see in Painting | H31: x | J31: x | L31: x | N31: x | P31: x
B32: Concealed brackets | H32: P | I32: =O32 -> 30000 | J32: i | L32: P | M32: 30000 | N32: P | O32: =M32 -> 30000 | P32: x
B33: Cane detection rail | D33: =5*2 -> 10 | E33: LF | F33: 65 | G33: =F33*D33 -> 650 | H33: i | J33: i | L33: i | N33: P | O33: =G33 -> 650 | P33: x
B34: Wired fence w/door at 7th floor Stair A&C | D34: =150*2 -> 300 | E34: SF | F34: 80 | G34: =F34*D34 -> 24000 | H34: i | J34: i | K34: =5934+11088 -> 17022 | L34: P | M34: =O34 -> 17022 | N34: P | O34: =K34 -> 17022 | P34: i
B35: Facade Metal Screen 10ea @ 170 SF = 1700 SF | C35: RFI#25 | D35: 1700 | E35: SF | F35: 150 | G35: =F35*D35 -> 255000 | H35: i | J35: i | K35: 179418 | L35: i | M35: 253000 | N35: P | O35: =M35 -> 253000 | P35: P | Q35: =O35 -> 253000 | T35: i | U35: =207360+96480 -> 303840
B36: 6"x6" galv steel frame | H36: i | J36: i | L36: i | N36: P | P36: P
B37: 4"x4"x3/32" mesh | H37: i | J37: i | L37: i | N37: P | P37: P
B38: Aircraft graphics 16ga steel plate laser cut | H38: i | J38: i | L38: i | N38: P | P38: P
B39: 20"x20" footings for screens - in Concrete | H39: x | J39: x | L39: x | N39: x | P39: x
B40: Finish | H40: i | J40: i | K40: {AAMA2604} | L40: i | N40: i | P40: i
B41: Single Elevator | H41: i | J41: i | K41: =19404+3400+6480+13392 -> 42676 | L41: P | M41: =O41 -> 42676 | N41: P | O41: =K41 -> 42676 | P41: i
B42: Hoist Beam, Sum pit cover, Pit ladder | D42: 2 | E42: EA | F42: 15000 | G42: =F42*D42 -> 30000 | H42: i | J42: i | L42: P | N42: P | P42: i
B43: Double Elevator | H43: i | J43: i | L43: P | N43: P | P43: i
B44: Hoist Beam, Sum pit cover, Pit ladder | D44: 2 | E44: EA | F44: 15000 | G44: =F44*D44 -> 30000 | H44: i | J44: i | L44: P | N44: P | P44: i
B45: Separator beams | D45: 7 | E45: EA | F45: 1500 | G45: =F45*D45 -> 10500 | H45: i | J45: i | L45: P | N45: P | P45: i
B46: Garage Sliding gates | E46: EA | H46: P | I46: =O46 -> 15840 | J46: i | K46: 15840 | L46: P | M46: =O46 -> 15840 | N46: P | O46: =K46 -> 15840 | P46: P | Q46: =M46 -> 15840
B47: Dumpster gates | C47: 1/AS102 | D47: 2 | E47: EA | F47: 7000 | G47: =F47*D47 -> 14000 | H47: i | J47: i | K47: 16192 | L47: P | M47: =O47 -> 12917 | N47: i | O47: 12917 | P47: i
B48: Galv Steel 20Ga w/ 8"x8" galv tube | H48: i | J48: i | L48: P | N48: i | P48: i
B49: Bollards (6" dia) | C49: 1/AS102, A557 | D49: =7+6 -> 13 | E49: EA | F49: 250 | G49: =F49*D49 -> 3250 | H49: i | J49: i | K49: =4000+3500 -> 7500 | L49: P | N49: i | P49: i
B51: General Conditions (equipment, mobilization, etc) | H51: i | I51: 43513.71 | J51: i | K51: 50998 | L51: i | N51: i | P51: i
B52: Hanger rod canopies - in Div 13 | C52: A644 | H52: x | J52: x | L52: x | N52: x | P52: x
F59: SUBTOTAL | G59: =SUM(G20:G58) -> 458120 | I59: =SUM(I12:I58) -> 334591.49 | K59: =SUM(K12:K58) -> 458856 | M59: =SUM(M12:M58) -> 486855 | O59: =SUM(O12:O58) -> 474707 | Q59: =SUM(Q12:Q58) -> 760591 | S59: =SUM(S11:S58) -> 0 | U59: =SUM(U12:U58) -> 303840 | W59: =SUM(W12:W58) -> 0
F60: BOND RATE | H60: 0 | J60: 0 | L60: 0 | N60: 0 | P60: 0 | R60: 0 | T60: 0 | V60: 0
F61: BOND AMOUNT | I61: =H60*I59 -> 0 | K61: =J60*$K$59 -> 0 | M61: =L60*M59 -> 0 | O61: =N60*O59 -> 0 | Q61: =P60*$Q$59 -> 0 | S61: =R60*$S$59 -> 0 | U61: =T60*$U$59 -> 0 | W61: =V60*W59 -> 0
F63: ADJUSTED TOTAL | I63: =SUM(I59:I61) -> 334591.49 | K63: =SUM(K59:K62) -> 458856 | M63: =SUM(M59:M61) -> 486855 | O63: =SUM(O59:O61) -> 474707 | Q63: =SUM(Q59:Q61) -> 760591 | S63: =SUM(S59:S61) -> 0 | U63: =SUM(U59:U61) -> 303840 | W63: =SUM(W59:W61) -> 0
F64: Cost per SF | I64: =I63/'Area Calculations'!$G$4 -> 0.57821476 | K64: =K63/'Area Calculations'!$G$4 -> 0.79295894 | M64: =M63/'Area Calculations'!$G$4 -> 0.84134462 | O64: =O63/'Area Calculations'!$G$4 -> 0.8203514 | Q64: =Q63/'Area Calculations'!$G$4 -> 1.3143937 | S64: =S63/'Area Calculations'!$G$4 -> 0 | U64: =U63/'Area Calculations'!$G$4 -> 0.52507245 | W64: =W63/'Area Calculations'!$G$4 -> 0
F65: Cost per Unit | I65: =I63/'Area Calculations'!$G$9 -> 3127.0233 | K65: =K63/'Area Calculations'!$G$9 -> 4288.3738 | M65: =M63/'Area Calculations'!$G$9 -> 4550.0467 | O65: =O63/'Area Calculations'!$G$9 -> 4436.514 | Q65: =Q63/'Area Calculations'!$G$9 -> 7108.3271 | S65: =S63/'Area Calculations'!$G$9 -> 0 | U65: =U63/'Area Calculations'!$G$9 -> 2839.6262 | W65: =W63/'Area Calculations'!$G$9 -> 0
A67: QUALIFICATIONS
A71: EXCLUSIONS/OWNER PROVIDED ITEMS:
B72: HSS tubes and structural steel at elevator guide rails shown in S311 are excluded
A75: ALTERNATES:
B76: Alternate No. 4 Exposed anchors in lieu of concealed anchors at wall mounted railings | K76: -36060
B77: Alternate No. 5 Primed and Painted railings in lieu of Electrospray ESP coating
B78: Add for garage corner guards | K78: 20880
A79: PROPOSED VE (Provide Clear Description):
A83: FULLY LOADED LABOR RATES
B84: Laborer
B85: Mechanic
B86: Superintendent
B87: Project Manager
A89: SCHEDULE
B90: Prepared shop drawings/submittals
B91: Mobilization
B92: Total duration to complete scope of work
A94: Winner
A95: Company | B95: =H5 -> Pilar Welding
A96: Contact | B96: =H6 -> Estimating
A97: Phone | B97: =H7 -> 561-524-9246
A98: Email | B98: =H8 -> estimating@pilarwelding.com
A99: Base Bid | B99: =H9 -> 334591.49

Sheet 06 10 Rough Carpentry
G1: Hedrick Plug
F2: X | G2: Excluded
F3: I | G3: Included
B4: BACK TO SUMMARY SHEET | G4: Sub Add/Deduct | H4: Bidder 1 | J4: Bidder 2 | L4: Bidder 3 | N4: Bidder 4 | P4: Bidder 5 | R4: Bidder 6
A5: Project: | B5: ='Area Calculations'!B4 -> ERAU Residential Hall & Garage Building | G5: Company
A6: Trade: | B6: Rough Carpentry | G6: Contact
A7: CSI Code: | B7: 06 10 00 | G7: Phone
A8: Date: | G8: Email
G9: Adjusted Bid | H9: =I55 -> 493891 | J9: =K55 -> 0 | L9: =M55 -> 0 | N9: =O55 -> 0 | P9: =Q55 -> 0 | R9: =S55 -> 0
C10: Plan/ Spec. Package | D10: QTY | E10: U/M | F10: Unit Cost | G10: Subtotal | H10: Yes/No | I10: Price | J10: Yes/No | K10: Price | L10: Yes/No | M10: Price | N10: Yes/No | O10: Price | P10: Yes/No | Q10: Price | R10: Yes/No | S10: Price
B11: GENERAL INCLUSIONS
B12: INCLUDES ALL SALES TAX
B13: ALL HOISTING & RIGGING REQUIRED TO COMPLETE THIS SCOPE
B14: PROVIDE P&P BONDS
B15: FLORIDA STATE CONTRACTORS LIC.
B16: GENERAL LIABILITY AND WORKERS COMP. INSURANCE LIMITS
B17: STATE AND LOCAL TAXES
B18: SPECIFIC TRADE SCOPE OF WORK REQUIREMENTS
B19: BASE BID
B21: roof blocking - pressure treated
B22: 10/A540 - 2x4 (3) & 2x8 (1) | D22: 946 | E22: lf | F22: =15+6.5 -> 21.5 | G22: =D22*F22 -> 20339 | I22: =G22 -> 20339
B23: 1, 4, 7/A540 - 2x6 (2) | D23: =1652+360 -> 2012 | E23: lf | F23: 16 | G23: =D23*F23 -> 32192 | I23: =G23 -> 32192
B24: 1/A520 | D24: 32 | E24: ea | F24: 75 | G24: =D24*F24 -> 2400 | I24: =G24 -> 2400
B26: Project Carptenter | D26: 186 | E26: WKS | F26: =59*40 -> 2360 | G26: =D26*F26 -> 438960 | I26: =G26 -> 438960
B27: Project Carpenter Forman | D27: 0 | E27: WKS | F27: =65*40 -> 2600 | G27: =D27*F27 -> 0 | I27: =G27 -> 0
F30: =21.5-8 -> 13.5
F51: SUBTOTAL | I51: =SUM(I12:I50) -> 493891 | K51: =SUM(K12:K50) -> 0 | M51: =SUM(M11:M50) -> 0 | O51: =SUM(O11:O50) -> 0 | Q51: =SUM(Q12:Q50) -> 0 | S51: =SUM(S12:S50) -> 0
F52: BOND RATE | H52: 0 | J52: 0 | L52: 0 | N52: 0 | P52: 0 | R52: 0
F53: BOND AMOUNT | I53: =H52*$I$51 -> 0 | K53: =J52*$K$51 -> 0 | M53: =L52*$M$51 -> 0 | O53: =N52*$O$51 -> 0 | Q53: =P52*$Q$51 -> 0 | S53: =R52*S51 -> 0
F55: ADJUSTED TOTAL | I55: =SUM(I51:I54) -> 493891 | K55: =SUM(K51:K53) -> 0 | M55: =SUM(M51:M53) -> 0 | O55: =SUM(O51:O53) -> 0 | Q55: =SUM(Q51:Q53) -> 0 | S55: =SUM(S51:S53) -> 0
F56: Cost per SF | I56: =I55/'Area Calculations'!$G$4 -> 0.85350368 | K56: =K55/'Area Calculations'!$G$4 -> 0 | M56: =M55/'Area Calculations'!$G$4 -> 0 | O56: =O55/'Area Calculations'!$G$4 -> 0 | Q56: =Q55/'Area Calculations'!$G$4 -> 0 | S56: =S55/'Area Calculations'!$G$4 -> 0
F57: Cost per Unit | I57: =I55/'Area Calculations'!$G$9 -> 4615.8037 | K57: =K55/'Area Calculations'!$G$9 -> 0 | M57: =M55/'Area Calculations'!$G$9 -> 0 | O57: =O55/'Area Calculations'!$G$9 -> 0 | Q57: =Q55/'Area Calculations'!$G$9 -> 0 | S57: =S55/'Area Calculations'!$G$9 -> 0
A59: QUALIFICATIONS
A63: EXCLUSIONS/OWNER PROVIDED ITEMS:
A67: ALTERNATES:
A71: PROPOSED VE (Provide Clear Description):
A75: FULLY LOADED LABOR RATES
B76: Laborer
B77: Mechanic
B78: Superintendent
B79: Project Manager
A81: SCHEDULE
B82: Prepared shop drawings/submittals
B83: Mobilization
B84: Total duration to complete scope of work
A86: Winner
A87: Company
A88: Contact
A89: Phone
A90: Email
A91: Base Bid | B91: =I55 -> 493891

Sheet 06 17 Wood Trusses
G1: Hedrick Plug
F2: X | G2: Excluded
F3: I | G3: Included
B4: BACK TO SUMMARY SHEET | G4: Sub Add/Deduct | H4: Bidder 1 | J4: Bidder 2 | L4: Bidder 3 | N4: Bidder 4 | P4: Bidder 5 | R4: Bidder 6
A5: Project: | B5: ='Area Calculations'!B4 -> ERAU Residential Hall & Garage Building | G5: Company
A6: Trade: | B6: Wood Trusses | G6: Contact
A7: CSI Code: | B7: 06 17 00 | G7: Phone
A8: Date: | G8: Email
G9: Adjusted Bid | H9: =I55 -> 0 | J9: =K55 -> 0 | L9: =M55 -> 0 | N9: =O55 -> 0 | P9: =Q55 -> 0 | R9: =S55 -> 0
C10: Plan/ Spec. Package | D10: QTY | E10: U/M | F10: Unit Cost | G10: Subtotal | H10: Yes/No | I10: Price | J10: Yes/No | K10: Price | L10: Yes/No | M10: Price | N10: Yes/No | O10: Price | P10: Yes/No | Q10: Price | R10: Yes/No | S10: Price
B11: GENERAL INCLUSIONS
B12: INCLUDES ALL SALES TAX
B13: ALL HOISTING & RIGGING REQUIRED TO COMPLETE THIS SCOPE
B14: PROVIDE P&P BONDS
B15: FLORIDA STATE CONTRACTORS LIC.
B16: GENERAL LIABILITY AND WORKERS COMP. INSURANCE LIMITS
B17: STATE AND LOCAL TAXES
B18: SPECIFIC TRADE SCOPE OF WORK REQUIREMENTS
B19: BASE BID
F51: SUBTOTAL | I51: =SUM(I12:I50) -> 0 | K51: =SUM(K12:K50) -> 0 | M51: =SUM(M11:M50) -> 0 | O51: =SUM(O11:O50) -> 0 | Q51: =SUM(Q12:Q50) -> 0 | S51: =SUM(S12:S50) -> 0
F52: BOND RATE | H52: 0 | J52: 0 | L52: 0 | N52: 0 | P52: 0 | R52: 0
F53: BOND AMOUNT | I53: =H52*$I$51 -> 0 | K53: =J52*$K$51 -> 0 | M53: =L52*$M$51 -> 0 | O53: =N52*$O$51 -> 0 | Q53: =P52*$Q$51 -> 0 | S53: =R52*S51 -> 0
F55: ADJUSTED TOTAL | I55: =SUM(I51:I53) -> 0 | K55: =SUM(K51:K53) -> 0 | M55: =SUM(M51:M53) -> 0 | O55: =SUM(O51:O53) -> 0 | Q55: =SUM(Q51:Q53) -> 0 | S55: =SUM(S51:S53) -> 0
F56: Cost per SF | I56: =I55/'Area Calculations'!$G$4 -> 0 | K56: =K55/'Area Calculations'!$G$4 -> 0 | M56: =M55/'Area Calculations'!$G$4 -> 0 | O56: =O55/'Area Calculations'!$G$4 -> 0 | Q56: =Q55/'Area Calculations'!$G$4 -> 0 | S56: =S55/'Area Calculations'!$G$4 -> 0
F57: Cost per Unit | I57: =I55/'Area Calculations'!$G$9 -> 0 | K57: =K55/'Area Calculations'!$G$9 -> 0 | M57: =M55/'Area Calculations'!$G$9 -> 0 | O57: =O55/'Area Calculations'!$G$9 -> 0 | Q57: =Q55/'Area Calculations'!$G$9 -> 0 | S57: =S55/'Area Calculations'!$G$9 -> 0
A59: QUALIFICATIONS
A63: EXCLUSIONS/OWNER PROVIDED ITEMS:
A67: ALTERNATES:
A71: PROPOSED VE (Provide Clear Description):
A75: FULLY LOADED LABOR RATES
B76: Laborer
B77: Mechanic
B78: Superintendent
B79: Project Manager
A81: SCHEDULE
B82: Prepared shop drawings/submittals
B83: Mobilization
B84: Total duration to complete scope of work
A86: Winner
A87: Company
A88: Contact
A89: Phone
A90: Email
A91: Base Bid

Sheet 06 21 Millwork
G1: Hedrick Plug
F2: X | G2: Excluded
F3: I | G3: Included
B4: BACK TO SUMMARY SHEET | G4: Sub Add/Deduct | H4: Bidder 1 | J4: Bidder 2 | L4: Bidder 3 | N4: Bidder 4 | P4: Bidder 5 | R4: Bidder 6
A5: Project: | B5: ='Area Calculations'!B4 -> ERAU Residential Hall & Garage Building | G5: Company | H5: Astera, Inc. | J5: National Kitchen & Bath, LLC. | L5: Catapult Construction | R5: Central Florida Millwork
A6: Trade: | B6: Millwork | G6: Contact | H6: Hanna Raharjo | J6: Michael K Schwartz | L6: Mary Gwen
A7: CSI Code: | B7: 06 20 00 | G7: Phone | H7: 877-374-6782 | J7: 954-294-1821 | L7: 312-722-1211
A8: Date: | G8: Email | H8: hanna@asterakb.com | J8: Michael@nationalkb.com> | L8: marygwen@mgcontractresources.com
G9: Adjusted Bid | H9: =I60 -> 305860 | J9: =K60 -> 311418.3 | L9: =M60 -> 331487.47 | P9: =Q60 -> 0 | R9: =S60 -> 0
C10: Plan/ Spec. Package | D10: QTY | E10: U/M | F10: Unit Cost | G10: Subtotal | H10: Yes/No | I10: Price | J10: Yes/No | K10: Price | L10: Yes/No | M10: Price | P10: Yes/No | Q10: Price | R10: Yes/No | S10: Price
B11: GENERAL INCLUSIONS
B12: INCLUDES ALL SALES TAX | H12: i | J12: i | L12: i
B13: ALL HOISTING & RIGGING REQUIRED TO COMPLETE THIS SCOPE | H13: i | J13: i | L13: i
B14: PROVIDE P&P BONDS | H14: x | J14: x | L14: x | M14: {2.0%}
B15: FLORIDA STATE CONTRACTORS LIC. | H15: i | J15: i | L15: i
B16: GENERAL LIABILITY AND WORKERS COMP. INSURANCE LIMITS | H16: i | J16: i | L16: i
B17: STATE AND LOCAL TAXES | H17: i | J17: i | L17: i
B18: COMPASS | H18: x | I18: {4.0} | J18: x | L18: x
B19: SPECIFIC TRADE SCOPE OF WORK REQUIREMENTS
B20: BASE BID
B22: Common Areas | H22: P | J22: P | L22: i
B23: Main Lobby 100 | C23: 1-4/A471 | H23: P | J23: P | L23: i
B24: Wood slats | C24: A473 | H24: P | J24: P | L24: i
B25: Ezo Wood 3D countour HD Oak | C25: 3/A473 | H25: P | I25: =$M$25 -> 32160 | J25: P | K25: =M25 -> 32160 | L25: i | M25: 32160
B26: 4" Black steel base | C26: 4/A473 | H26: P | J26: P | L26: i
B27: foam stone-texture cladding | C27: A471 | H27: P | J27: P | L27: i
B28: Reception desk | C28: A712, RFI#134, RFI#157 | H28: P | I28: =$M$28 -> 24640 | J28: P | K28: =M28 -> 24640 | L28: i | M28: 24640
B29: SS1 - Solid surface countertop | H29: P | J29: P | L29: i
B30: Metal brackets | H30: P | J30: P | L30: i
B31: PL-4 cabinets | H31: P | J31: P | L31: i
B32: Knee wall - in Drywall | H32: P | J32: P | L32: i
B33: Lobby 102&119 | C33: 2/A472 | H33: P | J33: P | L33: i
B34: QEM Sheet Moss dark green | H34: P | J34: P | L34: i
B35: Ezo Wood 3D countour HD Oak | H35: P | I35: =$K$35 -> 122860 | J35: P | K35: =M35 -> 122860 | L35: i | M35: =74220+48640 -> 122860
B36: Concrete textured wallpaper WP01&WP02 | H36: P | J36: P | L36: i
B37: 132 Kitchen, 1505 Kitchenette, 164 Kitchen | C37: A430,A431,A432 | H37: i | I37: =19400+300 -> 19700 | J37: i | K37: 31758.3 | L37: i | M37: =28395.04+21783.24 -> 50178.28
B38: Wall cabinets w/ adjustable shelves & closure trim | C38: A710 | H38: i | J38: i | L38: i
B39: Base cabinets | C39: A710 | H39: i | J39: i | L39: i
B40: Countertop | C40: A710 | H40: i | J40: i | L40: i
B41: Removable access panel (ADA) - PCB or Plywood with plam finish | C41: A710 | H41: i | J41: i | L41: i
B43: All public restrooms (135&136,158&159, 140&141, 149&150) | C43: 1/A430 | H43: i | I43: =6500 -> 6500 | J43: i | L43: i
B44: Vanity countertop & Panel - solid surface | C44: 12/A710 | H44: i | J44: i | L44: i
B45: Removable access panel (ADA) - PCB or Plywood with plam finish | C45: 12/A710 | H45: i | J45: i | L45: i
B47: Material specs: | H47: i | J47: i | L47: i
B48: 3/4" plywood w/ p.lam finish shelves and box | H48: i | J48: i | L48: i
B49: 3/4" moisture and water resistant particleboard construction is acceptable as per RFI#6 | H49: i | J49: i | L49: i
B50: Accessible pulls | H50: i | J50: i | L50: i
B51: All exposed surfaces to be p.lam. | H51: i | J51: i | L51: i
B52: Solid surface countertops as per Addendum#3 RFIs | H52: i | J52: i | L52: i
B54: Installation | D54: 1 | E54: LS | F54: 100000 | G54: =F54*D54 -> 100000 | H54: P | I54: =$G$54 -> 100000 | J54: P | K54: =$G$54 -> 100000 | L54: P | M54: =$G$54 -> 100000
F56: SUBTOTAL | I56: =SUM(I12:I55) -> 305860 | K56: =SUM(K12:K55) -> 311418.3 | M56: =SUM(M11:M55) -> 329838.28 | O56: =SUM(O11:O55) -> 0 | Q56: =SUM(Q12:Q55) -> 0 | S56: =SUM(S12:S55) -> 0
F57: BOND RATE | H57: 0 | J57: 0 | L57: 0.005 | N57: 0 | P57: 0 | R57: 0
F58: BOND AMOUNT | I58: =H57*$I$56 -> 0 | K58: =J57*$K$56 -> 0 | M58: =L57*$M$56 -> 1649.1914 | O58: =N57*$O$56 -> 0 | Q58: =P57*$Q$56 -> 0 | S58: =R57*S56 -> 0
F60: ADJUSTED TOTAL | I60: =SUM(I56:I59) -> 305860 | K60: =SUM(K56:K58) -> 311418.3 | M60: =SUM(M56:M58) -> 331487.47 | O60: =SUM(O56:O58) -> 0 | Q60: =SUM(Q56:Q58) -> 0 | S60: =SUM(S56:S58) -> 0
F61: Cost per SF | I61: =I60/'Area Calculations'!$G$4 -> 0.52856326 | K61: =K60/'Area Calculations'!$G$4 -> 0.53816868 | M61: =M60/'Area Calculations'!$G$4 -> 0.57285064 | O61: =O60/'Area Calculations'!$G$4 -> 0 | Q61: =Q60/'Area Calculations'!$G$4 -> 0 | S61: =S60/'Area Calculations'!$G$4 -> 0
F62: Cost per Unit | I62: =I60/'Area Calculations'!$G$9 -> 2858.5047 | K62: =K60/'Area Calculations'!$G$9 -> 2910.4514 | M62: =M60/'Area Calculations'!$G$9 -> 3098.0138 | O62: =O60/'Area Calculations'!$G$9 -> 0 | Q62: =Q60/'Area Calculations'!$G$9 -> 0 | S62: =S60/'Area Calculations'!$G$9 -> 0
A64: QUALIFICATIONS
A68: EXCLUSIONS/OWNER PROVIDED ITEMS:
A72: ALTERNATES:
A76: PROPOSED VE (Provide Clear Description):
A80: FULLY LOADED LABOR RATES
B81: Laborer
B82: Mechanic
B83: Superintendent
B84: Project Manager
A86: SCHEDULE
B87: Prepared shop drawings/submittals
B88: Mobilization
B89: Total duration to complete scope of work
A91: Winner
A92: Company | B92: =L5 -> Catapult Construction
A93: Contact | B93: =L6 -> Mary Gwen
A94: Phone | B94: =L7 -> 312-722-1211
A95: Email | B95: =L8 -> marygwen@mgcontractresources.com
A96: Base Bid | B96: =L9 -> 331487.47

Sheet 06 40 Arch Woodwork
G1: Hedrick Plug
F2: X | G2: Excluded
F3: I | G3: Included
B4: BACK TO SUMMARY SHEET | G4: Sub Add/Deduct | H4: Bidder 1 | J4: Bidder 2 | L4: Bidder 3 | N4: Bidder4 | P4: Bidder5 | R4: Bidder6
A5: Project: | B5: ='Area Calculations'!B4 -> ERAU Residential Hall & Garage Building | G5: Company
A6: Trade: | B6: Architectural Woodwork | G6: Contact
A7: CSI Code: | B7: 06 40 00 | G7: Phone
A8: Date: | G8: Email
G9: Adjusted Bid | H9: =I55 -> 0 | J9: =K55 -> 0 | L9: =M55 -> 0 | N9: =O55 -> 0 | P9: =Q55 -> 0 | R9: =S55 -> 0
C10: Plan/ Spec. Package | D10: QTY | E10: U/M | F10: Unit Cost | G10: Subtotal | H10: Yes/No | I10: Price | J10: Yes/No | K10: Price | L10: Yes/No | M10: Price | N10: Yes/No | O10: Price | P10: Yes/No | Q10: Price | R10: Yes/No | S10: Price
B11: GENERAL INCLUSIONS
B12: INCLUDES ALL SALES TAX
B13: ALL HOISTING & RIGGING REQUIRED TO COMPLETE THIS SCOPE
B14: PROVIDE P&P BONDS
B15: FLORIDA STATE CONTRACTORS LIC.
B16: GENERAL LIABILITY AND WORKERS COMP. INSURANCE LIMITS
B17: STATE AND LOCAL TAXES
B18: SPECIFIC TRADE SCOPE OF WORK REQUIREMENTS
B19: BASE BID
F51: SUBTOTAL | I51: =SUM(I12:I50) -> 0 | K51: =SUM(K12:K50) -> 0 | M51: =SUM(M12:M50) -> 0 | O51: =SUM(O12:O50) -> 0 | Q51: =SUM(Q12:Q50) -> 0 | S51: =SUM(S13:S50) -> 0
F52: BOND RATE | H52: 0 | J52: 0 | L52: 0 | N52: 0 | P52: 0 | R52: 0
F53: BOND AMOUNT | I53: =H52*I51 -> 0 | K53: =J52*K51 -> 0 | M53: =L52*M51 -> 0 | O53: =N52*O51 -> 0 | Q53: =P52*Q51 -> 0 | S53: =R52*S51 -> 0
F55: ADJUSTED TOTAL | I55: =SUM(I51:I54) -> 0 | K55: =SUM(K51:K54) -> 0 | M55: =SUM(M51:M54) -> 0 | O55: =SUM(O51:O54) -> 0 | Q55: =SUM(Q51:Q54) -> 0 | S55: =SUM(S51:S54) -> 0
F56: Cost per SF | I56: =I55/'Area Calculations'!$G$4 -> 0 | K56: =K55/'Area Calculations'!$G$4 -> 0 | M56: =M55/'Area Calculations'!$G$4 -> 0 | O56: =O55/'Area Calculations'!$G$4 -> 0 | Q56: =Q55/'Area Calculations'!$G$4 -> 0 | S56: =S55/'Area Calculations'!$G$4 -> 0
F57: Cost per Unit | I57: =I55/'Area Calculations'!$G$9 -> 0 | K57: =K55/'Area Calculations'!$G$9 -> 0 | M57: =M55/'Area Calculations'!$G$9 -> 0 | O57: =O55/'Area Calculations'!$G$9 -> 0 | Q57: =Q55/'Area Calculations'!$G$9 -> 0 | S57: =S55/'Area Calculations'!$G$9 -> 0
A59: QUALIFICATIONS
A63: EXCLUSIONS/OWNER PROVIDED ITEMS:
A67: ALTERNATES:
A71: PROPOSED VE (Provide Clear Description):
A75: FULLY LOADED LABOR RATES
B76: Laborer
B77: Mechanic
B78: Superintendent
B79: Project Manager
A81: SCHEDULE
B82: Prepared shop drawings/submittals
B83: Mobilization
B84: Total duration to complete scope of work
A86: Winner
A87: Company
A88: Contact
A89: Phone
A90: Email
A91: Base Bid

Sheet 07 10 Waterproofing
G1: Hedrick Plug
F2: X | G2: Excluded
F3: I | G3: Included
B4: BACK TO SUMMARY SHEET | G4: Sub Add/Deduct | H4: Bidder 3 | J4: Bidder 4 | L4: Bidder 1 | N4: Bidder 2 | P4: Bidder5 | R4: Bidder6
A5: Project: | B5: ='Area Calculations'!B4 -> ERAU Residential Hall & Garage Building | G5: Company | J5: GCC | L5: Daniel Insulation | N5: Tri Tech
A6: Trade: | B6: Waterproofing | G6: Contact
A7: CSI Code: | B7: 07 10 00 | G7: Phone
A8: Date: | G8: Email
G9: Adjusted Bid | H9: =I60 -> 710786.36 | J9: =K60 -> 673130.11 | L9: =M60 -> 1047798.7 | N9: =O60 -> 1298128.7 | P9: =Q60 -> 0 | R9: =S60 -> 0
C10: Plan/ Spec. Package | D10: QTY | E10: U/M | F10: Unit Cost | G10: Subtotal | H10: Yes/No | I10: Price | J10: Yes/No | K10: Price | L10: Yes/No | M10: Price | N10: Yes/No | O10: Price | P10: Yes/No | Q10: Price | R10: Yes/No | S10: Price
B11: GENERAL INCLUSIONS
B12: INCLUDES ALL SALES TAX
B13: ALL HOISTING & RIGGING REQUIRED TO COMPLETE THIS SCOPE
B14: PROVIDE P&P BONDS
B15: FLORIDA STATE CONTRACTORS LIC.
B16: GENERAL LIABILITY AND WORKERS COMP. INSURANCE LIMITS
B17: STATE AND LOCAL TAXES
B18: COMPASS
B19: SPECIFIC TRADE SCOPE OF WORK REQUIREMENTS
B20: BASE BID
B22: FLUID-APPLIED MEMBRANE AIR BARRIERS
B23: GCP Applied Technologies; Perma-A-Barrier VPL | K23: =SUM(G24:G30) -> 195921.38 | M23: 153557 | O23: 652200
B24: Formed metal wall panels | D24: ='07 42 Metal Panel'!D23 -> 20514 | E24: sf | F24: 4.85 | G24: =D24*F24 -> 99492.9 | I24: =$G24 -> 99492.9 | J24: I | L24: I | N24: I
B25: Composite metal panels | D25: ='07 42 Metal Panel'!D44 -> 8382 | E25: sf | F25: =$F$24 -> 4.85 | G25: =D25*F25 -> 40652.7 | I25: =$G25 -> 40652.7 | J25: I | L25: I | N25: I
B27: Exterior openings - continue fluid applied membrane
B28: Windows | D28: =SUM('08 50 Storefront & Windows'!AB64)*0.67 -> 5813.724 | E28: sf | F28: =$F$24 -> 4.85 | G28: =D28*F28 -> 28196.561 | I28: =$G28 -> 28196.561 | J28: I | L28: I | N28: I
B29: Curtainwall | D29: =SUM('08 50 Storefront & Windows'!AB44:AB47)*0.67 -> 559.9056 | E29: sf | F29: =$F$24 -> 4.85 | G29: =D29*F29 -> 2715.5422 | I29: =$G29 -> 2715.5422 | J29: I | L29: I | N29: I
B30: Storefront | D30: =SUM('08 50 Storefront & Windows'!AB49:AB63)*0.67 -> 5126.5318 | E30: sf | F30: =$F$24 -> 4.85 | G30: =D30*F30 -> 24863.679 | I30: =$G30 -> 24863.679 | J30: I | L30: I | N30: I
B32: Caulking
B33: Secondary at
B34: Windows | D34: =SUM('08 50 Storefront & Windows'!AB64) -> 8677.2 | E34: lf | F34: 6.5 | G34: =D34*F34 -> 56401.8 | I34: =$G34 -> 56401.8 | K34: =$G34 -> 56401.8 | M34: =$G34 -> 56401.8 | O34: =$G34 -> 56401.8
B35: Curtainwall | D35: =SUM('08 50 Storefront & Windows'!AB44:AB47) -> 835.68 | E35: lf | F35: 6.5 | G35: =D35*F35 -> 5431.92 | I35: =$G35 -> 5431.92 | K35: =$G35 -> 5431.92 | M35: =$G35 -> 5431.92 | O35: =$G35 -> 5431.92
B36: Storefront | D36: =SUM('08 50 Storefront & Windows'!AB49:AB63) -> 7651.54 | E36: lf | F36: 6.5 | G36: =D36*F36 -> 49735.01 | I36: =$G36 -> 49735.01 | K36: =$G36 -> 49735.01 | M36: =$G36 -> 49735.01 | O36: =$G36 -> 49735.01
B37: Expansion material & caulk - 3&4/A540 | D37: 130 | E37: lf | F37: 15 | G37: =D37*F37 -> 1950 | I37: =$G37 -> 1950 | K37: =$G37 -> 1950 | M37: =$G37 -> 1950 | O37: =$G37 -> 1950
B38: Building to sidewalk | E38: lf | F38: 8 | G38: =D38*F38 -> 0 | I38: =$G38 -> 0 | K38: =$G38 -> 0 | M38: =$G38 -> 0 | O38: =$G38 -> 0
B40: Elevator pits waterproofing | D40: =238+552 -> 790 | E40: sf | F40: 10 | G40: =D40*F40 -> 7900 | I40: =$G40 -> 7900 | K40: =$G40 -> 7900 | M40: 41829 | O40: 24350
B41: Volclay
B42: Carlise Miraclay
B44: Traffic Coating - garage upper level only? - can see where called for anywhere | D44: 52770 | E44: sf | F44: 5 | G44: =D44*F44 -> 263850 | I44: =$G44 -> 263850 | K44: 229730 | M44: 612834 | O44: 382000
B45: 1. Carlisle Coatings & Waterproofing, Inc.; CCW-5013.
B46: 2. Pacific Polymers International, Inc.; Elasto-Deck 5000.
B47: 3. Tamms Industries, Inc.; Tammsdeck System.
B49: Shower enclosure | D49: 382 | E49: ea
B50: waterproofing | D50: 382 | E50: ea | F50: =20*10 -> 200 | G50: =D50*F50 -> 76400 | I50: =$G50 -> 76400 | K50: =$G50 -> 76400 | M50: =$G50 -> 76400 | O50: =$G50 -> 76400
B51: mud set | D51: 382 | E51: ea | F51: 130 | G51: =D51*F51 -> 49660 | I51: =$G51 -> 49660 | K51: =$G51 -> 49660 | M51: =$G51 -> 49660 | O51: =$G51 -> 49660
F56: SUBTOTAL | G56: =SUM(G20:G55) -> 707250.11 | I56: =SUM(I20:I55) -> 707250.11 | K56: =SUM(K20:K55) -> 673130.11 | M56: =SUM(M20:M55) -> 1047798.7 | O56: =SUM(O20:O55) -> 1298128.7 | Q56: =SUM(Q20:Q55) -> 0 | S56: =SUM(S20:S55) -> 0
F57: BOND RATE | H57: 0.005 | J57: 0 | L57: 0 | N57: 0 | P57: 0 | R57: 0
F58: BOND AMOUNT | I58: =I56*H57 -> 3536.2506 | K58: =K56*J57 -> 0 | M58: =M56*L57 -> 0 | O58: =O56*N57 -> 0 | Q58: =Q56*P57 -> 0 | S58: =S56*R57 -> 0
F60: ADJUSTED TOTAL | I60: =SUM(I56:I58) -> 710786.36 | K60: =SUM(K56:K58) -> 673130.11 | M60: =SUM(M56:M59) -> 1047798.7 | O60: =SUM(O56:O58) -> 1298128.7 | Q60: =SUM(Q56:Q58) -> 0 | S60: =SUM(S56:S58) -> 0
F61: Cost per SF | I61: =I60/'Area Calculations'!$G$4 -> 1.2283252 | K61: =K60/'Area Calculations'!$G$4 -> 1.1632507 | M61: =M60/'Area Calculations'!$G$4 -> 1.8107236 | O61: =O60/'Area Calculations'!$G$4 -> 2.2433242 | Q61: =Q60/'Area Calculations'!$G$4 -> 0 | S61: =S60/'Area Calculations'!$G$4 -> 0
F62: Cost per Unit | I62: =I60/'Area Calculations'!$G$9 -> 6642.8632 | K62: =K60/'Area Calculations'!$G$9 -> 6290.9356 | M62: =M60/'Area Calculations'!$G$9 -> 9792.5115 | O62: =O60/'Area Calculations'!$G$9 -> 12132.044 | Q62: =Q60/'Area Calculations'!$G$9 -> 0 | S62: =S60/'Area Calculations'!$G$9 -> 0
A64: QUALIFICATIONS
B65: We have included waterproofing at the interior side of elevator pits only
B66: Traffic coating is include d at the top level of the garage only
A68: EXCLUSIONS/OWNER PROVIDED ITEMS:
A72: ALTERNATES:
A76: PROPOSED VE (Provide Clear Description):
A80: FULLY LOADED LABOR RATES
B81: Laborer
B82: Mechanic
B83: Superintendent
B84: Project Manager
A86: SCHEDULE
B87: Prepared shop drawings/submittals
B88: Mobilization
B89: Total duration to complete scope of work
A91: Winner
A92: Company
A93: Contact
A94: Phone
A95: Email
A96: Base Bid | B96: =I56 -> 707250.11

Sheet 07 21 Insulation
G1: Hedrick Plug
F2: X | G2: Excluded
F3: I | G3: Included
B4: BACK TO SUMMARY SHEET | G4: Sub Add/Deduct | H4: Bidder 1 | J4: Bidder 2 | L4: Bidder 3 | N4: Bidder 4 | P4: Bidder5 | R4: Bidder6
A5: Project: | B5: ='Area Calculations'!B4 -> ERAU Residential Hall & Garage Building | G5: Company
A6: Trade: | B6: Water Proofing | G6: Contact
A7: CSI Code: | B7: 07 17 00 | G7: Phone
A8: Date: | G8: Email
G9: Adjusted Bid | H9: =I55 -> 0 | J9: =K55 -> 0 | L9: =M55 -> 0 | N9: =O55 -> 0 | P9: =Q55 -> 0 | R9: =S55 -> 0
C10: Plan/ Spec. Package | D10: QTY | E10: U/M | F10: Unit Cost | G10: Subtotal | H10: Yes/No | I10: Price | J10: Yes/No | K10: Price | L10: Yes/No | M10: Price | N10: Yes/No | O10: Price | P10: Yes/No | Q10: Price | R10: Yes/No | S10: Price
B11: GENERAL INCLUSIONS
B12: INCLUDES ALL SALES TAX
B13: ALL HOISTING & RIGGING REQUIRED TO COMPLETE THIS SCOPE
B14: PROVIDE P&P BONDS
B15: FLORIDA STATE CONTRACTORS LIC.
B16: GENERAL LIABILITY AND WORKERS COMP. INSURANCE LIMITS
B17: STATE AND LOCAL TAXES
B18: SPECIFIC TRADE SCOPE OF WORK REQUIREMENTS
B19: BASE BID
F51: SUBTOTAL | I51: =SUM(I12:I50) -> 0 | K51: =SUM(K12:K50) -> 0 | M51: =SUM(M12:M50) -> 0 | O51: =SUM(O12:O50) -> 0 | Q51: =SUM(Q12:Q50) -> 0 | S51: =SUM(S12:S50) -> 0
F52: BOND RATE | H52: 0 | J52: 0 | L52: 0 | N52: 0 | P52: 0 | R52: 0
F53: BOND AMOUNT | I53: =I51*H52 -> 0 | K53: =K51*J52 -> 0 | M53: =M51*L52 -> 0 | O53: =O51*N52 -> 0 | Q53: =Q51*P52 -> 0 | S53: =S51*R52 -> 0
F55: ADJUSTED TOTAL | I55: =SUM(I51:I54) -> 0 | K55: =SUM(K51:K53) -> 0 | M55: =SUM(M51:M53) -> 0 | O55: =SUM(O51:O53) -> 0 | Q55: =SUM(Q51:Q53) -> 0 | S55: =SUM(S51:S53) -> 0
F56: Cost per SF | I56: =I55/'Area Calculations'!$G$4 -> 0 | K56: =K55/'Area Calculations'!$G$4 -> 0 | M56: =M55/'Area Calculations'!$G$4 -> 0 | O56: =O55/'Area Calculations'!$G$4 -> 0 | Q56: =Q55/'Area Calculations'!$G$4 -> 0 | S56: =S55/'Area Calculations'!$G$4 -> 0
F57: Cost per Unit | I57: =I55/'Area Calculations'!$G$9 -> 0 | K57: =K55/'Area Calculations'!$G$9 -> 0 | M57: =M55/'Area Calculations'!$G$9 -> 0 | O57: =O55/'Area Calculations'!$G$9 -> 0 | Q57: =Q55/'Area Calculations'!$G$9 -> 0 | S57: =S55/'Area Calculations'!$G$9 -> 0
A59: QUALIFICATIONS
A63: EXCLUSIONS/OWNER PROVIDED ITEMS:
A67: ALTERNATES:
A71: PROPOSED VE (Provide Clear Description):
A75: FULLY LOADED LABOR RATES
B76: Laborer
B77: Mechanic
B78: Superintendent
B79: Project Manager
A81: SCHEDULE
B82: Prepared shop drawings/submittals
B83: Mobilization
B84: Total duration to complete scope of work
A86: Winner
A87: Company
A88: Contact
A89: Phone
A90: Email
A91: Base Bid

Sheet 07 42 Metal Panel
G1: Hedrick Plug
F2: X | G2: Excluded
F3: I | G3: Included
B4: BACK TO SUMMARY SHEET | G4: Sub Add/Deduct | H4: Bidder 1 | J4: Bidder 2 | L4: Bidder 3 | N4: Bidder 4 | P4: Bidder 2 | R4: Bidder6
A5: Project: | B5: ='Area Calculations'!B4 -> ERAU Residential Hall & Garage Building | G5: Company | H5: Cladding & Component | J5: Cynergy | L5: Quality Metals Inc | N5: Kistler | P5: Paradise Architectural | R5: Rapid Accurate Design
A6: Trade: | B6: Metal Panel | G6: Contact | H6: Randy Sargent | J6: Richard Filiault | L6: Blake Bassett | N6: Jennifer Young | P6: Ralph Gainer | R6: Zach Thompson
A7: CSI Code: | B7: 07 42 00 | G7: Phone | H7: (770) 887-2777 | J7: (704) 999-3825 | L7: (407) 321-3181 | N7: (470) 831-4229 | P7: (305) 597-5714 | R7: 561-635-5907
A8: Date: | G8: Email | H8: jcumbess@ccsimagegroup.com | J8: rfiliault@cynergysystemsinc.com | L8: blake@qualitymetals.net | N8: Jennifer@KistlerUS.com | P8: rgainer@PanelsAndSteel.com | R8: zt@radaf.com
G9: Adjusted Bid | H9: =I55 -> 1293203.9 | J9: =K55 -> 1219213.8 | L9: =M55 -> 1359108 | N9: =O55 -> 1430850 | P9: =Q55 -> 2063012.8 | R9: =S55 -> 0
C10: Plan/ Spec. Package | D10: QTY | E10: U/M | F10: Unit Cost | G10: Subtotal | H10: Yes/No | I10: Price | J10: Yes/No | K10: Price | L10: Yes/No | M10: Price | N10: Yes/No | O10: Price | P10: Yes/No | Q10: Price | R10: Yes/No | S10: Price
B11: GENERAL INCLUSIONS
B12: INCLUDES ALL SALES TAX | H12: i
B13: ALL HOISTING & RIGGING REQUIRED TO COMPLETE THIS SCOPE | H13: i
B14: PROVIDE P&P BONDS | H14: x | I14: {2.0%}
B15: FLORIDA STATE CONTRACTORS LIC. | H15: i
B16: GENERAL LIABILITY AND WORKERS COMP. INSURANCE LIMITS | H16: i
B17: STATE AND LOCAL TAXES | H17: i
B18: COMPASS | H18: x | I18: {1.4}
B19: SPECIFIC TRADE SCOPE OF WORK REQUIREMENTS
B20: BASE BID | I20: 1286770 | M20: 1359108
B22: Prefinihsed Metal Panel System | C22: A600, 601
B23: Section 074213.13 - Formed Metal Wall Panels | D23: 20514 | E23: sf | H23: I | K23: 555218 | L23: I | N23: I | O23: =708950+95650 -> 804600 | P23: I | Q23: 1373730
B24: Manufacturers: Subject to compliance with requirements, provide basis of design product but products by one of the following may be submitted for substitution:
B25: AEP Span; a BlueScope Steel company.
B26: Alcoa Inc.
B27: Architectural Building Components.
B28: Architectural Metal Systems; a Nucor company.
B29: ATAS International, Inc.
B30: Berridge Manufacturing Company.
B31: CENTRIA Architectural Systems. | P31: I
B32: Fabral.
B33: MBCI; a division of NCI Building Systems, L.P.
B34: Metal-Fab Manufacturing, LLC
B35: Morin; a Kingspan Group company. | H35: I | J35: I | L35: I | N35: I
B36: Petersen Alum Corp. (Basis of Design) PAC-CLAD HWP, Berridge | L36: I
B37: Finish - Three-Coat Fluropolymer | L37: I
B38: Section 074213.23 Metal Composite Material Wall Panels | H38: I | N38: I
B39: Products: Subject to compliance with requirements.
B40: 3A Composites USA, Inc. Alucobond (FR) (Basis of Design) | H40: I | L40: I | N40: I | P40: I
B41: Alcoa Inc; Reynonbond (FR)
B42: Mitsubishi Plastics Composites America, Inc. (FR)
B43: Finish - Two-Coat Fluropolymer | L43: I
B44: Vertical at exterior elevations | D44: =6031+1983+368 -> 8382 | E44: sf | K44: 503088 | L44: I | O44: =524900+101350 -> 626250 | P44: I | Q44: 528375
B45: Canopy panels | H45: I | L45: I | N45: I
B46: A641 - 4 locations | D46: =(188+110)*4 -> 1192 | E46: sf | F46: =528375/7500 -> 70.45 | G46: =D46*F46 -> 83976.4 | K46: =$G46 -> 83976.4 | Q46: =$G46 -> 83976.4
B47: A642 - 1 locations | D47: =574+164 -> 738 | E47: sf | F47: =528375/7500 -> 70.45 | G47: =D47*F47 -> 51992.1 | K47: =$G47 -> 51992.1 | Q47: =$G47 -> 51992.1
B48: A643 - 2 locations | D48: =(133+44)*2 -> 354 | E48: sf | F48: =528375/7500 -> 70.45 | G48: =D48*F48 -> 24939.3 | K48: =$G48 -> 24939.3 | Q48: =$G48 -> 24939.3
F51: SUBTOTAL | I51: =SUM(I12:I50) -> 1286770 | K51: =SUM(K12:K50) -> 1219213.8 | M51: =SUM(M12:M50) -> 1359108 | O51: =SUM(O12:O50) -> 1430850 | Q51: =SUM(Q12:Q50) -> 2063012.8 | S51: =SUM(S12:S50) -> 0
F52: BOND RATE | H52: 0.005 | J52: 0 | L52: 0 | N52: 0 | P52: 0 | R52: 0
F53: BOND AMOUNT | I53: =I51*H52 -> 6433.85 | K53: =K51*J52 -> 0 | M53: =M51*L52 -> 0 | O53: =O51*N52 -> 0 | Q53: =Q51*P52 -> 0 | S53: =S51*R52 -> 0
F55: ADJUSTED TOTAL | I55: =SUM(I51:I54) -> 1293203.9 | K55: =SUM(K51:K54) -> 1219213.8 | M55: =SUM(M51:M54) -> 1359108 | O55: =SUM(O51:O54) -> 1430850 | Q55: =SUM(Q51:Q54) -> 2063012.8 | S55: =SUM(S51:S54) -> 0
F56: Cost per SF | I56: =I55/'Area Calculations'!$G$4 -> 2.2348134 | K56: =K55/'Area Calculations'!$G$4 -> 2.1069496 | M56: =M55/'Area Calculations'!$G$4 -> 2.3487038 | O56: =O55/'Area Calculations'!$G$4 -> 2.4726827 | Q56: =Q55/'Area Calculations'!$G$4 -> 3.5651369 | S56: =S55/'Area Calculations'!$G$4 -> 0
F57: Cost per Unit | I57: =I55/'Area Calculations'!$G$9 -> 12086.017 | K57: =K55/'Area Calculations'!$G$9 -> 11394.521 | M57: =M55/'Area Calculations'!$G$9 -> 12701.944 | O57: =O55/'Area Calculations'!$G$9 -> 13372.43 | Q57: =Q55/'Area Calculations'!$G$9 -> 19280.493 | S57: =S55/'Area Calculations'!$G$9 -> 0
A59: QUALIFICATIONS
A63: EXCLUSIONS/OWNER PROVIDED ITEMS:
A67: ALTERNATES:
A71: PROPOSED VE (Provide Clear Description):
A75: FULLY LOADED LABOR RATES
B76: Laborer
B77: Mechanic
B78: Superintendent
B79: Project Manager
A81: SCHEDULE
B82: Prepared shop drawings/submittals
B83: Mobilization
B84: Total duration to complete scope of work
A86: Winner
A87: Company | B87: =H5 -> Cladding & Component
A88: Contact | B88: =H6 -> Randy Sargent
A89: Phone | B89: =H7 -> (770) 887-2777
A90: Email | B90: =H8 -> jcumbess@ccsimagegroup.com
A91: Base Bid | B91: =I55 -> 1293203.9

Sheet 07 46 Siding
G1: Hedrick Plug
F2: X | G2: Excluded
F3: I | G3: Included
B4: BACK TO SUMMARY SHEET | G4: Sub Add/Deduct | H4: Bidder 1 | J4: Bidder 2 | L4: Bidder 3 | N4: Bidder 4 | P4: Bidder5 | R4: Bidder6
A5: Project: | B5: ='Area Calculations'!B4 -> ERAU Residential Hall & Garage Building | G5: Company
A6: Trade: | B6: Siding | G6: Contact
A7: CSI Code: | B7: 07 46 00 | G7: Phone
A8: Date: | G8: Email
G9: Adjusted Bid | H9: =I55 -> 0 | J9: =K55 -> 0 | L9: =M55 -> 0 | N9: =O55 -> 0 | P9: =Q55 -> 0 | R9: =S55 -> 0
C10: Plan/ Spec. Package | D10: QTY | E10: U/M | F10: Unit Cost | G10: Subtotal | H10: Yes/No | I10: Price | J10: Yes/No | K10: Price | L10: Yes/No | M10: Price | N10: Yes/No | O10: Price | P10: Yes/No | Q10: Price | R10: Yes/No | S10: Price
B11: GENERAL INCLUSIONS
B12: INCLUDES ALL SALES TAX
B13: ALL HOISTING & RIGGING REQUIRED TO COMPLETE THIS SCOPE
B14: PROVIDE P&P BONDS
B15: FLORIDA STATE CONTRACTORS LIC.
B16: GENERAL LIABILITY AND WORKERS COMP. INSURANCE LIMITS
B17: STATE AND LOCAL TAXES
B18: SPECIFIC TRADE SCOPE OF WORK REQUIREMENTS
B19: BASE BID
F51: SUBTOTAL | I51: =SUM(I12:I50) -> 0 | K51: =SUM(K12:K50) -> 0 | M51: =SUM(M12:M50) -> 0 | O51: =SUM(O12:O50) -> 0 | Q51: =SUM(Q12:Q50) -> 0 | S51: =SUM(S12:S50) -> 0
F52: BOND RATE | H52: 0 | J52: 0 | L52: 0 | N52: 0 | P52: 0 | R52: 0
F53: BOND AMOUNT | I53: =I51*H52 -> 0 | K53: =K51*J52 -> 0 | M53: =M51*L52 -> 0 | O53: =O51*N52 -> 0 | Q53: =Q51*P52 -> 0 | S53: =S51*R52 -> 0
F55: ADJUSTED TOTAL | I55: =SUM(I51:I54) -> 0 | K55: =SUM(K51:K54) -> 0 | M55: =SUM(M51:M54) -> 0 | O55: =SUM(O51:O54) -> 0 | Q55: =SUM(Q51:Q54) -> 0 | S55: =SUM(S51:S54) -> 0
F56: Cost per SF | I56: =I55/'Area Calculations'!$G$4 -> 0 | K56: =K55/'Area Calculations'!$G$4 -> 0 | M56: =M55/'Area Calculations'!$G$4 -> 0 | O56: =O55/'Area Calculations'!$G$4 -> 0 | Q56: =Q55/'Area Calculations'!$G$4 -> 0 | S56: =S55/'Area Calculations'!$G$4 -> 0
F57: Cost per Unit | I57: =I55/'Area Calculations'!$G$9 -> 0 | K57: =K55/'Area Calculations'!$G$9 -> 0 | M57: =M55/'Area Calculations'!$G$9 -> 0 | O57: =O55/'Area Calculations'!$G$9 -> 0 | Q57: =Q55/'Area Calculations'!$G$9 -> 0 | S57: =S55/'Area Calculations'!$G$9 -> 0
A59: QUALIFICATIONS
A63: EXCLUSIONS/OWNER PROVIDED ITEMS:
A67: ALTERNATES:
A71: PROPOSED VE (Provide Clear Description):
A75: FULLY LOADED LABOR RATES
B76: Laborer
B77: Mechanic
B78: Superintendent
B79: Project Manager
A81: SCHEDULE
B82: Prepared shop drawings/submittals
B83: Mobilization
B84: Total duration to complete scope of work
A86: Winner
A87: Company
A88: Contact
A89: Phone
A90: Email
A91: Base Bid

Sheet 07 50 Roofing
G1: Hedrick Plug
F2: X | G2: Excluded
F3: I | G3: Included
B4: BACK TO SUMMARY SHEET | G4: Sub Add/Deduct | H4: Bidder 2 | J4: Bidder 1 | L4: Bidder 3 | N4: Bidder 4 | P4: Bidder5 | R4: Bidder6
A5: Project: | B5: ='Area Calculations'!B4 -> ERAU Residential Hall & Garage Building | G5: Company | H5: Jenkins Roofing | J5: P&A Roofing
A6: Trade: | B6: Roofing | G6: Contact | H6: Vince Niesen | J6: Shaun Tuthill
A7: CSI Code: | B7: 07 50 00 | G7: Phone | H7: ( 904 ) 304-7400 | J7: (407) 650-9541
A8: Date: | G8: Email | H8: Vince@JenkinsRoofingInc.com | J8: stuthill@pa-roofing.com
G9: Adjusted Bid | H9: =I58 -> 1306500 | J9: =K58 -> 1441500 | L9: =M58 -> 0 | N9: =O58 -> 0 | P9: =Q58 -> 0 | R9: =S58 -> 0
C10: Plan/ Spec. Package | D10: QTY | E10: U/M | F10: Unit Cost | G10: Subtotal | H10: Yes/No | I10: Price | J10: Yes/No | K10: Price | L10: Yes/No | M10: Price | N10: Yes/No | O10: Price | P10: Yes/No | Q10: Price | R10: Yes/No | S10: Price
B11: GENERAL INCLUSIONS
B12: INCLUDES ALL SALES TAX | H12: i
B13: ALL HOISTING & RIGGING REQUIRED TO COMPLETE THIS SCOPE | H13: i
B14: PROVIDE P&P BONDS | H14: x | I14: {2.0%}
B15: FLORIDA STATE CONTRACTORS LIC. | H15: i
B16: GENERAL LIABILITY AND WORKERS COMP. INSURANCE LIMITS | H16: i
B17: STATE AND LOCAL TAXES | H17: i
B18: COMPASS | H18: x
B19: SPECIFIC TRADE SCOPE OF WORK REQUIREMENTS
B20: BASE BID | I20: =1100000+100000 -> 1200000 | K20: 1353500
B22: Membrane Roofing
B23: Section 075218 - Styrene-Butadiene-Styrene (SBS) Modified Bituminous Membrane Roofing/Over Insulated Lightweight Concrete
B24: Warranty Period: 2 years from date of Substantial Completion
B25: Siplast 20 Year Roof System Guarantee
B26: Manufacturers: Siplast, Inc. (Basis of Design) No substitution accepted
B27: Walktread: Paratread Roof Protection
B29: LWIC - R39 | D29: 94702 | E29: sf | H29: I | I29: 100000 | J29: I
B30: Roof membrane | D30: 94702 | E30: sf | H30: I | J30: I
B31: Flashings at roof drains & penetrations | H31: I | J31: I
B32: VTR | D32: 42 | E32: ea | H32: I | J32: I
B33: Parapet coping | H33: I | J33: I
B34: parapet | D34: 1652 | E34: lf
B35: parapet stair & elevator | D35: 359 | E35: lf
B36: parapet w/ gutter | D36: 946 | E36: lf
B37: Roof expansion joints | D37: 102 | E37: lf | F37: 250 | G37: =F37*D37 -> 25500 | H37: I | J37: I
B38: Gutters & downspouts | H38: I | J38: I
B39: 20 year warranty | H39: I | J39: I
B40: Exhaust fans - flashings | D40: 32 | E40: ea | F40: 250 | G40: =F40*D40 -> 8000 | H40: I | J40: I
B41: RTU - flashings | D41: 4 | E41: ea | F41: 750 | G41: =F41*D41 -> 3000 | H41: I | J41: I
B43: Canopies | H43: I | J43: I | K43: 88000
B44: A641 - 4 locations | D44: =(188)*4 -> 752 | E44: sf
B45: A642 - 1 locations | D45: =574 -> 574 | E45: sf
B46: A643 - 2 locations | D46: =(133)*2 -> 266 | E46: sf
F54: SUBTOTAL | I54: =SUM(I11:I53) -> 1300000 | K54: =SUM(K20:K53) -> 1441500 | M54: =SUM(M11:M53) -> 0 | O54: =SUM(O11:O53) -> 0 | Q54: =SUM(Q11:Q53) -> 0 | S54: =SUM(S11:S53) -> 0
F55: BOND RATE | H55: 0.005 | J55: 0 | L55: 0 | N55: 0 | P55: 0 | R55: 0
F56: BOND AMOUNT | I56: =I54*H55 -> 6500 | K56: =K54*J55 -> 0 | M56: =M54*L55 -> 0 | O56: =O54*N55 -> 0 | Q56: =Q54*P55 -> 0 | S56: =S54*R55 -> 0
F58: ADJUSTED TOTAL | I58: =SUM(I54:I57) -> 1306500 | K58: =SUM(K54:K57) -> 1441500 | M58: =SUM(M54:M56) -> 0 | O58: =SUM(O54:O56) -> 0 | Q58: =SUM(Q54:Q56) -> 0 | S58: =SUM(S54:S56) -> 0
F59: Cost per SF | I59: =I58/'Area Calculations'!$G$4 -> 2.2577908 | K59: =K58/'Area Calculations'!$G$4 -> 2.4910872 | M59: =M58/'Area Calculations'!$G$4 -> 0 | O59: =O58/'Area Calculations'!$G$4 -> 0 | Q59: =Q58/'Area Calculations'!$G$4 -> 0 | S59: =S58/'Area Calculations'!$G$4 -> 0
F60: Cost per Unit | I60: =I58/'Area Calculations'!$G$9 -> 12210.28 | K60: =K58/'Area Calculations'!$G$9 -> 13471.963 | M60: =M58/'Area Calculations'!$G$9 -> 0 | O60: =O58/'Area Calculations'!$G$9 -> 0 | Q60: =Q58/'Area Calculations'!$G$9 -> 0 | S60: =S58/'Area Calculations'!$G$9 -> 0
A62: QUALIFICATIONS
A66: EXCLUSIONS/OWNER PROVIDED ITEMS:
A70: ALTERNATES:
A74: PROPOSED VE (Provide Clear Description):
A78: FULLY LOADED LABOR RATES
B79: Laborer
B80: Mechanic
B81: Superintendent
B82: Project Manager
A84: SCHEDULE
B85: Prepared shop drawings/submittals
B86: Mobilization
B87: Total duration to complete scope of work
A89: Winner
A90: Company | B90: =H5 -> Jenkins Roofing
A91: Contact | B91: =H6 -> Vince Niesen
A92: Phone | B92: =H7 -> ( 904 ) 304-7400
A93: Email | B93: =H8 -> Vince@JenkinsRoofingInc.com
A94: Base Bid | B94: =I58 -> 1306500

Sheet 07 81 Spray Fireproofing
G1: Hedrick Plug
F2: X | G2: Excluded
F3: I | G3: Included
B4: BACK TO SUMMARY SHEET | G4: Sub Add/Deduct | H4: Bidder 1 | J4: Bidder 2 | L4: Bidder 3 | N4: Bidder 4 | P4: Bidder5 | R4: Bidder6
A5: Project: | B5: ='Area Calculations'!B4 -> ERAU Residential Hall & Garage Building | G5: Company | H5: Fire Stop Systems
A6: Trade: | B6: Spray Fireproofing | G6: Contact
A7: CSI Code: | B7: 07 76 00 | G7: Phone
A8: Date: | G8: Email
G9: Adjusted Bid | H9: =I55 -> 87200 | J9: =K55 -> 0 | L9: =M55 -> 0 | N9: =O55 -> 0 | P9: =Q55 -> 0 | R9: =S55 -> 0
C10: Plan/ Spec. Package | D10: QTY | E10: U/M | F10: Unit Cost | G10: Subtotal | H10: Yes/No | I10: Price | J10: Yes/No | K10: Price | L10: Yes/No | M10: Price | N10: Yes/No | O10: Price | P10: Yes/No | Q10: Price | R10: Yes/No | S10: Price
B11: GENERAL INCLUSIONS
B12: INCLUDES ALL SALES TAX
B13: ALL HOISTING & RIGGING REQUIRED TO COMPLETE THIS SCOPE
B14: PROVIDE P&P BONDS
B15: FLORIDA STATE CONTRACTORS LIC.
B16: GENERAL LIABILITY AND WORKERS COMP. INSURANCE LIMITS
B17: STATE AND LOCAL TAXES
B18: SPECIFIC TRADE SCOPE OF WORK REQUIREMENTS
B19: BASE BID | I19: 87200
B21: Floor beams
B22: Deck Angle
B23: Roof Beams
F51: SUBTOTAL | I51: =SUM(I11:I50) -> 87200 | K51: =SUM(K11:K50) -> 0 | M51: =SUM(M11:M50) -> 0 | O51: =SUM(O11:O50) -> 0 | Q51: =SUM(Q11:Q50) -> 0 | S51: =SUM(S11:S50) -> 0
F52: BOND RATE | H52: 0 | J52: 0 | L52: 0 | N52: 0 | P52: 0 | R52: 0
F53: BOND AMOUNT | I53: =I51*H52 -> 0 | K53: =K51*J52 -> 0 | M53: =M51*L52 -> 0 | O53: =O51*N52 -> 0 | Q53: =Q51*P52 -> 0 | S53: =S51*R52 -> 0
F55: ADJUSTED TOTAL | I55: =SUM(I51:I53) -> 87200 | K55: =SUM(K51:K53) -> 0 | M55: =SUM(M51:M53) -> 0 | O55: =SUM(O51:O53) -> 0 | Q55: =SUM(Q51:Q53) -> 0 | S55: =SUM(S51:S53) -> 0
F56: Cost per SF | I56: =I55/'Area Calculations'!$G$4 -> 0.1506922 | K56: =K55/'Area Calculations'!$G$4 -> 0 | M56: =M55/'Area Calculations'!$G$4 -> 0 | O56: =O55/'Area Calculations'!$G$4 -> 0 | Q56: =Q55/'Area Calculations'!$G$4 -> 0 | S56: =S55/'Area Calculations'!$G$4 -> 0
F57: Cost per Unit | I57: =I55/'Area Calculations'!$G$9 -> 814.95327 | K57: =K55/'Area Calculations'!$G$9 -> 0 | M57: =M55/'Area Calculations'!$G$9 -> 0 | O57: =O55/'Area Calculations'!$G$9 -> 0 | Q57: =Q55/'Area Calculations'!$G$9 -> 0 | S57: =S55/'Area Calculations'!$G$9 -> 0
A59: QUALIFICATIONS
A63: EXCLUSIONS/OWNER PROVIDED ITEMS:
A67: ALTERNATES:
A71: PROPOSED VE (Provide Clear Description):
A75: FULLY LOADED LABOR RATES
B76: Laborer
B77: Mechanic
B78: Superintendent
B79: Project Manager
A81: SCHEDULE
B82: Prepared shop drawings/submittals
B83: Mobilization
B84: Total duration to complete scope of work
A86: Winner
A87: Company | B87: Fire Stop Systems
A88: Contact
A89: Phone
A90: Email
A91: Base Bid | B91: =I55 -> 87200

Sheet 07 84 Firestopping
G1: Hedrick Plug
F2: X | G2: Excluded
F3: I | G3: Included
B4: BACK TO SUMMARY SHEET | G4: Sub Add/Deduct | H4: Bidder 1 | J4: Bidder 2 | L4: Bidder 3 | N4: Bidder 4 | P4: Bidder5 | R4: Bidder6
A5: Project: | B5: ='Area Calculations'!B4 -> ERAU Residential Hall & Garage Building | G5: Company | H5: Fire Stop Systems
A6: Trade: | B6: Firestopping | G6: Contact
A7: CSI Code: | B7: 07 84 00 | G7: Phone
A8: Date: | G8: Email
G9: Adjusted Bid | H9: =I55 -> 19175 | J9: =K55 -> 0 | L9: =M55 -> 0 | N9: =O55 -> 0 | P9: =Q55 -> 0 | R9: =S55 -> 0
C10: Plan/ Spec. Package | D10: QTY | E10: U/M | F10: Unit Cost | G10: Subtotal | H10: Yes/No | I10: Price | J10: Yes/No | K10: Price | L10: Yes/No | M10: Price | N10: Yes/No | O10: Price | P10: Yes/No | Q10: Price | R10: Yes/No | S10: Price
B11: GENERAL INCLUSIONS
B12: INCLUDES ALL SALES TAX
B13: ALL HOISTING & RIGGING REQUIRED TO COMPLETE THIS SCOPE
B14: PROVIDE P&P BONDS
B15: FLORIDA STATE CONTRACTORS LIC.
B16: GENERAL LIABILITY AND WORKERS COMP. INSURANCE LIMITS
B17: STATE AND LOCAL TAXES
B18: SPECIFIC TRADE SCOPE OF WORK REQUIREMENTS
B19: BASE BID
B21: Curtain Wall assembly | I21: 19175
F51: SUBTOTAL | I51: =SUM(I11:I50) -> 19175 | K51: =SUM(K11:K50) -> 0 | M51: =SUM(M11:M50) -> 0 | O51: =SUM(O11:O50) -> 0 | Q51: =SUM(Q11:Q50) -> 0 | S51: =SUM(S11:S50) -> 0
F52: BOND RATE | H52: 0 | J52: 0 | L52: 0 | N52: 0 | P52: 0 | R52: 0
F53: BOND AMOUNT | I53: =I51*H52 -> 0 | K53: =K51*J52 -> 0 | M53: =M51*L52 -> 0 | O53: =O51*N52 -> 0 | Q53: =Q51*P52 -> 0 | S53: =S51*R52 -> 0
F55: ADJUSTED TOTAL | I55: =SUM(I51:I53) -> 19175 | K55: =SUM(K51:K53) -> 0 | M55: =SUM(M51:M53) -> 0 | O55: =SUM(O51:O53) -> 0 | Q55: =SUM(Q51:Q53) -> 0 | S55: =SUM(S51:S53) -> 0
F56: Cost per SF | I56: =I55/'Area Calculations'!$G$4 -> 0.033136731 | K56: =K55/'Area Calculations'!$G$4 -> 0 | M56: =M55/'Area Calculations'!$G$4 -> 0 | O56: =O55/'Area Calculations'!$G$4 -> 0 | Q56: =Q55/'Area Calculations'!$G$4 -> 0 | S56: =S55/'Area Calculations'!$G$4 -> 0
F57: Cost per Unit | I57: =I55/'Area Calculations'!$G$9 -> 179.20561 | K57: =K55/'Area Calculations'!$G$9 -> 0 | M57: =M55/'Area Calculations'!$G$9 -> 0 | O57: =O55/'Area Calculations'!$G$9 -> 0 | Q57: =Q55/'Area Calculations'!$G$9 -> 0 | S57: =S55/'Area Calculations'!$G$9 -> 0
A59: QUALIFICATIONS
A63: EXCLUSIONS/OWNER PROVIDED ITEMS:
A67: ALTERNATES:
A71: PROPOSED VE (Provide Clear Description):
A75: FULLY LOADED LABOR RATES
B76: Laborer
B77: Mechanic
B78: Superintendent
B79: Project Manager
A81: SCHEDULE
B82: Prepared shop drawings/submittals
B83: Mobilization
B84: Total duration to complete scope of work
A86: Winner
A87: Company
A88: Contact
A89: Phone
A90: Email
A91: Base Bid | B91: =I51 -> 19175

Sheet 07 92 Exp Joint
G1: Hedrick Plug
F2: X | G2: Excluded
F3: I | G3: Included
B4: BACK TO SUMMARY SHEET | G4: Sub Add/Deduct | H4: Bidder 1 | J4: Bidder 2 | L4: Bidder 3 | N4: Bidder 4 | P4: Bidder5 | R4: Bidder6
A5: Project: | B5: ='Area Calculations'!B4 -> ERAU Residential Hall & Garage Building | G5: Company | H5: Daniel Insulation
A6: Trade: | B6: Expansion Joints | G6: Contact | H6: Justin Cesaretti
A7: CSI Code: | B7: 07 92 00 | G7: Phone | H7: (689) 262-0407
A8: Date: | G8: Email | H8: justin.cesaretti@truteam.com
G9: Adjusted Bid | H9: =I55 -> 170000 | J9: =K55 -> 0 | L9: =M55 -> 0 | N9: =O55 -> 0 | P9: =Q55 -> 0 | R9: =S55 -> 0
C10: Plan/ Spec. Package | D10: QTY | E10: U/M | F10: Unit Cost | G10: Subtotal | H10: Yes/No | I10: Price | J10: Yes/No | K10: Price | L10: Yes/No | M10: Price | N10: Yes/No | O10: Price | P10: Yes/No | Q10: Price | R10: Yes/No | S10: Price
B11: GENERAL INCLUSIONS
B12: INCLUDES ALL SALES TAX | H12: i
B13: ALL HOISTING & RIGGING REQUIRED TO COMPLETE THIS SCOPE | H13: i
B14: PROVIDE P&P BONDS | H14: x
B15: FLORIDA STATE CONTRACTORS LIC. | H15: i
B16: GENERAL LIABILITY AND WORKERS COMP. INSURANCE LIMITS | H16: i
B17: STATE AND LOCAL TAXES | H17: i
B18: COMPASS | H18: i | I18: {4.0}
B19: SPECIFIC TRADE SCOPE OF WORK REQUIREMENTS
B20: BASE BID
B23: Expansion joints shall be a maximum of 3", and their details and exact locations will be coordinated during the Precast Concrete Engineering Phase. For the purpose of bidding, assume the following typical conditions: •Horizontal expansion joints will occur between two precast slabs at each residential level. •Vertical expansion joints will occur between two aligned precast wall panels along the south and north elevations, and at interior corners adjacent to the storefront systems in the study rooms on the east elevation. •MM Systems or Watson Bowman Acme as the basis of design for pricing and coordination.
I24: 150000 | V24: A121 corridor ceiling | Y24: 6
B25: vertical walls corridor | C25: 1/A521 | D25: 208.4 | E25: lf | H25: I | V25: A123 corridor ceiling | Y25: 6
B26: corridor ceiling | C26: 2/A521 | D26: 514.17 | E26: lf | H26: I | V26: A121 corridor floor | Z26: 6
B27: corridor floor | C27: 2/A521 | D27: 514.17 | E27: lf | H27: I | V27: A121 vertical corridor | AA27: 2 | AB27: 11.17 | AC27: =AA27*AB27 -> 22.34
B28: exterior vertical - metal panel - outside / inside | C28: 3/A521 | D28: 120 | E28: lf | H28: I | V28: A131 corridor ceiling | Y28: 12
B29: exterior vertical - precast panel - outside / inside | C29: 4/A521 | D29: 32 | E29: lf | H29: I | V29: A133 corridor ceiling | Y29: 13
B30: roof deck - fire barrier only | C30: 5/A521 | D30: 102 | E30: lf | H30: I | I30: 20000 | V30: A151 corridor ceiling | Y30: 6
V31: A151 corridor floor | Z31: 6
V32: A151 corridor floor | Z32: 6
V33: A153 corridor ceiling | Y33: 6
V34: A153 corridor floor | Z34: 6
V40: A153 vertical corridor | AA40: 2 | AB40: 10.17 | AC40: =AA40*AB40 -> 20.34
V41: A161 corridor ceiling | Y41: 6
V42: A161 corridor floor | Z42: 6
V43: A161 vertical corridor | AA43: 2 | AB43: 10.42 | AC43: =AA43*AB43 -> 20.84
V44: A163 corridor ceiling | Y44: 6
V45: A163 corridor floor | Z45: 6
V46: A163 vertical corridor | AA46: 2 | AB46: 10.42 | AC46: =AA46*AB46 -> 20.84
Y47: =SUM(Y24:Y46) -> 61 | Z47: =SUM(Z24:Z46) -> 36 | AA47: =SUM(AA24:AA46) -> 8 | AC47: =SUM(AC24:AC46) -> 84.36
V49: A170 roof deck | Y49: 102
F51: SUBTOTAL | G51: =SUM(G21:G50) -> 0 | I51: =SUM(I21:I50) -> 170000 | K51: =SUM(K21:K50) -> 0 | M51: =SUM(M21:M50) -> 0 | O51: =SUM(O21:O50) -> 0 | Q51: =SUM(Q21:Q50) -> 0 | S51: =SUM(S21:S50) -> 0
F52: BOND RATE | H52: 0 | J52: 0 | L52: 0 | N52: 0 | P52: 0 | R52: 0
F53: BOND AMOUNT | I53: =I51*H52 -> 0 | K53: =K51*J52 -> 0 | M53: =M51*L52 -> 0 | O53: =O51*N52 -> 0 | Q53: =Q51*P52 -> 0 | S53: =S51*R52 -> 0
F55: ADJUSTED TOTAL | I55: =SUM(I51:I53) -> 170000 | K55: =SUM(K51:K53) -> 0 | M55: =SUM(M51:M53) -> 0 | O55: =SUM(O51:O53) -> 0 | Q55: =SUM(Q51:Q53) -> 0 | S55: =SUM(S51:S53) -> 0
F56: Cost per SF | I56: =I55/'Area Calculations'!$G$4 -> 0.29378066 | K56: =K55/'Area Calculations'!$G$4 -> 0 | M56: =M55/'Area Calculations'!$G$4 -> 0 | O56: =O55/'Area Calculations'!$G$4 -> 0 | Q56: =Q55/'Area Calculations'!$G$4 -> 0 | S56: =S55/'Area Calculations'!$G$4 -> 0
F57: Cost per Unit | I57: =I55/'Area Calculations'!$G$9 -> 1588.785 | K57: =K55/'Area Calculations'!$G$9 -> 0 | M57: =M55/'Area Calculations'!$G$9 -> 0 | O57: =O55/'Area Calculations'!$G$9 -> 0 | Q57: =Q55/'Area Calculations'!$G$9 -> 0 | S57: =S55/'Area Calculations'!$G$9 -> 0
A59: QUALIFICATIONS
A63: EXCLUSIONS/OWNER PROVIDED ITEMS:
A67: ALTERNATES:
A71: PROPOSED VE (Provide Clear Description):
A75: FULLY LOADED LABOR RATES
B76: Laborer
B77: Mechanic
B78: Superintendent
B79: Project Manager
A81: SCHEDULE
B82: Prepared shop drawings/submittals
B83: Mobilization
B84: Total duration to complete scope of work
A86: Winner
A87: Company | B87: =H5 -> Daniel Insulation
A88: Contact | B88: =H6 -> Justin Cesaretti
A89: Phone | B89: =H7 -> (689) 262-0407
A90: Email | B90: =H8 -> justin.cesaretti@truteam.com
A91: Base Bid | B91: =I55 -> 170000

Sheet 08 10 DFH
G1: Hedrick Plug
F2: X | G2: Excluded
F3: I | G3: Included
B4: BACK TO SUMMARY SHEET | G4: Sub Add/Deduct | H4: Bidder 4 | J4: Bidder 3 | L4: Bidder8 | N4: Bidder 2 | P4: Bidder7 | R4: Bidder 3 | T4: Bidder5 | V4: Bidder6 | X4: Bidder 1
A5: Project: | B5: ERAU Residential Hall & Garage Building | G5: Company | H5: Cook & Boardman | J5: Unified Doors & Hard | L5: Superior Hardware | N5: Allied Door & Hardware | P5: Taylor-Cotton-Ridley | R5: Commercial Doorways | T5: JDR Doors & Hardware | V5: Builders FirstSource | X5: APRO Construction Group
A6: Trade: | B6: Doors, Frames & Hardware | G6: Contact | N6: Mark Hill | P6: LynDea Drury | X6: Estimator
A7: CSI Code: | B7: 08 10 00 | G7: Phone | N7: (321) 481-7500 | P7: (407) 298-5114 | X7: (407) 960-7690
A8: Date: | G8: Email | N8: mhill@allieddoors.com | P8: ldrury@taylorcottonridley.com | X8: bids@aprocg.com
G9: Adjusted Bid | H9: =I171 -> 2072590 | J9: =K171 -> 2198500 | L9: =M171 -> 2325500 | N9: =O171 -> 0 | P9: =Q171 -> 0 | R9: =S171 -> 0 | T9: =U171 -> 0 | V9: =W171 -> 0 | X9: =Y171 -> 800291.42
C10: Plan/ Spec. Package | D10: QTY | E10: U/M | F10: Unit Cost | G10: Subtotal | H10: Yes/No | I10: Price | J10: Yes/No | K10: Price | L10: Yes/No | M10: Price | N10: Yes/No | O10: Price | P10: Yes/No | Q10: Price | R10: Yes/No | S10: Price | T10: Yes/No | U10: Price | V10: Yes/No | W10: Price | X10: Yes/No | Y10: Price
B11: GENERAL INCLUSIONS
B12: INCLUDES ALL SALES TAX | H12: i
B13: ALL HOISTING & RIGGING REQUIRED TO COMPLETE THIS SCOPE | H13: i
B14: PROVIDE P&P BONDS | H14: x
B15: FLORIDA STATE CONTRACTORS LIC. | H15: i
B16: GENERAL LIABILITY AND WORKERS COMP. INSURANCE LIMITS | H16: i
B17: STATE AND LOCAL TAXES | H17: i
B18: COMPASS | H18: i
B19: SPECIFIC TRADE SCOPE OF WORK REQUIREMENTS
B20: BASE BID
B22: Door Schedules | C22: A630 to A632 | I22: 1768660 | K22: 1538679.2 | M22: 1726391.5
B23: Common Area Doors
B24: HM Frames | H24: I | J24: I | L24: I
B25: HM Frame 2-8 x 7-0 | D25: 24 | E25: ea
B26: HM Frame 2-8 x 7-0 45 min | D26: 125 | E26: ea
B27: HM Frame 3-0 x 7-0 | D27: 67 | E27: ea
B28: HM Frame 3-0 x 7-0 45 min | D28: 12 | E28: ea
B29: HM Frame 3-0 x 7-0 90 min | D29: 1 | E29: ea
B30: HM Frame 3-2 x 7-0 90 min | D30: 91 | E30: ea
B31: HM Frame 3-4 x 7-0 45 min | D31: 1 | E31: ea
B32: HM Frame 3-4 x 7-0 90 min | D32: 10 | E32: ea
B33: HM Frame 4-0 x 8-0 | D33: 2 | E33: ea
B34: HM Frame 5-0 x 7-0 | D34: 1 | E34: ea
B35: HM Frame 6-0 x 7-0 | D35: 2 | E35: ea
B36: HM Frame 6-0 x 7-0 45 min | D36: 2 | E36: ea
... B39: HM Frame 6-0 x 8-0 90 min | D39: 8 | E39: ea
B40: HM Doors - # leafs | H40: I | J40: I | L40: I
B41: HM Frame 2-8 x 7-0 | D41: 24 | E41: ea
B42: HM Frame 2-8 x 7-0 45 min | D42: 125 | E42: ea
B43: HM Frame 3-0 x 7-0 | D43: 67 | E43: ea
B44: HM Frame 3-0 x 7-0 45 min | D44: 12 | E44: ea
B45: HM Frame 3-0 x 7-0 90 min | D45: 1 | E45: ea
B46: HM Frame 3-2 x 7-0 90 min | D46: 91 | E46: ea
B47: HM Frame 3-4 x 7-0 45 min | D47: 1 | E47: ea
B48: HM Frame 3-4 x 7-0 90 min | D48: 10 | E48: ea
B49: HM Frame 4-0 x 8-0 | D49: 2 | E49: ea
B50: HM Frame 5-0 x 7-0 | D50: =1*2 -> 2 | E50: ea
B51: HM Frame 6-0 x 7-0 | D51: =2*2 -> 4 | E51: ea
B52: HM Frame 6-0 x 7-0 45 min | D52: =2*2 -> 4 | E52: ea
B53: HM Frame 6-0 x 7-0 90 min | D53: =1*2 -> 2 | E53: ea
B54: HM Frame 6-0 x 8-0 | D54: =4*2 -> 8 | E54: ea
B55: HM Frame 6-0 x 8-0 90 min | D55: =8*2 -> 16 | E55: ea
B56: SC WD Doors - # leafs | H56: I | J56: I | L56: I
B57: Door - Type SC 3-0 x 7-0 | D57: 26 | E57: ea
B58: Door - Type SC 5-0 x 7-0 | D58: =1*2 -> 2 | E58: ea
B59: Door - Type SC 6-0 x 7-0 | D59: =2*2 -> 4 | E59: ea
B61: Vision Lites | J61: I
B62: Door - Type F 3-0 x 7-0 | D62: 12 | E62: ea | F62: 250 | G62: =D62*F62 -> 3000 | I62: =$G62 -> 3000 | M62: =$G62 -> 3000
B63: Door - Type F 6-0 x 7-0 | D63: =2*2 -> 4 | E63: ea | F63: 250 | G63: =D63*F63 -> 1000 | I63: =$G63 -> 1000 | M63: =$G63 -> 1000
B64: Door - Type F 6-0 x 8-0 | D64: =11*2 -> 22 | E64: ea | F64: 250 | G64: =D64*F64 -> 5500 | I64: =$G64 -> 5500 | M64: =$G64 -> 5500
A66: 103 | B66: Unit Doors | Y66: =111284.28+643212 -> 754496.28
B67: HM Frames
B68: HM Doors - # leafs | H68: I | J68: I | L68: I
B69: U1 - 3-0 x 7-0 - 20 min | D69: 103 | E69: ea
B70: Steel Redi-Frames | H70: I | J70: I | L70: I
B71: U1 - 3-0 x 7-0 - 20 min | D71: 103 | E71: ea
B72: U2 - 2-10 x 7-0 | D72: =4*103 -> 412 | E72: ea
B73: U3 - 2-10 x 7-0 | D73: =4*103 -> 412 | E73: ea
B74: U4 - 5-0 x 7-0 | D74: =1*103 -> 103 | E74: ea
B75: U5 - 2-8 x 7-0 | E75: ea
B76: SC WD Doors - # leafs | H76: I | J76: I | L76: I
B77: U2 - 2-10 x 7-0 | D77: =4*103 -> 412 | E77: ea
B78: U3 - 2-10 x 7-0 | D78: =4*103 -> 412 | E78: ea
B79: U4 - 5-0 x 7-0 | D79: =1*103*2 -> 206 | E79: ea
B80: U5 - 2-8 x 7-0 | E80: ea
B81: Guest & Staff Unit Doors
B82: HM Frames
B83: HM Doors - # leafs | H83: I | J83: I | L83: I
B84: U1 - 3-0 x 7-0 | D84: 4 | E84: ea
B85: Steel Redi-Frames | H85: I | J85: I | L85: I
B86: U1 - 3-0 x 7-0 | D86: 4 | E86: ea
B87: U2 - 2-10 x 7-0 | D87: 6 | E87: ea
B88: U3 - 2-10 x 7-0 | D88: 6 | E88: ea
B89: U4 - 5-0 x 7-0 | D89: 2 | E89: ea
B90: U5 - 2-8 x 7-0 | D90: 2 | E90: ea
B91: SC WD Doors - # leafs | H91: I | J91: I | L91: I
B92: U2 - 2-10 x 7-0 | D92: 6 | E92: ea
B93: U3 - 2-10 x 7-0 | D93: 6 | E93: ea
B94: U4 - 5-0 x 7-0 | D94: 4 | E94: ea
B95: U5 - 2-8 x 7-0 | D95: 2 | E95: ea
B97: Kick Plates | D97: =SUM(D41:D55) -> 369 | E97: ea
B99: Hardware - Common Area | H99: I | J99: I | L99: I
B100: Hardware Group 1 | D100: 1 | E100: ea
B101: Hardware Group 2 | D101: 8 | E101: ea
B102: Hardware Group 3 | D102: 1 | E102: ea
B103: Hardware Group 4 | D103: 2 | E103: ea
B104: Hardware Group 5 | D104: 2 | E104: ea
B105: Hardware Group 6 | D105: 2 | E105: ea
B106: Hardware Group 7 | D106: 3 | E106: ea
B107: Hardware Group 8 | D107: 1 | E107: ea
...

Sheet 08 30 Retractable Screens
G1: Hedrick Plug
G2: Excluded
B3: BACK TO SUMMARY SHEET | G3: Included | H3: Bidder 1 | J3: Bidder 2 | L3: Bidder 3 | N3: Bidder 4 | P3: Bidder5 | R3: Bidder6
A4: Project: | B4: ='Area Calculations'!B4 -> ERAU Residential Hall & Garage Building | G4: Company
A5: Trade: | B5: Retractable Screens | G5: Contact
A6: CSI Code: | B6: 08 30 | G6: Phone
A7: Date: | G7: Email
A8: Adjusted Bid | G8: Adjusted Bid
A9: BID DOCUMENTS: | C9: Plan/ Spec. Package | D9: QTY | E9: U/M | F9: Unit Cost | G9: Subtotal | H9: Yes/No | I9: Price | J9: Yes/No | K9: Price | L9: Yes/No | M9: Price | N9: Yes/No | O9: Price | P9: Yes/No | Q9: Price | R9: Yes/No | S9: Price
B10: Plans By Division
B11: ='Area Calculations'!#REF! -> #REF! | C11: P
B12: ='Area Calculations'!#REF! -> #REF! | C12: P
B13: ='Area Calculations'!#REF! -> #REF! | C13: P
B14: ='Area Calculations'!#REF! -> #REF! | C14: P
B15: ='Area Calculations'!#REF! -> #REF! | C15: P
B16: ='Area Calculations'!#REF! -> #REF! | C16: P
B17: ='Area Calculations'!#REF! -> #REF! | C17: P
B18: ='Area Calculations'!#REF! -> #REF! | C18: P
B19: ='Area Calculations'!#REF! -> #REF! | C19: P
B21: Retractable Screens
B22: GENERAL INCLUSIONS
B23: INCLUDES ALL SALES TAX
B24: ALL HOISTING & RIGGING REQUIRED TO COMPLETE THIS SCOPE
B25: PROVIDE P&P BONDS
B26: FLORIDA STATE CONTRACTORS LIC.
B27: GENERAL LIABILITY AND WORKERS COMP. INSURANCE LIMITS
B28: STATE AND LOCAL TAXES
B29: SPECIFIC TRADE SCOPE OF WORK REQUIREMENTS
B30: BASE BID
F41: SUBTOTAL | I41: =SUM(I23:I40) -> 0 | K41: =SUM(K23:K40) -> 0 | M41: =SUM(M23:M40) -> 0 | O41: =SUM(O23:O40) -> 0 | Q41: =SUM(Q23:Q40) -> 0 | S41: =SUM(S23:S40) -> 0
F42: BOND RATE | H42: 0 | P42: 0 | R42: 0
F43: BOND AMOUNT | I43: =I41*H42 -> 0 | K43: =K41*J42 -> 0 | M43: =M41*L42 -> 0 | O43: =O41*N42 -> 0 | Q43: =Q41*P42 -> 0 | S43: =S41*R42 -> 0
F45: ADJUSTED TOTAL | I45: =SUM(I41:I43) -> 0 | K45: =SUM(K41:K43) -> 0 | M45: =SUM(M41:M43) -> 0 | O45: =SUM(O41:O43) -> 0 | Q45: =SUM(Q41:Q43) -> 0 | S45: =SUM(S41:S43) -> 0
F46: Cost per SF | I46: =I45/'Area Calculations'!$G$4 -> 0 | K46: =K45/'Area Calculations'!$G$4 -> 0 | M46: =M45/'Area Calculations'!$G$4 -> 0 | O46: =O45/'Area Calculations'!$G$4 -> 0 | Q46: =Q45/'Area Calculations'!$G$4 -> 0 | S46: =S45/'Area Calculations'!$G$4 -> 0
F47: Cost per Unit | I47: =I45/'Area Calculations'!$G$9 -> 0 | K47: =K45/'Area Calculations'!$G$9 -> 0 | M47: =M45/'Area Calculations'!$G$9 -> 0 | O47: =O45/'Area Calculations'!$G$9 -> 0 | Q47: =Q45/'Area Calculations'!$G$9 -> 0 | S47: =S45/'Area Calculations'!$G$9 -> 0
A49: QUALIFICATIONS
A53: EXCLUSIONS/OWNER PROVIDED ITEMS:
A57: ALTERNATES:
A61: PROPOSED VE (Provide Clear Description):
A65: FULLY LOADED LABOR RATES
B66: Laborer
B67: Mechanic
B68: Superintendent
B69: Project Manager
A71: SCHEDULE
B72: Prepared shop drawings/submittals
B73: Mobilization
B74: Total duration to complete scope of work
A76: Winner
A77: Company
A78: Contact
A79: Phone
A80: Email
A81: Base Bid
B83: Need Prequalification
B84: Prequalified

Sheet 08 32 Hangar Doors
G1: Hedrick Plug
F2: X | G2: Excluded
F3: I | G3: Included
B4: BACK TO SUMMARY SHEET | G4: Sub Add/Deduct | H4: Bidder 1 | J4: Bidder 2 | L4: Bidder 3 | N4: Bidder 4 | P4: Bidder5 | R4: Bidder6
A5: Project: | B5: ='Area Calculations'!B4 -> ERAU Residential Hall & Garage Building | G5: Company | H5: Coast to Coast Garage Dr | J5: Southern Impact Welding | L5: Schweiss
A6: Trade: | B6: Hangar Doors | G6: Contact | H6: Natalie Morrison | J6: Nick | L6: Jeremy Rieke
A7: CSI Code: | B7: 08 32 00 | G7: Phone | H7: (954) 471-4698 | J7: (352) 235-5211 | L7: (800) 746-8273
A8: Date: | G8: Email | H8: nmorrison@c2cgaragedoors.com | J8: Sales@southernimpactwelding.com | L8: jeremy@schweissdoors.com
G9: Adjusted Bid | H9: =I56 -> 558065.19 | J9: =K56 -> 0 | L9: =M56 -> 93400.1 | N9: =O56 -> 0 | P9: =Q56 -> 0 | R9: =S56 -> 0
C10: Plan/ Spec. Package | D10: QTY | E10: U/M | F10: Unit Cost | G10: Subtotal | H10: Yes/No | I10: Price | J10: Yes/No | K10: Price | L10: Yes/No | M10: Price | N10: Yes/No | O10: Price | P10: Yes/No | Q10: Price | R10: Yes/No | S10: Price
B11: GENERAL INCLUSIONS
B12: INCLUDES ALL SALES TAX | H12: i
B13: ALL HOISTING & RIGGING REQUIRED TO COMPLETE THIS SCOPE | H13: i
B14: PROVIDE P&P BONDS | H14: x | I14: {2.0%}
B15: FLORIDA STATE CONTRACTORS LIC. | H15: i
B16: GENERAL LIABILITY AND WORKERS COMP. INSURANCE LIMITS | H16: i
B17: STATE AND LOCAL TAXES | H17: i
B18: COMPASS | H18: x
B19: SPECIFIC TRADE SCOPE OF WORK REQUIREMENTS
B20: BASE BID | I20: 546180
B22: Vertical Hydraulic Doors - 1st level | D22: 3 | E22: ea | H22: I | M22: 93400.1
B23: Basis of Design: Schweiss Bi-Fold Doors | L23: I
B24: Electric Operator | H24: I | L24: I
B25: Factory Primer Finish | H25: I | L25: I
B26: Walk-thru Door | H26: I | L26: I
B27: External Sheeting | D27: 1568 | E27: sf | F27: 5 | G27: =D27*F27 -> 7840 | I27: =$G27 -> 7840 | L27: I
B28: Installation | H28: I
B30: Sliding Hangar Door - 5th level | D30: 1 | E30: pr | H30: I
B31: Basis of Design: Door Engineering and Manufacturing
B32: Electric Operator | H32: I
B33: Factory Primer Finish | H33: I
B34: External Sheeting | D34: =14.5*8.75*2 -> 253.75 | E34: sf | F34: 5 | G34: =D34*F34 -> 1268.75 | I34: =$G34 -> 1268.75
B35: Installation | H35: I
D38: =D27+D34 -> 1821.75 | E38: sf | F38: =H9/D38 -> 306.33467 | G38: =D38*F38 -> 558065.19
B39: Vertical Hydraulic Doors - 1st level | D39: =D27 -> 1568 | E39: sf | F39: =F38 -> 306.33467 | G39: =D39*F39 -> 480332.77
B40: Sliding Hangar Door - 5th level | D40: =D34 -> 253.75 | E40: sf | F40: =F38 -> 306.33467 | G40: =D40*F40 -> 77732.424
F52: SUBTOTAL | I52: =SUM(I20:I51) -> 555288.75 | K52: =SUM(K20:K51) -> 0 | M52: =SUM(M20:M51) -> 93400.1 | O52: =SUM(O20:O51) -> 0 | Q52: =SUM(Q20:Q51) -> 0 | S52: =SUM(S20:S51) -> 0
F53: BOND RATE | H53: 0.005 | J53: 0 | L53: 0 | N53: 0 | P53: 0 | R53: 0
F54: BOND AMOUNT | I54: =H53*I52 -> 2776.4437 | K54: =J53*K52 -> 0 | M54: =L53*M52 -> 0 | O54: =N53*O52 -> 0 | Q54: =P53*Q52 -> 0 | S54: =R53*S52 -> 0
F56: ADJUSTED TOTAL | I56: =SUM(I52:I54) -> 558065.19 | K56: =SUM(K52:K54) -> 0 | M56: =SUM(M52:M54) -> 93400.1 | O56: =SUM(O52:O54) -> 0 | Q56: =SUM(Q52:Q54) -> 0 | S56: =SUM(S52:S54) -> 0
F57: Cost per SF | I57: =I56/'Area Calculations'!$G$4 -> 0.96440449 | K57: =K56/'Area Calculations'!$G$4 -> 0 | M57: =M56/'Area Calculations'!$G$4 -> 0.16140673 | O57: =O56/'Area Calculations'!$G$4 -> 0 | Q57: =Q56/'Area Calculations'!$G$4 -> 0 | S57: =S56/'Area Calculations'!$G$4 -> 0
F58: Cost per Unit | I58: =I56/'Area Calculations'!$G$9 -> 5215.5626 | K58: =K56/'Area Calculations'!$G$9 -> 0 | M58: =M56/'Area Calculations'!$G$9 -> 872.89813 | O58: =O56/'Area Calculations'!$G$9 -> 0 | Q58: =Q56/'Area Calculations'!$G$9 -> 0 | S58: =S56/'Area Calculations'!$G$9 -> 0
A60: QUALIFICATIONS
A64: EXCLUSIONS/OWNER PROVIDED ITEMS:
A68: ALTERNATES:
A72: PROPOSED VE (Provide Clear Description):
A76: FULLY LOADED LABOR RATES
B77: Laborer
B78: Mechanic
B79: Superintendent
B80: Project Manager
A82: SCHEDULE
B83: Prepared shop drawings/submittals
B84: Mobilization
B85: Total duration to complete scope of work
A87: Winner
A88: Company
A89: Contact
A90: Phone
A91: Email
A92: Base Bid | B92: =I56 -> 558065.19

Sheet 08 33 Overhead doors
G1: Hedrick Plug
F2: X | G2: Excluded
F3: I | G3: Included
B4: BACK TO SUMMARY SHEET | G4: Sub Add/Deduct | H4: Bidder 2 | J4: Bidder 1 | L4: Bidder 3 | N4: Bidder 4 | P4: Bidder5 | R4: Bidder6
A5: Project: | B5: ='Area Calculations'!B4 -> ERAU Residential Hall & Garage Building | G5: Company | H5: ODC of Daytona | J5: Miner | L5: Coast to Coast Garage Dr | N5: Door Systems of SF | P5: American Roll Up Door
A6: Trade: | B6: Overhead Doors | G6: Contact | H6: Jason Hardy | J6: Binky Conklin | L6: Natalie Morrison
A7: CSI Code: | B7: 08 33 00 | G7: Phone | H7: (386) 226-3820 | J7: (407) 600-7260 | L7: (954) 471-4698
A8: Date: | G8: Email | H8: jason@overheaddoordaytona.com | J8: bconklin@minercorp.com | L8: nmorrison@c2cgaragedoors.com
G9: Adjusted Bid | H9: =I58 -> 29480 | J9: =K58 -> 32500 | L9: =M58 -> 37930 | N9: =O58 -> 0 | P9: =Q58 -> 0 | R9: =S58 -> 0
C10: Plan/ Spec. Package | D10: QTY | E10: U/M | F10: Unit Cost | G10: Subtotal | H10: Yes/No | I10: Price | J10: Yes/No | K10: Price | L10: Yes/No | M10: Price | N10: Yes/No | O10: Price | P10: Yes/No | Q10: Price | R10: Yes/No | S10: Price
B11: GENERAL INCLUSIONS
B12: INCLUDES ALL SALES TAX | H12: i
B13: ALL HOISTING & RIGGING REQUIRED TO COMPLETE THIS SCOPE | H13: i
B14: PROVIDE P&P BONDS | H14: x
B15: FLORIDA STATE CONTRACTORS LIC. | H15: i
B16: GENERAL LIABILITY AND WORKERS COMP. INSURANCE LIMITS | H16: i
B17: STATE AND LOCAL TAXES | H17: i
B18: COMPASS | H18: x
B19: SPECIFIC TRADE SCOPE OF WORK REQUIREMENTS
B20: BASE BID | I20: 27980 | K20: 32500 | M20: 37930
B22: Overhead Coiling Door Fire rated
B23: 137B - 8-0 x 8-0 | D23: 1 | E23: ea | H23: I | J23: I | L23: I
B24: 153B - 8-0 x 8-0 | D24: 1 | E24: ea | H24: I | J24: I | L24: I
B26: Operation Cycles: not specified for fire rated oodr
B27: Insulated | H27: I | J27: I | L27: I
B28: Locking Device | D28: 2 | E28: ea | F28: 750 | G28: =D28*F28 -> 1500 | I28: 1500 | J28: I
B29: Motorized | H29: I | J29: I | L29: I
B30: Baked-Enamel or Powder-Coated Finish | H30: I | J30: I | L30: I
B31: Hood | H31: I | J31: I | L31: I
B32: Fire Rated - 45 min | H32: I | L32: I
F54: SUBTOTAL | I54: =SUM(I20:I53) -> 29480 | K54: =SUM(K20:K53) -> 32500 | M54: =SUM(M20:M53) -> 37930 | O54: =SUM(O20:O53) -> 0 | Q54: =SUM(Q20:Q53) -> 0 | S54: =SUM(S20:S53) -> 0
F55: BOND RATE | H55: 0 | J55: 0 | L55: 0 | N55: 0 | P55: 0 | R55: 0
F56: BOND AMOUNT | I56: =H55*I54 -> 0 | K56: =J55*K54 -> 0 | M56: =L55*M54 -> 0 | O56: =N55*O54 -> 0 | Q56: =P55*Q54 -> 0 | S56: =R55*S54 -> 0
F58: ADJUSTED TOTAL | I58: =SUM(I54:I56) -> 29480 | K58: =SUM(K54:K56) -> 32500 | M58: =SUM(M54:M56) -> 37930 | O58: =SUM(O54:O56) -> 0 | Q58: =SUM(Q54:Q56) -> 0 | S58: =SUM(S54:S56) -> 0
F59: Cost per SF | I59: =I58/'Area Calculations'!$G$4 -> 0.050945023 | K59: =K58/'Area Calculations'!$G$4 -> 0.05616395 | M59: =M58/'Area Calculations'!$G$4 -> 0.06554765 | O59: =O58/'Area Calculations'!$G$4 -> 0 | Q59: =Q58/'Area Calculations'!$G$4 -> 0 | S59: =S58/'Area Calculations'!$G$4 -> 0
F60: Cost per Unit | I60: =I58/'Area Calculations'!$G$9 -> 275.51402 | K60: =K58/'Area Calculations'!$G$9 -> 303.73832 | M60: =M58/'Area Calculations'!$G$9 -> 354.48598 | O60: =O58/'Area Calculations'!$G$9 -> 0 | Q60: =Q58/'Area Calculations'!$G$9 -> 0 | S60: =S58/'Area Calculations'!$G$9 -> 0
A62: QUALIFICATIONS
A66: EXCLUSIONS/OWNER PROVIDED ITEMS:
A70: ALTERNATES:
A74: PROPOSED VE (Provide Clear Description):
A78: FULLY LOADED LABOR RATES
B79: Laborer
B80: Mechanic
B81: Superintendent
B82: Project Manager
A84: SCHEDULE
B85: Prepared shop drawings/submittals
B86: Mobilization
B87: Total duration to complete scope of work
A89: Winner
A90: Company
A91: Contact
A92: Phone
A93: Email
A94: Base Bid | B94: =I58 -> 29480

Sheet 08 50 Storefront & Windows
G1: Hedrick Plug
F2: X | G2: Excluded
F3: I | G3: Included
B4: BACK TO SUMMARY SHEET | G4: Sub Add/Deduct | H4: Bidder 3 | J4: Bidder 2 | L4: Bidder 1 | N4: Bidder 4 | P4: Bidder 5 | R4: Bidder 6
A5: Project: | B5: ='Area Calculations'!B4 -> ERAU Residential Hall & Garage Building | G5: Company | H5: Sunryse Construction | J5: Contractors Glass | L5: A. Christian Glass | N5: Storm Troopers | P5: Miller Glass & Glazing
A6: Trade: | B6: Storefront & Windows | G6: Contact | H6: Jorge Salcedo | J6: Keith Taylor | L6: Jake Dable | N6: Jada Goksan
A7: CSI Code: | B7: 08 50 00 | G7: Phone | H7: (772) 219-3506 | J7: (904) 907-4378 | L7: (561) 866-2122 | N7: (754) 422-5617
A8: Date: | G8: Email | H8: jorge_scsi@bellsouth.ne | J8: ktaylor@contractorsglass.net | L8: jake@a-christianglass.com | N8: jada@stormtroopersgroup.com
G9: Adjusted Bid | H9: =I125 -> 5009000 | J9: =K125 -> 5198500 | L9: =M125 -> 4454215 | N9: =O125 -> 2774629.3 | P9: =Q125 -> 2350928.7 | R9: =S125 -> 0
C10: Plan/ Spec. Package | D10: QTY | E10: U/M | F10: Unit Cost | G10: Subtotal | H10: Yes/No | I10: Price | J10: Yes/No | K10: Price | L10: Yes/No | M10: Price | N10: Yes/No | O10: Price | P10: Yes/No | Q10: Price | R10: Yes/No | S10: Price
B11: GENERAL INCLUSIONS
B12: INCLUDES ALL SALES TAX | H12: i
B13: ALL HOISTING & RIGGING REQUIRED TO COMPLETE THIS SCOPE | H13: i
B14: PROVIDE P&P BONDS | H14: x | I14: {1.0%}
B15: FLORIDA STATE CONTRACTORS LIC. | H15: i
B16: GENERAL LIABILITY AND WORKERS COMP. INSURANCE LIMITS | H16: i
B17: STATE AND LOCAL TAXES | H17: i
B18: COMPASS | H18: x | I18: {1.7}
B19: SPECIFIC TRADE SCOPE OF WORK REQUIREMENTS
B20: BASE BID | I20: 4912000 | K20: 4991000
B22: Manufacturers: Subject to compliance with requirements, provide products by one of the following:
B23: EFCO Corporation.
B24: Kawneer North America
B25: Truelite | N25: I
B26: Vistawall Architectural Products
B27: YKK AP America Inc. | H27: I | J27: I
M28: ES Windows
B29: Sound Transmission: Provide aluminum-framed systems with fixed glazing and framing areas having the following sound-transmission characteristics:
B30: Exterior Storefronts: Acoustic: STC 32-36 depending on glazing.
B31: Interior Storefronts: Study Room to Hallway Separation: Minimum STC 35
B32: Fire rating: 20-minute rated glass with certification
B33: Vestibules into Residential Zones:
B34: Smoke-rated and self-closing doors required
B35: Minimum STC 32
B36: Impact - resistant safety glazing preferred.
B37: Office Partitions:
B38: Non rated, minimum STC 30
B39: Glazing laminated for safety and acoustic performance.
B41: Impact Rated - wind speed | H41: I
B43: Curtainwall | H43: I | M43: 3875880 | N43: I | O43: 315719.74 | V43: Quant | W43: W | X43: H | Y43: SF | Z43: Sills | AA43: LF opening | AB43: LF total | AC43: SF total | AD43: Doors
B44: =U44 -> CW-01 | D44: =AC44 -> 806.3825 | E44: sf | F44: 130 | G44: =D44*F44 -> 104829.73 | U44: CW-01 | V44: 1 | W44: 14.75 | X44: =54.67 -> 54.67 | Y44: =W44*X44 -> 806.3825 | Z44: =W44*V44 -> 14.75 | AA44: =(W44+W44+X44+X44) -> 138.84 | AB44: =V44*AA44 -> 138.84 | AC44: =V44*Y44 -> 806.3825
B45: =U45 -> CW-01 SF | D45: =AC45 -> 17.2575 | E45: sf | F45: 130 | G45: =D45*F45 -> 2243.475 | U45: CW-01 SF | V45: 1 | W45: 14.75 | X45: 1.17 | Y45: =W45*X45 -> 17.2575 | Z45: =W45*V45 -> 14.75 | AA45: =(W45+W45+X45+X45) -> 31.84 | AB45: =V45*AA45 -> 31.84 | AC45: =V45*Y45 -> 17.2575 | AD45: 2
B46: =U46 -> CW-02 | D46: =AC46 -> 3096.2622 | E46: sf | F46: 130 | G46: =D46*F46 -> 402514.09 | U46: CW-02 | V46: 2 | W46: 22.17 | X46: 69.83 | Y46: =W46*X46 -> 1548.1311 | Z46: =W46*V46 -> 44.34 | AA46: =(W46+W46+X46+X46) -> 184 | AB46: =V46*AA46 -> 368 | AC46: =V46*Y46 -> 3096.2622
B47: =U47 -> CW-03 | D47: =AC47 -> 1748.0772 | E47: sf | F47: 130 | G47: =D47*F47 -> 227250.04 | U47: CW-03 | V47: 2 | W47: 14.67 | X47: =74.33-14.75 -> 59.58 | Y47: =W47*X47 -> 874.0386 | Z47: =W47*V47 -> 29.34 | AA47: =(W47+W47+X47+X47) -> 148.5 | AB47: =V47*AA47 -> 297 | AC47: =V47*Y47 -> 1748.0772
B48: Storefront | G48: =D48*F48 -> 0 | H48: I | N48: I | O48: 919767.15 | Q48: 2350928.3
B49: =U49 -> SF-01 | D49: =AC49 -> 2611.7694 | E49: sf | F49: 85 | G49: =D49*F49 -> 222000.4 | Q49: =O48/Q48 -> 0.39123574 | U49: SF-01 | V49: 54 | W49: 4.33 | X49: 11.17 | Y49: =W49*X49 -> 48.3661 | Z49: =W49*V49 -> 233.82 | AA49: =(W49+W49+X49+X49) -> 31 | AB49: =V49*AA49 -> 1674 | AC49: =V49*Y49 -> 2611.7694
B50: =U50 -> SF-02a | D50: =AC50 -> 2095.0452 | E50: sf | F50: 85 | G50: =D50*F50 -> 178078.84 | U50: SF-02a | V50: 18 | W50: 10.42 | X50: 11.17 | Y50: =W50*X50 -> 116.3914 | Z50: =W50*V50 -> 187.56 | AA50: =(W50+W50+X50+X50) -> 43.18 | AB50: =V50*AA50 -> 777.24 | AC50: =V50*Y50 -> 2095.0452
B51: =U51 -> SF-02b | D51: =AC51 -> 1914.4666 | E51: sf | F51: 85 | G51: =D51*F51 -> 162729.66 | U51: SF-02b | V51: 19 | W51: 10.42 | X51: 9.67 | Y51: =W51*X51 -> 100.7614 | Z51: =W51*V51 -> 197.98 | AA51: =(W51+W51+X51+X51) -> 40.18 | AB51: =V51*AA51 -> 763.42 | AC51: =V51*Y51 -> 1914.4666
B52: =U52 -> SF-02c | D52: =AC52 -> 7588.6776 | E52: sf | F52: 85 | G52: =D52*F52 -> 645037.6 | U52: SF-02c | V52: 84 | W52: 10.42 | X52: 8.67 | Y52: =W52*X52 -> 90.3414 | Z52: =W52*V52 -> 875.28 | AA52: =(W52+W52+X52+X52) -> 38.18 | AB52: =V52*AA52 -> 3207.12 | AC52: =V52*Y52 -> 7588.6776
B53: =U53 -> SF-03a | D53: =AC53 -> 98.7428 | E53: sf | F53: 85 | G53: =D53*F53 -> 8393.138 | U53: SF-03a | V53: 2 | W53: 4.42 | X53: 11.17 | Y53: =W53*X53 -> 49.3714 | Z53: =W53*V53 -> 8.84 | AA53: =(W53+W53+X53+X53) -> 31.18 | AB53: =V53*AA53 -> 62.36 | AC53: =V53*Y53 -> 98.7428
B54: =U54 -> SF-03b | D54: =AC54 -> 85.4828 | E54: sf | F54: 85 | G54: =D54*F54 -> 7266.038 | U54: SF-03b | V54: 2 | W54: 4.42 | X54: 9.67 | Y54: =W54*X54 -> 42.7414 | Z54: =W54*V54 -> 8.84 | AA54: =(W54+W54+X54+X54) -> 28.18 | AB54: =V54*AA54 -> 56.36 | AC54: =V54*Y54 -> 85.4828
B55: =U55 -> SF-03c | D55: =AC55 -> 306.5712 | E55: sf | F55: 85 | G55: =D55*F55 -> 26058.552 | U55: SF-03c | V55: 8 | W55: 4.42 | X55: 8.67 | Y55: =W55*X55 -> 38.3214 | Z55: =W55*V55 -> 35.36 | AA55: =(W55+W55+X55+X55) -> 26.18 | AB55: =V55*AA55 -> 209.44 | AC55: =V55*Y55 -> 306.5712
B56: =U56 -> SF-04 | D56: =AC56 -> 990.5556 | E56: sf | F56: 85 | G56: =D56*F56 -> 84197.226 | U56: SF-04 | V56: 4 | W56: 22.17 | X56: 11.17 | Y56: =W56*X56 -> 247.6389 | Z56: =W56*V56 -> 88.68 | AA56: =(W56+W56+X56+X56) -> 66.68 | AB56: =V56*AA56 -> 266.72 | AC56: =V56*Y56 -> 990.5556
B57: =U57 -> SF-05a | D57: =AC57 -> 247.6389 | E57: sf | F57: 85 | G57: =D57*F57 -> 21049.306 | U57: SF-05a | V57: 1 | W57: 22.17 | X57: 11.17 | Y57: =W57*X57 -> 247.6389 | Z57: =W57*V57 -> 22.17 | AA57: =(W57+W57+X57+X57) -> 66.68 | AB57: =V57*AA57 -> 66.68 | AC57: =V57*Y57 -> 247.6389 | AD57: =2*V57 -> 2
B58: =U58 -> SF-05b | D58: =AC58 -> 247.6389 | E58: sf | F58: 85 | G58: =D58*F58 -> 21049.306 | U58: SF-05b | V58: 1 | W58: 22.17 | X58: 11.17 | Y58: =W58*X58 -> 247.6389 | Z58: =W58*V58 -> 22.17 | AA58: =(W58+W58+X58+X58) -> 66.68 | AB58: =V58*AA58 -> 66.68 | AC58: =V58*Y58 -> 247.6389 | AD58: =2*V58 -> 2
B59: =U59 -> SF-06 | D59: =AC59 -> 495.2778 | E59: sf | F59: 85 | G59: =D59*F59 -> 42098.613 | U59: SF-06 | V59: 2 | W59: 22.17 | X59: 11.17 | Y59: =W59*X59 -> 247.6389 | Z59: =W59*V59 -> 44.34 | AA59: =(W59+W59+X59+X59) -> 66.68 | AB59: =V59*AA59 -> 133.36 | AC59: =V59*Y59 -> 495.2778 | AD59: =2*V59 -> 4
B60: =U60 -> SF-08a | D60: =AC60 -> 66.1264 | E60: sf | F60: 85 | G60: =D60*F60 -> 5620.744 | U60: SF-08a | V60: 1 | W60: =0.17+3+2.75 -> 5.92 | X60: 11.17 | Y60: =W60*X60 -> 66.1264 | Z60: =W60*V60 -> 5.92 | AA60: =(W60+W60+X60+X60) -> 34.18 | AB60: =V60*AA60 -> 34.18 | AC60: =V60*Y60 -> 66.1264 | AD60: =1*V60 -> 1
B61: =U61 -> SF-08b | D61: =AC61 -> 66.1264 | E61: sf | F61: 85 | G61: =D61*F61 -> 5620.744 | U61: SF-08b | V61: 1 | W61: =0.17+3+2.75 -> 5.92 | X61: 11.17 | Y61: =W61*X61 -> 66.1264 | Z61: =W61*V61 -> 5.92 | AA61: =(W61+W61+X61+X61) -> 34.18 | AB61: =V61*AA61 -> 34.18 | AC61: =V61*Y61 -> 66.1264 | AD61: =1*V61 -> 1
B62: =U62 -> SF-09a | D62: =AC62 -> 228.9856 | E62: sf | F62: 85 | G62: =D62*F62 -> 19463.776 | U62: SF-09a | V62: 4 | W62: =0.17+3+2.75 -> 5.92 | X62: 9.67 | Y62: =W62*X62 -> 57.2464 | Z62: =W62*V62 -> 23.68 | AA62: =(W62+W62+X62+X62) -> 31.18 | AB62: =V62*AA62 -> 124.72 | AC62: =V62*Y62 -> 228.9856
B63: =U63 -> SF-09b | D63: =AC63 -> 307.9584 | E63: sf | F63: 85 | G63: =D63*F63 -> 26176.464 | U63: SF-09b | V63: 6 | W63: =0.17+3+2.75 -> 5.92 | X63: 8.67 | Y63: =W63*X63 -> 51.3264 | Z63: =W63*V63 -> 35.52 | AA63: =(W63+W63+X63+X63) -> 29.18 | AB63: =V63*AA63 -> 175.08 | AC63: =V63*Y63 -> 307.9584
B64: =U64 -> W1 | D64: =AC64 -> 10911.6 | E64: sf | F64: 85 | G64: =D64*F64 -> 927486 | H64: I | N64: I | O64: 726543.21 | U64: W1 | V64: 420 | W64: 4.33 | X64: 6 | Y64: =W64*X64 -> 25.98 | Z64: =W64*V64 -> 1818.6 | AA64: =(W64+W64+X64+X64) -> 20.66 | AB64: =V64*AA64 -> 8677.2 | AC64: =V64*Y64 -> 10911.6
B65: W1 sunshades | D65: =V64 -> 420 | E65: ea | F65: 500 | G65: =D65*F65 -> 210000 | H65: I | O65: =$G65 -> 210000
B66: Door leafs | D66: =AD66 -> 12 | E66: ea | G66: =D66*F66 -> 0 | AC66: =SUM(AC44:AC64) -> 33930.643 | AD66: =SUM(AD44:AD64) -> 12
G67: =D67*F67 -> 0
G68: =D68*F68 -> 0
B69: Interior Storefront | G69: =D69*F69 -> 0 | H69: I | M69: 572635 | N69: I | O69: 269548.8 | V69: Quant | W69: W | X69: H | Y69: SF | Z69: Sills | AA69: LF opening | AB69: LF total | AC69: SF total | AD69: Doors
B70: SF-11a | D70: =AC70 -> 293.4 | E70: sf | F70: 75 | G70: =D70*F70 -> 22005 | U70: SF-11a | V70: 2 | W70: 14.67 | X70: 10 | Y70: =W70*X70 -> 146.7 | Z70: =W70*V70 -> 29.34 | AA70: =(W70+W70+X70+X70) -> 49.34 | AB70: =V70*AA70 -> 98.68 | AC70: =V70*Y70 -> 293.4 | AD70: =1*V70 -> 2
B71: SF-12 | D71: =AC71 -> 146.7 | E71: sf | F71: 75 | G71: =D71*F71 -> 11002.5 | U71: SF-12 | V71: 1 | W71: 14.67 | X71: 10 | Y71: =W71*X71 -> 146.7 | Z71: =W71*V71 -> 14.67 | AA71: =(W71+W71+X71+X71) -> 49.34 | AB71: =V71*AA71 -> 49.34 | AC71: =V71*Y71 -> 146.7
B72: SF-13a - STC 35 | D72: =AC72 -> 128.3 | E72: sf | F72: 75 | G72: =D72*F72 -> 9622.5 | U72: SF-13a | V72: 1 | W72: 12.83 | X72: 10 | Y72: =W72*X72 -> 128.3 | Z72: =W72*V72 -> 12.83 | AA72: =(W72+W72+X72+X72) -> 45.66 | AB72: =V72*AA72 -> 45.66 | AC72: =V72*Y72 -> 128.3 | AD72: =1*V72 -> 1
B73: SF-13b - STC 35 | D73: =AC73 -> 128.3 | E73: sf | F73: 75 | G73: =D73*F73 -> 9622.5 | U73: SF-13b | V73: 1 | W73: 12.83 | X73: 10 | Y73: =W73*X73 -> 128.3 | Z73: =W73*V73 -> 12.83 | AA73: =(W73+W73+X73+X73) -> 45.66 | AB73: =V73*AA73 -> 45.66 | AC73: =V73*Y73 -> 128.3 | AD73: =1*V73 -> 1
B74: SF-14 | D74: =AC74 -> 148.3 | E74: sf | F74: 75 | G74: =D74*F74 -> 11122.5 | U74: SF-14 | V74: 1 | W74: 14.83 | X74: 10 | Y74: =W74*X74 -> 148.3 | Z74: =W74*V74 -> 14.83 | AA74: =(W74+W74+X74+X74) -> 49.66 | AB74: =V74*AA74 -> 49.66 | AC74: =V74*Y74 -> 148.3
B75: SF-15 - laminated | D75: =AC75 -> 104.2 | E75: sf | F75: 75 | G75: =D75*F75 -> 7815 | U75: SF-15 | V75: 1 | W75: 10.42 | X75: 10 | Y75: =W75*X75 -> 104.2 | Z75: =W75*V75 -> 10.42 | AA75: =(W75+W75+X75+X75) -> 40.84 | AB75: =V75*AA75 -> 40.84 | AC75: =V75*Y75 -> 104.2 | AD75: =1*V75 -> 1
B76: SF-16 - laminated | D76: =AC76 -> 320 | E76: sf | F76: 75 | G76: =D76*F76 -> 24000 | U76: SF-16 | V76: 4 | W76: 8 | X76: 10 | Y76: =W76*X76 -> 80 | Z76: =W76*V76 -> 32 | AA76: =(W76+W76+X76+X76) -> 36 | AB76: =V76*AA76 -> 144 | AC76: =V76*Y76 -> 320 | AD76: =1*V76 -> 4
B77: SF-17a - laminated | D77: =AC77 -> 200 | E77: sf | F77: 75 | G77: =D77*F77 -> 15000 | U77: SF-17a | V77: 4 | W77: 5 | X77: 10 | Y77: =W77*X77 -> 50 | Z77: =W77*V77 -> 20 | AA77: =(W77+W77+X77+X77) -> 30 | AB77: =V77*AA77 -> 120 | AC77: =V77*Y77 -> 200 | AD77: =1*V77 -> 4
B78: SF-17b - laminated | D78: =AC78 -> 150 | E78: sf | F78: 75 | G78: =D78*F78 -> 11250 | U78: SF-17b | V78: 3 | W78: 5 | X78: 10 | Y78: =W78*X78 -> 50 | Z78: =W78*V78 -> 15 | AA78: =(W78+W78+X78+X78) -> 30 | AB78: =V78*AA78 -> 90 | AC78: =V78*Y78 -> 150 | AD78: =1*V78 -> 3
