Workbook

Sheet Area Calculations
A1: 110025
B2: PROJECT AREA CALCULATIONS
B4: Bourbon Hotel Orlando
B5: Orlando | F5: Gross (sf) | G5: =E28 -> 389323
F6: AC (sf) | G6: =243055+18447 -> 261502
F7: Site (acres) | G7: =174581/43560 -> 4.0078283
F8: Parking Spaces | M8: Rooms | O8: penthouse | P8: suite | Q8: standard
F9: No. of Rooms | G9: =N15 -> 296 | M9: 2 | N9: =SUM(O9:Q9) -> 40 | P9: 1 | Q9: 39
F10: Build Duration (months) | M10: 3 | N10: =SUM(O10:Q10) -> 46 | P10: 3 | Q10: 43
M11: 4 | N11: =SUM(O11:Q11) -> 62 | P11: 6 | Q11: 56
M12: 5 | N12: =SUM(O12:Q12) -> 62 | P12: 6 | Q12: 56
A13: I. | B13: Floors | C13: Units | D13: AC SF | E13: Gross SF | F13: LSF | M13: 6 | N13: =SUM(O13:Q13) -> 62 | P13: 6 | Q13: 56
B14: Garage Level | E14: 110025 | M14: 7 | N14: 24 | O14: 3 | P14: 1 | Q14: 20
B15: Restaurant | E15: =SUM(I15:K15) -> 15680 | I15: 10434 | J15: 4259 | K15: 987 | N15: =SUM(N9:N14) -> 296 | O15: =SUM(O9:O14) -> 3 | P15: =SUM(P9:P14) -> 23 | Q15: =SUM(Q9:Q14) -> 270
B16: Restaurant Roof Garden | E16: 7081
B17: Level 1 Hotel | E17: 41647
B18: Level 2 thru 6 | E18: =SUM(I18:K18) -> 175894 | I18: 37358 | J18: 34634 | K18: =34634*3 -> 103902
B19: Level 7 | E19: 31962
B20: Level 7 Terrace | E20: 4950
B21: Bridge | E21: =1037+1047 -> 2084
B28: TOTAL | C28: =SUM(C14:C27) -> 0 | D28: =SUM(D14:D27) -> 0 | E28: =SUM(E14:E27) -> 389323 | F28: =SUM(F14:F27) -> 0
C30: total | D30: garage | E30: ground | F30: 2nd | G30: 3rd | H30: 4th - 6th | I30: 7th
B31: Corridors | C31: =C62+C63+C90 -> 39203
A32: IV. | B32: Corridors / Stairs | C32: =SUM(E32:I32) -> 0
B33: Corridors / Stairs | C33: =SUM(E33:I33) -> 0
B34: Corridors / Stairs | C34: =SUM(E34:I34) -> 0
B35: Corridors / Stairs | C35: =SUM(E35:I35) -> 0
B36: Corridors / Stairs | C36: =SUM(E36:I36) -> 0
B37: Corridors / Stairs | C37: =SUM(E37:I37) -> 0
B38: Corridors / Stairs | C38: =SUM(E38:I38) -> 0
A39: III. | B39: Corridors / Stairs | C39: =SUM(E39:I39) -> 0
B40: Corridors / Stairs | C40: =SUM(E40:I40) -> 0
B41: Corridors / Stairs | C41: =SUM(E41:I41) -> 0
B42: Corridors / Stairs | C42: =SUM(E42:I42) -> 0
B43: Corridors / Stairs | C43: =SUM(E43:I43) -> 0
A44: III. | B44: Corridors / Stairs | C44: =SUM(E44:I44) -> 0
B45: Corridors / Stairs | C45: =SUM(E45:I45) -> 0
B46: Corridors / Stairs | C46: =SUM(E46:I46) -> 0
B47: Corridors / Stairs | C47: =SUM(E47:I47) -> 0
B48: Corridors / Stairs | C48: =SUM(E48:I48) -> 0
B49: Corridors / Stairs | C49: =SUM(E49:I49) -> 0
B50: Elevator | C50: =C91 -> 6430
B51: Stairs | C51: =C103 -> 5988
B52: BOH / Service | C52: =C101 -> 19145
B53: MEP | C53: =C97 -> 1318
B54: Rooms | C54: =SUM(E54:I54) -> 130974 | F54: 16130 | G54: 25569 | H54: =25954*3 -> 77862 | I54: 11413
B55: Lobby / Reception | C55: =C95 -> 7754
B56: Restaurant / Spa / Amenity | C56: =C82+C83+C84+C87+C88+C89+C92+C93+C94+C102+C100 -> 38359
B57: Meeting | C57: =C96+C98 -> 12687
B58: Restrooms | C58: =C99 -> 1189
C59: =SUM(C31:C58) -> 263047
G60: Terrace
G61: =SUM(G62:G106) -> 8569
B62: Bridge 2 | C62: 1037 | D62: SF
B63: Bridge 3 | C63: 1047 | D63: SF
B64: Elevation - Back | C64: 21363 | D64: SF
B65: Elevation - Front | C65: 19432 | D65: SF
B66: Elevation - Left | C66: 34595 | D66: SF
B67: Elevation - Right | C67: 35035 | D67: SF
B68: Fountain | C68: 1 | D68: EA
B69: Garage Level | C69: 110792 | D69: SF | E69: 1514.36 | F69: LF
B70: Hotel - Prep Kitchen - Lev 2 | C70: 1351 | D70: SF
B71: Level 1 | C71: 57546 | D71: SF
B72: Level 1 Terrace | C72: 536 | D72: SF | G72: =C72 -> 536
B73: Level 2 | C73: 37660 | D73: SF
B74: Level 3 | C74: 34634 | D74: SF
B75: Level 3 Terrace | C75: 3083 | D75: SF | G75: =C75 -> 3083
B76: Level 4 thru 6 | C76: 34634 | D76: SF
B77: Level 7 | C77: 31962 | D77: SF
B78: Level 7 Terrace | C78: 4950 | D78: SF | G78: =C78 -> 4950
B79: Pool | C79: 3130 | D79: SF
B80: Pool Deck | C80: 12272 | D80: SF
B81: Pool Deck - lower | C81: 2404 | D81: SF
B82: Restaraunt - Level 1 | C82: 10434 | D82: SF
B83: Restaraunt - Level Mezz | C83: 4588 | D83: SF
B84: Restaraunt - Level Roof | C84: 1522 | D84: SF
B85: Restaraunt - Roof Garden | C85: 7081 | D85: SF
B86: Site | C86: 174581 | D86: SF
B87: Space- Bar / Lounge | C87: 4432 | D87: SF
B88: Space- Cafe / Deli | C88: 1108 | D88: SF
B89: Space- Destination Club | C89: 1880 | D89: SF
B90: Space- Corridor | C90: 37119 | D90: SF
... B105: Water Features | C105: 623 | D105: SF
B106: Water Features - shallow | C106: 4447 | D106: SF | E106: 1136.4 | F106: LF

Sheet Allowances
A3: ='Area Calculations'!B4 -> Bourbon Hotel Orlando | C3: ='Area Calculations'!B5 -> Orlando
A5: Allowances
A6: =TODAY() -> 46146
A8: NO. | B8: DESCRIPTION | C8: VALUE
A9: 1
A10: =A9+1 -> 2
A11: =A10+1 -> 3
A12: =A11+1 -> 4
A13: =A12+1 -> 5
A14: =A13+1 -> 6
A15: =A14+1 -> 7
A16: =A15+1 -> 8
A17: =A16+1 -> 9
A18: =A17+1 -> 10
A19: =A18+1 -> 11
A20: =A19+1 -> 12
A21: =A20+1 -> 13
... A26: =A25+1 -> 18
A27: =A26+1 -> 19 | B27: Total | C27: =SUM(C9:C26) -> 0
B29: *All ALLOWANCES IN BID TABS MUST BE LISTED HERE

Sheet Word C&A

Sheet Documents
A3: ='Area Calculations'!B4 -> Bourbon Hotel Orlando | C3: ='Area Calculations'!B5 -> Orlando
A5: List of Drawings
A6: =TODAY() -> 46146
A9: SHEET NO. | B9: DESCRIPTION | C9: DATE
D105: 11

Sheet Cost Summary
A3: ='Area Calculations'!B4 -> Bourbon Hotel Orlando
A4: ='Area Calculations'!B5 -> Orlando
A5: Conceptual Estimate - Cost Summary
A6: =NOW() -> 46146.223
A7: CSI | B7: CSI DESCRIPTION | C7: TOTAL | D7: $/
A8: 02 21 00 | B8: Surveying | C8: ='02 21 Survey '!$H$9 -> 60117 | D8: =C8/'Area Calculations'!$G$5 -> 0.1544142 | E8: ACRE
A9: 02 41 00 | B9: Demolition | C9: ='02 41 Demo'!$H$9 -> 0 | D9: =C9/'Area Calculations'!$G$5 -> 0 | E9: GSF
A10: 03 30 00 | B10: Concrete & CMU | C10: ='03 30 Conc & CMU'!$H$9 -> 33000765 | D10: =C10/'Area Calculations'!$G$5 -> 84.764489 | E10: GSF
A11: 04 40 00 | B11: Stone Cladding | C11: ='04 40 Stone Cladding'!$H$9 -> 132072 | D11: =C11/'Area Calculations'!$G$5 -> 0.33923503 | E11: GSF
A12: 05 30 00 | B12: Structural Steel | C12: ='05 10 Structural Steel'!$H$9 -> 11299290 | D12: =C12/'Area Calculations'!$G$5 -> 29.022919 | E12: GSF
A13: 05 52 00 | B13: Miscellaneous Metals | C13: ='05 52 Misc Metals'!$H$9 -> 1259600 | D13: =C13/'Area Calculations'!$G$5 -> 3.2353598 | E13: GSF
A14: 05 52 00 | B14: Railings - Glass | C14: ='05 70 Railings Glass'!$H$9 -> 698400 | D14: =C14/'Area Calculations'!$G$5 -> 1.7938832 | E14: GSF
A15: 06 10 00 | B15: Rough Carpentry | C15: ='06 10 Rough Carpentry'!$H$9 -> 236980 | D15: =C15/'Area Calculations'!$G$5 -> 0.60869766 | E15: GSF
A16: 06 50 00 | B16: Millwork | C16: Inc Buildout Cost
A17: 07 17 00 | B17: Waterproofing & Caulking | C17: ='07 17 Waterproofing & Caulk'!$H$9 -> 6411905 | D17: =C17/'Area Calculations'!$G$5 -> 16.469371 | E17: GSF
A18: 07 21 00 | B18: Sound Insulation | C18: ='07 21 Spray Foam Ins'!$H$9 -> 177267 | D18: =C18/'Area Calculations'!$G$5 -> 0.45532116 | E18: GSF
A19: 07 42 00 | B19: Metal Panel | C19: ='07 42 Metal Panel'!$H$9 -> 3361361 | D19: =C19/'Area Calculations'!$G$5 -> 8.6338619 | E19: GSF
A20: 07 50 00 | B20: Roofing | C20: ='07 50 Roofing'!$H$9 -> 1628655 | D20: =C20/'Area Calculations'!$G$5 -> 4.1833002 | E20: GSF
A21: 08 12 70 | B21: Doors, Frames, & Hardware | C21: Inc Buildout Cost
A22: 08 50 00 | B22: Storefront & Curtainwall | C22: ='08 50 Storefront'!$H$9 -> 8830610 | D22: =C22/'Area Calculations'!$G$5 -> 22.681963 | E22: GSF
A23: 08 50 00 | B23: Interior Glazing | C23: Inc Buildout Cost
A24: 09 29 00 | B24: Exterior Wall Framing | C24: ='09 29 Gypsum Board'!$H$9 -> 2590290 | D24: =C24/'Area Calculations'!$G$5 -> 6.6533187 | E24: GSF
A25: 09 29 00 | B25: Drywall | C25: Inc Buildout Cost
A26: 09 51 00 | B26: Acoustical Ceilings | C26: Inc Buildout Cost
A27: 09 60 00 | B27: Flooring | C27: Inc Buildout Cost
A28: 09 90 00 | B28: Painting - Exterior | C28: ='09 90 Painting'!$H$9 -> 29702 | D28: =C28/'Area Calculations'!$G$5 -> 0.076291408 | E28: GSF
A29: 09 90 00 | B29: Painting - Interior | C29: Inc Buildout Cost
A30: 10 28 00 | B30: Specialties | C30: Inc Buildout Cost
A31: 10 53 00 | B31: Signage | C31: ='10 53 Signage'!$H$9 -> 312233 | D31: =C31/'Area Calculations'!$G$5 -> 0.80198961 | E31: GSF
A32: 10 73 00 | B32: Canopies / Trellis | C32: ='10 73 Canopies'!$H$9 -> 2522500 | D32: =C32/'Area Calculations'!$G$5 -> 6.4791959 | E32: GSF
A33: 13 11 00 | B33: Pool & Water Features | C33: ='13 11 Pool'!$H$9 -> 4174180 | D33: =C33/'Area Calculations'!$G$5 -> 10.721637 | E33: GSF
A34: 14 00 00 | B34: Elevators | C34: ='14 00 Elevators'!$H$9 -> 3313230 | D34: =C34/'Area Calculations'!$G$5 -> 8.5102344 | E34: GSF
A35: 14 91 00 | B35: Laundry Chute | C35: ='14 91 Laundry Chute'!$H$9 -> 20300 | D35: =C35/'Area Calculations'!$G$5 -> 0.052141795 | E35: GSF
A36: 21 13 00 | B36: Fire Protection Systems | C36: ='21 13 Fire Protection'!$H$9 -> 1272593 | D36: =C36/'Area Calculations'!$G$5 -> 3.2687332 | E36: GSF
A37: 22 00 00 | B37: Plumbing | C37: ='22 00 Plumbing '!$H$9 -> 7234302 | D37: =C37/'Area Calculations'!$G$5 -> 18.581748 | E37: GSF
A38: 23 00 00 | B38: HVAC | C38: ='23 00 HVAC'!$H$9 -> 8615235 | D38: =C38/'Area Calculations'!$G$5 -> 22.128759 | E38: GSF
A39: 26 00 00 | B39: Electrical | C39: ='26 00 Electrical'!$H$9 -> 12741754 | D39: =C39/'Area Calculations'!$G$5 -> 32.727977 | E39: GSF
A40: 31 30 00 | B40: Sitework | C40: ='31 30 Site Work'!$H$9 -> 992609 | D40: =C40/'Area Calculations'!G7 -> 247667.55 | E40: ACRE
A41: 32 14 00 | B41: Hardscape | C41: ='32 14 00 Hardscape'!$H$9 -> 965407 | D41: =C41/'Area Calculations'!G7 -> 240880.33 | E41: ACRE
A42: 32 80 00 | B42: Landscape | C42: ='32 80 00 Landscape'!$H$9 -> 594475 | D42: =C42/'Area Calculations'!G7 -> 148328.46 | E42: ACRE
B44: Build-Out (Div 6 thru 11):
B45: Guestroom Interior Buildout - 296 Guestrooms | C45: =H45*D45 -> 5920000 | D45: 20000 | E45: Key | F45: 130974 | G45: sf | H45: 296 | I45: key | J45: =C45/F45 -> 45.199811 | K45: sf
B46: Corridors / Common Area | C46: =F46*D46 -> 1806735 | D46: 35 | E46: GSF | F46: ='Area Calculations'!C31+'Area Calculations'!C50+'Area Calculations'!C51 -> 51621 | G46: sf
B47: General Event / Amenity Space | C47: =F47*D47 -> 3649000 | D47: 250 | E47: GSF | F47: =1909+9844+2843 -> 14596 | G47: sf
B48: Back of House | C48: =F48*D48 -> 1023150 | D48: 50 | E48: GSF | F48: ='Area Calculations'!C52+'Area Calculations'!C53 -> 20463 | G48: sf
B49: Lobby / Reception | C49: =F49*D49 -> 1938500 | D49: 250 | E49: GSF | F49: 7754 | G49: sf
B50: Retail - White Box | C50: =F50*D50 -> 90720 | D50: 80 | E50: GSF | F50: 1134 | G50: sf
B51: Hotel - Prep Kitchen | C51: =F51*D51 -> 675500 | D51: 500 | E51: SF | F51: 1351 | G51: sf
B52: Bar / Lounge | C52: =F52*D52 -> 1772800 | D52: 400 | E52: SF | F52: 4432 | G52: sf
B53: Destination Club | C53: =F53*D53 -> 470000 | D53: 250 | E53: SF | F53: 1880 | G53: sf
B56: SUB-TOTAL | C56: =SUM(C8:C55) -> 129822237
B57: Construction Contingency | C57: =C56*D57 -> 0 | D57: 0
B58: SUB-TOTAL | C58: =SUM(C56:C57) -> 129822237
B59: General Conditions | C59: ='GCs & GRs'!L161 -> 6222864.1 | D59: =C59/C58 -> 0.047933731
B60: General Requirements | C60: ='GCs & GRs'!L162 -> 940672.56 | D60: =C60/C58 -> 0.0072458508
B61: Subcontractor Default Insurance | C61: =C58*D61 -> 1947333.6 | D61: 0.015
B62: OCIP (DIC) | C62: =(C58+C59+C60+C61)*D62 -> 486265.88 | D62: 0.0035
B63: Procore | C63: =C66*D63 -> 366063.11 | D63: 0.0025
B64: SUB-TOTAL | C64: =SUM(C58:C63) -> 1.3978544e+08
B65: Construction Fee | C65: =C64*D65 -> 6639808.2 | D65: 0.0475
B66: TOTAL CONSTRUCTION COST | C66: =SUM(C64:C65) -> 1.4642524e+08 | D66: =C66/'Area Calculations'!G5 -> 376.10222 | E66: GSF
B68: Gross (sf) / Cost Per Gross SF | C68: ='Area Calculations'!G5 -> 389323 | D68: =C66/C68 -> 376.10222 | E68: GSF
B69: AC (sf) / Cost Per AC SF | C69: ='Area Calculations'!G6 -> 261502 | D69: =C66/C69 -> 559.93929 | E69: AC SF
B70: Site (acres) / Site Work Cost Per Acre | C70: ='Area Calculations'!G7 -> 4.0078283 | D70: =D8+D40+D41+D42 -> 636876.49 | E70: ACRE
B71: No. of Rooms / Cost Per Key | C71: ='Area Calculations'!G9 -> 296 | D71: =C66/C71 -> 494679.88 | E71: Key
B73: Build-Out (Div 6 thru 28):
B74: Restaurant - Pavilion | C74: =F74*D74 -> 6782100 | D74: 650 | E74: SF | F74: 10434 | G74: sf | H74: 1501 Colins high end restaurant + add for kitchen equipment
B75: Restaurant - Pavilion Mezzanine | C75: =F75*D75 -> 1830400 | D75: 650 | E75: SF | F75: 2816 | G75: sf | H75: 1501 Colins high end restaurant + add for kitchen equipment
B76: Cafe / Deli | C76: =F76*D76 -> 443200 | D76: 400 | E76: SF | F76: 1108 | G76: sf | H76: NORA Juice Bar + add for appliances & kitchen equipment
B77: Destination Club | C77: =F77*D77 -> 282000 | D77: 150 | E77: SF | F77: 1880 | G77: sf
B78: Gelato | C78: =F78*D78 -> 226400 | D78: 400 | E78: SF | F78: 566 | G78: sf | H78: NORA Juice Bar + add for appliances & kitchen equipment
B79: KIBO Restaurant / Lounge | C79: =F79*D79 -> 3875950 | D79: 650 | E79: SF | F79: 5963 | G79: sf | H79: 1501 Colins high end restaurant + add for kitchen equipment
B80: Spa / Fitness | C80: =F80*D80 -> 1205750 | D80: 250 | E80: SF | F80: 4823 | G80: sf | H80: 1501 Colins high end spa inc spa equipment
B81: SUB-TOTAL | C81: =SUM(C74:C80) -> 14645800
B82: Construction Contingency | C82: =C81*D82 -> 0 | D82: =D57 -> 0
B83: SUB-TOTAL | C83: =SUM(C81:C82) -> 14645800
B84: General Conditions | C84: =C83*D84 -> 702027.83 | D84: =D59 -> 0.047933731
B85: General Requirements | C85: =C83*D85 -> 106121.28 | D85: =D60 -> 0.0072458508
B86: Subcontractor Default Insurance | C86: =C83*D86 -> 219687 | D86: =D61 -> 0.015
B87: General Liability Insurance | C87: =(C83+C84+C85+C86)*D87 -> 54857.726 | D87: =D62 -> 0.0035
B88: Procore | C88: =C91*D88 -> 41188.993 | D88: =D63 -> 0.0025
B89: SUB-TOTAL | C89: =SUM(C83:C87) -> 15728494
B90: Construction Fee | C90: =C89*D90 -> 747103.46 | D90: =D65 -> 0.0475
B91: TOTAL RESTAURANT, BAR, SPA | C91: =SUM(C89:C90) -> 16475597 | D91: =C91/C93 -> 597.15829 | E91: GSF
B93: Gross (sf) / Cost Per Gross SF | C93: =SUM(F74:F80) -> 27590 | D93: =C91/C93 -> 597.15829 | E93: GSF
B94: No. of Rooms / Cost Per Key | C94: ='Area Calculations'!G9 -> 296 | D94: =C91/C94 -> 55660.802 | E94: Key
B96: TOTAL CONSTRUCTION COST | C96: =C66 -> 1.4642524e+08 | D96: =D66 -> 376.10222 | E96: GSF
B97: TOTAL RESTAURANT, BAR, SPA | C97: =C91 -> 16475597 | D97: =D91 -> 597.15829 | E97: GSF
B98: TOTAL PROJECT COST | C98: =SUM(C96:C97) -> 1.6290084e+08 | D98: =C98/C99 -> 418.4208 | E98: GSF
B99: Combined - Gross (sf) / Cost Per Gross SF | C99: ='Area Calculations'!G5 -> 389323 | D99: =C98/C99 -> 418.4208 | E99: GSF
B100: Combined - No. of Rooms / Cost Per Key | C100: ='Area Calculations'!G9 -> 296 | D100: =D71+D94 -> 550340.68 | E100: Key

Sheet GCs & GRs
A1: Contract Reference | B1: General Condition Ref. | C1: TEST
C3: Construction | F3: Activity | H3: Start | I3: Finish | J3: Days | K3: Weeks | L3: Months | M3: % Time | N3: Remarks | O3: CUSTOMIZED LABOR RATES | P3: LABOR RATE FY 2025 *Updated 09.26.24 | R3: Demo to building pad
F4: Construction | H4: 46235 | I4: 46904 | J4: =SUM(I4-H4) -> 669 | K4: =SUM(J4/7) -> 95.571429 | L4: =SUM(J4/30) -> 22.3 | R4: Activity | T4: Start | U4: Finish | V4: Days | W4: Weeks | X4: Months
F5: Close Out | H5: =I4 -> 46904 | I5: =H5+60 -> 46964 | J5: =SUM(I5-H5) -> 60 | K5: =SUM(J5/7) -> 8.5714286 | L5: =SUM(J5/30) -> 2 | R5: Construction | T5: 0 | U5: 0 | V5: =SUM(U5-T5) -> 0 | W5: =SUM(V5/7) -> 0 | X5: =SUM(V5/30) -> 0
F6: General Conditions | H6: General Req. - Field Office | J6: General Req. | L6: Total | R6: Building
C7: Description | D7: Qty. | E7: U | F7: Unit | G7: Const. | H7: Unit | I7: General | J7: Unit | K7: General | Q7: LABOR RATE (MIAMI/FT. LAUDERDALE) | R7: Activity | T7: Start | U7: Finish | V7: Days | W7: Weeks | X7: Months | Y7: LABOR RATE (MF CENTRAL FLORIDA)
F8: Cost | G8: Cond. | H8: Cost | I8: Req. | J8: Cost | K8: Req. | R8: Construction | T8: 0 | U8: 0 | V8: =SUM(U8-T8) -> 0 | W8: =SUM(V8/7) -> 0 | X8: =SUM(V8/30) -> 0
C9: Field Labor - Construction | L9: =SUM(L10:L26) -> 5755110
A10: 1 | C10: Project Executive | D10: =$K$4 -> 95.571429 | E10: wks | F10: =(O10*40)*M10 -> 4256.9972 | G10: =SUM(D10*F10) -> 406847.3 | L10: =SUM(G10+I10+K10) -> 406847.3 | M10: 0.5 | O10: ='Labor Rates'!G10 -> 212.84986 | P10: 212.84986 | Q10: 253 | Y10: 216
A11: 2 | C11: Senior Project Manager | D11: =$K$4 -> 95.571429 | E11: wks | F11: =(O11*40)*M11 -> 7056.4365 | G11: =SUM(D11*F11) -> 674393.71 | L11: =SUM(G11+I11+K11) -> 674393.71 | M11: 1 | O11: ='Labor Rates'!G11 -> 176.41091 | P11: 176.41091 | Q11: 195 | Y11: 175
A12: 3 | C12: Project Manager - Level 3 | D12: =$K$4 -> 95.571429 | E12: wks | F12: =(O12*40)*M12 -> 0 | G12: =SUM(D12*F12) -> 0 | L12: =SUM(G12+I12+K12) -> 0 | M12: 0 | O12: ='Labor Rates'!G12 -> 162.46079 | P12: 162.46
A13: 4 | C13: Project Manager - Level 2 | D13: =$K$4 -> 95.571429 | E13: wks | F13: =(O13*40)*M13 -> 5947.817 | G13: =SUM(D13*F13) -> 568441.37 | L13: =SUM(G13+I13+K13) -> 568441.37 | M13: 1 | O13: ='Labor Rates'!G13 -> 148.69542 | P13: 148.69542 | Q13: 185 | Y13: 155
A14: 5 | C14: Project Manager - Level 1 | D14: =$K$4 -> 95.571429 | E14: wks | F14: =(O14*40)*M14 -> 5090.3426 | G14: =SUM(D14*F14) -> 486491.32 | L14: =SUM(G14+I14+K14) -> 486491.32 | M14: 1 | O14: ='Labor Rates'!G14 -> 127.25857 | P14: 127.25857 | Q14: 163 | Y14: 130
A15: 6 | C15: Project Administator | D15: =$K$4 -> 95.571429 | E15: wks | F15: =(O15*40)*M15 -> 3591.2833 | G15: =SUM(D15*F15) -> 343224.08 | L15: =SUM(G15+I15+K15) -> 343224.08 | M15: 1 | O15: ='Labor Rates'!G15 -> 89.782084 | P15: 89.782084 | Q15: 95 | Y15: 65
A16: 7 | C16: Project Accountant | D16: =$K$4 -> 95.571429 | E16: wks | F16: =(O16*40)*M16 -> 4633.7422 | G16: =SUM(D16*F16) -> 442853.36 | L16: =SUM(G16+I16+K16) -> 442853.36 | M16: 1 | O16: ='Labor Rates'!G16 -> 115.84355 | P16: 115.84355 | Q16: 81 | Y16: 60
A17: 8 | C17: Assistant Project Manager | D17: =$K$4 -> 95.571429 | E17: wks | F17: =(O17*40)*M17 -> 4467.6124 | G17: =SUM(D17*F17) -> 426976.1 | L17: =SUM(G17+I17+K17) -> 426976.1 | M17: 1 | O17: ='Labor Rates'!G17 -> 111.69031 | P17: 111.69031 | Q17: 118 | Y17: 95
A18: 9 | C18: Superintendent - Level 3 | D18: =$K$4 -> 95.571429 | E18: wks | F18: =(O18*40)*M18 -> 7114.6074 | G18: =SUM(D18*F18) -> 679953.19 | L18: =SUM(G18+I18+K18) -> 679953.19 | M18: 1 | O18: ='Labor Rates'!G18 -> 177.86518 | P18: 177.86518 | Q18: 183 | Y18: 194
A19: 10 | C19: Superintendent - Level 2 | D19: =$K$4 -> 95.571429 | E19: wks | F19: =(O19*40)*M19 -> 0 | G19: =SUM(D19*F19) -> 0 | L19: =SUM(G19+I19+K19) -> 0 | M19: 0 | O19: ='Labor Rates'!G19 -> 149.29951 | P19: 149.29951 | Q19: 161 | Y19: 173
A20: 11 | C20: Superintendent - Level 1 | D20: =$K$4 -> 95.571429 | E20: wks | F20: =(O20*40)*M20 -> 4887.7994 | G20: =SUM(D20*F20) -> 467133.97 | L20: =SUM(G20+I20+K20) -> 467133.97 | M20: 1 | O20: ='Labor Rates'!G20 -> 122.19499 | P20: 122.19499 | Q20: 121 | Y20: 155
A21: 12 | C21: Assistant Superinterndent | D21: =$K$4 -> 95.571429 | E21: wks | F21: =(O21*40)*M21 -> 5823.7833 | G21: =SUM(D21*F21) -> 556587.29 | L21: =SUM(G21+I21+K21) -> 556587.29 | M21: 1.8 | O21: ='Labor Rates'!G21 -> 80.885879 | P21: 80.885879 | Q21: 84 | Y21: 95
A22: 13 | C22: Quality Control Manager | D22: =$K$4 -> 95.571429 | E22: wks | F22: =(O22*40)*M22 -> 1389.5872 | G22: =SUM(D22*F22) -> 132804.84 | L22: =SUM(G22+I22+K22) -> 132804.84 | M22: 0.25 | O22: ='Labor Rates'!G22 -> 138.95872 | P22: 138.95872
A23: 14 | C23: Foreman | D23: =$K$4 -> 95.571429 | E23: wks | F23: =(O23*40)*M23 -> 2242.5364 | G23: =SUM(D23*F23) -> 214322.41 | L23: =SUM(G23+I23+K23) -> 214322.41 | M23: 1 | O23: ='Labor Rates'!G23 -> 56.06341 | P23: 56.06341 | Q23: 65 | Y23: 65
A24: 15 | C24: Accounting | D24: =$K$4 -> 95.571429 | E24: wks | F24: =(O24*40)*M24 -> 1252.1287 | G24: =SUM(D24*F24) -> 119667.73 | L24: =SUM(G24+I24+K24) -> 119667.73 | M24: 0.2 | O24: ='Labor Rates'!G24 -> 156.51609 | P24: 156.51609 | Q24: 80 | Y24: 90
A25: 16 | C25: VDC Manager | D25: =$K$4 -> 95.571429 | E25: wks | F25: =(O25*40)*M25 -> 1386.8106 | G25: =SUM(D25*F25) -> 132539.47 | L25: =SUM(G25+I25+K25) -> 132539.47 | M25: 0.25 | O25: ='Labor Rates'!G25 -> 138.68106 | P25: 138.68106 | Q25: 101 | Y25: 101
A26: 17 | C26: Safety Supervisor/Inspector | D26: =K4 -> 95.571429 | E26: wks | F26: =(O26*40)*M26 -> 1076.4086 | G26: =SUM(D26*F26) -> 102873.9 | L26: =SUM(G26+I26+K26) -> 102873.9 | M26: 0.25 | O26: ='Labor Rates'!G26 -> 107.64086 | P26: 107.64086 | Q26: 96 | Y26: 96
C27: Field Labor - Close Out | L27: =SUM(L28:L43) -> 467754.07
C28: Project Executive | D28: =$K$5 -> 8.5714286 | E28: wks | F28: =(40*P28)*M28 -> 0 | G28: =SUM(D28*F28) -> 0 | L28: =SUM(G28+I28+K28) -> 0 | M28: 0 | O28: =O10 -> 212.84986 | P28: =+P10 -> 212.84986 | Q28: =+Q10 -> 253 | Y28: =+Y10 -> 216
C29: Senior Project Manager | D29: =$K$5 -> 8.5714286 | E29: wks | F29: =(40*P29)*M29 -> 7056.4365 | G29: =SUM(D29*F29) -> 60483.741 | L29: =SUM(G29+I29+K29) -> 60483.741 | M29: =+M11 -> 1 | O29: =O11 -> 176.41091 | P29: =+P11 -> 176.41091 | Q29: =+Q11 -> 195 | Y29: =+Y11 -> 175
C30: Project Manager - Level 3 | D30: =$K$5 -> 8.5714286 | E30: wks | F30: =(40*P30)*M30 -> 0 | G30: =SUM(D30*F30) -> 0 | L30: =SUM(G30+I30+K30) -> 0 | M30: =+M12 -> 0 | O30: =O12 -> 162.46079 | P30: =P12 -> 162.46
C31: Project Manager - Level 2 | D31: =$K$5 -> 8.5714286 | E31: wks | F31: =(40*P31)*M31 -> 5947.817 | G31: =SUM(D31*F31) -> 50981.289 | L31: =SUM(G31+I31+K31) -> 50981.289 | M31: =+M13 -> 1 | O31: =O13 -> 148.69542 | P31: =+P13 -> 148.69542 | Q31: =+Q13 -> 185 | Y31: =+Y13 -> 155
C32: Project Manager - Level 1 | D32: =$K$5 -> 8.5714286 | E32: wks | F32: =(40*P32)*M32 -> 5090.3426 | G32: =SUM(D32*F32) -> 43631.508 | L32: =SUM(G32+I32+K32) -> 43631.508 | M32: =+M14 -> 1 | O32: =O14 -> 127.25857 | P32: =+P14 -> 127.25857 | Q32: =+Q14 -> 163 | Y32: =+Y14 -> 130
C33: Project Administator | D33: =$K$5 -> 8.5714286 | E33: wks | F33: =(40*P33)*M33 -> 3591.2833 | G33: =SUM(D33*F33) -> 30782.429 | L33: =SUM(G33+I33+K33) -> 30782.429 | M33: =+M15 -> 1 | O33: =O15 -> 89.782084 | P33: =+P15 -> 89.782084 | Q33: =+Q15 -> 95 | Y33: =+Y15 -> 65
C34: Project Coordinator | D34: =$K$5 -> 8.5714286 | E34: wks | F34: =(40*P34)*M34 -> 4633.7422 | G34: =SUM(D34*F34) -> 39717.79 | L34: =SUM(G34+I34+K34) -> 39717.79 | M34: =+M16 -> 1 | O34: =O16 -> 115.84355 | P34: =+P16 -> 115.84355 | Q34: =+Q16 -> 81 | Y34: =+Y16 -> 60
C35: Assistant Project Manager | D35: =$K$5 -> 8.5714286 | E35: wks | F35: =(40*P35)*M35 -> 4467.6124 | G35: =SUM(D35*F35) -> 38293.821 | L35: =SUM(G35+I35+K35) -> 38293.821 | M35: =+M17 -> 1 | O35: =O17 -> 111.69031 | P35: =+P17 -> 111.69031 | Q35: =+Q17 -> 118 | Y35: =+Y17 -> 95
C36: Superintendent - Level 3 | D36: =$K$5 -> 8.5714286 | E36: wks | F36: =(40*P36)*M36 -> 7114.6074 | G36: =SUM(D36*F36) -> 60982.349 | L36: =SUM(G36+I36+K36) -> 60982.349 | M36: =+M18 -> 1 | O36: =O18 -> 177.86518 | P36: =+P18 -> 177.86518 | Q36: =+Q18 -> 183 | Y36: =+Y18 -> 194
C37: Superintendent - Level 2 | D37: =$K$5 -> 8.5714286 | E37: wks | F37: =(40*P37)*M37 -> 0 | G37: =SUM(D37*F37) -> 0 | L37: =SUM(G37+I37+K37) -> 0 | M37: =+M19 -> 0 | O37: =O19 -> 149.29951 | P37: =+P19 -> 149.29951 | Q37: =+Q19 -> 161 | Y37: =+Y19 -> 173
C38: Superintendent - Level 1 | D38: =$K$5 -> 8.5714286 | E38: wks | F38: =(40*P38)*M38 -> 4887.7994 | G38: =SUM(D38*F38) -> 41895.424 | L38: =SUM(G38+I38+K38) -> 41895.424 | M38: =+M20 -> 1 | O38: =O20 -> 122.19499 | P38: =+P20 -> 122.19499 | Q38: =+Q20 -> 121 | Y38: =+Y20 -> 155
C39: Assistant Superinterndent | D39: =$K$5 -> 8.5714286 | E39: wks | F39: =(40*P39)*M39 -> 5823.7833 | G39: =SUM(D39*F39) -> 49918.142 | L39: =SUM(G39+I39+K39) -> 49918.142 | M39: =+M21 -> 1.8 | O39: =O21 -> 80.885879 | P39: =+P21 -> 80.885879 | Q39: =+Q21 -> 84 | Y39: =+Y21 -> 95
C40: Foreman | D40: =$K$5 -> 8.5714286 | E40: wks | F40: =(40*P40)*M40 -> 2242.5364 | G40: =SUM(D40*F40) -> 19221.741 | L40: =SUM(G40+I40+K40) -> 19221.741 | M40: =+M23 -> 1 | O40: =O23 -> 56.06341 | P40: =+P23 -> 56.06341 | Q40: =+Q23 -> 65 | Y40: =+Y23 -> 65
C41: Accounting | D41: =$K$5 -> 8.5714286 | E41: wks | F41: =(40*P41)*M41 -> 1252.1287 | G41: =SUM(D41*F41) -> 10732.532 | L41: =SUM(G41+I41+K41) -> 10732.532 | M41: =+M24 -> 0.2 | O41: =O24 -> 156.51609 | P41: =+P24 -> 156.51609 | Q41: =+Q24 -> 80 | Y41: =+Y24 -> 90
C42: VDC Manager | D42: =$K$5 -> 8.5714286 | E42: wks | F42: =(40*P42)*M42 -> 1386.8106 | G42: =SUM(D42*F42) -> 11886.948 | L42: =SUM(G42+I42+K42) -> 11886.948 | M42: =+M25 -> 0.25 | O42: =O25 -> 138.68106 | P42: =+P25 -> 138.68106 | Q42: =+Q25 -> 101 | Y42: =+Y25 -> 101
C43: Safety Supervisor/Inspector | D43: =$K$5 -> 8.5714286 | E43: wks | F43: =(40*P43)*M43 -> 1076.4086 | G43: =SUM(D43*F43) -> 9226.3592 | L43: =SUM(G43+I43+K43) -> 9226.3592 | M43: =+M26 -> 0.25 | O43: =O26 -> 107.64086 | P43: =+P26 -> 107.64086 | Q43: =+Q26 -> 96 | Y43: =+Y26 -> 96
C44: Field Office - Contractor | L44: =SUM(L45:L65) -> 186815
C45: Field Office Set Up / Removal - Double Wide | D45: 1 | E45: ea | H45: 16000 | I45: =SUM(D45*H45) -> 16000 | J45: ` | L45: =SUM(G45+I45+K45) -> 16000
C46: Field Office - Double Wide | D46: =$L$4 -> 22.3 | E46: mos | H46: 3500 | I46: =SUM(D46*H46) -> 78050 | L46: =SUM(G46+I46+K46) -> 78050
C47: Field Office Set Up / Removal - Single Wide | D47: 0 | E47: ea | H47: 15958 | I47: =SUM(D47*H47) -> 0 | L47: =SUM(G47+I47+K47) -> 0 | N47: WILLSCOT 4/16/2024 (36x10 mobile office)
C48: Field Office - Single Wide | D48: 0 | E48: mos | H48: 1732 | I48: =SUM(D48*H48) -> 0 | L48: =SUM(G48+I48+K48) -> 0 | N48: WILLSCOT 4/16/2024 (36x10 mobile office)
C49: Field Office Set Up / Removal - Connex | D49: 0 | E49: ea | H49: 1371 | I49: =SUM(D49*H49) -> 0 | L49: =SUM(G49+I49+K49) -> 0 | N49: WILLSCOT 20' COMBO W/10' OFFICE
C50: Field Office - Conex | D50: 0 | E50: mos | H50: 573 | I50: =SUM(D50*H50) -> 0 | L50: =SUM(G50+I50+K50) -> 0 | N50: WILLSCOT 20' COMBO W/10' OFFICE
C51: Connect Telephone Lines | D51: 1 | E51: ea | H51: 2000 | I51: =SUM(D51*H51) -> 2000 | L51: =SUM(G51+I51+K51) -> 2000
C52: Telephone | D52: =$L$4 -> 22.3 | E52: mos | H52: 250 | I52: =SUM(D52*H52) -> 5575 | L52: =SUM(G52+I52+K52) -> 5575
C53: Cellular Telephones | D53: =$L$4 -> 22.3 | E53: mos | H53: 0 | I53: =SUM(D53*H53) -> 0 | L53: =SUM(G53+I53+K53) -> 0 | N53: In labor rates
C54: Furniture | D54: 0 | E54: ls | H54: 500 | I54: =SUM(D54*H54) -> 0 | L54: =SUM(G54+I54+K54) -> 0
C55: Office Supplies | D55: =$L$4 -> 22.3 | E55: mos | H55: 100 | I55: =SUM(D55*H55) -> 2230 | L55: =SUM(G55+I55+K55) -> 2230
C56: Drinking Water | D56: =$L$4 -> 22.3 | E56: mos | H56: 50 | I56: =SUM(D56*H56) -> 1115 | L56: =SUM(G56+I56+K56) -> 1115
C57: Janitor Supplies/Cleaning | D57: =$L$4 -> 22.3 | E57: mos | H57: 250 | I57: =SUM(D57*H57) -> 5575 | L57: =SUM(G57+I57+K57) -> 5575
C58: Software Charge | D58: 0.0025 | E58: % | H58: 0 | I58: =SUM(D58*H58) -> 0 | L58: =SUM(G58+I58+K58) -> 0 | N58: .25% of GMP Total
C59: Computers | D59: 0 | E59: ls | H59: 0 | I59: =SUM(D59*H59) -> 0 | L59: =SUM(G59+I59+K59) -> 0
C60: Printers | D60: 2 | E60: ls | H60: 500 | I60: =SUM(D60*H60) -> 1000 | L60: =SUM(G60+I60+K60) -> 1000
C61: Copy Machine | D61: 1 | E61: ls | H61: 750 | I61: =SUM(D61*H61) -> 750 | L61: =SUM(G61+I61+K61) -> 750
C62: Alarm System | D62: =$L$4 -> 22.3 | E62: mos | H62: 0 | I62: =SUM(D62*H62) -> 0 | L62: =SUM(G62+I62+K62) -> 0
C63: Installation Office Equip. | D63: 0 | E63: ls | H63: 250 | I63: =SUM(D63*H63) -> 0 | L63: =SUM(G63+I63+K63) -> 0
C64: Storage Trailers Set Up / Removal | D64: 3 | E64: ea | H64: 840 | I64: =SUM(D64*H64) -> 2520 | L64: =SUM(G64+I64+K64) -> 2520 | N64: willscot 40' trailer
C65: Storage Trailers | D65: 20 | E65: mos | H65: 3600 | I65: =SUM(D65*H65) -> 72000 | L65: =SUM(G65+I65+K65) -> 72000 | N65: Rate - $1200 ea. per month
C66: Field Office - Owner | N66: =SUM(L67:L81) -> 0
C67: Field Office Set Up / Removal | D67: 1 | E67: ls | J67: 0 | K67: =SUM(D67*J67) -> 0 | L67: =SUM(G67+I67+K67) -> 0 | N67: assume not required
C68: Field Office | D68: =L4 -> 22.3 | E68: mos | J68: 0 | K68: =SUM(D68*J68) -> 0 | L68: =SUM(G68+I68+K68) -> 0 | N68: assume not required
C69: Connect Telephone Lines | D69: 1 | E69: ls | J69: 0 | K69: =SUM(D69*J69) -> 0 | L69: =SUM(G69+I69+K69) -> 0 | N69: assume not required
C70: Telephone | D70: =L4 -> 22.3 | E70: mos | J70: 0 | K70: =SUM(D70*J70) -> 0 | L70: =SUM(G70+I70+K70) -> 0 | N70: assume not required
C71: Cellular Telephones | D71: =L4+L5 -> 24.3 | E71: mos | J71: 0 | K71: =SUM(D71*J71) -> 0 | L71: =SUM(G71+I71+K71) -> 0 | N71: assume not required
C72: Furniture | D72: 1 | E72: ls | J72: 0 | K72: =SUM(D72*J72) -> 0 | L72: =SUM(G72+I72+K72) -> 0 | N72: assume not required
C73: Office Supplies | D73: =L4+L5 -> 24.3 | E73: mos | J73: 0 | K73: =SUM(D73*J73) -> 0 | L73: =SUM(G73+I73+K73) -> 0 | N73: assume not required
C74: Drinking Water | D74: =L4+L5 -> 24.3 | E74: mos | J74: 0 | K74: =SUM(D74*J74) -> 0 | L74: =SUM(G74+I74+K74) -> 0 | N74: assume not required
C75: Janitor Supplies | D75: =L4 -> 22.3 | E75: mos | J75: 0 | K75: =SUM(D75*J75) -> 0 | L75: =SUM(G75+I75+K75) -> 0 | N75: assume not required
C76: Computers | D76: 1 | E76: ls | J76: 0 | K76: =SUM(D76*J76) -> 0 | L76: =SUM(G76+I76+K76) -> 0 | N76: assume not required
C77: Printers | D77: 1 | E77: ls | J77: 0 | K77: =SUM(D77*J77) -> 0 | L77: =SUM(G77+I77+K77) -> 0 | N77: assume not required
C78: Copy Machine | D78: =L4+L5 -> 24.3 | E78: mos | J78: 0 | K78: =SUM(D78*J78) -> 0 | L78: =SUM(G78+I78+K78) -> 0 | N78: assume not required
C79: Fax Machine | D79: 1 | E79: ls | J79: 0 | K79: =SUM(D79*J79) -> 0 | L79: =SUM(G79+I79+K79) -> 0 | N79: assume not required
C80: Alarm System | D80: =L4 -> 22.3 | E80: mos | J80: 0 | K80: =SUM(D80*J80) -> 0 | L80: =SUM(G80+I80+K80) -> 0 | N80: assume not required
C81: Installation Office Equip. | D81: 1 | E81: ls | J81: 0 | K81: =SUM(D81*J81) -> 0 | L81: =SUM(G81+I81+K81) -> 0 | N81: assume not required
C82: Temporary Utilities | L82: =SUM(L83:L95) -> 132840
C83: Temp. Electrical Service | D83: 0 | E83: ls | J83: 5000 | K83: =SUM(D83*J83) -> 0 | L83: =SUM(G83+I83+K83) -> 0
C84: Temp. Electrical - Const. Phase | D84: =$L$4 -> 22.3 | E84: mos | J84: 1050 | K84: =SUM(D84*J84) -> 23415 | L84: =SUM(G84+I84+K84) -> 23415
C85: Temp. Electrical - Operate Phase | D85: =L4 -> 22.3 | E85: mos | J85: 0 | K85: =SUM(D85*J85) -> 0 | L85: =SUM(G85+I85+K85) -> 0
C86: Temp. Wiring & Lighting | D86: 0 | E86: sf | J86: 0 | K86: =SUM(D86*J86) -> 0 | L86: =SUM(G86+I86+K86) -> 0
C87: Temporary Water - Service | D87: 1 | E87: ls | J87: 3500 | K87: =SUM(D87*J87) -> 3500 | L87: =SUM(G87+I87+K87) -> 3500
C88: Temporary Water | D88: =L4 -> 22.3 | E88: mos | J88: 150 | K88: =SUM(D88*J88) -> 3345 | L88: =SUM(G88+I88+K88) -> 3345
C89: Temporary Toilets | D89: =L4 -> 22.3 | E89: mos | J89: =410*10 -> 4100 | K89: =SUM(D89*J89) -> 91430 | L89: =SUM(G89+I89+K89) -> 91430
C90: Temporary Toilet Set Up / Removal | D90: 0 | E90: ea | J90: 100 | K90: =SUM(D90*J90) -> 0 | L90: =SUM(G90+I90+K90) -> 0
C91: Temporary Washing Station | D91: 0 | E91: mos | J91: =2*410 -> 820 | K91: =SUM(D91*J91) -> 0 | L91: =SUM(G91+I91+K91) -> 0
C92: Temporary Washing Station Set Up / Removal | D92: 0 | E92: ea | J92: 100 | K92: =SUM(D92*J92) -> 0 | L92: =SUM(G92+I92+K92) -> 0
C93: Temporary Holding Tanks | D93: =L4 -> 22.3 | E93: mos | J93: 500 | K93: =SUM(D93*J93) -> 11150 | L93: =SUM(G93+I93+K93) -> 11150
C94: Temporary Ventilation | D94: 0 | E94: ls | J94: 0 | K94: =SUM(D94*J94) -> 0 | L94: =SUM(G94+I94+K94) -> 0
C95: Temporary Cooling | D95: =L4 -> 22.3 | E95: mos | J95: 0 | K95: =SUM(D95*J95) -> 0 | L95: =SUM(G95+I95+K95) -> 0
C96: Equipment | L96: =SUM(L97:L99) -> 72475
C97: Small Tools | D97: =$L$4 -> 22.3 | E97: mos | J97: 750 | K97: =SUM(D97*J97) -> 16725 | L97: =SUM(G97+I97+K97) -> 16725
C98: Equipment Rental | D98: =L4 -> 22.3 | E98: mos | J98: 2500 | K98: =SUM(D98*J98) -> 55750 | L98: =SUM(G98+I98+K98) -> 55750
C99: Engineering Instruments | D99: 0 | E99: ls | J99: 1000 | K99: =SUM(D99*J99) -> 0 | L99: =SUM(G99+I99+K99) -> 0
C100: Security | L100: =SUM(L101:L118) -> 23571.7
B101: 15000 | C101: Temporary Fence - 6' Post Driven w/ windscreen | D101: 1774 | E101: lf | J101: 8.3 | K101: =J101*D101 -> 14724.2 | L101: =SUM(G101+I101+K101) -> 14724.2
...

Sheet Labor Rates
A3: RE: West Melbourne Water Treatment Plant
A5: Hedrick Brothers Construction Co., Inc.
A6: Salaries and Burden Calculations
A7: As of 8/22/24
C8: MARK-UP | F8: 0.35
E9: Burdened Rate | F9: Mark-up | G9: Total
B10: 1 | C10: Proj Exec | E10: 157.66656 | F10: =E10*$F$8 -> 55.183297 | G10: =SUM(E10:F10) -> 212.84986
B11: 2 | C11: Sr PM | E11: 130.67475 | F11: =E11*$F$8 -> 45.736162 | G11: =SUM(E11:F11) -> 176.41091
B12: 3 | C12: PM 3 | E12: 120.34132 | F12: =E12*$F$8 -> 42.119463 | G12: =SUM(E12:F12) -> 162.46079
B13: 4 | C13: PM 2 | E13: 110.14476 | F13: =E13*$F$8 -> 38.550666 | G13: =SUM(E13:F13) -> 148.69542
B14: 5 | C14: PM 1 | E14: 94.265604 | F14: =E14*$F$8 -> 32.992961 | G14: =SUM(E14:F14) -> 127.25857
B15: 6 | C15: Proj Admin | E15: 66.505247 | F15: =E15*$F$8 -> 23.276836 | G15: =SUM(E15:F15) -> 89.782084
B16: 7 | C16: Proj Acct | E16: 85.81004 | F16: =E16*$F$8 -> 30.033514 | G16: =SUM(E16:F16) -> 115.84355
B17: 8 | C17: Asst PM | E17: 82.733564 | F17: =E17*$F$8 -> 28.956747 | G17: =SUM(E17:F17) -> 111.69031
B18: 9 | C18: Supt 3 | E18: 131.75199 | F18: =E18*$F$8 -> 46.113196 | G18: =SUM(E18:F18) -> 177.86518
B19: 10 | C19: Supt 2 | E19: 110.59223 | F19: =E19*$F$8 -> 38.70728 | G19: =SUM(E19:F19) -> 149.29951
B20: 11 | C20: Supt 1 | E20: 90.514804 | F20: =E20*$F$8 -> 31.680182 | G20: =SUM(E20:F20) -> 122.19499
B21: 12 | C21: Asst Supt | E21: 59.915466 | F21: =E21*$F$8 -> 20.970413 | G21: =SUM(E21:F21) -> 80.885879
... B26: 17 | C26: Safety | E26: 79.733968 | F26: =E26*$F$8 -> 27.906889 | G26: =SUM(E26:F26) -> 107.64086
C27: Labor | E27: 32.408056 | F27: =E27*$F$8 -> 11.34282 | G27: =SUM(E27:F27) -> 43.750875
C28: Apprentice | E28: 32.978211 | F28: =E28*$F$8 -> 11.542374 | G28: =SUM(E28:F28) -> 44.520584
C29: Carpenter | E29: 45.013251 | F29: =E29*$F$8 -> 15.754638 | G29: =SUM(E29:F29) -> 60.767889
C30: Driver | E30: 35.486876 | F30: =E30*$F$8 -> 12.420407 | G30: =SUM(E30:F30) -> 47.907283
C31: Leadman | E31: 46.605242 | F31: =E31*$F$8 -> 16.311835 | G31: =SUM(E31:F31) -> 62.917077
C32: Supt MEP | E32: 0 | F32: =E32*$F$8 -> 0 | G32: =SUM(E32:F32) -> 0
C33: Gen Supt | E33: 130.4108 | F33: =E33*$F$8 -> 45.643781 | G33: =SUM(E33:F33) -> 176.05459
C34: Cons Mgr | E34: 135.45804 | F34: =E34*$F$8 -> 47.410313 | G34: =SUM(E34:F34) -> 182.86835
C35: Proj Coor | E35: 0 | F35: =E35*$F$8 -> 0 | G35: =SUM(E35:F35) -> 0
C36: Mktg | E36: 85.41309 | F36: =E36*$F$8 -> 29.894582 | G36: =SUM(E36:F36) -> 115.30767
C37: Bus Dev | E37: 121.55329 | F37: =E37*$F$8 -> 42.543651 | G37: =SUM(E37:F37) -> 164.09694
C38: Chief, 3 & 2 | E38: 140.9198 | F38: =E38*$F$8 -> 49.321931 | G38: =SUM(E38:F38) -> 190.24173
... C40: Exec Asst | E40: 69.670191 | F40: =E40*$F$8 -> 24.384567 | G40: =SUM(E40:F40) -> 94.054759

Sheet 02 21 Survey 
G1: Hedrick Plug
F2: X | G2: Excluded
F3: I | G3: Included
B4: BACK TO SUMMARY SHEET | G4: Sub Add/Deduct
A5: Project: | B5: ='Area Calculations'!B4 -> Bourbon Hotel Orlando | G5: Company
A6: Trade: | B6: Surveying | G6: Contact
A7: CSI Code: | B7: 02 21 00 | G7: Phone
A8: Date: | G8: Email
G9: Adjusted Bid | H9: =I55 -> 60117 | J9: =K59 -> 0 | L9: =M59 -> 0 | N9: =O59 -> 0 | P9: =Q59 -> 0 | R9: =S59 -> 0
A10: BID DOCUMENTS: | C10: Plan/ Spec. Package | D10: QTY | E10: U/M | F10: Unit Cost | G10: Subtotal | H10: Yes/No | I10: Price | J10: Yes/No | K10: Price | L10: Yes/No | M10: Price | N10: Yes/No | O10: Price | P10: Yes/No | Q10: Price | R10: Yes/No | S10: Price
B11: GENERAL INCLUSIONS
B12: INCLUDES ALL SALES TAX
B13: ALL HOISTING & RIGGING REQUIRED TO COMPLETE THIS SCOPE
B14: PROVIDE P&P BONDS
B15: FLORIDA STATE CONTRACTORS LIC.
B16: GENERAL LIABILITY AND WORKERS COMP. INSURANCE LIMITS
B17: STATE AND LOCAL TAXES
B18: SPECIFIC TRADE SCOPE OF WORK REQUIREMENTS
B19: BASE BID
B21: Surveying | D21: ='Area Calculations'!G7 -> 4.0078283 | E21: acre | F21: 15000 | G21: =ROUND(D21*F21,0) -> 60117 | I21: =G21 -> 60117
G22: =ROUND(D22*F22,0) -> 0
G23: =ROUND(D23*F23,0) -> 0
G24: =ROUND(D24*F24,0) -> 0
G25: =ROUND(D25*F25,0) -> 0
G26: =ROUND(D26*F26,0) -> 0
G27: =ROUND(D27*F27,0) -> 0
G28: =ROUND(D28*F28,0) -> 0
G29: =ROUND(D29*F29,0) -> 0
G30: =ROUND(D30*F30,0) -> 0
G31: =ROUND(D31*F31,0) -> 0
G32: =ROUND(D32*F32,0) -> 0
G33: =ROUND(D33*F33,0) -> 0
... G49: =ROUND(D49*F49,0) -> 0
B51: SUBTOTAL | G51: =SUM(G19:G50) -> 60117 | I51: =SUBTOTAL(9,I21:I49) -> 60117 | K51: =SUBTOTAL(9,K21:K49) -> 0 | M51: =SUM(M19:M50) -> 0 | O51: =SUM(O19:O50) -> 0 | Q51: =SUM(Q19:Q50) -> 0 | S51: =SUM(S19:S50) -> 0
B52: BOND RATE | H52: 0 | J52: 0 | L52: 0 | N52: 0 | P52: 0 | R52: 0
B53: BOND AMOUNT | G53: =F52*G51 -> 0 | I53: =H52*I51 -> 0 | K53: =J52*K51 -> 0 | M53: =L52*M51 -> 0 | O53: =N52*O51 -> 0 | Q53: =P52*Q51 -> 0 | S53: =R52*S51 -> 0
B55: ADJUSTED TOTAL | G55: =SUM(G51:G53) -> 60117 | I55: =SUM(I51:I53) -> 60117 | K55: =SUM(K51:K53) -> 0 | M55: =SUM(M51:M53) -> 0 | O55: =SUM(O51:O53) -> 0 | Q55: =SUM(Q51:Q53) -> 0 | S55: =SUM(S51:S53) -> 0
B56: Cost per SF | G56: =G55/'Area Calculations'!$G$5 -> 0.1544142 | I56: =I55/'Area Calculations'!$G$5 -> 0.1544142 | K56: =K55/'Area Calculations'!$G$5 -> 0 | M56: =M55/'Area Calculations'!$G$5 -> 0 | O56: =O55/'Area Calculations'!$G$5 -> 0 | Q56: =Q55/'Area Calculations'!$G$5 -> 0 | S56: =S55/'Area Calculations'!$G$5 -> 0
A58: QUALIFICATIONS
A62: EXCLUSIONS/OWNER PROVIDED ITEMS:
A66: ALTERNATES:
A70: PROPOSED VE (Provide Clear Description):
A74: FULLY LOADED LABOR RATES
B75: Laborer
B76: Mechanic
B77: Superintendent
B78: Project Manager
A80: SCHEDULE
B81: Prepared shop drawings/submittals
B82: Mobilization
B83: Total duration to complete scope of work
A85: Winner
A86: Company
A87: Contact
A88: Phone
A89: Email
A90: Base Bid | B90: =$I$55 -> 60117
B92: Need Prequalification
B93: Prequalified

Sheet 02 41 Demo
G1: Hedrick Plug
F2: X | G2: Excluded
F3: I | G3: Included
B4: BACK TO SUMMARY SHEET | G4: Sub Add/Deduct
A5: Project: | B5: ='Area Calculations'!B4 -> Bourbon Hotel Orlando | G5: Company
A6: Trade: | B6: Demolition | G6: Contact
A7: CSI Code: | B7: 02 41 00 | G7: Phone
A8: Date: | G8: Email
G9: Adjusted Bid | H9: =I55 -> 0 | J9: =K59 -> 0 | L9: =M59 -> 0 | N9: =O59 -> 0 | P9: =Q59 -> 0 | R9: =S59 -> 0
A10: BID DOCUMENTS: | C10: Plan/ Spec. Package | D10: QTY | E10: U/M | F10: Unit Cost | G10: Subtotal | H10: Yes/No | I10: Price | J10: Yes/No | K10: Price | L10: Yes/No | M10: Price | N10: Yes/No | O10: Price | P10: Yes/No | Q10: Price | R10: Yes/No | S10: Price
B11: GENERAL INCLUSIONS
B12: INCLUDES ALL SALES TAX
B13: ALL HOISTING & RIGGING REQUIRED TO COMPLETE THIS SCOPE
B14: PROVIDE P&P BONDS
B15: FLORIDA STATE CONTRACTORS LIC.
B16: GENERAL LIABILITY AND WORKERS COMP. INSURANCE LIMITS
B17: STATE AND LOCAL TAXES
B18: SPECIFIC TRADE SCOPE OF WORK REQUIREMENTS
B19: BASE BID
G21: =ROUND(D21*F21,0) -> 0
G22: =ROUND(D22*F22,0) -> 0
G23: =ROUND(D23*F23,0) -> 0
G24: =ROUND(D24*F24,0) -> 0
G25: =ROUND(D25*F25,0) -> 0
G26: =ROUND(D26*F26,0) -> 0
G27: =ROUND(D27*F27,0) -> 0
G28: =ROUND(D28*F28,0) -> 0
G29: =ROUND(D29*F29,0) -> 0
G30: =ROUND(D30*F30,0) -> 0
G31: =ROUND(D31*F31,0) -> 0
G32: =ROUND(D32*F32,0) -> 0
... G49: =ROUND(D49*F49,0) -> 0
B51: SUBTOTAL | G51: =SUM(G19:G50) -> 0 | I51: =SUBTOTAL(9,I21:I49) -> 0 | K51: =SUBTOTAL(9,K21:K49) -> 0 | M51: =SUM(M19:M50) -> 0 | O51: =SUM(O19:O50) -> 0 | Q51: =SUM(Q19:Q50) -> 0 | S51: =SUM(S19:S50) -> 0
B52: BOND RATE | H52: 0 | J52: 0 | L52: 0 | N52: 0 | P52: 0 | R52: 0
B53: BOND AMOUNT | G53: =F52*G51 -> 0 | I53: =H52*I51 -> 0 | K53: =J52*K51 -> 0 | M53: =L52*M51 -> 0 | O53: =N52*O51 -> 0 | Q53: =P52*Q51 -> 0 | S53: =R52*S51 -> 0
B55: ADJUSTED TOTAL | G55: =SUM(G51:G53) -> 0 | I55: =SUM(I51:I53) -> 0 | K55: =SUM(K51:K53) -> 0 | M55: =SUM(M51:M53) -> 0 | O55: =SUM(O51:O53) -> 0 | Q55: =SUM(Q51:Q53) -> 0 | S55: =SUM(S51:S53) -> 0
B56: Cost per SF | G56: =G55/'Area Calculations'!$G$5 -> 0 | I56: =I55/'Area Calculations'!$G$5 -> 0 | K56: =K55/'Area Calculations'!$G$5 -> 0 | M56: =M55/'Area Calculations'!$G$5 -> 0 | O56: =O55/'Area Calculations'!$G$5 -> 0 | Q56: =Q55/'Area Calculations'!$G$5 -> 0 | S56: =S55/'Area Calculations'!$G$5 -> 0
A58: QUALIFICATIONS
A62: EXCLUSIONS/OWNER PROVIDED ITEMS:
A66: ALTERNATES:
A70: PROPOSED VE (Provide Clear Description):
A74: FULLY LOADED LABOR RATES
B75: Laborer
B76: Mechanic
B77: Superintendent
B78: Project Manager
A80: SCHEDULE
B81: Prepared shop drawings/submittals
B82: Mobilization
B83: Total duration to complete scope of work
A85: Winner
A86: Company
A87: Contact
A88: Phone
A89: Email
A90: Base Bid | B90: =$I$55 -> 0
B92: Need Prequalification
B93: Prequalified

Sheet 03 30 Conc & CMU
G1: Hedrick Plug
F2: X | G2: Excluded
F3: I | G3: Included
B4: BACK TO SUMMARY SHEET | G4: Sub Add/Deduct
A5: Project: | B5: ='Area Calculations'!B4 -> Bourbon Hotel Orlando | G5: Company
A6: Trade: | B6: Concrete & CMU | G6: Contact
A7: CSI Code: | B7: 03 30 00 | G7: Phone
A8: Date: | G8: Email
G9: Adjusted Bid | H9: =I$67 -> 33000765 | J9: =K$67 -> 16240695 | L9: =M$67 -> 128 | N9: =O$67 -> 260527.41 | P9: =Q$67 -> 0 | R9: =S$67 -> 0
A10: BID DOCUMENTS: | C10: Plan/ Spec. Package | D10: QTY | E10: U/M | F10: Unit Cost | G10: Subtotal | H10: Yes/No | I10: Price | J10: Yes/No | K10: Price | L10: Yes/No | M10: Price | N10: Yes/No | O10: Price | P10: Yes/No | Q10: Price | R10: Yes/No | S10: Price
B11: GENERAL INCLUSIONS
B12: INCLUDES ALL SALES TAX
B13: ALL HOISTING & RIGGING REQUIRED TO COMPLETE THIS SCOPE
B14: PROVIDE P&P BONDS
B15: FLORIDA STATE CONTRACTORS LIC.
B16: GENERAL LIABILITY AND WORKERS COMP. INSURANCE LIMITS
B17: STATE AND LOCAL TAXES
B18: SPECIFIC TRADE SCOPE OF WORK REQUIREMENTS
B19: BASE BID
B21: Concrete
B22: 10' x 24" continuios footings at periniter walls | D22: =1514*10*2/27 -> 1121.4815 | E22: cy | F22: 650 | G22: =ROUND(D22*F22,0) -> 728963 | I22: =G22 -> 728963
A23: 130 | B23: 10' x 10' x 24" spread footings at columns - 30' oc ew | D23: =10*10*2*130/27 -> 962.96296 | E23: cy | F23: 650 | G23: =ROUND(D23*F23,0) -> 625926 | I23: =G23 -> 625926
A24: 130 | B24: 24" x 24" columns at garage level - 30' oc ew | D24: =2*2*15*130/27 -> 288.88889 | E24: cy | F24: 2500 | G24: =ROUND(D24*F24,0) -> 722222 | I24: =G24 -> 722222
B25: Pad footings at stairs & elevators - 24" | D25: =4034*2/27 -> 298.81481 | E25: cy | F25: 660 | G25: =ROUND(D25*F25,0) -> 197218 | I25: =G25 -> 197218 | K25: =D25 -> 298.81481 | L25: cy | M25: 32 | O25: =K25*M25 -> 9562.0741
B26: Elevator pit walls | D26: 38 | E26: cy | F26: 1500 | G26: =ROUND(D26*F26,0) -> 57000 | I26: =G26 -> 57000 | K26: =D26 -> 38 | L26: cy | M26: 32 | O26: =K26*M26 -> 1216
B27: Garage level walls 12" thick - 15' | D27: =1514*15*2/27 -> 1682.2222 | E27: cy | F27: 1500 | G27: =ROUND(D27*F27,0) -> 2523333 | I27: =G27 -> 2523333 | K27: =D27 -> 1682.2222 | L27: cy | M27: 32 | O27: =K27*M27 -> 53831.111
A28: =304+230 -> 534 | B28: Garage level stairwell and elevator shaft walls - 12" | D28: =534*15/27 -> 296.66667 | E28: cy | F28: 1500 | G28: =ROUND(D28*F28,0) -> 445000 | I28: =G28 -> 445000
B29: Podium deck - 16" PT | D29: 110792 | E29: sf | F29: 45 | G29: =ROUND(D29*F29,0) -> 4985640 | I29: =G29 -> 4985640 | K29: =D29*1.33/27 -> 5457.5319 | L29: cy
B30: Slab on grade - 6" | D30: 110792 | E30: sf | F30: 12 | G30: =ROUND(D30*F30,0) -> 1329504 | I30: =G30 -> 1329504 | K30: =D30*0.5/27 -> 2051.7037 | L30: cy | M30: 32 | O30: =K30*M30 -> 65654.519
B31: Slab on metal deck - 5" | D31: =280266 -> 280266 | E31: sf | F31: 8 | G31: =ROUND(D31*F31,0) -> 2242128 | I31: =G31 -> 2242128 | K31: =D31*0.42/27 -> 4359.6933 | L31: cy
G32: =ROUND(D32*F32,0) -> 0 | I32: =G32 -> 0 | O32: =SUM(O25:O31) -> 130263.7
B33: total cy | D33: =SUM(D22:D28)+SUM(K29:K31) -> 16557.966 | E33: cy | F33: 980 | G33: =ROUND(D33*F33,0) -> 16226807 | I33: =G33 -> 16226807 | K33: =D33*F33 -> 16226807
G34: =ROUND(D34*F34,0) -> 0 | I34: =G34 -> 0
B35: Topping slab on podium deck | D35: 110792 | E35: sf | F35: 15 | G35: =ROUND(D35*F35,0) -> 1661880 | I35: =G35 -> 1661880
G36: =ROUND(D36*F36,0) -> 0 | I36: =G36 -> 0
B37: CMU - Hotel | G37: =ROUND(D37*F37,0) -> 0 | I37: =G37 -> 0
A38: 83'-6" | B38: stairwells - 8" | D38: =174*83.5 -> 14529 | E38: sf | F38: 20 | G38: =ROUND(D38*F38,0) -> 290580 | I38: =G38 -> 290580
A39: 83'-6" | B39: elevator shafts - 8" | D39: =257*83.5 -> 21459.5 | E39: sf | F39: 20 | G39: =ROUND(D39*F39,0) -> 429190 | I39: =G39 -> 429190
G40: =ROUND(D40*F40,0) -> 0 | I40: =G40 -> 0
B41: CMU - Restaurant | G41: =ROUND(D41*F41,0) -> 0 | I41: =G41 -> 0
A42: 36'-10" | B42: stairwells - 8" | D42: =55*36.83 -> 2025.65 | E42: sf | F42: 20 | G42: =ROUND(D42*F42,0) -> 40513 | I42: =G42 -> 40513
A43: 36'-10" | B43: elevator shafts - 8" | D43: =47*36.83 -> 1731.01 | E43: sf | F43: 20 | G43: =ROUND(D43*F43,0) -> 34620 | I43: =G43 -> 34620
G44: =ROUND(D44*F44,0) -> 0 | I44: =G44 -> 0
G45: =ROUND(D45*F45,0) -> 0 | I45: =G45 -> 0
B46: Pool Deck | G46: =ROUND(D46*F46,0) -> 0 | I46: =G46 -> 0
B47: added columns at pool & spa | D47: =10*10*2*10/27 -> 74.074074 | E47: cy | F47: 650 | G47: =ROUND(D47*F47,0) -> 48148 | I47: =G47 -> 48148
B48: added column footings at pool & spa | D48: =2*2*15*10/27 -> 22.222222 | E48: cy | F48: 650 | G48: =ROUND(D48*F48,0) -> 14444 | I48: =G48 -> 14444
B49: pool & deck perimiter walls - 8" to 5' | D49: 132 | E49: cy | F49: 1500 | G49: =ROUND(D49*F49,0) -> 198000 | I49: =G49 -> 198000
B50: geofoam fill | D50: =(12272-2404-123)*5/27 -> 1804.6296 | E50: cy | F50: 75 | G50: =ROUND(D50*F50,0) -> 135347 | I50: =G50 -> 135347
B52: landscape curb - 6" to 12" | D52: =2136*1*0.5/27 -> 39.555556 | E52: cy | F52: 650 | G52: =ROUND(D52*F52,0) -> 25711 | I52: =G52 -> 25711
B53: water feature curb - 6" to 12" | D53: =3206*1*0.5/27 -> 59.37037 | E53: cy | F53: 650 | G53: =ROUND(D53*F53,0) -> 38591 | I53: =G53 -> 38591
G54: =ROUND(D54*F54,0) -> 0 | I54: =G54 -> 0
G55: =ROUND(D55*F55,0) -> 0 | I55: =G55 -> 0
G56: =ROUND(D56*F56,0) -> 0 | I56: =G56 -> 0
G57: =ROUND(D57*F57,0) -> 0 | I57: =G57 -> 0
G58: =ROUND(D58*F58,0) -> 0 | I58: =G58 -> 0
G59: =ROUND(D59*F59,0) -> 0 | I59: =G59 -> 0
G60: =ROUND(D60*F60,0) -> 0 | I60: =G60 -> 0
G61: =ROUND(D61*F61,0) -> 0 | I61: =G61 -> 0
B63: SUBTOTAL Base Bid | G63: =SUBTOTAL(9,G27:G62) -> 30669436 | I63: =SUBTOTAL(9,I20:I62) -> 33000765 | K63: =SUBTOTAL(9,K20:K62) -> 16240695 | M63: =SUBTOTAL(9,M20:M62) -> 128 | O63: =SUBTOTAL(9,O20:O62) -> 260527.41 | Q63: =SUBTOTAL(9,Q20:Q62) -> 0 | S63: =SUBTOTAL(9,S20:S62) -> 0
B64: BOND RATE | H64: 0 | J64: 0 | L64: 0 | N64: 0 | P64: 0 | R64: 0
B65: BOND AMOUNT | G65: =F64*G63 -> 0 | I65: =H64*I63 -> 0 | K65: =J64*K63 -> 0 | M65: =L64*M63 -> 0 | O65: =N64*O63 -> 0 | Q65: =P64*Q63 -> 0 | S65: =R64*S63 -> 0
B67: ADJUSTED TOTAL | G67: =SUM(G63:G65) -> 30669436 | I67: =SUM(I63:I65) -> 33000765 | K67: =SUM(K63:K65) -> 16240695 | M67: =SUM(M63:M65) -> 128 | O67: =SUM(O63:O65) -> 260527.41 | Q67: =SUM(Q63:Q65) -> 0 | S67: =SUM(S63:S65) -> 0
B68: Cost per SF | G68: =G67/'Area Calculations'!$G$5 -> 78.776327 | I68: =I67/'Area Calculations'!$G$5 -> 84.764489 | K68: =K67/'Area Calculations'!$G$5 -> 41.71522 | M68: =M67/'Area Calculations'!$G$5 -> 0.00032877585 | O68: =O67/'Area Calculations'!$G$5 -> 0.66918062 | Q68: =Q67/'Area Calculations'!$G$5 -> 0 | S68: =S67/'Area Calculations'!$G$5 -> 0
A70: QUALIFICATIONS
A74: EXCLUSIONS/OWNER PROVIDED ITEMS:
A78: ALTERNATES:
A82: PROPOSED VE (Provide Clear Description):
A86: FULLY LOADED LABOR RATES
B87: Laborer
B88: Mechanic
B89: Superintendent
B90: Project Manager
A92: SCHEDULE
B93: Prepared shop drawings/submittals
B94: Mobilization
B95: Total duration to complete scope of work
A97: Winner
A98: Company
A99: Contact
A100: Phone
A101: Email
A102: Base Bid | B102: =K$67 -> 16240695
B104: Need Prequalification
B105: Prequalified

Sheet 04 40 Stone Cladding
G1: Hedrick Plug
F2: X | G2: Excluded
F3: I | G3: Included
B4: BACK TO SUMMARY SHEET | G4: Sub Add/Deduct
A5: Project: | B5: ='Area Calculations'!B4 -> Bourbon Hotel Orlando | G5: Company
A6: Trade: | B6: Stone Cladding | G6: Contact
A7: CSI Code: | B7: 04 40 00 | G7: Phone
A8: Date: | G8: Email
G9: Adjusted Bid | H9: =I$55 -> 132072 | J9: =K$55 -> 0 | L9: =M$55 -> 0 | N9: =O$55 -> 0 | P9: =Q$55 -> 0 | R9: =S$55 -> 0
A10: BID DOCUMENTS: | C10: Plan/ Spec. Package | D10: QTY | E10: U/M | F10: Unit Cost | G10: Subtotal | H10: Yes/No | I10: Price | J10: Yes/No | K10: Price | L10: Yes/No | M10: Price | N10: Yes/No | O10: Price | P10: Yes/No | Q10: Price | R10: Yes/No | S10: Price
B11: GENERAL INCLUSIONS
B12: INCLUDES ALL SALES TAX
B13: ALL HOISTING & RIGGING REQUIRED TO COMPLETE THIS SCOPE
B14: PROVIDE P&P BONDS
B15: FLORIDA STATE CONTRACTORS LIC.
B16: GENERAL LIABILITY AND WORKERS COMP. INSURANCE LIMITS
B17: STATE AND LOCAL TAXES
B18: SPECIFIC TRADE SCOPE OF WORK REQUIREMENTS
B19: BASE BID
B21: Stone cladding - assume coral stone - material | D21: =2567*1.15 -> 2952.05 | E21: sf | F21: 23 | G21: =ROUND(D21*F21,0) -> 67897 | I21: =G21 -> 67897
B22: Stone cladding - assume coral stone - labor | D22: 2567 | E22: sf | F22: 25 | G22: =ROUND(D22*F22,0) -> 64175 | I22: =G22 -> 64175
G23: =ROUND(D23*F23,0) -> 0
G24: =ROUND(D24*F24,0) -> 0
G25: =ROUND(D25*F25,0) -> 0
G26: =ROUND(D26*F26,0) -> 0
G27: =ROUND(D27*F27,0) -> 0
G28: =ROUND(D28*F28,0) -> 0
G29: =ROUND(D29*F29,0) -> 0
G30: =ROUND(D30*F30,0) -> 0
G31: =ROUND(D31*F31,0) -> 0
G32: =ROUND(D32*F32,0) -> 0
G33: =ROUND(D33*F33,0) -> 0
G34: =ROUND(D34*F34,0) -> 0
... G49: =ROUND(D49*F49,0) -> 0
B51: SUBTOTAL Base Bid | G51: =SUBTOTAL(9,G21:G50) -> 132072 | I51: =SUBTOTAL(9,I21:I50) -> 132072 | K51: =SUBTOTAL(9,K21:K50) -> 0 | M51: =SUBTOTAL(9,M21:M50) -> 0 | O51: =SUBTOTAL(9,O21:O50) -> 0 | Q51: =SUBTOTAL(9,Q21:Q50) -> 0 | S51: =SUBTOTAL(9,S21:S50) -> 0
B52: BOND RATE | H52: 0 | J52: 0 | L52: 0 | N52: 0 | P52: 0 | R52: 0
B53: BOND AMOUNT | G53: =F52*G51 -> 0 | I53: =H52*I51 -> 0 | K53: =J52*K51 -> 0 | M53: =L52*M51 -> 0 | O53: =N52*O51 -> 0 | Q53: =P52*Q51 -> 0 | S53: =R52*S51 -> 0
B55: ADJUSTED TOTAL | G55: =SUM(G51:G53) -> 132072 | I55: =SUM(I51:I53) -> 132072 | K55: =SUM(K51:K53) -> 0 | M55: =SUM(M51:M53) -> 0 | O55: =SUM(O51:O53) -> 0 | Q55: =SUM(Q51:Q53) -> 0 | S55: =SUM(S51:S53) -> 0
B56: Cost per SF | G56: =G55/'Area Calculations'!$G$5 -> 0.33923503 | I56: =I55/'Area Calculations'!$G$5 -> 0.33923503 | K56: =K55/'Area Calculations'!$G$5 -> 0 | M56: =M55/'Area Calculations'!$G$5 -> 0 | O56: =O55/'Area Calculations'!$G$5 -> 0 | Q56: =Q55/'Area Calculations'!$G$5 -> 0 | S56: =S55/'Area Calculations'!$G$5 -> 0
A58: QUALIFICATIONS
A62: EXCLUSIONS/OWNER PROVIDED ITEMS:
A66: ALTERNATES:
A70: PROPOSED VE (Provide Clear Description):
A74: FULLY LOADED LABOR RATES
B75: Laborer
B76: Mechanic
B77: Superintendent
B78: Project Manager
A80: SCHEDULE
B81: Prepared shop drawings/submittals
B82: Mobilization
B83: Total duration to complete scope of work
A85: Winner
A86: Company
A87: Contact
A88: Phone
A89: Email
A90: Base Bid | B90: =K$55 -> 0
B92: Need Prequalification
B93: Prequalified

Sheet 05 10 Structural Steel
G1: Hedrick Plug
F2: X | G2: Excluded
F3: I | G3: Included
B4: BACK TO SUMMARY SHEET | G4: Sub Add/Deduct
A5: Project: | B5: ='Area Calculations'!B4 -> Bourbon Hotel Orlando | G5: Company
A6: Trade: | B6: Structural Steel | G6: Contact
A7: CSI Code: | B7: 05 10 00 | G7: Phone
A8: Date: | G8: Email
G9: Adjusted Bid | H9: =I$55 -> 11299290 | J9: =K$55 -> 0 | L9: =M$55 -> 0 | N9: =O$55 -> 0 | P9: =Q$55 -> 0 | R9: =S$55 -> 0
A10: BID DOCUMENTS: | C10: Plan/ Spec. Package | D10: QTY | E10: U/M | F10: Unit Cost | G10: Subtotal | H10: Yes/No | I10: Price | J10: Yes/No | K10: Price | L10: Yes/No | M10: Price | N10: Yes/No | O10: Price | P10: Yes/No | Q10: Price | R10: Yes/No | S10: Price
B11: GENERAL INCLUSIONS
B12: INCLUDES ALL SALES TAX
B13: ALL HOISTING & RIGGING REQUIRED TO COMPLETE THIS SCOPE
B14: PROVIDE P&P BONDS
B15: FLORIDA STATE CONTRACTORS LIC.
B16: GENERAL LIABILITY AND WORKERS COMP. INSURANCE LIMITS
B17: STATE AND LOCAL TAXES
B18: SPECIFIC TRADE SCOPE OF WORK REQUIREMENTS
B19: BASE BID
B21: Steel frame structure ground level and up | D21: =SUM('Area Calculations'!E15:E20) -> 277214 | E21: sf | F21: 35 | G21: =ROUND(D21*F21,0) -> 9702490 | I21: =G21 -> 9702490
G22: =ROUND(D22*F22,0) -> 0 | I22: =G22 -> 0
B23: Porte Cochere | D23: 3420 | E23: sf | F23: 20 | G23: =ROUND(D23*F23,0) -> 68400 | I23: =G23 -> 68400
G24: =ROUND(D24*F24,0) -> 0 | I24: =G24 -> 0
B25: Bridge structure | D25: 1 | E25: ls | F25: 716900 | G25: =ROUND(D25*F25,0) -> 716900 | I25: =G25 -> 716900
G26: =ROUND(D26*F26,0) -> 0 | I26: =G26 -> 0
B27: Steel columns for canopies - material | D27: 1082 | E27: lf | F27: =150/2000*10000 -> 750 | G27: =ROUND(D27*F27,0) -> 811500 | I27: =G27 -> 811500
G28: =ROUND(D28*F28,0) -> 0 | I28: =G28 -> 0
G29: =ROUND(D29*F29,0) -> 0 | I29: =G29 -> 0
G30: =ROUND(D30*F30,0) -> 0 | I30: =G30 -> 0
G31: =ROUND(D31*F31,0) -> 0 | I31: =G31 -> 0
G32: =ROUND(D32*F32,0) -> 0 | I32: =G32 -> 0
G33: =ROUND(D33*F33,0) -> 0 | I33: =G33 -> 0
G34: =ROUND(D34*F34,0) -> 0 | I34: =G34 -> 0
G35: =ROUND(D35*F35,0) -> 0 | I35: =G35 -> 0
G36: =ROUND(D36*F36,0) -> 0 | I36: =G36 -> 0
G37: =ROUND(D37*F37,0) -> 0 | I37: =G37 -> 0
G38: =ROUND(D38*F38,0) -> 0 | I38: =G38 -> 0
G39: =ROUND(D39*F39,0) -> 0 | I39: =G39 -> 0
... G49: =ROUND(D49*F49,0) -> 0 | I49: =G49 -> 0
B51: SUBTOTAL Base Bid | G51: =SUBTOTAL(9,G21:G50) -> 11299290 | I51: =SUBTOTAL(9,I20:I50) -> 11299290 | K51: =SUBTOTAL(9,K20:K50) -> 0 | M51: =SUBTOTAL(9,M20:M50) -> 0 | O51: =SUBTOTAL(9,O20:O50) -> 0 | Q51: =SUBTOTAL(9,Q20:Q50) -> 0 | S51: =SUBTOTAL(9,S20:S50) -> 0
B52: BOND RATE | H52: 0 | J52: 0 | L52: 0 | N52: 0 | P52: 0 | R52: 0
B53: BOND AMOUNT | G53: =F52*G51 -> 0 | I53: =H52*I51 -> 0 | K53: =J52*K51 -> 0 | M53: =L52*M51 -> 0 | O53: =N52*O51 -> 0 | Q53: =P52*Q51 -> 0 | S53: =R52*S51 -> 0
B55: ADJUSTED TOTAL | G55: =SUM(G51:G53) -> 11299290 | I55: =SUM(I51:I53) -> 11299290 | K55: =SUM(K51:K53) -> 0 | M55: =SUM(M51:M53) -> 0 | O55: =SUM(O51:O53) -> 0 | Q55: =SUM(Q51:Q53) -> 0 | S55: =SUM(S51:S53) -> 0
B56: Cost per SF | G56: =G55/'Area Calculations'!$G$5 -> 29.022919 | I56: =I55/'Area Calculations'!$G$5 -> 29.022919 | K56: =K55/'Area Calculations'!$G$5 -> 0 | M56: =M55/'Area Calculations'!$G$5 -> 0 | O56: =O55/'Area Calculations'!$G$5 -> 0 | Q56: =Q55/'Area Calculations'!$G$5 -> 0 | S56: =S55/'Area Calculations'!$G$5 -> 0
A58: QUALIFICATIONS
A62: EXCLUSIONS/OWNER PROVIDED ITEMS:
A66: ALTERNATES:
A70: PROPOSED VE (Provide Clear Description):
A74: FULLY LOADED LABOR RATES
B75: Laborer
B76: Mechanic
B77: Superintendent
B78: Project Manager
A80: SCHEDULE
B81: Prepared shop drawings/submittals
B82: Mobilization
B83: Total duration to complete scope of work
A85: Winner
A86: Company
A87: Contact
A88: Phone
A89: Email
A90: Base Bid | B90: =$I$55 -> 11299290
B92: Need Prequalification
B93: Prequalified

Sheet 05 52 Misc Metals
G1: Hedrick Plug
F2: X | G2: Excluded
F3: I | G3: Included
B4: BACK TO SUMMARY SHEET | G4: Sub Add/Deduct
A5: Project: | B5: ='Area Calculations'!B4 -> Bourbon Hotel Orlando | G5: Company
A6: Trade: | B6: Miscellaneous Metals | G6: Contact
A7: CSI Code: | B7: 05 52 00 | G7: Phone
A8: Date: | G8: Email
G9: Adjusted Bid | H9: =I$59 -> 1259600 | J9: =K$59 -> 0 | L9: =M$59 -> 0 | N9: =O$59 -> 0 | P9: =Q$59 -> 0 | R9: =S$59 -> 0
A10: BID DOCUMENTS: | C10: Plan/ Spec. Package | D10: QTY | E10: U/M | F10: Unit Cost | G10: Subtotal | H10: Yes/No | I10: Price | J10: Yes/No | K10: Price | L10: Yes/No | M10: Price | N10: Yes/No | O10: Price | P10: Yes/No | Q10: Price | R10: Yes/No | S10: Price
B11: GENERAL INCLUSIONS
B12: INCLUDES ALL SALES TAX
B13: ALL HOISTING & RIGGING REQUIRED TO COMPLETE THIS SCOPE
B14: PROVIDE P&P BONDS
B15: FLORIDA STATE CONTRACTORS LIC.
B16: GENERAL LIABILITY AND WORKERS COMP. INSURANCE LIMITS
B17: STATE AND LOCAL TAXES
B18: SPECIFIC TRADE SCOPE OF WORK REQUIREMENTS
B19: BASE BID
B21: Steel stairs | G21: =ROUND(D21*F21,0) -> 0 | I21: =G21 -> 0
B22: hotel all to garage | D22: =8*2*2 -> 32 | E22: riser | F22: 12000 | G22: =ROUND(D22*F22,0) -> 384000 | I22: =G22 -> 384000
B23: hotel all to lobby | D23: =4*2*1 -> 8 | E23: riser | F23: 12000 | G23: =ROUND(D23*F23,0) -> 96000 | I23: =G23 -> 96000
B24: hotel 1st to 2nd | D24: =7*2*1 -> 14 | E24: riser | F24: 12000 | G24: =ROUND(D24*F24,0) -> 168000 | I24: =G24 -> 168000
B25: restaurant | D25: =4*2*1 -> 8 | E25: riser | F25: 12000 | G25: =ROUND(D25*F25,0) -> 96000 | I25: =G25 -> 96000
B26: Stairs wall rails | D26: =SUM(D22:D25)*18 -> 1116 | E26: lf | F26: 150 | G26: =ROUND(D26*F26,0) -> 167400 | I26: =G26 -> 167400
B27: Stairs hand rails | D27: =SUM(D22:D25)*18 -> 1116 | E27: lf | F27: 200 | G27: =ROUND(D27*F27,0) -> 223200 | I27: =G27 -> 223200
G28: =ROUND(D28*F28,0) -> 0 | I28: =G28 -> 0
B29: Elevator hoist beams | D29: 8 | E29: ea | F29: 2500 | G29: =ROUND(D29*F29,0) -> 20000 | I29: =G29 -> 20000
B30: Elevator sill angles | D30: 70 | E30: ea | F30: 1500 | G30: =ROUND(D30*F30,0) -> 105000 | I30: =G30 -> 105000
G31: =ROUND(D31*F31,0) -> 0 | I31: =G31 -> 0
G32: =ROUND(D32*F32,0) -> 0 | I32: =G32 -> 0
G33: =ROUND(D33*F33,0) -> 0 | I33: =G33 -> 0
G34: =ROUND(D34*F34,0) -> 0 | I34: =G34 -> 0
G35: =ROUND(D35*F35,0) -> 0 | I35: =G35 -> 0
G36: =ROUND(D36*F36,0) -> 0 | I36: =G36 -> 0
G37: =ROUND(D37*F37,0) -> 0 | I37: =G37 -> 0
G38: =ROUND(D38*F38,0) -> 0 | I38: =G38 -> 0
G39: =ROUND(D39*F39,0) -> 0 | I39: =G39 -> 0
G40: =ROUND(D40*F40,0) -> 0 | I40: =G40 -> 0
G41: =ROUND(D41*F41,0) -> 0 | I41: =G41 -> 0
G42: =ROUND(D42*F42,0) -> 0 | I42: =G42 -> 0
... G53: =ROUND(D53*F53,0) -> 0 | I53: =G53 -> 0
B55: SUBTOTAL Base Bid | G55: =SUBTOTAL(9,G21:G54) -> 1259600 | I55: =SUBTOTAL(9,I21:I54) -> 1259600 | K55: =SUM(K19:K54) -> 0 | M55: =SUM(M19:M54) -> 0 | O55: =SUM(O19:O54) -> 0 | Q55: =SUM(Q19:Q54) -> 0 | S55: =SUM(S19:S54) -> 0
B56: BOND RATE | H56: 0 | J56: 0 | L56: 0 | N56: 0 | P56: 0 | R56: 0
B57: BOND AMOUNT | G57: =F56*G55 -> 0 | I57: =H56*I55 -> 0 | K57: =J56*K55 -> 0 | M57: =L56*M55 -> 0 | O57: =N56*O55 -> 0 | Q57: =P56*Q55 -> 0 | S57: =R56*S55 -> 0
B59: ADJUSTED TOTAL | G59: =SUM(G55:G57) -> 1259600 | I59: =SUM(I55:I57) -> 1259600 | K59: =SUM(K55:K57) -> 0 | M59: =SUM(M55:M57) -> 0 | O59: =SUM(O55:O57) -> 0 | Q59: =SUM(Q55:Q57) -> 0 | S59: =SUM(S55:S57) -> 0
B60: Cost per SF | G60: =G59/'Area Calculations'!$G$5 -> 3.2353598 | I60: =I59/'Area Calculations'!$G$5 -> 3.2353598 | K60: =K59/'Area Calculations'!$G$5 -> 0 | M60: =M59/'Area Calculations'!$G$5 -> 0 | O60: =O59/'Area Calculations'!$G$5 -> 0 | Q60: =Q59/'Area Calculations'!$G$5 -> 0 | S60: =S59/'Area Calculations'!$G$5 -> 0
A62: QUALIFICATIONS
A66: EXCLUSIONS/OWNER PROVIDED ITEMS:
A70: ALTERNATES:
A74: PROPOSED VE (Provide Clear Description):
A78: FULLY LOADED LABOR RATES
B79: Laborer
B80: Mechanic
B81: Superintendent
B82: Project Manager
A84: SCHEDULE
B85: Prepared shop drawings/submittals
B86: Mobilization
B87: Total duration to complete scope of work
A89: Winner
A90: Company
A91: Contact
A92: Phone
A93: Email
A94: Base Bid | B94: =$I$59 -> 1259600
B96: Need Prequalification
B97: Prequalified

Sheet 05 70 Railings Glass
G1: Hedrick Plug
F2: X | G2: Excluded
F3: I | G3: Included
B4: BACK TO SUMMARY SHEET | G4: Sub Add/Deduct
A5: Project: | B5: ='Area Calculations'!B4 -> Bourbon Hotel Orlando | G5: Company
A6: Trade: | B6: Railings - Glass | G6: Contact
A7: CSI Code: | B7: 05 70 00 | G7: Phone
A8: Date: | G8: Email
G9: Adjusted Bid | H9: =I$55 -> 698400 | J9: =K$55 -> 0 | L9: =M$55 -> 0 | N9: =O$55 -> 0 | P9: =Q$55 -> 0 | R9: =S$55 -> 0
A10: BID DOCUMENTS: | C10: Plan/ Spec. Package | D10: QTY | E10: U/M | F10: Unit Cost | G10: Subtotal | H10: Yes/No | I10: Price | J10: Yes/No | K10: Price | L10: Yes/No | M10: Price | N10: Yes/No | O10: Price | P10: Yes/No | Q10: Price | R10: Yes/No | S10: Price
B11: GENERAL INCLUSIONS
B12: INCLUDES ALL SALES TAX
B13: ALL HOISTING & RIGGING REQUIRED TO COMPLETE THIS SCOPE
B14: PROVIDE P&P BONDS
B15: FLORIDA STATE CONTRACTORS LIC.
B16: GENERAL LIABILITY AND WORKERS COMP. INSURANCE LIMITS
B17: STATE AND LOCAL TAXES
B18: SPECIFIC TRADE SCOPE OF WORK REQUIREMENTS
B19: BASE BID
B21: Hotel - glass railing - 42" | D21: 875 | E21: lf | F21: 450 | G21: =ROUND(D21*F21,0) -> 393750 | I21: =G21 -> 393750
B22: Pool - glass railing - | D22: 677 | E22: lf | F22: 450 | G22: =ROUND(D22*F22,0) -> 304650 | I22: =G22 -> 304650
G23: =ROUND(D23*F23,0) -> 0 | I23: =G23 -> 0
G24: =ROUND(D24*F24,0) -> 0 | I24: =G24 -> 0
G25: =ROUND(D25*F25,0) -> 0 | I25: =G25 -> 0
G26: =ROUND(D26*F26,0) -> 0 | I26: =G26 -> 0
G27: =ROUND(D27*F27,0) -> 0 | I27: =G27 -> 0
G28: =ROUND(D28*F28,0) -> 0 | I28: =G28 -> 0
G29: =ROUND(D29*F29,0) -> 0 | I29: =G29 -> 0
G30: =ROUND(D30*F30,0) -> 0 | I30: =G30 -> 0
G31: =ROUND(D31*F31,0) -> 0 | I31: =G31 -> 0
G32: =ROUND(D32*F32,0) -> 0 | I32: =G32 -> 0
G33: =ROUND(D33*F33,0) -> 0 | I33: =G33 -> 0
G34: =ROUND(D34*F34,0) -> 0 | I34: =G34 -> 0
... G49: =ROUND(D49*F49,0) -> 0 | I49: =G49 -> 0
B51: SUBTOTAL Base Bid | G51: =SUBTOTAL(9,G21:G50) -> 698400 | I51: =SUBTOTAL(9,I21:I50) -> 698400 | K51: =SUM(K19:K50) -> 0 | M51: =SUM(M19:M50) -> 0 | O51: =SUM(O19:O50) -> 0 | Q51: =SUM(Q19:Q50) -> 0 | S51: =SUM(S19:S50) -> 0
B52: BOND RATE | H52: 0 | J52: 0 | L52: 0 | N52: 0 | P52: 0 | R52: 0
B53: BOND AMOUNT | G53: =F52*G51 -> 0 | I53: =H52*I51 -> 0 | K53: =J52*K51 -> 0 | M53: =L52*M51 -> 0 | O53: =N52*O51 -> 0 | Q53: =P52*Q51 -> 0 | S53: =R52*S51 -> 0
B55: ADJUSTED TOTAL | G55: =SUM(G51:G53) -> 698400 | I55: =SUM(I51:I53) -> 698400 | K55: =SUM(K51:K53) -> 0 | M55: =SUM(M51:M53) -> 0 | O55: =SUM(O51:O53) -> 0 | Q55: =SUM(Q51:Q53) -> 0 | S55: =SUM(S51:S53) -> 0
B56: Cost per SF | G56: =G55/'Area Calculations'!$G$5 -> 1.7938832 | I56: =I55/'Area Calculations'!$G$5 -> 1.7938832 | K56: =K55/'Area Calculations'!$G$5 -> 0 | M56: =M55/'Area Calculations'!$G$5 -> 0 | O56: =O55/'Area Calculations'!$G$5 -> 0 | Q56: =Q55/'Area Calculations'!$G$5 -> 0 | S56: =S55/'Area Calculations'!$G$5 -> 0
A58: QUALIFICATIONS
A62: EXCLUSIONS/OWNER PROVIDED ITEMS:
A66: ALTERNATES:
A70: PROPOSED VE (Provide Clear Description):
A74: FULLY LOADED LABOR RATES
B75: Laborer
B76: Mechanic
B77: Superintendent
B78: Project Manager
A80: SCHEDULE
B81: Prepared shop drawings/submittals
B82: Mobilization
B83: Total duration to complete scope of work
A85: Winner
A86: Company
A87: Contact
A88: Phone
A89: Email
A90: Base Bid | B90: =$I$55 -> 698400
B92: Need Prequalification
B93: Prequalified

Sheet 06 10 Rough Carpentry
G1: Hedrick Plug
F2: X | G2: Excluded
F3: I | G3: Included
B4: BACK TO SUMMARY SHEET | G4: Sub Add/Deduct
A5: Project: | B5: ='Area Calculations'!B4 -> Bourbon Hotel Orlando | G5: Company
A6: Trade: | B6: Rough Carpentry | G6: Contact
A7: CSI Code: | B7: 06 10 00 | G7: Phone
A8: Date: | G8: Email
G9: Adjusted Bid | H9: =I$55 -> 236980 | J9: =K$55 -> 0 | L9: =M$55 -> 0 | N9: =O$55 -> 0 | P9: =Q$55 -> 0 | R9: =S$55 -> 0
A10: BID DOCUMENTS: | C10: Plan/ Spec. Package | D10: QTY | E10: U/M | F10: Unit Cost | G10: Subtotal | H10: Yes/No | I10: Price | J10: Yes/No | K10: Price | L10: Yes/No | M10: Price | N10: Yes/No | O10: Price | P10: Yes/No | Q10: Price | R10: Yes/No | S10: Price
B11: GENERAL INCLUSIONS
B12: INCLUDES ALL SALES TAX
B13: ALL HOISTING & RIGGING REQUIRED TO COMPLETE THIS SCOPE
B14: PROVIDE P&P BONDS
B15: FLORIDA STATE CONTRACTORS LIC.
B16: GENERAL LIABILITY AND WORKERS COMP. INSURANCE LIMITS
B17: STATE AND LOCAL TAXES
B18: SPECIFIC TRADE SCOPE OF WORK REQUIREMENTS
B19: BASE BID
B21: hotel & restaurant | D21: =SUM('Area Calculations'!E15:E21) -> 279298 | E21: sf | F21: 0.75 | G21: =ROUND(D21*F21,0) -> 209474 | I21: =G21 -> 209474
B22: garage | D22: ='Area Calculations'!E14 -> 110025 | E22: sf | F22: 0.25 | G22: =ROUND(D22*F22,0) -> 27506 | I22: =G22 -> 27506
G23: =ROUND(D23*F23,0) -> 0 | I23: =G23 -> 0
G24: =ROUND(D24*F24,0) -> 0 | I24: =G24 -> 0
G25: =ROUND(D25*F25,0) -> 0 | I25: =G25 -> 0
G26: =ROUND(D26*F26,0) -> 0 | I26: =G26 -> 0
G27: =ROUND(D27*F27,0) -> 0 | I27: =G27 -> 0
G28: =ROUND(D28*F28,0) -> 0 | I28: =G28 -> 0
G29: =ROUND(D29*F29,0) -> 0 | I29: =G29 -> 0
G30: =ROUND(D30*F30,0) -> 0 | I30: =G30 -> 0
G31: =ROUND(D31*F31,0) -> 0 | I31: =G31 -> 0
G32: =ROUND(D32*F32,0) -> 0 | I32: =G32 -> 0
G33: =ROUND(D33*F33,0) -> 0 | I33: =G33 -> 0
G34: =ROUND(D34*F34,0) -> 0 | I34: =G34 -> 0
... G49: =ROUND(D49*F49,0) -> 0 | I49: =G49 -> 0
B51: SUBTOTAL Base Bid | G51: =SUBTOTAL(9,G21:G50) -> 236980 | I51: =SUBTOTAL(9,I21:I50) -> 236980 | K51: =SUBTOTAL(9,K21:K50) -> 0 | M51: =SUBTOTAL(9,M21:M50) -> 0 | O51: =SUBTOTAL(9,O21:O50) -> 0 | Q51: =SUBTOTAL(9,Q21:Q50) -> 0 | S51: =SUBTOTAL(9,S21:S50) -> 0
B52: BOND RATE | H52: 0 | J52: 0 | L52: 0 | N52: 0 | P52: 0 | R52: 0
B53: BOND AMOUNT | G53: =F52*G51 -> 0 | I53: =H52*I51 -> 0 | K53: =J52*K51 -> 0 | M53: =L52*M51 -> 0 | O53: =N52*O51 -> 0 | Q53: =P52*Q51 -> 0 | S53: =R52*S51 -> 0
B55: ADJUSTED TOTAL | G55: =SUM(G51:G53) -> 236980 | I55: =SUM(I51:I53) -> 236980 | K55: =SUM(K51:K53) -> 0 | M55: =SUM(M51:M53) -> 0 | O55: =SUM(O51:O53) -> 0 | Q55: =SUM(Q51:Q53) -> 0 | S55: =SUM(S51:S53) -> 0
B56: Cost per SF | G56: =G55/'Area Calculations'!$G$5 -> 0.60869766 | I56: =I55/'Area Calculations'!$G$5 -> 0.60869766 | K56: =K55/'Area Calculations'!$G$5 -> 0 | M56: =M55/'Area Calculations'!$G$5 -> 0 | O56: =O55/'Area Calculations'!$G$5 -> 0 | Q56: =Q55/'Area Calculations'!$G$5 -> 0 | S56: =S55/'Area Calculations'!$G$5 -> 0
A58: QUALIFICATIONS
A62: EXCLUSIONS/OWNER PROVIDED ITEMS:
A66: ALTERNATES:
A70: PROPOSED VE (Provide Clear Description):
A74: FULLY LOADED LABOR RATES
B75: Laborer
B76: Mechanic
B77: Superintendent
B78: Project Manager
A80: SCHEDULE
B81: Prepared shop drawings/submittals
B82: Mobilization
B83: Total duration to complete scope of work
A85: Winner
A86: Company
A87: Contact
A88: Phone
A89: Email
A90: Base Bid | B90: =I$55 -> 236980
B92: Need Prequalification
B93: Prequalified

Sheet 06 50 Millwork
G1: Hedrick Plug
F2: X | G2: Excluded
F3: I | G3: Included
B4: BACK TO SUMMARY SHEET | G4: Sub Add/Deduct
A5: Project: | B5: ='Area Calculations'!B4 -> Bourbon Hotel Orlando | G5: Company | H5: Borgzinner
A6: Trade: | B6: Millwork | G6: Contact | H6: Ken Stevens
A7: CSI Code: | B7: 06 50 00 | G7: Phone
A8: Date: | G8: Email
G9: Adjusted Bid | H9: =I$55 -> 0 | J9: =K$55 -> 0 | L9: =M$55 -> 0 | N9: =O$55 -> 0 | P9: =Q$55 -> 0 | R9: =S$55 -> 0
A10: BID DOCUMENTS: | C10: Plan/ Spec. Package | D10: QTY | E10: U/M | F10: Unit Cost | G10: Subtotal | H10: Yes/No | I10: Price | J10: Yes/No | K10: Price | L10: Yes/No | M10: Price | N10: Yes/No | O10: Price | P10: Yes/No | Q10: Price | R10: Yes/No | S10: Price
B11: GENERAL INCLUSIONS
B12: INCLUDES ALL SALES TAX
B13: ALL HOISTING & RIGGING REQUIRED TO COMPLETE THIS SCOPE
B14: PROVIDE P&P BONDS
B15: FLORIDA STATE CONTRACTORS LIC.
B16: GENERAL LIABILITY AND WORKERS COMP. INSURANCE LIMITS
B17: STATE AND LOCAL TAXES
B18: SPECIFIC TRADE SCOPE OF WORK REQUIREMENTS
B19: BASE BID
G21: =ROUND(D21*F21,0) -> 0 | I21: =G21 -> 0
G22: =ROUND(D22*F22,0) -> 0 | I22: =G22 -> 0
G23: =ROUND(D23*F23,0) -> 0 | I23: =G23 -> 0
G24: =ROUND(D24*F24,0) -> 0 | I24: =G24 -> 0
G25: =ROUND(D25*F25,0) -> 0 | I25: =G25 -> 0
G26: =ROUND(D26*F26,0) -> 0 | I26: =G26 -> 0
G27: =ROUND(D27*F27,0) -> 0 | I27: =G27 -> 0
G28: =ROUND(D28*F28,0) -> 0 | I28: =G28 -> 0
G29: =ROUND(D29*F29,0) -> 0 | I29: =G29 -> 0
G30: =ROUND(D30*F30,0) -> 0 | I30: =G30 -> 0
G31: =ROUND(D31*F31,0) -> 0 | I31: =G31 -> 0
G32: =ROUND(D32*F32,0) -> 0 | I32: =G32 -> 0
... G49: =ROUND(D49*F49,0) -> 0 | I49: =G49 -> 0
B51: SUBTOTAL Base Bid | G51: =SUBTOTAL(9,G21:G50) -> 0 | I51: =SUBTOTAL(9,I21:I50) -> 0 | K51: =SUM(K19:K50) -> 0 | M51: =SUM(M19:M50) -> 0 | O51: =SUM(O19:O50) -> 0 | Q51: =SUM(Q19:Q50) -> 0 | S51: =SUM(S19:S50) -> 0
B52: BOND RATE | H52: 0 | J52: 0 | L52: 0 | N52: 0 | P52: 0 | R52: 0
B53: BOND AMOUNT | G53: =F52*G51 -> 0 | I53: =H52*I51 -> 0 | K53: =J52*K51 -> 0 | M53: =L52*M51 -> 0 | O53: =N52*O51 -> 0 | Q53: =P52*Q51 -> 0 | S53: =R52*S51 -> 0
B55: ADJUSTED TOTAL | G55: =SUM(G51:G53) -> 0 | I55: =SUM(I51:I53) -> 0 | K55: =SUM(K51:K53) -> 0 | M55: =SUM(M51:M53) -> 0 | O55: =SUM(O51:O53) -> 0 | Q55: =SUM(Q51:Q53) -> 0 | S55: =SUM(S51:S53) -> 0
B56: Cost per SF | G56: =G55/'Area Calculations'!$G$5 -> 0 | I56: =I55/'Area Calculations'!$G$5 -> 0 | K56: =K55/'Area Calculations'!$G$5 -> 0 | M56: =M55/'Area Calculations'!$G$5 -> 0 | O56: =O55/'Area Calculations'!$G$5 -> 0 | Q56: =Q55/'Area Calculations'!$G$5 -> 0 | S56: =S55/'Area Calculations'!$G$5 -> 0
A58: QUALIFICATIONS
A62: EXCLUSIONS/OWNER PROVIDED ITEMS:
A66: ALTERNATES:
A70: PROPOSED VE (Provide Clear Description):
A74: FULLY LOADED LABOR RATES
B75: Laborer
B76: Mechanic
B77: Superintendent
B78: Project Manager
A80: SCHEDULE
B81: Prepared shop drawings/submittals
B82: Mobilization
B83: Total duration to complete scope of work
A85: Winner
A86: Company
A87: Contact
A88: Phone
A89: Email
A90: Base Bid | B90: =$I$55 -> 0
B92: Need Prequalification
B93: Prequalified

Sheet 07 17 Waterproofing & Caulk
G1: Hedrick Plug
F2: X | G2: Excluded
F3: I | G3: Included
B4: BACK TO SUMMARY SHEET | G4: Sub Add/Deduct
A5: Project: | B5: ='Area Calculations'!B4 -> Bourbon Hotel Orlando | G5: Company
A6: Trade: | B6: Waterproofing & Caulking | G6: Contact
A7: CSI Code: | B7: 07 17 00 | G7: Phone
A8: Date: | G8: Email
G9: Adjusted Bid | H9: =I$60 -> 6411905 | J9: =K$60 -> 0 | L9: =M$60 -> 0 | N9: =O$60 -> 0 | P9: =Q$60 -> 0 | R9: =S$60 -> 0
A10: BID DOCUMENTS: | C10: Plan/ Spec. Package | D10: QTY | E10: U/M | F10: Unit Cost | G10: Subtotal | H10: Yes/No | I10: Price | J10: Yes/No | K10: Price | L10: Yes/No | M10: Price | N10: Yes/No | O10: Price | P10: Yes/No | Q10: Price | R10: Yes/No | S10: Price
B11: GENERAL INCLUSIONS
B12: INCLUDES ALL SALES TAX
B13: ALL HOISTING & RIGGING REQUIRED TO COMPLETE THIS SCOPE
B14: PROVIDE P&P BONDS
B15: FLORIDA STATE CONTRACTORS LIC.
B16: GENERAL LIABILITY AND WORKERS COMP. INSURANCE LIMITS
B17: STATE AND LOCAL TAXES
B18: SPECIFIC TRADE SCOPE OF WORK REQUIREMENTS
B19: BASE BID
B21: Waterproofing | G21: =ROUND(D21*F21,0) -> 0 | I21: =G21 -> 0
B22: wrap footings | D22: =1514.36*24 -> 36344.64 | E22: sf | F22: 10.5 | G22: =ROUND(D22*F22,0) -> 381619 | I22: =G22 -> 381619
B23: SOG bottom | D23: 110792 | E23: sf | F23: 9 | G23: =ROUND(D23*F23,0) -> 997128 | I23: =G23 -> 997128
B24: below grade walls to 5' | D24: =1514.36*5 -> 7571.8 | E24: sf | F24: 10 | G24: =ROUND(D24*F24,0) -> 75718 | I24: =G24 -> 75718
B25: elevator pits | D25: 5 | E25: ea | F25: 15000 | G25: =ROUND(D25*F25,0) -> 75000 | I25: =G25 -> 75000
G26: =ROUND(D26*F26,0) -> 0 | I26: =G26 -> 0
B27: exterior walls - stucco | E27: sf | G27: =ROUND(D27*F27,0) -> 0 | I27: =G27 -> 0
B28: exterior walls - metal panel | D28: ='07 42 Metal Panel'!D21 -> 19200 | E28: sf | F28: 7.25 | G28: =ROUND(D28*F28,0) -> 139200 | I28: =G28 -> 139200
B29: exterior walls - stone veneer | D29: ='04 40 Stone Cladding'!D22 -> 2567 | E29: sf | F29: 7.25 | G29: =ROUND(D29*F29,0) -> 18611 | I29: =G29 -> 18611
G30: =ROUND(D30*F30,0) -> 0 | I30: =G30 -> 0
B31: podium deck - reinforced cold fluid applied - flat | D31: 110025 | E31: sf | F31: 35 | G31: =ROUND(D31*F31,0) -> 3850875 | I31: =G31 -> 3850875
B32: restaurant - roof deck / garden | D32: 7081 | E32: sf | F32: 35 | G32: =ROUND(D32*F32,0) -> 247835 | I32: =G32 -> 247835
B33: exterior terraces | D33: 8569 | E33: sf | F33: 28 | G33: =ROUND(D33*F33,0) -> 239932 | I33: =G33 -> 239932
B34: pool deck | D34: =12272-2404 -> 9868 | E34: sf | F34: 28 | G34: =ROUND(D34*F34,0) -> 276304 | I34: =G34 -> 276304
G35: =ROUND(D35*F35,0) -> 0 | I35: =G35 -> 0
B36: Caulking | G36: =ROUND(D36*F36,0) -> 0 | I36: =G36 -> 0
B37: exterior openings secondary caulk | D37: ='08 50 Storefront'!D21*0.3 -> 10257 | E37: lf | F37: 5 | G37: =ROUND(D37*F37,0) -> 51285 | I37: =G37 -> 51285
B38: misc penetrations, fire caulk, control joints | D38: ='Area Calculations'!G5 -> 389323 | E38: sf | F38: 0.15 | G38: =ROUND(D38*F38,0) -> 58398 | I38: =G38 -> 58398
G39: =ROUND(D39*F39,0) -> 0 | I39: =G39 -> 0
G40: =ROUND(D40*F40,0) -> 0 | I40: =G40 -> 0
G41: =ROUND(D41*F41,0) -> 0 | I41: =G41 -> 0
G42: =ROUND(D42*F42,0) -> 0 | I42: =G42 -> 0
G43: =ROUND(D43*F43,0) -> 0 | I43: =G43 -> 0
G44: =ROUND(D44*F44,0) -> 0 | I44: =G44 -> 0
G45: =ROUND(D45*F45,0) -> 0 | I45: =G45 -> 0
G46: =ROUND(D46*F46,0) -> 0 | I46: =G46 -> 0
G47: =ROUND(D47*F47,0) -> 0 | I47: =G47 -> 0
G48: =ROUND(D48*F48,0) -> 0 | I48: =G48 -> 0
G49: =ROUND(D49*F49,0) -> 0 | I49: =G49 -> 0
G50: =ROUND(D50*F50,0) -> 0 | I50: =G50 -> 0
... G54: =ROUND(D54*F54,0) -> 0 | I54: =G54 -> 0
B56: SUBTOTAL Base Bid | G56: =SUBTOTAL(9,G21:G55) -> 6411905 | I56: =SUBTOTAL(9,I21:I55) -> 6411905 | K56: =SUM(K19:K55) -> 0 | M56: =SUM(M19:M55) -> 0 | O56: =SUM(O19:O55) -> 0 | Q56: =SUM(Q19:Q55) -> 0 | S56: =SUM(S19:S55) -> 0
B57: BOND RATE | H57: 0 | J57: 0 | L57: 0 | N57: 0 | P57: 0 | R57: 0
B58: BOND AMOUNT | G58: =F57*G56 -> 0 | I58: =H57*I56 -> 0 | K58: =J57*K56 -> 0 | M58: =L57*M56 -> 0 | O58: =N57*O56 -> 0 | Q58: =P57*Q56 -> 0 | S58: =R57*S56 -> 0
B60: ADJUSTED TOTAL | G60: =SUM(G56:G58) -> 6411905 | I60: =SUM(I56:I58) -> 6411905 | K60: =SUM(K56:K58) -> 0 | M60: =SUM(M56:M58) -> 0 | O60: =SUM(O56:O58) -> 0 | Q60: =SUM(Q56:Q58) -> 0 | S60: =SUM(S56:S58) -> 0
B61: Cost per SF | G61: =G60/'Area Calculations'!$G$5 -> 16.469371 | I61: =I60/'Area Calculations'!$G$5 -> 16.469371 | K61: =K60/'Area Calculations'!$G$5 -> 0 | M61: =M60/'Area Calculations'!$G$5 -> 0 | O61: =O60/'Area Calculations'!$G$5 -> 0 | Q61: =Q60/'Area Calculations'!$G$5 -> 0 | S61: =S60/'Area Calculations'!$G$5 -> 0
A63: QUALIFICATIONS
A67: EXCLUSIONS/OWNER PROVIDED ITEMS:
A71: ALTERNATES:
A75: PROPOSED VE (Provide Clear Description):
A79: FULLY LOADED LABOR RATES
B80: Laborer
B81: Mechanic
B82: Superintendent
B83: Project Manager
A85: SCHEDULE
B86: Prepared shop drawings/submittals
B87: Mobilization
B88: Total duration to complete scope of work
A90: Winner
A91: Company
A92: Contact
A93: Phone
A94: Email
A95: Base Bid | B95: =$I$60 -> 6411905
B97: Need Prequalification
B98: Prequalified

Sheet 07 21 Spray Foam Ins
G1: Hedrick Plug
F2: X | G2: Excluded
F3: I | G3: Included
B4: BACK TO SUMMARY SHEET | G4: Sub Add/Deduct
A5: Project: | B5: Rybovich Safe Harbor | G5: Company
A6: Trade: | B6: Spary Foam Insulation | G6: Contact
A7: CSI Code: | B7: 07 21 00 | G7: Phone
A8: Date: | G8: Email
G9: Adjusted Bid | H9: =I$56 -> 177267 | J9: =K$56 -> 0 | L9: =M$56 -> 0 | N9: =O$56 -> 0 | P9: =Q$56 -> 0 | R9: =S$56 -> 0
A10: BID DOCUMENTS: | C10: Plan/ Spec. Package | D10: QTY | E10: U/M | F10: Unit Cost | G10: Subtotal | H10: Yes/No | I10: Price | J10: Yes/No | K10: Price | L10: Yes/No | M10: Price | N10: Yes/No | O10: Price | P10: Yes/No | Q10: Price | R10: Yes/No | S10: Price
B11: GENERAL INCLUSIONS
B12: INCLUDES ALL SALES TAX
B13: ALL HOISTING & RIGGING REQUIRED TO COMPLETE THIS SCOPE
B14: PROVIDE P&P BONDS
B15: FLORIDA STATE CONTRACTORS LIC.
B16: GENERAL LIABILITY AND WORKERS COMP. INSURANCE LIMITS
B17: STATE AND LOCAL TAXES
B18: SPECIFIC TRADE SCOPE OF WORK REQUIREMENTS
B19: BASE BID
B21: Spray foam insulation for sound attenuation - R13 at bottom of poudum deck | G21: =ROUND(D21*F21,0) -> 0
B22: open cell spray foam | D22: 110792 | E22: SF | F22: 1.6 | G22: =ROUND(D22*F22,0) -> 177267 | I22: =G22 -> 177267
G23: =ROUND(D23*F23,0) -> 0
G24: =ROUND(D24*F24,0) -> 0
G25: =ROUND(D25*F25,0) -> 0
G26: =ROUND(D26*F26,0) -> 0
G27: =ROUND(D27*F27,0) -> 0
G28: =ROUND(D28*F28,0) -> 0
G29: =ROUND(D29*F29,0) -> 0
G30: =ROUND(D30*F30,0) -> 0
G31: =ROUND(D31*F31,0) -> 0
G32: =ROUND(D32*F32,0) -> 0
G33: =ROUND(D33*F33,0) -> 0
G34: =ROUND(D34*F34,0) -> 0
... G50: =ROUND(D50*F50,0) -> 0
B52: SUBTOTAL Base Bid | G52: =SUBTOTAL(9,G21:G51) -> 177267 | I52: =SUBTOTAL(9,I20:I51) -> 177267 | K52: =SUBTOTAL(9,K20:K51) -> 0 | M52: =SUBTOTAL(9,M20:M51) -> 0 | O52: =SUBTOTAL(9,O20:O51) -> 0 | Q52: =SUBTOTAL(9,Q20:Q51) -> 0 | S52: =SUBTOTAL(9,S20:S51) -> 0
B53: BOND RATE | H53: 0 | J53: 0 | L53: 0 | N53: 0 | P53: 0 | R53: 0
B54: BOND AMOUNT | G54: =F53*G52 -> 0 | I54: =H53*I52 -> 0 | K54: =J53*K52 -> 0 | M54: =L53*M52 -> 0 | O54: =N53*O52 -> 0 | Q54: =P53*Q52 -> 0 | S54: =R53*S52 -> 0
B56: ADJUSTED TOTAL | G56: =SUM(G52:G54) -> 177267 | I56: =SUM(I52:I54) -> 177267 | K56: =SUM(K52:K54) -> 0 | M56: =SUM(M52:M54) -> 0 | O56: =SUM(O52:O54) -> 0 | Q56: =SUM(Q52:Q54) -> 0 | S56: =SUM(S52:S54) -> 0
B57: Cost per SF | G57: 4.0238571 | I57: 4.0238571 | K57: 0 | M57: 0 | O57: 0 | Q57: 0 | S57: 0
A59: QUALIFICATIONS
A63: EXCLUSIONS/OWNER PROVIDED ITEMS:
A67: ALTERNATES:
A71: PROPOSED VE (Provide Clear Description):
A75: FULLY LOADED LABOR RATES
B76: Laborer
B77: Mechanic
B78: Superintendent
B79: Project Manager
A81: SCHEDULE
B82: Prepared shop drawings/submittals
B83: Mobilization
B84: Total duration to complete scope of work
A86: Winner
A87: Company
A88: Contact
A89: Phone
A90: Email
A91: Base Bid | B91: =$I$56 -> 177267
B93: Need Prequalification
B94: Prequalified

Sheet 07 42 Metal Panel
G1: Hedrick Plug
F2: X | G2: Excluded
F3: I | G3: Included
B4: BACK TO SUMMARY SHEET | G4: Sub Add/Deduct
A5: Project: | B5: ='Area Calculations'!B4 -> Bourbon Hotel Orlando | G5: Company
A6: Trade: | B6: Metal Panel | G6: Contact
A7: CSI Code: | B7: 07 42 00 | G7: Phone
A8: Date: | G8: Email
G9: Adjusted Bid | H9: =I$55 -> 3361361 | J9: =K$55 -> 0 | L9: =M$55 -> 0 | N9: =O$55 -> 0 | P9: =Q$55 -> 0 | R9: =S$55 -> 0
A10: BID DOCUMENTS: | C10: Plan/ Spec. Package | D10: QTY | E10: U/M | F10: Unit Cost | G10: Subtotal | H10: Yes/No | I10: Price | J10: Yes/No | K10: Price | L10: Yes/No | M10: Price | N10: Yes/No | O10: Price | P10: Yes/No | Q10: Price | R10: Yes/No | S10: Price
B11: GENERAL INCLUSIONS
B12: INCLUDES ALL SALES TAX
B13: ALL HOISTING & RIGGING REQUIRED TO COMPLETE THIS SCOPE
B14: PROVIDE P&P BONDS
B15: FLORIDA STATE CONTRACTORS LIC.
B16: GENERAL LIABILITY AND WORKERS COMP. INSURANCE LIMITS
B17: STATE AND LOCAL TAXES
B18: SPECIFIC TRADE SCOPE OF WORK REQUIREMENTS
B19: BASE BID
B21: Wood look metal panel | D21: 19200 | E21: sf | F21: 60 | G21: =ROUND(D21*F21,0) -> 1152000 | I21: =G21 -> 1152000
G22: =ROUND(D22*F22,0) -> 0 | I22: =G22 -> 0
B23: Wood look metal panel - rainscreen roof at Porte Cochere | D23: 3420 | E23: sf | F23: 70 | G23: =ROUND(D23*F23,0) -> 239400 | I23: =G23 -> 239400
G24: =ROUND(D24*F24,0) -> 0 | I24: =G24 -> 0
B25: High roof soffits - wood look metal panel | D25: =28919+16075-31692+2403 -> 15705 | E25: sf | F25: 65 | G25: =ROUND(D25*F25,0) -> 1020825 | I25: =G25 -> 1020825
B26: High roof facia panel - wood look metal panel | D26: =1106+550 -> 1656 | E26: sf | F26: 60 | G26: =ROUND(D26*F26,0) -> 99360 | I26: =G26 -> 99360
G27: =ROUND(D27*F27,0) -> 0 | I27: =G27 -> 0
A28: 1082 | B28: Column cladding - assume 24" diameter | D28: =A28*6.283 -> 6798.206 | E28: sf | F28: 125 | G28: =ROUND(D28*F28,0) -> 849776 | I28: =G28 -> 849776
G29: =ROUND(D29*F29,0) -> 0 | I29: =G29 -> 0
G30: =ROUND(D30*F30,0) -> 0 | I30: =G30 -> 0
G31: =ROUND(D31*F31,0) -> 0 | I31: =G31 -> 0
G32: =ROUND(D32*F32,0) -> 0 | I32: =G32 -> 0
G33: =ROUND(D33*F33,0) -> 0 | I33: =G33 -> 0
G34: =ROUND(D34*F34,0) -> 0 | I34: =G34 -> 0
G35: =ROUND(D35*F35,0) -> 0 | I35: =G35 -> 0
G36: =ROUND(D36*F36,0) -> 0 | I36: =G36 -> 0
G37: =ROUND(D37*F37,0) -> 0 | I37: =G37 -> 0
G38: =ROUND(D38*F38,0) -> 0 | I38: =G38 -> 0
G39: =ROUND(D39*F39,0) -> 0 | I39: =G39 -> 0
G40: =ROUND(D40*F40,0) -> 0 | I40: =G40 -> 0
... G49: =ROUND(D49*F49,0) -> 0 | I49: =G49 -> 0
B51: SUBTOTAL Base Bid | G51: =SUBTOTAL(9,G21:G50) -> 3361361 | I51: =SUBTOTAL(9,I21:I50) -> 3361361 | K51: =SUM(K19:K50) -> 0 | M51: =SUM(M19:M50) -> 0 | O51: =SUM(O19:O50) -> 0 | Q51: =SUM(Q19:Q50) -> 0 | S51: =SUM(S19:S50) -> 0
B52: BOND RATE | H52: 0 | J52: 0 | L52: 0 | N52: 0 | P52: 0 | R52: 0
B53: BOND AMOUNT | G53: =F52*G51 -> 0 | I53: =H52*I51 -> 0 | K53: =J52*K51 -> 0 | M53: =L52*M51 -> 0 | O53: =N52*O51 -> 0 | Q53: =P52*Q51 -> 0 | S53: =R52*S51 -> 0
B55: ADJUSTED TOTAL | G55: =SUM(G51:G53) -> 3361361 | I55: =SUM(I51:I53) -> 3361361 | K55: =SUM(K51:K53) -> 0 | M55: =SUM(M51:M53) -> 0 | O55: =SUM(O51:O53) -> 0 | Q55: =SUM(Q51:Q53) -> 0 | S55: =SUM(S51:S53) -> 0
B56: Cost per SF | G56: =G55/'Area Calculations'!$G$5 -> 8.6338619 | I56: =I55/'Area Calculations'!$G$5 -> 8.6338619 | K56: =K55/'Area Calculations'!$G$5 -> 0 | M56: =M55/'Area Calculations'!$G$5 -> 0 | O56: =O55/'Area Calculations'!$G$5 -> 0 | Q56: =Q55/'Area Calculations'!$G$5 -> 0 | S56: =S55/'Area Calculations'!$G$5 -> 0
A58: QUALIFICATIONS
A62: EXCLUSIONS/OWNER PROVIDED ITEMS:
A66: ALTERNATES:
A70: PROPOSED VE (Provide Clear Description):
A74: FULLY LOADED LABOR RATES
B75: Laborer
B76: Mechanic
B77: Superintendent
B78: Project Manager
A80: SCHEDULE
B81: Prepared shop drawings/submittals
B82: Mobilization
B83: Total duration to complete scope of work
A85: Winner
A86: Company
A87: Contact
A88: Phone
A89: Email
A90: Base Bid | B90: =$I$55 -> 3361361
B92: Need Prequalification
B93: Prequalified

Sheet 07 50 Roofing
G1: Hedrick Plug
F2: X | G2: Excluded
F3: I | G3: Included
B4: BACK TO SUMMARY SHEET | G4: Sub Add/Deduct
A5: Project: | B5: ='Area Calculations'!B4 -> Bourbon Hotel Orlando | G5: Company
A6: Trade: | B6: Roofing | G6: Contact
A7: CSI Code: | B7: 07 50 00 | G7: Phone
A8: Date: | G8: Email
G9: Adjusted Bid | H9: =I$55 -> 1628655 | J9: =K$55 -> 0 | L9: =M$55 -> 0 | N9: =O$55 -> 0 | P9: =Q$55 -> 0 | R9: =S$55 -> 0
A10: BID DOCUMENTS: | C10: Plan/ Spec. Package | D10: QTY | E10: U/M | F10: Unit Cost | G10: Subtotal | H10: Yes/No | I10: Price | J10: Yes/No | K10: Price | L10: Yes/No | M10: Price | N10: Yes/No | O10: Price | P10: Yes/No | Q10: Price | R10: Yes/No | S10: Price
B11: GENERAL INCLUSIONS
B12: INCLUDES ALL SALES TAX
B13: ALL HOISTING & RIGGING REQUIRED TO COMPLETE THIS SCOPE
B14: PROVIDE P&P BONDS
B15: FLORIDA STATE CONTRACTORS LIC.
B16: GENERAL LIABILITY AND WORKERS COMP. INSURANCE LIMITS
B17: STATE AND LOCAL TAXES
B18: SPECIFIC TRADE SCOPE OF WORK REQUIREMENTS
B19: BASE BID
B21: High roofs - assume a TPO | D21: 46533 | E21: sf | F21: 35 | G21: =ROUND(D21*F21,0) -> 1628655 | I21: =G21 -> 1628655
G22: =ROUND(D22*F22,0) -> 0 | I22: =G22 -> 0
G23: =ROUND(D23*F23,0) -> 0 | I23: =G23 -> 0
G24: =ROUND(D24*F24,0) -> 0 | I24: =G24 -> 0
G25: =ROUND(D25*F25,0) -> 0 | I25: =G25 -> 0
G26: =ROUND(D26*F26,0) -> 0 | I26: =G26 -> 0
G27: =ROUND(D27*F27,0) -> 0 | I27: =G27 -> 0
G28: =ROUND(D28*F28,0) -> 0 | I28: =G28 -> 0
G29: =ROUND(D29*F29,0) -> 0 | I29: =G29 -> 0
G30: =ROUND(D30*F30,0) -> 0 | I30: =G30 -> 0
G31: =ROUND(D31*F31,0) -> 0 | I31: =G31 -> 0
G32: =ROUND(D32*F32,0) -> 0 | I32: =G32 -> 0
G33: =ROUND(D33*F33,0) -> 0 | I33: =G33 -> 0
... G49: =ROUND(D49*F49,0) -> 0 | I49: =G49 -> 0
B51: SUBTOTAL Base Bid | G51: =SUBTOTAL(9,G21:G50) -> 1628655 | I51: =SUBTOTAL(9,I21:I50) -> 1628655 | K51: =SUBTOTAL(9,K21:K50) -> 0 | M51: =SUBTOTAL(9,M21:M50) -> 0 | O51: =SUBTOTAL(9,O21:O50) -> 0 | Q51: =SUM(Q19:Q50) -> 0 | S51: =SUM(S19:S50) -> 0
B52: BOND RATE | H52: 0 | J52: 0 | L52: 0 | N52: 0 | P52: 0 | R52: 0
B53: BOND AMOUNT | G53: =F52*G51 -> 0 | I53: =H52*I51 -> 0 | K53: =J52*K51 -> 0 | M53: =L52*M51 -> 0 | O53: =N52*O51 -> 0 | Q53: =P52*Q51 -> 0 | S53: =R52*S51 -> 0
B55: ADJUSTED TOTAL | G55: =SUM(G51:G53) -> 1628655 | I55: =SUM(I51:I53) -> 1628655 | K55: =SUM(K51:K53) -> 0 | M55: =SUM(M51:M53) -> 0 | O55: =SUM(O51:O53) -> 0 | Q55: =SUM(Q51:Q53) -> 0 | S55: =SUM(S51:S53) -> 0
B56: Cost per SF | G56: =G55/'Area Calculations'!$G$5 -> 4.1833002 | I56: =I55/'Area Calculations'!$G$5 -> 4.1833002 | K56: =K55/'Area Calculations'!$G$5 -> 0 | M56: =M55/'Area Calculations'!$G$5 -> 0 | O56: =O55/'Area Calculations'!$G$5 -> 0 | Q56: =Q55/'Area Calculations'!$G$5 -> 0 | S56: =S55/'Area Calculations'!$G$5 -> 0
A58: QUALIFICATIONS
A62: EXCLUSIONS/OWNER PROVIDED ITEMS:
A66: ALTERNATES:
A70: PROPOSED VE (Provide Clear Description):
A74: FULLY LOADED LABOR RATES
B75: Laborer
B76: Mechanic
B77: Superintendent
B78: Project Manager
A80: SCHEDULE
B81: Prepared shop drawings/submittals
B82: Mobilization
B83: Total duration to complete scope of work
A85: Winner
A86: Company
A87: Contact
A88: Phone
A89: Email
A90: Base Bid | B90: =$I$55 -> 1628655
B92: Need Prequalification
B93: Prequalified

Sheet 08 14 DFH
G1: Hedrick Plug
F2: X | G2: Excluded
F3: I | G3: Included
B4: BACK TO SUMMARY SHEET | G4: Sub Add/Deduct
A5: Project: | B5: ='Area Calculations'!B4 -> Bourbon Hotel Orlando | G5: Company
A6: Trade: | B6: Doors, Frames & Hardware | G6: Contact
A7: CSI Code: | B7: 08 14 00 | G7: Phone
A8: Date: | G8: Email
G9: Adjusted Bid | H9: =I$55 -> 0 | J9: =K$55 -> 0 | L9: =M$55 -> 0 | N9: =O$55 -> 0 | P9: =Q$55 -> 0 | R9: =S$55 -> 0
A10: BID DOCUMENTS: | C10: Plan/ Spec. Package | D10: QTY | E10: U/M | F10: Unit Cost | G10: Subtotal | H10: Yes/No | I10: Price | J10: Yes/No | K10: Price | L10: Yes/No | M10: Price | N10: Yes/No | O10: Price | P10: Yes/No | Q10: Price | R10: Yes/No | S10: Price
B11: GENERAL INCLUSIONS
B12: INCLUDES ALL SALES TAX
B13: ALL HOISTING & RIGGING REQUIRED TO COMPLETE THIS SCOPE
B14: PROVIDE P&P BONDS
B15: FLORIDA STATE CONTRACTORS LIC.
B16: GENERAL LIABILITY AND WORKERS COMP. INSURANCE LIMITS
B17: STATE AND LOCAL TAXES
B18: SPECIFIC TRADE SCOPE OF WORK REQUIREMENTS
B19: BASE BID
G21: =ROUND(D21*F21,0) -> 0 | I21: =G21 -> 0
G22: =ROUND(D22*F22,0) -> 0 | I22: =G22 -> 0
G23: =ROUND(D23*F23,0) -> 0 | I23: =G23 -> 0
G24: =ROUND(D24*F24,0) -> 0 | I24: =G24 -> 0
G25: =ROUND(D25*F25,0) -> 0 | I25: =G25 -> 0
G26: =ROUND(D26*F26,0) -> 0 | I26: =G26 -> 0
G27: =ROUND(D27*F27,0) -> 0 | I27: =G27 -> 0
G28: =ROUND(D28*F28,0) -> 0 | I28: =G28 -> 0
G29: =ROUND(D29*F29,0) -> 0 | I29: =G29 -> 0
G30: =ROUND(D30*F30,0) -> 0 | I30: =G30 -> 0
G31: =ROUND(D31*F31,0) -> 0 | I31: =G31 -> 0
G32: =ROUND(D32*F32,0) -> 0 | I32: =G32 -> 0
... G49: =ROUND(D49*F49,0) -> 0 | I49: =G49 -> 0
B51: SUBTOTAL Base Bid | G51: =SUBTOTAL(9,G21:G50) -> 0 | I51: =SUBTOTAL(9,I21:I50) -> 0 | K51: =SUM(K19:K50) -> 0 | M51: =SUM(M19:M50) -> 0 | O51: =SUM(O19:O50) -> 0 | Q51: =SUM(Q19:Q50) -> 0 | S51: =SUM(S19:S50) -> 0
B52: BOND RATE | H52: 0 | J52: 0 | L52: 0 | N52: 0 | P52: 0 | R52: 0
B53: BOND AMOUNT | G53: =F52*G51 -> 0 | I53: =H52*I51 -> 0 | K53: =J52*K51 -> 0 | M53: =L52*M51 -> 0 | O53: =N52*O51 -> 0 | Q53: =P52*Q51 -> 0 | S53: =R52*S51 -> 0
B55: ADJUSTED TOTAL | G55: =SUM(G51:G53) -> 0 | I55: =SUM(I51:I53) -> 0 | K55: =SUM(K51:K53) -> 0 | M55: =SUM(M51:M53) -> 0 | O55: =SUM(O51:O53) -> 0 | Q55: =SUM(Q51:Q53) -> 0 | S55: =SUM(S51:S53) -> 0
B56: Cost per SF | G56: =G55/'Area Calculations'!$G$5 -> 0 | I56: =I55/'Area Calculations'!$G$5 -> 0 | K56: =K55/'Area Calculations'!$G$5 -> 0 | M56: =M55/'Area Calculations'!$G$5 -> 0 | O56: =O55/'Area Calculations'!$G$5 -> 0 | Q56: =Q55/'Area Calculations'!$G$5 -> 0 | S56: =S55/'Area Calculations'!$G$5 -> 0
A58: QUALIFICATIONS
A62: EXCLUSIONS/OWNER PROVIDED ITEMS:
A66: ALTERNATES:
A70: PROPOSED VE (Provide Clear Description):
A74: FULLY LOADED LABOR RATES
B75: Laborer
B76: Mechanic
B77: Superintendent
B78: Project Manager
A80: SCHEDULE
B81: Prepared shop drawings/submittals
B82: Mobilization
B83: Total duration to complete scope of work
A85: Winner
A86: Company
A87: Contact
A88: Phone
A89: Email
A90: Base Bid | B90: =$I$55 -> 0
B92: Need Prequalification
B93: Prequalified

Sheet 08 30 Retractable Screens
G1: Hedrick Plug
G2: Excluded
B3: BACK TO SUMMARY SHEET | G3: Included | H3: Bidder 1 | J3: Bidder 2 | L3: Bidder 3 | N3: Bidder 4 | P3: Bidder5 | R3: Bidder6
A4: Project: | B4: ='Area Calculations'!B4 -> Bourbon Hotel Orlando | G4: Company
A5: Trade: | B5: Retractable Screens | G5: Contact
A6: CSI Code: | B6: 08 30 | G6: Phone
A7: Date: | G7: Email
A8: Adjusted Bid | G8: Adjusted Bid
A9: BID DOCUMENTS: | C9: Plan/ Spec. Package | D9: QTY | E9: U/M | F9: Unit Cost | G9: Subtotal | H9: Yes/No | I9: Price | J9: Yes/No | K9: Price | L9: Yes/No | M9: Price | N9: Yes/No | O9: Price | P9: Yes/No | Q9: Price | R9: Yes/No | S9: Price
B10: Plans By Division
B11: ='Area Calculations'!#REF! -> #REF! | C11: P
B12: ='Area Calculations'!#REF! -> #REF! | C12: P
B13: ='Area Calculations'!#REF! -> #REF! | C13: P
B14: ='Area Calculations'!#REF! -> #REF! | C14: P
B15: ='Area Calculations'!#REF! -> #REF! | C15: P
B16: ='Area Calculations'!#REF! -> #REF! | C16: P
B17: ='Area Calculations'!#REF! -> #REF! | C17: P
B18: ='Area Calculations'!#REF! -> #REF! | C18: P
B19: ='Area Calculations'!#REF! -> #REF! | C19: P
B21: Retractable Screens
B22: GENERAL INCLUSIONS
B23: INCLUDES ALL SALES TAX
B24: ALL HOISTING & RIGGING REQUIRED TO COMPLETE THIS SCOPE
B25: PROVIDE P&P BONDS
B26: FLORIDA STATE CONTRACTORS LIC.
B27: GENERAL LIABILITY AND WORKERS COMP. INSURANCE LIMITS
B28: STATE AND LOCAL TAXES
B29: SPECIFIC TRADE SCOPE OF WORK REQUIREMENTS
B30: BASE BID
F41: SUBTOTAL | I41: =SUM(I23:I40) -> 0 | K41: =SUM(K23:K40) -> 0 | M41: =SUM(M23:M40) -> 0 | O41: =SUM(O23:O40) -> 0 | Q41: =SUM(Q23:Q40) -> 0 | S41: =SUM(S23:S40) -> 0
F42: BOND RATE | H42: 0 | P42: 0 | R42: 0
F43: BOND AMOUNT | I43: =I41*H42 -> 0 | K43: =K41*J42 -> 0 | M43: =M41*L42 -> 0 | O43: =O41*N42 -> 0 | Q43: =Q41*P42 -> 0 | S43: =S41*R42 -> 0
F45: ADJUSTED TOTAL | I45: =SUM(I41:I43) -> 0 | K45: =SUM(K41:K43) -> 0 | M45: =SUM(M41:M43) -> 0 | O45: =SUM(O41:O43) -> 0 | Q45: =SUM(Q41:Q43) -> 0 | S45: =SUM(S41:S43) -> 0
F46: Cost per SF | I46: =I45/'Area Calculations'!$G$5 -> 0 | K46: =K45/'Area Calculations'!$G$5 -> 0 | M46: =M45/'Area Calculations'!$G$5 -> 0 | O46: =O45/'Area Calculations'!$G$5 -> 0 | Q46: =Q45/'Area Calculations'!$G$5 -> 0 | S46: =S45/'Area Calculations'!$G$5 -> 0
F47: Cost per Unit | I47: =I45/'Area Calculations'!$G$9 -> 0 | K47: =K45/'Area Calculations'!$G$9 -> 0 | M47: =M45/'Area Calculations'!$G$9 -> 0 | O47: =O45/'Area Calculations'!$G$9 -> 0 | Q47: =Q45/'Area Calculations'!$G$9 -> 0 | S47: =S45/'Area Calculations'!$G$9 -> 0
A49: QUALIFICATIONS
A53: EXCLUSIONS/OWNER PROVIDED ITEMS:
A57: ALTERNATES:
A61: PROPOSED VE (Provide Clear Description):
A65: FULLY LOADED LABOR RATES
B66: Laborer
B67: Mechanic
B68: Superintendent
B69: Project Manager
A71: SCHEDULE
B72: Prepared shop drawings/submittals
B73: Mobilization
B74: Total duration to complete scope of work
A76: Winner
A77: Company
A78: Contact
A79: Phone
A80: Email
A81: Base Bid
B83: Need Prequalification
B84: Prequalified

Sheet 08 50 Storefront
G1: Hedrick Plug
F2: X | G2: Excluded
F3: I | G3: Included
B4: BACK TO SUMMARY SHEET | G4: Sub Add/Deduct
A5: Project: | B5: ='Area Calculations'!B4 -> Bourbon Hotel Orlando | G5: Company
A6: Trade: | B6: Storefront / Curtianwall | G6: Contact
A7: CSI Code: | B7: 08 50 00 | G7: Phone
A8: Date: | G8: Email
G9: Adjusted Bid | H9: =I$55 -> 8830610 | J9: =K$55 -> 0 | L9: =M$55 -> 0 | N9: =O$55 -> 0 | P9: =Q$55 -> 0 | R9: =S$55 -> 0
A10: BID DOCUMENTS: | C10: Plan/ Spec. Package | D10: QTY | E10: U/M | F10: Unit Cost | G10: Subtotal | H10: Yes/No | I10: Price | J10: Yes/No | K10: Price | L10: Yes/No | M10: Price | N10: Yes/No | O10: Price | P10: Yes/No | Q10: Price | R10: Yes/No | S10: Price
B11: GENERAL INCLUSIONS
B12: INCLUDES ALL SALES TAX
B13: ALL HOISTING & RIGGING REQUIRED TO COMPLETE THIS SCOPE
B14: PROVIDE P&P BONDS
B15: FLORIDA STATE CONTRACTORS LIC.
B16: GENERAL LIABILITY AND WORKERS COMP. INSURANCE LIMITS
B17: STATE AND LOCAL TAXES
B18: SPECIFIC TRADE SCOPE OF WORK REQUIREMENTS
B19: BASE BID
B21: Storefront | D21: 34190 | E21: sf | F21: 95 | G21: =ROUND(D21*F21,0) -> 3248050 | I21: =G21 -> 3248050
B22: Curtainwall | D22: 24082 | E22: sf | F22: 150 | G22: =ROUND(D22*F22,0) -> 3612300 | I22: =G22 -> 3612300
B23: Storefront w Longboard fins | D23: 7125 | E23: sf | F23: =95+55 -> 150 | G23: =ROUND(D23*F23,0) -> 1068750 | I23: =G23 -> 1068750
G24: =ROUND(D24*F24,0) -> 0 | I24: =G24 -> 0
B25: Bridge floor curtainwall | D25: =1867+1867+800 -> 4534 | E25: sf | F25: 165 | G25: =ROUND(D25*F25,0) -> 748110 | I25: =G25 -> 748110
B26: Solarium storefront | D26: 1534 | E26: sf | F26: 100 | G26: =ROUND(D26*F26,0) -> 153400 | I26: =G26 -> 153400
G27: =ROUND(D27*F27,0) -> 0 | I27: =G27 -> 0
G28: =ROUND(D28*F28,0) -> 0 | I28: =G28 -> 0
G29: =ROUND(D29*F29,0) -> 0 | I29: =G29 -> 0
G30: =ROUND(D30*F30,0) -> 0 | I30: =G30 -> 0
G31: =ROUND(D31*F31,0) -> 0 | I31: =G31 -> 0
G32: =ROUND(D32*F32,0) -> 0 | I32: =G32 -> 0
G33: =ROUND(D33*F33,0) -> 0 | I33: =G33 -> 0
G34: =ROUND(D34*F34,0) -> 0 | I34: =G34 -> 0
G35: =ROUND(D35*F35,0) -> 0 | I35: =G35 -> 0
G36: =ROUND(D36*F36,0) -> 0 | I36: =G36 -> 0
G37: =ROUND(D37*F37,0) -> 0 | I37: =G37 -> 0
G38: =ROUND(D38*F38,0) -> 0 | I38: =G38 -> 0
... G49: =ROUND(D49*F49,0) -> 0 | I49: =G49 -> 0
B51: SUBTOTAL Base Bid | G51: =SUBTOTAL(9,G21:G50) -> 8830610 | I51: =SUBTOTAL(9,I21:I50) -> 8830610 | K51: =SUBTOTAL(9,K21:K50) -> 0 | M51: =SUM(M19:M50) -> 0 | O51: =SUM(O19:O50) -> 0 | Q51: =SUM(Q19:Q50) -> 0 | S51: =SUM(S19:S50) -> 0
B52: BOND RATE | H52: 0 | J52: 0 | L52: 0 | N52: 0 | P52: 0 | R52: 0
B53: BOND AMOUNT | G53: =F52*G51 -> 0 | I53: =H52*I51 -> 0 | K53: =J52*K51 -> 0 | M53: =L52*M51 -> 0 | O53: =N52*O51 -> 0 | Q53: =P52*Q51 -> 0 | S53: =R52*S51 -> 0
B55: ADJUSTED TOTAL | G55: =SUM(G51:G53) -> 8830610 | I55: =SUM(I51:I53) -> 8830610 | K55: =SUM(K51:K53) -> 0 | M55: =SUM(M51:M53) -> 0 | O55: =SUM(O51:O53) -> 0 | Q55: =SUM(Q51:Q53) -> 0 | S55: =SUM(S51:S53) -> 0
B56: Cost per SF | G56: =G55/'Area Calculations'!$G$5 -> 22.681963 | I56: =I55/'Area Calculations'!$G$5 -> 22.681963 | K56: =K55/'Area Calculations'!$G$5 -> 0 | M56: =M55/'Area Calculations'!$G$5 -> 0 | O56: =O55/'Area Calculations'!$G$5 -> 0 | Q56: =Q55/'Area Calculations'!$G$5 -> 0 | S56: =S55/'Area Calculations'!$G$5 -> 0
A58: QUALIFICATIONS
A62: EXCLUSIONS/OWNER PROVIDED ITEMS:
A66: ALTERNATES:
A70: PROPOSED VE (Provide Clear Description):
A74: FULLY LOADED LABOR RATES
B75: Laborer
B76: Mechanic
B77: Superintendent
B78: Project Manager
A80: SCHEDULE
B81: Prepared shop drawings/submittals
B82: Mobilization
B83: Total duration to complete scope of work
A85: Winner
A86: Company
A87: Contact
A88: Phone
A89: Email
A90: Base Bid | B90: =$I$55 -> 8830610
B92: Need Prequalification
B93: Prequalified

Sheet 09 24 Stucco
G1: Hedrick Plug
F2: X | G2: Excluded
F3: I | G3: Included
B4: BACK TO SUMMARY SHEET | G4: Sub Add/Deduct
A5: Project: | B5: ='Area Calculations'!B4 -> Bourbon Hotel Orlando | G5: Company
A6: Trade: | B6: Stucco | G6: Contact
A7: CSI Code: | B7: 09 24 00 | G7: Phone
A8: Date: | G8: Email
G9: Adjusted Bid | H9: =I$59 -> 167882 | J9: =K$59 -> 0 | L9: =M$59 -> 0 | N9: =O$59 -> 0 | P9: =Q$59 -> 0 | R9: =S$59 -> 0
A10: BID DOCUMENTS: | C10: Plan/ Spec. Package | D10: QTY | E10: U/M | F10: Unit Cost | G10: Subtotal | H10: Yes/No | I10: Price | J10: Yes/No | K10: Price | L10: Yes/No | M10: Price | N10: Yes/No | O10: Price | P10: Yes/No | Q10: Price | R10: Yes/No | S10: Price
B11: GENERAL INCLUSIONS
B12: INCLUDES ALL SALES TAX
B13: ALL HOISTING & RIGGING REQUIRED TO COMPLETE THIS SCOPE
B14: PROVIDE P&P BONDS
B15: FLORIDA STATE CONTRACTORS LIC.
B16: GENERAL LIABILITY AND WORKERS COMP. INSURANCE LIMITS
B17: STATE AND LOCAL TAXES
B18: SPECIFIC TRADE SCOPE OF WORK REQUIREMENTS
B19: BASE BID
B21: Stucco building | D21: =SUM(D22:D27) -> 25828 | E21: sf | F21: 6.5 | G21: =ROUND(D21*F21,0) -> 167882 | I21: =G21 -> 167882
B22: Elevation - Back | D22: 21363 | E22: sf | G22: =ROUND(D22*F22,0) -> 0 | I22: =G22 -> 0
B23: Elevation - Front | D23: 19432 | E23: sf | G23: =ROUND(D23*F23,0) -> 0 | I23: =G23 -> 0
B24: Elevation - Left | D24: 34595 | E24: sf | G24: =ROUND(D24*F24,0) -> 0 | I24: =G24 -> 0
B25: Elevation - Right | D25: 35035 | E25: sf | G25: =ROUND(D25*F25,0) -> 0 | I25: =G25 -> 0
B26: less glazing | D26: =-SUM('08 50 Storefront'!D21:D23) -> -65397 | E26: sf | G26: =ROUND(D26*F26,0) -> 0 | I26: =G26 -> 0
B27: less metal panel | D27: =-'07 42 Metal Panel'!D21 -> -19200 | E27: sf | G27: =ROUND(D27*F27,0) -> 0 | I27: =G27 -> 0
G28: =ROUND(D28*F28,0) -> 0 | I28: =G28 -> 0
G29: =ROUND(D29*F29,0) -> 0 | I29: =G29 -> 0
G30: =ROUND(D30*F30,0) -> 0 | I30: =G30 -> 0
G31: =ROUND(D31*F31,0) -> 0 | I31: =G31 -> 0
G32: =ROUND(D32*F32,0) -> 0 | I32: =G32 -> 0
G33: =ROUND(D33*F33,0) -> 0 | I33: =G33 -> 0
G34: =ROUND(D34*F34,0) -> 0 | I34: =G34 -> 0
G35: =ROUND(D35*F35,0) -> 0 | I35: =G35 -> 0
G36: =ROUND(D36*F36,0) -> 0 | I36: =G36 -> 0
G37: =ROUND(D37*F37,0) -> 0 | I37: =G37 -> 0
G38: =ROUND(D38*F38,0) -> 0 | I38: =G38 -> 0
G39: =ROUND(D39*F39,0) -> 0 | I39: =G39 -> 0
... G53: =ROUND(D53*F53,0) -> 0 | I53: =G53 -> 0
B55: SUBTOTAL Base Bid | G55: =SUBTOTAL(9,G21:G54) -> 167882 | I55: =SUBTOTAL(9,I21:I54) -> 167882 | K55: =SUBTOTAL(9,K21:K54) -> 0 | M55: =SUBTOTAL(9,M21:M54) -> 0 | O55: =SUM(O19:O54) -> 0 | Q55: =SUM(Q19:Q54) -> 0 | S55: =SUM(S19:S54) -> 0
B56: BOND RATE | H56: 0 | J56: 0 | L56: 0 | N56: 0 | P56: 0 | R56: 0
B57: BOND AMOUNT | G57: =F56*G55 -> 0 | I57: =H56*I55 -> 0 | K57: =J56*K55 -> 0 | M57: =L56*M55 -> 0 | O57: =N56*O55 -> 0 | Q57: =P56*Q55 -> 0 | S57: =R56*S55 -> 0
B59: ADJUSTED TOTAL | G59: =SUM(G55:G57) -> 167882 | I59: =SUM(I55:I57) -> 167882 | K59: =SUM(K55:K57) -> 0 | M59: =SUM(M55:M57) -> 0 | O59: =SUM(O55:O57) -> 0 | Q59: =SUM(Q55:Q57) -> 0 | S59: =SUM(S55:S57) -> 0
B60: Cost per SF | G60: =G59/'Area Calculations'!$G$5 -> 0.43121521 | I60: =I59/'Area Calculations'!$G$5 -> 0.43121521 | K60: =K59/'Area Calculations'!$G$5 -> 0 | M60: =M59/'Area Calculations'!$G$5 -> 0 | O60: =O59/'Area Calculations'!$G$5 -> 0 | Q60: =Q59/'Area Calculations'!$G$5 -> 0 | S60: =S59/'Area Calculations'!$G$5 -> 0
A62: QUALIFICATIONS
A66: EXCLUSIONS/OWNER PROVIDED ITEMS:
A70: ALTERNATES:
A74: PROPOSED VE (Provide Clear Description):
A78: FULLY LOADED LABOR RATES
B79: Laborer
B80: Mechanic
B81: Superintendent
B82: Project Manager
A84: SCHEDULE
B85: Prepared shop drawings/submittals
B86: Mobilization
B87: Total duration to complete scope of work
A89: Winner
A90: Company
A91: Contact
A92: Phone
A93: Email
A94: Base Bid | B94: =$M$59 -> 0
B96: Need Prequalification
B97: Prequalified

Sheet 09 29 Gypsum Board
G1: Hedrick Plug
F2: X | G2: Excluded
F3: I | G3: Included
B4: BACK TO SUMMARY SHEET | G4: Sub Add/Deduct
A5: Project: | B5: ='Area Calculations'!B4 -> Bourbon Hotel Orlando | G5: Company
A6: Trade: | B6: Drywall / Framing | G6: Contact
A7: CSI Code: | B7: 09 29 | G7: Phone
A8: Date: | G8: Email
G9: Adjusted Bid | H9: =I$55 -> 2590290 | J9: =K$55 -> 0 | L9: =M$55 -> 0 | N9: =O$55 -> 0 | P9: =Q$55 -> 0 | R9: =S$55 -> 0
A10: BID DOCUMENTS: | C10: Plan/ Spec. Package | D10: QTY | E10: U/M | F10: Unit Cost | G10: Subtotal | H10: Yes/No | I10: Price | J10: Yes/No | K10: Price | L10: Yes/No | M10: Price | N10: Yes/No | O10: Price | P10: Yes/No | Q10: Price | R10: Yes/No | S10: Price
B11: GENERAL INCLUSIONS
B12: INCLUDES ALL SALES TAX
B13: ALL HOISTING & RIGGING REQUIRED TO COMPLETE THIS SCOPE
B14: PROVIDE P&P BONDS
B15: FLORIDA STATE CONTRACTORS LIC.
B16: GENERAL LIABILITY AND WORKERS COMP. INSURANCE LIMITS
B17: STATE AND LOCAL TAXES
B18: SPECIFIC TRADE SCOPE OF WORK REQUIREMENTS
B19: BASE BID | U19: paint
B21: Exterior wall framing - light ga structural studs w/ densglass | D21: =SUM(D22:D26) -> 86343 | E21: sf | F21: 30 | G21: =ROUND(D21*F21,0) -> 2590290 | I21: =G21 -> 2590290
B22: Elevation - Back | D22: 21363 | E22: sf | G22: =ROUND(D22*F22,0) -> 0 | I22: =G22 -> 0
B23: Elevation - Front | D23: 19432 | E23: sf | G23: =ROUND(D23*F23,0) -> 0 | I23: =G23 -> 0
B24: Elevation - Left | D24: 34595 | E24: sf | G24: =ROUND(D24*F24,0) -> 0 | I24: =G24 -> 0
B25: Elevation - Right | D25: 35035 | E25: sf | G25: =ROUND(D25*F25,0) -> 0 | I25: =G25 -> 0
B26: less curtainwall | D26: =-'08 50 Storefront'!D22 -> -24082 | E26: sf | G26: =ROUND(D26*F26,0) -> 0 | I26: =G26 -> 0
G27: =ROUND(D27*F27,0) -> 0 | I27: =G27 -> 0
G28: =ROUND(D28*F28,0) -> 0 | I28: =G28 -> 0
G29: =ROUND(D29*F29,0) -> 0 | I29: =G29 -> 0
G30: =ROUND(D30*F30,0) -> 0 | I30: =G30 -> 0
G31: =ROUND(D31*F31,0) -> 0 | I31: =G31 -> 0
G32: =ROUND(D32*F32,0) -> 0 | I32: =G32 -> 0
G33: =ROUND(D33*F33,0) -> 0 | I33: =G33 -> 0
G34: =ROUND(D34*F34,0) -> 0 | I34: =G34 -> 0
G35: =ROUND(D35*F35,0) -> 0 | I35: =G35 -> 0
G36: =ROUND(D36*F36,0) -> 0 | I36: =G36 -> 0
G37: =ROUND(D37*F37,0) -> 0 | I37: =G37 -> 0
G38: =ROUND(D38*F38,0) -> 0 | I38: =G38 -> 0
... G49: =ROUND(D49*F49,0) -> 0 | I49: =G49 -> 0
B51: SUBTOTAL Base Bid | G51: =SUBTOTAL(9,G21:G50) -> 2590290 | I51: =SUBTOTAL(9,I21:I50) -> 2590290 | K51: =SUBTOTAL(9,K21:K50) -> 0 | M51: =SUBTOTAL(9,M21:M50) -> 0 | O51: =SUM(O19:O50) -> 0 | Q51: =SUM(Q19:Q50) -> 0 | S51: =SUM(S19:S50) -> 0
B52: BOND RATE | H52: 0 | J52: 0 | L52: 0 | N52: 0 | P52: 0 | R52: 0
B53: BOND AMOUNT | G53: =F52*G51 -> 0 | I53: =H52*I51 -> 0 | K53: =J52*K51 -> 0 | M53: =L52*M51 -> 0 | O53: =N52*O51 -> 0 | Q53: =P52*Q51 -> 0 | S53: =R52*S51 -> 0
B55: ADJUSTED TOTAL | G55: =SUM(G51:G53) -> 2590290 | I55: =SUM(I51:I53) -> 2590290 | K55: =SUM(K51:K53) -> 0 | M55: =SUM(M51:M53) -> 0 | O55: =SUM(O51:O53) -> 0 | Q55: =SUM(Q51:Q53) -> 0 | S55: =SUM(S51:S53) -> 0
B56: Cost per SF | G56: =G55/'Area Calculations'!$G$5 -> 6.6533187 | I56: =I55/'Area Calculations'!$G$5 -> 6.6533187 | K56: =K55/'Area Calculations'!$G$5 -> 0 | M56: =M55/'Area Calculations'!$G$5 -> 0 | O56: =O55/'Area Calculations'!$G$5 -> 0 | Q56: =Q55/'Area Calculations'!$G$5 -> 0 | S56: =S55/'Area Calculations'!$G$5 -> 0
A58: QUALIFICATIONS
A62: EXCLUSIONS/OWNER PROVIDED ITEMS:
A66: ALTERNATES:
A70: PROPOSED VE (Provide Clear Description):
A74: FULLY LOADED LABOR RATES
B75: Laborer
B76: Mechanic
B77: Superintendent
B78: Project Manager
A80: SCHEDULE
B81: Prepared shop drawings/submittals
B82: Mobilization
B83: Total duration to complete scope of work
A85: Winner
A86: Company
A87: Contact
A88: Phone
A89: Email
A90: Base Bid | B90: =$M$55 -> 0
B92: Need Prequalification
B93: Prequalified

Sheet 09 51 ACT
G1: Hedrick Plug
F2: X | G2: Excluded
F3: I | G3: Included
B4: BACK TO SUMMARY SHEET | G4: Sub Add/Deduct
A5: Project: | B5: ='Area Calculations'!B4 -> Bourbon Hotel Orlando | G5: Company | H5: Lotspeich Co.
A6: Trade: | B6: Acoustical Ceilings | G6: Contact | H6: Blake Whitley
A7: CSI Code: | B7: 09 41 | G7: Phone | H7: (561) 300-5056
A8: Date: | G8: Email | H8: blake.whitley@lcfinc.com
G9: Adjusted Bid | H9: =I$55 -> 0 | J9: =K$55 -> 0 | L9: =M$55 -> 0 | N9: =O$55 -> 0 | P9: =Q$55 -> 0 | R9: =S$55 -> 0
A10: BID DOCUMENTS: | C10: Plan/ Spec. Package | D10: QTY | E10: U/M | F10: Unit Cost | G10: Subtotal | H10: Yes/No | I10: Price | J10: Yes/No | K10: Price | L10: Yes/No | M10: Price | N10: Yes/No | O10: Price | P10: Yes/No | Q10: Price | R10: Yes/No | S10: Price
B11: GENERAL INCLUSIONS
B12: INCLUDES ALL SALES TAX
B13: ALL HOISTING & RIGGING REQUIRED TO COMPLETE THIS SCOPE
B14: PROVIDE P&P BONDS
B15: FLORIDA STATE CONTRACTORS LIC.
B16: GENERAL LIABILITY AND WORKERS COMP. INSURANCE LIMITS
B17: STATE AND LOCAL TAXES
B18: SPECIFIC TRADE SCOPE OF WORK REQUIREMENTS
B19: BASE BID
G21: =ROUND(D21*F21,0) -> 0 | I21: =G21 -> 0
G22: =ROUND(D22*F22,0) -> 0 | I22: =G22 -> 0
G23: =ROUND(D23*F23,0) -> 0 | I23: =G23 -> 0
G24: =ROUND(D24*F24,0) -> 0 | I24: =G24 -> 0
G25: =ROUND(D25*F25,0) -> 0 | I25: =G25 -> 0
G26: =ROUND(D26*F26,0) -> 0 | I26: =G26 -> 0
G27: =ROUND(D27*F27,0) -> 0 | I27: =G27 -> 0
G28: =ROUND(D28*F28,0) -> 0 | I28: =G28 -> 0
G29: =ROUND(D29*F29,0) -> 0 | I29: =G29 -> 0
G30: =ROUND(D30*F30,0) -> 0 | I30: =G30 -> 0
G31: =ROUND(D31*F31,0) -> 0 | I31: =G31 -> 0
G32: =ROUND(D32*F32,0) -> 0 | I32: =G32 -> 0
... G49: =ROUND(D49*F49,0) -> 0 | I49: =G49 -> 0
B51: SUBTOTAL Base Bid | G51: =SUBTOTAL(9,G21:G50) -> 0 | I51: =SUBTOTAL(9,I21:I50) -> 0 | K51: =SUM(K19:K50) -> 0 | M51: =SUM(M19:M50) -> 0 | O51: =SUM(O19:O50) -> 0 | Q51: =SUM(Q19:Q50) -> 0 | S51: =SUM(S19:S50) -> 0
B52: BOND RATE | H52: 0 | J52: 0 | L52: 0 | N52: 0 | P52: 0 | R52: 0
B53: BOND AMOUNT | G53: =F52*G51 -> 0 | I53: =H52*I51 -> 0 | K53: =J52*K51 -> 0 | M53: =L52*M51 -> 0 | O53: =N52*O51 -> 0 | Q53: =P52*Q51 -> 0 | S53: =R52*S51 -> 0
B55: ADJUSTED TOTAL | G55: =SUM(G51:G53) -> 0 | I55: =SUM(I51:I53) -> 0 | K55: =SUM(K51:K53) -> 0 | M55: =SUM(M51:M53) -> 0 | O55: =SUM(O51:O53) -> 0 | Q55: =SUM(Q51:Q53) -> 0 | S55: =SUM(S51:S53) -> 0
B56: Cost per SF | G56: =G55/'Area Calculations'!$G$5 -> 0 | I56: =I55/'Area Calculations'!$G$5 -> 0 | K56: =K55/'Area Calculations'!$G$5 -> 0 | M56: =M55/'Area Calculations'!$G$5 -> 0 | O56: =O55/'Area Calculations'!$G$5 -> 0 | Q56: =Q55/'Area Calculations'!$G$5 -> 0 | S56: =S55/'Area Calculations'!$G$5 -> 0
A58: QUALIFICATIONS
A62: EXCLUSIONS/OWNER PROVIDED ITEMS:
A66: ALTERNATES:
A70: PROPOSED VE (Provide Clear Description):
A74: FULLY LOADED LABOR RATES
B75: Laborer
B76: Mechanic
B77: Superintendent
B78: Project Manager
A80: SCHEDULE
B81: Prepared shop drawings/submittals
B82: Mobilization
B83: Total duration to complete scope of work
A85: Winner
A86: Company
A87: Contact
A88: Phone
A89: Email
A90: Base Bid | B90: =$I$55 -> 0
B92: Need Prequalification
B93: Prequalified

Sheet 09 60 Flooring
G1: Hedrick Plug
F2: X | G2: Excluded
F3: I | G3: Included
B4: BACK TO SUMMARY SHEET | G4: Sub Add/Deduct
A5: Project: | B5: ='Area Calculations'!B4 -> Bourbon Hotel Orlando | G5: Company
A6: Trade: | B6: Flooring | G6: Contact
A7: CSI Code: | B7: 09 60 00 | G7: Phone
A8: Date: | G8: Email
G9: Adjusted Bid | H9: =I$55 -> 0 | J9: =K$55 -> 0 | L9: =M$55 -> 0 | N9: =O$55 -> 0 | P9: =Q$55 -> 0 | R9: =S$55 -> 0
A10: BID DOCUMENTS: | C10: Plan/ Spec. Package | D10: QTY | E10: U/M | F10: Unit Cost | G10: Subtotal | H10: Yes/No | I10: Price | J10: Yes/No | K10: Price | L10: Yes/No | M10: Price | N10: Yes/No | O10: Price | P10: Yes/No | Q10: Price | R10: Yes/No | S10: Price
B11: GENERAL INCLUSIONS
B12: INCLUDES ALL SALES TAX
B13: ALL HOISTING & RIGGING REQUIRED TO COMPLETE THIS SCOPE
B14: PROVIDE P&P BONDS
B15: FLORIDA STATE CONTRACTORS LIC.
B16: GENERAL LIABILITY AND WORKERS COMP. INSURANCE LIMITS
B17: STATE AND LOCAL TAXES
B18: SPECIFIC TRADE SCOPE OF WORK REQUIREMENTS
B19: BASE BID
G21: =ROUND(D21*F21,0) -> 0 | I21: =G21 -> 0
G22: =ROUND(D22*F22,0) -> 0 | I22: =G22 -> 0
G23: =ROUND(D23*F23,0) -> 0 | I23: =G23 -> 0
G24: =ROUND(D24*F24,0) -> 0 | I24: =G24 -> 0
G25: =ROUND(D25*F25,0) -> 0 | I25: =G25 -> 0
G26: =ROUND(D26*F26,0) -> 0 | I26: =G26 -> 0
G27: =ROUND(D27*F27,0) -> 0 | I27: =G27 -> 0
G28: =ROUND(D28*F28,0) -> 0 | I28: =G28 -> 0
G29: =ROUND(D29*F29,0) -> 0 | I29: =G29 -> 0
G30: =ROUND(D30*F30,0) -> 0 | I30: =G30 -> 0
G31: =ROUND(D31*F31,0) -> 0 | I31: =G31 -> 0
G32: =ROUND(D32*F32,0) -> 0 | I32: =G32 -> 0
... G49: =ROUND(D49*F49,0) -> 0 | I49: =G49 -> 0
B51: SUBTOTAL Base Bid | G51: =SUBTOTAL(9,G21:G50) -> 0 | I51: =SUBTOTAL(9,I21:I50) -> 0 | K51: =SUM(K19:K50) -> 0 | M51: =SUM(M19:M50) -> 0 | O51: =SUM(O19:O50) -> 0 | Q51: =SUM(Q19:Q50) -> 0 | S51: =SUM(S19:S50) -> 0
B52: BOND RATE | H52: 0 | J52: 0 | L52: 0 | N52: 0 | P52: 0 | R52: 0
B53: BOND AMOUNT | G53: =F52*G51 -> 0 | I53: =H52*I51 -> 0 | K53: =J52*K51 -> 0 | M53: =L52*M51 -> 0 | O53: =N52*O51 -> 0 | Q53: =P52*Q51 -> 0 | S53: =R52*S51 -> 0
B55: ADJUSTED TOTAL | G55: =SUM(G51:G53) -> 0 | I55: =SUM(I51:I53) -> 0 | K55: =SUM(K51:K53) -> 0 | M55: =SUM(M51:M53) -> 0 | O55: =SUM(O51:O53) -> 0 | Q55: =SUM(Q51:Q53) -> 0 | S55: =SUM(S51:S53) -> 0
B56: Cost per SF | G56: =G55/'Area Calculations'!$G$5 -> 0 | I56: =I55/'Area Calculations'!$G$5 -> 0 | K56: =K55/'Area Calculations'!$G$5 -> 0 | M56: =M55/'Area Calculations'!$G$5 -> 0 | O56: =O55/'Area Calculations'!$G$5 -> 0 | Q56: =Q55/'Area Calculations'!$G$5 -> 0 | S56: =S55/'Area Calculations'!$G$5 -> 0
A58: QUALIFICATIONS
A62: EXCLUSIONS/OWNER PROVIDED ITEMS:
A66: ALTERNATES:
A70: PROPOSED VE (Provide Clear Description):
A74: FULLY LOADED LABOR RATES
B75: Laborer
B76: Mechanic
B77: Superintendent
B78: Project Manager
A80: SCHEDULE
B81: Prepared shop drawings/submittals
B82: Mobilization
B83: Total duration to complete scope of work
A85: Winner
A86: Company
A87: Contact
A88: Phone
A89: Email
A90: Base Bid | B90: =$I$55 -> 0
B92: Need Prequalification
B93: Prequalified

Sheet 09 90 Painting
G1: Hedrick Plug
F2: X | G2: Excluded
F3: I | G3: Included
B4: BACK TO SUMMARY SHEET | G4: Sub Add/Deduct
A5: Project: | B5: ='Area Calculations'!B4 -> Bourbon Hotel Orlando | G5: Company
A6: Trade: | B6: Painting | G6: Contact
A7: CSI Code: | B7: 09 90 00 | G7: Phone
A8: Date: | G8: Email
G9: Adjusted Bid | H9: =I$55 -> 29702 | J9: =K$55 -> 0 | L9: =M$55 -> 0 | N9: =O$55 -> 0 | P9: =Q$55 -> 0 | R9: =S$55 -> 0
A10: BID DOCUMENTS: | C10: Plan/ Spec. Package | D10: QTY | E10: U/M | F10: Unit Cost | G10: Subtotal | H10: Yes/No | I10: Price | J10: Yes/No | K10: Price | L10: Yes/No | M10: Price | N10: Yes/No | O10: Price | P10: Yes/No | Q10: Price | R10: Yes/No | S10: Price
B11: GENERAL INCLUSIONS
B12: INCLUDES ALL SALES TAX
B13: ALL HOISTING & RIGGING REQUIRED TO COMPLETE THIS SCOPE
B14: PROVIDE P&P BONDS
B15: FLORIDA STATE CONTRACTORS LIC.
B16: GENERAL LIABILITY AND WORKERS COMP. INSURANCE LIMITS
B17: STATE AND LOCAL TAXES
B18: SPECIFIC TRADE SCOPE OF WORK REQUIREMENTS
B19: BASE BID
B21: Exterior | G21: =ROUND(D14*F21,0) -> 0 | I21: =G21 -> 0
B22: stucco | D22: ='09 24 Stucco'!D21 -> 25828 | E22: sf | F22: 1.15 | G22: =ROUND(D22*F22,0) -> 29702 | I22: =G22 -> 29702
G23: =ROUND(D16*F23,0) -> 0 | I23: =G23 -> 0
G24: =ROUND(D24*F24,0) -> 0 | I24: =G24 -> 0
G25: =ROUND(D18*F25,0) -> 0 | I25: =G25 -> 0
G26: =ROUND(D26*F26,0) -> 0 | I26: =G26 -> 0
G27: =ROUND(D20*F27,0) -> 0 | I27: =G27 -> 0
G28: =ROUND(D28*F28,0) -> 0 | I28: =G28 -> 0
G29: =ROUND(D22*F29,0) -> 0 | I29: =G29 -> 0
G30: =ROUND(D30*F30,0) -> 0 | I30: =G30 -> 0
G31: =ROUND(D31*F31,0) -> 0 | I31: =G31 -> 0
G32: =ROUND(D32*F32,0) -> 0 | I32: =G32 -> 0
G33: =ROUND(D33*F33,0) -> 0 | I33: =G33 -> 0
G34: =ROUND(D34*F34,0) -> 0 | I34: =G34 -> 0
G35: =ROUND(D35*F35,0) -> 0 | I35: =G35 -> 0
G36: =ROUND(D36*F36,0) -> 0 | I36: =G36 -> 0
G37: =ROUND(D37*F37,0) -> 0 | I37: =G37 -> 0
G38: =ROUND(D38*F38,0) -> 0 | I38: =G38 -> 0
G39: =ROUND(D39*F39,0) -> 0 | I39: =G39 -> 0
G40: =ROUND(D40*F40,0) -> 0 | I40: =G40 -> 0
G41: =ROUND(D41*F41,0) -> 0 | I41: =G41 -> 0
... G49: =ROUND(D49*F49,0) -> 0 | I49: =G49 -> 0
B51: SUBTOTAL Base Bid | G51: =SUBTOTAL(9,G21:G50) -> 29702 | I51: =SUBTOTAL(9,I21:I50) -> 29702 | K51: =SUM(K19:K50) -> 0 | M51: =SUM(M19:M50) -> 0 | O51: =SUM(O19:O50) -> 0 | Q51: =SUM(Q19:Q50) -> 0 | S51: =SUM(S19:S50) -> 0
B52: BOND RATE | H52: 0 | J52: 0 | L52: 0 | N52: 0 | P52: 0 | R52: 0
B53: BOND AMOUNT | G53: =F52*G51 -> 0 | I53: =H52*I51 -> 0 | K53: =J52*K51 -> 0 | M53: =L52*M51 -> 0 | O53: =N52*O51 -> 0 | Q53: =P52*Q51 -> 0 | S53: =R52*S51 -> 0
B55: ADJUSTED TOTAL | G55: =SUM(G51:G53) -> 29702 | I55: =SUM(I51:I53) -> 29702 | K55: =SUM(K51:K53) -> 0 | M55: =SUM(M51:M53) -> 0 | O55: =SUM(O51:O53) -> 0 | Q55: =SUM(Q51:Q53) -> 0 | S55: =SUM(S51:S53) -> 0
B56: Cost per SF | G56: =G55/'Area Calculations'!$G$5 -> 0.076291408 | I56: =I55/'Area Calculations'!$G$5 -> 0.076291408 | K56: =K55/'Area Calculations'!$G$5 -> 0 | M56: =M55/'Area Calculations'!$G$5 -> 0 | O56: =O55/'Area Calculations'!$G$5 -> 0 | Q56: =Q55/'Area Calculations'!$G$5 -> 0 | S56: =S55/'Area Calculations'!$G$5 -> 0
A58: QUALIFICATIONS
A62: EXCLUSIONS/OWNER PROVIDED ITEMS:
A66: ALTERNATES:
A70: PROPOSED VE (Provide Clear Description):
A74: FULLY LOADED LABOR RATES
B75: Laborer
B76: Mechanic
B77: Superintendent
B78: Project Manager
A80: SCHEDULE
B81: Prepared shop drawings/submittals
B82: Mobilization
B83: Total duration to complete scope of work
A85: Winner
A86: Company
A87: Contact
A88: Phone
A89: Email
A90: Base Bid | B90: =$I$55 -> 29702
B92: Need Prequalification
B93: Prequalified

Sheet 10 28 Specialties
G1: Hedrick Plug
F2: X | G2: Excluded
F3: I | G3: Included
B4: BACK TO SUMMARY SHEET | G4: Sub Add/Deduct
A5: Project: | B5: ='Area Calculations'!B4 -> Bourbon Hotel Orlando | G5: Company
A6: Trade: | B6: Specialties | G6: Contact
A7: CSI Code: | B7: 10 28 00 | G7: Phone
A8: Date: | G8: Email
G9: Adjusted Bid | H9: =I$55 -> 0 | J9: =K$55 -> 0 | L9: =M$55 -> 0 | N9: =O$55 -> 0 | P9: =Q$55 -> 0 | R9: =S$55 -> 0
A10: BID DOCUMENTS: | C10: Plan/ Spec. Package | D10: QTY | E10: U/M | F10: Unit Cost | G10: Subtotal | H10: Yes/No | I10: Price | J10: Yes/No | K10: Price | L10: Yes/No | M10: Price | N10: Yes/No | O10: Price | P10: Yes/No | Q10: Price | R10: Yes/No | S10: Price
B11: GENERAL INCLUSIONS
B12: INCLUDES ALL SALES TAX
B13: ALL HOISTING & RIGGING REQUIRED TO COMPLETE THIS SCOPE
B14: PROVIDE P&P BONDS
B15: FLORIDA STATE CONTRACTORS LIC.
B16: GENERAL LIABILITY AND WORKERS COMP. INSURANCE LIMITS
B17: STATE AND LOCAL TAXES
B18: SPECIFIC TRADE SCOPE OF WORK REQUIREMENTS
B19: BASE BID
G21: =ROUND(D21*F21,0) -> 0 | I21: =G21 -> 0
G22: =ROUND(D22*F22,0) -> 0 | I22: =G22 -> 0
G23: =ROUND(D23*F23,0) -> 0 | I23: =G23 -> 0
G24: =ROUND(D24*F24,0) -> 0 | I24: =G24 -> 0
G25: =ROUND(D25*F25,0) -> 0 | I25: =G25 -> 0
G26: =ROUND(D26*F26,0) -> 0 | I26: =G26 -> 0
G27: =ROUND(D27*F27,0) -> 0 | I27: =G27 -> 0
G28: =ROUND(D28*F28,0) -> 0 | I28: =G28 -> 0
G29: =ROUND(D29*F29,0) -> 0 | I29: =G29 -> 0
G30: =ROUND(D30*F30,0) -> 0 | I30: =G30 -> 0
G31: =ROUND(D31*F31,0) -> 0 | I31: =G31 -> 0
G32: =ROUND(D32*F32,0) -> 0 | I32: =G32 -> 0
... G49: =ROUND(D49*F49,0) -> 0 | I49: =G49 -> 0
B51: SUBTOTAL Base Bid | G51: =SUBTOTAL(9,G21:G50) -> 0 | I51: =SUBTOTAL(9,I21:I50) -> 0 | K51: =SUM(K19:K50) -> 0 | M51: =SUM(M19:M50) -> 0 | O51: =SUM(O19:O50) -> 0 | Q51: =SUM(Q19:Q50) -> 0 | S51: =SUM(S19:S50) -> 0
B52: BOND RATE | H52: 0 | J52: 0 | L52: 0 | N52: 0 | P52: 0 | R52: 0
B53: BOND AMOUNT | G53: =F52*G51 -> 0 | I53: =H52*I51 -> 0 | K53: =J52*K51 -> 0 | M53: =L52*M51 -> 0 | O53: =N52*O51 -> 0 | Q53: =P52*Q51 -> 0 | S53: =R52*S51 -> 0
B55: ADJUSTED TOTAL | G55: =SUM(G51:G53) -> 0 | I55: =SUM(I51:I53) -> 0 | K55: =SUM(K51:K53) -> 0 | M55: =SUM(M51:M53) -> 0 | O55: =SUM(O51:O53) -> 0 | Q55: =SUM(Q51:Q53) -> 0 | S55: =SUM(S51:S53) -> 0
B56: Cost per SF | G56: =G55/'Area Calculations'!$G$5 -> 0 | I56: =I55/'Area Calculations'!$G$5 -> 0 | K56: =K55/'Area Calculations'!$G$5 -> 0 | M56: =M55/'Area Calculations'!$G$5 -> 0 | O56: =O55/'Area Calculations'!$G$5 -> 0 | Q56: =Q55/'Area Calculations'!$G$5 -> 0 | S56: =S55/'Area Calculations'!$G$5 -> 0
A58: QUALIFICATIONS
A62: EXCLUSIONS/OWNER PROVIDED ITEMS:
A66: ALTERNATES:
A70: PROPOSED VE (Provide Clear Description):
A74: FULLY LOADED LABOR RATES
B75: Laborer
B76: Mechanic
B77: Superintendent
B78: Project Manager
A80: SCHEDULE
B81: Prepared shop drawings/submittals
B82: Mobilization
B83: Total duration to complete scope of work
A85: Winner
A86: Company
A87: Contact
A88: Phone
A89: Email
A90: Base Bid | B90: =$I$55 -> 0
B92: Need Prequalification
B93: Prequalified

Sheet 10 22 Operable Partitions
G1: Hedrick Plug
G2: Excluded
B3: BACK TO SUMMARY SHEET | G3: Included | H3: Bidder 1 | J3: Bidder 2 | L3: Bidder 3 | N3: Bidder 4 | P3: Bidder5 | R3: Bidder6
A4: Project: | B4: ='Area Calculations'!B4 -> Bourbon Hotel Orlando | G4: Company
A5: Trade: | B5: Operable Partitions | G5: Contact
A6: CSI Code: | B6: 10 22 | G6: Phone
A7: Date: | G7: Email
A8: Adjusted Bid | G8: Adjusted Bid | H8: =I70 -> 0 | J8: =K70 -> 0 | L8: =M70 -> 0 | N8: =O70 -> 0 | P8: =Q70 -> 0 | R8: =S70 -> 0
A9: BID DOCUMENTS: | C9: Plan/ Spec. Package | D9: QTY | E9: U/M | F9: Unit Cost | G9: Subtotal | H9: Yes/No | I9: Price | J9: Yes/No | K9: Price | L9: Yes/No | M9: Price | N9: Yes/No | O9: Price | P9: Yes/No | Q9: Price | R9: Yes/No | S9: Price
B10: Plans By Division
B11: ='Area Calculations'!#REF! -> #REF! | C11: P
B12: ='Area Calculations'!#REF! -> #REF! | C12: P
B13: ='Area Calculations'!#REF! -> #REF! | C13: P
B14: ='Area Calculations'!#REF! -> #REF! | C14: P
B15: ='Area Calculations'!#REF! -> #REF! | C15: P
B16: ='Area Calculations'!#REF! -> #REF! | C16: P
B17: ='Area Calculations'!#REF! -> #REF! | C17: P
B18: ='Area Calculations'!#REF! -> #REF! | C18: P
B19: ='Area Calculations'!#REF! -> #REF! | C19: P
B21: Operable Partitions
B22: GENERAL INCLUSIONS
B23: INCLUDES ALL SALES TAX
B24: ALL HOISTING & RIGGING REQUIRED TO COMPLETE THIS SCOPE
B25: PROVIDE P&P BONDS
B26: FLORIDA STATE CONTRACTORS LIC.
B27: GENERAL LIABILITY AND WORKERS COMP. INSURANCE LIMITS
B28: STATE AND LOCAL TAXES
B29: SPECIFIC TRADE SCOPE OF WORK REQUIREMENTS
B30: BASE BID
F66: SUBTOTAL | I66: =SUM(I23:I65) -> 0 | K66: =SUM(K23:K65) -> 0 | M66: =SUM(M23:M65) -> 0 | O66: =SUM(O23:O65) -> 0 | Q66: =SUM(Q23:Q65) -> 0 | S66: =SUM(S23:S65) -> 0
F67: BOND RATE | H67: 0 | J67: 0 | L67: 0 | N67: 0 | P67: 0 | R67: 0
F68: BOND AMOUNT | I68: =H67*I66 -> 0 | K68: =J67*K66 -> 0 | M68: =L67*M66 -> 0 | O68: =N67*O66 -> 0 | Q68: =P67*Q66 -> 0 | S68: =R67*S66 -> 0
F70: ADJUSTED TOTAL | I70: =SUM(I66:I68) -> 0 | K70: =SUM(K66:K68) -> 0 | M70: =SUM(M66:M68) -> 0 | O70: =SUM(O66:O68) -> 0 | Q70: =SUM(Q66:Q68) -> 0 | S70: =SUM(S66:S68) -> 0
F71: Cost per SF | I71: =I70/'Area Calculations'!$G$5 -> 0 | K71: =K70/'Area Calculations'!$G$5 -> 0 | M71: =M70/'Area Calculations'!$G$5 -> 0 | O71: =O70/'Area Calculations'!$G$5 -> 0 | Q71: =Q70/'Area Calculations'!$G$5 -> 0 | S71: =S70/'Area Calculations'!$G$5 -> 0
F72: Cost per Unit | I72: =I70/'Area Calculations'!$G$9 -> 0 | K72: =K70/'Area Calculations'!$G$9 -> 0 | M72: =M70/'Area Calculations'!$G$9 -> 0 | O72: =O70/'Area Calculations'!$G$9 -> 0 | Q72: =Q70/'Area Calculations'!$G$9 -> 0 | S72: =S70/'Area Calculations'!$G$9 -> 0
A74: QUALIFICATIONS
A78: EXCLUSIONS/OWNER PROVIDED ITEMS:
A82: ALTERNATES:
A86: PROPOSED VE (Provide Clear Description):
A90: FULLY LOADED LABOR RATES
B91: Laborer
B92: Mechanic
B93: Superintendent
B94: Project Manager
A96: SCHEDULE
B97: Prepared shop drawings/submittals
B98: Mobilization
B99: Total duration to complete scope of work
A101: Winner
A102: Company
A103: Contact
A104: Phone
A105: Email
A106: Base Bid
B108: Need Prequalification
B109: Prequalified

Sheet 10 30 Fireplace
G1: Hedrick Plug
G2: Excluded
B3: BACK TO SUMMARY SHEET | G3: Included | H3: Bidder 1 | J3: Bidder 2 | L3: Bidder 3 | N3: Bidder 4 | P3: Bidder5 | R3: Bidder6
A4: Project: | B4: ='Area Calculations'!B4 -> Bourbon Hotel Orlando | G4: Company
A5: Trade: | B5: Fireplace | G5: Contact
A6: CSI Code: | B6: 10 30 | G6: Phone
A7: Date: | G7: Email
A8: Adjusted Bid | G8: Adjusted Bid | H8: =I70 -> 0 | J8: =K70 -> 0 | L8: =M70 -> 0 | N8: =O70 -> 0 | P8: =Q70 -> 0 | R8: =S70 -> 0
A9: BID DOCUMENTS: | C9: Plan/ Spec. Package | D9: QTY | E9: U/M | F9: Unit Cost | G9: Subtotal | H9: Yes/No | I9: Price | J9: Yes/No | K9: Price | L9: Yes/No | M9: Price | N9: Yes/No | O9: Price | P9: Yes/No | Q9: Price | R9: Yes/No | S9: Price
B10: Plans By Division
B11: ='Area Calculations'!#REF! -> #REF! | C11: P
B12: ='Area Calculations'!#REF! -> #REF! | C12: P
B13: ='Area Calculations'!#REF! -> #REF! | C13: P
B14: ='Area Calculations'!#REF! -> #REF! | C14: P
B15: ='Area Calculations'!#REF! -> #REF! | C15: P
B16: ='Area Calculations'!#REF! -> #REF! | C16: P
B17: ='Area Calculations'!#REF! -> #REF! | C17: P
B18: ='Area Calculations'!#REF! -> #REF! | C18: P
B19: ='Area Calculations'!#REF! -> #REF! | C19: P
B21: Fireplace
B22: GENERAL INCLUSIONS
B23: INCLUDES ALL SALES TAX
B24: ALL HOISTING & RIGGING REQUIRED TO COMPLETE THIS SCOPE
B25: PROVIDE P&P BONDS
B26: FLORIDA STATE CONTRACTORS LIC.
B27: GENERAL LIABILITY AND WORKERS COMP. INSURANCE LIMITS
B28: STATE AND LOCAL TAXES
B29: SPECIFIC TRADE SCOPE OF WORK REQUIREMENTS
B30: BASE BID
F66: SUBTOTAL | I66: =SUM(I23:I65) -> 0 | K66: =SUM(K23:K65) -> 0 | M66: =SUM(M23:M65) -> 0 | O66: =SUM(O23:O65) -> 0 | Q66: =SUM(Q23:Q65) -> 0 | S66: =SUM(S23:S65) -> 0
F67: BOND RATE | H67: 0 | J67: 0 | L67: 0 | N67: 0 | P67: 0 | R67: 0
F68: BOND AMOUNT | I68: =H67*I66 -> 0 | K68: =J67*K66 -> 0 | M68: =L67*M66 -> 0 | O68: =N67*O66 -> 0 | Q68: =P67*Q66 -> 0 | S68: =R67*S66 -> 0
F70: ADJUSTED TOTAL | I70: =SUM(I66:I68) -> 0 | K70: =SUM(K66:K68) -> 0 | M70: =SUM(M66:M68) -> 0 | O70: =SUM(O66:O68) -> 0 | Q70: =SUM(Q66:Q68) -> 0 | S70: =SUM(S66:S68) -> 0
F71: Cost per SF | I71: =I70/'Area Calculations'!$G$5 -> 0 | K71: =K70/'Area Calculations'!$G$5 -> 0 | M71: =M70/'Area Calculations'!$G$5 -> 0 | O71: =O70/'Area Calculations'!$G$5 -> 0 | Q71: =Q70/'Area Calculations'!$G$5 -> 0 | S71: =S70/'Area Calculations'!$G$5 -> 0
F72: Cost per Unit | I72: =I70/'Area Calculations'!$G$9 -> 0 | K72: =K70/'Area Calculations'!$G$9 -> 0 | M72: =M70/'Area Calculations'!$G$9 -> 0 | O72: =O70/'Area Calculations'!$G$9 -> 0 | Q72: =Q70/'Area Calculations'!$G$9 -> 0 | S72: =S70/'Area Calculations'!$G$9 -> 0
A74: QUALIFICATIONS
A78: EXCLUSIONS/OWNER PROVIDED ITEMS:
A82: ALTERNATES:
A86: PROPOSED VE (Provide Clear Description):
A90: FULLY LOADED LABOR RATES
B91: Laborer
B92: Mechanic
B93: Superintendent
B94: Project Manager
A96: SCHEDULE
B97: Prepared shop drawings/submittals
B98: Mobilization
B99: Total duration to complete scope of work
A101: Winner
A102: Company
A103: Contact
A104: Phone
A105: Email
A106: Base Bid
B108: Need Prequalification
B109: Prequalified

Sheet 11 11 Laundry Equip.
G1: Hedrick Plug
G2: Excluded
B3: BACK TO SUMMARY SHEET | G3: Included | H3: Bidder 1 | J3: Bidder 2 | L3: Bidder 3 | N3: Bidder 4 | P3: Bidder5 | R3: Bidder6
A4: Project: | B4: ='Area Calculations'!B4 -> Bourbon Hotel Orlando | G4: Company
A5: Trade: | B5: Laundry Equipment | G5: Contact
A6: CSI Code: | B6: 11 11 | G6: Phone
A7: Date: | G7: Email
A8: Adjusted Bid | G8: Adjusted Bid | H8: =I51 -> 0 | J8: =K51 -> 0 | L8: =M51 -> 0 | N8: =O51 -> 0 | P8: =Q51 -> 0 | R8: =S51 -> 0
A9: BID DOCUMENTS: | C9: Plan/ Spec. Package | D9: QTY | E9: U/M | F9: Unit Cost | G9: Subtotal | H9: Yes/No | I9: Price | J9: Yes/No | K9: Price | L9: Yes/No | M9: Price | N9: Yes/No | O9: Price | P9: Yes/No | Q9: Price | R9: Yes/No | S9: Price
B10: Plans By Division
B11: ='Area Calculations'!#REF! -> #REF! | C11: P
B12: ='Area Calculations'!#REF! -> #REF! | C12: P
B13: ='Area Calculations'!#REF! -> #REF! | C13: P
B14: ='Area Calculations'!#REF! -> #REF! | C14: P
B15: ='Area Calculations'!#REF! -> #REF! | C15: P
B16: ='Area Calculations'!#REF! -> #REF! | C16: P
B17: ='Area Calculations'!#REF! -> #REF! | C17: P
B18: ='Area Calculations'!#REF! -> #REF! | C18: P
B19: ='Area Calculations'!#REF! -> #REF! | C19: P
B21: Laundry Equipment
B22: GENERAL INCLUSIONS
B23: INCLUDES ALL SALES TAX
B24: ALL HOISTING & RIGGING REQUIRED TO COMPLETE THIS SCOPE
B25: PROVIDE P&P BONDS
B26: FLORIDA STATE CONTRACTORS LIC.
B27: GENERAL LIABILITY AND WORKERS COMP. INSURANCE LIMITS
B28: STATE AND LOCAL TAXES
B29: SPECIFIC TRADE SCOPE OF WORK REQUIREMENTS
B30: BASE BID
F47: SUBTOTAL | I47: =SUM(I23:I46) -> 0 | K47: =SUM(K23:K46) -> 0 | M47: =SUM(M23:M46) -> 0 | O47: =SUM(O23:O46) -> 0 | Q47: =SUM(Q23:Q46) -> 0 | S47: =SUM(S23:S46) -> 0
F48: BOND RATE | H48: 0 | J48: 0 | L48: 0 | N48: 0 | P48: 0 | R48: 0
F49: BOND AMOUNT | I49: =H48*I47 -> 0 | K49: =J48*K47 -> 0 | M49: =L48*M47 -> 0 | O49: =N48*O47 -> 0 | Q49: =P48*Q47 -> 0 | S49: =R48*S47 -> 0
F51: ADJUSTED TOTAL | I51: =SUM(I47:I49) -> 0 | K51: =SUM(K47:K49) -> 0 | M51: =SUM(M47:M49) -> 0 | O51: =SUM(O47:O49) -> 0 | Q51: =SUM(Q47:Q49) -> 0 | S51: =SUM(S47:S49) -> 0
F52: Cost per SF | I52: =I51/'Area Calculations'!$G$5 -> 0 | K52: =K51/'Area Calculations'!$G$5 -> 0 | M52: =M51/'Area Calculations'!$G$5 -> 0 | O52: =O51/'Area Calculations'!$G$5 -> 0 | Q52: =Q51/'Area Calculations'!$G$5 -> 0 | S52: =S51/'Area Calculations'!$G$5 -> 0
F53: Cost per Unit | I53: =I51/'Area Calculations'!$G$9 -> 0 | K53: =K51/'Area Calculations'!$G$9 -> 0 | M53: =M51/'Area Calculations'!$G$9 -> 0 | O53: =O51/'Area Calculations'!$G$9 -> 0 | Q53: =Q51/'Area Calculations'!$G$9 -> 0 | S53: =S51/'Area Calculations'!$G$9 -> 0
A55: QUALIFICATIONS
A59: EXCLUSIONS/OWNER PROVIDED ITEMS:
A63: ALTERNATES:
A67: PROPOSED VE (Provide Clear Description):
A71: FULLY LOADED LABOR RATES
B72: Laborer
B73: Mechanic
B74: Superintendent
B75: Project Manager
A77: SCHEDULE
B78: Prepared shop drawings/submittals
B79: Mobilization
B80: Total duration to complete scope of work
A82: Winner
A83: Company
A84: Contact
A85: Phone
A86: Email
A87: Base Bid
B89: Need Prequalification
B90: Prequalified

Sheet 10 53 Signage
G1: Hedrick Plug
F2: X | G2: Excluded
F3: I | G3: Included
B4: BACK TO SUMMARY SHEET | G4: Sub Add/Deduct
A5: Project: | B5: ='Area Calculations'!B4 -> Bourbon Hotel Orlando | G5: Company
A6: Trade: | B6: Signage | G6: Contact
A7: CSI Code: | B7: 10 53 00 | G7: Phone
A8: Date: | G8: Email
G9: Adjusted Bid | H9: =I$55 -> 312233 | J9: =K$55 -> 0 | L9: =M$55 -> 0 | N9: =O$55 -> 0 | P9: =Q$55 -> 0 | R9: =S$55 -> 0
A10: BID DOCUMENTS: | C10: Plan/ Spec. Package | D10: QTY | E10: U/M | F10: Unit Cost | G10: Subtotal | H10: Yes/No | I10: Price | J10: Yes/No | K10: Price | L10: Yes/No | M10: Price | N10: Yes/No | O10: Price | P10: Yes/No | Q10: Price | R10: Yes/No | S10: Price
B11: GENERAL INCLUSIONS
B12: INCLUDES ALL SALES TAX
B13: ALL HOISTING & RIGGING REQUIRED TO COMPLETE THIS SCOPE
B14: PROVIDE P&P BONDS
B15: FLORIDA STATE CONTRACTORS LIC.
B16: GENERAL LIABILITY AND WORKERS COMP. INSURANCE LIMITS
B17: STATE AND LOCAL TAXES
B18: SPECIFIC TRADE SCOPE OF WORK REQUIREMENTS
B19: BASE BID
B21: Signage - common areas, units | D21: 390291 | E21: sf | F21: 0.8 | G21: =ROUND(D21*F21,0) -> 312233 | I21: =G21 -> 312233
G22: =ROUND(D22*F22,0) -> 0 | I22: =G22 -> 0
G23: =ROUND(D23*F23,0) -> 0 | I23: =G23 -> 0
G24: =ROUND(D24*F24,0) -> 0 | I24: =G24 -> 0
G25: =ROUND(D25*F25,0) -> 0 | I25: =G25 -> 0
G26: =ROUND(D26*F26,0) -> 0 | I26: =G26 -> 0
G27: =ROUND(D27*F27,0) -> 0 | I27: =G27 -> 0
G28: =ROUND(D28*F28,0) -> 0 | I28: =G28 -> 0
G29: =ROUND(D29*F29,0) -> 0 | I29: =G29 -> 0
G30: =ROUND(D30*F30,0) -> 0 | I30: =G30 -> 0
G31: =ROUND(D31*F31,0) -> 0 | I31: =G31 -> 0
G32: =ROUND(D32*F32,0) -> 0 | I32: =G32 -> 0
G33: =ROUND(D33*F33,0) -> 0 | I33: =G33 -> 0
... G48: =ROUND(D48*F48,0) -> 0 | I48: =G48 -> 0
B51: SUBTOTAL Base Bid | G51: =SUBTOTAL(9,G21:G50) -> 312233 | I51: =SUBTOTAL(9,I21:I50) -> 312233 | K51: =SUM(K19:K50) -> 0 | M51: =SUM(M19:M50) -> 0 | O51: =SUM(O19:O50) -> 0 | Q51: =SUM(Q19:Q50) -> 0 | S51: =SUM(S19:S50) -> 0
B52: BOND RATE | H52: 0 | J52: 0 | L52: 0 | N52: 0 | P52: 0 | R52: 0
B53: BOND AMOUNT | G53: =F52*G51 -> 0 | I53: =H52*I51 -> 0 | K53: =J52*K51 -> 0 | M53: =L52*M51 -> 0 | O53: =N52*O51 -> 0 | Q53: =P52*Q51 -> 0 | S53: =R52*S51 -> 0
B55: ADJUSTED TOTAL | G55: =SUM(G51:G53) -> 312233 | I55: =SUM(I51:I53) -> 312233 | K55: =SUM(K51:K53) -> 0 | M55: =SUM(M51:M53) -> 0 | O55: =SUM(O51:O53) -> 0 | Q55: =SUM(Q51:Q53) -> 0 | S55: =SUM(S51:S53) -> 0
B56: Cost per SF | G56: =G55/'Area Calculations'!$G$5 -> 0.80198961 | I56: =I55/'Area Calculations'!$G$5 -> 0.80198961 | K56: =K55/'Area Calculations'!$G$5 -> 0 | M56: =M55/'Area Calculations'!$G$5 -> 0 | O56: =O55/'Area Calculations'!$G$5 -> 0 | Q56: =Q55/'Area Calculations'!$G$5 -> 0 | S56: =S55/'Area Calculations'!$G$5 -> 0
A58: QUALIFICATIONS
A62: EXCLUSIONS/OWNER PROVIDED ITEMS:
A66: ALTERNATES:
A70: PROPOSED VE (Provide Clear Description):
A74: FULLY LOADED LABOR RATES
B75: Laborer
B76: Mechanic
B77: Superintendent
B78: Project Manager
A80: SCHEDULE
B81: Prepared shop drawings/submittals
B82: Mobilization
B83: Total duration to complete scope of work
A85: Winner
A86: Company
A87: Contact
A88: Phone
A89: Email
A90: Base Bid | B90: =$I$55 -> 312233
B92: Need Prequalification
B93: Prequalified

Sheet 12 30 Wall Protection
G1: Hedrick Plug
G2: Excluded
B3: BACK TO SUMMARY SHEET | G3: Included | H3: Bidder 1 | J3: Bidder 2 | L3: Bidder 3 | N3: Bidder 4 | P3: Bidder5 | R3: Bidder6
A4: Project: | B4: ='Area Calculations'!B4 -> Bourbon Hotel Orlando | G4: Company
A5: Trade: | B5: Wall Protection | G5: Contact
A6: CSI Code: | B6: 12 30 | G6: Phone
A7: Date: | G7: Email
A8: Adjusted Bid | G8: Adjusted Bid | H8: =I52 -> 0 | J8: =K52 -> 0 | L8: =M52 -> 0 | N8: =O52 -> 0 | P8: =Q52 -> 0 | R8: =S52 -> 0
A9: BID DOCUMENTS: | C9: Plan/ Spec. Package | D9: QTY | E9: U/M | F9: Unit Cost | G9: Subtotal | H9: Yes/No | I9: Price | J9: Yes/No | K9: Price | L9: Yes/No | M9: Price | N9: Yes/No | O9: Price | P9: Yes/No | Q9: Price | R9: Yes/No | S9: Price
B10: Plans By Division
B11: ='Area Calculations'!#REF! -> #REF! | C11: P
B12: ='Area Calculations'!#REF! -> #REF! | C12: P
B13: ='Area Calculations'!#REF! -> #REF! | C13: P
B14: ='Area Calculations'!#REF! -> #REF! | C14: P
B15: ='Area Calculations'!#REF! -> #REF! | C15: P
B16: ='Area Calculations'!#REF! -> #REF! | C16: P
B17: ='Area Calculations'!#REF! -> #REF! | C17: P
B18: ='Area Calculations'!#REF! -> #REF! | C18: P
B19: ='Area Calculations'!#REF! -> #REF! | C19: P
B21: Wall Protection
B22: GENERAL INCLUSIONS
B23: INCLUDES ALL SALES TAX
B24: ALL HOISTING & RIGGING REQUIRED TO COMPLETE THIS SCOPE
B25: PROVIDE P&P BONDS
B26: FLORIDA STATE CONTRACTORS LIC.
B27: GENERAL LIABILITY AND WORKERS COMP. INSURANCE LIMITS
B28: STATE AND LOCAL TAXES
B29: SPECIFIC TRADE SCOPE OF WORK REQUIREMENTS
B30: BASE BID
F48: SUBTOTAL | I48: =SUM(I23:I47) -> 0 | K48: =SUM(K23:K47) -> 0 | M48: =SUM(M23:M47) -> 0 | O48: =SUM(O23:O47) -> 0 | Q48: =SUM(Q23:Q47) -> 0 | S48: =SUM(S23:S47) -> 0
F49: BOND RATE | H49: 0 | J49: 0 | L49: 0 | N49: 0 | P49: 0 | R49: 0
F50: BOND AMOUNT | I50: =H49*I48 -> 0 | K50: =J49*K48 -> 0 | M50: =L49*M48 -> 0 | O50: =N49*O48 -> 0 | Q50: =P49*Q48 -> 0 | S50: =R49*S48 -> 0
F52: ADJUSTED TOTAL | I52: =SUM(I48:I50) -> 0 | K52: =SUM(K48:K50) -> 0 | M52: =SUM(M48:M50) -> 0 | O52: =SUM(O48:O50) -> 0 | Q52: =SUM(Q48:Q50) -> 0 | S52: =SUM(S48:S50) -> 0
F53: Cost per SF | I53: =I52/'Area Calculations'!$G$5 -> 0 | K53: =K52/'Area Calculations'!$G$5 -> 0 | M53: =M52/'Area Calculations'!$G$5 -> 0 | O53: =O52/'Area Calculations'!$G$5 -> 0 | Q53: =Q52/'Area Calculations'!$G$5 -> 0 | S53: =S52/'Area Calculations'!$G$5 -> 0
F54: Cost per Unit | I54: =I52/'Area Calculations'!$G$9 -> 0 | K54: =K52/'Area Calculations'!$G$9 -> 0 | M54: =M52/'Area Calculations'!$G$9 -> 0 | O54: =O52/'Area Calculations'!$G$9 -> 0 | Q54: =Q52/'Area Calculations'!$G$9 -> 0 | S54: =S52/'Area Calculations'!$G$9 -> 0
A56: QUALIFICATIONS
A60: EXCLUSIONS/OWNER PROVIDED ITEMS:
A64: ALTERNATES:
A68: PROPOSED VE (Provide Clear Description):
A72: FULLY LOADED LABOR RATES
B73: Laborer
B74: Mechanic
B75: Superintendent
B76: Project Manager
A78: SCHEDULE
B79: Prepared shop drawings/submittals
B80: Mobilization
B81: Total duration to complete scope of work
A83: Winner
A84: Company
A85: Contact
A86: Phone
A87: Email
A88: Base Bid
B90: Need Prequalification
B91: Prequalified

Sheet 14 80 Scaffolding
G1: Hedrick Plug
G2: Excluded
B3: BACK TO SUMMARY SHEET | G3: Included | H3: Bidder 1 | J3: Bidder 2 | L3: Bidder 3 | N3: Bidder 4 | P3: Bidder5 | R3: Bidder6
A4: Project: | B4: ='Area Calculations'!B4 -> Bourbon Hotel Orlando | G4: Company
A5: Trade: | B5: Scaffolding | G5: Contact
A6: CSI Code: | B6: 14 80 | G6: Phone
A7: Date: | G7: Email
A8: Adjusted Bid | G8: Adjusted Bid | H8: =I58 -> 0 | J8: =K58 -> 0 | L8: =M58 -> 0 | N8: =O58 -> 0 | P8: =Q58 -> 0 | R8: =S58 -> 0
A9: BID DOCUMENTS: | C9: Plan/ Spec. Package | D9: QTY | E9: U/M | F9: Unit Cost | G9: Subtotal | H9: Yes/No | I9: Price | J9: Yes/No | K9: Price | L9: Yes/No | M9: Price | N9: Yes/No | O9: Price | P9: Yes/No | Q9: Price | R9: Yes/No | S9: Price
B10: Plans By Division
B11: ='Area Calculations'!#REF! -> #REF! | C11: P
B12: ='Area Calculations'!#REF! -> #REF! | C12: P
B13: ='Area Calculations'!#REF! -> #REF! | C13: P
B14: ='Area Calculations'!#REF! -> #REF! | C14: P
B15: ='Area Calculations'!#REF! -> #REF! | C15: P
B16: ='Area Calculations'!#REF! -> #REF! | C16: P
B17: ='Area Calculations'!#REF! -> #REF! | C17: P
B18: ='Area Calculations'!#REF! -> #REF! | C18: P
B19: ='Area Calculations'!#REF! -> #REF! | C19: P
B21: Scaffolding
B22: GENERAL INCLUSIONS
B23: INCLUDES ALL SALES TAX
B24: ALL HOISTING & RIGGING REQUIRED TO COMPLETE THIS SCOPE
B25: PROVIDE P&P BONDS
B26: FLORIDA STATE CONTRACTORS LIC.
B27: GENERAL LIABILITY AND WORKERS COMP. INSURANCE LIMITS
B28: STATE AND LOCAL TAXES
B29: SPECIFIC TRADE SCOPE OF WORK REQUIREMENTS
B30: BASE BID
F54: SUBTOTAL | I54: =SUM(I23:I53) -> 0 | K54: =SUM(K23:K53) -> 0 | M54: =SUM(M23:M53) -> 0 | O54: =SUM(O23:O53) -> 0 | Q54: =SUM(Q23:Q53) -> 0 | S54: =SUM(S23:S53) -> 0
F55: BOND RATE | H55: 0 | J55: 0 | L55: 0 | N55: 0 | P55: 0 | R55: 0
F56: BOND AMOUNT | I56: =H55*I54 -> 0 | K56: =J55*K54 -> 0 | M56: =L55*M54 -> 0 | O56: =N55*O54 -> 0 | Q56: =P55*Q54 -> 0 | S56: =R55*S54 -> 0
F58: ADJUSTED TOTAL | I58: =SUM(I54:I56) -> 0 | K58: =SUM(K54:K56) -> 0 | M58: =SUM(M54:M56) -> 0 | O58: =SUM(O54:O56) -> 0 | Q58: =SUM(Q54:Q56) -> 0 | S58: =SUM(S54:S56) -> 0
F59: Cost per SF | I59: =I58/'Area Calculations'!$G$5 -> 0 | K59: =K58/'Area Calculations'!$G$5 -> 0 | M59: =M58/'Area Calculations'!$G$5 -> 0 | O59: =O58/'Area Calculations'!$G$5 -> 0 | Q59: =Q58/'Area Calculations'!$G$5 -> 0 | S59: =S58/'Area Calculations'!$G$5 -> 0
F60: Cost per Unit | I60: =I58/'Area Calculations'!$G$9 -> 0 | K60: =K58/'Area Calculations'!$G$9 -> 0 | M60: =M58/'Area Calculations'!$G$9 -> 0 | O60: =O58/'Area Calculations'!$G$9 -> 0 | Q60: =Q58/'Area Calculations'!$G$9 -> 0 | S60: =S58/'Area Calculations'!$G$9 -> 0
A62: QUALIFICATIONS
A66: EXCLUSIONS/OWNER PROVIDED ITEMS:
A70: ALTERNATES:
A74: PROPOSED VE (Provide Clear Description):
A78: FULLY LOADED LABOR RATES
B79: Laborer
B80: Mechanic
B81: Superintendent
B82: Project Manager
A84: SCHEDULE
B85: Prepared shop drawings/submittals
B86: Mobilization
B87: Total duration to complete scope of work
A89: Winner
A90: Company
A91: Contact
A92: Phone
A93: Email
A94: Base Bid
B96: Need Prequalification
B97: Prequalified

Sheet 13 11 Pool
G1: Hedrick Plug
F2: X | G2: Excluded
F3: I | G3: Included
B4: BACK TO SUMMARY SHEET | G4: Sub Add/Deduct
A5: Project: | B5: ='Area Calculations'!B4 -> Bourbon Hotel Orlando | G5: Company
A6: Trade: | B6: Pool & Water Features | G6: Contact
A7: CSI Code: | B7: 13 11 00 | G7: Phone
A8: Date: | G8: Email
G9: Adjusted Bid | H9: =I$56 -> 4174180 | J9: =K$56 -> 0 | L9: =M$56 -> 0 | N9: =O$56 -> 0 | P9: =Q$56 -> 0 | R9: =S$56 -> 0
A10: BID DOCUMENTS: | C10: Plan/ Spec. Package | D10: QTY | E10: U/M | F10: Unit Cost | G10: Subtotal | H10: Yes/No | I10: Price | J10: Yes/No | K10: Price | L10: Yes/No | M10: Price | N10: Yes/No | O10: Price | P10: Yes/No | Q10: Price | R10: Yes/No | S10: Price
B11: GENERAL INCLUSIONS
B12: INCLUDES ALL SALES TAX
B13: ALL HOISTING & RIGGING REQUIRED TO COMPLETE THIS SCOPE
B14: PROVIDE P&P BONDS
B15: FLORIDA STATE CONTRACTORS LIC.
B16: GENERAL LIABILITY AND WORKERS COMP. INSURANCE LIMITS
B17: STATE AND LOCAL TAXES
B18: SPECIFIC TRADE SCOPE OF WORK REQUIREMENTS
B19: BASE BID
B21: Pool - assume stainless Myrtha type | D21: 3130 | E21: sf | F21: =1488840/2280 -> 653 | G21: =ROUND(D21*F21,0) -> 2043890 | I21: =G21 -> 2043890
B22: Spa - | D22: 330 | E22: sf | F22: =1488840/2280 -> 653 | G22: =ROUND(D22*F22,0) -> 215490 | I22: =G22 -> 215490
B23: Water Features - | D23: 623 | E23: sf | F23: 400 | G23: =ROUND(D23*F23,0) -> 249200 | I23: =G23 -> 249200
B24: Water Features Shallow- | D24: 4447 | E24: sf | F24: =F23*0.75 -> 300 | G24: =ROUND(D24*F24,0) -> 1334100 | I24: =G24 -> 1334100
B25: Fountain - | D25: 805 | E25: sf | F25: 300 | G25: =ROUND(D25*F25,0) -> 241500 | I25: =G25 -> 241500
G26: =ROUND(D26*F26,0) -> 0 | I26: =G26 -> 0
B27: Waterfall - lobby | D27: 160 | E27: sf | F27: 450 | G27: =ROUND(D27*F27,0) -> 72000 | I27: =G27 -> 72000
B28: Coy Pond - 7th | D28: 60 | E28: ls | F28: 300 | G28: =ROUND(D28*F28,0) -> 18000 | I28: =G28 -> 18000
G29: =ROUND(D29*F29,0) -> 0 | I29: =G29 -> 0
G30: =ROUND(D30*F30,0) -> 0 | I30: =G30 -> 0
G31: =ROUND(D31*F31,0) -> 0 | I31: =G31 -> 0
G32: =ROUND(D32*F32,0) -> 0 | I32: =G32 -> 0
G33: =ROUND(D33*F33,0) -> 0 | I33: =G33 -> 0
G34: =ROUND(D34*F34,0) -> 0 | I34: =G34 -> 0
G35: =ROUND(D35*F35,0) -> 0 | I35: =G35 -> 0
G36: =ROUND(D36*F36,0) -> 0 | I36: =G36 -> 0
G37: =ROUND(D37*F37,0) -> 0 | I37: =G37 -> 0
G38: =ROUND(D38*F38,0) -> 0 | I38: =G38 -> 0
G39: =ROUND(D39*F39,0) -> 0 | I39: =G39 -> 0
G40: =ROUND(D40*F40,0) -> 0 | I40: =G40 -> 0
... G49: =ROUND(D49*F49,0) -> 0 | I49: =G49 -> 0
B52: SUBTOTAL Base Bid | G52: =SUBTOTAL(9,G21:G51) -> 4174180 | I52: =SUBTOTAL(9,I21:I51) -> 4174180 | K52: =SUM(K19:K51) -> 0 | M52: =SUM(M19:M51) -> 0 | O52: =SUM(O19:O51) -> 0 | Q52: =SUM(Q19:Q51) -> 0 | S52: =SUM(S19:S51) -> 0
B53: BOND RATE | H53: 0 | J53: 0 | L53: 0 | N53: 0 | P53: 0 | R53: 0
B54: BOND AMOUNT | G54: =F53*G52 -> 0 | I54: =H53*I52 -> 0 | K54: =J53*K52 -> 0 | M54: =L53*M52 -> 0 | O54: =N53*O52 -> 0 | Q54: =P53*Q52 -> 0 | S54: =R53*S52 -> 0
B56: ADJUSTED TOTAL | G56: =SUM(G52:G54) -> 4174180 | I56: =SUM(I52:I54) -> 4174180 | K56: =SUM(K52:K54) -> 0 | M56: =SUM(M52:M54) -> 0 | O56: =SUM(O52:O54) -> 0 | Q56: =SUM(Q52:Q54) -> 0 | S56: =SUM(S52:S54) -> 0
B57: Cost per SF | G57: =G56/'Area Calculations'!$G$5 -> 10.721637 | I57: =I56/'Area Calculations'!$G$5 -> 10.721637 | K57: =K56/'Area Calculations'!$G$5 -> 0 | M57: =M56/'Area Calculations'!$G$5 -> 0 | O57: =O56/'Area Calculations'!$G$5 -> 0 | Q57: =Q56/'Area Calculations'!$G$5 -> 0 | S57: =S56/'Area Calculations'!$G$5 -> 0
A59: QUALIFICATIONS
A63: EXCLUSIONS/OWNER PROVIDED ITEMS:
A67: ALTERNATES:
A71: PROPOSED VE (Provide Clear Description):
A75: FULLY LOADED LABOR RATES
B76: Laborer
B77: Mechanic
B78: Superintendent
B79: Project Manager
A81: SCHEDULE
B82: Prepared shop drawings/submittals
B83: Mobilization
B84: Total duration to complete scope of work
A86: Winner
A87: Company
A88: Contact
A89: Phone
A90: Email
A91: Base Bid | B91: =$I$56 -> 4174180
B93: Need Prequalification
B94: Prequalified

Sheet 10 73 Canopies
G1: Hedrick Plug
F2: X | G2: Excluded
F3: I | G3: Included
B4: BACK TO SUMMARY SHEET | G4: Sub Add/Deduct
A5: Project: | B5: ='Area Calculations'!B4 -> Bourbon Hotel Orlando | G5: Company
A6: Trade: | B6: Canopies / Trellis | G6: Contact
A7: CSI Code: | B7: 10 73 00 | G7: Phone
A8: Date: | G8: Email
G9: Adjusted Bid | H9: =I$55 -> 2522500 | J9: =K$55 -> 0 | L9: =M$55 -> 0 | N9: =O$55 -> 0 | P9: =Q$55 -> 0 | R9: =S$55 -> 0
A10: BID DOCUMENTS: | C10: Plan/ Spec. Package | D10: QTY | E10: U/M | F10: Unit Cost | G10: Subtotal | H10: Yes/No | I10: Price | J10: Yes/No | K10: Price | L10: Yes/No | M10: Price | N10: Yes/No | O10: Price | P10: Yes/No | Q10: Price | R10: Yes/No | S10: Price
B11: GENERAL INCLUSIONS
B12: INCLUDES ALL SALES TAX
B13: ALL HOISTING & RIGGING REQUIRED TO COMPLETE THIS SCOPE
B14: PROVIDE P&P BONDS
B15: FLORIDA STATE CONTRACTORS LIC.
B16: GENERAL LIABILITY AND WORKERS COMP. INSURANCE LIMITS
B17: STATE AND LOCAL TAXES
B18: SPECIFIC TRADE SCOPE OF WORK REQUIREMENTS
B19: BASE BID
B21: Canopies - assume aluminum tube clad with wood look aluminum panel | G21: =ROUND(D21*F21,0) -> 0 | I21: =G21 -> 0
B22: 3rd Level Eyebrow | D22: 1600 | E22: sf | F22: 250 | G22: =ROUND(D22*F22,0) -> 400000 | I22: =G22 -> 400000
B23: Hotel High Roof | D23: 4000 | E23: sf | F23: 300 | G23: =ROUND(D23*F23,0) -> 1200000 | I23: =G23 -> 1200000
B24: Restaurant Eyebrow | D24: 2370 | E24: sf | F24: 250 | G24: =ROUND(D24*F24,0) -> 592500 | I24: =G24 -> 592500
B25: Restaurant Lower | D25: 1320 | E25: sf | F25: 250 | G25: =ROUND(D25*F25,0) -> 330000 | I25: =G25 -> 330000
G26: =ROUND(D26*F26,0) -> 0 | I26: =G26 -> 0
G27: =ROUND(D27*F27,0) -> 0 | I27: =G27 -> 0
G28: =ROUND(D28*F28,0) -> 0 | I28: =G28 -> 0
G29: =ROUND(D29*F29,0) -> 0 | I29: =G29 -> 0
G30: =ROUND(D30*F30,0) -> 0 | I30: =G30 -> 0
G31: =ROUND(D31*F31,0) -> 0 | I31: =G31 -> 0
G32: =ROUND(D32*F32,0) -> 0 | I32: =G32 -> 0
G33: =ROUND(D33*F33,0) -> 0 | I33: =G33 -> 0
G34: =ROUND(D34*F34,0) -> 0 | I34: =G34 -> 0
G35: =ROUND(D35*F35,0) -> 0 | I35: =G35 -> 0
G36: =ROUND(D36*F36,0) -> 0 | I36: =G36 -> 0
G37: =ROUND(D37*F37,0) -> 0 | I37: =G37 -> 0
... G48: =ROUND(D48*F48,0) -> 0 | I48: =G48 -> 0
B51: SUBTOTAL Base Bid | G51: =SUBTOTAL(9,G21:G50) -> 2522500 | I51: =SUBTOTAL(9,I21:I50) -> 2522500 | K51: =SUM(K19:K50) -> 0 | M51: =SUM(M19:M50) -> 0 | O51: =SUM(O19:O50) -> 0 | Q51: =SUM(Q19:Q50) -> 0 | S51: =SUM(S19:S50) -> 0
B52: BOND RATE | H52: 0 | J52: 0 | L52: 0 | N52: 0 | P52: 0 | R52: 0
B53: BOND AMOUNT | G53: =F52*G51 -> 0 | I53: =H52*I51 -> 0 | K53: =J52*K51 -> 0 | M53: =L52*M51 -> 0 | O53: =N52*O51 -> 0 | Q53: =P52*Q51 -> 0 | S53: =R52*S51 -> 0
B55: ADJUSTED TOTAL | G55: =SUM(G51:G53) -> 2522500 | I55: =SUM(I51:I53) -> 2522500 | K55: =SUM(K51:K53) -> 0 | M55: =SUM(M51:M53) -> 0 | O55: =SUM(O51:O53) -> 0 | Q55: =SUM(Q51:Q53) -> 0 | S55: =SUM(S51:S53) -> 0
B56: Cost per SF | G56: =G55/'Area Calculations'!$G$5 -> 6.4791959 | I56: =I55/'Area Calculations'!$G$5 -> 6.4791959 | K56: =K55/'Area Calculations'!$G$5 -> 0 | M56: =M55/'Area Calculations'!$G$5 -> 0 | O56: =O55/'Area Calculations'!$G$5 -> 0 | Q56: =Q55/'Area Calculations'!$G$5 -> 0 | S56: =S55/'Area Calculations'!$G$5 -> 0
A58: QUALIFICATIONS
A62: EXCLUSIONS/OWNER PROVIDED ITEMS:
A66: ALTERNATES:
A70: PROPOSED VE (Provide Clear Description):
A74: FULLY LOADED LABOR RATES
B75: Laborer
B76: Mechanic
B77: Superintendent
B78: Project Manager
A80: SCHEDULE
B81: Prepared shop drawings/submittals
B82: Mobilization
B83: Total duration to complete scope of work
A85: Winner
A86: Company
A87: Contact
A88: Phone
A89: Email
A90: Base Bid | B90: =$I$55 -> 2522500
B92: Need Prequalification
B93: Prequalified

Sheet 14 00 Elevators
G1: Hedrick Plug
F2: X | G2: Excluded
F3: I | G3: Included
B4: BACK TO SUMMARY SHEET | G4: Sub Add/Deduct
A5: Project: | B5: ='Area Calculations'!B4 -> Bourbon Hotel Orlando | G5: Company
A6: Trade: | B6: Elevators | G6: Contact
A7: CSI Code: | B7: 14 00 00 | G7: Phone
A8: Date: | G8: Email
G9: Adjusted Bid | H9: =I$57 -> 3313230 | J9: =K$57 -> 0 | L9: =M$57 -> 0 | N9: =O$57 -> 0 | P9: =Q$57 -> 0 | R9: =S$57 -> 0
A10: BID DOCUMENTS: | C10: Plan/ Spec. Package | D10: QTY | E10: U/M | F10: Unit Cost | G10: Subtotal | H10: Yes/No | I10: Price | J10: Yes/No | K10: Price | L10: Yes/No | M10: Price | N10: Yes/No | O10: Price | P10: Yes/No | Q10: Price | R10: Yes/No | S10: Price
B11: GENERAL INCLUSIONS
B12: INCLUDES ALL SALES TAX
B13: ALL HOISTING & RIGGING REQUIRED TO COMPLETE THIS SCOPE
B14: PROVIDE P&P BONDS
B15: FLORIDA STATE CONTRACTORS LIC.
B16: GENERAL LIABILITY AND WORKERS COMP. INSURANCE LIMITS
B17: STATE AND LOCAL TAXES
B18: SPECIFIC TRADE SCOPE OF WORK REQUIREMENTS
B19: BASE BID
B21: South Wing | G21: =ROUND(D21*F21,0) -> 0 | I21: =G21 -> 0
B22: passenger - traction | D22: 7 | E22: stops | F22: 45000 | G22: =ROUND(D22*F22,0) -> 315000 | I22: =G22 -> 315000
B23: service - traction | D23: 7 | E23: stops | F23: 50000 | G23: =ROUND(D23*F23,0) -> 350000 | I23: =G23 -> 350000
B24: Lobby | G24: =ROUND(D24*F24,0) -> 0 | I24: =G24 -> 0
B25: passenger - traction | D25: 8 | E25: stops | F25: 45000 | G25: =ROUND(D25*F25,0) -> 360000 | I25: =G25 -> 360000
B26: service - traction | D26: 8 | E26: stops | F26: 55000 | G26: =ROUND(D26*F26,0) -> 440000 | I26: =G26 -> 440000
B27: passenger - glass - hydro | D27: 2 | E27: stops | F27: 65000 | G27: =ROUND(D27*F27,0) -> 130000 | I27: =G27 -> 130000
B28: Central | G28: =ROUND(D28*F28,0) -> 0 | I28: =G28 -> 0
B29: passenger - traction | D29: 7 | E29: stops | F29: 45000 | G29: =ROUND(D29*F29,0) -> 315000 | I29: =G29 -> 315000
B30: service - traction | D30: 7 | E30: stops | F30: 50000 | G30: =ROUND(D30*F30,0) -> 350000 | I30: =G30 -> 350000
B31: North Wing | G31: =ROUND(D31*F31,0) -> 0 | I31: =G31 -> 0
B32: passenger - traction | D32: 7 | E32: stops | F32: 45000 | G32: =ROUND(D32*F32,0) -> 315000 | I32: =G32 -> 315000
B33: Restaurant | G33: =ROUND(D33*F33,0) -> 0 | I33: =G33 -> 0
B34: passenger - hydro | D34: 4 | E34: stops | F34: 35000 | G34: =ROUND(D34*F34,0) -> 140000 | I34: =G34 -> 140000
B35: passenger - hydro | D35: 4 | E35: stops | F35: 35000 | G35: =ROUND(D35*F35,0) -> 140000 | I35: =G35 -> 140000
G36: =ROUND(D36*F36,0) -> 0 | I36: =G36 -> 0
B37: Cab Finish Allowance | G37: =ROUND(D37*F37,0) -> 0 | I37: =G37 -> 0
B38: passenger | D38: 6 | E38: ea | F38: 25000 | G38: =ROUND(D38*F38,0) -> 150000 | I38: =G38 -> 150000
B39: service | D39: 3 | E39: ea | F39: 10000 | G39: =ROUND(D39*F39,0) -> 30000 | I39: =G39 -> 30000
G40: =ROUND(D40*F40,0) -> 0 | I40: =G40 -> 0
B41: Temp usage - 3 elevators | G41: =ROUND(D41*F41,0) -> 0 | I41: =G41 -> 0
B42: recertification | D42: 3 | E42: ea | F42: 4500 | G42: =ROUND(D42*F42,0) -> 13500 | I42: =G42 -> 13500
B43: temp use - 6 mo per cab | D43: 18 | E43: mo | F43: 3500 | G43: =ROUND(D43*F43,0) -> 63000 | I43: =G43 -> 63000
B44: cab protection | D44: 3 | E44: ea | F44: 750 | G44: =ROUND(D44*F44,0) -> 2250 | I44: =G44 -> 2250
B45: opening Protection | D45: 24 | E45: ea | F45: 150 | G45: =ROUND(D45*F45,0) -> 3600 | I45: =G45 -> 3600
B46: operator - 40 hrs per wk | D46: 18 | E46: mo | F46: =50*40*4.33 -> 8660 | G46: =ROUND(D46*F46,0) -> 155880 | I46: =G46 -> 155880
G47: =ROUND(D47*F47,0) -> 0 | I47: =G47 -> 0
G48: =ROUND(D48*F48,0) -> 0 | I48: =G48 -> 0
B49: Handicap lifts | D49: 2 | E49: ea | F49: 20000 | G49: =ROUND(D49*F49,0) -> 40000 | I49: =G49 -> 40000
G50: =ROUND(D50*F50,0) -> 0 | I50: =G50 -> 0
G51: =ROUND(D51*F51,0) -> 0 | I51: =G51 -> 0
B53: SUBTOTAL Base Bid | G53: =SUBTOTAL(9,G21:G52) -> 3313230 | I53: =SUBTOTAL(9,I21:I52) -> 3313230 | K53: =SUM(K19:K52) -> 0 | M53: =SUM(M19:M52) -> 0 | O53: =SUM(O19:O52) -> 0 | Q53: =SUM(Q19:Q52) -> 0 | S53: =SUM(S19:S52) -> 0
B54: BOND RATE | H54: 0 | J54: 0 | L54: 0 | N54: 0 | P54: 0 | R54: 0
B55: BOND AMOUNT | G55: =F54*G53 -> 0 | I55: =H54*I53 -> 0 | K55: =J54*K53 -> 0 | M55: =L54*M53 -> 0 | O55: =N54*O53 -> 0 | Q55: =P54*Q53 -> 0 | S55: =R54*S53 -> 0
B57: ADJUSTED TOTAL | G57: =SUM(G53:G55) -> 3313230 | I57: =SUM(I53:I55) -> 3313230 | K57: =SUM(K53:K55) -> 0 | M57: =SUM(M53:M55) -> 0 | O57: =SUM(O53:O55) -> 0 | Q57: =SUM(Q53:Q55) -> 0 | S57: =SUM(S53:S55) -> 0
B58: Cost per SF | G58: =G57/'Area Calculations'!$G$5 -> 8.5102344 | I58: =I57/'Area Calculations'!$G$5 -> 8.5102344 | K58: =K57/'Area Calculations'!$G$5 -> 0 | M58: =M57/'Area Calculations'!$G$5 -> 0 | O58: =O57/'Area Calculations'!$G$5 -> 0 | Q58: =Q57/'Area Calculations'!$G$5 -> 0 | S58: =S57/'Area Calculations'!$G$5 -> 0
A60: QUALIFICATIONS
A64: EXCLUSIONS/OWNER PROVIDED ITEMS:
A68: ALTERNATES:
A72: PROPOSED VE (Provide Clear Description):
A76: FULLY LOADED LABOR RATES
B77: Laborer
B78: Mechanic
B79: Superintendent
B80: Project Manager
A82: SCHEDULE
B83: Prepared shop drawings/submittals
B84: Mobilization
B85: Total duration to complete scope of work
A87: Winner
A88: Company
A89: Contact
A90: Phone
A91: Email
A92: Base Bid | B92: =$I$57 -> 3313230
B94: Need Prequalification
B95: Prequalified

Sheet 14 91 Laundry Chute
G1: Hedrick Plug
F2: X | G2: Excluded
F3: I | G3: Included
B4: BACK TO SUMMARY SHEET | G4: Sub Add/Deduct
A5: Project: | B5: ='Area Calculations'!B4 -> Bourbon Hotel Orlando | G5: Company
A6: Trade: | B6: Laundry Chute | G6: Contact
A7: CSI Code: | B7: 14 91 00 | G7: Phone
A8: Date: | G8: Email
G9: Adjusted Bid | H9: =I$55 -> 20300 | J9: =K$55 -> 0 | L9: =M$55 -> 0 | N9: =O$55 -> 0 | P9: =Q$55 -> 0 | R9: =S$55 -> 0
A10: BID DOCUMENTS: | C10: Plan/ Spec. Package | D10: QTY | E10: U/M | F10: Unit Cost | G10: Subtotal | H10: Yes/No | I10: Price | J10: Yes/No | K10: Price | L10: Yes/No | M10: Price | N10: Yes/No | O10: Price | P10: Yes/No | Q10: Price | R10: Yes/No | S10: Price
B11: GENERAL INCLUSIONS
B12: INCLUDES ALL SALES TAX
B13: ALL HOISTING & RIGGING REQUIRED TO COMPLETE THIS SCOPE
B14: PROVIDE P&P BONDS
B15: FLORIDA STATE CONTRACTORS LIC.
B16: GENERAL LIABILITY AND WORKERS COMP. INSURANCE LIMITS
B17: STATE AND LOCAL TAXES
B18: SPECIFIC TRADE SCOPE OF WORK REQUIREMENTS
B19: BASE BID
B21: Laundry Chute | D21: 7 | E21: flrs | F21: 2900 | G21: =ROUND(D21*F21,0) -> 20300 | I21: =G21 -> 20300
G22: =ROUND(D22*F22,0) -> 0 | I22: =G22 -> 0
G23: =ROUND(D23*F23,0) -> 0 | I23: =G23 -> 0
G24: =ROUND(D24*F24,0) -> 0 | I24: =G24 -> 0
G25: =ROUND(D25*F25,0) -> 0 | I25: =G25 -> 0
G26: =ROUND(D26*F26,0) -> 0 | I26: =G26 -> 0
G27: =ROUND(D27*F27,0) -> 0 | I27: =G27 -> 0
G28: =ROUND(D28*F28,0) -> 0 | I28: =G28 -> 0
G29: =ROUND(D29*F29,0) -> 0 | I29: =G29 -> 0
G30: =ROUND(D30*F30,0) -> 0 | I30: =G30 -> 0
G31: =ROUND(D31*F31,0) -> 0 | I31: =G31 -> 0
G32: =ROUND(D32*F32,0) -> 0 | I32: =G32 -> 0
G33: =ROUND(D33*F33,0) -> 0 | I33: =G33 -> 0
... G49: =ROUND(D49*F49,0) -> 0 | I49: =G49 -> 0
B51: SUBTOTAL Base Bid | G51: =SUBTOTAL(9,G21:G50) -> 20300 | I51: =SUBTOTAL(9,I21:I50) -> 20300 | K51: =SUM(K19:K50) -> 0 | M51: =SUM(M19:M50) -> 0 | O51: =SUM(O19:O50) -> 0 | Q51: =SUM(Q19:Q50) -> 0 | S51: =SUM(S19:S50) -> 0
B52: BOND RATE | H52: 0 | J52: 0 | L52: 0 | N52: 0 | P52: 0 | R52: 0
B53: BOND AMOUNT | G53: =F52*G51 -> 0 | I53: =H52*I51 -> 0 | K53: =J52*K51 -> 0 | M53: =L52*M51 -> 0 | O53: =N52*O51 -> 0 | Q53: =P52*Q51 -> 0 | S53: =R52*S51 -> 0
B55: ADJUSTED TOTAL | G55: =SUM(G51:G53) -> 20300 | I55: =SUM(I51:I53) -> 20300 | K55: =SUM(K51:K53) -> 0 | M55: =SUM(M51:M53) -> 0 | O55: =SUM(O51:O53) -> 0 | Q55: =SUM(Q51:Q53) -> 0 | S55: =SUM(S51:S53) -> 0
B56: Cost per SF | G56: =G55/'Area Calculations'!$G$5 -> 0.052141795 | I56: =I55/'Area Calculations'!$G$5 -> 0.052141795 | K56: =K55/'Area Calculations'!$G$5 -> 0 | M56: =M55/'Area Calculations'!$G$5 -> 0 | O56: =O55/'Area Calculations'!$G$5 -> 0 | Q56: =Q55/'Area Calculations'!$G$5 -> 0 | S56: =S55/'Area Calculations'!$G$5 -> 0
A58: QUALIFICATIONS
A62: EXCLUSIONS/OWNER PROVIDED ITEMS:
A66: ALTERNATES:
A70: PROPOSED VE (Provide Clear Description):
A74: FULLY LOADED LABOR RATES
B75: Laborer
B76: Mechanic
B77: Superintendent
B78: Project Manager
A80: SCHEDULE
B81: Prepared shop drawings/submittals
B82: Mobilization
B83: Total duration to complete scope of work
A85: Winner
A86: Company
A87: Contact
A88: Phone
A89: Email
A90: Base Bid | B90: =$I$55 -> 20300
B92: Need Prequalification
B93: Prequalified

Sheet 21 13 Fire Protection
G1: Hedrick Plug
F2: X | G2: Excluded
F3: I | G3: Included
B4: BACK TO SUMMARY SHEET | G4: Sub Add/Deduct
A5: Project: | B5: ='Area Calculations'!B4 -> Bourbon Hotel Orlando | G5: Company
A6: Trade: | B6: Fire Protection | G6: Contact
A7: CSI Code: | B7: 21 13 00 | G7: Phone
A8: Date: | G8: Email
G9: Adjusted Bid | H9: =I$55 -> 1272593 | J9: =K$55 -> 0 | L9: =M$55 -> 0 | N9: =O$55 -> 0 | P9: =Q$55 -> 0 | R9: =S$55 -> 0
A10: BID DOCUMENTS: | C10: Plan/ Spec. Package | D10: QTY | E10: U/M | F10: Unit Cost | G10: Subtotal | H10: Yes/No | I10: Price | J10: Yes/No | K10: Price | L10: Yes/No | M10: Price | N10: Yes/No | O10: Price | P10: Yes/No | Q10: Price | R10: Yes/No | S10: Price
B11: GENERAL INCLUSIONS
B12: INCLUDES ALL SALES TAX
B13: ALL HOISTING & RIGGING REQUIRED TO COMPLETE THIS SCOPE
B14: PROVIDE P&P BONDS
B15: FLORIDA STATE CONTRACTORS LIC.
B16: GENERAL LIABILITY AND WORKERS COMP. INSURANCE LIMITS
B17: STATE AND LOCAL TAXES
B18: SPECIFIC TRADE SCOPE OF WORK REQUIREMENTS
B19: BASE BID
B21: Sprinkler system - hotel & restaurant | D21: =SUM('Area Calculations'!E15:E21) -> 279298 | E21: sf | F21: 3.5 | G21: =ROUND(D21*F21,0) -> 977543 | I21: =G21 -> 977543
B22: Sprinkler system - garage | D22: ='Area Calculations'!E14 -> 110025 | E22: sf | F22: 2 | G22: =ROUND(D22*F22,0) -> 220050 | I22: =G22 -> 220050
G23: =ROUND(D23*F23,0) -> 0 | I23: =G23 -> 0
B24: Fire pump | D24: 1 | E24: ls | F24: 75000 | G24: =ROUND(D24*F24,0) -> 75000 | I24: =G24 -> 75000
G25: =ROUND(D25*F25,0) -> 0 | I25: =G25 -> 0
G26: =ROUND(D26*F26,0) -> 0 | I26: =G26 -> 0
G27: =ROUND(D27*F27,0) -> 0 | I27: =G27 -> 0
G28: =ROUND(D28*F28,0) -> 0 | I28: =G28 -> 0
G29: =ROUND(D29*F29,0) -> 0 | I29: =G29 -> 0
G30: =ROUND(D30*F30,0) -> 0 | I30: =G30 -> 0
G31: =ROUND(D31*F31,0) -> 0 | I31: =G31 -> 0
G32: =ROUND(D32*F32,0) -> 0 | I32: =G32 -> 0
G33: =ROUND(D33*F33,0) -> 0 | I33: =G33 -> 0
G34: =ROUND(D34*F34,0) -> 0 | I34: =G34 -> 0
G35: =ROUND(D35*F35,0) -> 0 | I35: =G35 -> 0
G36: =ROUND(D36*F36,0) -> 0 | I36: =G36 -> 0
... G49: =ROUND(D49*F49,0) -> 0 | I49: =G49 -> 0
B51: SUBTOTAL Base Bid | G51: =SUBTOTAL(9,G21:G50) -> 1272593 | I51: =SUBTOTAL(9,I21:I50) -> 1272593 | K51: =SUM(K19:K50) -> 0 | M51: =SUM(M19:M50) -> 0 | O51: =SUM(O19:O50) -> 0 | Q51: =SUM(Q19:Q50) -> 0 | S51: =SUM(S19:S50) -> 0
B52: BOND RATE | H52: 0 | J52: 0 | L52: 0 | N52: 0 | P52: 0 | R52: 0
B53: BOND AMOUNT | G53: =F52*G51 -> 0 | I53: =H52*I51 -> 0 | K53: =J52*K51 -> 0 | M53: =L52*M51 -> 0 | O53: =N52*O51 -> 0 | Q53: =P52*Q51 -> 0 | S53: =R52*S51 -> 0
B55: ADJUSTED TOTAL | G55: =SUM(G51:G53) -> 1272593 | I55: =SUM(I51:I53) -> 1272593 | K55: =SUM(K51:K53) -> 0 | M55: =SUM(M51:M53) -> 0 | O55: =SUM(O51:O53) -> 0 | Q55: =SUM(Q51:Q53) -> 0 | S55: =SUM(S51:S53) -> 0
B56: Cost per SF | G56: =G55/'Area Calculations'!$G$5 -> 3.2687332 | I56: =I55/'Area Calculations'!$G$5 -> 3.2687332 | K56: =K55/'Area Calculations'!$G$5 -> 0 | M56: =M55/'Area Calculations'!$G$5 -> 0 | O56: =O55/'Area Calculations'!$G$5 -> 0 | Q56: =Q55/'Area Calculations'!$G$5 -> 0 | S56: =S55/'Area Calculations'!$G$5 -> 0
A58: QUALIFICATIONS
A62: EXCLUSIONS/OWNER PROVIDED ITEMS:
A66: ALTERNATES:
A70: PROPOSED VE (Provide Clear Description):
A74: FULLY LOADED LABOR RATES
B75: Laborer
B76: Mechanic
B77: Superintendent
B78: Project Manager
A80: SCHEDULE
B81: Prepared shop drawings/submittals
B82: Mobilization
B83: Total duration to complete scope of work
A85: Winner
A86: Company
A87: Contact
A88: Phone
A89: Email
A90: Base Bid | B90: =$I$55 -> 1272593
B92: Need Prequalification
B93: Prequalified

Sheet 22 00 Plumbing 
G1: Hedrick Plug
F2: X | G2: Excluded
F3: I | G3: Included
B4: BACK TO SUMMARY SHEET | G4: Sub Add/Deduct
A5: Project: | B5: ='Area Calculations'!B4 -> Bourbon Hotel Orlando | G5: Company
A6: Trade: | B6: Plumbing | G6: Contact
A7: CSI Code: | B7: 22 00 00 | G7: Phone
A8: Date: | G8: Email
G9: Adjusted Bid | H9: =I$55 -> 7234302 | J9: =K$55 -> 24440.209 | L9: =M$55 -> 0 | N9: =O$55 -> 0 | P9: =Q$55 -> 0 | R9: =S$55 -> 0
A10: BID DOCUMENTS: | C10: Plan/ Spec. Package | D10: QTY | E10: U/M | F10: Unit Cost | G10: Subtotal | H10: Yes/No | I10: Price | J10: Yes/No | K10: Price | L10: Yes/No | M10: Price | N10: Yes/No | O10: Price | P10: Yes/No | Q10: Price | R10: Yes/No | S10: Price
B11: GENERAL INCLUSIONS
B12: INCLUDES ALL SALES TAX
B13: ALL HOISTING & RIGGING REQUIRED TO COMPLETE THIS SCOPE
B14: PROVIDE P&P BONDS
B15: FLORIDA STATE CONTRACTORS LIC.
B16: GENERAL LIABILITY AND WORKERS COMP. INSURANCE LIMITS
B17: STATE AND LOCAL TAXES
B18: SPECIFIC TRADE SCOPE OF WORK REQUIREMENTS
B19: BASE BID
B21: Hotel - std plumbing | D21: ='Area Calculations'!Q15 -> 270 | E21: units | F21: 20000 | G21: =ROUND(D21*F21,0) -> 5400000 | I21: =G21 -> 5400000 | K21: =H9/296 -> 24440.209
B22: Hotel - std plumbing fixtures | D22: ='Area Calculations'!Q15 -> 270 | E22: units | F22: 1800 | G22: =ROUND(D22*F22,0) -> 486000 | I22: =G22 -> 486000
B23: Hotel - suite & penthouse plumbing | D23: ='Area Calculations'!O15+'Area Calculations'!P15 -> 26 | E23: units | F23: 40000 | G23: =ROUND(D23*F23,0) -> 1040000 | I23: =G23 -> 1040000
B24: Hotel - suite & penthouse plumbing fixtures | D24: ='Area Calculations'!O15+'Area Calculations'!P15 -> 26 | E24: units | F24: 1800 | G24: =ROUND(D24*F24,0) -> 46800 | I24: =G24 -> 46800
G25: =ROUND(D25*F25,0) -> 0 | I25: =G25 -> 0
B26: Back of house & common area plumbing | D26: ='Area Calculations'!G6 -> 261502 | E26: sf | F26: 1 | G26: =ROUND(D26*F26,0) -> 261502 | I26: =G26 -> 261502
G27: =ROUND(D27*F27,0) -> 0 | I27: =G27 -> 0
G28: =ROUND(D28*F28,0) -> 0 | I28: =G28 -> 0
G29: =ROUND(D29*F29,0) -> 0 | I29: =G29 -> 0
G30: =ROUND(D30*F30,0) -> 0 | I30: =G30 -> 0
G31: =ROUND(D31*F31,0) -> 0 | I31: =G31 -> 0
G32: =ROUND(D32*F32,0) -> 0 | I32: =G32 -> 0
G33: =ROUND(D33*F33,0) -> 0 | I33: =G33 -> 0
G34: =ROUND(D34*F34,0) -> 0 | I34: =G34 -> 0
G35: =ROUND(D35*F35,0) -> 0 | I35: =G35 -> 0
G36: =ROUND(D36*F36,0) -> 0 | I36: =G36 -> 0
G37: =ROUND(D37*F37,0) -> 0 | I37: =G37 -> 0
G38: =ROUND(D38*F38,0) -> 0 | I38: =G38 -> 0
... G49: =ROUND(D49*F49,0) -> 0 | I49: =G49 -> 0
B51: SUBTOTAL Base Bid | G51: =SUBTOTAL(9,G21:G50) -> 7234302 | I51: =SUBTOTAL(9,I21:I50) -> 7234302 | K51: =SUM(K19:K50) -> 24440.209 | M51: =SUM(M19:M50) -> 0 | O51: =SUM(O19:O50) -> 0 | Q51: =SUM(Q19:Q50) -> 0 | S51: =SUM(S19:S50) -> 0
B52: BOND RATE | H52: 0 | J52: 0 | L52: 0 | N52: 0 | P52: 0 | R52: 0
B53: BOND AMOUNT | G53: =F52*G51 -> 0 | I53: =H52*I51 -> 0 | K53: =J52*K51 -> 0 | M53: =L52*M51 -> 0 | O53: =N52*O51 -> 0 | Q53: =P52*Q51 -> 0 | S53: =R52*S51 -> 0
B55: ADJUSTED TOTAL | G55: =SUM(G51:G53) -> 7234302 | I55: =SUM(I51:I53) -> 7234302 | K55: =SUM(K51:K53) -> 24440.209 | M55: =SUM(M51:M53) -> 0 | O55: =SUM(O51:O53) -> 0 | Q55: =SUM(Q51:Q53) -> 0 | S55: =SUM(S51:S53) -> 0
B56: Cost per SF | G56: =G55/'Area Calculations'!$G$5 -> 18.581748 | I56: =I55/'Area Calculations'!$G$5 -> 18.581748 | K56: =K55/'Area Calculations'!$G$5 -> 0.062776177 | M56: =M55/'Area Calculations'!$G$5 -> 0 | O56: =O55/'Area Calculations'!$G$5 -> 0 | Q56: =Q55/'Area Calculations'!$G$5 -> 0 | S56: =S55/'Area Calculations'!$G$5 -> 0
I57: =I55/296 -> 24440.209
A58: QUALIFICATIONS
A62: EXCLUSIONS/OWNER PROVIDED ITEMS:
A66: ALTERNATES:
A70: PROPOSED VE (Provide Clear Description):
A74: FULLY LOADED LABOR RATES
B75: Laborer
B76: Mechanic
B77: Superintendent
B78: Project Manager
A80: SCHEDULE
B81: Prepared shop drawings/submittals
B82: Mobilization
B83: Total duration to complete scope of work
A85: Winner
A86: Company
A87: Contact
A88: Phone
A89: Email
A90: Base Bid | B90: =$I$55 -> 7234302
B92: Need Prequalification
B93: Prequalified

Sheet 23 00 HVAC
G1: Hedrick Plug
F2: X | G2: Excluded
F3: I | G3: Included
B4: BACK TO SUMMARY SHEET | G4: Sub Add/Deduct
A5: Project: | B5: ='Area Calculations'!B4 -> Bourbon Hotel Orlando | G5: Company
A6: Trade: | B6: HVAC | G6: Contact
A7: CSI Code: | B7: 23 00 00 | G7: Phone
A8: Date: | G8: Email
G9: Adjusted Bid | H9: =I$55 -> 8615235 | J9: =K$55 -> 6724337.1 | L9: =M$55 -> 0 | N9: =O$55 -> 0 | P9: =Q$55 -> 0 | R9: =S$55 -> 0
A10: BID DOCUMENTS: | C10: Plan/ Spec. Package | D10: QTY | E10: U/M | F10: Unit Cost | G10: Subtotal | H10: Yes/No | I10: Price | J10: Yes/No | K10: Price | L10: Yes/No | M10: Price | N10: Yes/No | O10: Price | P10: Yes/No | Q10: Price | R10: Yes/No | S10: Price
B11: GENERAL INCLUSIONS
B12: INCLUDES ALL SALES TAX
B13: ALL HOISTING & RIGGING REQUIRED TO COMPLETE THIS SCOPE
B14: PROVIDE P&P BONDS
B15: FLORIDA STATE CONTRACTORS LIC.
B16: GENERAL LIABILITY AND WORKERS COMP. INSURANCE LIMITS
B17: STATE AND LOCAL TAXES
B18: SPECIFIC TRADE SCOPE OF WORK REQUIREMENTS
B19: BASE BID
B21: Hotel - chilled water? | D21: ='Area Calculations'!G6 -> 261502 | E21: sf | F21: 30 | G21: =ROUND(D21*F21,0) -> 7845060 | I21: =G21 -> 7845060 | K21: =D21/350*9000 -> 6724337.1
B22: Restarauant - chilled water? | D22: ='Area Calculations'!D15 -> 0 | E22: sf | F22: 30 | G22: =ROUND(D22*F22,0) -> 0 | I22: =G22 -> 0
B23: Garage - ventilation | D23: ='Area Calculations'!E14 -> 110025 | E23: sf | F23: 7 | G23: =ROUND(D23*F23,0) -> 770175 | I23: =G23 -> 770175
G24: =ROUND(D24*F24,0) -> 0 | I24: =G24 -> 0
G25: =ROUND(D25*F25,0) -> 0 | I25: =G25 -> 0
G26: =ROUND(D26*F26,0) -> 0 | I26: =G26 -> 0
G27: =ROUND(D27*F27,0) -> 0 | I27: =G27 -> 0
G28: =ROUND(D28*F28,0) -> 0 | I28: =G28 -> 0
G29: =ROUND(D29*F29,0) -> 0 | I29: =G29 -> 0
G30: =ROUND(D30*F30,0) -> 0 | I30: =G30 -> 0
G31: =ROUND(D31*F31,0) -> 0 | I31: =G31 -> 0
G32: =ROUND(D32*F32,0) -> 0 | I32: =G32 -> 0
G33: =ROUND(D33*F33,0) -> 0 | I33: =G33 -> 0
G34: =ROUND(D34*F34,0) -> 0 | I34: =G34 -> 0
G35: =ROUND(D35*F35,0) -> 0 | I35: =G35 -> 0
... G49: =ROUND(D49*F49,0) -> 0 | I49: =G49 -> 0
B51: SUBTOTAL Base Bid | G51: =SUBTOTAL(9,G21:G50) -> 8615235 | I51: =SUBTOTAL(9,I21:I50) -> 8615235 | K51: =SUBTOTAL(9,K21:K50) -> 6724337.1 | M51: =SUM(M19:M50) -> 0 | O51: =SUM(O19:O50) -> 0 | Q51: =SUM(Q19:Q50) -> 0 | S51: =SUM(S19:S50) -> 0
B52: BOND RATE | H52: 0 | J52: 0 | L52: 0 | N52: 0 | P52: 0 | R52: 0
B53: BOND AMOUNT | G53: =F52*G51 -> 0 | I53: =H52*I51 -> 0 | K53: =J52*K51 -> 0 | M53: =L52*M51 -> 0 | O53: =N52*O51 -> 0 | Q53: =P52*Q51 -> 0 | S53: =R52*S51 -> 0
B55: ADJUSTED TOTAL | G55: =SUM(G51:G53) -> 8615235 | I55: =SUM(I51:I53) -> 8615235 | K55: =SUM(K51:K53) -> 6724337.1 | M55: =SUM(M51:M53) -> 0 | O55: =SUM(O51:O53) -> 0 | Q55: =SUM(Q51:Q53) -> 0 | S55: =SUM(S51:S53) -> 0
B56: Cost per SF | G56: =G55/'Area Calculations'!$G$5 -> 22.128759 | I56: =I55/'Area Calculations'!$G$5 -> 22.128759 | K56: =K55/'Area Calculations'!$G$5 -> 17.271872 | M56: =M55/'Area Calculations'!$G$5 -> 0 | O56: =O55/'Area Calculations'!$G$5 -> 0 | Q56: =Q55/'Area Calculations'!$G$5 -> 0 | S56: =S55/'Area Calculations'!$G$5 -> 0
A58: QUALIFICATIONS
A62: EXCLUSIONS/OWNER PROVIDED ITEMS:
A66: ALTERNATES:
A70: PROPOSED VE (Provide Clear Description):
A74: FULLY LOADED LABOR RATES
B75: Laborer
B76: Mechanic
B77: Superintendent
B78: Project Manager
A80: SCHEDULE
B81: Prepared shop drawings/submittals
B82: Mobilization
B83: Total duration to complete scope of work
A85: Winner
A86: Company
A87: Contact
A88: Phone
A89: Email
A90: Base Bid | B90: =$I$55 -> 8615235
B92: Need Prequalification
B93: Prequalified

Sheet 26 00 Electrical
G1: Hedrick Plug
F2: X | G2: Excluded
F3: I | G3: Included
B4: BACK TO SUMMARY SHEET | G4: Sub Add/Deduct
A5: Project: | B5: ='Area Calculations'!B4 -> Bourbon Hotel Orlando | G5: Company
A6: Trade: | B6: Electrical | G6: Contact
A7: CSI Code: | B7: 26 00 00 | G7: Phone
A8: Date: | G8: Email
G9: Adjusted Bid | H9: =I$55 -> 12741754 | J9: =K$55 -> 0 | L9: =M$55 -> 0 | N9: =O$55 -> 0 | P9: =Q$55 -> 0 | R9: =S$55 -> 0
A10: BID DOCUMENTS: | C10: Plan/ Spec. Package | D10: QTY | E10: U/M | F10: Unit Cost | G10: Subtotal | H10: Yes/No | I10: Price | J10: Yes/No | K10: Price | L10: Yes/No | M10: Price | N10: Yes/No | O10: Price | P10: Yes/No | Q10: Price | R10: Yes/No | S10: Price
B11: GENERAL INCLUSIONS
B12: INCLUDES ALL SALES TAX
B13: ALL HOISTING & RIGGING REQUIRED TO COMPLETE THIS SCOPE
B14: PROVIDE P&P BONDS
B15: FLORIDA STATE CONTRACTORS LIC.
B16: GENERAL LIABILITY AND WORKERS COMP. INSURANCE LIMITS
B17: STATE AND LOCAL TAXES
B18: SPECIFIC TRADE SCOPE OF WORK REQUIREMENTS
B19: BASE BID
B21: Hotel & Restaurant | G21: =ROUND(D21*F21,0) -> 0 | I21: =G21 -> 0
B22: Electrical | D22: ='Area Calculations'!G5-'Area Calculations'!E14 -> 279298 | E22: sf | F22: 30 | G22: =ROUND(D22*F22,0) -> 8378940 | I22: =G22 -> 8378940
B23: Light Fixtures - units | D23: 296 | E23: units | F23: 1800 | G23: =ROUND(D23*F23,0) -> 532800 | I23: =G23 -> 532800
B24: Light Fixtures - service / BOH | D24: 19145 | E24: sf | F24: 5 | G24: =ROUND(D24*F24,0) -> 95725 | I24: =G24 -> 95725
B25: Light Fixtures - corridor | D25: 38650 | E25: sf | F25: 5 | G25: =ROUND(D25*F25,0) -> 193250 | I25: =G25 -> 193250
B26: Light Fixtures - lobby / reception - decorative | D26: 7754 | E26: sf | F26: 10 | G26: =ROUND(D26*F26,0) -> 77540 | I26: =G26 -> 77540
B27: Fire Alarm | D27: ='Area Calculations'!G5-'Area Calculations'!E14 -> 279298 | E27: sf | F27: 1.25 | G27: =ROUND(D27*F27,0) -> 349123 | I27: =G27 -> 349123
B28: Low Voltage | D28: ='Area Calculations'!G5-'Area Calculations'!E14 -> 279298 | E28: sf | F28: 2.5 | G28: =ROUND(D28*F28,0) -> 698245 | I28: =G28 -> 698245
B29: Low Voltage - structured cabling | G29: =ROUND(D29*F29,0) -> 0 | I29: =G29 -> 0
B30: Low Voltage - security | G30: =ROUND(D30*F30,0) -> 0 | I30: =G30 -> 0
B31: Low Voltage - A/V | G31: =ROUND(D31*F31,0) -> 0 | I31: =G31 -> 0
B32: Low Voltage - Comunications | E32: sf | G32: =ROUND(D32*F32,0) -> 0 | I32: =G32 -> 0
B33: BDA / DAS system | D33: 390291 | E33: sf | F33: 1.2 | G33: =ROUND(D33*F33,0) -> 468349 | I33: =G33 -> 468349
B34: Lighting protection | D34: 1 | E34: ls | F34: 150000 | G34: =ROUND(D34*F34,0) -> 150000 | I34: =G34 -> 150000
B35: Generator | D35: 1 | E35: ls | F35: 350000 | G35: =ROUND(D35*F35,0) -> 350000 | I35: =G35 -> 350000
B36: Site - electrical | D36: 1 | E36: ls | F36: 30000 | G36: =ROUND(D36*F36,0) -> 30000 | I36: =G36 -> 30000
B37: Site - Lighting | D37: 1 | E37: ls | F37: 30000 | G37: =ROUND(D37*F37,0) -> 30000 | I37: =G37 -> 30000
G38: =ROUND(D38*F38,0) -> 0 | I38: =G38 -> 0
B39: Parking Level | G39: =ROUND(D39*F39,0) -> 0 | I39: =G39 -> 0
B40: Electrical | D40: 110025 | E40: sf | F40: 6.5 | G40: =ROUND(D40*F40,0) -> 715163 | I40: =G40 -> 715163
B41: Lighting | D41: 110025 | E41: sf | F41: 3 | G41: =ROUND(D41*F41,0) -> 330075 | I41: =G41 -> 330075
B42: Fire Alarm | D42: 110025 | E42: sf | F42: 1.25 | G42: =ROUND(D42*F42,0) -> 137531 | I42: =G42 -> 137531
B43: Low Voltage | D43: 110025 | E43: sf | F43: 0.5 | G43: =ROUND(D43*F43,0) -> 55013 | I43: =G43 -> 55013
G44: =ROUND(D44*F44,0) -> 0 | I44: =G44 -> 0
B45: Pool & water feature electrical | D45: 1 | E45: ls | F45: 150000 | G45: =ROUND(D45*F45,0) -> 150000 | I45: =G45 -> 150000
G46: =ROUND(D46*F46,0) -> 0 | I46: =G46 -> 0
G47: =ROUND(D47*F47,0) -> 0 | I47: =G47 -> 0
G48: =ROUND(D48*F48,0) -> 0 | I48: =G48 -> 0
G49: =ROUND(D49*F49,0) -> 0 | I49: =G49 -> 0
B51: SUBTOTAL Base Bid | G51: =SUBTOTAL(9,G22:G50) -> 12741754 | I51: =SUBTOTAL(9,I20:I50) -> 12741754 | K51: =SUBTOTAL(9,K20:K50) -> 0 | M51: =SUBTOTAL(9,M20:M50) -> 0 | O51: =SUBTOTAL(9,O20:O50) -> 0 | Q51: =SUBTOTAL(9,Q20:Q50) -> 0 | S51: =SUBTOTAL(9,S20:S50) -> 0
B52: BOND RATE | H52: 0 | J52: 0 | L52: 0 | N52: 0 | P52: 0 | R52: 0
B53: BOND AMOUNT | G53: =F52*G51 -> 0 | I53: =H52*I51 -> 0 | K53: =J52*K51 -> 0 | M53: =L52*M51 -> 0 | O53: =N52*O51 -> 0 | Q53: =P52*Q51 -> 0 | S53: =R52*S51 -> 0
B55: ADJUSTED TOTAL | G55: =SUM(G51:G53) -> 12741754 | I55: =SUM(I51:I53) -> 12741754 | K55: =SUM(K51:K53) -> 0 | M55: =SUM(M51:M53) -> 0 | O55: =SUM(O51:O53) -> 0 | Q55: =SUM(Q51:Q53) -> 0 | S55: =SUM(S51:S53) -> 0
B56: Cost per SF | G56: =G55/'Area Calculations'!$G$5 -> 32.727977 | I56: =I55/'Area Calculations'!$G$5 -> 32.727977 | K56: =K55/'Area Calculations'!$G$5 -> 0 | M56: =M55/'Area Calculations'!$G$5 -> 0 | O56: =O55/'Area Calculations'!$G$5 -> 0 | Q56: =Q55/'Area Calculations'!$G$5 -> 0 | S56: =S55/'Area Calculations'!$G$5 -> 0
A58: QUALIFICATIONS
A62: EXCLUSIONS/OWNER PROVIDED ITEMS:
A66: ALTERNATES:
B67: Generator
A70: PROPOSED VE (Provide Clear Description):
A74: FULLY LOADED LABOR RATES
A80: SCHEDULE
A85: Winner
A86: Company
A87: Contact
A88: Phone
A89: Email
A90: Base Bid | B90: =$I$55 -> 12741754
B92: Need Prequalification
B93: Prequalified

Sheet 31 30 Site Work
G1: Hedrick Plug
F2: X | G2: Excluded
F3: I | G3: Included
B4: BACK TO SUMMARY SHEET | G4: Sub Add/Deduct
A5: Project: | B5: ='Area Calculations'!B4 -> Bourbon Hotel Orlando | G5: Company
A6: Trade: | B6: Site Work | G6: Contact
A7: CSI Code: | B7: 31 30 00 | G7: Phone
A8: Date: | G8: Email
G9: Adjusted Bid | H9: =I$65 -> 992609 | J9: =K$65 -> 0 | L9: =M$65 -> 0 | N9: =O$65 -> 0 | P9: =Q$65 -> 0 | R9: =S$65 -> 0
A10: BID DOCUMENTS: | C10: Plan/ Spec. Package | D10: QTY | E10: U/M | F10: Unit Cost | G10: Subtotal | H10: Yes/No | I10: Price | J10: Yes/No | K10: Price | L10: Yes/No | M10: Price | N10: Yes/No | O10: Price | P10: Yes/No | Q10: Price | R10: Yes/No | S10: Price
B11: GENERAL INCLUSIONS
B12: INCLUDES ALL SALES TAX
B13: ALL HOISTING & RIGGING REQUIRED TO COMPLETE THIS SCOPE
B14: PROVIDE P&P BONDS
B15: FLORIDA STATE CONTRACTORS LIC.
B16: GENERAL LIABILITY AND WORKERS COMP. INSURANCE LIMITS
B17: STATE AND LOCAL TAXES
B18: SPECIFIC TRADE SCOPE OF WORK REQUIREMENTS
B19: BASE BID
B21: General
B22: General Conditions / Mobilization | G22: =ROUND(D22*F22,0) -> 0 | I22: =G22 -> 0
B23: Survey / layout / as-builts | D23: 1 | E23: ls | F23: 15000 | G23: =ROUND(D23*F23,0) -> 15000 | I23: =G23 -> 15000
B24: MOT | D24: 1 | E24: ls | F24: 25000 | G24: =ROUND(D24*F24,0) -> 25000 | I24: =G24 -> 25000
G25: =ROUND(D25*F25,0) -> 0 | I25: =G25 -> 0
B26: Erosion Control | G26: =ROUND(D26*F26,0) -> 0 | I26: =G26 -> 0
B27: Silt Fence | D27: 1774 | E27: lf | F27: 2.2 | G27: =ROUND(D27*F27,0) -> 3903 | I27: =G27 -> 3903
B28: Silt Fence - Maintenance sitework durration | G28: =ROUND(D28*F28,0) -> 0 | I28: =G28 -> 0
B29: Silt Fence - Maintenance HB | G29: =ROUND(D29*F29,0) -> 0 | I29: =G29 -> 0
B30: Construction Entrances | D30: 2 | E30: ea | F30: 10000 | G30: =ROUND(D30*F30,0) -> 20000 | I30: =G30 -> 20000
B31: Construction Entrances - Maintenance | G31: =ROUND(D31*F31,0) -> 0 | I31: =G31 -> 0
B32: Construction Entrances - Maintenance HB | D32: 6 | E32: mo | F32: 500 | G32: =ROUND(D32*F32,0) -> 3000 | I32: =G32 -> 3000
B33: Dust Control | D33: 1 | E33: ls | F33: 10000 | G33: =ROUND(D33*F33,0) -> 10000 | I33: =G33 -> 10000
B34: Street Sweeping | D34: 1 | E34: ls | F34: 12000 | G34: =ROUND(D34*F34,0) -> 12000 | I34: =G34 -> 12000
B35: Inlet Protection | D35: 5 | E35: ea | F35: 350 | G35: =ROUND(D35*F35,0) -> 1750 | I35: =G35 -> 1750
G36: =ROUND(D36*F36,0) -> 0 | I36: =G36 -> 0
B37: Demolition | G37: =ROUND(D37*F37,0) -> 0 | I37: =G37 -> 0
B38: clear & grub | D38: ='Area Calculations'!G7 -> 4.0078283 | E38: acre | F38: 1500 | G38: =ROUND(D38*F38,0) -> 6012 | I38: =G38 -> 6012
G39: =ROUND(D39*F39,0) -> 0 | I39: =G39 -> 0
B40: Earthwork | G40: =ROUND(D40*F40,0) -> 0 | I40: =G40 -> 0
B41: strip top soil & haul-off | D41: ='Area Calculations'!G7 -> 4.0078283 | E41: acre | F41: 2500 | G41: =ROUND(D41*F41,0) -> 10020 | I41: =G41 -> 10020
B42: site cut & haul-off | D42: =110025*4/27 -> 16300 | E42: cy | F42: 25 | G42: =ROUND(D42*F42,0) -> 407500 | I42: =G42 -> 407500
B43: back-fill perimiter podium walls | D43: =1514*4.5*3/27 -> 757 | E43: cy | F43: 5 | G43: =ROUND(D43*F43,0) -> 3785 | I43: =G43 -> 3785
B44: grade sidewalks | D44: =D51/9 -> 754.44444 | E44: sy | F44: 1 | G44: =ROUND(D44*F44,0) -> 754 | I44: =G44 -> 754
B45: grade green areas | D45: =28920/9 -> 3213.3333 | E45: sy | F45: 1 | G45: =ROUND(D45*F45,0) -> 3213 | I45: =G45 -> 3213
G46: =ROUND(D46*F46,0) -> 0 | I46: =G46 -> 0
B47: Subgrade / Base / Paving | D47: =2134/9 -> 237.11111 | E47: sy | F47: 35 | G47: =ROUND(D47*F47,0) -> 8299 | I47: =G47 -> 8299
G48: =ROUND(D48*F48,0) -> 0 | I48: =G48 -> 0
G49: =ROUND(D49*F49,0) -> 0 | I49: =G49 -> 0
B50: Concrete | G50: =ROUND(D50*F50,0) -> 0 | I50: =G50 -> 0
B51: sidewalk - 6" - on grade | D51: 6790 | E51: sf | F51: 10 | G51: =ROUND(D51*F51,0) -> 67900 | I51: =G51 -> 67900
B52: D curb - on grade | D52: 1466 | E52: lf | F52: 18 | G52: =ROUND(D52*F52,0) -> 26388 | I52: =G52 -> 26388
B53: concrete paving - 6" | D53: 19539 | E53: sf | F53: 15 | G53: =ROUND(D53*F53,0) -> 293085 | I53: =G53 -> 293085
G54: =ROUND(D54*F54,0) -> 0 | I54: =G54 -> 0
B55: Striping & Signage | D55: 1 | E55: ls | F55: 50000 | G55: =ROUND(D55*F55,0) -> 50000 | I55: =G55 -> 50000
G56: =ROUND(D56*F56,0) -> 0 | I56: =G56 -> 0
G57: =ROUND(D57*F57,0) -> 0 | I57: =G57 -> 0
B58: Dewatering | D58: 1 | E58: ls | F58: 25000 | G58: =ROUND(D58*F58,0) -> 25000 | I58: =G58 -> 25000
G59: =ROUND(D59*F59,0) -> 0 | I59: =G59 -> 0
B61: SUBTOTAL Base Bid | G61: =SUBTOTAL(9,G22:G60) -> 992609 | I61: =SUBTOTAL(9,I22:I60) -> 992609 | K61: =SUBTOTAL(9,K22:K60) -> 0 | M61: =SUBTOTAL(9,M22:M60) -> 0 | O61: =SUM(O19:O60) -> 0 | Q61: =SUM(Q19:Q60) -> 0 | S61: =SUM(S19:S60) -> 0
B62: BOND RATE | H62: 0 | J62: 0 | L62: 0 | N62: 0 | P62: 0 | R62: 0
B63: BOND AMOUNT | G63: =F62*G61 -> 0 | I63: =H62*I61 -> 0 | K63: =J62*K61 -> 0 | M63: =L62*M61 -> 0 | O63: =N62*O61 -> 0 | Q63: =P62*Q61 -> 0 | S63: =R62*S61 -> 0
B65: ADJUSTED TOTAL | G65: =SUM(G61:G63) -> 992609 | I65: =SUM(I61:I63) -> 992609 | K65: =SUM(K61:K63) -> 0 | M65: =SUM(M61:M63) -> 0 | O65: =SUM(O61:O63) -> 0 | Q65: =SUM(Q61:Q63) -> 0 | S65: =SUM(S61:S63) -> 0
B66: Cost per SF | G66: =G65/'Area Calculations'!$G$5 -> 2.5495771 | I66: =I65/'Area Calculations'!$G$5 -> 2.5495771 | K66: =K65/'Area Calculations'!$G$5 -> 0 | M66: =M65/'Area Calculations'!$G$5 -> 0 | O66: =O65/'Area Calculations'!$G$5 -> 0 | Q66: =Q65/'Area Calculations'!$G$5 -> 0 | S66: =S65/'Area Calculations'!$G$5 -> 0
A68: QUALIFICATIONS
A72: EXCLUSIONS/OWNER PROVIDED ITEMS:
A76: ALTERNATES:
A80: PROPOSED VE (Provide Clear Description):
A84: FULLY LOADED LABOR RATES
B85: Laborer
B86: Mechanic
B87: Superintendent
B88: Project Manager
A90: SCHEDULE
B91: Prepared shop drawings/submittals
B92: Mobilization
B93: Total duration to complete scope of work
A95: Winner
A96: Company
A97: Contact
A98: Phone
A99: Email
A100: Base Bid | B100: =$I$65 -> 992609
B102: Need Prequalification
B103: Prequalified

Sheet 32 14 00 Hardscape
G1: Hedrick Plug
F2: X | G2: Excluded
F3: I | G3: Included
B4: BACK TO SUMMARY SHEET | G4: Sub Add/Deduct
A5: Project: | B5: ='Area Calculations'!B4 -> Bourbon Hotel Orlando | G5: Company
A6: Trade: | B6: Hardscape | G6: Contact
A7: CSI Code: | B7: 32 14 00 | G7: Phone
A8: Date: | G8: Email
G9: Adjusted Bid | H9: =I$55 -> 965407 | J9: =K$55 -> 0 | L9: =M$55 -> 0 | N9: =O$55 -> 0 | P9: =Q$55 -> 0 | R9: =S$55 -> 0
A10: BID DOCUMENTS: | C10: Plan/ Spec. Package | D10: QTY | E10: U/M | F10: Unit Cost | G10: Subtotal | H10: Yes/No | I10: Price | J10: Yes/No | K10: Price | L10: Yes/No | M10: Price | N10: Yes/No | O10: Price | P10: Yes/No | Q10: Price | R10: Yes/No | S10: Price
B11: GENERAL INCLUSIONS
B12: INCLUDES ALL SALES TAX
B13: ALL HOISTING & RIGGING REQUIRED TO COMPLETE THIS SCOPE
B14: PROVIDE P&P BONDS
B15: FLORIDA STATE CONTRACTORS LIC.
B16: GENERAL LIABILITY AND WORKERS COMP. INSURANCE LIMITS
B17: STATE AND LOCAL TAXES
B18: SPECIFIC TRADE SCOPE OF WORK REQUIREMENTS
B19: BASE BID
B21: Pavers
B22: Traffic pavers | D22: 20235 | E22: sf | F22: 25 | G22: =ROUND(D22*F22,0) -> 505875 | I22: =G22 -> 505875
B23: Pool Deck pavers | D23: =12272+2404 -> 14676 | E23: sf | F23: 22 | G23: =ROUND(D23*F23,0) -> 322872 | I23: =G23 -> 322872
G24: =ROUND(D24*F24,0) -> 0 | I24: =G24 -> 0
B25: Concrete | G25: =ROUND(D25*F25,0) -> 0 | I25: =G25 -> 0
B26: Sidewalk on podium - assume 4" topping concrete | D26: 6859 | E26: sf | F26: 15 | G26: =ROUND(D26*F26,0) -> 102885 | I26: =G26 -> 102885
B27: Paver header curb | D27: 1351 | E27: lf | F27: 25 | G27: =ROUND(D27*F27,0) -> 33775 | I27: =G27 -> 33775
G28: =ROUND(D28*F28,0) -> 0 | I28: =G28 -> 0
G29: =ROUND(D29*F29,0) -> 0 | I29: =G29 -> 0
G30: =ROUND(D30*F30,0) -> 0 | I30: =G30 -> 0
G31: =ROUND(D31*F31,0) -> 0 | I31: =G31 -> 0
G32: =ROUND(D32*F32,0) -> 0 | I32: =G32 -> 0
G33: =ROUND(D33*F33,0) -> 0 | I33: =G33 -> 0
G34: =ROUND(D34*F34,0) -> 0 | I34: =G34 -> 0
G35: =ROUND(D35*F35,0) -> 0 | I35: =G35 -> 0
G36: =ROUND(D36*F36,0) -> 0 | I36: =G36 -> 0
G37: =ROUND(D37*F37,0) -> 0 | I37: =G37 -> 0
G38: =ROUND(D38*F38,0) -> 0 | I38: =G38 -> 0
G39: =ROUND(D39*F39,0) -> 0 | I39: =G39 -> 0
... G49: =ROUND(D49*F49,0) -> 0 | I49: =G49 -> 0
B51: SUBTOTAL Base Bid | G51: =SUBTOTAL(9,G22:G50) -> 965407 | I51: =SUBTOTAL(9,I22:I50) -> 965407 | K51: =SUBTOTAL(9,K22:K50) -> 0 | M51: =SUBTOTAL(9,M22:M50) -> 0 | O51: =SUM(O19:O50) -> 0 | Q51: =SUM(Q19:Q50) -> 0 | S51: =SUM(S19:S50) -> 0
B52: BOND RATE | H52: 0 | J52: 0 | L52: 0 | N52: 0 | P52: 0 | R52: 0
B53: BOND AMOUNT | G53: =F52*G51 -> 0 | I53: =H52*I51 -> 0 | K53: =J52*K51 -> 0 | M53: =L52*M51 -> 0 | O53: =N52*O51 -> 0 | Q53: =P52*Q51 -> 0 | S53: =R52*S51 -> 0
B55: ADJUSTED TOTAL | G55: =SUM(G51:G53) -> 965407 | I55: =SUM(I51:I53) -> 965407 | K55: =SUM(K51:K53) -> 0 | M55: =SUM(M51:M53) -> 0 | O55: =SUM(O51:O53) -> 0 | Q55: =SUM(Q51:Q53) -> 0 | S55: =SUM(S51:S53) -> 0
B56: Cost per SF | G56: =G55/'Area Calculations'!$G$5 -> 2.4797071 | I56: =I55/'Area Calculations'!$G$5 -> 2.4797071 | K56: =K55/'Area Calculations'!$G$5 -> 0 | M56: =M55/'Area Calculations'!$G$5 -> 0 | O56: =O55/'Area Calculations'!$G$5 -> 0 | Q56: =Q55/'Area Calculations'!$G$5 -> 0 | S56: =S55/'Area Calculations'!$G$5 -> 0
A58: QUALIFICATIONS
A62: EXCLUSIONS/OWNER PROVIDED ITEMS:
A66: ALTERNATES:
A70: PROPOSED VE (Provide Clear Description):
A74: FULLY LOADED LABOR RATES
B75: Laborer
B76: Mechanic
B77: Superintendent
B78: Project Manager
A80: SCHEDULE
B81: Prepared shop drawings/submittals
B82: Mobilization
B83: Total duration to complete scope of work
A85: Winner
A86: Company
A87: Contact
A88: Phone
A89: Email
A90: Base Bid | B90: =$I$55 -> 965407
B92: Need Prequalification
B93: Prequalified

Sheet 32 80 00 Landscape
G1: Hedrick Plug
F2: X | G2: Excluded
F3: I | G3: Included
B4: BACK TO SUMMARY SHEET | G4: Sub Add/Deduct
A5: Project: | B5: ='Area Calculations'!B4 -> Bourbon Hotel Orlando | G5: Company
A6: Trade: | B6: Landscape & Irrigation | G6: Contact
A7: CSI Code: | B7: 32 80 00 | G7: Phone
A8: Date: | G8: Email
G9: Adjusted Bid | H9: =I$55 -> 594475 | J9: =K$55 -> 0 | L9: =M$55 -> 0 | N9: =O$55 -> 0 | P9: =Q$55 -> 0 | R9: =S$55 -> 0
A10: BID DOCUMENTS: | C10: Plan/ Spec. Package | D10: QTY | E10: U/M | F10: Unit Cost | G10: Subtotal | H10: Yes/No | I10: Price | J10: Yes/No | K10: Price | L10: Yes/No | M10: Price | N10: Yes/No | O10: Price | P10: Yes/No | Q10: Price | R10: Yes/No | S10: Price
B11: GENERAL INCLUSIONS
B12: INCLUDES ALL SALES TAX
B13: ALL HOISTING & RIGGING REQUIRED TO COMPLETE THIS SCOPE
B14: PROVIDE P&P BONDS
B15: FLORIDA STATE CONTRACTORS LIC.
B16: GENERAL LIABILITY AND WORKERS COMP. INSURANCE LIMITS
B17: STATE AND LOCAL TAXES
B18: SPECIFIC TRADE SCOPE OF WORK REQUIREMENTS
B19: BASE BID
B22: Landscape & Irrigation at grade | D22: 28920 | E22: sf | F22: 10 | G22: =ROUND(D22*F22,0) -> 289200 | I22: =G22 -> 289200
B23: Landscape & Irrigation at podium level | D23: 13942 | E23: sf | F23: 10 | G23: =ROUND(D23*F23,0) -> 139420 | I23: =G23 -> 139420
B24: Landscape & Irrigation at Hotel exterior terrace | D24: 3976 | E24: sf | F24: 15 | G24: =ROUND(D24*F24,0) -> 59640 | I24: =G24 -> 59640
B25: Pavilion rooftop garden | D25: 7081 | E25: sf | F25: 15 | G25: =ROUND(D25*F25,0) -> 106215 | I25: =G25 -> 106215
G26: =ROUND(D26*F26,0) -> 0 | I26: =G26 -> 0
G27: =ROUND(D27*F27,0) -> 0 | I27: =G27 -> 0
G28: =ROUND(D28*F28,0) -> 0 | I28: =G28 -> 0
G29: =ROUND(D29*F29,0) -> 0 | I29: =G29 -> 0
G30: =ROUND(D30*F30,0) -> 0 | I30: =G30 -> 0
G31: =ROUND(D31*F31,0) -> 0 | I31: =G31 -> 0
G32: =ROUND(D32*F32,0) -> 0 | I32: =G32 -> 0
G33: =ROUND(D33*F33,0) -> 0 | I33: =G33 -> 0
G34: =ROUND(D34*F34,0) -> 0 | I34: =G34 -> 0
G35: =ROUND(D35*F35,0) -> 0 | I35: =G35 -> 0
G36: =ROUND(D36*F36,0) -> 0 | I36: =G36 -> 0
G37: =ROUND(D37*F37,0) -> 0 | I37: =G37 -> 0
... G49: =ROUND(D49*F49,0) -> 0 | I49: =G49 -> 0
B51: SUBTOTAL Base Bid | G51: =SUBTOTAL(9,G22:G50) -> 594475 | I51: =SUBTOTAL(9,I22:I50) -> 594475 | K51: =SUBTOTAL(9,K22:K50) -> 0 | M51: =SUBTOTAL(9,M22:M50) -> 0 | O51: =SUM(O19:O50) -> 0 | Q51: =SUM(Q19:Q50) -> 0 | S51: =SUM(S19:S50) -> 0
B52: BOND RATE | H52: 0 | J52: 0 | L52: 0 | N52: 0 | P52: 0 | R52: 0
B53: BOND AMOUNT | G53: =F52*G51 -> 0 | I53: =H52*I51 -> 0 | K53: =J52*K51 -> 0 | M53: =L52*M51 -> 0 | O53: =N52*O51 -> 0 | Q53: =P52*Q51 -> 0 | S53: =R52*S51 -> 0
B55: ADJUSTED TOTAL | G55: =SUM(G51:G53) -> 594475 | I55: =SUM(I51:I53) -> 594475 | K55: =SUM(K51:K53) -> 0 | M55: =SUM(M51:M53) -> 0 | O55: =SUM(O51:O53) -> 0 | Q55: =SUM(Q51:Q53) -> 0 | S55: =SUM(S51:S53) -> 0
B56: Cost per SF | G56: =G55/'Area Calculations'!$G$5 -> 1.5269455 | I56: =I55/'Area Calculations'!$G$5 -> 1.5269455 | K56: =K55/'Area Calculations'!$G$5 -> 0 | M56: =M55/'Area Calculations'!$G$5 -> 0 | O56: =O55/'Area Calculations'!$G$5 -> 0 | Q56: =Q55/'Area Calculations'!$G$5 -> 0 | S56: =S55/'Area Calculations'!$G$5 -> 0
A58: QUALIFICATIONS
A62: EXCLUSIONS/OWNER PROVIDED ITEMS:
A66: ALTERNATES:
A70: PROPOSED VE (Provide Clear Description):
A74: FULLY LOADED LABOR RATES
B75: Laborer
B76: Mechanic
B77: Superintendent
B78: Project Manager
A80: SCHEDULE
B81: Prepared shop drawings/submittals
B82: Mobilization
B83: Total duration to complete scope of work
A85: Winner
A86: Company
A87: Contact
A88: Phone
A89: Email
A90: Base Bid | B90: =$I$55 -> 594475
B92: Need Prequalification
B93: Prequalified

Sheet 41 22 Crane and Hoist
G1: Hedrick Plug
G2: Excluded
B3: BACK TO SUMMARY SHEET | G3: Included | H3: Bidder 1 | J3: Bidder 2 | L3: Bidder 3 | N3: Bidder 4 | P3: Bidder5 | R3: Bidder6
A4: Project: | B4: ='Area Calculations'!B4 -> Bourbon Hotel Orlando | G4: Company
A5: Trade: | B5: Cranes and Hoist | G5: Contact
A6: CSI Code: | B6: 41 22 | G6: Phone
A7: Date: | G7: Email
A8: Adjusted Bid | G8: Adjusted Bid | H8: =I73 -> 0 | J8: =K73 -> 0 | L8: =M73 -> 0 | N8: =O73 -> 0 | P8: =Q73 -> 0 | R8: =S73 -> 0
A9: BID DOCUMENTS: | C9: Plan/ Spec. Package | D9: QTY | E9: U/M | F9: Unit Cost | G9: Subtotal | H9: Yes/No | I9: Price | J9: Yes/No | K9: Price | L9: Yes/No | M9: Price | N9: Yes/No | O9: Price | P9: Yes/No | Q9: Price | R9: Yes/No | S9: Price
B10: Plans By Division
B11: ='Area Calculations'!#REF! -> #REF! | C11: P
B12: ='Area Calculations'!#REF! -> #REF! | C12: P
B13: ='Area Calculations'!#REF! -> #REF! | C13: P
B14: ='Area Calculations'!#REF! -> #REF! | C14: P
B15: ='Area Calculations'!#REF! -> #REF! | C15: P
B16: ='Area Calculations'!#REF! -> #REF! | C16: P
B17: ='Area Calculations'!#REF! -> #REF! | C17: P
B18: ='Area Calculations'!#REF! -> #REF! | C18: P
B19: ='Area Calculations'!#REF! -> #REF! | C19: P
B21: Crane and Hoist
B22: OCIP Insurance per exhibit
B23: GENERAL INCLUSIONS
B24: INCLUDES ALL SALES TAX
B25: ALL HOISTING & RIGGING REQUIRED TO COMPLETE THIS SCOPE
B26: PROVIDE P&P BONDS
B27: FLORIDA STATE CONTRACTORS LIC.
B28: GENERAL LIABILITY AND WORKERS COMP. INSURANCE LIMITS
B29: STATE AND LOCAL TAXES
B30: SPECIFIC TRADE SCOPE OF WORK REQUIREMENTS
B31: BASE BID
B33: Crane SK405.20 by Maxim Crane Works 10/04/23 | D33: 1 | E33: mo | F33: 49418.3
B34: Jib L05 (219 ft Max HR)
B35: Single Trolley
B36: Base S35 Anchor Stools
B37: Tip Capacity 10141 @219'
B38: Max capacity 22046 lbs @105'
B39: Init/Fin Hook Ht 99ft
B41: Crane SK405.20 by Maxim Crane Works 10/04/23 | D41: 1 | E41: mo | F41: 50298.3
B42: Jib L05 (219 ft Max HR)
B43: Single Trolley
B44: Base S32 Anchor Stools
B45: Tip Capacity 10141 @219'
B46: Max capacity 22046 lbs @105'
B47: Init/Fin Hook Ht 137ft
B49: Crane SK405.20 by Maxim Crane Works 10/04/23 | D49: 1 | E49: mo | F49: 52852
B50: Jib L04 (199 ft Max HR)
B51: Single Trolley
B52: Base S60 Anchor Stools
B53: Tip Capacity 13007 @199'
B54: Max capacity 22046 lbs @123'
B55: Init/Fin Hook Ht 176ft
B58: Single Hoist by United Hoist Equipment 4/16/2024 | D58: 1 | E58: mo | F58: 74300.8
B59: Tower Height 85ft
B60: No. of gates 6
B61: Capacity 6000
B63: Twin Hoist by United Hoist Equipment 4/16/2024 | D63: 1 | E63: mo | F63: 123514.3
B64: Tower Height 85ft
B65: No. of gates 12
B66: Capacity 6000
F69: SUBTOTAL | I69: =SUM(I31:I68) -> 0 | K69: =SUM(K31:K68) -> 0 | M69: =SUM(M31:M68) -> 0 | O69: =SUM(O31:O68) -> 0 | Q69: =SUM(Q31:Q68) -> 0 | S69: =SUM(S31:S68) -> 0
F70: BOND RATE | H70: 0 | J70: 0 | L70: 0 | N70: 0 | P70: 0 | R70: 0
F71: BOND AMOUNT | I71: =H70*I69 -> 0 | K71: =J70*K69 -> 0 | M71: =L70*M69 -> 0 | O71: =N70*O69 -> 0 | Q71: =P70*Q69 -> 0 | S71: =R70*S69 -> 0
F73: ADJUSTED TOTAL | I73: =SUM(I69:I71) -> 0 | K73: =SUM(K69:K71) -> 0 | M73: =SUM(M69:M71) -> 0 | O73: =SUM(O69:O71) -> 0 | Q73: =SUM(Q69:Q71) -> 0 | S73: =SUM(S69:S71) -> 0
F74: Cost per SF | I74: =I73/'Area Calculations'!$G$5 -> 0 | K74: =K73/'Area Calculations'!$G$5 -> 0 | M74: =M73/'Area Calculations'!$G$5 -> 0 | O74: =O73/'Area Calculations'!$G$5 -> 0 | Q74: =Q73/'Area Calculations'!$G$5 -> 0 | S74: =S73/'Area Calculations'!$G$5 -> 0
F75: Cost per Unit | I75: =I73/'Area Calculations'!$G$9 -> 0 | K75: =K73/'Area Calculations'!$G$9 -> 0 | M75: =M73/'Area Calculations'!$G$9 -> 0 | O75: =O73/'Area Calculations'!$G$9 -> 0 | Q75: =Q73/'Area Calculations'!$G$9 -> 0 | S75: =S73/'Area Calculations'!$G$9 -> 0
A77: QUALIFICATIONS
A81: EXCLUSIONS/OWNER PROVIDED ITEMS:
A85: ALTERNATES:
A89: PROPOSED VE (Provide Clear Description):
A93: FULLY LOADED LABOR RATES
B94: Laborer
B95: Mechanic
B96: Superintendent
B97: Project Manager
A99: SCHEDULE
B100: Prepared shop drawings/submittals
B101: Mobilization
B102: Total duration to complete scope of work
A104: Winner | B104: Crane
A105: Company
A106: Contact
A107: Phone
A108: Email
A109: Base Bid
A112: Winner | B112: Hoist
A113: Company
A114: Contact
A115: Phone
A116: Email
A117: Base Bid

Sheet SiteWorkPrices
B1: General Conditions
B2: 10 | C2: Mobilization | D2: 1.00LS | F2: 17500 | G2: 17500
B3: 20 | C3: Construction Layout And As-Built Survey | D3: 1.00LS | F3: 33960 | G3: 33960
B5: Erosion Control
B6: 50 | C6: Silt Fence | D6: 2,600.00LF | F6: 1 | G6: 2600
B7: 55 | C7: Silt Fence Maintenance | D7: 6.00MO | F7: 800 | G7: 4800
B8: 70 | C8: Inlet Protection | D8: 22.00EACH | F8: 250 | G8: 5500
B9: 75 | C9: Turbidity Barrier | D9: 100.00LF | F9: 10 | G9: 1000
B11: Site Prep And Mass Grading
B12: 108 | C12: Clear/Grub/Disk Site | D12: 1.00LS | F12: 31000 | G12: 31000
B13: 110 | C13: Site Cut To Fill | D13: 600.00CY | F13: 4.5 | G13: 2700
B14: 115 | C14: Import Fill, Place And Compact | D14: 19,500.00CY | F14: 12 | G14: 234000
B15: 120 | C15: Machine Grade Rough | D15: 28,300.00SY | F15: 0.35 | G15: 9905
B16: 125 | C16: Machine Grade Fine | D16: 28,300.00SY | F16: 1.2 | G16: 33960
B17: 130 | C17: Site Grade Final (Pre-Landscape) | D17: 1.00LS | F17: 34000 | G17: 34000
B18: 135 | C18: Sod Dry Retention Areas | D18: 4,200.00SY | F18: 2.5 | G18: 10500
B20: Paving Onsite
B21: 200 | C21: 12" Stabilized Subgrade, LBR40 | D21: 8,600.00SY | F21: 4.8 | G21: 41280
B22: 205 | C22: 6-1/2" FDOT Rock Base, LBR100 | D22: 8,100.00SY | F22: 11 | G22: 89100
B23: 215 | C23: 3/4" Asphalt Bottom Lift, Type S | D23: 8,000.00SY | F23: 6.6 | G23: 52800
B24: 220 | C24: 3/4" Asphalt Top Lift, Type S | D24: 8,000.00SY | F24: 7 | G24: 56000
B25: 225 | C25: Vehicular Brick Pavers (Standard Size/Color/Pattern) | D25: 85.00SY | F25: 51 | G25: 4335
B26: 230 | C26: Concrete Pavement 6" | D26: 1,500.00SF | F26: 6 | G26: 9000
B27: 240 | C27: Type D Curb (Machined) | D27: 4,250.00LF | F27: 11.2 | G27: 47600
B28: 241 | C28: Type D Curb (Hand Formed) | D28: 110.00LF | F28: 17.2 | G28: 1892
B29: 242 | C29: 2' Valley Gutter Curb | D29: 250.00LF | F29: 19.2 | G29: 4800
B30: 245 | C30: Header Curb | D30: 145.00LF | F30: 21 | G30: 3045
B31: 250 | C31: Concrete Sidewalk 4" | D31: 14,000.00SF | F31: 3.8 | G31: 53200
B32: 252 | C32: Concrete Bike Rack 4" | D32: 120.00SF | F32: 7.2 | G32: 864
... B35: 260 | C35: Striping And Signage | D35: 1.00LS | F35: 13650 | G35: 13650
B37: Storm Drainage
B38: 300 | C38: 4" HDPE RWL (Includes All Fittings) | D38: 55.00LF | F38: 34 | G38: 1870
B39: 305 | C39: 6" HDPE RWL (Includes All Fittings) | D39: 76.00LF | F39: 36 | G39: 2736
B40: 310 | C40: 8" HDPE RWL (Includes All Fittings) | D40: 271.00LF | F40: 43 | G40: 11653
B41: 315 | C41: 12" HDPE | D41: 560.00LF | F41: 38 | G41: 21280
B42: 320 | C42: 15" HDPE | D42: 467.00LF | F42: 44 | G42: 20548
B43: 325 | C43: 18" HDPE | D43: 142.00LF | F43: 50 | G43: 7100
B44: 330 | C44: 24" HDPE | D44: 1,775.00LF | F44: 60 | G44: 106500
B45: 332 | C45: 24" Cap | D45: 61.00LF | F45: 88 | G45: 5368
B46: 335 | C46: 12" HDPE Perforated W/2'x2' Under Drain | D46: 153.00LF | F46: 95 | G46: 14535
B47: 340 | C47: Cleanout With Concrete Collar | D47: 4.00EACH | F47: 980 | G47: 3920
B48: 345 | C48: Yard Drain | D48: 8.00EACH | F48: 1700 | G48: 13600
B49: 350 | C49: Type C Catch Basin W/USF 6212 | D49: 1.00EACH | F49: 4250 | G49: 4250
... B59: 385 | C59: Clean/Final Storm Drainage | D59: 3,560.00LF | F59: 5 | G59: 17800
B61: Sanitary Sewer
B62: 405 | C62: 8" SDR26 (6-8) | D62: 30.00LF | F62: 46 | G62: 1380
B63: 410 | C63: 8" SDR26 (8-10) | D63: 220.00LF | F63: 50 | G63: 11000
B64: 415 | C64: 4' Dia Manhole (6-8) | D64: 1.00EACH | F64: 6500 | G64: 6500
B65: 420 | C65: 4' Dia Manhole (8-10) | D65: 1.00EACH | F65: 7600 | G65: 7600
B66: 425 | C66: 6" SDR26-Sewer Services | D66: 278.00LF | F66: 40 | G66: 11120
B67: 426 | C67: 4" PVC Sanitary Sewer-Grease Trap (Includes All Fittings And Cleanouts) | D67: 1.00LS | F67: 2700 | G67: 2700
B68: 428 | C68: Grease Trap | D68: 2.00EACH | F68: 10000 | G68: 20000
B69: 440 | C69: Sanitary Sewer Dewatering | D69: 250.00LF | F69: 10 | G69: 2500
B70: 445 | C70: Test/Final Sanitary Sewer | D70: 250.00LF | F70: 5 | G70: 1250
B72: Force Main And Lift Station
B73: 460 | C73: 4" C900 Force Main | D73: 305.00LF | F73: 45 | G73: 13725
B74: 470 | C74: MJ Fittings | D74: 1.00LS | F74: 2300 | G74: 2300
B75: 475 | C75: Lift Station | D75: 1.00LS | F75: 132000 | G75: 132000
B76: 485 | C76: Sanitary Sewer Dewatering | D76: 305.00LF | F76: 10 | G76: 3050
B77: 490 | C77: Test/Final Force Main | D77: 305.00LF | F77: 5 | G77: 1525
B79: Potable Water Main
B80: 505 | C80: 8" C900 DR18 Water Main | D80: 1,343.00LF | F80: 30 | G80: 40290
B81: 506 | C81: 8" Ductile Iron Water Main | D81: 50.00LF | F81: 45 | G81: 2250
B82: 510 | C82: 8" Gate Valve Assembly | D82: 4.00EACH | F82: 2600 | G82: 10400
B83: 515 | C83: 6" C900 DR18 Water Main | D83: 110.00LF | F83: 28 | G83: 3080
B84: 520 | C84: 6" Gate Valve Assembly | D84: 2.00EACH | F84: 2350 | G84: 4700
B85: 525 | C85: 4" Single Water Service W/RPZ | D85: 1.00LS | F85: 22000 | G85: 22000
B86: 530 | C86: Fire Hydrant Assembly W/Gate Valve | D86: 4.00EACH | F86: 5300 | G86: 21200
B87: 535 | C87: 4" Gate Valve Assembly | D87: 1.00EACH | F87: 1800 | G87: 1800
B88: 540 | C88: MJ Fittings | D88: 1.00LS | F88: 3550 | G88: 3550
B89: 545 | C89: Lift Station Water Service | D89: 1.00EACH | F89: 2500 | G89: 2500
B90: 550 | C90: Test/Final Water Main | D90: 1.00LS | F90: 2800 | G90: 2800
B92: Fire Main
B93: 600 | C93: 6" Ductile Iron Fire Main | D93: 135.00LF | F93: 70 | G93: 9450
B94: 605 | C94: 6" DDCV | D94: 1.00EACH | F94: 10000 | G94: 10000
B95: 610 | C95: 4" Ductile Iron Fire Main | D95: 15.00LF | F95: 28 | G95: 420
B96: 615 | C96: MJDI Fittings | D96: 1.00LS | F96: 2100 | G96: 2100
B97: 620 | C97: 4" Fire Department Connection | D97: 1.00EACH | F97: 2500 | G97: 2500
B98: 625 | C98: 6" Fire Line Stub Out | D98: 1.00EACH | F98: 1800 | G98: 1800
B99: 630 | C99: Final/Test Fire Main | D99: 1.00LS | F99: 2200 | G99: 2200
B101: General Conditions
B102: 10 | C102: Mobilization | D102: 1.00LS | F102: 17500 | G102: 17500
B103: 20 | C103: Construction Layout And As-Built Survey | D103: 1.00LS | F103: 12040 | G103: 12040
B104: 30 | C104: MOT | D104: 1.00LS | F104: 10000 | G104: 10000
B106: Erosion Control
B107: 50 | C107: Silt Fence | D107: 1,700.00LF | F107: 1 | G107: 1700
B108: 55 | C108: Silt Fence Maintenance | F108: 6.00MO | H108: 800 | J108: 4800
B109: 60 | C109: Aggregate Construction Entrance | F109: 1.00EACH | G109: 3200 | I109: 3200
B110: 65 | C110: Construction Entrance Maintenance | D110: 12.00MO | F110: 1870 | G110: 22440
B111: 70 | C111: Inlet Protection | F111: 8.00EACH | H111: 250 | J111: 2000
B113: Site Prep And Mass Grading
B114: 100 | C114: Demo Existing Asphalt | D114: 900.00SY | F114: 5 | G114: 4500
B115: 105 | C115: Remove Existing Guardrail | H115: 1.00LS | J115: 2600 | M115: 2600
B116: 108 | C116: Clear/Grub/Disk Site | H116: 1.00LS | I116: 13400 | K116: 13400
B117: 110 | C117: Site Cut To Fill | G117: 700.00CY | K117: 4.5 | N117: 3150
B118: 115 | C118: Import Fill, Place And Compact | D118: 11,500.00CY | H118: 12 | I118: 138000
B119: 120 | C119: Machine Grade Rough | D119: 11,600.00SY | I119: 0.35 | L119: 4060
B120: 125 | C120: Machine Grade Fine | D120: 11,600.00SY | I120: 1.2 | K120: 13920
B121: 135 | C121: Sod Dry Retention Areas | F121: 3,800.00SY | J121: 2.5 | M121: 9500
B123: Paving Onsite
...

Sheet UnitPrices
B2: Unit AL-1a | C2: 12 | D2: EA | F2: 471 | G2: sf | H2: =$C$2*F2 -> 5652 | I2: sf | J2: Unit AL-0a | K2: 12 | L2: EA | N2: 357 | O2: sf | P2: =$K$2*N2 -> 4284 | Q2: sf | R2: Unit A1-da | S2: 10 | T2: EA | V2: 686 | W2: sf | X2: =S$2*V2 -> 6860 | Y2: sf | Z2: Unit AL-1b | AA2: 32 | AB2: EA | AD2: 507 | AE2: sf | AF2: =AA$2*AD2 -> 16224 | AG2: sf | AH2: Unit A1-db | AI2: 6 | AJ2: EA | AL2: 845 | AM2: sf | AN2: =AI$2*AL2 -> 5070 | AO2: sf | AP2: Unit MC-0a | AQ2: 4 | AR2: EA | AT2: 357 | AU2: sf | AV2: =AQ$2*AT2 -> 1428 | AW2: sf | AX2: Unit MC-0c | AY2: 2 | AZ2: EA | BB2: 374 | BC2: sf | BD2: =AY$2*BB2 -> 748 | BE2: sf | BF2: Unit MC-0b | BG2: 2 | BH2: EA | BJ2: 300 | BK2: sf | BL2: =BG$2*BJ2 -> 600 | BM2: sf | BN2: Unit MC-2b | BO2: 12 | BP2: EA | BR2: 507 | BS2: sf | BT2: =BO$2*BR2 -> 6084 | BU2: sf | BV2: Unit MC-2a | BW2: 4 | BX2: EA | BZ2: 471 | CA2: sf | CB2: =BW$2*BZ2 -> 1884 | CC2: sf | CD2: Unit MC-0d | CE2: 2 | CF2: EA | CH2: 306 | CI2: sf | CJ2: =CE$2*CH2 -> 612 | CK2: sf | CL2: Unit MC-1a | CM2: 2 | CN2: EA | CP2: 534 | CQ2: sf | CR2: =CM$2*CP2 -> 1068 | CS2: sf | CU2: =H2+P2+X2+AF2+AV2+AN2+BD2+BL2+BT2+CB2+CJ2+CR2 -> 50514 | CV2: sf
D3: drywall | L3: drywall | T3: drywall | AB3: drywall | AJ3: drywall | AR3: drywall | AZ3: drywall | BH3: drywall | BP3: drywall | BX3: drywall | CF3: drywall | CN3: drywall
E4: ceiling height | F4: 375 | G4: sf | H4: =$C$2*F4 -> 4500 | I4: sf | M4: ceiling height | N4: 263.25 | O4: sf | P4: =$K$2*N4 -> 3159 | Q4: sf | U4: ceiling height | V4: 624 | W4: sf | X4: =S$2*V4 -> 6240 | Y4: sf | AC4: ceiling height | AD4: 399.2 | AE4: sf | AF4: =AA$2*AD4 -> 12774.4 | AG4: sf | AK4: ceiling height | AL4: 629.51 | AM4: sf | AN4: =AI$2*AL4 -> 3777.06 | AO4: sf | AS4: ceiling height | AT4: 238.5 | AU4: sf | AV4: =AQ$2*AT4 -> 954 | AW4: sf | BA4: ceiling height | BB4: 289.52 | BC4: sf | BD4: =AY$2*BB4 -> 579.04 | BE4: sf | BI4: ceiling height | BJ4: 267.21 | BK4: sf | BL4: =BG$2*BJ4 -> 534.42 | BM4: sf | BQ4: ceiling height | BR4: 427.03 | BS4: sf | BT4: =BO$2*BR4 -> 5124.36 | BU4: sf | BY4: ceiling height | BZ4: 437.37 | CA4: sf | CB4: =BW$2*BZ4 -> 1749.48 | CC4: sf | CG4: ceiling height | CH4: 274.9 | CI4: sf | CJ4: =CE$2*CH4 -> 549.8 | CK4: sf | CO4: ceiling height | CP4: 465.15 | CQ4: sf | CR4: =CM$2*CP4 -> 930.3 | CS4: sf | CU4: =H4+P4+X4+AF4+AV4+AN4+BD4+BL4+BT4+CB4+CJ4+CR4 -> 40871.86 | CV4: sf
E5: demsing - full height 1/2 | F5: 321 | G5: sf | H5: =$C$2*F5 -> 3852 | I5: sf | M5: demsing - full height 1/2 | N5: 489 | O5: sf | P5: =$C$2*N5 -> 5868 | Q5: sf | U5: demsing - full height 1/2 | V5: 468 | W5: sf | X5: =S$2*V5 -> 4680 | Y5: sf | AC5: demsing - full height 1/2 | AD5: 469 | AE5: sf | AF5: =AA$2*AD5 -> 15008 | AG5: sf | AK5: demsing - full height 1/2 | AL5: 405 | AM5: sf | AN5: =AI$2*AL5 -> 2430 | AO5: sf | AS5: demsing - full height 1/2 | AT5: 487 | AU5: sf | AV5: =AQ$2*AT5 -> 1948 | AW5: sf | BA5: demsing - full height 1/2 | BB5: 453 | BC5: sf | BD5: =AY$2*BB5 -> 906 | BE5: sf | BI5: demsing - full height 1/2 | BJ5: 505 | BK5: sf | BL5: =BG$2*BJ5 -> 1010 | BM5: sf | BQ5: demsing - full height 1/2 | BR5: 467 | BS5: sf | BT5: =BO$2*BR5 -> 5604 | BU5: sf | BY5: demsing - full height 1/2 | BZ5: 296 | CA5: sf | CB5: =BW$2*BZ5 -> 1184 | CC5: sf | CG5: demsing - full height 1/2 | CH5: 309 | CI5: sf | CJ5: =CE$2*CH5 -> 618 | CK5: sf | CO5: demsing - full height 1/2 | CP5: 404 | CQ5: sf | CR5: =CM$2*CP5 -> 808 | CS5: sf | CU5: =H5+P5+X5+AF5+AV5+AN5+BD5+BL5+BT5+CB5+CJ5+CR5 -> 43916 | CV5: sf
E6: exterior wall furring with insulation | F6: 329 | G6: sf | H6: =$C$2*F6 -> 3948 | I6: sf | M6: exterior wall furring with insulation | N6: 150 | O6: sf | P6: =$C$2*N6 -> 1800 | Q6: sf | U6: exterior wall furring with insulation | V6: 333 | W6: sf | X6: =S$2*V6 -> 3330 | Y6: sf | AC6: exterior wall furring with insulation | AD6: 244.5 | AE6: sf | AF6: =AA$2*AD6 -> 7824 | AG6: sf | AK6: exterior wall furring with insulation | AL6: 431.75 | AM6: sf | AN6: =AI$2*AL6 -> 2590.5 | AO6: sf | AS6: exterior wall furring with insulation | AT6: 149.92 | AU6: sf | AV6: =AQ$2*AT6 -> 599.68 | AW6: sf | BA6: exterior wall furring with insulation | BB6: 20 | BC6: sf | BD6: =AY$2*BB6 -> 40 | BE6: sf | BI6: exterior wall furring with insulation | BJ6: 142.09 | BK6: sf | BL6: =BG$2*BJ6 -> 284.18 | BM6: sf | BQ6: exterior wall furring with insulation | BR6: 245.35 | BS6: sf | BT6: =BO$2*BR6 -> 2944.2 | BU6: sf | BY6: exterior wall furring with insulation | BZ6: 353.25 | CA6: sf | CB6: =BW$2*BZ6 -> 1413 | CC6: sf | CG6: exterior wall furring with insulation | CH6: 198.07 | CI6: sf | CJ6: =CE$2*CH6 -> 396.14 | CK6: sf | CO6: exterior wall furring with insulation | CP6: 235.5 | CQ6: sf | CR6: =CM$2*CP6 -> 471 | CS6: sf | CU6: =H6+P6+X6+AF6+AV6+AN6+BD6+BL6+BT6+CB6+CJ6+CR6 -> 25640.7 | CV6: sf
E7: drywall ceiling | F7: =F27 -> 390 | G7: sf | H7: =$C$2*F7 -> 4680 | I7: sf | M7: drywall ceiling | N7: =N27 -> 297 | O7: sf | P7: =$C$2*N7 -> 3564 | Q7: sf | U7: drywall ceiling | V7: =V27 -> 595 | W7: sf | X7: =$C$2*V7 -> 7140 | Y7: sf | AC7: drywall ceiling | AD7: =AD27 -> 429 | AE7: sf | AF7: =$C$2*AD7 -> 5148 | AG7: sf | AK7: drywall ceiling | AL7: =AL27 -> 761 | AM7: sf | AN7: =$C$2*AL7 -> 9132 | AO7: sf | AS7: drywall ceiling | AT7: =AT27 -> 300 | AU7: sf | AV7: =$C$2*AT7 -> 3600 | AW7: sf | BA7: drywall ceiling | BB7: =BB27 -> 316 | BC7: sf | BD7: =$C$2*BB7 -> 3792 | BE7: sf | BI7: drywall ceiling | BJ7: =BJ27 -> 247 | BK7: sf | BL7: =$C$2*BJ7 -> 2964 | BM7: sf | BQ7: drywall ceiling | BR7: =BR27 -> 436 | BS7: sf | BT7: =$C$2*BR7 -> 5232 | BU7: sf | BY7: drywall ceiling | BZ7: =BZ27 -> 405 | CA7: sf | CB7: =$C$2*BZ7 -> 4860 | CC7: sf | CG7: drywall ceiling | CH7: =CH27 -> 247 | CI7: sf | CJ7: =$C$2*CH7 -> 2964 | CK7: sf | CO7: drywall ceiling | CP7: =CP27 -> 455 | CQ7: sf | CR7: =$C$2*CP7 -> 5460 | CS7: sf | CU7: =H7+P7+X7+AF7+AV7+AN7+BD7+BL7+BT7+CB7+CJ7+CR7 -> 58536 | CV7: sf
E8: green board | M8: green board | U8: green board | AC8: green board | AK8: green board | AS8: green board | BA8: green board | BI8: green board | BQ8: green board | BY8: green board | CG8: green board | CO8: green board
D9: millwork | L9: millwork | T9: millwork | AB9: millwork | AJ9: millwork | AR9: millwork | AZ9: millwork | BH9: millwork | BP9: millwork | BX9: millwork | CF9: millwork | CN9: millwork
E10: kitchenette base cabinet | F10: 5 | G10: ft | H10: =$C$2*F10 -> 60 | I10: ft | M10: kitchenette base cabinet | N10: 5 | O10: ft | P10: =$K$2*N10 -> 60 | Q10: ft | U10: kitchenette base cabinet | V10: 5 | W10: ft | X10: =S$2*V10 -> 50 | Y10: ft | AC10: kitchenette base cabinet | AD10: 5 | AE10: ft | AF10: =AA$2*AD10 -> 160 | AG10: ft | AK10: kitchenette base cabinet | AL10: 5 | AM10: ft | AN10: =AI$2*AL10 -> 30 | AO10: ft | AS10: kitchenette base cabinet | AU10: ft | AV10: =AQ$2*AT10 -> 0 | AW10: ft | BA10: kitchenette base cabinet | BC10: ft | BD10: =AY$2*BB10 -> 0 | BE10: ft | BI10: kitchenette base cabinet | BK10: ft | BL10: =BG$2*BJ10 -> 0 | BM10: ft | BQ10: kitchenette base cabinet | BS10: ft | BT10: =BO$2*BR10 -> 0 | BU10: ft | BY10: kitchenette base cabinet | CA10: ft | CB10: =BW$2*BZ10 -> 0 | CC10: ft | CG10: kitchenette base cabinet | CI10: ft | CJ10: =CE$2*CH10 -> 0 | CK10: ft | CO10: kitchenette base cabinet | CQ10: ft | CR10: =CM$2*CP10 -> 0 | CS10: ft | CU10: =H10+P10+X10+AF10+AV10+AN10+BD10+BL10+BT10+CB10+CJ10+CR10 -> 360 | CV10: ft
E11: kitchenette upper cabinet | F11: 7.5 | G11: ft | H11: =$C$2*F11 -> 90 | I11: ft | M11: kitchenette upper cabinet | N11: 7.5 | O11: ft | P11: =$K$2*N11 -> 90 | Q11: ft | U11: kitchenette upper cabinet | V11: 7.5 | W11: ft | X11: =S$2*V11 -> 75 | Y11: ft | AC11: kitchenette upper cabinet | AD11: 7.5 | AE11: ft | AF11: =AA$2*AD11 -> 240 | AG11: ft | AK11: kitchenette upper cabinet | AL11: 7.5 | AM11: ft | AN11: =AI$2*AL11 -> 45 | AO11: ft | AS11: kitchenette base cabinet | AU11: ft | AV11: =AQ$2*AT11 -> 0 | AW11: ft | BA11: kitchenette upper cabinet | BC11: ft | BD11: =AY$2*BB11 -> 0 | BE11: ft | BI11: kitchenette upper cabinet | BK11: ft | BL11: =BG$2*BJ11 -> 0 | BM11: ft | BQ11: kitchenette upper cabinet | BS11: ft | BT11: =BO$2*BR11 -> 0 | BU11: ft | BY11: kitchenette upper cabinet | CA11: ft | CB11: =BW$2*BZ11 -> 0 | CC11: ft | CG11: kitchenette upper cabinet | CI11: ft | CJ11: =CE$2*CH11 -> 0 | CK11: ft | CO11: kitchenette upper cabinet | CQ11: ft | CR11: =CM$2*CP11 -> 0 | CS11: ft | CU11: =H11+P11+X11+AF11+AV11+AN11+BD11+BL11+BT11+CB11+CJ11+CR11 -> 540 | CV11: ft
