Workbook

Sheet Area Calculations
B2: PROJECT AREA CALCULATIONS
B4: Atlantic Fields Club Core / Dock Bar / Spa Pods / Water Features
B5: Hobe Sound | E5: Gross (sf) | F5: =D45 -> 88672
E6: AC (sf) | F6: =C45 -> 72629
E7: Leasable (sf) | F7: =E45 -> 0
E8: Site (acres) | F8: 1
E9: Parking Spaces
E10: No. of Units:
E11: Build Duration (months)
A14: I. | B14: Floors | C14: AC SF | D14: Gross SF | E14: LSF
B15: LEVEL 00
B16: DINING - LOWER LEVEL | C16: =D16 -> 7078 | D16: 7078
B17: DINING - LOWER LEVEL - COVERED PATIO | D17: 511
B18: DINING - LOWER LEVEL - COVERED SERVICE | D18: 1078
B19: FITNESS - LOWER LEVEL | C19: =D19 -> 4746 | D19: 4746
B20: POOL EQUIPMENT 01 | D20: 889
B21: POOL EQUIPMENT 02 | D21: 1413
B22: POOL EQUIPMENT 03 | D22: 562
B23: POOL EQUIPMENT 04 | D23: 1521
B24: WELLNESS - LOWER LEVEL | C24: =D24 -> 12861 | D24: 12861
B25: LEVEL 01
B26: DINING - LEVEL 01 | C26: =D26 -> 10905 | D26: 10905
B27: DINING - LEVEL 01 -COVERED PATIO | D27: 3621
B28: FITNESS - LEVEL 01 | C28: =D28 -> 7857 | D28: 7857
B29: FITNESS - LEVEL 01 - COVERED PATIO | D29: 2615
B30: WELLNESS - LEVEL 01 | C30: =D30 -> 14954 | D30: 14954
B31: WELLNESS - LEVEL 01 - COVERED PATIO | D31: 1522
B32: LEVEL 02
B33: DINING - LEVEL 02 | C33: =D33 -> 3386 | D33: 3386
B34: DINING - LEVEL 02 - COVERED PATIO | D34: 2032
B35: WELLNESS - LEVEL 02 | C35: =D35 -> 8314 | D35: 8314
B36: WELLNESS - LEVEL 02 - COVERED PATIO | D36: 279
B38: DoCK BAR | C38: =D38 -> 2528 | D38: 2528
B45: TOTAL | C45: =SUM(C15:C44) -> 72629 | D45: =SUM(D15:D44) -> 88672 | E45: =SUM(E15:E44) -> 0
A47: II. | C47: Site SF | D47: Site(acres)
B61: TOTAL | C61: =SUM(C51:C59) -> 0 | D61: =SUM(D50:D60) -> 0
A78: IV. | B78: SITE AREAS | E78: $ /UNIT | F78: %
B81: Site Perimeter | E81: LF
B82: Walk Gates
B83: Drive Gates
B84: Tire Grates / Truck Wash
A85: III. | B85: SITE AREAS | E85: $ /UNIT | F85: %
B86: Sidewalks
B87: Drives
B88: Asphalt Parking
B89: Fill CY
A90: III. | B90: Barking Spaces | D90: QTY. | F90: %
F92: =D92/$F$9 -> #DIV/0!
F93: =D93/$F$9 -> #DIV/0!
B95: TOTAL Units | D95: =SUM(D92:D94) -> 0 | F95: =SUM(F92:F94) -> #DIV/0!

Sheet Word C&A
B2: Note 4 - S-121 - W8x10 centered under all CMU
B4: Pool - standard tile, std glass tile - std coping
B23: Finishes
A24: 1 | B24: We have included 5/8" stucco with sand/float finish and bonding agent only at the wellness exterior site wall. All stucco accessories are included as PVC.
A25: 2 | B25: We have included 5/8" scratch coat under stone cladding as specified in A0.32 . The material is assumed to be compatible with the specified mortar bed for the stone cladding
A26: 3 | B26: We include UR-1 (Dur-a-Flex., style: quartz blends, color: hybr-flex EQ) at the tunnels connecting Dining, Fitness and Wellnes ground levels
A27: 4 | B27: We included concrete sealer SC-1 at BOH stair treads
A28: 5 | B28: We have exlcuded all finishes for D-107 Rhoze area as not shown in plans
A29: 6 | B29: We have included 3/4" plywood subfloor and Proflex SIM-90 sound membrane for all wood floors
A30: 7 | B30: We have included BOH ceilings as exposed non painted ceilings.
A31: 8 | B31: We have included high performance painting all decorative C channel fascia
A32: 9 | B32: We have included painting all exposed steel at occupied spaces
A33: 10 | B33: We have included painting exposed pipes at Golf Cart Barn
A34: 11 | B34: We have included Schluter waterproofing at all showers and Laticrete Hydroban waterproofing at Steam Rooms and Hammam room
B38: Framing and Drywall
A39: 1 | B39: We include G60 metal framing as specified. See VA log for deduct
A40: 2 | B40: We include 5/8" CDX fire treated plywood under all ceilings to receive wood cladding
A41: 3 | B41: We include 5/8" CDX plywood backing behind all walls to receive wood cladding
A42: 4 | B42: We have included level 5 finish for all front of house areas and level 4 finish for all BOH areas
A43: 5 | B43: We have included 2" rigid insulation for exterior block walls as specified. See VA log for VR Plus Fi Foil option
A44: 6 | B44: We have included R-11 Fiberglass Batt Insulation at interior walls and partitions
A45: 7 | B45: We have included 2" rigid insulation at unconditioned space below conditioned space. Areas to be included are W-001 Cart Barn and D-000A Service Area. See VA log
A46: 8 | B46: We have included 3 5/8" 18 Gga metal studs with 5/8" CDX plywood for all exterior ceilings and soffits
A47: 9 | B47: We have included 3 5/8" 18 Gga metal studs with 5/8" densglass for all exterior framed parapets to receive metal plates

Sheet RFI
A5: Atlantic Fields Club Core
A6: Hobe Sound
A7: Master RFI Log - Pending
A8: =TODAY() -> 46146
A9: No. | B9: Subject | C9: Reference | D9: Question | E9: Date Created | F9: Answer | G9: Date Answered
A10: 1 | B10: Bid Bond | C10: DOCUMENT 001116 - INVITATION TO BID 1.3 BID SECURITY | D10: Please confirm that a bid bond will be required to be submitted with our bid proposal. | E10: 45670 | F10: No bid bond to be required. | G10: 45688
A11: =1+A10 -> 2 | B11: Liquidated damages | C11: DOCUMENT 001116 - INVITATION TO BID 1.5 TIME OF COMPLETION AND LIQUIDATED DAMAGES | D11: This section states that the Work is subject to liquidated damages. Please confirm and if stipulated, provide amounts for damages and how they are to be applied. | E11: 45670 | F11: liquidated damages will be negotiated with the selected contractor. | G11: 45688
A12: =1+A11 -> 3 | B12: AIA Document A701 | C12: DOCUMENT 002113 - INSTRUCTIONS TO BIDDERS 1.2 SUMMARY: | D12: This section refers to an attached sample AIA Document A701 for reference. Please provide a copy of AIA Document A701. | E12: 45670
A13: =1+A15 -> 6 | B13: Existing site conditions | C13: DOCUMENT 003119 - EXISTING CONDITION INFORMATION 1.1 EXISTING CONDITION INFORMATION | D13: Paragraph B. of this section references a site survey of existing conditions. Please provide a copy of the site survey. Please confirm that this survey is representative of the site conditions that will exist when the general contractor is to start work on site. | E13: 45670 | F13: The rough grading is still in progress, so there is no site survey available at this time. However, a survey will be provided Owner will provide a building pad including geotechnical certification to elevation 42 NAVD. A topo survey of all buildings is still being developed but will be provided to the awarded General Contractor during the execution of the construction contract. | G13: 45688
A14: =1+A12 -> 4 | B14: Geotechnical investigation report. | C14: DOCUMENT 003132 - GEOTECHNICAL DATA 1.1 GEOTECHNICAL DATA | D14: Please provide a copy of the referenced geotechnical investigation report. | E14: 45670 | F14: The rough grading is still in progress, so the Geotech report provided is preliminary at this time. However, a final report will be provided prior to mobilization to the site. | G14: 45688
A15: =1+A14 -> 5 | B15: Additional borings | C15: DOCUMENT 003132 - GEOTECHNICAL DATA 1.1 GEOTECHNICAL DATA | D15: Paragraph C.2. states: Any party using information described in the geotechnical report shall make additional test borings and conduct other exploratory operations that may be required to determine the character of subsurface materials that may be encountered. Are we to include the costs for additional test borings and other exploratory operations in our bid proposal? Are we to allow time in our proposed schedule for this work? | E15: 45670 | F15: No. Owner will assume all costs for geotechnical reports and borings. | G15: 45688
A16: =1+A15 -> 6 | B16: Allowances | C16: DOCUMENT 004321 - ALLOWANCE FORM | D16: Paragraph 1.2 B. references Section 012100 "Allowances." Sections 012100 was not provided. Please provide a copy of Section 012100 "Allowances." | E16: 45670 | F16: Only one allowance has been determined at this time. $350,000 for Dining roof retractable awning. Otherwise, bid should be based on the documents provided. Final version of allowances will be added to Section 012100 document during Contract negotiations. | G16: 45688
A17: =1+A16 -> 7 | B17: Form of Agreement | C17: DOCUMENT 006000 - PROJECT FORMS 1.1 FORM OF AGREEMENT AND GENERAL CONDITIONS | D17: This section states that the contract for the Project is to be AIA Document A102, "Standard Form of Agreement between Owner and Contractor, Cost Plus Fee, Guaranteed Maximum Price." The Request for Proposal dated 12/23 references a Stipulate Sum contract. Please confirm the form of contract that will be used for the Project. | E17: 45670 | F17: The contract will be Cost Plus Fee, Guaranteed Maximum Price. Refer to sample copy of AIA A102. | G17: 45688
A18: =1+A17 -> 8 | B18: Special and Supplementary Conditions | C18: SECTION 010000 - GENERAL REQUIREMENTS | D18: Section 1.1 A. references Special and Supplementary Conditions. Please provide a copy of the Special and Supplementary Conditions. | E18: 45670 | F18: There are no special and supplementary conditions at this time. | G18: 45688
A19: =1+A18 -> 9 | B19: Kitchen Equipment | C19: SECTION 011000 - SUMMARY | D19: Section 1.7 B. states that the kitchen equipment installation will be under a separate contract with the owner. Sections 1.8 A. and B. indicate that the owner's contract for the kitchen equipment will be assigned to the Contractor. Please confirm that this contract will be assigned to the Contractor and if so, please provided a copy of the contract. Are we to include the value of this contract in our bid proposal? | E19: 45670 | F19: Section 1.8.B-a is incorrect and will be removed from the specifications. | G19: 45688
A20: =1+A19 -> 10 | B20: Owner Furnished Products | C20: SECTION 011000 - SUMMARY Section 1.9 OWNER-FURNISHED PRODUCTS | D20: Please confirm that the items listed in this section will be furnished and installed by the owner. See #8 above regarding the kitchen equipment. | E20: 45670 | F20: Section 1.9 contains owner furnished, contractor installed list of items. | G20: 45688
A21: =1+A20 -> 11 | B21: Owner Furnished Products | C21: SECTION 011000 - SUMMARY Section 1.9 OWNER-FURNISHED PRODUCTS | D21: Assuming that the items in this section are to be furnished and installed by the owner, please confirm that the owner will furnish and install all Division 27 and Division 28 "Low Voltage" scopes of work. | E21: 45670 | F21: Section 1.9 contains owner furnished, contractor installed list of items. Refer to KCL LV drawings for schedule of OFCI vs. | G21: 45688
A22: =1+A21 -> 12 | B22: Early turn over of areas of the project | C22: SECTION 011000 - SUMMARY Section 1.11 COORDINATION WITH OCCUPANTS | D22: This section indicates that the Contractor will be required to turn over areas of the project prior to overall completion of the project and that these areas are to receive a Certificate of Occupancy. Please provide a list of these areas and a schedule indicating when these area are required to be turned over. | E22: 45670 | F22: Main kitchen at Dining Level 01 to receive Temporary Certificate of Occupancy 30 days prior to scheduled construction completion. | G22: 45688
A23: =1+A22 -> 13 | B23: Alternates | C23: SECTION 012300 - ALTERNATES | D23: Section 3.1 references a SCHEDULE OF ALTERNATES. Please provide a copy of the SCHEDULE OF ALTERNATES. | E23: 45670 | F23: There are no additional alternates at this time. | G23: 45688
A24: =1+A23 -> 14 | B24: Site Access Prior to Bid Due Date | D24: Please provide instructions for site access prior to the bid due date. | E24: 45670 | F24: The project site requires security access. Access will be granted on a reserved. Please contact Director of Architecture Peter Oliver to schedule any site visits. | G24: 45688
A25: =1+A24 -> 15 | B25: Site Conditions at Construction Commencement | D25: Please clarify the anticipated site conditions at the commencement of construction, specifically regarding grading and utility installations. What grading will be competed? What utilities will be in place and up to what connection point? | E25: 45670 | F25: Rough grading will be completed to a pad elevation, provided by the Owner, of 42’-0” and utilities will be provided, by Owner, to within 20 feet of the building envelopes. Contractor shall be responsible for site work within the proposed area including parking installation. | G25: 45688
A26: =1+A25 -> 16 | B26: Utility Points of Connection | D26: Regarding the new utilities shown on the civil drawings to be installed by the Contractor, please provide the location of connection points to utilities being brought to the site by others. This includes, but is not limited to, storm drainage, sewer, water, fiber optic, and electrical connections. | E26: 45670 | F26: Owner is providing a pad ready site at all building locations. Owner will provide utilities (water, fireline, sanitary sewer, storm drainage) at 20’ outside of the building footprint. | G26: 45688
A27: =1+A26 -> 17 | B27: Interior Windows | C27: Window Elevation Notes | D27: Window Elevation Notes state that all interior window frame systems are to be Haworth Enclosed Frameless Glass Systems. Please provide a specification for the Haworth Glass system. | E27: 45670 | F27: All Interior window systems are to be Haworth single frame glass fronts systems. Haworth product "4SPACE will be highlighted with specific spec and locations on the revised Window schedule in next submittal | G27: 45688
A28: =1+A27 -> 18 | B28: Door Hardware | C28: Specifications | D28: Two separate Door Hardware Specifications 087100 have been provided. One was included with the architectural plans for the Club Core. The other was included with the overall group of specifications provided most recently. Please confirm which Specification 087100 we should use. | E28: 45670 | F28: Current door Hardware schedule has been revised and updated based on corresponding hardware types to specific doors. | G28: 45688
A29: =1+A28 -> 19 | B29: Dock Bar bar interior floor finish | D29: Please provided a specification for the Dock Bar bar interior floor finish. | E29: 45670 | F29: Interior Floor Finish will be Ipe. Please refer to A0.60. | G29: 45688
A30: =1+A29 -> 20 | B30: Intumescent Fire Coating | C30: A4.13 | D30: Please provide a specification for the Intumescent Fire Coating called for on the Cart Barn structural steel.. | E30: 45670 | F30: Exposed steel columns at Cart Barn intumescent fire coating is specified to be Isolatek CAFCO Spray film or equal. | G30: 45688
A31: =1+A30 -> 21 | B31: Fire Proofing | C31: 1/A4.01 | D31: Detail 1/A4.01 appears to show fire proofing on some of the steel members. Please confirm if this is required and if so, please provide a specification. | E31: 45670 | F31: See revised drawing A4.01 for updated information. Drawing 1/4.01 illustrates a close cell foam insultation (not fireproofing) to underside slab of interior space over an external space for thermal bridging. | G31: 45688
A32: =1+A31 -> 22 | B32: Dock construction | C32: Dock Bar - A8.01 | D32: The details on Drawing A8.01 for the Dock Bar show 2x framing members for the framing of the pier portion of the dock platform. These details refer to the structural drawings. The structural drawings do not include any information regarding this farming. Please provide structural details for the dock (pier) platform framing. | E32: 45673 | F32: Below FF Structural platform slab, piers and beams will all be provided by Ownership prior to Club Core Construction. All sub-flooring elements, columns, walls and roofing will all be coordinated as part of the Club Core scope of work. | G32: 45688
A33: =1+A32 -> 23 | B33: Existing site conditions | C33: DOCUMENT 003119 - EXISTING CONDITION INFORMATION 1.1 EXISTING CONDITION INFORMATION | D33: Paragraph C. 2. of this section references Document 003126 "Existing Hazardous Material Information". Please provide a copy of any hazardous materials reports. | E33: 45673 | F33: No Hazardous Materials are present. | G33: 45688
A34: =1+A33 -> 24 | B34: Storm Drainage Pipe Material | C34: Civil Sheet 24 | D34: Martin County Public Works - Standard Detail R-70 on Civil Sheet 24 states "ALL PIPE LOCATED UNDER ROADWAYS AND/OR RESIDENTIAL PARKING AREAS SHALL BE REINFORCED CONCRETE PIPE (RCP)." Please clarify storm drainage pipe material specification for installations in green areas or otherwise not governed by this detail. | E34: 45673 | F34: Pursuant to the Discovery PUD agreement, ADS may be used in lieu of RCP under all pavement areas. | G34: 45688
A35: =1+A34 -> 25 | B35: Civil Permit Responsibility | C35: Civil sheet 23 | D35: General Construction Note #6 on Civil sheet 23 states "CONTRACTOR SHALL OBTAIN ALL REQUIRED PERMITS / LICENSES PRIOR TO COMMENCING WORK." Please clarify which permits the Contractor shall be responsible for obtaining. | E35: 45673 | F35: Contractor shall be responsible for the building permit. All other permits shall be owners supplied. | G35: 45688
A36: =1+A35 -> 26 | B36: Spa Pod Water Supply | D36: The civil plans do not show a source for the domestic water for Spa Pod buildings. Please clarify. Please provide a plumbing site plan if available. | E36: 45673 | F36: Civil plans are currently being updated per comments from Martin County. Updated plans will be provided by February 14, 2025. Contractor should assume services will be provided to within 20 feet of all buildings. | G36: 45688
A37: =1+A36 -> 27 | B37: Fiber optic site conduits | C37: Telecom drawings TT3.02, TT3.02 | D37: Will the general contractor's electrical subcontractor be responsible for the telecom site conduits shown on the Telecon drawings? | E37: 45673 | F37: Yes, the general contractor's electrical subcontractor be responsible for the telecom site conduits shown on the Telecon drawings. | G37: 45688
A38: =1+A37 -> 28 | B38: Pool Technical Specifications. | D38: The General Notes on pool drawing W0.001 reference a set of "Technical Specifications". Please provide a copy of the following: 13 1105 AQUATIC SPECIFICATIONS TABLE OF CONTENTS 13 1110 AQUATICS GENERAL 13 1113 BELOW-GRADE SWIMMING POOLS (CONCRETE) 13 1114 BELOW-GRADE SWIMMING POOLS (SST/LINER-BASED BASINS) 13 1125 POOL BONDING AND GROUNDING 13 1126 POOL ELECTRICAL 13 1133 ELEVATED SWIMMING POOLS (CONCRETE) 13 1134 ELEVATED SWIMMING POOLS (SST/ LINER-BASED BASINS) 13 1146 SWIMMING POOL ACCESSORIES 22 5100 SWIMMING POOL PLUMBING SYSTEMS | E38: 45673 | F38: Specifications were provided with the doucuments included with the 02/19/25 RFI responses. | G38: 45707
A39: =1+A38 -> 29 | B39: Retractable Awning Canopy | C39: A6.30 | D39: Drawing A6.30 shows a retractable awning canopy in the roof adjacent to the Sky Bar. No information has been provided for this canopy. Should we include an allowance for this? | E39: 45673 | F39: Retractable roof system (Enfold) is still being coordinated, and design has not yet been solidified. Please include an allowance of $350,000.00 so suffice this item. | G39: 45688
A40: =1+A39 -> 30 | B40: Concrete Pier DCP-1 | C40: S-101 | D40: Concrete pier DCP-1 appears to sit on footing at 24'-10" which means pier would be taller than 24". Please confirm pier DCP-1 height | E40: 45673 | F40: DCP-1 extends from foundation at elevation 24'- 10" to first floor framing plan. | G40: 45688
A41: =1+A40 -> 31 | B41: Roofing assembly | D41: The architectural plans show the roofing membrane on ridged insulation on metal deck. Some structural drawing sections show the roofing membrane on ridged insulation on concrete (assume LWIC) on metal deck. Please confirm roofing insulation requirements. | E41: 45673 | F41: Projects roofing conditions are distinguished between two main systems. (i) 1-1/2" Metal Decking with Insulation and roofing application above. (ii) 3" Concrete Slab over 2" Metal Decking. Depending on location (Covered Exterior Space vs. Covered Interior space) Insulation application is as follows: Layer 1 (3.5" Iso board). Layer 2 ( 1/4" Tapered 1-1/2" start point insulation board) Layer 3 (1/8" spot fastened Asphaltic cover board. Please refer to sheet A2.50-A2.54 for all application areas and conditions. | G41: 45688
A42: =1+A41 -> 32 | B42: PVC Roofing Specification | C42: SECTION 07 54 19 POLYVINYL-CHLORIDE (PVC) ROOFING | D42: Roofing specification 07 54 19 was issued with the other Division 7 specifications. Please provide direction as to where this roofing type will apply. | E42: 45673 | F42: Roofing specification 07 54 19 will not be part of the building envelop and should be omitted from bid. | G42: 45688
A43: =1+A42 -> 33 | B43: Pit Slab - Wellness | C43: S-113 | D43: Please provide a section thru the 14" CONC PIT SLAB at column lines U & 21 of does Section 11/S-403.1 also apply here? | E43: 45673 | F43: Section 11/S-403.1 is a similar section at U/21. | G43: 45688
A44: =1+A43 -> 34 | B44: Pit Slab - Wellness | C44: Section 11/S-403.1 | D44: Is the 8" CONC PIT WALL on all 3 sides? | E44: 45673 | F44: yes | G44: 45688
A45: =1+A44 -> 35 | B45: Pool Equipment Room structure | C45: S-103 | D45: Section 12/S-403.2 at the south equipment room wall appears to be an incorrect section. Please provide a section from north wall to south wall. | E45: 45673 | F45: Section is applicable at first floor framing plan. | G45: 45688
A46: =1+A45 -> 36 | B46: Pool Equipment Room structure | C46: S-103 | D46: Please confirm WB-10 running in both directions is the same thing as the 30" CONC MAT. | E46: 45673 | F46: WB-10 is within the 30" concrete mat and is indicated to localize stirrups specified in the concrete beam schedule. | G46: 45688
A47: =1+A46 -> 37 | B47: First Floor Framing Plan - Dining | C47: S-111 | D47: Section 1/S-301.1 appears to be an incorrect section for this location. Please provide the correct section reference. | E47: 45673 | F47: Section 1/S-301.1 is a full building section and is correct on plan. | G47: 45688
A48: =1+A47 -> 38 | B48: Landscaping | C48: LP-200 | D48: Column 2 of the plant list is cropped at the top of the page. Please provide a copy of the complete plant list. | E48: 45673 | F48: column 2 was a continuation of column 1 no plants were missing. These plans will be updated. | G48: 45688
A49: =1+A48 -> 39 | B49: Grease Trap | C49: P119.30 Civil Sheet 29 | D49: Plumbing drawing P119.30 shows a single 1500 gal grease trap. Civil Sheet 29 shows 2 1000 gal grease traps. Please advise. | E49: 45673
A50: =1+A49 -> 40 | B50: Millwork | C50: Elevation 3/ID-5.01 | D50: Reference EQ-107 and EQ-108. Are Freezer and Fridge Drawers to receive MT-103 faced panels? | E50: 45673 | F50: EQ-107 and EQ-108 will receive MT-103 Finish. | G50: 45688
A51: =1+A50 -> 41 | B51: Club BOH Ceiling | C51: A6.10.2 | D51: Please provide specifications for F2 ceiling type (D-015 Storage, W-001 Car Barn) | E51: 45673 | F51: Ceiling type F2 will not be part of the building envelop ceiling type and should be omitted from bid. | G51: 45707
A52: =1+A51 -> 42 | B52: Concrete Piles for dock | D52: In order to determine the pile depth for the dock and dock bar piles we will need to know the lake bottom elevation and final lake water elevation relative to the elevations shown on the structural plans. | E52: 45678 | F52: Concrete Piles, Concrete Beams and 8" Slab are all being furnished and installed by Owner Subcontractor, and not by GC. | G52: 45688
A53: =1+A52 -> 43 | B53: Steel Facia at metal deck canopy | C53: Section 17/S-403.2 | D53: Section 17/S-403.2 incorrectly calls out the c-channel at the perimeter as a W12x20.7. Assuming that one size c-channel is to be used in all locations, what is the correct specification for the c-channel to be used at the facia of all perimeter metal deck canopy? | E53: 45678
A54: =1+A53 -> 44 | B54: BOH ceiling finishes | C54: I5.48,I5.47 | D54: There are no ceiling specifications for the BOH areas in the Club Core, Dock Bar, and Spa Dock. Please confirm if it is the design intent to have exposed, non-painted ceilings in all BOH areas. | E54: 45678 | F54: Yes, the design intent to have exposed, non-painted ceilings in all BOH areas. | G54: 45688
A55: =1+A54 -> 45 | B55: Dining structural roof framing | C55: S-131 | D55: See sheet S-131. There are steel beams labeled as "STEEL BEAM". Please provided sizes for these beams. | E55: 45678
A56: =1+A55 -> 46 | B56: Dining structural roof framing | C56: S-131 | D56: Please provide details for the steal framing at the roof opening for the roof pergola. Framing information surrounding opening is missing. Please advise. | E56: 45678
A57: =1+A56 -> 47 | B57: Fitness structural 3rd floor (roof) framing | C57: S-132 | D57: There are W8 STEEL BEAMS call out for the roof framing for Stair 3. Please provide W8 beam weight specification. | E57: 45678
A58: =1+A57 -> 48 | B58: Missing Note | C58: S-132 | D58: See sheet S-131. Columns at column line L are referenced to NOTE 4. Note 4 is not provided on this sheet. Please provide NOTE 4. | E58: 45678
A59: =1+A58 -> 49 | B59: Wellness spa rooms | D59: 1) Are the spa room modules/assemblies as shown on the Design for Leisure drawings to be included in the GC scope of work? 2) If the spa room modules/assemblies are part of the GC scope of work, is the GC to source the spa room modules/assemblies from Design for Leisure or can the GC go out to other sources? | E59: 45678
A60: =1+A59 -> 50 | B60: Wood panel canopy | C60: S-133 | D60: See sheet S-133 and the wood canopy along the north elevation between column lines U & V. There steel W8X24 beams supporting the canopy. There appear to be intermediate supports between the W8X24 beams. If these are intermediate supports, please provide material spec, sizes and appropriate details. | E60: 45678
A61: =1+A60 -> 51 | B61: Metal on planter wall | C61: A2.30 | D61: Please confirm that the planter shown at the Exterior Terrace D-117 at grid line 03, is to receive metal caldding. Detail 2/A8.13 at this planter does not call out the metal cladding. | E61: 45678 | F61: The planter will receive metal cladding finish. | G61: 45707
A62: =1+A61 -> 52 | B62: Exterior site walls | C62: Club Core 50% Hardscape plans | D62: Very few of the site walls shown on the hardscape plans are labeled with top of wall and bottom of wall elevations. These elevations are needed to determine the stone cladding quantities. Will updated hardscape plans be forthcoming? | E62: 45678
A63: =1+A62 -> 53 | B63: Exterior site walls | C63: Club Core 50% Hardscape plans | D63: See sheet L3.04. The wall details do not provide any structural information for the footings or the walls. This information is not provided on the structural plans. Will structural details for the site retaining walls be forthcoming? | E63: 45678
A64: =1+A63 -> 54 | B64: Finishes | D64: Are there any finish materials that will be supplied by others? If so, please provide a list or a schedule of those finish materials. | E64: 45678 | F64: Drapery Window treatments. Refer to the FFE project manual. | G64: 45707
A65: =1+A64 -> 55 | B65: Entry Bar Wall Finish | C65: ID-5.05 | D65: Please provide specifications for SF-102 plaster. | E65: 45678
A66: =1+A65 -> 56 | B66: Confirm wall type | C66: A2.10.2 | D66: See sheet A2.10.2. There are numerous walls labeled W7.8 which is 8" CMU. These walls are not shown on the structural drawings as CMU. Please advise. | E66: 45679 | F66: Refer to the updated Structural Drawings. | G66: 45707
A67: =1+A66 -> 57 | B67: Exterior wood at Port Cochere | C67: A4.23 | D67: Please provide specification and details for steel column wood infill. | E67: 45679 | F67: Refer to sheet A8.01. | G67: 45707
A68: =1+A67 -> 58 | B68: Exterior wood at Port Cochere | C68: A4.23 | D68: Please provide specification and details for the wood shingle system (ceiling). | E68: 45679
A69: =1+A68 -> 59 | B69: Exterior Soffits at Wellness | C69: A3.04 & A3.05 | D69: Elevations on Sheets A3.04 & A3.05 specify WD-09 at soffits. Sections 1 & 2 on Sheet A4.10 specify WD-08 at soffits. Please confirm soffits are to be WD-08, consistent with other buildings. | E69: 45679 | F69: Wood Soffit to be WD-08 consistently at all buildings. | G69: 45707
A70: =1+A69 -> 60 | B70: Aluminum Windows finish | C70: Spec 085113 | D70: The specification for the Aluminum Windows lists multiple finish types. Please confirm the finish type and color for the Aluminum Windows. | E70: 45679 | F70: Window color to be “High Performance White.” | G70: 45707
A71: =1+A70 -> 61 | B71: Folding Glass Storefronts finish | C71: Spec 084333 | D71: The specification for the Aluminum Windows lists multiple finish types in Sections 3.H. and 3. I. Please confirm the finish color (3.H.) and finish (3.I.) for the Folding Glass Storefronts. | E71: 45679 | F71: There are no longer any folding glass storefronts in the scope of work. Section 08 4333 will be deleted from the Specs. | G71: 45707
A72: =1+A71 -> 62 | B72: Architectural Material Schedule | C72: A0.60 | D72: See Material Schedule. MT-01 calls for a "High Performance Finish". Please provide a specification for this finish. | E72: 45679
A73: =1+A72 -> 63 | B73: Architectural Material Schedule | C73: A0.60 | D73: See Material Schedule. MT-04 calls for a Dark Bronze. Please provide the finish specification for MT-04. | E73: 45679
A74: =1+A73 -> 64 | B74: Planters metal cladding | C74: A0.60 | D74: See Material Schedule. MT-04 is called out for the planters. Some wall sections, elevations and details call for MT-01 at the planters. Please confirm which metal is to be applied at the planters. | E74: 45679 | F74: All planters have MT-04 finish. | G74: 45707
A75: =1+A74 -> 65 | B75: Steel members - architectural vs structural | D75: The architectural and structural are not coordinated with regard to steel member sizes. Are we to assume that the structural drawings will govern? | E75: 45679 | F75: The structural drawings will govern but the General Contractor is responsible for reviewing the Architectural sheets for any misc. steel not included in structural drawings. | G75: 45707
A76: =1+A75 -> 66 | B76: Canopy steel connection | C76: 17/S-401.3 | D76: See section 17/S-401.3. | E76: 45679
A77: =1+A76 -> 67 | B77: Landscape - sod | C77: LP-105 | D77: Sheet LP-105 specifies two areas of sod with differing symbols to the west of the Dining building. Please clarify what type of sod is to be used for each. | E77: 45679
A78: =1+A77 -> 68 | B78: Grasspave | C78: L3.02 | D78: Is a second layer of hyroseed or sod required to be placed over the Grasspave2? | E78: 45679
A79: =1+A78 -> 69 | B79: ST-02 cladding | C79: A0.60 Material Schedule | D79: Regarding the ST-02 Dominical Coral Stone, is it to be honed or filled or just to have a smooth saw cut face? | E79: 45679
A80: =1+A79 -> 70 | B80: Liquor Storage finishes | C80: ID-1.11, ID-7.01 | D80: Liquor storage elevations in ID-1.11 redirect to Door details. Please provide Liquor storage interior wall finishes | E80: 45684 | F80: Refer to updated drawings ID-1.11 and ID-7.01 | G80: 45707
A81: =1+A80 -> 71 | B81: Gym wall panel | C81: 2/ID-5.21, 3/ID-5.21 | D81: Elevation 2/ID-5.21 specifies WC-109 shiplap for the gym wall, while Elevation 4/ID-5.21 specifies WD-109 shiplap. Please confirm if WD-109 is the intended finish for both areas. | E81: 45684 | F81: Confirmed. ID-5.21/D-2 should read as WD-109 shiplap. | G81: 45707
A82: =1+A81 -> 72 | B82: Canopy steel connection | C82: 17/S-401.3 | D82: See section 17/S-401.3. Regarding the "W-Section Beam" where the canopy beam attaches to the tube steel, the size has not been provided on the plans. Please provide size and confirm structural shape for this steel. | E82: 45684
A83: =1+A82 -> 73 | B83: Ribbon Canopy structural | C83: 15/S-402.2 | D83: See detail 15/S-402.2. The beam type/size for the "Cont. Beam At Edge" is not provided. Please provide beam type/size. | E83: 45684
A84: =1+A83 -> 74 | B84: Ribbon Canopy architectural details | C84: 3/A4.20 | D84: See detail 3/A4.20. 1) Please provide specification for "WD Soffit". 2) Please provide specification for "Horizontal Stl Rain Screen" | E84: 45684 | F84: Wd. Soffit to be T&G cypress 5 ½” select grade clear (ref: A0.60). Horizontal steel rain screen is no longer part of this scope of work. | G84: 45707
A85: =1+A84 -> 75 | B85: Dining Port Cochere | C85: A4.22 | D85: See A4.22. Details for the Dinning Port Cochere are incomplete. Please provide complete details showing structure, finishes, materials, etc. | E85: 45684 | F85: Refer to updated sheet A4.22. | G85: 45707
A86: =1+A85 -> 76 | B86: Emergency Generator | C86: E101.00, E181.10 | D86: See E101.00 and E181.10. An emergency Generator and 2 ATS are shown. No specifications for the generator and ATS have been provided. Please provide generator and ATS specifications. | E86: 45684
A87: =1+A86 -> 77 | B87: Exterior stone clad walls | C87: Wall Type W4.8 - A0.32 | D87: See wall type W4.8 on drawing A0.32. This detail calls for a 3/4" direct bond plaster behind the stone. This is addition to the waterproofing, 5/8" scratch coat and 5/8" mud set. All of the double sided stone walls are exterior walls. Is the 3/4" direct bond plaster an actual requirement for this wall type. Please confirm. | E87: 45684 | F87: Refer to sheet A0.32 for updated wall type schedule. | G87: 45707
A88: =1+A87 -> 78 | B88: Ceiling finishes FOH | D88: Interior design drawings indicate painted ceilings for many FOH areas. Please clarify if these ceilings are C1 (painted plaster ceiling) or C3 (gypsum board ceiling) | E88: 45684 | F88: Refer to sheets A6.10 thru A6.32 for Reflected Ceiling Plans that document locations of ceiling finishes. | G88: 45707
A89: =1+A88 -> 79 | B89: Temporary Fence | D89: Please confirm the requirements for temporary fencing of the site. | E89: 45684
A90: =1+A89 -> 80 | B90: Landscape & Irrigation | D90: Please confirm that the landscape and irrigation scope of work will be provided and installed by others. | E90: 45684 | F90: Landscape material shall be supplied by owner; installation and irrigation will be the responsibility of the contractor. | G90: 45707
A91: =1+A90 -> 81 | B91: Civil Scope of Work - utilities | C91: Civil plan Sheets 25 thru 31 | D91: Please confirm that all site water and sanitary utilities will be provided and installed by others up to within 5' of the Club Core structures at the locations shown on the plumbing drawings where utilities are shown to enter the structures. | E91: 45684 | F91: Owner will provide utilities to within 5’-0” of the building envelopes. Contractor shall be responsible for site work within the proposed area including parking installation. | G91: 45707
A92: =1+A91 -> 82 | B92: Civil Scope of Work - storm water | C92: Civil plan Sheets 10 thru 16 | D92: Please confirm that all storm water piping will be provided and installed by others up to within 5' of the Club Core structures at the locations shown on the plumbing drawings where utilities are shown to enter the structures. Currently only the Wellness building shows any storm water piping exiting the building. | E92: 45684 | F92: Owner will provide necessary storm water piping to within 5’-0” of the building envelopes. Contractor shall be responsible for site work within the proposed area including parking installation. | G92: 45707
A93: =1+A92 -> 83 | B93: Civil Scope of Work - grading | C93: Civil plans | D93: 1) Please confirm the grading scope of work that the owner's sitework contractor in accordance with the civil plans. 2) Please confirm the overall site grade elevations that will be representative of the site condition when it is turned over to the GC for construction. | E93: 45684 | F93: A: 1) Contractor will be responsible for finish grading. 2) Rough grading will be completed to a pad elevation, provided by the Owner, of 42’-0”. | G93: 45707
A94: =1+A93 -> 84 | B94: Spa Pod Sanitary | C94: Civil plan Sheet 29 | D94: Please confirm what portion of the sanitary work shown on Civil plan Sheet 29 will be performed by others. | E94: 45684
A95: =1+A94 -> 85 | B95: Dock Bar | C95: Civil plan Sheet 26 | D95: Please confirm the location of the GC point of connection to the Dock Bar sanitary force main being installed by others. | E95: 45684
A96: =1+A95 -> 86 | B96: Hardscape | C96: Hardscape plans Sheets L1.00 thru L1.04 | D96: Please provide a marked up plan or plans that indicate the site wall, retaining wall, paver, concrete paving, crushed stone path, Grasspave and any other hardscape scope of work that will be provided and installed by others. | E96: 45684
A97: =1+A96 -> 87 | B97: Dining storm water piping at Level 00 | C97: P104.10 | D97: There is no storm water piping shown on P104.10. The Dining building storm water piping is not continued from above. Please advise. | E97: 45684 | F97: Storm piping is under development and will be provided in updated Plumbing Drawings on 2/28.. Reference Gravity piping sheets | G97: 45707
A98: =1+A97 -> 88 | B98: Fitness roof drains and storm water piping | C98: P112.22 thru P115.22 | D98: There are no roof drains shown for the Fitness building roof. There is no storm water piping shown on any level. Please Advise. | E98: 45684 | F98: Storm piping is under development and will be provided in updated Plumbing Drawings on 2/28. Reference Gravity piping sheets | G98: 45707
A99: =1+A98 -> 89 | B99: Ribbon Canopy gutter | C99: A2.45, 3/A4.20 | D99: See sheet A2.45. Roof Key Notes #18 and call out on Roof Plan call for a Gutter. Detail 3/A4.20 does not show a gutter. Please advise. | E99: 45684 | F99: STEEL GUTTERS TO BE DESIGNED AT EDGE OF ROOF. COORDINATION TO ALLOW FOR WATER SHED OFF ROOF AREA AT SPECIFIC LOCATION WILL BE SPECIFIED ON UPDATED ROOFING PLANS. | G99: 45707
A100: =1+A99 -> 90 | B100: Concrete add-mixture | C100: Structural Plans | D100: The structural plans include the following note: PROVIDE VANDEX AM-10 ADMIXTURE TO ALL EXTERIOR CONCRETE WALLS, EXPOSED CONCRETE SLABS, AND STRUCTURAL SLABS BELOW GRADE. The architectural drawings call for a waterproofing system on all footings, below grade walls, slab on grade, etc. Is this concrete admixture still required for these area? | E100: 45684
A101: =1+A100 -> 91 | B101: Soprema Roof Specification | C101: Specification 075216-3 | D101: See Specification 075216-3, 2.02 A. This specification states that SOPREMA is the basis of design. Are other equal roofing systems acceptable? | E101: 45684 | F101: SPECIFICATIONS FOR REVISIONS 7 HAVE BEEN REVISEDTO ALLOW FOR ALTERNATIVE MANUFACTURERS. | G101: 45707
A102: =1+A101 -> 92 | B102: Ribbon Canopy Columns | C102: 3/A4.20 | D102: See detail 3/A4.20. This detail is calling for a "WD COLUMN CAP". Is this a wood cladding just on the interior side of the canopy columns? Please clarify and provide specification for the wood. | E102: 45686 | F102: PLEASE SEE SHEET A8.00 FOR STEEL COLUMN, WOOD INSET DETAIL WOOD TO BE 3/4" WITH CLEAR COAT FINISH. | G102: 45707
A103: =1+A102 -> 93 | B103: Galvanized Rebar | C103: Structural Plans | D103: The structural plans include the following note: FOR BALCONIES, SLABS AND WALKWAYS EXPOSED TO WEATHER ALL REINFORCING STEEL SHALL BE GALVANIZED Please provide further clarification regarding where the galvanized reinforcing will be required. If possible, please provide highlighted plans or details indicating locations. | E103: 45686
A104: =1+A103 -> 94 | B104: Level 00 tunnel finishes. | C104: I5.16 | D104: See Interior Design sheet I5.16. There are finishes called out for BOH HALLWAY D-000. Are these finishes continued in the tunnels between Dining & Fitness and Fitness, & Wellness? | E104: 45686 | F104: Yes, these finishes continued in the tunnels between Dining & Fitness and Fitness, & Wellness. | G104: 45707
...

Sheet Documents
A3: ='Area Calculations'!B4 -> Atlantic Fields Club Core / Dock Bar / Spa Pods / Water Features
A4: ='Area Calculations'!B5 -> Hobe Sound
A5: List of Drawings
A6: =TODAY() -> 46146
A7: SHEET NO. | B7: DESCRIPTION | C7: DATE | D7: DATE REC'D | E7: Add #1
B8: CLUB CORE
B9: PEACOCK + LEWIS
A10: CVR | B10: COVER SHEET | C10: 45681 | D10: 45708
A11: A0.00 | B11: SHEET INDEX | C11: 45681 | D11: 45708
A12: A0.01 | B12: SHEET INDEX | C12: 45681 | D12: 45708
A13: S0.02 | B13: GENERAL NOTES AND PROJECT INFORMATION | C13: 45681 | D13: 45708
A14: A0.08 | B14: AREA PLANS | C14: 45681 | D14: 45708
A15: A0.09 | B15: ROOM SCHEDULE | C15: 45681 | D15: 45708
A16: A0.10 | B16: LIEF SAFETY & CODE STUDY | C16: 45681 | D16: 45708
A17: A0.10A | B17: PLUMBING CALCULATIONS | C17: 45681 | D17: 45708
A18: A0.11 | B18: ADA STANDARDS | C18: 45681 | D18: 45708
A19: A0.12 | B19: ADA STANDARDS | C19: 45681 | D19: 45708
A20: A0.13 | B20: LEVEL 00 - LIFE SAFETY OVERALL | C20: 45681 | D20: 45708
A21: A0.14 | B21: LEVEL 01 - LIFE SAFETY OVERALL | C21: 45681 | D21: 45708
... A32: A0.30 | B32: ASSEMBLIES - ROOFS, CEILINGS, FLOORS | C32: 45681 | D32: 45708
A33: A0.31 | B33: ASSEMBLIES - INTERIOR PARTITIONS | C33: 45681 | D33: 45708 | E33: 45723
A34: A0.32 | B34: ASSEMBLIES - EXTERIOR PARTITIONS | C34: 45681 | D34: 45708 | E34: 45723
A35: A0.34 | B35: PARTITION FRAMING DETAILS | C35: 45681 | D35: 45708 | E35: 45723
A36: A0.36 | B36: EXTERIOR DOOR AND WINDOW ELEVATIONS - DINING | C36: 45681 | D36: 45708 | E36: 45723
A37: A0.37 | B37: EXTERIOR DOOR AND WINDOW ELEVATIONS - DINING | C37: 45681 | D37: 45708 | E37: 45723
A38: A0.38 | B38: EXTERIOR DOOR AND WINDOW ELEVATIONS - FITNESS | C38: 45681 | D38: 45708 | E38: 45723
A39: A0.39 | B39: EXTERIOR DOOR AND WINDOW ELEVATIONS - WELLNESS | C39: 45681 | D39: 45708 | E39: 45723
A40: A0.40 | B40: EXTERIOR DOOR AND WINDOW ELEVATIONS - WELLNESS | C40: 45681 | D40: 45708 | E40: 45723
A41: A0.50 | B41: DOOR SCHEDULES | C41: 45681 | D41: 45708 | E41: 45723
A42: A0.51 | B42: DOOR SCHEDULES | C42: 45681 | D42: 45708 | E42: 45723
A43: A0.52 | B43: DOOR ELEVATIONS | C43: 45681 | D43: 45708 | E43: 45723
A44: A0.53 | B44: EXTERIOR DOOR DETAILS | C44: 45681 | D44: 45708
A45: A0.54 | B45: INTERIOR DOOR DETAILS | C45: 45681 | D45: 45708 | E45: 45723
A46: A0.54 A | B46: INTERIOR DOOR DETAILS | E46: 45723
A47: A0.54 B | B47: INTERIOR DOOR DETAILS | E47: 45723
A48: A0.55 | B48: SLIDING GLASS DOOR DETAILS | C48: 45681 | D48: 45708
A49: A0.55.2 | B49: SLIDING GLASS DOOR DETAILS | C49: 45681 | D49: 45708
A50: S0.55.3 | B50: SLIDING GLASS DOOR DETAILS | C50: 45681 | D50: 45708
A51: A0.56 | B51: OVERHEAD COILING DOOR DETAILS | C51: 45681 | D51: 45708
A52: A0.57 | B52: WINDOW + LOUVER DETAILS | C52: 45681 | D52: 45708
A53: A0.58 | B53: STOREFRONT DOOR DETAILS | C53: 45681 | D53: 45708
A54: A0.60 | B54: MATERIAL SCHEDULE | C54: 45681 | D54: 45708 | E54: 45723
A55: A1.00 | B55: SITE PLAN - OVERALL | C55: 45681 | D55: 45708
A56: A2.00 | B56: LEVEL 00 - OVERALL FLOOR PLAN | C56: 45681 | D56: 45708
A57: A2.01 | B57: LEVEL 01 - OVERALL FLOOR PLAN | C57: 45681 | D57: 45708
A58: A2.02 | B58: LEVEL 02 - OVERALL FLOOR PLAN | C58: 45681 | D58: 45708
A59: A2.03 | B59: OVERALL ROOF PLAN | C59: 45681 | D59: 45708
A60: A2.04 | B60: LEVEL 01 - OVERALL CANOPY FLOOR PLAN | C60: 45681 | D60: 45708
A61: A2.10 | B61: LEVEL 00 - DINING OVERALL DIMENSION PLAN | C61: 45681 | D61: 45708
A62: A2.10.1 | B62: LEVEL 00 - DINING SPECIAL CONDITION FLOOR PLAN | C62: 45681 | D62: 45708
A63: A2.10.2 | B63: LEVEL 00 - DINING ENLARGED FLOOR PLAN 01 | C63: 45681 | D63: 45708
A64: A2.10.3 | B64: LEVEL 00 - DINING ENLARGED FLOOR PLAN 02 | C64: 45681 | D64: 45708
A65: A2.11 | B65: LEVEL 00 - FITNESS OVERALL DIMENSION PLAN | C65: 45681 | D65: 45708
A66: A2.11.1 | B66: LEVEL 00 - FITNESS SPECIAL CONDITION FLOOR PLAN | C66: 45681 | D66: 45708
... A76: A2.20.1 | B76: LEVEL 01 - DINING SPECIAL CONDITION FLOOR PLAN | C76: 45681 | D76: 45708
A77: A2.20.2 | B77: LEVEL 01 - DINING ENLARGED FLOOR PLAN 01 | C77: 45681 | D77: 45708 | E77: 45723
A78: A2.20.3 | B78: LEVEL 01 - DINING ENLARGED FLOOR PLAN 02 | C78: 45681 | D78: 45708
A79: A2.20.4 | B79: LEVEL 01 - DINING ENLARGED FLOOR PLAN 03 | C79: 45681 | D79: 45708
A80: A2.20.5 | B80: LEVEL 01 - DINING ENLARGED FLOOR PLAN 04 | C80: 45681 | D80: 45708
A81: A2.20.6 | B81: LEVEL 01 - DINING ENLARGED FLOOR PLAN 05 | C81: 45681 | D81: 45708
A82: A2.20.7 | B82: LEVEL 01 - DINING ENLARGED FLOOR PLAN 06 | C82: 45681 | D82: 45708
A83: A2.21 | B83: LEVEL 01 - FITNESS OVERALL DIMENSION PLAN | C83: 45681 | D83: 45708
A84: A2.21.1 | B84: LEVEL 01 - FITNESS SPECIAL CONDITION FLOOR PLAN | C84: 45681 | D84: 45708
A85: A2.21.2 | B85: LEVEL 01 - FITNESS ENLARGED FLOOR PLAN 01 | C85: 45681 | D85: 45708
A86: A2.21.3 | B86: LEVEL 01 - FITNESS ENLARGED FLOOR PLAN 02 | C86: 45681 | D86: 45708
A87: A2.21.4 | B87: LEVEL 01 - FITNESS ENLARGED FLOOR PLAN 03 | C87: 45681 | D87: 45708
A88: A2.21.5 | B88: LEVEL 01 - FITNESS ENLARGED FLOOR PLAN 04 | C88: 45681 | D88: 45708
A89: A2.22 | B89: LEVEL 01 - WELLNESS OVERALL DIMENSION PLAN | C89: 45681 | D89: 45708
... A104: A2.31.1 | B104: LEVEL 02 - WELLNESS SPECIAL CONDITION FLOOR PLAN | C104: 45681 | D104: 45708
A105: A2.31.2 | B105: LEVEL 02 - WELLNESS ENLARGED FLOOR PLAN 01 | C105: 45681 | D105: 45708 | E105: 45723
A106: A2.31.3 | B106: LEVEL 02 - WELLNESS ENLARGED FLOOR PLAN 02 | C106: 45681 | D106: 45708
A107: A2.31.4 | B107: LEVEL 02 - WELLNESS ENLARGED FLOOR PLAN 03 | C107: 45681 | D107: 45708
A108: A2.31.5 | B108: LEVEL 02 - WELLNESS ENLARGED FLOOR PLAN 04 | C108: 45681 | D108: 45708
A109: A2.32 | B109: POOL DECK | C109: 45681 | D109: 45708 | E109: 45723
A110: A2.40 | B110: ROOF PLAN - DINING | C110: 45681 | D110: 45708 | E110: 45723
A111: A2.41 | B111: ROOF PLAN - DINING | C111: 45681 | D111: 45708 | E111: 45723
A112: A2.42 | B112: ROOF PLAN - FITNESS | C112: 45681 | D112: 45708 | E112: 45723
A113: A2.43 | B113: ROOF PLAN - WELLNESS | C113: 45681 | D113: 45708 | E113: 45723
A114: A2.44 | B114: ROOF PLAN - WELLNESS | C114: 45681 | D114: 45708 | E114: 45723
A115: A2.45 | B115: ROOF PLAN - RIBBON CANOPY | C115: 45681 | D115: 45708 | E115: 45723
A116: A2.50 | B116: ROOF DETAILS | C116: 45681 | D116: 45708 | E116: 45723
A117: A2.51 | B117: ROOF DETAILS | C117: 45681 | D117: 45708 | E117: 45723
A118: A2.52 | B118: ROOF DETAILS | C118: 45681 | D118: 45708 | E118: 45723
A119: S2.53 | B119: ROOF DETAILS | C119: 45681 | D119: 45708 | E119: 45723
A120: A2.54 | B120: ROOF DETAILS | C120: 45681 | D120: 45708 | E120: 45723
... A127: A3.10 | B127: BUILDING SECTIONS - DINING | C127: 45681 | D127: 45708 | E127: 45723
A128: A3.11 | B128: BUILDING SECTIONS - FITNESS | C128: 45681 | D128: 45708
A129: A3.12 | B129: BUILDING SECTIONS - FITNESS | C129: 45681 | D129: 45708
A130: A3.13 | B130: BUILDING SECTIONS - WELLNESS | C130: 45681 | D130: 45708
A131: A3.14 | B131: BUILDING SECTIONS - WELLNESS | C131: 45681 | D131: 45708
A132: A4.00 | B132: WALL SECTONS, ELEVATIONS - DINING | C132: 45681 | D132: 45708 | E132: 45723
A133: A4.01 | B133: WALL SECTONS, ELEVATIONS - DINING | C133: 45681 | D133: 45708
A134: A4.02 | B134: WALL SECTONS, ELEVATIONS - DINING | C134: 45681 | D134: 45708
A135: A4.03 | B135: WALL SECTONS, ELEVATIONS - DINING | C135: 45681 | D135: 45708
A136: A4.06 | B136: WALL SECTONS, ELEVATIONS - FITNESS | C136: 45681 | D136: 45708
A137: A4.07 | B137: WALL SECTONS, ELEVATIONS - FITNESS | C137: 45681 | D137: 45708
A138: A4.08 | B138: WALL SECTONS, ELEVATIONS - WELLNESS | C138: 45681 | D138: 45708
A139: A4.09 | B139: WALL SECTONS, ELEVATIONS - WELLNESS | C139: 45681 | D139: 45708
A140: A4.10 | B140: WALL SECTONS, ELEVATIONS - WELLNESS | C140: 45681 | D140: 45708
A141: A4.11 | B141: WALL SECTONS, ELEVATIONS - WELLNESS | C141: 45681 | D141: 45708
...

Sheet Sub List
A3: ='Area Calculations'!B4 -> Atlantic Fields Club Core / Dock Bar / Spa Pods / Water Features
A4: ='Area Calculations'!B5 -> Hobe Sound
A5: List of Subcontractors
A6: =TODAY() -> 46146
A7: NO. | B7: CSI DIV | C7: NAME
A8: 1 | B8: ='Cost Summary'!A8 -> 02 21 00 | C8: ='02 21 Survey '!H5 -> Velcon Engineering and Surveying
A9: =A8+1 -> 2 | B9: ='Cost Summary'!A9 -> 03 30 00 | C9: ='03 30 CIP Concrete'!H6 -> Victory Concrete
A10: =A9+1 -> 3 | B10: ='Cost Summary'!A10 -> 04 40 00 | C10: ='04 40 Stone Veneer'!H5 -> Titan Stone
A11: =A10+1 -> 4 | B11: ='Cost Summary'!A11 -> 05 10 00 | C11: ='05 10 Structural Steel'!J5 -> VM Iron Works
A12: =A11+1 -> 5 | B12: ='Cost Summary'!A12 -> 05 52 00 | C12: ='05 52 Railings'!H5 -> JC Iron Ornamental
A13: =A12+1 -> 6 | B13: ='Cost Summary'!A13 -> 05 70 00 | C13: ='05 70 Arch Metals'!H5 -> VM Iron Works
A14: =A13+1 -> 7 | B14: ='Cost Summary'!A14 -> 06 10 00 | C14: Hedrick / A-1 Industries
A15: =A14+1 -> 8 | B15: ='Cost Summary'!A15 -> 06 40 00 | C15: ='06 40 Exterior Finish Carpentry'!H5 -> Lotspeich Co.
A16: =A15+1 -> 9 | B16: ='Cost Summary'!A16 -> 06 50 00 | C16: ='06 50 Millwork'!H5 -> Beaubois
A17: =A16+1 -> 10 | B17: ='Cost Summary'!A17 -> 07 17 00 | C17: ='07 17 Waterproofing & Caulk'!H5 -> Triton
A18: =A17+1 -> 11 | B18: ='Cost Summary'!A18 -> 07 21 00 | C18: ='07 21 Insulation'!H5 -> Gale Insulation
A19: =A18+1 -> 12 | B19: ='Cost Summary'!A19 -> 07 50 00 | C19: ='07 50 Roofing'!H5 -> Vero Beach Roofing
A20: =A19+1 -> 13 | B20: ='Cost Summary'!A20 -> 07 81 00 | C20: ='07 81 Fireproofing'!H5 -> Fire Stop Systems
A21: =A20+1 -> 14 | B21: ='Cost Summary'!A21 -> 08 10 70 | C21: ='08 10 DFH'!H5 -> Atlantic Doors & Hard
A22: =A21+1 -> 15 | B22: ='Cost Summary'!A22 -> 08 11 00 | C22: ='08 11 Insect Screens'!H5 -> Shades by Design
A23: =A22+1 -> 16 | B23: ='Cost Summary'!A23 -> 08 33 00 | C23: ='08 33 OH Coiling Doors'!H5 -> D&D Garage Door
A24: =A23+1 -> 17 | B24: ='Cost Summary'!A24 -> 08 50 00 | C24: ='08 50 Storefront'!H5 -> Ready Window
A25: =A24+1 -> 18 | B25: ='Cost Summary'!A25 -> 08 60 00 | C25: ='08 60 Skylights'!H5 -> Skylight Concepts
A26: =A25+1 -> 19 | B26: ='Cost Summary'!A26 -> 09 24 00 | C26: ='09 24 Stucco'!H5 -> Welch Plastering, Inc.
A27: =A26+1 -> 20 | B27: ='Cost Summary'!A27 -> 09 26 00 | C27: ='09 26 Plaster'!L5 -> Foster Reeve & Associates
A28: =A27+1 -> 21 | B28: ='Cost Summary'!A28 -> 09 29 00 | C28: ='09 29 Gypsum Board'!H5 -> Tony Rodrigues Metal Framing, Inc.
A29: =A28+1 -> 22 | B29: ='Cost Summary'!A29 -> 09 30 00 | C29: ='09 30 Tile'!H5 -> Jack Walsh Carpets & Rugs, Inc.
A30: =A29+1 -> 23 | B30: ='Cost Summary'!A30 -> 09 41 00 | C30: ='09 41 Resinous Flooring'!H5 -> Applied Flooring Technologies
A31: =A30+1 -> 24 | B31: ='Cost Summary'!A31 -> 09 51 00 | C31: ='09 51 ACT'!H5 -> Lotspeich Co.
A32: =A31+1 -> 25 | B32: ='Cost Summary'!A32 -> 09 60 00 | C32: ='09 60 Resilient Flooring'!H5 -> Jack Walsh Carpets & Rugs, Inc.
A33: =A32+1 -> 26 | B33: ='Cost Summary'!A33 -> 09 64 00 | C33: ='09 64 Wood Flooring'!H5 -> Jack Walsh Carpets & Rugs, Inc.
A34: =A33+1 -> 27 | B34: ='Cost Summary'!A34 -> 09 90 00 | C34: ='09 90 Painting'!H5 -> Advanced Painting Contractors
A35: =A34+1 -> 28 | B35: ='Cost Summary'!A35 -> 10 22 00 | C35: ='10 22 Demountable Part'!H5 -> Pending
A36: =A35+1 -> 29 | B36: ='Cost Summary'!A36 -> 10 28 00 | C36: ='10 28 Specialties'!H5 -> Interior Specialties
A37: =A36+1 -> 30 | B37: ='Cost Summary'!A37 -> 10 30 00 | C37: ='10 30 Fireplace '!H5 -> Hedrick
A38: =A37+1 -> 31 | B38: ='Cost Summary'!A38 -> 10 51 00 | C38: ='10 51 Lockers'!H5 -> Hollman
A39: =A38+1 -> 32 | B39: ='Cost Summary'!A39 -> 10 53 00 | C39: ='10 53 Signage'!H5 -> Pending
A40: =A39+1 -> 33 | B40: ='Cost Summary'!A40 -> 10 73 00 | C40: ='10 73 Canopy'!H5 -> Pending
A41: =A40+1 -> 34 | B41: ='Cost Summary'!A41 -> 11 40 00 | C41: ='11 40 FS Equip'!H5 -> Cheney Bros
A42: =A41+1 -> 35 | B42: ='Cost Summary'!A42 -> 11 40 00 | C42: ='11 40 Appliances'!H5 -> Hedrick
A43: =A42+1 -> 36 | B43: ='Cost Summary'!A43 -> 12 20 00 | C43: ='12 20 Window Treatments'!H5 -> Shades by Design
A44: =A43+1 -> 37 | B44: ='Cost Summary'!A44 -> 13 11 00 | C44: ='13 11 Pool'!H5 -> Apex
A45: =A44+1 -> 38 | B45: ='Cost Summary'!A45 -> 13 12 00 | C45: ='13 12 Spa Rooms'!H5 -> Design for Leisure
A46: =A45+1 -> 39 | B46: ='Cost Summary'!A46 -> 14 00 00 | C46: ='14 00 Elevators'!H5 -> Otis Elevator Company
A47: =A46+1 -> 40 | B47: ='Cost Summary'!A47 -> 14 91 00 | C47: ='14 91 Linen Chute'!H5 -> Wilkinson Hi-Rise
A48: =A47+1 -> 41 | B48: ='Cost Summary'!A48 -> 21 13 00 | C48: ='21 13 Fire Protection'!H5 -> Century
A49: =A48+1 -> 42 | B49: ='Cost Summary'!A49 -> 22 00 00 | C49: ='22 00 Plumbing '!H5 -> Medic Air Systems
A50: =A49+1 -> 43 | B50: ='Cost Summary'!A50 -> 23 00 00 | C50: ='23 00 HVAC'!H5 -> Mechanicool Inc.
A51: =A50+1 -> 44 | B51: ='Cost Summary'!A51 -> 26 00 00 | C51: ='26 00 Electrical'!H5 -> ECSI
A52: =A51+1 -> 45 | B52: ='Cost Summary'!A52 -> 27 10 00 | C52: ='27 10 Structured Cable'!H5 -> Jade Communications
A53: =A52+1 -> 46 | B53: ='Cost Summary'!A53 -> 27 40 00 | C53: ='27 40 AV System'!H5 -> Jade Communications
A54: =A53+1 -> 47 | B54: ='Cost Summary'!A54 -> 27 50 00 | C54: ='27 53 BDA System'!H5 -> Nautilus RF LLC
A55: =A54+1 -> 48 | B55: ='Cost Summary'!A55 -> 28 10 00 | C55: ='28 10 Security'!H5 -> Jade Communications
A56: =A55+1 -> 49 | B56: ='Cost Summary'!A56 -> 31 30 10 | C56: ='31 30 Site Work'!H5 -> Guettler Brothers
A57: =A56+1 -> 50 | B57: ='Cost Summary'!A57 -> 31 32 00 | C57: ='31 32 Soil Stabilization'!H5 -> Pending
A58: =A57+1 -> 51 | B58: ='Cost Summary'!A58 -> 32 14 00 | C58: ='32 14 Hardsacpe - Walls'!H5 -> Pending
A59: =A58+1 -> 52 | B59: ='Cost Summary'!A59 -> 32 14 00 | C59: ='32 14 Hardsacpe - Pavers'!H5 -> Apex
A60: =A59+1 -> 53 | B60: ='Cost Summary'!A60 -> 32 31 00 | C60: ='32 31 Fence & Gates'!H5 -> A Great Fence
A61: =A60+1 -> 54 | B61: ='Cost Summary'!A61 -> 32 80 00 | C61: ='32 80 Landscape'!H5 -> TCI Rood
A62: =A61+1 -> 55

Sheet Sub Proposal Count
A3: ='Area Calculations'!B4 -> Atlantic Fields Club Core / Dock Bar / Spa Pods / Water Features
A4: ='Area Calculations'!B5 -> Hobe Sound
A5: Subcontractor Proposal Count
A6: =TODAY() -> 46146
A7: NO. | B7: CSI DIV | C7: CSI DESCRIPTION | D7: # SOLICITED | E7: # RECEIVED | F7: NOTES
A8: 1 | B8: ='Cost Summary'!A8 -> 02 21 00 | C8: Surveying | D8: 1 | E8: 1 | F8: Only solicited from Velcon Engineering and Surveying
A9: =A8+1 -> 2 | B9: ='Cost Summary'!A9 -> 03 30 00 | C9: Concrete & CMU | D9: 31 | E9: 7
A10: =A9+1 -> 3 | B10: ='Cost Summary'!A10 -> 04 40 00 | C10: Stone Veneer | D10: 19 | E10: 4
A11: =A10+1 -> 4 | B11: ='Cost Summary'!A11 -> 05 10 00 | C11: Structural Steel | D11: 24 | E11: 3
A12: =A11+1 -> 5 | B12: ='Cost Summary'!A12 -> 05 52 00 | C12: Handrails & Railings - Metal | D12: 13 | E12: 1
A13: =A12+1 -> 6 | B13: ='Cost Summary'!A13 -> 05 70 00 | C13: Interior & Exterior Architectural Metals | D13: 15 | E13: 1 | F13: Mostly allowances, 1 quote for dining stair
A14: =A13+1 -> 7 | B14: ='Cost Summary'!A14 -> 06 10 00 | C14: Rough Carpentry | D14: 3 | E14: 2 | F14: Truss quotes
A15: =A14+1 -> 8 | B15: ='Cost Summary'!A15 -> 06 40 00 | C15: Exterior Finish Carpentry | D15: 17 | E15: 2 | F15: 1 for exterior siding, 1 for Ipe decking
A16: =A15+1 -> 9 | B16: ='Cost Summary'!A16 -> 06 50 00 | C16: Millwork | D16: 23 | E16: 8
A17: =A16+1 -> 10 | B17: ='Cost Summary'!A17 -> 07 17 00 | C17: Waterproofing & Caulking | D17: 25 | E17: 2
A18: =A17+1 -> 11 | B18: ='Cost Summary'!A18 -> 07 21 00 | C18: Insulation - Spray Foam | D18: 10 | E18: 2
A19: =A18+1 -> 12 | B19: ='Cost Summary'!A19 -> 07 50 00 | C19: Roofing | D19: 34 | E19: 6
A20: =A19+1 -> 13 | B20: ='Cost Summary'!A20 -> 07 81 00 | C20: Fireproofing | D20: 8 | E20: 1
A21: =A20+1 -> 14 | B21: ='Cost Summary'!A21 -> 08 10 70 | C21: Doors, Frames, & Hardware | D21: 41 | E21: 1 | F21: Late issuance of total revison of door schedule caused 2 others to back out
A22: =A21+1 -> 15 | B22: ='Cost Summary'!A22 -> 08 11 00 | C22: Roll-Up Insect Screens | D22: 4 | E22: 2
A23: =A22+1 -> 16 | B23: ='Cost Summary'!A23 -> 08 33 00 | C23: Overhead Coiling Doors | D23: 36 | E23: 6
A24: =A23+1 -> 17 | B24: ='Cost Summary'!A24 -> 08 50 00 | C24: Storefront / Glass | D24: 29 | E24: 5
A25: =A24+1 -> 18 | B25: ='Cost Summary'!A25 -> 08 60 00 | C25: Skylights | D25: 2 | E25: 1
A26: =A25+1 -> 19 | B26: ='Cost Summary'!A26 -> 09 24 00 | C26: Stucco | D26: 12 | E26: 3
A27: =A26+1 -> 20 | B27: ='Cost Summary'!A27 -> 09 26 00 | C27: Plaster | D27: 40 | E27: 5
A28: =A27+1 -> 21 | B28: ='Cost Summary'!A28 -> 09 29 00 | C28: Drywall / Framing | D28: 23 | E28: 5
A29: =A28+1 -> 22 | B29: ='Cost Summary'!A29 -> 09 30 00 | C29: Tile Work, Tile & Stone Flooring | D29: 30 | E29: 3
A30: =A29+1 -> 23 | B30: ='Cost Summary'!A30 -> 09 41 00 | C30: Resinous Flooring | D30: 30 | E30: 3
A31: =A30+1 -> 24 | B31: ='Cost Summary'!A31 -> 09 51 00 | C31: Acoustical Ceilings | D31: 11 | E31: 5
A32: =A31+1 -> 25 | B32: ='Cost Summary'!A32 -> 09 60 00 | C32: Flooring | D32: 30 | E32: 3
A33: =A32+1 -> 26 | B33: ='Cost Summary'!A33 -> 09 64 00 | C33: Wood Flooring | D33: 11 | E33: 4
A34: =A33+1 -> 27 | B34: ='Cost Summary'!A34 -> 09 90 00 | C34: Painting | D34: 43 | E34: 5
A35: =A34+1 -> 28 | B35: ='Cost Summary'!A35 -> 10 22 00 | C35: Demountable Partitions | D35: 0 | E35: 0 | F35: Did not receive specification or confimation of locations
A36: =A35+1 -> 29 | B36: ='Cost Summary'!A36 -> 10 28 00 | C36: Specialties | D36: 15 | E36: 3
A37: =A36+1 -> 30 | B37: ='Cost Summary'!A37 -> 10 30 00 | C37: Fireplace | D37: 1 | E37: 1
A38: =A37+1 -> 31 | B38: ='Cost Summary'!A38 -> 10 51 00 | C38: Lockers | D38: 2 | E38: 2 | F38: Only 2 manufactueres specified
A39: =A38+1 -> 32 | B39: ='Cost Summary'!A39 -> 10 53 00 | C39: Signage | D39: 0 | E39: 0 | F39: Allowance
A40: =A39+1 -> 33 | B40: ='Cost Summary'!A40 -> 10 73 00 | C40: Canopy | D40: 0 | E40: 0 | F40: Allowance
A41: =A40+1 -> 34 | B41: ='Cost Summary'!A41 -> 11 40 00 | C41: Food Service & Laundry Equipment | D41: 16 | E41: 1 | F41: All but 1 sub backed out due to equipment supply by others
A42: =A41+1 -> 35 | B42: ='Cost Summary'!A42 -> 11 40 00 | C42: Appliances | D42: 1 | E42: 1
A43: =A42+1 -> 36 | B43: ='Cost Summary'!A43 -> 12 20 00 | C43: Window Treatments | D43: 21 | E43: 2
A44: =A43+1 -> 37 | B44: ='Cost Summary'!A44 -> 13 11 00 | C44: Swimming Pool, Spas & Water Features | D44: 8 | E44: 7
A45: =A44+1 -> 38 | B45: ='Cost Summary'!A45 -> 13 12 00 | C45: Spa Rooms: Steam, Sauna, Hammam, Snow Room | D45: 1 | E45: 1 | F45: Only Design for Leisure can provide their product
A46: =A45+1 -> 39 | B46: ='Cost Summary'!A46 -> 14 00 00 | C46: Elevators | D46: 4 | E46: 1 | F46: Specified as Otis
A47: =A46+1 -> 40 | B47: ='Cost Summary'!A47 -> 14 91 00 | C47: Linen Chute | D47: 6 | E47: 1
A48: =A47+1 -> 41 | B48: ='Cost Summary'!A48 -> 21 13 00 | C48: Fire Protection Systems | D48: 22 | E48: 4
A49: =A48+1 -> 42 | B49: ='Cost Summary'!A49 -> 22 00 00 | C49: Plumbing | D49: 62 | E49: 5
A50: =A49+1 -> 43 | B50: ='Cost Summary'!A50 -> 23 00 00 | C50: HVAC | D50: 99 | E50: 6
A51: =A50+1 -> 44 | B51: ='Cost Summary'!A51 -> 26 00 00 | C51: Electrical | D51: 45 | E51: 4
A52: =A51+1 -> 45 | B52: ='Cost Summary'!A52 -> 27 10 00 | C52: Structured Cabling | D52: 43 | E52: 4
A53: =A52+1 -> 46 | B53: ='Cost Summary'!A53 -> 27 40 00 | C53: Audio Visual Systems | D53: 42 | E53: 4
A54: =A53+1 -> 47 | B54: ='Cost Summary'!A54 -> 27 50 00 | C54: BDA System | D54: 2 | E54: 2
A55: =A54+1 -> 48 | B55: ='Cost Summary'!A55 -> 28 10 00 | C55: Electronic Security & Safety Systems | D55: 40 | E55: 2
A56: =A55+1 -> 49 | B56: ='Cost Summary'!A56 -> 31 30 10 | C56: Sitework | D56: 1 | E56: 1 | F56: Only solicited from Guettler Brothers
A57: =A56+1 -> 50 | B57: ='Cost Summary'!A57 -> 31 32 00 | C57: Soil Stabilization | D57: 0 | E57: 0 | F57: Not enough info provided to bid.
A58: =A57+1 -> 51 | B58: ='Cost Summary'!A58 -> 32 14 00 | C58: Hardscape - Walls | D58: 0 | E58: 0 | F58: All allowances
A59: =A58+1 -> 52 | B59: ='Cost Summary'!A59 -> 32 14 00 | C59: Hardscape - Pavers & Stone | D59: 13 | E59: 6
A60: =A59+1 -> 53 | B60: ='Cost Summary'!A60 -> 32 31 00 | C60: Fencing & Gates | D60: 9 | E60: 1 | F60: Most fence subs will only bid aluminum.
A61: =A60+1 -> 54 | B61: ='Cost Summary'!A61 -> 32 80 00 | C61: Landscaping & Irrigation | D61: 19 | E61: 5
A62: =A61+1 -> 55
D63: =SUM(D8:D62) -> 1037 | E63: =SUM(E8:E62) -> 155

Sheet Allowances
A3: ='Area Calculations'!B4 -> Atlantic Fields Club Core / Dock Bar / Spa Pods / Water Features
A4: ='Area Calculations'!B5 -> Hobe Sound
A5: Allowances
A6: =TODAY() -> 46146
A7: NO. | B7: CSI DIV | C7: DESCRIPTION | D7: VALUE
A8: 1 | B8: 03 30 00 | C8: Note S-200 - Contractor Shall Include In His Base Bid The Cost Of 5 Tons Of Additional Reinforcing Steel, Including Detailing, Fabrication, Bending, Furnishing, And Placing. This Extra Stock Shall Be Furnished And Used For Special Conditions As Directed By The Architect, The Architect'S Agent Or By The Owner'S Construction Supervisor. The Price Of The Unused Extra Stock Shall Be Credited To The Owner'S Account. | D8: ='03 30 CIP Concrete'!G219 -> 25000 | F8: zss
A9: =A8+1 -> 2 | B9: 05 10 00 | C9: Structural Steel Shown Not Sized | D9: ='05 10 Structural Steel'!I187 -> 193446
A10: =A9+1 -> 3 | B10: 05 10 00 | C10: Steel framing at opening for Pergola - S-131 | D10: ='05 10 Structural Steel'!I201 -> 14100
A11: =A10+1 -> 4 | B11: 05 10 00 | C11: Steel shown on architectural plans only | D11: ='05 10 Structural Steel'!I203 -> 149601
A12: =A11+1 -> 5 | B12: 05 10 00 | C12: Steel allowance for arch/struct steel not coordinated, incomplete drawings. | D12: ='05 10 Structural Steel'!I215 -> 210000
A13: =A12+1 -> 6 | B13: 05 10 00 | C13: Spec section 05 12 00 - 3.8 - A. --- All Steel to received SSPC-SP10 Blast & Carbo Zinc II HS Coating | D13: ='05 10 Structural Steel'!I237 -> 350000
A14: =A13+1 -> 7 | B14: 05 10 00 | C14: Note S-200 - Contractor Shall Include In His Base Bid The Cost Of 10,000 Pounds Of Additional Structural Steel (Members Over 10 Lbs. Per Foot) And 10,000 Pounds Of Miscellaneous Steel (Members 10 Lbs. Per Foot Or Less) Including Furnishing, Detailing, Fabrication, Cleaning, Painting, Delivery And Erection. | D14: ='05 10 Structural Steel'!I241+'05 10 Structural Steel'!I242 -> 60000
A15: =A14+1 -> 8 | B15: 05 10 00 | C15: Spa Pods - Steel shown on architectural plans only | D15: ='05 10 Structural Steel'!I279 -> 45998
A16: =A15+1 -> 9 | B16: 05 10 00 | C16: Facilitate steel erection - Crane access before lake fill? Crane barge? CANNOT MAKE FINAL DETERMININATION UNTIL BASE STRUCTURE IS COMPLETE AND WE UNDERSTAND EXISTING CONDITIONS. | D16: ='05 10 Structural Steel'!I268 -> 144000
A17: =A16+1 -> 10 | B17: 05 70 00 | C17: Ribbon Canopy - Decorative steel angle w/ high performance finish - not enough detail | D17: ='05 70 Arch Metals'!G23 -> 32580
A18: =A17+1 -> 11 | B18: 05 70 00 | C18: Club Core - Exterior metal plate cladding - MT-01 - not enough detail | D18: ='05 70 Arch Metals'!G25 -> 288100
A19: =A18+1 -> 12 | B19: 05 70 00 | C19: Club Core - Exterior metal plate cladding at planters - MT-01 & MT-04 - not enough detail | D19: ='05 70 Arch Metals'!G42 -> 154759
A20: =A19+1 -> 13 | B20: 05 70 00 | C20: Club Core - Misc metal plate trim - not enough detail | D20: ='05 70 Arch Metals'!G55 -> 22365
A21: =A20+1 -> 14 | B21: 05 70 00 | C21: Dock Bar - MT--05 misc metal plate trim - not enough detail | D21: ='05 70 Arch Metals'!I62 -> 47180
A22: =A21+1 -> 15 | B22: 05 70 00 | C22: Spa Pods - MT--05 misc metal plate trim - not enough detail | D22: ='05 70 Arch Metals'!G69 -> 63350
A23: =A22+1 -> 16 | B23: 06 40 00 | C23: Club Core Dining - Mechanical Yard Screen. Need WD-11 spec | D23: ='06 40 Exterior Finish Carpentry'!G34 -> 116400
A24: =A23+1 -> 17 | B24: 06 40 00 | C24: Club Core Dining - soffit - Port Cochere - Details incomplete | D24: ='06 40 Exterior Finish Carpentry'!G36 -> 21870
A25: =A24+1 -> 18 | B25: 06 40 00 | C25: Club Core Fitness - WD-06: Trellis - overhang - Details incomplete | D25: ='06 40 Exterior Finish Carpentry'!G40 -> 53039
A26: =A25+1 -> 19 | B26: 06 40 00 | C26: Wellness WD-06: Trellis - lower roof overhang - Details incomplete | D26: ='06 40 Exterior Finish Carpentry'!G52 -> 76800
A27: =A26+1 -> 20 | B27: 06 40 00 | C27: Wellness WD-06: Trellis - upper roof overhang - Details incomplete | D27: ='06 40 Exterior Finish Carpentry'!G53 -> 42720
A28: =A27+1 -> 21 | B28: 06 40 00 | C28: Fitness Pool Cabanas - No dimensions | D28: ='06 40 Exterior Finish Carpentry'!I69 -> 508440
A29: =A28+1 -> 22 | B29: 06 50 00 | C29: Club Core Dinning - Banquettes (D-008 & D-102) | D29: ='06 50 Millwork'!$I$24 -> 210000
A30: =A29+1 -> 23 | B30: 06 50 00 | C30: Club Core Wellness - Stainless-Steel cabinets for Cart wash and prep stations | D30: =43000 -> 43000
A31: =A30+1 -> 24 | B31: 07 50 00 | C31: Ribbon Canopy gutters - no detail - assume aluminum | D31: ='07 50 Roofing'!G79 -> 27150
A32: =A31+1 -> 25 | B32: 07 50 00 | C32: Ribbon Canopy downspouts? - no detail - assume aluminum | D32: ='07 50 Roofing'!G80 -> 2500
A33: =A32+1 -> 26 | B33: 08 10 00 | C33: Aluminum - Custom Engineered - Stacked Panel Shutter - no details | D33: ='08 10 DFH'!G167 -> 84996
A34: =A33+1 -> 27 | B34: 08 50 00 | C34: Glass Railings - conflicting details, missing detail | D34: ='08 50 Storefront'!G184 -> 149000
A35: =A34+1 -> 28 | B35: 10 22 00 | C35: Demountable Partitions - Dining - specifications & locations not provided | D35: ='10 22 Demountable Part'!G24 -> 17246
A36: =A35+1 -> 29 | B36: 10 22 00 | C36: Demountable Partitions - Wellness - specifications & locations not provided | D36: ='10 22 Demountable Part'!G26+'10 22 Demountable Part'!G27 -> 30389
A37: =A36+1 -> 30 | B37: 10 51 00 | C37: Employee Lockers - RFI response changed type - no spec provided | D37: ='10 51 Lockers'!G59 -> 26800
A38: =A37+1 -> 31 | B38: 10 53 00 | C38: Interior & Exterior Signage - sizes, locations, types not provided | D38: ='10 53 Signage'!I21 -> 52750
A39: =A38+1 -> 32 | B39: 10 73 00 | C39: Retractable Awning Canopy - A6.30 - Skybar | D39: ='10 73 Canopy'!G22 -> 350000
A40: =A39+1 -> 33 | B40: 12 20 00 | C40: Drapery track only - propvide and install - spec not provided | D40: ='12 20 Window Treatments'!I79+'12 20 Window Treatments'!I89+'12 20 Window Treatments'!I92 -> 11085
A41: =A40+1 -> 34 | B41: 12 20 00 | C41: Roller Shades - installation of power supplies, wiring & controls - not shown on electrical or lighting control drawings | D41: ='12 20 Window Treatments'!G84 -> 34500
A42: =A41+1 -> 35 | B42: 13 11 00 | C42: Rock/stone within water feature & surounding rock - material not specified | D42: ='13 11 Pool'!G66+'13 11 Pool'!G73 -> 817100
A43: =A42+1 -> 36 | B43: 13 11 00 | C43: Water Feature at Dining Entrance - no details | D43: ='13 11 Pool'!G77 -> 70000
A44: =A43+1 -> 37 | B44: 13 12 00 | C44: Design for Leisure spas - Lighting controls - nothing shown | D44: ='13 12 Spa Rooms'!G66 -> 21000
A45: =A44+1 -> 38 | B45: 14 00 00 | C45: FOH Cab finishes - ID-6.90 - details vague , assume for FOH cabs only | D45: ='14 00 Elevators'!G73 -> 75000
A46: =A45+1 -> 39 | B46: 22 00 00 | C46: ID Manual plumbing fixtures - ID Manual and plumbing drawings fixture schedule are not coordinated | D46: ='22 00 Plumbing '!G138 -> 25000
A47: =A46+1 -> 40 | B47: 22 00 00 | C47: Plumbing for Wellness spa rooms not shown on plumbing plans | D47: ='22 00 Plumbing '!G145 -> 31000
A48: =A47+1 -> 41 | B48: 22 00 00 | C48: Laundry Equipment - plumbing - drawings incomplete | D48: ='22 00 Plumbing '!G164 -> 5000
A49: =A48+1 -> 42 | B49: 23 00 00 | C49: Cooling options for Snow Room - see sheet 16 of Spa Model plans - no options shown on HVAC plans for providing service | D49: ='23 00 HVAC'!G131 -> 7500
A50: =A49+1 -> 43 | B50: 26 00 00 | C50: Site Lighting \ Landscape Lighting - electrical site lighting plans are incomplete. Fixture location plans that are part of Hardscape Lighting Plans are incomplete. | D50: ='26 00 Electrical'!G82 -> 400000
A51: =A50+1 -> 44 | B51: 32 14 00 | C51: Hardscape - Concrete Retaining Walls - no structural details - assume 12" depth footing cover. | D51: ='32 14 Hardsacpe - Walls'!G36 -> 806000
A52: =A51+1 -> 45 | B52: 32 14 00 | C52: Hardscape - French drain at retaining walls - no details | D52: ='32 14 Hardsacpe - Walls'!I97 -> 24700
A53: =A52+1 -> 46 | B53: 32 14 00 | C53: Hardscape - Pier for gate detail - no structural details - 8" CMU? | D53: ='32 14 Hardsacpe - Walls'!I101 -> 39600
A54: =A53+1 -> 47 | B54: 32 14 00 | C54: Hardscape - Pool Condenser Enclosure - no structural details - 8" CMU? | D54: ='32 14 Hardsacpe - Walls'!I104 -> 5600
A55: =A54+1 -> 48 | B55: 32 14 00 | C55: Hardscape - Concrete apron at Amphitheater - 6" - no structural details | D55: ='32 14 Hardsacpe - Walls'!I107 -> 1100
A56: =A55+1 -> 49 | B56: 32 14 00 | C56: Hardscape - Concrete apron (wall?) at Dining stairs - no details | D56: ='32 14 Hardsacpe - Walls'!I108 -> 2100
A57: =A56+1 -> 50 | B57: 32 14 00 | C57: Hardscape - Stone Veneer - Irregular Florida Keystone - full thickness - 3" to 4" - not able to accurately determine wall heights and stone exposure | D57: ='32 14 Hardsacpe - Walls'!I110 -> 542938
A58: =A57+1 -> 51 | B58: 32 31 00 | C58: Fence & Gates - Wood Pool Enclosure Gate - no detail or dimensions | D58: ='32 31 Fence & Gates'!G31 -> 25000
A59: =A58+1 -> 52 | B59: 32 80 00 | C59: Landscape - Root barrier - need to confirm locations | D59: ='32 80 Landscape'!G32 -> 98000
A60: =A59+1 -> 53
A61: =A60+1 -> 54
A62: =A61+1 -> 55 | C62: Total | D62: =SUM(D8:D61) -> 6655802

Sheet Cost Summary
A3: ='Area Calculations'!B4 -> Atlantic Fields Club Core / Dock Bar / Spa Pods / Water Features
A4: ='Area Calculations'!B5 -> Hobe Sound
A5: Hard Bid - Cost Summary
A6: =NOW() -> 46146.221
A7: CSI | B7: CSI DESCRIPTION | C7: Club Core | D7: Dock & Bar | E7: Spa Pods | F7: Hardscape, Landscape & Water Features | G7: Site Work | H7: TOTAL | I7: $/SF
A8: 02 21 00 | B8: Surveying | C8: ='02 21 Survey '!$I21 -> 22000 | D8: ='02 21 Survey '!$I30 -> 0 | E8: ='02 21 Survey '!$I33 -> 9350 | F8: ='02 21 Survey '!$I42 -> 22000 | G8: ='02 21 Survey '!$I50 -> 20000 | H8: ='02 21 Survey '!$B$95 -> 73350 | K8: =SUM(C8:G8)-H8 -> 0
A9: 03 30 00 | B9: Concrete & CMU | C9: ='03 30 CIP Concrete'!I21 -> 7239482 | D9: ='03 30 CIP Concrete'!I221 -> 108738 | E9: ='03 30 CIP Concrete'!I240 -> 300788 | H9: ='03 30 CIP Concrete'!$B300 -> 7649008 | K9: =SUM(C9:G9)-H9 -> 0
A10: 04 40 00 | B10: Stone Veneer | C10: ='04 40 Stone Veneer'!I21 -> 983329 | H10: ='04 40 Stone Veneer'!$B$107 -> 983329 | K10: =SUM(C10:G10)-H10 -> 0
A11: 05 10 00 | B11: Structural Steel | C11: ='05 10 Structural Steel'!K21 -> 4903059 | D11: ='05 10 Structural Steel'!K244 -> 368224 | E11: ='05 10 Structural Steel'!K270 -> 67958 | H11: ='05 10 Structural Steel'!$B331 -> 5339241 | K11: =SUM(C11:G11)-H11 -> 0
A12: 05 52 00 | B12: Handrails & Railings | C12: ='05 52 Railings'!I21 -> 0 | D12: ='05 52 Railings'!I27 -> 138000 | E12: ='05 52 Railings'!I32 -> 0 | H12: ='05 52 Railings'!$B$90 -> 138000 | K12: =SUM(C12:G12)-H12 -> 0
A13: 05 70 00 | B13: Interior & Exterior Architectural Metals | C13: ='05 70 Arch Metals'!I21 -> 1247804 | D13: ='05 70 Arch Metals'!I61 -> 47180 | E13: ='05 70 Arch Metals'!I68 -> 63350 | H13: ='05 70 Arch Metals'!$B$112 -> 1358334 | K13: =SUM(C13:G13)-H13 -> 0
A14: 06 10 00 | B14: Rough Carpentry | C14: ='06 10 Rough Carpentry'!I21 -> 109293 | D14: ='06 10 Rough Carpentry'!I49 -> 42397 | E14: ='06 10 Rough Carpentry'!I58 -> 141562.92 | H14: ='06 10 Rough Carpentry'!$B$119 -> 293252.92 | K14: =SUM(C14:G14)-H14 -> 0
A15: 06 40 00 | B15: Exterior Finish Carpentry | C15: ='06 40 Exterior Finish Carpentry'!I21 -> 3087156.8 | D15: ='06 40 Exterior Finish Carpentry'!I73 -> 611228.58 | E15: ='06 40 Exterior Finish Carpentry'!I92 -> 708166.67 | H15: ='06 40 Exterior Finish Carpentry'!$B$150 -> 4406552 | K15: =SUM(C15:G15)-H15 -> 0
A16: 06 50 00 | B16: Millwork | C16: =SUM('06 50 Millwork'!$I$12:$I$511) -> 6072272 | D16: =SUM('06 50 Millwork'!$I$512:$I$610) -> 590857 | E16: =SUM('06 50 Millwork'!$I$611:$I$651)+'06 50 Millwork'!$I$656 -> 194657 | H16: ='06 50 Millwork'!$B$693 -> 6857786 | K16: =SUM(C16:G16)-H16 -> 0
A17: 07 17 00 | B17: Waterproofing & Caulking | C17: ='07 17 Waterproofing & Caulk'!I$43 -> 2045883.5 | D17: ='07 17 Waterproofing & Caulk'!I$151 -> 8509 | E17: ='07 17 Waterproofing & Caulk'!I$157 -> 29850 | H17: ='07 17 Waterproofing & Caulk'!$B$203 -> 2084242.5 | K17: =SUM(C17:G17)-H17 -> 0
A18: 07 21 00 | B18: Insulation | C18: ='07 21 Insulation'!I21 -> 16261 | D18: ='07 21 Insulation'!I26 -> 36200 | E18: ='07 21 Insulation'!I33 -> 20510 | H18: ='07 21 Insulation'!$B$90 -> 72971 | K18: =SUM(C18:G18)-H18 -> 0
A19: 07 50 00 | B19: Roofing | C19: ='07 50 Roofing'!I21 -> 2220525 | D19: ='07 50 Roofing'!I99 -> 60300 | E19: ='07 50 Roofing'!I105 -> 92210 | H19: ='07 50 Roofing'!$B$153 -> 2373035 | K19: =SUM(C19:G19)-H19 -> 0
A20: 07 81 00 | B20: Fireproofing | C20: ='07 81 Fireproofing'!$I$21 -> 343200 | H20: ='07 81 Fireproofing'!$B$90 -> 343200 | K20: =SUM(C20:G20)-H20 -> 0
A21: 08 10 70 | B21: Doors, Frames, & Hardware | C21: ='08 10 DFH'!I21 -> 555850 | D21: ='08 10 DFH'!I145 -> 19950 | E21: ='08 10 DFH'!I160 -> 135946 | H21: ='08 10 DFH'!$B$220 -> 711746 | K21: =SUM(C21:G21)-H21 -> 0
A22: 08 11 00 | B22: Roll-Up Insect Screens | C22: ='08 11 Insect Screens'!$I$23 -> 260965.48 | D22: ='08 11 Insect Screens'!$I$50 -> 61218.138 | E22: ='08 11 Insect Screens'!$I$59 -> 39820.515 | H22: ='08 11 Insect Screens'!$B$110 -> 362004.13 | K22: =SUM(C22:G22)-H22 -> 0
A23: 08 33 00 | B23: Overhead Coiling Doors | C23: ='08 33 OH Coiling Doors'!I21 -> 20237.39 | H23: ='08 33 OH Coiling Doors'!$B$90 -> 20237.39 | K23: =SUM(C23:G23)-H23 -> 0
A24: 08 50 00 | B24: Storefront / Glass | C24: ='08 50 Storefront'!I25 -> 2327406.3 | E24: ='08 50 Storefront'!I193 -> 247760.7 | H24: ='08 50 Storefront'!$B$274 -> 2575167 | K24: =SUM(C24:G24)-H24 -> 0
A25: 08 60 00 | B25: Skylights | C25: ='08 60 Skylights'!I$21 -> 24736 | H25: ='08 60 Skylights'!$B$90 -> 24736 | K25: =SUM(C25:G25)-H25 -> 0
A26: 09 24 00 | B26: Stucco | C26: ='09 24 Stucco'!C72 -> 200300 | H26: ='09 24 Stucco'!$B$72 -> 200300 | K26: =SUM(C26:G26)-H26 -> 0
A27: 09 26 00 | B27: Plaster | C27: ='09 26 Plaster'!C92 -> 565992.54 | H27: ='09 26 Plaster'!$B$92 -> 565992.54 | K27: =SUM(C27:G27)-H27 -> 0
A28: 09 29 00 | B28: Drywall / Framing | C28: ='09 29 Gypsum Board'!C239 -> 2972787 | D28: ='09 29 Gypsum Board'!D239 -> 76546 | E28: ='09 29 Gypsum Board'!E239 -> 148960 | H28: ='09 29 Gypsum Board'!$B$239 -> 3198293 | K28: =SUM(C28:G28)-H28 -> 0
A29: 09 30 00 | B29: Tile Work, Tile & Stone Flooring | C29: ='09 30 Tile'!C253 -> 2681349.7 | D29: ='09 30 Tile'!D253 -> 4619.2 | E29: ='09 30 Tile'!E253 -> 207716.73 | H29: ='09 30 Tile'!$B$253 -> 2893685.6 | K29: =SUM(C29:G29)-H29 -> 0
A30: 09 41 00 | B30: Resinous Flooring | C30: ='09 41 Resinous Flooring'!C88 -> 223898.42 | D30: ='09 41 Resinous Flooring'!D88 -> 12480 | E30: ='09 41 Resinous Flooring'!E88 -> 0 | H30: ='09 41 Resinous Flooring'!$B88 -> 236378.42 | K30: =SUM(C30:G30)-H30 -> 0
A31: 09 51 00 | B31: Acoustical Ceilings | C31: ='09 51 ACT'!C79 -> 1536725 | D31: ='09 51 ACT'!D79 -> 2960 | E31: ='09 51 ACT'!E79 -> 106490 | H31: ='09 51 ACT'!$B79 -> 1646175 | K31: =SUM(C31:G31)-H31 -> 0
A32: 09 60 00 | B32: Flooring | C32: ='09 60 Resilient Flooring'!C94 -> 279493.41 | D32: ='09 60 Resilient Flooring'!D94 -> 0 | E32: ='09 60 Resilient Flooring'!E94 -> 11766.18 | H32: ='09 60 Resilient Flooring'!$B$94 -> 291259.59 | K32: =SUM(C32:G32)-H32 -> 0
A33: 09 64 00 | B33: Wood Flooring | C33: ='09 64 Wood Flooring'!C84 -> 879439.93 | D33: ='09 64 Wood Flooring'!D84 -> 14434.03 | E33: ='09 64 Wood Flooring'!E84 -> 0 | H33: ='09 64 Wood Flooring'!$B$84 -> 893873.96 | K33: =SUM(C33:G33)-H33 -> 0
A34: 09 90 00 | B34: Painting | C34: ='09 90 Painting'!C155 -> 935578.34 | D34: ='09 90 Painting'!D155 -> 25276 | E34: ='09 90 Painting'!E155 -> 14685 | H34: ='09 90 Painting'!$B155 -> 975539.34 | K34: =SUM(C34:G34)-H34 -> 0
A35: 10 22 00 | B35: Demountable Partitions | C35: ='10 22 Demountable Part'!I21 -> 47635 | H35: ='10 22 Demountable Part'!$B$90 -> 47635 | K35: =SUM(C35:G35)-H35 -> 0
A36: 10 28 00 | B36: Specialties | C36: ='10 28 Specialties'!C214 -> 99213.86 | D36: ='10 28 Specialties'!D214 -> 9942.3 | E36: ='10 28 Specialties'!E214 -> 11170.6 | H36: ='10 28 Specialties'!$B214 -> 120326.76 | K36: =SUM(C36:G36)-H36 -> 0
A37: 10 30 00 | B37: Fireplace | C37: ='10 30 Fireplace '!I21 -> 28550 | H37: ='10 30 Fireplace '!$B90 -> 28550 | K37: =SUM(C37:G37)-H37 -> 0
A38: 10 51 00 | B38: Lockers | C38: ='10 51 Lockers'!I21 -> 414093.8 | H38: ='10 51 Lockers'!$B$105 -> 414093.8 | K38: =SUM(C38:G38)-H38 -> 0
A39: 10 53 00 | B39: Signage | C39: ='10 53 Signage'!I23 -> 36500 | D39: ='10 53 Signage'!I31 -> 1050 | E39: ='10 53 Signage'!I34 -> 7700 | G39: ='10 53 Signage'!I39 -> 7500 | H39: ='10 53 Signage'!$B93 -> 52750 | K39: =SUM(C39:G39)-H39 -> 0
A40: 10 73 00 | B40: Canopy | C40: ='10 73 Canopy'!$I$21 -> 350000 | H40: ='10 73 Canopy'!$B$91 -> 350000 | K40: =SUM(C40:G40)-H40 -> 0
A41: 11 40 00 | B41: Food Service & Laundry Equipment | C41: ='11 40 FS Equip'!I21 -> 184253.95 | D41: ='11 40 FS Equip'!I48 -> 4480 | H41: ='11 40 FS Equip'!$B98 -> 188733.95 | K41: =SUM(C41:G41)-H41 -> 0
A42: 11 40 00 | B42: Appliances | C42: ='11 40 Appliances'!I21 -> 102552 | D42: ='11 40 Appliances'!I70 -> 11984 | H42: ='11 40 Appliances'!B120 -> 114536 | K42: =SUM(C42:G42)-H42 -> 0
A43: 12 20 00 | B43: Window Treatments | C43: ='12 20 Window Treatments'!I26 -> 451948.82 | D43: ='12 20 Window Treatments'!I88 -> 6420 | E43: ='12 20 Window Treatments'!I91 -> 3000 | H43: ='12 20 Window Treatments'!$B$134 -> 461368.82 | K43: =SUM(C43:G43)-H43 -> 0
A44: 13 11 00 | B44: Swimming Pool, Spas & Water Features | C44: ='13 11 Pool'!I21 -> 1910189 | E44: ='13 11 Pool'!I55 -> 234057 | F44: ='13 11 Pool'!I63 -> 3951946 | H44: ='13 11 Pool'!$B145 -> 6096192 | K44: =SUM(C44:G44)-H44 -> 0
A45: 13 12 00 | B45: Spa Rooms: Steam, Sauna, Hammam, Snow Room | C45: ='13 12 Spa Rooms'!$I$21 -> 1706404 | H45: ='13 12 Spa Rooms'!$B110 -> 1706404 | K45: =SUM(C45:G45)-H45 -> 0
A46: 14 00 00 | B46: Elevators | C46: ='14 00 Elevators'!I23 -> 1230500 | H46: ='14 00 Elevators'!$B$119 -> 1230500 | K46: =SUM(C46:G46)-H46 -> 0
A47: 14 91 00 | B47: Linen Chute | C47: ='14 91 Linen Chute'!$I$21 -> 42026 | H47: ='14 91 Linen Chute'!$B$90 -> 42026 | K47: =SUM(C47:G47)-H47 -> 0
A48: 21 13 00 | B48: Fire Protection Systems | C48: ='21 13 Fire Protection'!I21 -> 319000 | H48: ='21 13 Fire Protection'!B95 -> 319000 | I48: =H48/86144 -> 3.7031018 | K48: =SUM(C48:G48)-H48 -> 0
A49: 22 00 00 | B49: Plumbing | C49: ='22 00 Plumbing '!I21 -> 3758478 | D49: ='22 00 Plumbing '!I173 -> 140000 | E49: ='22 00 Plumbing '!I198 -> 88622 | H49: ='22 00 Plumbing '!$B268 -> 3987100 | I49: =H49/86144 -> 46.284129 | K49: =SUM(C49:G49)-H49 -> 0
A50: 23 00 00 | B50: HVAC | C50: ='23 00 HVAC'!I21 -> 4652684 | D50: ='23 00 HVAC'!I136 -> 54504 | E50: ='23 00 HVAC'!I146 -> 562496 | H50: ='23 00 HVAC'!$B204 -> 5269684 | I50: =H50/86144 -> 61.172966 | K50: =SUM(C50:G50)-H50 -> 0
A51: 26 00 00 | B51: Electrical | C51: ='26 00 Electrical'!I21 -> 4679125 | D51: ='26 00 Electrical'!I64 -> 296113 | E51: ='26 00 Electrical'!I72 -> 281439 | F51: ='26 00 Electrical'!I81 -> 400000 | H51: ='26 00 Electrical'!$B129 -> 5656677 | I51: =H51/86144 -> 65.665363 | K51: =SUM(C51:G51)-H51 -> 0
A52: 27 10 00 | B52: Structured Cabling | C52: ='27 10 Structured Cable'!I21 -> 358290.72 | D52: ='27 10 Structured Cable'!I92 -> 27213.11 | E52: ='27 10 Structured Cable'!I106 -> 26005.11 | H52: ='27 10 Structured Cable'!$B162 -> 411508.94 | I52: =H52/86144 -> 4.776989 | K52: =SUM(C52:G52)-H52 -> 0
A53: 27 40 00 | B53: Audio Visual Systems | C53: ='27 40 AV System'!I21 -> 728428.08 | D53: ='27 40 AV System'!I189 -> 33762.14 | E53: ='27 40 AV System'!I210 -> 81614.28 | H53: ='27 40 AV System'!$B266 -> 843804.5 | I53: =H53/86144 -> 9.7952788 | K53: =SUM(C53:G53)-H53 -> 0
A54: 27 50 00 | B54: BDA System | C54: ='27 53 BDA System'!I21 -> 95500 | H54: ='27 53 BDA System'!$B90 -> 95500 | I54: =H54/86144 -> 1.1086088 | K54: =SUM(C54:G54)-H54 -> 0
A55: 28 10 00 | B55: Electronic Security & Safety Systems | C55: ='28 10 Security'!I21 -> 401795.28 | H55: ='28 10 Security'!$B149 -> 401795.28 | I55: =H55/86144 -> 4.6642283 | K55: =SUM(C55:G55)-H55 -> 0
A56: 31 30 10 | B56: Sitework | G56: ='31 30 Site Work'!B112 -> 2628144 | H56: ='31 30 Site Work'!$B112 -> 2628144 | K56: =SUM(C56:G56)-H56 -> 0
A57: 31 32 00 | B57: Soil Stabilization | G57: 0 | H57: ='31 32 Soil Stabilization'!$B91 -> 0 | K57: =SUM(C57:G57)-H57 -> 0
A58: 32 14 00 | B58: Hardscape - Walls | F58: ='32 14 Hardsacpe - Walls'!$I$21 -> 2205447 | H58: ='32 14 Hardsacpe - Walls'!$B$180 -> 2205447 | K58: =SUM(C58:G58)-H58 -> 0
A59: 32 14 00 | B59: Hardscape - Pavers & Stone | F59: ='32 14 Hardsacpe - Pavers'!$I$21 -> 2904043 | H59: ='32 14 Hardsacpe - Pavers'!$B$105 -> 2904043 | K59: =SUM(C59:G59)-H59 -> 0
A60: 32 31 00 | B60: Fencing & Gates | F60: ='32 31 Fence & Gates'!$I$21 -> 206780 | H60: ='32 31 Fence & Gates'!$B$90 -> 206780 | K60: =SUM(C60:G60)-H60 -> 0
A61: 32 80 00 | B61: Landscaping & Irrigation | F61: ='32 80 Landscape'!I51 -> 1769458.7 | H61: ='32 80 Landscape'!B90 -> 1769458.7 | K61: =SUM(C61:G61)-H61 -> 0
A62: 35 00 00 | B62: Marine (Pier & Dock) Construction | D62: (by others) | H62: ='35 00 Marine'!$B$90 -> 0 | K62: =SUM(C62:G62)-H62 -> 0
K63: =SUM(C63:G63)-H63 -> 0
B64: SUB-TOTAL 1 (Cost of Work) Building | C64: =SUM(C8:C63) -> 63352192 | D64: =SUM(D8:D63) -> 2814585.5 | E64: =SUM(E8:E63) -> 3837651.7 | F64: =SUM(F8:F63) -> 11459675 | G64: =SUM(G8:G63) -> 2655644 | H64: =SUM(H8:H63) -> 84119748 | I64: =SUM(I8:I63) -> 197.17066 | K64: =SUM(C64:G64)-H64 -> 0
B65: GC Contingency | C65: =C64*$J$65 -> 1267043.8 | D65: =D64*$J$65 -> 56291.71 | E65: =E64*$J$65 -> 76753.034 | F65: =F64*$J$65 -> 229193.49 | G65: =G64*$J$65 -> 53112.88 | H65: =H64*$J$65 -> 1682395 | J65: 0.02 | K65: =SUM(C65:G65)-H65 -> 0
B66: SUB-TOTAL 2 (Contingencies) | C66: =SUM(C64:C65) -> 64619236 | D66: =SUM(D64:D65) -> 2870877.2 | E66: =SUM(E64:E65) -> 3914404.7 | F66: =SUM(F64:F65) -> 11688868 | G66: =SUM(G64:G65) -> 2708756.9 | H66: =SUM(H64:H65) -> 85802143 | I66: =SUM(I64:I65) -> 197.17066 | K66: =SUM(C66:G66)-H66 -> 0
B67: General Conditions | C67: =C66*$J$67 -> 3283436 | D67: =D66*$J$67 -> 145875.16 | E67: =E66*$J$67 -> 198898.94 | F67: =F66*$J$67 -> 593935.38 | G67: =G66*$J$67 -> 137637.5 | H67: ='GCs & GRs'!L158 -> 4359783 | J67: =H67/H66 -> 0.050812052 | K67: =SUM(C67:G67)-H67 -> 0
B68: General Requirements | C68: =C66*$J$68 -> 981937.24 | D68: =D66*$J$68 -> 43625.109 | E68: =E66*$J$68 -> 59482.285 | F68: =F66*$J$68 -> 177621.03 | G68: =G66*$J$68 -> 41161.571 | H68: ='GCs & GRs'!L159 -> 1303827.2 | J68: =H68/H66 -> 0.015195742 | K68: =SUM(C68:G68)-H68 -> 0
B69: Procore Expense | C69: =C66*$J$69 -> 56483.935 | D69: =D66*$J$69 -> 2509.4454 | E69: =E66*$J$69 -> 3421.597 | F69: =F66*$J$69 -> 10217.287 | G69: =G66*$J$69 -> 2367.7353 | H69: 75000 | J69: =H69/H66 -> 0.00087410404 | K69: =SUM(C69:G69)-H69 -> 0
B70: Inspections, Testing | H70: By Owner
B71: Permits | H71: By Owner
B72: Builders Risk Insurance & Deductibles | H72: By Owner
B73: Subcontractor Default Insurance | C73: =C66*$J$73 -> 969288.54 | D73: =D66*$J$73 -> 43063.158 | E73: =E66*$J$73 -> 58716.071 | F73: =F66*$J$73 -> 175333.02 | G73: =G66*$J$73 -> 40631.353 | H73: =H66*$J$73 -> 1287032.1 | J73: 0.015 | K73: =SUM(C73:G73)-H73 -> 0
B74: General Liability Insurance | C74: =(C66+C67+C68+C73)*$J$74 -> 873173.72 | D74: =(D66+D67+D68+D73)*$J$74 -> 38793.008 | E74: =(E66+E67+E68+E73)*$J$74 -> 52893.775 | F74: =(F66+F67+F68+F73)*$J$74 -> 157946.97 | G74: =(G66+G67+G68+G73)*$J$74 -> 36602.341 | H74: =(H66+H67+H68+H73)*$J$74 -> 1159409.8 | J74: 0.0125 | K74: =SUM(C74:G74)-H74 -> 0
B75: SUB-TOTAL 3 (Bonds, Insurances, & GC's) | C75: =SUM(C66:C74) -> 70783556 | D75: =SUM(D66:D74) -> 3144743.1 | E75: =SUM(E66:E74) -> 4287817.4 | F75: =SUM(F66:F74) -> 12803922 | G75: =SUM(G66:G74) -> 2967157.4 | H75: =SUM(H66:H74) -> 93987195 | I75: =SUM(I66:I74) -> 197.17066 | K75: =SUM(C75:G75)-H75 -> 0
B76: GC Fee (OH&P) | C76: =C75*$J$76 -> 3362218.9 | D76: =D75*$J$76 -> 149375.3 | E76: =E75*$J$76 -> 203671.33 | F76: =F75*$J$76 -> 608186.29 | G76: =G75*$J$76 -> 140939.98 | H76: =H75*$J$76 -> 4464391.8 | I76: =I75*$J$76 -> 9.3656066 | J76: 0.0475 | K76: =SUM(C76:G76)-H76 -> 0
B77: ESTIMATE TOTAL | C77: =SUM(C75:C76) -> 74145775 | D77: =SUM(D75:D76) -> 3294118.4 | E77: =SUM(E75:E76) -> 4491488.7 | F77: =SUM(F75:F76) -> 13412108 | G77: =SUM(G75:G76) -> 3108097.4 | H77: =SUM(H75:H76) -> 98451587 | I77: =C77/C78 -> 860.71897 | K77: =SUM(C77:G77)-H77 -> 0
B78: GSF | C78: =SUM('Area Calculations'!D16:D36) -> 86144 | D78: ='Area Calculations'!D38 -> 2528 | K78: =SUM(C78:G78)-H78 -> 88672
B79: Cost per sf | C79: =C77/C78 -> 860.71897 | D79: =D77/D78 -> 1303.0532
D80: =D79/'Area Calculations'!D45 -> 0.014695204

Sheet GCs & GRs
A1: Contract Reference | B1: General Condition Ref. | C1: ='Area Calculations'!B4 -> Atlantic Fields Club Core / Dock Bar / Spa Pods / Water Features
C3: Construction | F3: Activity | H3: Start | I3: Finish | J3: Days | K3: Weeks | L3: Months | M3: % Time | N3: Remarks | S3: Start | T3: Finish | U3: Days | V3: Weeks | W3: Months
F4: Construction | H4: 45839 | I4: 46632 | J4: =I4-H4 -> 793 | K4: =J4/7 -> 113.28571 | L4: =J4/30.42 -> 26.068376
F5: Close Out | J5: =L5*30.4 -> 30.4 | K5: =L5*4.33 -> 4.33 | L5: 1
F6: General Conditions | H6: General Req. - Field Office | J6: General Req. | L6: Total
C7: Description | D7: Qty. | E7: U | F7: Unit Cost | G7: Const. | H7: Unit | I7: General | J7: Unit | K7: General | O7: LABOR RATE FY 2025 *Updated 09.26.24
F8: Cost | G8: Cond. | H8: Cost | I8: Req. | J8: Cost | K8: Req.
C9: Field Labor - Construction | L9: =SUM(L10:L27) -> 4280977.3
C10: Project Executive | D10: =V10 -> 124.42857 | E10: wks | F10: =(O10*40)*M10 -> 1813.2 | G10: =SUM(D10*F10) -> 225613.89 | L10: =SUM(G10+I10+K10) -> 225613.89 | M10: 0.25 | O10: 181.32 | Q10: Construction | S10: 45761 | T10: 46632 | U10: =SUM(T10-S10) -> 871 | V10: =SUM(U10/7) -> 124.42857 | W10: =SUM(U10/30) -> 29.033333
D11: =$K$4 -> 113.28571 | E11: wks | F11: =(O11*40)*M11 -> 0 | G11: =SUM(D11*F11) -> 0 | L11: =SUM(G11+I11+K11) -> 0 | M11: 0
C12: Senior Project Manager | D12: =V12 -> 124.42857 | E12: wks | F12: =(O12*40)*M12 -> 6011.2 | G12: =SUM(D12*F12) -> 747965.03 | L12: =SUM(G12+I12+K12) -> 747965.03 | M12: 1 | O12: 150.28 | Q12: Construction | S12: 45761 | T12: 46632 | U12: =SUM(T12-S12) -> 871 | V12: =SUM(U12/7) -> 124.42857 | W12: =SUM(U12/30) -> 29.033333
C13: Project Manager - Level 2 | D13: =$K$4 -> 113.28571 | E13: wks | F13: =(O13*40)*M13 -> 0 | G13: =SUM(D13*F13) -> 0 | L13: =SUM(G13+I13+K13) -> 0 | M13: 0
C14: Project Manager - Level 1 | D14: =V14 -> 111 | E14: wks | F14: =(O14*40)*M14 -> 4336.4 | G14: =SUM(D14*F14) -> 481340.4 | L14: =SUM(G14+I14+K14) -> 481340.4 | M14: 1 | O14: 108.41 | Q14: Construction | S14: 45855 | T14: 46632 | U14: =SUM(T14-S14) -> 777 | V14: =SUM(U14/7) -> 111 | W14: =SUM(U14/30) -> 25.9
C15: Project Administator | D15: =V15 -> 111 | E15: wks | F15: =(O15*40)*M15 -> 3059.2 | G15: =SUM(D15*F15) -> 339571.2 | L15: =SUM(G15+I15+K15) -> 339571.2 | M15: 1 | O15: 76.48 | Q15: Construction | S15: 45855 | T15: 46632 | U15: =SUM(T15-S15) -> 777 | V15: =SUM(U15/7) -> 111 | W15: =SUM(U15/30) -> 25.9
C16: Project Accountant | D16: =V16 -> 111 | E16: wks | F16: =(O16*40)*M16 -> 1973.6 | G16: =SUM(D16*F16) -> 219069.6 | L16: =SUM(G16+I16+K16) -> 219069.6 | M16: 0.5 | O16: 98.68 | Q16: Construction | S16: 45855 | T16: 46632 | U16: =SUM(T16-S16) -> 777 | V16: =SUM(U16/7) -> 111 | W16: =SUM(U16/30) -> 25.9
C17: Assistant Project Manager | D17: =$K$4 -> 113.28571 | E17: wks | F17: =(O17*40)*M17 -> 0 | G17: =SUM(D17*F17) -> 0 | L17: =SUM(G17+I17+K17) -> 0 | M17: 0 | Q17: Construction | U17: =SUM(T17-S17) -> 0 | V17: =SUM(U17/7) -> 0 | W17: =SUM(U17/30) -> 0
C18: Superintendent - Level 3 | D18: =V18 -> 117.28571 | E18: wks | F18: =(O18*40)*M18 -> 6060.4 | G18: =SUM(D18*F18) -> 710798.34 | L18: =SUM(G18+I18+K18) -> 710798.34 | M18: 1 | O18: 151.51 | Q18: Construction | S18: 45811 | T18: 46632 | U18: =SUM(T18-S18) -> 821 | V18: =SUM(U18/7) -> 117.28571 | W18: =SUM(U18/30) -> 27.366667
C19: Superintendent - Level 2 | D19: =V19 -> 97.428571 | E19: wks | F19: =(O19*40)*M19 -> 5087.2 | G19: =SUM(D19*F19) -> 495638.63 | L19: =SUM(G19+I19+K19) -> 495638.63 | M19: 1 | O19: 127.18 | Q19: Construction | S19: 45950 | T19: 46632 | U19: =SUM(T19-S19) -> 682 | V19: =SUM(U19/7) -> 97.428571 | W19: =SUM(U19/30) -> 22.733333
C20: Superintendent - Level 2 | D20: =V20 -> 81.428571 | E20: wks | F20: =(O20*40)*M20 -> 5087.2 | G20: =SUM(D20*F20) -> 414243.43 | L20: =SUM(G20+I20+K20) -> 414243.43 | M20: 1 | O20: 127.18 | Q20: Construction | S20: 46062 | T20: 46632 | U20: =SUM(T20-S20) -> 570 | V20: =SUM(U20/7) -> 81.428571 | W20: =SUM(U20/30) -> 19
C21: Superintendent - Level 1 | D21: =$K$4 -> 113.28571 | E21: wks | F21: =(O21*40)*M21 -> 0 | G21: =SUM(D21*F21) -> 0 | L21: =SUM(G21+I21+K21) -> 0 | M21: 0
C22: Assistant Superinterndent | D22: =V22 -> 113.28571 | E22: wks | F22: =(O22*40)*M22 -> 0 | G22: =SUM(D22*F22) -> 0 | L22: =SUM(G22+I22+K22) -> 0 | M22: 0 | Q22: Construction | S22: 45839 | T22: 46632 | U22: =SUM(T22-S22) -> 793 | V22: =SUM(U22/7) -> 113.28571 | W22: =SUM(U22/30) -> 26.433333
C23: Quality Control Manager | D23: =$K$4 -> 113.28571 | E23: wks | F23: =(O23*40)*M23 -> 1183.7 | G23: =SUM(D23*F23) -> 134096.3 | L23: =SUM(G23+I23+K23) -> 134096.3 | M23: 0.25 | O23: 118.37 | Q23: Construction | U23: =SUM(T23-S23) -> 0 | V23: =SUM(U23/7) -> 0 | W23: =SUM(U23/30) -> 0
C24: Foreman | D24: =$K$4 -> 113.28571 | E24: wks | F24: =(O24*40)*M24 -> 1910.4 | G24: =SUM(D24*F24) -> 216421.03 | L24: =SUM(G24+I24+K24) -> 216421.03 | M24: 1 | O24: 47.76
C25: Accounting | D25: =$K$4 -> 113.28571 | E25: wks | F25: =(O25*40)*M25 -> 1066.64 | G25: =SUM(D25*F25) -> 120835.07 | L25: =SUM(G25+I25+K25) -> 120835.07 | M25: 0.2 | O25: 133.33 | Q25: Construction | U25: =SUM(T25-S25) -> 0 | V25: =SUM(U25/7) -> 0 | W25: =SUM(U25/30) -> 0
C26: VDC Manager | D26: =$K$4 -> 113.28571 | E26: wks | F26: =(O26*40)*M26 -> 1181.4 | G26: =SUM(D26*F26) -> 133835.74 | L26: =SUM(G26+I26+K26) -> 133835.74 | M26: 0.25 | O26: 118.14 | Q26: Construction | U26: =SUM(T26-S26) -> 0 | V26: =SUM(U26/7) -> 0 | W26: =SUM(U26/30) -> 0
C27: Safety Supervisor/Inspector | D27: =K4 -> 113.28571 | E27: wks | F27: =(O27*40)*M27 -> 366.76 | G27: =SUM(D27*F27) -> 41548.669 | L27: =SUM(G27+I27+K27) -> 41548.669 | M27: 0.1 | O27: 91.69 | Q27: Construction | U27: =SUM(T27-S27) -> 0 | V27: =SUM(U27/7) -> 0 | W27: =SUM(U27/30) -> 0
C28: Field Labor - Close Out | L28: =SUM(L29:L43) -> 78805.654
C29: Project Executive | D29: =$K$5 -> 4.33 | E29: wks | F29: =(40*O29)*M29 -> 725.28 | G29: =SUM(D29*F29) -> 3140.4624 | L29: =SUM(G29+I29+K29) -> 3140.4624 | M29: 0.1 | O29: =+O10 -> 181.32
C30: Senior Project Manager | D30: =$K$5 -> 4.33 | E30: wks | F30: =(40*O30)*M30 -> 0 | G30: =SUM(D30*F30) -> 0 | L30: =SUM(G30+I30+K30) -> 0 | M30: =+M11 -> 0 | O30: =+O11 -> 0
C31: Project Manager - Level 3 | D31: =$K$5 -> 4.33 | E31: wks | F31: =(40*O31)*M31 -> 6011.2 | G31: =SUM(D31*F31) -> 26028.496 | L31: =SUM(G31+I31+K31) -> 26028.496 | M31: =+M12 -> 1 | O31: =O12 -> 150.28
C32: Project Manager - Level 2 | D32: =$K$5 -> 4.33 | E32: wks | F32: =(40*O32)*M32 -> 0 | G32: =SUM(D32*F32) -> 0 | L32: =SUM(G32+I32+K32) -> 0 | M32: =+M13 -> 0 | O32: =+O13 -> 0
C33: Project Manager - Level 1 | D33: =$K$5 -> 4.33 | E33: wks | F33: =(40*O33)*M33 -> 4336.4 | G33: =SUM(D33*F33) -> 18776.612 | L33: =SUM(G33+I33+K33) -> 18776.612 | M33: =+M14 -> 1 | O33: =+O14 -> 108.41
C34: Project Administator | D34: =$K$5 -> 4.33 | E34: wks | F34: =(40*O34)*M34 -> 0 | G34: =SUM(D34*F34) -> 0 | L34: =SUM(G34+I34+K34) -> 0 | M34: 0 | O34: =+O15 -> 76.48
C35: Assistant Project Manager | D35: =$K$5 -> 4.33 | E35: wks | F35: =(40*O35)*M35 -> 0 | G35: =SUM(D35*F35) -> 0 | L35: =SUM(G35+I35+K35) -> 0 | M35: =+M17 -> 0 | O35: =+O17 -> 0
C36: Superintendent - Level 3 | D36: =$K$5 -> 4.33 | E36: wks | F36: =(40*O36)*M36 -> 6060.4 | G36: =SUM(D36*F36) -> 26241.532 | L36: =SUM(G36+I36+K36) -> 26241.532 | M36: =+M18 -> 1 | O36: =+O18 -> 151.51
C37: Superintendent - Level 2 | D37: =$K$5 -> 4.33 | E37: wks | F37: =(40*O37)*M37 -> 0 | G37: =SUM(D37*F37) -> 0 | L37: =SUM(G37+I37+K37) -> 0 | M37: 0 | O37: =+O19 -> 127.18
C38: Superintendent - Level 1 | D38: =$K$5 -> 4.33 | E38: wks | F38: =(40*O38)*M38 -> 0 | G38: =SUM(D38*F38) -> 0 | L38: =SUM(G38+I38+K38) -> 0 | M38: =+M21 -> 0 | O38: =+O21 -> 0
C39: Assistant Superinterndent | D39: =$K$5 -> 4.33 | E39: wks | F39: =(40*O39)*M39 -> 0 | G39: =SUM(D39*F39) -> 0 | L39: =SUM(G39+I39+K39) -> 0 | M39: =+M22 -> 0 | O39: =+O22 -> 0
C40: Foreman | D40: =$K$5 -> 4.33 | E40: wks | F40: =(40*O40)*M40 -> 0 | G40: =SUM(D40*F40) -> 0 | L40: =SUM(G40+I40+K40) -> 0 | M40: 0 | O40: =+O24 -> 47.76
C41: Accounting | D41: =$K$5 -> 4.33 | E41: wks | F41: =(40*O41)*M41 -> 1066.64 | G41: =SUM(D41*F41) -> 4618.5512 | L41: =SUM(G41+I41+K41) -> 4618.5512 | M41: =+M25 -> 0.2 | O41: =+O25 -> 133.33
C42: VDC Manager | D42: =$K$5 -> 4.33 | E42: wks | F42: =(40*O42)*M42 -> 0 | G42: =SUM(D42*F42) -> 0 | L42: =SUM(G42+I42+K42) -> 0 | M42: 0 | O42: =+O26 -> 118.14
C43: Safety Supervisor/Inspector | D43: =$K$5 -> 4.33 | E43: wks | F43: =(40*O43)*M43 -> 0 | G43: =SUM(D43*F43) -> 0 | L43: =SUM(G43+I43+K43) -> 0 | M43: 0 | O43: =+O27 -> 91.69
C44: Field Office - Contractor | L44: =SUM(L45:L64) -> 247378.76
C45: Field Office Set Up / Removal - Double Wide | D45: 1 | E45: ea | H45: 16000 | I45: =SUM(D45*H45) -> 16000 | J45: ` | L45: =SUM(G45+I45+K45) -> 16000
C46: Field Office - Double Wide | D46: =$L$4 -> 26.068376 | E46: mos | H46: 3500 | I46: =SUM(D46*H46) -> 91239.316 | L46: =SUM(G46+I46+K46) -> 91239.316
C47: Field Office Set Up / Removal - Single Wide | E47: ea | H47: 15958 | I47: =SUM(D47*H47) -> 0 | L47: =SUM(G47+I47+K47) -> 0 | N47: WILLSCOT 4/16/2024 (36x10 mobile office)
C48: Field Office - Single Wide | E48: mos | H48: 1732 | I48: =SUM(D48*H48) -> 0 | L48: =SUM(G48+I48+K48) -> 0 | N48: WILLSCOT 4/16/2024 (36x10 mobile office)
C49: Field Office Set Up / Removal - Connex | D49: 1 | E49: ea | H49: 1371 | I49: =SUM(D49*H49) -> 1371 | L49: =SUM(G49+I49+K49) -> 1371 | N49: WILLSCOT 20' COMBO W/10' OFFICE
C50: Field Office - Conex | D50: 18 | E50: mos | H50: 573 | I50: =SUM(D50*H50) -> 10314 | L50: =SUM(G50+I50+K50) -> 10314 | N50: WILLSCOT 20' COMBO W/10' OFFICE
C51: Connect Telephone Lines | D51: 1 | E51: ea | H51: 2000 | I51: =SUM(D51*H51) -> 2000 | L51: =SUM(G51+I51+K51) -> 2000
C52: Telephone | D52: =$L$4 -> 26.068376 | E52: mos | H52: 250 | I52: =SUM(D52*H52) -> 6517.094 | L52: =SUM(G52+I52+K52) -> 6517.094
C53: Cellular Telephones | D53: =$L$4 -> 26.068376 | E53: mos | H53: 0 | I53: =SUM(D53*H53) -> 0 | L53: =SUM(G53+I53+K53) -> 0 | N53: In labor rates
C54: Furniture | D54: 0 | E54: ls | H54: 500 | I54: =SUM(D54*H54) -> 0 | L54: =SUM(G54+I54+K54) -> 0
C55: Office Supplies | D55: =$L$4 -> 26.068376 | E55: mos | H55: 100 | I55: =SUM(D55*H55) -> 2606.8376 | L55: =SUM(G55+I55+K55) -> 2606.8376
C56: Drinking Water | D56: =$L$4 -> 26.068376 | E56: mos | H56: 50 | I56: =SUM(D56*H56) -> 1303.4188 | L56: =SUM(G56+I56+K56) -> 1303.4188
C57: Janitor Supplies/Cleaning | D57: =$L$4 -> 26.068376 | E57: mos | H57: 250 | I57: =SUM(D57*H57) -> 6517.094 | L57: =SUM(G57+I57+K57) -> 6517.094
C58: Computers | D58: 0 | E58: ls | H58: 0 | I58: =SUM(D58*H58) -> 0 | L58: =SUM(G58+I58+K58) -> 0
C59: Printers | D59: 2 | E59: ls | H59: 500 | I59: =SUM(D59*H59) -> 1000 | L59: =SUM(G59+I59+K59) -> 1000
C60: Copy Machine | D60: 1 | E60: ls | H60: 750 | I60: =SUM(D60*H60) -> 750 | L60: =SUM(G60+I60+K60) -> 750
C61: Alarm System | D61: =$L$4 -> 26.068376 | E61: mos | H61: 0 | I61: =SUM(D61*H61) -> 0 | L61: =SUM(G61+I61+K61) -> 0
C62: Offsite Storage | D62: 12 | E62: mos | H62: 7500 | I62: =SUM(D62*H62) -> 90000 | L62: =SUM(G62+I62+K62) -> 90000
C63: Storage Trailers Set Up / Removal | D63: 4 | E63: ea | H63: 840 | I63: =SUM(D63*H63) -> 3360 | L63: =SUM(G63+I63+K63) -> 3360 | N63: willscot 40' trailer
C64: Storage Trailers | D64: 12 | E64: mos | H64: 1200 | I64: =SUM(D64*H64) -> 14400 | L64: =SUM(G64+I64+K64) -> 14400 | N64: Rate - $1200 ea. per month
C65: Field Office - Owner | N65: =SUM(L66:L80) -> 0
C66: Field Office Set Up / Removal | D66: 1 | E66: ls | J66: 0 | K66: =SUM(D66*J66) -> 0 | L66: =SUM(G66+I66+K66) -> 0 | N66: assume not required
C67: Field Office | D67: =L4 -> 26.068376 | E67: mos | J67: 0 | K67: =SUM(D67*J67) -> 0 | L67: =SUM(G67+I67+K67) -> 0 | N67: assume not required
C68: Connect Telephone Lines | D68: 1 | E68: ls | J68: 0 | K68: =SUM(D68*J68) -> 0 | L68: =SUM(G68+I68+K68) -> 0 | N68: assume not required
C69: Telephone | D69: =L4 -> 26.068376 | E69: mos | J69: 0 | K69: =SUM(D69*J69) -> 0 | L69: =SUM(G69+I69+K69) -> 0 | N69: assume not required
C70: Cellular Telephones | D70: =L4+L5 -> 27.068376 | E70: mos | J70: 0 | K70: =SUM(D70*J70) -> 0 | L70: =SUM(G70+I70+K70) -> 0 | N70: assume not required
C71: Furniture | D71: 1 | E71: ls | J71: 0 | K71: =SUM(D71*J71) -> 0 | L71: =SUM(G71+I71+K71) -> 0 | N71: assume not required
C72: Office Supplies | D72: =L4+L5 -> 27.068376 | E72: mos | J72: 0 | K72: =SUM(D72*J72) -> 0 | L72: =SUM(G72+I72+K72) -> 0 | N72: assume not required
C73: Drinking Water | D73: =L4+L5 -> 27.068376 | E73: mos | J73: 0 | K73: =SUM(D73*J73) -> 0 | L73: =SUM(G73+I73+K73) -> 0 | N73: assume not required
C74: Janitor Supplies | D74: =L4 -> 26.068376 | E74: mos | J74: 0 | K74: =SUM(D74*J74) -> 0 | L74: =SUM(G74+I74+K74) -> 0 | N74: assume not required
C75: Computers | D75: 1 | E75: ls | J75: 0 | K75: =SUM(D75*J75) -> 0 | L75: =SUM(G75+I75+K75) -> 0 | N75: assume not required
C76: Printers | D76: 1 | E76: ls | J76: 0 | K76: =SUM(D76*J76) -> 0 | L76: =SUM(G76+I76+K76) -> 0 | N76: assume not required
C77: Copy Machine | D77: =L4+L5 -> 27.068376 | E77: mos | J77: 0 | K77: =SUM(D77*J77) -> 0 | L77: =SUM(G77+I77+K77) -> 0 | N77: assume not required
C78: Fax Machine | D78: 1 | E78: ls | J78: 0 | K78: =SUM(D78*J78) -> 0 | L78: =SUM(G78+I78+K78) -> 0 | N78: assume not required
C79: Alarm System | D79: =L4 -> 26.068376 | E79: mos | J79: 0 | K79: =SUM(D79*J79) -> 0 | L79: =SUM(G79+I79+K79) -> 0 | N79: assume not required
C80: Installation Office Equip. | D80: 1 | E80: ls | J80: 0 | K80: =SUM(D80*J80) -> 0 | L80: =SUM(G80+I80+K80) -> 0 | N80: assume not required
C81: Temporary Utilities | L81: =SUM(L82:L94) -> 181598.58
C82: Temp. Electrical Service | D82: 1 | E82: ls | J82: 5000 | K82: =SUM(D82*J82) -> 5000 | L82: =SUM(G82+I82+K82) -> 5000
C83: Temp. Electrical - Const. Phase | D83: =$L$4 -> 26.068376 | E83: mos | J83: 1050 | K83: =SUM(D83*J83) -> 27371.795 | L83: =SUM(G83+I83+K83) -> 27371.795
C84: Temp. Electrical - Operate Phase | D84: =L4 -> 26.068376 | E84: mos | J84: 0 | K84: =SUM(D84*J84) -> 0 | L84: =SUM(G84+I84+K84) -> 0 | N84: by owner
C85: Temp. Wiring & Lighting | D85: 0 | E85: sf | J85: 0 | K85: =SUM(D85*J85) -> 0 | L85: =SUM(G85+I85+K85) -> 0 | N85: by elect sub
C86: Temporary Water - Service | D86: 1 | E86: ls | J86: 3500 | K86: =SUM(D86*J86) -> 3500 | L86: =SUM(G86+I86+K86) -> 3500 | N86: by owner
C87: Temporary Water | D87: =L4 -> 26.068376 | E87: mos | J87: 150 | K87: =SUM(D87*J87) -> 3910.2564 | L87: =SUM(G87+I87+K87) -> 3910.2564
C88: Temporary Toilets | D88: =L4 -> 26.068376 | E88: mos | J88: =410*10 -> 4100 | K88: =SUM(D88*J88) -> 106880.34 | L88: =SUM(G88+I88+K88) -> 106880.34 | N88: Rate - $350 ea per month
C89: Temporary Toilet Set Up / Removal | D89: 4 | E89: ea | J89: 100 | K89: =SUM(D89*J89) -> 400 | L89: =SUM(G89+I89+K89) -> 400
C90: Temporary Washing Station | D90: 26.1 | E90: mos | J90: =2*410 -> 820 | K90: =SUM(D90*J90) -> 21402 | L90: =SUM(G90+I90+K90) -> 21402
C91: Temporary Washing Station Set Up / Removal | D91: 1 | E91: ea | J91: 100 | K91: =SUM(D91*J91) -> 100 | L91: =SUM(G91+I91+K91) -> 100
C92: Temporary Holding Tanks | D92: =L4 -> 26.068376 | E92: mos | J92: 500 | K92: =SUM(D92*J92) -> 13034.188 | L92: =SUM(G92+I92+K92) -> 13034.188
C93: Temporary Ventilation | D93: 0 | E93: ls | J93: 0 | K93: =SUM(D93*J93) -> 0 | L93: =SUM(G93+I93+K93) -> 0
C94: Temporary Cooling | D94: =L4 -> 26.068376 | E94: mos | J94: 0 | K94: =SUM(D94*J94) -> 0 | L94: =SUM(G94+I94+K94) -> 0
C95: Equipment | L95: =SUM(L96:L99) -> 397542.74
C96: Small Tools | D96: =$L$4 -> 26.068376 | E96: mos | J96: 750 | K96: =SUM(D96*J96) -> 19551.282 | L96: =SUM(G96+I96+K96) -> 19551.282
C97: Equipment Rental | D97: =$L$4 -> 26.068376 | E97: mos | J97: 2500 | K97: =SUM(D97*J97) -> 65170.94 | L97: =SUM(G97+I97+K97) -> 65170.94
C98: Shuttle | D98: =$L$4 -> 26.068376 | E98: mos | J98: 12000 | K98: =SUM(D98*J98) -> 312820.51 | L98: =SUM(G98+I98+K98) -> 312820.51
C99: Engineering Instruments | D99: 0 | E99: ls | J99: 1000 | K99: =SUM(D99*J99) -> 0 | L99: =SUM(G99+I99+K99) -> 0
C100: Security | L100: =SUM(L101:L115) -> 110815.47
B101: 15000 | C101: Temporary Fence - 6' Post Driven w/ windscreen | D101: 0 | E101: lf | J101: 8.3 | K101: =J101*D101 -> 0 | L101: =SUM(G101+I101+K101) -> 0 | N101: West Side only
...

Sheet 02 21 Survey 
G1: Hedrick Plug
F2: X | G2: Excluded
F3: I | G3: Included
B4: BACK TO SUMMARY SHEET | G4: Sub Add/Deduct
A5: Project: | B5: Atlantic Fields Club Core | G5: Company | H5: Velcon Engineering and Surveying
A6: Trade: | B6: Surveying | G6: Contact
A7: CSI Code: | B7: 02 21 00 | G7: Phone
A8: Date: | G8: Email
G9: Adjusted Bid | H9: =I60 -> 73350 | J9: =K64 -> 0 | L9: =M64 -> 0 | N9: =O64 -> 0 | P9: =Q64 -> 0 | R9: =S64 -> 0
A10: BID DOCUMENTS: | C10: Plan/ Spec. Package | D10: QTY | E10: U/M | F10: Unit Cost | G10: Subtotal | H10: Yes/No | I10: Price | J10: Yes/No | K10: Price | L10: Yes/No | M10: Price | N10: Yes/No | O10: Price | P10: Yes/No | Q10: Price | R10: Yes/No | S10: Price
B11: GENERAL INCLUSIONS
B12: INCLUDES ALL SALES TAX
B13: ALL HOISTING & RIGGING REQUIRED TO COMPLETE THIS SCOPE
B14: PROVIDE P&P BONDS
B15: FLORIDA STATE CONTRACTORS LIC.
B16: GENERAL LIABILITY AND WORKERS COMP. INSURANCE LIMITS
B17: STATE AND LOCAL TAXES
B18: SPECIFIC TRADE SCOPE OF WORK REQUIREMENTS
B19: BASE BID
B21: Club Core | I21: =SUBTOTAL(9,I22:I29) -> 22000 | K21: =SUBTOTAL(9,K22:K29) -> 0 | M21: =SUBTOTAL(9,M22:M29) -> 0 | O21: =SUBTOTAL(9,O22:O29) -> 0 | Q21: =SUBTOTAL(9,Q22:Q29) -> 0 | S21: =SUBTOTAL(9,S22:S29) -> 0
B22: Set up digital files | D22: 1 | E22: ls | F22: 1500 | G22: =ROUND(D22*F22,0) -> 1500 | I22: =G22 -> 1500
B23: Calculations | D23: 1 | E23: ls | F23: 1000 | G23: =ROUND(D23*F23,0) -> 1000 | I23: =G23 -> 1000
B24: Verify horizontal and vertical control | D24: 1 | E24: ls | F24: 2500 | G24: =ROUND(D24*F24,0) -> 2500 | I24: =G24 -> 2500
B25: Building foundations layout | D25: 1 | E25: ls | F25: =1500*3 -> 4500 | G25: =ROUND(D25*F25,0) -> 4500 | I25: =G25 -> 4500
B26: FEMA Certificate | D26: 1 | E26: ls | F26: 3000 | G26: =ROUND(D26*F26,0) -> 3000 | I26: =G26 -> 3000
B27: Final as-built survey | D27: 1 | E27: ls | F27: 7500 | G27: =ROUND(D27*F27,0) -> 7500 | I27: =G27 -> 7500
B28: Pool & Spas | D28: 1 | E28: ls | F28: 2000 | G28: =ROUND(D28*F28,0) -> 2000 | I28: =G28 -> 2000
G29: =ROUND(D29*F29,0) -> 0
B30: Dock Bar - NA | G30: =ROUND(D30*F30,0) -> 0 | I30: =SUBTOTAL(9,I31:I32) -> 0 | K30: =SUBTOTAL(9,K31:K32) -> 0 | M30: =SUBTOTAL(9,M31:M32) -> 0 | O30: =SUBTOTAL(9,O31:O32) -> 0 | Q30: =SUBTOTAL(9,Q31:Q32) -> 0 | S30: =SUBTOTAL(9,S31:S32) -> 0
B31: Base structure will already be in place | D31: 1 | E31: ls | F31: 0 | G31: =ROUND(D31*F31,0) -> 0
G32: =ROUND(D32*F32,0) -> 0
B33: Spa Pods | G33: =ROUND(D33*F33,0) -> 0 | I33: =SUBTOTAL(9,I34:I41) -> 9350 | K33: =SUBTOTAL(9,K35:K41) -> 0 | M33: =SUBTOTAL(9,M35:M41) -> 0 | O33: =SUBTOTAL(9,O35:O41) -> 0 | Q33: =SUBTOTAL(9,Q35:Q41) -> 0 | S33: =SUBTOTAL(9,S35:S41) -> 0
B34: Set up digital files | D34: 1 | E34: ls | F34: 1500 | G34: =ROUND(D34*F34,0) -> 1500 | I34: =G34 -> 1500
B35: Calculations | D35: 1 | E35: ls | F35: 1000 | G35: =ROUND(D35*F35,0) -> 1000 | I35: =G35 -> 1000
B36: Verify horizontal and vertical control | D36: 1 | E36: ls | F36: 750 | G36: =ROUND(D36*F36,0) -> 750 | I36: =G36 -> 750
B37: Building foundations layout | D37: 1 | E37: ls | F37: =350*6 -> 2100 | G37: =ROUND(D37*F37,0) -> 2100 | I37: =G37 -> 2100
B38: FEMA Certificate | D38: 1 | E38: ls | F38: 1500 | G38: =ROUND(D38*F38,0) -> 1500 | I38: =G38 -> 1500
B39: Final as-built survey | D39: 1 | E39: ls | F39: 2500 | G39: =ROUND(D39*F39,0) -> 2500 | I39: =G39 -> 2500
B40: Pool & Spas | D40: 1 | E40: ls | G40: =ROUND(D40*F40,0) -> 0 | I40: =G40 -> 0
G41: =ROUND(D41*F41,0) -> 0
B42: Hardsacape | G42: =ROUND(D42*F42,0) -> 0 | I42: =SUBTOTAL(9,I43:I49) -> 22000 | K42: =SUBTOTAL(9,K46:K49) -> 0 | M42: =SUBTOTAL(9,M46:M49) -> 0 | O42: =SUBTOTAL(9,O46:O49) -> 0 | Q42: =SUBTOTAL(9,Q46:Q49) -> 0 | S42: =SUBTOTAL(9,S46:S49) -> 0
B43: Set up digital files | D43: 1 | E43: ls | F43: 1500 | G43: =ROUND(D43*F43,0) -> 1500 | I43: =G43 -> 1500
B44: Calculations | D44: 1 | E44: ls | F44: 1000 | G44: =ROUND(D44*F44,0) -> 1000 | I44: =G44 -> 1000
B45: Verify horizontal and vertical control | D45: 1 | E45: ls | F45: 2000 | G45: =ROUND(D45*F45,0) -> 2000 | I45: =G45 -> 2000
B46: Retaining walls | D46: 1 | E46: ls | F46: 5000 | G46: =ROUND(D46*F46,0) -> 5000 | I46: =G46 -> 5000
B47: Paths & Sidewalks | D47: 1 | E47: ls | F47: 7500 | G47: =ROUND(D47*F47,0) -> 7500 | I47: =G47 -> 7500
B48: Water Features | D48: 1 | E48: ls | F48: 5000 | G48: =ROUND(D48*F48,0) -> 5000 | I48: =G48 -> 5000
G49: =ROUND(D49*F49,0) -> 0
B50: Sitework | G50: =ROUND(D50*F50,0) -> 0 | I50: =SUBTOTAL(9,I51:I55) -> 20000 | K50: =SUBTOTAL(9,K51:K55) -> 0 | M50: =SUBTOTAL(9,M51:M55) -> 0 | O50: =SUBTOTAL(9,O51:O55) -> 0 | Q50: =SUBTOTAL(9,Q51:Q55) -> 0 | S50: =SUBTOTAL(9,S51:S55) -> 0
D51: 1 | E51: ls | F51: 20000 | G51: =ROUND(D51*F51,0) -> 20000 | I51: =G51 -> 20000
G52: =ROUND(D52*F52,0) -> 0
G53: =ROUND(D53*F53,0) -> 0
G54: =ROUND(D54*F54,0) -> 0
G55: =ROUND(D55*F55,0) -> 0
B56: SUBTOTAL | G56: =SUM(G19:G55) -> 73350 | I56: =SUBTOTAL(9,I20:I55) -> 73350 | K56: =SUBTOTAL(9,K20:K55) -> 0 | M56: =SUBTOTAL(9,M20:M55) -> 0 | O56: =SUBTOTAL(9,O20:O55) -> 0 | Q56: =SUBTOTAL(9,Q20:Q55) -> 0 | S56: =SUBTOTAL(9,S20:S55) -> 0
B57: BOND RATE | H57: 0 | J57: 0 | L57: 0 | N57: 0 | P57: 0 | R57: 0
B58: BOND AMOUNT | G58: =F57*G56 -> 0 | I58: =H57*I56 -> 0 | K58: =J57*K56 -> 0 | M58: =L57*M56 -> 0 | O58: =N57*O56 -> 0 | Q58: =P57*Q56 -> 0 | S58: =R57*S56 -> 0
B60: ADJUSTED TOTAL | G60: =SUM(G56:G58) -> 73350 | I60: =SUM(I56:I58) -> 73350 | K60: =SUM(K56:K58) -> 0 | M60: =SUM(M56:M58) -> 0 | O60: =SUM(O56:O58) -> 0 | Q60: =SUM(Q56:Q58) -> 0 | S60: =SUM(S56:S58) -> 0
B61: Cost per SF | G61: 0.35521917 | I61: 0.35521917 | K61: 0 | M61: 0 | O61: 0 | Q61: 0 | S61: 0
A63: QUALIFICATIONS
A67: EXCLUSIONS/OWNER PROVIDED ITEMS:
A71: ALTERNATES:
A75: PROPOSED VE (Provide Clear Description):
A79: FULLY LOADED LABOR RATES
B80: Laborer
B81: Mechanic
B82: Superintendent
B83: Project Manager
A85: SCHEDULE
B86: Prepared shop drawings/submittals
B87: Mobilization
B88: Total duration to complete scope of work
A90: Winner
A91: Company
A92: Contact
A93: Phone
A94: Email
A95: Base Bid | B95: =$I$60 -> 73350
B97: Need Prequalification
B98: Prequalified

Sheet 03 30 CIP Concrete
G1: Hedrick Plug
F2: X | G2: Excluded
F3: I | G3: Included
B4: BACK TO SUMMARY SHEET | G4: Sub Add/Deduct
D5: PREQUALIFIED? (If not, add Sub Bond) | H5: YES | J5: NO | L5: NO | N5: YES | P5: =L5 -> NO | R5: =N5 -> YES | T5: YES
A6: Project: | B6: Atlantic Fields Club Core | G6: Company | H6: Victory Concrete | J6: Construction Trade Part | L6: Proshell | N6: Starlite Building Serv | P6: Cook Shell | R6: Ron Kendal | T6: Pate Construction
A7: Trade: | B7: Concrete & CMU | G7: Contact | H7: Jeff Grebla | J7: David Webster | L7: Julien Beauregard | N7: Sean Williams | P7: Elias Morales | R7: Christopher Markley | T7: Jason Tartaglia
A8: CSI Code: | B8: 03 30 00 | G8: Phone | H8: (561) 227-9577 | J8: (561) 441-9752 | L8: (561) 889-0405 | N8: (561) 719-7607 | P8: (772) 247-7150 | R8: (754) 233-1319 | T8: (561) 261-7473
A9: Date: | G9: Email | H9: jsgrebla@vconcreteco.com | J9: davew@ctpflorida.com | L9: julien@proshellconstruction.com | N9: starlitebuildingservices.com | P9: EMorales@cookshellcontractors.com | R9: cmarkley@ronkm.com | T9: jason.tartaglia@pateformwork.com
G10: Adjusted Bid | H10: =I$265 -> 7649008 | J10: =K$265 -> 6434574.1 | L10: =M$265 -> 7348275.8 | N10: =O$265 -> 7223508 | P10: =Q$265 -> 7702632 | R10: =S$265 -> 8088319.5 | T10: =U$265 -> 8046000
A11: BID DOCUMENTS: | C11: Plan/ Spec. Package | D11: QTY | E11: U/M | F11: Unit Cost | G11: Subtotal | H11: Yes/No | I11: Price | J11: Yes/No | K11: Price | L11: Yes/No | M11: Price | N11: Yes/No | O11: Price | P11: Yes/No | Q11: Price | R11: Yes/No | S11: Price | T11: Yes/No | U11: Price
B12: GENERAL INCLUSIONS
B13: INCLUDES ALL SALES TAX | H13: i | J13: i | L13: i | N13: i | P13: i | R13: i | T13: i
B14: ALL HOISTING & RIGGING REQUIRED TO COMPLETE THIS SCOPE | H14: i | J14: i | L14: i | N14: i | P14: i | R14: i | T14: i
B15: FLORIDA STATE CONTRACTORS LIC. | H15: i | J15: i | L15: i | N15: i | P15: i | R15: i | T15: i
B16: GENERAL LIABILITY AND WORKERS COMP. INSURANCE LIMITS | H16: i | J16: i | L16: i | N16: i | P16: i | R16: i | T16: i
B17: STATE AND LOCAL TAXES | H17: i | J17: i | L17: i | N17: i | P17: i | R17: i | T17: i
B18: SPECIFIC TRADE SCOPE OF WORK REQUIREMENTS
B19: BASE BID
B21: Club Core | G21: =SUBTOTAL(9,G22:G220) -> 8178756 | I21: =SUBTOTAL(9,I22:I220) -> 7239482 | K21: =SUBTOTAL(9,K22:K220) -> 5906473 | M21: =SUBTOTAL(9,M22:M220) -> 6411042 | O21: =SUBTOTAL(9,O22:O220) -> 6808825 | Q21: =SUBTOTAL(9,Q22:Q220) -> 7198900 | S21: =SUBTOTAL(9,S22:S220) -> 7413100 | U21: =SUBTOTAL(9,U22:U220) -> 7646000
B22: Base Bid | G22: =ROUND(D22*F22,0) -> 0 | I22: 7193482 | K22: =1978164+1035790+2395918+359909 -> 5769781 | M22: 6274350 | O22: 6672133 | Q22: 7152900 | S22: 7367100 | U22: 7600000
B23: Dining | G23: =ROUND(D23*F23,0) -> 0
B24: Beams | D24: =SUM(D25:D27) -> 43.82 | E24: cy | F24: 1600 | G24: =ROUND(D24*F24,0) -> 70112 | H24: I | L24: I | N24: I | P24: I | R24: I | T24: I
B25: DB-1 | D25: 12.62 | E25: cy | G25: =ROUND(D25*F25,0) -> 0 | X25: DB-1 | Y25: 2' 8" | Z25: 128 | AA25: LF | AB25: 12.62 | AC25: CY
B26: DTB-1 | D26: 11.7 | E26: cy | G26: =ROUND(D26*F26,0) -> 0 | X26: DTB-1 | Y26: 2' 0" | Z26: 255 | AA26: LF | AB26: 11.7 | AC26: CY
B27: DTB-2 | D27: 19.5 | E27: cy | G27: =ROUND(D27*F27,0) -> 0 | X27: DTB-2 | Y27: 2' 0" | Z27: 395 | AA27: LF | AB27: 19.5 | AC27: CY
B28: Columns | D28: =SUM(D29:D36) -> 23.91 | E28: cy | F28: 1800 | G28: =ROUND(D28*F28,0) -> 43038 | H28: I | L28: I | N28: I | P28: I | R28: I | T28: I
B29: DC-1 to 14-11" | D29: 1.1 | E29: cy | G29: =ROUND(D29*F29,0) -> 0 | X29: DC-1 to 14-11" | Y29: 14' 11" | Z29: 1 | AA29: EA | AB29: 1.1 | AC29: CY
B30: DC-1 to 14-2" | D30: 3.15 | E30: cy | G30: =ROUND(D30*F30,0) -> 0 | X30: DC-1 to 14-2" | Y30: 14' 2" | Z30: 3 | AA30: EA | AB30: 3.15 | AC30: CY
B31: DC-1 to 17'-0" | D31: 2.52 | E31: cy | G31: =ROUND(D31*F31,0) -> 0 | X31: DC-1 to 17'-0" | Y31: 17' 0" | Z31: 2 | AA31: EA | AB31: 2.52 | AC31: CY
B32: DC-2 to 14'-2" | D32: 0.7 | E32: cy | G32: =ROUND(D32*F32,0) -> 0 | X32: DC-2 to 14'-2" | Y32: 14' 2" | Z32: 1 | AA32: EA | AB32: 0.7 | AC32: CY
B33: DC-2 to 17'-0" | D33: 0.84 | E33: cy | G33: =ROUND(D33*F33,0) -> 0 | X33: DC-2 to 17'-0" | Y33: 17' 0" | Z33: 1 | AA33: EA | AB33: 0.84 | AC33: CY
B34: DC-3 to14'-11" | D34: 0.94 | E34: cy | G34: =ROUND(D34*F34,0) -> 0 | X34: DC-3 to14'-11" | Y34: 17' 0" | Z34: 1 | AA34: EA | AB34: 0.94 | AC34: CY
B35: DCP-1 to 2'-0" | D35: 3.33 | E35: cy | G35: =ROUND(D35*F35,0) -> 0 | X35: DCP-1 to 2'-0" | Y35: 2' 0" | Z35: 5 | AA35: EA | AB35: 3.33 | AC35: CY
B36: DCP-2 to 17'-0" | D36: 11.33 | E36: cy | G36: =ROUND(D36*F36,0) -> 0 | X36: DCP-2 to 17'-0" | Y36: 17' 0" | Z36: 9 | AA36: EA | AB36: 11.33 | AC36: CY
B37: Walls | D37: =SUM(D38) -> 487.49 | E37: cy | F37: 2000 | G37: =ROUND(D37*F37,0) -> 974980 | H37: I | L37: I | N37: I | P37: I | R37: I | T37: I
B38: DCW-1 to 17'-0" | D38: 487.49 | E38: cy | G38: =ROUND(D38*F38,0) -> 0 | X38: DCW-1 to 17'-0" | Y38: 17' 0" | Z38: 581 | AA38: LF | AB38: 487.49 | AC38: CY
B39: Footings | D39: =SUM(D40:D51) -> 772.73 | E39: cy | F39: 650 | G39: =ROUND(D39*F39,0) -> 502275 | H39: I | L39: I | N39: I | P39: I | R39: I | T39: I
B40: DF140.24 | D40: 493.46 | E40: cy | G40: =ROUND(D40*F40,0) -> 0 | X40: DF140.24 | Y40: 2' 0" | Z40: 476 | AA40: LF | AB40: 493.46 | AC40: CY | AD40: 2 | AE40: =Z40 -> 476
B41: DF180150 | D41: 30 | E41: cy | G41: =ROUND(D41*F41,0) -> 0 | X41: DF180150 | Y41: 3' 0" | Z41: 1 | AA41: EA | AB41: 30 | AC41: CY | AD41: 3 | AE41: =Z41 -> 1
B42: DF200150 | D42: 100 | E42: cy | G42: =ROUND(D42*F42,0) -> 0 | X42: DF200150 | Y42: 3' 0" | Z42: 3 | AA42: EA | AB42: 100 | AC42: CY | AD42: 3 | AE42: =Z42 -> 3
B43: DF40.12 | D43: 17.06 | E43: cy | G43: =ROUND(D43*F43,0) -> 0 | X43: DF40.12 | Y43: 1' 0" | Z43: 115 | AA43: LF | AB43: 17.06 | AC43: CY | AD43: 1 | AE43: =Z43 -> 115
B44: DF45 - Dining Port C | D44: 6 | E44: cy | G44: =ROUND(D44*F44,0) -> 0 | X44: DF45 - Dining Port C | Y44: 1' 4" | Z44: 6 | AA44: EA | AB44: 6 | AC44: CY | AD44: 1.33 | AE44: =Z44 -> 6
B45: DF50 | D45: 14.04 | E45: cy | G45: =ROUND(D45*F45,0) -> 0 | X45: DF50 | Y45: 1' 2" | Z45: 13 | AA45: EA | AB45: 14.04 | AC45: CY | AD45: 1.17 | AE45: =Z45 -> 13
B46: DF60 | D46: 10.67 | E46: cy | G46: =ROUND(D46*F46,0) -> 0 | X46: DF60 | Y46: 1' 4" | Z46: 6 | AA46: EA | AB46: 10.67 | AC46: CY | AD46: 1.33 | AE46: =Z46 -> 6
B47: DF65 | D47: 4.17 | E47: cy | G47: =ROUND(D47*F47,0) -> 0 | X47: DF65 | Y47: 1' 4" | Z47: 2 | AA47: EA | AB47: 4.17 | AC47: CY | AD47: 1.33 | AE47: =Z47 -> 2
B48: DF70 | D48: 4.84 | E48: cy | G48: =ROUND(D48*F48,0) -> 0 | X48: DF70 | Y48: 1' 4" | Z48: 2 | AA48: EA | AB48: 4.84 | AC48: CY | AD48: 1.33 | AE48: =Z48 -> 2
B49: DF85 | D49: 12.04 | E49: cy | G49: =ROUND(D49*F49,0) -> 0 | X49: DF85 | Y49: 1' 6" | Z49: 3 | AA49: EA | AB49: 12.04 | AC49: CY | AD49: 1.5 | AE49: =Z49 -> 3
B50: DF95 | D50: 5.57 | E50: cy | G50: =ROUND(D50*F50,0) -> 0 | X50: DF95 | Y50: 1' 8" | Z50: 1 | AA50: EA | AB50: 5.57 | AC50: CY | AD50: 1.67 | AE50: =Z50 -> 1
B51: DFXXX.24 | D51: 74.88 | E51: cy | G51: =ROUND(D51*F51,0) -> 0 | X51: DFXXX.24 | Y51: 2' 0" | Z51: 50 | AA51: LF | AB51: 74.88 | AC51: CY | AD51: 2 | AE51: =Z51 -> 50
B52: Planters | G52: =ROUND(D52*F52,0) -> 0
B53: Dining Level 1 | D53: =SUM(D54:D55) -> 2.1696296 | E53: cy | F53: 1600 | G53: =ROUND(D53*F53,0) -> 3471 | H53: I | K53: =$G53 -> 3471 | M53: =$G53 -> 3471 | O53: =$G53 -> 3471 | P53: I | R53: I | T53: I
A54: 0.58 | B54: see 4/A8.11, /A4.01, A2.20 outside | D54: =49*0.58/27 -> 1.0525926 | E54: cy | G54: =ROUND(D54*F54,0) -> 0
A55: 0.58 | B55: see 4/A8.11, /A4.01, A2.20 inside | D55: =52*0.58/27 -> 1.117037 | E55: cy | G55: =ROUND(D55*F55,0) -> 0
B56: Dining Level 2 | D56: =SUM(D57:D59) -> 36.673185 | E56: cy | F56: 1500 | G56: =ROUND(D56*F56,0) -> 55010 | H56: I | K56: =$G56 -> 55010 | M56: =$G56 -> 55010 | O56: =$G56 -> 55010 | P56: I | R56: I | T56: I
A57: 2.3 | B57: see 2/8.11, 2/A4.00, A2.30 front | D57: =232.42*2.3/27 -> 19.798741 | E57: cy | F57: =$F$53 -> 1600 | G57: =ROUND(D57*F57,0) -> 31678
A58: 1.56 | B58: see 2/8.11, 2/A4.00, A2.30 rear | D58: =222.75*1.56/27 -> 12.87 | E58: cy | G58: =ROUND(D58*F58,0) -> 0
A59: =3.17*0.5 -> 1.585 | B59: see 2/A4.03, A2.30 | D59: =68*1.59/27 -> 4.0044444 | E59: cy | G59: =ROUND(D59*F59,0) -> 0
G60: =ROUND(D60*F60,0) -> 0
B61: Fitness | G61: =ROUND(D61*F61,0) -> 0
B62: Beams | D62: =SUM(D63:D72) -> 61.55 | E62: cy | F62: =$F$24 -> 1600 | G62: =ROUND(D62*F62,0) -> 98480 | H62: I | L62: I | N62: I | P62: I | R62: I | T62: I
B63: FB-1 | D63: 7.09 | E63: cy | G63: =ROUND(D63*F63,0) -> 0 | X63: FB-1 | Y63: 2' 0" | Z63: 96 | AA63: LF | AB63: 7.09 | AC63: CY
B64: FB-2 | D64: 16.84 | E64: cy | G64: =ROUND(D64*F64,0) -> 0 | X64: FB-2 | Y64: 3' 0" | Z64: 114 | AA64: LF | AB64: 16.84 | AC64: CY
B65: FB-3 | D65: 2.36 | E65: cy | G65: =ROUND(D65*F65,0) -> 0 | X65: FB-3 | Y65: 3' 0" | Z65: 21 | AA65: LF | AB65: 2.36 | AC65: CY
B66: FB-4 | D66: 3.26 | E66: cy | G66: =ROUND(D66*F66,0) -> 0 | X66: FB-4 | Y66: 2' 9" | Z66: 32 | AA66: LF | AB66: 3.26 | AC66: CY
B67: FB-5 | D67: 2.36 | E67: cy | G67: =ROUND(D67*F67,0) -> 0 | X67: FB-5 | Y67: 2' 6" | Z67: 26 | AA67: LF | AB67: 2.36 | AC67: CY
B68: FB-6 | D68: 0.3 | E68: cy | G68: =ROUND(D68*F68,0) -> 0 | X68: FB-6 | Y68: 1' 4" | Z68: 9 | AA68: LF | AB68: 0.3 | AC68: CY
B69: FTB-1 | D69: 3.76 | E69: cy | G69: =ROUND(D69*F69,0) -> 0 | X69: FTB-1 | Y69: 1' 4" | Z69: 114 | AA69: LF | AB69: 3.76 | AC69: CY
B70: FTB-2 | D70: 23.75 | E70: cy | G70: =ROUND(D70*F70,0) -> 0 | X70: FTB-2 | Y70: 3' 6" | Z70: 183 | AA70: LF | AB70: 23.75 | AC70: CY
B71: FTB-3 | D71: 1.36 | E71: cy | G71: =ROUND(D71*F71,0) -> 0 | X71: FTB-3 | Y71: 2' 0" | Z71: 18 | AA71: LF | AB71: 1.36 | AC71: CY
B72: FTB-5 | D72: 0.47 | E72: cy | G72: =ROUND(D72*F72,0) -> 0 | X72: FTB-5 | Y72: 2' 0" | Z72: 10 | AA72: LF | AB72: 0.47 | AC72: CY
B73: Columns | D73: =SUM(D74:D78) -> 13.13 | E73: cy | F73: =$F$28 -> 1800 | G73: =ROUND(D73*F73,0) -> 23634 | H73: I | L73: I | N73: I | P73: I | R73: I | T73: I
B74: FC-1 to 16-7" | D74: 0.61 | E74: cy | G74: =ROUND(D74*F74,0) -> 0 | X74: FC-1 to 16-7" | Y74: 16' 7" | Z74: 1 | AA74: EA | AB74: 0.61 | AC74: CY
B75: FC-2 to 16-7" | D75: 2.46 | E75: cy | G75: =ROUND(D75*F75,0) -> 0 | X75: FC-2 to 16-7" | Y75: 16' 7" | Z75: 3 | AA75: EA | AB75: 2.46 | AC75: CY
B76: FC-3 to 16-7" | D76: 1.13 | E76: cy | G76: =ROUND(D76*F76,0) -> 0 | X76: FC-3 to 16-7" | Y76: 16' 7" | Z76: 1 | AA76: EA | AB76: 1.13 | AC76: CY
B77: FC-4 to 16-7" | D77: 2.41 | E77: cy | G77: =ROUND(D77*F77,0) -> 0 | X77: FC-4 to 16-7" | Y77: 16' 7" | Z77: 4 | AA77: LF | AB77: 2.41 | AC77: CY
B78: FCP-1 to 2'-0" | D78: 6.52 | E78: cy | G78: =ROUND(D78*F78,0) -> 0 | X78: FCP-1 to 2'-0" | Y78: 2' 0" | Z78: 9 | AA78: EA | AB78: 6.52 | AC78: CY
B79: Walls | D79: =SUM(D80:D81) -> 517.34 | E79: cy | F79: 2000 | G79: =ROUND(D79*F79,0) -> 1034680 | H79: I | L79: I | N79: I | P79: I | R79: I | T79: I
B80: FCW-1 to 17'-0" | D80: 505.45 | E80: cy | G80: =ROUND(D80*F80,0) -> 0 | X80: FCW-1 to 17'-0" | Y80: 17' 0" | Z80: 602 | AA80: LF | AB80: 505.45 | AC80: CY
B81: FCW-2 to 17'-0" | D81: 11.89 | E81: cy | G81: =ROUND(D81*F81,0) -> 0 | X81: FCW-2 to 17'-0" | Y81: 17' 0" | Z81: 28 | AA81: LF | AB81: 11.89 | AC81: CY
B82: Footings | D82: =SUM(D83:D91) -> 631.2 | E82: cy | F82: =$F$39 -> 650 | G82: =ROUND(D82*F82,0) -> 410280 | H82: I | L82: I | N82: I | P82: I | R82: I | T82: I
B83: FF20.12 | D83: 8.21 | E83: cy | G83: =ROUND(D83*F83,0) -> 0 | X83: FF20.12 | Y83: 1' 0" | Z83: 111 | AA83: LF | AB83: 8.21 | AC83: CY | AD83: 1 | AE83: =Z83 -> 111
B84: FF25.12 | D84: 4.51 | E84: cy | G84: =ROUND(D84*F84,0) -> 0 | X84: FF25.12 | Y84: 1' 0" | Z84: 49 | AA84: LF | AB84: 4.51 | AC84: CY | AD84: 1 | AE84: =Z84 -> 49
B85: FF30.12 | D85: 4.43 | E85: cy | G85: =ROUND(D85*F85,0) -> 0 | X85: FF30.12 | Y85: 1' 0" | Z85: 40 | AA85: LF | AB85: 4.43 | AC85: CY | AD85: 1 | AE85: =Z85 -> 40
B86: FF45 | D86: 34.88 | E86: cy | G86: =ROUND(D86*F86,0) -> 0 | X86: FF45 | Y86: 1' 6" | Z86: 31 | AA86: EA | AB86: 34.88 | AC86: CY | AD86: 1.5 | AE86: =Z86 -> 31
B87: FF50 | D87: 9.72 | E87: cy | G87: =ROUND(D87*F87,0) -> 0 | X87: FF50 | Y87: 1' 6" | Z87: 7 | AA87: EA | AB87: 9.72 | AC87: CY | AD87: 1.5 | AE87: =Z87 -> 7
B88: FF55 | D88: 5.56 | E88: cy | G88: =ROUND(D88*F88,0) -> 0 | X88: FF55 | Y88: 1' 6" | Z88: 4 | AA88: EA | AB88: 5.56 | AC88: CY | AD88: 1.5 | AE88: =Z88 -> 4
B89: FF70120 | D89: 3.63 | E89: cy | G89: =ROUND(D89*F89,0) -> 0 | X89: FF70120 | Y89: 1' 2" | Z89: 1 | AA89: EA | AB89: 3.63 | AC89: CY | AD89: 1.17 | AE89: =Z89 -> 1
B90: FF75 | D90: 4.86 | E90: cy | G90: =ROUND(D90*F90,0) -> 0 | X90: FF75 | Y90: 1' 2" | Z90: 2 | AA90: EA | AB90: 4.86 | AC90: CY | AD90: 1 | AE90: =Z90 -> 2
B91: FFXXX.24 | D91: 555.4 | E91: cy | G91: =ROUND(D91*F91,0) -> 0 | X91: FFXXX.24 | Y91: 0" | Z91: 7498 | AA91: SF | AB91: 555.4 | AC91: CY | AD91: 1.7 | AE91: =Z91 -> 7498
G92: =ROUND(D92*F92,0) -> 0
B93: Wellness | G93: =ROUND(D93*F93,0) -> 0
B94: Beams | D94: =SUM(D95:D105) -> 84.56 | E94: cy | F94: =$F$24 -> 1600 | G94: =ROUND(D94*F94,0) -> 135296 | H94: I | L94: I | N94: I | P94: I | R94: I | T94: I
B95: WB - 01 | D95: 35.24 | E95: cy | G95: =ROUND(D95*F95,0) -> 0 | X95: WB - 01 | Y95: 2' 8" | Z95: 357 | AA95: LF | AB95: 35.24 | AC95: CY
B96: WB - 04 | D96: 4.48 | E96: cy | G96: =ROUND(D96*F96,0) -> 0 | X96: WB - 04 | Y96: 1' 0" | Z96: 181 | AA96: LF | AB96: 4.48 | AC96: CY
B97: WB - 05 | D97: 4.6 | E97: cy | G97: =ROUND(D97*F97,0) -> 0 | X97: WB - 05 | Y97: 1' 4" | Z97: 93 | AA97: LF | AB97: 4.6 | AC97: CY
B98: WB - 06 | D98: 1.31 | E98: cy | G98: =ROUND(D98*F98,0) -> 0 | X98: WB - 06 | Y98: 3' 0" | Z98: 18 | AA98: LF | AB98: 1.31 | AC98: CY
B99: WB - 07 | D99: 12.07 | E99: cy | G99: =ROUND(D99*F99,0) -> 0 | X99: WB - 07 | Y99: 2' 0" | Z99: 244 | AA99: LF | AB99: 12.07 | AC99: CY
B100: WB - 08 | D100: 1.58 | E100: cy | G100: =ROUND(D100*F100,0) -> 0 | X100: WB - 08 | Y100: 1' 0" | Z100: 43 | AA100: LF | AB100: 1.58 | AC100: CY
B101: WB - 08" x 58" | D101: 11.64 | E101: cy | G101: =ROUND(D101*F101,0) -> 0 | X101: WB - 08" x 58" | Y101: 4' 10" | Z101: 98 | AA101: LF | AB101: 11.64 | AC101: CY
...

Sheet 04 40 Stone Veneer
G1: Hedrick Plug
F2: X | G2: Excluded
F3: I | G3: Included
B4: BACK TO SUMMARY SHEET | G4: Sub Add/Deduct
A5: Project: | B5: ='Area Calculations'!B4 -> Atlantic Fields Club Core / Dock Bar / Spa Pods / Water Features | G5: Company | H5: Titan Stone | J5: Marbon Stone | L5: Palm Beach Stone | P5: Precision Stone
A6: Trade: | B6: Stone Veneer | G6: Contact | H6: Matthew Teston | J6: Paul Vassalotti | L6: William Thayer | P6: Pamela Van Dina
A7: CSI Code: | B7: 04 40 00 | G7: Phone | H7: (954) 662-2553 | J7: (561) 727-8377 | L7: (561) 835-4085 | P7: (516) 997-6190 ext. 117
A8: Date: | G8: Email | H8: mteston@titanstone.com | J8: paul@marbon.com | L8: william@palmbeachstone.com | P8: pamela@precisionstone.net
G9: Adjusted Bid | H9: =I$72 -> 983329 | J9: =K$72 -> 980366.8 | L9: =M$72 -> 0 | N9: =O$72 -> 0 | P9: =Q$72 -> 1592450 | R9: =S$72 -> 0
A10: BID DOCUMENTS: | C10: Plan/ Spec. Package | D10: QTY | E10: U/M | F10: Unit Cost | G10: Subtotal | H10: Yes/No | I10: Price | J10: Yes/No | K10: Price | L10: Yes/No | M10: Price | N10: Yes/No | O10: Price | P10: Yes/No | Q10: Price | R10: Yes/No | S10: Price
B11: GENERAL INCLUSIONS
B12: INCLUDES ALL SALES TAX
B13: ALL HOISTING & RIGGING REQUIRED TO COMPLETE THIS SCOPE
B14: PROVIDE P&P BONDS
B15: FLORIDA STATE CONTRACTORS LIC.
B16: GENERAL LIABILITY AND WORKERS COMP. INSURANCE LIMITS
B17: STATE AND LOCAL TAXES
B18: SPECIFIC TRADE SCOPE OF WORK REQUIREMENTS
B19: BASE BID
B21: Club Core | I21: =SUBTOTAL(9,I22:I66) -> 983329 | K21: =SUBTOTAL(9,K22:K66) -> 980366.8 | M21: =SUBTOTAL(9,M22:M66) -> 0 | O21: =SUBTOTAL(9,O22:O66) -> 0 | Q21: =SUBTOTAL(9,Q22:Q66) -> 1592450 | S21: =SUBTOTAL(9,S22:S66) -> 0
A22: =32*4/2 -> 64 | B22: ST-02 Stone Cladding | G22: =ROUND(D22*F22,0) -> 0
B23: Specifications
B24: Dominical Coral Stone | F24: =SUM(I24:I27) -> 839167 | G24: =ROUND(D24*F24,0) -> 0 | I24: =502609 -> 502609 | K24: 681074.8
B25: Thickness - 1 3/4" | F25: =F24/D55 -> 58.033679 | G25: =ROUND(D25*F25,0) -> 0 | I25: =151000 -> 151000 | J25: I
B26: Scratch Coat - 5/8" - BY STUCCO SUB | H26: X | J26: X
B27: Mud Set - 5/8" | G27: =ROUND(D27*F27,0) -> 0 | I27: =165273+20285 -> 185558 | J27: I
B28: Thickness may require stone to be pinned. | H28: I | J28: X | K28: NOT REQUIRED
B30: ST-02 Stone Cladding - exterior
B31: Dining - East Elevation | C31: 1/A3.00 | D31: =6+113+114+113+114+893 -> 1353 | E31: sf | G31: =ROUND(D31*F31,0) -> 0 | H31: I | J31: I | Q31: =340230+95840 -> 436070
B32: Dining - East Mech Yard Elevation | C32: 2/A3.00 | D32: 0 | E32: sf | G32: =ROUND(D32*F32,0) -> 0 | P32: I
B33: Dining - North Elevation | C33: 3/A3.00 | D33: =251+99 -> 350 | E33: sf | G33: =ROUND(D33*F33,0) -> 0 | H33: I | J33: I | P33: I
B34: Dining - West Elevation | C34: 1/A3.01 | D34: 67 | E34: sf | G34: =ROUND(D34*F34,0) -> 0 | H34: I | J34: I | P34: I
B35: Dining - South Elevation | C35: 2/A3.01 | D35: =379+25 -> 404 | E35: sf | G35: =ROUND(D35*F35,0) -> 0 | H35: I | J35: I | P35: I
B36: Fitness - North Elevation | C36: 1/A3.02 | D36: =143+118+116+103+104+104+105+104+280+283 -> 1460 | E36: sf | G36: =ROUND(D36*F36,0) -> 0 | H36: I | J36: I | Q36: =313310+196330 -> 509640
B37: Fitness - East Elevation | C37: 2/A3.02 | D37: 995 | E37: sf | G37: =ROUND(D37*F37,0) -> 0 | H37: I | J37: I | P37: I
B38: Fitness - South Elevation | C38: 1/A3.03 | D38: =33+115+100+136 -> 384 | E38: sf | G38: =ROUND(D38*F38,0) -> 0 | H38: I | J38: I | P38: I
B39: Fitness - West Elevation | C39: 2/A3.03 | D39: =168+364+413+81+81+92 -> 1199 | E39: sf | G39: =ROUND(D39*F39,0) -> 0 | H39: I | J39: I | P39: I
B40: Wellness - North Elevation | C40: 1/A3.04 | D40: =99+154+11+11+668+715 -> 1658 | E40: sf | G40: =ROUND(D40*F40,0) -> 0 | H40: I | J40: I | Q40: =362640+284100 -> 646740
B41: Wellness- East Elevation | C41: 2/A3.04 | D41: =432+140+203+153+10 -> 938 | E41: sf | G41: =ROUND(D41*F41,0) -> 0 | H41: I | J41: I | P41: I
B42: Wellness - South Elevation | C42: 1/A3.05 | D42: =20+144+114+56+138+13+13+8 -> 506 | E42: sf | G42: =ROUND(D42*F42,0) -> 0 | H42: I | J42: I | P42: I
B43: Wellness- West Elevation | C43: 2/A3.05 | D43: =775+916 -> 1691 | E43: sf | G43: =ROUND(D43*F43,0) -> 0 | H43: I | J43: I | P43: I
B44: Wellness Ext Vestibule at Mens W-137 & Womens W-135 | C44: A2.22 | D44: =43*3 -> 129 | E44: sf | G44: =ROUND(D44*F44,0) -> 0 | H44: I | K44: =D44*48 -> 6192
B45: Wellness exterior low wall - Garden at Thermal Area W-132 | C45: A2.22 | D45: 776 | E45: sf | G45: =ROUND(D45*F45,0) -> 0 | H45: I | J45: I | P45: I
B46: Wellness exterior walls at Exterior Patios W-140/141 | C46: A2.22.3 | D46: 968 | E46: sf | G46: =ROUND(D46*F46,0) -> 0 | H46: I | J46: I | P46: I
G47: =ROUND(D47*F47,0) -> 0
B48: ST-02 Stone Cladding - interior - Dining Fireplace | C48: A4.3 | D48: =164+48 -> 212 | E48: sf | G48: =ROUND(D48*F48,0) -> 0 | H48: I | J48: I | Q48: =$G48 -> 0
G49: =ROUND(D49*F49,0) -> 0
B50: Stone Hearth - box frames w/ ST-101.3 caldding | E50: sf | G50: =ROUND(D50*F50,0) -> 0
B51: stone -ST-101.3 -leathered linestone | D51: 60 | E51: sf | F51: 150 | G51: =ROUND(D51*F51,0) -> 9000 | I51: =$G51 -> 9000 | K51: =$G51 -> 9000
B52: wood frame | D52: 1 | E52: ls | F52: 2500 | G52: =ROUND(D52*F52,0) -> 2500 | I52: =$G52 -> 2500 | K52: =$G52 -> 2500
G53: =ROUND(D53*F53,0) -> 0
B54: waste & breakage - 10% | D54: =SUM(D31:D48)*0.1 -> 1309 | E54: sf | G54: =ROUND(D54*F54,0) -> 0
B55: Total | D55: =SUM(D31:D54) -> 14460 | E55: sf | G55: =ROUND(D55*F55,0) -> 0
G56: =ROUND(D56*F56,0) -> 0
B57: Addendum #1 | G57: =ROUND(D57*F57,0) -> 0 | I57: =62377+20285 -> 82662
B58: exterior - D-114 Outdoor Dining | C58: 1/A2.20.2 | D58: 975 | E58: sf | G58: =ROUND(D58*F58,0) -> 0 | H58: I | K58: =D58*48 -> 46800 | Q58: =$G58 -> 0
B59: exterior - D-001 Kids Space (patio) | C59: A2.10.3 | D59: 472 | E59: sf | G59: =ROUND(D59*F59,0) -> 0 | H59: I | K59: =D59*48 -> 22656
B60: interior - Dining Service | C60: A2.10.2 | D60: =1720+1658 -> 3378 | E60: sf | G60: =ROUND(D60*F60,0) -> 0 | H60: I | K60: =D60*48 -> 162144 | Q60: =$G60 -> 0
G62: =ROUND(D62*F62,0) -> 0
B63: Interior Stone Door Jambs & Portals | D63: 20 | E63: ea | F63: 2500 | G63: =ROUND(D63*F63,0) -> 50000 | I63: =$G63 -> 50000 | K63: =$G63 -> 50000
G64: =ROUND(D64*F64,0) -> 0
B65: Dock Bar - NA | G65: =ROUND(D65*F65,0) -> 0
B66: Spa Pods - NA | G66: =ROUND(D66*F66,0) -> 0
G67: =ROUND(D67*F67,0) -> 0
B68: SUBTOTAL Base Bid | G68: =SUBTOTAL(9,G22:G67) -> 61500 | I68: =SUBTOTAL(9,I21:I67) -> 983329 | K68: =SUBTOTAL(9,K21:K67) -> 980366.8 | M68: =SUBTOTAL(9,M21:M67) -> 0 | O68: =SUBTOTAL(9,O21:O67) -> 0 | Q68: =SUBTOTAL(9,Q21:Q67) -> 1592450 | S68: =SUBTOTAL(9,S22:S67) -> 0
B69: BOND RATE | H69: 0 | J69: 0 | L69: 0 | N69: 0 | P69: 0 | R69: 0
B70: BOND AMOUNT | G70: =F69*G68 -> 0 | I70: =H69*I68 -> 0 | K70: =J69*K68 -> 0 | M70: =L69*M68 -> 0 | O70: =N69*O68 -> 0 | Q70: =P69*Q68 -> 0 | S70: =R69*S68 -> 0
B72: ADJUSTED TOTAL | G72: =SUM(G68:G70) -> 61500 | I72: =SUM(I68:I70) -> 983329 | K72: =SUM(K68:K70) -> 980366.8 | M72: =SUM(M68:M70) -> 0 | O72: =SUM(O68:O70) -> 0 | Q72: =SUM(Q68:Q70) -> 1592450 | S72: =SUM(S68:S70) -> 0
B73: Cost per SF | G73: =G72/'Area Calculations'!$F$5 -> 0.6935673 | I73: =I72/'Area Calculations'!$F$5 -> 11.08951 | K73: =K72/'Area Calculations'!$F$5 -> 11.056103 | M73: =M72/'Area Calculations'!$F$5 -> 0 | O73: =O72/'Area Calculations'!$F$5 -> 0 | Q73: =Q72/'Area Calculations'!$F$5 -> 17.958882 | S73: =S72/'Area Calculations'!$F$5 -> 0
A75: QUALIFICATIONS
A79: EXCLUSIONS/OWNER PROVIDED ITEMS:
A83: ALTERNATES:
A87: PROPOSED VE (Provide Clear Description):
A91: FULLY LOADED LABOR RATES
B92: Laborer
B93: Mechanic
B94: Superintendent
B95: Project Manager
A97: SCHEDULE
B98: Prepared shop drawings/submittals
B99: Mobilization
B100: Total duration to complete scope of work
A102: Winner
A103: Company
A104: Contact
A105: Phone
A106: Email
A107: Base Bid | B107: =I$72 -> 983329
B109: Need Prequalification
B110: Prequalified

Sheet 05 10 Structural Steel
I1: Hedrick Plug
H2: X | I2: Excluded
H3: I | I3: Included
B4: BACK TO SUMMARY SHEET | I4: Sub Add/Deduct
A5: Project: | B5: Atlantic Fields Club Core | I5: Company | J5: VM Iron Works | L5: Suncor | N5: Steel Fabricators
A6: Trade: | B6: Structural Steel | I6: Contact | J6: Johnny Lorusso | L6: Scott Kuiper | N6: Joe Zavertnik
A7: CSI Code: | B7: 05 10 00 | I7: Phone | J7: (772) 781-0318 | L7: (305) 359-1400 | N7: (954) 288-7153
A8: Date: | I8: Email | J8: johnny@vmironwork.com | L8: Scott.K@suncor.net | N8: jzavertnik@sfab.com
I9: Adjusted Bid | J9: =K$296 -> 5339241 | L9: =M$296 -> 5634370 | N9: =O$296 -> 6246031 | P9: =Q$296 -> 0 | R9: =S$296 -> 0 | T9: =U$296 -> 0
A10: BID DOCUMENTS: | C10: QTY | D10: U/M | E10: Weight | F10: QTY | G10: U/M | H10: Unit Cost | I10: Subtotal | J10: Yes/No | K10: Price | L10: Yes/No | M10: Price | N10: Yes/No | O10: Price | P10: Yes/No | Q10: Price | R10: Yes/No | S10: Price | T10: Yes/No | U10: Price
B11: GENERAL INCLUSIONS
B12: INCLUDES ALL SALES TAX
B13: ALL HOISTING & RIGGING REQUIRED TO COMPLETE THIS SCOPE
B14: PROVIDE P&P BONDS
B15: FLORIDA STATE CONTRACTORS LIC.
B16: GENERAL LIABILITY AND WORKERS COMP. INSURANCE LIMITS
B17: STATE AND LOCAL TAXES
B18: SPECIFIC TRADE SCOPE OF WORK REQUIREMENTS
B19: BASE BID
I20: =ROUND(F20*H20,0) -> 0
B21: Club Core | I21: =ROUND(F21*H21,0) -> 0 | K21: =SUBTOTAL(9,K22:K243) -> 4903059 | M21: =SUBTOTAL(9,M22:M243) -> 5114816 | O21: =SUBTOTAL(9,O22:O243) -> 5622745 | Q21: =SUBTOTAL(9,Q22:Q243) -> 0 | S21: =SUBTOTAL(9,S22:S243) -> 0 | U21: =SUBTOTAL(9,U22:U243) -> 0
B22: Steel | I22: =ROUND(F22*H22,0) -> 0 | O22: 4833380
B23: Dining | I23: =ROUND(F23*H23,0) -> 0 | K23: 1574745 | M23: =1637843+5000 -> 1642843
B24: Fitness | I24: =ROUND(F24*H24,0) -> 0 | K24: 716675 | M24: 735225
B25: Wellness | I25: =ROUND(F25*H25,0) -> 0 | K25: 1427960 | M25: =1566001+138600 -> 1704601
I26: =ROUND(F26*H26,0) -> 0
B27: Steel Joists | I27: =ROUND(F27*H27,0) -> 0 | J27: I | L27: I | N27: I
B28: =X28 -> 10K1 | C28: =Z28 -> 133 | D28: lf | E28: 5 | F28: =C28*E28/2000 -> 0.3325 | G28: ton | I28: =ROUND(F28*H28,0) -> 0 | W28: 157 | X28: 10K1 | Y28: 0" | Z28: 133 | AA28: LF
B29: =X29 -> 12K1 | C29: =Z29 -> 91 | D29: lf | E29: 5 | F29: =C29*E29/2000 -> 0.2275 | G29: ton | I29: =ROUND(F29*H29,0) -> 0 | W29: 221 | X29: 12K1 | Y29: 0" | Z29: 91 | AA29: LF
B30: =X30 -> 12K3 | C30: =Z30 -> 73 | D30: lf | E30: 5.7 | F30: =C30*E30/2000 -> 0.20805 | G30: ton | I30: =ROUND(F30*H30,0) -> 0 | W30: 263 | X30: 12K3 | Y30: 13' 4" | Z30: 73 | AA30: LF
B31: =X31 -> 16K3 - 13'-4" | C31: =Z31 -> 213.33 | D31: lf | E31: 6.3 | F31: =C31*E31/2000 -> 0.6719895 | G31: ton | I31: =ROUND(F31*H31,0) -> 0 | W31: 207 | X31: 16K3 - 13'-4" | Y31: 13' 4" | Z31: 213.33 | AA31: LF | AB31: 16 | AC31: EA
B32: =X32 -> 16K4 | C32: =Z32 -> 81 | D32: lf | E32: 7 | F32: =C32*E32/2000 -> 0.2835 | G32: ton | I32: =ROUND(F32*H32,0) -> 0 | W32: 158 | X32: 16K4 | Y32: 0" | Z32: 81 | AA32: LF
B33: =X33 -> 18K4 | C33: =Z33 -> 312 | D33: lf | E33: 7.2 | F33: =C33*E33/2000 -> 1.1232 | G33: ton | I33: =ROUND(F33*H33,0) -> 0 | W33: 223 | X33: 18K4 | Y33: 0" | Z33: 312 | AA33: LF
B34: =X34 -> 20K06 | C34: =Z34 -> 376 | D34: lf | E34: 8.9 | F34: =C34*E34/2000 -> 1.6732 | G34: ton | I34: =ROUND(F34*H34,0) -> 0 | W34: 265 | X34: 20K06 | Y34: 0" | Z34: 376 | AA34: LF
B35: =X35 -> 22K10 | C35: =Z35 -> 379 | D35: lf | E35: 12.6 | F35: =C35*E35/2000 -> 2.3877 | G35: ton | I35: =ROUND(F35*H35,0) -> 0 | W35: 163 | X35: 22K10 | Y35: 0" | Z35: 379 | AA35: LF
B36: =X36 -> 24K09 | C36: =Z36 -> 109 | D36: lf | E36: 12 | F36: =C36*E36/2000 -> 0.654 | G36: ton | I36: =ROUND(F36*H36,0) -> 0 | W36: 264 | X36: 24K09 | Y36: 0" | Z36: 109 | AA36: LF
B37: =X37 -> 30K07 | C37: =Z37 -> 504 | D37: lf | E37: 12.3 | F37: =C37*E37/2000 -> 3.0996 | G37: ton | I37: =ROUND(F37*H37,0) -> 0 | W37: 261 | X37: 30K07 | Y37: 49' 9" | Z37: 504 | AA37: LF
B38: =X38 -> 30K11 | C38: =Z38 -> 705 | D38: lf | E38: 16.4 | F38: =C38*E38/2000 -> 5.781 | G38: ton | I38: =ROUND(F38*H38,0) -> 0 | W38: 209 | X38: 30K11 | Y38: 49' 9" | Z38: 705 | AA38: LF
B39: =X39 -> 30K11 - 49'-9" | C39: =Z39 -> 1144.25 | D39: lf | E39: 16.4 | F39: =C39*E39/2000 -> 9.38285 | G39: ton | I39: =ROUND(F39*H39,0) -> 0 | W39: 208 | X39: 30K11 - 49'-9" | Y39: 49' 9" | Z39: 1144.25 | AA39: LF | AB39: 23 | AC39: EA
B40: total tons | F40: =SUM(F28:F39) -> 25.825089 | G40: ton | H40: 2000 | I40: =ROUND(F40*H40,0) -> 51650
B41: bridging | F41: =F40*0.15 -> 3.8737634 | G41: ton | H41: =H40 -> 2000 | I41: =ROUND(F41*H41,0) -> 7748
I42: =ROUND(F42*H42,0) -> 0
B43: Steel Members | I43: =ROUND(F43*H43,0) -> 0 | J43: I | L43: I | N43: I
B44: =X44 -> C08X13.7 | C44: =Z44 -> 450 | D44: lf | E44: 13.7 | F44: =C44*E44/2000 -> 3.0825 | G44: ton | I44: =ROUND(F44*H44,0) -> 0 | W44: 212 | X44: C08X13.7 | Y44: 0" | Z44: 450 | AA44: LF
B45: =X45 -> C09X13.4 | C45: =Z45 -> 1193 | D45: lf | E45: 13.4 | F45: =C45*E45/2000 -> 7.9931 | G45: ton | I45: =ROUND(F45*H45,0) -> 0 | W45: 194 | X45: C09X13.4 | Y45: 0" | Z45: 1193 | AA45: LF
B46: =X46 -> C09X15 | C46: =Z46 -> 165 | D46: lf | E46: 15 | F46: =C46*E46/2000 -> 1.2375 | G46: ton | I46: =ROUND(F46*H46,0) -> 0 | W46: 218 | X46: C09X15 | Y46: 0" | Z46: 165 | AA46: LF
B47: =X47 -> DSC-1 - 15.67 HSS6x6x5/16 | C47: =Z47 -> 47 | D47: lf | E47: 23.34 | F47: =C47*E47/2000 -> 0.54849 | G47: ton | I47: =ROUND(F47*H47,0) -> 0 | W47: 15 | X47: DSC-1 - 15.67 HSS6x6x5/16 | Y47: 15' 8" | Z47: 47 | AA47: LF | AB47: 3 | AC47: EA
B48: =X48 -> DSC-2 - 14.17 W8X58 | C48: =Z48 -> 85 | D48: lf | E48: 58 | F48: =C48*E48/2000 -> 2.465 | G48: ton | I48: =ROUND(F48*H48,0) -> 0 | W48: 32 | X48: DSC-2 - 14.17 W8X58 | Y48: 14' 2" | Z48: 85 | AA48: LF | AB48: 6 | AC48: EA
B49: =X49 -> DSC-2 - 15.67 W8X58 | C49: =Z49 -> 47 | D49: lf | E49: 58 | F49: =C49*E49/2000 -> 1.363 | G49: ton | I49: =ROUND(F49*H49,0) -> 0 | W49: 16 | X49: DSC-2 - 15.67 W8X58 | Y49: 15' 8" | Z49: 47 | AA49: LF | AB49: 3 | AC49: EA
B50: =X50 -> DSC-3 - 14.17 W8X67 | C50: =Z50 -> 113.33 | D50: lf | E50: 67 | F50: =C50*E50/2000 -> 3.796555 | G50: ton | I50: =ROUND(F50*H50,0) -> 0 | W50: 33 | X50: DSC-3 - 14.17 W8X67 | Y50: 14' 2" | Z50: 113.33 | AA50: LF | AB50: 8 | AC50: EA
B51: =X51 -> DSC-3 - 15.56 W8X67 | C51: =Z51 -> 93.5 | D51: lf | E51: 67 | F51: =C51*E51/2000 -> 3.13225 | G51: ton | I51: =ROUND(F51*H51,0) -> 0 | W51: 185 | X51: DSC-3 - 15.56 W8X67 | Y51: 15' 7" | Z51: 93.5 | AA51: LF | AB51: 6 | AC51: EA
B52: =X52 -> DSC-4 - 14.17 W8X67 | C52: =Z52 -> 127.5 | D52: lf | E52: 67 | F52: =C52*E52/2000 -> 4.27125 | G52: ton | I52: =ROUND(F52*H52,0) -> 0 | W52: 30 | X52: DSC-4 - 14.17 W8X67 | Y52: 14' 2" | Z52: 127.5 | AA52: LF | AB52: 9 | AC52: EA
B53: =X53 -> DSC-4 - 15.56 W8X67 | C53: =Z53 -> 15.58 | D53: lf | E53: 67 | F53: =C53*E53/2000 -> 0.52193 | G53: ton | I53: =ROUND(F53*H53,0) -> 0 | W53: 186 | X53: DSC-4 - 15.56 W8X67 | Y53: 15' 7" | Z53: 15.58 | AA53: LF | AB53: 1 | AC53: EA
B54: =X54 -> DSC-5 - 14.17 W12X65 | C54: =Z54 -> 155.83 | D54: lf | E54: 65 | F54: =C54*E54/2000 -> 5.064475 | G54: ton | I54: =ROUND(F54*H54,0) -> 0 | W54: 31 | X54: DSC-5 - 14.17 W12X65 | Y54: 14' 2" | Z54: 155.83 | AA54: LF | AB54: 11 | AC54: EA
B55: =X55 -> DSC-6 - 14.17 HSS12x12x5/8 | C55: =Z55 -> 56.67 | D55: lf | E55: 93.34 | F55: =C55*E55/2000 -> 2.6447889 | G55: ton | I55: =ROUND(F55*H55,0) -> 0 | W55: 29 | X55: DSC-6 - 14.17 HSS12x12x5/8 | Y55: 14' 2" | Z55: 56.67 | AA55: LF | AB55: 4 | AC55: EA
B56: =X56 -> DSC-7 - 14.17 HSS8x8x5/8 | C56: =Z56 -> 14.17 | D56: lf | E56: 59.32 | F56: =C56*E56/2000 -> 0.4202822 | G56: ton | I56: =ROUND(F56*H56,0) -> 0 | W56: 34 | X56: DSC-7 - 14.17 HSS8x8x5/8 | Y56: 14' 2" | Z56: 14.17 | AA56: LF | AB56: 1 | AC56: EA
B57: =X57 -> DSC-7 - 15.56 HSS8x8x5/8 | C57: =Z57 -> 15.58 | D57: lf | E57: 59.32 | F57: =C57*E57/2000 -> 0.4621028 | G57: ton | I57: =ROUND(F57*H57,0) -> 0 | W57: 189 | X57: DSC-7 - 15.56 HSS8x8x5/8 | Y57: 15' 7" | Z57: 15.58 | AA57: LF | AB57: 1 | AC57: EA
B58: =X58 -> DSC-8 - 15.67 HSS6x6x5/8 | C58: =Z58 -> 15.67 | D58: lf | E58: 42.3 | F58: =C58*E58/2000 -> 0.3314205 | G58: ton | I58: =ROUND(F58*H58,0) -> 0 | W58: 17 | X58: DSC-8 - 15.67 HSS6x6x5/8 | Y58: 15' 8" | Z58: 15.67 | AA58: LF | AB58: 1 | AC58: EA
... B63: =X63 -> FSC-4 - 15.00 HSS10x10x1/2 | C63: =Z63 -> 150 | D63: lf | E63: 62.46 | F63: =C63*E63/2000 -> 4.6845 | G63: ton | I63: =ROUND(F63*H63,0) -> 0 | W63: 199 | X63: FSC-4 - 15.00 HSS10x10x1/2 | Y63: 15' 0" | Z63: 150 | AA63: LF | AB63: 10 | AC63: EA
B64: =X64 -> HSS02 1/2X2 1/2X3/16 | C64: =Z64-C168 -> 199 | D64: lf | E64: 4.32 | F64: =C64*E64/2000 -> 0.42984 | G64: ton | I64: =ROUND(F64*H64,0) -> 0 | X64: HSS02 1/2X2 1/2X3/16 | Z64: 328 | AA64: LF
B65: =X65 -> HSS03X3X1/4 | C65: =Z65 -> 151 | D65: lf | E65: 8.81 | F65: =C65*E65/2000 -> 0.665155 | G65: ton | I65: =ROUND(F65*H65,0) -> 0 | X65: HSS03X3X1/4 | Z65: 151 | AA65: LF
B66: =X66 -> HSS05X2 1/2X1/4 | C66: =Z66-C162 -> 98 | D66: lf | E66: 11.36 | F66: =C66*E66/2000 -> 0.55664 | G66: ton | I66: =ROUND(F66*H66,0) -> 0 | X66: HSS05X2 1/2X1/4 | Z66: 526 | AA66: LF
B67: =X67 -> HSS06X8X1/4 | C67: =Z67 -> 177 | D67: lf | E67: 22.42 | F67: =C67*E67/2000 -> 1.98417 | G67: ton | I67: =ROUND(F67*H67,0) -> 0 | X67: HSS06X8X1/4 | Z67: 177 | AA67: LF
B68: =X68 -> HSS08X8X5/8 - 10'-5" | C68: =Z68 -> 166.67 | D68: lf | E68: 59.32 | F68: =C68*E68/2000 -> 4.9434322 | G68: ton | I68: =ROUND(F68*H68,0) -> 0 | W68: 174 | X68: HSS08X8X5/8 - 10'-5" | Y68: 10' 5" | Z68: 166.67 | AA68: LF | AB68: 16 | AC68: EA
B69: =X69 -> HSS12X2X1/8- 14.67 | C69: =Z69 -> 29.34 | D69: lf | E69: 17.08 | F69: =C69*E69/2000 -> 0.2505636 | G69: ton | I69: =ROUND(F69*H69,0) -> 0 | W69: 204 | X69: HSS12X2X1/8- 14.67 | Y69: 0" | Z69: =2*14.67 -> 29.34 | AA69: LF | AB69: 2 | AC69: EA
B70: =X70 -> HSS12x8x3/8 | C70: =Z70 -> 160 | D70: lf | E70: 47.9 | F70: =C70*E70/2000 -> 3.832 | G70: ton | I70: =ROUND(F70*H70,0) -> 0 | W70: 216 | X70: HSS12x8x3/8 | Y70: 10' 5" | Z70: 160 | AA70: LF
B71: =X71 -> HSS14X6X1/4 | C71: =Z71 -> 35 | D71: lf | E71: 32.63 | F71: =C71*E71/2000 -> 0.571025 | G71: ton | I71: =ROUND(F71*H71,0) -> 0 | W71: 184 | X71: HSS14X6X1/4 | Y71: 10' 5" | Z71: 35 | AA71: LF
B72: =X72 -> HSS14X6X5/16 | C72: =Z72 -> 291 | D72: lf | E72: 40.35 | F72: =C72*E72/2000 -> 5.870925 | G72: ton | I72: =ROUND(F72*H72,0) -> 0 | W72: 249 | X72: HSS14X6X5/16 | Y72: 10' 5" | Z72: 291 | AA72: LF
B73: =X73 -> HSS18X6X1/4 | C73: =Z73 -> 385 | D73: lf | E73: 39.43 | F73: =C73*E73/2000 -> 7.590275 | G73: ton | I73: =ROUND(F73*H73,0) -> 0 | W73: 183 | X73: HSS18X6X1/4 | Y73: 10' 5" | Z73: 385 | AA73: LF
B74: =X74 -> HSS18X6X3/8 | C74: =Z74 -> 181 | D74: lf | E74: 58.1 | F74: =C74*E74/2000 -> 5.25805 | G74: ton | I74: =ROUND(F74*H74,0) -> 0 | W74: 215 | X74: HSS18X6X3/8 | Y74: 10' 5" | Z74: 181 | AA74: LF
B75: =X75 -> L2X2X1/2 | C75: =Z75 -> 52 | D75: lf | E75: 4.7 | F75: =C75*E75/2000 -> 0.1222 | G75: ton | I75: =ROUND(F75*H75,0) -> 0 | X75: L2X2X1/2 | Z75: 52 | AA75: LF
B76: =X76 -> L3X3X1/4 | C76: =Z76 -> 469 | D76: lf | E76: 4.9 | F76: =C76*E76/2000 -> 1.14905 | G76: ton | I76: =ROUND(F76*H76,0) -> 0 | X76: L3X3X1/4 | Z76: 469 | AA76: LF
B77: =X77 -> W04X13 - 4 EA | C77: =Z77 -> 242 | D77: lf | E77: 13 | F77: =C77*E77/2000 -> 1.573 | G77: ton | I77: =ROUND(F77*H77,0) -> 0 | W77: 213 | X77: W04X13 - 4 EA | Y77: 0" | Z77: 242 | AA77: LF
B78: =X78 -> W06X12 | C78: =Z78 -> 207 | D78: lf | E78: 12 | F78: =C78*E78/2000 -> 1.242 | G78: ton | I78: =ROUND(F78*H78,0) -> 0 | W78: 155 | X78: W06X12 | Y78: 0" | Z78: 207 | AA78: LF
B79: =X79 -> W06X12 - 4'-6" | C79: =Z79 -> 198 | D79: lf | E79: 12 | F79: =C79*E79/2000 -> 1.188 | G79: ton | I79: =ROUND(F79*H79,0) -> 0 | W79: 259 | X79: W06X12 - 4'-6" | Y79: 4' 6" | Z79: 198 | AA79: LF | AB79: 44 | AC79: EA
B80: =X80 -> W06X12 - 6'-10" | C80: =Z80 -> 68.33 | D80: lf | E80: 12 | F80: =C80*E80/2000 -> 0.40998 | G80: ton | I80: =ROUND(F80*H80,0) -> 0 | W80: 252 | X80: W06X12 - 6'-10" | Y80: 6' 10" | Z80: 68.33 | AA80: LF | AB80: 10 | AC80: EA
B81: =X81 -> W06X12 - 6'-6" | C81: =Z81 -> 429 | D81: lf | E81: 12 | F81: =C81*E81/2000 -> 2.574 | G81: ton | I81: =ROUND(F81*H81,0) -> 0 | W81: 251 | X81: W06X12 - 6'-6" | Y81: 6' 6" | Z81: 429 | AA81: LF | AB81: 66 | AC81: EA
B82: =X82 -> W06X12 - 6'-8" | C82: =Z82 -> 413.33 | D82: lf | E82: 12 | F82: =C82*E82/2000 -> 2.47998 | G82: ton | I82: =ROUND(F82*H82,0) -> 0 | W82: 250 | X82: W06X12 - 6'-8" | Y82: 6' 8" | Z82: 413.33 | AA82: LF | AB82: 62 | AC82: EA
B83: =X83 -> W06X12 - 7'-0" | C83: =Z83 -> 1295 | D83: lf | E83: 12 | F83: =C83*E83/2000 -> 7.77 | G83: ton | I83: =ROUND(F83*H83,0) -> 0 | W83: 153 | X83: W06X12 - 7'-0" | Y83: 7' 0" | Z83: 1295 | AA83: LF | AB83: 185 | AC83: EA
B84: =X84 -> W06X12 - 7'-6" | C84: =Z84 -> 157.5 | D84: lf | E84: 12 | F84: =C84*E84/2000 -> 0.945 | G84: ton | I84: =ROUND(F84*H84,0) -> 0 | W84: 192 | X84: W06X12 - 7'-6" | Y84: 7' 6" | Z84: 157.5 | AA84: LF | AB84: 21 | AC84: EA
B85: =X85 -> W06X12 - 9'-8" | C85: =Z85 -> 106.33 | D85: lf | E85: 12 | F85: =C85*E85/2000 -> 0.63798 | G85: ton | I85: =ROUND(F85*H85,0) -> 0 | W85: 258 | X85: W06X12 - 9'-8" | Y85: 9' 8" | Z85: 106.33 | AA85: LF | AB85: 11 | AC85: EA
B86: =X86 -> W06X15 - 6'-6" | C86: =Z86 -> 208 | D86: lf | E86: 15 | F86: =C86*E86/2000 -> 1.56 | G86: ton | I86: =ROUND(F86*H86,0) -> 0 | W86: 206 | X86: W06X15 - 6'-6" | Y86: 6' 6" | Z86: 208 | AA86: LF | AB86: 32 | AC86: EA
B87: =X87 -> W06X15 - 8'-4" | C87: =Z87 -> 291.67 | D87: lf | E87: 15 | F87: =C87*E87/2000 -> 2.187525 | G87: ton | I87: =ROUND(F87*H87,0) -> 0 | W87: 205 | X87: W06X15 - 8'-4" | Y87: 8' 4" | Z87: 291.67 | AA87: LF | AB87: 35 | AC87: EA
B88: =X88 -> W06X20 | C88: =Z88 -> 263 | D88: lf | E88: 20 | F88: =C88*E88/2000 -> 2.63 | G88: ton | I88: =ROUND(F88*H88,0) -> 0 | W88: 193 | X88: W06X20 | Y88: 0" | Z88: 263 | AA88: LF
B89: =X89 -> W06X25 | C89: =Z89 -> 279 | D89: lf | E89: 25 | F89: =C89*E89/2000 -> 3.4875 | G89: ton | I89: =ROUND(F89*H89,0) -> 0 | W89: 156 | X89: W06X25 | Y89: 0" | Z89: 279 | AA89: LF
B90: =X90 -> W06X31 | C90: =Z90 -> 26 | D90: lf | E90: 31 | F90: =C90*E90/2000 -> 0.403 | G90: ton | I90: =ROUND(F90*H90,0) -> 0 | W90: 220 | X90: W06X31 | Y90: 0" | Z90: 26 | AA90: LF
B91: =X91 -> W08X10 | C91: =Z91 -> 244 | D91: lf | E91: 10 | F91: =C91*E91/2000 -> 1.22 | G91: ton | I91: =ROUND(F91*H91,0) -> 0 | W91: 148 | X91: W08X10 | Y91: 0" | Z91: 244 | AA91: LF
B92: =X92 -> W08X13 | C92: =Z92 -> 246 | D92: lf | E92: 13 | F92: =C92*E92/2000 -> 1.599 | G92: ton | I92: =ROUND(F92*H92,0) -> 0 | W92: 169 | X92: W08X13 | Y92: 0" | Z92: 246 | AA92: LF
B93: =X93 -> W08X15 | C93: =Z93 -> 57 | D93: lf | E93: 15 | F93: =C93*E93/2000 -> 0.4275 | G93: ton | I93: =ROUND(F93*H93,0) -> 0 | W93: 201 | X93: W08X15 | Y93: 0" | Z93: 57 | AA93: LF
B94: =X94 -> W08X18 | C94: =Z94 -> 38 | D94: lf | E94: 18 | F94: =C94*E94/2000 -> 0.342 | G94: ton | I94: =ROUND(F94*H94,0) -> 0 | W94: 210 | X94: W08X18 | Y94: 0" | Z94: 38 | AA94: LF
B95: =X95 -> W08X24 | C95: =Z95 -> 288 | D95: lf | E95: 24 | F95: =C95*E95/2000 -> 3.456 | G95: ton | I95: =ROUND(F95*H95,0) -> 0 | W95: 248 | X95: W08X24 | Y95: 9' 8" | Z95: 288 | AA95: LF
B96: =X96 -> W08X24 - 9'-8" | C96: =Z96 -> 154.67 | D96: lf | E96: 24 | F96: =C96*E96/2000 -> 1.85604 | G96: ton | I96: =ROUND(F96*H96,0) -> 0 | W96: 219 | X96: W08X24 - 9'-8" | Y96: 9' 8" | Z96: 154.67 | AA96: LF | AB96: 16 | AC96: EA
B97: =X97 -> W08X31 | C97: =Z97 -> 47 | D97: lf | E97: 31 | F97: =C97*E97/2000 -> 0.7285 | G97: ton | I97: =ROUND(F97*H97,0) -> 0 | W97: 170 | X97: W08X31 | Y97: 0" | Z97: 47 | AA97: LF
B98: =X98 -> W08X40 | C98: =Z98 -> 164 | D98: lf | E98: 40 | F98: =C98*E98/2000 -> 3.28 | G98: ton | I98: =ROUND(F98*H98,0) -> 0 | W98: 180 | X98: W08X40 | Y98: 0" | Z98: 164 | AA98: LF
B99: =X99 -> W08X48 | C99: =Z99 -> 18 | D99: lf | E99: 48 | F99: =C99*E99/2000 -> 0.432 | G99: ton | I99: =ROUND(F99*H99,0) -> 0 | W99: 262 | X99: W08X48 | Y99: 0" | Z99: 18 | AA99: LF
B100: =X100 -> W08X67 | C100: =Z100 -> 1086 | D100: lf | E100: 67 | F100: =C100*E100/2000 -> 36.381 | G100: ton | I100: =ROUND(F100*H100,0) -> 0 | W100: 181 | X100: W08X67 | Y100: 0" | Z100: 1086 | AA100: LF
B101: =X101 -> W10X15 | C101: =Z101 -> 440 | D101: lf | E101: 15 | F101: =C101*E101/2000 -> 3.3 | G101: ton | I101: =ROUND(F101*H101,0) -> 0 | W101: 175 | X101: W10X15 | Y101: 0" | Z101: 440 | AA101: LF
B102: =X102 -> W10X54 | C102: =Z102 -> 93 | D102: lf | E102: 54 | F102: =C102*E102/2000 -> 2.511 | G102: ton | I102: =ROUND(F102*H102,0) -> 0 | X102: W10X54 | Y102: 0" | Z102: 93 | AA102: LF | AB102: 7 | AC102: EA
B103: =X103 -> W12X16 | C103: =Z103 -> 348 | D103: lf | E103: 16 | F103: =C103*E103/2000 -> 2.784 | G103: ton | I103: =ROUND(F103*H103,0) -> 0 | W103: 160 | X103: W12X16 | Y103: 0" | Z103: 348 | AA103: LF
B104: =X104 -> W12X22 | C104: =Z104 -> 521 | D104: lf | E104: 22 | F104: =C104*E104/2000 -> 5.731 | G104: ton | I104: =ROUND(F104*H104,0) -> 0 | W104: 162 | X104: W12X22 | Y104: 0" | Z104: 521 | AA104: LF
...

Sheet 05 52 Railings
G1: Hedrick Plug
F2: X | G2: Excluded
F3: I | G3: Included
B4: BACK TO SUMMARY SHEET | G4: Sub Add/Deduct
A5: Project: | B5: ='Area Calculations'!B4 -> Atlantic Fields Club Core / Dock Bar / Spa Pods / Water Features | G5: Company | H5: JC Iron Ornamental
A6: Trade: | B6: Handrails & Railings | G6: Contact
A7: CSI Code: | B7: 05 52 00 | G7: Phone
A8: Date: | G8: Email
G9: Adjusted Bid | H9: =I$55 -> 138000 | J9: =K$55 -> 0 | L9: =M$55 -> 0 | N9: =O$55 -> 0 | P9: =Q$55 -> 0 | R9: =S$55 -> 0
A10: BID DOCUMENTS: | C10: Plan/ Spec. Package | D10: QTY | E10: U/M | F10: Unit Cost | G10: Subtotal | H10: Yes/No | I10: Price | J10: Yes/No | K10: Price | L10: Yes/No | M10: Price | N10: Yes/No | O10: Price | P10: Yes/No | Q10: Price | R10: Yes/No | S10: Price
B11: GENERAL INCLUSIONS
B12: INCLUDES ALL SALES TAX
B13: ALL HOISTING & RIGGING REQUIRED TO COMPLETE THIS SCOPE
B14: PROVIDE P&P BONDS
B15: FLORIDA STATE CONTRACTORS LIC.
B16: GENERAL LIABILITY AND WORKERS COMP. INSURANCE LIMITS
B17: STATE AND LOCAL TAXES
B18: SPECIFIC TRADE SCOPE OF WORK REQUIREMENTS
B19: BASE BID
B21: Club Core | I21: =SUBTOTAL(9,I22:I26) -> 0 | K21: =SUBTOTAL(9,K22:K26) -> 0 | M21: =SUBTOTAL(9,M22:M26) -> 0 | O21: =SUBTOTAL(9,O22:O26) -> 0 | Q21: =SUBTOTAL(9,Q22:Q26) -> 0 | S21: =SUBTOTAL(9,S22:S26) -> 0
B22: Metal guardrail w/ SS cabling | G22: =ROUND(D22*F22,0) -> 0
B23: Wellness Level 2 - Exterior Terrace - 3'-6" - included as glass - see 08 50 | C23: 06/A8.16 | D23: 33 | E23: lf | G23: =ROUND(D23*F23,0) -> 0
G24: =ROUND(D24*F24,0) -> 0
G25: =ROUND(D25*F25,0) -> 0
G26: =ROUND(D26*F26,0) -> 0
B27: Dock Bar | G27: =ROUND(D27*F27,0) -> 0 | I27: =SUBTOTAL(9,I28:I31) -> 138000 | K27: =SUBTOTAL(9,K28:K31) -> 0 | M27: =SUBTOTAL(9,M28:M31) -> 0 | O27: =SUBTOTAL(9,O28:O31) -> 0 | Q27: =SUBTOTAL(9,Q28:Q31) -> 0 | S27: =SUBTOTAL(9,S28:S31) -> 0
B28: Metal guardrail w/ SS cabling | C28: A8.01 | D28: 456 | E28: lf | F28: 300 | G28: =ROUND(D28*F28,0) -> 136800 | I28: 138000
G29: =ROUND(D29*F29,0) -> 0
G30: =ROUND(D30*F30,0) -> 0
G31: =ROUND(D31*F31,0) -> 0
B32: Spa Pods - NA | G32: =ROUND(D32*F32,0) -> 0 | I32: =SUBTOTAL(9,I33:I35) -> 0 | K32: =SUBTOTAL(9,K33:K35) -> 0 | M32: =SUBTOTAL(9,M33:M35) -> 0 | O32: =SUBTOTAL(9,O33:O35) -> 0 | Q32: =SUBTOTAL(9,Q33:Q35) -> 0 | S32: =SUBTOTAL(9,S33:S35) -> 0
G33: =ROUND(D33*F33,0) -> 0
G34: =ROUND(D34*F34,0) -> 0
G35: =ROUND(D35*F35,0) -> 0
B36: Hardscape | G36: =ROUND(D36*F36,0) -> 0 | I36: =SUBTOTAL(9,I37:I50) -> 0 | K36: =SUBTOTAL(9,K37:K50) -> 0 | M36: =SUBTOTAL(9,M37:M50) -> 0 | O36: =SUBTOTAL(9,O37:O50) -> 0 | Q36: =SUBTOTAL(9,Q37:Q50) -> 0 | S36: =SUBTOTAL(9,S37:S50) -> 0
B37: Hand Rail - See 32 31 Fence & Gates | G37: =ROUND(D37*F37,0) -> 0
G38: =ROUND(D38*F38,0) -> 0
G39: =ROUND(D39*F39,0) -> 0
G40: =ROUND(D40*F40,0) -> 0
G41: =ROUND(D41*F41,0) -> 0
G42: =ROUND(D42*F42,0) -> 0
G43: =ROUND(D43*F43,0) -> 0
G44: =ROUND(D44*F44,0) -> 0
G45: =ROUND(D45*F45,0) -> 0
G46: =ROUND(D46*F46,0) -> 0
G47: =ROUND(D47*F47,0) -> 0
G48: =ROUND(D48*F48,0) -> 0
G49: =ROUND(D49*F49,0) -> 0
B51: SUBTOTAL Base Bid | G51: =SUBTOTAL(9,G22:G50) -> 136800 | I51: =SUBTOTAL(9,I22:I50) -> 138000 | K51: =SUM(K19:K50) -> 0 | M51: =SUM(M19:M50) -> 0 | O51: =SUM(O19:O50) -> 0 | Q51: =SUM(Q19:Q50) -> 0 | S51: =SUM(S19:S50) -> 0
B52: BOND RATE | H52: 0 | J52: 0 | L52: 0 | N52: 0 | P52: 0 | R52: 0
B53: BOND AMOUNT | G53: =F52*G51 -> 0 | I53: =H52*I51 -> 0 | K53: =J52*K51 -> 0 | M53: =L52*M51 -> 0 | O53: =N52*O51 -> 0 | Q53: =P52*Q51 -> 0 | S53: =R52*S51 -> 0
B55: ADJUSTED TOTAL | G55: =SUM(G51:G53) -> 136800 | I55: =SUM(I51:I53) -> 138000 | K55: =SUM(K51:K53) -> 0 | M55: =SUM(M51:M53) -> 0 | O55: =SUM(O51:O53) -> 0 | Q55: =SUM(Q51:Q53) -> 0 | S55: =SUM(S51:S53) -> 0
B56: Cost per SF | G56: =G55/'Area Calculations'!$F$5 -> 1.5427643 | I56: =I55/'Area Calculations'!$F$5 -> 1.5562974 | K56: =K55/'Area Calculations'!$F$5 -> 0 | M56: =M55/'Area Calculations'!$F$5 -> 0 | O56: =O55/'Area Calculations'!$F$5 -> 0 | Q56: =Q55/'Area Calculations'!$F$5 -> 0 | S56: =S55/'Area Calculations'!$F$5 -> 0
A58: QUALIFICATIONS
A62: EXCLUSIONS/OWNER PROVIDED ITEMS:
A66: ALTERNATES:
A70: PROPOSED VE (Provide Clear Description):
A74: FULLY LOADED LABOR RATES
B75: Laborer
B76: Mechanic
B77: Superintendent
B78: Project Manager
A80: SCHEDULE
B81: Prepared shop drawings/submittals
B82: Mobilization
B83: Total duration to complete scope of work
A85: Winner
A86: Company
A87: Contact
A88: Phone
A89: Email
A90: Base Bid | B90: =$I$55 -> 138000
B92: Need Prequalification
B93: Prequalified

Sheet 05 70 Arch Metals
G1: Hedrick Plug
F2: X | G2: Excluded
F3: I | G3: Included
B4: BACK TO SUMMARY SHEET | G4: Sub Add/Deduct
A5: Project: | B5: ='Area Calculations'!B4 -> Atlantic Fields Club Core / Dock Bar / Spa Pods / Water Features | G5: Company | H5: VM Iron Works
A6: Trade: | B6: Interior & Exterior Architectural Metals | G6: Contact | H6: Johnny Lorusso
A7: CSI Code: | B7: 05 70 00 | G7: Phone | H7: (772) 781-0318
A8: Date: | G8: Email | H8: johnny@vmironwork.com
G9: Adjusted Bid | H9: =I$77 -> 1358334 | J9: =K$85 -> 0 | L9: =M$85 -> 0 | N9: =O$85 -> 0 | P9: =Q$85 -> 0 | R9: =S$85 -> 0
A10: BID DOCUMENTS: | C10: Plan/ Spec. Package | D10: QTY | E10: U/M | F10: Unit Cost | G10: Subtotal | H10: Yes/No | I10: Price | J10: Yes/No | K10: Price | L10: Yes/No | M10: Price | N10: Yes/No | O10: Price | P10: Yes/No | Q10: Price | R10: Yes/No | S10: Price
B11: GENERAL INCLUSIONS
B12: INCLUDES ALL SALES TAX
B13: ALL HOISTING & RIGGING REQUIRED TO COMPLETE THIS SCOPE
B14: PROVIDE P&P BONDS
B15: FLORIDA STATE CONTRACTORS LIC.
B16: GENERAL LIABILITY AND WORKERS COMP. INSURANCE LIMITS
B17: STATE AND LOCAL TAXES
B18: SPECIFIC TRADE SCOPE OF WORK REQUIREMENTS
B19: BASE BID
B21: Club Core | I21: =SUBTOTAL(9,I22:I61) -> 1247804 | K21: =SUBTOTAL(9,K22:K61) -> 0 | M21: =SUBTOTAL(9,M22:M61) -> 0 | O21: =SUBTOTAL(9,O22:O61) -> 0 | Q21: =SUBTOTAL(9,Q22:Q61) -> 0 | S21: =SUBTOTAL(9,S22:S61) -> 0
B22: Ribbon Canopy | G22: =ROUND(D22*F22,0) -> 0
A23: Allowance | B23: Ribbon Canopy - Decorative steel angle w/ high performance finish - not enough detail | C23: 3/A4.20 | D23: 1086 | E23: sf | F23: 30 | G23: =ROUND(D23*F23,0) -> 32580 | I23: =$G23 -> 32580
G24: =ROUND(D24*F24,0) -> 0
A25: Allowance | B25: Club Core - Exterior metal plate cladding - MT-01 - not enough detail | D25: =SUM(D26:D40) -> 5762 | E25: sf | F25: 50 | G25: =ROUND(D25*F25,0) -> 288100 | I25: =$G25 -> 288100
B26: Dining - North Elevation - MT-01 Plate - parapet & facia | C26: 1/A3.00 | D26: =245+147 -> 392 | E26: sf | G26: =ROUND(D26*F26,0) -> 0
B27: Dining - East Mech Yard Elevation - MT-01 Plate - parapet & facia | C27: 1/A3.00 | D27: 327 | E27: sf | G27: =ROUND(D27*F27,0) -> 0
B28: Dining - East Elevation - MT-01 Plate - parapet & facia | C28: 1/A3.00 | D28: =336+402 -> 738 | E28: sf | G28: =ROUND(D28*F28,0) -> 0
B29: Dining - West Elevation - MT-01 Plate - parapet & facia | C29: 1/A3.01 | D29: =340+401 -> 741 | E29: sf | G29: =ROUND(D29*F29,0) -> 0
B30: Dining - South Elevation - MT-01 Plate - parapet & facia | C30: 2/A3.01 | D30: =260+104 -> 364 | E30: sf | G30: =ROUND(D30*F30,0) -> 0
B31: Fitness-North Elevation - MT-01 Flashing - above windows | C31: 1/A3.02 | D31: 24 | E31: sf | G31: =ROUND(D31*F31,0) -> 0
B32: Fitness-North Elevation - MT-01 Plate - parapet | C32: 1/A3.02 | D32: 296 | E32: sf | G32: =ROUND(D32*F32,0) -> 0
B33: Fitness-East Elevation - MT-01 Plate - parapet | C33: 2/A3.02 | D33: 192 | E33: sf | G33: =ROUND(D33*F33,0) -> 0
B34: Fitness-South Elevation - MT-01 Plate - parapet | C34: 1/A3.03 | D34: 347 | E34: sf | G34: =ROUND(D34*F34,0) -> 0
B35: Fitness-West Elevation - MT-01 Flashing - above windows | C35: 2/A3.03 | D35: 30 | E35: sf | G35: =ROUND(D35*F35,0) -> 0
B36: Fitness-West Elevation - MT-01 Plate - parapet | C36: 2/A3.03 | D36: 117 | E36: sf | G36: =ROUND(D36*F36,0) -> 0
B37: Wellness-North Elevation - MT-01 Plate - parapet | C37: 1/A3.04 | D37: =390+25+53 -> 468 | E37: sf | G37: =ROUND(D37*F37,0) -> 0
B38: Wellness-West Elevation - MT-01 Plate - parapet | C38: 2/A3.04 | D38: =227+274 -> 501 | E38: sf | G38: =ROUND(D38*F38,0) -> 0
B39: Wellness-South Elevation - MT-01 Plate - parapet | C39: 1/A3.05 | D39: =362+406 -> 768 | E39: sf | G39: =ROUND(D39*F39,0) -> 0
B40: Wellness-West Elevation - MT-01 Plate - parapet | C40: 2/A3.05 | D40: =290+167 -> 457 | E40: sf | G40: =ROUND(D40*F40,0) -> 0
G41: =ROUND(D41*F41,0) -> 0
A42: Allowance | B42: Club Core - Exterior metal plate cladding at planters - MT-01 & MT-04 - not enough detail | D42: =SUM(D43:D52) -> 3095.17 | E42: sf | F42: 50 | G42: =ROUND(D42*F42,0) -> 154759 | I42: =$G42 -> 154759
B43: Dining Level 1 | G43: =ROUND(D43*F43,0) -> 0
B44: MT-04 Plate - planter | C44: 4/A8.11, /A4.01, A2.20 outside | D44: 85 | E44: sf | G44: =ROUND(D44*F44,0) -> 0
B45: MT-04 Plate - planter | C45: 4/A8.11, /A4.01, A2.20 inside | D45: 79 | E45: sf | G45: =ROUND(D45*F45,0) -> 0
B46: MT-04 Plate - base - 4" | C46: 4/A8.11, /A4.01, A2.20 | D46: =49*0.33 -> 16.17 | E46: sf | G46: =ROUND(D46*F46,0) -> 0
B47: Dining Level 2 | G47: =ROUND(D47*F47,0) -> 0
A48: =2.75+0.56 -> 3.31 | B48: MT-01 Plate - planter | C48: 2/8.11, 2/A4.00, A2.30 | D48: 743 | E48: sf | G48: =ROUND(D48*F48,0) -> 0
A49: =2.75+0.42 -> 3.17 | B49: MT-01 Plate w/ screen sill - planter | C49: 2/8.11, 2/A4.00, A2.30 | D49: 736 | E49: sf | G49: =ROUND(D49*F49,0) -> 0
A50: 3.67 | B50: MT-01 Plate - planter (wrapped) | C50: 2/A4.03, A2.30 | D50: 250 | E50: sf | G50: =ROUND(D50*F50,0) -> 0
B51: Wellness Level 2 | G51: =ROUND(D51*F51,0) -> 0
A52: 2.67 | B52: MT-01 Plate - planter (wrapped) | C52: 2/A8.16, A/4.10, A2.31 | D52: 1186 | E52: sf | G52: =ROUND(D52*F52,0) -> 0
B53: MT-01 Chanel Vertical C12X3 | C53: 7/A8.03, A2.21.5, A2.21 | E53: lf | G53: =ROUND(D53*F53,0) -> 0
G54: =ROUND(D54*F54,0) -> 0
A55: Allowance | B55: Club Core - Misc metal plate trim - not enough detail | D55: =SUM(D56:D57) -> 298.2 | E55: sf | F55: 75 | G55: =ROUND(D55*F55,0) -> 22365 | I55: =$G55 -> 22365
A56: 6 | B56: door jamb at bug screens | C56: 3/A8.00 | D56: =A56*15*(1+1+0.25+0.25) -> 225 | E56: sf | G56: =ROUND(D56*F56,0) -> 0
A57: 4 | B57: window jamb st reveal | C57: 6/A8.0 | D57: =A57*15*(0.33+0.33+0.56) -> 73.2 | E57: sf | G57: =ROUND(D57*F57,0) -> 0
G58: =ROUND(D58*F58,0) -> 0 | I58: VMI
B59: Dining Circular Stair | C59: A.7.00, A-7.01, A-7.02 | D59: 1 | E59: ls | F59: 750000 | G59: =ROUND(D59*F59,0) -> 750000 | I59: =G59 -> 750000
G60: =ROUND(D60*F60,0) -> 0
B61: Dock Bar | G61: =ROUND(D61*F61,0) -> 0 | I61: =SUBTOTAL(9,I62:I68) -> 47180 | K61: =SUBTOTAL(9,K62:K70) -> 0 | M61: =SUBTOTAL(9,M62:M70) -> 0 | O61: =SUBTOTAL(9,O62:O70) -> 0 | Q61: =SUBTOTAL(9,Q62:Q70) -> 0 | S61: =SUBTOTAL(9,S62:S70) -> 0
A62: Allowance | B62: Dock Bar - MT--05 misc metal plate trim - not enough detail | D62: =SUM(D63:D66) -> 629.0722 | E62: sf | F62: 75 | G62: =ROUND(D62*F62,0) -> 47180 | I62: =$G62 -> 47180
B63: MT-?? steel plate at roof edge - 24" | C63: 1/A4.00 | D63: =255*2 -> 510 | E63: sf | G63: =ROUND(D63*F63,0) -> 0
A64: 11.17 | B64: MT-05 steel plate - at bug screens - 12" & 12" - x 2 | C64: 3/A8.00 | D64: =2*A64*2 -> 44.68 | E64: sf | G64: =ROUND(D64*F64,0) -> 0
A65: 11.17 | B65: MT-05 steel plate - at bug screens - 12" - x 2 | C65: 4/A8.00 | D65: =1*A65*2 -> 22.34 | E65: sf | G65: =ROUND(D65*F65,0) -> 0
A66: 11.17 | B66: MT-05 steel plate - at bug screens - 12" & 10" & 3" & 3" - x2 | C66: 4/A8.00 | D66: =2.33*A66*2 -> 52.0522 | E66: sf | G66: =ROUND(D66*F66,0) -> 0
G67: =ROUND(D67*F67,0) -> 0
B68: Spa Pods | G68: =ROUND(D68*F68,0) -> 0 | I68: =SUBTOTAL(9,I69:I72) -> 63350 | K68: =SUBTOTAL(9,K69:K72) -> 0 | M68: =SUBTOTAL(9,M69:M72) -> 0 | O68: =SUBTOTAL(9,O69:O72) -> 0 | Q68: =SUBTOTAL(9,Q69:Q72) -> 0 | S68: =SUBTOTAL(9,S69:S72) -> 0
A69: Allowance | B69: Spa Pods - MT--05 misc metal plate trim - not enough detail | G69: =SUM(G70:G71) -> 63350 | I69: =$G69 -> 63350
B70: MT-?? Steel angle at roof edge - 8" x 8" x ?" | C70: 3/A8.01 | D70: 630 | E70: lf | F70: 80 | G70: =ROUND(D70*F70,0) -> 50400
B71: MT-?? Steel WT - top & botoom screen wall 5" x 4" x ?" | C71: A8.10 | D71: 185 | E71: lf | F71: 70 | G71: =ROUND(D71*F71,0) -> 12950
B73: SUBTOTAL Base Bid | G73: =SUBTOTAL(9,G22:G72) -> 1421684 | I73: =SUBTOTAL(9,I21:I72) -> 1358334 | K73: =SUM(K19:K72) -> 0 | M73: =SUM(M19:M72) -> 0 | O73: =SUM(O19:O72) -> 0 | Q73: =SUM(Q19:Q72) -> 0 | S73: =SUM(S19:S72) -> 0
B74: BOND RATE | H74: 0 | J74: 0 | L74: 0 | N74: 0 | P74: 0 | R74: 0
B75: BOND AMOUNT | G75: =F74*G73 -> 0 | I75: =H74*I73 -> 0 | K75: =J74*K73 -> 0 | M75: =L74*M73 -> 0 | O75: =N74*O73 -> 0 | Q75: =P74*Q73 -> 0 | S75: =R74*S73 -> 0
B77: ADJUSTED TOTAL | G77: =SUM(G73:G75) -> 1421684 | I77: =SUM(I73:I75) -> 1358334 | K77: =SUM(K73:K75) -> 0 | M77: =SUM(M73:M75) -> 0 | O77: =SUM(O73:O75) -> 0 | Q77: =SUM(Q73:Q75) -> 0 | S77: =SUM(S73:S75) -> 0
B78: Cost per SF | G78: =G77/'Area Calculations'!$F$5 -> 16.033066 | I78: =I77/'Area Calculations'!$F$5 -> 15.318635 | K78: =K77/'Area Calculations'!$F$5 -> 0 | M78: =M77/'Area Calculations'!$F$5 -> 0 | O78: =O77/'Area Calculations'!$F$5 -> 0 | Q78: =Q77/'Area Calculations'!$F$5 -> 0 | S78: =S77/'Area Calculations'!$F$5 -> 0
A80: QUALIFICATIONS
A84: EXCLUSIONS/OWNER PROVIDED ITEMS:
A88: ALTERNATES:
A92: PROPOSED VE (Provide Clear Description):
A96: FULLY LOADED LABOR RATES
B97: Laborer
B98: Mechanic
B99: Superintendent
B100: Project Manager
A102: SCHEDULE
B103: Prepared shop drawings/submittals
B104: Mobilization
B105: Total duration to complete scope of work
A107: Winner
A108: Company
A109: Contact
A110: Phone
A111: Email
A112: Base Bid | B112: =$I$77 -> 1358334
B114: Need Prequalification
B115: Prequalified

Sheet 06 10 Rough Carpentry
G1: Hedrick Plug
F2: X | G2: Excluded
F3: I | G3: Included
B4: BACK TO SUMMARY SHEET | G4: Sub Add/Deduct
A5: Project: | B5: ='Area Calculations'!B4 -> Atlantic Fields Club Core / Dock Bar / Spa Pods / Water Features | G5: Company
A6: Trade: | B6: Rough Carpentry | G6: Contact
A7: CSI Code: | B7: 06 10 00 | G7: Phone
A8: Date: | G8: Email
G9: Adjusted Bid | H9: =I$84 -> 293252.92 | J9: =K$84 -> 146663.14 | L9: =M$84 -> 0 | N9: =O$84 -> 0 | P9: =Q$84 -> 0 | R9: =S$84 -> 0
A10: BID DOCUMENTS: | C10: Plan/ Spec. Package | D10: QTY | E10: U/M | F10: Unit Cost | G10: Subtotal | H10: Yes/No | I10: Price | J10: Yes/No | K10: Price | L10: Yes/No | M10: Price | N10: Yes/No | O10: Price | P10: Yes/No | Q10: Price | R10: Yes/No | S10: Price
B11: GENERAL INCLUSIONS
B12: INCLUDES ALL SALES TAX
B13: ALL HOISTING & RIGGING REQUIRED TO COMPLETE THIS SCOPE
B14: PROVIDE P&P BONDS
B15: FLORIDA STATE CONTRACTORS LIC.
B16: GENERAL LIABILITY AND WORKERS COMP. INSURANCE LIMITS
B17: STATE AND LOCAL TAXES
B18: SPECIFIC TRADE SCOPE OF WORK REQUIREMENTS
B19: BASE BID
B21: Club Core | G21: =SUBTOTAL(9,G22:G219) -> 527494.97 | I21: =SUBTOTAL(9,I22:I48) -> 109293 | K21: =SUBTOTAL(9,K22:K48) -> 0 | M21: =SUBTOTAL(9,M22:M48) -> 0 | O21: =SUBTOTAL(9,O22:O48) -> 0 | Q21: =SUBTOTAL(9,Q22:Q48) -> 0 | S21: =SUBTOTAL(9,S22:S48) -> 0
B22: coping cap blocking | G22: =ROUND(D22*F22,0) -> 0 | I22: =G22 -> 0
B23: Dining lower roof parapet - 2x12 | C23: 2/A4.01 & 7/A2.50 | D23: 128 | E23: lf | F23: 6.5 | G23: =ROUND(D23*F23,0) -> 832 | I23: =G23 -> 832
B24: Dining upper roof parapet - 2x12 | C24: 2/A3.10 | D24: 441 | E24: lf | F24: 6.5 | G24: =ROUND(D24*F24,0) -> 2867 | I24: =G24 -> 2867
B25: Fitness lower roof parapet - 2x12 | C25: 2/A3.11 & 3/A4.06 | D25: 160 | E25: lf | F25: 6.5 | G25: =ROUND(D25*F25,0) -> 1040 | I25: =G25 -> 1040
B26: Fitness upper roof parapet - 2x12 | C26: 2/A3.11 & 3/A4.06 | D26: 400 | E26: lf | F26: 6.5 | G26: =ROUND(D26*F26,0) -> 2600 | I26: =G26 -> 2600
B27: Wellness upper roof parapet - 2x12 | C27: A2.44 & 1/A3.13 | D27: 542 | E27: lf | F27: 6.5 | G27: =ROUND(D27*F27,0) -> 3523 | I27: =G27 -> 3523
G28: =ROUND(D28*F28,0) -> 0 | I28: =G28 -> 0
B29: roof edge blocking | G29: =ROUND(D29*F29,0) -> 0 | I29: =G29 -> 0
B30: Dining high & low overhang edge - 2- 2x6 | C30: 1 & 2/A2.50 | D30: =1058*2 -> 2116 | E30: lf | F30: 5 | G30: =ROUND(D30*F30,0) -> 10580 | I30: =G30 -> 10580
B31: Dining high & low overhang edge - 1/2" ext sheathing - 4" strip | C31: 1 & 2/A2.50 | D31: =1058*0.33 -> 349.14 | E31: sf | F31: 10 | G31: =ROUND(D31*F31,0) -> 3491 | I31: =G31 -> 3491
B32: Dining upper roof edge - 2 - 2x6 | C32: 1/A4.01 & 3/A2.50 | D32: =2*261 -> 522 | E32: lf | F32: 5 | G32: =ROUND(D32*F32,0) -> 2610 | I32: =G32 -> 2610
B33: Fitness overhang edge - 2- 2x6 | C33: 1&3/A4.06 | D33: =412*2 -> 824 | E33: lf | F33: 5 | G33: =ROUND(D33*F33,0) -> 4120 | I33: =G33 -> 4120
B34: Wellness low overhang edge | C34: A2.43 & A3.13 | D34: 330 | E34: lf | F34: 5 | G34: =ROUND(D34*F34,0) -> 1650 | I34: =G34 -> 1650
B35: Wellness low roof edge - 2 - 2x6 | C35: 1/A4.01 & 3/A2.50 | D35: =462*2 -> 924 | E35: lf | F35: 5 | G35: =ROUND(D35*F35,0) -> 4620 | I35: =G35 -> 4620
B36: Fitness upper overhang edge - 2- 2x6 | C36: A2.44 & 1/A3.13 | D36: =2*600 -> 1200 | E36: lf | F36: 5 | G36: =ROUND(D36*F36,0) -> 6000 | I36: =G36 -> 6000
B37: misc 2x blocking at roof edge | D37: 4000 | E37: lf | F37: 5 | G37: =ROUND(D37*F37,0) -> 20000 | I37: =G37 -> 20000
G38: =ROUND(D38*F38,0) -> 0 | I38: =G38 -> 0
B39: Raised platform at Restaurant D-112 | C39: 1/A4.03 | D39: 363 | E39: sf | F39: 10 | G39: =ROUND(D39*F39,0) -> 3630 | I39: =G39 -> 3630
B40: Step at Dining Room - D-102 | C40: 2/A4.03 | D40: 5 | E40: lf | F40: 10 | G40: =ROUND(D40*F40,0) -> 50 | I40: =G40 -> 50
B41: Step/platform at Dining Room - D-102 | C41: A/2.20 | D41: 112 | E41: sf | F41: 10 | G41: =ROUND(D41*F41,0) -> 1120 | I41: =G41 -> 1120
A42: 18 | B42: Blocking in typ columns at insect screens - 4 - 2x8 | C42: 4/A8.00 | D42: =18*4*15 -> 1080 | E42: lf | F42: 5.5 | G42: =ROUND(D42*F42,0) -> 5940 | I42: =G42 -> 5940
A43: 14 | B43: Blocking in corner columns at insect screens - 4- 2x8 | C43: 1/A8.00 | D43: =14*4*15 -> 840 | E43: lf | F43: 5.5 | G43: =ROUND(D43*F43,0) -> 4620 | I43: =G43 -> 4620
G44: =ROUND(D44*F44,0) -> 0 | I44: =G44 -> 0
B45: misc 2x blocking at exterior details | D45: 1 | E45: ls | F45: 15000 | G45: =ROUND(D45*F45,0) -> 15000 | I45: =G45 -> 15000
G46: =ROUND(D46*F46,0) -> 0 | I46: =G46 -> 0
B47: Safety Railings | D47: 1 | E47: ls | F47: 15000 | G47: =ROUND(D47*F47,0) -> 15000 | I47: =G47 -> 15000
G48: =ROUND(D48*F48,0) -> 0 | I48: =G48 -> 0
B49: Dock Bar | G49: =ROUND(D49*F49,0) -> 0 | I49: =SUBTOTAL(9,I50:I57) -> 42397 | K49: =SUBTOTAL(9,K50:K57) -> 0 | M49: =SUBTOTAL(9,M50:M57) -> 0 | O49: =SUBTOTAL(9,O50:O57) -> 0 | Q49: =SUBTOTAL(9,Q50:Q57) -> 0 | S49: =SUBTOTAL(9,S50:S57) -> 0
A50: 2 | B50: Column base at door - 2x4 | C50: 4/A8.00 | D50: =A50*10.25 -> 20.5 | E50: lf | F50: 5.5 | G50: =ROUND(D50*F50,0) -> 113 | I50: =G50 -> 113
A51: 2 | B51: Column base at door - 2 - 2x8 | C51: 4/A8.00 | D51: =A51*10.25*2 -> 41 | E51: lf | F51: 5.5 | G51: =ROUND(D51*F51,0) -> 226 | I51: =G51 -> 226
A52: 2 | B52: Column base corner - 5 - 2x8 | C52: 3/A8.00 | D52: =A52*10.25*5 -> 102.5 | E52: lf | F52: 5.5 | G52: =ROUND(D52*F52,0) -> 564 | I52: =G52 -> 564
A53: 4 | B53: Column base straight - 2 - 2x8 | C53: 2/A8.00 | D53: =A53*10.25*2 -> 82 | E53: lf | F53: 5.5 | G53: =ROUND(D53*F53,0) -> 451 | I53: =G53 -> 451
A54: 2 | B54: Base bug screen - 2x6 | C54: 1/A8.00 | D54: =A54*10.25 -> 20.5 | E54: lf | F54: 5.5 | G54: =ROUND(D54*F54,0) -> 113 | I54: =G54 -> 113
B55: 1/2" plywood roof deck sheathing | C55: 2/A2.05 | D55: 4093 | E55: sf | F55: 10 | G55: =ROUND(D55*F55,0) -> 40930 | I55: =$G55 -> 40930
B56: 1/2" plywood ceiling sheathing - see drywall | C56: 2/A2.05 | D56: 4093 | E56: sf | F56: 10 | I56: =G56 -> 0
G57: =ROUND(D57*F57,0) -> 0 | I57: =G57 -> 0
B58: Spa Pods | G58: =ROUND(D58*F58,0) -> 0 | I58: =SUBTOTAL(9,I59:I79) -> 141562.92 | K58: =SUBTOTAL(9,K59:K79) -> 146663.14 | M58: =SUBTOTAL(9,M59:M79) -> 0 | O58: =SUBTOTAL(9,O59:O79) -> 0 | Q58: =SUBTOTAL(9,Q59:Q79) -> 0 | S58: =SUBTOTAL(9,S59:S79) -> 0
G59: =ROUND(D59*F59,0) -> 0 | I59: =G59 -> 0
B60: wood trusses supply | G60: =ROUND(D60*F60,0) -> 0 | I60: A-1 Industries | K60: Universal
B61: BOH & Comfort Station | D61: 858 | E61: sf | G61: =ROUND(D61*F61,0) -> 0 | I61: 3796.01 | K61: 5643.62
B62: Massage Treatment Pavilion | D62: 1906 | E62: sf | G62: =ROUND(D62*F62,0) -> 0 | I62: 7191.08 | K62: 7783.76
B63: Meditation Pavilion | D63: 471 | E63: sf | G63: =ROUND(D63*F63,0) -> 0 | I63: 1483.63 | K63: 3447.54
B64: Double Treatment Pavilion | D64: 1163 | E64: sf | G64: =ROUND(D64*F64,0) -> 0 | I64: 5814.29 | K64: 6146.06
B65: Double Treatment Pavilion ADA | D65: 1163 | E65: sf | G65: =ROUND(D65*F65,0) -> 0 | I65: 6566.05 | K65: 6111.08
B66: Single Treatment Pavilion | D66: 893 | E66: sf | G66: =ROUND(D66*F66,0) -> 0 | I66: 4655.86 | K66: 5475.08
B67: rough carpentry | G67: =ROUND(D67*F67,0) -> 0
B68: WD Column - 6" x 6" x 9'-0" | D68: 20 | E68: ea | F68: 250 | G68: =ROUND(D68*F68,0) -> 5000 | I68: =$G68 -> 5000 | K68: =$G68 -> 5000
B69: WD beam - LVL - 5.25x16 | D69: 19 | E69: lf | F69: 200 | G69: =ROUND(D69*F69,0) -> 3800 | I69: =$G69 -> 3800 | K69: =$G69 -> 3800
B70: WD beam - 4x8 | D70: 40 | E70: lf | F70: 200 | G70: =ROUND(D70*F70,0) -> 8000 | I70: =$G70 -> 8000 | K70: =$G70 -> 8000
B71: set wood trusses | D71: 5292 | E71: sf | F71: 6 | G71: =ROUND(D71*F71,0) -> 31752 | I71: =$G71 -> 31752 | K71: =$G71 -> 31752
B72: 5/8" plywood sheathing | D72: 5292 | E72: sf | F72: 12 | G72: =ROUND(D72*F72,0) -> 63504 | I72: =$G72 -> 63504 | K72: =$G72 -> 63504
G73: =ROUND(D73*F73,0) -> 0 | I73: =G73 -> 0
G74: =ROUND(D74*F74,0) -> 0 | I74: =G74 -> 0
G75: =ROUND(D75*F75,0) -> 0 | I75: =G75 -> 0
G76: =ROUND(D76*F76,0) -> 0 | I76: =G76 -> 0
G77: =ROUND(D77*F77,0) -> 0 | I77: =G77 -> 0
G78: =ROUND(D78*F78,0) -> 0 | I78: =G78 -> 0
G79: =ROUND(D79*F79,0) -> 0 | I79: =G79 -> 0
B80: SUBTOTAL Base Bid | G80: =SUBTOTAL(9,G21:G79) -> 263746 | I80: =SUBTOTAL(9,I20:I79) -> 293252.92 | K80: =SUBTOTAL(9,K20:K79) -> 146663.14 | M80: =SUBTOTAL(9,M20:M79) -> 0 | O80: =SUBTOTAL(9,O20:O79) -> 0 | Q80: =SUBTOTAL(9,Q20:Q79) -> 0 | S80: =SUBTOTAL(9,S20:S79) -> 0
B81: BOND RATE | H81: 0 | J81: 0 | L81: 0 | N81: 0 | P81: 0 | R81: 0
B82: BOND AMOUNT | G82: =F81*G80 -> 0 | I82: =H81*I80 -> 0 | K82: =J81*K80 -> 0 | M82: =L81*M80 -> 0 | O82: =N81*O80 -> 0 | Q82: =P81*Q80 -> 0 | S82: =R81*S80 -> 0
B84: ADJUSTED TOTAL | G84: =SUM(G80:G82) -> 263746 | I84: =SUM(I80:I82) -> 293252.92 | K84: =SUM(K80:K82) -> 146663.14 | M84: =SUM(M80:M82) -> 0 | O84: =SUM(O80:O82) -> 0 | Q84: =SUM(Q80:Q82) -> 0 | S84: =SUM(S80:S82) -> 0
B85: Cost per SF | G85: =G84/'Area Calculations'!$F$5 -> 2.9744 | I85: =I84/'Area Calculations'!$F$5 -> 3.3071648 | K85: =K84/'Area Calculations'!$F$5 -> 1.6539961 | M85: =M84/'Area Calculations'!$F$5 -> 0 | O85: =O84/'Area Calculations'!$F$5 -> 0 | Q85: =Q84/'Area Calculations'!$F$5 -> 0 | S85: =S84/'Area Calculations'!$F$5 -> 0
A87: QUALIFICATIONS
A91: EXCLUSIONS/OWNER PROVIDED ITEMS:
A95: ALTERNATES:
A99: PROPOSED VE (Provide Clear Description):
A103: FULLY LOADED LABOR RATES
B104: Laborer
B105: Mechanic
B106: Superintendent
B107: Project Manager
A109: SCHEDULE
B110: Prepared shop drawings/submittals
B111: Mobilization
B112: Total duration to complete scope of work
A114: Winner
A115: Company
A116: Contact
A117: Phone
...

Sheet 06 40 Exterior Finish Carpentry
G1: Hedrick Plug
F2: X | G2: Excluded
F3: I | G3: Included
B4: BACK TO SUMMARY SHEET | G4: Sub Add/Deduct
A5: Project: | B5: Atlantic Fields Club Core | G5: Company | H5: Lotspeich Co.
A6: Trade: | B6: Exterior Finish Carpentry | G6: Contact | H6: Ryan Schultz
A7: CSI Code: | B7: 06 40 00 | G7: Phone | H7: (954) 978-2388
A8: Date: | G8: Email | H8: ryan.schultz@lcfinc.com
G9: Adjusted Bid | H9: =I$114 -> 4406552 | J9: =K$114 -> 0 | L9: =M$114 -> 0 | N9: =O$114 -> 0 | P9: =Q$114 -> 0 | R9: =S$114 -> 0
A10: BID DOCUMENTS: | C10: Plan/ Spec. Package | D10: QTY | E10: U/M | F10: Unit Cost | G10: Subtotal | H10: Yes/No | I10: Price | J10: Yes/No | K10: Price | L10: Yes/No | M10: Price | N10: Yes/No | O10: Price | P10: Yes/No | Q10: Price | R10: Yes/No | S10: Price
B11: GENERAL INCLUSIONS
B12: INCLUDES ALL SALES TAX
B13: ALL HOISTING & RIGGING REQUIRED TO COMPLETE THIS SCOPE
B14: PROVIDE P&P BONDS
B15: FLORIDA STATE CONTRACTORS LIC.
B16: GENERAL LIABILITY AND WORKERS COMP. INSURANCE LIMITS
B17: STATE AND LOCAL TAXES
B18: SPECIFIC TRADE SCOPE OF WORK REQUIREMENTS
B19: BASE BID
B21: Club Core | I21: =SUBTOTAL(9,I22:I71) -> 3087156.8 | K21: =SUBTOTAL(9,K22:K71) -> 0 | M21: =SUBTOTAL(9,M22:M71) -> 0 | O21: =SUBTOTAL(9,O22:O71) -> 0 | Q21: =SUBTOTAL(9,Q22:Q71) -> 0 | S21: =SUBTOTAL(9,S22:S71) -> 0
B22: Wood infill at Port Cochere steel columns - 1/A4.23 | G22: =ROUND(D22*F22,0) -> 0
G23: =ROUND(D23*F23,0) -> 0
B24: Dining | G24: =ROUND(D24*F24,0) -> 0
B25: WD-08: Accoya - Cypress T&G 5-1/2", select grade w/ clear coat | C25: A0.60 | G25: =ROUND(D25*F25,0) -> 0 | I25: 494000
B26: soffits | C26: A6.10 / A6.20 / A6.30 | D26: 12490 | E26: sf | G26: =ROUND(D26*F26,0) -> 0
B27: details | C27: A4.00 - A4.03 | G27: =ROUND(D27*F27,0) -> 0
B28: WD-10: Lunawood T&G - Luna Triple 32x140, Luna Thermo-D, Planed | C28: A0.60 | G28: =ROUND(D28*F28,0) -> 0 | I28: 257000
B29: exterior wall cladding - elevations | C29: A3.00 / A3.01 | D29: 4276 | E29: sf | G29: =ROUND(D29*F29,0) -> 0
B30: details | C30: A0.32 - W1 | G30: =ROUND(D30*F30,0) -> 0
B31: infill at steel columns at bug screens - assume 9" wide x 12'-0" tall | C31: 1 & 4/A8.00 | D31: 30 | E31: ea | F31: 600 | G31: =ROUND(D31*F31,0) -> 18000 | I31: =$G31 -> 18000
B32: infill at steel columns at Port Cochere - assume 12" wide x 15'-0" tall | C32: A4.23 | D32: 8 | E32: ea | F32: 900 | G32: =ROUND(D32*F32,0) -> 7200 | I32: =$G32 -> 7200
B33: WD-11: 2x4 Battens - finish to match WD-10 w / Thermowood backing | C33: A0.60 | G33: =ROUND(D33*F33,0) -> 0
A34: Allowance | B34: Club Core Dining - Mechanical Yard Screen. Need WD-11 spec | C34: A2.40 / 2/A4.01 | D34: 970 | E34: sf | F34: 120 | G34: =ROUND(D34*F34,0) -> 116400 | I34: =$G34 -> 116400
B35: WD-XX: ? - WD-08: Accoya - Cypress T&G 5-1/2", select grade w/ clear coat | G35: =ROUND(D35*F35,0) -> 0
A36: Allowance | B36: Club Core Dining - soffit - Port Cochere - Details incomplete | C36: A6.20 | D36: 486 | E36: sf | F36: 45 | G36: =ROUND(D36*F36,0) -> 21870 | I36: =$G36 -> 21870
B37: details | C37: 3/A4.23 | G37: =ROUND(D37*F37,0) -> 0
B38: Fitness | G38: =ROUND(D38*F38,0) -> 0
B39: WD-06: Trellis - Lunawood Batten, Luna SHP 42 x 140 (2 x 6) | C39: A0.60 | G39: =ROUND(D39*F39,0) -> 0
A40: Allowance | B40: Club Core Fitness - WD-06: Trellis - overhang - Details incomplete | C40: A6.21 | D40: =147.33*18 -> 2651.94 | E40: lf | F40: 20 | G40: =ROUND(D40*F40,0) -> 53039 | I40: =$G40 -> 53039
B41: details | C41: 1/A4.07 | G41: =ROUND(D41*F41,0) -> 0
B42: WD-08: Accoya - Cypress T&G 5-1/2", select grade w/ clear coat | C42: A0.60 | G42: =ROUND(D42*F42,0) -> 0 | I42: 199000
B43: soffit perimiter | C43: A6.21 | D43: 3670 | E43: sf | G43: =ROUND(D43*F43,0) -> 0
B44: details | C44: 1&3/A4.06 | G44: =ROUND(D44*F44,0) -> 0
B45: WD-10: Lunawood T&G - Luna Triple 32x140, Luna Thermo-D, Planed | C45: A0.60 | G45: =ROUND(D45*F45,0) -> 0
B46: infill at steel columns at bug screens - assume 9" wide x 12'-0" tall | C46: 1 & 4/A8.00 | D46: 12 | E46: ea | F46: 600 | G46: =ROUND(D46*F46,0) -> 7200 | I46: =$G46 -> 7200
B47: WD-XX: Wood Shingle System | G47: =ROUND(D47*F47,0) -> 0
A48: Allowance | B48: Club Core Fitness - soffit - Port Cochere - No details | C48: 3/A4.23 | D48: 1113 | E48: sf | F48: 50 | G48: =ROUND(D48*F48,0) -> 55650 | I48: =$G48 -> 55650
G49: =ROUND(D49*F49,0) -> 0
B50: Wellness | G50: =ROUND(D50*F50,0) -> 0
B51: WD-06: Trellis - Lunawood Batten, Luna SHP 42 x 140 - 2x4 batten | C51: A0.60 | G51: =ROUND(D51*F51,0) -> 0
A52: Allowance | B52: Wellness WD-06: Trellis - lower roof overhang - Details incomplete | C52: A6.22 / A6.31 | D52: 3840 | E52: lf | F52: 20 | G52: =ROUND(D52*F52,0) -> 76800 | I52: =$G52 -> 76800 | U52: mat | V52: 3840 | W52: lf | X52: 6 | Y52: =V52*X52 -> 23040
A53: Allowance | B53: Wellness WD-06: Trellis - upper roof overhang - Details incomplete | C53: A6.22 / A6.31 | D53: 2136 | E53: lf | F53: 20 | G53: =ROUND(D53*F53,0) -> 42720 | I53: =$G53 -> 42720 | U53: labor | V53: =24*15 -> 360 | W53: pcs | X53: 85 | Y53: =V53*X53 -> 30600
B54: details | C54: A4.08 - A4.13 | G54: =ROUND(D54*F54,0) -> 0 | U54: mat | V54: 2136 | W54: lf | X54: 6 | Y54: =V54*X54 -> 12816
B55: WD-08: Accoya - Cypress T&G 5-1/2", select grade w/ clear coat | C55: A0.60 | G55: =ROUND(D55*F55,0) -> 0 | I55: 364000 | U55: labor | V55: =28*12 -> 336 | W55: pcs | X55: 85 | Y55: =V55*X55 -> 28560
B56: soffit perimiter | C56: A6.22 / A6.31 | D56: 8763 | E56: sf | G56: =ROUND(D56*F56,0) -> 0 | V56: =V52+V54 -> 5976 | W56: lf | X56: =Y56/V56 -> 15.899598 | Y56: =SUM(Y52:Y55) -> 95016
B57: details | C57: A4.08-A4.13 | G57: =ROUND(D57*F57,0) -> 0
B58: WD-10: Lunawood T&G - Luna Triple 32x140, Luna Thermo-D, Planed | C58: A0.60 | G58: =ROUND(D58*F58,0) -> 0 | I58: 292000 | V58: =V54+V52 -> 5976 | W58: lf | X58: =5*1.07 -> 5.35 | Y58: =V58*X58 -> 31971.6
B59: exterior wall cladding - elevations | C59: A3.04 / A3.05 | D59: 3878 | E59: sf | G59: =ROUND(D59*F59,0) -> 0 | V59: ship | Y59: 1500
B60: details | C60: A4.08-A4.13 | G60: =ROUND(D60*F60,0) -> 0 | V60: =V58 -> 5976 | W60: lf | X60: =Y60/V60 -> 5.601004 | Y60: =SUM(Y58:Y59) -> 33471.6
B61: infill at steel columns at bug screens - assume 9" wide x 12'-0" tall | C61: 1 & 4/A8.00 | D61: 10 | E61: ea | F61: 600 | G61: =ROUND(D61*F61,0) -> 6000 | I61: =$G61 -> 6000
G62: =ROUND(D62*F62,0) -> 0 | V62: boom lift | W62: hr | X62: 60
B63: Ribbon Canopy | G63: =ROUND(D63*F63,0) -> 0 | V63: 2 men | W63: hr | X63: 100
B64: WD-08: Wd Soffit - Accoya - Cypress T&G 5-1/2", select grade w/ clear coat | G64: =ROUND(D64*F64,0) -> 0 | X64: =SUM(X62:X63) -> 160
B65: soffit | C65: 2 & 3/A4.20 | D65: 3134 | E65: sf | G65: =ROUND(D65*F65,0) -> 0 | I65: 144000
V66: 15 pcs /8 hours | X66: =8/15 -> 0.53333333 | Y66: pcs / hr
B67: Clear Coat on T&G Cypress | I67: =(I25+I42+I55+I65)*0.35290404040404 -> 423837.75 | X67: =X64*X66 -> 85.333333 | Y67: /pc
A69: Allowance | B69: Fitness Pool Cabanas - No dimensions | G69: =SUM(G70:G71) -> 508440 | I69: =$G69 -> 508440
B70: IPE slats - (12+12+12) x 13.25 x 10 | D70: =36*13.25*10 -> 4770 | E70: ea | F70: 72 | G70: =ROUND(D70*F70,0) -> 343440
B71: steel | D71: 10 | E71: ea | F71: 16500 | G71: =ROUND(D71*F71,0) -> 165000
B73: Dock Bar | I73: =SUBTOTAL(9,I74:I91) -> 611228.58 | K73: =SUBTOTAL(9,K74:K91) -> 0 | M73: =SUBTOTAL(9,M74:M91) -> 0 | O73: =SUBTOTAL(9,O74:O91) -> 0 | Q73: =SUBTOTAL(9,Q74:Q91) -> 0 | S73: =SUBTOTAL(9,S74:S91) -> 0
B74: WD-XX: ? - WD-08: Accoya - Cypress T&G 5-1/2", select grade w/ clear coat | G74: =ROUND(D74*F74,0) -> 0
B75: Ceiling - allow for slope | C75: A6.02 | D75: 2805 | E75: sf | G75: =ROUND(D75*F75,0) -> 0 | I75: 119000
B76: WD-10: Lunawood T&G - Luna Triple 32x140, Luna Thermo-D, Planed | C76: A0.60 (Club C) | G76: =ROUND(D76*F76,0) -> 0
B77: exterior wall cladding - elevations | C77: A3.00 | D77: 1602 | E77: sf | G77: =ROUND(D77*F77,0) -> 0 | I77: 105000
B78: details | C78: A8.00 | G78: =ROUND(D78*F78,0) -> 0
B79: infill at steel columns - assume 10" wide x 10'-3" tall | C79: 2 & 4/A8.00 | D79: 16 | E79: ea | F79: 520 | G79: =ROUND(D79*F79,0) -> 8320 | I79: =$G79 -> 8320
G80: =ROUND(D80*F80,0) -> 0
B81: Clear Coat on T&G Cypress | G81: =ROUND(D81*F81,0) -> 0 | I81: =I75*0.35290404040404 -> 41995.581
I83: Deckmasters
B84: WD-14 IPE decking on 2x sleepers | F84: =I84/3643 -> 71.095251 | I84: 259000
B85: WD-14 - IPE decking - Dock Bar & Patio | D85: 2805 | E85: sf | G85: =ROUND(D85*F85,0) -> 0 | H85: I
B86: WD-14 - IPE decking - pier | D86: 829 | E86: sf | G86: =ROUND(D86*F86,0) -> 0 | H86: I
B87: WD-14 - IPE facia at deck - 14" | C87: 4/A8.01 | D87: 532 | E87: sf | F87: 65 | G87: =ROUND(D87*F87,0) -> 34580 | I87: =$G87 -> 34580
B88: WD-14 - IPE railing cap - 5" | C88: 4/A8.01 | D88: 456 | E88: lf | F88: 65 | G88: =ROUND(D88*F88,0) -> 29640 | I88: =$G88 -> 29640
B89: WD-14 - IPE railing vertical infill - 3' 6 1/2" x 2" | C89: 5/A8.01 | D89: 115 | E89: ea | F89: 65 | G89: =ROUND(D89*F89,0) -> 7475 | I89: =$G89 -> 7475
B90: Temp plywood decking at pier to facilitate decking installation. | D90: =D86 -> 829 | E90: sf | F90: 7.5 | G90: =ROUND(D90*F90,0) -> 6218 | I90: =$G90 -> 6218
G91: =ROUND(D91*F91,0) -> 0
B92: Spa Pods | G92: =ROUND(D92*F92,0) -> 0 | I92: =SUBTOTAL(9,I93:I108) -> 708166.67 | K92: =SUBTOTAL(9,K93:K108) -> 0 | M92: =SUBTOTAL(9,M93:M108) -> 0 | O92: =SUBTOTAL(9,O93:O108) -> 0 | Q92: =SUBTOTAL(9,Q93:Q108) -> 0 | S92: =SUBTOTAL(9,S93:S108) -> 0
B93: WD-08: Accoya - Cypress T&G 5-1/2", select grade w/ clear coat | C93: A0.60 (Club C) | G93: =ROUND(D93*F93,0) -> 0 | I93: 264000
B94: soffit perimiter | C94: A6.02 / A6.03 | D94: 3738 | E94: sf | G94: =ROUND(D94*F94,0) -> 0
B95: Details | C95: A8.01 / A8.02 | G95: =ROUND(D95*F95,0) -> 0
B96: WD-10: Lunawood T&G - Luna Triple 32x140, Luna Thermo-D, Planed | C96: A0.60 (Club C) | G96: =ROUND(D96*F96,0) -> 0 | I96: 267000
B97: exterior wall cladding - elevations | C97: A3.00 / A3.01 | D97: 4833 | E97: sf | G97: =ROUND(D97*F97,0) -> 0
B98: details | C98: A8.01 / A8.02 | G98: =ROUND(D98*F98,0) -> 0
B99: WD-11: ? - Lunawood Batten, Luna SHP 42 x 140 - 2x4 batten | G99: =ROUND(D99*F99,0) -> 0
B100: slat wall - 9'6" tall | C100: A8.10 | D100: 1740 | E100: sf | G100: =ROUND(D100*F100,0) -> 0 | I100: 84000
D101: =D100/9.5 -> 183.15789 | E101: lf | G101: =ROUND(D101*F101,0) -> 0
B102: Clear Coat on T&G Cypress | G102: =ROUND(D102*F102,0) -> 0 | I102: =I93*0.35290404040404 -> 93166.667
G103: =ROUND(D103*F103,0) -> 0
B104: total Cypress | D104: =D26+D36+D43+D48+D56+D65+D75+D94 -> 36199 | E104: sf | F104: =1584000/D104 -> 43.758115
...

Sheet 06 50 Millwork
G1: Hedrick Plug
B2: PAGE 56 COMPLETE | F2: X | G2: Excluded
F3: I | G3: Included
B4: BACK TO SUMMARY SHEET | G4: Sub Add/Deduct
A5: Project: | B5: ='Area Calculations'!B4 -> Atlantic Fields Club Core / Dock Bar / Spa Pods / Water Features | G5: Company | H5: Beaubois | J5: J2 Cabs | L5: Mortensen | N5: Premier Arch. | P5: Baron Manufacturing | R5: District 95 | T5: JRA Marble | V5: Martinez Otero
A6: Trade: | B6: Millwork | G6: Contact | H6: Iain Paterson | J6: Keven Nelson | L6: Michael Bliss | N6: Paul Hays | P6: Neil Gavan | R6: Franklin Herrera | T6: Juan | V6: Steven Pipes
A7: CSI Code: | B7: 06 50 00 | G7: Phone | H7: 561-436-1356 | J7: 352-629-1700 | L7: 954-822-0447 | N7: 331-234-0977 | P7: 954-590-3800 | R7: 754-204-4703 | T7: 646-841-7227 | V7: 646-853-1206
A8: Date: | G8: Email | H8: iain.paterson@beaubois.com | J8: keven@j2cabinetryandtrim.com | L8: mbliss@mortensenwoodwork.com | N8: phays@premier-ap.com | P8: neil@baronmfg.com | R8: franklin@district95woodwork.com | T8: jramarble@gmail.com | V8: scp@martinezotero.com
G9: Adjusted Bid | H9: =I$658 -> 6857786 | J9: =$K$658 -> 7315506.9 | L9: =M$658 -> 9703627.8 | N9: =O$658 -> 7841388 | P9: =Q$658 -> 0 | R9: =S$658 -> 0 | T9: =U$658 -> 0 | V9: =W$658 -> 0
A10: BID DOCUMENTS: | C10: Plan/ Spec. Package | D10: QTY | E10: U/M | F10: Unit Cost | G10: Subtotal | H10: Yes/No | I10: Price | J10: Yes/No | K10: Price | L10: Yes/No | M10: Price | N10: Yes/No | O10: Price | P10: Yes/No | Q10: Price | R10: Yes/No | S10: Price | T10: Yes/No | U10: Price | V10: Yes/No | W10: Price | X10: Yes/No | Y10: Price
B11: GENERAL INCLUSIONS
B12: INCLUDES ALL SALES TAX | H12: i | I12: 231743 | J12: ? | L12: i | P12: ?
B13: ALL HOISTING & RIGGING REQUIRED TO COMPLETE THIS SCOPE | H13: i | J13: i | L13: i | P13: i
B14: PROVIDE P&P BONDS | H14: x | I14: {0.8%) | J14: x | L14: x | P14: x
B15: FLORIDA STATE CONTRACTORS LIC. | H15: i | J15: i | L15: i | P15: i
B16: GENERAL LIABILITY AND WORKERS COMP. INSURANCE LIMITS | H16: i | J16: i | L16: i | P16: i
B17: STATE AND LOCAL TAXES | H17: i | J17: ? | L17: i | P17: ?
B18: PRE-QUALIFIED IN COMPASS | H18: ? | I18: {2.1} | J18: ? | K18: {5.3} | L18: ? | M18: {3.7} | P18: ? | Q18: {3.1}
B19: SPECIFIC TRADE SCOPE OF WORK REQUIREMENTS
B20: BASE BID | O20: 7798388 | Q20: NOT REVISING
B21: Disclaimer The list of millwork and millwork-related items provided (over 350 items) is offered solely as a general reference to help subcontractors identify elements typically included in their scope of work. This list is not exhaustive and must not be relied upon as the sole basis for bidding. Each bidder is responsible for conducting a thorough review of the plans, specifications, and all relevant contract documents to ensure complete and accurate pricing. Subcontractors are further advised that: Hardware and Accessories: All hardware or accessories integrated into the millwork items listed must be included in the subcontractor’s proposal, except for appliances, audio-visual equipment, or any other items customarily provided by others. Due Diligence: It is the responsibility of each subcontractor to verify all dimensions, materials, finishes, and installation details within the construction documents. Any discrepancies or omissions noted must be clarified before submitting a final bid. Scope Confirmation: Bidders should confirm the full extent of work with the General Contractor or Owner’s Representative to avoid overlap, duplication, or exclusion of necessary items. By using or referring to this list, the subcontractor acknowledges that it is their duty to confirm the completeness and accuracy of all scope elements in their proposal. The General Contractor and Owner assume no liability for errors or omissions arising from reliance solely on this list.
B23: Acoustical Ceilings WD-101, WD-302, WD-113 | H23: i | I23: -1362000 | J23: x | L23: x | P23: x | Q23: Not responsive | U23: Not responsive
A24: Allowance | B24: Banquette at D-008 and D-102 | H24: x | I24: 210000 | K24: 210000 | M24: 210000 | N24: ?
B26: RFI responses Acknowledgement | H26: i | J26: ? | L26: i | P26: ?
B27: Addendums acknowledgement | H27: i | J27: ? | L27: i | P27: ?
B28: All hardware for all millwork | H28: i | J28: ? | L28: i | P28: ?
B29: Materials per specs, manual and drawings | H29: i | J29: ? | L29: i | P29: ?
B30: Core
B31: Doors, Frames and Hardware are per schedule | C31: A0.50, A0.51 | H31: X, UNO | I31: See D,F&H | J31: x | L31: X, UNO | P31: ?
B32: Wood Door Casings and portals per schedule and details | C32: A0.50-A0.51 A0.53 - A0.54B | H32: i | J32: ? | L32: i | P32: ?
B33: Wellness | I33: 3310682 | K33: 3244345 | M33: =4314253.4+(0.4*162488) -> 4379248.6
B34: Level 00 | C34: ID-3.16
B35: W-001 Cart Barn
A36: RFI | B36: Cart wash Stainless steel cabs, shelves, base, countertop and 4" backsplash | C36: ID-5.30, 1/ID-5.32 1,2/ID-6.58 | H36: i | I36: ALLOWANCE {43,000} | J36: ? | L36: i | O36: 43000 | P36: i
A37: RFI | B37: Cart prep stainless steel cabs, shelves, base, countertop and 4" backsplash | C37: ID-5.30, 2/ID-5.32 1,2/ID-6.59 | H37: i | J37: ? | L37: i | P37: i
B38: W-002 Golf Bag Storage
A39: RFI | B39: Golf Bag racks | C39: A2.12, ID-3.16 | H39: x | I39: EXCLUDE | J39: x | L39: x | N39: x | P39: x
A40: RFI | B40: W-006 Laundry | C40: ID-3.16, ID-3.16B | H40: x | J40: x | L40: x | N40: x | P40: x
A41: RFI | B41: W-007 Pool Equipment | C41: ID-3.16, ID-3.16B | H41: x | J41: x | L41: x | N41: x | P41: x
B42: W-009 Shoe Drop | C42: ID-3.16, ID-3.16B
A43: RFI | B43: Millwork Cabs (PLAM-3), open shelves, Countertop and 4" backsplash (ST-1) | C43: ID-5.27, ID-6.56 | H43: i | I43: PLAM-1 | J43: i | K43: PLAM-1 | L43: i | M43: PLAM-1 | O43: ??? | P43: i
A44: RFI | B44: W-010 Electrical | C44: ID-3.16, ID-3.16B | H44: x | J44: x | L44: x | P44: x
A45: RFI | B45: W-015 Pool Equipment | C45: ID-3.16, ID-3.16B | H45: x | J45: x | L45: x | P45: x
A46: RFI | B46: W-018 Plunge Pool Equipment | C46: ID-3.16, ID-3.16B | H46: x | J46: x | L46: x | P46: x
B47: W-019 Office
A48: RFI | B48: Wall panel PLAM-X | C48: 2/ID-5.25 | H48: i | I48: PL-101 | J48: x | K48: Plug | L48: i | M48: PLAM-3 | P48: ?
B49: Installation of owner supplied stuff | C49: ID-5.25 | H49: x | I49: EXCLUDE | J49: x | P49: x
B50: W-020 Men's restroom
A51: RFI | B51: Millwork Vanities (PLAM_2) & Countertop & 4" Backsplash (ST2) | C51: ID-3.16, ID-5.28 1-2/ID-6.57 | H51: i | J51: i | L51: i | P51: i
B52: W-021 Women's restroom
A53: RFI | B53: Millwork Vanities (PLAM_2) & Countertop & 4" Backsplash (ST2) | C53: ID-3.16, ID-5.28 1-2/ID-6.57 | H53: i | J53: i | L53: i | P53: i
B54: W-022 Employee Lounge | C54: ID-5.26
B55: reference sheet I5.14 note on ID-5.26 for lockers | H55: x | I55: EXCLUDE | L55: x | P55: x
B56: Kitchen cabs, open shelves, trim cap, millwork fixed panels (PLAM-3) and counters & 4" backsplash (ST-3) | C56: 1,4/ID-5.26 2,3,4/ID-6.54 1,2/ID-6.55 | H56: i | J56: i | L56: i | P56: i
B57: TV Wall Unit PLAM-3 & counter ST-3 | C57: 1,3/ID-5.26 1/ID-6.54 | H57: i | J57: ? | L57: i | P57: ?
B58: Lockers | H58: x | J58: x | L58: i | M58: -34466.08 | P58: i | Q58: ???
B59: Level 01 | C59: ID-1.17, ID-2.15 ID3.17, A2.22 A6.22
B60: W-100 Retail | C60: ID-3.17B, ID5.57
B61: Hanging Millwork (metal angle brackets, wood double supports WD-109, wood shelves WD-109, hanging rods MT-101) | C61: 2/ID-5.57 1,2,3,4,5/ID-6.60.3 | H61: i | J61: i | L61: i | P61: i
B62: Cash Desk & Backwrap (Millwork & Ribs WD-109, Paneling WD-109, countertop & Shroud ST-114.1, Shelves, grommets, wood cap, trim, wood tile) | C62: 2,3/ID-5.57 ID-6.60.2 12/ID-6.60.3 | H62: i | J62: i | L62: i | P62: i
B63: Casing WD-109 | C63: 3,4,6,7/ID-5.57 4/ID-7.04 | H63: i | J63: ? | L63: i | P63: i
B64: Shelf display (Millwork & Ribs WD-109, Paneling WD-109, Shelves, wood rail, header, filler) | C64: 3,4,5/ID5.57 ID-6.60.1 | H64: i | J64: i | L64: i | P64: i
B65: Free-standing display/Stor w/provisions for sink WD-109 & ST-114.1 | C65: 4/ID-5.57 6,7,8,9,10,11,12/ID-6.60.3 | H65: i | J65: i | L65: i | P65: i | Q65: ???
B66: Free-standing display/Stor without sink WD-109 & ST-114.1 | C66: 2/ID-5.57 6,7,8,9,10,11,12/ID-6.60.3 | H66: i | J66: ? | L66: i | P66: ?
B67: Interior exposed columns solid wood paneling | C67: A2.22, A8.01 ID-1.17, 2/ID-5.57 | H67: i | J67: ? | L67: i | P67: ?
B68: W-102 Vanity | C68: ID-5.60
B69: (2) Men's Changing Towel Drop Millwork w/ shelves WD-105 and countertop & apron ST-112.1 | C69: 2/ID-5.61 4/ID-6.62.0 2,3,4/ID-6.69.4 | H69: i | J69: i | L69: i | P69: i | Q69: ???
B70: Men's Changing Swim Spin Millwork w/ shelves WD-105 and countertop & apron ST-122.1 w/swimsuit spinner | C70: 4/ID-5.61 3/ID-6.62.0 1,3/ID-6.69.4 | H70: i | J70: i | L70: i | P70: ?
B71: (2) Men's Changing Dry Vanity Millwork WD-105 with counter & apron ST-122.1 | C71: 5/ID-5.61 2/ID-6.62.0 1,2/ID-6.69.3 | H71: i | J71: i | L71: i | P71: ?
B72: Casing WD-105 | C72: 5,6,7/ID-5.61 2/ID-7.04, 6/ID-7.04 | H72: i | J72: ? | L72: i | P72: ?
B73: Portal WD-105 | C73: 5,6/ID-5.61 2/ID-7.04 | H73: i | J73: ? | L73: i | P73: ?
B74: Vanity WD-105, countertop & apron ST-122.1 | C74: 7/ID-5.61 1/ID-6.62.0 1,2/ID-6.69.2 | H74: i | J74: i | L74: i | P74: ?
B75: Pilasters ST-122.1 | C75: 7/ID-5.61 1/ID-6.62.0 1,2/ID-6.69.2 | H75: x | I75: See Tile | J75: ? | L75: x | P75: ?
A76: RFI | B76: Vanity return walls WD-105??? | C76: 3/ID-5.61 4/ID-6.69.2 | H76: i | I76: WD-105 | J76: ? | L76: i | P76: ?
B77: Vanity backsplash ST-122.1 and vanity niche and shelves ST-122.2 | C77: 7/ID-5.61 1/ID-6.62.0 2,4/ID-6.69.2 | H77: x | I77: See Tile | J77: i | L77: x | P77: ?
B78: W-108 Thermal Area
A79: RFI | B79: Millwork WD-105 and countertop & backsplash ST-116.1 w/ wood shelves, surround and backsplash | C79: 1/ID-5.60, 2/ID-5.65 7/ID-6.62.0 1,2,3/ID-6.69.6 | H79: i | J79: i | L79: i | P79: i
B80: Casing WD-105 | C80: 3/ID-5.65 | H80: i | J80: i | L80: i | P80: i
B81: W-109 Hallway
B82: Casing WD-105 | C82: 2,3,4,5,6/ID-5.60 4/ID-7.03, 2/ID-7.04 | H82: i | J82: ? | L82: i | P82: ?
B83: Portal WD-105 | C83: 2,3,4,5/ID-5.60 2/ID-7.04 | H83: i | J83: ? | L83: i | P83: ?
B84: (2) Millwork ((1) double and (1) triple) WD-105 and countertop and apron ST-122.1 and shelves | C84: 3/ID-5.60 5,6/ID-6.62.0 1,2,3/ID-6.69.5 | H84: i | J84: ? | L84: i | P84: i | Q84: ???
B85: Window wood frame Casing WD-105 | C85: 5/ID-5.60 | H85: i | J85: ? | L85: i | P85: ?
B86: Ceiling Beams WD-109 | C86: 2,3,4,5/ID-5.60 3/ID-6.20 | H86: i | J86: ? | L86: i | P86: i | Q86: ???
B87: W-110 Lockers | C87: ID-5.60 | H87: x | J87: i | L87: i | M87: -120199.04
B88: WD-105 Portal/cladding, wood edge and cove | C88: 1,2,3,4/ID-5.64 ID-6.65, 5/ID-6.08 | H88: i | J88: ? | L88: i | P88: i | Q88: ???
B89: W-111 Lockers | C89: ID-5.60 | H89: x | J89: i | L89: i | M89: -110925.96
B90: WD-105 Portal/cladding, wood edge and cove | C90: 1,2,3,4/ID-5.64 ID-6.65, 5/ID-6.08 | H90: i | J90: ? | L90: i | P90: i | Q90: ???
B91: W-112 Lockers | C91: ID-5.60 | H91: x | J91: i | L91: i | M91: -97083.84
B92: WD-105 Portal/cladding, wood edge and cove | C92: 1,2,3,4/ID-5.64 ID-6.65, 5/ID-6.08 | H92: i | J92: ? | L92: i | P92: i | Q92: ???
B93: W-114 Men's Restroom | C93: ID-5.60, ID-5.63
B94: Casing WD-105 | C94: 2,3,5,9,11/ID-5.63 | H94: i | J94: i | L94: i | P94: i
B95: Portal WD-105 | C95: 2/ID-5.63 | H95: i | J95: ? | L95: i | P95: ?
B96: Urinal Screen MT-105 & G-106 | C96: 1,3/ID-5.63 4,5,6/ID-6.69.1 | H96: i | J96: ? | L96: i | P96: ?
B97: (2) Headrest UPH-102 | C97: 3/ID-5.63 | H97: i | J97: ? | L97: i | P97: ?
B98: W-114A Men's W/C | C98: ID-5.60, ID-5.63
B99: Vanity and apron WD-105, countertop ST-112.1 | C99: 10,13/ID-5.63 1/ID-6.69.1 3/ID-6.69.2 | H99: i | J99: i | L99: i | P99: i
B100: W-115 Barber | C100: ID-5.60
B101: (2) Barber stations Millwork PT-106, countertop & backsplash ST-112.3, frame and adjustable shelving, wood surround | C101: 5/ID-5.64 1,2,3,4/ID-6.70 | H101: i | J101: i | L101: i | P101: i | Q101: ???
B102: Void spaces in barber stations to be laminated with metal | C102: 2/ID-6.70 | H102: i | J102: ? | L102: i | P102: ?
...

Sheet 07 17 Waterproofing & Caulk
G1: Hedrick Plug
F2: X | G2: Excluded
F3: I | G3: Included
B4: BACK TO SUMMARY SHEET | G4: Sub Add/Deduct
A5: Project: | B5: ='Area Calculations'!B4 -> Atlantic Fields Club Core / Dock Bar / Spa Pods / Water Features | G5: Company | H5: Triton | J5: Alpha
A6: Trade: | B6: Waterproofing & Caulking | G6: Contact | H6: JR. Hopf | J6: Rafael Delgado
A7: CSI Code: | B7: 07 17 00 | G7: Phone | H7: (561) 516-0448 | J7: (786) 585-3947
A8: Date: | G8: Email | H8: jr.hopf@outlook.com | J8: RDelgado@alphaiwp.com
G9: Adjusted Bid | H9: =I$168 -> 2084242.5 | J9: =K$168 -> 2044381 | L9: =M$168 -> 0 | N9: =O$168 -> 0 | P9: =Q$168 -> 0 | R9: =S$168 -> 0
A10: BID DOCUMENTS: | C10: Plan/ Spec. Package | D10: QTY | E10: U/M | F10: Unit Cost | G10: Subtotal | H10: Yes/No | I10: Price | J10: Yes/No | K10: Price | L10: Yes/No | M10: Price | N10: Yes/No | O10: Price | P10: Yes/No | Q10: Price | R10: Yes/No | S10: Price
B11: GENERAL INCLUSIONS
B12: INCLUDES ALL SALES TAX
B13: ALL HOISTING & RIGGING REQUIRED TO COMPLETE THIS SCOPE
B14: PROVIDE P&P BONDS
B15: FLORIDA STATE CONTRACTORS LIC.
B16: GENERAL LIABILITY AND WORKERS COMP. INSURANCE LIMITS
B17: STATE AND LOCAL TAXES
B18: SPECIFIC TRADE SCOPE OF WORK REQUIREMENTS
B19: BASE BID
B21: Waterproofing
B22: top & bottom of footings
B23: bottom SOG
... B41: SOPREMA SOPRASEAL STICK 1100T
B43: Club Core | I43: =SUBTOTAL(9,I44:I150) -> 2045883.5 | K43: =SUBTOTAL(9,K44:K162) -> 2044381 | M43: =SUBTOTAL(9,M44:M162) -> 0 | O43: =SUBTOTAL(9,O44:O162) -> 0 | Q43: =SUBTOTAL(9,Q44:Q162) -> 0 | S43: =SUBTOTAL(9,S44:S162) -> 0
B44: Waterproofing | G44: =ROUND(D44*F44,0) -> 0
B45: Foundation Footings, Walls, SOG | G45: =ROUND(D45*F45,0) -> 0 | K45: 753363
B46: wrap footings | G46: =ROUND(D46*F46,0) -> 0 | J46: I
B47: Dining | D47: =SUM(D48:D60) -> 24009 | E47: sf | F47: =I47/D47 -> 10.496064 | G47: =ROUND(D47*F47,0) -> 252000 | I47: 252000
B48: DF140.24 | D48: 15277 | E48: sf | G48: =ROUND(D48*F48,0) -> 0
B49: DFXXX.24 | D49: 2223 | E49: sf | G49: =ROUND(D49*F49,0) -> 0
B50: DF40.12 | D50: 1151 | E50: sf | G50: =ROUND(D50*F50,0) -> 0
B51: DF180150 | D51: 738 | E51: sf | G51: =ROUND(D51*F51,0) -> 0
B52: DF200150 | D52: 2430 | E52: sf | G52: =ROUND(D52*F52,0) -> 0
B53: DF50 | D53: 953 | E53: SF | G53: =ROUND(D53*F53,0) -> 0
B54: DF60 | D54: 624 | E54: sf | G54: =ROUND(D54*F54,0) -> 0
B55: DF65 | D55: 238 | E55: sf | G55: =ROUND(D55*F55,0) -> 0
B56: DF70 | D56: 271 | E56: sf | G56: =ROUND(D56*F56,0) -> 0
B57: DF85 | D57: 586 | E57: sf | G57: =ROUND(D57*F57,0) -> 0
B58: DF95 | D58: 244 | E58: sf | G58: =ROUND(D58*F58,0) -> 0
B59: back out foundation wall footprint on footings - conc | D59: -581 | E59: sf | G59: =ROUND(D59*F59,0) -> 0
B60: back out foundation wall footprint on footings - CMU | D60: =-105+-40 -> -145 | E60: sf | G60: =ROUND(D60*F60,0) -> 0
B61: Fitness | D61: =SUM(D62:D68) -> 17549.91 | E61: sf | G61: =ROUND(D61*F61,0) -> 0 | I61: 184275
B62: FFXXX.24 | D62: =(7498*2)+(981*2) -> 16958 | E62: sf | G62: =ROUND(D62*F62,0) -> 0
B63: FF30.12 | D63: 145 | E63: sf | G63: =ROUND(D63*F63,0) -> 0
B64: FF50 | D64: 560 | E64: sf | G64: =ROUND(D64*F64,0) -> 0
B65: FF70120 | D65: 212 | E65: sf | G65: =ROUND(D65*F65,0) -> 0
B66: FF75 | D66: 295 | E66: sf | G66: =ROUND(D66*F66,0) -> 0
B67: back out foundation wall footprint on footings - conc | D67: -602 | E67: sf | G67: =ROUND(D67*F67,0) -> 0
B68: back out foundation wall footprint on footings - CMU | D68: =-27*0.67 -> -18.09 | E68: sf | G68: =ROUND(D68*F68,0) -> 0
B69: Wellness | D69: =SUM(D70:D82) -> 33380.615 | E69: sf | G69: =ROUND(D69*F69,0) -> 0 | I69: 350700
B70: WF140.24 | D70: 19443 | E70: sf | G70: =ROUND(D70*F70,0) -> 0
B71: WFXXX.20 | D71: =(239*2)+(93*1.67) -> 633.31 | E71: sf | G71: =ROUND(D71*F71,0) -> 0
B72: WFXXX.24 | D72: =(1153*2)+(459*2) -> 3224 | E72: sf | G72: =ROUND(D72*F72,0) -> 0
B73: WF40.12 | D73: 495 | E73: sf | G73: =ROUND(D73*F73,0) -> 0
B74: WF50.18 | D74: 642 | E74: sf | G74: =ROUND(D74*F74,0) -> 0
B75: WF70 | D75: 140 | E75: sf | G75: =ROUND(D75*F75,0) -> 0
B76: WF75 | D76: 325 | E76: sf | G76: =ROUND(D76*F76,0) -> 0
B77: WF90 | D77: 234 | E77: sf | G77: =ROUND(D77*F77,0) -> 0
B78: WF100 | D78: 1120 | E78: sf | G78: =ROUND(D78*F78,0) -> 0
B79: WF120 | D79: 1600 | E79: sf | G79: =ROUND(D79*F79,0) -> 0
B80: pool equip vault | D80: =3035+(225.27*2.5)+1427+1579 -> 6604.175 | E80: sf | G80: =ROUND(D80*F80,0) -> 0
B81: back out foundation wall footprint on footings - conc | D81: =-115+-857 -> -972 | E81: sf | G81: =ROUND(D81*F81,0) -> 0
B82: back out foundation wall footprint on footings - CMU | D82: =-161*0.67 -> -107.87 | E82: sf | G82: =ROUND(D82*F82,0) -> 0
B83: wrap SOG bottom, walls, tunnel lid, elevator pits | K83: 240000
B84: Dining
B85: SOG bottom - level 00 | D85: 7927 | E85: sf | F85: =I85/D85 -> 8.0736723 | G85: =ROUND(D85*F85,0) -> 64000 | I85: 64000
B86: SOG bottom - level 01 | D86: 7521 | E86: sf | G86: =ROUND(D86*F86,0) -> 0 | I86: 60000
B87: DCW1 walls | D87: =9883+1207 -> 11090 | E87: sf | F87: =I87/D87 -> 9.9413886 | G87: =ROUND(D87*F87,0) -> 110250 | I87: 110250
B88: tunnel lid | D88: 701 | E88: sf | F88: 30 | G88: =ROUND(D88*F88,0) -> 21030 | I88: =$G88 -> 21030 | K88: =$G88 -> 21030
B89: Fitness | K89: 197000
B90: SOG bottom - level 00 | D90: 4301 | E90: sf | G90: =ROUND(D90*F90,0) -> 0 | I90: 34400
B91: SOG bottom - level 01 | D91: 6228 | E91: sf | G91: =ROUND(D91*F91,0) -> 0 | I91: 83440
B92: FCW1 walls | D92: =9351+1078 -> 10429 | E92: sf | F92: =I92/D92 -> 7.5275674 | G92: =ROUND(D92*F92,0) -> 78505 | I92: 78505
B93: tunnel lid | D93: 784 | E93: sf | F93: 30 | G93: =ROUND(D93*F93,0) -> 23520 | I93: =$G93 -> 23520 | K93: =$G93 -> 23520
B94: Wellness
B95: wrap footings | G95: =ROUND(D95*F95,0) -> 0
B96: SOG bottom - level 00 | D96: 15695 | E96: sf | G96: =ROUND(D96*F96,0) -> 0 | I96: 125560 | K96: 233000
B97: SOG bottom - level 01 | D97: 1940 | E97: sf | F97: =I97/D97 -> 8 | G97: =ROUND(D97*F97,0) -> 15520 | I97: 15520
B98: WCW1 walls | D98: =11615+1398 -> 13013 | E98: sf | F98: =I98/D98 -> 7.0010758 | G98: =ROUND(D98*F98,0) -> 91105 | I98: 91105
B99: Elevator Pits
B100: Dining
B101: elevator pits - interior | D101: =252 -> 252 | E101: sf | G101: =ROUND(D101*F101,0) -> 0 | I101: 1750 | K101: 12880
B102: elevator pits - exterior | D102: =491+207 -> 698 | E102: sf | G102: =ROUND(D102*F102,0) -> 0 | I102: 7350 | J102: I
B103: Wellness
B104: elevator pits - interior | D104: 269 | E104: sf | G104: =ROUND(D104*F104,0) -> 0 | I104: 1890 | K104: 12117
B105: elevator pits - exterior | D105: 511 | E105: sf | G105: =ROUND(D105*F105,0) -> 0 | I105: 5407.5 | J105: I
B107: Planters | K107: =116236+14618 -> 130854
B108: Dining | G108: =ROUND(D108*F108,0) -> 0 | I108: =108275+1250 -> 109525
B109: see 4/A8.11, /A4.01, A2.20 | G109: =ROUND(D109*F109,0) -> 0
A110: =1.67*2 -> 3.34 | B110: exterior - Sopra Seal LM 204 | D110: =A110*49 -> 163.66 | E110: sf | F110: 35.5 | G110: =ROUND(D110*F110,0) -> 5810 | H110: I | J110: I
A111: 3.17 | B111: interior - ALSAN TRAFIK RS 730 PMMA | D111: =A111*49 -> 155.33 | E111: sf | F111: 35.5 | G111: =ROUND(D111*F111,0) -> 5514 | H111: I | J111: I
B112: see 2/8.11, 2/A4.00, A2.30 | G112: =ROUND(D112*F112,0) -> 0
A113: =5.46+3.75 -> 9.21 | B113: exterior - Sopra Seal LM 204 | D113: =A113*226 -> 2081.46 | E113: sf | F113: 35.5 | G113: =ROUND(D113*F113,0) -> 73892 | H113: I | J113: I
A114: 7.5 | B114: interior - ALSAN TRAFIK RS 730 PMMA | D114: =A114*226 -> 1695 | E114: sf | F114: 35.5 | G114: =ROUND(D114*F114,0) -> 60173 | H114: I | J114: I
B115: see 2/A4.03, A2.30 | G115: =ROUND(D115*F115,0) -> 0
A116: =3.67*2 -> 7.34 | B116: exterior - Sopra Seal LM 204 | D116: =A116*31 -> 227.54 | E116: sf | F116: 35.5 | G116: =ROUND(D116*F116,0) -> 8078 | H116: I | J116: I
A117: 8.33 | B117: interior - ALSAN TRAFIK RS 730 PMMA | D117: =A117*31 -> 258.23 | E117: sf | F117: 35.5 | G117: =ROUND(D117*F117,0) -> 9167 | H117: I | J117: I
B118: Wellness | G118: =ROUND(D118*F118,0) -> 0 | I118: =62125+6500 -> 68625
B119: see 2/A8.16, A/4.10, A2.31 | G119: =ROUND(D119*F119,0) -> 0
A120: =2.67*2 -> 5.34 | B120: exterior - Sopra Seal LM 204 | D120: =A120*244 -> 1302.96 | E120: sf | F120: 35.5 | G120: =ROUND(D120*F120,0) -> 46255 | H120: I | J120: I
...

