Workbook
Name FCP: 'Bond Calculator'!$B$7

Sheet Area Calculations
B2: PROJECT AREA CALCULATIONS
B4: Project Name | H4: Gross (sf) | I4: =G35 -> 0 | J4: FORMULA OFF GCS
B5: Location | H5: AC (sf) | I5: =E35 -> 0
H6: Rentable (sf) | I6: =F35 -> 0
H7: Site (acres) | I7: 1 | J7: FORMULA OFF GCS
H8: Parking Spaces | I8: 1
B9: =NOW() -> 46146.225 | H9: Build Duration (months) | I9: 1 | J9: FORMULA OFF GCS
B10: Drawings Date
A13: I. | B13: Floor | C13: Building | D13: Room | E13: ACSF | F13: RSF | G13: Gross SF | H13: GROSS%
H14: =G14/$I$4 -> #DIV/0!
H15: =G15/$I$4 -> #DIV/0!
H16: =G16/$I$4 -> #DIV/0!
H17: =G17/$I$4 -> #DIV/0!
H18: =G18/$I$4 -> #DIV/0!
H19: =G19/$I$4 -> #DIV/0!
H20: =G20/$I$4 -> #DIV/0!
H21: =G21/$I$4 -> #DIV/0!
H22: =G22/$I$4 -> #DIV/0!
H23: =G23/$I$4 -> #DIV/0!
H24: =G24/$I$4 -> #DIV/0!
H25: =G25/$I$4 -> #DIV/0!
... H34: =G34/$I$4 -> #DIV/0!
B35: TOTAL | E35: =SUM(E14:E34) -> 0 | F35: =SUM(F14:F34) -> 0 | G35: =SUM(G14:G34) -> 0 | H35: =SUM(H14:H34) -> #DIV/0!
A37: II. | C37: Units | E37: Site SF | G37: Site(acres) | I37: %
H40: =SUM(G41:G45) -> 0
I41: =G41/$I$7 -> 0
I42: =G42/$I$7 -> 0
I43: =G43/$I$7 -> 0
I44: =G44/$I$7 -> 0
I45: =G45/$I$7 -> 0
H46: =SUM(G47:G49) -> 0
I47: =G47/$I$7 -> 0
I48: =G48/$I$7 -> 0
I49: =G49/$I$7 -> 0
B51: TOTAL | E51: =SUM(E41:E49) -> 0 | G51: =SUM(G40:G50) -> 0 | I51: =SUM(I40:I50) -> 0
C53: Levels | G53: GSF | I53: %
I56: =G56/$I$4 -> #DIV/0!
I57: =G57/$I$4 -> #DIV/0!
I58: =G58/$I$4 -> #DIV/0!
B60: TOTAL GSF | G60: =SUM(G55:G59) -> 0 | I60: =SUM(I55:I59) -> #DIV/0!
L61: Design Team
L62: Architectural Drawings by
L63: Structural Drawings by
L64: MEP FA FP Drawings by
L65: Civil Drawings by
L66: Land scape Drawings by
L67: Kitchen Drawings by
L68: Storefront Designer by
L69: Geotech report by
L70: Specifications
A76: IV. | B76: SITE AREAS | H76: $ /UNIT | I76: %
B79: Site Perimeter | H79: LF
B80: Walk Gates
B81: Drive Gates
B82: Tire Grates / Truck Wash
A83: III. | B83: SITE AREAS | H83: $ /UNIT | I83: %
B84: Sidewalks
B85: Drives
B86: Asphalt Parking
B87: Fill CY
A88: III. | B88: Barking Spaces | C88: FLOOR BREAKDOWN | G88: QTY. | I88: %
I90: =G90/$I$8 -> 0
I91: =G91/$I$8 -> 0
B93: TOTAL Units | G93: =SUM(G90:G92) -> 0 | I93: =SUM(I90:I92) -> 0

Sheet Bond Calculator
A1: Hedrick Brothers Construction
A3: Performance / Payment Bond | E3: Performance / Payment Bond
A4: General Construction | E4: Design Build
A5: 42888 | E5: 42053
B6: =IF(B13>500000,500000,B13) -> 500000 | C6: 0.0091 | D6: =B6*C6 -> 4550 | F6: 0 | G6: 0.01875 | H6: =SUM(F6*G6) -> 0
B7: =IF(B13<2500000,(B13-B6),IF(B13>B6,2000000,0)) -> 1720594.1 | C7: 0.00725 | D7: =B7*C7 -> 12474.307 | F7: 0 | G7: 0.015 | H7: =SUM(F7*G7) -> 0
B8: =IF(B13<5000000,MAX(0,B13-2500000),IF(B13>2500000,2500000)) -> 0 | C8: 0.0063 | D8: =B8*C8 -> 0 | F8: 0 | G8: 0.01125 | H8: =SUM(F8*G8) -> 0
B9: =IF(B13<7500000,MAX(0,B13-5000000),IF(B13>7500000,2500000,0)) -> 0 | C9: 0.00555 | D9: =B9*C9 -> 0 | F9: 0 | G9: 0.009 | H9: =SUM(F9*G9) -> 0
B10: =IF(B13<7500000,MAX(0,B13-7500000),IF(B13>7500000,(B13-7500000))) -> 0 | C10: 0.0051 | D10: =B10*C10 -> 0 | F10: 0 | G10: 0.00825 | H10: =SUM(F10*G10) -> 0
D11: =B11*C11 -> 0 | F11: 0 | G11: 0.0075 | H11: =SUM(F11*G11) -> 0
A12: Contract Value | B12: ='Cost Summary'!D123 -> 0 | C12: Total | D12: =SUM(D6:D11) -> 17024.307 | E12: Contract Value | F12: =SUM(F6+F7+F8+F9+F10+F11) -> 0 | G12: Total | H12: =SUM(H6:H11) -> 0
A13: Cost Summary | B13: 2220594.1 | D13: =SUM(D12/B12) -> #DIV/0! | H13: =SUM(H12/F12) -> #DIV/0!
B14: =B12-B13 -> -2220594.1

Sheet Allowances
A7: ='Area Calculations'!B4 -> Project Name | C7: ='Area Calculations'!B5 -> Location
A9: Allowances
A10: =TODAY() -> 46146
A12: NO. | B12: DESCRIPTION | C12: VALUE
A13: 1 | C13: 0
A14: =A13+1 -> 2 | C14: 0
A15: =A14+1 -> 3 | C15: 0
A16: =A15+1 -> 4 | C16: 0
A17: =A16+1 -> 5 | C17: 0
A18: =A17+1 -> 6 | C18: 0
A19: =A18+1 -> 7 | C19: 0
A20: =A19+1 -> 8 | C20: 0
A21: =A20+1 -> 9 | C21: 0
A22: =A21+1 -> 10 | C22: 0
A23: =A22+1 -> 11 | C23: 0
A24: =A23+1 -> 12 | C24: 0
A25: =A24+1 -> 13 | C25: 0
... A28: =A27+1 -> 16 | C28: 0
A29: =A28+1 -> 17
A30: =A29+1 -> 18
A31: =A30+1 -> 19 | B31: Total | C31: =SUM(C13:C30) -> 0
B33: *All ALLOWANCES IN BID TABS MUST BE LISTED HERE

Sheet Alternates
A7: ='Area Calculations'!B4 -> Project Name | C7: ='Area Calculations'!B5 -> Location
A9: Alternates
A10: =TODAY() -> 46146
A12: NO. | B12: DESCRIPTION | C12: VALUE
A13: ALT. #1 | B13: Description | C13: 0
A14: ALT. #2 | B14: Description | C14: 0
A15: ALT. #3 | B15: Description | C15: 0
A16: ALT. #4 | B16: Description | C16: 0
A17: ALT. #5 | B17: Description | C17: 0
A18: ALT. #6 | B18: Description | C18: 0
A19: ALT. #7 | B19: Description | C19: 0
A20: ALT. #8 | B20: Description | C20: 0
A21: ALT. #9 | B21: Description | C21: 0
A22: ALT. #10 | B22: Description | C22: 0
A23: ALT. #11 | B23: Description | C23: 0
A24: ALT. #12 | B24: Description | C24: 0
... A27: ALT. #15 | B27: Description | C27: 0
B28: Total | C28: =SUM(C13:C27) -> 0

Sheet Labor Rates Calculator
A5: Hedrick Brothers Construction Co., Inc.
A6: Salaries and Burden Calculations
A7: As of 8/22/24
C8: MARK-UP | F8: 0.15
E9: Burdened Rate | F9: Mark-up | G9: Total | I9: ANNUAL BURDENED AMOUNT | J9: ANNUAL BURDENED AMOUNT (W/ M/U)
B10: 1 | C10: Proj Exec | E10: 157.66656 | F10: =E10*$F$8 -> 23.649984 | G10: =SUM(E10:F10) -> 181.31655 | I10: =E10*2080 -> 327946.45 | J10: =G10*2080 -> 377138.42
B11: 2 | C11: Sr PM | E11: 130.67475 | F11: =E11*$F$8 -> 19.601212 | G11: =SUM(E11:F11) -> 150.27596 | I11: =E11*2080 -> 271803.48 | J11: =G11*2080 -> 312574
B12: 3 | C12: PM 3 | E12: 120.34132 | F12: =E12*$F$8 -> 18.051199 | G12: =SUM(E12:F12) -> 138.39252 | I12: =E12*2080 -> 250309.95 | J12: =G12*2080 -> 287856.45
B13: 4 | C13: PM 2 | E13: 110.14476 | F13: =E13*$F$8 -> 16.521714 | G13: =SUM(E13:F13) -> 126.66647 | I13: =E13*2080 -> 229101.1 | J13: =G13*2080 -> 263466.26
B14: 5 | C14: PM 1 | E14: 94.265604 | F14: =E14*$F$8 -> 14.139841 | G14: =SUM(E14:F14) -> 108.40544 | I14: =E14*2080 -> 196072.46 | J14: =G14*2080 -> 225483.32
B15: 6 | C15: Proj Admin | E15: 66.505247 | F15: =E15*$F$8 -> 9.9757871 | G15: =SUM(E15:F15) -> 76.481034 | I15: =E15*2080 -> 138330.91 | J15: =G15*2080 -> 159080.55
B16: 7 | C16: Proj Acct | E16: 85.81004 | F16: =E16*$F$8 -> 12.871506 | G16: =SUM(E16:F16) -> 98.681546 | I16: =E16*2080 -> 178484.88 | J16: =G16*2080 -> 205257.62
B17: 8 | C17: Asst PM | E17: 82.733564 | F17: =E17*$F$8 -> 12.410035 | G17: =SUM(E17:F17) -> 95.143598 | I17: =E17*2080 -> 172085.81 | J17: =G17*2080 -> 197898.68
B18: 9 | C18: Supt 3 | E18: 131.75199 | F18: =E18*$F$8 -> 19.762798 | G18: =SUM(E18:F18) -> 151.51479 | I18: =E18*2080 -> 274044.14 | J18: =G18*2080 -> 315150.76
B19: 10 | C19: Supt 2 | E19: 110.59223 | F19: =E19*$F$8 -> 16.588834 | G19: =SUM(E19:F19) -> 127.18106 | I19: =E19*2080 -> 230031.83 | J19: =G19*2080 -> 264536.61
B20: 11 | C20: Supt 1 | E20: 90.514804 | F20: =E20*$F$8 -> 13.577221 | G20: =SUM(E20:F20) -> 104.09203 | I20: =E20*2080 -> 188270.79 | J20: =G20*2080 -> 216511.41
B21: 12 | C21: Asst Supt | E21: 59.915466 | F21: =E21*$F$8 -> 8.9873199 | G21: =SUM(E21:F21) -> 68.902786 | I21: =E21*2080 -> 124624.17 | J21: =G21*2080 -> 143317.79
... B26: 17 | C26: Safety | E26: 79.733968 | F26: =E26*$F$8 -> 11.960095 | G26: =SUM(E26:F26) -> 91.694063 | I26: =E26*2080 -> 165846.65 | J26: =G26*2080 -> 190723.65
C27: Labor | E27: 32.408056 | F27: =E27*$F$8 -> 4.8612084 | G27: =SUM(E27:F27) -> 37.269264 | I27: =E27*2080 -> 67408.756 | J27: =G27*2080 -> 77520.069
C28: Apprentice | E28: 32.978211 | F28: =E28*$F$8 -> 4.9467316 | G28: =SUM(E28:F28) -> 37.924942 | I28: =E28*2080 -> 68594.678 | J28: =G28*2080 -> 78883.88
C29: Carpenter | E29: 45.013251 | F29: =E29*$F$8 -> 6.7519877 | G29: =SUM(E29:F29) -> 51.765239 | I29: =E29*2080 -> 93627.563 | J29: =G29*2080 -> 107671.7
C30: Driver | E30: 35.486876 | F30: =E30*$F$8 -> 5.3230314 | G30: =SUM(E30:F30) -> 40.809908 | I30: =E30*2080 -> 73812.702 | J30: =G30*2080 -> 84884.608
C31: Leadman | E31: 46.605242 | F31: =E31*$F$8 -> 6.9907863 | G31: =SUM(E31:F31) -> 53.596029 | I31: =E31*2080 -> 96938.904 | J31: =G31*2080 -> 111479.74
C32: Supt MEP | E32: 0 | F32: =E32*$F$8 -> 0 | G32: =SUM(E32:F32) -> 0 | I32: =E32*2080 -> 0 | J32: =G32*2080 -> 0
C33: Gen Supt | E33: 130.4108 | F33: =E33*$F$8 -> 19.561621 | G33: =SUM(E33:F33) -> 149.97242 | I33: =E33*2080 -> 271254.47 | J33: =G33*2080 -> 311942.64
C34: Cons Mgr | E34: 135.45804 | F34: =E34*$F$8 -> 20.318705 | G34: =SUM(E34:F34) -> 155.77674 | I34: =E34*2080 -> 281752.72 | J34: =G34*2080 -> 324015.62
C35: Proj Coor | E35: 0 | F35: =E35*$F$8 -> 0 | G35: =SUM(E35:F35) -> 0 | I35: =E35*2080 -> 0 | J35: =G35*2080 -> 0
C36: Mktg | E36: 85.41309 | F36: =E36*$F$8 -> 12.811964 | G36: =SUM(E36:F36) -> 98.225054 | I36: =E36*2080 -> 177659.23 | J36: =G36*2080 -> 204308.11
C37: Bus Dev | E37: 121.55329 | F37: =E37*$F$8 -> 18.232993 | G37: =SUM(E37:F37) -> 139.78628 | I37: =E37*2080 -> 252830.84 | J37: =G37*2080 -> 290755.47
C38: Chief, 3 & 2 | E38: 140.9198 | F38: =E38*$F$8 -> 21.13797 | G38: =SUM(E38:F38) -> 162.05777 | I38: =E38*2080 -> 293113.19 | J38: =G38*2080 -> 337080.17
... C40: Exec Asst | E40: 69.670191 | F40: =E40*$F$8 -> 10.450529 | G40: =SUM(E40:F40) -> 80.12072 | I40: =E40*2080 -> 144914 | J40: =G40*2080 -> 166651.1
D41: TOTAL | E41: =SUM(E10:E40) -> 2612.4097 | F41: =SUM(F10:F40) -> 391.86145 | G41: =SUM(G10:G40) -> 3004.2711 | I41: =SUM(I10:I40) -> 5433812.1 | J41: =SUM(J10:J40) -> 6248883.9
G42: =E41/G41 -> 0.86956522 | I42: =I41/J41 -> 0.86956522

Sheet GCs & GRs
A1: Contract Reference | B1: General Condition Ref. | C1: ='Area Calculations'!B4 -> Project Name
C3: Construction | F3: Activity | H3: Start | I3: Finish | J3: Days | K3: Weeks | L3: Months | M3: % Time | N3: Remarks | Q3: Demo to building pad
F4: Construction | H4: 0 | I4: 0 | J4: =SUM(I4-H4) -> 0 | K4: =SUM(J4/7) -> 0 | L4: =SUM(J4/30) -> 0 | Q4: Activity | S4: Start | T4: Finish | U4: Days | V4: Weeks | W4: Months
F5: Close Out | H5: 0 | I5: 0 | J5: =SUM(I5-H5) -> 0 | K5: =SUM(J5/7) -> 0 | L5: =SUM(J5/30) -> 0 | Q5: Construction | S5: 0 | T5: 0 | U5: =SUM(T5-S5) -> 0 | V5: =SUM(U5/7) -> 0 | W5: =SUM(U5/30) -> 0
F6: General Conditions | H6: General Req. - Field Office | J6: General Req. | L6: Total | Q6: Building
C7: Description | D7: Qty. | E7: U | F7: Unit | G7: Const. | H7: Unit | I7: General | J7: Unit | K7: General | O7: LABOR RATE FY 2025 *Updated 09.26.24 | P7: LABOR RATE (MIAMI/FT. LAUDERDALE) | Q7: Activity | S7: Start | T7: Finish | U7: Days | V7: Weeks | W7: Months | X7: LABOR RATE (MF CENTRAL FLORIDA)
F8: Cost | G8: Cond. | H8: Cost | I8: Req. | J8: Cost | K8: Req. | Q8: Construction | S8: 0 | T8: 0 | U8: =SUM(T8-S8) -> 0 | V8: =SUM(U8/7) -> 0 | W8: =SUM(U8/30) -> 0
C9: Field Labor - Construction | L9: =SUM(L10:L25) -> 0
C10: Project Executive | D10: =$K$4 -> 0 | E10: wks | F10: =(O10*40)*M10 -> 0 | G10: =SUM(D10*F10) -> 0 | L10: =SUM(G10+I10+K10) -> 0 | M10: 0 | O10: ='Labor Rates Calculator'!G10 -> 181.31655 | P10: 253 | X10: 216
C11: Senior Project Manager | D11: =$K$4 -> 0 | E11: wks | F11: =(O11*40)*M11 -> 0 | G11: =SUM(D11*F11) -> 0 | L11: =SUM(G11+I11+K11) -> 0 | M11: 0 | O11: ='Labor Rates Calculator'!G11 -> 150.27596 | P11: 195 | X11: 175
C12: Project Manager - Level 3 | D12: =$K$4 -> 0 | E12: wks | F12: =(O12*40)*M12 -> 0 | G12: =SUM(D12*F12) -> 0 | L12: =SUM(G12+I12+K12) -> 0 | M12: 0 | O12: ='Labor Rates Calculator'!G12 -> 138.39252
C13: Project Manager - Level 2 | D13: =$K$4 -> 0 | E13: wks | F13: =(O13*40)*M13 -> 0 | G13: =SUM(D13*F13) -> 0 | L13: =SUM(G13+I13+K13) -> 0 | M13: 0 | O13: ='Labor Rates Calculator'!G13 -> 126.66647 | P13: 185 | X13: 155
C14: Project Manager - Level 1 | D14: =$K$4 -> 0 | E14: wks | F14: =(O14*40)*M14 -> 0 | G14: =SUM(D14*F14) -> 0 | L14: =SUM(G14+I14+K14) -> 0 | M14: 0 | O14: ='Labor Rates Calculator'!G14 -> 108.40544 | P14: 163 | X14: 130
C15: Project Administator | D15: =$K$4 -> 0 | E15: wks | F15: =(O15*40)*M15 -> 0 | G15: =SUM(D15*F15) -> 0 | L15: =SUM(G15+I15+K15) -> 0 | M15: 0 | O15: ='Labor Rates Calculator'!G15 -> 76.481034 | P15: 95 | X15: 65
C16: Project Accountant | D16: =$K$4 -> 0 | E16: wks | F16: =(O16*40)*M16 -> 0 | G16: =SUM(D16*F16) -> 0 | L16: =SUM(G16+I16+K16) -> 0 | M16: 0 | O16: ='Labor Rates Calculator'!G16 -> 98.681546 | P16: 81 | X16: 60
C17: Assistant Project Manager | D17: =$K$4 -> 0 | E17: wks | F17: =(O17*40)*M17 -> 0 | G17: =SUM(D17*F17) -> 0 | L17: =SUM(G17+I17+K17) -> 0 | M17: 0 | O17: ='Labor Rates Calculator'!G17 -> 95.143598 | P17: 118 | X17: 95
C18: Superintendent - Level 3 | D18: =$K$4 -> 0 | E18: wks | F18: =(O18*40)*M18 -> 0 | G18: =SUM(D18*F18) -> 0 | L18: =SUM(G18+I18+K18) -> 0 | M18: 0 | O18: ='Labor Rates Calculator'!G18 -> 151.51479 | P18: 183 | X18: 194
C19: Superintendent - Level 2 | D19: =$K$4 -> 0 | E19: wks | F19: =(O19*40)*M19 -> 0 | G19: =SUM(D19*F19) -> 0 | L19: =SUM(G19+I19+K19) -> 0 | M19: 0 | O19: ='Labor Rates Calculator'!G19 -> 127.18106 | P19: 161 | X19: 173
C20: Superintendent - Level 1 | D20: =$K$4 -> 0 | E20: wks | F20: =(O20*40)*M20 -> 0 | G20: =SUM(D20*F20) -> 0 | L20: =SUM(G20+I20+K20) -> 0 | M20: 0 | O20: ='Labor Rates Calculator'!G20 -> 104.09203 | P20: 121 | X20: 155
C21: Assistant Superinterndent | D21: =$K$4 -> 0 | E21: wks | F21: =(O21*40)*M21 -> 0 | G21: =SUM(D21*F21) -> 0 | L21: =SUM(G21+I21+K21) -> 0 | M21: 0 | O21: ='Labor Rates Calculator'!G21 -> 68.902786 | P21: 84 | X21: 95
C22: Quality Control Manager | D22: =$K$4 -> 0 | E22: wks | F22: =(O22*40)*M22 -> 0 | G22: =SUM(D22*F22) -> 0 | L22: =SUM(G22+I22+K22) -> 0 | M22: 0 | O22: ='Labor Rates Calculator'!G22 -> 118.37225
C23: Foreman | D23: =$K$4 -> 0 | E23: wks | F23: =(O23*40)*M23 -> 0 | G23: =SUM(D23*F23) -> 0 | L23: =SUM(G23+I23+K23) -> 0 | M23: 0 | O23: ='Labor Rates Calculator'!G23 -> 47.75772 | P23: 65 | X23: 65
C24: Accounting | D24: =$K$4 -> 0 | E24: wks | F24: =(O24*40)*M24 -> 0 | G24: =SUM(D24*F24) -> 0 | L24: =SUM(G24+I24+K24) -> 0 | M24: 0 | O24: ='Labor Rates Calculator'!G24 -> 133.32852 | P24: 80 | X24: 90
C25: Safety Supervisor/Inspector | D25: =K4 -> 0 | E25: wks | F25: =(O25*40)*M25 -> 0 | G25: =SUM(D25*F25) -> 0 | L25: =SUM(G25+I25+K25) -> 0 | M25: 0 | O25: ='Labor Rates Calculator'!G26 -> 91.694063 | P25: 96 | X25: 96
C26: Field Labor - Close Out | L26: =SUM(L27:L41) -> 0
C27: Project Executive | D27: =$K$5 -> 0 | E27: wks | F27: =(40*O27)*M27 -> 0 | G27: =SUM(D27*F27) -> 0 | L27: =SUM(G27+I27+K27) -> 0 | M27: 0 | O27: =+O10 -> 181.31655 | P27: =+P10 -> 253 | X27: =+X10 -> 216
C28: Senior Project Manager | D28: =$K$5 -> 0 | E28: wks | F28: =(40*O28)*M28 -> 0 | G28: =SUM(D28*F28) -> 0 | L28: =SUM(G28+I28+K28) -> 0 | M28: =+M11 -> 0 | O28: =+O11 -> 150.27596 | P28: =+P11 -> 195 | X28: =+X11 -> 175
C29: Project Manager - Level 3 | D29: =$K$5 -> 0 | E29: wks | F29: =(40*O29)*M29 -> 0 | G29: =SUM(D29*F29) -> 0 | L29: =SUM(G29+I29+K29) -> 0 | M29: =+M12 -> 0 | O29: =O12 -> 138.39252
C30: Project Manager - Level 2 | D30: =$K$5 -> 0 | E30: wks | F30: =(40*O30)*M30 -> 0 | G30: =SUM(D30*F30) -> 0 | L30: =SUM(G30+I30+K30) -> 0 | M30: =+M13 -> 0 | O30: =+O13 -> 126.66647 | P30: =+P13 -> 185 | X30: =+X13 -> 155
C31: Project Manager - Level 1 | D31: =$K$5 -> 0 | E31: wks | F31: =(40*O31)*M31 -> 0 | G31: =SUM(D31*F31) -> 0 | L31: =SUM(G31+I31+K31) -> 0 | M31: =+M14 -> 0 | O31: =+O14 -> 108.40544 | P31: =+P14 -> 163 | X31: =+X14 -> 130
C32: Project Administator | D32: =$K$5 -> 0 | E32: wks | F32: =(40*O32)*M32 -> 0 | G32: =SUM(D32*F32) -> 0 | L32: =SUM(G32+I32+K32) -> 0 | M32: =+M15 -> 0 | O32: =+O15 -> 76.481034 | P32: =+P15 -> 95 | X32: =+X15 -> 65
C33: Project Coordinator | D33: =$K$5 -> 0 | E33: wks | F33: =(40*O33)*M33 -> 0 | G33: =SUM(D33*F33) -> 0 | L33: =SUM(G33+I33+K33) -> 0 | M33: =+M16 -> 0 | O33: =+O16 -> 98.681546 | P33: =+P16 -> 81 | X33: =+X16 -> 60
C34: Assistant Project Manager | D34: =$K$5 -> 0 | E34: wks | F34: =(40*O34)*M34 -> 0 | G34: =SUM(D34*F34) -> 0 | L34: =SUM(G34+I34+K34) -> 0 | M34: =+M17 -> 0 | O34: =+O17 -> 95.143598 | P34: =+P17 -> 118 | X34: =+X17 -> 95
C35: Superintendent - Level 3 | D35: =$K$5 -> 0 | E35: wks | F35: =(40*O35)*M35 -> 0 | G35: =SUM(D35*F35) -> 0 | L35: =SUM(G35+I35+K35) -> 0 | M35: =+M18 -> 0 | O35: =+O18 -> 151.51479 | P35: =+P18 -> 183 | X35: =+X18 -> 194
C36: Superintendent - Level 2 | D36: =$K$5 -> 0 | E36: wks | F36: =(40*O36)*M36 -> 0 | G36: =SUM(D36*F36) -> 0 | L36: =SUM(G36+I36+K36) -> 0 | M36: =+M19 -> 0 | O36: =+O19 -> 127.18106 | P36: =+P19 -> 161 | X36: =+X19 -> 173
C37: Superintendent - Level 1 | D37: =$K$5 -> 0 | E37: wks | F37: =(40*O37)*M37 -> 0 | G37: =SUM(D37*F37) -> 0 | L37: =SUM(G37+I37+K37) -> 0 | M37: =+M20 -> 0 | O37: =+O20 -> 104.09203 | P37: =+P20 -> 121 | X37: =+X20 -> 155
C38: Assistant Superinterndent | D38: =$K$5 -> 0 | E38: wks | F38: =(40*O38)*M38 -> 0 | G38: =SUM(D38*F38) -> 0 | L38: =SUM(G38+I38+K38) -> 0 | M38: =+M21 -> 0 | O38: =+O21 -> 68.902786 | P38: =+P21 -> 84 | X38: =+X21 -> 95
C39: Foreman | D39: =$K$5 -> 0 | E39: wks | F39: =(40*O39)*M39 -> 0 | G39: =SUM(D39*F39) -> 0 | L39: =SUM(G39+I39+K39) -> 0 | M39: =+M23 -> 0 | O39: =+O23 -> 47.75772 | P39: =+P23 -> 65 | X39: =+X23 -> 65
C40: Accounting | D40: =$K$5 -> 0 | E40: wks | F40: =(40*O40)*M40 -> 0 | G40: =SUM(D40*F40) -> 0 | L40: =SUM(G40+I40+K40) -> 0 | M40: =+M24 -> 0 | O40: =+O24 -> 133.32852 | P40: =+P24 -> 80 | X40: =+X24 -> 90
C41: Safety Supervisor/Inspector | D41: =$K$5 -> 0 | E41: wks | F41: =(40*O41)*M41 -> 0 | G41: =SUM(D41*F41) -> 0 | L41: =SUM(G41+I41+K41) -> 0 | M41: =+M25 -> 0 | O41: =+O25 -> 91.694063 | P41: =+P25 -> 96 | X41: =+X25 -> 96
C42: Field Office - Contractor | L42: =SUM(L43:L62) -> 0
C43: Field Office Set Up / Removal - Double Wide | D43: 0 | E43: ea | H43: 16000 | I43: =SUM(D43*H43) -> 0 | J43: ` | L43: =SUM(G43+I43+K43) -> 0
C44: Field Office - Double Wide | D44: =$L$4 -> 0 | E44: mos | H44: 3800 | I44: =SUM(D44*H44) -> 0 | L44: =SUM(G44+I44+K44) -> 0
C45: Field Office Set Up / Removal - Single Wide | D45: =$L$4 -> 0 | E45: ea | H45: 15958 | I45: =SUM(D45*H45) -> 0 | L45: =SUM(G45+I45+K45) -> 0
C46: Field Office - Single Wide | D46: =$L$4 -> 0 | E46: mos | H46: 1900 | I46: =SUM(D46*H46) -> 0 | L46: =SUM(G46+I46+K46) -> 0
C47: Field Office Set Up / Removal - Connex | D47: =$L$4 -> 0 | E47: ea | H47: 1371 | I47: =SUM(D47*H47) -> 0 | L47: =SUM(G47+I47+K47) -> 0
C48: Field Office - Conex | D48: =$L$4 -> 0 | E48: mos | H48: 573 | I48: =SUM(D48*H48) -> 0 | L48: =SUM(G48+I48+K48) -> 0
C49: Connect Telephone Lines | D49: 0 | E49: ea | H49: 2000 | I49: =SUM(D49*H49) -> 0 | L49: =SUM(G49+I49+K49) -> 0
C50: Telephone | D50: =$L$4 -> 0 | E50: mos | H50: 250 | I50: =SUM(D50*H50) -> 0 | L50: =SUM(G50+I50+K50) -> 0
C51: Cellular Telephones | D51: =$L$4 -> 0 | E51: mos | H51: 0 | I51: =SUM(D51*H51) -> 0 | L51: =SUM(G51+I51+K51) -> 0 | N51: In labor rates
C52: Furniture | D52: 0 | E52: ls | H52: 500 | I52: =SUM(D52*H52) -> 0 | L52: =SUM(G52+I52+K52) -> 0
C53: Office Supplies | D53: =$L$4 -> 0 | E53: mos | H53: 100 | I53: =SUM(D53*H53) -> 0 | L53: =SUM(G53+I53+K53) -> 0
C54: Drinking Water | D54: =$L$4 -> 0 | E54: mos | H54: 50 | I54: =SUM(D54*H54) -> 0 | L54: =SUM(G54+I54+K54) -> 0
C55: Janitor Supplies/Cleaning | D55: =$L$4 -> 0 | E55: mos | H55: 250 | I55: =SUM(D55*H55) -> 0 | L55: =SUM(G55+I55+K55) -> 0
C56: Computers | D56: 0 | E56: ls | H56: 0 | I56: =SUM(D56*H56) -> 0 | L56: =SUM(G56+I56+K56) -> 0
C57: Printers | D57: 0 | E57: ls | H57: 500 | I57: =SUM(D57*H57) -> 0 | L57: =SUM(G57+I57+K57) -> 0
C58: Copy Machine | D58: =$L$4 -> 0 | E58: ls | H58: 2500 | I58: =SUM(D58*H58) -> 0 | L58: =SUM(G58+I58+K58) -> 0
C59: Alarm System | D59: =$L$4 -> 0 | E59: mos | H59: 0 | I59: =SUM(D59*H59) -> 0 | L59: =SUM(G59+I59+K59) -> 0
C60: Installation Office Equip. | D60: 0 | E60: ls | H60: 250 | I60: =SUM(D60*H60) -> 0 | L60: =SUM(G60+I60+K60) -> 0
C61: Storage Trailers Set Up / Removal | D61: 0 | E61: ea | H61: 840 | I61: =SUM(D61*H61) -> 0 | L61: =SUM(G61+I61+K61) -> 0 | N61: willscot 40' trailer
C62: Storage Trailers | D62: 0 | E62: mos | H62: 1200 | I62: =SUM(D62*H62) -> 0 | L62: =SUM(G62+I62+K62) -> 0 | N62: Rate - $1200 ea. per month
C63: Field Office - Owner | N63: =SUM(L64:L78) -> 0
C64: Field Office Set Up / Removal | D64: 1 | E64: ls | J64: 0 | K64: =SUM(D64*J64) -> 0 | L64: =SUM(G64+I64+K64) -> 0 | N64: assume not required
C65: Field Office | D65: =L4 -> 0 | E65: mos | J65: 0 | K65: =SUM(D65*J65) -> 0 | L65: =SUM(G65+I65+K65) -> 0 | N65: assume not required
C66: Connect Telephone Lines | D66: 1 | E66: ls | J66: 0 | K66: =SUM(D66*J66) -> 0 | L66: =SUM(G66+I66+K66) -> 0 | N66: assume not required
C67: Telephone | D67: =L4 -> 0 | E67: mos | J67: 0 | K67: =SUM(D67*J67) -> 0 | L67: =SUM(G67+I67+K67) -> 0 | N67: assume not required
C68: Cellular Telephones | D68: =L4+L5 -> 0 | E68: mos | J68: 0 | K68: =SUM(D68*J68) -> 0 | L68: =SUM(G68+I68+K68) -> 0 | N68: assume not required
C69: Furniture | D69: 1 | E69: ls | J69: 0 | K69: =SUM(D69*J69) -> 0 | L69: =SUM(G69+I69+K69) -> 0 | N69: assume not required
C70: Office Supplies | D70: =L4+L5 -> 0 | E70: mos | J70: 0 | K70: =SUM(D70*J70) -> 0 | L70: =SUM(G70+I70+K70) -> 0 | N70: assume not required
C71: Drinking Water | D71: =L4+L5 -> 0 | E71: mos | J71: 0 | K71: =SUM(D71*J71) -> 0 | L71: =SUM(G71+I71+K71) -> 0 | N71: assume not required
C72: Janitor Supplies | D72: =L4 -> 0 | E72: mos | J72: 0 | K72: =SUM(D72*J72) -> 0 | L72: =SUM(G72+I72+K72) -> 0 | N72: assume not required
C73: Computers | D73: 1 | E73: ls | J73: 0 | K73: =SUM(D73*J73) -> 0 | L73: =SUM(G73+I73+K73) -> 0 | N73: assume not required
C74: Printers | D74: 1 | E74: ls | J74: 0 | K74: =SUM(D74*J74) -> 0 | L74: =SUM(G74+I74+K74) -> 0 | N74: assume not required
C75: Copy Machine | D75: =L4+L5 -> 0 | E75: mos | J75: 0 | K75: =SUM(D75*J75) -> 0 | L75: =SUM(G75+I75+K75) -> 0 | N75: assume not required
C76: Fax Machine | D76: 1 | E76: ls | J76: 0 | K76: =SUM(D76*J76) -> 0 | L76: =SUM(G76+I76+K76) -> 0 | N76: assume not required
C77: Alarm System | D77: =L4 -> 0 | E77: mos | J77: 0 | K77: =SUM(D77*J77) -> 0 | L77: =SUM(G77+I77+K77) -> 0 | N77: assume not required
C78: Installation Office Equip. | D78: 1 | E78: ls | J78: 0 | K78: =SUM(D78*J78) -> 0 | L78: =SUM(G78+I78+K78) -> 0 | N78: assume not required
C79: Temporary Utilities | L79: =SUM(L80:L92) -> 0
C80: Temp. Electrical Service | D80: 0 | E80: ls | J80: 0 | K80: =SUM(D80*J80) -> 0 | L80: =SUM(G80+I80+K80) -> 0 | N80: by elect sub
C81: Temp. Electrical - Const. Phase | D81: =$L$4 -> 0 | E81: mos | J81: 0 | K81: =SUM(D81*J81) -> 0 | L81: =SUM(G81+I81+K81) -> 0 | N81: by owner
C82: Temp. Electrical - Operate Phase | D82: =L4 -> 0 | E82: mos | J82: 0 | K82: =SUM(D82*J82) -> 0 | L82: =SUM(G82+I82+K82) -> 0 | N82: by owner
C83: Temp. Wiring & Lighting | D83: 0 | E83: sf | J83: 0 | K83: =SUM(D83*J83) -> 0 | L83: =SUM(G83+I83+K83) -> 0 | N83: by elect sub
C84: Temporary Water - Service | D84: 0 | E84: ls | J84: 0 | K84: =SUM(D84*J84) -> 0 | L84: =SUM(G84+I84+K84) -> 0 | N84: by owner
C85: Temporary Water | D85: =L4 -> 0 | E85: mos | J85: 0 | K85: =SUM(D85*J85) -> 0 | L85: =SUM(G85+I85+K85) -> 0
C86: Temporary Toilets | D86: =L4 -> 0 | E86: mos | J86: 407 | K86: =SUM(D86*J86) -> 0 | L86: =SUM(G86+I86+K86) -> 0 | N86: 04/15/2024 united site services
C87: Temporary Toilet Set Up / Removal | D87: 0 | E87: ea | J87: 93 | K87: =SUM(D87*J87) -> 0 | L87: =SUM(G87+I87+K87) -> 0 | N87: 04/15/2024 united site services
C88: Temporary Washing Station | D88: 0 | E88: mos | J88: 407 | K88: =SUM(D88*J88) -> 0 | L88: =SUM(G88+I88+K88) -> 0 | N88: 04/15/2024 united site services
C89: Temporary Washing Station Set Up / Removal | D89: 0 | E89: ea | J89: 93 | K89: =SUM(D89*J89) -> 0 | L89: =SUM(G89+I89+K89) -> 0 | N89: 04/15/2024 united site services
C90: Temporary Holding Tanks | D90: =L4 -> 0 | E90: mos | J90: 0 | K90: =SUM(D90*J90) -> 0 | L90: =SUM(G90+I90+K90) -> 0
C91: Temporary Ventilation | D91: 0 | E91: ls | J91: 0 | K91: =SUM(D91*J91) -> 0 | L91: =SUM(G91+I91+K91) -> 0
C92: Temporary Cooling | D92: =L4 -> 0 | E92: mos | J92: 0 | K92: =SUM(D92*J92) -> 0 | L92: =SUM(G92+I92+K92) -> 0
C93: Equipment | L93: =SUM(L94:L96) -> 0
C94: Small Tools | D94: =$L$4 -> 0 | E94: mos | J94: 1500 | K94: =SUM(D94*J94) -> 0 | L94: =SUM(G94+I94+K94) -> 0
C95: Equipment Rental | D95: =L4 -> 0 | E95: mos | J95: 2500 | K95: =SUM(D95*J95) -> 0 | L95: =SUM(G95+I95+K95) -> 0
C96: Engineering Instruments | D96: 0 | E96: ls | J96: 1000 | K96: =SUM(D96*J96) -> 0 | L96: =SUM(G96+I96+K96) -> 0
C97: Security | L97: =SUM(L98:L115) -> 0
B98: 15000 | C98: Temporary Fence - 6' Post Driven w/ windscreen | D98: 0 | E98: lf | J98: 8.3 | K98: =J98*D98 -> 0 | L98: =SUM(G98+I98+K98) -> 0 | N98: rent national 4/15/2024
C99: Temporary Fence - 8' Post Driven w/ windscreen | D99: 0 | E99: lf | J99: 9.8 | K99: =J99*D99 -> 0 | L99: =SUM(G99+I99+K99) -> 0 | N99: rent national 4/15/2024
C100: Temporary Fence - 6' Panels w/ windscreen | D100: 0 | E100: lf | J100: 6.49 | K100: =SUM(D100*J100) -> 0 | L100: =SUM(G100+I100+K100) -> 0 | N100: rent national 4/15/2024
C101: Temporary Fence - 8' Panels w/ windscreen | D101: 0 | E101: lf | J101: 7.49 | K101: =SUM(D101*J101) -> 0 | L101: =SUM(G101+I101+K101) -> 0 | N101: rent national 4/15/2024
...

Sheet Cost Summary
A1: COST ESTIMATE (ROM)
A6: ='Area Calculations'!B4 -> Project Name
A7: ='Area Calculations'!B5 -> Location | F7: Gross (sf) | G7: ='Area Calculations'!I4 -> 0
F8: A/C (SF
F9: Build Duration (months) | G9: ='Area Calculations'!I5 -> 0
A11: =NOW() -> 46146.225
A13: CSI | B13: CSI DESCRIPTION | D13: TOTAL | E13: $ /GSF | F13: % | G13: Prev. | H13: Delta | I13: Notes
A15: 01A | B15: Surveying | D15: ='01A Surveying'!B117 -> 0 | E15: =D15/$G$7 -> #DIV/0! | F15: =D15/$D$123 -> #DIV/0! | H15: =D15-G15 -> 0
A16: 01B | B16: Materials Testing | D16: ='01B Material Testing'!B106 -> 0 | E16: =D16/$G$7 -> #DIV/0! | F16: =D16/$D$123 -> #DIV/0! | H16: =D16-G16 -> 0
A17: 01C | B17: Final Cleaning | D17: ='01C Final Cleaning'!B106 -> 0 | E17: =D17/$G$7 -> #DIV/0! | F17: =D17/$D$123 -> #DIV/0! | H17: =D17-G17 -> 0
A18: 02A | B18: Demolition | D18: ='02A Demolition'!B93 -> 0 | E18: =D18/$G$7 -> #DIV/0! | F18: =D18/$D$123 -> #DIV/0! | H18: =D18-G18 -> 0
A19: 02B | B19: Abatement; Environmental Protection | D19: ='02B Abatement'!B93 -> 0 | E19: =D19/$G$7 -> #DIV/0! | F19: =D19/$D$123 -> #DIV/0! | H19: =D19-G19 -> 0
A20: 03A | B20: Concrete (Conventional) | D20: ='03A Concrete'!B129 -> 0 | E20: =D20/$G$7 -> #DIV/0! | F20: =D20/$D$123 -> #DIV/0! | H20: =D20-G20 -> 0
A21: 03B | B21: Precast Hollow Core | D21: ='03B Precast Hollow Core'!B82 -> 0 | E21: =D21/$G$7 -> #DIV/0! | F21: =D21/$D$123 -> #DIV/0! | H21: =D21-G21 -> 0
A22: 03C | B22: Architectural Precast | D22: ='03C Architectural Precast'!B86 -> 0 | E22: =D22/$G$7 -> #DIV/0! | F22: =D22/$D$123 -> #DIV/0! | H22: =D22-G22 -> 0
A23: 03C | B23: Concrete (Tilt-Up) | D23: ='03C Concrete Tilt Up'!B82 -> 0 | E23: =D23/$G$7 -> #DIV/0! | F23: =D23/$D$123 -> #DIV/0! | H23: =D23-G23 -> 0
A24: 03D | B24: Structural Precast | D24: ='03D Structural Precast'!B132 -> 0 | E24: =D24/$G$7 -> #DIV/0! | F24: =D24/$D$123 -> #DIV/0! | H24: =D24-G24 -> 0
A25: 03E | B25: Cranes and Hoisting | D25: ='03E Cranes and Hoisting'!B132 -> 0 | E25: =D25/$G$7 -> #DIV/0! | F25: =D25/$D$123 -> #DIV/0! | H25: =D25-G25 -> 0
A26: 03F | B26: Concrete Restoration | D26: ='03F Concrete Restoration'!B132 -> 0 | E26: =D26/$G$7 -> #DIV/0! | F26: =D26/$D$123 -> #DIV/0! | H26: =D26-G26 -> 0
A27: 04A | B27: Masonry | D27: ='04A Masonry'!B122 -> 0 | E27: =D27/$G$7 -> #DIV/0! | F27: =D27/$D$123 -> #DIV/0! | H27: =D27-G27 -> 0
A28: 04B | B28: Cast Stone, Stone Veneer | D28: ='04B Stone Veneer'!B101 -> 0 | E28: =D28/$G$7 -> #DIV/0! | F28: =D28/$D$123 -> #DIV/0! | H28: =D28-G28 -> 0
A29: 05A | B29: Structural Steel | D29: ='05A Structural Steel'!B92 -> 0 | E29: =D29/$G$7 -> #DIV/0! | F29: =D29/$D$123 -> #DIV/0! | H29: =D29-G29 -> 0
A30: 05B | B30: Metal Trusses | D30: ='05B Metal Trusses'!B88 -> 0 | E30: =D30/$G$7 -> #DIV/0! | F30: =D30/$D$123 -> #DIV/0! | H30: =D30-G30 -> 0
A31: 05C | B31: Misc. Metals | D31: ='05C Misc. Metals'!B91 -> 0 | E31: =D31/$G$7 -> #DIV/0! | F31: =D31/$D$123 -> #DIV/0! | H31: =D31-G31 -> 0
A32: 05D | B32: Handrails & Railings | D32: ='05D Handrailings & Railings'!B91 -> 0 | E32: =D32/$G$7 -> #DIV/0! | F32: =D32/$D$123 -> #DIV/0! | H32: =D32-G32 -> 0
A33: 05E | B33: Glass Railings | D33: ='05E Glass Railings'!B91 -> 0 | E33: =D33/$G$7 -> #DIV/0! | F33: =D33/$D$123 -> #DIV/0! | H33: =D33-G33 -> 0
A34: 06A | B34: Rough Carpentry | D34: ='06A Rough Carpentry'!B103 -> 0 | E34: =D34/$G$7 -> #DIV/0! | F34: =D34/$D$123 -> #DIV/0! | H34: =D34-G34 -> 0
A35: 06C | B35: Wood Trusses | D35: ='06C Wood Trusses'!B106 -> 0 | E35: =D35/$G$7 -> #DIV/0! | F35: =D35/$D$123 -> #DIV/0! | H35: =D35-G35 -> 0
A36: 06D | B36: Interior Finish Cabinetry | D36: ='06D Interior Finish Carpentry'!B100 -> 0 | E36: =D36/$G$7 -> #DIV/0! | F36: =D36/$D$123 -> #DIV/0! | H36: =D36-G36 -> 0
A37: 06E | B37: Heavy Timber Construction | D37: ='06E Heavy Timber Construction'!B88 -> 0 | E37: =D37/$G$7 -> #DIV/0! | F37: =D37/$D$123 -> #DIV/0! | H37: =D37-G37 -> 0
A38: 06F | B38: Millwork | D38: ='06F Millwork'!B90 -> 0 | E38: =D38/$G$7 -> #DIV/0! | F38: =D38/$D$123 -> #DIV/0! | H38: =D38-G38 -> 0
A39: 06G | B39: Exterior Finish Carpentry | D39: ='06G Exterior Finish Carpent'!B100 -> 0 | E39: =D39/$G$7 -> #DIV/0! | F39: =D39/$D$123 -> #DIV/0! | H39: =D39-G39 -> 0
A40: 07B | B40: Sprayed Insulation | D40: ='07B Sprayed Insulation'!B94 -> 0 | E40: =D40/$G$7 -> #DIV/0! | F40: =D40/$D$123 -> #DIV/0! | H40: =D40-G40 -> 0
A41: 07C | B41: Fireproofing & Firestopping | D41: ='07C Fireproofing&Firestopping'!B85 -> 0 | E41: =D41/$G$7 -> #DIV/0! | F41: =D41/$D$123 -> #DIV/0! | H41: =D41-G41 -> 0
A42: 07D | B42: Roofing | D42: ='07D Roofing'!B89 -> 0 | E42: =D42/$G$7 -> #DIV/0! | F42: =D42/$D$123 -> #DIV/0! | H42: =D42-G42 -> 0
A43: 07E | B43: Caulking & Waterproofing | D43: ='07E Caulking & Waterproofing'!B100 -> 0 | E43: =D43/$G$7 -> #DIV/0! | F43: =D43/$D$123 -> #DIV/0! | H43: =D43-G43 -> 0
A44: 07F | B44: Siding | D44: ='07F Siding'!B95 -> 0 | E44: =D44/$G$7 -> #DIV/0! | F44: =D44/$D$123 -> #DIV/0! | H44: =D44-G44 -> 0
A45: 07H | B45: Panelized Exterior Skin | D45: ='07H Panelized Exterior Skin'!B94 -> 0 | E45: =D45/$G$7 -> #DIV/0! | F45: =D45/$D$123 -> #DIV/0! | H45: =D45-G45 -> 0
A46: 08A | B46: Doors, Frames, & Hardware | D46: ='08A Doors, Frames, & Hardware'!B82 -> 0 | E46: =D46/$G$7 -> #DIV/0! | F46: =D46/$D$123 -> #DIV/0! | H46: =D46-G46 -> 0
A47: 08B | B47: Overhead Coiling Doors | D47: ='08B Overhead Coiling Doors'!B79 -> 0 | E47: =D47/$G$7 -> #DIV/0! | F47: =D47/$D$123 -> #DIV/0! | H47: =D47-G47 -> 0
A48: 08C | B48: Glass and Glazing | D48: ='08C Glass and Glazing'!B105 -> 0 | E48: =D48/$G$7 -> #DIV/0! | F48: =D48/$D$123 -> #DIV/0! | H48: =D48-G48 -> 0
A49: 08D | B49: Skylights | D49: ='08D Skylights'!B84 -> 0 | E49: =D49/$G$7 -> #DIV/0! | F49: =D49/$D$123 -> #DIV/0! | H49: =D49-G49 -> 0
A50: 08E | B50: Mirrors | D50: ='08E Mirrors'!B84 -> 0 | E50: =D50/$G$7 -> #DIV/0! | F50: =D50/$D$123 -> #DIV/0! | H50: =D50-G50 -> 0
A51: 09A | B51: Stucco | D51: ='09A Stucco'!B87 -> 0 | E51: =D51/$G$7 -> #DIV/0! | F51: =D51/$D$123 -> #DIV/0! | H51: =D51-G51 -> 0
A52: 09B | B52: Drywall / Framing | D52: ='09B Drywall&Framing'!B92 -> 0 | E52: =D52/$G$7 -> #DIV/0! | F52: =D52/$D$123 -> #DIV/0! | H52: =D52-G52 -> 0
A53: 09C | B53: Acoustical Ceilings | D53: ='09C Acoustical Ceilings'!B87 -> 0 | E53: =D53/$G$7 -> #DIV/0! | F53: =D53/$D$123 -> #DIV/0! | H53: =D53-G53 -> 0
A54: 09D | B54: Acoustical Treatments | D54: ='09D Acoustical Treatment'!B87 -> 0 | E54: =D54/$G$7 -> #DIV/0! | F54: =D54/$D$123 -> #DIV/0! | H54: =D54-G54 -> 0
A55: 09E | B55: Tile & Stone | D55: ='09E Tile & Stone'!B116 -> 0 | E55: =D55/$G$7 -> #DIV/0! | F55: =D55/$D$123 -> #DIV/0! | H55: =D55-G55 -> 0
A56: 09F | B56: Flooring: Carpet and Resilient Flooring | D56: ='09F Carpet & Resilient'!B103 -> 0 | E56: =D56/$G$7 -> #DIV/0! | F56: =D56/$D$123 -> #DIV/0! | H56: =D56-G56 -> 0
A57: 09G | B57: Wood Flooring | D57: ='09G Wood Flooring'!B103 -> 0 | E57: =D57/$G$7 -> #DIV/0! | F57: =D57/$D$123 -> #DIV/0! | H57: =D57-G57 -> 0
A58: 09H | B58: Resinuous Flooring & Polished Concrete | D58: ='09H Resinuous & Polished C'!B105 -> 0 | E58: =D58/$G$7 -> #DIV/0! | F58: =D58/$D$123 -> #DIV/0! | H58: =D58-G58 -> 0
A59: 09I | B59: Painting | D59: ='09I Painting'!B104 -> 0 | E59: =D59/$G$7 -> #DIV/0! | F59: =D59/$D$123 -> #DIV/0! | H59: =D59-G59 -> 0
A60: 09J | B60: Venetian Plaster | D60: ='09J Venetian Plaster'!B104 -> 0 | E60: =D60/$G$7 -> #DIV/0! | F60: =D60/$D$123 -> #DIV/0! | H60: =D60-G60 -> 0
A61: 10A | B61: Signage | D61: ='10A Signage'!B86 -> 0 | E61: =D61/$G$7 -> #DIV/0! | F61: =D61/$D$123 -> #DIV/0! | H61: =D61-G61 -> 0
A62: 10B | B62: Operable Partitions | D62: ='10B Operable Partitions'!B86 -> 0 | E62: =D62/$G$7 -> #DIV/0! | F62: =D62/$D$123 -> #DIV/0! | H62: =D62-G62 -> 0
A63: 10C | B63: Toilet Partitions & Bathroom Accessories | D63: ='10C Toilet Partitions & Bath'!B126 -> 0 | E63: =D63/$G$7 -> #DIV/0! | F63: =D63/$D$123 -> #DIV/0! | H63: =D63-G63 -> 0
A64: 10D | B64: Shower enclosures | D64: ='10D Shower Enclosures'!B108 -> 0 | E64: =D64/$G$7 -> #DIV/0! | F64: =D64/$D$123 -> #DIV/0! | H64: =D64-G64 -> 0
A65: 10E | B65: Wall & Corner Guards | D65: ='10E Wall & Corner Guards'!B95 -> 0 | E65: =D65/$G$7 -> #DIV/0! | F65: =D65/$D$123 -> #DIV/0! | H65: =D65-G65 -> 0
A66: 10F | B66: Lockers | D66: ='10F Lockers'!B90 -> 0 | E66: =D66/$G$7 -> #DIV/0! | F66: =D66/$D$123 -> #DIV/0! | H66: =D66-G66 -> 0
A67: 10G | B67: Mesh Storage Lockers | D67: ='10G Mesh Sto Lockers'!B90 -> 0 | E67: =D67/$G$7 -> #DIV/0! | F67: =D67/$D$123 -> #DIV/0! | H67: =D67-G67 -> 0
A68: 10H | B68: Fireplaces | D68: ='10H Fireplaces'!B90 -> 0 | E68: =D68/$G$7 -> #DIV/0! | F68: =D68/$D$123 -> #DIV/0! | H68: =D68-G68 -> 0
A69: 10I | B69: Fire Extinguishers& Cabinets | D69: ='10I Fire Extinguishers&Cabinet'!B94 -> 0 | E69: =D69/$G$7 -> #DIV/0! | F69: =D69/$D$123 -> #DIV/0! | H69: =D69-G69 -> 0
A70: 10J | B70: Postal Specialties | D70: ='10J Postal Specialties'!B96 -> 0 | E70: =D70/$G$7 -> #DIV/0! | F70: =D70/$D$123 -> #DIV/0! | H70: =D70-G70 -> 0
A71: 10K | B71: Flood Mitigation | D71: ='10K Flood Mitigation'!B96 -> 0 | E71: =D71/$G$7 -> #DIV/0! | F71: =D71/$D$123 -> #DIV/0! | H71: =D71-G71 -> 0
A72: 10L | B72: Flagpoles | D72: ='10L Flagpoles'!B96 -> 0 | E72: =D72/$G$7 -> #DIV/0! | F72: =D72/$D$123 -> #DIV/0! | H72: =D72-G72 -> 0
A73: 11A | B73: Loading Dock Equipment | D73: ='11A Loading Dock Equip'!B97 -> 0 | E73: =D73/$G$7 -> #DIV/0! | F73: =D73/$D$123 -> #DIV/0! | H73: =D73-G73 -> 0
A74: 11B | B74: Food Service Equipment | D74: ='11B Food Service Equip'!B97 -> 0 | E74: =D74/$G$7 -> #DIV/0! | F74: =D74/$D$123 -> #DIV/0! | H74: =D74-G74 -> 0
A75: 11C | B75: Appliances | D75: ='11C Appliances'!B97 -> 0 | E75: =D75/$G$7 -> #DIV/0! | F75: =D75/$D$123 -> #DIV/0! | H75: =D75-G75 -> 0
A76: 11D | B76: Athletic Equipment & Surfacing | D76: ='11D Athletic Equipment&Surf'!B97 -> 0 | E76: =D76/$G$7 -> #DIV/0! | F76: =D76/$D$123 -> #DIV/0! | H76: =D76-G76 -> 0
A77: 12A | B77: Window Treatment | D77: ='12A Window Treatment'!B88 -> 0 | E77: =D77/$G$7 -> #DIV/0! | F77: =D77/$D$123 -> #DIV/0! | H77: =D77-G77 -> 0
A78: 12C | B78: Lab Casework | D78: ='12C Lab Casework'!B88 -> 0 | E78: =D78/$G$7 -> #DIV/0! | F78: =D78/$D$123 -> #DIV/0! | H78: =D78-G78 -> 0
A79: 13A | B79: Pre-Engineered Walkway Covers | D79: ='13A Pre Eng Walk Covers'!B96 -> 0 | E79: =D79/$G$7 -> #DIV/0! | F79: =D79/$D$123 -> #DIV/0! | H79: =D79-G79 -> 0
A80: 13B | B80: Swimming Pool | D80: ='13B Swimming Pools'!B96 -> 0 | E80: =D80/$G$7 -> #DIV/0! | F80: =D80/$D$123 -> #DIV/0! | H80: =D80-G80 -> 0
A81: 13C | B81: Awnings, Canopies, Bahama Shutters | D81: ='13C Awnings,Canopies,Shutters'!B96 -> 0 | E81: =D81/$G$7 -> #DIV/0! | F81: =D81/$D$123 -> #DIV/0! | H81: =D81-G81 -> 0
A82: 13D | B82: Saunas | D82: ='13D Saunas'!B96 -> 0 | E82: =D82/$G$7 -> #DIV/0! | F82: =D82/$D$123 -> #DIV/0! | H82: =D82-G82 -> 0
A83: 13E | B83: Playground Equipment | D83: ='13D Saunas'!B96 -> 0 | E83: =D83/$G$7 -> #DIV/0! | F83: =D83/$D$123 -> #DIV/0! | H83: =D83-G83 -> 0
A84: 13F | B84: Shade Structures | D84: ='13F Shade Structures'!B96 -> 0 | E84: =D84/$G$7 -> #DIV/0! | F84: =D84/$D$123 -> #DIV/0! | H84: =D84-G84 -> 0
A85: 13G | B85: Metal Buildings | D85: ='13G Metal Buildings'!B96 -> 0 | E85: =D85/$G$7 -> #DIV/0! | F85: =D85/$D$123 -> #DIV/0! | H85: =D85-G85 -> 0
A86: 14A | B86: Elevators | D86: ='14A Elevators'!B108 -> 0 | E86: =D86/$G$7 -> #DIV/0! | F86: =D86/$D$123 -> #DIV/0! | H86: =D86-G86 -> 0
A87: 14B | B87: Chutes & Collectors | D87: ='14B Chutes&Collectors'!B79 -> 0 | E87: =D87/$G$7 -> #DIV/0! | F87: =D87/$D$123 -> #DIV/0! | H87: =D87-G87 -> 0
A88: 14C | B88: Elevator Interiors/Modernization | D88: ='14C Elevator Interior&Modern'!B107 -> 0 | E88: =D88/$G$7 -> #DIV/0! | F88: =D88/$D$123 -> #DIV/0! | H88: =D88-G88 -> 0
A89: 14D | B89: Wheelchair Lifts | D89: ='14D Wheelchair Lifts'!B96 -> 0 | E89: =D89/$G$7 -> #DIV/0! | F89: =D89/$D$123 -> #DIV/0! | H89: =D89-G89 -> 0
A90: 14E | B90: Vehicle Lifts | D90: ='14E Vehicle Lifts'!B96 -> 0 | E90: =D90/$G$7 -> #DIV/0! | F90: =D90/$D$123 -> #DIV/0! | H90: =D90-G90 -> 0
A91: 21A | B91: Fire Sprinkler | D91: ='21A Fire Sprinkler'!B101 -> 0 | E91: =D91/$G$7 -> #DIV/0! | F91: =D91/$D$123 -> #DIV/0! | H91: =D91-G91 -> 0
A92: 22A | B92: Plumbing | D92: ='22A Plumbing '!B127 -> 0 | E92: =D92/$G$7 -> #DIV/0! | F92: =D92/$D$123 -> #DIV/0! | H92: =D92-G92 -> 0
A93: 23A | B93: HVAC | D93: ='23A HVAC'!B131 -> 0 | E93: =D93/$G$7 -> #DIV/0! | F93: =D93/$D$123 -> #DIV/0! | H93: =D93-G93 -> 0
A94: 26A | B94: Electrical | D94: ='26A Electrical'!B141 -> 0 | E94: =D94/$G$7 -> #DIV/0! | F94: =D94/$D$123 -> #DIV/0! | H94: =D94-G94 -> 0
A95: 27A | B95: Fire Alarm | D95: ='27A Fire Alarm'!B88 -> 0 | E95: =D95/$G$7 -> #DIV/0! | F95: =D95/$D$123 -> #DIV/0! | H95: =D95-G95 -> 0
A96: 28A | B96: Low Voltage | D96: ='28A Low Voltage'!B87 -> 0 | E96: =D96/$G$7 -> #DIV/0! | F96: =D96/$D$123 -> #DIV/0! | H96: =D96-G96 -> 0
A97: 31A | B97: Sitework | D97: ='31A Sitework'!B191 -> 0 | E97: =D97/$G$7 -> #DIV/0! | F97: =D97/$D$123 -> #DIV/0! | H97: =D97-G97 -> 0
A98: 31B | B98: Dewatering | D98: ='31B Dewatering'!B83 -> 0 | E98: =D98/$G$7 -> #DIV/0! | F98: =D98/$D$123 -> #DIV/0! | H98: =D98-G98 -> 0
A99: 31D | B99: Soil Improvements | D99: ='31D Soil Improvements'!B84 -> 0 | E99: =D99/$G$7 -> #DIV/0! | F99: =D99/$D$123 -> #DIV/0! | H99: =D99-G99 -> 0
A100: 31F | B100: Sheet Piling | D100: ='31F Sheet Piling'!B81 -> 0 | E100: =D100/$G$7 -> #DIV/0! | F100: =D100/$D$123 -> #DIV/0! | H100: =D100-G100 -> 0
A101: 31G | B101: Auger Cast Piles | D101: ='31G Auger Cast Piles'!B81 -> 0 | E101: =D101/$G$7 -> #DIV/0! | F101: =D101/$D$123 -> #DIV/0! | H101: =D101-G101 -> 0
A102: 32A | B102: Pavers | D102: ='32A Pavers'!B95 -> 0 | E102: =D102/$G$7 -> #DIV/0! | F102: =D102/$D$123 -> #DIV/0! | H102: =D102-G102 -> 0
A103: 32B | B103: Site Furnishings | D103: ='32B Site Furnishings'!B83 -> 0 | E103: =D103/$G$7 -> #DIV/0! | F103: =D103/$D$123 -> #DIV/0! | H103: =D103-G103 -> 0
A104: 32C | B104: Landscape and Irrigation | D104: ='32C Landscape and Irrigation'!B96 -> 0 | E104: =D104/$G$7 -> #DIV/0! | F104: =D104/$D$123 -> #DIV/0! | H104: =D104-G104 -> 0
A105: 32D | B105: Fencing | D105: ='32D Fencing'!B88 -> 0 | E105: =D105/$G$7 -> #DIV/0! | F105: =D105/$D$123 -> #DIV/0! | H105: =D105-G105 -> 0
A106: 32E | B106: Synthetic Fields | D106: ='32E Synthetic Fields'!B116 -> 0 | E106: =D106/$G$7 -> #DIV/0! | F106: =D106/$D$123 -> #DIV/0! | H106: =D106-G106 -> 0
A107: 35A | B107: Marine Work | D107: ='35A Marine Work'!B92 -> 0 | E107: =D107/$G$7 -> #DIV/0! | F107: =D107/$D$123 -> #DIV/0! | H107: =D107-G107 -> 0
...

Sheet IDS
G1: Hedrick Plug
F2: X | G2: Excluded
B3: BACK TO SUMMARY SHEET | F3: I | G3: Included | H3: Bidder 1 | J3: Bidder 2 | L3: Bidder 3 | N3: Bidder 4 | P3: Bidder5 | R3: Bidder6
A4: Project: | B4: ='[1]Area Calculations'!B4 -> 0 | G4: Company | H4: HB Construction
A5: Trade: | B5: IDS Services | G5: Contact | H5: Butch Carmichael
A6: CSI Code: | G6: Phone | H6: 561-225-4868
A7: Date: | G7: Email | H7: <bcarmichael@hedrickbrothers.com>
A8: Adjusted Bid | G8: Adjusted Bid | H8: =I99 -> 0 | J8: =K99 -> 0 | L8: =M99 -> 0 | N8: =O99 -> 0 | P8: =Q99 -> 0 | R8: =S99 -> 0
A9: BID DOCUMENTS: | C9: Plan/ Spec. Package | D9: QTY | E9: U/M | F9: Unit Cost | G9: Subtotal | H9: Yes/No | I9: Price | J9: Yes/No | K9: Price | L9: Yes/No | M9: Price | N9: Yes/No | O9: Price | P9: Yes/No | Q9: Price | R9: Yes/No | S9: Price
B10: Plans By Division
B11: ='[1]Area Calculations'!J54 -> 0 | C11: P
B12: ='[1]Area Calculations'!J55 -> 0 | C12: P
B13: ='[1]Area Calculations'!J56 -> 0 | C13: P
B14: ='[1]Area Calculations'!J57 -> 0 | C14: P
B15: ='[1]Area Calculations'!J58 -> 0 | C15: P
B16: ='[1]Area Calculations'!J59 -> 0 | C16: P
B17: ='[1]Area Calculations'!J60 -> 0 | C17: P
B18: ='[1]Area Calculations'!J61 -> 0 | C18: P
B19: ='[1]Area Calculations'!J62 -> 0 | C19: P
B21: Survey
B22: OCIP Insurance per exhibit
B23: GENERAL INCLUSIONS
B24: INCLUDES ALL SALES TAX
B25: ALL HOISTING & RIGGING REQUIRED TO COMPLETE THIS SCOPE
B26: PROVIDE P&P BONDS
B27: FLORIDA STATE CONTRACTORS LIC.
B28: GENERAL LIABILITY AND WORKERS COMP. INSURANCE LIMITS
B29: STATE AND LOCAL TAXES
B30: SPECIFIC TRADE SCOPE OF WORK REQUIREMENTS
B31: BASE BID | D31: 1 | E31: EA
B33: Pre-construction Modeling/BIM Execution Plan Meetings
B34: BIM Execution Plan Meeting including writing of BEP | H34: i
B35: Initial Jobsite Visit | H35: x
B36: Model Architectural | H36: i
B37: Model Structural | H37: i
B38: Model Mechanical/HVAC | H38: i
B39: Model Plumbing | H39: i
B40: Model Electrical | H40: x
B41: Model Fire Sprinkler | H41: x
B42: Model Civil | H42: x
B43: Model FF&E | H43: x
B45: Pre-construction - Digital Scanning
B46: Drone Mapping | H46: x
B47: Laser Scan of Existing Building after Demo | H47: x
B48: Photos of Existing Furniture to be Modeled | H48: x
B50: Pre-construction - BIM Coordination Meetings/ Clash Meetings
B51: Coordination/ Clash Meetings | H51: i
B52: Modification of Architectural Model | H52: i
B53: Modification of Structural Model | H53: i
B54: Modification of Mechanical/HVAC Model | H54: i
B55: Modification of Plumbing Model | H55: i
B56: Modification of Electrical Model | H56: x
B57: Modification of Fire Sprinkler Model | H57: x
B58: Modification of Civil Model | H58: x
B59: Modification of FF&E Model | H59: x
B61: Construction - BIM Coordination Meetings/ Clash Meetings
B62: Coordination/ Clash Meetings | H62: i
B63: Modification of Architectural Model | H63: i
B64: Modification of Structural Model | H64: i
B65: Modification of Mechanical/HVAC Model | H65: i
B66: Modification of Plumbing Model | H66: i
B67: Modification of Electrical Model | H67: x
B68: Modification of Fire Sprinkler Model | H68: x
B69: Modification of Civil Model | H69: x
B70: Modification of FF&E Model | H70: x
B72: As-Built Digital Scanning
B73: Pre-Drywall Laser Scan | H73: x
B74: Laser Scan to Verify Installation | H74: x
B76: Closeout Documents/ As-Builts
B77: Link RFIs to Model | H77: x
B78: Link Submittals to Model | H78: x
B79: Link O&M Documents to Model | H79: x
B80: Link Warranties & Guarantees to Model | H80: x
B82: Additional Services
B83: Additional Jobsite Visits | H83: x
B84: Interior Renderings | H84: x
B85: Exterior Renderings | H85: x
B86: 3D Fly Through | H86: x
B87: 4D Simulation | H87: x
B88: VR Presentations | H88: x
B89: Full Virtual Tour | H89: x
B90: Site Logistics | H90: x
B91: 5D Quantity Take-Off | H91: x
B92: Space Planning | H92: x
B93: Other: | H93: x
F95: SUBTOTAL | I95: =SUM(I31:I94) -> 0 | K95: =SUM(K31:K94) -> 0 | M95: =SUM(M31:M94) -> 0 | O95: =SUM(O31:O94) -> 0 | Q95: =SUM(Q31:Q94) -> 0 | S95: =SUM(S31:S94) -> 0
F96: BOND RATE | H96: 0 | J96: 0 | L96: 0 | N96: 0 | P96: 0 | R96: 0
F97: BOND AMOUNT | I97: =H96*I95 -> 0 | K97: =J96*K95 -> 0 | M97: =L96*M95 -> 0 | O97: =N96*O95 -> 0 | Q97: =P96*Q95 -> 0 | S97: =R96*S95 -> 0
F99: ADJUSTED TOTAL | I99: =SUM(I95:I97) -> 0 | K99: =SUM(K95:K97) -> 0 | M99: =SUM(M95:M97) -> 0 | O99: =SUM(O95:O97) -> 0 | Q99: =SUM(Q95:Q97) -> 0 | S99: =SUM(S95:S97) -> 0
F100: Cost per SF | I100: =I99/'[1]Area Calculations'!$G$4 -> #DIV/0! | K100: =K99/'[1]Area Calculations'!$G$4 -> #DIV/0! | M100: =M99/'[1]Area Calculations'!$G$4 -> #DIV/0! | O100: =O99/'[1]Area Calculations'!$G$4 -> #DIV/0! | Q100: =Q99/'[1]Area Calculations'!$G$4 -> #DIV/0! | R100: =R99/'[1]Area Calculations'!$G$4 -> #DIV/0! | S100: =S99/'[1]Cost Summary'!#REF! -> #REF!
F101: Cost per Unit | I101: =I99/'[1]Area Calculations'!$G$9 -> #DIV/0! | K101: =K99/'[1]Area Calculations'!$G$9 -> #DIV/0! | M101: =M99/'[1]Area Calculations'!$G$9 -> #DIV/0! | O101: =O99/'[1]Area Calculations'!$G$9 -> #DIV/0! | Q101: =Q99/'[1]Area Calculations'!$G$9 -> #DIV/0! | R101: =R99/'[1]Area Calculations'!$G$9 -> #DIV/0! | S101: =S99/'[1]Cost Summary'!#REF! -> #REF!
A103: QUALIFICATIONS
A107: EXCLUSIONS/OWNER PROVIDED ITEMS:
A111: ALTERNATES:
A115: PROPOSED VE (Provide Clear Description):
A119: FULLY LOADED LABOR RATES
B120: Laborer
B121: Mechanic
B122: Superintendent
B123: Project Manager
...

Sheet 01A Surveying
G1: Hedrick Plug
F2: X | G2: Excluded
B3: BACK TO SUMMARY SHEET | F3: I | G3: Included | H3: Bidder 1 | J3: Bidder 2 | L3: Bidder 3 | N3: Bidder 4 | P3: Bidder5 | R3: Bidder6
A4: Project: | B4: ='Area Calculations'!B4 -> Project Name | G4: Company
A5: Trade: | B5: Surveying | G5: Contact
A6: CSI Code: | B6: 01A | G6: Phone
A7: Date: | G7: Email
A8: Adjusted Bid | G8: Adjusted Bid | H8: =I81 -> 0 | J8: =K81 -> 0 | L8: =M81 -> 0 | N8: =O81 -> 0 | P8: =Q81 -> 0 | R8: =S81 -> 0
A9: BID DOCUMENTS: | C9: Plan/ Spec. Package | D9: QTY | E9: U/M | F9: Unit Cost | G9: Subtotal | H9: Yes/No | I9: Price | J9: Yes/No | K9: Price | L9: Yes/No | M9: Price | N9: Yes/No | O9: Price | P9: Yes/No | Q9: Price | R9: Yes/No | S9: Price
B10: Plans By Division
B11: ='Area Calculations'!L62 -> Architectural Drawings by | C11: P
B12: ='Area Calculations'!L63 -> Structural Drawings by | C12: P
B13: ='Area Calculations'!L64 -> MEP FA FP Drawings by | C13: P
B14: ='Area Calculations'!L65 -> Civil Drawings by | C14: P
B15: ='Area Calculations'!L66 -> Land scape Drawings by | C15: P
B16: ='Area Calculations'!L67 -> Kitchen Drawings by | C16: P
B17: ='Area Calculations'!L68 -> Storefront Designer by | C17: P
B18: ='Area Calculations'!L69 -> Geotech report by | C18: P
B19: ='Area Calculations'!L70 -> Specifications | C19: P
B21: Surveying
B22: OCIP Insurance per exhibit
B23: GENERAL INCLUSIONS
B24: INCLUDES ALL SALES TAX
B25: ALL HOISTING & RIGGING REQUIRED TO COMPLETE THIS SCOPE
B26: PROVIDE P&P BONDS
B27: FLORIDA STATE CONTRACTORS LIC.
B28: GENERAL LIABILITY AND WORKERS COMP. INSURANCE LIMITS
B29: STATE AND LOCAL TAXES
B30: COMPASS
B31: SPECIFIC TRADE SCOPE OF WORK REQUIREMENTS
B32: BASE BID | D32: 1 | E32: EA
B34: Set Boundary
B35: Stake Building corners
B36: Parking Lot subgrade
B37: Parking Lot Base Rock
B38: Turn Lane subgrade
B39: Turn Lane baserock
B40: Tin tabs for curbs and tree islands | H40: i
B41: Sidewalks
B42: Curbing
H43: x
B44: Utilities
B45: Water Layout | H45: x
B46: Sanitary-Layout
B47: Storm-Layout | H47: i
B49: Building
B50: Building Sign
B51: Stake Building-5'off-sets
B52: Form board survey
B53: Dumpster enclosure
B54: Light Poles
B55: Final survey
B56: FEMA Certificate
B58: As-Builts
B59: Water Service
B60: Sanitary Service
B61: Storm Drainage
... B65: Additional Staking/Re-Staking
F77: SUBTOTAL | I77: =SUM(I32:I76) -> 0 | K77: =SUM(K32:K76) -> 0 | M77: =SUM(M32:M76) -> 0 | O77: =SUM(O32:O76) -> 0 | Q77: =SUM(Q32:Q76) -> 0 | S77: =SUM(S32:S76) -> 0
F78: BOND RATE | H78: 0 | J78: 0 | L78: 0 | N78: 0 | P78: 0 | R78: 0
F79: BOND AMOUNT | I79: =H78*I77 -> 0 | K79: =J78*K77 -> 0 | M79: =L78*M77 -> 0 | O79: =N78*O77 -> 0 | Q79: =P78*Q77 -> 0 | S79: =R78*S77 -> 0
F81: ADJUSTED TOTAL | I81: =SUM(I77:I79) -> 0 | K81: =SUM(K77:K79) -> 0 | M81: =SUM(M77:M79) -> 0 | O81: =SUM(O77:O79) -> 0 | Q81: =SUM(Q77:Q79) -> 0 | S81: =SUM(S77:S79) -> 0
F82: Cost per SF | I82: =I81/'Area Calculations'!$I$4 -> #DIV/0! | K82: =K81/'Area Calculations'!$I$4 -> #DIV/0! | M82: =M81/'Area Calculations'!$I$4 -> #DIV/0! | O82: =O81/'Area Calculations'!$I$4 -> #DIV/0! | Q82: =Q81/'Area Calculations'!$I$4 -> #DIV/0! | R82: =R81/'Area Calculations'!$I$4 -> #DIV/0! | S82: =S81/'Cost Summary'!#REF! -> #REF!
F83: Cost per Unit | I83: =I81/'Area Calculations'!#REF! -> #REF! | K83: =K81/'Area Calculations'!#REF! -> #REF! | M83: =M81/'Area Calculations'!#REF! -> #REF! | O83: =O81/'Area Calculations'!#REF! -> #REF! | Q83: =Q81/'Area Calculations'!#REF! -> #REF! | R83: =R81/'Area Calculations'!#REF! -> #REF! | S83: =S81/'Cost Summary'!#REF! -> #REF!
A85: QUALIFICATIONS
A89: EXCLUSIONS/OWNER PROVIDED ITEMS:
A93: ALTERNATES:
A97: PROPOSED VE (Provide Clear Description):
A101: FULLY LOADED LABOR RATES
B102: Laborer
B103: Mechanic
B104: Superintendent
B105: Project Manager
A107: SCHEDULE
B108: Prepared shop drawings/submittals
B109: Mobilization
B110: Total duration to complete scope of work
A112: Winner
A113: Company
A114: Contact
A115: Phone
A116: Email
A117: Base Bid
B119: Need Prequalification
B120: Prequalified

Sheet 01B Material Testing
G1: Hedrick Plug
F2: X | G2: Excluded
B3: BACK TO SUMMARY SHEET | F3: I | G3: Included | H3: Bidder 1 | J3: Bidder 2 | L3: Bidder 3 | N3: Bidder 4 | P3: Bidder5 | R3: Bidder6
A4: Project: | B4: ='Area Calculations'!B4 -> Project Name | G4: Company
A5: Trade: | B5: Material Testing | G5: Contact
A6: CSI Code: | B6: 01B | G6: Phone
A7: Date: | G7: Email
A8: Adjusted Bid | G8: Adjusted Bid | H8: =I70 -> 0 | J8: =K70 -> 0 | L8: =M70 -> 0 | N8: =O70 -> 0 | P8: =Q70 -> 0 | R8: =S70 -> 0
A9: BID DOCUMENTS: | C9: Plan/ Spec. Package | D9: QTY | E9: U/M | F9: Unit Cost | G9: Subtotal | H9: Yes/No | I9: Price | J9: Yes/No | K9: Price | L9: Yes/No | M9: Price | N9: Yes/No | O9: Price | P9: Yes/No | Q9: Price | R9: Yes/No | S9: Price
B10: Plans By Division
B11: ='Area Calculations'!L62 -> Architectural Drawings by | C11: P
B12: ='Area Calculations'!L63 -> Structural Drawings by | C12: P
B13: ='Area Calculations'!L64 -> MEP FA FP Drawings by | C13: P
B14: ='Area Calculations'!L65 -> Civil Drawings by | C14: P
B15: ='Area Calculations'!L66 -> Land scape Drawings by | C15: P
B16: ='Area Calculations'!L67 -> Kitchen Drawings by | C16: P
B17: ='Area Calculations'!L68 -> Storefront Designer by | C17: P
B18: ='Area Calculations'!L69 -> Geotech report by | C18: P
B19: ='Area Calculations'!L70 -> Specifications | C19: P
B21: Material Testing
B22: GENERAL INCLUSIONS
B23: INCLUDES ALL SALES TAX
B24: ALL HOISTING & RIGGING REQUIRED TO COMPLETE THIS SCOPE
B25: PROVIDE P&P BONDS
B26: FLORIDA STATE CONTRACTORS LIC.
B27: GENERAL LIABILITY AND WORKERS COMP. INSURANCE LIMITS
B28: STATE AND LOCAL TAXES
B29: COMPASS
B30: SPECIFIC TRADE SCOPE OF WORK REQUIREMENTS
B31: BASE BID
H36: x
H37: i
F66: SUBTOTAL | I66: =SUM(I22:I65) -> 0 | K66: =SUM(K22:K65) -> 0 | M66: =SUM(M22:M65) -> 0 | O66: =SUM(O22:O65) -> 0 | Q66: =SUM(Q22:Q65) -> 0 | S66: =SUM(S22:S65) -> 0
F67: BOND RATE | H67: 0 | J67: 0 | L67: 0 | N67: 0 | P67: 0 | R67: 0
F68: BOND AMOUNT | I68: =H67*I66 -> 0 | K68: =J67*K66 -> 0 | M68: =L67*M66 -> 0 | O68: =N67*O66 -> 0 | Q68: =P67*Q66 -> 0 | S68: =R67*S66 -> 0
F70: ADJUSTED TOTAL | I70: =SUM(I66:I68) -> 0 | K70: =SUM(K66:K68) -> 0 | M70: =SUM(M66:M68) -> 0 | O70: =SUM(O66:O68) -> 0 | Q70: =SUM(Q66:Q68) -> 0 | S70: =SUM(S66:S68) -> 0
F71: Cost per SF | I71: =I70/'Area Calculations'!$I$4 -> #DIV/0! | K71: =K70/'Area Calculations'!$I$4 -> #DIV/0! | M71: =M70/'Area Calculations'!$I$4 -> #DIV/0! | O71: =O70/'Area Calculations'!$I$4 -> #DIV/0! | Q71: =Q70/'Area Calculations'!$I$4 -> #DIV/0! | S71: =S70/'Area Calculations'!$I$4 -> #DIV/0!
F72: Cost per Unit | I72: =I70/'Area Calculations'!#REF! -> #REF! | K72: =K70/'Area Calculations'!#REF! -> #REF! | M72: =M70/'Area Calculations'!#REF! -> #REF! | O72: =O70/'Area Calculations'!#REF! -> #REF! | Q72: =Q70/'Area Calculations'!#REF! -> #REF! | S72: =S70/'Area Calculations'!#REF! -> #REF!
A74: QUALIFICATIONS
A78: EXCLUSIONS/OWNER PROVIDED ITEMS:
A82: ALTERNATES:
A86: PROPOSED VE (Provide Clear Description):
A90: FULLY LOADED LABOR RATES
B91: Laborer
B92: Mechanic
B93: Superintendent
B94: Project Manager
A96: SCHEDULE
B97: Prepared shop drawings/submittals
B98: Mobilization
B99: Total duration to complete scope of work
A101: Winner
A102: Company
A103: Contact
A104: Phone
A105: Email
A106: Base Bid
B108: Need Prequalification
B109: Prequalified

Sheet 01C Final Cleaning
G1: Hedrick Plug
F2: X | G2: Excluded
B3: BACK TO SUMMARY SHEET | F3: I | G3: Included | H3: Bidder 1 | J3: Bidder 2 | L3: Bidder 3 | N3: Bidder 4 | P3: Bidder5 | R3: Bidder6
A4: Project: | B4: ='Area Calculations'!B4 -> Project Name | G4: Company
A5: Trade: | B5: Final Cleaning | G5: Contact
A6: CSI Code: | B6: 01C | G6: Phone
A7: Date: | G7: Email
A8: Adjusted Bid | G8: Adjusted Bid | H8: =I70 -> 0 | J8: =K70 -> 0 | L8: =M70 -> 0 | N8: =O70 -> 0 | P8: =Q70 -> 0 | R8: =S70 -> 0
A9: BID DOCUMENTS: | C9: Plan/ Spec. Package | D9: QTY | E9: U/M | F9: Unit Cost | G9: Subtotal | H9: Yes/No | I9: Price | J9: Yes/No | K9: Price | L9: Yes/No | M9: Price | N9: Yes/No | O9: Price | P9: Yes/No | Q9: Price | R9: Yes/No | S9: Price
B10: Plans By Division
B11: ='Area Calculations'!L62 -> Architectural Drawings by | C11: P
B12: ='Area Calculations'!L63 -> Structural Drawings by | C12: P
B13: ='Area Calculations'!L64 -> MEP FA FP Drawings by | C13: P
B14: ='Area Calculations'!L65 -> Civil Drawings by | C14: P
B15: ='Area Calculations'!L66 -> Land scape Drawings by | C15: P
B16: ='Area Calculations'!L67 -> Kitchen Drawings by | C16: P
B17: ='Area Calculations'!L68 -> Storefront Designer by | C17: P
B18: ='Area Calculations'!L69 -> Geotech report by | C18: P
B19: ='Area Calculations'!L70 -> Specifications | C19: P
B21: Final Cleaning
B22: GENERAL INCLUSIONS
B23: INCLUDES ALL SALES TAX
B24: ALL HOISTING & RIGGING REQUIRED TO COMPLETE THIS SCOPE
B25: PROVIDE P&P BONDS
B26: FLORIDA STATE CONTRACTORS LIC.
B27: GENERAL LIABILITY AND WORKERS COMP. INSURANCE LIMITS
B28: STATE AND LOCAL TAXES
B29: COMPASS
B30: SPECIFIC TRADE SCOPE OF WORK REQUIREMENTS
B31: BASE BID
H36: x
H37: i
F66: SUBTOTAL | I66: =SUM(I22:I65) -> 0 | K66: =SUM(K22:K65) -> 0 | M66: =SUM(M22:M65) -> 0 | O66: =SUM(O22:O65) -> 0 | Q66: =SUM(Q22:Q65) -> 0 | S66: =SUM(S22:S65) -> 0
F67: BOND RATE | H67: 0 | J67: 0 | L67: 0 | N67: 0 | P67: 0 | R67: 0
F68: BOND AMOUNT | I68: =H67*I66 -> 0 | K68: =J67*K66 -> 0 | M68: =L67*M66 -> 0 | O68: =N67*O66 -> 0 | Q68: =P67*Q66 -> 0 | S68: =R67*S66 -> 0
F70: ADJUSTED TOTAL | I70: =SUM(I66:I68) -> 0 | K70: =SUM(K66:K68) -> 0 | M70: =SUM(M66:M68) -> 0 | O70: =SUM(O66:O68) -> 0 | Q70: =SUM(Q66:Q68) -> 0 | S70: =SUM(S66:S68) -> 0
F71: Cost per SF | I71: =I70/'Area Calculations'!$I$4 -> #DIV/0! | K71: =K70/'Area Calculations'!$I$4 -> #DIV/0! | M71: =M70/'Area Calculations'!$I$4 -> #DIV/0! | O71: =O70/'Area Calculations'!$I$4 -> #DIV/0! | Q71: =Q70/'Area Calculations'!$I$4 -> #DIV/0! | S71: =S70/'Area Calculations'!$I$4 -> #DIV/0!
F72: Cost per Unit | I72: =I70/'Area Calculations'!#REF! -> #REF! | K72: =K70/'Area Calculations'!#REF! -> #REF! | M72: =M70/'Area Calculations'!#REF! -> #REF! | O72: =O70/'Area Calculations'!#REF! -> #REF! | Q72: =Q70/'Area Calculations'!#REF! -> #REF! | S72: =S70/'Area Calculations'!#REF! -> #REF!
A74: QUALIFICATIONS
A78: EXCLUSIONS/OWNER PROVIDED ITEMS:
A82: ALTERNATES:
A86: PROPOSED VE (Provide Clear Description):
A90: FULLY LOADED LABOR RATES
B91: Laborer
B92: Mechanic
B93: Superintendent
B94: Project Manager
A96: SCHEDULE
B97: Prepared shop drawings/submittals
B98: Mobilization
B99: Total duration to complete scope of work
A101: Winner
A102: Company
A103: Contact
A104: Phone
A105: Email
A106: Base Bid
B108: Need Prequalification
B109: Prequalified

Sheet 02A Demolition
G1: Hedrick Plug
F2: X | G2: Excluded
B3: BACK TO SUMMARY SHEET | F3: I | G3: Included | H3: Bidder 1 | J3: Bidder 2 | L3: Bidder 3 | N3: Bidder 4 | P3: Bidder5 | R3: Bidder6
A4: Project: | B4: ='Area Calculations'!B4 -> Project Name | G4: Company
A5: Trade: | B5: Demolition | G5: Contact
A6: CSI Code: | B6: 02A | G6: Phone
A7: Date: | G7: Email
A8: Adjusted Bid | G8: Adjusted Bid | H8: =I57 -> 0 | J8: =K57 -> 0 | L8: =M57 -> 0 | N8: =O57 -> 0 | P8: =Q57 -> 0 | R8: =S57 -> 0
A9: BID DOCUMENTS: | C9: Plan/ Spec. Package | D9: QTY | E9: U/M | F9: Unit Cost | G9: Subtotal | H9: Yes/No | I9: Price | J9: Yes/No | K9: Price | L9: Yes/No | M9: Price | N9: Yes/No | O9: Price | P9: Yes/No | Q9: Price | R9: Yes/No | S9: Price
B10: Plans By Division
B11: ='Area Calculations'!L62 -> Architectural Drawings by | C11: P
B12: ='Area Calculations'!L63 -> Structural Drawings by | C12: P
B13: ='Area Calculations'!L64 -> MEP FA FP Drawings by | C13: P
B14: ='Area Calculations'!L65 -> Civil Drawings by | C14: P
B15: ='Area Calculations'!L66 -> Land scape Drawings by | C15: P
B16: ='Area Calculations'!L67 -> Kitchen Drawings by | C16: P
B17: ='Area Calculations'!L68 -> Storefront Designer by | C17: P
B18: ='Area Calculations'!L69 -> Geotech report by | C18: P
B19: ='Area Calculations'!L70 -> Specifications | C19: P
B21: Demolition
B22: OCIP Insurance per exhibit
B23: GENERAL INCLUSIONS
B24: INCLUDES ALL SALES TAX
B25: ALL HOISTING & RIGGING REQUIRED TO COMPLETE THIS SCOPE
B26: PROVIDE P&P BONDS
B27: FLORIDA STATE CONTRACTORS LIC.
B28: GENERAL LIABILITY AND WORKERS COMP. INSURANCE LIMITS
B29: STATE AND LOCAL TAXES
B30: COMPASS
B31: SPECIFIC TRADE SCOPE OF WORK REQUIREMENTS
B32: BASE BID
H35: x
F53: SUBTOTAL | I53: =SUM(I22:I52) -> 0 | K53: =SUM(K22:K52) -> 0 | M53: =SUM(M22:M52) -> 0 | O53: =SUM(O22:O52) -> 0 | Q53: =SUM(Q22:Q52) -> 0 | S53: =SUM(S22:S52) -> 0
F54: BOND RATE | H54: 0 | J54: 0 | L54: 0 | N54: 0 | P54: 0 | R54: 0
F55: BOND AMOUNT | I55: =H54*I53 -> 0 | K55: =J54*K53 -> 0 | M55: =L54*M53 -> 0 | O55: =N54*O53 -> 0 | Q55: =P54*Q53 -> 0 | S55: =R54*S53 -> 0
F57: ADJUSTED TOTAL | I57: =SUM(I53:I55) -> 0 | K57: =SUM(K53:K55) -> 0 | M57: =SUM(M53:M55) -> 0 | O57: =SUM(O53:O55) -> 0 | Q57: =SUM(Q53:Q55) -> 0 | S57: =SUM(S53:S55) -> 0
F58: Cost per SF | I58: =I57/'Area Calculations'!$I$4 -> #DIV/0! | K58: =K57/'Area Calculations'!$I$4 -> #DIV/0! | M58: =M57/'Area Calculations'!$I$4 -> #DIV/0! | O58: =O57/'Area Calculations'!$I$4 -> #DIV/0! | Q58: =Q57/'Area Calculations'!$I$4 -> #DIV/0! | S58: =S57/'Area Calculations'!$I$4 -> #DIV/0!
F59: Cost per Unit | I59: =I57/'Area Calculations'!#REF! -> #REF! | K59: =K57/'Area Calculations'!#REF! -> #REF! | M59: =M57/'Area Calculations'!#REF! -> #REF! | O59: =O57/'Area Calculations'!#REF! -> #REF! | Q59: =Q57/'Area Calculations'!#REF! -> #REF! | S59: =S57/'Area Calculations'!#REF! -> #REF!
A61: QUALIFICATIONS
A65: EXCLUSIONS/OWNER PROVIDED ITEMS:
A69: ALTERNATES:
A73: PROPOSED VE (Provide Clear Description):
A77: FULLY LOADED LABOR RATES
B78: Laborer
B79: Mechanic
B80: Superintendent
B81: Project Manager
A83: SCHEDULE
B84: Prepared shop drawings/submittals
B85: Mobilization
B86: Total duration to complete scope of work
A88: Winner
A89: Company
A90: Contact
A91: Phone
A92: Email
A93: Base Bid
B95: Need Prequalification
B96: Prequalified

Sheet 02B Abatement
G1: Hedrick Plug
F2: X | G2: Excluded
B3: BACK TO SUMMARY SHEET | F3: I | G3: Included | H3: Bidder 1 | J3: Bidder 2 | L3: Bidder 3 | N3: Bidder 4 | P3: Bidder5 | R3: Bidder6
A4: Project: | B4: ='Area Calculations'!B4 -> Project Name | G4: Company
A5: Trade: | B5: Abatement | G5: Contact
A6: CSI Code: | B6: 02B | G6: Phone
A7: Date: | G7: Email
A8: Adjusted Bid | G8: Adjusted Bid | H8: =I57 -> 0 | J8: =K57 -> 0 | L8: =M57 -> 0 | N8: =O57 -> 0 | P8: =Q57 -> 0 | R8: =S57 -> 0
A9: BID DOCUMENTS: | C9: Plan/ Spec. Package | D9: QTY | E9: U/M | F9: Unit Cost | G9: Subtotal | H9: Yes/No | I9: Price | J9: Yes/No | K9: Price | L9: Yes/No | M9: Price | N9: Yes/No | O9: Price | P9: Yes/No | Q9: Price | R9: Yes/No | S9: Price
B10: Plans By Division
B11: ='Area Calculations'!L62 -> Architectural Drawings by | C11: P
B12: ='Area Calculations'!L63 -> Structural Drawings by | C12: P
B13: ='Area Calculations'!L64 -> MEP FA FP Drawings by | C13: P
B14: ='Area Calculations'!L65 -> Civil Drawings by | C14: P
B15: ='Area Calculations'!L66 -> Land scape Drawings by | C15: P
B16: ='Area Calculations'!L67 -> Kitchen Drawings by | C16: P
B17: ='Area Calculations'!L68 -> Storefront Designer by | C17: P
B18: ='Area Calculations'!L69 -> Geotech report by | C18: P
B19: ='Area Calculations'!L70 -> Specifications | C19: P
B21: Abatement
B22: OCIP Insurance per exhibit
B23: GENERAL INCLUSIONS
B24: INCLUDES ALL SALES TAX
B25: ALL HOISTING & RIGGING REQUIRED TO COMPLETE THIS SCOPE
B26: PROVIDE P&P BONDS
B27: FLORIDA STATE CONTRACTORS LIC.
B28: GENERAL LIABILITY AND WORKERS COMP. INSURANCE LIMITS
B29: STATE AND LOCAL TAXES
B30: COMPASS
B31: SPECIFIC TRADE SCOPE OF WORK REQUIREMENTS
B32: BASE BID
H35: x
F53: SUBTOTAL | I53: =SUM(I22:I52) -> 0 | K53: =SUM(K22:K52) -> 0 | M53: =SUM(M22:M52) -> 0 | O53: =SUM(O22:O52) -> 0 | Q53: =SUM(Q22:Q52) -> 0 | S53: =SUM(S22:S52) -> 0
F54: BOND RATE | H54: 0 | J54: 0 | L54: 0 | N54: 0 | P54: 0 | R54: 0
F55: BOND AMOUNT | I55: =H54*I53 -> 0 | K55: =J54*K53 -> 0 | M55: =L54*M53 -> 0 | O55: =N54*O53 -> 0 | Q55: =P54*Q53 -> 0 | S55: =R54*S53 -> 0
F57: ADJUSTED TOTAL | I57: =SUM(I53:I55) -> 0 | K57: =SUM(K53:K55) -> 0 | M57: =SUM(M53:M55) -> 0 | O57: =SUM(O53:O55) -> 0 | Q57: =SUM(Q53:Q55) -> 0 | S57: =SUM(S53:S55) -> 0
F58: Cost per SF | I58: =I57/'Area Calculations'!$I$4 -> #DIV/0! | K58: =K57/'Area Calculations'!$I$4 -> #DIV/0! | M58: =M57/'Area Calculations'!$I$4 -> #DIV/0! | O58: =O57/'Area Calculations'!$I$4 -> #DIV/0! | Q58: =Q57/'Area Calculations'!$I$4 -> #DIV/0! | S58: =S57/'Area Calculations'!$I$4 -> #DIV/0!
F59: Cost per Unit | I59: =I57/'Area Calculations'!#REF! -> #REF! | K59: =K57/'Area Calculations'!#REF! -> #REF! | M59: =M57/'Area Calculations'!#REF! -> #REF! | O59: =O57/'Area Calculations'!#REF! -> #REF! | Q59: =Q57/'Area Calculations'!#REF! -> #REF! | S59: =S57/'Area Calculations'!#REF! -> #REF!
A61: QUALIFICATIONS
A65: EXCLUSIONS/OWNER PROVIDED ITEMS:
A69: ALTERNATES:
A73: PROPOSED VE (Provide Clear Description):
A77: FULLY LOADED LABOR RATES
B78: Laborer
B79: Mechanic
B80: Superintendent
B81: Project Manager
A83: SCHEDULE
B84: Prepared shop drawings/submittals
B85: Mobilization
B86: Total duration to complete scope of work
A88: Winner
A89: Company
A90: Contact
A91: Phone
A92: Email
A93: Base Bid
B95: Need Prequalification
B96: Prequalified

Sheet 03A Concrete
G1: Hedrick Plug
F2: X | G2: Excluded
B3: BACK TO SUMMARY SHEET | F3: I | G3: Included | H3: Bidder 1 | J3: Bidder2 | L3: Bidder 3 | N3: Bidder 4 | P3: Bidder 5 | R3: Bidder 6
A4: Project: | B4: ='Area Calculations'!B4 -> Project Name | G4: Company
A5: Trade: | B5: Concrete | G5: Contact
A6: CSI Code: | B6: 03A | G6: Phone
A7: Date: | G7: Email
A8: Adjusted Bid | G8: Adjusted Bid | H8: =I87 -> 0 | J8: =K87 -> 0 | L8: =M87 -> 0 | N8: =O87 -> 0 | P8: =Q87 -> 0 | R8: =S87 -> 0
A9: BID DOCUMENTS: | C9: Plan/ Spec. Package | D9: QTY | E9: U/M | F9: Unit Cost | G9: Subtotal | H9: Yes/No | I9: Price | J9: Yes/No | K9: Price | L9: Yes/No | M9: Price | N9: Yes/No | O9: Price | P9: Yes/No | Q9: Price | R9: Yes/No | S9: Price
B10: Plans By Division
B11: ='Area Calculations'!L62 -> Architectural Drawings by | C11: P
B12: ='Area Calculations'!L63 -> Structural Drawings by | C12: P
B13: ='Area Calculations'!L64 -> MEP FA FP Drawings by | C13: P
B14: ='Area Calculations'!L65 -> Civil Drawings by | C14: P
B15: ='Area Calculations'!L66 -> Land scape Drawings by | C15: P
B16: ='Area Calculations'!L67 -> Kitchen Drawings by
B17: ='Area Calculations'!L68 -> Storefront Designer by
B18: ='Area Calculations'!L69 -> Geotech report by | C18: P
B19: ='Area Calculations'!L70 -> Specifications
B21: Concrete
B22: GENERAL INCLUSIONS
B23: INCLUDES ALL SALES TAX
B24: ALL HOISTING & RIGGING REQUIRED TO COMPLETE THIS SCOPE
B25: PROVIDE P&P BONDS
B26: FLORIDA STATE CONTRACTORS LIC.
B27: GENERAL LIABILITY AND WORKERS COMP. INSURANCE LIMITS
B28: STATE AND LOCAL TAXES
B29: COMPASS
B30: SPECIFIC TRADE SCOPE OF WORK REQUIREMENTS
B31: BASE BID
B33: CIP Beams , incl.:
... B53: CMU, Incl.: 8" & 12"
B54: a. Layout and formwork | C54: S0-01
B55: b. Reinf., as scheduled/detailed
B56: c. ?-psi concrete grout; 0.? w/c
B57: d. Pumping as required
B58: e. Horizontal Reinf.
B59: f. Lintels, ladder wire and accessories
B60: g. Setting of Joist Embeds & door frames
B61: h. Above scope included for: | H61: i
B62: 1)
B63: 2)
B64: 3)
B68: Concrete
B69: Rebars
F83: SUBTOTAL | I83: =SUM(I24:I82) -> 0 | K83: =SUM(K24:K82) -> 0 | M83: =SUM(M24:M82) -> 0 | O83: =SUM(O24:O82) -> 0 | Q83: =SUM(Q24:Q82) -> 0 | S83: =SUM(S24:S82) -> 0
F84: BOND RATE | H84: 0 | J84: 0 | L84: 0 | N84: 0 | P84: 0 | R84: 0
F85: BOND AMOUNT | I85: =H84*I83 -> 0 | K85: =J84*K83 -> 0 | M85: =L84*M83 -> 0 | O85: =N84*O83 -> 0 | Q85: =P84*Q83 -> 0 | S85: =R84*S83 -> 0
F87: ADJUSTED TOTAL | I87: =SUM(I83:I86) -> 0 | K87: =SUM(K83:K86) -> 0 | M87: =SUM(M83:M85) -> 0 | O87: =SUM(O83:O85) -> 0 | Q87: =SUM(Q83:Q85) -> 0 | S87: =SUM(S83:S85) -> 0
F88: Cost per SF | I88: =I87/'Area Calculations'!$I$4 -> #DIV/0! | K88: =K87/'Area Calculations'!$I$4 -> #DIV/0! | M88: =M87/'Area Calculations'!$I$4 -> #DIV/0! | O88: =O87/'Area Calculations'!$I$4 -> #DIV/0! | Q88: =Q87/'Area Calculations'!$I$4 -> #DIV/0! | S88: =S87/'Area Calculations'!$I$4 -> #DIV/0!
F89: Cost per Unit | I89: =I87/'Area Calculations'!#REF! -> #REF! | K89: =K87/'Area Calculations'!#REF! -> #REF! | M89: =M87/'Area Calculations'!#REF! -> #REF! | O89: =O87/'Area Calculations'!#REF! -> #REF! | Q89: =Q87/'Area Calculations'!#REF! -> #REF! | S89: =S87/'Area Calculations'!#REF! -> #REF!
A91: QUALIFICATIONS
A95: EXCLUSIONS/OWNER PROVIDED ITEMS:
A99: ALTERNATES:
A103: PROPOSED VE (Provide Clear Description):
A107: UNIT RATES
A113: FULLY LOADED LABOR RATES
B114: Laborer
B115: Mechanic
B116: Superintendent
B117: Project Manager
A119: SCHEDULE
B120: Prepared shop drawings/submittals
B121: Mobilization
B122: Total duration to complete scope of work
A124: Winner
A125: Company
A126: Contact
A127: Phone
A128: Email
A129: Base Bid
B131: Need Prequalification
B132: Prequalified

Sheet 03B Precast Hollow Core
G1: Hedrick Plug
F2: X | G2: Excluded
B3: BACK TO SUMMARY SHEET | F3: I | G3: Included | H3: Bidder1 | J3: Bidder 2 | L3: Bidder 3 | N3: Bidder 4 | P3: Bidder 5 | R3: Bidder 6
A4: Project: | B4: ='Area Calculations'!B4 -> Project Name | G4: Company
A5: Trade: | B5: Precast Hollow Core | G5: Contact
A6: CSI Code: | B6: 03B | G6: Phone
A7: Date: | G7: Email
A8: Adjusted Bid | G8: Adjusted Bid | H8: =I46 -> 0 | J8: =K46 -> 0 | L8: =M46 -> 0 | N8: =O46 -> 0 | P8: =Q46 -> 0 | R8: =S46 -> 0
A9: BID DOCUMENTS: | C9: Plan/ Spec. Package | D9: QTY | E9: U/M | F9: Unit Cost | G9: Subtotal | H9: Yes/No | I9: Price | J9: Yes/No | K9: Price | L9: Yes/No | M9: Price | N9: Yes/No | O9: Price | P9: Yes/No | Q9: Price | R9: Yes/No | S9: Price
B10: Plans By Division
B11: ='Area Calculations'!L62 -> Architectural Drawings by | C11: P
B12: ='Area Calculations'!L63 -> Structural Drawings by | C12: P
B13: ='Area Calculations'!L64 -> MEP FA FP Drawings by | C13: P
B14: ='Area Calculations'!L65 -> Civil Drawings by | C14: P
B15: ='Area Calculations'!L66 -> Land scape Drawings by | C15: P
B16: ='Area Calculations'!L67 -> Kitchen Drawings by
B17: ='Area Calculations'!L68 -> Storefront Designer by
B18: ='Area Calculations'!L69 -> Geotech report by | C18: P
B19: ='Area Calculations'!L70 -> Specifications
B21: Precast Hollow Core
B22: GENERAL INCLUSIONS
B23: INCLUDES ALL SALES TAX
B24: ALL HOISTING & RIGGING REQUIRED TO COMPLETE THIS SCOPE
B25: PROVIDE P&P BONDS
B26: FLORIDA STATE CONTRACTORS LIC.
B27: GENERAL LIABILITY AND WORKERS COMP. INSURANCE LIMITS
B28: STATE AND LOCAL TAXES
B29: COMPASS
B30: SPECIFIC TRADE SCOPE OF WORK REQUIREMENTS
B31: BASE BID
B32: Building SF
L34: i
F42: SUBTOTAL | I42: =SUM(I24:I41) -> 0 | K42: =SUM(K24:K41) -> 0 | M42: =SUM(M24:M41) -> 0 | O42: =SUM(O24:O41) -> 0 | Q42: =SUM(Q24:Q41) -> 0 | S42: =SUM(S24:S41) -> 0
F43: BOND RATE | H43: 0 | J43: 0 | L43: 0 | N43: 0 | P43: 0 | R43: 0
F44: BOND AMOUNT | I44: =H43*I42 -> 0 | K44: =J43*K42 -> 0 | M44: =L43*M42 -> 0 | O44: =N43*O42 -> 0 | Q44: =P43*Q42 -> 0 | S44: =R43*S42 -> 0
F46: ADJUSTED TOTAL | I46: =SUM(I42:I44) -> 0 | K46: =SUM(K42:K44) -> 0 | M46: =SUM(M42:M44) -> 0 | O46: =SUM(O42:O44) -> 0 | Q46: =SUM(Q42:Q44) -> 0 | S46: =SUM(S42:S44) -> 0
F47: Cost per SF | I47: =I46/'Area Calculations'!$I$4 -> #DIV/0! | K47: =K46/'Area Calculations'!$I$4 -> #DIV/0! | M47: =M46/'Area Calculations'!$I$4 -> #DIV/0! | O47: =O46/'Area Calculations'!$I$4 -> #DIV/0! | Q47: =Q46/'Area Calculations'!$I$4 -> #DIV/0! | S47: =S46/'Area Calculations'!$I$4 -> #DIV/0!
F48: Cost per Unit | I48: =I46/'Area Calculations'!#REF! -> #REF! | K48: =K46/'Area Calculations'!#REF! -> #REF! | M48: =M46/'Area Calculations'!#REF! -> #REF! | O48: =O46/'Area Calculations'!#REF! -> #REF! | Q48: =Q46/'Area Calculations'!#REF! -> #REF! | S48: =S46/'Area Calculations'!#REF! -> #REF!
A50: QUALIFICATIONS
A54: EXCLUSIONS/OWNER PROVIDED ITEMS:
A58: ALTERNATES:
A62: PROPOSED VE (Provide Clear Description):
A66: FULLY LOADED LABOR RATES
B67: Laborer
B68: Mechanic
B69: Superintendent
B70: Project Manager
A72: SCHEDULE
B73: Prepared shop drawings/submittals
B74: Mobilization
B75: Total duration to complete scope of work
A77: Winner
A78: Company
A79: Contact
A80: Phone
A81: Email
A82: Base Bid
B84: Need Prequalification
B85: Prequalified

Sheet 03C Architectural Precast
G1: Hedrick Plug
F2: X | G2: Excluded
B3: BACK TO SUMMARY SHEET | F3: I | G3: Included | H3: Bidder1 | J3: Bidder 2 | L3: Bidder 3 | N3: Bidder 4 | P3: Bidder 5 | R3: Bidder 6
A4: Project: | B4: ='Area Calculations'!B4 -> Project Name | G4: Company
A5: Trade: | B5: Architectural Precast | G5: Contact
A6: CSI Code: | B6: 03C | G6: Phone
A7: Date: | G7: Email
A8: Adjusted Bid | G8: Adjusted Bid | H8: =I50 -> 0 | J8: =K50 -> 0 | L8: =M50 -> 0 | N8: =O50 -> 0 | P8: =Q50 -> 0 | R8: =S50 -> 0
A9: BID DOCUMENTS: | C9: Plan/ Spec. Package | D9: QTY | E9: U/M | F9: Unit Cost | G9: Subtotal | H9: Yes/No | I9: Price | J9: Yes/No | K9: Price | L9: Yes/No | M9: Price | N9: Yes/No | O9: Price | P9: Yes/No | Q9: Price | R9: Yes/No | S9: Price
B10: Plans By Division
B11: ='Area Calculations'!L62 -> Architectural Drawings by | C11: P
B12: ='Area Calculations'!L63 -> Structural Drawings by | C12: P
B13: ='Area Calculations'!L64 -> MEP FA FP Drawings by | C13: P
B14: ='Area Calculations'!L65 -> Civil Drawings by | C14: P
B15: ='Area Calculations'!L66 -> Land scape Drawings by | C15: P
B16: ='Area Calculations'!L67 -> Kitchen Drawings by
B17: ='Area Calculations'!L68 -> Storefront Designer by
B18: ='Area Calculations'!L69 -> Geotech report by | C18: P
B19: ='Area Calculations'!L70 -> Specifications
B21: Architectural Precast
B22: GENERAL INCLUSIONS
B23: INCLUDES ALL SALES TAX
B24: ALL HOISTING & RIGGING REQUIRED TO COMPLETE THIS SCOPE
B25: PROVIDE P&P BONDS
B26: FLORIDA STATE CONTRACTORS LIC.
B27: GENERAL LIABILITY AND WORKERS COMP. INSURANCE LIMITS
B28: STATE AND LOCAL TAXES
B29: COMPASS
B30: SPECIFIC TRADE SCOPE OF WORK REQUIREMENTS
B31: BASE BID
B32: Building SF
H38: i
F46: SUBTOTAL | I46: =SUM(I24:I45) -> 0 | K46: =SUM(K24:K45) -> 0 | M46: =SUM(M24:M45) -> 0 | O46: =SUM(O24:O45) -> 0 | Q46: =SUM(Q24:Q45) -> 0 | S46: =SUM(S24:S45) -> 0
F47: BOND RATE | H47: 0 | J47: 0 | L47: 0 | N47: 0 | P47: 0 | R47: 0
F48: BOND AMOUNT | I48: =H47*I46 -> 0 | K48: =J47*K46 -> 0 | M48: =L47*M46 -> 0 | O48: =N47*O46 -> 0 | Q48: =P47*Q46 -> 0 | S48: =R47*S46 -> 0
F50: ADJUSTED TOTAL | I50: =SUM(I46:I48) -> 0 | K50: =SUM(K46:K48) -> 0 | M50: =SUM(M46:M48) -> 0 | O50: =SUM(O46:O48) -> 0 | Q50: =SUM(Q46:Q48) -> 0 | S50: =SUM(S46:S48) -> 0
F51: Cost per SF | I51: =I50/'Area Calculations'!$I$4 -> #DIV/0! | K51: =K50/'Area Calculations'!$I$4 -> #DIV/0! | M51: =M50/'Area Calculations'!$I$4 -> #DIV/0! | O51: =O50/'Area Calculations'!$I$4 -> #DIV/0! | Q51: =Q50/'Area Calculations'!$I$4 -> #DIV/0! | S51: =S50/'Area Calculations'!$I$4 -> #DIV/0!
F52: Cost per Unit | I52: =I50/'Area Calculations'!#REF! -> #REF! | K52: =K50/'Area Calculations'!#REF! -> #REF! | M52: =M50/'Area Calculations'!#REF! -> #REF! | O52: =O50/'Area Calculations'!#REF! -> #REF! | Q52: =Q50/'Area Calculations'!#REF! -> #REF! | S52: =S50/'Area Calculations'!#REF! -> #REF!
A54: QUALIFICATIONS
A58: EXCLUSIONS/OWNER PROVIDED ITEMS:
A62: ALTERNATES:
A66: PROPOSED VE (Provide Clear Description):
A70: FULLY LOADED LABOR RATES
B71: Laborer
B72: Mechanic
B73: Superintendent
B74: Project Manager
A76: SCHEDULE
B77: Prepared shop drawings/submittals
B78: Mobilization
B79: Total duration to complete scope of work
A81: Winner
A82: Company
A83: Contact
A84: Phone
A85: Email
A86: Base Bid
B88: Need Prequalification
B89: Prequalified

Sheet 03C Concrete Tilt Up
G1: Hedrick Plug
F2: X | G2: Excluded
B3: BACK TO SUMMARY SHEET | F3: I | G3: Included | H3: Bidder1 | J3: Bidder 2 | L3: Bidder 3 | N3: Bidder 4 | P3: Bidder 5 | R3: Bidder 6
A4: Project: | B4: ='Area Calculations'!B4 -> Project Name | G4: Company
A5: Trade: | B5: Concrete Tilt Up | G5: Contact
A6: CSI Code: | B6: 03C | G6: Phone
A7: Date: | G7: Email
A8: Adjusted Bid | G8: Adjusted Bid | H8: =I46 -> 0 | J8: =K46 -> 0 | L8: =M46 -> 0 | N8: =O46 -> 0 | P8: =Q46 -> 0 | R8: =S46 -> 0
A9: BID DOCUMENTS: | C9: Plan/ Spec. Package | D9: QTY | E9: U/M | F9: Unit Cost | G9: Subtotal | H9: Yes/No | I9: Price | J9: Yes/No | K9: Price | L9: Yes/No | M9: Price | N9: Yes/No | O9: Price | P9: Yes/No | Q9: Price | R9: Yes/No | S9: Price
B10: Plans By Division
B11: ='Area Calculations'!L62 -> Architectural Drawings by | C11: P
B12: ='Area Calculations'!L63 -> Structural Drawings by | C12: P
B13: ='Area Calculations'!L64 -> MEP FA FP Drawings by | C13: P
B14: ='Area Calculations'!L65 -> Civil Drawings by | C14: P
B15: ='Area Calculations'!L66 -> Land scape Drawings by | C15: P
B16: ='Area Calculations'!L67 -> Kitchen Drawings by
B17: ='Area Calculations'!L68 -> Storefront Designer by
B18: ='Area Calculations'!L69 -> Geotech report by | C18: P
B19: ='Area Calculations'!L70 -> Specifications
B21: Concrete Tilt Up
B22: GENERAL INCLUSIONS
B23: INCLUDES ALL SALES TAX
B24: ALL HOISTING & RIGGING REQUIRED TO COMPLETE THIS SCOPE
B25: PROVIDE P&P BONDS
B26: FLORIDA STATE CONTRACTORS LIC.
B27: GENERAL LIABILITY AND WORKERS COMP. INSURANCE LIMITS
B28: STATE AND LOCAL TAXES
B29: COMPASS
B30: SPECIFIC TRADE SCOPE OF WORK REQUIREMENTS
B31: BASE BID
B32: Building SF
L34: i
F42: SUBTOTAL | I42: =SUM(I24:I41) -> 0 | K42: =SUM(K24:K41) -> 0 | M42: =SUM(M24:M41) -> 0 | O42: =SUM(O24:O41) -> 0 | Q42: =SUM(Q24:Q41) -> 0 | S42: =SUM(S24:S41) -> 0
F43: BOND RATE | H43: 0 | J43: 0 | L43: 0 | N43: 0 | P43: 0 | R43: 0
F44: BOND AMOUNT | I44: =H43*I42 -> 0 | K44: =J43*K42 -> 0 | M44: =L43*M42 -> 0 | O44: =N43*O42 -> 0 | Q44: =P43*Q42 -> 0 | S44: =R43*S42 -> 0
F46: ADJUSTED TOTAL | I46: =SUM(I42:I44) -> 0 | K46: =SUM(K42:K44) -> 0 | M46: =SUM(M42:M44) -> 0 | O46: =SUM(O42:O44) -> 0 | Q46: =SUM(Q42:Q44) -> 0 | S46: =SUM(S42:S44) -> 0
F47: Cost per SF | I47: =I46/'Area Calculations'!$I$4 -> #DIV/0! | K47: =K46/'Area Calculations'!$I$4 -> #DIV/0! | M47: =M46/'Area Calculations'!$I$4 -> #DIV/0! | O47: =O46/'Area Calculations'!$I$4 -> #DIV/0! | Q47: =Q46/'Area Calculations'!$I$4 -> #DIV/0! | S47: =S46/'Area Calculations'!$I$4 -> #DIV/0!
F48: Cost per Unit | I48: =I46/'Area Calculations'!#REF! -> #REF! | K48: =K46/'Area Calculations'!#REF! -> #REF! | M48: =M46/'Area Calculations'!#REF! -> #REF! | O48: =O46/'Area Calculations'!#REF! -> #REF! | Q48: =Q46/'Area Calculations'!#REF! -> #REF! | S48: =S46/'Area Calculations'!#REF! -> #REF!
A50: QUALIFICATIONS
A54: EXCLUSIONS/OWNER PROVIDED ITEMS:
A58: ALTERNATES:
A62: PROPOSED VE (Provide Clear Description):
A66: FULLY LOADED LABOR RATES
B67: Laborer
B68: Mechanic
B69: Superintendent
B70: Project Manager
A72: SCHEDULE
B73: Prepared shop drawings/submittals
B74: Mobilization
B75: Total duration to complete scope of work
A77: Winner
A78: Company
A79: Contact
A80: Phone
A81: Email
A82: Base Bid
B84: Need Prequalification
B85: Prequalified

Sheet 03D Structural Precast
G1: Hedrick Plug
F2: X | G2: Excluded
B3: BACK TO SUMMARY SHEET | F3: I | G3: Included | H3: Bidder1 | J3: Bidder 2 | L3: Bidder 3 | N3: Bidder 4 | P3: Bidder 5 | R3: Bidder 6
A4: Project: | B4: ='Area Calculations'!B4 -> Project Name | G4: Company
A5: Trade: | B5: Structural Precast | G5: Contact
A6: CSI Code: | B6: 03D | G6: Phone
A7: Date: | G7: Email
A8: Adjusted Bid | G8: Adjusted Bid | H8: =I96 -> 0 | J8: =K96 -> 0 | L8: =M96 -> 0 | N8: =O96 -> 0 | P8: =Q96 -> 0 | R8: =S96 -> 0
A9: BID DOCUMENTS: | C9: Plan/ Spec. Package | D9: QTY | E9: U/M | F9: Unit Cost | G9: Subtotal | H9: Yes/No | I9: Price | J9: Yes/No | K9: Price | L9: Yes/No | M9: Price | N9: Yes/No | O9: Price | P9: Yes/No | Q9: Price | R9: Yes/No | S9: Price
B10: Plans By Division
B11: ='Area Calculations'!L62 -> Architectural Drawings by | C11: P
B12: ='Area Calculations'!L63 -> Structural Drawings by | C12: P
B13: ='Area Calculations'!L64 -> MEP FA FP Drawings by | C13: P
B14: ='Area Calculations'!L65 -> Civil Drawings by | C14: P
B15: ='Area Calculations'!L66 -> Land scape Drawings by | C15: P
B16: ='Area Calculations'!L67 -> Kitchen Drawings by
B17: ='Area Calculations'!L68 -> Storefront Designer by
B18: ='Area Calculations'!L69 -> Geotech report by | C18: P
B19: ='Area Calculations'!L70 -> Specifications
B21: Structural Precast
B22: GENERAL INCLUSIONS
B23: INCLUDES ALL SALES TAX
B24: ALL HOISTING & RIGGING REQUIRED TO COMPLETE THIS SCOPE
B25: PROVIDE P&P BONDS
B26: FLORIDA STATE CONTRACTORS LIC.
B27: GENERAL LIABILITY AND WORKERS COMP. INSURANCE LIMITS
B28: STATE AND LOCAL TAXES
B29: COMPASS
B30: SPECIFIC TRADE SCOPE OF WORK REQUIREMENTS
B31: BASE BID
B32: Building SF
... B41: Dumpster Enclosure
B42: Monument Sign - | H42: i
B44: SLAB-ON-GRADE
B45: 5" Slab w/ WWF 6x6 w.2.9xw2.9
B46: a. Soil poisoning and pre-treat
B47: b. Fine grading building pad
B48: d. F&I rebar, as per plans
B49: e. F&I wire mesh, as per plans
B50: f. 4,000 PSI
B51: g. Sawcut constr. / control joints
B52: h. Finish slab to FF25/FL17
B53: i. Leave out strip, compact
B54: j. Patch slab after tilt operations
B55: k. Provide curing compound
... B85: Panel structural engineering
F92: SUBTOTAL | I92: =SUM(I24:I91) -> 0 | K92: =SUM(K24:K91) -> 0 | M92: =SUM(M24:M91) -> 0 | O92: =SUM(O24:O91) -> 0 | Q92: =SUM(Q24:Q91) -> 0 | S92: =SUM(S24:S91) -> 0
F93: BOND RATE | H93: 0 | J93: 0 | L93: 0 | N93: 0 | P93: 0 | R93: 0
F94: BOND AMOUNT | I94: =H93*I92 -> 0 | K94: =J93*K92 -> 0 | M94: =L93*M92 -> 0 | O94: =N93*O92 -> 0 | Q94: =P93*Q92 -> 0 | S94: =R93*S92 -> 0
F96: ADJUSTED TOTAL | I96: =SUM(I92:I94) -> 0 | K96: =SUM(K92:K94) -> 0 | M96: =SUM(M92:M94) -> 0 | O96: =SUM(O92:O94) -> 0 | Q96: =SUM(Q92:Q94) -> 0 | S96: =SUM(S92:S94) -> 0
F97: Cost per SF | I97: =I96/'Area Calculations'!$I$4 -> #DIV/0! | K97: =K96/'Area Calculations'!$I$4 -> #DIV/0! | M97: =M96/'Area Calculations'!$I$4 -> #DIV/0! | O97: =O96/'Area Calculations'!$I$4 -> #DIV/0! | Q97: =Q96/'Area Calculations'!$I$4 -> #DIV/0! | S97: =S96/'Area Calculations'!$I$4 -> #DIV/0!
F98: Cost per Unit | I98: =I96/'Area Calculations'!#REF! -> #REF! | K98: =K96/'Area Calculations'!#REF! -> #REF! | M98: =M96/'Area Calculations'!#REF! -> #REF! | O98: =O96/'Area Calculations'!#REF! -> #REF! | Q98: =Q96/'Area Calculations'!#REF! -> #REF! | S98: =S96/'Area Calculations'!#REF! -> #REF!
A100: QUALIFICATIONS
A104: EXCLUSIONS/OWNER PROVIDED ITEMS:
A108: ALTERNATES:
A112: PROPOSED VE (Provide Clear Description):
A116: FULLY LOADED LABOR RATES
B117: Laborer
B118: Mechanic
B119: Superintendent
B120: Project Manager
A122: SCHEDULE
B123: Prepared shop drawings/submittals
B124: Mobilization
B125: Total duration to complete scope of work
A127: Winner
A128: Company
A129: Contact
A130: Phone
A131: Email
A132: Base Bid
B134: Need Prequalification
B135: Prequalified

Sheet 03E Cranes and Hoisting
G1: Hedrick Plug
F2: X | G2: Excluded
B3: BACK TO SUMMARY SHEET | F3: I | G3: Included | H3: Bidder1 | J3: Bidder 2 | L3: Bidder 3 | N3: Bidder 4 | P3: Bidder 5 | R3: Bidder 6
A4: Project: | B4: ='Area Calculations'!B4 -> Project Name | G4: Company
A5: Trade: | B5: Cranes and Hoisting | G5: Contact
A6: CSI Code: | B6: 03E | G6: Phone
A7: Date: | G7: Email
A8: Adjusted Bid | G8: Adjusted Bid | H8: =I96 -> 0 | J8: =K96 -> 0 | L8: =M96 -> 0 | N8: =O96 -> 0 | P8: =Q96 -> 0 | R8: =S96 -> 0
A9: BID DOCUMENTS: | C9: Plan/ Spec. Package | D9: QTY | E9: U/M | F9: Unit Cost | G9: Subtotal | H9: Yes/No | I9: Price | J9: Yes/No | K9: Price | L9: Yes/No | M9: Price | N9: Yes/No | O9: Price | P9: Yes/No | Q9: Price | R9: Yes/No | S9: Price
B10: Plans By Division
B11: ='Area Calculations'!L62 -> Architectural Drawings by | C11: P
B12: ='Area Calculations'!L63 -> Structural Drawings by | C12: P
B13: ='Area Calculations'!L64 -> MEP FA FP Drawings by | C13: P
B14: ='Area Calculations'!L65 -> Civil Drawings by | C14: P
B15: ='Area Calculations'!L66 -> Land scape Drawings by | C15: P
B16: ='Area Calculations'!L67 -> Kitchen Drawings by
B17: ='Area Calculations'!L68 -> Storefront Designer by
B18: ='Area Calculations'!L69 -> Geotech report by | C18: P
B19: ='Area Calculations'!L70 -> Specifications
B21: Cranes and Hoisting
B22: GENERAL INCLUSIONS
B23: INCLUDES ALL SALES TAX
B24: ALL HOISTING & RIGGING REQUIRED TO COMPLETE THIS SCOPE
B25: PROVIDE P&P BONDS
B26: FLORIDA STATE CONTRACTORS LIC.
B27: GENERAL LIABILITY AND WORKERS COMP. INSURANCE LIMITS
B28: STATE AND LOCAL TAXES
B29: COMPASS
B30: SPECIFIC TRADE SCOPE OF WORK REQUIREMENTS
B31: BASE BID
B32: Building SF
... B41: Dumpster Enclosure
B42: Monument Sign - | H42: i
B44: SLAB-ON-GRADE
B45: 5" Slab w/ WWF 6x6 w.2.9xw2.9
B46: a. Soil poisoning and pre-treat
B47: b. Fine grading building pad
B48: d. F&I rebar, as per plans
B49: e. F&I wire mesh, as per plans
B50: f. 4,000 PSI
B51: g. Sawcut constr. / control joints
B52: h. Finish slab to FF25/FL17
B53: i. Leave out strip, compact
B54: j. Patch slab after tilt operations
B55: k. Provide curing compound
... B85: Panel structural engineering
F92: SUBTOTAL | I92: =SUM(I24:I91) -> 0 | K92: =SUM(K24:K91) -> 0 | M92: =SUM(M24:M91) -> 0 | O92: =SUM(O24:O91) -> 0 | Q92: =SUM(Q24:Q91) -> 0 | S92: =SUM(S24:S91) -> 0
F93: BOND RATE | H93: 0 | J93: 0 | L93: 0 | N93: 0 | P93: 0 | R93: 0
F94: BOND AMOUNT | I94: =H93*I92 -> 0 | K94: =J93*K92 -> 0 | M94: =L93*M92 -> 0 | O94: =N93*O92 -> 0 | Q94: =P93*Q92 -> 0 | S94: =R93*S92 -> 0
F96: ADJUSTED TOTAL | I96: =SUM(I92:I94) -> 0 | K96: =SUM(K92:K94) -> 0 | M96: =SUM(M92:M94) -> 0 | O96: =SUM(O92:O94) -> 0 | Q96: =SUM(Q92:Q94) -> 0 | S96: =SUM(S92:S94) -> 0
F97: Cost per SF | I97: =I96/'Area Calculations'!$I$4 -> #DIV/0! | K97: =K96/'Area Calculations'!$I$4 -> #DIV/0! | M97: =M96/'Area Calculations'!$I$4 -> #DIV/0! | O97: =O96/'Area Calculations'!$I$4 -> #DIV/0! | Q97: =Q96/'Area Calculations'!$I$4 -> #DIV/0! | S97: =S96/'Area Calculations'!$I$4 -> #DIV/0!
F98: Cost per Unit | I98: =I96/'Area Calculations'!#REF! -> #REF! | K98: =K96/'Area Calculations'!#REF! -> #REF! | M98: =M96/'Area Calculations'!#REF! -> #REF! | O98: =O96/'Area Calculations'!#REF! -> #REF! | Q98: =Q96/'Area Calculations'!#REF! -> #REF! | S98: =S96/'Area Calculations'!#REF! -> #REF!
A100: QUALIFICATIONS
A104: EXCLUSIONS/OWNER PROVIDED ITEMS:
A108: ALTERNATES:
A112: PROPOSED VE (Provide Clear Description):
A116: FULLY LOADED LABOR RATES
B117: Laborer
B118: Mechanic
B119: Superintendent
B120: Project Manager
A122: SCHEDULE
B123: Prepared shop drawings/submittals
B124: Mobilization
B125: Total duration to complete scope of work
A127: Winner
A128: Company
A129: Contact
A130: Phone
A131: Email
A132: Base Bid
B134: Need Prequalification
B135: Prequalified

Sheet 03F Concrete Restoration
G1: Hedrick Plug
F2: X | G2: Excluded
B3: BACK TO SUMMARY SHEET | F3: I | G3: Included | H3: Bidder1 | J3: Bidder 2 | L3: Bidder 3 | N3: Bidder 4 | P3: Bidder 5 | R3: Bidder 6
A4: Project: | B4: ='Area Calculations'!B4 -> Project Name | G4: Company
A5: Trade: | B5: Concrete Restoration | G5: Contact
A6: CSI Code: | B6: 03F | G6: Phone
A7: Date: | G7: Email
A8: Adjusted Bid | G8: Adjusted Bid | H8: =I96 -> 0 | J8: =K96 -> 0 | L8: =M96 -> 0 | N8: =O96 -> 0 | P8: =Q96 -> 0 | R8: =S96 -> 0
A9: BID DOCUMENTS: | C9: Plan/ Spec. Package | D9: QTY | E9: U/M | F9: Unit Cost | G9: Subtotal | H9: Yes/No | I9: Price | J9: Yes/No | K9: Price | L9: Yes/No | M9: Price | N9: Yes/No | O9: Price | P9: Yes/No | Q9: Price | R9: Yes/No | S9: Price
B10: Plans By Division
B11: ='Area Calculations'!L62 -> Architectural Drawings by | C11: P
B12: ='Area Calculations'!L63 -> Structural Drawings by | C12: P
B13: ='Area Calculations'!L64 -> MEP FA FP Drawings by | C13: P
B14: ='Area Calculations'!L65 -> Civil Drawings by | C14: P
B15: ='Area Calculations'!L66 -> Land scape Drawings by | C15: P
B16: ='Area Calculations'!L67 -> Kitchen Drawings by
B17: ='Area Calculations'!L68 -> Storefront Designer by
B18: ='Area Calculations'!L69 -> Geotech report by | C18: P
B19: ='Area Calculations'!L70 -> Specifications
B21: Concrete Restoration
B22: GENERAL INCLUSIONS
B23: INCLUDES ALL SALES TAX
B24: ALL HOISTING & RIGGING REQUIRED TO COMPLETE THIS SCOPE
B25: PROVIDE P&P BONDS
B26: FLORIDA STATE CONTRACTORS LIC.
B27: GENERAL LIABILITY AND WORKERS COMP. INSURANCE LIMITS
B28: STATE AND LOCAL TAXES
B29: COMPASS
B30: SPECIFIC TRADE SCOPE OF WORK REQUIREMENTS
B31: BASE BID
B32: Building SF
... B41: Dumpster Enclosure
B42: Monument Sign - | H42: i
B44: SLAB-ON-GRADE
B45: 5" Slab w/ WWF 6x6 w.2.9xw2.9
B46: a. Soil poisoning and pre-treat
B47: b. Fine grading building pad
B48: d. F&I rebar, as per plans
B49: e. F&I wire mesh, as per plans
B50: f. 4,000 PSI
B51: g. Sawcut constr. / control joints
B52: h. Finish slab to FF25/FL17
B53: i. Leave out strip, compact
B54: j. Patch slab after tilt operations
B55: k. Provide curing compound
... B85: Panel structural engineering
F92: SUBTOTAL | I92: =SUM(I24:I91) -> 0 | K92: =SUM(K24:K91) -> 0 | M92: =SUM(M24:M91) -> 0 | O92: =SUM(O24:O91) -> 0 | Q92: =SUM(Q24:Q91) -> 0 | S92: =SUM(S24:S91) -> 0
F93: BOND RATE | H93: 0 | J93: 0 | L93: 0 | N93: 0 | P93: 0 | R93: 0
F94: BOND AMOUNT | I94: =H93*I92 -> 0 | K94: =J93*K92 -> 0 | M94: =L93*M92 -> 0 | O94: =N93*O92 -> 0 | Q94: =P93*Q92 -> 0 | S94: =R93*S92 -> 0
F96: ADJUSTED TOTAL | I96: =SUM(I92:I94) -> 0 | K96: =SUM(K92:K94) -> 0 | M96: =SUM(M92:M94) -> 0 | O96: =SUM(O92:O94) -> 0 | Q96: =SUM(Q92:Q94) -> 0 | S96: =SUM(S92:S94) -> 0
F97: Cost per SF | I97: =I96/'Area Calculations'!$I$4 -> #DIV/0! | K97: =K96/'Area Calculations'!$I$4 -> #DIV/0! | M97: =M96/'Area Calculations'!$I$4 -> #DIV/0! | O97: =O96/'Area Calculations'!$I$4 -> #DIV/0! | Q97: =Q96/'Area Calculations'!$I$4 -> #DIV/0! | S97: =S96/'Area Calculations'!$I$4 -> #DIV/0!
F98: Cost per Unit | I98: =I96/'Area Calculations'!#REF! -> #REF! | K98: =K96/'Area Calculations'!#REF! -> #REF! | M98: =M96/'Area Calculations'!#REF! -> #REF! | O98: =O96/'Area Calculations'!#REF! -> #REF! | Q98: =Q96/'Area Calculations'!#REF! -> #REF! | S98: =S96/'Area Calculations'!#REF! -> #REF!
A100: QUALIFICATIONS
A104: EXCLUSIONS/OWNER PROVIDED ITEMS:
A108: ALTERNATES:
A112: PROPOSED VE (Provide Clear Description):
A116: FULLY LOADED LABOR RATES
B117: Laborer
B118: Mechanic
B119: Superintendent
B120: Project Manager
A122: SCHEDULE
B123: Prepared shop drawings/submittals
B124: Mobilization
B125: Total duration to complete scope of work
A127: Winner
A128: Company
A129: Contact
A130: Phone
A131: Email
A132: Base Bid
B134: Need Prequalification
B135: Prequalified

Sheet 04A Masonry
G1: Hedrick Plug
F2: X | G2: Excluded
B3: BACK TO SUMMARY SHEET | F3: I | G3: Included | H3: Bidder1 | J3: Bidder 2 | L3: Bidder 3 | N3: Bidder 4 | P3: Bidder 5 | R3: Bidder 6
A4: Project: | B4: ='Area Calculations'!B4 -> Project Name | G4: Company
A5: Trade: | B5: Masonry | G5: Contact
A6: CSI Code: | B6: 04A | G6: Phone
A7: Date: | G7: Email
A8: Adjusted Bid | G8: Adjusted Bid | H8: =I86 -> 0 | J8: =K86 -> 0 | L8: =M86 -> 0 | N8: =O86 -> 0 | P8: =Q86 -> 0 | R8: =S86 -> 0
A9: BID DOCUMENTS: | C9: Plan/ Spec. Package | D9: QTY | E9: U/M | F9: Unit Cost | G9: Subtotal | H9: Yes/No | I9: Price | J9: Yes/No | K9: Price | L9: Yes/No | M9: Price | N9: Yes/No | O9: Price | P9: Yes/No | Q9: Price | R9: Yes/No | S9: Price
B10: Plans By Division
B11: ='Area Calculations'!L62 -> Architectural Drawings by | C11: P
B12: ='Area Calculations'!L63 -> Structural Drawings by | C12: P
B13: ='Area Calculations'!L64 -> MEP FA FP Drawings by | C13: P
B14: ='Area Calculations'!L65 -> Civil Drawings by | C14: P
B15: ='Area Calculations'!L66 -> Land scape Drawings by | C15: P
B16: ='Area Calculations'!L67 -> Kitchen Drawings by
B17: ='Area Calculations'!L68 -> Storefront Designer by
B18: ='Area Calculations'!L69 -> Geotech report by | C18: P
B19: ='Area Calculations'!L70 -> Specifications
B21: Masonry
B22: GENERAL INCLUSIONS
B23: INCLUDES ALL SALES TAX
B24: ALL HOISTING & RIGGING REQUIRED TO COMPLETE THIS SCOPE
B25: PROVIDE P&P BONDS
B26: FLORIDA STATE CONTRACTORS LIC.
B27: GENERAL LIABILITY AND WORKERS COMP. INSURANCE LIMITS
B28: STATE AND LOCAL TAXES
B29: COMPASS
B30: SPECIFIC TRADE SCOPE OF WORK REQUIREMENTS
B31: BASE BID
B32: Building SF
... B39: e. Horizontal Reinf.
B40: f. Lintels, ladder wire and accessories | H40: i
B41: g. Setting of Joist Embeds & door frames
B42: h. Above scope included for:
B43: 1)
B44: 2)
B45: 3)
F82: SUBTOTAL | I82: =SUM(I24:I81) -> 0 | K82: =SUM(K24:K81) -> 0 | M82: =SUM(M24:M81) -> 0 | O82: =SUM(O24:O81) -> 0 | Q82: =SUM(Q24:Q81) -> 0 | S82: =SUM(S24:S81) -> 0
F83: BOND RATE | H83: 0 | J83: 0 | L83: 0 | N83: 0 | P83: 0 | R83: 0
F84: BOND AMOUNT | I84: =H83*I82 -> 0 | K84: =J83*K82 -> 0 | M84: =L83*M82 -> 0 | O84: =N83*O82 -> 0 | Q84: =P83*Q82 -> 0 | S84: =R83*S82 -> 0
F86: ADJUSTED TOTAL | I86: =SUM(I82:I84) -> 0 | K86: =SUM(K82:K84) -> 0 | M86: =SUM(M82:M84) -> 0 | O86: =SUM(O82:O84) -> 0 | Q86: =SUM(Q82:Q84) -> 0 | S86: =SUM(S82:S84) -> 0
F87: Cost per SF | I87: =I86/'Area Calculations'!$I$4 -> #DIV/0! | K87: =K86/'Area Calculations'!$I$4 -> #DIV/0! | M87: =M86/'Area Calculations'!$I$4 -> #DIV/0! | O87: =O86/'Area Calculations'!$I$4 -> #DIV/0! | Q87: =Q86/'Area Calculations'!$I$4 -> #DIV/0! | S87: =S86/'Area Calculations'!$I$4 -> #DIV/0!
F88: Cost per Unit | I88: =I86/'Area Calculations'!#REF! -> #REF! | K88: =K86/'Area Calculations'!#REF! -> #REF! | M88: =M86/'Area Calculations'!#REF! -> #REF! | O88: =O86/'Area Calculations'!#REF! -> #REF! | Q88: =Q86/'Area Calculations'!#REF! -> #REF! | S88: =S86/'Area Calculations'!#REF! -> #REF!
A90: QUALIFICATIONS
A94: EXCLUSIONS/OWNER PROVIDED ITEMS:
A98: ALTERNATES:
A102: PROPOSED VE (Provide Clear Description):
A106: FULLY LOADED LABOR RATES
B107: Laborer
B108: Mechanic
B109: Superintendent
B110: Project Manager
A112: SCHEDULE
B113: Prepared shop drawings/submittals
B114: Mobilization
B115: Total duration to complete scope of work
A117: Winner
A118: Company
A119: Contact
A120: Phone
A121: Email
A122: Base Bid
B124: Need Prequalification
B125: Prequalified

Sheet 04B Stone Veneer
G1: Hedrick Plug
F2: X | G2: Excluded
B3: BACK TO SUMMARY SHEET | F3: I | G3: Included | H3: Bidder 1 | J3: Bidder2 | L3: Bidder 3 | N3: Bidder 4 | P3: Bidder5 | R3: Bidder6
A4: Project: | B4: ='Area Calculations'!B4 -> Project Name | G4: Company
A5: Trade: | B5: Cast Stone, Stone Veneer | G5: Contact
A6: CSI Code: | B6: 04B | G6: Phone
A7: Date: | G7: Email
A8: Adjusted Bid | G8: Adjusted Bid | H8: =I65 -> 0 | J8: =K65 -> 0 | L8: =M65 -> 0 | N8: =O65 -> 0 | P8: =Q65 -> 0 | R8: =S65 -> 0
A9: BID DOCUMENTS: | C9: Plan/ Spec. Package | D9: QTY | E9: U/M | F9: Unit Cost | G9: Subtotal | H9: Yes/No | I9: Price | J9: Yes/No | K9: Price | L9: Yes/No | M9: Price | N9: Yes/No | O9: Price | P9: Yes/No | Q9: Price | R9: Yes/No | S9: Price
B10: Plans By Division
B11: ='Area Calculations'!L62 -> Architectural Drawings by | C11: P
B12: ='Area Calculations'!L63 -> Structural Drawings by | C12: P
B13: ='Area Calculations'!L64 -> MEP FA FP Drawings by | C13: P
B14: ='Area Calculations'!L65 -> Civil Drawings by | C14: P
B15: ='Area Calculations'!L66 -> Land scape Drawings by | C15: P
B16: ='Area Calculations'!L67 -> Kitchen Drawings by | C16: P
B17: ='Area Calculations'!L68 -> Storefront Designer by | C17: P
B18: ='Area Calculations'!L69 -> Geotech report by | C18: P
B19: ='Area Calculations'!L70 -> Specifications
B21: Cast Stone, Stone Veneer
B22: GENERAL INCLUSIONS
B23: INCLUDES ALL SALES TAX
B24: ALL HOISTING & RIGGING REQUIRED TO COMPLETE THIS SCOPE
B25: PROVIDE P&P BONDS
B26: FLORIDA STATE CONTRACTORS LIC.
B27: GENERAL LIABILITY AND WORKERS COMP. INSURANCE LIMITS
B28: STATE AND LOCAL TAXES
B29: COMPASS
B30: SPECIFIC TRADE SCOPE OF WORK REQUIREMENTS
B31: BASE BID
B33: Stone Veneer, Incl.:
... B54: Self-adhering reflective rubberized asphalt membrane , 25 mils thickness minimum flashing, corner flashing to be 8"-12" and opening flashing to be 4" minimum
B55: Silicone sealant | H55: x
F61: SUBTOTAL | I61: =SUM(I16:I60) -> 0 | K61: =SUM(K16:K60) -> 0 | M61: =SUM(M16:M60) -> 0 | O61: =SUM(O16:O60) -> 0 | Q61: =SUM(Q16:Q60) -> 0 | S61: =SUM(S16:S60) -> 0
F62: BOND RATE | H62: 0 | J62: 0 | L62: 0 | N62: 0 | P62: 0 | R62: 0
F63: BOND AMOUNT | I63: =H62*I61 -> 0 | K63: =J62*K61 -> 0 | M63: =L62*M61 -> 0 | O63: =N62*O61 -> 0 | Q63: =P62*Q61 -> 0 | S63: =R62*S61 -> 0
F65: ADJUSTED TOTAL | I65: =SUM(I61:I63) -> 0 | K65: =SUM(K61:K63) -> 0 | M65: =SUM(M61:M63) -> 0 | O65: =SUM(O61:O63) -> 0 | Q65: =SUM(Q61:Q63) -> 0 | S65: =SUM(S61:S63) -> 0
F66: Cost per SF | I66: =I65/'Area Calculations'!$I$4 -> #DIV/0! | K66: =K65/'Area Calculations'!$I$4 -> #DIV/0! | M66: =M65/'Area Calculations'!$I$4 -> #DIV/0! | O66: =O65/'Area Calculations'!$I$4 -> #DIV/0! | Q66: =Q65/'Area Calculations'!$I$4 -> #DIV/0! | S66: =S65/'Area Calculations'!$I$4 -> #DIV/0!
F67: Cost per Unit | I67: =I65/'Area Calculations'!#REF! -> #REF! | K67: =K65/'Area Calculations'!#REF! -> #REF! | M67: =M65/'Area Calculations'!#REF! -> #REF! | O67: =O65/'Area Calculations'!#REF! -> #REF! | Q67: =Q65/'Area Calculations'!#REF! -> #REF! | S67: =S65/'Area Calculations'!#REF! -> #REF!
A69: QUALIFICATIONS
A73: EXCLUSIONS/OWNER PROVIDED ITEMS:
A77: ALTERNATES:
A81: PROPOSED VE (Provide Clear Description):
A85: FULLY LOADED LABOR RATES
B86: Laborer
B87: Mechanic
B88: Superintendent
B89: Project Manager
A91: SCHEDULE
B92: Prepared shop drawings/submittals
B93: Mobilization
B94: Total duration to complete scope of work
A96: Winner
A97: Company
A98: Contact
A99: Phone
A100: Email
A101: Base Bid
B103: Need Prequalification
B104: Prequalified

Sheet 05A Structural Steel
G1: Hedrick Plug
F2: X | G2: Excluded
B3: BACK TO SUMMARY SHEET | F3: I | G3: Included | H3: Bidder 1 | J3: Bidder 2 | L3: Bidder 3 | N3: Bidder 4 | P3: Bidder5 | R3: Bidder6
A4: Project: | B4: ='Area Calculations'!B4 -> Project Name | G4: Company
A5: Trade: | B5: Structural Steel | G5: Contact
A6: CSI Code: | B6: 05A | G6: Phone
A7: Date: | G7: Email
A8: Adjusted Bid | G8: Adjusted Bid | H8: =I56 -> 0 | J8: =K56 -> 0 | L8: =M56 -> 0 | N8: =O56 -> 0 | P8: =Q56 -> 0 | R8: =S56 -> 0
A9: BID DOCUMENTS: | C9: Plan/ Spec. Package | D9: QTY | E9: U/M | F9: Unit Cost | G9: Subtotal | H9: Yes/No | I9: Price | J9: Yes/No | K9: Price | L9: Yes/No | M9: Price | N9: Yes/No | O9: Price | P9: Yes/No | Q9: Price | R9: Yes/No | S9: Price
B10: Plans By Division
B11: ='Area Calculations'!L62 -> Architectural Drawings by | C11: P
B12: ='Area Calculations'!L63 -> Structural Drawings by | C12: P
B13: ='Area Calculations'!L64 -> MEP FA FP Drawings by | C13: P
B14: ='Area Calculations'!L65 -> Civil Drawings by | C14: P
B15: ='Area Calculations'!L66 -> Land scape Drawings by | C15: P
B16: ='Area Calculations'!L67 -> Kitchen Drawings by | C16: P
B17: ='Area Calculations'!L68 -> Storefront Designer by | C17: P
B18: ='Area Calculations'!L69 -> Geotech report by | C18: P
B19: ='Area Calculations'!L70 -> Specifications | C19: P
B21: Structural Steel
B22: GENERAL INCLUSIONS
B23: INCLUDES ALL SALES TAX
B24: ALL HOISTING & RIGGING REQUIRED TO COMPLETE THIS SCOPE
B25: PROVIDE P&P BONDS
B26: FLORIDA STATE CONTRACTORS LIC.
B27: GENERAL LIABILITY AND WORKERS COMP. INSURANCE LIMITS
B28: STATE AND LOCAL TAXES
B29: COMPASS
B30: SPECIFIC TRADE SCOPE OF WORK REQUIREMENTS
B31: BASE BID
B32: Building SF
... B40: f. Above scope included for:
H44: x
F52: SUBTOTAL | I52: =SUM(I23:I51) -> 0 | K52: =SUM(K23:K51) -> 0 | M52: =SUM(M23:M51) -> 0 | O52: =SUM(O23:O51) -> 0 | Q52: =SUM(Q23:Q51) -> 0 | S52: =SUM(S23:S51) -> 0
F53: BOND RATE | H53: 0 | J53: 0 | L53: 0 | N53: 0 | P53: 0 | R53: 0
F54: BOND AMOUNT | I54: =H53*$I$52 -> 0 | K54: =J53*$I$52 -> 0 | M54: =L53*$I$52 -> 0 | O54: =N53*$I$52 -> 0 | Q54: =P53*$I$52 -> 0 | S54: =R53*$I$52 -> 0
F56: ADJUSTED TOTAL | I56: =SUM(I52:I54) -> 0 | K56: =SUM(K52:K54) -> 0 | M56: =SUM(M52:M54) -> 0 | O56: =SUM(O52:O54) -> 0 | Q56: =SUM(Q52:Q54) -> 0 | S56: =SUM(S52:S54) -> 0
F57: Cost per SF | I57: =I56/'Area Calculations'!$I$4 -> #DIV/0! | K57: =K56/'Area Calculations'!$I$4 -> #DIV/0! | M57: =M56/'Area Calculations'!$I$4 -> #DIV/0! | O57: =O56/'Area Calculations'!$I$4 -> #DIV/0! | Q57: =Q56/'Area Calculations'!$I$4 -> #DIV/0! | S57: =S56/'Area Calculations'!$I$4 -> #DIV/0!
F58: Cost per Unit | I58: =I56/'Area Calculations'!#REF! -> #REF! | K58: =K56/'Area Calculations'!#REF! -> #REF! | M58: =M56/'Area Calculations'!#REF! -> #REF! | O58: =O56/'Area Calculations'!#REF! -> #REF! | Q58: =Q56/'Area Calculations'!#REF! -> #REF! | S58: =S56/'Area Calculations'!#REF! -> #REF!
A60: QUALIFICATIONS
A64: EXCLUSIONS/OWNER PROVIDED ITEMS:
A68: ALTERNATES:
A72: PROPOSED VE (Provide Clear Description):
A76: FULLY LOADED LABOR RATES
B77: Laborer
B78: Mechanic
B79: Superintendent
B80: Project Manager
A82: SCHEDULE
B83: Prepared shop drawings/submittals
B84: Mobilization
B85: Total duration to complete scope of work
A87: Winner
A88: Company
A89: Contact
A90: Phone
A91: Email
A92: Base Bid
B94: Need Prequalification
B95: Prequalified

Sheet 05B Metal Trusses
G1: Hedrick Plug
F2: X | G2: Excluded
B3: BACK TO SUMMARY SHEET | F3: I | G3: Included | H3: Bidder 1 | J3: Bidder 2 | L3: Bidder 3 | N3: Bidder 4 | P3: Bidder 5 | R3: Bidder 6
A4: Project: | B4: ='Area Calculations'!B4 -> Project Name | G4: Company
A5: Trade: | B5: Metal Trusses | G5: Contact
A6: CSI Code: | B6: 05B | G6: Phone
A7: Date: | G7: Email
A8: Adjusted Bid | G8: Adjusted Bid | H8: =I52 -> 0 | J8: =K52 -> 0 | L8: =M52 -> 0 | N8: =O52 -> 0 | P8: =Q52 -> 0 | R8: =S52 -> 0
A9: BID DOCUMENTS: | C9: Plan/ Spec. Package | D9: QTY | E9: U/M | F9: Unit Cost | G9: Subtotal | H9: Yes/No | I9: Price | J9: Yes/No | K9: Price | L9: Yes/No | M9: Price | N9: Yes/No | O9: Price | P9: Yes/No | Q9: Price | R9: Yes/No | S9: Price
B10: Plans By Division
B11: ='Area Calculations'!L62 -> Architectural Drawings by | C11: P
B12: ='Area Calculations'!L63 -> Structural Drawings by | C12: P
B13: ='Area Calculations'!L64 -> MEP FA FP Drawings by | C13: P
B14: ='Area Calculations'!L65 -> Civil Drawings by | C14: P
B15: ='Area Calculations'!L66 -> Land scape Drawings by | C15: P
B16: ='Area Calculations'!L67 -> Kitchen Drawings by | C16: P
B17: ='Area Calculations'!L68 -> Storefront Designer by | C17: P
B18: ='Area Calculations'!L69 -> Geotech report by | C18: P
B19: ='Area Calculations'!L70 -> Specifications | C19: P
B21: Metal Trusses
B22: GENERAL INCLUSIONS
B23: INCLUDES ALL SALES TAX
B24: ALL HOISTING & RIGGING REQUIRED TO COMPLETE THIS SCOPE
B25: PROVIDE P&P BONDS
B26: FLORIDA STATE CONTRACTORS LIC.
B27: GENERAL LIABILITY AND WORKERS COMP. INSURANCE LIMITS
B28: STATE AND LOCAL TAXES
B29: COMPASS
B30: SPECIFIC TRADE SCOPE OF WORK REQUIREMENTS
B31: BASE BID
B32: Building SF
B34: Structural Steel , incl.:
B35: a. Equipment, cranes, etc. | H35: i
B36: b. scheduled/detailed shop drawings.
B37: c. Steel Columns, W-Beams, Joists and Metal Decking as scheduled.
B38: d. Steel connections, angle iron, steel beam at elevator.
B39: e. Roof top equipment structural requirements.
B40: f. Above scope included for:
F48: SUBTOTAL | I48: =SUM(I23:I47) -> 0 | K48: =SUM(K23:K47) -> 0 | M48: =SUM(M23:M47) -> 0 | O48: =SUM(O23:O47) -> 0 | Q48: =SUM(Q23:Q47) -> 0 | S48: =SUM(S23:S47) -> 0
F49: BOND RATE | H49: 0 | J49: 0 | L49: 0 | N49: 0 | P49: 0 | R49: 0
F50: BOND AMOUNT | I50: =H49*$I$48 -> 0 | K50: =J49*$K$48 -> 0 | M50: =L49*$K$48 -> 0 | O50: =N49*$K$48 -> 0 | Q50: =P49*$K$48 -> 0 | S50: =R49*$K$48 -> 0
F52: ADJUSTED TOTAL | I52: =SUM(I48:I50) -> 0 | K52: =SUM(K48:K50) -> 0 | M52: =SUM(M48:M50) -> 0 | O52: =SUM(O48:O50) -> 0 | Q52: =SUM(Q48:Q50) -> 0 | S52: =SUM(S48:S50) -> 0
F53: Cost per SF | I53: =I52/'Area Calculations'!$I$4 -> #DIV/0! | K53: =K52/'Area Calculations'!$I$4 -> #DIV/0! | M53: =M52/'Area Calculations'!$I$4 -> #DIV/0! | O53: =O52/'Area Calculations'!$I$4 -> #DIV/0! | Q53: =Q52/'Area Calculations'!$I$4 -> #DIV/0! | S53: =S52/'Area Calculations'!$I$4 -> #DIV/0!
F54: Cost per Unit | I54: =I52/'Area Calculations'!#REF! -> #REF! | K54: =K52/'Area Calculations'!#REF! -> #REF! | M54: =M52/'Area Calculations'!#REF! -> #REF! | O54: =O52/'Area Calculations'!#REF! -> #REF! | Q54: =Q52/'Area Calculations'!#REF! -> #REF! | S54: =S52/'Area Calculations'!#REF! -> #REF!
A56: QUALIFICATIONS
A60: EXCLUSIONS/OWNER PROVIDED ITEMS:
A64: ALTERNATES:
A68: PROPOSED VE (Provide Clear Description):
A72: FULLY LOADED LABOR RATES
B73: Laborer
B74: Mechanic
B75: Superintendent
B76: Project Manager
A78: SCHEDULE
B79: Prepared shop drawings/submittals
B80: Mobilization
B81: Total duration to complete scope of work
A83: Winner
A84: Company
A85: Contact
A86: Phone
A87: Email
A88: Base Bid
B90: Need Prequalification
B91: Prequalified

Sheet 05C Misc. Metals
G1: Hedrick Plug
F2: X | G2: Excluded
B3: BACK TO SUMMARY SHEET | F3: I | G3: Included | H3: Bidder 1 | J3: Bidder 2 | L3: Bidder 3 | N3: Bidder 4 | P3: Bidder 5 | R3: Bidder 6
A4: Project: | B4: ='Area Calculations'!B4 -> Project Name | G4: Company
A5: Trade: | B5: Misc. Metals | G5: Contact
A6: CSI Code: | B6: 05C | G6: Phone
A7: Date: | G7: Email
A8: Adjusted Bid | G8: Adjusted Bid | H8: =I55 -> 0 | J8: =K55 -> 0 | L8: =M55 -> 0 | N8: =O55 -> 0 | P8: =Q55 -> 0 | R8: =S55 -> 0
A9: BID DOCUMENTS: | C9: Plan/ Spec. Package | D9: QTY | E9: U/M | F9: Unit Cost | G9: Subtotal | H9: Yes/No | I9: Price | J9: Yes/No | K9: Price | L9: Yes/No | M9: Price | N9: Yes/No | O9: Price | P9: Yes/No | Q9: Price | R9: Yes/No | S9: Price
B10: Plans By Division
B11: ='Area Calculations'!L62 -> Architectural Drawings by | C11: P
B12: ='Area Calculations'!L63 -> Structural Drawings by | C12: P
B13: ='Area Calculations'!L64 -> MEP FA FP Drawings by | C13: P
B14: ='Area Calculations'!L65 -> Civil Drawings by | C14: P
B15: ='Area Calculations'!L66 -> Land scape Drawings by | C15: P
B16: ='Area Calculations'!L67 -> Kitchen Drawings by | C16: P
B17: ='Area Calculations'!L68 -> Storefront Designer by | C17: P
B18: ='Area Calculations'!L69 -> Geotech report by | C18: P
B19: ='Area Calculations'!L70 -> Specifications | C19: P
B21: Misc. Metals
B22: GENERAL INCLUSIONS
B23: INCLUDES ALL SALES TAX
B24: ALL HOISTING & RIGGING REQUIRED TO COMPLETE THIS SCOPE
B25: PROVIDE P&P BONDS
B26: FLORIDA STATE CONTRACTORS LIC.
B27: GENERAL LIABILITY AND WORKERS COMP. INSURANCE LIMITS
B28: STATE AND LOCAL TAXES
B29: COMPASS
B30: SPECIFIC TRADE SCOPE OF WORK REQUIREMENTS
B31: BASE BID
H38: x
F51: SUBTOTAL | I51: =SUM(I23:I50) -> 0 | K51: =SUM(K23:K50) -> 0 | M51: =SUM(M22:M50) -> 0 | O51: =SUM(O22:O50) -> 0 | Q51: =SUM(Q23:Q50) -> 0 | S51: =SUM(S23:S50) -> 0
F52: BOND RATE | H52: 0 | J52: 0 | L52: 0.02 | N52: 0.02 | P52: 0.02 | R52: 0.02
F53: BOND AMOUNT | I53: =H52*$I$51 -> 0 | K53: =J52*$K$51 -> 0 | M53: =L52*$M$51 -> 0 | O53: =N52*$O$51 -> 0 | Q53: =P52*$Q$51 -> 0 | S53: =R52*S51 -> 0
F55: ADJUSTED TOTAL | I55: =SUM(I51:I54) -> 0 | K55: =SUM(K51:K53) -> 0 | M55: =SUM(M51:M53) -> 0 | O55: =SUM(O51:O53) -> 0 | Q55: =SUM(Q51:Q53) -> 0 | S55: =SUM(S51:S53) -> 0
F56: Cost per SF | I56: =I55/'Area Calculations'!$I$4 -> #DIV/0! | K56: =K55/'Area Calculations'!$I$4 -> #DIV/0! | M56: =M55/'Area Calculations'!$I$4 -> #DIV/0! | O56: =O55/'Area Calculations'!$I$4 -> #DIV/0! | Q56: =Q55/'Area Calculations'!$I$4 -> #DIV/0! | S56: =S55/'Area Calculations'!$I$4 -> #DIV/0!
F57: Cost per Unit | I57: =I55/'Area Calculations'!#REF! -> #REF! | K57: =K55/'Area Calculations'!#REF! -> #REF! | M57: =M55/'Area Calculations'!#REF! -> #REF! | O57: =O55/'Area Calculations'!#REF! -> #REF! | Q57: =Q55/'Area Calculations'!#REF! -> #REF! | S57: =S55/'Area Calculations'!#REF! -> #REF!
A59: QUALIFICATIONS
A63: EXCLUSIONS/OWNER PROVIDED ITEMS:
A67: ALTERNATES:
A71: PROPOSED VE (Provide Clear Description):
A75: FULLY LOADED LABOR RATES
B76: Laborer
B77: Mechanic
B78: Superintendent
B79: Project Manager
A81: SCHEDULE
B82: Prepared shop drawings/submittals
B83: Mobilization
B84: Total duration to complete scope of work
A86: Winner
A87: Company
A88: Contact
A89: Phone
A90: Email
A91: Base Bid
B93: Need Prequalification
B94: Prequalified

Sheet 05D Handrailings & Railings
G1: Hedrick Plug
F2: X | G2: Excluded
B3: BACK TO SUMMARY SHEET | F3: I | G3: Included | H3: Bidder 1 | J3: Bidder 2 | L3: Bidder 3 | N3: Bidder 4 | P3: Bidder 5 | R3: Bidder 6
A4: Project: | B4: ='Area Calculations'!B4 -> Project Name | G4: Company
A5: Trade: | B5: Handrailings & Railings | G5: Contact
A6: CSI Code: | B6: 05D | G6: Phone
A7: Date: | G7: Email
A8: Adjusted Bid | G8: Adjusted Bid | H8: =I55 -> 0 | J8: =K55 -> 0 | L8: =M55 -> 0 | N8: =O55 -> 0 | P8: =Q55 -> 0 | R8: =S55 -> 0
A9: BID DOCUMENTS: | C9: Plan/ Spec. Package | D9: QTY | E9: U/M | F9: Unit Cost | G9: Subtotal | H9: Yes/No | I9: Price | J9: Yes/No | K9: Price | L9: Yes/No | M9: Price | N9: Yes/No | O9: Price | P9: Yes/No | Q9: Price | R9: Yes/No | S9: Price
B10: Plans By Division
B11: ='Area Calculations'!L62 -> Architectural Drawings by | C11: P
B12: ='Area Calculations'!L63 -> Structural Drawings by | C12: P
B13: ='Area Calculations'!L64 -> MEP FA FP Drawings by | C13: P
B14: ='Area Calculations'!L65 -> Civil Drawings by | C14: P
B15: ='Area Calculations'!L66 -> Land scape Drawings by | C15: P
B16: ='Area Calculations'!L67 -> Kitchen Drawings by | C16: P
B17: ='Area Calculations'!L68 -> Storefront Designer by | C17: P
B18: ='Area Calculations'!L69 -> Geotech report by | C18: P
B19: ='Area Calculations'!L70 -> Specifications | C19: P
B21: Handrailings & Railings
B22: GENERAL INCLUSIONS
B23: INCLUDES ALL SALES TAX
B24: ALL HOISTING & RIGGING REQUIRED TO COMPLETE THIS SCOPE
B25: PROVIDE P&P BONDS
B26: FLORIDA STATE CONTRACTORS LIC.
B27: GENERAL LIABILITY AND WORKERS COMP. INSURANCE LIMITS
B28: STATE AND LOCAL TAXES
B29: COMPASS
B30: SPECIFIC TRADE SCOPE OF WORK REQUIREMENTS
B31: BASE BID
H38: x
F51: SUBTOTAL | I51: =SUM(I23:I50) -> 0 | K51: =SUM(K23:K50) -> 0 | M51: =SUM(M22:M50) -> 0 | O51: =SUM(O22:O50) -> 0 | Q51: =SUM(Q23:Q50) -> 0 | S51: =SUM(S23:S50) -> 0
F52: BOND RATE | H52: 0 | J52: 0 | L52: 0.02 | N52: 0.02 | P52: 0.02 | R52: 0.02
F53: BOND AMOUNT | I53: =H52*$I$51 -> 0 | K53: =J52*$K$51 -> 0 | M53: =L52*$M$51 -> 0 | O53: =N52*$O$51 -> 0 | Q53: =P52*$Q$51 -> 0 | S53: =R52*S51 -> 0
F55: ADJUSTED TOTAL | I55: =SUM(I51:I54) -> 0 | K55: =SUM(K51:K53) -> 0 | M55: =SUM(M51:M53) -> 0 | O55: =SUM(O51:O53) -> 0 | Q55: =SUM(Q51:Q53) -> 0 | S55: =SUM(S51:S53) -> 0
F56: Cost per SF | I56: =I55/'Area Calculations'!$I$4 -> #DIV/0! | K56: =K55/'Area Calculations'!$I$4 -> #DIV/0! | M56: =M55/'Area Calculations'!$I$4 -> #DIV/0! | O56: =O55/'Area Calculations'!$I$4 -> #DIV/0! | Q56: =Q55/'Area Calculations'!$I$4 -> #DIV/0! | S56: =S55/'Area Calculations'!$I$4 -> #DIV/0!
F57: Cost per Unit | I57: =I55/'Area Calculations'!#REF! -> #REF! | K57: =K55/'Area Calculations'!#REF! -> #REF! | M57: =M55/'Area Calculations'!#REF! -> #REF! | O57: =O55/'Area Calculations'!#REF! -> #REF! | Q57: =Q55/'Area Calculations'!#REF! -> #REF! | S57: =S55/'Area Calculations'!#REF! -> #REF!
A59: QUALIFICATIONS
A63: EXCLUSIONS/OWNER PROVIDED ITEMS:
A67: ALTERNATES:
A71: PROPOSED VE (Provide Clear Description):
A75: FULLY LOADED LABOR RATES
B76: Laborer
B77: Mechanic
B78: Superintendent
B79: Project Manager
A81: SCHEDULE
B82: Prepared shop drawings/submittals
B83: Mobilization
B84: Total duration to complete scope of work
A86: Winner
A87: Company
A88: Contact
A89: Phone
A90: Email
A91: Base Bid
B93: Need Prequalification
B94: Prequalified

Sheet 05E Glass Railings
G1: Hedrick Plug
F2: X | G2: Excluded
B3: BACK TO SUMMARY SHEET | F3: I | G3: Included | H3: Bidder 1 | J3: Bidder 2 | L3: Bidder 3 | N3: Bidder 4 | P3: Bidder 5 | R3: Bidder 6
A4: Project: | B4: ='Area Calculations'!B4 -> Project Name | G4: Company
A5: Trade: | B5: Glass Railings | G5: Contact
A6: CSI Code: | B6: 05E | G6: Phone
A7: Date: | G7: Email
A8: Adjusted Bid | G8: Adjusted Bid | H8: =I55 -> 0 | J8: =K55 -> 0 | L8: =M55 -> 0 | N8: =O55 -> 0 | P8: =Q55 -> 0 | R8: =S55 -> 0
A9: BID DOCUMENTS: | C9: Plan/ Spec. Package | D9: QTY | E9: U/M | F9: Unit Cost | G9: Subtotal | H9: Yes/No | I9: Price | J9: Yes/No | K9: Price | L9: Yes/No | M9: Price | N9: Yes/No | O9: Price | P9: Yes/No | Q9: Price | R9: Yes/No | S9: Price
B10: Plans By Division
B11: ='Area Calculations'!L62 -> Architectural Drawings by | C11: P
B12: ='Area Calculations'!L63 -> Structural Drawings by | C12: P
B13: ='Area Calculations'!L64 -> MEP FA FP Drawings by | C13: P
B14: ='Area Calculations'!L65 -> Civil Drawings by | C14: P
B15: ='Area Calculations'!L66 -> Land scape Drawings by | C15: P
B16: ='Area Calculations'!L67 -> Kitchen Drawings by | C16: P
B17: ='Area Calculations'!L68 -> Storefront Designer by | C17: P
B18: ='Area Calculations'!L69 -> Geotech report by | C18: P
B19: ='Area Calculations'!L70 -> Specifications | C19: P
B21: Glass Railings
B22: GENERAL INCLUSIONS
B23: INCLUDES ALL SALES TAX
B24: ALL HOISTING & RIGGING REQUIRED TO COMPLETE THIS SCOPE
B25: PROVIDE P&P BONDS
B26: FLORIDA STATE CONTRACTORS LIC.
B27: GENERAL LIABILITY AND WORKERS COMP. INSURANCE LIMITS
B28: STATE AND LOCAL TAXES
B29: COMPASS
B30: SPECIFIC TRADE SCOPE OF WORK REQUIREMENTS
B31: BASE BID
H38: x
F51: SUBTOTAL | I51: =SUM(I23:I50) -> 0 | K51: =SUM(K23:K50) -> 0 | M51: =SUM(M22:M50) -> 0 | O51: =SUM(O22:O50) -> 0 | Q51: =SUM(Q23:Q50) -> 0 | S51: =SUM(S23:S50) -> 0
F52: BOND RATE | H52: 0 | J52: 0 | L52: 0.02 | N52: 0.02 | P52: 0.02 | R52: 0.02
F53: BOND AMOUNT | I53: =H52*$I$51 -> 0 | K53: =J52*$K$51 -> 0 | M53: =L52*$M$51 -> 0 | O53: =N52*$O$51 -> 0 | Q53: =P52*$Q$51 -> 0 | S53: =R52*S51 -> 0
F55: ADJUSTED TOTAL | I55: =SUM(I51:I54) -> 0 | K55: =SUM(K51:K53) -> 0 | M55: =SUM(M51:M53) -> 0 | O55: =SUM(O51:O53) -> 0 | Q55: =SUM(Q51:Q53) -> 0 | S55: =SUM(S51:S53) -> 0
F56: Cost per SF | I56: =I55/'Area Calculations'!$I$4 -> #DIV/0! | K56: =K55/'Area Calculations'!$I$4 -> #DIV/0! | M56: =M55/'Area Calculations'!$I$4 -> #DIV/0! | O56: =O55/'Area Calculations'!$I$4 -> #DIV/0! | Q56: =Q55/'Area Calculations'!$I$4 -> #DIV/0! | S56: =S55/'Area Calculations'!$I$4 -> #DIV/0!
F57: Cost per Unit | I57: =I55/'Area Calculations'!#REF! -> #REF! | K57: =K55/'Area Calculations'!#REF! -> #REF! | M57: =M55/'Area Calculations'!#REF! -> #REF! | O57: =O55/'Area Calculations'!#REF! -> #REF! | Q57: =Q55/'Area Calculations'!#REF! -> #REF! | S57: =S55/'Area Calculations'!#REF! -> #REF!
A59: QUALIFICATIONS
A63: EXCLUSIONS/OWNER PROVIDED ITEMS:
A67: ALTERNATES:
A71: PROPOSED VE (Provide Clear Description):
A75: FULLY LOADED LABOR RATES
B76: Laborer
B77: Mechanic
B78: Superintendent
B79: Project Manager
A81: SCHEDULE
B82: Prepared shop drawings/submittals
B83: Mobilization
B84: Total duration to complete scope of work
A86: Winner
A87: Company
A88: Contact
A89: Phone
A90: Email
A91: Base Bid
B93: Need Prequalification
B94: Prequalified

Sheet 06A Rough Carpentry
G1: Hedrick Plug
F2: X | G2: Excluded
B3: BACK TO SUMMARY SHEET | F3: I | G3: Included | H3: Bidder 1 | J3: Bidder 2 | L3: Bidder 3 | N3: Bidder 4 | P3: Bidder 5 | R3: Bidder 6
A4: Project: | B4: ='Area Calculations'!B4 -> Project Name | G4: Company
A5: Trade: | B5: Rough Carpentry | G5: Contact
A6: CSI Code: | B6: 06A | G6: Phone
A7: Date: | G7: Email
A8: Adjusted Bid | G8: Adjusted Bid | H8: =I67 -> 0 | J8: =K67 -> 0 | L8: =M67 -> 0 | N8: =O67 -> 0 | P8: =Q67 -> 0 | R8: =S67 -> 0
A9: BID DOCUMENTS: | C9: Plan/ Spec. Package | D9: QTY | E9: U/M | F9: Unit Cost | G9: Subtotal | H9: Yes/No | I9: Price | J9: Yes/No | K9: Price | L9: Yes/No | M9: Price | N9: Yes/No | O9: Price | P9: Yes/No | Q9: Price | R9: Yes/No | S9: Price
B10: Plans By Division
B11: ='Area Calculations'!L62 -> Architectural Drawings by | C11: P
B12: ='Area Calculations'!L63 -> Structural Drawings by | C12: P
B13: ='Area Calculations'!L64 -> MEP FA FP Drawings by | C13: P
B14: ='Area Calculations'!L65 -> Civil Drawings by | C14: P
B15: ='Area Calculations'!L66 -> Land scape Drawings by | C15: P
B16: ='Area Calculations'!L67 -> Kitchen Drawings by | C16: P
B17: ='Area Calculations'!L68 -> Storefront Designer by | C17: P
B18: ='Area Calculations'!L69 -> Geotech report by | C18: P
B19: ='Area Calculations'!L70 -> Specifications | C19: P
B21: Rough Carpentry
B22: GENERAL INCLUSIONS
B23: INCLUDES ALL SALES TAX
B24: ALL HOISTING & RIGGING REQUIRED TO COMPLETE THIS SCOPE
B25: PROVIDE P&P BONDS
B26: FLORIDA STATE CONTRACTORS LIC.
B27: GENERAL LIABILITY AND WORKERS COMP. INSURANCE LIMITS
B28: STATE AND LOCAL TAXES
B29: COMPASS
B30: SPECIFIC TRADE SCOPE OF WORK REQUIREMENTS
B31: BASE BID
B32: Building SF
... B35: a. size off wood buck - material
B36: b. labor to install | H36: i
B37: c. achoring material
B39: Exterior Windows:
B40: a. size off wood buck - material
B41: b. labor to install
B42: c. achoring material
B44: Parapet Wood Nailers:
B45: a. size off wood buck - material
B46: b. labor to install
B47: c. achoring material
B49: Rough Carpentry
B50: a. Install wood trusses
B51: b. install girder trusses at main roof and cupola
... B60: 2)
F63: SUBTOTAL | I63: =SUM(I23:I62) -> 0 | K63: =SUM(K23:K62) -> 0 | M63: =SUM(M22:M62) -> 0 | O63: =SUM(O22:O62) -> 0 | Q63: =SUM(Q23:Q62) -> 0 | S63: =SUM(S23:S62) -> 0
F64: BOND RATE | H64: 0 | J64: 0 | L64: 0 | N64: 0 | P64: 0 | R64: 0
F65: BOND AMOUNT | I65: =H64*$I$63 -> 0 | K65: =J64*$K$63 -> 0 | M65: =L64*$M$63 -> 0 | O65: =N64*$O$63 -> 0 | Q65: =P64*$Q$63 -> 0 | S65: =R64*S63 -> 0
F67: ADJUSTED TOTAL | I67: =SUM(I63:I66) -> 0 | K67: =SUM(K63:K65) -> 0 | M67: =SUM(M63:M65) -> 0 | O67: =SUM(O63:O65) -> 0 | Q67: =SUM(Q63:Q65) -> 0 | S67: =SUM(S63:S65) -> 0
F68: Cost per SF | I68: =I67/'Area Calculations'!$I$4 -> #DIV/0! | K68: =K67/'Area Calculations'!$I$4 -> #DIV/0! | M68: =M67/'Area Calculations'!$I$4 -> #DIV/0! | O68: =O67/'Area Calculations'!$I$4 -> #DIV/0! | Q68: =Q67/'Area Calculations'!$I$4 -> #DIV/0! | S68: =S67/'Area Calculations'!$I$4 -> #DIV/0!
F69: Cost per Unit | I69: =I67/'Area Calculations'!#REF! -> #REF! | K69: =K67/'Area Calculations'!#REF! -> #REF! | M69: =M67/'Area Calculations'!#REF! -> #REF! | O69: =O67/'Area Calculations'!#REF! -> #REF! | Q69: =Q67/'Area Calculations'!#REF! -> #REF! | S69: =S67/'Area Calculations'!#REF! -> #REF!
A71: QUALIFICATIONS
A75: EXCLUSIONS/OWNER PROVIDED ITEMS:
A79: ALTERNATES:
A83: PROPOSED VE (Provide Clear Description):
A87: FULLY LOADED LABOR RATES
B88: Laborer
B89: Mechanic
B90: Superintendent
B91: Project Manager
A93: SCHEDULE
B94: Prepared shop drawings/submittals
B95: Mobilization
B96: Total duration to complete scope of work
A98: Winner
A99: Company
A100: Contact
A101: Phone
A102: Email
A103: Base Bid
B105: Need Prequalification
B106: Prequalified

Sheet 06C Wood Trusses
G1: Hedrick Plug
F2: X | G2: Excluded
B3: BACK TO SUMMARY SHEET | F3: I | G3: Included | H3: Bidder 1 | J3: Bidder 2 | L3: Bidder 3 | N3: Bidder 4 | P3: Bidder 5 | R3: Bidder 6
A4: Project: | B4: ='Area Calculations'!B4 -> Project Name | G4: Company
A5: Trade: | B5: Wood Trusses | G5: Contact
A6: CSI Code: | B6: 06C | G6: Phone
A7: Date: | G7: Email
A8: Adjusted Bid | G8: Adjusted Bid | H8: =I70 -> 0 | J8: =K70 -> 0 | L8: =M70 -> 0 | N8: =O70 -> 0 | P8: =Q70 -> 0 | R8: =S70 -> 0
A9: BID DOCUMENTS: | C9: Plan/ Spec. Package | D9: QTY | E9: U/M | F9: Unit Cost | G9: Subtotal | H9: Yes/No | I9: Price | J9: Yes/No | K9: Price | L9: Yes/No | M9: Price | N9: Yes/No | O9: Price | P9: Yes/No | Q9: Price | R9: Yes/No | S9: Price
B10: Plans By Division
B11: ='Area Calculations'!L62 -> Architectural Drawings by | C11: P
B12: ='Area Calculations'!L63 -> Structural Drawings by | C12: P
B13: ='Area Calculations'!L64 -> MEP FA FP Drawings by | C13: P
B14: ='Area Calculations'!L65 -> Civil Drawings by | C14: P
B15: ='Area Calculations'!L66 -> Land scape Drawings by | C15: P
B16: ='Area Calculations'!L67 -> Kitchen Drawings by | C16: P
B17: ='Area Calculations'!L68 -> Storefront Designer by | C17: P
B18: ='Area Calculations'!L69 -> Geotech report by | C18: P
B19: ='Area Calculations'!L70 -> Specifications | C19: P
B21: Wood Trusses
B22: GENERAL INCLUSIONS
B23: INCLUDES ALL SALES TAX
B24: ALL HOISTING & RIGGING REQUIRED TO COMPLETE THIS SCOPE
B25: PROVIDE P&P BONDS
B26: FLORIDA STATE CONTRACTORS LIC.
B27: GENERAL LIABILITY AND WORKERS COMP. INSURANCE LIMITS
B28: STATE AND LOCAL TAXES
B29: COMPASS
B30: SPECIFIC TRADE SCOPE OF WORK REQUIREMENTS
B31: BASE BID
B32: Building SF
... B41: 1)
H58: x
F66: SUBTOTAL | I66: =SUM(I23:I65) -> 0 | K66: =SUM(K23:K65) -> 0 | M66: =SUM(M22:M65) -> 0 | O66: =SUM(O22:O65) -> 0 | Q66: =SUM(Q23:Q65) -> 0 | S66: =SUM(S23:S65) -> 0
F67: BOND RATE | H67: 0 | J67: 0 | L67: 0 | N67: 0 | P67: 0 | R67: 0
F68: BOND AMOUNT | I68: =H67*$I$66 -> 0 | K68: =J67*$K$66 -> 0 | M68: =L67*$M$66 -> 0 | O68: =N67*$O$66 -> 0 | Q68: =P67*$Q$66 -> 0 | S68: =R67*S66 -> 0
F70: ADJUSTED TOTAL | I70: =SUM(I66:I68) -> 0 | K70: =SUM(K66:K68) -> 0 | M70: =SUM(M66:M68) -> 0 | O70: =SUM(O66:O68) -> 0 | Q70: =SUM(Q66:Q68) -> 0 | S70: =SUM(S66:S68) -> 0
F71: Cost per SF | I71: =I70/'Area Calculations'!$I$4 -> #DIV/0! | K71: =K70/'Area Calculations'!$I$4 -> #DIV/0! | M71: =M70/'Area Calculations'!$I$4 -> #DIV/0! | O71: =O70/'Area Calculations'!$I$4 -> #DIV/0! | Q71: =Q70/'Area Calculations'!$I$4 -> #DIV/0! | S71: =S70/'Area Calculations'!$I$4 -> #DIV/0!
F72: Cost per Unit | I72: =I70/'Area Calculations'!#REF! -> #REF! | K72: =K70/'Area Calculations'!#REF! -> #REF! | M72: =M70/'Area Calculations'!#REF! -> #REF! | O72: =O70/'Area Calculations'!#REF! -> #REF! | Q72: =Q70/'Area Calculations'!#REF! -> #REF! | S72: =S70/'Area Calculations'!#REF! -> #REF!
A74: QUALIFICATIONS
A78: EXCLUSIONS/OWNER PROVIDED ITEMS:
A82: ALTERNATES:
A86: PROPOSED VE (Provide Clear Description):
A90: FULLY LOADED LABOR RATES
B91: Laborer
B92: Mechanic
B93: Superintendent
B94: Project Manager
A96: SCHEDULE
B97: Prepared shop drawings/submittals
B98: Mobilization
B99: Total duration to complete scope of work
A101: Winner
A102: Company
A103: Contact
A104: Phone
A105: Email
A106: Base Bid
B108: Need Prequalification
B109: Prequalified

Sheet 06D Interior Finish Carpentry
G1: Hedrick Plug
F2: X | G2: Excluded
B3: BACK TO SUMMARY SHEET | F3: I | G3: Included | H3: Bidder 1 | J3: Bidder 2 | L3: Bidder 3 | N3: Bidder 4 | P3: Bidder 5 | R3: Bidder 6
A4: Project: | B4: ='Area Calculations'!B4 -> Project Name | G4: Company
A5: Trade: | B5: Interior Finish Carpentry | G5: Contact
A6: CSI Code: | B6: 06D | G6: Phone
A7: Date: | G7: Email
A8: Adjusted Bid | G8: Adjusted Bid | H8: =I64 -> 0 | J8: =K64 -> 0 | L8: =M64 -> 0 | N8: =O64 -> 0 | P8: =Q64 -> 0 | R8: =S64 -> 0
A9: BID DOCUMENTS: | C9: Plan/ Spec. Package | D9: QTY | E9: U/M | F9: Unit Cost | G9: Subtotal | H9: Yes/No | I9: Price | J9: Yes/No | K9: Price | L9: Yes/No | M9: Price | N9: Yes/No | O9: Price | P9: Yes/No | Q9: Price | R9: Yes/No | S9: Price
B10: Plans By Division
B11: ='Area Calculations'!L62 -> Architectural Drawings by | C11: P
B12: ='Area Calculations'!L63 -> Structural Drawings by | C12: P
B13: ='Area Calculations'!L64 -> MEP FA FP Drawings by | C13: P
B14: ='Area Calculations'!L65 -> Civil Drawings by | C14: P
B15: ='Area Calculations'!L66 -> Land scape Drawings by | C15: P
B16: ='Area Calculations'!L67 -> Kitchen Drawings by | C16: P
B17: ='Area Calculations'!L68 -> Storefront Designer by | C17: P
B18: ='Area Calculations'!L69 -> Geotech report by | C18: P
B19: ='Area Calculations'!L70 -> Specifications | C19: P
B21: Interior Finish Carpentry
B22: GENERAL INCLUSIONS
B23: INCLUDES ALL SALES TAX
B24: ALL HOISTING & RIGGING REQUIRED TO COMPLETE THIS SCOPE
B25: PROVIDE P&P BONDS
B26: FLORIDA STATE CONTRACTORS LIC.
B27: GENERAL LIABILITY AND WORKERS COMP. INSURANCE LIMITS
B28: STATE AND LOCAL TAXES
B29: COMPASS
B30: SPECIFIC TRADE SCOPE OF WORK REQUIREMENTS
B31: BASE BID
B34: Install Doors:
... B36: a. single leaf
B37: b. 2 leaf | J37: i
B39: Exterior Doors:
B40: a. single leaf
B41: b. 2 leaf
B43: Base Molding:
B44: a. base (material)
B45: b. base (install) - Paint Grade $1.75 LF and Stain Grade $2.50 LF
B47: Chair Rail:
B48: a. chair rail (material)
B49: b. chair rail (install)
B51: Crown Molding:
B52: a. crown molding (material)
B53: b. crown molding (install)
B54: c. crown molding backing
F60: SUBTOTAL | I60: =SUM(I23:I59) -> 0 | K60: =SUM(K23:K59) -> 0 | M60: =SUM(M22:M59) -> 0 | O60: =SUM(O22:O59) -> 0 | Q60: =SUM(Q23:Q59) -> 0 | S60: =SUM(S23:S59) -> 0
F61: BOND RATE | H61: 0 | J61: 0 | L61: 0 | N61: 0 | P61: 0 | R61: 0
F62: BOND AMOUNT | I62: =H61*$I$60 -> 0 | K62: =J61*$K$60 -> 0 | M62: =L61*$M$60 -> 0 | O62: =N61*$O$60 -> 0 | Q62: =P61*$Q$60 -> 0 | S62: =R61*S60 -> 0
F64: ADJUSTED TOTAL | I64: =SUM(I60:I63) -> 0 | K64: =SUM(K60:K62) -> 0 | M64: =SUM(M60:M62) -> 0 | O64: =SUM(O60:O62) -> 0 | Q64: =SUM(Q60:Q62) -> 0 | S64: =SUM(S60:S62) -> 0
F65: Cost per SF | I65: =I64/'Area Calculations'!$I$4 -> #DIV/0! | K65: =K64/'Area Calculations'!$I$4 -> #DIV/0! | M65: =M64/'Area Calculations'!$I$4 -> #DIV/0! | O65: =O64/'Area Calculations'!$I$4 -> #DIV/0! | Q65: =Q64/'Area Calculations'!$I$4 -> #DIV/0! | S65: =S64/'Area Calculations'!$I$4 -> #DIV/0!
F66: Cost per Unit | I66: =I64/'Area Calculations'!#REF! -> #REF! | K66: =K64/'Area Calculations'!#REF! -> #REF! | M66: =M64/'Area Calculations'!#REF! -> #REF! | O66: =O64/'Area Calculations'!#REF! -> #REF! | Q66: =Q64/'Area Calculations'!#REF! -> #REF! | S66: =S64/'Area Calculations'!#REF! -> #REF!
A68: QUALIFICATIONS
A72: EXCLUSIONS/OWNER PROVIDED ITEMS:
A76: ALTERNATES:
A80: PROPOSED VE (Provide Clear Description):
A84: FULLY LOADED LABOR RATES
B85: Laborer
B86: Mechanic
B87: Superintendent
B88: Project Manager
A90: SCHEDULE
B91: Prepared shop drawings/submittals
B92: Mobilization
B93: Total duration to complete scope of work
A95: Winner
A96: Company
A97: Contact
A98: Phone
A99: Email
A100: Base Bid
B102: Need Prequalification
B103: Prequalified

Sheet 06E Heavy Timber Construction
G1: Hedrick Plug
F2: X | G2: Excluded
B3: BACK TO SUMMARY SHEET | F3: I | G3: Included | H3: Bidder 1 | J3: Bidder 2 | L3: Bidder 3 | N3: Bidder4 | P3: Bidder5 | R3: Bidder6
A4: Project: | B4: ='Area Calculations'!B4 -> Project Name | G4: Company
A5: Trade: | B5: Heavy Timber Construction | G5: Contact
A6: CSI Code: | B6: 06E | G6: Phone
A7: Date: | G7: Email
A8: Adjusted Bid | G8: Adjusted Bid | H8: =I52 -> 0 | J8: =K52 -> 0 | L8: =M52 -> 0 | N8: =O52 -> 0 | P8: =Q52 -> 0 | R8: =S52 -> 0
A9: BID DOCUMENTS: | C9: Plan/ Spec. Package | D9: QTY | E9: U/M | F9: Unit Cost | G9: Subtotal | H9: Yes/No | I9: Price | J9: Yes/No | K9: Price | L9: Yes/No | M9: Price | N9: Yes/No | O9: Price | P9: Yes/No | Q9: Price | R9: Yes/No | S9: Price
B10: Plans By Division
B11: ='Area Calculations'!L62 -> Architectural Drawings by | C11: P
B12: ='Area Calculations'!L63 -> Structural Drawings by | C12: P
B13: ='Area Calculations'!L64 -> MEP FA FP Drawings by | C13: P
B14: ='Area Calculations'!L65 -> Civil Drawings by | C14: P
B15: ='Area Calculations'!L66 -> Land scape Drawings by | C15: P
B16: ='Area Calculations'!L67 -> Kitchen Drawings by | C16: P
B17: ='Area Calculations'!L68 -> Storefront Designer by | C17: P
B18: ='Area Calculations'!L69 -> Geotech report by | C18: P
B19: ='Area Calculations'!L70 -> Specifications | C19: P
B21: Heavy Timber Construction
A22: 3 | B22: This Subcontractor is responsible to supply and install a complete U.L. listed firestopping system for each penetration of their work through any fire rated assembly in order to maintain the fire rating of that work. Subcontractor to provide affidavit form their qualifier indicating all fire caulking is complete for the entire project. | C22: P
B23: GENERAL INCLUSIONS
B24: INCLUDES ALL SALES TAX
B25: ALL HOISTING & RIGGING REQUIRED TO COMPLETE THIS SCOPE
B26: PROVIDE P&P BONDS
B27: FLORIDA STATE CONTRACTORS LIC.
B28: GENERAL LIABILITY AND WORKERS COMP. INSURANCE LIMITS
B29: STATE AND LOCAL TAXES
B30: COMPASS
B31: SPECIFIC TRADE SCOPE OF WORK REQUIREMENTS
B32: BASE BID
H37: x
F48: SUBTOTAL | I48: =SUM(I24:I47) -> 0 | K48: =SUM(K24:K47) -> 0 | M48: =SUM(M24:M47) -> 0 | O48: =SUM(O24:O47) -> 0 | Q48: =SUM(Q24:Q47) -> 0 | S48: =SUM(S24:S47) -> 0
F49: BOND RATE | H49: 0 | J49: 0 | L49: 0 | N49: 0 | P49: 0 | R49: 0
F50: BOND AMOUNT | I50: =H49*I48 -> 0 | K50: =J49*K48 -> 0 | M50: =L49*M48 -> 0 | O50: =N49*O48 -> 0 | Q50: =P49*Q48 -> 0 | S50: =R49*S48 -> 0
F52: ADJUSTED TOTAL | I52: =SUM(I48:I51) -> 0 | K52: =SUM(K48:K51) -> 0 | M52: =SUM(M48:M51) -> 0 | O52: =SUM(O48:O51) -> 0 | Q52: =SUM(Q48:Q51) -> 0 | S52: =SUM(S48:S51) -> 0
F53: Cost per SF | I53: =I52/'Area Calculations'!$I$4 -> #DIV/0! | K53: =K52/'Area Calculations'!$I$4 -> #DIV/0! | M53: =M52/'Area Calculations'!$I$4 -> #DIV/0! | O53: =O52/'Area Calculations'!$I$4 -> #DIV/0! | Q53: =Q52/'Area Calculations'!$I$4 -> #DIV/0! | S53: =S52/'Area Calculations'!$I$4 -> #DIV/0!
F54: Cost per Unit | I54: =I52/'Area Calculations'!#REF! -> #REF! | K54: =K52/'Area Calculations'!#REF! -> #REF! | M54: =M52/'Area Calculations'!#REF! -> #REF! | O54: =O52/'Area Calculations'!#REF! -> #REF! | Q54: =Q52/'Area Calculations'!#REF! -> #REF! | S54: =S52/'Area Calculations'!#REF! -> #REF!
A56: QUALIFICATIONS
A60: EXCLUSIONS/OWNER PROVIDED ITEMS:
A64: ALTERNATES:
A68: PROPOSED VE (Provide Clear Description):
A72: FULLY LOADED LABOR RATES
B73: Laborer
B74: Mechanic
B75: Superintendent
B76: Project Manager
A78: SCHEDULE
B79: Prepared shop drawings/submittals
B80: Mobilization
B81: Total duration to complete scope of work
A83: Winner
A84: Company
A85: Contact
A86: Phone
A87: Email
A88: Base Bid
B90: Need Prequalification
B91: Prequalified

Sheet 06F Millwork
G1: Hedrick Plug
F2: X | G2: Excluded
B3: BACK TO SUMMARY SHEET | F3: I | G3: Included | H3: Bidder 1 | J3: Bidder 2 | L3: Bidder 3 | N3: Bidder4 | P3: Bidder5 | R3: Bidder6
A4: Project: | B4: ='Area Calculations'!B4 -> Project Name | G4: Company
A5: Trade: | B5: Millwork | G5: Contact
A6: CSI Code: | B6: 06F | G6: Phone
A7: Date: | G7: Email
A8: Adjusted Bid | G8: Adjusted Bid | H8: =I54 -> 0 | J8: =K54 -> 0 | L8: =M54 -> 0 | N8: =O54 -> 0 | P8: =Q54 -> 0 | R8: =S54 -> 0
A9: BID DOCUMENTS: | C9: Plan/ Spec. Package | D9: QTY | E9: U/M | F9: Unit Cost | G9: Subtotal | H9: Yes/No | I9: Price | J9: Yes/No | K9: Price | L9: Yes/No | M9: Price | N9: Yes/No | O9: Price | P9: Yes/No | Q9: Price | R9: Yes/No | S9: Price
B10: Plans By Division
B11: ='Area Calculations'!L62 -> Architectural Drawings by | C11: P
B12: ='Area Calculations'!L63 -> Structural Drawings by | C12: P
B13: ='Area Calculations'!L64 -> MEP FA FP Drawings by | C13: P
B14: ='Area Calculations'!L65 -> Civil Drawings by | C14: P
B15: ='Area Calculations'!L66 -> Land scape Drawings by | C15: P
B16: ='Area Calculations'!L67 -> Kitchen Drawings by | C16: P
B17: ='Area Calculations'!L68 -> Storefront Designer by | C17: P
B18: ='Area Calculations'!L69 -> Geotech report by | C18: P
B19: ='Area Calculations'!L70 -> Specifications | C19: P
B20: ='Area Calculations'!L71 -> 0 | C20: P
B21: ='Area Calculations'!L72 -> 0 | C21: P
B23: Millwork
B24: GENERAL INCLUSIONS
B25: INCLUDES ALL SALES TAX
B26: ALL HOISTING & RIGGING REQUIRED TO COMPLETE THIS SCOPE
B27: PROVIDE P&P BONDS
B28: FLORIDA STATE CONTRACTORS LIC.
B29: GENERAL LIABILITY AND WORKERS COMP. INSURANCE LIMITS
B30: STATE AND LOCAL TAXES
B31: COMPASS
B32: SPECIFIC TRADE SCOPE OF WORK REQUIREMENTS
B33: BASE BID
H40: i
F50: SUBTOTAL | I50: =SUM(I25:I49) -> 0 | K50: =SUM(K25:K49) -> 0 | M50: =SUM(M25:M49) -> 0 | O50: =SUM(O25:O49) -> 0 | Q50: =SUM(Q25:Q49) -> 0 | S50: =SUM(S26:S49) -> 0
F51: BOND RATE | H51: 0 | J51: 0 | L51: 0 | N51: 0 | P51: 0 | R51: 0
F52: BOND AMOUNT | I52: =H51*I50 -> 0 | K52: =J51*K50 -> 0 | M52: =L51*M50 -> 0 | O52: =N51*O50 -> 0 | Q52: =P51*Q50 -> 0 | S52: =R51*S50 -> 0
F54: ADJUSTED TOTAL | I54: =SUM(I50:I53) -> 0 | K54: =SUM(K50:K53) -> 0 | M54: =SUM(M50:M53) -> 0 | O54: =SUM(O50:O53) -> 0 | Q54: =SUM(Q50:Q53) -> 0 | S54: =SUM(S50:S53) -> 0
F55: Cost per SF | I55: =I54/'Area Calculations'!$I$4 -> #DIV/0! | K55: =K54/'Area Calculations'!$I$4 -> #DIV/0! | M55: =M54/'Area Calculations'!$I$4 -> #DIV/0! | O55: =O54/'Area Calculations'!$I$4 -> #DIV/0! | Q55: =Q54/'Area Calculations'!$I$4 -> #DIV/0! | S55: =S54/'Area Calculations'!$I$4 -> #DIV/0!
F56: Cost per Unit | I56: =I54/'Area Calculations'!#REF! -> #REF! | K56: =K54/'Area Calculations'!#REF! -> #REF! | M56: =M54/'Area Calculations'!#REF! -> #REF! | O56: =O54/'Area Calculations'!#REF! -> #REF! | Q56: =Q54/'Area Calculations'!#REF! -> #REF! | S56: =S54/'Area Calculations'!#REF! -> #REF!
A58: QUALIFICATIONS
A62: EXCLUSIONS/OWNER PROVIDED ITEMS:
A66: ALTERNATES:
A70: PROPOSED VE (Provide Clear Description):
A74: FULLY LOADED LABOR RATES
B75: Laborer
B76: Mechanic
B77: Superintendent
B78: Project Manager
A80: SCHEDULE
B81: Prepared shop drawings/submittals
B82: Mobilization
B83: Total duration to complete scope of work
A85: Winner
A86: Company
A87: Contact
A88: Phone
A89: Email
A90: Base Bid
B92: Need Prequalification
B93: Prequalified

Sheet 06G Exterior Finish Carpent
G1: Hedrick Plug
F2: X | G2: Excluded
B3: BACK TO SUMMARY SHEET | F3: I | G3: Included | H3: Bidder 1 | J3: Bidder 2 | L3: Bidder 3 | N3: Bidder 4 | P3: Bidder 5 | R3: Bidder 6
A4: Project: | B4: ='Area Calculations'!B4 -> Project Name | G4: Company
A5: Trade: | B5: Exterior Finish Carpentry | G5: Contact
A6: CSI Code: | B6: 06G | G6: Phone
A7: Date: | G7: Email
A8: Adjusted Bid | G8: Adjusted Bid | H8: =I64 -> 0 | J8: =K64 -> 0 | L8: =M64 -> 0 | N8: =O64 -> 0 | P8: =Q64 -> 0 | R8: =S64 -> 0
A9: BID DOCUMENTS: | C9: Plan/ Spec. Package | D9: QTY | E9: U/M | F9: Unit Cost | G9: Subtotal | H9: Yes/No | I9: Price | J9: Yes/No | K9: Price | L9: Yes/No | M9: Price | N9: Yes/No | O9: Price | P9: Yes/No | Q9: Price | R9: Yes/No | S9: Price
B10: Plans By Division
B11: ='Area Calculations'!L62 -> Architectural Drawings by | C11: P
B12: ='Area Calculations'!L63 -> Structural Drawings by | C12: P
B13: ='Area Calculations'!L64 -> MEP FA FP Drawings by | C13: P
B14: ='Area Calculations'!L65 -> Civil Drawings by | C14: P
B15: ='Area Calculations'!L66 -> Land scape Drawings by | C15: P
B16: ='Area Calculations'!L67 -> Kitchen Drawings by | C16: P
B17: ='Area Calculations'!L68 -> Storefront Designer by | C17: P
B18: ='Area Calculations'!L69 -> Geotech report by | C18: P
B19: ='Area Calculations'!L70 -> Specifications | C19: P
B21: Exterior Finish Carpentry
B22: GENERAL INCLUSIONS
B23: INCLUDES ALL SALES TAX
B24: ALL HOISTING & RIGGING REQUIRED TO COMPLETE THIS SCOPE
B25: PROVIDE P&P BONDS
B26: FLORIDA STATE CONTRACTORS LIC.
B27: GENERAL LIABILITY AND WORKERS COMP. INSURANCE LIMITS
B28: STATE AND LOCAL TAXES
B29: COMPASS
B30: SPECIFIC TRADE SCOPE OF WORK REQUIREMENTS
B31: BASE BID
B34: Install Doors:
... B36: a. single leaf
B37: b. 2 leaf | J37: i
B39: Exterior Doors:
B40: a. single leaf
B41: b. 2 leaf
B43: Base Molding:
B44: a. base (material)
B45: b. base (install) - Paint Grade $1.75 LF and Stain Grade $2.50 LF
B47: Chair Rail:
B48: a. chair rail (material)
B49: b. chair rail (install)
B51: Crown Molding:
B52: a. crown molding (material)
B53: b. crown molding (install)
B54: c. crown molding backing
F60: SUBTOTAL | I60: =SUM(I23:I59) -> 0 | K60: =SUM(K23:K59) -> 0 | M60: =SUM(M22:M59) -> 0 | O60: =SUM(O22:O59) -> 0 | Q60: =SUM(Q23:Q59) -> 0 | S60: =SUM(S23:S59) -> 0
F61: BOND RATE | H61: 0 | J61: 0 | L61: 0 | N61: 0 | P61: 0 | R61: 0
F62: BOND AMOUNT | I62: =H61*$I$60 -> 0 | K62: =J61*$K$60 -> 0 | M62: =L61*$M$60 -> 0 | O62: =N61*$O$60 -> 0 | Q62: =P61*$Q$60 -> 0 | S62: =R61*S60 -> 0
F64: ADJUSTED TOTAL | I64: =SUM(I60:I63) -> 0 | K64: =SUM(K60:K62) -> 0 | M64: =SUM(M60:M62) -> 0 | O64: =SUM(O60:O62) -> 0 | Q64: =SUM(Q60:Q62) -> 0 | S64: =SUM(S60:S62) -> 0
F65: Cost per SF | I65: =I64/'Area Calculations'!$I$4 -> #DIV/0! | K65: =K64/'Area Calculations'!$I$4 -> #DIV/0! | M65: =M64/'Area Calculations'!$I$4 -> #DIV/0! | O65: =O64/'Area Calculations'!$I$4 -> #DIV/0! | Q65: =Q64/'Area Calculations'!$I$4 -> #DIV/0! | S65: =S64/'Area Calculations'!$I$4 -> #DIV/0!
F66: Cost per Unit | I66: =I64/'Area Calculations'!#REF! -> #REF! | K66: =K64/'Area Calculations'!#REF! -> #REF! | M66: =M64/'Area Calculations'!#REF! -> #REF! | O66: =O64/'Area Calculations'!#REF! -> #REF! | Q66: =Q64/'Area Calculations'!#REF! -> #REF! | S66: =S64/'Area Calculations'!#REF! -> #REF!
A68: QUALIFICATIONS
A72: EXCLUSIONS/OWNER PROVIDED ITEMS:
A76: ALTERNATES:
A80: PROPOSED VE (Provide Clear Description):
A84: FULLY LOADED LABOR RATES
B85: Laborer
B86: Mechanic
B87: Superintendent
B88: Project Manager
A90: SCHEDULE
B91: Prepared shop drawings/submittals
B92: Mobilization
B93: Total duration to complete scope of work
A95: Winner
A96: Company
A97: Contact
A98: Phone
A99: Email
A100: Base Bid
B102: Need Prequalification
B103: Prequalified

Sheet 07B Sprayed Insulation
G1: Hedrick Plug
F2: X | G2: Excluded
B3: BACK TO SUMMARY SHEET | F3: I | G3: Included | H3: Bidder 1 | J3: Bidder 2 | L3: Bidder 3 | N3: Bidder 4 | P3: Bidder5 | R3: Bidder6
A4: Project: | B4: ='Area Calculations'!B4 -> Project Name | G4: Company
A5: Trade: | B5: Sprayed Insulation | G5: Contact
A6: CSI Code: | B6: 07B | G6: Phone
A7: Date: | G7: Email
A8: Adjusted Bid | G8: Adjusted Bid | H8: =I58 -> 0 | J8: =K58 -> 0 | L8: =M58 -> 0 | N8: =O58 -> 0 | P8: =Q58 -> 0 | R8: =S58 -> 0
A9: BID DOCUMENTS: | C9: Plan/ Spec. Package | D9: QTY | E9: U/M | F9: Unit Cost | G9: Subtotal | H9: Yes/No | I9: Price | J9: Yes/No | K9: Price | L9: Yes/No | M9: Price | N9: Yes/No | O9: Price | P9: Yes/No | Q9: Price | R9: Yes/No | S9: Price
B10: Plans By Division
B11: ='Area Calculations'!L62 -> Architectural Drawings by | C11: P
B12: ='Area Calculations'!L63 -> Structural Drawings by | C12: P
B13: ='Area Calculations'!L64 -> MEP FA FP Drawings by | C13: P
B14: ='Area Calculations'!L65 -> Civil Drawings by | C14: P
B15: ='Area Calculations'!L66 -> Land scape Drawings by | C15: P
B16: ='Area Calculations'!L67 -> Kitchen Drawings by | C16: P
B17: ='Area Calculations'!L68 -> Storefront Designer by | C17: P
B18: ='Area Calculations'!L69 -> Geotech report by | C18: P
B19: ='Area Calculations'!L70 -> Specifications | C19: P
B20: ='Area Calculations'!L71 -> 0 | C20: P
B21: ='Area Calculations'!L72 -> 0 | C21: P
B22: ='Area Calculations'!L73 -> 0 | C22: P
B23: ='Area Calculations'!L74 -> 0 | C23: P
B25: Sprayed Insulation
B26: GENERAL INCLUSIONS
B27: INCLUDES ALL SALES TAX
B28: ALL HOISTING & RIGGING REQUIRED TO COMPLETE THIS SCOPE
B29: PROVIDE P&P BONDS
B30: FLORIDA STATE CONTRACTORS LIC.
B31: GENERAL LIABILITY AND WORKERS COMP. INSURANCE LIMITS
B32: STATE AND LOCAL TAXES
B33: SPECIFIC TRADE SCOPE OF WORK REQUIREMENTS
B34: BASE BID
B35: Building SF
H43: i
F54: SUBTOTAL | I54: =SUM(I26:I53) -> 0 | K54: =SUM(K26:K53) -> 0 | M54: =SUM(M26:M53) -> 0 | O54: =SUM(O26:O53) -> 0 | Q54: =SUM(Q26:Q53) -> 0 | S54: =SUM(S26:S53) -> 0
F55: BOND RATE | H55: 0 | J55: 0 | L55: 0 | N55: 0 | P55: 0 | R55: 0
F56: BOND AMOUNT | I56: =I54*H55 -> 0 | K56: =K54*J55 -> 0 | M56: =M54*L55 -> 0 | O56: =O54*N55 -> 0 | Q56: =Q54*P55 -> 0 | S56: =S54*R55 -> 0
F58: ADJUSTED TOTAL | I58: =SUM(I54:I56) -> 0 | K58: =SUM(K54:K56) -> 0 | M58: =SUM(M54:M56) -> 0 | O58: =SUM(O54:O56) -> 0 | Q58: =SUM(Q54:Q56) -> 0 | S58: =SUM(S54:S56) -> 0
F59: Cost per SF | I59: =I58/'Area Calculations'!$I$4 -> #DIV/0! | K59: =K58/'Area Calculations'!$I$4 -> #DIV/0! | M59: =M58/'Area Calculations'!$I$4 -> #DIV/0! | O59: =O58/'Area Calculations'!$I$4 -> #DIV/0! | Q59: =Q58/'Area Calculations'!$I$4 -> #DIV/0! | S59: =S58/'Area Calculations'!$I$4 -> #DIV/0!
F60: Cost per Unit | I60: =I58/'Area Calculations'!#REF! -> #REF! | K60: =K58/'Area Calculations'!#REF! -> #REF! | M60: =M58/'Area Calculations'!#REF! -> #REF! | O60: =O58/'Area Calculations'!#REF! -> #REF! | Q60: =Q58/'Area Calculations'!#REF! -> #REF! | S60: =S58/'Area Calculations'!#REF! -> #REF!
A62: QUALIFICATIONS
A66: EXCLUSIONS/OWNER PROVIDED ITEMS:
A70: ALTERNATES:
A74: PROPOSED VE (Provide Clear Description):
A78: FULLY LOADED LABOR RATES
B79: Laborer
B80: Mechanic
B81: Superintendent
B82: Project Manager
A84: SCHEDULE
B85: Prepared shop drawings/submittals
B86: Mobilization
B87: Total duration to complete scope of work
A89: Winner
A90: Company
A91: Contact
A92: Phone
A93: Email
A94: Base Bid
B96: Need Prequalification
B97: Prequalified

Sheet 07C Fireproofing&Firestopping
G1: Hedrick Plug
F2: X | G2: Excluded
B3: BACK TO SUMMARY SHEET | F3: I | G3: Included | H3: Bidder 1 | J3: Bidder 2 | L3: Bidder 3 | N3: Bidder 4 | P3: Bidder5 | R3: Bidder6
A4: Project: | B4: ='Area Calculations'!B4 -> Project Name | G4: Company
A5: Trade: | B5: Fireproofing & Firestopping | G5: Contact
A6: CSI Code: | B6: 07C | G6: Phone
A7: Date: | G7: Email
A8: Adjusted Bid | G8: Adjusted Bid | H8: =I49 -> 0 | J8: =K49 -> 0 | L8: =M49 -> 0 | N8: =O49 -> 0 | P8: =Q49 -> 0 | R8: =S49 -> 0
A9: BID DOCUMENTS: | C9: Plan/ Spec. Package | D9: QTY | E9: U/M | F9: Unit Cost | G9: Subtotal | H9: Yes/No | I9: Price | J9: Yes/No | K9: Price | L9: Yes/No | M9: Price | N9: Yes/No | O9: Price | P9: Yes/No | Q9: Price | R9: Yes/No | S9: Price
B10: Plans By Division
B11: ='Area Calculations'!L62 -> Architectural Drawings by | C11: P
B12: ='Area Calculations'!L63 -> Structural Drawings by | C12: P
B13: ='Area Calculations'!L64 -> MEP FA FP Drawings by | C13: P
B14: ='Area Calculations'!L65 -> Civil Drawings by | C14: P
B15: ='Area Calculations'!L66 -> Land scape Drawings by | C15: P
B16: ='Area Calculations'!L67 -> Kitchen Drawings by | C16: P
B17: ='Area Calculations'!L68 -> Storefront Designer by | C17: P
B18: ='Area Calculations'!L69 -> Geotech report by | C18: P
B20: Fireproofing & Firestopping
B21: GENERAL INCLUSIONS
B22: INCLUDES ALL SALES TAX
B23: ALL HOISTING & RIGGING REQUIRED TO COMPLETE THIS SCOPE
B24: PROVIDE P&P BONDS
B25: FLORIDA STATE CONTRACTORS LIC.
B26: GENERAL LIABILITY AND WORKERS COMP. INSURANCE LIMITS
B27: STATE AND LOCAL TAXES
B28: COMPASS
B29: SPECIFIC TRADE SCOPE OF WORK REQUIREMENTS
B30: BASE BID
B31: Building SF
H35: i
B38: Penetartions for MEP FP
B39: Fire-rated head of walls and partitions
B44: Permits
F45: SUBTOTAL | I45: =SUM(I21:I44) -> 0 | K45: =SUM(K21:K44) -> 0 | M45: =SUM(M21:M44) -> 0 | O45: =SUM(O21:O44) -> 0 | Q45: =SUM(Q21:Q44) -> 0 | S45: =SUM(S21:S44) -> 0
F46: BOND RATE | H46: 0 | J46: 0 | L46: 0 | N46: 0 | P46: 0 | R46: 0
F47: BOND AMOUNT | I47: =I45*H46 -> 0 | K47: =K45*J46 -> 0 | M47: =M45*L46 -> 0 | O47: =O45*N46 -> 0 | Q47: =Q45*P46 -> 0 | S47: =S45*R46 -> 0
F48: Davis Bacon | H48: 0 | I48: =I45*H48 -> 0
F49: ADJUSTED TOTAL | I49: =SUM(I45:I48) -> 0 | K49: =SUM(K45:K47) -> 0 | M49: =SUM(M45:M47) -> 0 | O49: =SUM(O45:O47) -> 0 | Q49: =SUM(Q45:Q47) -> 0 | S49: =SUM(S45:S47) -> 0
F50: Cost per SF | I50: =I49/'Area Calculations'!$I$4 -> #DIV/0! | K50: =K49/'Area Calculations'!$I$4 -> #DIV/0! | M50: =M49/'Area Calculations'!$I$4 -> #DIV/0! | O50: =O49/'Area Calculations'!$I$4 -> #DIV/0! | Q50: =Q49/'Area Calculations'!$I$4 -> #DIV/0! | S50: =S49/'Area Calculations'!$I$4 -> #DIV/0!
F51: Cost per Unit | I51: =I49/'Area Calculations'!#REF! -> #REF! | K51: =K49/'Area Calculations'!#REF! -> #REF! | M51: =M49/'Area Calculations'!#REF! -> #REF! | O51: =O49/'Area Calculations'!#REF! -> #REF! | Q51: =Q49/'Area Calculations'!#REF! -> #REF! | S51: =S49/'Area Calculations'!#REF! -> #REF!
A53: QUALIFICATIONS
A57: EXCLUSIONS/OWNER PROVIDED ITEMS:
A61: ALTERNATES:
A65: PROPOSED VE (Provide Clear Description):
A69: FULLY LOADED LABOR RATES
B70: Laborer
B71: Mechanic
B72: Superintendent
B73: Project Manager
A75: SCHEDULE
B76: Prepared shop drawings/submittals
B77: Mobilization
B78: Total duration to complete scope of work
A80: Winner
A81: Company
A82: Contact
A83: Phone
A84: Email
A85: Base Bid
B87: Need Prequalification
B88: Prequalified

Sheet 07D Roofing
G1: Hedrick Plug
F2: X | G2: Excluded
B3: BACK TO SUMMARY SHEET | F3: I | G3: Included | H3: Bidder 1 | J3: Bidder 2 | L3: Bidder 3 | N3: Bidder 4 | P3: Bidder5 | R3: Bidder6
A4: Project: | B4: ='Area Calculations'!B4 -> Project Name | G4: Company
A5: Trade: | B5: Roofing | G5: Contact
A6: CSI Code: | B6: 07D | G6: Phone
A7: Date: | G7: Email
A8: Adjusted Bid | G8: Adjusted Bid | H8: =I53 -> 0 | J8: =K53 -> 0 | L8: =M53 -> 0 | N8: =O53 -> 0 | P8: =Q53 -> 0 | R8: =S53 -> 0
A9: BID DOCUMENTS: | C9: Plan/ Spec. Package | D9: QTY | E9: U/M | F9: Unit Cost | G9: Subtotal | H9: Yes/No | I9: Price | J9: Yes/No | K9: Price | L9: Yes/No | M9: Price | N9: Yes/No | O9: Price | P9: Yes/No | Q9: Price | R9: Yes/No | S9: Price
B10: Plans By Division
B11: ='Area Calculations'!L62 -> Architectural Drawings by | C11: P
B12: ='Area Calculations'!L63 -> Structural Drawings by | C12: P
B13: ='Area Calculations'!L64 -> MEP FA FP Drawings by | C13: P
B14: ='Area Calculations'!L65 -> Civil Drawings by | C14: P
B15: ='Area Calculations'!L66 -> Land scape Drawings by | C15: P
B16: ='Area Calculations'!L67 -> Kitchen Drawings by | C16: P
B17: ='Area Calculations'!L68 -> Storefront Designer by | C17: P
B18: ='Area Calculations'!L69 -> Geotech report by | C18: P
B19: ='Area Calculations'!L70 -> Specifications | C19: P
B21: Roofing
B22: GENERAL INCLUSIONS
B23: INCLUDES ALL SALES TAX
B24: ALL HOISTING & RIGGING REQUIRED TO COMPLETE THIS SCOPE
B25: PROVIDE P&P BONDS
B26: FLORIDA STATE CONTRACTORS LIC.
B27: GENERAL LIABILITY AND WORKERS COMP. INSURANCE LIMITS
B28: STATE AND LOCAL TAXES
B29: COMPASS
B30: SPECIFIC TRADE SCOPE OF WORK REQUIREMENTS
B31: BASE BID
B32: Building SF
D34: 270 | E34: SQ
E35: SQ
H39: x
B47: Davis-Bacon
B48: Permit
F49: SUBTOTAL | I49: =SUM(I21:I48) -> 0 | K49: =SUM(K21:K48) -> 0 | M49: =SUM(M21:M48) -> 0 | O49: =SUM(O21:O48) -> 0 | Q49: =SUM(Q21:Q48) -> 0 | S49: =SUM(S21:S48) -> 0
F50: BOND RATE | H50: 0 | J50: 0 | L50: 0 | N50: 0 | P50: 0 | R50: 0
F51: BOND AMOUNT | I51: =I49*H50 -> 0 | K51: =K49*J50 -> 0 | M51: =M49*L50 -> 0 | O51: =O49*N50 -> 0 | Q51: =Q49*P50 -> 0 | S51: =S49*R50 -> 0
F53: ADJUSTED TOTAL | I53: =SUM(I49:I52) -> 0 | K53: =SUM(K49:K52) -> 0 | M53: =SUM(M49:M51) -> 0 | O53: =SUM(O49:O51) -> 0 | Q53: =SUM(Q49:Q51) -> 0 | S53: =SUM(S49:S51) -> 0
F54: Cost per SF | I54: =I53/'Area Calculations'!$I$4 -> #DIV/0! | K54: =K53/'Area Calculations'!$I$4 -> #DIV/0! | M54: =M53/'Area Calculations'!$I$4 -> #DIV/0! | O54: =O53/'Area Calculations'!$I$4 -> #DIV/0! | Q54: =Q53/'Area Calculations'!$I$4 -> #DIV/0! | S54: =S53/'Area Calculations'!$I$4 -> #DIV/0!
F55: Cost per Unit | I55: =I53/'Area Calculations'!#REF! -> #REF! | K55: =K53/'Area Calculations'!#REF! -> #REF! | M55: =M53/'Area Calculations'!#REF! -> #REF! | O55: =O53/'Area Calculations'!#REF! -> #REF! | Q55: =Q53/'Area Calculations'!#REF! -> #REF! | S55: =S53/'Area Calculations'!#REF! -> #REF!
A57: QUALIFICATIONS
A61: EXCLUSIONS/OWNER PROVIDED ITEMS:
A65: ALTERNATES:
A69: PROPOSED VE (Provide Clear Description):
A73: FULLY LOADED LABOR RATES
B74: Laborer
B75: Mechanic
B76: Superintendent
B77: Project Manager
A79: SCHEDULE
B80: Prepared shop drawings/submittals
B81: Mobilization
B82: Total duration to complete scope of work
A84: Winner
A85: Company
A86: Contact
A87: Phone
A88: Email
A89: Base Bid
B91: Need Prequalification
B92: Prequalified

Sheet 07E Caulking & Waterproofing
G1: Hedrick Plug
F2: X | G2: Excluded
B3: BACK TO SUMMARY SHEET | F3: I | G3: Included | H3: Bidder 1 | J3: Bidder 2 | L3: Bidder 3 | N3: Bidder 4 | P3: Bidder5 | R3: Bidder6
A4: Project: | B4: ='Area Calculations'!B4 -> Project Name | G4: Company
A5: Trade: | B5: Caulking & Waterproofing | G5: Contact
A6: CSI Code: | B6: 07E | G6: Phone
A7: Date: | G7: Email
A8: Adjusted Bid | G8: Adjusted Bid | H8: =I64 -> 0 | J8: =K64 -> 0 | L8: =M64 -> 0 | N8: =O64 -> 0 | P8: =Q64 -> 0 | R8: =S64 -> 0
A9: BID DOCUMENTS: | C9: Plan/ Spec. Package | D9: QTY | E9: U/M | F9: Unit Cost | G9: Subtotal | H9: Yes/No | I9: Price | J9: Yes/No | K9: Price | L9: Yes/No | M9: Price | N9: Yes/No | O9: Price | P9: Yes/No | Q9: Price | R9: Yes/No | S9: Price
B10: Plans By Division
B11: ='Area Calculations'!L62 -> Architectural Drawings by | C11: P
B12: ='Area Calculations'!L63 -> Structural Drawings by | C12: P
B13: ='Area Calculations'!L64 -> MEP FA FP Drawings by | C13: P
B14: ='Area Calculations'!L65 -> Civil Drawings by | C14: P
B15: ='Area Calculations'!L66 -> Land scape Drawings by | C15: P
B16: ='Area Calculations'!L67 -> Kitchen Drawings by | C16: P
B17: ='Area Calculations'!L68 -> Storefront Designer by | C17: P
B18: ='Area Calculations'!L69 -> Geotech report by | C18: P
B19: ='Area Calculations'!L70 -> Specifications | C19: P
B20: ='Area Calculations'!L71 -> 0 | C20: P
B21: ='Area Calculations'!L72 -> 0 | C21: P
B22: ='Area Calculations'!L73 -> 0 | C22: P
B23: ='Area Calculations'!L74 -> 0 | C23: P
B25: Caulking & Waterproofing
B26: GENERAL INCLUSIONS
B27: INCLUDES ALL SALES TAX
B28: ALL HOISTING & RIGGING REQUIRED TO COMPLETE THIS SCOPE
B29: PROVIDE P&P BONDS
B30: FLORIDA STATE CONTRACTORS LIC.
B31: GENERAL LIABILITY AND WORKERS COMP. INSURANCE LIMITS
B32: STATE AND LOCAL TAXES
B33: COMPASS
B34: SPECIFIC TRADE SCOPE OF WORK REQUIREMENTS
B35: BASE BID
B37: Waterproofing, incl.:
... B46: Window and Door Openings:
B47: Specified or Provided Waterproofing System: | H47: i
B48: a. door openings
B49: b. window openings
B50: c. exterior louvers, etc.
B53: Elevator Pit:
B54: Specified or Provided Waterproofing System:
B55: a. number of elevator pits
F60: SUBTOTAL | I60: =SUM(I27:I59) -> 0 | K60: =SUM(K27:K59) -> 0 | M60: =SUM(M27:M59) -> 0 | O60: =SUM(O27:O59) -> 0 | Q60: =SUM(Q27:Q59) -> 0 | S60: =SUM(S27:S59) -> 0
F61: BOND RATE | H61: 0 | J61: 0 | L61: 0 | N61: 0 | P61: 0 | R61: 0
F62: BOND AMOUNT | I62: =I60*H61 -> 0 | K62: =K60*J61 -> 0 | M62: =M60*L61 -> 0 | O62: =O60*N61 -> 0 | Q62: =Q60*P61 -> 0 | S62: =S60*R61 -> 0
F64: ADJUSTED TOTAL | I64: =SUM(I60:I63) -> 0 | K64: =SUM(K60:K62) -> 0 | M64: =SUM(M60:M62) -> 0 | O64: =SUM(O60:O62) -> 0 | Q64: =SUM(Q60:Q62) -> 0 | S64: =SUM(S60:S62) -> 0
F65: Cost per SF | I65: =I64/'Area Calculations'!$I$4 -> #DIV/0! | K65: =K64/'Area Calculations'!$I$4 -> #DIV/0! | M65: =M64/'Area Calculations'!$I$4 -> #DIV/0! | O65: =O64/'Area Calculations'!$I$4 -> #DIV/0! | Q65: =Q64/'Area Calculations'!$I$4 -> #DIV/0! | S65: =S64/'Area Calculations'!$I$4 -> #DIV/0!
F66: Cost per Unit | I66: =I64/'Area Calculations'!#REF! -> #REF! | K66: =K64/'Area Calculations'!#REF! -> #REF! | M66: =M64/'Area Calculations'!#REF! -> #REF! | O66: =O64/'Area Calculations'!#REF! -> #REF! | Q66: =Q64/'Area Calculations'!#REF! -> #REF! | S66: =S64/'Area Calculations'!#REF! -> #REF!
A68: QUALIFICATIONS
A72: EXCLUSIONS/OWNER PROVIDED ITEMS:
A76: ALTERNATES:
A80: PROPOSED VE (Provide Clear Description):
A84: FULLY LOADED LABOR RATES
B85: Laborer
B86: Mechanic
B87: Superintendent
B88: Project Manager
A90: SCHEDULE
B91: Prepared shop drawings/submittals
B92: Mobilization
B93: Total duration to complete scope of work
A95: Winner
A96: Company
A97: Contact
A98: Phone
A99: Email
A100: Base Bid
B102: Need Prequalification
B103: Prequalified

Sheet 07F Siding
G1: Hedrick Plug
F2: X | G2: Excluded
B3: BACK TO SUMMARY SHEET | F3: I | G3: Included | H3: Bidder 1 | J3: Bidder 2 | L3: Bidder 3 | N3: Bidder 4 | P3: Bidder5 | R3: Bidder6
A4: Project: | B4: ='Area Calculations'!B4 -> Project Name | G4: Company
A5: Trade: | B5: Siding | G5: Contact
A6: CSI Code: | B6: 07F | G6: Phone
A7: Date: | G7: Email
A8: Adjusted Bid | G8: Adjusted Bid | H8: =I59 -> 0 | J8: =K59 -> 0 | L8: =M59 -> 0 | N8: =O59 -> 0 | P8: =Q59 -> 0 | R8: =S59 -> 0
A9: BID DOCUMENTS: | C9: Plan/ Spec. Package | D9: QTY | E9: U/M | F9: Unit Cost | G9: Subtotal | H9: Yes/No | I9: Price | J9: Yes/No | K9: Price | L9: Yes/No | M9: Price | N9: Yes/No | O9: Price | P9: Yes/No | Q9: Price | R9: Yes/No | S9: Price
B10: Plans By Division
B11: ='Area Calculations'!L62 -> Architectural Drawings by | C11: P
B12: ='Area Calculations'!L63 -> Structural Drawings by | C12: P
B13: ='Area Calculations'!L64 -> MEP FA FP Drawings by | C13: P
B14: ='Area Calculations'!L65 -> Civil Drawings by | C14: P
B15: ='Area Calculations'!L66 -> Land scape Drawings by | C15: P
B16: ='Area Calculations'!L67 -> Kitchen Drawings by | C16: P
B17: ='Area Calculations'!L68 -> Storefront Designer by | C17: P
B18: ='Area Calculations'!L69 -> Geotech report by | C18: P
B19: ='Area Calculations'!L70 -> Specifications | C19: P
B20: ='Area Calculations'!L71 -> 0 | C20: P
B21: ='Area Calculations'!L72 -> 0 | C21: P
B22: ='Area Calculations'!L73 -> 0 | C22: P
B23: ='Area Calculations'!L74 -> 0 | C23: P
B25: Siding
B26: GENERAL INCLUSIONS
B27: INCLUDES ALL SALES TAX
B28: ALL HOISTING & RIGGING REQUIRED TO COMPLETE THIS SCOPE
B29: PROVIDE P&P BONDS
B30: FLORIDA STATE CONTRACTORS LIC.
B31: GENERAL LIABILITY AND WORKERS COMP. INSURANCE LIMITS
B32: STATE AND LOCAL TAXES
B33: COMPASS
B34: SPECIFIC TRADE SCOPE OF WORK REQUIREMENTS
B35: BASE BID
B36: Building SF
H43: x
F55: SUBTOTAL | I55: =SUM(I27:I54) -> 0 | K55: =SUM(K27:K54) -> 0 | M55: =SUM(M27:M54) -> 0 | O55: =SUM(O27:O54) -> 0 | Q55: =SUM(Q27:Q54) -> 0 | S55: =SUM(S27:S54) -> 0
F56: BOND RATE | H56: 0 | J56: 0 | L56: 0 | N56: 0 | P56: 0 | R56: 0
F57: BOND AMOUNT | I57: =I55*H56 -> 0 | K57: =K55*J56 -> 0 | M57: =M55*L56 -> 0 | O57: =O55*N56 -> 0 | Q57: =Q55*P56 -> 0 | S57: =S55*R56 -> 0
F59: ADJUSTED TOTAL | I59: =SUM(I55:I58) -> 0 | K59: =SUM(K55:K58) -> 0 | M59: =SUM(M55:M58) -> 0 | O59: =SUM(O55:O58) -> 0 | Q59: =SUM(Q55:Q58) -> 0 | S59: =SUM(S55:S58) -> 0
F60: Cost per SF | I60: =I59/'Area Calculations'!$I$4 -> #DIV/0! | K60: =K59/'Area Calculations'!$I$4 -> #DIV/0! | M60: =M59/'Area Calculations'!$I$4 -> #DIV/0! | O60: =O59/'Area Calculations'!$I$4 -> #DIV/0! | Q60: =Q59/'Area Calculations'!$I$4 -> #DIV/0! | S60: =S59/'Area Calculations'!$I$4 -> #DIV/0!
F61: Cost per Unit | I61: =I59/'Area Calculations'!#REF! -> #REF! | K61: =K59/'Area Calculations'!#REF! -> #REF! | M61: =M59/'Area Calculations'!#REF! -> #REF! | O61: =O59/'Area Calculations'!#REF! -> #REF! | Q61: =Q59/'Area Calculations'!#REF! -> #REF! | S61: =S59/'Area Calculations'!#REF! -> #REF!
A63: QUALIFICATIONS
A67: EXCLUSIONS/OWNER PROVIDED ITEMS:
A71: ALTERNATES:
A75: PROPOSED VE (Provide Clear Description):
A79: FULLY LOADED LABOR RATES
B80: Laborer
B81: Mechanic
B82: Superintendent
B83: Project Manager
A85: SCHEDULE
B86: Prepared shop drawings/submittals
B87: Mobilization
B88: Total duration to complete scope of work
A90: Winner
A91: Company
A92: Contact
A93: Phone
A94: Email
A95: Base Bid
B97: Need Prequalification
B98: Prequalified

Sheet 07H Panelized Exterior Skin
G1: Hedrick Plug
F2: X | G2: Excluded
B3: BACK TO SUMMARY SHEET | F3: I | G3: Included | H3: Bidder 1 | J3: Bidder 2 | L3: Bidder 3 | N3: Bidder 4 | P3: Bidder5 | R3: Bidder6
A4: Project: | B4: ='Area Calculations'!B4 -> Project Name | G4: Company
A5: Trade: | B5: Panelized Exterior Skin | G5: Contact
A6: CSI Code: | B6: 07H | G6: Phone
A7: Date: | G7: Email
A8: Adjusted Bid | G8: Adjusted Bid | H8: =I58 -> 0 | J8: =K58 -> 0 | L8: =M58 -> 0 | N8: =O58 -> 0 | P8: =Q58 -> 0 | R8: =S58 -> 0
A9: BID DOCUMENTS: | C9: Plan/ Spec. Package | D9: QTY | E9: U/M | F9: Unit Cost | G9: Subtotal | H9: Yes/No | I9: Price | J9: Yes/No | K9: Price | L9: Yes/No | M9: Price | N9: Yes/No | O9: Price | P9: Yes/No | Q9: Price | R9: Yes/No | S9: Price
B10: Plans By Division
B11: ='Area Calculations'!L62 -> Architectural Drawings by | C11: P
B12: ='Area Calculations'!L63 -> Structural Drawings by | C12: P
B13: ='Area Calculations'!L64 -> MEP FA FP Drawings by | C13: P
B14: ='Area Calculations'!L65 -> Civil Drawings by | C14: P
B15: ='Area Calculations'!L66 -> Land scape Drawings by | C15: P
B16: ='Area Calculations'!L67 -> Kitchen Drawings by | C16: P
B17: ='Area Calculations'!L68 -> Storefront Designer by | C17: P
B18: ='Area Calculations'!L69 -> Geotech report by | C18: P
B19: ='Area Calculations'!L70 -> Specifications | C19: P
B21: Panelized Exterior Skin
B22: GENERAL INCLUSIONS
B23: INCLUDES ALL SALES TAX
B24: ALL HOISTING & RIGGING REQUIRED TO COMPLETE THIS SCOPE
B25: PROVIDE P&P BONDS
B26: FLORIDA STATE CONTRACTORS LIC.
B27: GENERAL LIABILITY AND WORKERS COMP. INSURANCE LIMITS
B28: STATE AND LOCAL TAXES
B29: COMPASS
B30: SPECIFIC TRADE SCOPE OF WORK REQUIREMENTS
B31: BASE BID
B32: Building SF
H44: x
F54: SUBTOTAL | I54: =SUM(I23:I53) -> 0 | K54: =SUM(K23:K53) -> 0 | M54: =SUM(M23:M53) -> 0 | O54: =SUM(O23:O53) -> 0 | Q54: =SUM(Q23:Q53) -> 0 | S54: =SUM(S23:S53) -> 0
F55: BOND RATE | H55: 0 | J55: 0 | L55: 0 | N55: 0 | P55: 0 | R55: 0
F56: BOND AMOUNT | I56: =I54*H55 -> 0 | K56: =K54*J55 -> 0 | M56: =M54*L55 -> 0 | O56: =O54*N55 -> 0 | Q56: =Q54*P55 -> 0 | S56: =S54*R55 -> 0
F58: ADJUSTED TOTAL | I58: =SUM(I54:I57) -> 0 | K58: =SUM(K54:K57) -> 0 | M58: =SUM(M54:M57) -> 0 | O58: =SUM(O54:O57) -> 0 | Q58: =SUM(Q54:Q57) -> 0 | S58: =SUM(S54:S57) -> 0
F59: Cost per SF | I59: =I58/'Area Calculations'!$I$4 -> #DIV/0! | K59: =K58/'Area Calculations'!$I$4 -> #DIV/0! | M59: =M58/'Area Calculations'!$I$4 -> #DIV/0! | O59: =O58/'Area Calculations'!$I$4 -> #DIV/0! | Q59: =Q58/'Area Calculations'!$I$4 -> #DIV/0! | S59: =S58/'Area Calculations'!$I$4 -> #DIV/0!
F60: Cost per Unit | I60: =I58/'Area Calculations'!#REF! -> #REF! | K60: =K58/'Area Calculations'!#REF! -> #REF! | M60: =M58/'Area Calculations'!#REF! -> #REF! | O60: =O58/'Area Calculations'!#REF! -> #REF! | Q60: =Q58/'Area Calculations'!#REF! -> #REF! | S60: =S58/'Area Calculations'!#REF! -> #REF!
A62: QUALIFICATIONS
A66: EXCLUSIONS/OWNER PROVIDED ITEMS:
A70: ALTERNATES:
A74: PROPOSED VE (Provide Clear Description):
A78: FULLY LOADED LABOR RATES
B79: Laborer
B80: Mechanic
B81: Superintendent
B82: Project Manager
A84: SCHEDULE
B85: Prepared shop drawings/submittals
B86: Mobilization
B87: Total duration to complete scope of work
A89: Winner
A90: Company
A91: Contact
A92: Phone
A93: Email
A94: Base Bid
B96: Need Prequalification
B97: Prequalified

Sheet 08A Doors, Frames, & Hardware
G1: Hedrick Plug
F2: X | G2: Excluded
B3: BACK TO SUMMARY SHEET | F3: I | G3: Included | H3: Bidder 1 | J3: Bidder 2 | L3: Bidder 3 | N3: Bidder 4 | P3: Bidder5 | R3: Bidder6
A4: Project: | B4: ='Area Calculations'!B4 -> Project Name | G4: Company
A5: Trade: | B5: Doors, Frames, & Hardware | G5: Contact
A6: CSI Code: | B6: 08A | G6: Phone
A7: Date: | G7: Email
A8: Adjusted Bid | G8: Adjusted Bid | H8: =I46 -> 0 | J8: 0 | L8: 0 | N8: 0 | P8: 0 | R8: 0
A9: BID DOCUMENTS: | C9: Plan/ Spec. Package | D9: QTY | E9: U/M | F9: Unit Cost | G9: Subtotal | H9: Yes/No | I9: Price | J9: Yes/No | K9: Price | L9: Yes/No | M9: Price | N9: Yes/No | O9: Price | P9: Yes/No | Q9: Price | R9: Yes/No | S9: Price
B10: Plans By Division
B11: ='Area Calculations'!L62 -> Architectural Drawings by | C11: P
B12: ='Area Calculations'!L63 -> Structural Drawings by | C12: P
B13: ='Area Calculations'!L64 -> MEP FA FP Drawings by | C13: P
B14: ='Area Calculations'!L65 -> Civil Drawings by | C14: P
B15: ='Area Calculations'!L66 -> Land scape Drawings by | C15: P
B16: ='Area Calculations'!L67 -> Kitchen Drawings by | C16: P
B17: ='Area Calculations'!L68 -> Storefront Designer by | C17: P
B18: ='Area Calculations'!L69 -> Geotech report by | C18: P
B19: ='Area Calculations'!L70 -> Specifications | C19: P
B21: Doors, Frames, & Hardware
B22: GENERAL INCLUSIONS
B23: INCLUDES ALL SALES TAX
B24: ALL HOISTING & RIGGING REQUIRED TO COMPLETE THIS SCOPE
B25: PROVIDE P&P BONDS
B26: FLORIDA STATE CONTRACTORS LIC.
B27: GENERAL LIABILITY AND WORKERS COMP. INSURANCE LIMITS
B28: STATE AND LOCAL TAXES
B29: COMPASS
B30: SPECIFIC TRADE SCOPE OF WORK REQUIREMENTS
B31: BASE BID
B32: Building SF
... B38: Double doors
B39: Installation | H39: i
F42: SUBTOTAL | I42: =SUM(I21:I41) -> 0 | K42: =SUM(K21:K41) -> 0 | M42: =SUM(M21:M41) -> 0 | O42: =SUM(O21:O41) -> 0 | Q42: =SUM(Q21:Q41) -> 0 | S42: =SUM(S21:S41) -> 0
F43: BOND RATE | H43: 0 | P43: 0 | R43: 0
F44: BOND AMOUNT | I44: =I42*H43 -> 0 | K44: =K42*J43 -> 0 | M44: =M42*L43 -> 0 | O44: =O42*N43 -> 0 | Q44: =Q42*P43 -> 0 | S44: =S42*R43 -> 0
F46: ADJUSTED TOTAL | I46: =SUM(I42:I44) -> 0 | K46: =SUM(K42:K44) -> 0 | M46: =SUM(M42:M44) -> 0 | O46: =SUM(O42:O44) -> 0 | Q46: =SUM(Q42:Q44) -> 0 | S46: =SUM(S42:S44) -> 0
F47: Cost per SF | I47: =I46/'Area Calculations'!$I$4 -> #DIV/0! | K47: =K46/'Area Calculations'!$I$4 -> #DIV/0! | M47: =M46/'Area Calculations'!$I$4 -> #DIV/0! | O47: =O46/'Area Calculations'!$I$4 -> #DIV/0! | Q47: =Q46/'Area Calculations'!$I$4 -> #DIV/0! | S47: =S46/'Area Calculations'!$I$4 -> #DIV/0!
F48: Cost per Unit | I48: =I46/'Area Calculations'!#REF! -> #REF! | K48: =K46/'Area Calculations'!#REF! -> #REF! | M48: =M46/'Area Calculations'!#REF! -> #REF! | O48: =O46/'Area Calculations'!#REF! -> #REF! | Q48: =Q46/'Area Calculations'!#REF! -> #REF! | S48: =S46/'Area Calculations'!#REF! -> #REF!
A50: QUALIFICATIONS
A54: EXCLUSIONS/OWNER PROVIDED ITEMS:
A58: ALTERNATES:
A62: PROPOSED VE (Provide Clear Description):
A66: FULLY LOADED LABOR RATES
B67: Laborer
B68: Mechanic
B69: Superintendent
B70: Project Manager
A72: SCHEDULE
B73: Prepared shop drawings/submittals
B74: Mobilization
B75: Total duration to complete scope of work
A77: Winner
A78: Company
A79: Contact
A80: Phone
A81: Email
A82: Base Bid
B84: Need Prequalification
B85: Prequalified

Sheet 08 30 Retractable Screens
G1: Hedrick Plug
G2: Excluded
B3: BACK TO SUMMARY SHEET | G3: Included | H3: Bidder 1 | J3: Bidder 2 | L3: Bidder 3 | N3: Bidder 4 | P3: Bidder5 | R3: Bidder6
A4: Project: | B4: ='Area Calculations'!B4 -> Project Name | G4: Company
A5: Trade: | B5: Retractable Screens | G5: Contact
A6: CSI Code: | B6: 08 30 | G6: Phone
A7: Date: | G7: Email
A8: Adjusted Bid | G8: Adjusted Bid
A9: BID DOCUMENTS: | C9: Plan/ Spec. Package | D9: QTY | E9: U/M | F9: Unit Cost | G9: Subtotal | H9: Yes/No | I9: Price | J9: Yes/No | K9: Price | L9: Yes/No | M9: Price | N9: Yes/No | O9: Price | P9: Yes/No | Q9: Price | R9: Yes/No | S9: Price
B10: Plans By Division
B11: ='Area Calculations'!L62 -> Architectural Drawings by | C11: P
B12: ='Area Calculations'!L63 -> Structural Drawings by | C12: P
B13: ='Area Calculations'!L64 -> MEP FA FP Drawings by | C13: P
B14: ='Area Calculations'!L65 -> Civil Drawings by | C14: P
B15: ='Area Calculations'!L66 -> Land scape Drawings by | C15: P
B16: ='Area Calculations'!L67 -> Kitchen Drawings by | C16: P
B17: ='Area Calculations'!L68 -> Storefront Designer by | C17: P
B18: ='Area Calculations'!L69 -> Geotech report by | C18: P
B19: ='Area Calculations'!L70 -> Specifications | C19: P
B21: Retractable Screens
B22: GENERAL INCLUSIONS
B23: INCLUDES ALL SALES TAX
B24: ALL HOISTING & RIGGING REQUIRED TO COMPLETE THIS SCOPE
B25: PROVIDE P&P BONDS
B26: FLORIDA STATE CONTRACTORS LIC.
B27: GENERAL LIABILITY AND WORKERS COMP. INSURANCE LIMITS
B28: STATE AND LOCAL TAXES
B29: SPECIFIC TRADE SCOPE OF WORK REQUIREMENTS
B30: BASE BID
F41: SUBTOTAL | I41: =SUM(I23:I40) -> 0 | K41: =SUM(K23:K40) -> 0 | M41: =SUM(M23:M40) -> 0 | O41: =SUM(O23:O40) -> 0 | Q41: =SUM(Q23:Q40) -> 0 | S41: =SUM(S23:S40) -> 0
F42: BOND RATE | H42: 0 | P42: 0 | R42: 0
F43: BOND AMOUNT | I43: =I41*H42 -> 0 | K43: =K41*J42 -> 0 | M43: =M41*L42 -> 0 | O43: =O41*N42 -> 0 | Q43: =Q41*P42 -> 0 | S43: =S41*R42 -> 0
F45: ADJUSTED TOTAL | I45: =SUM(I41:I43) -> 0 | K45: =SUM(K41:K43) -> 0 | M45: =SUM(M41:M43) -> 0 | O45: =SUM(O41:O43) -> 0 | Q45: =SUM(Q41:Q43) -> 0 | S45: =SUM(S41:S43) -> 0
F46: Cost per SF | I46: =I45/'Area Calculations'!$I$4 -> #DIV/0! | K46: =K45/'Area Calculations'!$I$4 -> #DIV/0! | M46: =M45/'Area Calculations'!$I$4 -> #DIV/0! | O46: =O45/'Area Calculations'!$I$4 -> #DIV/0! | Q46: =Q45/'Area Calculations'!$I$4 -> #DIV/0! | S46: =S45/'Area Calculations'!$I$4 -> #DIV/0!
F47: Cost per Unit | I47: =I45/'Area Calculations'!#REF! -> #REF! | K47: =K45/'Area Calculations'!#REF! -> #REF! | M47: =M45/'Area Calculations'!#REF! -> #REF! | O47: =O45/'Area Calculations'!#REF! -> #REF! | Q47: =Q45/'Area Calculations'!#REF! -> #REF! | S47: =S45/'Area Calculations'!#REF! -> #REF!
A49: QUALIFICATIONS
A53: EXCLUSIONS/OWNER PROVIDED ITEMS:
A57: ALTERNATES:
A61: PROPOSED VE (Provide Clear Description):
A65: FULLY LOADED LABOR RATES
B66: Laborer
B67: Mechanic
B68: Superintendent
B69: Project Manager
A71: SCHEDULE
B72: Prepared shop drawings/submittals
B73: Mobilization
B74: Total duration to complete scope of work
A76: Winner
A77: Company
A78: Contact
A79: Phone
A80: Email
A81: Base Bid
B83: Need Prequalification
B84: Prequalified

Sheet 08B Overhead Coiling Doors
G1: Hedrick Plug
F2: X | G2: Excluded
B3: BACK TO SUMMARY SHEET | F3: I | G3: Included | H3: Bidder 1 | J3: Bidder 2 | L3: Bidder 3 | N3: Bidder 4 | P3: Bidder5 | R3: Bidder6
A4: Project: | B4: ='Area Calculations'!B4 -> Project Name | G4: Company
A5: Trade: | B5: Overhead Coiling Doors | G5: Contact
A6: CSI Code: | B6: 08B | G6: Phone
A7: Date: | G7: Email
A8: Adjusted Bid | G8: Adjusted Bid | H8: =I43 -> 0 | J8: =K43 -> 0 | L8: =M43 -> 0 | N8: =O43 -> 0 | P8: =Q43 -> 0 | R8: =S43 -> 0
A9: BID DOCUMENTS: | C9: Plan/ Spec. Package | D9: QTY | E9: U/M | F9: Unit Cost | G9: Subtotal | H9: Yes/No | I9: Price | J9: Yes/No | K9: Price | L9: Yes/No | M9: Price | N9: Yes/No | O9: Price | P9: Yes/No | Q9: Price | R9: Yes/No | S9: Price
B10: Plans By Division
B11: ='Area Calculations'!L62 -> Architectural Drawings by | C11: P
B12: ='Area Calculations'!L63 -> Structural Drawings by | C12: P
B13: ='Area Calculations'!L64 -> MEP FA FP Drawings by | C13: P
B14: ='Area Calculations'!L65 -> Civil Drawings by | C14: P
B15: ='Area Calculations'!L66 -> Land scape Drawings by | C15: P
B16: ='Area Calculations'!L67 -> Kitchen Drawings by | C16: P
B17: ='Area Calculations'!L68 -> Storefront Designer by | C17: P
B18: ='Area Calculations'!L69 -> Geotech report by | C18: P
B19: ='Area Calculations'!L70 -> Specifications | C19: P
B21: Overhead Coiling Doors
B22: GENERAL INCLUSIONS
B23: INCLUDES ALL SALES TAX
B24: ALL HOISTING & RIGGING REQUIRED TO COMPLETE THIS SCOPE
B25: PROVIDE P&P BONDS
B26: FLORIDA STATE CONTRACTORS LIC.
B27: GENERAL LIABILITY AND WORKERS COMP. INSURANCE LIMITS
B28: STATE AND LOCAL TAXES
B29: COMPASS
B30: SPECIFIC TRADE SCOPE OF WORK REQUIREMENTS
B31: BASE BID
B32: Building SF
H34: i
F39: SUBTOTAL | I39: =SUM(I23:I38) -> 0 | K39: =SUM(K23:K38) -> 0 | M39: =SUM(M23:M38) -> 0 | O39: =SUM(O23:O38) -> 0 | Q39: =SUM(Q23:Q38) -> 0 | S39: =SUM(S23:S38) -> 0
F40: BOND RATE | H40: 0 | J40: 0 | L40: 0 | N40: 0 | P40: 0 | R40: 0
F41: BOND AMOUNT | I41: =H40*I39 -> 0 | K41: =J40*K39 -> 0 | M41: =L40*M39 -> 0 | O41: =N40*O39 -> 0 | Q41: =P40*Q39 -> 0 | S41: =R40*S39 -> 0
F43: ADJUSTED TOTAL | I43: =SUM(I39:I41) -> 0 | K43: =SUM(K39:K41) -> 0 | M43: =SUM(M39:M41) -> 0 | O43: =SUM(O39:O41) -> 0 | Q43: =SUM(Q39:Q41) -> 0 | S43: =SUM(S39:S41) -> 0
F44: Cost per SF | I44: =I43/'Area Calculations'!$I$4 -> #DIV/0! | K44: =K43/'Area Calculations'!$I$4 -> #DIV/0! | M44: =M43/'Area Calculations'!$I$4 -> #DIV/0! | O44: =O43/'Area Calculations'!$I$4 -> #DIV/0! | Q44: =Q43/'Area Calculations'!$I$4 -> #DIV/0! | S44: =S43/'Area Calculations'!$I$4 -> #DIV/0!
F45: Cost per Unit | I45: =I43/'Area Calculations'!#REF! -> #REF! | K45: =K43/'Area Calculations'!#REF! -> #REF! | M45: =M43/'Area Calculations'!#REF! -> #REF! | O45: =O43/'Area Calculations'!#REF! -> #REF! | Q45: =Q43/'Area Calculations'!#REF! -> #REF! | S45: =S43/'Area Calculations'!#REF! -> #REF!
A47: QUALIFICATIONS
A51: EXCLUSIONS/OWNER PROVIDED ITEMS:
A55: ALTERNATES:
A59: PROPOSED VE (Provide Clear Description):
A63: FULLY LOADED LABOR RATES
B64: Laborer
B65: Mechanic
B66: Superintendent
B67: Project Manager
A69: SCHEDULE
B70: Prepared shop drawings/submittals
B71: Mobilization
B72: Total duration to complete scope of work
A74: Winner
A75: Company
A76: Contact
A77: Phone
A78: Email
A79: Base Bid
B81: Need Prequalification
B82: Prequalified

Sheet 08C Glass and Glazing
G1: Hedrick Plug
F2: X | G2: Excluded
B3: BACK TO SUMMARY SHEET | F3: I | G3: Included | H3: Bidder 1 | J3: Bidder 2 | L3: Bidder 3 | N3: Bidder 4 | P3: Bidder 5 | R3: Bidder 6
A4: Project: | B4: ='Area Calculations'!B4 -> Project Name | G4: Company
A5: Trade: | B5: Glass and Glazing | G5: Contact
A6: CSI Code: | B6: 08C | G6: Phone
A7: Date: | G7: Email
A8: Adjusted Bid | G8: Adjusted Bid | H8: =I69 -> 0 | J8: =K69 -> 0 | L8: =M69 -> 0 | N8: =O69 -> 0 | P8: =Q69 -> 0 | R8: =S69 -> 0
A9: BID DOCUMENTS: | C9: Plan/ Spec. Package | D9: QTY | E9: U/M | F9: Unit Cost | G9: Subtotal | H9: Yes/No | I9: Price | J9: Yes/No | K9: Price | L9: Yes/No | M9: Price | N9: Yes/No | O9: Price | P9: Yes/No | Q9: Price | R9: Yes/No | S9: Price
B10: Plans By Division
B11: ='Area Calculations'!L62 -> Architectural Drawings by | C11: P
B12: ='Area Calculations'!L63 -> Structural Drawings by | C12: P
B13: ='Area Calculations'!L64 -> MEP FA FP Drawings by | C13: P
B14: ='Area Calculations'!L65 -> Civil Drawings by | C14: P
B15: ='Area Calculations'!L66 -> Land scape Drawings by | C15: P
B16: ='Area Calculations'!L67 -> Kitchen Drawings by | C16: P
B17: ='Area Calculations'!L68 -> Storefront Designer by | C17: P
B18: ='Area Calculations'!L69 -> Geotech report by | C18: P
B19: ='Area Calculations'!L70 -> Specifications | C19: P
B21: Glass and Glazing
B22: GENERAL INCLUSIONS
B23: INCLUDES ALL SALES TAX
B24: ALL HOISTING & RIGGING REQUIRED TO COMPLETE THIS SCOPE
B25: PROVIDE P&P BONDS
B26: FLORIDA STATE CONTRACTORS LIC.
B27: GENERAL LIABILITY AND WORKERS COMP. INSURANCE LIMITS
B28: STATE AND LOCAL TAXES
B29: COMPASS
B30: SPECIFIC TRADE SCOPE OF WORK REQUIREMENTS
B31: BASE BID
B32: Building SF
... B53: Mullions: Surface Applied?
H59: i
B60: Interior Windows:
B61: Manufacturer:
B62: Series:
B63: Glazing:
B64: Frame:
F65: SUBTOTAL | I65: =SUM(I23:I64) -> 0 | K65: =SUM(K26:K64) -> 0 | M65: =SUM(M23:M64) -> 0 | O65: =SUM(O23:O64) -> 0 | Q65: =SUM(Q26:Q64) -> 0 | S65: =SUM(S26:S64) -> 0
F66: BOND RATE | H66: 0 | J66: 0 | L66: 0 | N66: 0 | P66: 0 | R66: 0
F67: BOND AMOUNT | I67: =H66*I65 -> 0 | K67: =J66*K65 -> 0 | M67: =L66*M65 -> 0 | O67: =N66*O65 -> 0 | Q67: =P66*Q65 -> 0 | S67: =R66*S65 -> 0
F69: ADJUSTED TOTAL | I69: =SUM(I65:I67) -> 0 | K69: =SUM(K65:K67) -> 0 | M69: =SUM(M65:M67) -> 0 | O69: =SUM(O65:O67) -> 0 | Q69: =SUM(Q65:Q67) -> 0 | S69: =SUM(S65:S67) -> 0
F70: Cost per SF | I70: =I69/'Area Calculations'!$I$4 -> #DIV/0! | K70: =K69/'Area Calculations'!$I$4 -> #DIV/0! | M70: =M69/'Area Calculations'!$I$4 -> #DIV/0! | O70: =O69/'Area Calculations'!$I$4 -> #DIV/0! | Q70: =Q69/'Area Calculations'!$I$4 -> #DIV/0! | S70: =S69/'Area Calculations'!$I$4 -> #DIV/0!
F71: Cost per Unit | I71: =I69/'Area Calculations'!#REF! -> #REF! | K71: =K69/'Area Calculations'!#REF! -> #REF! | M71: =M69/'Area Calculations'!#REF! -> #REF! | O71: =O69/'Area Calculations'!#REF! -> #REF! | Q71: =Q69/'Area Calculations'!#REF! -> #REF! | S71: =S69/'Area Calculations'!#REF! -> #REF!
A73: QUALIFICATIONS
A77: EXCLUSIONS/OWNER PROVIDED ITEMS:
A81: ALTERNATES:
A85: PROPOSED VE (Provide Clear Description):
A89: FULLY LOADED LABOR RATES
B90: Laborer
B91: Mechanic
B92: Superintendent
B93: Project Manager
A95: SCHEDULE
B96: Prepared shop drawings/submittals
B97: Mobilization
B98: Total duration to complete scope of work
A100: Winner
A101: Company
A102: Contact
A103: Phone
A104: Email
A105: Base Bid
B107: Need Prequalification
B108: Prequalified

Sheet 08D Skylights
G1: Hedrick Plug
F2: X | G2: Excluded
B3: BACK TO SUMMARY SHEET | F3: I | G3: Included | H3: Bidder 1 | J3: Bidder 2 | L3: Bidder 3 | N3: Bidder 4 | P3: Bidder 5 | R3: Bidder 6
A4: Project: | B4: ='Area Calculations'!B4 -> Project Name | G4: Company
A5: Trade: | B5: Skylights | G5: Contact
A6: CSI Code: | B6: 08D | G6: Phone
A7: Date: | G7: Email
A8: Adjusted Bid | G8: Adjusted Bid | H8: =I48 -> 0 | J8: =K48 -> 0 | L8: =M48 -> 0 | N8: =O48 -> 0 | P8: =Q48 -> 0 | R8: =S46 -> 0
A9: BID DOCUMENTS: | C9: Plan/ Spec. Package | D9: QTY | E9: U/M | F9: Unit Cost | G9: Subtotal | H9: Yes/No | I9: Price | J9: Yes/No | K9: Price | L9: Yes/No | M9: Price | N9: Yes/No | O9: Price | P9: Yes/No | Q9: Price | R9: Yes/No | S9: Price
B10: Plans By Division
B11: ='Area Calculations'!L62 -> Architectural Drawings by | C11: P
B12: ='Area Calculations'!L63 -> Structural Drawings by | C12: P
B13: ='Area Calculations'!L64 -> MEP FA FP Drawings by | C13: P
B14: ='Area Calculations'!L65 -> Civil Drawings by | C14: P
B15: ='Area Calculations'!L66 -> Land scape Drawings by | C15: P
B16: ='Area Calculations'!L67 -> Kitchen Drawings by | C16: P
B17: ='Area Calculations'!L68 -> Storefront Designer by | C17: P
B18: ='Area Calculations'!L69 -> Geotech report by | C18: P
B19: ='Area Calculations'!L70 -> Specifications | C19: P
B21: Skylights
B22: GENERAL INCLUSIONS
B23: INCLUDES ALL SALES TAX
B24: ALL HOISTING & RIGGING REQUIRED TO COMPLETE THIS SCOPE
B25: PROVIDE P&P BONDS
B26: FLORIDA STATE CONTRACTORS LIC.
B27: GENERAL LIABILITY AND WORKERS COMP. INSURANCE LIMITS
B28: STATE AND LOCAL TAXES
B29: COMPASS
B30: SPECIFIC TRADE SCOPE OF WORK REQUIREMENTS
B31: BASE BID
B32: Building SF
H36: i
F44: SUBTOTAL | I44: =SUM(I23:I43) -> 0 | K44: =SUM(K23:K43) -> 0 | M44: =SUM(M23:M43) -> 0 | O44: =SUM(O26:O43) -> 0 | Q44: =SUM(Q26:Q43) -> 0 | S44: =SUM(S26:S43) -> 0
F45: BOND RATE | H45: 0 | J45: 0 | L45: 0 | N45: 0 | P45: 0 | R45: 0
F46: BOND AMOUNT | I46: =H45*I44 -> 0 | K46: =J45*K44 -> 0 | M46: =L45*M44 -> 0 | O46: =N45*O44 -> 0 | Q46: =P45*Q44 -> 0 | S46: =R45*S44 -> 0
F48: ADJUSTED TOTAL | I48: =SUM(I44:I46) -> 0 | K48: =SUM(K44:K46) -> 0 | M48: =SUM(M44:M46) -> 0 | O48: =SUM(O44:O46) -> 0 | Q48: =SUM(Q44:Q46) -> 0 | S48: =SUM(S44:S46) -> 0
F49: Cost per SF | I49: =I48/'Area Calculations'!$I$4 -> #DIV/0! | K49: =K48/'Area Calculations'!$I$4 -> #DIV/0! | M49: =M48/'Area Calculations'!$I$4 -> #DIV/0! | O49: =O48/'Area Calculations'!$I$4 -> #DIV/0! | Q49: =Q48/'Area Calculations'!$I$4 -> #DIV/0! | S49: =S48/'Area Calculations'!$I$4 -> #DIV/0!
F50: Cost per Unit | I50: =I48/'Area Calculations'!#REF! -> #REF! | K50: =K48/'Area Calculations'!#REF! -> #REF! | M50: =M48/'Area Calculations'!#REF! -> #REF! | O50: =O48/'Area Calculations'!#REF! -> #REF! | Q50: =Q48/'Area Calculations'!#REF! -> #REF! | S50: =S48/'Area Calculations'!#REF! -> #REF!
A52: QUALIFICATIONS
A56: EXCLUSIONS/OWNER PROVIDED ITEMS:
A60: ALTERNATES:
A64: PROPOSED VE (Provide Clear Description):
A68: FULLY LOADED LABOR RATES
B69: Laborer
B70: Mechanic
B71: Superintendent
B72: Project Manager
A74: SCHEDULE
B75: Prepared shop drawings/submittals
B76: Mobilization
B77: Total duration to complete scope of work
A79: Winner
A80: Company
A81: Contact
A82: Phone
A83: Email
A84: Base Bid
B86: Need Prequalification
B87: Prequalified

Sheet 08E Mirrors
G1: Hedrick Plug
F2: X | G2: Excluded
B3: BACK TO SUMMARY SHEET | F3: I | G3: Included | H3: Bidder 1 | J3: Bidder 2 | L3: Bidder 3 | N3: Bidder 4 | P3: Bidder 5 | R3: Bidder 6
A4: Project: | B4: ='Area Calculations'!B4 -> Project Name | G4: Company
A5: Trade: | B5: Mirrors | G5: Contact
A6: CSI Code: | B6: 08E | G6: Phone
A7: Date: | G7: Email
A8: Adjusted Bid | G8: Adjusted Bid | H8: =I48 -> 0 | J8: =K48 -> 0 | L8: =M48 -> 0 | N8: =O48 -> 0 | P8: =Q48 -> 0 | R8: =S46 -> 0
A9: BID DOCUMENTS: | C9: Plan/ Spec. Package | D9: QTY | E9: U/M | F9: Unit Cost | G9: Subtotal | H9: Yes/No | I9: Price | J9: Yes/No | K9: Price | L9: Yes/No | M9: Price | N9: Yes/No | O9: Price | P9: Yes/No | Q9: Price | R9: Yes/No | S9: Price
B10: Plans By Division
B11: ='Area Calculations'!L62 -> Architectural Drawings by | C11: P
B12: ='Area Calculations'!L63 -> Structural Drawings by | C12: P
B13: ='Area Calculations'!L64 -> MEP FA FP Drawings by | C13: P
B14: ='Area Calculations'!L65 -> Civil Drawings by | C14: P
B15: ='Area Calculations'!L66 -> Land scape Drawings by | C15: P
B16: ='Area Calculations'!L67 -> Kitchen Drawings by | C16: P
B17: ='Area Calculations'!L68 -> Storefront Designer by | C17: P
B18: ='Area Calculations'!L69 -> Geotech report by | C18: P
B19: ='Area Calculations'!L70 -> Specifications | C19: P
B21: Mirrors
B22: GENERAL INCLUSIONS
B23: INCLUDES ALL SALES TAX
B24: ALL HOISTING & RIGGING REQUIRED TO COMPLETE THIS SCOPE
B25: PROVIDE P&P BONDS
B26: FLORIDA STATE CONTRACTORS LIC.
B27: GENERAL LIABILITY AND WORKERS COMP. INSURANCE LIMITS
B28: STATE AND LOCAL TAXES
B29: COMPASS
B30: SPECIFIC TRADE SCOPE OF WORK REQUIREMENTS
B31: BASE BID
B32: Building SF
H36: i
F44: SUBTOTAL | I44: =SUM(I23:I43) -> 0 | K44: =SUM(K23:K43) -> 0 | M44: =SUM(M23:M43) -> 0 | O44: =SUM(O26:O43) -> 0 | Q44: =SUM(Q26:Q43) -> 0 | S44: =SUM(S26:S43) -> 0
F45: BOND RATE | H45: 0 | J45: 0 | L45: 0 | N45: 0 | P45: 0 | R45: 0
F46: BOND AMOUNT | I46: =H45*I44 -> 0 | K46: =J45*K44 -> 0 | M46: =L45*M44 -> 0 | O46: =N45*O44 -> 0 | Q46: =P45*Q44 -> 0 | S46: =R45*S44 -> 0
F48: ADJUSTED TOTAL | I48: =SUM(I44:I46) -> 0 | K48: =SUM(K44:K46) -> 0 | M48: =SUM(M44:M46) -> 0 | O48: =SUM(O44:O46) -> 0 | Q48: =SUM(Q44:Q46) -> 0 | S48: =SUM(S44:S46) -> 0
F49: Cost per SF | I49: =I48/'Area Calculations'!$I$4 -> #DIV/0! | K49: =K48/'Area Calculations'!$I$4 -> #DIV/0! | M49: =M48/'Area Calculations'!$I$4 -> #DIV/0! | O49: =O48/'Area Calculations'!$I$4 -> #DIV/0! | Q49: =Q48/'Area Calculations'!$I$4 -> #DIV/0! | S49: =S48/'Area Calculations'!$I$4 -> #DIV/0!
F50: Cost per Unit | I50: =I48/'Area Calculations'!#REF! -> #REF! | K50: =K48/'Area Calculations'!#REF! -> #REF! | M50: =M48/'Area Calculations'!#REF! -> #REF! | O50: =O48/'Area Calculations'!#REF! -> #REF! | Q50: =Q48/'Area Calculations'!#REF! -> #REF! | S50: =S48/'Area Calculations'!#REF! -> #REF!
A52: QUALIFICATIONS
A56: EXCLUSIONS/OWNER PROVIDED ITEMS:
A60: ALTERNATES:
A64: PROPOSED VE (Provide Clear Description):
A68: FULLY LOADED LABOR RATES
B69: Laborer
B70: Mechanic
B71: Superintendent
B72: Project Manager
A74: SCHEDULE
B75: Prepared shop drawings/submittals
B76: Mobilization
B77: Total duration to complete scope of work
A79: Winner
A80: Company
A81: Contact
A82: Phone
A83: Email
A84: Base Bid
B86: Need Prequalification
B87: Prequalified

Sheet 09A Stucco
G1: Hedrick Plug
F2: X | G2: Excluded
B3: BACK TO SUMMARY SHEET | F3: I | G3: Included | H3: Bidder 1 | J3: Bidder 2 | L3: Bidder 4 | N3: Bidder 3 | P3: Bidder 5 | R3: Bidder 6
A4: Project: | B4: ='Area Calculations'!B4 -> Project Name | G4: Company
A5: Trade: | B5: Stucco | G5: Contact
A6: CSI Code: | B6: 09A | G6: Phone
A7: Date: | G7: Email
A8: Adjusted Bid | G8: Adjusted Bid | H8: =I51 -> 0 | J8: =K51 -> 0 | L8: =M51 -> 0 | N8: =O51 -> 0 | P8: =Q51 -> 0 | R8: =S51 -> 0
A9: BID DOCUMENTS: | C9: Plan/ Spec. Package | D9: QTY | E9: U/M | F9: Unit Cost | G9: Subtotal | H9: Yes/No | I9: Price | J9: Yes/No | K9: Price | L9: Yes/No | M9: Price | N9: Yes/No | O9: Price | P9: Yes/No | Q9: Price | R9: Yes/No | S9: Price
B10: Plans By Division
B11: ='Area Calculations'!L62 -> Architectural Drawings by | C11: P
B12: ='Area Calculations'!L63 -> Structural Drawings by | C12: P
B13: ='Area Calculations'!L64 -> MEP FA FP Drawings by | C13: P
B14: ='Area Calculations'!L65 -> Civil Drawings by | C14: P
B15: ='Area Calculations'!L66 -> Land scape Drawings by | C15: P
B16: ='Area Calculations'!L67 -> Kitchen Drawings by | C16: P
B17: ='Area Calculations'!L68 -> Storefront Designer by | C17: P
B18: ='Area Calculations'!L69 -> Geotech report by | C18: P
B19: ='Area Calculations'!L70 -> Specifications | C19: P
B21: Stucco
B22: GENERAL INCLUSIONS
B23: INCLUDES ALL SALES TAX
B24: ALL HOISTING & RIGGING REQUIRED TO COMPLETE THIS SCOPE
B25: PROVIDE P&P BONDS
B26: FLORIDA STATE CONTRACTORS LIC.
B27: GENERAL LIABILITY AND WORKERS COMP. INSURANCE LIMITS
B28: STATE AND LOCAL TAXES
B29: SPECIFIC TRADE SCOPE OF WORK REQUIREMENTS
B30: BASE BID
B31: Building SF
B33: Stucco, incl.:
... B36: c. all required equipment and scaffolding as needed
B37: d. foam out lookers and brackets as shown | H37: i
B38: e. Above scope included for:
F47: SUBTOTAL | I47: =SUM(I23:I46) -> 0 | K47: =SUM(K23:K46) -> 0 | M47: =SUM(M26:M46) -> 0 | O47: =SUM(O23:O46) -> 0 | Q47: =SUM(Q26:Q46) -> 0 | S47: =SUM(S26:S46) -> 0
F48: BOND RATE | H48: 0 | J48: 0 | L48: 0 | N48: 0 | P48: 0 | R48: 0
F49: BOND AMOUNT | I49: =H48*I47 -> 0 | K49: =J48*K47 -> 0 | M49: =L48*M47 -> 0 | O49: =N48*O47 -> 0 | Q49: =P48*Q47 -> 0 | S49: =R48*S47 -> 0
F51: ADJUSTED TOTAL | I51: =SUM(I47:I49) -> 0 | K51: =SUM(K47:K49) -> 0 | M51: =SUM(M47:M49) -> 0 | O51: =SUM(O47:O49) -> 0 | Q51: =SUM(Q47:Q49) -> 0 | S51: =SUM(S47:S49) -> 0
F52: Cost per SF | I52: =I51/'Area Calculations'!$I$4 -> #DIV/0! | K52: =K51/'Area Calculations'!$I$4 -> #DIV/0! | M52: =M51/'Area Calculations'!$I$4 -> #DIV/0! | O52: =O51/'Area Calculations'!$I$4 -> #DIV/0! | Q52: =Q51/'Area Calculations'!$I$4 -> #DIV/0! | S52: =S51/'Area Calculations'!$I$4 -> #DIV/0!
F53: Cost per Unit | I53: =I51/'Area Calculations'!#REF! -> #REF! | K53: =K51/'Area Calculations'!#REF! -> #REF! | M53: =M51/'Area Calculations'!#REF! -> #REF! | O53: =O51/'Area Calculations'!#REF! -> #REF! | Q53: =Q51/'Area Calculations'!#REF! -> #REF! | S53: =S51/'Area Calculations'!#REF! -> #REF!
A55: QUALIFICATIONS
A59: EXCLUSIONS/OWNER PROVIDED ITEMS:
A63: ALTERNATES:
A67: PROPOSED VE (Provide Clear Description):
A71: FULLY LOADED LABOR RATES
B72: Laborer
B73: Mechanic
B74: Superintendent
B75: Project Manager
A77: SCHEDULE
B78: Prepared shop drawings/submittals
B79: Mobilization
B80: Total duration to complete scope of work
A82: Winner
A83: Company
A84: Contact
A85: Phone
A86: Email
A87: Base Bid
B89: Need Prequalification
B90: Prequalified

Sheet 09B Drywall&Framing
G1: Hedrick Plug
F2: X | G2: Excluded
B3: BACK TO SUMMARY SHEET | F3: I | G3: Included | H3: Bidder 1 | J3: Bidder 2 | L3: Bidder 3 | N3: Bidder 4 | P3: Bidder5 | R3: Bidder6
A4: Project: | B4: ='Area Calculations'!B4 -> Project Name | G4: Company
A5: Trade: | B5: Drywall & Framing | G5: Contact
A6: CSI Code: | B6: 09B | G6: Phone
A7: Date: | G7: Email
A8: Adjusted Bid | G8: Adjusted Bid | H8: =I56 -> 0 | J8: =K56 -> 0 | L8: =M56 -> 0
A9: BID DOCUMENTS: | C9: Plan/ Spec. Package | D9: QTY | E9: U/M | F9: Unit Cost | G9: Subtotal | H9: Yes/No | I9: Price | J9: Yes/No | K9: Price | L9: Yes/No | M9: Price | N9: Yes/No | O9: Price | P9: Yes/No | Q9: Price | R9: Yes/No | S9: Price
B10: Plans By Division
B11: ='Area Calculations'!L62 -> Architectural Drawings by | C11: P
B12: ='Area Calculations'!L63 -> Structural Drawings by | C12: P
B13: ='Area Calculations'!L64 -> MEP FA FP Drawings by | C13: P
B14: ='Area Calculations'!L65 -> Civil Drawings by | C14: P
B15: ='Area Calculations'!L66 -> Land scape Drawings by | C15: P
B16: ='Area Calculations'!L67 -> Kitchen Drawings by | C16: P
B17: ='Area Calculations'!L68 -> Storefront Designer by | C17: P
B18: ='Area Calculations'!L69 -> Geotech report by | C18: P
B20: Drywall & Framing
B21: GENERAL INCLUSIONS
B22: INCLUDES ALL SALES TAX
B23: ALL HOISTING & RIGGING REQUIRED TO COMPLETE THIS SCOPE
B24: PROVIDE P&P BONDS
B25: FLORIDA STATE CONTRACTORS LIC.
B26: GENERAL LIABILITY AND WORKERS COMP. INSURANCE LIMITS
B27: STATE AND LOCAL TAXES
B28: COMPASS
B29: SPECIFIC TRADE SCOPE OF WORK REQUIREMENTS
B30: BASE BID
B31: Building SF
... B35: a. furnish all metal studs, channels, horizontal bracing, gypsum board products and insulation as scheduled
B36: b. equipment, lifts, power tools, etc. as required | H36: i
B37: c. Level 4 finish and X finish as scheduled
B38: d. provide in wall backing for cabinets, door frames, fire extinguishers, accessories, etc. as required/scheduled.
B39: e. include labor for wall and ceiling layout as required
B40: f. provide fire caulking, sound caulking, etc. to complete partition/wall type for a complete wall and ceiling assembly.
B41: g. OSHA requirements
B42: h. daily clean up for your scope of work
B43: i. Above scope included for:
F52: SUBTOTAL | I52: =SUM(I22:I51) -> 0 | K52: =SUM(K22:K51) -> 0 | M52: =SUM(M22:M51) -> 0 | O52: =SUM(O22:O51) -> 0 | Q52: =SUM(Q22:Q51) -> 0 | S52: =SUM(S22:S51) -> 0
F53: BOND RATE | H53: 0 | J53: 0 | L53: 0 | N53: 0 | P53: 0 | R53: 0
F54: BOND AMOUNT | I54: =I52*H53 -> 0 | K54: =K52*J53 -> 0 | M54: =M52*L53 -> 0 | O54: =O52*N53 -> 0 | Q54: =Q52*P53 -> 0 | S54: =S52*R53 -> 0
F56: ADJUSTED TOTAL | I56: =SUM(I52:I54) -> 0 | K56: =SUM(K52:K54) -> 0 | M56: =SUM(M52:M54) -> 0 | O56: =SUM(O52:O54) -> 0 | Q56: =SUM(Q52:Q54) -> 0 | S56: =SUM(S52:S54) -> 0
F57: Cost per SF | I57: =I56/'Area Calculations'!$I$4 -> #DIV/0! | K57: =K56/'Area Calculations'!$I$4 -> #DIV/0! | M57: =M56/'Area Calculations'!$I$4 -> #DIV/0! | O57: =O56/'Area Calculations'!$I$4 -> #DIV/0! | Q57: =Q56/'Area Calculations'!$I$4 -> #DIV/0! | S57: =S56/'Area Calculations'!$I$4 -> #DIV/0!
F58: Cost per Unit | I58: =I56/'Area Calculations'!#REF! -> #REF! | K58: =K56/'Area Calculations'!#REF! -> #REF! | M58: =M56/'Area Calculations'!#REF! -> #REF! | O58: =O56/'Area Calculations'!#REF! -> #REF! | Q58: =Q56/'Area Calculations'!#REF! -> #REF! | S58: =S56/'Area Calculations'!#REF! -> #REF!
A60: QUALIFICATIONS
A64: EXCLUSIONS/OWNER PROVIDED ITEMS:
A68: ALTERNATES:
A72: PROPOSED VE (Provide Clear Description):
A76: FULLY LOADED LABOR RATES
B77: Laborer
B78: Mechanic
B79: Superintendent
B80: Project Manager
A82: SCHEDULE
B83: Prepared shop drawings/submittals
B84: Mobilization
B85: Total duration to complete scope of work
A87: Winner
A88: Company
A89: Contact
A90: Phone
A91: Email
A92: Base Bid
B94: Need Prequalification
B95: Prequalified

Sheet 09C Acoustical Ceilings
G1: Hedrick Plug
F2: X | G2: Excluded
B3: BACK TO SUMMARY SHEET | F3: I | G3: Included | H3: Bidder 1 | J3: Bidder 2 | L3: Bidder 3 | N3: Bidder 4 | P3: Bidder 5 | R3: Bidder 6
A4: Project: | B4: ='Area Calculations'!B4 -> Project Name | G4: Company
A5: Trade: | B5: Acoustical Ceilings | G5: Contact
A6: CSI Code: | B6: 09C | G6: Phone
A7: Date: | G7: Email
A8: Adjusted Bid | G8: Adjusted Bid
A9: BID DOCUMENTS: | C9: Plan/ Spec. Package | D9: QTY | E9: U/M | F9: Unit Cost | G9: Subtotal | H9: Yes/No | I9: Price | J9: Yes/No | K9: Price | L9: Yes/No | M9: Price | N9: Yes/No | O9: Price | P9: Yes/No | Q9: Price | R9: Yes/No | S9: Price
B10: Plans By Division
B11: ='Area Calculations'!L62 -> Architectural Drawings by | C11: P
B12: ='Area Calculations'!L63 -> Structural Drawings by | C12: P
B13: ='Area Calculations'!L64 -> MEP FA FP Drawings by | C13: P
B14: ='Area Calculations'!L65 -> Civil Drawings by | C14: P
B15: ='Area Calculations'!L66 -> Land scape Drawings by | C15: P
B16: ='Area Calculations'!L67 -> Kitchen Drawings by | C16: P
B17: ='Area Calculations'!L68 -> Storefront Designer by | C17: P
B18: ='Area Calculations'!L69 -> Geotech report by | C18: P
B19: ='Area Calculations'!L70 -> Specifications | C19: P
B21: Acoustical Ceilings
B22: GENERAL INCLUSIONS
B23: INCLUDES ALL SALES TAX
B24: ALL HOISTING & RIGGING REQUIRED TO COMPLETE THIS SCOPE
B25: PROVIDE P&P BONDS
B26: FLORIDA STATE CONTRACTORS LIC.
B27: GENERAL LIABILITY AND WORKERS COMP. INSURANCE LIMITS
B28: STATE AND LOCAL TAXES
B29: COMPASS
B30: SPECIFIC TRADE SCOPE OF WORK REQUIREMENTS
B31: BASE BID
B34: Acoustical Ceilings, incl.:
B35: a. furnish and install all wire hangers, ACT tiles, grid as specified
B36: b. equipment, lifts, power tools, etc. as required | H36: i
B37: c. OSHA requirements
B38: d. daily clean up for your scope of work
B39: e. Above scope included for:
B41: Manufacturer:
B42: Tile Specification:
B43: Grid Specification:
F47: SUBTOTAL | I47: =SUM(I23:I46) -> 0 | K47: =SUM(K23:K46) -> 0 | M47: =SUM(M23:M46) -> 0 | O47: =SUM(O26:O46) -> 0 | Q47: =SUM(Q26:Q46) -> 0 | S47: =SUM(S26:S46) -> 0
F48: BOND RATE | H48: 0 | J48: 0 | L48: 0 | N48: 0 | P48: 0 | R48: 0
F49: BOND AMOUNT | I49: =H48*I47 -> 0 | K49: =J48*K47 -> 0 | M49: =L48*M47 -> 0 | O49: =N48*O47 -> 0 | Q49: =P48*Q47 -> 0 | S49: =R48*S47 -> 0
F51: ADJUSTED TOTAL | I51: =SUM(I47:I49) -> 0 | K51: =SUM(K47:K49) -> 0 | M51: =SUM(M47:M49) -> 0 | O51: =SUM(O47:O49) -> 0 | Q51: =SUM(Q47:Q49) -> 0 | S51: =SUM(S47:S49) -> 0
F52: Cost per SF | I52: =I51/'Area Calculations'!$I$4 -> #DIV/0! | K52: =K51/'Area Calculations'!$I$4 -> #DIV/0! | M52: =M51/'Area Calculations'!$I$4 -> #DIV/0! | O52: =O51/'Area Calculations'!$I$4 -> #DIV/0! | Q52: =Q51/'Area Calculations'!$I$4 -> #DIV/0! | S52: =S51/'Area Calculations'!$I$4 -> #DIV/0!
F53: Cost per Unit | I53: =I51/'Area Calculations'!#REF! -> #REF! | K53: =K51/'Area Calculations'!#REF! -> #REF! | M53: =M51/'Area Calculations'!#REF! -> #REF! | O53: =O51/'Area Calculations'!#REF! -> #REF! | Q53: =Q51/'Area Calculations'!#REF! -> #REF! | S53: =S51/'Area Calculations'!#REF! -> #REF!
A55: QUALIFICATIONS
A59: EXCLUSIONS/OWNER PROVIDED ITEMS:
A63: ALTERNATES:
A67: PROPOSED VE (Provide Clear Description):
A71: FULLY LOADED LABOR RATES
B72: Laborer
B73: Mechanic
B74: Superintendent
B75: Project Manager
A77: SCHEDULE
B78: Prepared shop drawings/submittals
B79: Mobilization
B80: Total duration to complete scope of work
A82: Winner
A83: Company
A84: Contact
A85: Phone
A86: Email
A87: Base Bid
B89: Need Prequalification
B90: Prequalified

Sheet 09D Acoustical Treatment
G1: Hedrick Plug
F2: X | G2: Excluded
B3: BACK TO SUMMARY SHEET | F3: I | G3: Included | H3: Bidder 1 | J3: Bidder 2 | L3: Bidder 3 | N3: Bidder 4 | P3: Bidder 5 | R3: Bidder 6
A4: Project: | B4: ='Area Calculations'!B4 -> Project Name | G4: Company
A5: Trade: | B5: Acoustical Treatment | G5: Contact
A6: CSI Code: | B6: 09D | G6: Phone
A7: Date: | G7: Email
A8: Adjusted Bid | G8: Adjusted Bid
A9: BID DOCUMENTS: | C9: Plan/ Spec. Package | D9: QTY | E9: U/M | F9: Unit Cost | G9: Subtotal | H9: Yes/No | I9: Price | J9: Yes/No | K9: Price | L9: Yes/No | M9: Price | N9: Yes/No | O9: Price | P9: Yes/No | Q9: Price | R9: Yes/No | S9: Price
B10: Plans By Division
B11: ='Area Calculations'!L62 -> Architectural Drawings by | C11: P
B12: ='Area Calculations'!L63 -> Structural Drawings by | C12: P
B13: ='Area Calculations'!L64 -> MEP FA FP Drawings by | C13: P
B14: ='Area Calculations'!L65 -> Civil Drawings by | C14: P
B15: ='Area Calculations'!L66 -> Land scape Drawings by | C15: P
B16: ='Area Calculations'!L67 -> Kitchen Drawings by | C16: P
B17: ='Area Calculations'!L68 -> Storefront Designer by | C17: P
B18: ='Area Calculations'!L69 -> Geotech report by | C18: P
B19: ='Area Calculations'!L70 -> Specifications | C19: P
B21: Acoustical Treatment
B22: GENERAL INCLUSIONS
B23: INCLUDES ALL SALES TAX
B24: ALL HOISTING & RIGGING REQUIRED TO COMPLETE THIS SCOPE
B25: PROVIDE P&P BONDS
B26: FLORIDA STATE CONTRACTORS LIC.
B27: GENERAL LIABILITY AND WORKERS COMP. INSURANCE LIMITS
B28: STATE AND LOCAL TAXES
B29: COMPASS
B30: SPECIFIC TRADE SCOPE OF WORK REQUIREMENTS
B31: BASE BID
B34: Acoustical Ceilings, incl.:
B35: a. furnish and install all wire hangers, ACT tiles, grid as specified
B36: b. equipment, lifts, power tools, etc. as required | H36: i
B37: c. OSHA requirements
B38: d. daily clean up for your scope of work
B39: e. Above scope included for:
B41: Manufacturer:
B42: Tile Specification:
B43: Grid Specification:
F47: SUBTOTAL | I47: =SUM(I23:I46) -> 0 | K47: =SUM(K23:K46) -> 0 | M47: =SUM(M23:M46) -> 0 | O47: =SUM(O26:O46) -> 0 | Q47: =SUM(Q26:Q46) -> 0 | S47: =SUM(S26:S46) -> 0
F48: BOND RATE | H48: 0 | J48: 0 | L48: 0 | N48: 0 | P48: 0 | R48: 0
F49: BOND AMOUNT | I49: =H48*I47 -> 0 | K49: =J48*K47 -> 0 | M49: =L48*M47 -> 0 | O49: =N48*O47 -> 0 | Q49: =P48*Q47 -> 0 | S49: =R48*S47 -> 0
F51: ADJUSTED TOTAL | I51: =SUM(I47:I49) -> 0 | K51: =SUM(K47:K49) -> 0 | M51: =SUM(M47:M49) -> 0 | O51: =SUM(O47:O49) -> 0 | Q51: =SUM(Q47:Q49) -> 0 | S51: =SUM(S47:S49) -> 0
F52: Cost per SF | I52: =I51/'Area Calculations'!$I$4 -> #DIV/0! | K52: =K51/'Area Calculations'!$I$4 -> #DIV/0! | M52: =M51/'Area Calculations'!$I$4 -> #DIV/0! | O52: =O51/'Area Calculations'!$I$4 -> #DIV/0! | Q52: =Q51/'Area Calculations'!$I$4 -> #DIV/0! | S52: =S51/'Area Calculations'!$I$4 -> #DIV/0!
F53: Cost per Unit | I53: =I51/'Area Calculations'!#REF! -> #REF! | K53: =K51/'Area Calculations'!#REF! -> #REF! | M53: =M51/'Area Calculations'!#REF! -> #REF! | O53: =O51/'Area Calculations'!#REF! -> #REF! | Q53: =Q51/'Area Calculations'!#REF! -> #REF! | S53: =S51/'Area Calculations'!#REF! -> #REF!
A55: QUALIFICATIONS
A59: EXCLUSIONS/OWNER PROVIDED ITEMS:
A63: ALTERNATES:
A67: PROPOSED VE (Provide Clear Description):
A71: FULLY LOADED LABOR RATES
B72: Laborer
B73: Mechanic
B74: Superintendent
B75: Project Manager
A77: SCHEDULE
B78: Prepared shop drawings/submittals
B79: Mobilization
B80: Total duration to complete scope of work
A82: Winner
A83: Company
A84: Contact
A85: Phone
A86: Email
A87: Base Bid
B89: Need Prequalification
B90: Prequalified

Sheet 09E Tile & Stone
G1: Hedrick Plug
F2: X | G2: Excluded
B3: BACK TO SUMMARY SHEET | F3: I | G3: Included | H3: Bidder 1 | J3: Bidder 2 | L3: Bidder 3 | N3: Bidder 4 | P3: Bidder 5 | R3: Bidder 6
A4: Project: | B4: ='Area Calculations'!B4 -> Project Name | G4: Company
A5: Trade: | B5: Tile & Stone | G5: Contact
A6: CSI Code: | B6: 09E | G6: Phone
A7: Date: | G7: Email
A8: Adjusted Bid | G8: Adjusted Bid | H8: =I80 -> 0 | J8: =K80 -> 0
A9: BID DOCUMENTS: | C9: Plan/ Spec. Package | D9: QTY | E9: U/M | F9: Unit Cost | G9: Subtotal | H9: Yes/No | I9: Price | J9: Yes/No | K9: Price | L9: Yes/No | M9: Price | N9: Yes/No | O9: Price | P9: Yes/No | Q9: Price | R9: Yes/No | S9: Price
B10: Plans By Division
B11: ='Area Calculations'!L62 -> Architectural Drawings by | C11: P
B12: ='Area Calculations'!L63 -> Structural Drawings by | C12: P
B13: ='Area Calculations'!L64 -> MEP FA FP Drawings by | C13: P
B14: ='Area Calculations'!L65 -> Civil Drawings by | C14: P
B15: ='Area Calculations'!L66 -> Land scape Drawings by | C15: P
B16: ='Area Calculations'!L67 -> Kitchen Drawings by | C16: P
B17: ='Area Calculations'!L68 -> Storefront Designer by | C17: P
B18: ='Area Calculations'!L69 -> Geotech report by | C18: P
B19: ='Area Calculations'!L70 -> Specifications | C19: P
B21: Tile & Stone
B22: GENERAL INCLUSIONS
B23: INCLUDES ALL SALES TAX
B24: ALL HOISTING & RIGGING REQUIRED TO COMPLETE THIS SCOPE
B25: PROVIDE P&P BONDS
B26: FLORIDA STATE CONTRACTORS LIC.
B27: GENERAL LIABILITY AND WORKERS COMP. INSURANCE LIMITS
B28: STATE AND LOCAL TAXES
B29: COMPASS
B30: SPECIFIC TRADE SCOPE OF WORK REQUIREMENTS
B31: BASE BID
B32: Building SF
... B41: Exterior
H42: i
B44: General scope
B45: Installation
B46: Floor preparation
B47: Sound insulation
F76: SUBTOTAL | I76: =SUM(I23:I75) -> 0 | K76: =SUM(K23:K75) -> 0 | M76: =SUM(M23:M75) -> 0 | O76: =SUM(O26:O75) -> 0 | Q76: =SUM(Q26:Q75) -> 0 | S76: =SUM(S26:S75) -> 0
F77: BOND RATE | H77: 0 | J77: 0 | L77: 0 | N77: 0 | P77: 0 | R77: 0
F78: BOND AMOUNT | I78: =H77*I76 -> 0 | K78: =J77*K76 -> 0 | M78: =L77*M76 -> 0 | O78: =N77*O76 -> 0 | Q78: =P77*Q76 -> 0 | S78: =R77*S76 -> 0
F80: ADJUSTED TOTAL | I80: =SUM(I76:I78) -> 0 | K80: =SUM(K76:K78) -> 0 | M80: =SUM(M76:M78) -> 0 | O80: =SUM(O76:O78) -> 0 | Q80: =SUM(Q76:Q78) -> 0 | S80: =SUM(S76:S78) -> 0
F81: Cost per SF | I81: =I80/'Area Calculations'!$I$4 -> #DIV/0! | K81: =K80/'Area Calculations'!$I$4 -> #DIV/0! | M81: =M80/'Area Calculations'!$I$4 -> #DIV/0! | O81: =O80/'Area Calculations'!$I$4 -> #DIV/0! | Q81: =Q80/'Area Calculations'!$I$4 -> #DIV/0! | S81: =S80/'Area Calculations'!$I$4 -> #DIV/0!
F82: Cost per Unit | I82: =I80/'Area Calculations'!#REF! -> #REF! | K82: =K80/'Area Calculations'!#REF! -> #REF! | M82: =M80/'Area Calculations'!#REF! -> #REF! | O82: =O80/'Area Calculations'!#REF! -> #REF! | Q82: =Q80/'Area Calculations'!#REF! -> #REF! | S82: =S80/'Area Calculations'!#REF! -> #REF!
A84: QUALIFICATIONS
A88: EXCLUSIONS/OWNER PROVIDED ITEMS:
A92: ALTERNATES:
A96: PROPOSED VE (Provide Clear Description):
A100: FULLY LOADED LABOR RATES
B101: Laborer
B102: Mechanic
B103: Superintendent
B104: Project Manager
A106: SCHEDULE
B107: Prepared shop drawings/submittals
B108: Mobilization
B109: Total duration to complete scope of work
A111: Winner
A112: Company
A113: Contact
A114: Phone
A115: Email
A116: Base Bid
B118: Need Prequalification
B119: Prequalified

Sheet 09F Carpet & Resilient
G1: Hedrick Plug
F2: X | G2: Excluded
B3: BACK TO SUMMARY SHEET | F3: I | G3: Included | H3: Bidder 1 | J3: Bidder 2 | L3: Bidder 3 | N3: Bidder 4 | P3: Bidder 5 | R3: Bidder 6
A4: Project: | B4: ='Area Calculations'!B4 -> Project Name | G4: Company
A5: Trade: | B5: Carpet & Resilient | G5: Contact
A6: CSI Code: | B6: 09F | G6: Phone
A7: Date: | G7: Email
A8: Adjusted Bid | G8: Adjusted Bid | H8: =I67 -> 0 | J8: =K67 -> 0 | L8: =M67 -> 0
A9: BID DOCUMENTS: | C9: Plan/ Spec. Package | D9: QTY | E9: U/M | F9: Unit Cost | G9: Subtotal | H9: Yes/No | I9: Price | J9: Yes/No | K9: Price | L9: Yes/No | M9: Price | N9: Yes/No | O9: Price | P9: Yes/No | Q9: Price | R9: Yes/No | S9: Price
B10: Plans By Division
B11: ='Area Calculations'!L62 -> Architectural Drawings by | C11: P
B12: ='Area Calculations'!L63 -> Structural Drawings by | C12: P
B13: ='Area Calculations'!L64 -> MEP FA FP Drawings by | C13: P
B14: ='Area Calculations'!L65 -> Civil Drawings by | C14: P
B15: ='Area Calculations'!L66 -> Land scape Drawings by | C15: P
B16: ='Area Calculations'!L67 -> Kitchen Drawings by | C16: P
B17: ='Area Calculations'!L68 -> Storefront Designer by | C17: P
B18: ='Area Calculations'!L69 -> Geotech report by | C18: P
B19: ='Area Calculations'!L70 -> Specifications | C19: P
B21: Carpet & Resilient
B22: GENERAL INCLUSIONS
B23: INCLUDES ALL SALES TAX
B24: ALL HOISTING & RIGGING REQUIRED TO COMPLETE THIS SCOPE
B25: PROVIDE P&P BONDS
B26: FLORIDA STATE CONTRACTORS LIC.
B27: GENERAL LIABILITY AND WORKERS COMP. INSURANCE LIMITS
B28: STATE AND LOCAL TAXES
B29: COMPASS
B30: SPECIFIC TRADE SCOPE OF WORK REQUIREMENTS
B31: BASE BID
B32: Building SF
H40: i
F63: SUBTOTAL | I63: =SUM(I23:I62) -> 0 | K63: =SUM(K23:K62) -> 0 | M63: =SUM(M23:M62) -> 0 | O63: =SUM(O26:O62) -> 0 | Q63: =SUM(Q26:Q62) -> 0 | S63: =SUM(S26:S62) -> 0
F64: BOND RATE | H64: 0 | J64: 0 | L64: 0 | N64: 0 | P64: 0 | R64: 0
F65: BOND AMOUNT | I65: =H64*I63 -> 0 | K65: =J64*K63 -> 0 | M65: =L64*M63 -> 0 | O65: =N64*O63 -> 0 | Q65: =P64*Q63 -> 0 | S65: =R64*S63 -> 0
F67: ADJUSTED TOTAL | I67: =SUM(I63:I65) -> 0 | K67: =SUM(K63:K65) -> 0 | M67: =SUM(M63:M65) -> 0 | O67: =SUM(O63:O65) -> 0 | Q67: =SUM(Q63:Q65) -> 0 | S67: =SUM(S63:S65) -> 0
F68: Cost per SF | I68: =I67/'Area Calculations'!$I$4 -> #DIV/0! | K68: =K67/'Area Calculations'!$I$4 -> #DIV/0! | M68: =M67/'Area Calculations'!$I$4 -> #DIV/0! | O68: =O67/'Area Calculations'!$I$4 -> #DIV/0! | Q68: =Q67/'Area Calculations'!$I$4 -> #DIV/0! | S68: =S67/'Area Calculations'!$I$4 -> #DIV/0!
F69: Cost per Unit | I69: =I67/'Area Calculations'!#REF! -> #REF! | K69: =K67/'Area Calculations'!#REF! -> #REF! | M69: =M67/'Area Calculations'!#REF! -> #REF! | O69: =O67/'Area Calculations'!#REF! -> #REF! | Q69: =Q67/'Area Calculations'!#REF! -> #REF! | S69: =S67/'Area Calculations'!#REF! -> #REF!
A71: QUALIFICATIONS
A75: EXCLUSIONS/OWNER PROVIDED ITEMS:
A79: ALTERNATES:
A83: PROPOSED VE (Provide Clear Description):
A87: FULLY LOADED LABOR RATES
B88: Laborer
B89: Mechanic
B90: Superintendent
B91: Project Manager
A93: SCHEDULE
B94: Prepared shop drawings/submittals
B95: Mobilization
B96: Total duration to complete scope of work
A98: Winner
A99: Company
A100: Contact
A101: Phone
A102: Email
A103: Base Bid
B105: Need Prequalification
B106: Prequalified

Sheet 09G Wood Flooring
G1: Hedrick Plug
F2: X | G2: Excluded | J2: 9544464105 | L2: 2704855874
B3: BACK TO SUMMARY SHEET | F3: I | G3: Included | H3: Bidder 1 | J3: Bidder 2 | L3: Bidder 3 | N3: Bidder 4 | P3: Bidder 5 | R3: Bidder 6
A4: Project: | B4: ='Area Calculations'!B4 -> Project Name | G4: Company
A5: Trade: | B5: Wood Flooring | G5: Contact
A6: CSI Code: | B6: 09G | G6: Phone
A7: Date: | G7: Email
A8: Adjusted Bid | G8: Adjusted Bid
A9: BID DOCUMENTS: | C9: Plan/ Spec. Package | D9: QTY | E9: U/M | F9: Unit Cost | G9: Subtotal | H9: Yes/No | I9: Price | J9: Yes/No | K9: Price | L9: Yes/No | M9: Price | N9: Yes/No | O9: Price | P9: Yes/No | Q9: Price | R9: Yes/No | S9: Price
B10: Plans By Division
B11: ='Area Calculations'!L62 -> Architectural Drawings by | C11: P
B12: ='Area Calculations'!L63 -> Structural Drawings by | C12: P
B13: ='Area Calculations'!L64 -> MEP FA FP Drawings by | C13: P
B14: ='Area Calculations'!L65 -> Civil Drawings by | C14: P
B15: ='Area Calculations'!L66 -> Land scape Drawings by | C15: P
B16: ='Area Calculations'!L67 -> Kitchen Drawings by | C16: P
B17: ='Area Calculations'!L68 -> Storefront Designer by | C17: P
B18: ='Area Calculations'!L69 -> Geotech report by | C18: P
B19: ='Area Calculations'!L70 -> Specifications | C19: P
B21: Wood Flooring
B22: GENERAL INCLUSIONS
B23: INCLUDES ALL SALES TAX
B24: ALL HOISTING & RIGGING REQUIRED TO COMPLETE THIS SCOPE
B25: PROVIDE P&P BONDS
B26: FLORIDA STATE CONTRACTORS LIC.
B27: GENERAL LIABILITY AND WORKERS COMP. INSURANCE LIMITS
B28: STATE AND LOCAL TAXES
B29: COMPASS
B30: SPECIFIC TRADE SCOPE OF WORK REQUIREMENTS
B31: BASE BID
H38: i
F63: SUBTOTAL | I63: =SUM(I23:I62) -> 0 | K63: =SUM(K23:K62) -> 0 | M63: =SUM(M23:M62) -> 0 | O63: =SUM(O26:O62) -> 0 | Q63: =SUM(Q26:Q62) -> 0 | S63: =SUM(S26:S62) -> 0
F64: BOND RATE | H64: 0 | J64: 0 | L64: 0 | N64: 0 | P64: 0 | R64: 0
F65: BOND AMOUNT | I65: =H64*I63 -> 0 | K65: =J64*K63 -> 0 | M65: =L64*M63 -> 0 | O65: =N64*O63 -> 0 | Q65: =P64*Q63 -> 0 | S65: =R64*S63 -> 0
F67: ADJUSTED TOTAL | I67: =SUM(I63:I65) -> 0 | K67: =SUM(K63:K65) -> 0 | M67: =SUM(M63:M65) -> 0 | O67: =SUM(O63:O65) -> 0 | Q67: =SUM(Q63:Q65) -> 0 | S67: =SUM(S63:S65) -> 0
F68: Cost per SF | I68: =I67/'Area Calculations'!$I$4 -> #DIV/0! | K68: =K67/'Area Calculations'!$I$4 -> #DIV/0! | M68: =M67/'Area Calculations'!$I$4 -> #DIV/0! | O68: =O67/'Area Calculations'!$I$4 -> #DIV/0! | Q68: =Q67/'Area Calculations'!$I$4 -> #DIV/0! | S68: =S67/'Area Calculations'!$I$4 -> #DIV/0!
F69: Cost per Unit | I69: =I67/'Area Calculations'!#REF! -> #REF! | K69: =K67/'Area Calculations'!#REF! -> #REF! | M69: =M67/'Area Calculations'!#REF! -> #REF! | O69: =O67/'Area Calculations'!#REF! -> #REF! | Q69: =Q67/'Area Calculations'!#REF! -> #REF! | S69: =S67/'Area Calculations'!#REF! -> #REF!
A71: QUALIFICATIONS
A75: EXCLUSIONS/OWNER PROVIDED ITEMS:
A79: ALTERNATES:
A83: PROPOSED VE (Provide Clear Description):
A87: FULLY LOADED LABOR RATES
B88: Laborer
B89: Mechanic
B90: Superintendent
B91: Project Manager
A93: SCHEDULE
B94: Prepared shop drawings/submittals
B95: Mobilization
B96: Total duration to complete scope of work
A98: Winner
A99: Company
A100: Contact
A101: Phone
A102: Email
A103: Base Bid
B105: Need Prequalification
B106: Prequalified

Sheet 09H Resinuous & Polished C
G1: Hedrick Plug
F2: X | G2: Excluded
B3: BACK TO SUMMARY SHEET | F3: I | G3: Included | H3: Bidder 1 | J3: Bidder 2 | L3: Bidder 3 | N3: Bidder 4 | P3: Bidder 5 | R3: Bidder 6
A4: Project: | B4: ='Area Calculations'!B4 -> Project Name | G4: Company
A5: Trade: | B5: Resinuous & Polished Concrete | G5: Contact
A6: CSI Code: | B6: 09H | G6: Phone
A7: Date: | G7: Email
A8: Adjusted Bid | G8: Adjusted Bid
